Workbook

Sheet Summary
A1: ABT standard model (trial) · research run 2026-10-23
A2: The supervisor's reconciled assumption set as a live model. Trial: shown beside the blended page target, not used for trade levels until its weight is decided. Edit blue cells on Model (drivers) and Valuation (assumptions).
A3: Price target box | B3: Value
A4: Live price | B4: =IFERROR(GOOGLEFINANCE("ABT","price"),Valuation!$B$67)
A5: Price as of | B5: =NOW()
A6: Model target (12-month median) | B6: =Distribution!$B$13
A7: Upside to model target from live price | B7: =B6/B4-1
A8: Research target (12m) (no scenario deltas) | B8: =Valuation!$D$7
A9: Probability-weighted mean | B9: =Distribution!$B$10
A10: 10th percentile | B10: =Distribution!$B$14
A11: 25th percentile | B11: =Distribution!$B$15
A12: 75th percentile | B12: =Distribution!$B$16
A13: 90th percentile | B13: =Distribution!$B$17
A14: Target date | B14: =Valuation!$B$45
A15: Price at the run | B15: =Valuation!$B$67
A16: Blended page target (options 67% + agents 33%, not live) | B16: 110.911
A17: Supervisor research target (12m) (its own methods) | B17: 109.19
A18: Thesis break price (supervisor) | B18: 78
A19: Supervisor confidence | B19: low
A21: Key estimates | B21: FY2025A | C21: =Model!E5 | D21: =Model!F5
A22: Net sales | B22: =IF(Model!D36="","",Model!D36) | C22: =Model!E36 | D22: =Model!F36
A23: % YoY | B23: =IF(Model!D37="","",Model!D37) | C23: =Model!E37 | D23: =Model!F37
A24: Pretax margin | B24: =IF(Model!D47="","",Model!D47) | C24: =Model!E47 | D24: =Model!F47
A25: Diluted EPS (model) | B25: =IF(Model!D54="","",Model!D54) | C25: =Model!E54 | D25: =Model!F54
A26: % YoY | B26: =IF(Model!D55="","",Model!D55) | C26: =Model!E55 | D26: =Model!F55
A27: Free cash flow to firm | B27: =IF(Model!D64="","",Model!D64) | C27: =Model!E64 | D27: =Model!F64
A29: Valuation method | B29: Value per share | C29: Weight
A30: =Valuation!A4 | B30: =Valuation!D4 | C30: =Valuation!E4
A31: =Valuation!A5 | B31: =Valuation!D5 | C31: =Valuation!E5
A32: =Valuation!A6 | B32: =Valuation!D6 | C32: =Valuation!E6
A34: Scenario | B34: Probability | C34: Value at target date | D34: What has to happen
A35: =Distribution!A4 | B35: =Distribution!B4 | C35: =Distribution!C4 | D35: =Distribution!D4
A36: =Distribution!A5 | B36: =Distribution!B5 | C36: =Distribution!C5 | D36: =Distribution!D5
A37: =Distribution!A6 | B37: =Distribution!B6 | C37: =Distribution!C6 | D37: =Distribution!D6
A39: Price at target date | B39: Probability above
A40: =ROUND(Valuation!$B$67*0.7,0) | B40: =SUMPRODUCT(Distribution!$B$4:$B$6,1-NORMSDIST((LN(A40)-LN(Distribution!$C$4:$C$6))/Distribution!$B$9))
A41: =ROUND(Valuation!$B$67*0.8,0) | B41: =SUMPRODUCT(Distribution!$B$4:$B$6,1-NORMSDIST((LN(A41)-LN(Distribution!$C$4:$C$6))/Distribution!$B$9))
A42: =ROUND(Valuation!$B$67*0.9,0) | B42: =SUMPRODUCT(Distribution!$B$4:$B$6,1-NORMSDIST((LN(A42)-LN(Distribution!$C$4:$C$6))/Distribution!$B$9))
A43: =ROUND(Valuation!$B$67*1.0,0) | B43: =SUMPRODUCT(Distribution!$B$4:$B$6,1-NORMSDIST((LN(A43)-LN(Distribution!$C$4:$C$6))/Distribution!$B$9))
A44: =ROUND(Valuation!$B$67*1.1,0) | B44: =SUMPRODUCT(Distribution!$B$4:$B$6,1-NORMSDIST((LN(A44)-LN(Distribution!$C$4:$C$6))/Distribution!$B$9))
A45: =ROUND(Valuation!$B$67*1.2,0) | B45: =SUMPRODUCT(Distribution!$B$4:$B$6,1-NORMSDIST((LN(A45)-LN(Distribution!$C$4:$C$6))/Distribution!$B$9))
A46: =ROUND(Valuation!$B$67*1.3,0) | B46: =SUMPRODUCT(Distribution!$B$4:$B$6,1-NORMSDIST((LN(A46)-LN(Distribution!$C$4:$C$6))/Distribution!$B$9))
A47: =ROUND(Valuation!$B$67*1.5,0) | B47: =SUMPRODUCT(Distribution!$B$4:$B$6,1-NORMSDIST((LN(A47)-LN(Distribution!$C$4:$C$6))/Distribution!$B$9))
A49: Model checks | B49: Status
A50: Scenario probabilities sum to 100% | B50: =IF(ABS(Distribution!B8-1)<0.005,"ok","FLAG: "&TEXT(Distribution!B8,"0.0%"))
A51: WACC exceeds terminal growth by 1 point or more | B51: =IF('Calc - research target (12m)'!B55="ok","ok","FLAG")
A52: Projection runs a full year past the target date | B52: =IF('Calc - research target (12m)'!B56="ok","ok","FLAG")
A53: Method weights add up to more than zero | B53: =IF(SUM(Valuation!E4:E6)>0,"ok","FLAG")
A54: Terminal value under 85% of the DCF | B54: =IF('Calc - research target (12m)'!B46<0.85,"ok","note: "&TEXT('Calc - research target (12m)'!B46,"0%")&" of the DCF is terminal value")
A55: Segment base revenues tie to the last reported net sales (within 2%) | B55: =IF(ABS(Valuation!$B$98/Valuation!$B$50-1)<=0.02,"ok","FLAG")
A56: Matches the engine run at publication (target, research target (12m)) | B56: =IF(AND(ABS(Distribution!$B$13-108.6682)<0.01,ABS(Valuation!$D$7-109.1869)<0.01),"ok","inputs edited since publication")
A57: All checks | B57: =IF(COUNTIF(B50:B56,"ok")=7,"all ok",7-COUNTIF(B50:B56,"ok")&" to look at")

Sheet Model
A1: ABT: annual model, base case
A2: (M of US dollars except per share; fiscal years named by the calendar year they end in)
A3: Blue = input · black = formula · green = link to another tab · actuals from SEC filings (fact ids in the last column, links on Sources)
A5: Fiscal year | B5: FY2023A | C5: FY2024A | D5: FY2025A | E5: FY2026E | F5: FY2027E | G5: FY2028E | H5: Source / note
A6: Period end | B6: 45291 | C6: 45657 | D6: 46022 | E6: =IF(DAY(Valuation!$B$49+1)=1,EOMONTH(Valuation!$B$49,12*E7),EDATE(Valuation!$B$49,12*E7)) | F6: =IF(DAY(Valuation!$B$49+1)=1,EOMONTH(Valuation!$B$49,12*F7),EDATE(Valuation!$B$49,12*F7)) | G6: =IF(DAY(Valuation!$B$49+1)=1,EOMONTH(Valuation!$B$49,12*G7),EDATE(Valuation!$B$49,12*G7))
A7: Projection year | B7: -2 | C7: -1 | D7: 0 | E7: 1 | F7: 2 | G7: 3
A10: Segment build (blue = input: revenue growth and EBIT margin by segment and year)
A11: Medical Devices (Diabetes Care, EP, Rhythm, HF, Vascular, Structural Heart, Neuromodulation) | D11: =Valuation!$B$93 | E11: =Valuation!$B$93*(1+E12) | F11: =E11*(1+F12) | G11: =F11*(1+G12)
A12: Revenue growth | E12: 0.087716837 | F12: 0.067747066 | G12: 0.060429164
A13: Segment EBIT | E13: =E11*E14 | F13: =F11*F14 | G13: =G11*G14
A14: EBIT margin | E14: 0.339 | F14: 0.341 | G14: 0.343
A15: Diagnostics (Core Lab, Rapid/Molecular, Cancer Dx/Exact Sciences) | D15: =Valuation!$B$94 | E15: =Valuation!$B$94*(1+E16) | F15: =E15*(1+F16) | G15: =F15*(1+G16)
A16: Revenue growth | E16: 0.35224348 | F16: 0.12122466 | G16: 0.05800738
A17: Segment EBIT | E17: =E15*E18 | F17: =F15*F18 | G17: =G15*G18
A18: EBIT margin | E18: 0.19 | F18: 0.198 | G18: 0.205
A19: Nutrition | D19: =Valuation!$B$95 | E19: =Valuation!$B$95*(1+E20) | F19: =E19*(1+F20) | G19: =F19*(1+G20)
A20: Revenue growth | E20: 0.0015 | F20: 0.035 | G20: 0.035
A21: Segment EBIT | E21: =E19*E22 | F21: =F19*F22 | G21: =G19*G22
A22: EBIT margin | E22: 0.185 | F22: 0.185 | G22: 0.185
A23: Established Pharmaceuticals | D23: =Valuation!$B$96 | E23: =Valuation!$B$96*(1+E24) | F23: =E23*(1+F24) | G23: =F23*(1+G24)
A24: Revenue growth | E24: 0.08724711 | F24: 0.069945174 | G24: 0.070031056
A25: Segment EBIT | E25: =E23*E26 | F25: =F23*F26 | G25: =G23*G26
A26: EBIT margin | E26: 0.23 | F26: 0.23 | G26: 0.23
A27: Other | D27: =Valuation!$B$97 | E27: =Valuation!$B$97*(1+E28) | F27: =E27*(1+F28) | G27: =F27*(1+G28)
A28: Revenue growth | E28: 0 | F28: 0 | G28: 0
A29: Segment EBIT | E29: =E27*E30 | F29: =F27*F30 | G29: =G27*G30
A30: EBIT margin | E30: 0 | F30: 0 | G30: 0
A31: Total segment revenue (= net sales) | D31: =D11+D15+D19+D23+D27 | E31: =E11+E15+E19+E23+E27 | F31: =F11+F15+F19+F23+F27 | G31: =G11+G15+G19+G23+G27 | H31: base revenues on Valuation (segment build); net sales = this total
A32: Total segment EBIT | E32: =E13+E17+E21+E25+E29 | F32: =F13+F17+F21+F25+F29 | G32: =G13+G17+G21+G25+G29
A33: Corporate / unallocated EBIT (blue = input) | E33: -820 | F33: -888 | G33: -948 | H33: years[].corporate_ebit; EBIT = total segment EBIT + corporate
A35: Sales
A36: Net sales | B36: 40109 | C36: 41950 | D36: 44328 | E36: =E31 | F36: =F31 | G36: =G31 | H36: SEC XBRL F1, F2, F3
A37: % YoY | C37: =IF(OR(C36="",B36="",B36=0),"",C36/B36-1) | D37: =IF(OR(D36="",C36="",C36=0),"",D36/C36-1) | E37: =E36/Valuation!$B$50-1 | F37: =F36/E36-1 | G37: =G36/F36-1
A39: Operating profit
A40: EBIT (operating income) | E40: =E32+E33 | F40: =F32+F33 | G40: =G32+G33
A41: EBIT margin | E41: =E40/E36 | F41: =F40/F36 | G41: =G40/G36
A42: D&A | E42: =E36*E76 | F42: =F36*F76 | G42: =G36*G76
A43: EBITDA | E43: =E40+E42 | F43: =F40+F42 | G43: =G40+G42
A44: EBITDA margin | E44: =E43/E36 | F44: =F43/F36 | G44: =G43/G36
A45: Net interest income / (expense) | E45: =-Valuation!$B$58*Valuation!$B$56 | F45: =-Valuation!$B$58*E70 | G45: =-Valuation!$B$58*F70 | H45: rate x prior year-end net debt (memo roll)
A46: Pretax income | B46: 6664 | C46: 7013 | D46: 8466 | E46: =E40+E45 | F46: =F40+F45 | G46: =G40+G45 | H46: SEC XBRL F83, F84, F85
A47: Pretax margin | B47: =B46/B36 | C47: =C46/C36 | D47: =D46/D36 | E47: =E46/E36 | F47: =F46/F36 | G47: =G46/G36
A48: Income tax | B48: 941 | C48: -6389 | D48: 1942 | E48: =E46*E75 | F48: =F46*F75 | G48: =G46*G75 | H48: SEC XBRL F76, F77, F78
A49: Effective tax rate | B49: =B48/B46 | C49: =C48/C46 | D49: =D48/D46 | E49: =E48/E46 | F49: =F48/F46 | G49: =G48/G46
A50: Net income | B50: 5723 | C50: 13402 | D50: 6524 | E50: =E46-E48 | F50: =F46-F48 | G50: =G46-G48 | H50: SEC XBRL F15, F16, F17
A51: % YoY | C51: =IF(OR(C50="",B50="",B50=0),"",C50/B50-1) | D51: =IF(OR(D50="",C50="",C50=0),"",D50/C50-1) | E51: =IF(OR(D50="",D50=0),"",E50/D50-1) | F51: =IF(OR(E50="",E50=0),"",F50/E50-1) | G51: =IF(OR(F50="",F50=0),"",G50/F50-1)
A52: Diluted shares (M, average) | B52: 1749 | C52: 1748 | D52: 1748 | E52: =Valuation!$B$60*(1+Valuation!$B$62)^(E7-0.5-((Valuation!$B$61-Valuation!$B$49)/365.25)) | F52: =Valuation!$B$60*(1+Valuation!$B$62)^(F7-0.5-((Valuation!$B$61-Valuation!$B$49)/365.25)) | G52: =Valuation!$B$60*(1+Valuation!$B$62)^(G7-0.5-((Valuation!$B$61-Valuation!$B$49)/365.25)) | H52: diluted count rolled at the annual change to mid-year
A53: % YoY | C53: =IF(OR(C52="",B52="",B52=0),"",C52/B52-1) | D53: =IF(OR(D52="",C52="",C52=0),"",D52/C52-1) | E53: =IF(OR(D52="",D52=0),"",E52/D52-1) | F53: =IF(OR(E52="",E52=0),"",F52/E52-1) | G53: =IF(OR(F52="",F52=0),"",G52/F52-1)
A54: Diluted EPS | B54: 3.26 | C54: 7.64 | D54: 3.72 | E54: =E50/E52 | F54: =F50/F52 | G54: =G50/G52 | H54: SEC XBRL F22, F23, F24
A55: % YoY | C55: =IF(OR(C54="",B54="",B54=0),"",C54/B54-1) | D55: =IF(OR(D54="",C54="",C54=0),"",D54/C54-1) | E55: =IF(OR(D54="",D54=0),"",E54/D54-1) | F55: =IF(OR(E54="",E54=0),"",F54/E54-1) | G55: =IF(OR(F54="",F54=0),"",G54/F54-1)
A57: Cash flow
A58: NOPAT (EBIT x (1 - tax)) | E58: =E40*(1-E75) | F58: =F40*(1-F75) | G58: =G40*(1-G75)
A59: + D&A | B59: =B42 | C59: =C42 | D59: =D42 | E59: =E42 | F59: =F42 | G59: =G42
A60: - Capex | B60: 2202 | C60: 2207 | D60: 2171 | E60: =E36*E77 | F60: =F36*F77 | G60: =G36*G77 | H60: SEC XBRL F48, F49, F50
A61: Capex % of sales | B61: =B60/B36 | C61: =C60/C36 | D61: =D60/D36 | E61: =E60/E36 | F61: =F60/F36 | G61: =G60/G36
A62: - Working capital increase | E62: =E78*(E36-Valuation!$B$50) | F62: =F78*(F36-E36) | G62: =G78*(G36-F36)
A63: - Stock comp (adjusted EBIT only) | E63: =IF(AND(Valuation!$B$47="adjusted",Valuation!$B$48="cost"),E67*(1-E75),0) | F63: =IF(AND(Valuation!$B$47="adjusted",Valuation!$B$48="cost"),F67*(1-F75),0) | G63: =IF(AND(Valuation!$B$47="adjusted",Valuation!$B$48="cost"),G67*(1-G75),0)
A64: Free cash flow to firm | E64: =E58+E59-E60-E62-E63 | F64: =F58+F59-F60-F62-F63 | G64: =G58+G59-G60-G62-G63 | H64: what the DCF discounts (Calc tabs)
A65: Operating cash flow (reported) | B65: 7261 | C65: 8558 | D65: 9566 | H65: SEC XBRL F41, F42, F43
A66: FCF (operating cash flow - capex) | B66: =B65-B60 | C66: =C65-C60 | D66: =D65-D60
A67: Stock comp (memo) | B67: 644 | C67: 673 | D67: 664 | E67: =E36*E79 | F67: =F36*F79 | G67: =G36*G79 | H67: SEC XBRL F34, F35, F36
A68: Buybacks + dividends + other uses | B68: 4783 | C68: 5131 | D68: 5009 | E68: =E36*E81+E80+E82 | F68: =F36*F81+F80+F82 | G68: =G36*G81+G80+G82 | H68: SEC XBRL F55, F62, F56, F63, F57, F64
A69: % of sales | B69: =B68/B36 | C69: =C68/C36 | D69: =D68/D36 | E69: =E68/E36 | F69: =F68/F36 | G69: =G68/G36
A70: Net debt / (net cash), year end (memo) | E70: =Valuation!$B$56-E64-E45*(1-E75)+E68 | F70: =E70-F64-F45*(1-F75)+F68 | G70: =F70-G64-G45*(1-G75)+G68 | H70: rolled from the balance-date figure; feeds interest only
A72: Drivers (blue = input; a year left black carries the prior year)
A73: Revenue growth | C73: =C37 | D73: =D37 | E73: =E37 | F73: =F37 | G73: =G37 | H73: implied by the segment build (edit the segment rows)
A74: EBIT margin | E74: =E41 | F74: =F41 | G74: =G41 | H74: implied by the segment build and corporate EBIT
A75: Tax rate | B75: =B49 | C75: =C49 | D75: =D49 | E75: 0.155 | F75: 0.155 | G75: 0.155
A76: D&A % revenue | B76: =B42/B36 | C76: =C42/C36 | D76: =D42/D36 | E76: 0.032 | F76: 0.032 | G76: 0.032
A77: Capex % revenue | B77: =B61 | C77: =C61 | D77: =D61 | E77: 0.044 | F77: 0.044 | G77: 0.044
A78: Working capital % of revenue increase | E78: 0.12 | F78: 0.12 | G78: 0.12
A79: Stock comp % revenue | B79: =B67/B36 | C79: =C67/C36 | D79: =D67/D36 | E79: 0.015 | F79: 0.015 | G79: 0.015
A80: Shareholder returns ($) | E80: 5200 | F80: 5200 | G80: 5600
A81: Shareholder returns % revenue | B81: =B69 | C81: =C69 | D81: =D69 | E81: 0 | F81: =E81 | G81: =F81
A82: Other uses of cash ($: M&A, investments) | E82: 0 | F82: 0 | G82: 0
A83: Adj. EBITDA addback % revenue | E83: 0 | F83: =E83 | G83: =F83
A85: Versus company guidance and street consensus
A86: no guidance or consensus figures in this run's reference block

Sheet Valuation
A1: ABT: valuation and price target derivation
A2: Value per share at the target date = weighted methods below; the 12-month target is the median of the scenario mix (Distribution tab).
A3: Method | B3: Multiple | C3: Metric at target date | D3: Value per share | E3: Weight | F3: Contribution
A4: ='Calc - research target (12m)'!A67 | B4: =IF('Calc - research target (12m)'!C67="","",'Calc - research target (12m)'!C67) | C4: =IF('Calc - research target (12m)'!I67="","",'Calc - research target (12m)'!I67) | D4: ='Calc - research target (12m)'!F67 | E4: ='Calc - research target (12m)'!G67 | F4: =D4*E4/SUM($E$4:$E$6)
A5: ='Calc - research target (12m)'!A68 | B5: =IF('Calc - research target (12m)'!C68="","",'Calc - research target (12m)'!C68) | C5: =IF('Calc - research target (12m)'!I68="","",'Calc - research target (12m)'!I68) | D5: ='Calc - research target (12m)'!F68 | E5: ='Calc - research target (12m)'!G68 | F5: =D5*E5/SUM($E$4:$E$6)
A6: ='Calc - research target (12m)'!A69 | B6: =IF('Calc - research target (12m)'!C69="","",'Calc - research target (12m)'!C69) | C6: =IF('Calc - research target (12m)'!I69="","",'Calc - research target (12m)'!I69) | D6: ='Calc - research target (12m)'!F69 | E6: ='Calc - research target (12m)'!G69 | F6: =D6*E6/SUM($E$4:$E$6)
A7: Research target (12m) per share | D7: ='Calc - research target (12m)'!$F$70 | F7: =SUM(F4:F6)
A9: 12-month EPS basis (what the P/E is applied to)
A10: Fiscal year | B10: =Model!E5 | C10: =Model!F5 | D10: =Model!G5
A11: Share of the 12 months after the target date | B11: ='Calc - research target (12m)'!C38 | C11: ='Calc - research target (12m)'!D38 | D11: ='Calc - research target (12m)'!E38
A12: Model EPS (Model tab) | B12: =Model!E54 | C12: =Model!F54 | D12: =Model!G54
A13: Model EPS, next 12 months after the target date | B13: =SUMPRODUCT(B11:D11,B12:D12)
A16: DCF build (free cash flow to firm, discounted to the target date)
A17: Fiscal year | B17: =Model!E5 | C17: =Model!F5 | D17: =Model!G5
A18: Free cash flow to firm | B18: ='Calc - research target (12m)'!C31 | C18: ='Calc - research target (12m)'!D31 | D18: ='Calc - research target (12m)'!E31
A19: Share of the year after the target date | B19: ='Calc - research target (12m)'!C35 | C19: ='Calc - research target (12m)'!D35 | D19: ='Calc - research target (12m)'!E35
A20: PV at target date | B20: ='Calc - research target (12m)'!C36 | C20: ='Calc - research target (12m)'!D36 | D20: ='Calc - research target (12m)'!E36
A22: PV of free cash flow after the target date | B22: ='Calc - research target (12m)'!B42
A23: Terminal value (final year) | B23: ='Calc - research target (12m)'!B43
A24: PV of terminal value | B24: ='Calc - research target (12m)'!B44
A25: Enterprise value at target date | B25: ='Calc - research target (12m)'!B45
A26: Terminal value share of DCF | B26: ='Calc - research target (12m)'!B46
A27: Net debt at target date | B27: ='Calc - research target (12m)'!B50
A28: Minority interests | B28: ='Calc - research target (12m)'!B51
A29: Adjustments | B29: ='Calc - research target (12m)'!B52
A30: Diluted shares at target date (M) | B30: ='Calc - research target (12m)'!B53
A31: DCF value per share | B31: ='Calc - research target (12m)'!F67
A32: WACC | B32: ='Calc - research target (12m)'!B12
A42: Assumptions (blue = input; sources on the Sources tab)
A43: Input | B43: Value | C43: Basis / note
A44: Run date (valuation as of) | B44: 46318
A45: Target date (run date + 365 days) | B45: =B44+365 | C45: 12-month horizon
A46: Money unit | B46: $M
A47: EBIT basis (gaap / adjusted) | B47: gaap | C47: gaap = after stock comp
A48: Stock comp treatment (cost / dilution) | B48: cost | C48: used only when EBIT is adjusted
A49: Last reported fiscal year end | B49: 46022
A50: Net sales, last reported year ($M) | B50: 44328
A51: WACC | B51: 0.1 | C51: not used: no DCF leg (Kilian 2026-10-21); a placeholder so the DCF block still computes
A52: Terminal method (gordon / exit_multiple / steady_state) | B52: gordon
A53: Terminal growth | B53: 0.02
A54: Exit EV/EBITDA (exit_multiple only)
A55: Balance-sheet date | B55: 46203
A56: Net debt / (net cash) at balance date ($M) | B56: 27005 | C56: excludes operating leases
A57: Minority interests + preferred stock | B57: 652
A58: Interest rate on net debt / cash | B58: 0.044
A59: Net debt at target date (override; blank = bridge)
A60: Diluted shares (M) | B60: 1738
A61: Share count date | B61: 46295
A62: Annual change in diluted shares | B62: -0.005 | C62: net of buybacks and stock-comp dilution
A63: Shares at target date (override; blank = from annual change)
A64: DCF weight | B64: 0 | C64: Kilian 2026-10-21: 0 unless the name has a DCF leg (dcf_policy)
A65: Sum-of-the-parts weight | B65: 0
A66: Spread within each scenario (lognormal vol) | B66: 0.12
A67: Share price at the run | B67: 103.7 | C67: close used by the run (2026-10-23)
A69: Target multiple | B69: Multiple | C69: Weight | D69: Basis (ntm / ltm) | E69: EBITDA basis | F69: Stated EPS | G69: Stated FCF/share | H69: Levered | I69: Peer basis
A70: P/E | B70: 17.42 | C70: 0.6 | D70: ntm | E70: gaap | H70: TRUE | I70: Approved 11-peer set (MDT BSX SYK BDX ZBH TMO DHR JNJ + Siemens Healthineers, Terumo, Olympus; Kilian 2026-10-26) on one calendar NTM window 2026-10-23 to 2027-10-22, company-adjusted consensus EPS (Zacks; Vara for SHL; Terumo/Olympus adjusted from reported consensus + company adjusted-vs-reported gaps): median 16.84x (Terumo); 17.5x if Terumo on reported FY3/28. ABT 17.6x on the same window ($103.70 / $5.90). [SUPERSEDED 2026-10-26 by exit k=0.8: 17.42x, see the EXIT note at the end] 16.8x = the median, no premium/discount (growth above median offsets mix; litigation already in adjustments). See inputs_detail 'horizon P/E'. EXIT k=0.8 (2026-10-26T12:28Z): Exit-multiple rule (Kilian card 2026-10-26 12:16Z; METHOD.md Peer comparables): exit = peer median x (own NTM multiple / peer median)^k, k = 0.8. Peer median 16.84x; own 17.57x: ABT $103.70 / NTM adjusted EPS $5.90 on the same window = 17.57x (peer_basis 'ABT 17.6x on the same window'; est.json 103.70 / 5.9012). 16.84 x (17.57 / 16.84)^0.8 = 16.84 x 1.0345 = 17.42x (was 16.8x). The EV/EBITDA leg (13.3x = ABT's own NTM adjusted multiple) has no on-basis peer median (the 14.25x filing TTM GAAP median is a reference only), so it is unchanged and flagged.
A71: EV/EBITDA | B71: 13.3 | C71: 0.4 | D71: ntm | E71: gaap | H71: TRUE | I71: ABT's own NTM adjusted EV/EBITDA today ~13.35x (EV ~$198.6B / NTM adjusted EBITDA ~$14.88B on the build): 13.3x = no re-rating. The 6-peer filing TTM median 14.25x is GAAP EBITDA and is a reference only, not applied
A73: Segment (sum of the parts) | B73: NTM metric | C73: Metric | D73: Multiple | E73: Note
A74: none
A76: Adjustment (equity level) | B76: Value | C76: Probability | D76: Note
A77: NEC Gill + ~2,000-infant settlement agreements (~$670M, 8-K 2026-08-20), after tax, paid after the 2026-06-30 balance date | B77: -520 | C77: 1 | D77: $670M x (1 - ~22.5% deductible compensatory payment); excluded from adjusted EPS (specified item)
A78: DOJ / 40-state False Claims Act infant-formula settlement ($348,700,868 + $35,491,288 = $384.2M, CA AG 2026-09-21), after tax | B78: -350 | C78: 1 | D78: ~9% tax shield assumed on the restitution part; variant -$384M with no deduction
A79: Remaining NEC claims (~1,700 suits / ~12,700 infants per 8-K 2026-08-20), expected after-tax cost | B79: -750 | C79: 1 | D79: ~$970M pre-tax = ~$76k per infant, ~2x the ~$35k per infant implied by the August deal (($670M - ~$600M Gill judgment+interest)/~2,000), loaded for verdict risk and defense; low confidence
A80: FreeStyle Libre 3 / 3 Plus Class I recall product-liability claims (FDA: 7 deaths, 860 serious injuries reported), after tax | B80: -300 | C80: 0.5 | D80: probability that claims lead to a material payout x expected after-tax cost; low confidence
A81: Specified-items cash outside adjusted EPS (restructuring, Exact Sciences integration, acquisition costs), 2026-07-01 to the horizon, after tax | B81: -600 | C81: 1 | D81: FY2025 FCF $7,395M (CFO $9,566M F43 - capex $2,171M F50) vs adjusted net earnings $9,040M + depreciation $1,434M - capex - NWC = ~$8,020M: ~$620M/yr of cash the adjusted build does not see; ~$460M/yr ex one-offs x 1.3 years
A82: Nutrition separation one-time cash costs before the horizon (8-K 2026-10-21: charges to be quantified; CFO: specified items excluded from adjusted EPS), after tax | B82: -300 | C82: 1 | D82: ~$400M pre-tax (~4.7% of ~$8.5B Nutrition sales) x ~75% spent before 2027-10-20 x (1-21%) ~ -$240M, rounded up for advisory and financing costs; low confidence
A84: Custom method | B84: Value per share | C84: Weight | D84: Explanation
A85: none
A87: Scenario | B87: Probability | C87: Growth Δ | D87: Margin Δ | E87: Multiple Δ (turns) | F87: WACC Δ | G87: Multiple %Δ (FCF yield, segments) | H87: Stated EPS/FCF %Δ | I87: Custom methods %Δ | J87: Story
A88: bear | B88: 0.25 | D88: -0.012 | E88: -2.5 | J88: CGM stays low-single-digit and Medicare competitive-bid prices (awards 2027, effective ~2028) cut harder; Volt PFA stays sub-scale; Cologuard loses volume to blood tests; Libre warning-letter escalation or Section 232 tariffs; NEC tail $2-3B. Growth -2pt, margin -1.2pt, P/E 14.5x / EV/EBITDA 10.8x. | K88: driver deltas: cgm -0.08 %; ep -0.12 %; cancer_dx -0.1 %; cv_other -0.04 %; dx_base -0.03 %; epd -0.04 %
A89: base | B89: 0.5 | J89: [exit k=0.8 2026-10-26: P/E 16.8x -> 17.42x] Comparable growth ~6% in 2027 (CEO: pretty similar to this year), ~6% 2028; adjusted EPS ~$6.0 FY27 / ~$6.5 FY28; 16.8x NTM P/E and 13.3x NTM EBITDA, less ~$2.1B expected after-tax litigation and separation cash.
A90: bull | B90: 0.25 | D90: 0.007 | E90: 2 | J90: Libre Duo, the 2027 payer change and Medicare type-2 non-insulin coverage reaccelerate CGM toward ~10%; Volt gains PFA share; Exact synergies; the Nutrition Form 10 lets RemainCo price near the device/Dx peer median (19x). | K90: driver deltas: cgm +0.09 %; ep +0.1 %; cancer_dx +0.06 %; cv_other +0.025 %; dx_base +0.015 %; epd +0.02 %
A92: Segment build (segment_build) | B92: Base revenue ($M) | C92: Driver note (growth and EBIT margin by year: Model tab)
A93: Medical Devices (Diabetes Care, EP, Rhythm, HF, Vascular, Structural Heart, Neuromodulation) | B93: 21387 | C93: revenue from drivers (driver_build); ebit_margin kept as a plain input. Old note: FY2025 $21,387M, segment OE $7,212M = 33.7% (10-K FY2025 segment note). FY2026 = 9M $17,218M (Q3 release) + Q4 ~$6,110M (Q4'25 $5,677M derived as FY25 less 9M25 x 1.076: EP ~20% in Q4 per CEO, Diabetes low-to-mid single digit) = ~$23,330M (+9.05%). FY2027 +6.5%: Diabetes ~$8.6B x +4.5% (CEO: low-to-mid single digit for the next few quarters; Libre Duo Dec-2026; payer change 2027-01-01), EP ~$3.4B x +15%, other CV/neuro ~$11.3B x +5.5%. FY2028 +6.2%: Medicare CGM competitive-bid pricing (contracts awarded 2027 per CMS final rule) trims Diabetes. Margin 33.9% / 34.1% / 34.3%: FY2025 33.7% (10-K) + 20 bp/yr (EP and structural-heart mix vs CGM price pressure). [citation gate 2026-10-21: was 34.5-34.9% with an underived +0.8pt FY2026 step]
A94: Diagnostics (Core Lab, Rapid/Molecular, Cancer Dx/Exact Sciences) | B94: 8937 | C94: revenue from drivers (driver_build); ebit_margin kept as a plain input. Old note: FY2025 $8,937M, segment OE $1,740M = 19.5% (10-K). FY2026 = 9M $8,577M + Q4 ~$3,520M (Q4'25 $2,459M derived; ex-Cancer +2.5%, Cancer Dx ~$990M vs Q3 $968M) = ~$12,095M (+35.3%; Exact consolidated from 2026-03-23). FY2027: Core Lab ~$5.6B x 1.05, R&M ~$3.5B x 1.01, Cancer Dx pro forma ~$3.8B x 1.12 (Q3 comparable +13.8%; adds the Q1 stub) = 5.88 + 3.535 + 4.256 = ~$13.67B (+13.0%; citation gate 2026-10-21, was ~$13.64B / +12.8%). FY2028 +5.8% (Cancer +11% with blood-test competition incl. Abbott's own SimpleScreen CRC, Core Lab +5%, R&M +1%). Margin 19.0% (Exact at high-teens exiting Q3 per CEO) to 20.5% with synergies.
A95: Nutrition | B95: 8451 | C95: FY2025 $8,451M, OE $1,558M = 18.4% (10-K). FY2026 = 9M $6,423M + Q4 ~$2,040M (Q4'25 ~$1,943M x 1.05; Q3 comparable +4.9%) = ~$8,463M. FY2027/28 +3.5% (volume + price/mix; 9M26 comparable -2.1% so Q3 is a rebound, competitor recall tailwind not extrapolated). Kept consolidated: the separation is expected by end-2027 (8-K 2026-10-21), modelled as a ladder branch, value-neutral to holders.
A96: Established Pharmaceuticals | B96: 5536 | C96: revenue from drivers (driver_build); ebit_margin kept as a plain input. Old note: FY2025 $5,536M, OE $1,290M = 23.3% (10-K). FY2026 = 9M $4,539M + Q4 ~$1,480M (Q4'25 ~$1,383M x 1.07; Q3 comparable +8.4%, Key Emerging Markets +10.9%) = ~$6,019M (+8.7%). FY2027/28 +7% (branded generics in key emerging markets, less EM FX). Margin 23%.
A97: Other | B97: 17 | C97: FY2025 other sales $17M (44,328 total less four segments 44,311); held flat at zero margin.
A98: Sum of segment base revenues | B98: =SUM(B93:B97) | C98: =IF(ABS(B98/Valuation!$B$50-1)<=0.02,"ties to the last reported net sales (within 2%)","FLAG: does not tie to the last reported net sales")

Sheet Sensitivity
A1: ABT: sensitivity tables (bold = current inputs; every cell recalculates from the live model)
A3: DCF value per share: WACC (down) x terminal growth (across)
A4: WACC \ growth | B4: =Valuation!$B$53+(-0.01) | C4: =Valuation!$B$53+(-0.005) | D4: =Valuation!$B$53+(0) | E4: =Valuation!$B$53+(0.005) | F4: =Valuation!$B$53+(0.01)
A5: =Valuation!$B$51+(-0.01) | B5: =IF($A5-B$4<=0.01,"n/a",((SUMPRODUCT('Calc - research target (12m)'!$C$31:$E$31,'Calc - research target (12m)'!$C$35:$E$35,(1+$A5)^(-('Calc - research target (12m)'!$C$19:$E$19-'Calc - research target (12m)'!$B$13)))+'Calc - research target (12m)'!$E$31*(1+B$4)/($A5-B$4)/(1+$A5)^('Calc - research target (12m)'!$B$16-'Calc - research target (12m)'!$B$13))-'Calc - research target (12m)'!$B$50-'Calc - research target (12m)'!$B$51+'Calc - research target (12m)'!$B$52)/'Calc - research target (12m)'!$B$53) | C5: =IF($A5-C$4<=0.01,"n/a",((SUMPRODUCT('Calc - research target (12m)'!$C$31:$E$31,'Calc - research target (12m)'!$C$35:$E$35,(1+$A5)^(-('Calc - research target (12m)'!$C$19:$E$19-'Calc - research target (12m)'!$B$13)))+'Calc - research target (12m)'!$E$31*(1+C$4)/($A5-C$4)/(1+$A5)^('Calc - research target (12m)'!$B$16-'Calc - research target (12m)'!$B$13))-'Calc - research target (12m)'!$B$50-'Calc - research target (12m)'!$B$51+'Calc - research target (12m)'!$B$52)/'Calc - research target (12m)'!$B$53) | D5: =IF($A5-D$4<=0.01,"n/a",((SUMPRODUCT('Calc - research target (12m)'!$C$31:$E$31,'Calc - research target (12m)'!$C$35:$E$35,(1+$A5)^(-('Calc - research target (12m)'!$C$19:$E$19-'Calc - research target (12m)'!$B$13)))+'Calc - research target (12m)'!$E$31*(1+D$4)/($A5-D$4)/(1+$A5)^('Calc - research target (12m)'!$B$16-'Calc - research target (12m)'!$B$13))-'Calc - research target (12m)'!$B$50-'Calc - research target (12m)'!$B$51+'Calc - research target (12m)'!$B$52)/'Calc - research target (12m)'!$B$53) | E5: =IF($A5-E$4<=0.01,"n/a",((SUMPRODUCT('Calc - research target (12m)'!$C$31:$E$31,'Calc - research target (12m)'!$C$35:$E$35,(1+$A5)^(-('Calc - research target (12m)'!$C$19:$E$19-'Calc - research target (12m)'!$B$13)))+'Calc - research target (12m)'!$E$31*(1+E$4)/($A5-E$4)/(1+$A5)^('Calc - research target (12m)'!$B$16-'Calc - research target (12m)'!$B$13))-'Calc - research target (12m)'!$B$50-'Calc - research target (12m)'!$B$51+'Calc - research target (12m)'!$B$52)/'Calc - research target (12m)'!$B$53) | F5: =IF($A5-F$4<=0.01,"n/a",((SUMPRODUCT('Calc - research target (12m)'!$C$31:$E$31,'Calc - research target (12m)'!$C$35:$E$35,(1+$A5)^(-('Calc - research target (12m)'!$C$19:$E$19-'Calc - research target (12m)'!$B$13)))+'Calc - research target (12m)'!$E$31*(1+F$4)/($A5-F$4)/(1+$A5)^('Calc - research target (12m)'!$B$16-'Calc - research target (12m)'!$B$13))-'Calc - research target (12m)'!$B$50-'Calc - research target (12m)'!$B$51+'Calc - research target (12m)'!$B$52)/'Calc - research target (12m)'!$B$53)
A6: =Valuation!$B$51+(-0.005) | B6: =IF($A6-B$4<=0.01,"n/a",((SUMPRODUCT('Calc - research target (12m)'!$C$31:$E$31,'Calc - research target (12m)'!$C$35:$E$35,(1+$A6)^(-('Calc - research target (12m)'!$C$19:$E$19-'Calc - research target (12m)'!$B$13)))+'Calc - research target (12m)'!$E$31*(1+B$4)/($A6-B$4)/(1+$A6)^('Calc - research target (12m)'!$B$16-'Calc - research target (12m)'!$B$13))-'Calc - research target (12m)'!$B$50-'Calc - research target (12m)'!$B$51+'Calc - research target (12m)'!$B$52)/'Calc - research target (12m)'!$B$53) | C6: =IF($A6-C$4<=0.01,"n/a",((SUMPRODUCT('Calc - research target (12m)'!$C$31:$E$31,'Calc - research target (12m)'!$C$35:$E$35,(1+$A6)^(-('Calc - research target (12m)'!$C$19:$E$19-'Calc - research target (12m)'!$B$13)))+'Calc - research target (12m)'!$E$31*(1+C$4)/($A6-C$4)/(1+$A6)^('Calc - research target (12m)'!$B$16-'Calc - research target (12m)'!$B$13))-'Calc - research target (12m)'!$B$50-'Calc - research target (12m)'!$B$51+'Calc - research target (12m)'!$B$52)/'Calc - research target (12m)'!$B$53) | D6: =IF($A6-D$4<=0.01,"n/a",((SUMPRODUCT('Calc - research target (12m)'!$C$31:$E$31,'Calc - research target (12m)'!$C$35:$E$35,(1+$A6)^(-('Calc - research target (12m)'!$C$19:$E$19-'Calc - research target (12m)'!$B$13)))+'Calc - research target (12m)'!$E$31*(1+D$4)/($A6-D$4)/(1+$A6)^('Calc - research target (12m)'!$B$16-'Calc - research target (12m)'!$B$13))-'Calc - research target (12m)'!$B$50-'Calc - research target (12m)'!$B$51+'Calc - research target (12m)'!$B$52)/'Calc - research target (12m)'!$B$53) | E6: =IF($A6-E$4<=0.01,"n/a",((SUMPRODUCT('Calc - research target (12m)'!$C$31:$E$31,'Calc - research target (12m)'!$C$35:$E$35,(1+$A6)^(-('Calc - research target (12m)'!$C$19:$E$19-'Calc - research target (12m)'!$B$13)))+'Calc - research target (12m)'!$E$31*(1+E$4)/($A6-E$4)/(1+$A6)^('Calc - research target (12m)'!$B$16-'Calc - research target (12m)'!$B$13))-'Calc - research target (12m)'!$B$50-'Calc - research target (12m)'!$B$51+'Calc - research target (12m)'!$B$52)/'Calc - research target (12m)'!$B$53) | F6: =IF($A6-F$4<=0.01,"n/a",((SUMPRODUCT('Calc - research target (12m)'!$C$31:$E$31,'Calc - research target (12m)'!$C$35:$E$35,(1+$A6)^(-('Calc - research target (12m)'!$C$19:$E$19-'Calc - research target (12m)'!$B$13)))+'Calc - research target (12m)'!$E$31*(1+F$4)/($A6-F$4)/(1+$A6)^('Calc - research target (12m)'!$B$16-'Calc - research target (12m)'!$B$13))-'Calc - research target (12m)'!$B$50-'Calc - research target (12m)'!$B$51+'Calc - research target (12m)'!$B$52)/'Calc - research target (12m)'!$B$53)
A7: =Valuation!$B$51+(0) | B7: =IF($A7-B$4<=0.01,"n/a",((SUMPRODUCT('Calc - research target (12m)'!$C$31:$E$31,'Calc - research target (12m)'!$C$35:$E$35,(1+$A7)^(-('Calc - research target (12m)'!$C$19:$E$19-'Calc - research target (12m)'!$B$13)))+'Calc - research target (12m)'!$E$31*(1+B$4)/($A7-B$4)/(1+$A7)^('Calc - research target (12m)'!$B$16-'Calc - research target (12m)'!$B$13))-'Calc - research target (12m)'!$B$50-'Calc - research target (12m)'!$B$51+'Calc - research target (12m)'!$B$52)/'Calc - research target (12m)'!$B$53) | C7: =IF($A7-C$4<=0.01,"n/a",((SUMPRODUCT('Calc - research target (12m)'!$C$31:$E$31,'Calc - research target (12m)'!$C$35:$E$35,(1+$A7)^(-('Calc - research target (12m)'!$C$19:$E$19-'Calc - research target (12m)'!$B$13)))+'Calc - research target (12m)'!$E$31*(1+C$4)/($A7-C$4)/(1+$A7)^('Calc - research target (12m)'!$B$16-'Calc - research target (12m)'!$B$13))-'Calc - research target (12m)'!$B$50-'Calc - research target (12m)'!$B$51+'Calc - research target (12m)'!$B$52)/'Calc - research target (12m)'!$B$53) | D7: =IF($A7-D$4<=0.01,"n/a",((SUMPRODUCT('Calc - research target (12m)'!$C$31:$E$31,'Calc - research target (12m)'!$C$35:$E$35,(1+$A7)^(-('Calc - research target (12m)'!$C$19:$E$19-'Calc - research target (12m)'!$B$13)))+'Calc - research target (12m)'!$E$31*(1+D$4)/($A7-D$4)/(1+$A7)^('Calc - research target (12m)'!$B$16-'Calc - research target (12m)'!$B$13))-'Calc - research target (12m)'!$B$50-'Calc - research target (12m)'!$B$51+'Calc - research target (12m)'!$B$52)/'Calc - research target (12m)'!$B$53) | E7: =IF($A7-E$4<=0.01,"n/a",((SUMPRODUCT('Calc - research target (12m)'!$C$31:$E$31,'Calc - research target (12m)'!$C$35:$E$35,(1+$A7)^(-('Calc - research target (12m)'!$C$19:$E$19-'Calc - research target (12m)'!$B$13)))+'Calc - research target (12m)'!$E$31*(1+E$4)/($A7-E$4)/(1+$A7)^('Calc - research target (12m)'!$B$16-'Calc - research target (12m)'!$B$13))-'Calc - research target (12m)'!$B$50-'Calc - research target (12m)'!$B$51+'Calc - research target (12m)'!$B$52)/'Calc - research target (12m)'!$B$53) | F7: =IF($A7-F$4<=0.01,"n/a",((SUMPRODUCT('Calc - research target (12m)'!$C$31:$E$31,'Calc - research target (12m)'!$C$35:$E$35,(1+$A7)^(-('Calc - research target (12m)'!$C$19:$E$19-'Calc - research target (12m)'!$B$13)))+'Calc - research target (12m)'!$E$31*(1+F$4)/($A7-F$4)/(1+$A7)^('Calc - research target (12m)'!$B$16-'Calc - research target (12m)'!$B$13))-'Calc - research target (12m)'!$B$50-'Calc - research target (12m)'!$B$51+'Calc - research target (12m)'!$B$52)/'Calc - research target (12m)'!$B$53)
A8: =Valuation!$B$51+(0.005) | B8: =IF($A8-B$4<=0.01,"n/a",((SUMPRODUCT('Calc - research target (12m)'!$C$31:$E$31,'Calc - research target (12m)'!$C$35:$E$35,(1+$A8)^(-('Calc - research target (12m)'!$C$19:$E$19-'Calc - research target (12m)'!$B$13)))+'Calc - research target (12m)'!$E$31*(1+B$4)/($A8-B$4)/(1+$A8)^('Calc - research target (12m)'!$B$16-'Calc - research target (12m)'!$B$13))-'Calc - research target (12m)'!$B$50-'Calc - research target (12m)'!$B$51+'Calc - research target (12m)'!$B$52)/'Calc - research target (12m)'!$B$53) | C8: =IF($A8-C$4<=0.01,"n/a",((SUMPRODUCT('Calc - research target (12m)'!$C$31:$E$31,'Calc - research target (12m)'!$C$35:$E$35,(1+$A8)^(-('Calc - research target (12m)'!$C$19:$E$19-'Calc - research target (12m)'!$B$13)))+'Calc - research target (12m)'!$E$31*(1+C$4)/($A8-C$4)/(1+$A8)^('Calc - research target (12m)'!$B$16-'Calc - research target (12m)'!$B$13))-'Calc - research target (12m)'!$B$50-'Calc - research target (12m)'!$B$51+'Calc - research target (12m)'!$B$52)/'Calc - research target (12m)'!$B$53) | D8: =IF($A8-D$4<=0.01,"n/a",((SUMPRODUCT('Calc - research target (12m)'!$C$31:$E$31,'Calc - research target (12m)'!$C$35:$E$35,(1+$A8)^(-('Calc - research target (12m)'!$C$19:$E$19-'Calc - research target (12m)'!$B$13)))+'Calc - research target (12m)'!$E$31*(1+D$4)/($A8-D$4)/(1+$A8)^('Calc - research target (12m)'!$B$16-'Calc - research target (12m)'!$B$13))-'Calc - research target (12m)'!$B$50-'Calc - research target (12m)'!$B$51+'Calc - research target (12m)'!$B$52)/'Calc - research target (12m)'!$B$53) | E8: =IF($A8-E$4<=0.01,"n/a",((SUMPRODUCT('Calc - research target (12m)'!$C$31:$E$31,'Calc - research target (12m)'!$C$35:$E$35,(1+$A8)^(-('Calc - research target (12m)'!$C$19:$E$19-'Calc - research target (12m)'!$B$13)))+'Calc - research target (12m)'!$E$31*(1+E$4)/($A8-E$4)/(1+$A8)^('Calc - research target (12m)'!$B$16-'Calc - research target (12m)'!$B$13))-'Calc - research target (12m)'!$B$50-'Calc - research target (12m)'!$B$51+'Calc - research target (12m)'!$B$52)/'Calc - research target (12m)'!$B$53) | F8: =IF($A8-F$4<=0.01,"n/a",((SUMPRODUCT('Calc - research target (12m)'!$C$31:$E$31,'Calc - research target (12m)'!$C$35:$E$35,(1+$A8)^(-('Calc - research target (12m)'!$C$19:$E$19-'Calc - research target (12m)'!$B$13)))+'Calc - research target (12m)'!$E$31*(1+F$4)/($A8-F$4)/(1+$A8)^('Calc - research target (12m)'!$B$16-'Calc - research target (12m)'!$B$13))-'Calc - research target (12m)'!$B$50-'Calc - research target (12m)'!$B$51+'Calc - research target (12m)'!$B$52)/'Calc - research target (12m)'!$B$53)
A9: =Valuation!$B$51+(0.01) | B9: =IF($A9-B$4<=0.01,"n/a",((SUMPRODUCT('Calc - research target (12m)'!$C$31:$E$31,'Calc - research target (12m)'!$C$35:$E$35,(1+$A9)^(-('Calc - research target (12m)'!$C$19:$E$19-'Calc - research target (12m)'!$B$13)))+'Calc - research target (12m)'!$E$31*(1+B$4)/($A9-B$4)/(1+$A9)^('Calc - research target (12m)'!$B$16-'Calc - research target (12m)'!$B$13))-'Calc - research target (12m)'!$B$50-'Calc - research target (12m)'!$B$51+'Calc - research target (12m)'!$B$52)/'Calc - research target (12m)'!$B$53) | C9: =IF($A9-C$4<=0.01,"n/a",((SUMPRODUCT('Calc - research target (12m)'!$C$31:$E$31,'Calc - research target (12m)'!$C$35:$E$35,(1+$A9)^(-('Calc - research target (12m)'!$C$19:$E$19-'Calc - research target (12m)'!$B$13)))+'Calc - research target (12m)'!$E$31*(1+C$4)/($A9-C$4)/(1+$A9)^('Calc - research target (12m)'!$B$16-'Calc - research target (12m)'!$B$13))-'Calc - research target (12m)'!$B$50-'Calc - research target (12m)'!$B$51+'Calc - research target (12m)'!$B$52)/'Calc - research target (12m)'!$B$53) | D9: =IF($A9-D$4<=0.01,"n/a",((SUMPRODUCT('Calc - research target (12m)'!$C$31:$E$31,'Calc - research target (12m)'!$C$35:$E$35,(1+$A9)^(-('Calc - research target (12m)'!$C$19:$E$19-'Calc - research target (12m)'!$B$13)))+'Calc - research target (12m)'!$E$31*(1+D$4)/($A9-D$4)/(1+$A9)^('Calc - research target (12m)'!$B$16-'Calc - research target (12m)'!$B$13))-'Calc - research target (12m)'!$B$50-'Calc - research target (12m)'!$B$51+'Calc - research target (12m)'!$B$52)/'Calc - research target (12m)'!$B$53) | E9: =IF($A9-E$4<=0.01,"n/a",((SUMPRODUCT('Calc - research target (12m)'!$C$31:$E$31,'Calc - research target (12m)'!$C$35:$E$35,(1+$A9)^(-('Calc - research target (12m)'!$C$19:$E$19-'Calc - research target (12m)'!$B$13)))+'Calc - research target (12m)'!$E$31*(1+E$4)/($A9-E$4)/(1+$A9)^('Calc - research target (12m)'!$B$16-'Calc - research target (12m)'!$B$13))-'Calc - research target (12m)'!$B$50-'Calc - research target (12m)'!$B$51+'Calc - research target (12m)'!$B$52)/'Calc - research target (12m)'!$B$53) | F9: =IF($A9-F$4<=0.01,"n/a",((SUMPRODUCT('Calc - research target (12m)'!$C$31:$E$31,'Calc - research target (12m)'!$C$35:$E$35,(1+$A9)^(-('Calc - research target (12m)'!$C$19:$E$19-'Calc - research target (12m)'!$B$13)))+'Calc - research target (12m)'!$E$31*(1+F$4)/($A9-F$4)/(1+$A9)^('Calc - research target (12m)'!$B$16-'Calc - research target (12m)'!$B$13))-'Calc - research target (12m)'!$B$50-'Calc - research target (12m)'!$B$51+'Calc - research target (12m)'!$B$52)/'Calc - research target (12m)'!$B$53)
A11: Research target (12m) per share: P/E multiple (down) x metric at target date (across)
A12: Multiple \ metric | B12: ='Calc - research target (12m)'!$E$68*0.9 | C12: ='Calc - research target (12m)'!$E$68*0.95 | D12: ='Calc - research target (12m)'!$E$68*1.0 | E12: ='Calc - research target (12m)'!$E$68*1.05 | F12: ='Calc - research target (12m)'!$E$68*1.1
A13: =Valuation!$B$70+(-3) | B13: =((SUMPRODUCT('Calc - research target (12m)'!$F$67:$F$69,'Calc - research target (12m)'!$G$67:$G$69)-'Calc - research target (12m)'!$F$68*'Calc - research target (12m)'!$G$68)+'Calc - research target (12m)'!$G$68*($A13*(B$12-'Calc - research target (12m)'!$B$54)/'Calc - research target (12m)'!$B$53+'Calc - research target (12m)'!$B$52/'Calc - research target (12m)'!$B$53))/SUM('Calc - research target (12m)'!$G$67:$G$69) | C13: =((SUMPRODUCT('Calc - research target (12m)'!$F$67:$F$69,'Calc - research target (12m)'!$G$67:$G$69)-'Calc - research target (12m)'!$F$68*'Calc - research target (12m)'!$G$68)+'Calc - research target (12m)'!$G$68*($A13*(C$12-'Calc - research target (12m)'!$B$54)/'Calc - research target (12m)'!$B$53+'Calc - research target (12m)'!$B$52/'Calc - research target (12m)'!$B$53))/SUM('Calc - research target (12m)'!$G$67:$G$69) | D13: =((SUMPRODUCT('Calc - research target (12m)'!$F$67:$F$69,'Calc - research target (12m)'!$G$67:$G$69)-'Calc - research target (12m)'!$F$68*'Calc - research target (12m)'!$G$68)+'Calc - research target (12m)'!$G$68*($A13*(D$12-'Calc - research target (12m)'!$B$54)/'Calc - research target (12m)'!$B$53+'Calc - research target (12m)'!$B$52/'Calc - research target (12m)'!$B$53))/SUM('Calc - research target (12m)'!$G$67:$G$69) | E13: =((SUMPRODUCT('Calc - research target (12m)'!$F$67:$F$69,'Calc - research target (12m)'!$G$67:$G$69)-'Calc - research target (12m)'!$F$68*'Calc - research target (12m)'!$G$68)+'Calc - research target (12m)'!$G$68*($A13*(E$12-'Calc - research target (12m)'!$B$54)/'Calc - research target (12m)'!$B$53+'Calc - research target (12m)'!$B$52/'Calc - research target (12m)'!$B$53))/SUM('Calc - research target (12m)'!$G$67:$G$69) | F13: =((SUMPRODUCT('Calc - research target (12m)'!$F$67:$F$69,'Calc - research target (12m)'!$G$67:$G$69)-'Calc - research target (12m)'!$F$68*'Calc - research target (12m)'!$G$68)+'Calc - research target (12m)'!$G$68*($A13*(F$12-'Calc - research target (12m)'!$B$54)/'Calc - research target (12m)'!$B$53+'Calc - research target (12m)'!$B$52/'Calc - research target (12m)'!$B$53))/SUM('Calc - research target (12m)'!$G$67:$G$69)
A14: =Valuation!$B$70+(-2) | B14: =((SUMPRODUCT('Calc - research target (12m)'!$F$67:$F$69,'Calc - research target (12m)'!$G$67:$G$69)-'Calc - research target (12m)'!$F$68*'Calc - research target (12m)'!$G$68)+'Calc - research target (12m)'!$G$68*($A14*(B$12-'Calc - research target (12m)'!$B$54)/'Calc - research target (12m)'!$B$53+'Calc - research target (12m)'!$B$52/'Calc - research target (12m)'!$B$53))/SUM('Calc - research target (12m)'!$G$67:$G$69) | C14: =((SUMPRODUCT('Calc - research target (12m)'!$F$67:$F$69,'Calc - research target (12m)'!$G$67:$G$69)-'Calc - research target (12m)'!$F$68*'Calc - research target (12m)'!$G$68)+'Calc - research target (12m)'!$G$68*($A14*(C$12-'Calc - research target (12m)'!$B$54)/'Calc - research target (12m)'!$B$53+'Calc - research target (12m)'!$B$52/'Calc - research target (12m)'!$B$53))/SUM('Calc - research target (12m)'!$G$67:$G$69) | D14: =((SUMPRODUCT('Calc - research target (12m)'!$F$67:$F$69,'Calc - research target (12m)'!$G$67:$G$69)-'Calc - research target (12m)'!$F$68*'Calc - research target (12m)'!$G$68)+'Calc - research target (12m)'!$G$68*($A14*(D$12-'Calc - research target (12m)'!$B$54)/'Calc - research target (12m)'!$B$53+'Calc - research target (12m)'!$B$52/'Calc - research target (12m)'!$B$53))/SUM('Calc - research target (12m)'!$G$67:$G$69) | E14: =((SUMPRODUCT('Calc - research target (12m)'!$F$67:$F$69,'Calc - research target (12m)'!$G$67:$G$69)-'Calc - research target (12m)'!$F$68*'Calc - research target (12m)'!$G$68)+'Calc - research target (12m)'!$G$68*($A14*(E$12-'Calc - research target (12m)'!$B$54)/'Calc - research target (12m)'!$B$53+'Calc - research target (12m)'!$B$52/'Calc - research target (12m)'!$B$53))/SUM('Calc - research target (12m)'!$G$67:$G$69) | F14: =((SUMPRODUCT('Calc - research target (12m)'!$F$67:$F$69,'Calc - research target (12m)'!$G$67:$G$69)-'Calc - research target (12m)'!$F$68*'Calc - research target (12m)'!$G$68)+'Calc - research target (12m)'!$G$68*($A14*(F$12-'Calc - research target (12m)'!$B$54)/'Calc - research target (12m)'!$B$53+'Calc - research target (12m)'!$B$52/'Calc - research target (12m)'!$B$53))/SUM('Calc - research target (12m)'!$G$67:$G$69)
A15: =Valuation!$B$70+(-1) | B15: =((SUMPRODUCT('Calc - research target (12m)'!$F$67:$F$69,'Calc - research target (12m)'!$G$67:$G$69)-'Calc - research target (12m)'!$F$68*'Calc - research target (12m)'!$G$68)+'Calc - research target (12m)'!$G$68*($A15*(B$12-'Calc - research target (12m)'!$B$54)/'Calc - research target (12m)'!$B$53+'Calc - research target (12m)'!$B$52/'Calc - research target (12m)'!$B$53))/SUM('Calc - research target (12m)'!$G$67:$G$69) | C15: =((SUMPRODUCT('Calc - research target (12m)'!$F$67:$F$69,'Calc - research target (12m)'!$G$67:$G$69)-'Calc - research target (12m)'!$F$68*'Calc - research target (12m)'!$G$68)+'Calc - research target (12m)'!$G$68*($A15*(C$12-'Calc - research target (12m)'!$B$54)/'Calc - research target (12m)'!$B$53+'Calc - research target (12m)'!$B$52/'Calc - research target (12m)'!$B$53))/SUM('Calc - research target (12m)'!$G$67:$G$69) | D15: =((SUMPRODUCT('Calc - research target (12m)'!$F$67:$F$69,'Calc - research target (12m)'!$G$67:$G$69)-'Calc - research target (12m)'!$F$68*'Calc - research target (12m)'!$G$68)+'Calc - research target (12m)'!$G$68*($A15*(D$12-'Calc - research target (12m)'!$B$54)/'Calc - research target (12m)'!$B$53+'Calc - research target (12m)'!$B$52/'Calc - research target (12m)'!$B$53))/SUM('Calc - research target (12m)'!$G$67:$G$69) | E15: =((SUMPRODUCT('Calc - research target (12m)'!$F$67:$F$69,'Calc - research target (12m)'!$G$67:$G$69)-'Calc - research target (12m)'!$F$68*'Calc - research target (12m)'!$G$68)+'Calc - research target (12m)'!$G$68*($A15*(E$12-'Calc - research target (12m)'!$B$54)/'Calc - research target (12m)'!$B$53+'Calc - research target (12m)'!$B$52/'Calc - research target (12m)'!$B$53))/SUM('Calc - research target (12m)'!$G$67:$G$69) | F15: =((SUMPRODUCT('Calc - research target (12m)'!$F$67:$F$69,'Calc - research target (12m)'!$G$67:$G$69)-'Calc - research target (12m)'!$F$68*'Calc - research target (12m)'!$G$68)+'Calc - research target (12m)'!$G$68*($A15*(F$12-'Calc - research target (12m)'!$B$54)/'Calc - research target (12m)'!$B$53+'Calc - research target (12m)'!$B$52/'Calc - research target (12m)'!$B$53))/SUM('Calc - research target (12m)'!$G$67:$G$69)
A16: =Valuation!$B$70+(0) | B16: =((SUMPRODUCT('Calc - research target (12m)'!$F$67:$F$69,'Calc - research target (12m)'!$G$67:$G$69)-'Calc - research target (12m)'!$F$68*'Calc - research target (12m)'!$G$68)+'Calc - research target (12m)'!$G$68*($A16*(B$12-'Calc - research target (12m)'!$B$54)/'Calc - research target (12m)'!$B$53+'Calc - research target (12m)'!$B$52/'Calc - research target (12m)'!$B$53))/SUM('Calc - research target (12m)'!$G$67:$G$69) | C16: =((SUMPRODUCT('Calc - research target (12m)'!$F$67:$F$69,'Calc - research target (12m)'!$G$67:$G$69)-'Calc - research target (12m)'!$F$68*'Calc - research target (12m)'!$G$68)+'Calc - research target (12m)'!$G$68*($A16*(C$12-'Calc - research target (12m)'!$B$54)/'Calc - research target (12m)'!$B$53+'Calc - research target (12m)'!$B$52/'Calc - research target (12m)'!$B$53))/SUM('Calc - research target (12m)'!$G$67:$G$69) | D16: =((SUMPRODUCT('Calc - research target (12m)'!$F$67:$F$69,'Calc - research target (12m)'!$G$67:$G$69)-'Calc - research target (12m)'!$F$68*'Calc - research target (12m)'!$G$68)+'Calc - research target (12m)'!$G$68*($A16*(D$12-'Calc - research target (12m)'!$B$54)/'Calc - research target (12m)'!$B$53+'Calc - research target (12m)'!$B$52/'Calc - research target (12m)'!$B$53))/SUM('Calc - research target (12m)'!$G$67:$G$69) | E16: =((SUMPRODUCT('Calc - research target (12m)'!$F$67:$F$69,'Calc - research target (12m)'!$G$67:$G$69)-'Calc - research target (12m)'!$F$68*'Calc - research target (12m)'!$G$68)+'Calc - research target (12m)'!$G$68*($A16*(E$12-'Calc - research target (12m)'!$B$54)/'Calc - research target (12m)'!$B$53+'Calc - research target (12m)'!$B$52/'Calc - research target (12m)'!$B$53))/SUM('Calc - research target (12m)'!$G$67:$G$69) | F16: =((SUMPRODUCT('Calc - research target (12m)'!$F$67:$F$69,'Calc - research target (12m)'!$G$67:$G$69)-'Calc - research target (12m)'!$F$68*'Calc - research target (12m)'!$G$68)+'Calc - research target (12m)'!$G$68*($A16*(F$12-'Calc - research target (12m)'!$B$54)/'Calc - research target (12m)'!$B$53+'Calc - research target (12m)'!$B$52/'Calc - research target (12m)'!$B$53))/SUM('Calc - research target (12m)'!$G$67:$G$69)
A17: =Valuation!$B$70+(1) | B17: =((SUMPRODUCT('Calc - research target (12m)'!$F$67:$F$69,'Calc - research target (12m)'!$G$67:$G$69)-'Calc - research target (12m)'!$F$68*'Calc - research target (12m)'!$G$68)+'Calc - research target (12m)'!$G$68*($A17*(B$12-'Calc - research target (12m)'!$B$54)/'Calc - research target (12m)'!$B$53+'Calc - research target (12m)'!$B$52/'Calc - research target (12m)'!$B$53))/SUM('Calc - research target (12m)'!$G$67:$G$69) | C17: =((SUMPRODUCT('Calc - research target (12m)'!$F$67:$F$69,'Calc - research target (12m)'!$G$67:$G$69)-'Calc - research target (12m)'!$F$68*'Calc - research target (12m)'!$G$68)+'Calc - research target (12m)'!$G$68*($A17*(C$12-'Calc - research target (12m)'!$B$54)/'Calc - research target (12m)'!$B$53+'Calc - research target (12m)'!$B$52/'Calc - research target (12m)'!$B$53))/SUM('Calc - research target (12m)'!$G$67:$G$69) | D17: =((SUMPRODUCT('Calc - research target (12m)'!$F$67:$F$69,'Calc - research target (12m)'!$G$67:$G$69)-'Calc - research target (12m)'!$F$68*'Calc - research target (12m)'!$G$68)+'Calc - research target (12m)'!$G$68*($A17*(D$12-'Calc - research target (12m)'!$B$54)/'Calc - research target (12m)'!$B$53+'Calc - research target (12m)'!$B$52/'Calc - research target (12m)'!$B$53))/SUM('Calc - research target (12m)'!$G$67:$G$69) | E17: =((SUMPRODUCT('Calc - research target (12m)'!$F$67:$F$69,'Calc - research target (12m)'!$G$67:$G$69)-'Calc - research target (12m)'!$F$68*'Calc - research target (12m)'!$G$68)+'Calc - research target (12m)'!$G$68*($A17*(E$12-'Calc - research target (12m)'!$B$54)/'Calc - research target (12m)'!$B$53+'Calc - research target (12m)'!$B$52/'Calc - research target (12m)'!$B$53))/SUM('Calc - research target (12m)'!$G$67:$G$69) | F17: =((SUMPRODUCT('Calc - research target (12m)'!$F$67:$F$69,'Calc - research target (12m)'!$G$67:$G$69)-'Calc - research target (12m)'!$F$68*'Calc - research target (12m)'!$G$68)+'Calc - research target (12m)'!$G$68*($A17*(F$12-'Calc - research target (12m)'!$B$54)/'Calc - research target (12m)'!$B$53+'Calc - research target (12m)'!$B$52/'Calc - research target (12m)'!$B$53))/SUM('Calc - research target (12m)'!$G$67:$G$69)
A18: =Valuation!$B$70+(2) | B18: =((SUMPRODUCT('Calc - research target (12m)'!$F$67:$F$69,'Calc - research target (12m)'!$G$67:$G$69)-'Calc - research target (12m)'!$F$68*'Calc - research target (12m)'!$G$68)+'Calc - research target (12m)'!$G$68*($A18*(B$12-'Calc - research target (12m)'!$B$54)/'Calc - research target (12m)'!$B$53+'Calc - research target (12m)'!$B$52/'Calc - research target (12m)'!$B$53))/SUM('Calc - research target (12m)'!$G$67:$G$69) | C18: =((SUMPRODUCT('Calc - research target (12m)'!$F$67:$F$69,'Calc - research target (12m)'!$G$67:$G$69)-'Calc - research target (12m)'!$F$68*'Calc - research target (12m)'!$G$68)+'Calc - research target (12m)'!$G$68*($A18*(C$12-'Calc - research target (12m)'!$B$54)/'Calc - research target (12m)'!$B$53+'Calc - research target (12m)'!$B$52/'Calc - research target (12m)'!$B$53))/SUM('Calc - research target (12m)'!$G$67:$G$69) | D18: =((SUMPRODUCT('Calc - research target (12m)'!$F$67:$F$69,'Calc - research target (12m)'!$G$67:$G$69)-'Calc - research target (12m)'!$F$68*'Calc - research target (12m)'!$G$68)+'Calc - research target (12m)'!$G$68*($A18*(D$12-'Calc - research target (12m)'!$B$54)/'Calc - research target (12m)'!$B$53+'Calc - research target (12m)'!$B$52/'Calc - research target (12m)'!$B$53))/SUM('Calc - research target (12m)'!$G$67:$G$69) | E18: =((SUMPRODUCT('Calc - research target (12m)'!$F$67:$F$69,'Calc - research target (12m)'!$G$67:$G$69)-'Calc - research target (12m)'!$F$68*'Calc - research target (12m)'!$G$68)+'Calc - research target (12m)'!$G$68*($A18*(E$12-'Calc - research target (12m)'!$B$54)/'Calc - research target (12m)'!$B$53+'Calc - research target (12m)'!$B$52/'Calc - research target (12m)'!$B$53))/SUM('Calc - research target (12m)'!$G$67:$G$69) | F18: =((SUMPRODUCT('Calc - research target (12m)'!$F$67:$F$69,'Calc - research target (12m)'!$G$67:$G$69)-'Calc - research target (12m)'!$F$68*'Calc - research target (12m)'!$G$68)+'Calc - research target (12m)'!$G$68*($A18*(F$12-'Calc - research target (12m)'!$B$54)/'Calc - research target (12m)'!$B$53+'Calc - research target (12m)'!$B$52/'Calc - research target (12m)'!$B$53))/SUM('Calc - research target (12m)'!$G$67:$G$69)
A19: =Valuation!$B$70+(3) | B19: =((SUMPRODUCT('Calc - research target (12m)'!$F$67:$F$69,'Calc - research target (12m)'!$G$67:$G$69)-'Calc - research target (12m)'!$F$68*'Calc - research target (12m)'!$G$68)+'Calc - research target (12m)'!$G$68*($A19*(B$12-'Calc - research target (12m)'!$B$54)/'Calc - research target (12m)'!$B$53+'Calc - research target (12m)'!$B$52/'Calc - research target (12m)'!$B$53))/SUM('Calc - research target (12m)'!$G$67:$G$69) | C19: =((SUMPRODUCT('Calc - research target (12m)'!$F$67:$F$69,'Calc - research target (12m)'!$G$67:$G$69)-'Calc - research target (12m)'!$F$68*'Calc - research target (12m)'!$G$68)+'Calc - research target (12m)'!$G$68*($A19*(C$12-'Calc - research target (12m)'!$B$54)/'Calc - research target (12m)'!$B$53+'Calc - research target (12m)'!$B$52/'Calc - research target (12m)'!$B$53))/SUM('Calc - research target (12m)'!$G$67:$G$69) | D19: =((SUMPRODUCT('Calc - research target (12m)'!$F$67:$F$69,'Calc - research target (12m)'!$G$67:$G$69)-'Calc - research target (12m)'!$F$68*'Calc - research target (12m)'!$G$68)+'Calc - research target (12m)'!$G$68*($A19*(D$12-'Calc - research target (12m)'!$B$54)/'Calc - research target (12m)'!$B$53+'Calc - research target (12m)'!$B$52/'Calc - research target (12m)'!$B$53))/SUM('Calc - research target (12m)'!$G$67:$G$69) | E19: =((SUMPRODUCT('Calc - research target (12m)'!$F$67:$F$69,'Calc - research target (12m)'!$G$67:$G$69)-'Calc - research target (12m)'!$F$68*'Calc - research target (12m)'!$G$68)+'Calc - research target (12m)'!$G$68*($A19*(E$12-'Calc - research target (12m)'!$B$54)/'Calc - research target (12m)'!$B$53+'Calc - research target (12m)'!$B$52/'Calc - research target (12m)'!$B$53))/SUM('Calc - research target (12m)'!$G$67:$G$69) | F19: =((SUMPRODUCT('Calc - research target (12m)'!$F$67:$F$69,'Calc - research target (12m)'!$G$67:$G$69)-'Calc - research target (12m)'!$F$68*'Calc - research target (12m)'!$G$68)+'Calc - research target (12m)'!$G$68*($A19*(F$12-'Calc - research target (12m)'!$B$54)/'Calc - research target (12m)'!$B$53+'Calc - research target (12m)'!$B$52/'Calc - research target (12m)'!$B$53))/SUM('Calc - research target (12m)'!$G$67:$G$69)
A22: FY2027E diluted EPS: revenue growth change in every year (down) x EBIT margin change (across)
A23: Growth Δ \ margin Δ | B23: -0.01 | C23: -0.005 | D23: 0 | E23: 0.005 | F23: 0.01
A24: -0.02 | B24: =(Valuation!$B$93*(1+Model!E12+$A24)*(1+Model!F12+$A24)*(Model!F14+B$23)+Valuation!$B$94*(1+Model!E16+$A24)*(1+Model!F16+$A24)*(Model!F18+B$23)+Valuation!$B$95*(1+Model!E20+$A24)*(1+Model!F20+$A24)*(Model!F22+B$23)+Valuation!$B$96*(1+Model!E24+$A24)*(1+Model!F24+$A24)*(Model!F26+B$23)+Valuation!$B$97*(1+Model!E28+$A24)*(1+Model!F28+$A24)*(Model!F30+B$23)+Model!F33+Model!F45)*(1-Model!F75)/Model!F52 | C24: =(Valuation!$B$93*(1+Model!E12+$A24)*(1+Model!F12+$A24)*(Model!F14+C$23)+Valuation!$B$94*(1+Model!E16+$A24)*(1+Model!F16+$A24)*(Model!F18+C$23)+Valuation!$B$95*(1+Model!E20+$A24)*(1+Model!F20+$A24)*(Model!F22+C$23)+Valuation!$B$96*(1+Model!E24+$A24)*(1+Model!F24+$A24)*(Model!F26+C$23)+Valuation!$B$97*(1+Model!E28+$A24)*(1+Model!F28+$A24)*(Model!F30+C$23)+Model!F33+Model!F45)*(1-Model!F75)/Model!F52 | D24: =(Valuation!$B$93*(1+Model!E12+$A24)*(1+Model!F12+$A24)*(Model!F14+D$23)+Valuation!$B$94*(1+Model!E16+$A24)*(1+Model!F16+$A24)*(Model!F18+D$23)+Valuation!$B$95*(1+Model!E20+$A24)*(1+Model!F20+$A24)*(Model!F22+D$23)+Valuation!$B$96*(1+Model!E24+$A24)*(1+Model!F24+$A24)*(Model!F26+D$23)+Valuation!$B$97*(1+Model!E28+$A24)*(1+Model!F28+$A24)*(Model!F30+D$23)+Model!F33+Model!F45)*(1-Model!F75)/Model!F52 | E24: =(Valuation!$B$93*(1+Model!E12+$A24)*(1+Model!F12+$A24)*(Model!F14+E$23)+Valuation!$B$94*(1+Model!E16+$A24)*(1+Model!F16+$A24)*(Model!F18+E$23)+Valuation!$B$95*(1+Model!E20+$A24)*(1+Model!F20+$A24)*(Model!F22+E$23)+Valuation!$B$96*(1+Model!E24+$A24)*(1+Model!F24+$A24)*(Model!F26+E$23)+Valuation!$B$97*(1+Model!E28+$A24)*(1+Model!F28+$A24)*(Model!F30+E$23)+Model!F33+Model!F45)*(1-Model!F75)/Model!F52 | F24: =(Valuation!$B$93*(1+Model!E12+$A24)*(1+Model!F12+$A24)*(Model!F14+F$23)+Valuation!$B$94*(1+Model!E16+$A24)*(1+Model!F16+$A24)*(Model!F18+F$23)+Valuation!$B$95*(1+Model!E20+$A24)*(1+Model!F20+$A24)*(Model!F22+F$23)+Valuation!$B$96*(1+Model!E24+$A24)*(1+Model!F24+$A24)*(Model!F26+F$23)+Valuation!$B$97*(1+Model!E28+$A24)*(1+Model!F28+$A24)*(Model!F30+F$23)+Model!F33+Model!F45)*(1-Model!F75)/Model!F52
A25: -0.01 | B25: =(Valuation!$B$93*(1+Model!E12+$A25)*(1+Model!F12+$A25)*(Model!F14+B$23)+Valuation!$B$94*(1+Model!E16+$A25)*(1+Model!F16+$A25)*(Model!F18+B$23)+Valuation!$B$95*(1+Model!E20+$A25)*(1+Model!F20+$A25)*(Model!F22+B$23)+Valuation!$B$96*(1+Model!E24+$A25)*(1+Model!F24+$A25)*(Model!F26+B$23)+Valuation!$B$97*(1+Model!E28+$A25)*(1+Model!F28+$A25)*(Model!F30+B$23)+Model!F33+Model!F45)*(1-Model!F75)/Model!F52 | C25: =(Valuation!$B$93*(1+Model!E12+$A25)*(1+Model!F12+$A25)*(Model!F14+C$23)+Valuation!$B$94*(1+Model!E16+$A25)*(1+Model!F16+$A25)*(Model!F18+C$23)+Valuation!$B$95*(1+Model!E20+$A25)*(1+Model!F20+$A25)*(Model!F22+C$23)+Valuation!$B$96*(1+Model!E24+$A25)*(1+Model!F24+$A25)*(Model!F26+C$23)+Valuation!$B$97*(1+Model!E28+$A25)*(1+Model!F28+$A25)*(Model!F30+C$23)+Model!F33+Model!F45)*(1-Model!F75)/Model!F52 | D25: =(Valuation!$B$93*(1+Model!E12+$A25)*(1+Model!F12+$A25)*(Model!F14+D$23)+Valuation!$B$94*(1+Model!E16+$A25)*(1+Model!F16+$A25)*(Model!F18+D$23)+Valuation!$B$95*(1+Model!E20+$A25)*(1+Model!F20+$A25)*(Model!F22+D$23)+Valuation!$B$96*(1+Model!E24+$A25)*(1+Model!F24+$A25)*(Model!F26+D$23)+Valuation!$B$97*(1+Model!E28+$A25)*(1+Model!F28+$A25)*(Model!F30+D$23)+Model!F33+Model!F45)*(1-Model!F75)/Model!F52 | E25: =(Valuation!$B$93*(1+Model!E12+$A25)*(1+Model!F12+$A25)*(Model!F14+E$23)+Valuation!$B$94*(1+Model!E16+$A25)*(1+Model!F16+$A25)*(Model!F18+E$23)+Valuation!$B$95*(1+Model!E20+$A25)*(1+Model!F20+$A25)*(Model!F22+E$23)+Valuation!$B$96*(1+Model!E24+$A25)*(1+Model!F24+$A25)*(Model!F26+E$23)+Valuation!$B$97*(1+Model!E28+$A25)*(1+Model!F28+$A25)*(Model!F30+E$23)+Model!F33+Model!F45)*(1-Model!F75)/Model!F52 | F25: =(Valuation!$B$93*(1+Model!E12+$A25)*(1+Model!F12+$A25)*(Model!F14+F$23)+Valuation!$B$94*(1+Model!E16+$A25)*(1+Model!F16+$A25)*(Model!F18+F$23)+Valuation!$B$95*(1+Model!E20+$A25)*(1+Model!F20+$A25)*(Model!F22+F$23)+Valuation!$B$96*(1+Model!E24+$A25)*(1+Model!F24+$A25)*(Model!F26+F$23)+Valuation!$B$97*(1+Model!E28+$A25)*(1+Model!F28+$A25)*(Model!F30+F$23)+Model!F33+Model!F45)*(1-Model!F75)/Model!F52
A26: 0 | B26: =(Valuation!$B$93*(1+Model!E12+$A26)*(1+Model!F12+$A26)*(Model!F14+B$23)+Valuation!$B$94*(1+Model!E16+$A26)*(1+Model!F16+$A26)*(Model!F18+B$23)+Valuation!$B$95*(1+Model!E20+$A26)*(1+Model!F20+$A26)*(Model!F22+B$23)+Valuation!$B$96*(1+Model!E24+$A26)*(1+Model!F24+$A26)*(Model!F26+B$23)+Valuation!$B$97*(1+Model!E28+$A26)*(1+Model!F28+$A26)*(Model!F30+B$23)+Model!F33+Model!F45)*(1-Model!F75)/Model!F52 | C26: =(Valuation!$B$93*(1+Model!E12+$A26)*(1+Model!F12+$A26)*(Model!F14+C$23)+Valuation!$B$94*(1+Model!E16+$A26)*(1+Model!F16+$A26)*(Model!F18+C$23)+Valuation!$B$95*(1+Model!E20+$A26)*(1+Model!F20+$A26)*(Model!F22+C$23)+Valuation!$B$96*(1+Model!E24+$A26)*(1+Model!F24+$A26)*(Model!F26+C$23)+Valuation!$B$97*(1+Model!E28+$A26)*(1+Model!F28+$A26)*(Model!F30+C$23)+Model!F33+Model!F45)*(1-Model!F75)/Model!F52 | D26: =(Valuation!$B$93*(1+Model!E12+$A26)*(1+Model!F12+$A26)*(Model!F14+D$23)+Valuation!$B$94*(1+Model!E16+$A26)*(1+Model!F16+$A26)*(Model!F18+D$23)+Valuation!$B$95*(1+Model!E20+$A26)*(1+Model!F20+$A26)*(Model!F22+D$23)+Valuation!$B$96*(1+Model!E24+$A26)*(1+Model!F24+$A26)*(Model!F26+D$23)+Valuation!$B$97*(1+Model!E28+$A26)*(1+Model!F28+$A26)*(Model!F30+D$23)+Model!F33+Model!F45)*(1-Model!F75)/Model!F52 | E26: =(Valuation!$B$93*(1+Model!E12+$A26)*(1+Model!F12+$A26)*(Model!F14+E$23)+Valuation!$B$94*(1+Model!E16+$A26)*(1+Model!F16+$A26)*(Model!F18+E$23)+Valuation!$B$95*(1+Model!E20+$A26)*(1+Model!F20+$A26)*(Model!F22+E$23)+Valuation!$B$96*(1+Model!E24+$A26)*(1+Model!F24+$A26)*(Model!F26+E$23)+Valuation!$B$97*(1+Model!E28+$A26)*(1+Model!F28+$A26)*(Model!F30+E$23)+Model!F33+Model!F45)*(1-Model!F75)/Model!F52 | F26: =(Valuation!$B$93*(1+Model!E12+$A26)*(1+Model!F12+$A26)*(Model!F14+F$23)+Valuation!$B$94*(1+Model!E16+$A26)*(1+Model!F16+$A26)*(Model!F18+F$23)+Valuation!$B$95*(1+Model!E20+$A26)*(1+Model!F20+$A26)*(Model!F22+F$23)+Valuation!$B$96*(1+Model!E24+$A26)*(1+Model!F24+$A26)*(Model!F26+F$23)+Valuation!$B$97*(1+Model!E28+$A26)*(1+Model!F28+$A26)*(Model!F30+F$23)+Model!F33+Model!F45)*(1-Model!F75)/Model!F52
A27: 0.01 | B27: =(Valuation!$B$93*(1+Model!E12+$A27)*(1+Model!F12+$A27)*(Model!F14+B$23)+Valuation!$B$94*(1+Model!E16+$A27)*(1+Model!F16+$A27)*(Model!F18+B$23)+Valuation!$B$95*(1+Model!E20+$A27)*(1+Model!F20+$A27)*(Model!F22+B$23)+Valuation!$B$96*(1+Model!E24+$A27)*(1+Model!F24+$A27)*(Model!F26+B$23)+Valuation!$B$97*(1+Model!E28+$A27)*(1+Model!F28+$A27)*(Model!F30+B$23)+Model!F33+Model!F45)*(1-Model!F75)/Model!F52 | C27: =(Valuation!$B$93*(1+Model!E12+$A27)*(1+Model!F12+$A27)*(Model!F14+C$23)+Valuation!$B$94*(1+Model!E16+$A27)*(1+Model!F16+$A27)*(Model!F18+C$23)+Valuation!$B$95*(1+Model!E20+$A27)*(1+Model!F20+$A27)*(Model!F22+C$23)+Valuation!$B$96*(1+Model!E24+$A27)*(1+Model!F24+$A27)*(Model!F26+C$23)+Valuation!$B$97*(1+Model!E28+$A27)*(1+Model!F28+$A27)*(Model!F30+C$23)+Model!F33+Model!F45)*(1-Model!F75)/Model!F52 | D27: =(Valuation!$B$93*(1+Model!E12+$A27)*(1+Model!F12+$A27)*(Model!F14+D$23)+Valuation!$B$94*(1+Model!E16+$A27)*(1+Model!F16+$A27)*(Model!F18+D$23)+Valuation!$B$95*(1+Model!E20+$A27)*(1+Model!F20+$A27)*(Model!F22+D$23)+Valuation!$B$96*(1+Model!E24+$A27)*(1+Model!F24+$A27)*(Model!F26+D$23)+Valuation!$B$97*(1+Model!E28+$A27)*(1+Model!F28+$A27)*(Model!F30+D$23)+Model!F33+Model!F45)*(1-Model!F75)/Model!F52 | E27: =(Valuation!$B$93*(1+Model!E12+$A27)*(1+Model!F12+$A27)*(Model!F14+E$23)+Valuation!$B$94*(1+Model!E16+$A27)*(1+Model!F16+$A27)*(Model!F18+E$23)+Valuation!$B$95*(1+Model!E20+$A27)*(1+Model!F20+$A27)*(Model!F22+E$23)+Valuation!$B$96*(1+Model!E24+$A27)*(1+Model!F24+$A27)*(Model!F26+E$23)+Valuation!$B$97*(1+Model!E28+$A27)*(1+Model!F28+$A27)*(Model!F30+E$23)+Model!F33+Model!F45)*(1-Model!F75)/Model!F52 | F27: =(Valuation!$B$93*(1+Model!E12+$A27)*(1+Model!F12+$A27)*(Model!F14+F$23)+Valuation!$B$94*(1+Model!E16+$A27)*(1+Model!F16+$A27)*(Model!F18+F$23)+Valuation!$B$95*(1+Model!E20+$A27)*(1+Model!F20+$A27)*(Model!F22+F$23)+Valuation!$B$96*(1+Model!E24+$A27)*(1+Model!F24+$A27)*(Model!F26+F$23)+Valuation!$B$97*(1+Model!E28+$A27)*(1+Model!F28+$A27)*(Model!F30+F$23)+Model!F33+Model!F45)*(1-Model!F75)/Model!F52
A28: 0.02 | B28: =(Valuation!$B$93*(1+Model!E12+$A28)*(1+Model!F12+$A28)*(Model!F14+B$23)+Valuation!$B$94*(1+Model!E16+$A28)*(1+Model!F16+$A28)*(Model!F18+B$23)+Valuation!$B$95*(1+Model!E20+$A28)*(1+Model!F20+$A28)*(Model!F22+B$23)+Valuation!$B$96*(1+Model!E24+$A28)*(1+Model!F24+$A28)*(Model!F26+B$23)+Valuation!$B$97*(1+Model!E28+$A28)*(1+Model!F28+$A28)*(Model!F30+B$23)+Model!F33+Model!F45)*(1-Model!F75)/Model!F52 | C28: =(Valuation!$B$93*(1+Model!E12+$A28)*(1+Model!F12+$A28)*(Model!F14+C$23)+Valuation!$B$94*(1+Model!E16+$A28)*(1+Model!F16+$A28)*(Model!F18+C$23)+Valuation!$B$95*(1+Model!E20+$A28)*(1+Model!F20+$A28)*(Model!F22+C$23)+Valuation!$B$96*(1+Model!E24+$A28)*(1+Model!F24+$A28)*(Model!F26+C$23)+Valuation!$B$97*(1+Model!E28+$A28)*(1+Model!F28+$A28)*(Model!F30+C$23)+Model!F33+Model!F45)*(1-Model!F75)/Model!F52 | D28: =(Valuation!$B$93*(1+Model!E12+$A28)*(1+Model!F12+$A28)*(Model!F14+D$23)+Valuation!$B$94*(1+Model!E16+$A28)*(1+Model!F16+$A28)*(Model!F18+D$23)+Valuation!$B$95*(1+Model!E20+$A28)*(1+Model!F20+$A28)*(Model!F22+D$23)+Valuation!$B$96*(1+Model!E24+$A28)*(1+Model!F24+$A28)*(Model!F26+D$23)+Valuation!$B$97*(1+Model!E28+$A28)*(1+Model!F28+$A28)*(Model!F30+D$23)+Model!F33+Model!F45)*(1-Model!F75)/Model!F52 | E28: =(Valuation!$B$93*(1+Model!E12+$A28)*(1+Model!F12+$A28)*(Model!F14+E$23)+Valuation!$B$94*(1+Model!E16+$A28)*(1+Model!F16+$A28)*(Model!F18+E$23)+Valuation!$B$95*(1+Model!E20+$A28)*(1+Model!F20+$A28)*(Model!F22+E$23)+Valuation!$B$96*(1+Model!E24+$A28)*(1+Model!F24+$A28)*(Model!F26+E$23)+Valuation!$B$97*(1+Model!E28+$A28)*(1+Model!F28+$A28)*(Model!F30+E$23)+Model!F33+Model!F45)*(1-Model!F75)/Model!F52 | F28: =(Valuation!$B$93*(1+Model!E12+$A28)*(1+Model!F12+$A28)*(Model!F14+F$23)+Valuation!$B$94*(1+Model!E16+$A28)*(1+Model!F16+$A28)*(Model!F18+F$23)+Valuation!$B$95*(1+Model!E20+$A28)*(1+Model!F20+$A28)*(Model!F22+F$23)+Valuation!$B$96*(1+Model!E24+$A28)*(1+Model!F24+$A28)*(Model!F26+F$23)+Valuation!$B$97*(1+Model!E28+$A28)*(1+Model!F28+$A28)*(Model!F30+F$23)+Model!F33+Model!F45)*(1-Model!F75)/Model!F52
A30: Net interest and the share count are held at the base case in table 3.

Sheet Distribution
A1: ABT: 12-month distribution (mix of lognormals around each scenario value)
A3: Scenario | B3: Probability | C3: Value at target date | D3: Story
A4: bear | B4: =Valuation!B88 | C4: ='Calc - bear'!$F$70 | D4: =Valuation!J88
A5: base | B5: =Valuation!B89 | C5: ='Calc - base'!$F$70 | D5: =Valuation!J89
A6: bull | B6: =Valuation!B90 | C6: ='Calc - bull'!$F$70 | D6: =Valuation!J90
A8: Probabilities sum to | B8: =SUM(B4:B6)
A9: Spread within each scenario | B9: =Valuation!$B$66
A10: Probability-weighted mean | B10: =($B$4*$C$4+$B$5*$C$5+$B$6*$C$6)*EXP($B$9^2/2)
A12: Quantile | B12: Price
A13: Median (model target) | B13: =SQRT(A60*B60)
A14: 10th percentile | B14: =SQRT(D60*E60)
A15: 25th percentile | B15: =SQRT(G60*H60)
A16: 75th percentile | B16: =SQRT(J60*K60)
A17: 90th percentile | B17: =SQRT(M60*N60)
A19: Each quantile solved by bisection (block: low, high, probability above the midpoint)
A20: Median (model target): low | B20: high | C20: P(above mid) | D20: 10th percentile: low | E20: high | F20: P(above mid) | G20: 25th percentile: low | H20: high | I20: P(above mid) | J20: 75th percentile: low | K20: high | L20: P(above mid) | M20: 90th percentile: low | N20: high | O20: P(above mid)
A21: =MIN($C$4,$C$5,$C$6)*0.2 | B21: =MAX($C$4,$C$5,$C$6)*4 | C21: =SUMPRODUCT($B$4:$B$6,1-NORMSDIST((LN(SQRT(A21*B21))-LN($C$4:$C$6))/$B$9)) | D21: =MIN($C$4,$C$5,$C$6)*0.2 | E21: =MAX($C$4,$C$5,$C$6)*4 | F21: =SUMPRODUCT($B$4:$B$6,1-NORMSDIST((LN(SQRT(D21*E21))-LN($C$4:$C$6))/$B$9)) | G21: =MIN($C$4,$C$5,$C$6)*0.2 | H21: =MAX($C$4,$C$5,$C$6)*4 | I21: =SUMPRODUCT($B$4:$B$6,1-NORMSDIST((LN(SQRT(G21*H21))-LN($C$4:$C$6))/$B$9)) | J21: =MIN($C$4,$C$5,$C$6)*0.2 | K21: =MAX($C$4,$C$5,$C$6)*4 | L21: =SUMPRODUCT($B$4:$B$6,1-NORMSDIST((LN(SQRT(J21*K21))-LN($C$4:$C$6))/$B$9)) | M21: =MIN($C$4,$C$5,$C$6)*0.2 | N21: =MAX($C$4,$C$5,$C$6)*4 | O21: =SUMPRODUCT($B$4:$B$6,1-NORMSDIST((LN(SQRT(M21*N21))-LN($C$4:$C$6))/$B$9))
A22: =IF(C21>0.5,SQRT(A21*B21),A21) | B22: =IF(C21>0.5,B21,SQRT(A21*B21)) | C22: =SUMPRODUCT($B$4:$B$6,1-NORMSDIST((LN(SQRT(A22*B22))-LN($C$4:$C$6))/$B$9)) | D22: =IF(F21>0.9,SQRT(D21*E21),D21) | E22: =IF(F21>0.9,E21,SQRT(D21*E21)) | F22: =SUMPRODUCT($B$4:$B$6,1-NORMSDIST((LN(SQRT(D22*E22))-LN($C$4:$C$6))/$B$9)) | G22: =IF(I21>0.75,SQRT(G21*H21),G21) | H22: =IF(I21>0.75,H21,SQRT(G21*H21)) | I22: =SUMPRODUCT($B$4:$B$6,1-NORMSDIST((LN(SQRT(G22*H22))-LN($C$4:$C$6))/$B$9)) | J22: =IF(L21>0.25,SQRT(J21*K21),J21) | K22: =IF(L21>0.25,K21,SQRT(J21*K21)) | L22: =SUMPRODUCT($B$4:$B$6,1-NORMSDIST((LN(SQRT(J22*K22))-LN($C$4:$C$6))/$B$9)) | M22: =IF(O21>0.09999999999999998,SQRT(M21*N21),M21) | N22: =IF(O21>0.09999999999999998,N21,SQRT(M21*N21)) | O22: =SUMPRODUCT($B$4:$B$6,1-NORMSDIST((LN(SQRT(M22*N22))-LN($C$4:$C$6))/$B$9))
A23: =IF(C22>0.5,SQRT(A22*B22),A22) | B23: =IF(C22>0.5,B22,SQRT(A22*B22)) | C23: =SUMPRODUCT($B$4:$B$6,1-NORMSDIST((LN(SQRT(A23*B23))-LN($C$4:$C$6))/$B$9)) | D23: =IF(F22>0.9,SQRT(D22*E22),D22) | E23: =IF(F22>0.9,E22,SQRT(D22*E22)) | F23: =SUMPRODUCT($B$4:$B$6,1-NORMSDIST((LN(SQRT(D23*E23))-LN($C$4:$C$6))/$B$9)) | G23: =IF(I22>0.75,SQRT(G22*H22),G22) | H23: =IF(I22>0.75,H22,SQRT(G22*H22)) | I23: =SUMPRODUCT($B$4:$B$6,1-NORMSDIST((LN(SQRT(G23*H23))-LN($C$4:$C$6))/$B$9)) | J23: =IF(L22>0.25,SQRT(J22*K22),J22) | K23: =IF(L22>0.25,K22,SQRT(J22*K22)) | L23: =SUMPRODUCT($B$4:$B$6,1-NORMSDIST((LN(SQRT(J23*K23))-LN($C$4:$C$6))/$B$9)) | M23: =IF(O22>0.09999999999999998,SQRT(M22*N22),M22) | N23: =IF(O22>0.09999999999999998,N22,SQRT(M22*N22)) | O23: =SUMPRODUCT($B$4:$B$6,1-NORMSDIST((LN(SQRT(M23*N23))-LN($C$4:$C$6))/$B$9))
A24: =IF(C23>0.5,SQRT(A23*B23),A23) | B24: =IF(C23>0.5,B23,SQRT(A23*B23)) | C24: =SUMPRODUCT($B$4:$B$6,1-NORMSDIST((LN(SQRT(A24*B24))-LN($C$4:$C$6))/$B$9)) | D24: =IF(F23>0.9,SQRT(D23*E23),D23) | E24: =IF(F23>0.9,E23,SQRT(D23*E23)) | F24: =SUMPRODUCT($B$4:$B$6,1-NORMSDIST((LN(SQRT(D24*E24))-LN($C$4:$C$6))/$B$9)) | G24: =IF(I23>0.75,SQRT(G23*H23),G23) | H24: =IF(I23>0.75,H23,SQRT(G23*H23)) | I24: =SUMPRODUCT($B$4:$B$6,1-NORMSDIST((LN(SQRT(G24*H24))-LN($C$4:$C$6))/$B$9)) | J24: =IF(L23>0.25,SQRT(J23*K23),J23) | K24: =IF(L23>0.25,K23,SQRT(J23*K23)) | L24: =SUMPRODUCT($B$4:$B$6,1-NORMSDIST((LN(SQRT(J24*K24))-LN($C$4:$C$6))/$B$9)) | M24: =IF(O23>0.09999999999999998,SQRT(M23*N23),M23) | N24: =IF(O23>0.09999999999999998,N23,SQRT(M23*N23)) | O24: =SUMPRODUCT($B$4:$B$6,1-NORMSDIST((LN(SQRT(M24*N24))-LN($C$4:$C$6))/$B$9))
A25: =IF(C24>0.5,SQRT(A24*B24),A24) | B25: =IF(C24>0.5,B24,SQRT(A24*B24)) | C25: =SUMPRODUCT($B$4:$B$6,1-NORMSDIST((LN(SQRT(A25*B25))-LN($C$4:$C$6))/$B$9)) | D25: =IF(F24>0.9,SQRT(D24*E24),D24) | E25: =IF(F24>0.9,E24,SQRT(D24*E24)) | F25: =SUMPRODUCT($B$4:$B$6,1-NORMSDIST((LN(SQRT(D25*E25))-LN($C$4:$C$6))/$B$9)) | G25: =IF(I24>0.75,SQRT(G24*H24),G24) | H25: =IF(I24>0.75,H24,SQRT(G24*H24)) | I25: =SUMPRODUCT($B$4:$B$6,1-NORMSDIST((LN(SQRT(G25*H25))-LN($C$4:$C$6))/$B$9)) | J25: =IF(L24>0.25,SQRT(J24*K24),J24) | K25: =IF(L24>0.25,K24,SQRT(J24*K24)) | L25: =SUMPRODUCT($B$4:$B$6,1-NORMSDIST((LN(SQRT(J25*K25))-LN($C$4:$C$6))/$B$9)) | M25: =IF(O24>0.09999999999999998,SQRT(M24*N24),M24) | N25: =IF(O24>0.09999999999999998,N24,SQRT(M24*N24)) | O25: =SUMPRODUCT($B$4:$B$6,1-NORMSDIST((LN(SQRT(M25*N25))-LN($C$4:$C$6))/$B$9))
A26: =IF(C25>0.5,SQRT(A25*B25),A25) | B26: =IF(C25>0.5,B25,SQRT(A25*B25)) | C26: =SUMPRODUCT($B$4:$B$6,1-NORMSDIST((LN(SQRT(A26*B26))-LN($C$4:$C$6))/$B$9)) | D26: =IF(F25>0.9,SQRT(D25*E25),D25) | E26: =IF(F25>0.9,E25,SQRT(D25*E25)) | F26: =SUMPRODUCT($B$4:$B$6,1-NORMSDIST((LN(SQRT(D26*E26))-LN($C$4:$C$6))/$B$9)) | G26: =IF(I25>0.75,SQRT(G25*H25),G25) | H26: =IF(I25>0.75,H25,SQRT(G25*H25)) | I26: =SUMPRODUCT($B$4:$B$6,1-NORMSDIST((LN(SQRT(G26*H26))-LN($C$4:$C$6))/$B$9)) | J26: =IF(L25>0.25,SQRT(J25*K25),J25) | K26: =IF(L25>0.25,K25,SQRT(J25*K25)) | L26: =SUMPRODUCT($B$4:$B$6,1-NORMSDIST((LN(SQRT(J26*K26))-LN($C$4:$C$6))/$B$9)) | M26: =IF(O25>0.09999999999999998,SQRT(M25*N25),M25) | N26: =IF(O25>0.09999999999999998,N25,SQRT(M25*N25)) | O26: =SUMPRODUCT($B$4:$B$6,1-NORMSDIST((LN(SQRT(M26*N26))-LN($C$4:$C$6))/$B$9))
A27: =IF(C26>0.5,SQRT(A26*B26),A26) | B27: =IF(C26>0.5,B26,SQRT(A26*B26)) | C27: =SUMPRODUCT($B$4:$B$6,1-NORMSDIST((LN(SQRT(A27*B27))-LN($C$4:$C$6))/$B$9)) | D27: =IF(F26>0.9,SQRT(D26*E26),D26) | E27: =IF(F26>0.9,E26,SQRT(D26*E26)) | F27: =SUMPRODUCT($B$4:$B$6,1-NORMSDIST((LN(SQRT(D27*E27))-LN($C$4:$C$6))/$B$9)) | G27: =IF(I26>0.75,SQRT(G26*H26),G26) | H27: =IF(I26>0.75,H26,SQRT(G26*H26)) | I27: =SUMPRODUCT($B$4:$B$6,1-NORMSDIST((LN(SQRT(G27*H27))-LN($C$4:$C$6))/$B$9)) | J27: =IF(L26>0.25,SQRT(J26*K26),J26) | K27: =IF(L26>0.25,K26,SQRT(J26*K26)) | L27: =SUMPRODUCT($B$4:$B$6,1-NORMSDIST((LN(SQRT(J27*K27))-LN($C$4:$C$6))/$B$9)) | M27: =IF(O26>0.09999999999999998,SQRT(M26*N26),M26) | N27: =IF(O26>0.09999999999999998,N26,SQRT(M26*N26)) | O27: =SUMPRODUCT($B$4:$B$6,1-NORMSDIST((LN(SQRT(M27*N27))-LN($C$4:$C$6))/$B$9))
A28: =IF(C27>0.5,SQRT(A27*B27),A27) | B28: =IF(C27>0.5,B27,SQRT(A27*B27)) | C28: =SUMPRODUCT($B$4:$B$6,1-NORMSDIST((LN(SQRT(A28*B28))-LN($C$4:$C$6))/$B$9)) | D28: =IF(F27>0.9,SQRT(D27*E27),D27) | E28: =IF(F27>0.9,E27,SQRT(D27*E27)) | F28: =SUMPRODUCT($B$4:$B$6,1-NORMSDIST((LN(SQRT(D28*E28))-LN($C$4:$C$6))/$B$9)) | G28: =IF(I27>0.75,SQRT(G27*H27),G27) | H28: =IF(I27>0.75,H27,SQRT(G27*H27)) | I28: =SUMPRODUCT($B$4:$B$6,1-NORMSDIST((LN(SQRT(G28*H28))-LN($C$4:$C$6))/$B$9)) | J28: =IF(L27>0.25,SQRT(J27*K27),J27) | K28: =IF(L27>0.25,K27,SQRT(J27*K27)) | L28: =SUMPRODUCT($B$4:$B$6,1-NORMSDIST((LN(SQRT(J28*K28))-LN($C$4:$C$6))/$B$9)) | M28: =IF(O27>0.09999999999999998,SQRT(M27*N27),M27) | N28: =IF(O27>0.09999999999999998,N27,SQRT(M27*N27)) | O28: =SUMPRODUCT($B$4:$B$6,1-NORMSDIST((LN(SQRT(M28*N28))-LN($C$4:$C$6))/$B$9))
A29: =IF(C28>0.5,SQRT(A28*B28),A28) | B29: =IF(C28>0.5,B28,SQRT(A28*B28)) | C29: =SUMPRODUCT($B$4:$B$6,1-NORMSDIST((LN(SQRT(A29*B29))-LN($C$4:$C$6))/$B$9)) | D29: =IF(F28>0.9,SQRT(D28*E28),D28) | E29: =IF(F28>0.9,E28,SQRT(D28*E28)) | F29: =SUMPRODUCT($B$4:$B$6,1-NORMSDIST((LN(SQRT(D29*E29))-LN($C$4:$C$6))/$B$9)) | G29: =IF(I28>0.75,SQRT(G28*H28),G28) | H29: =IF(I28>0.75,H28,SQRT(G28*H28)) | I29: =SUMPRODUCT($B$4:$B$6,1-NORMSDIST((LN(SQRT(G29*H29))-LN($C$4:$C$6))/$B$9)) | J29: =IF(L28>0.25,SQRT(J28*K28),J28) | K29: =IF(L28>0.25,K28,SQRT(J28*K28)) | L29: =SUMPRODUCT($B$4:$B$6,1-NORMSDIST((LN(SQRT(J29*K29))-LN($C$4:$C$6))/$B$9)) | M29: =IF(O28>0.09999999999999998,SQRT(M28*N28),M28) | N29: =IF(O28>0.09999999999999998,N28,SQRT(M28*N28)) | O29: =SUMPRODUCT($B$4:$B$6,1-NORMSDIST((LN(SQRT(M29*N29))-LN($C$4:$C$6))/$B$9))
A30: =IF(C29>0.5,SQRT(A29*B29),A29) | B30: =IF(C29>0.5,B29,SQRT(A29*B29)) | C30: =SUMPRODUCT($B$4:$B$6,1-NORMSDIST((LN(SQRT(A30*B30))-LN($C$4:$C$6))/$B$9)) | D30: =IF(F29>0.9,SQRT(D29*E29),D29) | E30: =IF(F29>0.9,E29,SQRT(D29*E29)) | F30: =SUMPRODUCT($B$4:$B$6,1-NORMSDIST((LN(SQRT(D30*E30))-LN($C$4:$C$6))/$B$9)) | G30: =IF(I29>0.75,SQRT(G29*H29),G29) | H30: =IF(I29>0.75,H29,SQRT(G29*H29)) | I30: =SUMPRODUCT($B$4:$B$6,1-NORMSDIST((LN(SQRT(G30*H30))-LN($C$4:$C$6))/$B$9)) | J30: =IF(L29>0.25,SQRT(J29*K29),J29) | K30: =IF(L29>0.25,K29,SQRT(J29*K29)) | L30: =SUMPRODUCT($B$4:$B$6,1-NORMSDIST((LN(SQRT(J30*K30))-LN($C$4:$C$6))/$B$9)) | M30: =IF(O29>0.09999999999999998,SQRT(M29*N29),M29) | N30: =IF(O29>0.09999999999999998,N29,SQRT(M29*N29)) | O30: =SUMPRODUCT($B$4:$B$6,1-NORMSDIST((LN(SQRT(M30*N30))-LN($C$4:$C$6))/$B$9))
A31: =IF(C30>0.5,SQRT(A30*B30),A30) | B31: =IF(C30>0.5,B30,SQRT(A30*B30)) | C31: =SUMPRODUCT($B$4:$B$6,1-NORMSDIST((LN(SQRT(A31*B31))-LN($C$4:$C$6))/$B$9)) | D31: =IF(F30>0.9,SQRT(D30*E30),D30) | E31: =IF(F30>0.9,E30,SQRT(D30*E30)) | F31: =SUMPRODUCT($B$4:$B$6,1-NORMSDIST((LN(SQRT(D31*E31))-LN($C$4:$C$6))/$B$9)) | G31: =IF(I30>0.75,SQRT(G30*H30),G30) | H31: =IF(I30>0.75,H30,SQRT(G30*H30)) | I31: =SUMPRODUCT($B$4:$B$6,1-NORMSDIST((LN(SQRT(G31*H31))-LN($C$4:$C$6))/$B$9)) | J31: =IF(L30>0.25,SQRT(J30*K30),J30) | K31: =IF(L30>0.25,K30,SQRT(J30*K30)) | L31: =SUMPRODUCT($B$4:$B$6,1-NORMSDIST((LN(SQRT(J31*K31))-LN($C$4:$C$6))/$B$9)) | M31: =IF(O30>0.09999999999999998,SQRT(M30*N30),M30) | N31: =IF(O30>0.09999999999999998,N30,SQRT(M30*N30)) | O31: =SUMPRODUCT($B$4:$B$6,1-NORMSDIST((LN(SQRT(M31*N31))-LN($C$4:$C$6))/$B$9))
A32: =IF(C31>0.5,SQRT(A31*B31),A31) | B32: =IF(C31>0.5,B31,SQRT(A31*B31)) | C32: =SUMPRODUCT($B$4:$B$6,1-NORMSDIST((LN(SQRT(A32*B32))-LN($C$4:$C$6))/$B$9)) | D32: =IF(F31>0.9,SQRT(D31*E31),D31) | E32: =IF(F31>0.9,E31,SQRT(D31*E31)) | F32: =SUMPRODUCT($B$4:$B$6,1-NORMSDIST((LN(SQRT(D32*E32))-LN($C$4:$C$6))/$B$9)) | G32: =IF(I31>0.75,SQRT(G31*H31),G31) | H32: =IF(I31>0.75,H31,SQRT(G31*H31)) | I32: =SUMPRODUCT($B$4:$B$6,1-NORMSDIST((LN(SQRT(G32*H32))-LN($C$4:$C$6))/$B$9)) | J32: =IF(L31>0.25,SQRT(J31*K31),J31) | K32: =IF(L31>0.25,K31,SQRT(J31*K31)) | L32: =SUMPRODUCT($B$4:$B$6,1-NORMSDIST((LN(SQRT(J32*K32))-LN($C$4:$C$6))/$B$9)) | M32: =IF(O31>0.09999999999999998,SQRT(M31*N31),M31) | N32: =IF(O31>0.09999999999999998,N31,SQRT(M31*N31)) | O32: =SUMPRODUCT($B$4:$B$6,1-NORMSDIST((LN(SQRT(M32*N32))-LN($C$4:$C$6))/$B$9))
A33: =IF(C32>0.5,SQRT(A32*B32),A32) | B33: =IF(C32>0.5,B32,SQRT(A32*B32)) | C33: =SUMPRODUCT($B$4:$B$6,1-NORMSDIST((LN(SQRT(A33*B33))-LN($C$4:$C$6))/$B$9)) | D33: =IF(F32>0.9,SQRT(D32*E32),D32) | E33: =IF(F32>0.9,E32,SQRT(D32*E32)) | F33: =SUMPRODUCT($B$4:$B$6,1-NORMSDIST((LN(SQRT(D33*E33))-LN($C$4:$C$6))/$B$9)) | G33: =IF(I32>0.75,SQRT(G32*H32),G32) | H33: =IF(I32>0.75,H32,SQRT(G32*H32)) | I33: =SUMPRODUCT($B$4:$B$6,1-NORMSDIST((LN(SQRT(G33*H33))-LN($C$4:$C$6))/$B$9)) | J33: =IF(L32>0.25,SQRT(J32*K32),J32) | K33: =IF(L32>0.25,K32,SQRT(J32*K32)) | L33: =SUMPRODUCT($B$4:$B$6,1-NORMSDIST((LN(SQRT(J33*K33))-LN($C$4:$C$6))/$B$9)) | M33: =IF(O32>0.09999999999999998,SQRT(M32*N32),M32) | N33: =IF(O32>0.09999999999999998,N32,SQRT(M32*N32)) | O33: =SUMPRODUCT($B$4:$B$6,1-NORMSDIST((LN(SQRT(M33*N33))-LN($C$4:$C$6))/$B$9))
... A60: =IF(C59>0.5,SQRT(A59*B59),A59) | B60: =IF(C59>0.5,B59,SQRT(A59*B59)) | C60: =SUMPRODUCT($B$4:$B$6,1-NORMSDIST((LN(SQRT(A60*B60))-LN($C$4:$C$6))/$B$9)) | D60: =IF(F59>0.9,SQRT(D59*E59),D59) | E60: =IF(F59>0.9,E59,SQRT(D59*E59)) | F60: =SUMPRODUCT($B$4:$B$6,1-NORMSDIST((LN(SQRT(D60*E60))-LN($C$4:$C$6))/$B$9)) | G60: =IF(I59>0.75,SQRT(G59*H59),G59) | H60: =IF(I59>0.75,H59,SQRT(G59*H59)) | I60: =SUMPRODUCT($B$4:$B$6,1-NORMSDIST((LN(SQRT(G60*H60))-LN($C$4:$C$6))/$B$9)) | J60: =IF(L59>0.25,SQRT(J59*K59),J59) | K60: =IF(L59>0.25,K59,SQRT(J59*K59)) | L60: =SUMPRODUCT($B$4:$B$6,1-NORMSDIST((LN(SQRT(J60*K60))-LN($C$4:$C$6))/$B$9)) | M60: =IF(O59>0.09999999999999998,SQRT(M59*N59),M59) | N60: =IF(O59>0.09999999999999998,N59,SQRT(M59*N59)) | O60: =SUMPRODUCT($B$4:$B$6,1-NORMSDIST((LN(SQRT(M60*N60))-LN($C$4:$C$6))/$B$9))

Sheet Calc - research target (12m)
A1: ABT engine calculation: research target (12m) (reconciled set, no scenario deltas)
A2: Machinery behind the Valuation and Distribution tabs; drivers come from Model, assumptions from Valuation.
A4: Scenario Growth Δ | B4: 0
A5: Scenario Margin Δ | B5: 0
A6: Scenario Multiple Δ (turns) | B6: 0
A7: Scenario WACC Δ | B7: 0
A8: Scenario Multiple %Δ | B8: 0
A9: Scenario Stated EPS/FCF %Δ | B9: 0
A10: Scenario Custom %Δ | B10: 0
A12: WACC | B12: =Valuation!$B$51+B7
A13: Years from last FY end to target date | B13: =(Valuation!$B$45-Valuation!$B$49)/365.25
A14: Years from last FY end to balance date | B14: =(Valuation!$B$55-Valuation!$B$49)/365.25
A15: Years from last FY end to share count date | B15: =(Valuation!$B$61-Valuation!$B$49)/365.25
A16: Projected years | B16: 3
A18: Projection | B18: Base | C18: =Model!E5 | D18: =Model!F5 | E18: =Model!G5
A19: Year index | B19: 0 | C19: 1 | D19: 2 | E19: 3
A20: Period end | C20: =Valuation!$B$49+ROUND(365.25*C19,0) | D20: =Valuation!$B$49+ROUND(365.25*D19,0) | E20: =Valuation!$B$49+ROUND(365.25*E19,0)
A21: Revenue growth | C21: =C22/B22-1 | D21: =D22/C22-1 | E21: =E22/D22-1
A22: Revenue | B22: =Valuation!$B$50 | C22: =C151 | D22: =D151 | E22: =E151
A23: EBIT margin | C23: =C24/C22 | D23: =D24/D22 | E23: =E24/E22
A24: EBIT | C24: =C154 | D24: =D154 | E24: =E154
A25: Tax rate | C25: =Model!E75 | D25: =Model!F75 | E25: =Model!G75
A26: NOPAT | C26: =C24*(1-C25) | D26: =D24*(1-D25) | E26: =E24*(1-E25)
A27: D&A | C27: =C22*(Model!E76) | D27: =D22*(Model!F76) | E27: =E22*(Model!G76)
A28: Capex | C28: =C22*(Model!E77) | D28: =D22*(Model!F77) | E28: =E22*(Model!G77)
A29: Working capital increase | C29: =(Model!E78)*(C22-B22) | D29: =(Model!F78)*(D22-C22) | E29: =(Model!G78)*(E22-D22)
A30: Stock comp | C30: =C22*(Model!E79) | D30: =D22*(Model!F79) | E30: =E22*(Model!G79)
A31: Free cash flow to firm | C31: =C26+C27-C28-C29-IF(AND(Valuation!$B$47="adjusted",Valuation!$B$48="cost"),C30*(1-C25),0) | D31: =D26+D27-D28-D29-IF(AND(Valuation!$B$47="adjusted",Valuation!$B$48="cost"),D30*(1-D25),0) | E31: =E26+E27-E28-E29-IF(AND(Valuation!$B$47="adjusted",Valuation!$B$48="cost"),E30*(1-E25),0)
A32: EBITDA | C32: =C24+C27 | D32: =D24+D27 | E32: =E24+E27
A33: Adj. EBITDA | C33: =C24+C27+C22*(Model!E83) | D33: =D24+D27+D22*(Model!F83) | E33: =E24+E27+E22*(Model!G83)
A34: Shareholder returns + other uses | C34: =C22*Model!E81+Model!E80+Model!E82 | D34: =D22*Model!F81+Model!F80+Model!F82 | E34: =E22*Model!G81+Model!G80+Model!G82
A35: Share of year after target date | C35: =IF(C19<=$B$13,0,C19-MAX(C19-1,$B$13)) | D35: =IF(D19<=$B$13,0,D19-MAX(D19-1,$B$13)) | E35: =IF(E19<=$B$13,0,E19-MAX(E19-1,$B$13))
A36: PV at target date of FCFF | C36: =IF(C35=0,0,C31*C35/(1+$B$12)^(C19-$B$13)) | D36: =IF(D35=0,0,D31*D35/(1+$B$12)^(D19-$B$13)) | E36: =IF(E35=0,0,E31*E35/(1+$B$12)^(E19-$B$13))
A37: Overlap: balance date to target date | C37: =MAX(0,MIN(C19,$B$13)-MAX(C19-1,$B$14)) | D37: =MAX(0,MIN(D19,$B$13)-MAX(D19-1,$B$14)) | E37: =MAX(0,MIN(E19,$B$13)-MAX(E19-1,$B$14))
A38: NTM weight at target date | C38: =MAX(0,MIN(C19,$B$13+1)-MAX(C19-1,$B$13)) | D38: =MAX(0,MIN(D19,$B$13+1)-MAX(D19-1,$B$13)) | E38: =MAX(0,MIN(E19,$B$13+1)-MAX(E19-1,$B$13))
A39: LTM weight at target date | B39: =MAX(0,MIN(0,$B$13)-MAX(-1,$B$13-1)) | C39: =MAX(0,MIN(C19,$B$13)-MAX(C19-1,$B$13-1)) | D39: =MAX(0,MIN(D19,$B$13)-MAX(D19-1,$B$13-1)) | E39: =MAX(0,MIN(E19,$B$13)-MAX(E19-1,$B$13-1))
A41: Value at the target date
A42: PV of free cash flow after the target date | B42: =SUM($C$36:$E$36)
A43: Terminal value at final year | B43: =IF(Valuation!$B$52="exit_multiple",Valuation!$B$54*E32,E31*(1+Valuation!$B$53)/($B$12-Valuation!$B$53))
A44: PV of terminal value at target date | B44: =B43/(1+$B$12)^($B$16-$B$13)
A45: DCF enterprise value at target date | B45: =B42+B44
A46: Terminal value share of DCF | B46: =B44/B45
A47: Free cash flow earned, balance date to target date | B47: =SUMPRODUCT($C$37:$E$37,$C$31:$E$31)
A48: Shareholder returns + other uses paid | B48: =SUMPRODUCT($C$37:$E$37,$C$34:$E$34)
A49: Interest drag on net debt | B49: =Valuation!$B$58*(1-$C$25)*MAX(Valuation!$B$56,0)*MAX($B$13-$B$14,0)
A50: Net debt at target date | B50: =IF(Valuation!$B$59="",Valuation!$B$56-B47+B49+B48,Valuation!$B$59)
A51: Minority interests | B51: =Valuation!$B$57
A52: Adjustments (probability-weighted) | B52: =(Valuation!B77)*Valuation!C77+(Valuation!B78)*Valuation!C78+(Valuation!B79)*Valuation!C79+(Valuation!B80)*Valuation!C80+(Valuation!B81)*Valuation!C81+(Valuation!B82)*Valuation!C82+0
A53: Diluted shares at target date (M) | B53: =IF(Valuation!$B$63="",Valuation!$B$60*(1+Valuation!$B$62)^MAX($B$13-$B$15,0),Valuation!$B$63)
A54: After-tax interest on target-date net debt | B54: =Valuation!$B$58*(1-$C$25)*MAX(B50,0)
A55: Check: WACC vs terminal growth | B55: =IF(AND(Valuation!$B$52<>"exit_multiple",$B$12<=Valuation!$B$53+0.01),"WACC must exceed terminal growth by 1 point","ok")
A56: Check: projection length | B56: =IF(OR($B$13>=$B$16-1,$B$13+1>$B$16),"add projected years past the target date","ok")
A58: Metric at target date | B58: Next 12 months | C58: Last 12 months
A59: Revenue | B59: =SUMPRODUCT($C$38:$E$38,$C$22:$E$22) | C59: =SUMPRODUCT($C$39:$E$39,$C$22:$E$22)+$B$39*$B$22
A60: EBIT | B60: =SUMPRODUCT($C$38:$E$38,$C$24:$E$24) | C60: =SUMPRODUCT($C$39:$E$39,$C$24:$E$24)
A61: EBITDA | B61: =SUMPRODUCT($C$38:$E$38,$C$32:$E$32) | C61: =SUMPRODUCT($C$39:$E$39,$C$32:$E$32)
A62: Adj. EBITDA | B62: =SUMPRODUCT($C$38:$E$38,$C$33:$E$33) | C62: =SUMPRODUCT($C$39:$E$39,$C$33:$E$33)
A63: NOPAT | B63: =SUMPRODUCT($C$38:$E$38,$C$26:$E$26) | C63: =SUMPRODUCT($C$39:$E$39,$C$26:$E$26)
A64: Free cash flow to firm | B64: =SUMPRODUCT($C$38:$E$38,$C$31:$E$31) | C64: =SUMPRODUCT($C$39:$E$39,$C$31:$E$31)
A66: Valuation method | B66: Metric | C66: Multiple used | D66: Basis | E66: Metric at target date | F66: Value per share | G66: Weight | H66: Metric key | I66: Metric shown (stated per-share figure when used)
A67: DCF (cash flow to target date + terminal) | F67: =((B45)-$B$50-$B$51+$B$52)/$B$53 | G67: =Valuation!$B$64
A68: ="Multiple: "&Valuation!A70&" ("&Valuation!D70&")" | B68: =Valuation!A70 | C68: =IF(B68="FCF yield",(Valuation!B70)*(1-$B$8),(Valuation!B70)+IF(B68="EV/sales",0.1,1)*$B$6) | D68: =Valuation!D70 | E68: =IF(D68="ltm",CHOOSE(H68,$C$59,$C$60,$C$61,$C$62,$C$63,$C$64),CHOOSE(H68,$B$59,$B$60,$B$61,$B$62,$B$63,$B$64)) | F68: =IF(OR(B68="EV/EBITDA",B68="EV/sales",B68="EV/EBIT"),((C68*E68)-$B$50-$B$51+$B$52)/$B$53,IF(B68="P/E",IF(Valuation!F70<>"",C68*(Valuation!F70)*(1+$B$9),C68*(E68-$B$54)/$B$53),IF(Valuation!G70<>"",(Valuation!G70)*(1+$B$9)/C68,(E68-IF(Valuation!H70,$B$54,0))/C68/$B$53))+$B$52/$B$53) | G68: =Valuation!C70 | H68: =IF(B68="EV/sales",1,IF(B68="EV/EBIT",2,IF(B68="EV/EBITDA",IF(Valuation!E70="adjusted",4,3),IF(B68="P/E",5,6)))) | I68: =IF(AND(B68="P/E",Valuation!F70<>""),(Valuation!F70)*(1+$B$9),IF(AND(B68="FCF yield",Valuation!G70<>""),(Valuation!G70)*(1+$B$9),E68))
A69: ="Multiple: "&Valuation!A71&" ("&Valuation!D71&")" | B69: =Valuation!A71 | C69: =IF(B69="FCF yield",(Valuation!B71)*(1-$B$8),(Valuation!B71)+IF(B69="EV/sales",0.1,1)*$B$6) | D69: =Valuation!D71 | E69: =IF(D69="ltm",CHOOSE(H69,$C$59,$C$60,$C$61,$C$62,$C$63,$C$64),CHOOSE(H69,$B$59,$B$60,$B$61,$B$62,$B$63,$B$64)) | F69: =IF(OR(B69="EV/EBITDA",B69="EV/sales",B69="EV/EBIT"),((C69*E69)-$B$50-$B$51+$B$52)/$B$53,IF(B69="P/E",IF(Valuation!F71<>"",C69*(Valuation!F71)*(1+$B$9),C69*(E69-$B$54)/$B$53),IF(Valuation!G71<>"",(Valuation!G71)*(1+$B$9)/C69,(E69-IF(Valuation!H71,$B$54,0))/C69/$B$53))+$B$52/$B$53) | G69: =Valuation!C71 | H69: =IF(B69="EV/sales",1,IF(B69="EV/EBIT",2,IF(B69="EV/EBITDA",IF(Valuation!E71="adjusted",4,3),IF(B69="P/E",5,6)))) | I69: =IF(AND(B69="P/E",Valuation!F71<>""),(Valuation!F71)*(1+$B$9),IF(AND(B69="FCF yield",Valuation!G71<>""),(Valuation!G71)*(1+$B$9),E69))
A70: Value per share at target date (weighted methods) | F70: =SUMPRODUCT(F67:F69,G67:G69)/SUM(G67:G69)
A129: Segment build (model_engine.seg_build): revenue and EBIT are the segment sums plus corporate EBIT
A130: Segment | B130: Base | C130: =Model!E5 | D130: =Model!F5 | E130: =Model!G5
A131: Medical Devices (Diabetes Care, EP, Rhyt: revenue growth | C131: =Model!E12+$B$4 | D131: =Model!F12+$B$4 | E131: =Model!G12+$B$4
A132: Medical Devices (Diabetes Care, EP, Rhyt: revenue | B132: =Valuation!$B$93 | C132: =B132*(1+C131) | D132: =C132*(1+D131) | E132: =D132*(1+E131)
A133: Medical Devices (Diabetes Care, EP, Rhyt: EBIT margin | C133: =Model!E14+$B$5 | D133: =Model!F14+$B$5 | E133: =Model!G14+$B$5
A134: Medical Devices (Diabetes Care, EP, Rhyt: EBIT | C134: =C132*C133 | D134: =D132*D133 | E134: =E132*E133
A135: Diagnostics (Core Lab, Rapid/Molecular, : revenue growth | C135: =Model!E16+$B$4 | D135: =Model!F16+$B$4 | E135: =Model!G16+$B$4
A136: Diagnostics (Core Lab, Rapid/Molecular, : revenue | B136: =Valuation!$B$94 | C136: =B136*(1+C135) | D136: =C136*(1+D135) | E136: =D136*(1+E135)
A137: Diagnostics (Core Lab, Rapid/Molecular, : EBIT margin | C137: =Model!E18+$B$5 | D137: =Model!F18+$B$5 | E137: =Model!G18+$B$5
A138: Diagnostics (Core Lab, Rapid/Molecular, : EBIT | C138: =C136*C137 | D138: =D136*D137 | E138: =E136*E137
A139: Nutrition: revenue growth | C139: =Model!E20+$B$4 | D139: =Model!F20+$B$4 | E139: =Model!G20+$B$4
A140: Nutrition: revenue | B140: =Valuation!$B$95 | C140: =B140*(1+C139) | D140: =C140*(1+D139) | E140: =D140*(1+E139)
A141: Nutrition: EBIT margin | C141: =Model!E22+$B$5 | D141: =Model!F22+$B$5 | E141: =Model!G22+$B$5
A142: Nutrition: EBIT | C142: =C140*C141 | D142: =D140*D141 | E142: =E140*E141
A143: Established Pharmaceuticals: revenue growth | C143: =Model!E24+$B$4 | D143: =Model!F24+$B$4 | E143: =Model!G24+$B$4
A144: Established Pharmaceuticals: revenue | B144: =Valuation!$B$96 | C144: =B144*(1+C143) | D144: =C144*(1+D143) | E144: =D144*(1+E143)
A145: Established Pharmaceuticals: EBIT margin | C145: =Model!E26+$B$5 | D145: =Model!F26+$B$5 | E145: =Model!G26+$B$5
A146: Established Pharmaceuticals: EBIT | C146: =C144*C145 | D146: =D144*D145 | E146: =E144*E145
A147: Other: revenue growth | C147: =Model!E28+$B$4 | D147: =Model!F28+$B$4 | E147: =Model!G28+$B$4
A148: Other: revenue | B148: =Valuation!$B$97 | C148: =B148*(1+C147) | D148: =C148*(1+D147) | E148: =D148*(1+E147)
A149: Other: EBIT margin | C149: =Model!E30+$B$5 | D149: =Model!F30+$B$5 | E149: =Model!G30+$B$5
A150: Other: EBIT | C150: =C148*C149 | D150: =D148*D149 | E150: =E148*E149
A151: Total segment revenue | C151: =C132+C136+C140+C144+C148 | D151: =D132+D136+D140+D144+D148 | E151: =E132+E136+E140+E144+E148
A152: Total segment EBIT | C152: =C134+C138+C142+C146+C150 | D152: =D134+D138+D142+D146+D150 | E152: =E134+E138+E142+E146+E150
A153: Corporate / unallocated EBIT | C153: =Model!E33 | D153: =Model!F33 | E153: =Model!G33
A154: EBIT (segments + corporate) | C154: =C152+C153 | D154: =D152+D153 | E154: =E152+E153

Sheet Calc - bear
A1: ABT engine calculation: bear scenario
A2: Machinery behind the Valuation and Distribution tabs; drivers come from Model, assumptions from Valuation.
A4: Scenario Growth Δ | B4: =N(Valuation!C88)
A5: Scenario Margin Δ | B5: =N(Valuation!D88)
A6: Scenario Multiple Δ (turns) | B6: =N(Valuation!E88)
A7: Scenario WACC Δ | B7: =N(Valuation!F88)
A8: Scenario Multiple %Δ | B8: =N(Valuation!G88)
A9: Scenario Stated EPS/FCF %Δ | B9: =N(Valuation!H88)
A10: Scenario Custom %Δ | B10: =N(Valuation!I88)
A12: WACC | B12: =Valuation!$B$51+B7
A13: Years from last FY end to target date | B13: =(Valuation!$B$45-Valuation!$B$49)/365.25
A14: Years from last FY end to balance date | B14: =(Valuation!$B$55-Valuation!$B$49)/365.25
A15: Years from last FY end to share count date | B15: =(Valuation!$B$61-Valuation!$B$49)/365.25
A16: Projected years | B16: 3
A18: Projection | B18: Base | C18: =Model!E5 | D18: =Model!F5 | E18: =Model!G5
A19: Year index | B19: 0 | C19: 1 | D19: 2 | E19: 3
A20: Period end | C20: =Valuation!$B$49+ROUND(365.25*C19,0) | D20: =Valuation!$B$49+ROUND(365.25*D19,0) | E20: =Valuation!$B$49+ROUND(365.25*E19,0)
A21: Revenue growth | C21: =C22/B22-1 | D21: =D22/C22-1 | E21: =E22/D22-1
A22: Revenue | B22: =Valuation!$B$50 | C22: =C151 | D22: =D151 | E22: =E151
A23: EBIT margin | C23: =C24/C22 | D23: =D24/D22 | E23: =E24/E22
A24: EBIT | C24: =C154 | D24: =D154 | E24: =E154
A25: Tax rate | C25: =Model!E75 | D25: =Model!F75 | E25: =Model!G75
A26: NOPAT | C26: =C24*(1-C25) | D26: =D24*(1-D25) | E26: =E24*(1-E25)
A27: D&A | C27: =C22*(Model!E76) | D27: =D22*(Model!F76) | E27: =E22*(Model!G76)
A28: Capex | C28: =C22*(Model!E77) | D28: =D22*(Model!F77) | E28: =E22*(Model!G77)
A29: Working capital increase | C29: =(Model!E78)*(C22-B22) | D29: =(Model!F78)*(D22-C22) | E29: =(Model!G78)*(E22-D22)
A30: Stock comp | C30: =C22*(Model!E79) | D30: =D22*(Model!F79) | E30: =E22*(Model!G79)
A31: Free cash flow to firm | C31: =C26+C27-C28-C29-IF(AND(Valuation!$B$47="adjusted",Valuation!$B$48="cost"),C30*(1-C25),0) | D31: =D26+D27-D28-D29-IF(AND(Valuation!$B$47="adjusted",Valuation!$B$48="cost"),D30*(1-D25),0) | E31: =E26+E27-E28-E29-IF(AND(Valuation!$B$47="adjusted",Valuation!$B$48="cost"),E30*(1-E25),0)
A32: EBITDA | C32: =C24+C27 | D32: =D24+D27 | E32: =E24+E27
A33: Adj. EBITDA | C33: =C24+C27+C22*(Model!E83) | D33: =D24+D27+D22*(Model!F83) | E33: =E24+E27+E22*(Model!G83)
A34: Shareholder returns + other uses | C34: =C22*Model!E81+Model!E80+Model!E82 | D34: =D22*Model!F81+Model!F80+Model!F82 | E34: =E22*Model!G81+Model!G80+Model!G82
A35: Share of year after target date | C35: =IF(C19<=$B$13,0,C19-MAX(C19-1,$B$13)) | D35: =IF(D19<=$B$13,0,D19-MAX(D19-1,$B$13)) | E35: =IF(E19<=$B$13,0,E19-MAX(E19-1,$B$13))
A36: PV at target date of FCFF | C36: =IF(C35=0,0,C31*C35/(1+$B$12)^(C19-$B$13)) | D36: =IF(D35=0,0,D31*D35/(1+$B$12)^(D19-$B$13)) | E36: =IF(E35=0,0,E31*E35/(1+$B$12)^(E19-$B$13))
A37: Overlap: balance date to target date | C37: =MAX(0,MIN(C19,$B$13)-MAX(C19-1,$B$14)) | D37: =MAX(0,MIN(D19,$B$13)-MAX(D19-1,$B$14)) | E37: =MAX(0,MIN(E19,$B$13)-MAX(E19-1,$B$14))
A38: NTM weight at target date | C38: =MAX(0,MIN(C19,$B$13+1)-MAX(C19-1,$B$13)) | D38: =MAX(0,MIN(D19,$B$13+1)-MAX(D19-1,$B$13)) | E38: =MAX(0,MIN(E19,$B$13+1)-MAX(E19-1,$B$13))
A39: LTM weight at target date | B39: =MAX(0,MIN(0,$B$13)-MAX(-1,$B$13-1)) | C39: =MAX(0,MIN(C19,$B$13)-MAX(C19-1,$B$13-1)) | D39: =MAX(0,MIN(D19,$B$13)-MAX(D19-1,$B$13-1)) | E39: =MAX(0,MIN(E19,$B$13)-MAX(E19-1,$B$13-1))
A41: Value at the target date
A42: PV of free cash flow after the target date | B42: =SUM($C$36:$E$36)
A43: Terminal value at final year | B43: =IF(Valuation!$B$52="exit_multiple",Valuation!$B$54*E32,E31*(1+Valuation!$B$53)/($B$12-Valuation!$B$53))
A44: PV of terminal value at target date | B44: =B43/(1+$B$12)^($B$16-$B$13)
A45: DCF enterprise value at target date | B45: =B42+B44
A46: Terminal value share of DCF | B46: =B44/B45
A47: Free cash flow earned, balance date to target date | B47: =SUMPRODUCT($C$37:$E$37,$C$31:$E$31)
A48: Shareholder returns + other uses paid | B48: =SUMPRODUCT($C$37:$E$37,$C$34:$E$34)
A49: Interest drag on net debt | B49: =Valuation!$B$58*(1-$C$25)*MAX(Valuation!$B$56,0)*MAX($B$13-$B$14,0)
A50: Net debt at target date | B50: =IF(Valuation!$B$59="",Valuation!$B$56-B47+B49+B48,Valuation!$B$59)
A51: Minority interests | B51: =Valuation!$B$57
A52: Adjustments (probability-weighted) | B52: =(Valuation!B77)*Valuation!C77+(Valuation!B78)*Valuation!C78+(Valuation!B79)*Valuation!C79+(Valuation!B80)*Valuation!C80+(Valuation!B81)*Valuation!C81+(Valuation!B82)*Valuation!C82+0
A53: Diluted shares at target date (M) | B53: =IF(Valuation!$B$63="",Valuation!$B$60*(1+Valuation!$B$62)^MAX($B$13-$B$15,0),Valuation!$B$63)
A54: After-tax interest on target-date net debt | B54: =Valuation!$B$58*(1-$C$25)*MAX(B50,0)
A55: Check: WACC vs terminal growth | B55: =IF(AND(Valuation!$B$52<>"exit_multiple",$B$12<=Valuation!$B$53+0.01),"WACC must exceed terminal growth by 1 point","ok")
A56: Check: projection length | B56: =IF(OR($B$13>=$B$16-1,$B$13+1>$B$16),"add projected years past the target date","ok")
A58: Metric at target date | B58: Next 12 months | C58: Last 12 months
A59: Revenue | B59: =SUMPRODUCT($C$38:$E$38,$C$22:$E$22) | C59: =SUMPRODUCT($C$39:$E$39,$C$22:$E$22)+$B$39*$B$22
A60: EBIT | B60: =SUMPRODUCT($C$38:$E$38,$C$24:$E$24) | C60: =SUMPRODUCT($C$39:$E$39,$C$24:$E$24)
A61: EBITDA | B61: =SUMPRODUCT($C$38:$E$38,$C$32:$E$32) | C61: =SUMPRODUCT($C$39:$E$39,$C$32:$E$32)
A62: Adj. EBITDA | B62: =SUMPRODUCT($C$38:$E$38,$C$33:$E$33) | C62: =SUMPRODUCT($C$39:$E$39,$C$33:$E$33)
A63: NOPAT | B63: =SUMPRODUCT($C$38:$E$38,$C$26:$E$26) | C63: =SUMPRODUCT($C$39:$E$39,$C$26:$E$26)
A64: Free cash flow to firm | B64: =SUMPRODUCT($C$38:$E$38,$C$31:$E$31) | C64: =SUMPRODUCT($C$39:$E$39,$C$31:$E$31)
A66: Valuation method | B66: Metric | C66: Multiple used | D66: Basis | E66: Metric at target date | F66: Value per share | G66: Weight | H66: Metric key | I66: Metric shown (stated per-share figure when used)
A67: DCF (cash flow to target date + terminal) | F67: =((B45)-$B$50-$B$51+$B$52)/$B$53 | G67: =Valuation!$B$64
A68: ="Multiple: "&Valuation!A70&" ("&Valuation!D70&")" | B68: =Valuation!A70 | C68: =IF(B68="FCF yield",(Valuation!B70)*(1-$B$8),(Valuation!B70)+IF(B68="EV/sales",0.1,1)*$B$6) | D68: =Valuation!D70 | E68: =IF(D68="ltm",CHOOSE(H68,$C$59,$C$60,$C$61,$C$62,$C$63,$C$64),CHOOSE(H68,$B$59,$B$60,$B$61,$B$62,$B$63,$B$64)) | F68: =IF(OR(B68="EV/EBITDA",B68="EV/sales",B68="EV/EBIT"),((C68*E68)-$B$50-$B$51+$B$52)/$B$53,IF(B68="P/E",IF(Valuation!F70<>"",C68*(Valuation!F70)*(1+$B$9),C68*(E68-$B$54)/$B$53),IF(Valuation!G70<>"",(Valuation!G70)*(1+$B$9)/C68,(E68-IF(Valuation!H70,$B$54,0))/C68/$B$53))+$B$52/$B$53) | G68: =Valuation!C70 | H68: =IF(B68="EV/sales",1,IF(B68="EV/EBIT",2,IF(B68="EV/EBITDA",IF(Valuation!E70="adjusted",4,3),IF(B68="P/E",5,6)))) | I68: =IF(AND(B68="P/E",Valuation!F70<>""),(Valuation!F70)*(1+$B$9),IF(AND(B68="FCF yield",Valuation!G70<>""),(Valuation!G70)*(1+$B$9),E68))
A69: ="Multiple: "&Valuation!A71&" ("&Valuation!D71&")" | B69: =Valuation!A71 | C69: =IF(B69="FCF yield",(Valuation!B71)*(1-$B$8),(Valuation!B71)+IF(B69="EV/sales",0.1,1)*$B$6) | D69: =Valuation!D71 | E69: =IF(D69="ltm",CHOOSE(H69,$C$59,$C$60,$C$61,$C$62,$C$63,$C$64),CHOOSE(H69,$B$59,$B$60,$B$61,$B$62,$B$63,$B$64)) | F69: =IF(OR(B69="EV/EBITDA",B69="EV/sales",B69="EV/EBIT"),((C69*E69)-$B$50-$B$51+$B$52)/$B$53,IF(B69="P/E",IF(Valuation!F71<>"",C69*(Valuation!F71)*(1+$B$9),C69*(E69-$B$54)/$B$53),IF(Valuation!G71<>"",(Valuation!G71)*(1+$B$9)/C69,(E69-IF(Valuation!H71,$B$54,0))/C69/$B$53))+$B$52/$B$53) | G69: =Valuation!C71 | H69: =IF(B69="EV/sales",1,IF(B69="EV/EBIT",2,IF(B69="EV/EBITDA",IF(Valuation!E71="adjusted",4,3),IF(B69="P/E",5,6)))) | I69: =IF(AND(B69="P/E",Valuation!F71<>""),(Valuation!F71)*(1+$B$9),IF(AND(B69="FCF yield",Valuation!G71<>""),(Valuation!G71)*(1+$B$9),E69))
A70: Value per share at target date (weighted methods) | F70: =SUMPRODUCT(F67:F69,G67:G69)/SUM(G67:G69)
A129: Segment build (model_engine.seg_build): revenue and EBIT are the segment sums plus corporate EBIT
A130: Segment | B130: Base | C130: =Model!E5 | D130: =Model!F5 | E130: =Model!G5
A131: Medical Devices (Diabetes Care, EP, Rhyt: revenue growth | C131: =Model!E12+$B$4+$B$250 | D131: =Model!F12+$B$4+$B$251 | E131: =Model!G12+$B$4+$B$252
A132: Medical Devices (Diabetes Care, EP, Rhyt: revenue | B132: =Valuation!$B$93 | C132: =B132*(1+C131) | D132: =C132*(1+D131) | E132: =D132*(1+E131)
A133: Medical Devices (Diabetes Care, EP, Rhyt: EBIT margin | C133: =Model!E14+$B$5 | D133: =Model!F14+$B$5 | E133: =Model!G14+$B$5
A134: Medical Devices (Diabetes Care, EP, Rhyt: EBIT | C134: =C132*C133 | D134: =D132*D133 | E134: =E132*E133
A135: Diagnostics (Core Lab, Rapid/Molecular, : revenue growth | C135: =Model!E16+$B$4+$B$253 | D135: =Model!F16+$B$4+$B$254 | E135: =Model!G16+$B$4+$B$255
A136: Diagnostics (Core Lab, Rapid/Molecular, : revenue | B136: =Valuation!$B$94 | C136: =B136*(1+C135) | D136: =C136*(1+D135) | E136: =D136*(1+E135)
A137: Diagnostics (Core Lab, Rapid/Molecular, : EBIT margin | C137: =Model!E18+$B$5 | D137: =Model!F18+$B$5 | E137: =Model!G18+$B$5
A138: Diagnostics (Core Lab, Rapid/Molecular, : EBIT | C138: =C136*C137 | D138: =D136*D137 | E138: =E136*E137
A139: Nutrition: revenue growth | C139: =Model!E20+$B$4 | D139: =Model!F20+$B$4 | E139: =Model!G20+$B$4
A140: Nutrition: revenue | B140: =Valuation!$B$95 | C140: =B140*(1+C139) | D140: =C140*(1+D139) | E140: =D140*(1+E139)
A141: Nutrition: EBIT margin | C141: =Model!E22+$B$5 | D141: =Model!F22+$B$5 | E141: =Model!G22+$B$5
A142: Nutrition: EBIT | C142: =C140*C141 | D142: =D140*D141 | E142: =E140*E141
A143: Established Pharmaceuticals: revenue growth | C143: =Model!E24+$B$4+$B$256 | D143: =Model!F24+$B$4 | E143: =Model!G24+$B$4
A144: Established Pharmaceuticals: revenue | B144: =Valuation!$B$96 | C144: =B144*(1+C143) | D144: =C144*(1+D143) | E144: =D144*(1+E143)
A145: Established Pharmaceuticals: EBIT margin | C145: =Model!E26+$B$5 | D145: =Model!F26+$B$5 | E145: =Model!G26+$B$5
A146: Established Pharmaceuticals: EBIT | C146: =C144*C145 | D146: =D144*D145 | E146: =E144*E145
A147: Other: revenue growth | C147: =Model!E28+$B$4 | D147: =Model!F28+$B$4 | E147: =Model!G28+$B$4
A148: Other: revenue | B148: =Valuation!$B$97 | C148: =B148*(1+C147) | D148: =C148*(1+D147) | E148: =D148*(1+E147)
A149: Other: EBIT margin | C149: =Model!E30+$B$5 | D149: =Model!F30+$B$5 | E149: =Model!G30+$B$5
A150: Other: EBIT | C150: =C148*C149 | D150: =D148*D149 | E150: =E148*E149
A151: Total segment revenue | C151: =C132+C136+C140+C144+C148 | D151: =D132+D136+D140+D144+D148 | E151: =E132+E136+E140+E144+E148
A152: Total segment EBIT | C152: =C134+C138+C142+C146+C150 | D152: =D134+D138+D142+D146+D150 | E152: =E134+E138+E142+E146+E150
A153: Corporate / unallocated EBIT | C153: =Model!E33 | D153: =Model!F33 | E153: =Model!G33
A154: EBIT (segments + corporate) | C154: =C152+C153 | D154: =D152+D153 | E154: =E152+E153
A249: Driver scenario shifts: line-item changes model_drivers.py resolves from this scenario's driver deltas (added to the Model tab inputs)
A250: Medical Devices (Diabetes Care, EP, Rhyt: revenue growth, year 1 | B250: -0.072595502
A251: Medical Devices (Diabetes Care, EP, Rhyt: revenue growth, year 2 | B251: -0.00068243354
A252: Medical Devices (Diabetes Care, EP, Rhyt: revenue growth, year 3 | B252: -0.00041293341
A253: Diagnostics (Core Lab, Rapid/Molecular, : revenue growth, year 1 | B253: -0.063853642
A254: Diagnostics (Core Lab, Rapid/Molecular, : revenue growth, year 2 | B254: -0.0047820315
A255: Diagnostics (Core Lab, Rapid/Molecular, : revenue growth, year 3 | B255: -0.0011707938
A256: Established Pharmaceuticals: revenue growth, year 1 | B256: -0.043489884

Sheet Calc - base
A1: ABT engine calculation: base scenario
A2: Machinery behind the Valuation and Distribution tabs; drivers come from Model, assumptions from Valuation.
A4: Scenario Growth Δ | B4: =N(Valuation!C89)
A5: Scenario Margin Δ | B5: =N(Valuation!D89)
A6: Scenario Multiple Δ (turns) | B6: =N(Valuation!E89)
A7: Scenario WACC Δ | B7: =N(Valuation!F89)
A8: Scenario Multiple %Δ | B8: =N(Valuation!G89)
A9: Scenario Stated EPS/FCF %Δ | B9: =N(Valuation!H89)
A10: Scenario Custom %Δ | B10: =N(Valuation!I89)
A12: WACC | B12: =Valuation!$B$51+B7
A13: Years from last FY end to target date | B13: =(Valuation!$B$45-Valuation!$B$49)/365.25
A14: Years from last FY end to balance date | B14: =(Valuation!$B$55-Valuation!$B$49)/365.25
A15: Years from last FY end to share count date | B15: =(Valuation!$B$61-Valuation!$B$49)/365.25
A16: Projected years | B16: 3
A18: Projection | B18: Base | C18: =Model!E5 | D18: =Model!F5 | E18: =Model!G5
A19: Year index | B19: 0 | C19: 1 | D19: 2 | E19: 3
A20: Period end | C20: =Valuation!$B$49+ROUND(365.25*C19,0) | D20: =Valuation!$B$49+ROUND(365.25*D19,0) | E20: =Valuation!$B$49+ROUND(365.25*E19,0)
A21: Revenue growth | C21: =C22/B22-1 | D21: =D22/C22-1 | E21: =E22/D22-1
A22: Revenue | B22: =Valuation!$B$50 | C22: =C151 | D22: =D151 | E22: =E151
A23: EBIT margin | C23: =C24/C22 | D23: =D24/D22 | E23: =E24/E22
A24: EBIT | C24: =C154 | D24: =D154 | E24: =E154
A25: Tax rate | C25: =Model!E75 | D25: =Model!F75 | E25: =Model!G75
A26: NOPAT | C26: =C24*(1-C25) | D26: =D24*(1-D25) | E26: =E24*(1-E25)
A27: D&A | C27: =C22*(Model!E76) | D27: =D22*(Model!F76) | E27: =E22*(Model!G76)
A28: Capex | C28: =C22*(Model!E77) | D28: =D22*(Model!F77) | E28: =E22*(Model!G77)
A29: Working capital increase | C29: =(Model!E78)*(C22-B22) | D29: =(Model!F78)*(D22-C22) | E29: =(Model!G78)*(E22-D22)
A30: Stock comp | C30: =C22*(Model!E79) | D30: =D22*(Model!F79) | E30: =E22*(Model!G79)
A31: Free cash flow to firm | C31: =C26+C27-C28-C29-IF(AND(Valuation!$B$47="adjusted",Valuation!$B$48="cost"),C30*(1-C25),0) | D31: =D26+D27-D28-D29-IF(AND(Valuation!$B$47="adjusted",Valuation!$B$48="cost"),D30*(1-D25),0) | E31: =E26+E27-E28-E29-IF(AND(Valuation!$B$47="adjusted",Valuation!$B$48="cost"),E30*(1-E25),0)
A32: EBITDA | C32: =C24+C27 | D32: =D24+D27 | E32: =E24+E27
A33: Adj. EBITDA | C33: =C24+C27+C22*(Model!E83) | D33: =D24+D27+D22*(Model!F83) | E33: =E24+E27+E22*(Model!G83)
A34: Shareholder returns + other uses | C34: =C22*Model!E81+Model!E80+Model!E82 | D34: =D22*Model!F81+Model!F80+Model!F82 | E34: =E22*Model!G81+Model!G80+Model!G82
A35: Share of year after target date | C35: =IF(C19<=$B$13,0,C19-MAX(C19-1,$B$13)) | D35: =IF(D19<=$B$13,0,D19-MAX(D19-1,$B$13)) | E35: =IF(E19<=$B$13,0,E19-MAX(E19-1,$B$13))
A36: PV at target date of FCFF | C36: =IF(C35=0,0,C31*C35/(1+$B$12)^(C19-$B$13)) | D36: =IF(D35=0,0,D31*D35/(1+$B$12)^(D19-$B$13)) | E36: =IF(E35=0,0,E31*E35/(1+$B$12)^(E19-$B$13))
A37: Overlap: balance date to target date | C37: =MAX(0,MIN(C19,$B$13)-MAX(C19-1,$B$14)) | D37: =MAX(0,MIN(D19,$B$13)-MAX(D19-1,$B$14)) | E37: =MAX(0,MIN(E19,$B$13)-MAX(E19-1,$B$14))
A38: NTM weight at target date | C38: =MAX(0,MIN(C19,$B$13+1)-MAX(C19-1,$B$13)) | D38: =MAX(0,MIN(D19,$B$13+1)-MAX(D19-1,$B$13)) | E38: =MAX(0,MIN(E19,$B$13+1)-MAX(E19-1,$B$13))
A39: LTM weight at target date | B39: =MAX(0,MIN(0,$B$13)-MAX(-1,$B$13-1)) | C39: =MAX(0,MIN(C19,$B$13)-MAX(C19-1,$B$13-1)) | D39: =MAX(0,MIN(D19,$B$13)-MAX(D19-1,$B$13-1)) | E39: =MAX(0,MIN(E19,$B$13)-MAX(E19-1,$B$13-1))
A41: Value at the target date
A42: PV of free cash flow after the target date | B42: =SUM($C$36:$E$36)
A43: Terminal value at final year | B43: =IF(Valuation!$B$52="exit_multiple",Valuation!$B$54*E32,E31*(1+Valuation!$B$53)/($B$12-Valuation!$B$53))
A44: PV of terminal value at target date | B44: =B43/(1+$B$12)^($B$16-$B$13)
A45: DCF enterprise value at target date | B45: =B42+B44
A46: Terminal value share of DCF | B46: =B44/B45
A47: Free cash flow earned, balance date to target date | B47: =SUMPRODUCT($C$37:$E$37,$C$31:$E$31)
A48: Shareholder returns + other uses paid | B48: =SUMPRODUCT($C$37:$E$37,$C$34:$E$34)
A49: Interest drag on net debt | B49: =Valuation!$B$58*(1-$C$25)*MAX(Valuation!$B$56,0)*MAX($B$13-$B$14,0)
A50: Net debt at target date | B50: =IF(Valuation!$B$59="",Valuation!$B$56-B47+B49+B48,Valuation!$B$59)
A51: Minority interests | B51: =Valuation!$B$57
A52: Adjustments (probability-weighted) | B52: =(Valuation!B77)*Valuation!C77+(Valuation!B78)*Valuation!C78+(Valuation!B79)*Valuation!C79+(Valuation!B80)*Valuation!C80+(Valuation!B81)*Valuation!C81+(Valuation!B82)*Valuation!C82+0
A53: Diluted shares at target date (M) | B53: =IF(Valuation!$B$63="",Valuation!$B$60*(1+Valuation!$B$62)^MAX($B$13-$B$15,0),Valuation!$B$63)
A54: After-tax interest on target-date net debt | B54: =Valuation!$B$58*(1-$C$25)*MAX(B50,0)
A55: Check: WACC vs terminal growth | B55: =IF(AND(Valuation!$B$52<>"exit_multiple",$B$12<=Valuation!$B$53+0.01),"WACC must exceed terminal growth by 1 point","ok")
A56: Check: projection length | B56: =IF(OR($B$13>=$B$16-1,$B$13+1>$B$16),"add projected years past the target date","ok")
A58: Metric at target date | B58: Next 12 months | C58: Last 12 months
A59: Revenue | B59: =SUMPRODUCT($C$38:$E$38,$C$22:$E$22) | C59: =SUMPRODUCT($C$39:$E$39,$C$22:$E$22)+$B$39*$B$22
A60: EBIT | B60: =SUMPRODUCT($C$38:$E$38,$C$24:$E$24) | C60: =SUMPRODUCT($C$39:$E$39,$C$24:$E$24)
A61: EBITDA | B61: =SUMPRODUCT($C$38:$E$38,$C$32:$E$32) | C61: =SUMPRODUCT($C$39:$E$39,$C$32:$E$32)
A62: Adj. EBITDA | B62: =SUMPRODUCT($C$38:$E$38,$C$33:$E$33) | C62: =SUMPRODUCT($C$39:$E$39,$C$33:$E$33)
A63: NOPAT | B63: =SUMPRODUCT($C$38:$E$38,$C$26:$E$26) | C63: =SUMPRODUCT($C$39:$E$39,$C$26:$E$26)
A64: Free cash flow to firm | B64: =SUMPRODUCT($C$38:$E$38,$C$31:$E$31) | C64: =SUMPRODUCT($C$39:$E$39,$C$31:$E$31)
A66: Valuation method | B66: Metric | C66: Multiple used | D66: Basis | E66: Metric at target date | F66: Value per share | G66: Weight | H66: Metric key | I66: Metric shown (stated per-share figure when used)
A67: DCF (cash flow to target date + terminal) | F67: =((B45)-$B$50-$B$51+$B$52)/$B$53 | G67: =Valuation!$B$64
A68: ="Multiple: "&Valuation!A70&" ("&Valuation!D70&")" | B68: =Valuation!A70 | C68: =IF(B68="FCF yield",(Valuation!B70)*(1-$B$8),(Valuation!B70)+IF(B68="EV/sales",0.1,1)*$B$6) | D68: =Valuation!D70 | E68: =IF(D68="ltm",CHOOSE(H68,$C$59,$C$60,$C$61,$C$62,$C$63,$C$64),CHOOSE(H68,$B$59,$B$60,$B$61,$B$62,$B$63,$B$64)) | F68: =IF(OR(B68="EV/EBITDA",B68="EV/sales",B68="EV/EBIT"),((C68*E68)-$B$50-$B$51+$B$52)/$B$53,IF(B68="P/E",IF(Valuation!F70<>"",C68*(Valuation!F70)*(1+$B$9),C68*(E68-$B$54)/$B$53),IF(Valuation!G70<>"",(Valuation!G70)*(1+$B$9)/C68,(E68-IF(Valuation!H70,$B$54,0))/C68/$B$53))+$B$52/$B$53) | G68: =Valuation!C70 | H68: =IF(B68="EV/sales",1,IF(B68="EV/EBIT",2,IF(B68="EV/EBITDA",IF(Valuation!E70="adjusted",4,3),IF(B68="P/E",5,6)))) | I68: =IF(AND(B68="P/E",Valuation!F70<>""),(Valuation!F70)*(1+$B$9),IF(AND(B68="FCF yield",Valuation!G70<>""),(Valuation!G70)*(1+$B$9),E68))
A69: ="Multiple: "&Valuation!A71&" ("&Valuation!D71&")" | B69: =Valuation!A71 | C69: =IF(B69="FCF yield",(Valuation!B71)*(1-$B$8),(Valuation!B71)+IF(B69="EV/sales",0.1,1)*$B$6) | D69: =Valuation!D71 | E69: =IF(D69="ltm",CHOOSE(H69,$C$59,$C$60,$C$61,$C$62,$C$63,$C$64),CHOOSE(H69,$B$59,$B$60,$B$61,$B$62,$B$63,$B$64)) | F69: =IF(OR(B69="EV/EBITDA",B69="EV/sales",B69="EV/EBIT"),((C69*E69)-$B$50-$B$51+$B$52)/$B$53,IF(B69="P/E",IF(Valuation!F71<>"",C69*(Valuation!F71)*(1+$B$9),C69*(E69-$B$54)/$B$53),IF(Valuation!G71<>"",(Valuation!G71)*(1+$B$9)/C69,(E69-IF(Valuation!H71,$B$54,0))/C69/$B$53))+$B$52/$B$53) | G69: =Valuation!C71 | H69: =IF(B69="EV/sales",1,IF(B69="EV/EBIT",2,IF(B69="EV/EBITDA",IF(Valuation!E71="adjusted",4,3),IF(B69="P/E",5,6)))) | I69: =IF(AND(B69="P/E",Valuation!F71<>""),(Valuation!F71)*(1+$B$9),IF(AND(B69="FCF yield",Valuation!G71<>""),(Valuation!G71)*(1+$B$9),E69))
A70: Value per share at target date (weighted methods) | F70: =SUMPRODUCT(F67:F69,G67:G69)/SUM(G67:G69)
A129: Segment build (model_engine.seg_build): revenue and EBIT are the segment sums plus corporate EBIT
A130: Segment | B130: Base | C130: =Model!E5 | D130: =Model!F5 | E130: =Model!G5
A131: Medical Devices (Diabetes Care, EP, Rhyt: revenue growth | C131: =Model!E12+$B$4 | D131: =Model!F12+$B$4 | E131: =Model!G12+$B$4
A132: Medical Devices (Diabetes Care, EP, Rhyt: revenue | B132: =Valuation!$B$93 | C132: =B132*(1+C131) | D132: =C132*(1+D131) | E132: =D132*(1+E131)
A133: Medical Devices (Diabetes Care, EP, Rhyt: EBIT margin | C133: =Model!E14+$B$5 | D133: =Model!F14+$B$5 | E133: =Model!G14+$B$5
A134: Medical Devices (Diabetes Care, EP, Rhyt: EBIT | C134: =C132*C133 | D134: =D132*D133 | E134: =E132*E133
A135: Diagnostics (Core Lab, Rapid/Molecular, : revenue growth | C135: =Model!E16+$B$4 | D135: =Model!F16+$B$4 | E135: =Model!G16+$B$4
A136: Diagnostics (Core Lab, Rapid/Molecular, : revenue | B136: =Valuation!$B$94 | C136: =B136*(1+C135) | D136: =C136*(1+D135) | E136: =D136*(1+E135)
A137: Diagnostics (Core Lab, Rapid/Molecular, : EBIT margin | C137: =Model!E18+$B$5 | D137: =Model!F18+$B$5 | E137: =Model!G18+$B$5
A138: Diagnostics (Core Lab, Rapid/Molecular, : EBIT | C138: =C136*C137 | D138: =D136*D137 | E138: =E136*E137
A139: Nutrition: revenue growth | C139: =Model!E20+$B$4 | D139: =Model!F20+$B$4 | E139: =Model!G20+$B$4
A140: Nutrition: revenue | B140: =Valuation!$B$95 | C140: =B140*(1+C139) | D140: =C140*(1+D139) | E140: =D140*(1+E139)
A141: Nutrition: EBIT margin | C141: =Model!E22+$B$5 | D141: =Model!F22+$B$5 | E141: =Model!G22+$B$5
A142: Nutrition: EBIT | C142: =C140*C141 | D142: =D140*D141 | E142: =E140*E141
A143: Established Pharmaceuticals: revenue growth | C143: =Model!E24+$B$4 | D143: =Model!F24+$B$4 | E143: =Model!G24+$B$4
A144: Established Pharmaceuticals: revenue | B144: =Valuation!$B$96 | C144: =B144*(1+C143) | D144: =C144*(1+D143) | E144: =D144*(1+E143)
A145: Established Pharmaceuticals: EBIT margin | C145: =Model!E26+$B$5 | D145: =Model!F26+$B$5 | E145: =Model!G26+$B$5
A146: Established Pharmaceuticals: EBIT | C146: =C144*C145 | D146: =D144*D145 | E146: =E144*E145
A147: Other: revenue growth | C147: =Model!E28+$B$4 | D147: =Model!F28+$B$4 | E147: =Model!G28+$B$4
A148: Other: revenue | B148: =Valuation!$B$97 | C148: =B148*(1+C147) | D148: =C148*(1+D147) | E148: =D148*(1+E147)
A149: Other: EBIT margin | C149: =Model!E30+$B$5 | D149: =Model!F30+$B$5 | E149: =Model!G30+$B$5
A150: Other: EBIT | C150: =C148*C149 | D150: =D148*D149 | E150: =E148*E149
A151: Total segment revenue | C151: =C132+C136+C140+C144+C148 | D151: =D132+D136+D140+D144+D148 | E151: =E132+E136+E140+E144+E148
A152: Total segment EBIT | C152: =C134+C138+C142+C146+C150 | D152: =D134+D138+D142+D146+D150 | E152: =E134+E138+E142+E146+E150
A153: Corporate / unallocated EBIT | C153: =Model!E33 | D153: =Model!F33 | E153: =Model!G33
A154: EBIT (segments + corporate) | C154: =C152+C153 | D154: =D152+D153 | E154: =E152+E153

Sheet Calc - bull
A1: ABT engine calculation: bull scenario
A2: Machinery behind the Valuation and Distribution tabs; drivers come from Model, assumptions from Valuation.
A4: Scenario Growth Δ | B4: =N(Valuation!C90)
A5: Scenario Margin Δ | B5: =N(Valuation!D90)
A6: Scenario Multiple Δ (turns) | B6: =N(Valuation!E90)
A7: Scenario WACC Δ | B7: =N(Valuation!F90)
A8: Scenario Multiple %Δ | B8: =N(Valuation!G90)
A9: Scenario Stated EPS/FCF %Δ | B9: =N(Valuation!H90)
A10: Scenario Custom %Δ | B10: =N(Valuation!I90)
A12: WACC | B12: =Valuation!$B$51+B7
A13: Years from last FY end to target date | B13: =(Valuation!$B$45-Valuation!$B$49)/365.25
A14: Years from last FY end to balance date | B14: =(Valuation!$B$55-Valuation!$B$49)/365.25
A15: Years from last FY end to share count date | B15: =(Valuation!$B$61-Valuation!$B$49)/365.25
A16: Projected years | B16: 3
A18: Projection | B18: Base | C18: =Model!E5 | D18: =Model!F5 | E18: =Model!G5
A19: Year index | B19: 0 | C19: 1 | D19: 2 | E19: 3
A20: Period end | C20: =Valuation!$B$49+ROUND(365.25*C19,0) | D20: =Valuation!$B$49+ROUND(365.25*D19,0) | E20: =Valuation!$B$49+ROUND(365.25*E19,0)
A21: Revenue growth | C21: =C22/B22-1 | D21: =D22/C22-1 | E21: =E22/D22-1
A22: Revenue | B22: =Valuation!$B$50 | C22: =C151 | D22: =D151 | E22: =E151
A23: EBIT margin | C23: =C24/C22 | D23: =D24/D22 | E23: =E24/E22
A24: EBIT | C24: =C154 | D24: =D154 | E24: =E154
A25: Tax rate | C25: =Model!E75 | D25: =Model!F75 | E25: =Model!G75
A26: NOPAT | C26: =C24*(1-C25) | D26: =D24*(1-D25) | E26: =E24*(1-E25)
A27: D&A | C27: =C22*(Model!E76) | D27: =D22*(Model!F76) | E27: =E22*(Model!G76)
A28: Capex | C28: =C22*(Model!E77) | D28: =D22*(Model!F77) | E28: =E22*(Model!G77)
A29: Working capital increase | C29: =(Model!E78)*(C22-B22) | D29: =(Model!F78)*(D22-C22) | E29: =(Model!G78)*(E22-D22)
A30: Stock comp | C30: =C22*(Model!E79) | D30: =D22*(Model!F79) | E30: =E22*(Model!G79)
A31: Free cash flow to firm | C31: =C26+C27-C28-C29-IF(AND(Valuation!$B$47="adjusted",Valuation!$B$48="cost"),C30*(1-C25),0) | D31: =D26+D27-D28-D29-IF(AND(Valuation!$B$47="adjusted",Valuation!$B$48="cost"),D30*(1-D25),0) | E31: =E26+E27-E28-E29-IF(AND(Valuation!$B$47="adjusted",Valuation!$B$48="cost"),E30*(1-E25),0)
A32: EBITDA | C32: =C24+C27 | D32: =D24+D27 | E32: =E24+E27
A33: Adj. EBITDA | C33: =C24+C27+C22*(Model!E83) | D33: =D24+D27+D22*(Model!F83) | E33: =E24+E27+E22*(Model!G83)
A34: Shareholder returns + other uses | C34: =C22*Model!E81+Model!E80+Model!E82 | D34: =D22*Model!F81+Model!F80+Model!F82 | E34: =E22*Model!G81+Model!G80+Model!G82
A35: Share of year after target date | C35: =IF(C19<=$B$13,0,C19-MAX(C19-1,$B$13)) | D35: =IF(D19<=$B$13,0,D19-MAX(D19-1,$B$13)) | E35: =IF(E19<=$B$13,0,E19-MAX(E19-1,$B$13))
A36: PV at target date of FCFF | C36: =IF(C35=0,0,C31*C35/(1+$B$12)^(C19-$B$13)) | D36: =IF(D35=0,0,D31*D35/(1+$B$12)^(D19-$B$13)) | E36: =IF(E35=0,0,E31*E35/(1+$B$12)^(E19-$B$13))
A37: Overlap: balance date to target date | C37: =MAX(0,MIN(C19,$B$13)-MAX(C19-1,$B$14)) | D37: =MAX(0,MIN(D19,$B$13)-MAX(D19-1,$B$14)) | E37: =MAX(0,MIN(E19,$B$13)-MAX(E19-1,$B$14))
A38: NTM weight at target date | C38: =MAX(0,MIN(C19,$B$13+1)-MAX(C19-1,$B$13)) | D38: =MAX(0,MIN(D19,$B$13+1)-MAX(D19-1,$B$13)) | E38: =MAX(0,MIN(E19,$B$13+1)-MAX(E19-1,$B$13))
A39: LTM weight at target date | B39: =MAX(0,MIN(0,$B$13)-MAX(-1,$B$13-1)) | C39: =MAX(0,MIN(C19,$B$13)-MAX(C19-1,$B$13-1)) | D39: =MAX(0,MIN(D19,$B$13)-MAX(D19-1,$B$13-1)) | E39: =MAX(0,MIN(E19,$B$13)-MAX(E19-1,$B$13-1))
A41: Value at the target date
A42: PV of free cash flow after the target date | B42: =SUM($C$36:$E$36)
A43: Terminal value at final year | B43: =IF(Valuation!$B$52="exit_multiple",Valuation!$B$54*E32,E31*(1+Valuation!$B$53)/($B$12-Valuation!$B$53))
A44: PV of terminal value at target date | B44: =B43/(1+$B$12)^($B$16-$B$13)
A45: DCF enterprise value at target date | B45: =B42+B44
A46: Terminal value share of DCF | B46: =B44/B45
A47: Free cash flow earned, balance date to target date | B47: =SUMPRODUCT($C$37:$E$37,$C$31:$E$31)
A48: Shareholder returns + other uses paid | B48: =SUMPRODUCT($C$37:$E$37,$C$34:$E$34)
A49: Interest drag on net debt | B49: =Valuation!$B$58*(1-$C$25)*MAX(Valuation!$B$56,0)*MAX($B$13-$B$14,0)
A50: Net debt at target date | B50: =IF(Valuation!$B$59="",Valuation!$B$56-B47+B49+B48,Valuation!$B$59)
A51: Minority interests | B51: =Valuation!$B$57
A52: Adjustments (probability-weighted) | B52: =(Valuation!B77)*Valuation!C77+(Valuation!B78)*Valuation!C78+(Valuation!B79)*Valuation!C79+(Valuation!B80)*Valuation!C80+(Valuation!B81)*Valuation!C81+(Valuation!B82)*Valuation!C82+0
A53: Diluted shares at target date (M) | B53: =IF(Valuation!$B$63="",Valuation!$B$60*(1+Valuation!$B$62)^MAX($B$13-$B$15,0),Valuation!$B$63)
A54: After-tax interest on target-date net debt | B54: =Valuation!$B$58*(1-$C$25)*MAX(B50,0)
A55: Check: WACC vs terminal growth | B55: =IF(AND(Valuation!$B$52<>"exit_multiple",$B$12<=Valuation!$B$53+0.01),"WACC must exceed terminal growth by 1 point","ok")
A56: Check: projection length | B56: =IF(OR($B$13>=$B$16-1,$B$13+1>$B$16),"add projected years past the target date","ok")
A58: Metric at target date | B58: Next 12 months | C58: Last 12 months
A59: Revenue | B59: =SUMPRODUCT($C$38:$E$38,$C$22:$E$22) | C59: =SUMPRODUCT($C$39:$E$39,$C$22:$E$22)+$B$39*$B$22
A60: EBIT | B60: =SUMPRODUCT($C$38:$E$38,$C$24:$E$24) | C60: =SUMPRODUCT($C$39:$E$39,$C$24:$E$24)
A61: EBITDA | B61: =SUMPRODUCT($C$38:$E$38,$C$32:$E$32) | C61: =SUMPRODUCT($C$39:$E$39,$C$32:$E$32)
A62: Adj. EBITDA | B62: =SUMPRODUCT($C$38:$E$38,$C$33:$E$33) | C62: =SUMPRODUCT($C$39:$E$39,$C$33:$E$33)
A63: NOPAT | B63: =SUMPRODUCT($C$38:$E$38,$C$26:$E$26) | C63: =SUMPRODUCT($C$39:$E$39,$C$26:$E$26)
A64: Free cash flow to firm | B64: =SUMPRODUCT($C$38:$E$38,$C$31:$E$31) | C64: =SUMPRODUCT($C$39:$E$39,$C$31:$E$31)
A66: Valuation method | B66: Metric | C66: Multiple used | D66: Basis | E66: Metric at target date | F66: Value per share | G66: Weight | H66: Metric key | I66: Metric shown (stated per-share figure when used)
A67: DCF (cash flow to target date + terminal) | F67: =((B45)-$B$50-$B$51+$B$52)/$B$53 | G67: =Valuation!$B$64
A68: ="Multiple: "&Valuation!A70&" ("&Valuation!D70&")" | B68: =Valuation!A70 | C68: =IF(B68="FCF yield",(Valuation!B70)*(1-$B$8),(Valuation!B70)+IF(B68="EV/sales",0.1,1)*$B$6) | D68: =Valuation!D70 | E68: =IF(D68="ltm",CHOOSE(H68,$C$59,$C$60,$C$61,$C$62,$C$63,$C$64),CHOOSE(H68,$B$59,$B$60,$B$61,$B$62,$B$63,$B$64)) | F68: =IF(OR(B68="EV/EBITDA",B68="EV/sales",B68="EV/EBIT"),((C68*E68)-$B$50-$B$51+$B$52)/$B$53,IF(B68="P/E",IF(Valuation!F70<>"",C68*(Valuation!F70)*(1+$B$9),C68*(E68-$B$54)/$B$53),IF(Valuation!G70<>"",(Valuation!G70)*(1+$B$9)/C68,(E68-IF(Valuation!H70,$B$54,0))/C68/$B$53))+$B$52/$B$53) | G68: =Valuation!C70 | H68: =IF(B68="EV/sales",1,IF(B68="EV/EBIT",2,IF(B68="EV/EBITDA",IF(Valuation!E70="adjusted",4,3),IF(B68="P/E",5,6)))) | I68: =IF(AND(B68="P/E",Valuation!F70<>""),(Valuation!F70)*(1+$B$9),IF(AND(B68="FCF yield",Valuation!G70<>""),(Valuation!G70)*(1+$B$9),E68))
A69: ="Multiple: "&Valuation!A71&" ("&Valuation!D71&")" | B69: =Valuation!A71 | C69: =IF(B69="FCF yield",(Valuation!B71)*(1-$B$8),(Valuation!B71)+IF(B69="EV/sales",0.1,1)*$B$6) | D69: =Valuation!D71 | E69: =IF(D69="ltm",CHOOSE(H69,$C$59,$C$60,$C$61,$C$62,$C$63,$C$64),CHOOSE(H69,$B$59,$B$60,$B$61,$B$62,$B$63,$B$64)) | F69: =IF(OR(B69="EV/EBITDA",B69="EV/sales",B69="EV/EBIT"),((C69*E69)-$B$50-$B$51+$B$52)/$B$53,IF(B69="P/E",IF(Valuation!F71<>"",C69*(Valuation!F71)*(1+$B$9),C69*(E69-$B$54)/$B$53),IF(Valuation!G71<>"",(Valuation!G71)*(1+$B$9)/C69,(E69-IF(Valuation!H71,$B$54,0))/C69/$B$53))+$B$52/$B$53) | G69: =Valuation!C71 | H69: =IF(B69="EV/sales",1,IF(B69="EV/EBIT",2,IF(B69="EV/EBITDA",IF(Valuation!E71="adjusted",4,3),IF(B69="P/E",5,6)))) | I69: =IF(AND(B69="P/E",Valuation!F71<>""),(Valuation!F71)*(1+$B$9),IF(AND(B69="FCF yield",Valuation!G71<>""),(Valuation!G71)*(1+$B$9),E69))
A70: Value per share at target date (weighted methods) | F70: =SUMPRODUCT(F67:F69,G67:G69)/SUM(G67:G69)
A129: Segment build (model_engine.seg_build): revenue and EBIT are the segment sums plus corporate EBIT
A130: Segment | B130: Base | C130: =Model!E5 | D130: =Model!F5 | E130: =Model!G5
A131: Medical Devices (Diabetes Care, EP, Rhyt: revenue growth | C131: =Model!E12+$B$4+$B$250 | D131: =Model!F12+$B$4+$B$251 | E131: =Model!G12+$B$4+$B$252
A132: Medical Devices (Diabetes Care, EP, Rhyt: revenue | B132: =Valuation!$B$93 | C132: =B132*(1+C131) | D132: =C132*(1+D131) | E132: =D132*(1+E131)
A133: Medical Devices (Diabetes Care, EP, Rhyt: EBIT margin | C133: =Model!E14+$B$5 | D133: =Model!F14+$B$5 | E133: =Model!G14+$B$5
A134: Medical Devices (Diabetes Care, EP, Rhyt: EBIT | C134: =C132*C133 | D134: =D132*D133 | E134: =E132*E133
A135: Diagnostics (Core Lab, Rapid/Molecular, : revenue growth | C135: =Model!E16+$B$4+$B$253 | D135: =Model!F16+$B$4+$B$254 | E135: =Model!G16+$B$4+$B$255
A136: Diagnostics (Core Lab, Rapid/Molecular, : revenue | B136: =Valuation!$B$94 | C136: =B136*(1+C135) | D136: =C136*(1+D135) | E136: =D136*(1+E135)
A137: Diagnostics (Core Lab, Rapid/Molecular, : EBIT margin | C137: =Model!E18+$B$5 | D137: =Model!F18+$B$5 | E137: =Model!G18+$B$5
A138: Diagnostics (Core Lab, Rapid/Molecular, : EBIT | C138: =C136*C137 | D138: =D136*D137 | E138: =E136*E137
A139: Nutrition: revenue growth | C139: =Model!E20+$B$4 | D139: =Model!F20+$B$4 | E139: =Model!G20+$B$4
A140: Nutrition: revenue | B140: =Valuation!$B$95 | C140: =B140*(1+C139) | D140: =C140*(1+D139) | E140: =D140*(1+E139)
A141: Nutrition: EBIT margin | C141: =Model!E22+$B$5 | D141: =Model!F22+$B$5 | E141: =Model!G22+$B$5
A142: Nutrition: EBIT | C142: =C140*C141 | D142: =D140*D141 | E142: =E140*E141
A143: Established Pharmaceuticals: revenue growth | C143: =Model!E24+$B$4+$B$256 | D143: =Model!F24+$B$4 | E143: =Model!G24+$B$4
A144: Established Pharmaceuticals: revenue | B144: =Valuation!$B$96 | C144: =B144*(1+C143) | D144: =C144*(1+D143) | E144: =D144*(1+E143)
A145: Established Pharmaceuticals: EBIT margin | C145: =Model!E26+$B$5 | D145: =Model!F26+$B$5 | E145: =Model!G26+$B$5
A146: Established Pharmaceuticals: EBIT | C146: =C144*C145 | D146: =D144*D145 | E146: =E144*E145
A147: Other: revenue growth | C147: =Model!E28+$B$4 | D147: =Model!F28+$B$4 | E147: =Model!G28+$B$4
A148: Other: revenue | B148: =Valuation!$B$97 | C148: =B148*(1+C147) | D148: =C148*(1+D147) | E148: =D148*(1+E147)
A149: Other: EBIT margin | C149: =Model!E30+$B$5 | D149: =Model!F30+$B$5 | E149: =Model!G30+$B$5
A150: Other: EBIT | C150: =C148*C149 | D150: =D148*D149 | E150: =E148*E149
A151: Total segment revenue | C151: =C132+C136+C140+C144+C148 | D151: =D132+D136+D140+D144+D148 | E151: =E132+E136+E140+E144+E148
A152: Total segment EBIT | C152: =C134+C138+C142+C146+C150 | D152: =D134+D138+D142+D146+D150 | E152: =E134+E138+E142+E146+E150
A153: Corporate / unallocated EBIT | C153: =Model!E33 | D153: =Model!F33 | E153: =Model!G33
A154: EBIT (segments + corporate) | C154: =C152+C153 | D154: =D152+D153 | E154: =E152+E153
A249: Driver scenario shifts: line-item changes model_drivers.py resolves from this scenario's driver deltas (added to the Model tab inputs)
A250: Medical Devices (Diabetes Care, EP, Rhyt: revenue growth, year 1 | B250: 0.06560995
A251: Medical Devices (Diabetes Care, EP, Rhyt: revenue growth, year 2 | B251: 0.00034307339
A252: Medical Devices (Diabetes Care, EP, Rhyt: revenue growth, year 3 | B252: 9.9821438e-05
A253: Diagnostics (Core Lab, Rapid/Molecular, : revenue growth, year 1 | B253: 0.035253441
A254: Diagnostics (Core Lab, Rapid/Molecular, : revenue growth, year 2 | B254: 0.0028545797
A255: Diagnostics (Core Lab, Rapid/Molecular, : revenue growth, year 3 | B255: 0.00069414411
A256: Established Pharmaceuticals: revenue growth, year 1 | B256: 0.021744942

Sheet Agents
A1: ABT: each forecaster's own assumption set through the same engine (from model_engine.json, not live)
A3: Set | B3: Research target (12m) | C3: Median | D3: 25th pct | E3: 75th pct | F3: WACC | G3: Y1 growth | H3: Y1 margin | I3: Terminal growth | J3: DCF weight | K3: Years | L3: Multiples | M3: Supervisor's note
A4: agent 1 | B4: 110.82404 | C4: 108.07835 | D4: 90.171267 | E4: 124.97816 | J4: 0 | K4: 3 | L4: P/E 17.5 (ntm); EV/EBITDA 13.5 (ntm) | M4: 17.5x P/E (+0.5x vs the others) justified by the spin removing Nutrition, which is ~90% likely to happen after the horizon; SOTP leg at 0.20 weight with no weight evidence; no Libre 3 claims.
A5: agent 2 | B5: 108.79936 | C5: 108.24739 | D5: 90.896167 | E5: 124.22331 | J5: 0 | K5: 3 | L5: P/E 17.2 (ntm); EV/EBITDA 13.3 (ntm) | M5: Clean build; peer_basis text in horizon_multiples is stale (12-peer 19.4x, 8-peer 15.5x); no separation or specified-items cash; Dx FY26 Q4 ~1% low.
A6: agent 3 | B6: 104.52984 | C6: 100.82671 | D6: 83.164706 | E6: 119.16269 | J6: 0 | K6: 3 | L6: P/E 17.0 (ntm); EV/EBITDA 13.5 (ntm) | M6: EV/EBITDA leg ($99.7) cuts EBITDA for recurring specified items and also applies a peer multiple: the cash cost is real but belongs in one place; Nutrition growth 2.5% light vs Q3 +4.9%. [Gate 2026-10-21: FY28 growth, shareholder returns and NTM EPS ($6.39) arithmetic corrected from its own inputs: $104.89 -> $104.53.]
A7: agent 4 | B7: 107.95791 | C7: 105.88921 | D7: 88.622697 | E7: 123.66939 | J7: 0 | K7: 3 | L7: P/E 17.0 (ntm); EV/EBITDA 13.5 (ntm) | M7: Corporate cost allocated into segments (Devices 27.8%, corporate +$650M) so segment margins are off the 10-K basis; Libre claims -$600M x 0.5 the highest; long-dated list misses Section 232 and Libre escalation. [Gate 2026-10-21: Dx FY27 +11.0% -> +12.8% from its own build: $107.56 -> $107.96.]
A8: agent 5 | B8: 106.25765 | C8: 105.53993 | D8: 87.494227 | E8: 124.16771 | J8: 0 | K8: 3 | L8: P/E 17.0 (ntm); EV/EBITDA 12.75 (ntm) | M8: Dx margins 16.5-18.5% below the 10-K 19.5% and the CEO's high-teens Exact margin (~$300M EBIT too low); EV/EBITDA 12.75x below ABT's own 13.4x; SOTP 0.15 weight without evidence. [Gate 2026-10-21: Libre claims -$300M -> -$220M x 0.5 from its own range: $106.23 -> $106.26.]
A9: supervisor | B9: 109.18688 | C9: 108.66815 | D9: 91.058174 | E9: 124.89347 | J9: 0 | K9: 3 | L9: P/E 17.42 (ntm); EV/EBITDA 13.3 (ntm)

Sheet Sources
A1: ABT: where each input comes from (source numbers point to the list below; F ids to the SEC fact table)
A3: Input | B3: Value | C3: Basis | D3: Sources | E3: SEC fact ids | F3: Derivation
A4: base revenue FY2025 | B4: $44,328M | C4: reported | D4: 5 | E4: F3 | F4: 10-K FY2025; segments 21,387 + 8,937 + 8,451 + 5,536 = 44,311 plus Other $17M
A5: FY2026 segment revenue (all four) | B5: Devices ~$23,330M, Dx ~$12,095M, Nutrition ~$8,463M, EPD ~$6,019M (total ~$49,913M) | C5: estimate | D5: 1, 5 | E5: F3 | F5: 9M 2026 reported (17,218 / 8,577 / 6,423 / 4,539, src 1) + Q4 = Q4 2025 (FY2025 less 9M 2025 implied by the 9M growth rates) x Q3 run-rate growth; Dx Q4 = ex-Cancer 2,459 x 1.025 + Cancer ~990 (Q3 968)
A6: FY2027/28 Medical Devices growth | B6: +6.5% / +6.2% | C6: estimate | D6: 1, 8, 9 | F6: Diabetes ~$8.6B x 4.5% (CEO: low-to-mid single digit for Q4 and next few quarters), EP ~$3.4B x 15% (~20% in Q4), rest ~$11.3B x 5.5% = +6.5%; FY28 trims Diabetes for Medicare competitive-bid pricing (contracts awarded 2027)
A7: FY2027/28 Diagnostics growth | B7: +13.0% / +5.8% | C7: estimate | D7: 1, 8 | F7: Core Lab ~$5.6B x 1.05 = 5.88 + R&M ~$3.5B x 1.01 = 3.535 + Cancer Dx pro forma ~$3.8B x 1.12 = 4.256 (Q3 comparable +13.8%; adds the Q1 stub) = ~$13.67B / FY2026 ~$12.09B = +13.0%; FY28 Cancer +11%, Core Lab +5%, R&M +1% = ~$14.47B (+5.8%) [citation gate 2026-10-21: FY27 corrected from ~$13.64B / +12.8%]
A8: Nutrition / EPD growth FY27-28 | B8: +3.5% / +7.0% per year | C8: estimate | D8: 1 | F8: Q3 comparable Nutrition +4.9% after 9M -2.1%; EPD Q3 +8.4%, Key Emerging Markets +10.9%, less EM FX
A9: segment EBIT margins | B9: Devices 33.9-34.3%, Dx 19.0-20.5%, Nutrition 18.5%, EPD 23% | C9: estimate | D9: 5, 8 | F9: FY2025 segment operating earnings / sales (10-K segment note, src 5): Devices 7,212 / 21,387 = 33.7%, Dx 1,740 / 8,937 = 19.5%, Nutrition 1,558 / 8,451 = 18.4%, EPD 1,290 / 5,536 = 23.3%. Devices 33.7% + 20 bp/yr = 33.9% / 34.1% / 34.3% (EP and structural-heart mix vs CGM price pressure); Dx dips to 19.0% with Exact at a high-teens margin (CEO, src 8) then 19.8% / 20.5% with synergies; Nutrition 18.5% and EPD 23% at the FY2025 level. [citation gate 2026-10-21: Devices was 34.5-34.9% with an underived FY2026 step]
A10: corporate_ebit (unallocated net of other income) | B10: -$820M / -$888M / -$948M | C10: estimate | D10: 1, 7 | F10: FY26 adjusted pretax = $5.525 x ~1,741M / (1 - 15.3%) = ~$11,357M; + net interest (9M $664M + Q4 ~$297M) = ~$12,318M adjusted EBIT incl. other income; less segment OE on the build ~$13,154M = ~-$836M, set at -$820M so the engine FY26 EPS on actual interest stays $5.52 (guide $5.50-5.55); then grows with SBC and corporate costs ~8% (FY27 -$888M) and ~7% (FY28 -$948M). [citation gate 2026-10-21: was -$960M/-$1,040M/-$1,110M before the Devices margin was put on the 10-K base; total FY26 EBIT unchanged]
A11: tax rate (adjusted) | B11: 15.5% | C11: estimate | D11: 1 | F11: Q3 2026 and 9M 2026 adjusted (excluding specified items) tax rate 15.2% (release); 15.5% is a forward assumption slightly above it (no FY tax guidance on the release).
A12: D&A (depreciation only), capex, NWC | B12: 3.2% / 4.4% / 12% of incremental revenue | C12: estimate | D12: 5, 6 | E12: F50, F54 | F12: Depreciation FY25 $1,434M / $44,328M = 3.2% (10-K cash flow statement); capex FY25 $2,171M = 4.9%, H1 2026 $896M on ~$23.8B = 3.8% -> 4.4% between; NWC: FY2025 10-K balance sheet operating working capital = trade receivables 7,929 + inventories 6,488 + other prepaid expenses and receivables 2,640 - trade payables 4,240 - salaries/wages/commissions 1,745 - other accrued liabilities 5,812 = 5,260 = 11.9% of $44,328M sales (FY2024: 4,650 / 41,950 = 11.1%); held at a constant ~12% intensity, so 12% of incremental revenue. [citation gate 2026-10-21: NWC derivation added]
A13: SBC | B13: costed once in EBIT (ebit_basis gaap so the engine does not subtract it again) | C13: judgment | D13: 5, 1 | E13: F36 | F13: Modelling choice: FY2025 share-based compensation $664M (10-K cash flow statement; F36) = 1.5% of revenue is expensed inside Abbott's adjusted operating earnings (the release's specified items do not include SBC), and the reconciled EBIT is that adjusted basis; ebit_basis "gaap" tells the engine not to subtract sbc_pct_rev a second time. Peer consensus EPS is on the same SBC-expensed adjusted basis. [citation gate 2026-10-21: relabelled reported -> judgment; only the $664M is a reported figure]
A14: net debt (2026-06-30) | B14: $27,005M | C14: reported | D14: 6 | E14: F97 | F14: LTD 29,603 + current LTD 3,005 - cash 5,104 - short-term investments 499 (Q2 10-Q, opened); post-Exact; Q3 10-Q not yet filed
A15: minorities | B15: $652M | C15: reported | D15: 6 | F15: Noncontrolling interests balance at 2026-06-30
A16: interest rate | B16: 4.4% | C16: estimate | D16: 1, 6 | F16: Q3 net interest $297M x 4 / $27,005M = 4.40%
A17: diluted shares | B17: 1,738M (Q3 2026), -0.5%/yr | C17: estimate | D17: 1 | E17: F30, F33 | F17: 1,738M is the reported Q3 2026 average diluted count (release: Q3 2025 1,749M, 9M26 1,743M vs 9M25 1,749M). The -0.5%/yr change is derived: between the -0.6% Q3 y/y (1,738 / 1,749) and -0.3% 9M y/y (1,743 / 1,749) changes, with ~$0.4-0.6B/yr buybacks in the set offset by SBC dilution. [citation gate 2026-10-21: count reported, trend relabelled estimate]
A18: shareholder returns | B18: $5,200M / $5,200M / $5,600M | C18: estimate | D18: 1, 6 | E18: F64 | F18: Dividend $0.63/qtr x ~1,735M = ~$4.37B/yr; H1 2026 buybacks $1,225M + dividends $2,200M (10-Q); engine counts FY26 only after 6/30 (x0.5 = $2.6B: dividends ~$2.19B + ~$0.4B buybacks); FY27 dividend +~5% and ~$0.6B buybacks while deleveraging
A19: horizon P/E | B19: 17.42x | C19: estimate | D19: 17, 18, 19, 20, 21, 22, 23, 24, 25, 26, 27, 28, 29, 30, 31, 32, 33, 34, 35 | E19: MDT.price, BSX.price, SYK.price, BDX.price, ZBH.price, TMO.price, DHR.price, JNJ.price, MDT.pe_ntm, BSX.pe_ntm, SYK.pe_ntm, BDX.pe_ntm, ZBH.pe_ntm, TMO.pe_ntm, DHR.pe_ntm, JNJ.pe_ntm | F19: Exit-multiple rule (Kilian card 2026-10-26 12:16Z; METHOD.md Peer comparables): exit = peer median x (own NTM multiple / peer median)^k, k = 0.8. Peer median 16.84x (unchanged, gated 2026-10-26: see the rest of this derivation). Own multiple 17.57x on the peers' basis: ABT $103.70 / NTM adjusted EPS $5.90 on the same window = 17.57x (peer_basis 'ABT 17.6x on the same window'; est.json 103.70 / 5.9012). Exit = 16.84 x (17.57 / 16.84)^0.8 = 16.84 x 1.0345 = 17.42x (was 16.8x). The EV/EBITDA leg (13.3x = ABT's own NTM adjusted multiple) has no on-basis peer median (the 14.25x filing TTM GAAP median is a reference only), so it is unchanged and flagged. PREVIOUS DERIVATION: Approved set (Kilian 2026-10-26 06:07Z; valuation/peer_refresh_2026-10-26/README.md): 11 diversified medtech/life-science peers on one calendar NTM window 2026-10-23 to 2027-10-22, fiscal years weighted by days in the window, 2026-10-23 closes, consensus EPS on the company-ADJUSTED basis ABT uses. US (Zacks via Nasdaq.com, retrieved 2026-10-26): MDT 15.5x ($95.41 / (0.518 x FY4/27 $5.98 + 0.482 x $6.35)), BSX 13.7x ($45.69 / (0.189 x FY12/26 $3.24 + 0.811 x $3.36)), SYK 18.9x ($307.15 / (0.189 x FY12/26 $14.93 + 0.811 x $16.60)), BDX 15.0x ($198.91 / (0.937 x FY9/27 $13.24 + 0.063 x $14.02)), ZBH 11.1x ($98.56 / (0.189 x FY12/26 $8.54 + 0.811 x $8.98)), TMO 24.8x ($673.82 / (0.189 x FY12/26 $25.20 + 0.811 x $27.68)), DHR 25.1x ($230.50 / (0.189 x FY12/26 $8.59 + 0.811 x $9.30)), JNJ 22.8x ($263.81 / (0.189 x FY12/26 $11.12 + 0.811 x $11.69)). Siemens Healthineers 17.5x (EUR 41.86 / (0.937 x FY9/27 2.37 + 0.063 x FY9/28 2.70) = 2.391; company-compiled Vara adjusted-EPS consensus 2026-08-27; MarketScreener's 2.104/2.473 is REPORTED EPS incl. ~EUR 0.32/yr PPA amortization, 19.7x, not comparable). Terumo 16.8x (JPY 2,399 / (0.436 x 140.47 + 0.564 x 143.94) = 142.43; adjusted = MarketScreener reported consensus + after-tax (25%, the guide's own -97.5 bn OP -> -73.1 bn NI ratio) gap between adjusted OP and OP over 1,475.1M shares: FY3/27 82.25 + (274.5-160.0) bn x 0.75 / 1,475.1M = 140.47 (removes the CSL Plasma charge and acquired-intangible amortization); FY3/28 129.3 + 28.8 bn (Q1 FY3/27 amortization 7.211 bn x 4) x 0.75 / 1,475.1M = 143.94). Olympus 13.9x (JPY 1,719 / (0.436 x 114.55 + 0.564 x 130.40) = 123.50; reported consensus 98.05 / 113.9 + 16.5 = guide gap adjusted EPS mid 112.5 vs EPS mid 96.0). Sorted: ZBH 11.1, BSX 13.7, Olympus 13.9, BDX 15.0, MDT 15.5, Terumo 16.8, SHL 17.5, SYK 18.9, JNJ 22.8, TMO 24.8, DHR 25.2: median 16.84x (Terumo). Sensitivity: Terumo on reported FY3/28 alone (18.6x) -> median 17.5x (SHL); all three foreign on reported EPS -> 18.9x (SYK, the README starting number, mixed basis). ABT on the same window: $103.70 / (0.189 x $5.52 + 0.811 x $5.99 = $5.90) = 17.6x. 16.8x = the median, no premium or discount: ABT's FY27/FY26 consensus EPS growth +8.5% is above the set median +6.2%; NEC/Libre claims are already deducted as equity adjustments and the 2028 CGM bidding is in the driver build, so a multiple discount for them would double count; the Nutrition/EPD mix drag is offset by the growth. The 10-21 set's ~7% discount was against an 18.2x median raised by single-franchise growers (EW 26.5x, DXCM 27.2x) that the approved set drops. Out: EW, DXCM (single franchise; DXCM 26.0x and PODD 19.9x are Diabetes Care segment comps only, context, no SOTP leg), GEHC (imaging), BAX (distressed); Smith & Nephew (SNN 13.5x, 2 Zacks analysts) argued out: orthopaedics/sports medicine/wound, a business ABT does not have, with ZBH already covering ortho; it would cut the median to 16.2x. SBC basis check (coordinator basis warning 2026-10-26): ABT's adjusted EPS expenses SBC (excludes only acquisition-accelerated awards and excess tax benefits; Ex. 99.1 2026-10-21) and so do all eight US peers: none of their latest Ex. 99.1 non-GAAP reconciliations adds back SBC (MDT, ZBH mention it only in the cash-flow statement; DHR only for its special equity awards, ~$0.2/share, which moves DHR above the median either way); all exclude acquired-intangible amortization like ABT. SHL's adjusted EPS excludes PPA, severance and portfolio items, Terumo's adjusted operating profit excludes acquired-intangible amortization and non-recurring items; Olympus's adjusted measure excludes only Other income/expenses, so Olympus EPS still carries acquired-intangible amortization (on ABT's basis its EPS would be higher and its P/E below 13.9x: it stays under the median, no effect on 16.84x); none adds back SBC. Script record runs/2026-10-23/ABT/peers_sbc_check.json. Provider-EPS reconciliation per row (coordinator 2026-10-26 06:25Z: show each provider figure against the company's own GAAP and adjusted numbers): ABT: Zacks FY26 $5.52 vs company adjusted guide $5.50-5.55 (Ex.99.1 2026-10-21); GAAP excludes intangible amortization add-back -> adjusted basis; MDT: Zacks FY4/27 $5.98 vs non-GAAP guide $5.94-6.00 (Ex.99.1 2026-09-01); Q1 GAAP $1.14 vs non-GAAP $1.45 -> adjusted; BSX: Zacks FY26 $3.24 vs adjusted guide $3.28-3.32 (Ex.99.1 2026-07-29; consensus 1-2% below the guide); Q2 GAAP $0.61 vs adjusted $0.86 -> adjusted; SYK: Zacks FY26 $14.93 vs adjusted guide $14.95-15.10 (Ex.99.1 2026-07-30); Q2 GAAP $3.30 vs adjusted $3.69 -> adjusted; BDX: Zacks FY9/26 $12.67 vs adjusted guide $12.62-12.72 (Ex.99.1 2026-08-06) -> adjusted; ZBH: Zacks FY26 $8.54 vs adjusted guide $8.40-8.55 (Ex.99.1 2026-08-05) -> adjusted; TMO: Zacks FY26 $25.20 vs Q3 adjusted EPS $6.68 / GAAP $4.64 (Ex.99.1 2026-10-21; guide given on the call only): consensus is on the adjusted run-rate, GAAP would be ~$18 -> adjusted; DHR: Zacks FY26 $8.59 vs adjusted guide $8.57-8.62 (Ex.99.1 2026-10-21); Q3 GAAP $1.71 vs adjusted $2.11 -> adjusted (regular SBC expensed; only special equity awards, $0.02 in Q3, excluded); JNJ: Zacks FY26 $11.12 vs adjusted guide $11.05-11.15 (Ex.99.1 2026-10-13) -> adjusted; SHL: MarketScreener 2.104/2.473 = reported (Vara reported 2.06/2.38); Vara adjusted 2.37/2.70 used; Q3 basic 0.60 vs adjusted 0.70 (PPA 0.08); TERUMO: MarketScreener FY3/27 82.25 ~ company guide basic EPS 81.35 (reported, incl. CSL charge); adjusted via adjusted OP 274.5 vs OP 160.0 bn; OLYMPUS: MarketScreener FY3/27 98.05 inside reported EPS guide 90-102 (reported); adjusted guide 106-119 -> +16.5.
A20: horizon EV/EBITDA | B20: 13.3x NTM adjusted EBITDA (EBIT + depreciation) | C20: judgment | D20: 6, 14, 12 | E20: F97 | F20: Anchored on ABT's own multiple on the same basis as the leg: EV ~$198.6B ($98.36 x 1,738M + net debt $27,005M + minorities $652M) / NTM adjusted EBITDA (adjusted EBIT + depreciation) from 2026-10-21 on the reconciled build ~$14.88B = 13.3-13.4x; 13.3x = no re-rating. The 6-peer filing TTM median 14.25x (MDT, BSX, SYK, BDX, EW, ZBH) is on GAAP EBITDA (GAAP op income + D&A) and is NOT applied to ABT's adjusted EBITDA; it is a reference only (peers would sit lower on an adjusted basis). The -$600M specified-items cash adjustment is a separate equity item, not an offset to a basis gap. [citation gate 2026-10-21: basis mismatch removed; the multiple is unchanged]
A21: adjustments (after tax, probability-weighted) | B21: -$2,670M (-$1.54/share) | C21: estimate | D21: 2, 3, 4, 6, 7, 10 | E21: F43, F50 | F21: NEC August deal -$520M ($670M verified, ~22.5% tax) + DOJ/states -$350M ($384,192,156 verified, CA AG) + remaining NEC -$750M + Libre 3 claims -$300M x 0.5 + specified-items cash -$600M + Nutrition separation cash -$300M
A22: driver:cgm | B22: Diabetes Care sales (FreeStyle Libre CGM): 7,998 -> 8,670/9,060/9,377 (estimate) | C22: estimate | F22: FY26 = 9M26 6,453 + Q4 (Q4'25 = 7,998 - 6,453/1.100 = 2132) x 1.04 = 8670; FY27 x 1.045; FY28 x 1.035
A23: driver:ep | B23: Electrophysiology sales (Volt PFA, mapping, Amulet LAA from 2026): 2,764 -> 3,441/3,958/4,432 (estimate) | C23: estimate | F23: 9M25 restated = 2,522/1.152 = 2189 (incl. Amulet 156); Q4'25 restated = (2,764 - (2189 - 156)) + ~55 Amulet (Q3'25 run-rate) = 786; FY26 = 2,522 + 786 x 1.17 = 3441 (y1 growth includes ~$211M of transferred Amulet sales); FY27 +15%, FY28 +12% as PFA adoption matures
A24: driver:cv_other | B24: Other Medical Devices sales (Rhythm Mgmt, Heart Failure, Vascular, Structural Heart, Neuromodulation): 1.062e+04 -> 1.115e+04/1.182e+04/1.253e+04 (estimate) | C24: estimate | F24: 9M26 = 17,218 - 6,453 - 2,522 = 8243; Q4'25 = (21,387 - 15,712) - 2132 - 786 = 2758; FY26 = 8243 + 2758 x 1.055 = 11152 (Q3 reported +5.2%); FY27/28 +6.0%: Q3 comparable mix-weighted +6.6% (RM +10.0, HF +6.0, Vascular +5.7, SH +6.9, Neuro -1.1 on Q3 sales weights), 9M +7.1%, less ~0.6-1.1pt fade/FX. Old set implied ~+5.5%
A25: driver:dx_base | B25: Core Laboratory + Rapid/Molecular Diagnostics sales (ex Cancer Dx): 8,937 -> 9,112/9,430/9,762 (estimate) | C25: estimate | F25: FY26 = 6,594 + Q4'25 (8,937 - 6,480 = 2457) x 1.025 = 9112 (Core Lab ~5663, R&M ~3449); FY27/28 Core Lab +5% (Q3 +5.4%), R&M +1% (Q3 +0.9%)
A26: driver:cancer_dx | B26: Cancer Diagnostics sales (Exact Sciences: Cologuard, precision oncology), as consolidated by Abbott: 0 -> 2,973/4,120/4,574 (estimate) | C26: estimate | F26: FY26 = 1,983 + Q4 ~990 (Q3 968 +~2% sequential) = 2973; FY27 = full-year pro forma FY26 (706 + 1,983 + 990 = 3679) x 1.12 (Q3 comparable +13.8%, 9M +13.5%, fading on blood-test competition); FY28 x 1.11. The old set used a ~$3.8B pro forma base (~$4.26B FY27); the release's $706M pre-acquisition figure gives $3.68B
A27: driver:epd | B27: Established Pharmaceuticals sales (branded generics, ~76% Key Emerging Markets): 5,536 -> 6,019/6,440/6,891 (estimate) | C27: estimate | F27: FY26 = 4,539 + Q4'25 (5,536 - 4,539/1.093 = 1383) x 1.07 = 6019; FY27/28 +7%: KEM ~76% x ~9.5% ex-FX (10-K FY25 +9.5%) + Other ~24% x ~2% = ~7.7%, less ~0.7pt EM FX
A29: # | B29: Source | C29: Date | D29: Link
A30: 1 | B30: Abbott Q3 2026 earnings release (8-K Ex. 99.1): sales $13,013M, comparable +7.0%, adj EPS $1.42, FY26 adj EPS $5.50-5.55, comparable ~6.0%, Q4 $1.62-1.67, diluted shares 1,738M, net interest $297M, 9M segment sales, dividend $0.63 | C30: 2026-10-21 | D30: https://www.sec.gov/Archives/edgar/data/0000001800/000162828026066601/abt-2026q3xexhibitx991.htm
A31: 2 | B31: Abbott 8-K Ex. 99.1: intention to separate Nutrition (~$8.5B sales) via tax-free distribution, completion expected by end of 2027, one-time charges to be quantified, combined dividend equal to Abbott's | C31: 2026-10-21 | D31: https://www.sec.gov/Archives/edgar/data/0000001800/000110465926117587/tm2627971d1_ex99-1.htm
A32: 3 | B32: Abbott 8-K Ex. 99.1: agreements resolving Gill (~$600M judgment plus interest) and ~2,000 other NEC claims for ~$670M; ~1,700 suits / ~12,700 infants remain | C32: 2026-08-20 | D32: https://www.sec.gov/Archives/edgar/data/0000001800/000110465926099247/tm2623675d1_ex99-1.htm
A33: 4 | B33: California Attorney General: U.S. and state coalition settlement with Abbott over infant formula: $348,700,868 federal + $35,491,288 states | C33: 2026-09-21 | D33: https://oag.ca.gov/news/press-releases/attorney-general-bonta-us-coalition-secure-385-million-settlement-abbott-over
A34: 5 | B34: Abbott 10-K FY2025: segment sales and operating earnings (EPD 5,536/1,290; Nutrition 8,451/1,558; Diagnostics 8,937/1,740; Medical Devices 21,387/7,212), depreciation $1,434M | C34: 2026-02-20 | D34: https://www.sec.gov/Archives/edgar/data/1800/000162828026010185/abt-20251231.htm
A35: 6 | B35: Abbott 10-Q Q2 2026: cash $5,104M, short-term investments $499M, current LTD $3,005M, LTD $29,603M, NCI $652M, H1 buybacks $1,225M, dividends $2,200M, capex $896M, CFO $3,803M | C35: 2026-07-28 | D35: https://www.sec.gov/Archives/edgar/data/1800/000162828026050134/abt-20260630.htm
A36: 7 | B36: Abbott Q4/FY2025 earnings release (8-K Ex. 99.1): FY2025 adjusted net earnings $9,040M, adjusted EPS $5.15 | C36: 2026-01-22 | D36: https://www.sec.gov/Archives/edgar/data/1800/000162828026002982/abt-2025q4xexhibitx991.htm
A37: 8 | B37: Investing.com: Abbott Q3 2026 earnings call transcript (2027 sales 'pretty similar to this year'; diabetes 'low to mid-single' for Q4 and next few quarters; EP ~20% in Q4; Cancer Dx high-teens margin; separation costs are specified items; separation by end of next year) | C37: 2026-10-21 | D37: https://www.investing.com/news/transcripts/earnings-call-transcript-abbott-q3-2026-results-show-growth-but-shares-fall-93CH-4963517
A38: 9 | B38: MedTech Dive: CMS final rule adds CGMs and insulin pumps to competitive bidding, bundled monthly rental, contracts awarded in 2027 | C38: 2025-12-01 | D38: https://www.medtechdive.com/news/cms-final-rule-diabetes-competitive-bidding/806719/
A39: 10 | B39: FDA: Abbott Diabetes Care removes certain FreeStyle Libre 3 and 3 Plus sensors (860 serious injuries, 7 deaths) [page returned HTTP 401 to the citation gate; figures relied on from AHA News, src 11] | C39: 2026-01 | D39: https://www.fda.gov/medical-devices/medical-device-recalls-and-early-alerts/glucose-monitor-sensor-recall-abbott-diabetes-care-removes-certain-freestyle-libre-3-and-freestyle
A40: 11 | B40: AHA News: FDA identifies Class I recall of certain FreeStyle Libre 3 / 3 Plus sensors | C40: 2026-02-04 | D40: https://www.aha.org/news/headline/2026-02-04-fda-issues-most-serious-recall-certain-glucose-monitor-sensors
A41: 12 | B41: Run peer comps table peers.md / peers.json (prices X.price; consensus snapshots data/estimates/SYM.json: Nasdaq.com/Zacks for BSX, SYK, BDX, EW; Alpha Vantage for the rest; table NTM from each peer's last filed quarter; gate rebased to one calendar NTM window, median 18.2x) | C41: 2026-10-21 | D41: file:///mnt/project-files/valuation/runs/2026-10-20/ABT/peers.md
... A64: 35 | B64: JNJ results release Ex. 99.1 (8-K item 2.02, filed 2026-10-13): non-GAAP/adjusted EPS reconciliation; stock-based compensation is not an adjustment (mentions: cash-flow statement or special/acquisition-accelerated awards only) | C64: 2026-10-13 | D64: https://www.sec.gov/Archives/edgar/data/200406/000020040626000189/a2026q3exhibit991.htm
A66: Fact id | B66: Figure | C66: Value | D66: Filing
A67: F1 | B67: revenue FY ending 2023-12-31 (us-gaap:RevenueFromContractWithCustomerExcludingAssessedTax) | C67: 40109000000 | D67: https://www.sec.gov/Archives/edgar/data/1800/000162828026010185/
A68: F2 | B68: revenue FY ending 2024-12-31 (us-gaap:RevenueFromContractWithCustomerExcludingAssessedTax) | C68: 41950000000 | D68: https://www.sec.gov/Archives/edgar/data/1800/000162828026010185/
A69: F3 | B69: revenue FY ending 2025-12-31 (us-gaap:RevenueFromContractWithCustomerExcludingAssessedTax) | C69: 44328000000 | D69: https://www.sec.gov/Archives/edgar/data/1800/000162828026010185/
A70: F4 | B70: revenue YTD 2026-01-01 to 2026-03-31 | C70: 11164000000 | D70: https://www.sec.gov/Archives/edgar/data/1800/000162828026028357/
A71: F5 | B71: revenue prior-year YTD 2025-01-01 to 2025-03-31 | C71: 10358000000 | D71: https://www.sec.gov/Archives/edgar/data/1800/000162828026028357/
A72: F6 | B72: revenue TTM to 2026-03-31 | C72: 45134000000
A73: F7 | B73: revenue quarter 2026-01-01 to 2026-03-31 | C73: 11164000000 | D73: https://www.sec.gov/Archives/edgar/data/1800/000162828026028357/
A74: F8 | B74: operating_income FY ending 2023-12-31 (us-gaap:OperatingIncomeLoss) | C74: 6478000000 | D74: https://www.sec.gov/Archives/edgar/data/1800/000162828026010185/
A75: F9 | B75: operating_income FY ending 2024-12-31 (us-gaap:OperatingIncomeLoss) | C75: 6825000000 | D75: https://www.sec.gov/Archives/edgar/data/1800/000162828026010185/
A76: F10 | B76: operating_income FY ending 2025-12-31 (us-gaap:OperatingIncomeLoss) | C76: 8053000000 | D76: https://www.sec.gov/Archives/edgar/data/1800/000162828026010185/
A77: F11 | B77: operating_income YTD 2026-01-01 to 2026-03-31 | C77: 1345000000 | D77: https://www.sec.gov/Archives/edgar/data/1800/000162828026028357/
A78: F12 | B78: operating_income prior-year YTD 2025-01-01 to 2025-03-31 | C78: 1693000000 | D78: https://www.sec.gov/Archives/edgar/data/1800/000162828026028357/
A79: F13 | B79: operating_income TTM to 2026-03-31 | C79: 7705000000
A80: F14 | B80: operating_income quarter 2026-01-01 to 2026-03-31 | C80: 1345000000 | D80: https://www.sec.gov/Archives/edgar/data/1800/000162828026028357/
A81: F15 | B81: net_income FY ending 2023-12-31 (us-gaap:NetIncomeLoss) | C81: 5723000000 | D81: https://www.sec.gov/Archives/edgar/data/1800/000162828026010185/
A82: F16 | B82: net_income FY ending 2024-12-31 (us-gaap:NetIncomeLoss) | C82: 13402000000 | D82: https://www.sec.gov/Archives/edgar/data/1800/000162828026010185/
A83: F17 | B83: net_income FY ending 2025-12-31 (us-gaap:NetIncomeLoss) | C83: 6524000000 | D83: https://www.sec.gov/Archives/edgar/data/1800/000162828026010185/
A84: F18 | B84: net_income YTD 2026-01-01 to 2026-03-31 | C84: 1077000000 | D84: https://www.sec.gov/Archives/edgar/data/1800/000162828026028357/
A85: F19 | B85: net_income prior-year YTD 2025-01-01 to 2025-03-31 | C85: 1325000000 | D85: https://www.sec.gov/Archives/edgar/data/1800/000162828026028357/
A86: F20 | B86: net_income TTM to 2026-03-31 | C86: 6276000000
A87: F21 | B87: net_income quarter 2026-01-01 to 2026-03-31 | C87: 1077000000 | D87: https://www.sec.gov/Archives/edgar/data/1800/000162828026028357/
A88: F22 | B88: eps_diluted FY ending 2023-12-31 (us-gaap:EarningsPerShareDiluted) | C88: 3.26 | D88: https://www.sec.gov/Archives/edgar/data/1800/000162828026010185/
A89: F23 | B89: eps_diluted FY ending 2024-12-31 (us-gaap:EarningsPerShareDiluted) | C89: 7.64 | D89: https://www.sec.gov/Archives/edgar/data/1800/000162828026010185/
A90: F24 | B90: eps_diluted FY ending 2025-12-31 (us-gaap:EarningsPerShareDiluted) | C90: 3.72 | D90: https://www.sec.gov/Archives/edgar/data/1800/000162828026010185/
A91: F25 | B91: eps_diluted YTD 2026-01-01 to 2026-03-31 | C91: 0.61 | D91: https://www.sec.gov/Archives/edgar/data/1800/000162828026028357/
A92: F26 | B92: eps_diluted prior-year YTD 2025-01-01 to 2025-03-31 | C92: 0.76 | D92: https://www.sec.gov/Archives/edgar/data/1800/000162828026028357/
A93: F27 | B93: eps_diluted quarter 2026-01-01 to 2026-03-31 | C93: 0.61 | D93: https://www.sec.gov/Archives/edgar/data/1800/000162828026028357/
A94: F28 | B94: diluted_shares_wavg FY ending 2023-12-31 (us-gaap:WeightedAverageNumberOfDilutedSharesOutstanding) | C94: 1749000000 | D94: https://www.sec.gov/Archives/edgar/data/1800/000162828026010185/
A95: F29 | B95: diluted_shares_wavg FY ending 2024-12-31 (us-gaap:WeightedAverageNumberOfDilutedSharesOutstanding) | C95: 1748000000 | D95: https://www.sec.gov/Archives/edgar/data/1800/000162828026010185/
A96: F30 | B96: diluted_shares_wavg FY ending 2025-12-31 (us-gaap:WeightedAverageNumberOfDilutedSharesOutstanding) | C96: 1748000000 | D96: https://www.sec.gov/Archives/edgar/data/1800/000162828026010185/
A97: F31 | B97: diluted_shares_wavg YTD 2026-01-01 to 2026-03-31 | C97: 1747073000 | D97: https://www.sec.gov/Archives/edgar/data/1800/000162828026028357/
A98: F32 | B98: diluted_shares_wavg prior-year YTD 2025-01-01 to 2025-03-31 | C98: 1747220000 | D98: https://www.sec.gov/Archives/edgar/data/1800/000162828026028357/
... A104: F38 | B104: sbc prior-year YTD 2025-01-01 to 2025-03-31 | C104: 289000000 | D104: https://www.sec.gov/Archives/edgar/data/1800/000162828026028357/
A105: F39 | B105: sbc TTM to 2026-03-31 | C105: 692000000
A106: F40 | B106: sbc quarter 2026-01-01 to 2026-03-31 | C106: 317000000 | D106: https://www.sec.gov/Archives/edgar/data/1800/000162828026028357/
A107: F41 | B107: cfo FY ending 2023-12-31 (us-gaap:NetCashProvidedByUsedInOperatingActivities) | C107: 7261000000 | D107: https://www.sec.gov/Archives/edgar/data/1800/000162828026010185/
A108: F42 | B108: cfo FY ending 2024-12-31 (us-gaap:NetCashProvidedByUsedInOperatingActivities) | C108: 8558000000 | D108: https://www.sec.gov/Archives/edgar/data/1800/000162828026010185/
A109: F43 | B109: cfo FY ending 2025-12-31 (us-gaap:NetCashProvidedByUsedInOperatingActivities) | C109: 9566000000 | D109: https://www.sec.gov/Archives/edgar/data/1800/000162828026010185/
A110: F44 | B110: cfo YTD 2026-01-01 to 2026-03-31 | C110: 1315000000 | D110: https://www.sec.gov/Archives/edgar/data/1800/000162828026028357/
A111: F45 | B111: cfo prior-year YTD 2025-01-01 to 2025-03-31 | C111: 1417000000 | D111: https://www.sec.gov/Archives/edgar/data/1800/000162828026028357/
A112: F46 | B112: cfo TTM to 2026-03-31 | C112: 9464000000
A113: F47 | B113: cfo quarter 2026-01-01 to 2026-03-31 | C113: 1315000000 | D113: https://www.sec.gov/Archives/edgar/data/1800/000162828026028357/
A114: F48 | B114: capex FY ending 2023-12-31 (us-gaap:PaymentsToAcquirePropertyPlantAndEquipment) | C114: 2202000000 | D114: https://www.sec.gov/Archives/edgar/data/1800/000162828026010185/
A115: F49 | B115: capex FY ending 2024-12-31 (us-gaap:PaymentsToAcquirePropertyPlantAndEquipment) | C115: 2207000000 | D115: https://www.sec.gov/Archives/edgar/data/1800/000162828026010185/
A116: F50 | B116: capex FY ending 2025-12-31 (us-gaap:PaymentsToAcquirePropertyPlantAndEquipment) | C116: 2171000000 | D116: https://www.sec.gov/Archives/edgar/data/1800/000162828026010185/
A117: F51 | B117: capex YTD 2026-01-01 to 2026-03-31 | C117: 399000000 | D117: https://www.sec.gov/Archives/edgar/data/1800/000162828026028357/
A118: F52 | B118: capex prior-year YTD 2025-01-01 to 2025-03-31 | C118: 484000000 | D118: https://www.sec.gov/Archives/edgar/data/1800/000162828026028357/
A119: F53 | B119: capex TTM to 2026-03-31 | C119: 2086000000
A120: F54 | B120: capex quarter 2026-01-01 to 2026-03-31 | C120: 399000000 | D120: https://www.sec.gov/Archives/edgar/data/1800/000162828026028357/
A121: F55 | B121: buybacks FY ending 2023-12-31 (us-gaap:PaymentsForRepurchaseOfCommonStock) | C121: 1227000000 | D121: https://www.sec.gov/Archives/edgar/data/1800/000162828026010185/
A122: F56 | B122: buybacks FY ending 2024-12-31 (us-gaap:PaymentsForRepurchaseOfCommonStock) | C122: 1295000000 | D122: https://www.sec.gov/Archives/edgar/data/1800/000162828026010185/
A123: F57 | B123: buybacks FY ending 2025-12-31 (us-gaap:PaymentsForRepurchaseOfCommonStock) | C123: 893000000 | D123: https://www.sec.gov/Archives/edgar/data/1800/000162828026010185/
A124: F58 | B124: buybacks YTD 2026-01-01 to 2026-03-31 | C124: 180000000 | D124: https://www.sec.gov/Archives/edgar/data/1800/000162828026028357/
A125: F59 | B125: buybacks prior-year YTD 2025-01-01 to 2025-03-31 | C125: 280000000 | D125: https://www.sec.gov/Archives/edgar/data/1800/000162828026028357/
A126: F60 | B126: buybacks TTM to 2026-03-31 | C126: 793000000
A127: F61 | B127: buybacks quarter 2026-01-01 to 2026-03-31 | C127: 180000000 | D127: https://www.sec.gov/Archives/edgar/data/1800/000162828026028357/
A128: F62 | B128: dividends_paid FY ending 2023-12-31 (us-gaap:PaymentsOfDividendsCommonStock) | C128: 3556000000 | D128: https://www.sec.gov/Archives/edgar/data/1800/000162828026010185/
A129: F63 | B129: dividends_paid FY ending 2024-12-31 (us-gaap:PaymentsOfDividendsCommonStock) | C129: 3836000000 | D129: https://www.sec.gov/Archives/edgar/data/1800/000162828026010185/
A130: F64 | B130: dividends_paid FY ending 2025-12-31 (us-gaap:PaymentsOfDividendsCommonStock) | C130: 4116000000 | D130: https://www.sec.gov/Archives/edgar/data/1800/000162828026010185/
...
