Workbook

Sheet Summary
A1: T standard model (trial) · research run 2026-10-23
A2: The supervisor's reconciled assumption set as a live model. Trial: shown beside the blended page target, not used for trade levels until its weight is decided. Edit blue cells on Model (drivers) and Valuation (assumptions).
A3: Price target box | B3: Value
A4: Live price | B4: =IFERROR(GOOGLEFINANCE("T","price"),Valuation!$B$68)
A5: Price as of | B5: =NOW()
A6: Model target (12-month median) | B6: =Distribution!$B$13
A7: Upside to model target from live price | B7: =B6/B4-1
A8: Research target (12m) (no scenario deltas) | B8: =Valuation!$D$8
A9: Probability-weighted mean | B9: =Distribution!$B$10
A10: 10th percentile | B10: =Distribution!$B$14
A11: 25th percentile | B11: =Distribution!$B$15
A12: 75th percentile | B12: =Distribution!$B$16
A13: 90th percentile | B13: =Distribution!$B$17
A14: Target date | B14: =Valuation!$B$46
A15: Price at the run | B15: =Valuation!$B$68
A16: Blended page target (options 67% + agents 33%, not live) | B16: 22.6484
A17: Supervisor research target (12m) (its own methods) | B17: 23.16
A18: Thesis break price (supervisor) | B18: 16.5
A19: Supervisor confidence | B19: low
A21: Key estimates | B21: FY2025A | C21: =Model!E5 | D21: =Model!F5
A22: Net sales | B22: =IF(Model!D36="","",Model!D36) | C22: =Model!E36 | D22: =Model!F36
A23: % YoY | B23: =IF(Model!D37="","",Model!D37) | C23: =Model!E37 | D23: =Model!F37
A24: Pretax margin | B24: =IF(Model!D47="","",Model!D47) | C24: =Model!E47 | D24: =Model!F47
A25: Diluted EPS (model) | B25: =IF(Model!D54="","",Model!D54) | C25: =Model!E54 | D25: =Model!F54
A26: % YoY | B26: =IF(Model!D55="","",Model!D55) | C26: =Model!E55 | D26: =Model!F55
A27: Free cash flow to firm | B27: =IF(Model!D64="","",Model!D64) | C27: =Model!E64 | D27: =Model!F64
A28: Guidance midpoint: EPS (adjusted) | C28: 2.4
A29: Consensus: EPS (MarketScreener consensus basis) | D29: 2.621
A31: Valuation method | B31: Value per share | C31: Weight
A32: =Valuation!A4 | B32: =Valuation!D4 | C32: =Valuation!E4
A33: =Valuation!A5 | B33: =Valuation!D5 | C33: =Valuation!E5
A34: =Valuation!A6 | B34: =Valuation!D6 | C34: =Valuation!E6
A35: =Valuation!A7 | B35: =Valuation!D7 | C35: =Valuation!E7
A37: Scenario | B37: Probability | C37: Value at target date | D37: What has to happen
A38: =Distribution!A4 | B38: =Distribution!B4 | C38: =Distribution!C4 | D38: =Distribution!D4
A39: =Distribution!A5 | B39: =Distribution!B5 | C39: =Distribution!C5 | D39: =Distribution!D5
A40: =Distribution!A6 | B40: =Distribution!B6 | C40: =Distribution!C6 | D40: =Distribution!D6
A42: Price at target date | B42: Probability above
A43: =ROUND(Valuation!$B$68*0.7,0) | B43: =SUMPRODUCT(Distribution!$B$4:$B$6,1-NORMSDIST((LN(A43)-LN(Distribution!$C$4:$C$6))/Distribution!$B$9))
A44: =ROUND(Valuation!$B$68*0.8,0) | B44: =SUMPRODUCT(Distribution!$B$4:$B$6,1-NORMSDIST((LN(A44)-LN(Distribution!$C$4:$C$6))/Distribution!$B$9))
A45: =ROUND(Valuation!$B$68*0.9,0) | B45: =SUMPRODUCT(Distribution!$B$4:$B$6,1-NORMSDIST((LN(A45)-LN(Distribution!$C$4:$C$6))/Distribution!$B$9))
A46: =ROUND(Valuation!$B$68*1.0,0) | B46: =SUMPRODUCT(Distribution!$B$4:$B$6,1-NORMSDIST((LN(A46)-LN(Distribution!$C$4:$C$6))/Distribution!$B$9))
A47: =ROUND(Valuation!$B$68*1.1,0) | B47: =SUMPRODUCT(Distribution!$B$4:$B$6,1-NORMSDIST((LN(A47)-LN(Distribution!$C$4:$C$6))/Distribution!$B$9))
A48: =ROUND(Valuation!$B$68*1.2,0) | B48: =SUMPRODUCT(Distribution!$B$4:$B$6,1-NORMSDIST((LN(A48)-LN(Distribution!$C$4:$C$6))/Distribution!$B$9))
A49: =ROUND(Valuation!$B$68*1.3,0) | B49: =SUMPRODUCT(Distribution!$B$4:$B$6,1-NORMSDIST((LN(A49)-LN(Distribution!$C$4:$C$6))/Distribution!$B$9))
A50: =ROUND(Valuation!$B$68*1.5,0) | B50: =SUMPRODUCT(Distribution!$B$4:$B$6,1-NORMSDIST((LN(A50)-LN(Distribution!$C$4:$C$6))/Distribution!$B$9))
A52: Model checks | B52: Status
A53: Scenario probabilities sum to 100% | B53: =IF(ABS(Distribution!B8-1)<0.005,"ok","FLAG: "&TEXT(Distribution!B8,"0.0%"))
A54: WACC exceeds terminal growth by 1 point or more | B54: =IF('Calc - research target (12m)'!B55="ok","ok","FLAG")
A55: Projection runs a full year past the target date | B55: =IF('Calc - research target (12m)'!B56="ok","ok","FLAG")
A56: Method weights add up to more than zero | B56: =IF(SUM(Valuation!E4:E7)>0,"ok","FLAG")
A57: Terminal value under 85% of the DCF | B57: =IF('Calc - research target (12m)'!B46<0.85,"ok","note: "&TEXT('Calc - research target (12m)'!B46,"0%")&" of the DCF is terminal value")
A58: Segment base revenues tie to the last reported net sales (within 2%) | B58: =IF(ABS(Valuation!$B$96/Valuation!$B$51-1)<=0.02,"ok","FLAG")
A59: Matches the engine run at publication (target, research target (12m)) | B59: =IF(AND(ABS(Distribution!$B$13-22.9885)<0.01,ABS(Valuation!$D$8-23.1576)<0.01),"ok","inputs edited since publication")
A60: All checks | B60: =IF(COUNTIF(B53:B59,"ok")=7,"all ok",7-COUNTIF(B53:B59,"ok")&" to look at")

Sheet Model
A1: T: annual model, base case
A2: (M of US dollars except per share; fiscal years named by the calendar year they end in)
A3: Blue = input · black = formula · green = link to another tab · actuals from SEC filings (fact ids in the last column, links on Sources)
A5: Fiscal year | B5: FY2023A | C5: FY2024A | D5: FY2025A | E5: FY2026E | F5: FY2027E | G5: FY2028E | H5: Source / note
A6: Period end | B6: 45291 | C6: 45657 | D6: 46022 | E6: =IF(DAY(Valuation!$B$50+1)=1,EOMONTH(Valuation!$B$50,12*E7),EDATE(Valuation!$B$50,12*E7)) | F6: =IF(DAY(Valuation!$B$50+1)=1,EOMONTH(Valuation!$B$50,12*F7),EDATE(Valuation!$B$50,12*F7)) | G6: =IF(DAY(Valuation!$B$50+1)=1,EOMONTH(Valuation!$B$50,12*G7),EDATE(Valuation!$B$50,12*G7))
A7: Projection year | B7: -2 | C7: -1 | D7: 0 | E7: 1 | F7: 2 | G7: 3
A10: Segment build (blue = input: revenue growth and EBIT margin by segment and year)
A11: AC Wireless and Home | D11: =Valuation!$B$91 | E11: =Valuation!$B$91*(1+E12) | F11: =E11*(1+F12) | G11: =F11*(1+G12)
A12: Revenue growth | E12: 0.05340247 | F12: 0.041366921 | G12: 0.032735299
A13: Segment EBIT | E13: =E11*E14 | F13: =F11*F14 | G13: =G11*G14
A14: EBIT margin | E14: 0.24723 | F14: 0.25654 | G14: 0.26693
A15: AC Business Wireline and Other | D15: =Valuation!$B$92 | E15: =Valuation!$B$92*(1+E16) | F15: =E15*(1+F16) | G15: =F15*(1+G16)
A16: Revenue growth | E16: -0.015 | F16: -0.008 | G16: -0.003
A17: Segment EBIT | E17: =E15*E18 | F17: =F15*F18 | G17: =G15*G18
A18: EBIT margin | E18: 0.24723 | F18: 0.25654 | G18: 0.26693
A19: Legacy | D19: =Valuation!$B$93 | E19: =Valuation!$B$93*(1+E20) | F19: =E19*(1+F20) | G19: =F19*(1+G20)
A20: Revenue growth | E20: -0.2541 | F20: -0.27 | G20: -0.3
A21: Segment EBIT | E21: =E19*E22 | F21: =F19*F22 | G21: =G19*G22
A22: EBIT margin | E22: 0.3214 | F22: 0.2 | G22: -0.05
A23: Latin America | D23: =Valuation!$B$94 | E23: =Valuation!$B$94*(1+E24) | F23: =E23*(1+F24) | G23: =F23*(1+G24)
A24: Revenue growth | E24: 0.13 | F24: -0.83 | G24: -1
A25: Segment EBIT | E25: =E23*E26 | F25: =F23*F26 | G25: =G23*G26
A26: EBIT margin | E26: 0.18 | F26: 0.18 | G26: 0
A27: Corporate and Other | D27: =Valuation!$B$95 | E27: =Valuation!$B$95*(1+E28) | F27: =E27*(1+F28) | G27: =F27*(1+G28)
A28: Revenue growth | E28: -0.05 | F28: =E28 | G28: =F28
A29: Segment EBIT | E29: =E27*E30 | F29: =F27*F30 | G29: =G27*G30
A30: EBIT margin | E30: 0 | F30: =E30 | G30: =F30
A31: Total segment revenue (= net sales) | D31: =D11+D15+D19+D23+D27 | E31: =E11+E15+E19+E23+E27 | F31: =F11+F15+F19+F23+F27 | G31: =G11+G15+G19+G23+G27 | H31: base revenues on Valuation (segment build); net sales = this total
A32: Total segment EBIT | E32: =E13+E17+E21+E25+E29 | F32: =F13+F17+F21+F25+F29 | G32: =G13+G17+G21+G25+G29
A33: Corporate / unallocated EBIT (blue = input) | E33: -3495 | F33: -2445 | G33: -2445 | H33: years[].corporate_ebit; EBIT = total segment EBIT + corporate
A35: Sales
A36: Net sales | B36: 122428 | C36: 122336 | D36: 125648 | E36: =E31 | F36: =F31 | G36: =G31 | H36: SEC XBRL F1, F2, F3
A37: % YoY | C37: =IF(OR(C36="",B36="",B36=0),"",C36/B36-1) | D37: =IF(OR(D36="",C36="",C36=0),"",D36/C36-1) | E37: =E36/Valuation!$B$51-1 | F37: =F36/E36-1 | G37: =G36/F36-1
A39: Operating profit
A40: EBIT (operating income) | E40: =E32+E33 | F40: =F32+F33 | G40: =G32+G33
A41: EBIT margin | E41: =E40/E36 | F41: =F40/F36 | G41: =G40/G36
A42: D&A | B42: 18777 | C42: 20580 | D42: 20886 | E42: =E36*E76 | F42: =F36*F76 | G42: =G36*G76 | H42: SEC XBRL F34, F35, F36
A43: EBITDA | E43: =E40+E42 | F43: =F40+F42 | G43: =G40+G42
A44: EBITDA margin | E44: =E43/E36 | F44: =F43/F36 | G44: =G43/G36
A45: Net interest income / (expense) | E45: =-Valuation!$B$59*Valuation!$B$57 | F45: =-Valuation!$B$59*E70 | G45: =-Valuation!$B$59*F70 | H45: rate x prior year-end net debt (memo roll)
A46: Pretax income | B46: 19848 | C46: 16698 | D46: 27007 | E46: =E40+E45 | F46: =F40+F45 | G46: =G40+G45 | H46: SEC XBRL F84, F85, F86
A47: Pretax margin | B47: =B46/B36 | C47: =C46/C36 | D47: =D46/D36 | E47: =E46/E36 | F47: =F46/F36 | G47: =G46/G36
A48: Income tax | B48: 4225 | C48: 4445 | D48: 3621 | E48: =E46*E75 | F48: =F46*F75 | G48: =G46*G75 | H48: SEC XBRL F77, F78, F79
A49: Effective tax rate | B49: =B48/B46 | C49: =C48/C46 | D49: =D48/D46 | E49: =E48/E46 | F49: =F48/F46 | G49: =G48/G46
A50: Net income | B50: 14400 | C50: 10948 | D50: 21953 | E50: =E46-E48 | F50: =F46-F48 | G50: =G46-G48 | H50: SEC XBRL F15, F16, F17
A51: % YoY | C51: =IF(OR(C50="",B50="",B50=0),"",C50/B50-1) | D51: =IF(OR(D50="",C50="",C50=0),"",D50/C50-1) | E51: =IF(OR(D50="",D50=0),"",E50/D50-1) | F51: =IF(OR(E50="",E50=0),"",F50/E50-1) | G51: =IF(OR(F50="",F50=0),"",G50/F50-1)
A52: Diluted shares (M, average) | B52: 7258 | C52: 7204 | D52: 7179 | E52: =Valuation!$B$61*(1+Valuation!$B$63)^(E7-0.5-((Valuation!$B$62-Valuation!$B$50)/365.25)) | F52: =Valuation!$B$61*(1+Valuation!$B$63)^(F7-0.5-((Valuation!$B$62-Valuation!$B$50)/365.25)) | G52: =Valuation!$B$61*(1+Valuation!$B$63)^(G7-0.5-((Valuation!$B$62-Valuation!$B$50)/365.25)) | H52: diluted count rolled at the annual change to mid-year
A53: % YoY | C53: =IF(OR(C52="",B52="",B52=0),"",C52/B52-1) | D53: =IF(OR(D52="",C52="",C52=0),"",D52/C52-1) | E53: =IF(OR(D52="",D52=0),"",E52/D52-1) | F53: =IF(OR(E52="",E52=0),"",F52/E52-1) | G53: =IF(OR(F52="",F52=0),"",G52/F52-1)
A54: Diluted EPS | B54: 1.97 | C54: 1.49 | D54: 3.04 | E54: =E50/E52 | F54: =F50/F52 | G54: =G50/G52 | H54: SEC XBRL F22, F23, F24
A55: % YoY | C55: =IF(OR(C54="",B54="",B54=0),"",C54/B54-1) | D55: =IF(OR(D54="",C54="",C54=0),"",D54/C54-1) | E55: =IF(OR(D54="",D54=0),"",E54/D54-1) | F55: =IF(OR(E54="",E54=0),"",F54/E54-1) | G55: =IF(OR(F54="",F54=0),"",G54/F54-1)
A57: Cash flow
A58: NOPAT (EBIT x (1 - tax)) | E58: =E40*(1-E75) | F58: =F40*(1-F75) | G58: =G40*(1-G75)
A59: + D&A | B59: =B42 | C59: =C42 | D59: =D42 | E59: =E42 | F59: =F42 | G59: =G42
A60: - Capex | B60: 17853 | C60: 20263 | D60: 20842 | E60: =E36*E77 | F60: =F36*F77 | G60: =G36*G77 | H60: SEC XBRL F49, F50, F51
A61: Capex % of sales | B61: =B60/B36 | C61: =C60/C36 | D61: =D60/D36 | E61: =E60/E36 | F61: =F60/F36 | G61: =G60/G36
A62: - Working capital increase | E62: =E78*(E36-Valuation!$B$51) | F62: =F78*(F36-E36) | G62: =G78*(G36-F36)
A63: - Stock comp (adjusted EBIT only) | E63: =IF(AND(Valuation!$B$48="adjusted",Valuation!$B$49="cost"),E67*(1-E75),0) | F63: =IF(AND(Valuation!$B$48="adjusted",Valuation!$B$49="cost"),F67*(1-F75),0) | G63: =IF(AND(Valuation!$B$48="adjusted",Valuation!$B$49="cost"),G67*(1-G75),0)
A64: Free cash flow to firm | E64: =E58+E59-E60-E62-E63 | F64: =F58+F59-F60-F62-F63 | G64: =G58+G59-G60-G62-G63 | H64: what the DCF discounts (Calc tabs)
A65: Operating cash flow (reported) | B65: 38314 | C65: 38771 | D65: 40284 | H65: SEC XBRL F45, F46, F47
A66: FCF (operating cash flow - capex) | B66: =B65-B60 | C66: =C65-C60 | D66: =D65-D60
A67: Stock comp (memo) | B67: 479 | C67: 505 | D67: 536 | E67: =E36*E79 | F67: =F36*F79 | G67: =G36*G79 | H67: SEC XBRL F41, F42, F43
A68: Buybacks + dividends + other uses | B68: 8330 | C68: 8423 | D68: 12680 | E68: =E36*E81+E80+E82 | F68: =F36*F81+F80+F82 | G68: =G36*G81+G80+G82 | H68: SEC XBRL F56, F63, F57, F64, F58, F65
A69: % of sales | B69: =B68/B36 | C69: =C68/C36 | D69: =D68/D36 | E69: =E68/E36 | F69: =F68/F36 | G69: =G68/G36
A70: Net debt / (net cash), year end (memo) | E70: =Valuation!$B$57-E64-E45*(1-E75)+E68 | F70: =E70-F64-F45*(1-F75)+F68 | G70: =F70-G64-G45*(1-G75)+G68 | H70: rolled from the balance-date figure; feeds interest only
A72: Drivers (blue = input; a year left black carries the prior year)
A73: Revenue growth | C73: =C37 | D73: =D37 | E73: =E37 | F73: =F37 | G73: =G37 | H73: implied by the segment build (edit the segment rows)
A74: EBIT margin | E74: =E41 | F74: =F41 | G74: =G41 | H74: implied by the segment build and corporate EBIT
A75: Tax rate | B75: =B49 | C75: =C49 | D75: =D49 | E75: 0.215 | F75: 0.215 | G75: 0.215
A76: D&A % revenue | B76: =B42/B36 | C76: =C42/C36 | D76: =D42/D36 | E76: 0.15253 | F76: 0.15139 | G76: 0.15415
A77: Capex % revenue | B77: =B61 | C77: =C61 | D77: =D61 | E77: 0.18115132 | F77: 0.17870727 | G77: 0.17613174
A78: Working capital % of revenue increase | E78: 0 | F78: 0 | G78: 0
A79: Stock comp % revenue | B79: =B67/B36 | C79: =C67/C36 | D79: =D67/D36 | E79: 0.0043 | F79: 0.0043 | G79: 0.0043
A80: Shareholder returns ($) | E80: 0 | F80: 0 | G80: 0
A81: Shareholder returns % revenue | B81: =B69 | C81: =C69 | D81: =D69 | E81: 0 | F81: =E81 | G81: =F81
A82: Other uses of cash ($: M&A, investments) | E82: 0 | F82: 0 | G82: 0
A83: Adj. EBITDA addback % revenue | E83: 0 | F83: 0 | G83: 0
A85: Versus company guidance and street consensus
A86: Guidance: adjusted EPS (adjusted), midpoint | E86: =AVERAGE(2.4,2.4) | H86: 2.4 to 2.4; as of 2026-10-21; source 4 (AT&T 8-K Ex.99.1: Q3 2026 earnings release and outlook)
A87: Guidance: adjusted EBITDA growth (adjusted), midpoint | E87: =AVERAGE(0.035,0.04) | H87: 0.035 to 0.04; as of 2026-10-21; source 4 (AT&T 8-K Ex.99.1: Q3 2026 earnings release and outlook)
A88: Guidance: free cash flow (CFO - capex - vendor financing), midpoint | E88: 18000 | H88: as of 2026-10-21; source 4 (AT&T 8-K Ex.99.1: Q3 2026 earnings release and outlook)
A89: Guidance: free cash flow (as above), midpoint | F89: 19000 | H89: as of 2026-10-21; source 4 (AT&T 8-K Ex.99.1: Q3 2026 earnings release and outlook)
A90: Guidance: free cash flow (as above), midpoint | G90: 21000 | H90: as of 2026-10-21; source 4 (AT&T 8-K Ex.99.1: Q3 2026 earnings release and outlook)
A91: Guidance: capital investment (capex + vendor financing), midpoint | E91: =AVERAGE(23000,24000) | H91: 2.3e+04 to 2.4e+04; as of 2026-10-21; source 4 (AT&T 8-K Ex.99.1: Q3 2026 earnings release and outlook)
A92: Guidance: capital investment (capex + vendor financing), midpoint | F92: =AVERAGE(22000,23000) | H92: 2.2e+04 to 2.3e+04; as of 2026-10-21; source 4 (AT&T 8-K Ex.99.1: Q3 2026 earnings release and outlook)
A93: Guidance: capital investment (capex + vendor financing), midpoint | G93: =AVERAGE(22000,23000) | H93: 2.2e+04 to 2.3e+04; as of 2026-10-21; source 4 (AT&T 8-K Ex.99.1: Q3 2026 earnings release and outlook)
A94: Guidance: adjusted EBITDA growth (adjusted, ex-Mexico), midpoint | G94: 0.05 | H94: as of 2026-10-21; source 4 (AT&T 8-K Ex.99.1: Q3 2026 earnings release and outlook)
A95: Guidance: dividend per share (annualised), midpoint | E95: =AVERAGE(1.11,1.11) | H95: 1.11 to 1.11; as of 2026-10-21; source 4 (AT&T 8-K Ex.99.1: Q3 2026 earnings release and outlook)
A96: Guidance: adjusted EPS (long-term target: double-digit 3-year CAGR from $2.12; floor $2.12 x 1.1^3) (adjusted; long-term target), midpoint | G96: =AVERAGE(2.82,2.82) | H96: 2.82 to 2.82; as of 2026-10-21; source 4, 8 (AT&T 8-K Ex.99.1: Q3 2026 earnings release and outlook)
A97: Guidance: Advanced Connectivity EBITDA growth (segment EBITDA; 'mid-to-high-single-digit range annually' read as 5-8%), midpoint | F97: =AVERAGE(0.05,0.08) | H97: 0.05 to 0.08; as of 2026-10-21; source 4 (AT&T 8-K Ex.99.1: Q3 2026 earnings release and outlook)
A98: Guidance: Advanced Connectivity service revenue growth ('mid-single-digit range annually' read as 4-6% (5%+ in 2026)), midpoint | F98: =AVERAGE(0.04,0.06) | H98: 0.04 to 0.06; as of 2026-10-21; source 4 (AT&T 8-K Ex.99.1: Q3 2026 earnings release and outlook)
A99: Guidance: Advanced Connectivity service revenue growth ('mid-single-digit range annually' read as 4-6%), midpoint | G99: =AVERAGE(0.04,0.06) | H99: 0.04 to 0.06; as of 2026-10-21; source 4 (AT&T 8-K Ex.99.1: Q3 2026 earnings release and outlook)
A100: Guidance: Legacy service revenue growth ('decline of 20%+ in 2026', immaterial by end-2029), midpoint | E100: =AVERAGE(-0.2,-0.2) | H100: -0.2 to -0.2; as of 2026-10-21; source 4 (AT&T 8-K Ex.99.1: Q3 2026 earnings release and outlook)
A101: Consensus: EBITDA (adjusted (consensus)) | E101: 48254 | H101: as of 2026-10-23; source 19 (MarketScreener: AT&T consensus estimates (24 analysts))
A102: Consensus: EBITDA (adjusted (consensus)) | F102: 49750 | H102: as of 2026-10-23; source 19 (MarketScreener: AT&T consensus estimates (24 analysts))
A103: Consensus: EBITDA (adjusted (consensus)) | G103: 51989 | H103: as of 2026-10-23; source 19 (MarketScreener: AT&T consensus estimates (24 analysts))
A104: Consensus: free cash flow (consensus) | F104: 19239 | H104: as of 2026-10-23; source 19 (MarketScreener: AT&T consensus estimates (24 analysts))
A105: Consensus: free cash flow (consensus) | G105: 20973 | H105: as of 2026-10-23; source 19 (MarketScreener: AT&T consensus estimates (24 analysts))
A106: Consensus: EPS (MarketScreener consensus basis) | F106: 2.621 | H106: as of 2026-10-23; source 19 (MarketScreener: AT&T consensus estimates (24 analysts))
A107: Model vs consensus | F107: =F54/F106-1
A108: Consensus: EPS (MarketScreener consensus basis) | G108: 2.934 | H108: as of 2026-10-23; source 19 (MarketScreener: AT&T consensus estimates (24 analysts))
...

Sheet Valuation
A1: T: valuation and price target derivation
A2: Value per share at the target date = weighted methods below; the 12-month target is the median of the scenario mix (Distribution tab).
A3: Method | B3: Multiple | C3: Metric at target date | D3: Value per share | E3: Weight | F3: Contribution
A4: ='Calc - research target (12m)'!A67 | B4: =IF('Calc - research target (12m)'!C67="","",'Calc - research target (12m)'!C67) | C4: =IF('Calc - research target (12m)'!I67="","",'Calc - research target (12m)'!I67) | D4: ='Calc - research target (12m)'!F67 | E4: ='Calc - research target (12m)'!G67 | F4: =D4*E4/SUM($E$4:$E$7)
A5: ='Calc - research target (12m)'!A68 | B5: =IF('Calc - research target (12m)'!C68="","",'Calc - research target (12m)'!C68) | C5: =IF('Calc - research target (12m)'!I68="","",'Calc - research target (12m)'!I68) | D5: ='Calc - research target (12m)'!F68 | E5: ='Calc - research target (12m)'!G68 | F5: =D5*E5/SUM($E$4:$E$7)
A6: ='Calc - research target (12m)'!A69 | B6: =IF('Calc - research target (12m)'!C69="","",'Calc - research target (12m)'!C69) | C6: =IF('Calc - research target (12m)'!I69="","",'Calc - research target (12m)'!I69) | D6: ='Calc - research target (12m)'!F69 | E6: ='Calc - research target (12m)'!G69 | F6: =D6*E6/SUM($E$4:$E$7)
A7: ='Calc - research target (12m)'!A70 | B7: =IF('Calc - research target (12m)'!C70="","",'Calc - research target (12m)'!C70) | C7: =IF('Calc - research target (12m)'!I70="","",'Calc - research target (12m)'!I70) | D7: ='Calc - research target (12m)'!F70 | E7: ='Calc - research target (12m)'!G70 | F7: =D7*E7/SUM($E$4:$E$7)
A8: Research target (12m) per share | D8: ='Calc - research target (12m)'!$F$71 | F8: =SUM(F4:F7)
A10: 12-month EPS basis (what the P/E is applied to)
A11: Fiscal year | B11: =Model!E5 | C11: =Model!F5 | D11: =Model!G5
A12: Share of the 12 months after the target date | B12: ='Calc - research target (12m)'!C38 | C12: ='Calc - research target (12m)'!D38 | D12: ='Calc - research target (12m)'!E38
A13: Model EPS (Model tab) | B13: =Model!E54 | C13: =Model!F54 | D13: =Model!G54
A14: Model EPS, next 12 months after the target date | B14: =SUMPRODUCT(B12:D12,B13:D13)
A15: Stated next-12-month EPS used by the P/E method (consensus basis, cited) | B15: =Valuation!F72 | C15: =B15/B14-1 | D15: vs model EPS
A17: DCF build (free cash flow to firm, discounted to the target date)
A18: Fiscal year | B18: =Model!E5 | C18: =Model!F5 | D18: =Model!G5
A19: Free cash flow to firm | B19: ='Calc - research target (12m)'!C31 | C19: ='Calc - research target (12m)'!D31 | D19: ='Calc - research target (12m)'!E31
A20: Share of the year after the target date | B20: ='Calc - research target (12m)'!C35 | C20: ='Calc - research target (12m)'!D35 | D20: ='Calc - research target (12m)'!E35
A21: PV at target date | B21: ='Calc - research target (12m)'!C36 | C21: ='Calc - research target (12m)'!D36 | D21: ='Calc - research target (12m)'!E36
A23: PV of free cash flow after the target date | B23: ='Calc - research target (12m)'!B42
A24: Terminal value (final year) | B24: ='Calc - research target (12m)'!B43
A25: PV of terminal value | B25: ='Calc - research target (12m)'!B44
A26: Enterprise value at target date | B26: ='Calc - research target (12m)'!B45
A27: Terminal value share of DCF | B27: ='Calc - research target (12m)'!B46
A28: Net debt at target date | B28: ='Calc - research target (12m)'!B50
A29: Minority interests | B29: ='Calc - research target (12m)'!B51
A30: Adjustments | B30: ='Calc - research target (12m)'!B52
A31: Diluted shares at target date (M) | B31: ='Calc - research target (12m)'!B53
A32: DCF value per share | B32: ='Calc - research target (12m)'!F67
A33: WACC | B33: ='Calc - research target (12m)'!B12
A43: Assumptions (blue = input; sources on the Sources tab)
A44: Input | B44: Value | C44: Basis / note
A45: Run date (valuation as of) | B45: 46318
A46: Target date (run date + 365 days) | B46: =B45+365 | C46: 12-month horizon
A47: Money unit | B47: $M
A48: EBIT basis (gaap / adjusted) | B48: adjusted | C48: gaap = after stock comp
A49: Stock comp treatment (cost / dilution) | B49: cost | C49: used only when EBIT is adjusted
A50: Last reported fiscal year end | B50: 46022
A51: Net sales, last reported year ($M) | B51: 125648
A52: WACC | B52: 0.1 | C52: not used: no DCF leg (Kilian 2026-10-21); a placeholder so the DCF block still computes
A53: Terminal method (gordon / exit_multiple / steady_state) | B53: gordon
A54: Terminal growth | B54: 0.02
A55: Exit EV/EBITDA (exit_multiple only)
A56: Balance-sheet date | B56: 46295
A57: Net debt / (net cash) at balance date ($M) | B57: 149819 | C57: excludes operating leases
A58: Minority interests + preferred stock | B58: 20935 | C58: minorities 17,985 + preferred 2,950
A59: Interest rate on net debt / cash | B59: 0.05
A60: Net debt at target date (override; blank = bridge) | B60: 144260
A61: Diluted shares (M) | B61: 6745.5
A62: Share count date | B62: 46310
A63: Annual change in diluted shares | B63: -0.0531 | C63: net of buybacks and stock-comp dilution
A64: Shares at target date (override; blank = from annual change) | B64: 6387
A65: DCF weight | B65: 0 | C65: Kilian 2026-10-21: 0 unless the name has a DCF leg (dcf_policy)
A66: Sum-of-the-parts weight | B66: 0
A67: Spread within each scenario (lognormal vol) | B67: 0.14
A68: Share price at the run | B68: 20.93 | C68: close used by the run (2026-10-23)
A70: Target multiple | B70: Multiple | C70: Weight | D70: Basis (ntm / ltm) | E70: EBITDA basis | F70: Stated EPS | G70: Stated FCF/share | H70: Levered | I70: Peer basis
A71: EV/EBITDA | B71: 6.1 | C71: 0.5 | D71: ntm | E71: adjusted | H71: TRUE | I71: EV incl. $18.0B NCI and $2.95B preferred, excl. the fiber stake: 6.1x = ~5.69x on the peers' basis; peer benchmark = 11-incumbent CY2027E median ex-DT 5.98x (12-peer 5.52x incl. DT, reference only; comps_review). Decided by Kilian 2026-10-26: keep the post-SpaceX multiple.
A72: P/E | B72: 8.3 | C72: 0.35 | D72: ntm | E72: adjusted | F72: 2.8611256 | H72: TRUE | I72: NTM adjusted EPS; AT&T today 8.34x on Zacks consensus NTM EPS (0.19 x $2.38 + 0.81 x $2.54 = $2.510, Nasdaq API, one source and basis); peer P/E median 10.55x is indicative only (EPS basis unstated); VZ 8.51x, CMCSA 7.4x
A73: FCF yield | B73: 0.123 | C73: 0.15 | D73: ntm | E73: adjusted | G73: 2.8208272 | H73: TRUE | I73: FCF to common (after NCI distributions and preferred dividends) on horizon shares; AT&T today 12.3% on consensus NTM FCF (0.19 x 17.97B + 0.81 x 19.24B - 1.65B) / 6,745.5M
A75: Segment (sum of the parts) | B75: NTM metric | C75: Metric | D75: Multiple | E75: Note
A76: none
A78: Adjustment (equity level) | B78: Value | C78: Probability | D78: Note
A79: Composite Fiber 37 stake (Forged Fiber held-for-sale net assets) | B79: 4058 | C79: 0.9 | D79: equity-level; 10-Q R63: Lumen Mass Markets discontinued-operations assets 4,781 less liabilities 723 = 4,058 (opened); R17: AT&T sells 50% of Composite Fiber 37 to GIP/CPP Investments, which buy equity in the JV, joint board with an investor tie-break on the CEO, equity method, close H1 2027 (opened); x0.9 for governance and close risk; no holdco discount (see reasoning)
A80: Upper C-band auction spend (expected) | B80: -5000 | C80: 0.4 | D80: equity-level; FCC DA 26-769: Auction 115 (160 MHz, 3.98-4.14 GHz) bidding tentatively from 2027-04-27, statutory completion by 2027-07-04, so payments fall before the horizon; ~$5B AT&T spend if it wins, p 0.4 (it just bought EchoStar spectrum and leverage is 3.13x); no NTM EBITDA from it
A82: Custom method | B82: Value per share | C82: Weight | D82: Explanation
A83: none
A85: Scenario | B85: Probability | C85: Growth Δ | D85: Margin Δ | E85: Multiple Δ (turns) | F85: WACC Δ | G85: Multiple %Δ (FCF yield, segments) | H85: Stated EPS/FCF %Δ | I85: Custom methods %Δ | J85: Story
A86: bear | B86: 0.25 | E86: -0.8 | G86: -0.12 | J86: Starlink Mobile signs terrestrial site access and prices for share from late 2027 while Verizon keeps promotions high: wireless ARPU flat from 2027, fiber ARPU keeps falling, AC EBITDA roughly flat; the market prices AT&T near cable (5.3x EBITDA, ~7x EPS, ~14% FCF yield). | K86: driver deltas: ws_arpu -0.025 %; pp_subs -0.01 %; hi_arpu -0.03 %; ac_m -0.012
A87: base | B87: 0.5 | J87: Drivers as set: AC EBITDA +6.4%/+6.0%/+5.5%, Legacy EBITDA negative in 2028, FCF $18.1B/$18.5B/$19.9B, ~5%/yr share count reduction; multiples stay at today's post-SpaceX levels (6.1x / 8.3x / 12.3%).
A88: bull | B88: 0.25 | E88: 0.7 | G88: 0.1 | J88: Starlink Mobile stays a satellite/niche offer without national terrestrial coverage, price actions stick and fiber ARPU recovers; EBITDA reaches the 5%+ 2028 plan; multiple recovers toward 6.8x (pre-Oct-8). | K88: driver deltas: ws_arpu +0.015 %; pp_subs +0.005 %; hi_arpu +0.02 %; ac_m +0.008
A90: Segment build (segment_build) | B90: Base revenue ($M) | C90: Driver note (growth and EBIT margin by year: Model tab)
A91: AC Wireless and Home | B91: 99620 | C91: postpaid phones x (wireless service ARPU x 12 + equipment $310.64/sub/yr) + home internet connections x ARPU x 12
A92: AC Business Wireline and Other | B92: 12804 | C92: plain: business fiber/transitional and other AC revenue; margin from ac_m
A93: Legacy | B93: 8472 | C93: plain: copper run-off (service revenue -20%+ guide; 9M 2026 -25.3%)
A94: Latin America | B94: 4379 | C94: plain: Mexico wireless, sold (close expected Q1 2027); margin is an EBITDA margin (its D&A sits in corporate)
A95: Corporate and Other | B95: 373 | C95: plain
A96: Sum of segment base revenues | B96: =SUM(B91:B95) | C96: =IF(ABS(B96/Valuation!$B$51-1)<=0.02,"ties to the last reported net sales (within 2%)","FLAG: does not tie to the last reported net sales")

Sheet Sensitivity
A1: T: sensitivity tables (bold = current inputs; every cell recalculates from the live model)
A3: DCF value per share: WACC (down) x terminal growth (across)
A4: WACC \ growth | B4: =Valuation!$B$54+(-0.01) | C4: =Valuation!$B$54+(-0.005) | D4: =Valuation!$B$54+(0) | E4: =Valuation!$B$54+(0.005) | F4: =Valuation!$B$54+(0.01)
A5: =Valuation!$B$52+(-0.01) | B5: =IF($A5-B$4<=0.01,"n/a",((SUMPRODUCT('Calc - research target (12m)'!$C$31:$E$31,'Calc - research target (12m)'!$C$35:$E$35,(1+$A5)^(-('Calc - research target (12m)'!$C$19:$E$19-'Calc - research target (12m)'!$B$13)))+'Calc - research target (12m)'!$E$31*(1+B$4)/($A5-B$4)/(1+$A5)^('Calc - research target (12m)'!$B$16-'Calc - research target (12m)'!$B$13))-'Calc - research target (12m)'!$B$50-'Calc - research target (12m)'!$B$51+'Calc - research target (12m)'!$B$52)/'Calc - research target (12m)'!$B$53) | C5: =IF($A5-C$4<=0.01,"n/a",((SUMPRODUCT('Calc - research target (12m)'!$C$31:$E$31,'Calc - research target (12m)'!$C$35:$E$35,(1+$A5)^(-('Calc - research target (12m)'!$C$19:$E$19-'Calc - research target (12m)'!$B$13)))+'Calc - research target (12m)'!$E$31*(1+C$4)/($A5-C$4)/(1+$A5)^('Calc - research target (12m)'!$B$16-'Calc - research target (12m)'!$B$13))-'Calc - research target (12m)'!$B$50-'Calc - research target (12m)'!$B$51+'Calc - research target (12m)'!$B$52)/'Calc - research target (12m)'!$B$53) | D5: =IF($A5-D$4<=0.01,"n/a",((SUMPRODUCT('Calc - research target (12m)'!$C$31:$E$31,'Calc - research target (12m)'!$C$35:$E$35,(1+$A5)^(-('Calc - research target (12m)'!$C$19:$E$19-'Calc - research target (12m)'!$B$13)))+'Calc - research target (12m)'!$E$31*(1+D$4)/($A5-D$4)/(1+$A5)^('Calc - research target (12m)'!$B$16-'Calc - research target (12m)'!$B$13))-'Calc - research target (12m)'!$B$50-'Calc - research target (12m)'!$B$51+'Calc - research target (12m)'!$B$52)/'Calc - research target (12m)'!$B$53) | E5: =IF($A5-E$4<=0.01,"n/a",((SUMPRODUCT('Calc - research target (12m)'!$C$31:$E$31,'Calc - research target (12m)'!$C$35:$E$35,(1+$A5)^(-('Calc - research target (12m)'!$C$19:$E$19-'Calc - research target (12m)'!$B$13)))+'Calc - research target (12m)'!$E$31*(1+E$4)/($A5-E$4)/(1+$A5)^('Calc - research target (12m)'!$B$16-'Calc - research target (12m)'!$B$13))-'Calc - research target (12m)'!$B$50-'Calc - research target (12m)'!$B$51+'Calc - research target (12m)'!$B$52)/'Calc - research target (12m)'!$B$53) | F5: =IF($A5-F$4<=0.01,"n/a",((SUMPRODUCT('Calc - research target (12m)'!$C$31:$E$31,'Calc - research target (12m)'!$C$35:$E$35,(1+$A5)^(-('Calc - research target (12m)'!$C$19:$E$19-'Calc - research target (12m)'!$B$13)))+'Calc - research target (12m)'!$E$31*(1+F$4)/($A5-F$4)/(1+$A5)^('Calc - research target (12m)'!$B$16-'Calc - research target (12m)'!$B$13))-'Calc - research target (12m)'!$B$50-'Calc - research target (12m)'!$B$51+'Calc - research target (12m)'!$B$52)/'Calc - research target (12m)'!$B$53)
A6: =Valuation!$B$52+(-0.005) | B6: =IF($A6-B$4<=0.01,"n/a",((SUMPRODUCT('Calc - research target (12m)'!$C$31:$E$31,'Calc - research target (12m)'!$C$35:$E$35,(1+$A6)^(-('Calc - research target (12m)'!$C$19:$E$19-'Calc - research target (12m)'!$B$13)))+'Calc - research target (12m)'!$E$31*(1+B$4)/($A6-B$4)/(1+$A6)^('Calc - research target (12m)'!$B$16-'Calc - research target (12m)'!$B$13))-'Calc - research target (12m)'!$B$50-'Calc - research target (12m)'!$B$51+'Calc - research target (12m)'!$B$52)/'Calc - research target (12m)'!$B$53) | C6: =IF($A6-C$4<=0.01,"n/a",((SUMPRODUCT('Calc - research target (12m)'!$C$31:$E$31,'Calc - research target (12m)'!$C$35:$E$35,(1+$A6)^(-('Calc - research target (12m)'!$C$19:$E$19-'Calc - research target (12m)'!$B$13)))+'Calc - research target (12m)'!$E$31*(1+C$4)/($A6-C$4)/(1+$A6)^('Calc - research target (12m)'!$B$16-'Calc - research target (12m)'!$B$13))-'Calc - research target (12m)'!$B$50-'Calc - research target (12m)'!$B$51+'Calc - research target (12m)'!$B$52)/'Calc - research target (12m)'!$B$53) | D6: =IF($A6-D$4<=0.01,"n/a",((SUMPRODUCT('Calc - research target (12m)'!$C$31:$E$31,'Calc - research target (12m)'!$C$35:$E$35,(1+$A6)^(-('Calc - research target (12m)'!$C$19:$E$19-'Calc - research target (12m)'!$B$13)))+'Calc - research target (12m)'!$E$31*(1+D$4)/($A6-D$4)/(1+$A6)^('Calc - research target (12m)'!$B$16-'Calc - research target (12m)'!$B$13))-'Calc - research target (12m)'!$B$50-'Calc - research target (12m)'!$B$51+'Calc - research target (12m)'!$B$52)/'Calc - research target (12m)'!$B$53) | E6: =IF($A6-E$4<=0.01,"n/a",((SUMPRODUCT('Calc - research target (12m)'!$C$31:$E$31,'Calc - research target (12m)'!$C$35:$E$35,(1+$A6)^(-('Calc - research target (12m)'!$C$19:$E$19-'Calc - research target (12m)'!$B$13)))+'Calc - research target (12m)'!$E$31*(1+E$4)/($A6-E$4)/(1+$A6)^('Calc - research target (12m)'!$B$16-'Calc - research target (12m)'!$B$13))-'Calc - research target (12m)'!$B$50-'Calc - research target (12m)'!$B$51+'Calc - research target (12m)'!$B$52)/'Calc - research target (12m)'!$B$53) | F6: =IF($A6-F$4<=0.01,"n/a",((SUMPRODUCT('Calc - research target (12m)'!$C$31:$E$31,'Calc - research target (12m)'!$C$35:$E$35,(1+$A6)^(-('Calc - research target (12m)'!$C$19:$E$19-'Calc - research target (12m)'!$B$13)))+'Calc - research target (12m)'!$E$31*(1+F$4)/($A6-F$4)/(1+$A6)^('Calc - research target (12m)'!$B$16-'Calc - research target (12m)'!$B$13))-'Calc - research target (12m)'!$B$50-'Calc - research target (12m)'!$B$51+'Calc - research target (12m)'!$B$52)/'Calc - research target (12m)'!$B$53)
A7: =Valuation!$B$52+(0) | B7: =IF($A7-B$4<=0.01,"n/a",((SUMPRODUCT('Calc - research target (12m)'!$C$31:$E$31,'Calc - research target (12m)'!$C$35:$E$35,(1+$A7)^(-('Calc - research target (12m)'!$C$19:$E$19-'Calc - research target (12m)'!$B$13)))+'Calc - research target (12m)'!$E$31*(1+B$4)/($A7-B$4)/(1+$A7)^('Calc - research target (12m)'!$B$16-'Calc - research target (12m)'!$B$13))-'Calc - research target (12m)'!$B$50-'Calc - research target (12m)'!$B$51+'Calc - research target (12m)'!$B$52)/'Calc - research target (12m)'!$B$53) | C7: =IF($A7-C$4<=0.01,"n/a",((SUMPRODUCT('Calc - research target (12m)'!$C$31:$E$31,'Calc - research target (12m)'!$C$35:$E$35,(1+$A7)^(-('Calc - research target (12m)'!$C$19:$E$19-'Calc - research target (12m)'!$B$13)))+'Calc - research target (12m)'!$E$31*(1+C$4)/($A7-C$4)/(1+$A7)^('Calc - research target (12m)'!$B$16-'Calc - research target (12m)'!$B$13))-'Calc - research target (12m)'!$B$50-'Calc - research target (12m)'!$B$51+'Calc - research target (12m)'!$B$52)/'Calc - research target (12m)'!$B$53) | D7: =IF($A7-D$4<=0.01,"n/a",((SUMPRODUCT('Calc - research target (12m)'!$C$31:$E$31,'Calc - research target (12m)'!$C$35:$E$35,(1+$A7)^(-('Calc - research target (12m)'!$C$19:$E$19-'Calc - research target (12m)'!$B$13)))+'Calc - research target (12m)'!$E$31*(1+D$4)/($A7-D$4)/(1+$A7)^('Calc - research target (12m)'!$B$16-'Calc - research target (12m)'!$B$13))-'Calc - research target (12m)'!$B$50-'Calc - research target (12m)'!$B$51+'Calc - research target (12m)'!$B$52)/'Calc - research target (12m)'!$B$53) | E7: =IF($A7-E$4<=0.01,"n/a",((SUMPRODUCT('Calc - research target (12m)'!$C$31:$E$31,'Calc - research target (12m)'!$C$35:$E$35,(1+$A7)^(-('Calc - research target (12m)'!$C$19:$E$19-'Calc - research target (12m)'!$B$13)))+'Calc - research target (12m)'!$E$31*(1+E$4)/($A7-E$4)/(1+$A7)^('Calc - research target (12m)'!$B$16-'Calc - research target (12m)'!$B$13))-'Calc - research target (12m)'!$B$50-'Calc - research target (12m)'!$B$51+'Calc - research target (12m)'!$B$52)/'Calc - research target (12m)'!$B$53) | F7: =IF($A7-F$4<=0.01,"n/a",((SUMPRODUCT('Calc - research target (12m)'!$C$31:$E$31,'Calc - research target (12m)'!$C$35:$E$35,(1+$A7)^(-('Calc - research target (12m)'!$C$19:$E$19-'Calc - research target (12m)'!$B$13)))+'Calc - research target (12m)'!$E$31*(1+F$4)/($A7-F$4)/(1+$A7)^('Calc - research target (12m)'!$B$16-'Calc - research target (12m)'!$B$13))-'Calc - research target (12m)'!$B$50-'Calc - research target (12m)'!$B$51+'Calc - research target (12m)'!$B$52)/'Calc - research target (12m)'!$B$53)
A8: =Valuation!$B$52+(0.005) | B8: =IF($A8-B$4<=0.01,"n/a",((SUMPRODUCT('Calc - research target (12m)'!$C$31:$E$31,'Calc - research target (12m)'!$C$35:$E$35,(1+$A8)^(-('Calc - research target (12m)'!$C$19:$E$19-'Calc - research target (12m)'!$B$13)))+'Calc - research target (12m)'!$E$31*(1+B$4)/($A8-B$4)/(1+$A8)^('Calc - research target (12m)'!$B$16-'Calc - research target (12m)'!$B$13))-'Calc - research target (12m)'!$B$50-'Calc - research target (12m)'!$B$51+'Calc - research target (12m)'!$B$52)/'Calc - research target (12m)'!$B$53) | C8: =IF($A8-C$4<=0.01,"n/a",((SUMPRODUCT('Calc - research target (12m)'!$C$31:$E$31,'Calc - research target (12m)'!$C$35:$E$35,(1+$A8)^(-('Calc - research target (12m)'!$C$19:$E$19-'Calc - research target (12m)'!$B$13)))+'Calc - research target (12m)'!$E$31*(1+C$4)/($A8-C$4)/(1+$A8)^('Calc - research target (12m)'!$B$16-'Calc - research target (12m)'!$B$13))-'Calc - research target (12m)'!$B$50-'Calc - research target (12m)'!$B$51+'Calc - research target (12m)'!$B$52)/'Calc - research target (12m)'!$B$53) | D8: =IF($A8-D$4<=0.01,"n/a",((SUMPRODUCT('Calc - research target (12m)'!$C$31:$E$31,'Calc - research target (12m)'!$C$35:$E$35,(1+$A8)^(-('Calc - research target (12m)'!$C$19:$E$19-'Calc - research target (12m)'!$B$13)))+'Calc - research target (12m)'!$E$31*(1+D$4)/($A8-D$4)/(1+$A8)^('Calc - research target (12m)'!$B$16-'Calc - research target (12m)'!$B$13))-'Calc - research target (12m)'!$B$50-'Calc - research target (12m)'!$B$51+'Calc - research target (12m)'!$B$52)/'Calc - research target (12m)'!$B$53) | E8: =IF($A8-E$4<=0.01,"n/a",((SUMPRODUCT('Calc - research target (12m)'!$C$31:$E$31,'Calc - research target (12m)'!$C$35:$E$35,(1+$A8)^(-('Calc - research target (12m)'!$C$19:$E$19-'Calc - research target (12m)'!$B$13)))+'Calc - research target (12m)'!$E$31*(1+E$4)/($A8-E$4)/(1+$A8)^('Calc - research target (12m)'!$B$16-'Calc - research target (12m)'!$B$13))-'Calc - research target (12m)'!$B$50-'Calc - research target (12m)'!$B$51+'Calc - research target (12m)'!$B$52)/'Calc - research target (12m)'!$B$53) | F8: =IF($A8-F$4<=0.01,"n/a",((SUMPRODUCT('Calc - research target (12m)'!$C$31:$E$31,'Calc - research target (12m)'!$C$35:$E$35,(1+$A8)^(-('Calc - research target (12m)'!$C$19:$E$19-'Calc - research target (12m)'!$B$13)))+'Calc - research target (12m)'!$E$31*(1+F$4)/($A8-F$4)/(1+$A8)^('Calc - research target (12m)'!$B$16-'Calc - research target (12m)'!$B$13))-'Calc - research target (12m)'!$B$50-'Calc - research target (12m)'!$B$51+'Calc - research target (12m)'!$B$52)/'Calc - research target (12m)'!$B$53)
A9: =Valuation!$B$52+(0.01) | B9: =IF($A9-B$4<=0.01,"n/a",((SUMPRODUCT('Calc - research target (12m)'!$C$31:$E$31,'Calc - research target (12m)'!$C$35:$E$35,(1+$A9)^(-('Calc - research target (12m)'!$C$19:$E$19-'Calc - research target (12m)'!$B$13)))+'Calc - research target (12m)'!$E$31*(1+B$4)/($A9-B$4)/(1+$A9)^('Calc - research target (12m)'!$B$16-'Calc - research target (12m)'!$B$13))-'Calc - research target (12m)'!$B$50-'Calc - research target (12m)'!$B$51+'Calc - research target (12m)'!$B$52)/'Calc - research target (12m)'!$B$53) | C9: =IF($A9-C$4<=0.01,"n/a",((SUMPRODUCT('Calc - research target (12m)'!$C$31:$E$31,'Calc - research target (12m)'!$C$35:$E$35,(1+$A9)^(-('Calc - research target (12m)'!$C$19:$E$19-'Calc - research target (12m)'!$B$13)))+'Calc - research target (12m)'!$E$31*(1+C$4)/($A9-C$4)/(1+$A9)^('Calc - research target (12m)'!$B$16-'Calc - research target (12m)'!$B$13))-'Calc - research target (12m)'!$B$50-'Calc - research target (12m)'!$B$51+'Calc - research target (12m)'!$B$52)/'Calc - research target (12m)'!$B$53) | D9: =IF($A9-D$4<=0.01,"n/a",((SUMPRODUCT('Calc - research target (12m)'!$C$31:$E$31,'Calc - research target (12m)'!$C$35:$E$35,(1+$A9)^(-('Calc - research target (12m)'!$C$19:$E$19-'Calc - research target (12m)'!$B$13)))+'Calc - research target (12m)'!$E$31*(1+D$4)/($A9-D$4)/(1+$A9)^('Calc - research target (12m)'!$B$16-'Calc - research target (12m)'!$B$13))-'Calc - research target (12m)'!$B$50-'Calc - research target (12m)'!$B$51+'Calc - research target (12m)'!$B$52)/'Calc - research target (12m)'!$B$53) | E9: =IF($A9-E$4<=0.01,"n/a",((SUMPRODUCT('Calc - research target (12m)'!$C$31:$E$31,'Calc - research target (12m)'!$C$35:$E$35,(1+$A9)^(-('Calc - research target (12m)'!$C$19:$E$19-'Calc - research target (12m)'!$B$13)))+'Calc - research target (12m)'!$E$31*(1+E$4)/($A9-E$4)/(1+$A9)^('Calc - research target (12m)'!$B$16-'Calc - research target (12m)'!$B$13))-'Calc - research target (12m)'!$B$50-'Calc - research target (12m)'!$B$51+'Calc - research target (12m)'!$B$52)/'Calc - research target (12m)'!$B$53) | F9: =IF($A9-F$4<=0.01,"n/a",((SUMPRODUCT('Calc - research target (12m)'!$C$31:$E$31,'Calc - research target (12m)'!$C$35:$E$35,(1+$A9)^(-('Calc - research target (12m)'!$C$19:$E$19-'Calc - research target (12m)'!$B$13)))+'Calc - research target (12m)'!$E$31*(1+F$4)/($A9-F$4)/(1+$A9)^('Calc - research target (12m)'!$B$16-'Calc - research target (12m)'!$B$13))-'Calc - research target (12m)'!$B$50-'Calc - research target (12m)'!$B$51+'Calc - research target (12m)'!$B$52)/'Calc - research target (12m)'!$B$53)
A11: Research target (12m) per share: EV/EBITDA multiple (down) x metric at target date (across)
A12: Multiple \ metric | B12: ='Calc - research target (12m)'!$E$68*0.9 | C12: ='Calc - research target (12m)'!$E$68*0.95 | D12: ='Calc - research target (12m)'!$E$68*1.0 | E12: ='Calc - research target (12m)'!$E$68*1.05 | F12: ='Calc - research target (12m)'!$E$68*1.1
A13: =Valuation!$B$71+(-3) | B13: =((SUMPRODUCT('Calc - research target (12m)'!$F$67:$F$70,'Calc - research target (12m)'!$G$67:$G$70)-'Calc - research target (12m)'!$F$68*'Calc - research target (12m)'!$G$68)+'Calc - research target (12m)'!$G$68*((($A13*B$12)-'Calc - research target (12m)'!$B$50-'Calc - research target (12m)'!$B$51+'Calc - research target (12m)'!$B$52)/'Calc - research target (12m)'!$B$53))/SUM('Calc - research target (12m)'!$G$67:$G$70) | C13: =((SUMPRODUCT('Calc - research target (12m)'!$F$67:$F$70,'Calc - research target (12m)'!$G$67:$G$70)-'Calc - research target (12m)'!$F$68*'Calc - research target (12m)'!$G$68)+'Calc - research target (12m)'!$G$68*((($A13*C$12)-'Calc - research target (12m)'!$B$50-'Calc - research target (12m)'!$B$51+'Calc - research target (12m)'!$B$52)/'Calc - research target (12m)'!$B$53))/SUM('Calc - research target (12m)'!$G$67:$G$70) | D13: =((SUMPRODUCT('Calc - research target (12m)'!$F$67:$F$70,'Calc - research target (12m)'!$G$67:$G$70)-'Calc - research target (12m)'!$F$68*'Calc - research target (12m)'!$G$68)+'Calc - research target (12m)'!$G$68*((($A13*D$12)-'Calc - research target (12m)'!$B$50-'Calc - research target (12m)'!$B$51+'Calc - research target (12m)'!$B$52)/'Calc - research target (12m)'!$B$53))/SUM('Calc - research target (12m)'!$G$67:$G$70) | E13: =((SUMPRODUCT('Calc - research target (12m)'!$F$67:$F$70,'Calc - research target (12m)'!$G$67:$G$70)-'Calc - research target (12m)'!$F$68*'Calc - research target (12m)'!$G$68)+'Calc - research target (12m)'!$G$68*((($A13*E$12)-'Calc - research target (12m)'!$B$50-'Calc - research target (12m)'!$B$51+'Calc - research target (12m)'!$B$52)/'Calc - research target (12m)'!$B$53))/SUM('Calc - research target (12m)'!$G$67:$G$70) | F13: =((SUMPRODUCT('Calc - research target (12m)'!$F$67:$F$70,'Calc - research target (12m)'!$G$67:$G$70)-'Calc - research target (12m)'!$F$68*'Calc - research target (12m)'!$G$68)+'Calc - research target (12m)'!$G$68*((($A13*F$12)-'Calc - research target (12m)'!$B$50-'Calc - research target (12m)'!$B$51+'Calc - research target (12m)'!$B$52)/'Calc - research target (12m)'!$B$53))/SUM('Calc - research target (12m)'!$G$67:$G$70)
A14: =Valuation!$B$71+(-2) | B14: =((SUMPRODUCT('Calc - research target (12m)'!$F$67:$F$70,'Calc - research target (12m)'!$G$67:$G$70)-'Calc - research target (12m)'!$F$68*'Calc - research target (12m)'!$G$68)+'Calc - research target (12m)'!$G$68*((($A14*B$12)-'Calc - research target (12m)'!$B$50-'Calc - research target (12m)'!$B$51+'Calc - research target (12m)'!$B$52)/'Calc - research target (12m)'!$B$53))/SUM('Calc - research target (12m)'!$G$67:$G$70) | C14: =((SUMPRODUCT('Calc - research target (12m)'!$F$67:$F$70,'Calc - research target (12m)'!$G$67:$G$70)-'Calc - research target (12m)'!$F$68*'Calc - research target (12m)'!$G$68)+'Calc - research target (12m)'!$G$68*((($A14*C$12)-'Calc - research target (12m)'!$B$50-'Calc - research target (12m)'!$B$51+'Calc - research target (12m)'!$B$52)/'Calc - research target (12m)'!$B$53))/SUM('Calc - research target (12m)'!$G$67:$G$70) | D14: =((SUMPRODUCT('Calc - research target (12m)'!$F$67:$F$70,'Calc - research target (12m)'!$G$67:$G$70)-'Calc - research target (12m)'!$F$68*'Calc - research target (12m)'!$G$68)+'Calc - research target (12m)'!$G$68*((($A14*D$12)-'Calc - research target (12m)'!$B$50-'Calc - research target (12m)'!$B$51+'Calc - research target (12m)'!$B$52)/'Calc - research target (12m)'!$B$53))/SUM('Calc - research target (12m)'!$G$67:$G$70) | E14: =((SUMPRODUCT('Calc - research target (12m)'!$F$67:$F$70,'Calc - research target (12m)'!$G$67:$G$70)-'Calc - research target (12m)'!$F$68*'Calc - research target (12m)'!$G$68)+'Calc - research target (12m)'!$G$68*((($A14*E$12)-'Calc - research target (12m)'!$B$50-'Calc - research target (12m)'!$B$51+'Calc - research target (12m)'!$B$52)/'Calc - research target (12m)'!$B$53))/SUM('Calc - research target (12m)'!$G$67:$G$70) | F14: =((SUMPRODUCT('Calc - research target (12m)'!$F$67:$F$70,'Calc - research target (12m)'!$G$67:$G$70)-'Calc - research target (12m)'!$F$68*'Calc - research target (12m)'!$G$68)+'Calc - research target (12m)'!$G$68*((($A14*F$12)-'Calc - research target (12m)'!$B$50-'Calc - research target (12m)'!$B$51+'Calc - research target (12m)'!$B$52)/'Calc - research target (12m)'!$B$53))/SUM('Calc - research target (12m)'!$G$67:$G$70)
A15: =Valuation!$B$71+(-1) | B15: =((SUMPRODUCT('Calc - research target (12m)'!$F$67:$F$70,'Calc - research target (12m)'!$G$67:$G$70)-'Calc - research target (12m)'!$F$68*'Calc - research target (12m)'!$G$68)+'Calc - research target (12m)'!$G$68*((($A15*B$12)-'Calc - research target (12m)'!$B$50-'Calc - research target (12m)'!$B$51+'Calc - research target (12m)'!$B$52)/'Calc - research target (12m)'!$B$53))/SUM('Calc - research target (12m)'!$G$67:$G$70) | C15: =((SUMPRODUCT('Calc - research target (12m)'!$F$67:$F$70,'Calc - research target (12m)'!$G$67:$G$70)-'Calc - research target (12m)'!$F$68*'Calc - research target (12m)'!$G$68)+'Calc - research target (12m)'!$G$68*((($A15*C$12)-'Calc - research target (12m)'!$B$50-'Calc - research target (12m)'!$B$51+'Calc - research target (12m)'!$B$52)/'Calc - research target (12m)'!$B$53))/SUM('Calc - research target (12m)'!$G$67:$G$70) | D15: =((SUMPRODUCT('Calc - research target (12m)'!$F$67:$F$70,'Calc - research target (12m)'!$G$67:$G$70)-'Calc - research target (12m)'!$F$68*'Calc - research target (12m)'!$G$68)+'Calc - research target (12m)'!$G$68*((($A15*D$12)-'Calc - research target (12m)'!$B$50-'Calc - research target (12m)'!$B$51+'Calc - research target (12m)'!$B$52)/'Calc - research target (12m)'!$B$53))/SUM('Calc - research target (12m)'!$G$67:$G$70) | E15: =((SUMPRODUCT('Calc - research target (12m)'!$F$67:$F$70,'Calc - research target (12m)'!$G$67:$G$70)-'Calc - research target (12m)'!$F$68*'Calc - research target (12m)'!$G$68)+'Calc - research target (12m)'!$G$68*((($A15*E$12)-'Calc - research target (12m)'!$B$50-'Calc - research target (12m)'!$B$51+'Calc - research target (12m)'!$B$52)/'Calc - research target (12m)'!$B$53))/SUM('Calc - research target (12m)'!$G$67:$G$70) | F15: =((SUMPRODUCT('Calc - research target (12m)'!$F$67:$F$70,'Calc - research target (12m)'!$G$67:$G$70)-'Calc - research target (12m)'!$F$68*'Calc - research target (12m)'!$G$68)+'Calc - research target (12m)'!$G$68*((($A15*F$12)-'Calc - research target (12m)'!$B$50-'Calc - research target (12m)'!$B$51+'Calc - research target (12m)'!$B$52)/'Calc - research target (12m)'!$B$53))/SUM('Calc - research target (12m)'!$G$67:$G$70)
A16: =Valuation!$B$71+(0) | B16: =((SUMPRODUCT('Calc - research target (12m)'!$F$67:$F$70,'Calc - research target (12m)'!$G$67:$G$70)-'Calc - research target (12m)'!$F$68*'Calc - research target (12m)'!$G$68)+'Calc - research target (12m)'!$G$68*((($A16*B$12)-'Calc - research target (12m)'!$B$50-'Calc - research target (12m)'!$B$51+'Calc - research target (12m)'!$B$52)/'Calc - research target (12m)'!$B$53))/SUM('Calc - research target (12m)'!$G$67:$G$70) | C16: =((SUMPRODUCT('Calc - research target (12m)'!$F$67:$F$70,'Calc - research target (12m)'!$G$67:$G$70)-'Calc - research target (12m)'!$F$68*'Calc - research target (12m)'!$G$68)+'Calc - research target (12m)'!$G$68*((($A16*C$12)-'Calc - research target (12m)'!$B$50-'Calc - research target (12m)'!$B$51+'Calc - research target (12m)'!$B$52)/'Calc - research target (12m)'!$B$53))/SUM('Calc - research target (12m)'!$G$67:$G$70) | D16: =((SUMPRODUCT('Calc - research target (12m)'!$F$67:$F$70,'Calc - research target (12m)'!$G$67:$G$70)-'Calc - research target (12m)'!$F$68*'Calc - research target (12m)'!$G$68)+'Calc - research target (12m)'!$G$68*((($A16*D$12)-'Calc - research target (12m)'!$B$50-'Calc - research target (12m)'!$B$51+'Calc - research target (12m)'!$B$52)/'Calc - research target (12m)'!$B$53))/SUM('Calc - research target (12m)'!$G$67:$G$70) | E16: =((SUMPRODUCT('Calc - research target (12m)'!$F$67:$F$70,'Calc - research target (12m)'!$G$67:$G$70)-'Calc - research target (12m)'!$F$68*'Calc - research target (12m)'!$G$68)+'Calc - research target (12m)'!$G$68*((($A16*E$12)-'Calc - research target (12m)'!$B$50-'Calc - research target (12m)'!$B$51+'Calc - research target (12m)'!$B$52)/'Calc - research target (12m)'!$B$53))/SUM('Calc - research target (12m)'!$G$67:$G$70) | F16: =((SUMPRODUCT('Calc - research target (12m)'!$F$67:$F$70,'Calc - research target (12m)'!$G$67:$G$70)-'Calc - research target (12m)'!$F$68*'Calc - research target (12m)'!$G$68)+'Calc - research target (12m)'!$G$68*((($A16*F$12)-'Calc - research target (12m)'!$B$50-'Calc - research target (12m)'!$B$51+'Calc - research target (12m)'!$B$52)/'Calc - research target (12m)'!$B$53))/SUM('Calc - research target (12m)'!$G$67:$G$70)
A17: =Valuation!$B$71+(1) | B17: =((SUMPRODUCT('Calc - research target (12m)'!$F$67:$F$70,'Calc - research target (12m)'!$G$67:$G$70)-'Calc - research target (12m)'!$F$68*'Calc - research target (12m)'!$G$68)+'Calc - research target (12m)'!$G$68*((($A17*B$12)-'Calc - research target (12m)'!$B$50-'Calc - research target (12m)'!$B$51+'Calc - research target (12m)'!$B$52)/'Calc - research target (12m)'!$B$53))/SUM('Calc - research target (12m)'!$G$67:$G$70) | C17: =((SUMPRODUCT('Calc - research target (12m)'!$F$67:$F$70,'Calc - research target (12m)'!$G$67:$G$70)-'Calc - research target (12m)'!$F$68*'Calc - research target (12m)'!$G$68)+'Calc - research target (12m)'!$G$68*((($A17*C$12)-'Calc - research target (12m)'!$B$50-'Calc - research target (12m)'!$B$51+'Calc - research target (12m)'!$B$52)/'Calc - research target (12m)'!$B$53))/SUM('Calc - research target (12m)'!$G$67:$G$70) | D17: =((SUMPRODUCT('Calc - research target (12m)'!$F$67:$F$70,'Calc - research target (12m)'!$G$67:$G$70)-'Calc - research target (12m)'!$F$68*'Calc - research target (12m)'!$G$68)+'Calc - research target (12m)'!$G$68*((($A17*D$12)-'Calc - research target (12m)'!$B$50-'Calc - research target (12m)'!$B$51+'Calc - research target (12m)'!$B$52)/'Calc - research target (12m)'!$B$53))/SUM('Calc - research target (12m)'!$G$67:$G$70) | E17: =((SUMPRODUCT('Calc - research target (12m)'!$F$67:$F$70,'Calc - research target (12m)'!$G$67:$G$70)-'Calc - research target (12m)'!$F$68*'Calc - research target (12m)'!$G$68)+'Calc - research target (12m)'!$G$68*((($A17*E$12)-'Calc - research target (12m)'!$B$50-'Calc - research target (12m)'!$B$51+'Calc - research target (12m)'!$B$52)/'Calc - research target (12m)'!$B$53))/SUM('Calc - research target (12m)'!$G$67:$G$70) | F17: =((SUMPRODUCT('Calc - research target (12m)'!$F$67:$F$70,'Calc - research target (12m)'!$G$67:$G$70)-'Calc - research target (12m)'!$F$68*'Calc - research target (12m)'!$G$68)+'Calc - research target (12m)'!$G$68*((($A17*F$12)-'Calc - research target (12m)'!$B$50-'Calc - research target (12m)'!$B$51+'Calc - research target (12m)'!$B$52)/'Calc - research target (12m)'!$B$53))/SUM('Calc - research target (12m)'!$G$67:$G$70)
A18: =Valuation!$B$71+(2) | B18: =((SUMPRODUCT('Calc - research target (12m)'!$F$67:$F$70,'Calc - research target (12m)'!$G$67:$G$70)-'Calc - research target (12m)'!$F$68*'Calc - research target (12m)'!$G$68)+'Calc - research target (12m)'!$G$68*((($A18*B$12)-'Calc - research target (12m)'!$B$50-'Calc - research target (12m)'!$B$51+'Calc - research target (12m)'!$B$52)/'Calc - research target (12m)'!$B$53))/SUM('Calc - research target (12m)'!$G$67:$G$70) | C18: =((SUMPRODUCT('Calc - research target (12m)'!$F$67:$F$70,'Calc - research target (12m)'!$G$67:$G$70)-'Calc - research target (12m)'!$F$68*'Calc - research target (12m)'!$G$68)+'Calc - research target (12m)'!$G$68*((($A18*C$12)-'Calc - research target (12m)'!$B$50-'Calc - research target (12m)'!$B$51+'Calc - research target (12m)'!$B$52)/'Calc - research target (12m)'!$B$53))/SUM('Calc - research target (12m)'!$G$67:$G$70) | D18: =((SUMPRODUCT('Calc - research target (12m)'!$F$67:$F$70,'Calc - research target (12m)'!$G$67:$G$70)-'Calc - research target (12m)'!$F$68*'Calc - research target (12m)'!$G$68)+'Calc - research target (12m)'!$G$68*((($A18*D$12)-'Calc - research target (12m)'!$B$50-'Calc - research target (12m)'!$B$51+'Calc - research target (12m)'!$B$52)/'Calc - research target (12m)'!$B$53))/SUM('Calc - research target (12m)'!$G$67:$G$70) | E18: =((SUMPRODUCT('Calc - research target (12m)'!$F$67:$F$70,'Calc - research target (12m)'!$G$67:$G$70)-'Calc - research target (12m)'!$F$68*'Calc - research target (12m)'!$G$68)+'Calc - research target (12m)'!$G$68*((($A18*E$12)-'Calc - research target (12m)'!$B$50-'Calc - research target (12m)'!$B$51+'Calc - research target (12m)'!$B$52)/'Calc - research target (12m)'!$B$53))/SUM('Calc - research target (12m)'!$G$67:$G$70) | F18: =((SUMPRODUCT('Calc - research target (12m)'!$F$67:$F$70,'Calc - research target (12m)'!$G$67:$G$70)-'Calc - research target (12m)'!$F$68*'Calc - research target (12m)'!$G$68)+'Calc - research target (12m)'!$G$68*((($A18*F$12)-'Calc - research target (12m)'!$B$50-'Calc - research target (12m)'!$B$51+'Calc - research target (12m)'!$B$52)/'Calc - research target (12m)'!$B$53))/SUM('Calc - research target (12m)'!$G$67:$G$70)
A19: =Valuation!$B$71+(3) | B19: =((SUMPRODUCT('Calc - research target (12m)'!$F$67:$F$70,'Calc - research target (12m)'!$G$67:$G$70)-'Calc - research target (12m)'!$F$68*'Calc - research target (12m)'!$G$68)+'Calc - research target (12m)'!$G$68*((($A19*B$12)-'Calc - research target (12m)'!$B$50-'Calc - research target (12m)'!$B$51+'Calc - research target (12m)'!$B$52)/'Calc - research target (12m)'!$B$53))/SUM('Calc - research target (12m)'!$G$67:$G$70) | C19: =((SUMPRODUCT('Calc - research target (12m)'!$F$67:$F$70,'Calc - research target (12m)'!$G$67:$G$70)-'Calc - research target (12m)'!$F$68*'Calc - research target (12m)'!$G$68)+'Calc - research target (12m)'!$G$68*((($A19*C$12)-'Calc - research target (12m)'!$B$50-'Calc - research target (12m)'!$B$51+'Calc - research target (12m)'!$B$52)/'Calc - research target (12m)'!$B$53))/SUM('Calc - research target (12m)'!$G$67:$G$70) | D19: =((SUMPRODUCT('Calc - research target (12m)'!$F$67:$F$70,'Calc - research target (12m)'!$G$67:$G$70)-'Calc - research target (12m)'!$F$68*'Calc - research target (12m)'!$G$68)+'Calc - research target (12m)'!$G$68*((($A19*D$12)-'Calc - research target (12m)'!$B$50-'Calc - research target (12m)'!$B$51+'Calc - research target (12m)'!$B$52)/'Calc - research target (12m)'!$B$53))/SUM('Calc - research target (12m)'!$G$67:$G$70) | E19: =((SUMPRODUCT('Calc - research target (12m)'!$F$67:$F$70,'Calc - research target (12m)'!$G$67:$G$70)-'Calc - research target (12m)'!$F$68*'Calc - research target (12m)'!$G$68)+'Calc - research target (12m)'!$G$68*((($A19*E$12)-'Calc - research target (12m)'!$B$50-'Calc - research target (12m)'!$B$51+'Calc - research target (12m)'!$B$52)/'Calc - research target (12m)'!$B$53))/SUM('Calc - research target (12m)'!$G$67:$G$70) | F19: =((SUMPRODUCT('Calc - research target (12m)'!$F$67:$F$70,'Calc - research target (12m)'!$G$67:$G$70)-'Calc - research target (12m)'!$F$68*'Calc - research target (12m)'!$G$68)+'Calc - research target (12m)'!$G$68*((($A19*F$12)-'Calc - research target (12m)'!$B$50-'Calc - research target (12m)'!$B$51+'Calc - research target (12m)'!$B$52)/'Calc - research target (12m)'!$B$53))/SUM('Calc - research target (12m)'!$G$67:$G$70)
A22: FY2027E diluted EPS: revenue growth change in every year (down) x EBIT margin change (across)
A23: Growth Δ \ margin Δ | B23: -0.01 | C23: -0.005 | D23: 0 | E23: 0.005 | F23: 0.01
A24: -0.02 | B24: =(Valuation!$B$91*(1+Model!E12+$A24)*(1+Model!F12+$A24)*(Model!F14+B$23)+Valuation!$B$92*(1+Model!E16+$A24)*(1+Model!F16+$A24)*(Model!F18+B$23)+Valuation!$B$93*(1+Model!E20+$A24)*(1+Model!F20+$A24)*(Model!F22+B$23)+Valuation!$B$94*(1+Model!E24+$A24)*(1+Model!F24+$A24)*(Model!F26+B$23)+Valuation!$B$95*(1+Model!E28+$A24)*(1+Model!F28+$A24)*(Model!F30+B$23)+Model!F33+Model!F45)*(1-Model!F75)/Model!F52 | C24: =(Valuation!$B$91*(1+Model!E12+$A24)*(1+Model!F12+$A24)*(Model!F14+C$23)+Valuation!$B$92*(1+Model!E16+$A24)*(1+Model!F16+$A24)*(Model!F18+C$23)+Valuation!$B$93*(1+Model!E20+$A24)*(1+Model!F20+$A24)*(Model!F22+C$23)+Valuation!$B$94*(1+Model!E24+$A24)*(1+Model!F24+$A24)*(Model!F26+C$23)+Valuation!$B$95*(1+Model!E28+$A24)*(1+Model!F28+$A24)*(Model!F30+C$23)+Model!F33+Model!F45)*(1-Model!F75)/Model!F52 | D24: =(Valuation!$B$91*(1+Model!E12+$A24)*(1+Model!F12+$A24)*(Model!F14+D$23)+Valuation!$B$92*(1+Model!E16+$A24)*(1+Model!F16+$A24)*(Model!F18+D$23)+Valuation!$B$93*(1+Model!E20+$A24)*(1+Model!F20+$A24)*(Model!F22+D$23)+Valuation!$B$94*(1+Model!E24+$A24)*(1+Model!F24+$A24)*(Model!F26+D$23)+Valuation!$B$95*(1+Model!E28+$A24)*(1+Model!F28+$A24)*(Model!F30+D$23)+Model!F33+Model!F45)*(1-Model!F75)/Model!F52 | E24: =(Valuation!$B$91*(1+Model!E12+$A24)*(1+Model!F12+$A24)*(Model!F14+E$23)+Valuation!$B$92*(1+Model!E16+$A24)*(1+Model!F16+$A24)*(Model!F18+E$23)+Valuation!$B$93*(1+Model!E20+$A24)*(1+Model!F20+$A24)*(Model!F22+E$23)+Valuation!$B$94*(1+Model!E24+$A24)*(1+Model!F24+$A24)*(Model!F26+E$23)+Valuation!$B$95*(1+Model!E28+$A24)*(1+Model!F28+$A24)*(Model!F30+E$23)+Model!F33+Model!F45)*(1-Model!F75)/Model!F52 | F24: =(Valuation!$B$91*(1+Model!E12+$A24)*(1+Model!F12+$A24)*(Model!F14+F$23)+Valuation!$B$92*(1+Model!E16+$A24)*(1+Model!F16+$A24)*(Model!F18+F$23)+Valuation!$B$93*(1+Model!E20+$A24)*(1+Model!F20+$A24)*(Model!F22+F$23)+Valuation!$B$94*(1+Model!E24+$A24)*(1+Model!F24+$A24)*(Model!F26+F$23)+Valuation!$B$95*(1+Model!E28+$A24)*(1+Model!F28+$A24)*(Model!F30+F$23)+Model!F33+Model!F45)*(1-Model!F75)/Model!F52
A25: -0.01 | B25: =(Valuation!$B$91*(1+Model!E12+$A25)*(1+Model!F12+$A25)*(Model!F14+B$23)+Valuation!$B$92*(1+Model!E16+$A25)*(1+Model!F16+$A25)*(Model!F18+B$23)+Valuation!$B$93*(1+Model!E20+$A25)*(1+Model!F20+$A25)*(Model!F22+B$23)+Valuation!$B$94*(1+Model!E24+$A25)*(1+Model!F24+$A25)*(Model!F26+B$23)+Valuation!$B$95*(1+Model!E28+$A25)*(1+Model!F28+$A25)*(Model!F30+B$23)+Model!F33+Model!F45)*(1-Model!F75)/Model!F52 | C25: =(Valuation!$B$91*(1+Model!E12+$A25)*(1+Model!F12+$A25)*(Model!F14+C$23)+Valuation!$B$92*(1+Model!E16+$A25)*(1+Model!F16+$A25)*(Model!F18+C$23)+Valuation!$B$93*(1+Model!E20+$A25)*(1+Model!F20+$A25)*(Model!F22+C$23)+Valuation!$B$94*(1+Model!E24+$A25)*(1+Model!F24+$A25)*(Model!F26+C$23)+Valuation!$B$95*(1+Model!E28+$A25)*(1+Model!F28+$A25)*(Model!F30+C$23)+Model!F33+Model!F45)*(1-Model!F75)/Model!F52 | D25: =(Valuation!$B$91*(1+Model!E12+$A25)*(1+Model!F12+$A25)*(Model!F14+D$23)+Valuation!$B$92*(1+Model!E16+$A25)*(1+Model!F16+$A25)*(Model!F18+D$23)+Valuation!$B$93*(1+Model!E20+$A25)*(1+Model!F20+$A25)*(Model!F22+D$23)+Valuation!$B$94*(1+Model!E24+$A25)*(1+Model!F24+$A25)*(Model!F26+D$23)+Valuation!$B$95*(1+Model!E28+$A25)*(1+Model!F28+$A25)*(Model!F30+D$23)+Model!F33+Model!F45)*(1-Model!F75)/Model!F52 | E25: =(Valuation!$B$91*(1+Model!E12+$A25)*(1+Model!F12+$A25)*(Model!F14+E$23)+Valuation!$B$92*(1+Model!E16+$A25)*(1+Model!F16+$A25)*(Model!F18+E$23)+Valuation!$B$93*(1+Model!E20+$A25)*(1+Model!F20+$A25)*(Model!F22+E$23)+Valuation!$B$94*(1+Model!E24+$A25)*(1+Model!F24+$A25)*(Model!F26+E$23)+Valuation!$B$95*(1+Model!E28+$A25)*(1+Model!F28+$A25)*(Model!F30+E$23)+Model!F33+Model!F45)*(1-Model!F75)/Model!F52 | F25: =(Valuation!$B$91*(1+Model!E12+$A25)*(1+Model!F12+$A25)*(Model!F14+F$23)+Valuation!$B$92*(1+Model!E16+$A25)*(1+Model!F16+$A25)*(Model!F18+F$23)+Valuation!$B$93*(1+Model!E20+$A25)*(1+Model!F20+$A25)*(Model!F22+F$23)+Valuation!$B$94*(1+Model!E24+$A25)*(1+Model!F24+$A25)*(Model!F26+F$23)+Valuation!$B$95*(1+Model!E28+$A25)*(1+Model!F28+$A25)*(Model!F30+F$23)+Model!F33+Model!F45)*(1-Model!F75)/Model!F52
A26: 0 | B26: =(Valuation!$B$91*(1+Model!E12+$A26)*(1+Model!F12+$A26)*(Model!F14+B$23)+Valuation!$B$92*(1+Model!E16+$A26)*(1+Model!F16+$A26)*(Model!F18+B$23)+Valuation!$B$93*(1+Model!E20+$A26)*(1+Model!F20+$A26)*(Model!F22+B$23)+Valuation!$B$94*(1+Model!E24+$A26)*(1+Model!F24+$A26)*(Model!F26+B$23)+Valuation!$B$95*(1+Model!E28+$A26)*(1+Model!F28+$A26)*(Model!F30+B$23)+Model!F33+Model!F45)*(1-Model!F75)/Model!F52 | C26: =(Valuation!$B$91*(1+Model!E12+$A26)*(1+Model!F12+$A26)*(Model!F14+C$23)+Valuation!$B$92*(1+Model!E16+$A26)*(1+Model!F16+$A26)*(Model!F18+C$23)+Valuation!$B$93*(1+Model!E20+$A26)*(1+Model!F20+$A26)*(Model!F22+C$23)+Valuation!$B$94*(1+Model!E24+$A26)*(1+Model!F24+$A26)*(Model!F26+C$23)+Valuation!$B$95*(1+Model!E28+$A26)*(1+Model!F28+$A26)*(Model!F30+C$23)+Model!F33+Model!F45)*(1-Model!F75)/Model!F52 | D26: =(Valuation!$B$91*(1+Model!E12+$A26)*(1+Model!F12+$A26)*(Model!F14+D$23)+Valuation!$B$92*(1+Model!E16+$A26)*(1+Model!F16+$A26)*(Model!F18+D$23)+Valuation!$B$93*(1+Model!E20+$A26)*(1+Model!F20+$A26)*(Model!F22+D$23)+Valuation!$B$94*(1+Model!E24+$A26)*(1+Model!F24+$A26)*(Model!F26+D$23)+Valuation!$B$95*(1+Model!E28+$A26)*(1+Model!F28+$A26)*(Model!F30+D$23)+Model!F33+Model!F45)*(1-Model!F75)/Model!F52 | E26: =(Valuation!$B$91*(1+Model!E12+$A26)*(1+Model!F12+$A26)*(Model!F14+E$23)+Valuation!$B$92*(1+Model!E16+$A26)*(1+Model!F16+$A26)*(Model!F18+E$23)+Valuation!$B$93*(1+Model!E20+$A26)*(1+Model!F20+$A26)*(Model!F22+E$23)+Valuation!$B$94*(1+Model!E24+$A26)*(1+Model!F24+$A26)*(Model!F26+E$23)+Valuation!$B$95*(1+Model!E28+$A26)*(1+Model!F28+$A26)*(Model!F30+E$23)+Model!F33+Model!F45)*(1-Model!F75)/Model!F52 | F26: =(Valuation!$B$91*(1+Model!E12+$A26)*(1+Model!F12+$A26)*(Model!F14+F$23)+Valuation!$B$92*(1+Model!E16+$A26)*(1+Model!F16+$A26)*(Model!F18+F$23)+Valuation!$B$93*(1+Model!E20+$A26)*(1+Model!F20+$A26)*(Model!F22+F$23)+Valuation!$B$94*(1+Model!E24+$A26)*(1+Model!F24+$A26)*(Model!F26+F$23)+Valuation!$B$95*(1+Model!E28+$A26)*(1+Model!F28+$A26)*(Model!F30+F$23)+Model!F33+Model!F45)*(1-Model!F75)/Model!F52
A27: 0.01 | B27: =(Valuation!$B$91*(1+Model!E12+$A27)*(1+Model!F12+$A27)*(Model!F14+B$23)+Valuation!$B$92*(1+Model!E16+$A27)*(1+Model!F16+$A27)*(Model!F18+B$23)+Valuation!$B$93*(1+Model!E20+$A27)*(1+Model!F20+$A27)*(Model!F22+B$23)+Valuation!$B$94*(1+Model!E24+$A27)*(1+Model!F24+$A27)*(Model!F26+B$23)+Valuation!$B$95*(1+Model!E28+$A27)*(1+Model!F28+$A27)*(Model!F30+B$23)+Model!F33+Model!F45)*(1-Model!F75)/Model!F52 | C27: =(Valuation!$B$91*(1+Model!E12+$A27)*(1+Model!F12+$A27)*(Model!F14+C$23)+Valuation!$B$92*(1+Model!E16+$A27)*(1+Model!F16+$A27)*(Model!F18+C$23)+Valuation!$B$93*(1+Model!E20+$A27)*(1+Model!F20+$A27)*(Model!F22+C$23)+Valuation!$B$94*(1+Model!E24+$A27)*(1+Model!F24+$A27)*(Model!F26+C$23)+Valuation!$B$95*(1+Model!E28+$A27)*(1+Model!F28+$A27)*(Model!F30+C$23)+Model!F33+Model!F45)*(1-Model!F75)/Model!F52 | D27: =(Valuation!$B$91*(1+Model!E12+$A27)*(1+Model!F12+$A27)*(Model!F14+D$23)+Valuation!$B$92*(1+Model!E16+$A27)*(1+Model!F16+$A27)*(Model!F18+D$23)+Valuation!$B$93*(1+Model!E20+$A27)*(1+Model!F20+$A27)*(Model!F22+D$23)+Valuation!$B$94*(1+Model!E24+$A27)*(1+Model!F24+$A27)*(Model!F26+D$23)+Valuation!$B$95*(1+Model!E28+$A27)*(1+Model!F28+$A27)*(Model!F30+D$23)+Model!F33+Model!F45)*(1-Model!F75)/Model!F52 | E27: =(Valuation!$B$91*(1+Model!E12+$A27)*(1+Model!F12+$A27)*(Model!F14+E$23)+Valuation!$B$92*(1+Model!E16+$A27)*(1+Model!F16+$A27)*(Model!F18+E$23)+Valuation!$B$93*(1+Model!E20+$A27)*(1+Model!F20+$A27)*(Model!F22+E$23)+Valuation!$B$94*(1+Model!E24+$A27)*(1+Model!F24+$A27)*(Model!F26+E$23)+Valuation!$B$95*(1+Model!E28+$A27)*(1+Model!F28+$A27)*(Model!F30+E$23)+Model!F33+Model!F45)*(1-Model!F75)/Model!F52 | F27: =(Valuation!$B$91*(1+Model!E12+$A27)*(1+Model!F12+$A27)*(Model!F14+F$23)+Valuation!$B$92*(1+Model!E16+$A27)*(1+Model!F16+$A27)*(Model!F18+F$23)+Valuation!$B$93*(1+Model!E20+$A27)*(1+Model!F20+$A27)*(Model!F22+F$23)+Valuation!$B$94*(1+Model!E24+$A27)*(1+Model!F24+$A27)*(Model!F26+F$23)+Valuation!$B$95*(1+Model!E28+$A27)*(1+Model!F28+$A27)*(Model!F30+F$23)+Model!F33+Model!F45)*(1-Model!F75)/Model!F52
A28: 0.02 | B28: =(Valuation!$B$91*(1+Model!E12+$A28)*(1+Model!F12+$A28)*(Model!F14+B$23)+Valuation!$B$92*(1+Model!E16+$A28)*(1+Model!F16+$A28)*(Model!F18+B$23)+Valuation!$B$93*(1+Model!E20+$A28)*(1+Model!F20+$A28)*(Model!F22+B$23)+Valuation!$B$94*(1+Model!E24+$A28)*(1+Model!F24+$A28)*(Model!F26+B$23)+Valuation!$B$95*(1+Model!E28+$A28)*(1+Model!F28+$A28)*(Model!F30+B$23)+Model!F33+Model!F45)*(1-Model!F75)/Model!F52 | C28: =(Valuation!$B$91*(1+Model!E12+$A28)*(1+Model!F12+$A28)*(Model!F14+C$23)+Valuation!$B$92*(1+Model!E16+$A28)*(1+Model!F16+$A28)*(Model!F18+C$23)+Valuation!$B$93*(1+Model!E20+$A28)*(1+Model!F20+$A28)*(Model!F22+C$23)+Valuation!$B$94*(1+Model!E24+$A28)*(1+Model!F24+$A28)*(Model!F26+C$23)+Valuation!$B$95*(1+Model!E28+$A28)*(1+Model!F28+$A28)*(Model!F30+C$23)+Model!F33+Model!F45)*(1-Model!F75)/Model!F52 | D28: =(Valuation!$B$91*(1+Model!E12+$A28)*(1+Model!F12+$A28)*(Model!F14+D$23)+Valuation!$B$92*(1+Model!E16+$A28)*(1+Model!F16+$A28)*(Model!F18+D$23)+Valuation!$B$93*(1+Model!E20+$A28)*(1+Model!F20+$A28)*(Model!F22+D$23)+Valuation!$B$94*(1+Model!E24+$A28)*(1+Model!F24+$A28)*(Model!F26+D$23)+Valuation!$B$95*(1+Model!E28+$A28)*(1+Model!F28+$A28)*(Model!F30+D$23)+Model!F33+Model!F45)*(1-Model!F75)/Model!F52 | E28: =(Valuation!$B$91*(1+Model!E12+$A28)*(1+Model!F12+$A28)*(Model!F14+E$23)+Valuation!$B$92*(1+Model!E16+$A28)*(1+Model!F16+$A28)*(Model!F18+E$23)+Valuation!$B$93*(1+Model!E20+$A28)*(1+Model!F20+$A28)*(Model!F22+E$23)+Valuation!$B$94*(1+Model!E24+$A28)*(1+Model!F24+$A28)*(Model!F26+E$23)+Valuation!$B$95*(1+Model!E28+$A28)*(1+Model!F28+$A28)*(Model!F30+E$23)+Model!F33+Model!F45)*(1-Model!F75)/Model!F52 | F28: =(Valuation!$B$91*(1+Model!E12+$A28)*(1+Model!F12+$A28)*(Model!F14+F$23)+Valuation!$B$92*(1+Model!E16+$A28)*(1+Model!F16+$A28)*(Model!F18+F$23)+Valuation!$B$93*(1+Model!E20+$A28)*(1+Model!F20+$A28)*(Model!F22+F$23)+Valuation!$B$94*(1+Model!E24+$A28)*(1+Model!F24+$A28)*(Model!F26+F$23)+Valuation!$B$95*(1+Model!E28+$A28)*(1+Model!F28+$A28)*(Model!F30+F$23)+Model!F33+Model!F45)*(1-Model!F75)/Model!F52
A30: Net interest and the share count are held at the base case in table 3.

Sheet Distribution
A1: T: 12-month distribution (mix of lognormals around each scenario value)
A3: Scenario | B3: Probability | C3: Value at target date | D3: Story
A4: bear | B4: =Valuation!B86 | C4: ='Calc - bear'!$F$71 | D4: =Valuation!J86
A5: base | B5: =Valuation!B87 | C5: ='Calc - base'!$F$71 | D5: =Valuation!J87
A6: bull | B6: =Valuation!B88 | C6: ='Calc - bull'!$F$71 | D6: =Valuation!J88
A8: Probabilities sum to | B8: =SUM(B4:B6)
A9: Spread within each scenario | B9: =Valuation!$B$67
A10: Probability-weighted mean | B10: =($B$4*$C$4+$B$5*$C$5+$B$6*$C$6)*EXP($B$9^2/2)
A12: Quantile | B12: Price
A13: Median (model target) | B13: =SQRT(A60*B60)
A14: 10th percentile | B14: =SQRT(D60*E60)
A15: 25th percentile | B15: =SQRT(G60*H60)
A16: 75th percentile | B16: =SQRT(J60*K60)
A17: 90th percentile | B17: =SQRT(M60*N60)
A19: Each quantile solved by bisection (block: low, high, probability above the midpoint)
A20: Median (model target): low | B20: high | C20: P(above mid) | D20: 10th percentile: low | E20: high | F20: P(above mid) | G20: 25th percentile: low | H20: high | I20: P(above mid) | J20: 75th percentile: low | K20: high | L20: P(above mid) | M20: 90th percentile: low | N20: high | O20: P(above mid)
A21: =MIN($C$4,$C$5,$C$6)*0.2 | B21: =MAX($C$4,$C$5,$C$6)*4 | C21: =SUMPRODUCT($B$4:$B$6,1-NORMSDIST((LN(SQRT(A21*B21))-LN($C$4:$C$6))/$B$9)) | D21: =MIN($C$4,$C$5,$C$6)*0.2 | E21: =MAX($C$4,$C$5,$C$6)*4 | F21: =SUMPRODUCT($B$4:$B$6,1-NORMSDIST((LN(SQRT(D21*E21))-LN($C$4:$C$6))/$B$9)) | G21: =MIN($C$4,$C$5,$C$6)*0.2 | H21: =MAX($C$4,$C$5,$C$6)*4 | I21: =SUMPRODUCT($B$4:$B$6,1-NORMSDIST((LN(SQRT(G21*H21))-LN($C$4:$C$6))/$B$9)) | J21: =MIN($C$4,$C$5,$C$6)*0.2 | K21: =MAX($C$4,$C$5,$C$6)*4 | L21: =SUMPRODUCT($B$4:$B$6,1-NORMSDIST((LN(SQRT(J21*K21))-LN($C$4:$C$6))/$B$9)) | M21: =MIN($C$4,$C$5,$C$6)*0.2 | N21: =MAX($C$4,$C$5,$C$6)*4 | O21: =SUMPRODUCT($B$4:$B$6,1-NORMSDIST((LN(SQRT(M21*N21))-LN($C$4:$C$6))/$B$9))
A22: =IF(C21>0.5,SQRT(A21*B21),A21) | B22: =IF(C21>0.5,B21,SQRT(A21*B21)) | C22: =SUMPRODUCT($B$4:$B$6,1-NORMSDIST((LN(SQRT(A22*B22))-LN($C$4:$C$6))/$B$9)) | D22: =IF(F21>0.9,SQRT(D21*E21),D21) | E22: =IF(F21>0.9,E21,SQRT(D21*E21)) | F22: =SUMPRODUCT($B$4:$B$6,1-NORMSDIST((LN(SQRT(D22*E22))-LN($C$4:$C$6))/$B$9)) | G22: =IF(I21>0.75,SQRT(G21*H21),G21) | H22: =IF(I21>0.75,H21,SQRT(G21*H21)) | I22: =SUMPRODUCT($B$4:$B$6,1-NORMSDIST((LN(SQRT(G22*H22))-LN($C$4:$C$6))/$B$9)) | J22: =IF(L21>0.25,SQRT(J21*K21),J21) | K22: =IF(L21>0.25,K21,SQRT(J21*K21)) | L22: =SUMPRODUCT($B$4:$B$6,1-NORMSDIST((LN(SQRT(J22*K22))-LN($C$4:$C$6))/$B$9)) | M22: =IF(O21>0.09999999999999998,SQRT(M21*N21),M21) | N22: =IF(O21>0.09999999999999998,N21,SQRT(M21*N21)) | O22: =SUMPRODUCT($B$4:$B$6,1-NORMSDIST((LN(SQRT(M22*N22))-LN($C$4:$C$6))/$B$9))
A23: =IF(C22>0.5,SQRT(A22*B22),A22) | B23: =IF(C22>0.5,B22,SQRT(A22*B22)) | C23: =SUMPRODUCT($B$4:$B$6,1-NORMSDIST((LN(SQRT(A23*B23))-LN($C$4:$C$6))/$B$9)) | D23: =IF(F22>0.9,SQRT(D22*E22),D22) | E23: =IF(F22>0.9,E22,SQRT(D22*E22)) | F23: =SUMPRODUCT($B$4:$B$6,1-NORMSDIST((LN(SQRT(D23*E23))-LN($C$4:$C$6))/$B$9)) | G23: =IF(I22>0.75,SQRT(G22*H22),G22) | H23: =IF(I22>0.75,H22,SQRT(G22*H22)) | I23: =SUMPRODUCT($B$4:$B$6,1-NORMSDIST((LN(SQRT(G23*H23))-LN($C$4:$C$6))/$B$9)) | J23: =IF(L22>0.25,SQRT(J22*K22),J22) | K23: =IF(L22>0.25,K22,SQRT(J22*K22)) | L23: =SUMPRODUCT($B$4:$B$6,1-NORMSDIST((LN(SQRT(J23*K23))-LN($C$4:$C$6))/$B$9)) | M23: =IF(O22>0.09999999999999998,SQRT(M22*N22),M22) | N23: =IF(O22>0.09999999999999998,N22,SQRT(M22*N22)) | O23: =SUMPRODUCT($B$4:$B$6,1-NORMSDIST((LN(SQRT(M23*N23))-LN($C$4:$C$6))/$B$9))
A24: =IF(C23>0.5,SQRT(A23*B23),A23) | B24: =IF(C23>0.5,B23,SQRT(A23*B23)) | C24: =SUMPRODUCT($B$4:$B$6,1-NORMSDIST((LN(SQRT(A24*B24))-LN($C$4:$C$6))/$B$9)) | D24: =IF(F23>0.9,SQRT(D23*E23),D23) | E24: =IF(F23>0.9,E23,SQRT(D23*E23)) | F24: =SUMPRODUCT($B$4:$B$6,1-NORMSDIST((LN(SQRT(D24*E24))-LN($C$4:$C$6))/$B$9)) | G24: =IF(I23>0.75,SQRT(G23*H23),G23) | H24: =IF(I23>0.75,H23,SQRT(G23*H23)) | I24: =SUMPRODUCT($B$4:$B$6,1-NORMSDIST((LN(SQRT(G24*H24))-LN($C$4:$C$6))/$B$9)) | J24: =IF(L23>0.25,SQRT(J23*K23),J23) | K24: =IF(L23>0.25,K23,SQRT(J23*K23)) | L24: =SUMPRODUCT($B$4:$B$6,1-NORMSDIST((LN(SQRT(J24*K24))-LN($C$4:$C$6))/$B$9)) | M24: =IF(O23>0.09999999999999998,SQRT(M23*N23),M23) | N24: =IF(O23>0.09999999999999998,N23,SQRT(M23*N23)) | O24: =SUMPRODUCT($B$4:$B$6,1-NORMSDIST((LN(SQRT(M24*N24))-LN($C$4:$C$6))/$B$9))
A25: =IF(C24>0.5,SQRT(A24*B24),A24) | B25: =IF(C24>0.5,B24,SQRT(A24*B24)) | C25: =SUMPRODUCT($B$4:$B$6,1-NORMSDIST((LN(SQRT(A25*B25))-LN($C$4:$C$6))/$B$9)) | D25: =IF(F24>0.9,SQRT(D24*E24),D24) | E25: =IF(F24>0.9,E24,SQRT(D24*E24)) | F25: =SUMPRODUCT($B$4:$B$6,1-NORMSDIST((LN(SQRT(D25*E25))-LN($C$4:$C$6))/$B$9)) | G25: =IF(I24>0.75,SQRT(G24*H24),G24) | H25: =IF(I24>0.75,H24,SQRT(G24*H24)) | I25: =SUMPRODUCT($B$4:$B$6,1-NORMSDIST((LN(SQRT(G25*H25))-LN($C$4:$C$6))/$B$9)) | J25: =IF(L24>0.25,SQRT(J24*K24),J24) | K25: =IF(L24>0.25,K24,SQRT(J24*K24)) | L25: =SUMPRODUCT($B$4:$B$6,1-NORMSDIST((LN(SQRT(J25*K25))-LN($C$4:$C$6))/$B$9)) | M25: =IF(O24>0.09999999999999998,SQRT(M24*N24),M24) | N25: =IF(O24>0.09999999999999998,N24,SQRT(M24*N24)) | O25: =SUMPRODUCT($B$4:$B$6,1-NORMSDIST((LN(SQRT(M25*N25))-LN($C$4:$C$6))/$B$9))
A26: =IF(C25>0.5,SQRT(A25*B25),A25) | B26: =IF(C25>0.5,B25,SQRT(A25*B25)) | C26: =SUMPRODUCT($B$4:$B$6,1-NORMSDIST((LN(SQRT(A26*B26))-LN($C$4:$C$6))/$B$9)) | D26: =IF(F25>0.9,SQRT(D25*E25),D25) | E26: =IF(F25>0.9,E25,SQRT(D25*E25)) | F26: =SUMPRODUCT($B$4:$B$6,1-NORMSDIST((LN(SQRT(D26*E26))-LN($C$4:$C$6))/$B$9)) | G26: =IF(I25>0.75,SQRT(G25*H25),G25) | H26: =IF(I25>0.75,H25,SQRT(G25*H25)) | I26: =SUMPRODUCT($B$4:$B$6,1-NORMSDIST((LN(SQRT(G26*H26))-LN($C$4:$C$6))/$B$9)) | J26: =IF(L25>0.25,SQRT(J25*K25),J25) | K26: =IF(L25>0.25,K25,SQRT(J25*K25)) | L26: =SUMPRODUCT($B$4:$B$6,1-NORMSDIST((LN(SQRT(J26*K26))-LN($C$4:$C$6))/$B$9)) | M26: =IF(O25>0.09999999999999998,SQRT(M25*N25),M25) | N26: =IF(O25>0.09999999999999998,N25,SQRT(M25*N25)) | O26: =SUMPRODUCT($B$4:$B$6,1-NORMSDIST((LN(SQRT(M26*N26))-LN($C$4:$C$6))/$B$9))
A27: =IF(C26>0.5,SQRT(A26*B26),A26) | B27: =IF(C26>0.5,B26,SQRT(A26*B26)) | C27: =SUMPRODUCT($B$4:$B$6,1-NORMSDIST((LN(SQRT(A27*B27))-LN($C$4:$C$6))/$B$9)) | D27: =IF(F26>0.9,SQRT(D26*E26),D26) | E27: =IF(F26>0.9,E26,SQRT(D26*E26)) | F27: =SUMPRODUCT($B$4:$B$6,1-NORMSDIST((LN(SQRT(D27*E27))-LN($C$4:$C$6))/$B$9)) | G27: =IF(I26>0.75,SQRT(G26*H26),G26) | H27: =IF(I26>0.75,H26,SQRT(G26*H26)) | I27: =SUMPRODUCT($B$4:$B$6,1-NORMSDIST((LN(SQRT(G27*H27))-LN($C$4:$C$6))/$B$9)) | J27: =IF(L26>0.25,SQRT(J26*K26),J26) | K27: =IF(L26>0.25,K26,SQRT(J26*K26)) | L27: =SUMPRODUCT($B$4:$B$6,1-NORMSDIST((LN(SQRT(J27*K27))-LN($C$4:$C$6))/$B$9)) | M27: =IF(O26>0.09999999999999998,SQRT(M26*N26),M26) | N27: =IF(O26>0.09999999999999998,N26,SQRT(M26*N26)) | O27: =SUMPRODUCT($B$4:$B$6,1-NORMSDIST((LN(SQRT(M27*N27))-LN($C$4:$C$6))/$B$9))
A28: =IF(C27>0.5,SQRT(A27*B27),A27) | B28: =IF(C27>0.5,B27,SQRT(A27*B27)) | C28: =SUMPRODUCT($B$4:$B$6,1-NORMSDIST((LN(SQRT(A28*B28))-LN($C$4:$C$6))/$B$9)) | D28: =IF(F27>0.9,SQRT(D27*E27),D27) | E28: =IF(F27>0.9,E27,SQRT(D27*E27)) | F28: =SUMPRODUCT($B$4:$B$6,1-NORMSDIST((LN(SQRT(D28*E28))-LN($C$4:$C$6))/$B$9)) | G28: =IF(I27>0.75,SQRT(G27*H27),G27) | H28: =IF(I27>0.75,H27,SQRT(G27*H27)) | I28: =SUMPRODUCT($B$4:$B$6,1-NORMSDIST((LN(SQRT(G28*H28))-LN($C$4:$C$6))/$B$9)) | J28: =IF(L27>0.25,SQRT(J27*K27),J27) | K28: =IF(L27>0.25,K27,SQRT(J27*K27)) | L28: =SUMPRODUCT($B$4:$B$6,1-NORMSDIST((LN(SQRT(J28*K28))-LN($C$4:$C$6))/$B$9)) | M28: =IF(O27>0.09999999999999998,SQRT(M27*N27),M27) | N28: =IF(O27>0.09999999999999998,N27,SQRT(M27*N27)) | O28: =SUMPRODUCT($B$4:$B$6,1-NORMSDIST((LN(SQRT(M28*N28))-LN($C$4:$C$6))/$B$9))
A29: =IF(C28>0.5,SQRT(A28*B28),A28) | B29: =IF(C28>0.5,B28,SQRT(A28*B28)) | C29: =SUMPRODUCT($B$4:$B$6,1-NORMSDIST((LN(SQRT(A29*B29))-LN($C$4:$C$6))/$B$9)) | D29: =IF(F28>0.9,SQRT(D28*E28),D28) | E29: =IF(F28>0.9,E28,SQRT(D28*E28)) | F29: =SUMPRODUCT($B$4:$B$6,1-NORMSDIST((LN(SQRT(D29*E29))-LN($C$4:$C$6))/$B$9)) | G29: =IF(I28>0.75,SQRT(G28*H28),G28) | H29: =IF(I28>0.75,H28,SQRT(G28*H28)) | I29: =SUMPRODUCT($B$4:$B$6,1-NORMSDIST((LN(SQRT(G29*H29))-LN($C$4:$C$6))/$B$9)) | J29: =IF(L28>0.25,SQRT(J28*K28),J28) | K29: =IF(L28>0.25,K28,SQRT(J28*K28)) | L29: =SUMPRODUCT($B$4:$B$6,1-NORMSDIST((LN(SQRT(J29*K29))-LN($C$4:$C$6))/$B$9)) | M29: =IF(O28>0.09999999999999998,SQRT(M28*N28),M28) | N29: =IF(O28>0.09999999999999998,N28,SQRT(M28*N28)) | O29: =SUMPRODUCT($B$4:$B$6,1-NORMSDIST((LN(SQRT(M29*N29))-LN($C$4:$C$6))/$B$9))
A30: =IF(C29>0.5,SQRT(A29*B29),A29) | B30: =IF(C29>0.5,B29,SQRT(A29*B29)) | C30: =SUMPRODUCT($B$4:$B$6,1-NORMSDIST((LN(SQRT(A30*B30))-LN($C$4:$C$6))/$B$9)) | D30: =IF(F29>0.9,SQRT(D29*E29),D29) | E30: =IF(F29>0.9,E29,SQRT(D29*E29)) | F30: =SUMPRODUCT($B$4:$B$6,1-NORMSDIST((LN(SQRT(D30*E30))-LN($C$4:$C$6))/$B$9)) | G30: =IF(I29>0.75,SQRT(G29*H29),G29) | H30: =IF(I29>0.75,H29,SQRT(G29*H29)) | I30: =SUMPRODUCT($B$4:$B$6,1-NORMSDIST((LN(SQRT(G30*H30))-LN($C$4:$C$6))/$B$9)) | J30: =IF(L29>0.25,SQRT(J29*K29),J29) | K30: =IF(L29>0.25,K29,SQRT(J29*K29)) | L30: =SUMPRODUCT($B$4:$B$6,1-NORMSDIST((LN(SQRT(J30*K30))-LN($C$4:$C$6))/$B$9)) | M30: =IF(O29>0.09999999999999998,SQRT(M29*N29),M29) | N30: =IF(O29>0.09999999999999998,N29,SQRT(M29*N29)) | O30: =SUMPRODUCT($B$4:$B$6,1-NORMSDIST((LN(SQRT(M30*N30))-LN($C$4:$C$6))/$B$9))
A31: =IF(C30>0.5,SQRT(A30*B30),A30) | B31: =IF(C30>0.5,B30,SQRT(A30*B30)) | C31: =SUMPRODUCT($B$4:$B$6,1-NORMSDIST((LN(SQRT(A31*B31))-LN($C$4:$C$6))/$B$9)) | D31: =IF(F30>0.9,SQRT(D30*E30),D30) | E31: =IF(F30>0.9,E30,SQRT(D30*E30)) | F31: =SUMPRODUCT($B$4:$B$6,1-NORMSDIST((LN(SQRT(D31*E31))-LN($C$4:$C$6))/$B$9)) | G31: =IF(I30>0.75,SQRT(G30*H30),G30) | H31: =IF(I30>0.75,H30,SQRT(G30*H30)) | I31: =SUMPRODUCT($B$4:$B$6,1-NORMSDIST((LN(SQRT(G31*H31))-LN($C$4:$C$6))/$B$9)) | J31: =IF(L30>0.25,SQRT(J30*K30),J30) | K31: =IF(L30>0.25,K30,SQRT(J30*K30)) | L31: =SUMPRODUCT($B$4:$B$6,1-NORMSDIST((LN(SQRT(J31*K31))-LN($C$4:$C$6))/$B$9)) | M31: =IF(O30>0.09999999999999998,SQRT(M30*N30),M30) | N31: =IF(O30>0.09999999999999998,N30,SQRT(M30*N30)) | O31: =SUMPRODUCT($B$4:$B$6,1-NORMSDIST((LN(SQRT(M31*N31))-LN($C$4:$C$6))/$B$9))
A32: =IF(C31>0.5,SQRT(A31*B31),A31) | B32: =IF(C31>0.5,B31,SQRT(A31*B31)) | C32: =SUMPRODUCT($B$4:$B$6,1-NORMSDIST((LN(SQRT(A32*B32))-LN($C$4:$C$6))/$B$9)) | D32: =IF(F31>0.9,SQRT(D31*E31),D31) | E32: =IF(F31>0.9,E31,SQRT(D31*E31)) | F32: =SUMPRODUCT($B$4:$B$6,1-NORMSDIST((LN(SQRT(D32*E32))-LN($C$4:$C$6))/$B$9)) | G32: =IF(I31>0.75,SQRT(G31*H31),G31) | H32: =IF(I31>0.75,H31,SQRT(G31*H31)) | I32: =SUMPRODUCT($B$4:$B$6,1-NORMSDIST((LN(SQRT(G32*H32))-LN($C$4:$C$6))/$B$9)) | J32: =IF(L31>0.25,SQRT(J31*K31),J31) | K32: =IF(L31>0.25,K31,SQRT(J31*K31)) | L32: =SUMPRODUCT($B$4:$B$6,1-NORMSDIST((LN(SQRT(J32*K32))-LN($C$4:$C$6))/$B$9)) | M32: =IF(O31>0.09999999999999998,SQRT(M31*N31),M31) | N32: =IF(O31>0.09999999999999998,N31,SQRT(M31*N31)) | O32: =SUMPRODUCT($B$4:$B$6,1-NORMSDIST((LN(SQRT(M32*N32))-LN($C$4:$C$6))/$B$9))
A33: =IF(C32>0.5,SQRT(A32*B32),A32) | B33: =IF(C32>0.5,B32,SQRT(A32*B32)) | C33: =SUMPRODUCT($B$4:$B$6,1-NORMSDIST((LN(SQRT(A33*B33))-LN($C$4:$C$6))/$B$9)) | D33: =IF(F32>0.9,SQRT(D32*E32),D32) | E33: =IF(F32>0.9,E32,SQRT(D32*E32)) | F33: =SUMPRODUCT($B$4:$B$6,1-NORMSDIST((LN(SQRT(D33*E33))-LN($C$4:$C$6))/$B$9)) | G33: =IF(I32>0.75,SQRT(G32*H32),G32) | H33: =IF(I32>0.75,H32,SQRT(G32*H32)) | I33: =SUMPRODUCT($B$4:$B$6,1-NORMSDIST((LN(SQRT(G33*H33))-LN($C$4:$C$6))/$B$9)) | J33: =IF(L32>0.25,SQRT(J32*K32),J32) | K33: =IF(L32>0.25,K32,SQRT(J32*K32)) | L33: =SUMPRODUCT($B$4:$B$6,1-NORMSDIST((LN(SQRT(J33*K33))-LN($C$4:$C$6))/$B$9)) | M33: =IF(O32>0.09999999999999998,SQRT(M32*N32),M32) | N33: =IF(O32>0.09999999999999998,N32,SQRT(M32*N32)) | O33: =SUMPRODUCT($B$4:$B$6,1-NORMSDIST((LN(SQRT(M33*N33))-LN($C$4:$C$6))/$B$9))
... A60: =IF(C59>0.5,SQRT(A59*B59),A59) | B60: =IF(C59>0.5,B59,SQRT(A59*B59)) | C60: =SUMPRODUCT($B$4:$B$6,1-NORMSDIST((LN(SQRT(A60*B60))-LN($C$4:$C$6))/$B$9)) | D60: =IF(F59>0.9,SQRT(D59*E59),D59) | E60: =IF(F59>0.9,E59,SQRT(D59*E59)) | F60: =SUMPRODUCT($B$4:$B$6,1-NORMSDIST((LN(SQRT(D60*E60))-LN($C$4:$C$6))/$B$9)) | G60: =IF(I59>0.75,SQRT(G59*H59),G59) | H60: =IF(I59>0.75,H59,SQRT(G59*H59)) | I60: =SUMPRODUCT($B$4:$B$6,1-NORMSDIST((LN(SQRT(G60*H60))-LN($C$4:$C$6))/$B$9)) | J60: =IF(L59>0.25,SQRT(J59*K59),J59) | K60: =IF(L59>0.25,K59,SQRT(J59*K59)) | L60: =SUMPRODUCT($B$4:$B$6,1-NORMSDIST((LN(SQRT(J60*K60))-LN($C$4:$C$6))/$B$9)) | M60: =IF(O59>0.09999999999999998,SQRT(M59*N59),M59) | N60: =IF(O59>0.09999999999999998,N59,SQRT(M59*N59)) | O60: =SUMPRODUCT($B$4:$B$6,1-NORMSDIST((LN(SQRT(M60*N60))-LN($C$4:$C$6))/$B$9))

Sheet Calc - research target (12m)
A1: T engine calculation: research target (12m) (reconciled set, no scenario deltas)
A2: Machinery behind the Valuation and Distribution tabs; drivers come from Model, assumptions from Valuation.
A4: Scenario Growth Δ | B4: 0
A5: Scenario Margin Δ | B5: 0
A6: Scenario Multiple Δ (turns) | B6: 0
A7: Scenario WACC Δ | B7: 0
A8: Scenario Multiple %Δ | B8: 0
A9: Scenario Stated EPS/FCF %Δ | B9: 0
A10: Scenario Custom %Δ | B10: 0
A12: WACC | B12: =Valuation!$B$52+B7
A13: Years from last FY end to target date | B13: =(Valuation!$B$46-Valuation!$B$50)/365.25
A14: Years from last FY end to balance date | B14: =(Valuation!$B$56-Valuation!$B$50)/365.25
A15: Years from last FY end to share count date | B15: =(Valuation!$B$62-Valuation!$B$50)/365.25
A16: Projected years | B16: 3
A18: Projection | B18: Base | C18: =Model!E5 | D18: =Model!F5 | E18: =Model!G5
A19: Year index | B19: 0 | C19: 1 | D19: 2 | E19: 3
A20: Period end | C20: =Valuation!$B$50+ROUND(365.25*C19,0) | D20: =Valuation!$B$50+ROUND(365.25*D19,0) | E20: =Valuation!$B$50+ROUND(365.25*E19,0)
A21: Revenue growth | C21: =C22/B22-1 | D21: =D22/C22-1 | E21: =E22/D22-1
A22: Revenue | B22: =Valuation!$B$51 | C22: =C151 | D22: =D151 | E22: =E151
A23: EBIT margin | C23: =C24/C22 | D23: =D24/D22 | E23: =E24/E22
A24: EBIT | C24: =C154 | D24: =D154 | E24: =E154
A25: Tax rate | C25: =Model!E75 | D25: =Model!F75 | E25: =Model!G75
A26: NOPAT | C26: =C24*(1-C25) | D26: =D24*(1-D25) | E26: =E24*(1-E25)
A27: D&A | C27: =C22*(Model!E76) | D27: =D22*(Model!F76) | E27: =E22*(Model!G76)
A28: Capex | C28: =C22*(Model!E77) | D28: =D22*(Model!F77) | E28: =E22*(Model!G77)
A29: Working capital increase | C29: =(Model!E78)*(C22-B22) | D29: =(Model!F78)*(D22-C22) | E29: =(Model!G78)*(E22-D22)
A30: Stock comp | C30: =C22*(Model!E79) | D30: =D22*(Model!F79) | E30: =E22*(Model!G79)
A31: Free cash flow to firm | C31: =C26+C27-C28-C29-IF(AND(Valuation!$B$48="adjusted",Valuation!$B$49="cost"),C30*(1-C25),0) | D31: =D26+D27-D28-D29-IF(AND(Valuation!$B$48="adjusted",Valuation!$B$49="cost"),D30*(1-D25),0) | E31: =E26+E27-E28-E29-IF(AND(Valuation!$B$48="adjusted",Valuation!$B$49="cost"),E30*(1-E25),0)
A32: EBITDA | C32: =C24+C27 | D32: =D24+D27 | E32: =E24+E27
A33: Adj. EBITDA | C33: =C24+C27+C22*(Model!E83) | D33: =D24+D27+D22*(Model!F83) | E33: =E24+E27+E22*(Model!G83)
A34: Shareholder returns + other uses | C34: =C22*Model!E81+Model!E80+Model!E82 | D34: =D22*Model!F81+Model!F80+Model!F82 | E34: =E22*Model!G81+Model!G80+Model!G82
A35: Share of year after target date | C35: =IF(C19<=$B$13,0,C19-MAX(C19-1,$B$13)) | D35: =IF(D19<=$B$13,0,D19-MAX(D19-1,$B$13)) | E35: =IF(E19<=$B$13,0,E19-MAX(E19-1,$B$13))
A36: PV at target date of FCFF | C36: =IF(C35=0,0,C31*C35/(1+$B$12)^(C19-$B$13)) | D36: =IF(D35=0,0,D31*D35/(1+$B$12)^(D19-$B$13)) | E36: =IF(E35=0,0,E31*E35/(1+$B$12)^(E19-$B$13))
A37: Overlap: balance date to target date | C37: =MAX(0,MIN(C19,$B$13)-MAX(C19-1,$B$14)) | D37: =MAX(0,MIN(D19,$B$13)-MAX(D19-1,$B$14)) | E37: =MAX(0,MIN(E19,$B$13)-MAX(E19-1,$B$14))
A38: NTM weight at target date | C38: =MAX(0,MIN(C19,$B$13+1)-MAX(C19-1,$B$13)) | D38: =MAX(0,MIN(D19,$B$13+1)-MAX(D19-1,$B$13)) | E38: =MAX(0,MIN(E19,$B$13+1)-MAX(E19-1,$B$13))
A39: LTM weight at target date | B39: =MAX(0,MIN(0,$B$13)-MAX(-1,$B$13-1)) | C39: =MAX(0,MIN(C19,$B$13)-MAX(C19-1,$B$13-1)) | D39: =MAX(0,MIN(D19,$B$13)-MAX(D19-1,$B$13-1)) | E39: =MAX(0,MIN(E19,$B$13)-MAX(E19-1,$B$13-1))
A41: Value at the target date
A42: PV of free cash flow after the target date | B42: =SUM($C$36:$E$36)
A43: Terminal value at final year | B43: =IF(Valuation!$B$53="exit_multiple",Valuation!$B$55*E32,E31*(1+Valuation!$B$54)/($B$12-Valuation!$B$54))
A44: PV of terminal value at target date | B44: =B43/(1+$B$12)^($B$16-$B$13)
A45: DCF enterprise value at target date | B45: =B42+B44
A46: Terminal value share of DCF | B46: =B44/B45
A47: Free cash flow earned, balance date to target date | B47: =SUMPRODUCT($C$37:$E$37,$C$31:$E$31)
A48: Shareholder returns + other uses paid | B48: =SUMPRODUCT($C$37:$E$37,$C$34:$E$34)
A49: Interest drag on net debt | B49: =Valuation!$B$59*(1-$C$25)*MAX(Valuation!$B$57,0)*MAX($B$13-$B$14,0)
A50: Net debt at target date | B50: =IF(Valuation!$B$60="",Valuation!$B$57-B47+B49+B48,Valuation!$B$60)
A51: Minority interests | B51: =Valuation!$B$58
A52: Adjustments (probability-weighted) | B52: =(Valuation!B79)*Valuation!C79+(Valuation!B80)*Valuation!C80+0
A53: Diluted shares at target date (M) | B53: =IF(Valuation!$B$64="",Valuation!$B$61*(1+Valuation!$B$63)^MAX($B$13-$B$15,0),Valuation!$B$64)
A54: After-tax interest on target-date net debt | B54: =Valuation!$B$59*(1-$C$25)*MAX(B50,0)
A55: Check: WACC vs terminal growth | B55: =IF(AND(Valuation!$B$53<>"exit_multiple",$B$12<=Valuation!$B$54+0.01),"WACC must exceed terminal growth by 1 point","ok")
A56: Check: projection length | B56: =IF(OR($B$13>=$B$16-1,$B$13+1>$B$16),"add projected years past the target date","ok")
A58: Metric at target date | B58: Next 12 months | C58: Last 12 months
A59: Revenue | B59: =SUMPRODUCT($C$38:$E$38,$C$22:$E$22) | C59: =SUMPRODUCT($C$39:$E$39,$C$22:$E$22)+$B$39*$B$22
A60: EBIT | B60: =SUMPRODUCT($C$38:$E$38,$C$24:$E$24) | C60: =SUMPRODUCT($C$39:$E$39,$C$24:$E$24)
A61: EBITDA | B61: =SUMPRODUCT($C$38:$E$38,$C$32:$E$32) | C61: =SUMPRODUCT($C$39:$E$39,$C$32:$E$32)
A62: Adj. EBITDA | B62: =SUMPRODUCT($C$38:$E$38,$C$33:$E$33) | C62: =SUMPRODUCT($C$39:$E$39,$C$33:$E$33)
A63: NOPAT | B63: =SUMPRODUCT($C$38:$E$38,$C$26:$E$26) | C63: =SUMPRODUCT($C$39:$E$39,$C$26:$E$26)
A64: Free cash flow to firm | B64: =SUMPRODUCT($C$38:$E$38,$C$31:$E$31) | C64: =SUMPRODUCT($C$39:$E$39,$C$31:$E$31)
A66: Valuation method | B66: Metric | C66: Multiple used | D66: Basis | E66: Metric at target date | F66: Value per share | G66: Weight | H66: Metric key | I66: Metric shown (stated per-share figure when used)
A67: DCF (cash flow to target date + terminal) | F67: =((B45)-$B$50-$B$51+$B$52)/$B$53 | G67: =Valuation!$B$65
A68: ="Multiple: "&Valuation!A71&" ("&Valuation!D71&")" | B68: =Valuation!A71 | C68: =IF(B68="FCF yield",(Valuation!B71)*(1-$B$8),(Valuation!B71)+IF(B68="EV/sales",0.1,1)*$B$6) | D68: =Valuation!D71 | E68: =IF(D68="ltm",CHOOSE(H68,$C$59,$C$60,$C$61,$C$62,$C$63,$C$64),CHOOSE(H68,$B$59,$B$60,$B$61,$B$62,$B$63,$B$64)) | F68: =IF(OR(B68="EV/EBITDA",B68="EV/sales",B68="EV/EBIT"),((C68*E68)-$B$50-$B$51+$B$52)/$B$53,IF(B68="P/E",IF(Valuation!F71<>"",C68*(Valuation!F71)*(1+$B$9),C68*(E68-$B$54)/$B$53),IF(Valuation!G71<>"",(Valuation!G71)*(1+$B$9)/C68,(E68-IF(Valuation!H71,$B$54,0))/C68/$B$53))+$B$52/$B$53) | G68: =Valuation!C71 | H68: =IF(B68="EV/sales",1,IF(B68="EV/EBIT",2,IF(B68="EV/EBITDA",IF(Valuation!E71="adjusted",4,3),IF(B68="P/E",5,6)))) | I68: =IF(AND(B68="P/E",Valuation!F71<>""),(Valuation!F71)*(1+$B$9),IF(AND(B68="FCF yield",Valuation!G71<>""),(Valuation!G71)*(1+$B$9),E68))
A69: ="Multiple: "&Valuation!A72&" ("&Valuation!D72&")" | B69: =Valuation!A72 | C69: =IF(B69="FCF yield",(Valuation!B72)*(1-$B$8),(Valuation!B72)+IF(B69="EV/sales",0.1,1)*$B$6) | D69: =Valuation!D72 | E69: =IF(D69="ltm",CHOOSE(H69,$C$59,$C$60,$C$61,$C$62,$C$63,$C$64),CHOOSE(H69,$B$59,$B$60,$B$61,$B$62,$B$63,$B$64)) | F69: =IF(OR(B69="EV/EBITDA",B69="EV/sales",B69="EV/EBIT"),((C69*E69)-$B$50-$B$51+$B$52)/$B$53,IF(B69="P/E",IF(Valuation!F72<>"",C69*(Valuation!F72)*(1+$B$9),C69*(E69-$B$54)/$B$53),IF(Valuation!G72<>"",(Valuation!G72)*(1+$B$9)/C69,(E69-IF(Valuation!H72,$B$54,0))/C69/$B$53))+$B$52/$B$53) | G69: =Valuation!C72 | H69: =IF(B69="EV/sales",1,IF(B69="EV/EBIT",2,IF(B69="EV/EBITDA",IF(Valuation!E72="adjusted",4,3),IF(B69="P/E",5,6)))) | I69: =IF(AND(B69="P/E",Valuation!F72<>""),(Valuation!F72)*(1+$B$9),IF(AND(B69="FCF yield",Valuation!G72<>""),(Valuation!G72)*(1+$B$9),E69))
A70: ="Multiple: "&Valuation!A73&" ("&Valuation!D73&")" | B70: =Valuation!A73 | C70: =IF(B70="FCF yield",(Valuation!B73)*(1-$B$8),(Valuation!B73)+IF(B70="EV/sales",0.1,1)*$B$6) | D70: =Valuation!D73 | E70: =IF(D70="ltm",CHOOSE(H70,$C$59,$C$60,$C$61,$C$62,$C$63,$C$64),CHOOSE(H70,$B$59,$B$60,$B$61,$B$62,$B$63,$B$64)) | F70: =IF(OR(B70="EV/EBITDA",B70="EV/sales",B70="EV/EBIT"),((C70*E70)-$B$50-$B$51+$B$52)/$B$53,IF(B70="P/E",IF(Valuation!F73<>"",C70*(Valuation!F73)*(1+$B$9),C70*(E70-$B$54)/$B$53),IF(Valuation!G73<>"",(Valuation!G73)*(1+$B$9)/C70,(E70-IF(Valuation!H73,$B$54,0))/C70/$B$53))+$B$52/$B$53) | G70: =Valuation!C73 | H70: =IF(B70="EV/sales",1,IF(B70="EV/EBIT",2,IF(B70="EV/EBITDA",IF(Valuation!E73="adjusted",4,3),IF(B70="P/E",5,6)))) | I70: =IF(AND(B70="P/E",Valuation!F73<>""),(Valuation!F73)*(1+$B$9),IF(AND(B70="FCF yield",Valuation!G73<>""),(Valuation!G73)*(1+$B$9),E70))
A71: Value per share at target date (weighted methods) | F71: =SUMPRODUCT(F67:F70,G67:G70)/SUM(G67:G70)
A129: Segment build (model_engine.seg_build): revenue and EBIT are the segment sums plus corporate EBIT
A130: Segment | B130: Base | C130: =Model!E5 | D130: =Model!F5 | E130: =Model!G5
A131: AC Wireless and Home: revenue growth | C131: =Model!E12+$B$4 | D131: =Model!F12+$B$4 | E131: =Model!G12+$B$4
A132: AC Wireless and Home: revenue | B132: =Valuation!$B$91 | C132: =B132*(1+C131) | D132: =C132*(1+D131) | E132: =D132*(1+E131)
A133: AC Wireless and Home: EBIT margin | C133: =Model!E14+$B$5 | D133: =Model!F14+$B$5 | E133: =Model!G14+$B$5
A134: AC Wireless and Home: EBIT | C134: =C132*C133 | D134: =D132*D133 | E134: =E132*E133
A135: AC Business Wireline and Other: revenue growth | C135: =Model!E16+$B$4 | D135: =Model!F16+$B$4 | E135: =Model!G16+$B$4
A136: AC Business Wireline and Other: revenue | B136: =Valuation!$B$92 | C136: =B136*(1+C135) | D136: =C136*(1+D135) | E136: =D136*(1+E135)
A137: AC Business Wireline and Other: EBIT margin | C137: =Model!E18+$B$5 | D137: =Model!F18+$B$5 | E137: =Model!G18+$B$5
A138: AC Business Wireline and Other: EBIT | C138: =C136*C137 | D138: =D136*D137 | E138: =E136*E137
A139: Legacy: revenue growth | C139: =Model!E20+$B$4 | D139: =Model!F20+$B$4 | E139: =Model!G20+$B$4
A140: Legacy: revenue | B140: =Valuation!$B$93 | C140: =B140*(1+C139) | D140: =C140*(1+D139) | E140: =D140*(1+E139)
A141: Legacy: EBIT margin | C141: =Model!E22+$B$5 | D141: =Model!F22+$B$5 | E141: =Model!G22+$B$5
A142: Legacy: EBIT | C142: =C140*C141 | D142: =D140*D141 | E142: =E140*E141
A143: Latin America: revenue growth | C143: =Model!E24+$B$4 | D143: =Model!F24+$B$4 | E143: =Model!G24+$B$4
A144: Latin America: revenue | B144: =Valuation!$B$94 | C144: =B144*(1+C143) | D144: =C144*(1+D143) | E144: =D144*(1+E143)
A145: Latin America: EBIT margin | C145: =Model!E26+$B$5 | D145: =Model!F26+$B$5 | E145: =Model!G26+$B$5
A146: Latin America: EBIT | C146: =C144*C145 | D146: =D144*D145 | E146: =E144*E145
A147: Corporate and Other: revenue growth | C147: =Model!E28+$B$4 | D147: =Model!F28+$B$4 | E147: =Model!G28+$B$4
A148: Corporate and Other: revenue | B148: =Valuation!$B$95 | C148: =B148*(1+C147) | D148: =C148*(1+D147) | E148: =D148*(1+E147)
A149: Corporate and Other: EBIT margin | C149: =Model!E30+$B$5 | D149: =Model!F30+$B$5 | E149: =Model!G30+$B$5
A150: Corporate and Other: EBIT | C150: =C148*C149 | D150: =D148*D149 | E150: =E148*E149
A151: Total segment revenue | C151: =C132+C136+C140+C144+C148 | D151: =D132+D136+D140+D144+D148 | E151: =E132+E136+E140+E144+E148
A152: Total segment EBIT | C152: =C134+C138+C142+C146+C150 | D152: =D134+D138+D142+D146+D150 | E152: =E134+E138+E142+E146+E150
A153: Corporate / unallocated EBIT | C153: =Model!E33 | D153: =Model!F33 | E153: =Model!G33
A154: EBIT (segments + corporate) | C154: =C152+C153 | D154: =D152+D153 | E154: =E152+E153

Sheet Calc - bear
A1: T engine calculation: bear scenario
A2: Machinery behind the Valuation and Distribution tabs; drivers come from Model, assumptions from Valuation.
A4: Scenario Growth Δ | B4: =N(Valuation!C86)
A5: Scenario Margin Δ | B5: =N(Valuation!D86)
A6: Scenario Multiple Δ (turns) | B6: =N(Valuation!E86)
A7: Scenario WACC Δ | B7: =N(Valuation!F86)
A8: Scenario Multiple %Δ | B8: =N(Valuation!G86)
A9: Scenario Stated EPS/FCF %Δ | B9: =N(Valuation!H86)
A10: Scenario Custom %Δ | B10: =N(Valuation!I86)
A12: WACC | B12: =Valuation!$B$52+B7
A13: Years from last FY end to target date | B13: =(Valuation!$B$46-Valuation!$B$50)/365.25
A14: Years from last FY end to balance date | B14: =(Valuation!$B$56-Valuation!$B$50)/365.25
A15: Years from last FY end to share count date | B15: =(Valuation!$B$62-Valuation!$B$50)/365.25
A16: Projected years | B16: 3
A18: Projection | B18: Base | C18: =Model!E5 | D18: =Model!F5 | E18: =Model!G5
A19: Year index | B19: 0 | C19: 1 | D19: 2 | E19: 3
A20: Period end | C20: =Valuation!$B$50+ROUND(365.25*C19,0) | D20: =Valuation!$B$50+ROUND(365.25*D19,0) | E20: =Valuation!$B$50+ROUND(365.25*E19,0)
A21: Revenue growth | C21: =C22/B22-1 | D21: =D22/C22-1 | E21: =E22/D22-1
A22: Revenue | B22: =Valuation!$B$51 | C22: =C151 | D22: =D151 | E22: =E151
A23: EBIT margin | C23: =C24/C22 | D23: =D24/D22 | E23: =E24/E22
A24: EBIT | C24: =C154 | D24: =D154 | E24: =E154
A25: Tax rate | C25: =Model!E75 | D25: =Model!F75 | E25: =Model!G75
A26: NOPAT | C26: =C24*(1-C25) | D26: =D24*(1-D25) | E26: =E24*(1-E25)
A27: D&A | C27: =C22*(Model!E76) | D27: =D22*(Model!F76) | E27: =E22*(Model!G76)
A28: Capex | C28: =C22*(Model!E77+$B$250) | D28: =D22*(Model!F77+$B$251) | E28: =E22*(Model!G77+$B$252)
A29: Working capital increase | C29: =(Model!E78)*(C22-B22) | D29: =(Model!F78)*(D22-C22) | E29: =(Model!G78)*(E22-D22)
A30: Stock comp | C30: =C22*(Model!E79) | D30: =D22*(Model!F79) | E30: =E22*(Model!G79)
A31: Free cash flow to firm | C31: =C26+C27-C28-C29-IF(AND(Valuation!$B$48="adjusted",Valuation!$B$49="cost"),C30*(1-C25),0) | D31: =D26+D27-D28-D29-IF(AND(Valuation!$B$48="adjusted",Valuation!$B$49="cost"),D30*(1-D25),0) | E31: =E26+E27-E28-E29-IF(AND(Valuation!$B$48="adjusted",Valuation!$B$49="cost"),E30*(1-E25),0)
A32: EBITDA | C32: =C24+C27 | D32: =D24+D27 | E32: =E24+E27
A33: Adj. EBITDA | C33: =C24+C27+C22*(Model!E83) | D33: =D24+D27+D22*(Model!F83) | E33: =E24+E27+E22*(Model!G83)
A34: Shareholder returns + other uses | C34: =C22*Model!E81+Model!E80+Model!E82 | D34: =D22*Model!F81+Model!F80+Model!F82 | E34: =E22*Model!G81+Model!G80+Model!G82
A35: Share of year after target date | C35: =IF(C19<=$B$13,0,C19-MAX(C19-1,$B$13)) | D35: =IF(D19<=$B$13,0,D19-MAX(D19-1,$B$13)) | E35: =IF(E19<=$B$13,0,E19-MAX(E19-1,$B$13))
A36: PV at target date of FCFF | C36: =IF(C35=0,0,C31*C35/(1+$B$12)^(C19-$B$13)) | D36: =IF(D35=0,0,D31*D35/(1+$B$12)^(D19-$B$13)) | E36: =IF(E35=0,0,E31*E35/(1+$B$12)^(E19-$B$13))
A37: Overlap: balance date to target date | C37: =MAX(0,MIN(C19,$B$13)-MAX(C19-1,$B$14)) | D37: =MAX(0,MIN(D19,$B$13)-MAX(D19-1,$B$14)) | E37: =MAX(0,MIN(E19,$B$13)-MAX(E19-1,$B$14))
A38: NTM weight at target date | C38: =MAX(0,MIN(C19,$B$13+1)-MAX(C19-1,$B$13)) | D38: =MAX(0,MIN(D19,$B$13+1)-MAX(D19-1,$B$13)) | E38: =MAX(0,MIN(E19,$B$13+1)-MAX(E19-1,$B$13))
A39: LTM weight at target date | B39: =MAX(0,MIN(0,$B$13)-MAX(-1,$B$13-1)) | C39: =MAX(0,MIN(C19,$B$13)-MAX(C19-1,$B$13-1)) | D39: =MAX(0,MIN(D19,$B$13)-MAX(D19-1,$B$13-1)) | E39: =MAX(0,MIN(E19,$B$13)-MAX(E19-1,$B$13-1))
A41: Value at the target date
A42: PV of free cash flow after the target date | B42: =SUM($C$36:$E$36)
A43: Terminal value at final year | B43: =IF(Valuation!$B$53="exit_multiple",Valuation!$B$55*E32,E31*(1+Valuation!$B$54)/($B$12-Valuation!$B$54))
A44: PV of terminal value at target date | B44: =B43/(1+$B$12)^($B$16-$B$13)
A45: DCF enterprise value at target date | B45: =B42+B44
A46: Terminal value share of DCF | B46: =B44/B45
A47: Free cash flow earned, balance date to target date | B47: =SUMPRODUCT($C$37:$E$37,$C$31:$E$31)
A48: Shareholder returns + other uses paid | B48: =SUMPRODUCT($C$37:$E$37,$C$34:$E$34)
A49: Interest drag on net debt | B49: =Valuation!$B$59*(1-$C$25)*MAX(Valuation!$B$57,0)*MAX($B$13-$B$14,0)
A50: Net debt at target date | B50: =IF(Valuation!$B$60="",Valuation!$B$57-B47+B49+B48,Valuation!$B$60)
A51: Minority interests | B51: =Valuation!$B$58
A52: Adjustments (probability-weighted) | B52: =(Valuation!B79)*Valuation!C79+(Valuation!B80)*Valuation!C80+0
A53: Diluted shares at target date (M) | B53: =IF(Valuation!$B$64="",Valuation!$B$61*(1+Valuation!$B$63)^MAX($B$13-$B$15,0),Valuation!$B$64)
A54: After-tax interest on target-date net debt | B54: =Valuation!$B$59*(1-$C$25)*MAX(B50,0)
A55: Check: WACC vs terminal growth | B55: =IF(AND(Valuation!$B$53<>"exit_multiple",$B$12<=Valuation!$B$54+0.01),"WACC must exceed terminal growth by 1 point","ok")
A56: Check: projection length | B56: =IF(OR($B$13>=$B$16-1,$B$13+1>$B$16),"add projected years past the target date","ok")
A58: Metric at target date | B58: Next 12 months | C58: Last 12 months
A59: Revenue | B59: =SUMPRODUCT($C$38:$E$38,$C$22:$E$22) | C59: =SUMPRODUCT($C$39:$E$39,$C$22:$E$22)+$B$39*$B$22
A60: EBIT | B60: =SUMPRODUCT($C$38:$E$38,$C$24:$E$24) | C60: =SUMPRODUCT($C$39:$E$39,$C$24:$E$24)
A61: EBITDA | B61: =SUMPRODUCT($C$38:$E$38,$C$32:$E$32) | C61: =SUMPRODUCT($C$39:$E$39,$C$32:$E$32)
A62: Adj. EBITDA | B62: =SUMPRODUCT($C$38:$E$38,$C$33:$E$33) | C62: =SUMPRODUCT($C$39:$E$39,$C$33:$E$33)
A63: NOPAT | B63: =SUMPRODUCT($C$38:$E$38,$C$26:$E$26) | C63: =SUMPRODUCT($C$39:$E$39,$C$26:$E$26)
A64: Free cash flow to firm | B64: =SUMPRODUCT($C$38:$E$38,$C$31:$E$31) | C64: =SUMPRODUCT($C$39:$E$39,$C$31:$E$31)
A66: Valuation method | B66: Metric | C66: Multiple used | D66: Basis | E66: Metric at target date | F66: Value per share | G66: Weight | H66: Metric key | I66: Metric shown (stated per-share figure when used)
A67: DCF (cash flow to target date + terminal) | F67: =((B45)-$B$50-$B$51+$B$52)/$B$53 | G67: =Valuation!$B$65
A68: ="Multiple: "&Valuation!A71&" ("&Valuation!D71&")" | B68: =Valuation!A71 | C68: =IF(B68="FCF yield",(Valuation!B71)*(1-$B$8),(Valuation!B71)+IF(B68="EV/sales",0.1,1)*$B$6) | D68: =Valuation!D71 | E68: =IF(D68="ltm",CHOOSE(H68,$C$59,$C$60,$C$61,$C$62,$C$63,$C$64),CHOOSE(H68,$B$59,$B$60,$B$61,$B$62,$B$63,$B$64)) | F68: =IF(OR(B68="EV/EBITDA",B68="EV/sales",B68="EV/EBIT"),((C68*E68)-$B$50-$B$51+$B$52)/$B$53,IF(B68="P/E",IF(Valuation!F71<>"",C68*(Valuation!F71)*(1+$B$9),C68*(E68-$B$54)/$B$53),IF(Valuation!G71<>"",(Valuation!G71)*(1+$B$9)/C68,(E68-IF(Valuation!H71,$B$54,0))/C68/$B$53))+$B$52/$B$53) | G68: =Valuation!C71 | H68: =IF(B68="EV/sales",1,IF(B68="EV/EBIT",2,IF(B68="EV/EBITDA",IF(Valuation!E71="adjusted",4,3),IF(B68="P/E",5,6)))) | I68: =IF(AND(B68="P/E",Valuation!F71<>""),(Valuation!F71)*(1+$B$9),IF(AND(B68="FCF yield",Valuation!G71<>""),(Valuation!G71)*(1+$B$9),E68))
A69: ="Multiple: "&Valuation!A72&" ("&Valuation!D72&")" | B69: =Valuation!A72 | C69: =IF(B69="FCF yield",(Valuation!B72)*(1-$B$8),(Valuation!B72)+IF(B69="EV/sales",0.1,1)*$B$6) | D69: =Valuation!D72 | E69: =IF(D69="ltm",CHOOSE(H69,$C$59,$C$60,$C$61,$C$62,$C$63,$C$64),CHOOSE(H69,$B$59,$B$60,$B$61,$B$62,$B$63,$B$64)) | F69: =IF(OR(B69="EV/EBITDA",B69="EV/sales",B69="EV/EBIT"),((C69*E69)-$B$50-$B$51+$B$52)/$B$53,IF(B69="P/E",IF(Valuation!F72<>"",C69*(Valuation!F72+$B$262)*(1+$B$9),C69*(E69-$B$54)/$B$53),IF(Valuation!G72<>"",(Valuation!G72)*(1+$B$9)/C69,(E69-IF(Valuation!H72,$B$54,0))/C69/$B$53))+$B$52/$B$53) | G69: =Valuation!C72 | H69: =IF(B69="EV/sales",1,IF(B69="EV/EBIT",2,IF(B69="EV/EBITDA",IF(Valuation!E72="adjusted",4,3),IF(B69="P/E",5,6)))) | I69: =IF(AND(B69="P/E",Valuation!F72<>""),(Valuation!F72+$B$262)*(1+$B$9),IF(AND(B69="FCF yield",Valuation!G72<>""),(Valuation!G72)*(1+$B$9),E69))
A70: ="Multiple: "&Valuation!A73&" ("&Valuation!D73&")" | B70: =Valuation!A73 | C70: =IF(B70="FCF yield",(Valuation!B73)*(1-$B$8),(Valuation!B73)+IF(B70="EV/sales",0.1,1)*$B$6) | D70: =Valuation!D73 | E70: =IF(D70="ltm",CHOOSE(H70,$C$59,$C$60,$C$61,$C$62,$C$63,$C$64),CHOOSE(H70,$B$59,$B$60,$B$61,$B$62,$B$63,$B$64)) | F70: =IF(OR(B70="EV/EBITDA",B70="EV/sales",B70="EV/EBIT"),((C70*E70)-$B$50-$B$51+$B$52)/$B$53,IF(B70="P/E",IF(Valuation!F73<>"",C70*(Valuation!F73)*(1+$B$9),C70*(E70-$B$54)/$B$53),IF(Valuation!G73<>"",(Valuation!G73+$B$263)*(1+$B$9)/C70,(E70-IF(Valuation!H73,$B$54,0))/C70/$B$53))+$B$52/$B$53) | G70: =Valuation!C73 | H70: =IF(B70="EV/sales",1,IF(B70="EV/EBIT",2,IF(B70="EV/EBITDA",IF(Valuation!E73="adjusted",4,3),IF(B70="P/E",5,6)))) | I70: =IF(AND(B70="P/E",Valuation!F73<>""),(Valuation!F73)*(1+$B$9),IF(AND(B70="FCF yield",Valuation!G73<>""),(Valuation!G73+$B$263)*(1+$B$9),E70))
A71: Value per share at target date (weighted methods) | F71: =SUMPRODUCT(F67:F70,G67:G70)/SUM(G67:G70)
A129: Segment build (model_engine.seg_build): revenue and EBIT are the segment sums plus corporate EBIT
A130: Segment | B130: Base | C130: =Model!E5 | D130: =Model!F5 | E130: =Model!G5
A131: AC Wireless and Home: revenue growth | C131: =Model!E12+$B$4+$B$253 | D131: =Model!F12+$B$4+$B$255 | E131: =Model!G12+$B$4+$B$257
A132: AC Wireless and Home: revenue | B132: =Valuation!$B$91 | C132: =B132*(1+C131) | D132: =C132*(1+D131) | E132: =D132*(1+E131)
A133: AC Wireless and Home: EBIT margin | C133: =Model!E14+$B$5+$B$254 | D133: =Model!F14+$B$5+$B$256 | E133: =Model!G14+$B$5+$B$258
A134: AC Wireless and Home: EBIT | C134: =C132*C133 | D134: =D132*D133 | E134: =E132*E133
A135: AC Business Wireline and Other: revenue growth | C135: =Model!E16+$B$4 | D135: =Model!F16+$B$4 | E135: =Model!G16+$B$4
A136: AC Business Wireline and Other: revenue | B136: =Valuation!$B$92 | C136: =B136*(1+C135) | D136: =C136*(1+D135) | E136: =D136*(1+E135)
A137: AC Business Wireline and Other: EBIT margin | C137: =Model!E18+$B$5+$B$259 | D137: =Model!F18+$B$5+$B$260 | E137: =Model!G18+$B$5+$B$261
A138: AC Business Wireline and Other: EBIT | C138: =C136*C137 | D138: =D136*D137 | E138: =E136*E137
A139: Legacy: revenue growth | C139: =Model!E20+$B$4 | D139: =Model!F20+$B$4 | E139: =Model!G20+$B$4
A140: Legacy: revenue | B140: =Valuation!$B$93 | C140: =B140*(1+C139) | D140: =C140*(1+D139) | E140: =D140*(1+E139)
A141: Legacy: EBIT margin | C141: =Model!E22+$B$5 | D141: =Model!F22+$B$5 | E141: =Model!G22+$B$5
A142: Legacy: EBIT | C142: =C140*C141 | D142: =D140*D141 | E142: =E140*E141
A143: Latin America: revenue growth | C143: =Model!E24+$B$4 | D143: =Model!F24+$B$4 | E143: =Model!G24+$B$4
A144: Latin America: revenue | B144: =Valuation!$B$94 | C144: =B144*(1+C143) | D144: =C144*(1+D143) | E144: =D144*(1+E143)
A145: Latin America: EBIT margin | C145: =Model!E26+$B$5 | D145: =Model!F26+$B$5 | E145: =Model!G26+$B$5
A146: Latin America: EBIT | C146: =C144*C145 | D146: =D144*D145 | E146: =E144*E145
A147: Corporate and Other: revenue growth | C147: =Model!E28+$B$4 | D147: =Model!F28+$B$4 | E147: =Model!G28+$B$4
A148: Corporate and Other: revenue | B148: =Valuation!$B$95 | C148: =B148*(1+C147) | D148: =C148*(1+D147) | E148: =D148*(1+E147)
A149: Corporate and Other: EBIT margin | C149: =Model!E30+$B$5 | D149: =Model!F30+$B$5 | E149: =Model!G30+$B$5
A150: Corporate and Other: EBIT | C150: =C148*C149 | D150: =D148*D149 | E150: =E148*E149
A151: Total segment revenue | C151: =C132+C136+C140+C144+C148 | D151: =D132+D136+D140+D144+D148 | E151: =E132+E136+E140+E144+E148
A152: Total segment EBIT | C152: =C134+C138+C142+C146+C150 | D152: =D134+D138+D142+D146+D150 | E152: =E134+E138+E142+E146+E150
A153: Corporate / unallocated EBIT | C153: =Model!E33 | D153: =Model!F33 | E153: =Model!G33
A154: EBIT (segments + corporate) | C154: =C152+C153 | D154: =D152+D153 | E154: =E152+E153
A249: Driver scenario shifts: line-item changes model_drivers.py resolves from this scenario's driver deltas (added to the Model tab inputs)
A250: Capex % revenue, year 1 | B250: 0.0043288175
A251: Capex % revenue, year 2 | B251: 0.004521271
A252: Capex % revenue, year 3 | B252: 0.0045659355
A253: AC Wireless and Home: revenue growth, year 1 | B253: -0.030262145
A254: AC Wireless and Home: EBIT margin, year 1 | B254: -0.012
A255: AC Wireless and Home: revenue growth, year 2 | B255: -8.5935961e-05
A256: AC Wireless and Home: EBIT margin, year 2 | B256: -0.012
A257: AC Wireless and Home: revenue growth, year 3 | B257: -5.057242e-05
...

Sheet Calc - base
A1: T engine calculation: base scenario
A2: Machinery behind the Valuation and Distribution tabs; drivers come from Model, assumptions from Valuation.
A4: Scenario Growth Δ | B4: =N(Valuation!C87)
A5: Scenario Margin Δ | B5: =N(Valuation!D87)
A6: Scenario Multiple Δ (turns) | B6: =N(Valuation!E87)
A7: Scenario WACC Δ | B7: =N(Valuation!F87)
A8: Scenario Multiple %Δ | B8: =N(Valuation!G87)
A9: Scenario Stated EPS/FCF %Δ | B9: =N(Valuation!H87)
A10: Scenario Custom %Δ | B10: =N(Valuation!I87)
A12: WACC | B12: =Valuation!$B$52+B7
A13: Years from last FY end to target date | B13: =(Valuation!$B$46-Valuation!$B$50)/365.25
A14: Years from last FY end to balance date | B14: =(Valuation!$B$56-Valuation!$B$50)/365.25
A15: Years from last FY end to share count date | B15: =(Valuation!$B$62-Valuation!$B$50)/365.25
A16: Projected years | B16: 3
A18: Projection | B18: Base | C18: =Model!E5 | D18: =Model!F5 | E18: =Model!G5
A19: Year index | B19: 0 | C19: 1 | D19: 2 | E19: 3
A20: Period end | C20: =Valuation!$B$50+ROUND(365.25*C19,0) | D20: =Valuation!$B$50+ROUND(365.25*D19,0) | E20: =Valuation!$B$50+ROUND(365.25*E19,0)
A21: Revenue growth | C21: =C22/B22-1 | D21: =D22/C22-1 | E21: =E22/D22-1
A22: Revenue | B22: =Valuation!$B$51 | C22: =C151 | D22: =D151 | E22: =E151
A23: EBIT margin | C23: =C24/C22 | D23: =D24/D22 | E23: =E24/E22
A24: EBIT | C24: =C154 | D24: =D154 | E24: =E154
A25: Tax rate | C25: =Model!E75 | D25: =Model!F75 | E25: =Model!G75
A26: NOPAT | C26: =C24*(1-C25) | D26: =D24*(1-D25) | E26: =E24*(1-E25)
A27: D&A | C27: =C22*(Model!E76) | D27: =D22*(Model!F76) | E27: =E22*(Model!G76)
A28: Capex | C28: =C22*(Model!E77) | D28: =D22*(Model!F77) | E28: =E22*(Model!G77)
A29: Working capital increase | C29: =(Model!E78)*(C22-B22) | D29: =(Model!F78)*(D22-C22) | E29: =(Model!G78)*(E22-D22)
A30: Stock comp | C30: =C22*(Model!E79) | D30: =D22*(Model!F79) | E30: =E22*(Model!G79)
A31: Free cash flow to firm | C31: =C26+C27-C28-C29-IF(AND(Valuation!$B$48="adjusted",Valuation!$B$49="cost"),C30*(1-C25),0) | D31: =D26+D27-D28-D29-IF(AND(Valuation!$B$48="adjusted",Valuation!$B$49="cost"),D30*(1-D25),0) | E31: =E26+E27-E28-E29-IF(AND(Valuation!$B$48="adjusted",Valuation!$B$49="cost"),E30*(1-E25),0)
A32: EBITDA | C32: =C24+C27 | D32: =D24+D27 | E32: =E24+E27
A33: Adj. EBITDA | C33: =C24+C27+C22*(Model!E83) | D33: =D24+D27+D22*(Model!F83) | E33: =E24+E27+E22*(Model!G83)
A34: Shareholder returns + other uses | C34: =C22*Model!E81+Model!E80+Model!E82 | D34: =D22*Model!F81+Model!F80+Model!F82 | E34: =E22*Model!G81+Model!G80+Model!G82
A35: Share of year after target date | C35: =IF(C19<=$B$13,0,C19-MAX(C19-1,$B$13)) | D35: =IF(D19<=$B$13,0,D19-MAX(D19-1,$B$13)) | E35: =IF(E19<=$B$13,0,E19-MAX(E19-1,$B$13))
A36: PV at target date of FCFF | C36: =IF(C35=0,0,C31*C35/(1+$B$12)^(C19-$B$13)) | D36: =IF(D35=0,0,D31*D35/(1+$B$12)^(D19-$B$13)) | E36: =IF(E35=0,0,E31*E35/(1+$B$12)^(E19-$B$13))
A37: Overlap: balance date to target date | C37: =MAX(0,MIN(C19,$B$13)-MAX(C19-1,$B$14)) | D37: =MAX(0,MIN(D19,$B$13)-MAX(D19-1,$B$14)) | E37: =MAX(0,MIN(E19,$B$13)-MAX(E19-1,$B$14))
A38: NTM weight at target date | C38: =MAX(0,MIN(C19,$B$13+1)-MAX(C19-1,$B$13)) | D38: =MAX(0,MIN(D19,$B$13+1)-MAX(D19-1,$B$13)) | E38: =MAX(0,MIN(E19,$B$13+1)-MAX(E19-1,$B$13))
A39: LTM weight at target date | B39: =MAX(0,MIN(0,$B$13)-MAX(-1,$B$13-1)) | C39: =MAX(0,MIN(C19,$B$13)-MAX(C19-1,$B$13-1)) | D39: =MAX(0,MIN(D19,$B$13)-MAX(D19-1,$B$13-1)) | E39: =MAX(0,MIN(E19,$B$13)-MAX(E19-1,$B$13-1))
A41: Value at the target date
A42: PV of free cash flow after the target date | B42: =SUM($C$36:$E$36)
A43: Terminal value at final year | B43: =IF(Valuation!$B$53="exit_multiple",Valuation!$B$55*E32,E31*(1+Valuation!$B$54)/($B$12-Valuation!$B$54))
A44: PV of terminal value at target date | B44: =B43/(1+$B$12)^($B$16-$B$13)
A45: DCF enterprise value at target date | B45: =B42+B44
A46: Terminal value share of DCF | B46: =B44/B45
A47: Free cash flow earned, balance date to target date | B47: =SUMPRODUCT($C$37:$E$37,$C$31:$E$31)
A48: Shareholder returns + other uses paid | B48: =SUMPRODUCT($C$37:$E$37,$C$34:$E$34)
A49: Interest drag on net debt | B49: =Valuation!$B$59*(1-$C$25)*MAX(Valuation!$B$57,0)*MAX($B$13-$B$14,0)
A50: Net debt at target date | B50: =IF(Valuation!$B$60="",Valuation!$B$57-B47+B49+B48,Valuation!$B$60)
A51: Minority interests | B51: =Valuation!$B$58
A52: Adjustments (probability-weighted) | B52: =(Valuation!B79)*Valuation!C79+(Valuation!B80)*Valuation!C80+0
A53: Diluted shares at target date (M) | B53: =IF(Valuation!$B$64="",Valuation!$B$61*(1+Valuation!$B$63)^MAX($B$13-$B$15,0),Valuation!$B$64)
A54: After-tax interest on target-date net debt | B54: =Valuation!$B$59*(1-$C$25)*MAX(B50,0)
A55: Check: WACC vs terminal growth | B55: =IF(AND(Valuation!$B$53<>"exit_multiple",$B$12<=Valuation!$B$54+0.01),"WACC must exceed terminal growth by 1 point","ok")
A56: Check: projection length | B56: =IF(OR($B$13>=$B$16-1,$B$13+1>$B$16),"add projected years past the target date","ok")
A58: Metric at target date | B58: Next 12 months | C58: Last 12 months
A59: Revenue | B59: =SUMPRODUCT($C$38:$E$38,$C$22:$E$22) | C59: =SUMPRODUCT($C$39:$E$39,$C$22:$E$22)+$B$39*$B$22
A60: EBIT | B60: =SUMPRODUCT($C$38:$E$38,$C$24:$E$24) | C60: =SUMPRODUCT($C$39:$E$39,$C$24:$E$24)
A61: EBITDA | B61: =SUMPRODUCT($C$38:$E$38,$C$32:$E$32) | C61: =SUMPRODUCT($C$39:$E$39,$C$32:$E$32)
A62: Adj. EBITDA | B62: =SUMPRODUCT($C$38:$E$38,$C$33:$E$33) | C62: =SUMPRODUCT($C$39:$E$39,$C$33:$E$33)
A63: NOPAT | B63: =SUMPRODUCT($C$38:$E$38,$C$26:$E$26) | C63: =SUMPRODUCT($C$39:$E$39,$C$26:$E$26)
A64: Free cash flow to firm | B64: =SUMPRODUCT($C$38:$E$38,$C$31:$E$31) | C64: =SUMPRODUCT($C$39:$E$39,$C$31:$E$31)
A66: Valuation method | B66: Metric | C66: Multiple used | D66: Basis | E66: Metric at target date | F66: Value per share | G66: Weight | H66: Metric key | I66: Metric shown (stated per-share figure when used)
A67: DCF (cash flow to target date + terminal) | F67: =((B45)-$B$50-$B$51+$B$52)/$B$53 | G67: =Valuation!$B$65
A68: ="Multiple: "&Valuation!A71&" ("&Valuation!D71&")" | B68: =Valuation!A71 | C68: =IF(B68="FCF yield",(Valuation!B71)*(1-$B$8),(Valuation!B71)+IF(B68="EV/sales",0.1,1)*$B$6) | D68: =Valuation!D71 | E68: =IF(D68="ltm",CHOOSE(H68,$C$59,$C$60,$C$61,$C$62,$C$63,$C$64),CHOOSE(H68,$B$59,$B$60,$B$61,$B$62,$B$63,$B$64)) | F68: =IF(OR(B68="EV/EBITDA",B68="EV/sales",B68="EV/EBIT"),((C68*E68)-$B$50-$B$51+$B$52)/$B$53,IF(B68="P/E",IF(Valuation!F71<>"",C68*(Valuation!F71)*(1+$B$9),C68*(E68-$B$54)/$B$53),IF(Valuation!G71<>"",(Valuation!G71)*(1+$B$9)/C68,(E68-IF(Valuation!H71,$B$54,0))/C68/$B$53))+$B$52/$B$53) | G68: =Valuation!C71 | H68: =IF(B68="EV/sales",1,IF(B68="EV/EBIT",2,IF(B68="EV/EBITDA",IF(Valuation!E71="adjusted",4,3),IF(B68="P/E",5,6)))) | I68: =IF(AND(B68="P/E",Valuation!F71<>""),(Valuation!F71)*(1+$B$9),IF(AND(B68="FCF yield",Valuation!G71<>""),(Valuation!G71)*(1+$B$9),E68))
A69: ="Multiple: "&Valuation!A72&" ("&Valuation!D72&")" | B69: =Valuation!A72 | C69: =IF(B69="FCF yield",(Valuation!B72)*(1-$B$8),(Valuation!B72)+IF(B69="EV/sales",0.1,1)*$B$6) | D69: =Valuation!D72 | E69: =IF(D69="ltm",CHOOSE(H69,$C$59,$C$60,$C$61,$C$62,$C$63,$C$64),CHOOSE(H69,$B$59,$B$60,$B$61,$B$62,$B$63,$B$64)) | F69: =IF(OR(B69="EV/EBITDA",B69="EV/sales",B69="EV/EBIT"),((C69*E69)-$B$50-$B$51+$B$52)/$B$53,IF(B69="P/E",IF(Valuation!F72<>"",C69*(Valuation!F72)*(1+$B$9),C69*(E69-$B$54)/$B$53),IF(Valuation!G72<>"",(Valuation!G72)*(1+$B$9)/C69,(E69-IF(Valuation!H72,$B$54,0))/C69/$B$53))+$B$52/$B$53) | G69: =Valuation!C72 | H69: =IF(B69="EV/sales",1,IF(B69="EV/EBIT",2,IF(B69="EV/EBITDA",IF(Valuation!E72="adjusted",4,3),IF(B69="P/E",5,6)))) | I69: =IF(AND(B69="P/E",Valuation!F72<>""),(Valuation!F72)*(1+$B$9),IF(AND(B69="FCF yield",Valuation!G72<>""),(Valuation!G72)*(1+$B$9),E69))
A70: ="Multiple: "&Valuation!A73&" ("&Valuation!D73&")" | B70: =Valuation!A73 | C70: =IF(B70="FCF yield",(Valuation!B73)*(1-$B$8),(Valuation!B73)+IF(B70="EV/sales",0.1,1)*$B$6) | D70: =Valuation!D73 | E70: =IF(D70="ltm",CHOOSE(H70,$C$59,$C$60,$C$61,$C$62,$C$63,$C$64),CHOOSE(H70,$B$59,$B$60,$B$61,$B$62,$B$63,$B$64)) | F70: =IF(OR(B70="EV/EBITDA",B70="EV/sales",B70="EV/EBIT"),((C70*E70)-$B$50-$B$51+$B$52)/$B$53,IF(B70="P/E",IF(Valuation!F73<>"",C70*(Valuation!F73)*(1+$B$9),C70*(E70-$B$54)/$B$53),IF(Valuation!G73<>"",(Valuation!G73)*(1+$B$9)/C70,(E70-IF(Valuation!H73,$B$54,0))/C70/$B$53))+$B$52/$B$53) | G70: =Valuation!C73 | H70: =IF(B70="EV/sales",1,IF(B70="EV/EBIT",2,IF(B70="EV/EBITDA",IF(Valuation!E73="adjusted",4,3),IF(B70="P/E",5,6)))) | I70: =IF(AND(B70="P/E",Valuation!F73<>""),(Valuation!F73)*(1+$B$9),IF(AND(B70="FCF yield",Valuation!G73<>""),(Valuation!G73)*(1+$B$9),E70))
A71: Value per share at target date (weighted methods) | F71: =SUMPRODUCT(F67:F70,G67:G70)/SUM(G67:G70)
A129: Segment build (model_engine.seg_build): revenue and EBIT are the segment sums plus corporate EBIT
A130: Segment | B130: Base | C130: =Model!E5 | D130: =Model!F5 | E130: =Model!G5
A131: AC Wireless and Home: revenue growth | C131: =Model!E12+$B$4 | D131: =Model!F12+$B$4 | E131: =Model!G12+$B$4
A132: AC Wireless and Home: revenue | B132: =Valuation!$B$91 | C132: =B132*(1+C131) | D132: =C132*(1+D131) | E132: =D132*(1+E131)
A133: AC Wireless and Home: EBIT margin | C133: =Model!E14+$B$5 | D133: =Model!F14+$B$5 | E133: =Model!G14+$B$5
A134: AC Wireless and Home: EBIT | C134: =C132*C133 | D134: =D132*D133 | E134: =E132*E133
A135: AC Business Wireline and Other: revenue growth | C135: =Model!E16+$B$4 | D135: =Model!F16+$B$4 | E135: =Model!G16+$B$4
A136: AC Business Wireline and Other: revenue | B136: =Valuation!$B$92 | C136: =B136*(1+C135) | D136: =C136*(1+D135) | E136: =D136*(1+E135)
A137: AC Business Wireline and Other: EBIT margin | C137: =Model!E18+$B$5 | D137: =Model!F18+$B$5 | E137: =Model!G18+$B$5
A138: AC Business Wireline and Other: EBIT | C138: =C136*C137 | D138: =D136*D137 | E138: =E136*E137
A139: Legacy: revenue growth | C139: =Model!E20+$B$4 | D139: =Model!F20+$B$4 | E139: =Model!G20+$B$4
A140: Legacy: revenue | B140: =Valuation!$B$93 | C140: =B140*(1+C139) | D140: =C140*(1+D139) | E140: =D140*(1+E139)
A141: Legacy: EBIT margin | C141: =Model!E22+$B$5 | D141: =Model!F22+$B$5 | E141: =Model!G22+$B$5
A142: Legacy: EBIT | C142: =C140*C141 | D142: =D140*D141 | E142: =E140*E141
A143: Latin America: revenue growth | C143: =Model!E24+$B$4 | D143: =Model!F24+$B$4 | E143: =Model!G24+$B$4
A144: Latin America: revenue | B144: =Valuation!$B$94 | C144: =B144*(1+C143) | D144: =C144*(1+D143) | E144: =D144*(1+E143)
A145: Latin America: EBIT margin | C145: =Model!E26+$B$5 | D145: =Model!F26+$B$5 | E145: =Model!G26+$B$5
A146: Latin America: EBIT | C146: =C144*C145 | D146: =D144*D145 | E146: =E144*E145
A147: Corporate and Other: revenue growth | C147: =Model!E28+$B$4 | D147: =Model!F28+$B$4 | E147: =Model!G28+$B$4
A148: Corporate and Other: revenue | B148: =Valuation!$B$95 | C148: =B148*(1+C147) | D148: =C148*(1+D147) | E148: =D148*(1+E147)
A149: Corporate and Other: EBIT margin | C149: =Model!E30+$B$5 | D149: =Model!F30+$B$5 | E149: =Model!G30+$B$5
A150: Corporate and Other: EBIT | C150: =C148*C149 | D150: =D148*D149 | E150: =E148*E149
A151: Total segment revenue | C151: =C132+C136+C140+C144+C148 | D151: =D132+D136+D140+D144+D148 | E151: =E132+E136+E140+E144+E148
A152: Total segment EBIT | C152: =C134+C138+C142+C146+C150 | D152: =D134+D138+D142+D146+D150 | E152: =E134+E138+E142+E146+E150
A153: Corporate / unallocated EBIT | C153: =Model!E33 | D153: =Model!F33 | E153: =Model!G33
A154: EBIT (segments + corporate) | C154: =C152+C153 | D154: =D152+D153 | E154: =E152+E153

Sheet Calc - bull
A1: T engine calculation: bull scenario
A2: Machinery behind the Valuation and Distribution tabs; drivers come from Model, assumptions from Valuation.
A4: Scenario Growth Δ | B4: =N(Valuation!C88)
A5: Scenario Margin Δ | B5: =N(Valuation!D88)
A6: Scenario Multiple Δ (turns) | B6: =N(Valuation!E88)
A7: Scenario WACC Δ | B7: =N(Valuation!F88)
A8: Scenario Multiple %Δ | B8: =N(Valuation!G88)
A9: Scenario Stated EPS/FCF %Δ | B9: =N(Valuation!H88)
A10: Scenario Custom %Δ | B10: =N(Valuation!I88)
A12: WACC | B12: =Valuation!$B$52+B7
A13: Years from last FY end to target date | B13: =(Valuation!$B$46-Valuation!$B$50)/365.25
A14: Years from last FY end to balance date | B14: =(Valuation!$B$56-Valuation!$B$50)/365.25
A15: Years from last FY end to share count date | B15: =(Valuation!$B$62-Valuation!$B$50)/365.25
A16: Projected years | B16: 3
A18: Projection | B18: Base | C18: =Model!E5 | D18: =Model!F5 | E18: =Model!G5
A19: Year index | B19: 0 | C19: 1 | D19: 2 | E19: 3
A20: Period end | C20: =Valuation!$B$50+ROUND(365.25*C19,0) | D20: =Valuation!$B$50+ROUND(365.25*D19,0) | E20: =Valuation!$B$50+ROUND(365.25*E19,0)
A21: Revenue growth | C21: =C22/B22-1 | D21: =D22/C22-1 | E21: =E22/D22-1
A22: Revenue | B22: =Valuation!$B$51 | C22: =C151 | D22: =D151 | E22: =E151
A23: EBIT margin | C23: =C24/C22 | D23: =D24/D22 | E23: =E24/E22
A24: EBIT | C24: =C154 | D24: =D154 | E24: =E154
A25: Tax rate | C25: =Model!E75 | D25: =Model!F75 | E25: =Model!G75
A26: NOPAT | C26: =C24*(1-C25) | D26: =D24*(1-D25) | E26: =E24*(1-E25)
A27: D&A | C27: =C22*(Model!E76) | D27: =D22*(Model!F76) | E27: =E22*(Model!G76)
A28: Capex | C28: =C22*(Model!E77+$B$250) | D28: =D22*(Model!F77+$B$251) | E28: =E22*(Model!G77+$B$252)
A29: Working capital increase | C29: =(Model!E78)*(C22-B22) | D29: =(Model!F78)*(D22-C22) | E29: =(Model!G78)*(E22-D22)
A30: Stock comp | C30: =C22*(Model!E79) | D30: =D22*(Model!F79) | E30: =E22*(Model!G79)
A31: Free cash flow to firm | C31: =C26+C27-C28-C29-IF(AND(Valuation!$B$48="adjusted",Valuation!$B$49="cost"),C30*(1-C25),0) | D31: =D26+D27-D28-D29-IF(AND(Valuation!$B$48="adjusted",Valuation!$B$49="cost"),D30*(1-D25),0) | E31: =E26+E27-E28-E29-IF(AND(Valuation!$B$48="adjusted",Valuation!$B$49="cost"),E30*(1-E25),0)
A32: EBITDA | C32: =C24+C27 | D32: =D24+D27 | E32: =E24+E27
A33: Adj. EBITDA | C33: =C24+C27+C22*(Model!E83) | D33: =D24+D27+D22*(Model!F83) | E33: =E24+E27+E22*(Model!G83)
A34: Shareholder returns + other uses | C34: =C22*Model!E81+Model!E80+Model!E82 | D34: =D22*Model!F81+Model!F80+Model!F82 | E34: =E22*Model!G81+Model!G80+Model!G82
A35: Share of year after target date | C35: =IF(C19<=$B$13,0,C19-MAX(C19-1,$B$13)) | D35: =IF(D19<=$B$13,0,D19-MAX(D19-1,$B$13)) | E35: =IF(E19<=$B$13,0,E19-MAX(E19-1,$B$13))
A36: PV at target date of FCFF | C36: =IF(C35=0,0,C31*C35/(1+$B$12)^(C19-$B$13)) | D36: =IF(D35=0,0,D31*D35/(1+$B$12)^(D19-$B$13)) | E36: =IF(E35=0,0,E31*E35/(1+$B$12)^(E19-$B$13))
A37: Overlap: balance date to target date | C37: =MAX(0,MIN(C19,$B$13)-MAX(C19-1,$B$14)) | D37: =MAX(0,MIN(D19,$B$13)-MAX(D19-1,$B$14)) | E37: =MAX(0,MIN(E19,$B$13)-MAX(E19-1,$B$14))
A38: NTM weight at target date | C38: =MAX(0,MIN(C19,$B$13+1)-MAX(C19-1,$B$13)) | D38: =MAX(0,MIN(D19,$B$13+1)-MAX(D19-1,$B$13)) | E38: =MAX(0,MIN(E19,$B$13+1)-MAX(E19-1,$B$13))
A39: LTM weight at target date | B39: =MAX(0,MIN(0,$B$13)-MAX(-1,$B$13-1)) | C39: =MAX(0,MIN(C19,$B$13)-MAX(C19-1,$B$13-1)) | D39: =MAX(0,MIN(D19,$B$13)-MAX(D19-1,$B$13-1)) | E39: =MAX(0,MIN(E19,$B$13)-MAX(E19-1,$B$13-1))
A41: Value at the target date
A42: PV of free cash flow after the target date | B42: =SUM($C$36:$E$36)
A43: Terminal value at final year | B43: =IF(Valuation!$B$53="exit_multiple",Valuation!$B$55*E32,E31*(1+Valuation!$B$54)/($B$12-Valuation!$B$54))
A44: PV of terminal value at target date | B44: =B43/(1+$B$12)^($B$16-$B$13)
A45: DCF enterprise value at target date | B45: =B42+B44
A46: Terminal value share of DCF | B46: =B44/B45
A47: Free cash flow earned, balance date to target date | B47: =SUMPRODUCT($C$37:$E$37,$C$31:$E$31)
A48: Shareholder returns + other uses paid | B48: =SUMPRODUCT($C$37:$E$37,$C$34:$E$34)
A49: Interest drag on net debt | B49: =Valuation!$B$59*(1-$C$25)*MAX(Valuation!$B$57,0)*MAX($B$13-$B$14,0)
A50: Net debt at target date | B50: =IF(Valuation!$B$60="",Valuation!$B$57-B47+B49+B48,Valuation!$B$60)
A51: Minority interests | B51: =Valuation!$B$58
A52: Adjustments (probability-weighted) | B52: =(Valuation!B79)*Valuation!C79+(Valuation!B80)*Valuation!C80+0
A53: Diluted shares at target date (M) | B53: =IF(Valuation!$B$64="",Valuation!$B$61*(1+Valuation!$B$63)^MAX($B$13-$B$15,0),Valuation!$B$64)
A54: After-tax interest on target-date net debt | B54: =Valuation!$B$59*(1-$C$25)*MAX(B50,0)
A55: Check: WACC vs terminal growth | B55: =IF(AND(Valuation!$B$53<>"exit_multiple",$B$12<=Valuation!$B$54+0.01),"WACC must exceed terminal growth by 1 point","ok")
A56: Check: projection length | B56: =IF(OR($B$13>=$B$16-1,$B$13+1>$B$16),"add projected years past the target date","ok")
A58: Metric at target date | B58: Next 12 months | C58: Last 12 months
A59: Revenue | B59: =SUMPRODUCT($C$38:$E$38,$C$22:$E$22) | C59: =SUMPRODUCT($C$39:$E$39,$C$22:$E$22)+$B$39*$B$22
A60: EBIT | B60: =SUMPRODUCT($C$38:$E$38,$C$24:$E$24) | C60: =SUMPRODUCT($C$39:$E$39,$C$24:$E$24)
A61: EBITDA | B61: =SUMPRODUCT($C$38:$E$38,$C$32:$E$32) | C61: =SUMPRODUCT($C$39:$E$39,$C$32:$E$32)
A62: Adj. EBITDA | B62: =SUMPRODUCT($C$38:$E$38,$C$33:$E$33) | C62: =SUMPRODUCT($C$39:$E$39,$C$33:$E$33)
A63: NOPAT | B63: =SUMPRODUCT($C$38:$E$38,$C$26:$E$26) | C63: =SUMPRODUCT($C$39:$E$39,$C$26:$E$26)
A64: Free cash flow to firm | B64: =SUMPRODUCT($C$38:$E$38,$C$31:$E$31) | C64: =SUMPRODUCT($C$39:$E$39,$C$31:$E$31)
A66: Valuation method | B66: Metric | C66: Multiple used | D66: Basis | E66: Metric at target date | F66: Value per share | G66: Weight | H66: Metric key | I66: Metric shown (stated per-share figure when used)
A67: DCF (cash flow to target date + terminal) | F67: =((B45)-$B$50-$B$51+$B$52)/$B$53 | G67: =Valuation!$B$65
A68: ="Multiple: "&Valuation!A71&" ("&Valuation!D71&")" | B68: =Valuation!A71 | C68: =IF(B68="FCF yield",(Valuation!B71)*(1-$B$8),(Valuation!B71)+IF(B68="EV/sales",0.1,1)*$B$6) | D68: =Valuation!D71 | E68: =IF(D68="ltm",CHOOSE(H68,$C$59,$C$60,$C$61,$C$62,$C$63,$C$64),CHOOSE(H68,$B$59,$B$60,$B$61,$B$62,$B$63,$B$64)) | F68: =IF(OR(B68="EV/EBITDA",B68="EV/sales",B68="EV/EBIT"),((C68*E68)-$B$50-$B$51+$B$52)/$B$53,IF(B68="P/E",IF(Valuation!F71<>"",C68*(Valuation!F71)*(1+$B$9),C68*(E68-$B$54)/$B$53),IF(Valuation!G71<>"",(Valuation!G71)*(1+$B$9)/C68,(E68-IF(Valuation!H71,$B$54,0))/C68/$B$53))+$B$52/$B$53) | G68: =Valuation!C71 | H68: =IF(B68="EV/sales",1,IF(B68="EV/EBIT",2,IF(B68="EV/EBITDA",IF(Valuation!E71="adjusted",4,3),IF(B68="P/E",5,6)))) | I68: =IF(AND(B68="P/E",Valuation!F71<>""),(Valuation!F71)*(1+$B$9),IF(AND(B68="FCF yield",Valuation!G71<>""),(Valuation!G71)*(1+$B$9),E68))
A69: ="Multiple: "&Valuation!A72&" ("&Valuation!D72&")" | B69: =Valuation!A72 | C69: =IF(B69="FCF yield",(Valuation!B72)*(1-$B$8),(Valuation!B72)+IF(B69="EV/sales",0.1,1)*$B$6) | D69: =Valuation!D72 | E69: =IF(D69="ltm",CHOOSE(H69,$C$59,$C$60,$C$61,$C$62,$C$63,$C$64),CHOOSE(H69,$B$59,$B$60,$B$61,$B$62,$B$63,$B$64)) | F69: =IF(OR(B69="EV/EBITDA",B69="EV/sales",B69="EV/EBIT"),((C69*E69)-$B$50-$B$51+$B$52)/$B$53,IF(B69="P/E",IF(Valuation!F72<>"",C69*(Valuation!F72+$B$262)*(1+$B$9),C69*(E69-$B$54)/$B$53),IF(Valuation!G72<>"",(Valuation!G72)*(1+$B$9)/C69,(E69-IF(Valuation!H72,$B$54,0))/C69/$B$53))+$B$52/$B$53) | G69: =Valuation!C72 | H69: =IF(B69="EV/sales",1,IF(B69="EV/EBIT",2,IF(B69="EV/EBITDA",IF(Valuation!E72="adjusted",4,3),IF(B69="P/E",5,6)))) | I69: =IF(AND(B69="P/E",Valuation!F72<>""),(Valuation!F72+$B$262)*(1+$B$9),IF(AND(B69="FCF yield",Valuation!G72<>""),(Valuation!G72)*(1+$B$9),E69))
A70: ="Multiple: "&Valuation!A73&" ("&Valuation!D73&")" | B70: =Valuation!A73 | C70: =IF(B70="FCF yield",(Valuation!B73)*(1-$B$8),(Valuation!B73)+IF(B70="EV/sales",0.1,1)*$B$6) | D70: =Valuation!D73 | E70: =IF(D70="ltm",CHOOSE(H70,$C$59,$C$60,$C$61,$C$62,$C$63,$C$64),CHOOSE(H70,$B$59,$B$60,$B$61,$B$62,$B$63,$B$64)) | F70: =IF(OR(B70="EV/EBITDA",B70="EV/sales",B70="EV/EBIT"),((C70*E70)-$B$50-$B$51+$B$52)/$B$53,IF(B70="P/E",IF(Valuation!F73<>"",C70*(Valuation!F73)*(1+$B$9),C70*(E70-$B$54)/$B$53),IF(Valuation!G73<>"",(Valuation!G73+$B$263)*(1+$B$9)/C70,(E70-IF(Valuation!H73,$B$54,0))/C70/$B$53))+$B$52/$B$53) | G70: =Valuation!C73 | H70: =IF(B70="EV/sales",1,IF(B70="EV/EBIT",2,IF(B70="EV/EBITDA",IF(Valuation!E73="adjusted",4,3),IF(B70="P/E",5,6)))) | I70: =IF(AND(B70="P/E",Valuation!F73<>""),(Valuation!F73)*(1+$B$9),IF(AND(B70="FCF yield",Valuation!G73<>""),(Valuation!G73+$B$263)*(1+$B$9),E70))
A71: Value per share at target date (weighted methods) | F71: =SUMPRODUCT(F67:F70,G67:G70)/SUM(G67:G70)
A129: Segment build (model_engine.seg_build): revenue and EBIT are the segment sums plus corporate EBIT
A130: Segment | B130: Base | C130: =Model!E5 | D130: =Model!F5 | E130: =Model!G5
A131: AC Wireless and Home: revenue growth | C131: =Model!E12+$B$4+$B$253 | D131: =Model!F12+$B$4+$B$255 | E131: =Model!G12+$B$4+$B$257
A132: AC Wireless and Home: revenue | B132: =Valuation!$B$91 | C132: =B132*(1+C131) | D132: =C132*(1+D131) | E132: =D132*(1+E131)
A133: AC Wireless and Home: EBIT margin | C133: =Model!E14+$B$5+$B$254 | D133: =Model!F14+$B$5+$B$256 | E133: =Model!G14+$B$5+$B$258
A134: AC Wireless and Home: EBIT | C134: =C132*C133 | D134: =D132*D133 | E134: =E132*E133
A135: AC Business Wireline and Other: revenue growth | C135: =Model!E16+$B$4 | D135: =Model!F16+$B$4 | E135: =Model!G16+$B$4
A136: AC Business Wireline and Other: revenue | B136: =Valuation!$B$92 | C136: =B136*(1+C135) | D136: =C136*(1+D135) | E136: =D136*(1+E135)
A137: AC Business Wireline and Other: EBIT margin | C137: =Model!E18+$B$5+$B$259 | D137: =Model!F18+$B$5+$B$260 | E137: =Model!G18+$B$5+$B$261
A138: AC Business Wireline and Other: EBIT | C138: =C136*C137 | D138: =D136*D137 | E138: =E136*E137
A139: Legacy: revenue growth | C139: =Model!E20+$B$4 | D139: =Model!F20+$B$4 | E139: =Model!G20+$B$4
A140: Legacy: revenue | B140: =Valuation!$B$93 | C140: =B140*(1+C139) | D140: =C140*(1+D139) | E140: =D140*(1+E139)
A141: Legacy: EBIT margin | C141: =Model!E22+$B$5 | D141: =Model!F22+$B$5 | E141: =Model!G22+$B$5
A142: Legacy: EBIT | C142: =C140*C141 | D142: =D140*D141 | E142: =E140*E141
A143: Latin America: revenue growth | C143: =Model!E24+$B$4 | D143: =Model!F24+$B$4 | E143: =Model!G24+$B$4
A144: Latin America: revenue | B144: =Valuation!$B$94 | C144: =B144*(1+C143) | D144: =C144*(1+D143) | E144: =D144*(1+E143)
A145: Latin America: EBIT margin | C145: =Model!E26+$B$5 | D145: =Model!F26+$B$5 | E145: =Model!G26+$B$5
A146: Latin America: EBIT | C146: =C144*C145 | D146: =D144*D145 | E146: =E144*E145
A147: Corporate and Other: revenue growth | C147: =Model!E28+$B$4 | D147: =Model!F28+$B$4 | E147: =Model!G28+$B$4
A148: Corporate and Other: revenue | B148: =Valuation!$B$95 | C148: =B148*(1+C147) | D148: =C148*(1+D147) | E148: =D148*(1+E147)
A149: Corporate and Other: EBIT margin | C149: =Model!E30+$B$5 | D149: =Model!F30+$B$5 | E149: =Model!G30+$B$5
A150: Corporate and Other: EBIT | C150: =C148*C149 | D150: =D148*D149 | E150: =E148*E149
A151: Total segment revenue | C151: =C132+C136+C140+C144+C148 | D151: =D132+D136+D140+D144+D148 | E151: =E132+E136+E140+E144+E148
A152: Total segment EBIT | C152: =C134+C138+C142+C146+C150 | D152: =D134+D138+D142+D146+D150 | E152: =E134+E138+E142+E146+E150
A153: Corporate / unallocated EBIT | C153: =Model!E33 | D153: =Model!F33 | E153: =Model!G33
A154: EBIT (segments + corporate) | C154: =C152+C153 | D154: =D152+D153 | E154: =E152+E153
A249: Driver scenario shifts: line-item changes model_drivers.py resolves from this scenario's driver deltas (added to the Model tab inputs)
A250: Capex % revenue, year 1 | B250: -0.0024279368
A251: Capex % revenue, year 2 | B251: -0.0025353269
A252: Capex % revenue, year 3 | B252: -0.0025637328
A253: AC Wireless and Home: revenue growth, year 1 | B253: 0.017615048
A254: AC Wireless and Home: EBIT margin, year 1 | B254: 0.008
A255: AC Wireless and Home: revenue growth, year 2 | B255: 8.1262276e-05
A256: AC Wireless and Home: EBIT margin, year 2 | B256: 0.008
A257: AC Wireless and Home: revenue growth, year 3 | B257: 6.7419969e-05
...

Sheet Agents
A1: T: each forecaster's own assumption set through the same engine (from model_engine.json, not live)
A3: Set | B3: Research target (12m) | C3: Median | D3: 25th pct | E3: 75th pct | F3: WACC | G3: Y1 growth | H3: Y1 margin | I3: Terminal growth | J3: DCF weight | K3: Years | L3: Multiples | M3: Supervisor's note
A4: agent 1 | B4: 24.387323 | C4: 24.046699 | D4: 18.97315 | E4: 28.082739 | J4: 0 | K4: 3 | L4: EV/EBITDA 6.2 (ntm); P/E 8.1 (ntm); FCF yield 0.123 (ntm) | M4: Highest value: 6.2x EV/EBITDA (above the decided 6.1x, +$0.40) and consolidated 2028 EBITDA +4.75% (AC +6.0% with a milder Legacy swing); otherwise a clean, fully linked build.
A5: agent 2 | B5: 22.244276 | C5: 21.987861 | D5: 18.257202 | E5: 25.960889 | J5: 0 | K5: 3 | L5: EV/EBITDA 6.0 (ntm); P/E 8.0 (ntm); FCF yield 0.125 (ntm) | M5: Lowest value: 6.0x EV/EBITDA (below the decided 6.1x, -$0.39) and FCF yield 12.5% (above today's 12.3%); a well-argued industry build.
A6: agent 3 | B6: 22.456184 | C6: 22.344245 | D6: 18.889316 | E6: 25.615799 | J6: 0 | K6: 3 | L6: EV/EBITDA 6.0 (ntm); P/E 8.0 (ntm); FCF yield 0.12 (ntm) | M6: EPS and FCF/share are stated, not linked to the drivers (no driver_build.set), so the bear/bull moves come from eps_pct; AC EBITDA +5.5%/+5.0% is the low end without a driver reason; 6.0x.
A7: agent 4 | B7: 23.481611 | C7: 23.313558 | D7: 18.882216 | E7: 26.9763 | J7: 0 | K7: 3 | L7: EV/EBITDA 6.2 (ntm); P/E 8.0 (ntm); FCF yield 0.124 (ntm) | M7: 6.2x EV/EBITDA (+$0.40 vs 6.1x) and a P/E weight of 0.40 without blend evidence; wireless ARPU +1.8% in 2027 is above what the Q3 exit rate supports.
A8: agent 5 | B8: 22.830544 | C8: 22.65825 | D8: 18.258555 | E8: 26.506676 | J8: 0 | K8: 3 | L8: EV/EBITDA 6.1 (ntm); P/E 8.2 (ntm); FCF yield 0.12 (ntm) | M8: EPS and FCF/share are stated, not driver-linked (no driver_build.set); 2027-28 FCF blends 45% on the record-adjusted guide, which is a record view rather than a build; fiber stake x0.85 and C-band -$3.0B are the harshest without new evidence.
A9: supervisor | B9: 23.157632 | C9: 22.988548 | D9: 18.948128 | E9: 26.827961 | J9: 0 | K9: 3 | L9: EV/EBITDA 6.1 (ntm); P/E 8.3 (ntm); FCF yield 0.123 (ntm)

Sheet Sources
A1: T: where each input comes from (source numbers point to the list below; F ids to the SEC fact table)
A3: Input | B3: Value | C3: Basis | D3: Sources | E3: SEC fact ids | F3: Derivation
A4: driver:pp_subs | B4: Average postpaid phone subscribers (AT&T, Advanced Connectivity): base 73.4815 -> 74.95 / 76.18 / 77.05 M | C4: estimate | D4: 10, 5, 57 | F4: Base FY2025 = (72.749 + 74.214) / 2 = 73.4815M. FY2026: Dec-26 = 75.283 + Q4 adds ~0.40 = 75.68; avg (74.214 + 75.68) / 2 = 74.95. FY2027: +1.0M adds (2026 ~1.5M; Q3 adds slowed to 379k, Verizon steering to the top of its 750k-1M phone-add guide [57]) -> Dec-27 76.68, avg 76.18. FY2028: +0.75M (Starlink Mobile service start targeted end-2027) -> Dec-28 77.43, avg 77.05.
A5: driver:ws_arpu | B5: AC wireless service revenue per average postpaid phone: base 76.4183 -> 77.75 / 79.0 / 79.59 $/month | C5: estimate | D5: 9, 5, 7 | F5: Base 67,384 / 73.4815 / 12 = $76.42. FY2026 (52,118 + Q4 ~17,810) / 74.95 / 12 = $77.75 (+1.7%). Q3 2026 run rate 17,764 / avg Q3 subs 75.09M / 3 = $78.86, i.e. the April and June 2026 price actions are already in the exit rate; FY2027 = exit rate +0.2% fees = $79.00 (+1.6%); FY2028 +0.75% = $79.59 (no new list-price rise assumed with a fourth entrant due).
A6: driver:hi_subs | B6: Average consumer AT&T Fiber + Internet Air connections: base 10.928 -> 14.06 / 16.59 / 18.89 M | C6: estimate | D6: 10, 5, 7 | F6: Base (9.953 + 11.903) / 2 = 10.928M. FY2026 time-weighted for the Lumen subscribers added in Q1: quarter averages ~12.9 / 13.82 / 14.44 / 15.09 -> 14.06M (agent_2's derivation, checked against Sep-26 14.791M). FY2027: adds ~2.4M (2026 organic ~2.4M: Q1 ~0.52, Q2 0.555, Q3 0.696, Q4 ~0.6) -> Dec-26 15.391 (Sep-26 14.791 + Q4 ~0.6), Dec-27 17.79, avg (15.39 + 17.79) / 2 = 16.59. FY2028: adds ~2.2M -> Dec-28 19.99, avg 18.89.
A7: driver:hi_arpu | B7: Advanced home internet revenue per average connection: base 71.7576 -> 69.52 / 67.3 / 67.65 $/month | C7: estimate | D7: 9, 5, 7 | F7: Base 9,410 / 10.928 / 12 = $71.76. FY2026 (8,700 + Q4 ~3,030) / 14.06 / 12 = $69.52 (-3.1% blended; fiber alone -4%, Internet Air mix offsets). Q3 2026 2,975 / 14.44 / 3 = $68.66; Q4 exit ~$67.0. FY2027 $67.30 (+0.5% on the exit rate, 'relatively stable'); FY2028 $67.65 (+0.5%).
A8: driver:ac_m | B8: Advanced Connectivity EBITDA margin: base 0.3962 -> 0.4032 / 0.4125 / 0.4229 fraction | C8: estimate | D8: 9, 6, 4 | F8: Base 44,547 / 112,424 = 39.62%. Path set so AC EBITDA = 47,400 in FY2026 (35,920 + Q4 ~11,480 = Q4-25 10,968 x 1.047; Q4 carries device-launch and fiber go-to-market costs per the call) = +6.4%, +6.0% in FY2027 (50,244) and +5.5% in FY2028 (53,007), divided by the driven AC revenue 117,552 / 121,792 / 125,332: 0.4032 / 0.4125 / 0.4229. The +5.5% in 2028 follows from the driver path: AC service revenue +4.1% (2027) and +3.3% (2028) plus ~1pt a year of margin from cost removal. AC EBIT margin = ac_m - 15.6% AC D&A (Q3 2026 AC D&A 4,702 on AC revenue 29,481 = 15.95%, falling as D&A drops y/y).
A9: driver:cap_inv | B9: Capital investment (capex + vendor financing payments): base 22023 -> 23400 / 22800 / 22700 $M | C9: estimate | D9: 8, 6, 4, 7 | E9: F51 | F9: FY2026 16,786 + Q4 ~6,600 (Q3 5.6B; Q4 seasonally heavier) = 23.4B; FY2027 22.8B and FY2028 22.7B, upper half of the cut range: record lands at or above the first guide (FY2024 22.1 vs 21-22; FY2025 22.0 vs ~22), the 60M+ fiber-location target is unchanged.
A10: base revenue FY2025 and segment bases | B10: 125,648 = AC 112,424 (wireless service 67,384 + advanced home internet 9,410 + equipment 22,826 + business fiber 7,243 + business transitional 4,911 + other 650) + Legacy 8,472 + Latin America 4,379 + corporate 373 | C10: reported | D10: 9, 8 | E10: F3 | F10: Q4 2025 Ex.99.4 recast (AC lines opened this round); Latin America and corporate as in round 1 (sum to F3).
A11: Legacy segment | B11: revenue 6,319 / 4,613 / 3,229; EBITDA margin 32.1% / 20% / -5% (EBITDA 2,031 / 923 / -161); no Legacy D&A | C11: estimate | D11: 9, 5, 4, 7 | F11: FY2025 Legacy revenue 8,472, EBITDA 3,339 (Ex.99.4); 9M 2026 revenue 4,919, operating income = EBITDA 1,633, D&A 0 (Ex.99.2) (opened). FY2026 = 1,633 + Q4 ~398 (Q4-25 682, Ex.99.4, x 0.73 less ~$100M vendor settlements that hit Legacy, call) = 2,031. 2027 revenue -27%, margin 20% (cost removal lags the run-off); 2028 -30%, margin -5% (guide: Legacy EBITDA negative after 2027).
A12: Latin America (Mexico) and corporate | B12: Latin America revenue 4,948 / 841 / 0 at an 18% EBITDA margin (9M 2026 revenue 3,637); corporate EBITDA -2,130 a year (corporate D&A ~315 a year below EBITDA) | C12: estimate | D12: 5, 6, 2 | F12: Mexico sale signed 2026-10-13, close Q1 2027 (R17, opened). Corporate: 9M 2026 adjusted EBITDA 36,638 - AC 35,920 - Legacy 1,633 - Latin America 683 (Ex.99.3) = -1,598 -> ~-2,130 a year. Corporate D&A 9M 236 (14,910 - AC 14,094 - LatAm 580) -> ~315 a year, kept after the Mexico sale.
A13: D&A | B13: 19,703 / 19,315 / 19,867 (AC D&A 16.0% of AC revenue in 2026, 15.6% after; Latin America D&A 580 in 9M 2026 then nil; corporate D&A ~315 a year) | C13: estimate | D13: 6, 9, 5 | E13: F39 | F13: FY2025 AC D&A 19,959 (17.75% of AC revenue, Ex.99.4); 9M 2026 AC D&A 14,094 (16.3%), Q3 4,702 on AC revenue 29,481 (15.95%) (opened); 9M 2026 total D&A 14,910 (F39 derived) -> non-AC 816 = Latin America 580 (Ex.99.2/99.3; stopped in Q4 under held-for-sale accounting, call) + corporate ~236; corporate D&A ~315 a year continues in 2027-28 (subtracted in corporate_ebit, so EBITDA is unchanged).
A14: EPS bridge items (other income, interest, NCI, tax, average shares) | B14: other income 2,463 / 2,250 / 2,150; corporate D&A 315 a year in 2027-28; interest 7,700 / 8,050 / 7,950; NCI + preferred 1,644; tax 21.5%; average diluted shares 6,880 / 6,485 / 6,196M | C14: estimate | D14: 1, 6, 4, 14 | E14: F33 | F14: Q3 2026 interest 1,979 (10-Q, opened) x 4 = 7.9B run rate on 159.6B gross debt, debt due within one year 9,483 (10-Q) refinanced at higher rates (call: higher cash interest from higher gross debt and rates); NCI income 1,113 in 9M (-> ~1,500) + preferred dividends 143; other income calibrated so FY2026 EPS = 2.41 (guide '$2.40 range', 9M $1.86); shares: 6,745.5M diluted now, ~$7B a year buybacks at ~$22-23.5 less ~15M issuance. Gate fix: FY2026 other income recalibrated to ~2,463 so FY2026 EPS stays at 2.41 after the Legacy (-42), corporate (-30) and Q4 corporate D&A (-79) fixes; 2027-28 EPS now carries corporate D&A 315 a year.
A15: FCF bridge items (K = EBITDA - capital investment - FCF) | B15: 6,735 / 7,918 / 8,068 -> FCF 18,129 / 18,470 / 19,947 | C15: estimate | D15: 6, 7, 4 | F15: FY2026 FCF = 9M 12,129 (Ex.99.3) + Q4 ~6,000 (call) = 18,129; K2026 = 48,264 - 23,400 - 18,129. K2027 = K2026 + interest 350 + cash taxes 250 (call: 2026 cash taxes ~$750M under the 2025 tax law) + separation cash 650 (call: ~$800M charge, cash primarily 2027) - 67 other. K2028 = K2027 - 650 + 900 (cash taxes as the catch-up deductions run off) - 100 interest. Gate fix: corporate EBITDA -2,130 (was -2,100; see the corporate line) lowers 2027-28 EBITDA and FCF by ~30 each.
A16: net debt 2026-09-30 | B16: 149819 | C16: reported | D16: 6 | F16: Q3 2026 Ex.99.3 net debt $149,819M, 3.13x annualised adjusted EBITDA (opened); total debt 159,627 and cash 10,767 in the 10-Q balance sheet.
A17: net_debt_horizon (2027-10-23) | B17: 144260.0 | C17: estimate | D17: 6, 7, 4, 2, 14 | F17: Dec-26 = 149,819 - Q4 FCF 6,000 + dividend paid 2026-11-02 (0.2775 x 6,737M = 1,870) + Q4 buybacks ~2,500 (~$10B 2026 plan less 9M) + NCI/preferred ~410 = 148,600. Oct-23-2027 = 148,600 - 0.752 x 2027 FCF 18,470 (13,889: 9M 2026 was 66.9% of the year plus 23/92 of Q4's 33.1%) + three 2027 dividends 5,428 + buybacks 5,670 (0.81 x ~$7B) + NCI/preferred 1,337 - Mexico cash 2,000 x 0.9 - Mexico finance leases 1,209 x 0.9 leaving with the business = ~144,260.
A18: minorities | B18: 17985 | C18: reported | D18: 1 | F18: 10-Q balance sheet 2026-09-30: noncontrolling interest 15,979 + redeemable noncontrolling interest 2,006 (opened).
A19: preferred | B19: 2950 | C19: estimate | D19: 59, 60, 14 | F19: Derived: Series A 48,000 and Series C 70,000 shares outstanding at 2026-09-30 (10-Q R6) x $25,000 per share liquidation preference (10-K R26) = 1,200 + 1,750 = 2,950; quarterly dividends $312.50 / $296.875 per share (finviz) are consistent.
A20: shares | B20: now 6,745.5M (6,736.5M outstanding 2026-10-15 + ~9M dilutive); horizon 6,387M | C20: estimate | D20: 1, 4 | E20: F33 | F20: Cover 6,736,473,433 shares at 2026-10-15 (opened); 9M 2026 repurchases ~291M shares (10-Q). Q4 2026 ~$2.5B at ~$21.5 = 116M; 2027 to Oct-23 ~$5.67B at ~$22 = 258M; +15M stock-plan issuance -> 6,387M.
A21: Composite Fiber 37 stake adjustment | B21: 4,058 x 0.9 | C21: estimate | D21: 3, 2 | F21: R63 4,781 - 723 = 4,058 (opened); R17 JV terms (opened).
A22: Upper C-band spend adjustment | B22: -5,000 x 0.4 | C22: estimate | D22: 52, 24, 69 | F22: Auction 115 schedule (DA 26-769; statutory completion 2027-07-04). Size: AT&T ~$5B if it wins (2021 C-band, Auction 107: AT&T $23.4B for 1,621 licences, ~80 MHz in 95% of the country per Evercore, Light Reading; Auction 115 offers 160 MHz); p 0.4.
A23: EV/EBITDA NTM horizon multiple | B23: 6.1x on EV incl. NCI and preferred, excl. the fiber stake (decided by Kilian 2026-10-26: keep) | C23: judgment | D23: 19, 20, 27, 28, 29, 30, 31, 32, 33, 39, 40, 41, 42, 55 | F23: AT&T today: EV on our basis (141.2 + 149.8 + 18.0 + 2.95 - 3.65 = 308.3B) / consensus NTM EBITDA 49.5B = 6.23x; on the peers' basis 5.78x (MarketScreener 2027E). 6.1x = 5.69x on the peers' basis: -5% to the ex-DT peer benchmark 5.98x (11 incumbents; +3% to the 12-peer 5.52x incl. DT, reference only).
A24: P/E NTM horizon multiple and EPS | B24: 8.3x on driver-linked NTM EPS (0.19 x 2.66 + 0.81 x 2.91) | C24: judgment | D24: 21, 19, 20, 28 | F24: Today's market level on one consensus basis (Zacks via Nasdaq API): $20.93 / (0.19 x $2.38 + 0.81 x $2.54) = 8.34x -> 8.3x (rounded down as before); peer median 10.55x is indicative (EPS basis unstated on MarketScreener); structural discount (NCI/preferred claims ~$1.6B a year, 3.1x leverage, SpaceX exposure).
A25: FCF yield horizon multiple and FCF/share | B25: 12.3% on driver-linked NTM FCF to common per horizon share | C25: judgment | D25: 19, 6, 7 | F25: Today's level on consensus NTM FCF to common: (0.19 x 17.97B + 0.81 x 19.24B - 1.65B) / 6,745.5M = $2.57 / $20.93 = 12.3%.
A26: tax rate | B26: 0.215 | C26: estimate | D26: 6, 5 | F26: Adjusted 9M 2026 effective rate ~21.2% (agent_5 from Ex.99.2/99.3).
A27: leg weights | B27: EV/EBITDA 0.5, P/E 0.35, FCF yield 0.15 | C27: judgment | D27: 56 | F27: Forecasters' median weights (EV/EBITDA 0.45-0.5, P/E 0.30-0.40, FCF 0.15-0.20); the WRDS blend-weight study tests DCF vs forward P/E only, so no evidence moves them.
A29: # | B29: Source | C29: Date | D29: Link
A30: 1 | B30: AT&T Form 10-Q for the quarter ended 2026-09-30 | C30: 2026-10-21 | D30: https://www.sec.gov/Archives/edgar/data/732717/000073271726000372/t-20260930.htm
A31: 2 | B31: AT&T 10-Q Q3 2026, XBRL report R17: Acquisitions, Dispositions and Other Adjustments (Mexico sale, Composite Fiber 37 JV, EchoStar) | C31: 2026-10-21 | D31: https://www.sec.gov/Archives/edgar/data/732717/000073271726000372/R17.htm
A32: 3 | B32: AT&T 10-Q Q3 2026, XBRL report R63: assets and liabilities of discontinued operations (Lumen Mass Markets / Forged Fiber) | C32: 2026-10-21 | D32: https://www.sec.gov/Archives/edgar/data/732717/000073271726000372/R63.htm
A33: 4 | B33: AT&T 8-K Ex.99.1: Q3 2026 earnings release and outlook | C33: 2026-10-21 | D33: https://www.sec.gov/Archives/edgar/data/732717/000073271726000370/t-3q2026exhibit991.htm
A34: 5 | B34: AT&T 8-K Ex.99.2: Q3 2026 financial and operating data | C34: 2026-10-21 | D34: https://www.sec.gov/Archives/edgar/data/732717/000073271726000370/t-3q2026exhibit992.htm
A35: 6 | B35: AT&T 8-K Ex.99.3: Q3 2026 non-GAAP reconciliations (FCF, capital investment, adjusted EBITDA, net debt) | C35: 2026-10-21 | D35: https://www.sec.gov/Archives/edgar/data/732717/000073271726000370/t-3q2026exhibit993.htm
A36: 7 | B36: AT&T Q3 2026 earnings call transcript (LSEG StreetEvents, AT&T investor relations) | C36: 2026-10-21 | D36: https://investors.att.com/~/media/Files/A/ATT-IR-V2/financial-reports/quarterly-earnings/2026/3Q-2026/t-usq-transcript-2026-10-21.pdf
A37: 8 | B37: AT&T 8-K Ex.99.1: Q4 2025 earnings release (FY2025 actuals; first 2026 and 2027-28 outlook) | C37: 2026-01-28 | D37: https://www.sec.gov/Archives/edgar/data/732717/000073271726000047/t-4q2025exhibit991.htm
A38: 9 | B38: AT&T 8-K Ex.99.4: FY2025 supplemental segment information recast to Advanced Connectivity / Legacy | C38: 2026-01-28 | D38: https://www.sec.gov/Archives/edgar/data/732717/000073271726000047/t-4q2025exhibit994.htm
A39: 10 | B39: AT&T 8-K Ex.99.2: Q4 2025 financial and operating data (year-end subscribers) | C39: 2026-01-28 | D39: https://www.sec.gov/Archives/edgar/data/732717/000073271726000047/t-4q2025exhibit992.htm
A40: 11 | B40: AT&T 8-K Ex.99.1: Q4 2024 earnings release (FY2024 actuals; 2025 outlook) | C40: 2025-01-27 | D40: https://www.sec.gov/Archives/edgar/data/732717/000073271725000007/t-4q2024exhibit991.htm
A41: 12 | B41: AT&T 8-K Ex.99.1: Q4 2023 earnings release (FY2023 actuals; 2024 outlook) | C41: 2024-01-24 | D41: https://www.sec.gov/Archives/edgar/data/732717/000073271724000006/t-4q2023exhibit991.htm
... A100: 71 | B100: Cord Cutters News (Luke Bouma): FCC Oct-29-2026 agenda, SCS NPRM would open an additional 482 MHz | C100: 2026-10 | D100: https://cordcuttersnews.com/fcc-agenda-targets-better-wireless-coverage-stronger-equipment-checks-and-rural-broadband-oversight/?amp=1
A102: Fact id | B102: Figure | C102: Value | D102: Filing
A103: F1 | B103: revenue FY ending 2023-12-31 (us-gaap:Revenues) | C103: 122428000000 | D103: https://www.sec.gov/Archives/edgar/data/732717/000073271726000120/
A104: F2 | B104: revenue FY ending 2024-12-31 (us-gaap:Revenues) | C104: 122336000000 | D104: https://www.sec.gov/Archives/edgar/data/732717/000073271726000120/
A105: F3 | B105: revenue FY ending 2025-12-31 (us-gaap:Revenues) | C105: 125648000000 | D105: https://www.sec.gov/Archives/edgar/data/732717/000073271726000120/
A106: F4 | B106: revenue YTD 2026-01-01 to 2026-09-30 | C106: 95386000000 | D106: https://www.sec.gov/Archives/edgar/data/732717/000073271726000372/
A107: F5 | B107: revenue prior-year YTD 2025-01-01 to 2025-09-30 | C107: 92182000000 | D107: https://www.sec.gov/Archives/edgar/data/732717/000073271726000372/
A108: F6 | B108: revenue TTM to 2026-09-30 | C108: 128852000000
A109: F7 | B109: revenue quarter 2026-07-01 to 2026-09-30 | C109: 32322000000 | D109: https://www.sec.gov/Archives/edgar/data/732717/000073271726000372/
A110: F8 | B110: operating_income FY ending 2023-12-31 (us-gaap:OperatingIncomeLoss) | C110: 23461000000 | D110: https://www.sec.gov/Archives/edgar/data/732717/000073271726000120/
A111: F9 | B111: operating_income FY ending 2024-12-31 (us-gaap:OperatingIncomeLoss) | C111: 19049000000 | D111: https://www.sec.gov/Archives/edgar/data/732717/000073271726000120/
A112: F10 | B112: operating_income FY ending 2025-12-31 (us-gaap:OperatingIncomeLoss) | C112: 24162000000 | D112: https://www.sec.gov/Archives/edgar/data/732717/000073271726000120/
A113: F11 | B113: operating_income YTD 2026-01-01 to 2026-09-30 | C113: 17791000000 | D113: https://www.sec.gov/Archives/edgar/data/732717/000073271726000372/
A114: F12 | B114: operating_income prior-year YTD 2025-01-01 to 2025-09-30 | C114: 18374000000 | D114: https://www.sec.gov/Archives/edgar/data/732717/000073271726000372/
A115: F13 | B115: operating_income TTM to 2026-09-30 | C115: 23579000000
A116: F14 | B116: operating_income quarter 2026-07-01 to 2026-09-30 | C116: 4095000000 | D116: https://www.sec.gov/Archives/edgar/data/732717/000073271726000372/
A117: F15 | B117: net_income FY ending 2023-12-31 (us-gaap:NetIncomeLoss) | C117: 14400000000 | D117: https://www.sec.gov/Archives/edgar/data/732717/000073271726000120/
A118: F16 | B118: net_income FY ending 2024-12-31 (us-gaap:NetIncomeLoss) | C118: 10948000000 | D118: https://www.sec.gov/Archives/edgar/data/732717/000073271726000120/
A119: F17 | B119: net_income FY ending 2025-12-31 (us-gaap:NetIncomeLoss) | C119: 21953000000 | D119: https://www.sec.gov/Archives/edgar/data/732717/000073271726000120/
A120: F18 | B120: net_income YTD 2026-01-01 to 2026-09-30 | C120: 9347000000 | D120: https://www.sec.gov/Archives/edgar/data/732717/000073271726000372/
A121: F19 | B121: net_income prior-year YTD 2025-01-01 to 2025-09-30 | C121: 18165000000 | D121: https://www.sec.gov/Archives/edgar/data/732717/000073271726000372/
A122: F20 | B122: net_income TTM to 2026-09-30 | C122: 13135000000
A123: F21 | B123: net_income quarter 2026-07-01 to 2026-09-30 | C123: 891000000 | D123: https://www.sec.gov/Archives/edgar/data/732717/000073271726000372/
A124: F22 | B124: eps_diluted FY ending 2023-12-31 (us-gaap:EarningsPerShareDiluted) | C124: 1.97 | D124: https://www.sec.gov/Archives/edgar/data/732717/000073271726000120/
A125: F23 | B125: eps_diluted FY ending 2024-12-31 (us-gaap:EarningsPerShareDiluted) | C125: 1.49 | D125: https://www.sec.gov/Archives/edgar/data/732717/000073271726000120/
A126: F24 | B126: eps_diluted FY ending 2025-12-31 (us-gaap:EarningsPerShareDiluted) | C126: 3.04 | D126: https://www.sec.gov/Archives/edgar/data/732717/000073271726000120/
A127: F25 | B127: eps_diluted YTD 2026-01-01 to 2026-09-30 | C127: 1.33 | D127: https://www.sec.gov/Archives/edgar/data/732717/000073271726000372/
A128: F26 | B128: eps_diluted prior-year YTD 2025-01-01 to 2025-09-30 | C128: 2.51 | D128: https://www.sec.gov/Archives/edgar/data/732717/000073271726000372/
A129: F27 | B129: eps_diluted quarter 2026-07-01 to 2026-09-30 | C129: 0.12 | D129: https://www.sec.gov/Archives/edgar/data/732717/000073271726000372/
A130: F28 | B130: diluted_shares_wavg FY ending 2023-12-31 (us-gaap:WeightedAverageNumberOfDilutedSharesOutstanding) | C130: 7258000000 | D130: https://www.sec.gov/Archives/edgar/data/732717/000073271726000120/
A131: F29 | B131: diluted_shares_wavg FY ending 2024-12-31 (us-gaap:WeightedAverageNumberOfDilutedSharesOutstanding) | C131: 7204000000 | D131: https://www.sec.gov/Archives/edgar/data/732717/000073271726000120/
A132: F30 | B132: diluted_shares_wavg FY ending 2025-12-31 (us-gaap:WeightedAverageNumberOfDilutedSharesOutstanding) | C132: 7179000000 | D132: https://www.sec.gov/Archives/edgar/data/732717/000073271726000120/
A133: F31 | B133: diluted_shares_wavg YTD 2026-01-01 to 2026-09-30 | C133: 6938000000 | D133: https://www.sec.gov/Archives/edgar/data/732717/000073271726000372/
A134: F32 | B134: diluted_shares_wavg prior-year YTD 2025-01-01 to 2025-09-30 | C134: 7203000000 | D134: https://www.sec.gov/Archives/edgar/data/732717/000073271726000372/
... A140: F38 | B140: d_and_a prior-year YTD 2025-01-01 to 2025-09-30 | C140: 15758000000 | D140: https://www.sec.gov/Archives/edgar/data/732717/000073271726000372/
A141: F39 | B141: d_and_a TTM to 2026-09-30 | C141: 20038000000
A142: F40 | B142: d_and_a quarter 2026-07-01 to 2026-09-30 | C142: 4978000000 | D142: https://www.sec.gov/Archives/edgar/data/732717/000073271726000372/
A143: F41 | B143: sbc FY ending 2023-12-31 (us-gaap:AllocatedShareBasedCompensationExpense) | C143: 479000000 | D143: https://www.sec.gov/Archives/edgar/data/732717/000073271726000120/
A144: F42 | B144: sbc FY ending 2024-12-31 (us-gaap:AllocatedShareBasedCompensationExpense) | C144: 505000000 | D144: https://www.sec.gov/Archives/edgar/data/732717/000073271726000120/
A145: F43 | B145: sbc FY ending 2025-12-31 (us-gaap:AllocatedShareBasedCompensationExpense) | C145: 536000000 | D145: https://www.sec.gov/Archives/edgar/data/732717/000073271726000120/
A146: F44 | B146: sbc TTM to 2025-12-31 (latest filing is the annual report) | C146: 536000000
A147: F45 | B147: cfo FY ending 2023-12-31 (us-gaap:NetCashProvidedByUsedInOperatingActivities) | C147: 38314000000 | D147: https://www.sec.gov/Archives/edgar/data/732717/000073271726000120/
A148: F46 | B148: cfo FY ending 2024-12-31 (us-gaap:NetCashProvidedByUsedInOperatingActivities) | C148: 38771000000 | D148: https://www.sec.gov/Archives/edgar/data/732717/000073271726000120/
A149: F47 | B149: cfo FY ending 2025-12-31 (us-gaap:NetCashProvidedByUsedInOperatingActivities) | C149: 40284000000 | D149: https://www.sec.gov/Archives/edgar/data/732717/000073271726000120/
A150: F48 | B150: cfo TTM to 2025-12-31 (latest filing is the annual report) | C150: 40284000000
A151: F49 | B151: capex FY ending 2023-12-31 (us-gaap:PaymentsToAcquireProductiveAssets) | C151: 17853000000 | D151: https://www.sec.gov/Archives/edgar/data/732717/000073271726000120/
A152: F50 | B152: capex FY ending 2024-12-31 (us-gaap:PaymentsToAcquireProductiveAssets) | C152: 20263000000 | D152: https://www.sec.gov/Archives/edgar/data/732717/000073271726000120/
A153: F51 | B153: capex FY ending 2025-12-31 (us-gaap:PaymentsToAcquireProductiveAssets) | C153: 20842000000 | D153: https://www.sec.gov/Archives/edgar/data/732717/000073271726000120/
A154: F52 | B154: capex YTD 2026-01-01 to 2026-09-30 | C154: 15638000000 | D154: https://www.sec.gov/Archives/edgar/data/732717/000073271726000372/
A155: F53 | B155: capex prior-year YTD 2025-01-01 to 2025-09-30 | C155: 14061000000 | D155: https://www.sec.gov/Archives/edgar/data/732717/000073271726000372/
A156: F54 | B156: capex TTM to 2026-09-30 | C156: 22419000000
A157: F55 | B157: capex quarter 2026-01-01 to 2026-03-31 | C157: 4877000000 | D157: https://www.sec.gov/Archives/edgar/data/732717/000073271726000206/
A158: F56 | B158: buybacks FY ending 2023-12-31 (us-gaap:PaymentsForRepurchaseOfCommonStock) | C158: 194000000 | D158: https://www.sec.gov/Archives/edgar/data/732717/000073271726000120/
A159: F57 | B159: buybacks FY ending 2024-12-31 (us-gaap:PaymentsForRepurchaseOfCommonStock) | C159: 215000000 | D159: https://www.sec.gov/Archives/edgar/data/732717/000073271726000120/
A160: F58 | B160: buybacks FY ending 2025-12-31 (us-gaap:PaymentsForRepurchaseOfCommonStock) | C160: 4500000000 | D160: https://www.sec.gov/Archives/edgar/data/732717/000073271726000120/
A161: F59 | B161: buybacks YTD 2026-01-01 to 2026-09-30 | C161: 7472000000 | D161: https://www.sec.gov/Archives/edgar/data/732717/000073271726000372/
A162: F60 | B162: buybacks prior-year YTD 2025-01-01 to 2025-09-30 | C162: 2669000000 | D162: https://www.sec.gov/Archives/edgar/data/732717/000073271726000372/
A163: F61 | B163: buybacks TTM to 2026-09-30 | C163: 9303000000
A164: F62 | B164: buybacks quarter 2026-01-01 to 2026-03-31 | C164: 2475000000 | D164: https://www.sec.gov/Archives/edgar/data/732717/000073271726000206/
A165: F63 | B165: dividends_paid FY ending 2023-12-31 (us-gaap:PaymentsOfDividendsCommonStock) | C165: 8136000000 | D165: https://www.sec.gov/Archives/edgar/data/732717/000073271726000120/
A166: F64 | B166: dividends_paid FY ending 2024-12-31 (us-gaap:PaymentsOfDividendsCommonStock) | C166: 8208000000 | D166: https://www.sec.gov/Archives/edgar/data/732717/000073271726000120/
...
