Workbook

Sheet Summary
A1: MCHP standard model (trial) · research run 2026-09-25
A2: The supervisor's reconciled assumption set as a live model. Trial: shown beside the blended page target, not used for trade levels until its weight is decided. Edit blue cells on Model (drivers) and Valuation (assumptions).
A3: Price target box | B3: Value
A4: Live price | B4: =IFERROR(GOOGLEFINANCE("MCHP","price"),Valuation!$B$68)
A5: Price as of | B5: =NOW()
A6: Model target (12-month median) | B6: =Distribution!$B$13
A7: Upside to model target from live price | B7: =B6/B4-1
A8: Fair value at target date (no scenario deltas) | B8: =Valuation!$D$8
A9: Probability-weighted mean | B9: =Distribution!$B$10
A10: 10th percentile | B10: =Distribution!$B$14
A11: 25th percentile | B11: =Distribution!$B$15
A12: 75th percentile | B12: =Distribution!$B$16
A13: 90th percentile | B13: =Distribution!$B$17
A14: Target date | B14: =Valuation!$B$46
A15: Price at the run | B15: =Valuation!$B$68
A16: Blended page target (options 67% + agents 33%, not live) | B16: 85.7094
A17: Supervisor fair value (its own methods) | B17: 85
A18: Thesis break price (supervisor) | B18: 55
A19: Supervisor confidence | B19: low
A21: Key estimates | B21: FY2026A | C21: =Model!E5 | D21: =Model!F5
A22: Net sales | B22: =IF(Model!D11="","",Model!D11) | C22: =Model!E11 | D22: =Model!F11
A23: % YoY | B23: =IF(Model!D12="","",Model!D12) | C23: =Model!E12 | D23: =Model!F12
A24: Pretax margin | B24: =IF(Model!D22="","",Model!D22) | C24: =Model!E22 | D24: =Model!F22
A25: Diluted EPS (model) | B25: =IF(Model!D29="","",Model!D29) | C25: =Model!E29 | D25: =Model!F29
A26: % YoY | B26: =IF(Model!D30="","",Model!D30) | C26: =Model!E30 | D26: =Model!F30
A27: Free cash flow to firm | B27: =IF(Model!D39="","",Model!D39) | C27: =Model!E39 | D27: =Model!F39
A29: Valuation method | B29: Value per share | C29: Weight
A30: =Valuation!A4 | B30: =Valuation!D4 | C30: =Valuation!E4
A31: =Valuation!A5 | B31: =Valuation!D5 | C31: =Valuation!E5
A32: =Valuation!A6 | B32: =Valuation!D6 | C32: =Valuation!E6
A33: =Valuation!A7 | B33: =Valuation!D7 | C33: =Valuation!E7
A35: Scenario | B35: Probability | C35: Value at target date | D35: What has to happen
A36: =Distribution!A4 | B36: =Distribution!B4 | C36: =Distribution!C4 | D36: =Distribution!D4
A37: =Distribution!A5 | B37: =Distribution!B5 | C37: =Distribution!C5 | D37: =Distribution!D5
A38: =Distribution!A6 | B38: =Distribution!B6 | C38: =Distribution!C6 | D38: =Distribution!D6
A40: Price at target date | B40: Probability above
A41: =ROUND(Valuation!$B$68*0.7,0) | B41: =SUMPRODUCT(Distribution!$B$4:$B$6,1-NORMSDIST((LN(A41)-LN(Distribution!$C$4:$C$6))/Distribution!$B$9))
A42: =ROUND(Valuation!$B$68*0.8,0) | B42: =SUMPRODUCT(Distribution!$B$4:$B$6,1-NORMSDIST((LN(A42)-LN(Distribution!$C$4:$C$6))/Distribution!$B$9))
A43: =ROUND(Valuation!$B$68*0.9,0) | B43: =SUMPRODUCT(Distribution!$B$4:$B$6,1-NORMSDIST((LN(A43)-LN(Distribution!$C$4:$C$6))/Distribution!$B$9))
A44: =ROUND(Valuation!$B$68*1.0,0) | B44: =SUMPRODUCT(Distribution!$B$4:$B$6,1-NORMSDIST((LN(A44)-LN(Distribution!$C$4:$C$6))/Distribution!$B$9))
A45: =ROUND(Valuation!$B$68*1.1,0) | B45: =SUMPRODUCT(Distribution!$B$4:$B$6,1-NORMSDIST((LN(A45)-LN(Distribution!$C$4:$C$6))/Distribution!$B$9))
A46: =ROUND(Valuation!$B$68*1.2,0) | B46: =SUMPRODUCT(Distribution!$B$4:$B$6,1-NORMSDIST((LN(A46)-LN(Distribution!$C$4:$C$6))/Distribution!$B$9))
A47: =ROUND(Valuation!$B$68*1.3,0) | B47: =SUMPRODUCT(Distribution!$B$4:$B$6,1-NORMSDIST((LN(A47)-LN(Distribution!$C$4:$C$6))/Distribution!$B$9))
A48: =ROUND(Valuation!$B$68*1.5,0) | B48: =SUMPRODUCT(Distribution!$B$4:$B$6,1-NORMSDIST((LN(A48)-LN(Distribution!$C$4:$C$6))/Distribution!$B$9))
A50: Model checks | B50: Status
A51: Scenario probabilities sum to 100% | B51: =IF(ABS(Distribution!B8-1)<0.005,"ok","FLAG: "&TEXT(Distribution!B8,"0.0%"))
A52: WACC exceeds terminal growth by 1 point or more | B52: =IF('Calc - fair value'!B55="ok","ok","FLAG")
A53: Projection runs a full year past the target date | B53: =IF('Calc - fair value'!B56="ok","ok","FLAG")
A54: Method weights add up to more than zero | B54: =IF(SUM(Valuation!E4:E7)>0,"ok","FLAG")
A55: Terminal value under 85% of the DCF | B55: =IF('Calc - fair value'!B46<0.85,"ok","note: "&TEXT('Calc - fair value'!B46,"0%")&" of the DCF is terminal value")
A56: Matches the engine run at publication (target, fair value) | B56: =IF(AND(ABS(Distribution!$B$13-85.4015)<0.01,ABS(Valuation!$D$8-85.3236)<0.01),"ok","inputs edited since publication")
A57: All checks | B57: =IF(COUNTIF(B51:B56,"ok")=6,"all ok",6-COUNTIF(B51:B56,"ok")&" to look at")

Sheet Model
A1: MCHP: annual model, base case
A2: (M of US dollars except per share; fiscal years named by the calendar year they end in)
A3: Blue = input · black = formula · green = link to another tab · actuals from SEC filings (fact ids in the last column, links on Sources)
A5: Fiscal year | B5: FY2024A | C5: FY2025A | D5: FY2026A | E5: FY2027E | F5: FY2028E | G5: FY2029E | H5: Source / note
A6: Period end | B6: 45382 | C6: 45747 | D6: 46112 | E6: =IF(DAY(Valuation!$B$50+1)=1,EOMONTH(Valuation!$B$50,12*E7),EDATE(Valuation!$B$50,12*E7)) | F6: =IF(DAY(Valuation!$B$50+1)=1,EOMONTH(Valuation!$B$50,12*F7),EDATE(Valuation!$B$50,12*F7)) | G6: =IF(DAY(Valuation!$B$50+1)=1,EOMONTH(Valuation!$B$50,12*G7),EDATE(Valuation!$B$50,12*G7))
A7: Projection year | B7: -2 | C7: -1 | D7: 0 | E7: 1 | F7: 2 | G7: 3
A10: Sales
A11: Net sales | B11: 7634.4 | C11: 4401.6 | D11: 4713.1 | E11: =Valuation!$B$51*(1+E48) | F11: =E11*(1+F48) | G11: =F11*(1+G48) | H11: SEC XBRL F1, F2, F3
A12: % YoY | C12: =IF(OR(C11="",B11="",B11=0),"",C11/B11-1) | D12: =IF(OR(D11="",C11="",C11=0),"",D11/C11-1) | E12: =E11/Valuation!$B$51-1 | F12: =F11/E11-1 | G12: =G11/F11-1
A14: Operating profit
A15: EBIT (operating income) | E15: =E11*E49 | F15: =F11*F49 | G15: =G11*G49
A16: EBIT margin | E16: =E15/E11 | F16: =F15/F11 | G16: =G15/G11
A17: D&A | B17: 879.5 | C17: 750.1 | D17: 689.3 | E17: =E11*E51 | F17: =F11*F51 | G17: =G11*G51 | H17: SEC XBRL F34, F35, F36
A18: EBITDA | E18: =E15+E17 | F18: =F15+F17 | G18: =G15+G17
A19: EBITDA margin | E19: =E18/E11 | F19: =F18/F11 | G19: =G18/G11
A20: Net interest income / (expense) | E20: =-Valuation!$B$59*Valuation!$B$57 | F20: =-Valuation!$B$59*E45 | G20: =-Valuation!$B$59*F45 | H20: rate x prior year-end net debt (memo roll)
A21: Pretax income | B21: 2365.9 | C21: 38.9 | D21: 273.5 | E21: =E15+E20 | F21: =F15+F20 | G21: =G15+G20 | H21: SEC XBRL F87, F88, F89
A22: Pretax margin | B22: =B21/B11 | C22: =C21/C11 | D22: =D21/D11 | E22: =E21/E11 | F22: =F21/F11 | G22: =G21/G11
A23: Income tax | B23: 459 | C23: 39.4 | D23: 43.5 | E23: =E21*E50 | F23: =F21*F50 | G23: =G21*G50 | H23: SEC XBRL F80, F81, F82
A24: Effective tax rate | B24: =B23/B21 | C24: =C23/C21 | D24: =D23/D21 | E24: =E23/E21 | F24: =F23/F21 | G24: =G23/G21
A25: Net income | B25: 1906.9 | C25: -0.5 | D25: 230 | E25: =E21-E23 | F25: =F21-F23 | G25: =G21-G23 | H25: SEC XBRL F15, F16, F17
A26: % YoY | C26: =IF(OR(C25="",B25="",B25=0),"",C25/B25-1) | D26: =IF(OR(D25="",C25="",C25=0),"",D25/C25-1) | E26: =IF(OR(D25="",D25=0),"",E25/D25-1) | F26: =IF(OR(E25="",E25=0),"",F25/E25-1) | G26: =IF(OR(F25="",F25=0),"",G25/F25-1)
A27: Diluted shares (M, average) | B27: 548 | C27: 537.3 | D27: 545.2 | E27: =Valuation!$B$61*(1+Valuation!$B$63)^(E7-0.5-((Valuation!$B$62-Valuation!$B$50)/365.25)) | F27: =Valuation!$B$61*(1+Valuation!$B$63)^(F7-0.5-((Valuation!$B$62-Valuation!$B$50)/365.25)) | G27: =Valuation!$B$61*(1+Valuation!$B$63)^(G7-0.5-((Valuation!$B$62-Valuation!$B$50)/365.25)) | H27: diluted count rolled at the annual change to mid-year
A28: % YoY | C28: =IF(OR(C27="",B27="",B27=0),"",C27/B27-1) | D28: =IF(OR(D27="",C27="",C27=0),"",D27/C27-1) | E28: =IF(OR(D27="",D27=0),"",E27/D27-1) | F28: =IF(OR(E27="",E27=0),"",F27/E27-1) | G28: =IF(OR(F27="",F27=0),"",G27/F27-1)
A29: Diluted EPS | B29: 3.48 | C29: -0.01 | D29: 0.22 | E29: =E25/E27 | F29: =F25/F27 | G29: =G25/G27 | H29: SEC XBRL F22, F23, F24
A30: % YoY | C30: =IF(OR(C29="",B29="",B29=0),"",C29/B29-1) | D30: =IF(OR(D29="",C29="",C29=0),"",D29/C29-1) | E30: =IF(OR(D29="",D29=0),"",E29/D29-1) | F30: =IF(OR(E29="",E29=0),"",F29/E29-1) | G30: =IF(OR(F29="",F29=0),"",G29/F29-1)
A32: Cash flow
A33: NOPAT (EBIT x (1 - tax)) | E33: =E15*(1-E50) | F33: =F15*(1-F50) | G33: =G15*(1-G50)
A34: + D&A | B34: =B17 | C34: =C17 | D34: =D17 | E34: =E17 | F34: =F17 | G34: =G17
A35: - Capex | B35: 285.1 | C35: 126 | D35: 91.1 | E35: =E11*E52 | F35: =F11*F52 | G35: =G11*G52 | H35: SEC XBRL F55, F56, F57
A36: Capex % of sales | B36: =B35/B11 | C36: =C35/C11 | D36: =D35/D11 | E36: =E35/E11 | F36: =F35/F11 | G36: =G35/G11
A37: - Working capital increase | E37: =E53*(E11-Valuation!$B$51) | F37: =F53*(F11-E11) | G37: =G53*(G11-F11)
A38: - Stock comp (adjusted EBIT only) | E38: =IF(AND(Valuation!$B$48="adjusted",Valuation!$B$49="cost"),E42*(1-E50),0) | F38: =IF(AND(Valuation!$B$48="adjusted",Valuation!$B$49="cost"),F42*(1-F50),0) | G38: =IF(AND(Valuation!$B$48="adjusted",Valuation!$B$49="cost"),G42*(1-G50),0)
A39: Free cash flow to firm | E39: =E33+E34-E35-E37-E38 | F39: =F33+F34-F35-F37-F38 | G39: =G33+G34-G35-G37-G38 | H39: what the DCF discounts (Calc tabs)
A40: Operating cash flow (reported) | B40: 2892.7 | C40: 898.1 | D40: 962.1 | H40: SEC XBRL F48, F49, F50
A41: FCF (operating cash flow - capex) | B41: =B40-B35 | C41: =C40-C35 | D41: =D40-D35
A42: Stock comp (memo) | B42: 177.5 | C42: 180.4 | D42: 255.4 | E42: =E11*E54 | F42: =F11*F54 | G42: =G11*G54 | H42: SEC XBRL F41, F42, F43
A43: Buybacks + dividends + other uses | B43: 1893.6 | C43: 1072.2 | D43: 984 | E43: =E11*E56+E55+E57 | F43: =F11*F56+F55+F57 | G43: =G11*G56+G55+G57 | H43: SEC XBRL F62, F66, F63, F67, F64, F68
A44: % of sales | B44: =B43/B11 | C44: =C43/C11 | D44: =D43/D11 | E44: =E43/E11 | F44: =F43/F11 | G44: =G43/G11
A45: Net debt / (net cash), year end (memo) | E45: =Valuation!$B$57-E39-E20*(1-E50)+E43 | F45: =E45-F39-F20*(1-F50)+F43 | G45: =F45-G39-G20*(1-G50)+G43 | H45: rolled from the balance-date figure; feeds interest only
A47: Drivers (blue = input; a year left black carries the prior year)
A48: Revenue growth | C48: =C12 | D48: =D12 | E48: 0.33568 | F48: 0.1755 | G48: 0.0419
A49: EBIT margin | E49: 0.3808 | F49: 0.4 | G49: =F49
A50: Tax rate | B50: =B24 | C50: =C24 | D50: =D24 | E50: 0.075 | F50: 0.08 | G50: =F50
A51: D&A % revenue | B51: =B17/B11 | C51: =C17/C11 | D51: =D17/D11 | E51: 0.0274 | F51: 0.0274 | G51: =F51
A52: Capex % revenue | B52: =B36 | C52: =C36 | D52: =D36 | E52: 0.01689 | F52: 0.01689 | G52: =F52
A53: Working capital % of revenue increase | E53: 0.1245 | F53: 0.1245 | G53: =F53
A54: Stock comp % revenue | B54: =B42/B11 | C54: =C42/C11 | D54: =D42/D11 | E54: 0.0542 | F54: 0.0542 | G54: =F54
A55: Shareholder returns ($) | E55: 0 | F55: 0 | G55: =F55
A56: Shareholder returns % revenue | B56: =B44 | C56: =C44 | D56: =D44 | E56: 0 | F56: =E56 | G56: =F56
A57: Other uses of cash ($: M&A, investments) | E57: 0 | F57: =E57 | G57: =F57
A58: Adj. EBITDA addback % revenue | E58: 0 | F58: 0 | G58: =F58
A60: Versus company guidance and street consensus
A61: Guidance: tax rate (non-GAAP (Q2 guide $42.2-44.3M on $562.2-590.7M pretax)), midpoint | E61: =AVERAGE(0.075,0.075) | H61: 0.075 to 0.075; as of 2026-08-06; source 3, 10 (Microchip Q1 FY2027 results press release (8-K Ex. 99.1))
A62: Model vs guidance midpoint | E62: =(E24-E61)*10000 | H62: =IF(E24<0.075,"below the guided range",IF(E24>0.075,"above the guided range","inside the guided range"))
A63: Guidance: capex ($M, approximate (Sep quarter $20-25M)), midpoint | E63: =AVERAGE(100.0,100.0) | H63: 100 to 100; as of 2026-08-06; source 3 (Microchip Q1 FY2027 results press release (8-K Ex. 99.1))

Sheet Valuation
A1: MCHP: valuation and price target derivation
A2: Value per share at the target date = weighted methods below; the 12-month target is the median of the scenario mix (Distribution tab).
A3: Method | B3: Multiple | C3: Metric at target date | D3: Value per share | E3: Weight | F3: Contribution
A4: ='Calc - fair value'!A67 | B4: =IF('Calc - fair value'!C67="","",'Calc - fair value'!C67) | C4: =IF('Calc - fair value'!I67="","",'Calc - fair value'!I67) | D4: ='Calc - fair value'!F67 | E4: ='Calc - fair value'!G67 | F4: =D4*E4/SUM($E$4:$E$7)
A5: ='Calc - fair value'!A68 | B5: =IF('Calc - fair value'!C68="","",'Calc - fair value'!C68) | C5: =IF('Calc - fair value'!I68="","",'Calc - fair value'!I68) | D5: ='Calc - fair value'!F68 | E5: ='Calc - fair value'!G68 | F5: =D5*E5/SUM($E$4:$E$7)
A6: ='Calc - fair value'!A69 | B6: =IF('Calc - fair value'!C69="","",'Calc - fair value'!C69) | C6: =IF('Calc - fair value'!I69="","",'Calc - fair value'!I69) | D6: ='Calc - fair value'!F69 | E6: ='Calc - fair value'!G69 | F6: =D6*E6/SUM($E$4:$E$7)
A7: ='Calc - fair value'!A70 | B7: =IF('Calc - fair value'!C70="","",'Calc - fair value'!C70) | C7: =IF('Calc - fair value'!I70="","",'Calc - fair value'!I70) | D7: ='Calc - fair value'!F70 | E7: ='Calc - fair value'!G70 | F7: =D7*E7/SUM($E$4:$E$7)
A8: Fair value per share at target date | D8: ='Calc - fair value'!$F$71 | F8: =SUM(F4:F7)
A10: 12-month EPS basis (what the P/E is applied to)
A11: Fiscal year | B11: =Model!E5 | C11: =Model!F5 | D11: =Model!G5
A12: Share of the 12 months after the target date | B12: ='Calc - fair value'!C38 | C12: ='Calc - fair value'!D38 | D12: ='Calc - fair value'!E38
A13: Model EPS (Model tab) | B13: =Model!E29 | C13: =Model!F29 | D13: =Model!G29
A14: Model EPS, next 12 months after the target date | B14: =SUMPRODUCT(B12:D12,B13:D13)
A15: Stated next-12-month EPS used by the P/E method (consensus basis, cited) | B15: =Valuation!F71 | C15: =B15/B14-1 | D15: vs model EPS
A17: DCF build (free cash flow to firm, discounted to the target date)
A18: Fiscal year | B18: =Model!E5 | C18: =Model!F5 | D18: =Model!G5
A19: Free cash flow to firm | B19: ='Calc - fair value'!C31 | C19: ='Calc - fair value'!D31 | D19: ='Calc - fair value'!E31
A20: Share of the year after the target date | B20: ='Calc - fair value'!C35 | C20: ='Calc - fair value'!D35 | D20: ='Calc - fair value'!E35
A21: PV at target date | B21: ='Calc - fair value'!C36 | C21: ='Calc - fair value'!D36 | D21: ='Calc - fair value'!E36
A23: PV of free cash flow after the target date | B23: ='Calc - fair value'!B42
A24: Terminal value (final year) | B24: ='Calc - fair value'!B43
A25: PV of terminal value | B25: ='Calc - fair value'!B44
A26: Enterprise value at target date | B26: ='Calc - fair value'!B45
A27: Terminal value share of DCF | B27: ='Calc - fair value'!B46
A28: Net debt at target date | B28: ='Calc - fair value'!B50
A29: Minority interests | B29: ='Calc - fair value'!B51
A30: Adjustments | B30: ='Calc - fair value'!B52
A31: Diluted shares at target date (M) | B31: ='Calc - fair value'!B53
A32: DCF value per share | B32: ='Calc - fair value'!F67
A33: WACC | B33: ='Calc - fair value'!B12
A34: WACC at which the DCF equals the multiples (reverse DCF, engine run; not live) | B34: 0.047127172
A43: Assumptions (blue = input; sources on the Sources tab)
A44: Input | B44: Value | C44: Basis / note
A45: Run date (valuation as of) | B45: 46290
A46: Target date (run date + 365 days) | B46: =B45+365 | C46: 12-month horizon
A47: Money unit | B47: $M
A48: EBIT basis (gaap / adjusted) | B48: adjusted | C48: gaap = after stock comp
A49: Stock comp treatment (cost / dilution) | B49: cost | C49: used only when EBIT is adjusted
A50: Last reported fiscal year end | B50: 46112
A51: Net sales, last reported year ($M) | B51: 4713.1
A52: WACC | B52: 0.1358 | C52: filled in (not stated in this set's original work): cost of equity 0.1462 = T-bill 0.0412 + beta 2.10 x 5% (the price target's market leg, 2026-09-25); after-tax debt 0.0474 x (1 - 0.075) on net debt and minorities 5,089 vs equity 45,192 (574.30M x $78.69) -> WACC 0.1358
A53: Terminal method (gordon / exit_multiple) | B53: gordon
A54: Terminal growth | B54: 0
A55: Exit EV/EBITDA (exit_multiple only)
A56: Balance-sheet date | B56: 46203
A57: Net debt / (net cash) at balance date ($M) | B57: 5089 | C57: excludes operating leases
A58: Minority interests | B58: 0
A59: Interest rate on net debt / cash | B59: 0.0474
A60: Net debt at target date (override; blank = bridge) | B60: 3800
A61: Diluted shares (M) | B61: 574.3
A62: Share count date | B62: 46203
A63: Annual change in diluted shares | B63: 0 | C63: net of buybacks and stock-comp dilution
A64: Shares at target date (override; blank = from annual change) | B64: 575
A65: DCF weight | B65: 0
A66: Sum-of-the-parts weight | B66: 0
A67: Spread within each scenario (lognormal vol) | B67: 0.31
A68: Share price at the run | B68: 78.69 | C68: close used by the run (2026-09-25)
A70: Target multiple | B70: Multiple | C70: Weight | D70: Basis (ntm / ltm) | E70: EBITDA basis | F70: Stated EPS | G70: Stated FCF/share | H70: Levered | I70: Peer basis
A71: P/E | B71: 18.75 | C71: 0.5 | D71: ntm | E71: gaap | F71: 4.6 | H71: TRUE | I71: NTM P/E (citation gate rebuild at 2026-09-25 closes, estimate): NXPI ~13.7x, ON ~18.5x, TXN ~27.6x, ADI ~24.6x; MCHP ~19.1x NTM, 17.2x FY28 consensus. 18.75x sits at the top of the NXPI-ON range.
A72: FCF yield | B72: 0.05 | C72: 0.3 | D72: ntm | E72: gaap | G72: 4.26 | H72: TRUE | I72: TTM FCF yield at 2026-09-25 closes (gate rebuild, estimate): NXPI 4.7%, ON 5.0%, TXN 2.1%, ADI 2.6%.
A73: EV/EBITDA | B73: 16 | C73: 0.2 | D73: ntm | E73: adjusted | H73: TRUE | I73: Trailing GAAP EV/EBITDA (gate rebuild, estimate): NXPI 13.6x, ON 21.0x, TXN ~27.6x, ADI 28.6x; 16x is the P/E-consistent multiple, not a peer median.
A75: Segment (sum of the parts) | B75: NTM metric | C75: Metric | D75: Multiple | E75: Note
A76: none
A78: Adjustment (equity level) | B78: Value | C78: Probability | D78: Note
A79: none
A81: Custom method | B81: Value per share | C81: Weight | D81: Explanation
A82: none
A84: Scenario | B84: Probability | C84: Growth Δ | D84: Margin Δ | E84: Multiple Δ (turns) | F84: WACC Δ | G84: Multiple %Δ (FCF yield, segments) | H84: Stated EPS/FCF %Δ | I84: Custom methods %Δ | J84: Story
A85: bear | B85: 0.2 | D85: -0.0978 | E85: -3.5 | G85: -0.2295 | H85: -0.2444 | J85: Forecasters' common bear (supervisor: "Agreed", bear weight 20-22% at $52): the upcycle peaks around mid-2027, near the horizon, as the market prices FY29; book-to-bill below 1, GM back toward ~61-62%, distributor inventory rebuilding from 25 days, semis derate with 10-yr yields above 5%; below ~$62.5 the mandatory convertible adds dilution. Deltas are the forecasters' medians (EPS -24.4%, -3.5 turns).
A86: base | B86: 0.55 | J86: Recovery continues at a slowing rate: FY28 revenue ~$7.4B, GM 65-66%, op margin ~40%, NTM EPS ~$4.55-4.65 at ~18.5-19x, net debt ~$3.8B by Sep-2027, dividend continues, no buybacks yet. No deltas (the reconciled set is the base case).
A87: bull | B87: 0.25 | D87: 0.0681 | E87: 3.5 | G87: 0.1573 | H87: 0.1702 | J87: Extended cycle: data center / PCIe Gen6, Hailo edge AI, industrial and A&D strength; pricing sticks, NTM EPS ~$5.2-5.7, deleveraging reopens buybacks and semis re-rate to ~21-23.5x. Deltas are the forecasters' medians (EPS +17.0%, +3.5 turns).

Sheet Sensitivity
A1: MCHP: sensitivity tables (bold = current inputs; every cell recalculates from the live model)
A3: DCF value per share: WACC (down) x terminal growth (across)
A4: WACC \ growth | B4: =Valuation!$B$54+(-0.01) | C4: =Valuation!$B$54+(-0.005) | D4: =Valuation!$B$54+(0) | E4: =Valuation!$B$54+(0.005) | F4: =Valuation!$B$54+(0.01)
A5: =Valuation!$B$52+(-0.01) | B5: =IF($A5-B$4<=0.01,"n/a",((SUMPRODUCT('Calc - fair value'!$C$31:$E$31,'Calc - fair value'!$C$35:$E$35,(1+$A5)^(-('Calc - fair value'!$C$19:$E$19-'Calc - fair value'!$B$13)))+'Calc - fair value'!$E$31*(1+B$4)/($A5-B$4)/(1+$A5)^('Calc - fair value'!$B$16-'Calc - fair value'!$B$13))-'Calc - fair value'!$B$50-'Calc - fair value'!$B$51+'Calc - fair value'!$B$52)/'Calc - fair value'!$B$53) | C5: =IF($A5-C$4<=0.01,"n/a",((SUMPRODUCT('Calc - fair value'!$C$31:$E$31,'Calc - fair value'!$C$35:$E$35,(1+$A5)^(-('Calc - fair value'!$C$19:$E$19-'Calc - fair value'!$B$13)))+'Calc - fair value'!$E$31*(1+C$4)/($A5-C$4)/(1+$A5)^('Calc - fair value'!$B$16-'Calc - fair value'!$B$13))-'Calc - fair value'!$B$50-'Calc - fair value'!$B$51+'Calc - fair value'!$B$52)/'Calc - fair value'!$B$53) | D5: =IF($A5-D$4<=0.01,"n/a",((SUMPRODUCT('Calc - fair value'!$C$31:$E$31,'Calc - fair value'!$C$35:$E$35,(1+$A5)^(-('Calc - fair value'!$C$19:$E$19-'Calc - fair value'!$B$13)))+'Calc - fair value'!$E$31*(1+D$4)/($A5-D$4)/(1+$A5)^('Calc - fair value'!$B$16-'Calc - fair value'!$B$13))-'Calc - fair value'!$B$50-'Calc - fair value'!$B$51+'Calc - fair value'!$B$52)/'Calc - fair value'!$B$53) | E5: =IF($A5-E$4<=0.01,"n/a",((SUMPRODUCT('Calc - fair value'!$C$31:$E$31,'Calc - fair value'!$C$35:$E$35,(1+$A5)^(-('Calc - fair value'!$C$19:$E$19-'Calc - fair value'!$B$13)))+'Calc - fair value'!$E$31*(1+E$4)/($A5-E$4)/(1+$A5)^('Calc - fair value'!$B$16-'Calc - fair value'!$B$13))-'Calc - fair value'!$B$50-'Calc - fair value'!$B$51+'Calc - fair value'!$B$52)/'Calc - fair value'!$B$53) | F5: =IF($A5-F$4<=0.01,"n/a",((SUMPRODUCT('Calc - fair value'!$C$31:$E$31,'Calc - fair value'!$C$35:$E$35,(1+$A5)^(-('Calc - fair value'!$C$19:$E$19-'Calc - fair value'!$B$13)))+'Calc - fair value'!$E$31*(1+F$4)/($A5-F$4)/(1+$A5)^('Calc - fair value'!$B$16-'Calc - fair value'!$B$13))-'Calc - fair value'!$B$50-'Calc - fair value'!$B$51+'Calc - fair value'!$B$52)/'Calc - fair value'!$B$53)
A6: =Valuation!$B$52+(-0.005) | B6: =IF($A6-B$4<=0.01,"n/a",((SUMPRODUCT('Calc - fair value'!$C$31:$E$31,'Calc - fair value'!$C$35:$E$35,(1+$A6)^(-('Calc - fair value'!$C$19:$E$19-'Calc - fair value'!$B$13)))+'Calc - fair value'!$E$31*(1+B$4)/($A6-B$4)/(1+$A6)^('Calc - fair value'!$B$16-'Calc - fair value'!$B$13))-'Calc - fair value'!$B$50-'Calc - fair value'!$B$51+'Calc - fair value'!$B$52)/'Calc - fair value'!$B$53) | C6: =IF($A6-C$4<=0.01,"n/a",((SUMPRODUCT('Calc - fair value'!$C$31:$E$31,'Calc - fair value'!$C$35:$E$35,(1+$A6)^(-('Calc - fair value'!$C$19:$E$19-'Calc - fair value'!$B$13)))+'Calc - fair value'!$E$31*(1+C$4)/($A6-C$4)/(1+$A6)^('Calc - fair value'!$B$16-'Calc - fair value'!$B$13))-'Calc - fair value'!$B$50-'Calc - fair value'!$B$51+'Calc - fair value'!$B$52)/'Calc - fair value'!$B$53) | D6: =IF($A6-D$4<=0.01,"n/a",((SUMPRODUCT('Calc - fair value'!$C$31:$E$31,'Calc - fair value'!$C$35:$E$35,(1+$A6)^(-('Calc - fair value'!$C$19:$E$19-'Calc - fair value'!$B$13)))+'Calc - fair value'!$E$31*(1+D$4)/($A6-D$4)/(1+$A6)^('Calc - fair value'!$B$16-'Calc - fair value'!$B$13))-'Calc - fair value'!$B$50-'Calc - fair value'!$B$51+'Calc - fair value'!$B$52)/'Calc - fair value'!$B$53) | E6: =IF($A6-E$4<=0.01,"n/a",((SUMPRODUCT('Calc - fair value'!$C$31:$E$31,'Calc - fair value'!$C$35:$E$35,(1+$A6)^(-('Calc - fair value'!$C$19:$E$19-'Calc - fair value'!$B$13)))+'Calc - fair value'!$E$31*(1+E$4)/($A6-E$4)/(1+$A6)^('Calc - fair value'!$B$16-'Calc - fair value'!$B$13))-'Calc - fair value'!$B$50-'Calc - fair value'!$B$51+'Calc - fair value'!$B$52)/'Calc - fair value'!$B$53) | F6: =IF($A6-F$4<=0.01,"n/a",((SUMPRODUCT('Calc - fair value'!$C$31:$E$31,'Calc - fair value'!$C$35:$E$35,(1+$A6)^(-('Calc - fair value'!$C$19:$E$19-'Calc - fair value'!$B$13)))+'Calc - fair value'!$E$31*(1+F$4)/($A6-F$4)/(1+$A6)^('Calc - fair value'!$B$16-'Calc - fair value'!$B$13))-'Calc - fair value'!$B$50-'Calc - fair value'!$B$51+'Calc - fair value'!$B$52)/'Calc - fair value'!$B$53)
A7: =Valuation!$B$52+(0) | B7: =IF($A7-B$4<=0.01,"n/a",((SUMPRODUCT('Calc - fair value'!$C$31:$E$31,'Calc - fair value'!$C$35:$E$35,(1+$A7)^(-('Calc - fair value'!$C$19:$E$19-'Calc - fair value'!$B$13)))+'Calc - fair value'!$E$31*(1+B$4)/($A7-B$4)/(1+$A7)^('Calc - fair value'!$B$16-'Calc - fair value'!$B$13))-'Calc - fair value'!$B$50-'Calc - fair value'!$B$51+'Calc - fair value'!$B$52)/'Calc - fair value'!$B$53) | C7: =IF($A7-C$4<=0.01,"n/a",((SUMPRODUCT('Calc - fair value'!$C$31:$E$31,'Calc - fair value'!$C$35:$E$35,(1+$A7)^(-('Calc - fair value'!$C$19:$E$19-'Calc - fair value'!$B$13)))+'Calc - fair value'!$E$31*(1+C$4)/($A7-C$4)/(1+$A7)^('Calc - fair value'!$B$16-'Calc - fair value'!$B$13))-'Calc - fair value'!$B$50-'Calc - fair value'!$B$51+'Calc - fair value'!$B$52)/'Calc - fair value'!$B$53) | D7: =IF($A7-D$4<=0.01,"n/a",((SUMPRODUCT('Calc - fair value'!$C$31:$E$31,'Calc - fair value'!$C$35:$E$35,(1+$A7)^(-('Calc - fair value'!$C$19:$E$19-'Calc - fair value'!$B$13)))+'Calc - fair value'!$E$31*(1+D$4)/($A7-D$4)/(1+$A7)^('Calc - fair value'!$B$16-'Calc - fair value'!$B$13))-'Calc - fair value'!$B$50-'Calc - fair value'!$B$51+'Calc - fair value'!$B$52)/'Calc - fair value'!$B$53) | E7: =IF($A7-E$4<=0.01,"n/a",((SUMPRODUCT('Calc - fair value'!$C$31:$E$31,'Calc - fair value'!$C$35:$E$35,(1+$A7)^(-('Calc - fair value'!$C$19:$E$19-'Calc - fair value'!$B$13)))+'Calc - fair value'!$E$31*(1+E$4)/($A7-E$4)/(1+$A7)^('Calc - fair value'!$B$16-'Calc - fair value'!$B$13))-'Calc - fair value'!$B$50-'Calc - fair value'!$B$51+'Calc - fair value'!$B$52)/'Calc - fair value'!$B$53) | F7: =IF($A7-F$4<=0.01,"n/a",((SUMPRODUCT('Calc - fair value'!$C$31:$E$31,'Calc - fair value'!$C$35:$E$35,(1+$A7)^(-('Calc - fair value'!$C$19:$E$19-'Calc - fair value'!$B$13)))+'Calc - fair value'!$E$31*(1+F$4)/($A7-F$4)/(1+$A7)^('Calc - fair value'!$B$16-'Calc - fair value'!$B$13))-'Calc - fair value'!$B$50-'Calc - fair value'!$B$51+'Calc - fair value'!$B$52)/'Calc - fair value'!$B$53)
A8: =Valuation!$B$52+(0.005) | B8: =IF($A8-B$4<=0.01,"n/a",((SUMPRODUCT('Calc - fair value'!$C$31:$E$31,'Calc - fair value'!$C$35:$E$35,(1+$A8)^(-('Calc - fair value'!$C$19:$E$19-'Calc - fair value'!$B$13)))+'Calc - fair value'!$E$31*(1+B$4)/($A8-B$4)/(1+$A8)^('Calc - fair value'!$B$16-'Calc - fair value'!$B$13))-'Calc - fair value'!$B$50-'Calc - fair value'!$B$51+'Calc - fair value'!$B$52)/'Calc - fair value'!$B$53) | C8: =IF($A8-C$4<=0.01,"n/a",((SUMPRODUCT('Calc - fair value'!$C$31:$E$31,'Calc - fair value'!$C$35:$E$35,(1+$A8)^(-('Calc - fair value'!$C$19:$E$19-'Calc - fair value'!$B$13)))+'Calc - fair value'!$E$31*(1+C$4)/($A8-C$4)/(1+$A8)^('Calc - fair value'!$B$16-'Calc - fair value'!$B$13))-'Calc - fair value'!$B$50-'Calc - fair value'!$B$51+'Calc - fair value'!$B$52)/'Calc - fair value'!$B$53) | D8: =IF($A8-D$4<=0.01,"n/a",((SUMPRODUCT('Calc - fair value'!$C$31:$E$31,'Calc - fair value'!$C$35:$E$35,(1+$A8)^(-('Calc - fair value'!$C$19:$E$19-'Calc - fair value'!$B$13)))+'Calc - fair value'!$E$31*(1+D$4)/($A8-D$4)/(1+$A8)^('Calc - fair value'!$B$16-'Calc - fair value'!$B$13))-'Calc - fair value'!$B$50-'Calc - fair value'!$B$51+'Calc - fair value'!$B$52)/'Calc - fair value'!$B$53) | E8: =IF($A8-E$4<=0.01,"n/a",((SUMPRODUCT('Calc - fair value'!$C$31:$E$31,'Calc - fair value'!$C$35:$E$35,(1+$A8)^(-('Calc - fair value'!$C$19:$E$19-'Calc - fair value'!$B$13)))+'Calc - fair value'!$E$31*(1+E$4)/($A8-E$4)/(1+$A8)^('Calc - fair value'!$B$16-'Calc - fair value'!$B$13))-'Calc - fair value'!$B$50-'Calc - fair value'!$B$51+'Calc - fair value'!$B$52)/'Calc - fair value'!$B$53) | F8: =IF($A8-F$4<=0.01,"n/a",((SUMPRODUCT('Calc - fair value'!$C$31:$E$31,'Calc - fair value'!$C$35:$E$35,(1+$A8)^(-('Calc - fair value'!$C$19:$E$19-'Calc - fair value'!$B$13)))+'Calc - fair value'!$E$31*(1+F$4)/($A8-F$4)/(1+$A8)^('Calc - fair value'!$B$16-'Calc - fair value'!$B$13))-'Calc - fair value'!$B$50-'Calc - fair value'!$B$51+'Calc - fair value'!$B$52)/'Calc - fair value'!$B$53)
A9: =Valuation!$B$52+(0.01) | B9: =IF($A9-B$4<=0.01,"n/a",((SUMPRODUCT('Calc - fair value'!$C$31:$E$31,'Calc - fair value'!$C$35:$E$35,(1+$A9)^(-('Calc - fair value'!$C$19:$E$19-'Calc - fair value'!$B$13)))+'Calc - fair value'!$E$31*(1+B$4)/($A9-B$4)/(1+$A9)^('Calc - fair value'!$B$16-'Calc - fair value'!$B$13))-'Calc - fair value'!$B$50-'Calc - fair value'!$B$51+'Calc - fair value'!$B$52)/'Calc - fair value'!$B$53) | C9: =IF($A9-C$4<=0.01,"n/a",((SUMPRODUCT('Calc - fair value'!$C$31:$E$31,'Calc - fair value'!$C$35:$E$35,(1+$A9)^(-('Calc - fair value'!$C$19:$E$19-'Calc - fair value'!$B$13)))+'Calc - fair value'!$E$31*(1+C$4)/($A9-C$4)/(1+$A9)^('Calc - fair value'!$B$16-'Calc - fair value'!$B$13))-'Calc - fair value'!$B$50-'Calc - fair value'!$B$51+'Calc - fair value'!$B$52)/'Calc - fair value'!$B$53) | D9: =IF($A9-D$4<=0.01,"n/a",((SUMPRODUCT('Calc - fair value'!$C$31:$E$31,'Calc - fair value'!$C$35:$E$35,(1+$A9)^(-('Calc - fair value'!$C$19:$E$19-'Calc - fair value'!$B$13)))+'Calc - fair value'!$E$31*(1+D$4)/($A9-D$4)/(1+$A9)^('Calc - fair value'!$B$16-'Calc - fair value'!$B$13))-'Calc - fair value'!$B$50-'Calc - fair value'!$B$51+'Calc - fair value'!$B$52)/'Calc - fair value'!$B$53) | E9: =IF($A9-E$4<=0.01,"n/a",((SUMPRODUCT('Calc - fair value'!$C$31:$E$31,'Calc - fair value'!$C$35:$E$35,(1+$A9)^(-('Calc - fair value'!$C$19:$E$19-'Calc - fair value'!$B$13)))+'Calc - fair value'!$E$31*(1+E$4)/($A9-E$4)/(1+$A9)^('Calc - fair value'!$B$16-'Calc - fair value'!$B$13))-'Calc - fair value'!$B$50-'Calc - fair value'!$B$51+'Calc - fair value'!$B$52)/'Calc - fair value'!$B$53) | F9: =IF($A9-F$4<=0.01,"n/a",((SUMPRODUCT('Calc - fair value'!$C$31:$E$31,'Calc - fair value'!$C$35:$E$35,(1+$A9)^(-('Calc - fair value'!$C$19:$E$19-'Calc - fair value'!$B$13)))+'Calc - fair value'!$E$31*(1+F$4)/($A9-F$4)/(1+$A9)^('Calc - fair value'!$B$16-'Calc - fair value'!$B$13))-'Calc - fair value'!$B$50-'Calc - fair value'!$B$51+'Calc - fair value'!$B$52)/'Calc - fair value'!$B$53)
A11: Fair value per share: P/E multiple (down) x stated EPS (across)
A12: Multiple \ metric | B12: =Valuation!F71*0.9 | C12: =Valuation!F71*0.95 | D12: =Valuation!F71*1.0 | E12: =Valuation!F71*1.05 | F12: =Valuation!F71*1.1
A13: =Valuation!$B$71+(-3) | B13: =((SUMPRODUCT('Calc - fair value'!$F$67:$F$70,'Calc - fair value'!$G$67:$G$70)-'Calc - fair value'!$F$68*'Calc - fair value'!$G$68)+'Calc - fair value'!$G$68*($A13*B$12+'Calc - fair value'!$B$52/'Calc - fair value'!$B$53))/SUM('Calc - fair value'!$G$67:$G$70) | C13: =((SUMPRODUCT('Calc - fair value'!$F$67:$F$70,'Calc - fair value'!$G$67:$G$70)-'Calc - fair value'!$F$68*'Calc - fair value'!$G$68)+'Calc - fair value'!$G$68*($A13*C$12+'Calc - fair value'!$B$52/'Calc - fair value'!$B$53))/SUM('Calc - fair value'!$G$67:$G$70) | D13: =((SUMPRODUCT('Calc - fair value'!$F$67:$F$70,'Calc - fair value'!$G$67:$G$70)-'Calc - fair value'!$F$68*'Calc - fair value'!$G$68)+'Calc - fair value'!$G$68*($A13*D$12+'Calc - fair value'!$B$52/'Calc - fair value'!$B$53))/SUM('Calc - fair value'!$G$67:$G$70) | E13: =((SUMPRODUCT('Calc - fair value'!$F$67:$F$70,'Calc - fair value'!$G$67:$G$70)-'Calc - fair value'!$F$68*'Calc - fair value'!$G$68)+'Calc - fair value'!$G$68*($A13*E$12+'Calc - fair value'!$B$52/'Calc - fair value'!$B$53))/SUM('Calc - fair value'!$G$67:$G$70) | F13: =((SUMPRODUCT('Calc - fair value'!$F$67:$F$70,'Calc - fair value'!$G$67:$G$70)-'Calc - fair value'!$F$68*'Calc - fair value'!$G$68)+'Calc - fair value'!$G$68*($A13*F$12+'Calc - fair value'!$B$52/'Calc - fair value'!$B$53))/SUM('Calc - fair value'!$G$67:$G$70)
A14: =Valuation!$B$71+(-2) | B14: =((SUMPRODUCT('Calc - fair value'!$F$67:$F$70,'Calc - fair value'!$G$67:$G$70)-'Calc - fair value'!$F$68*'Calc - fair value'!$G$68)+'Calc - fair value'!$G$68*($A14*B$12+'Calc - fair value'!$B$52/'Calc - fair value'!$B$53))/SUM('Calc - fair value'!$G$67:$G$70) | C14: =((SUMPRODUCT('Calc - fair value'!$F$67:$F$70,'Calc - fair value'!$G$67:$G$70)-'Calc - fair value'!$F$68*'Calc - fair value'!$G$68)+'Calc - fair value'!$G$68*($A14*C$12+'Calc - fair value'!$B$52/'Calc - fair value'!$B$53))/SUM('Calc - fair value'!$G$67:$G$70) | D14: =((SUMPRODUCT('Calc - fair value'!$F$67:$F$70,'Calc - fair value'!$G$67:$G$70)-'Calc - fair value'!$F$68*'Calc - fair value'!$G$68)+'Calc - fair value'!$G$68*($A14*D$12+'Calc - fair value'!$B$52/'Calc - fair value'!$B$53))/SUM('Calc - fair value'!$G$67:$G$70) | E14: =((SUMPRODUCT('Calc - fair value'!$F$67:$F$70,'Calc - fair value'!$G$67:$G$70)-'Calc - fair value'!$F$68*'Calc - fair value'!$G$68)+'Calc - fair value'!$G$68*($A14*E$12+'Calc - fair value'!$B$52/'Calc - fair value'!$B$53))/SUM('Calc - fair value'!$G$67:$G$70) | F14: =((SUMPRODUCT('Calc - fair value'!$F$67:$F$70,'Calc - fair value'!$G$67:$G$70)-'Calc - fair value'!$F$68*'Calc - fair value'!$G$68)+'Calc - fair value'!$G$68*($A14*F$12+'Calc - fair value'!$B$52/'Calc - fair value'!$B$53))/SUM('Calc - fair value'!$G$67:$G$70)
A15: =Valuation!$B$71+(-1) | B15: =((SUMPRODUCT('Calc - fair value'!$F$67:$F$70,'Calc - fair value'!$G$67:$G$70)-'Calc - fair value'!$F$68*'Calc - fair value'!$G$68)+'Calc - fair value'!$G$68*($A15*B$12+'Calc - fair value'!$B$52/'Calc - fair value'!$B$53))/SUM('Calc - fair value'!$G$67:$G$70) | C15: =((SUMPRODUCT('Calc - fair value'!$F$67:$F$70,'Calc - fair value'!$G$67:$G$70)-'Calc - fair value'!$F$68*'Calc - fair value'!$G$68)+'Calc - fair value'!$G$68*($A15*C$12+'Calc - fair value'!$B$52/'Calc - fair value'!$B$53))/SUM('Calc - fair value'!$G$67:$G$70) | D15: =((SUMPRODUCT('Calc - fair value'!$F$67:$F$70,'Calc - fair value'!$G$67:$G$70)-'Calc - fair value'!$F$68*'Calc - fair value'!$G$68)+'Calc - fair value'!$G$68*($A15*D$12+'Calc - fair value'!$B$52/'Calc - fair value'!$B$53))/SUM('Calc - fair value'!$G$67:$G$70) | E15: =((SUMPRODUCT('Calc - fair value'!$F$67:$F$70,'Calc - fair value'!$G$67:$G$70)-'Calc - fair value'!$F$68*'Calc - fair value'!$G$68)+'Calc - fair value'!$G$68*($A15*E$12+'Calc - fair value'!$B$52/'Calc - fair value'!$B$53))/SUM('Calc - fair value'!$G$67:$G$70) | F15: =((SUMPRODUCT('Calc - fair value'!$F$67:$F$70,'Calc - fair value'!$G$67:$G$70)-'Calc - fair value'!$F$68*'Calc - fair value'!$G$68)+'Calc - fair value'!$G$68*($A15*F$12+'Calc - fair value'!$B$52/'Calc - fair value'!$B$53))/SUM('Calc - fair value'!$G$67:$G$70)
A16: =Valuation!$B$71+(0) | B16: =((SUMPRODUCT('Calc - fair value'!$F$67:$F$70,'Calc - fair value'!$G$67:$G$70)-'Calc - fair value'!$F$68*'Calc - fair value'!$G$68)+'Calc - fair value'!$G$68*($A16*B$12+'Calc - fair value'!$B$52/'Calc - fair value'!$B$53))/SUM('Calc - fair value'!$G$67:$G$70) | C16: =((SUMPRODUCT('Calc - fair value'!$F$67:$F$70,'Calc - fair value'!$G$67:$G$70)-'Calc - fair value'!$F$68*'Calc - fair value'!$G$68)+'Calc - fair value'!$G$68*($A16*C$12+'Calc - fair value'!$B$52/'Calc - fair value'!$B$53))/SUM('Calc - fair value'!$G$67:$G$70) | D16: =((SUMPRODUCT('Calc - fair value'!$F$67:$F$70,'Calc - fair value'!$G$67:$G$70)-'Calc - fair value'!$F$68*'Calc - fair value'!$G$68)+'Calc - fair value'!$G$68*($A16*D$12+'Calc - fair value'!$B$52/'Calc - fair value'!$B$53))/SUM('Calc - fair value'!$G$67:$G$70) | E16: =((SUMPRODUCT('Calc - fair value'!$F$67:$F$70,'Calc - fair value'!$G$67:$G$70)-'Calc - fair value'!$F$68*'Calc - fair value'!$G$68)+'Calc - fair value'!$G$68*($A16*E$12+'Calc - fair value'!$B$52/'Calc - fair value'!$B$53))/SUM('Calc - fair value'!$G$67:$G$70) | F16: =((SUMPRODUCT('Calc - fair value'!$F$67:$F$70,'Calc - fair value'!$G$67:$G$70)-'Calc - fair value'!$F$68*'Calc - fair value'!$G$68)+'Calc - fair value'!$G$68*($A16*F$12+'Calc - fair value'!$B$52/'Calc - fair value'!$B$53))/SUM('Calc - fair value'!$G$67:$G$70)
A17: =Valuation!$B$71+(1) | B17: =((SUMPRODUCT('Calc - fair value'!$F$67:$F$70,'Calc - fair value'!$G$67:$G$70)-'Calc - fair value'!$F$68*'Calc - fair value'!$G$68)+'Calc - fair value'!$G$68*($A17*B$12+'Calc - fair value'!$B$52/'Calc - fair value'!$B$53))/SUM('Calc - fair value'!$G$67:$G$70) | C17: =((SUMPRODUCT('Calc - fair value'!$F$67:$F$70,'Calc - fair value'!$G$67:$G$70)-'Calc - fair value'!$F$68*'Calc - fair value'!$G$68)+'Calc - fair value'!$G$68*($A17*C$12+'Calc - fair value'!$B$52/'Calc - fair value'!$B$53))/SUM('Calc - fair value'!$G$67:$G$70) | D17: =((SUMPRODUCT('Calc - fair value'!$F$67:$F$70,'Calc - fair value'!$G$67:$G$70)-'Calc - fair value'!$F$68*'Calc - fair value'!$G$68)+'Calc - fair value'!$G$68*($A17*D$12+'Calc - fair value'!$B$52/'Calc - fair value'!$B$53))/SUM('Calc - fair value'!$G$67:$G$70) | E17: =((SUMPRODUCT('Calc - fair value'!$F$67:$F$70,'Calc - fair value'!$G$67:$G$70)-'Calc - fair value'!$F$68*'Calc - fair value'!$G$68)+'Calc - fair value'!$G$68*($A17*E$12+'Calc - fair value'!$B$52/'Calc - fair value'!$B$53))/SUM('Calc - fair value'!$G$67:$G$70) | F17: =((SUMPRODUCT('Calc - fair value'!$F$67:$F$70,'Calc - fair value'!$G$67:$G$70)-'Calc - fair value'!$F$68*'Calc - fair value'!$G$68)+'Calc - fair value'!$G$68*($A17*F$12+'Calc - fair value'!$B$52/'Calc - fair value'!$B$53))/SUM('Calc - fair value'!$G$67:$G$70)
A18: =Valuation!$B$71+(2) | B18: =((SUMPRODUCT('Calc - fair value'!$F$67:$F$70,'Calc - fair value'!$G$67:$G$70)-'Calc - fair value'!$F$68*'Calc - fair value'!$G$68)+'Calc - fair value'!$G$68*($A18*B$12+'Calc - fair value'!$B$52/'Calc - fair value'!$B$53))/SUM('Calc - fair value'!$G$67:$G$70) | C18: =((SUMPRODUCT('Calc - fair value'!$F$67:$F$70,'Calc - fair value'!$G$67:$G$70)-'Calc - fair value'!$F$68*'Calc - fair value'!$G$68)+'Calc - fair value'!$G$68*($A18*C$12+'Calc - fair value'!$B$52/'Calc - fair value'!$B$53))/SUM('Calc - fair value'!$G$67:$G$70) | D18: =((SUMPRODUCT('Calc - fair value'!$F$67:$F$70,'Calc - fair value'!$G$67:$G$70)-'Calc - fair value'!$F$68*'Calc - fair value'!$G$68)+'Calc - fair value'!$G$68*($A18*D$12+'Calc - fair value'!$B$52/'Calc - fair value'!$B$53))/SUM('Calc - fair value'!$G$67:$G$70) | E18: =((SUMPRODUCT('Calc - fair value'!$F$67:$F$70,'Calc - fair value'!$G$67:$G$70)-'Calc - fair value'!$F$68*'Calc - fair value'!$G$68)+'Calc - fair value'!$G$68*($A18*E$12+'Calc - fair value'!$B$52/'Calc - fair value'!$B$53))/SUM('Calc - fair value'!$G$67:$G$70) | F18: =((SUMPRODUCT('Calc - fair value'!$F$67:$F$70,'Calc - fair value'!$G$67:$G$70)-'Calc - fair value'!$F$68*'Calc - fair value'!$G$68)+'Calc - fair value'!$G$68*($A18*F$12+'Calc - fair value'!$B$52/'Calc - fair value'!$B$53))/SUM('Calc - fair value'!$G$67:$G$70)
A19: =Valuation!$B$71+(3) | B19: =((SUMPRODUCT('Calc - fair value'!$F$67:$F$70,'Calc - fair value'!$G$67:$G$70)-'Calc - fair value'!$F$68*'Calc - fair value'!$G$68)+'Calc - fair value'!$G$68*($A19*B$12+'Calc - fair value'!$B$52/'Calc - fair value'!$B$53))/SUM('Calc - fair value'!$G$67:$G$70) | C19: =((SUMPRODUCT('Calc - fair value'!$F$67:$F$70,'Calc - fair value'!$G$67:$G$70)-'Calc - fair value'!$F$68*'Calc - fair value'!$G$68)+'Calc - fair value'!$G$68*($A19*C$12+'Calc - fair value'!$B$52/'Calc - fair value'!$B$53))/SUM('Calc - fair value'!$G$67:$G$70) | D19: =((SUMPRODUCT('Calc - fair value'!$F$67:$F$70,'Calc - fair value'!$G$67:$G$70)-'Calc - fair value'!$F$68*'Calc - fair value'!$G$68)+'Calc - fair value'!$G$68*($A19*D$12+'Calc - fair value'!$B$52/'Calc - fair value'!$B$53))/SUM('Calc - fair value'!$G$67:$G$70) | E19: =((SUMPRODUCT('Calc - fair value'!$F$67:$F$70,'Calc - fair value'!$G$67:$G$70)-'Calc - fair value'!$F$68*'Calc - fair value'!$G$68)+'Calc - fair value'!$G$68*($A19*E$12+'Calc - fair value'!$B$52/'Calc - fair value'!$B$53))/SUM('Calc - fair value'!$G$67:$G$70) | F19: =((SUMPRODUCT('Calc - fair value'!$F$67:$F$70,'Calc - fair value'!$G$67:$G$70)-'Calc - fair value'!$F$68*'Calc - fair value'!$G$68)+'Calc - fair value'!$G$68*($A19*F$12+'Calc - fair value'!$B$52/'Calc - fair value'!$B$53))/SUM('Calc - fair value'!$G$67:$G$70)
A22: FY2028E diluted EPS: revenue growth change in every year (down) x EBIT margin change (across)
A23: Growth Δ \ margin Δ | B23: -0.01 | C23: -0.005 | D23: 0 | E23: 0.005 | F23: 0.01
A24: -0.02 | B24: =(Valuation!$B$51*(1+Model!E48+$A24)*(1+Model!F48+$A24)*(Model!F49+B$23)+Model!F20)*(1-Model!F50)/Model!F27 | C24: =(Valuation!$B$51*(1+Model!E48+$A24)*(1+Model!F48+$A24)*(Model!F49+C$23)+Model!F20)*(1-Model!F50)/Model!F27 | D24: =(Valuation!$B$51*(1+Model!E48+$A24)*(1+Model!F48+$A24)*(Model!F49+D$23)+Model!F20)*(1-Model!F50)/Model!F27 | E24: =(Valuation!$B$51*(1+Model!E48+$A24)*(1+Model!F48+$A24)*(Model!F49+E$23)+Model!F20)*(1-Model!F50)/Model!F27 | F24: =(Valuation!$B$51*(1+Model!E48+$A24)*(1+Model!F48+$A24)*(Model!F49+F$23)+Model!F20)*(1-Model!F50)/Model!F27
A25: -0.01 | B25: =(Valuation!$B$51*(1+Model!E48+$A25)*(1+Model!F48+$A25)*(Model!F49+B$23)+Model!F20)*(1-Model!F50)/Model!F27 | C25: =(Valuation!$B$51*(1+Model!E48+$A25)*(1+Model!F48+$A25)*(Model!F49+C$23)+Model!F20)*(1-Model!F50)/Model!F27 | D25: =(Valuation!$B$51*(1+Model!E48+$A25)*(1+Model!F48+$A25)*(Model!F49+D$23)+Model!F20)*(1-Model!F50)/Model!F27 | E25: =(Valuation!$B$51*(1+Model!E48+$A25)*(1+Model!F48+$A25)*(Model!F49+E$23)+Model!F20)*(1-Model!F50)/Model!F27 | F25: =(Valuation!$B$51*(1+Model!E48+$A25)*(1+Model!F48+$A25)*(Model!F49+F$23)+Model!F20)*(1-Model!F50)/Model!F27
A26: 0 | B26: =(Valuation!$B$51*(1+Model!E48+$A26)*(1+Model!F48+$A26)*(Model!F49+B$23)+Model!F20)*(1-Model!F50)/Model!F27 | C26: =(Valuation!$B$51*(1+Model!E48+$A26)*(1+Model!F48+$A26)*(Model!F49+C$23)+Model!F20)*(1-Model!F50)/Model!F27 | D26: =(Valuation!$B$51*(1+Model!E48+$A26)*(1+Model!F48+$A26)*(Model!F49+D$23)+Model!F20)*(1-Model!F50)/Model!F27 | E26: =(Valuation!$B$51*(1+Model!E48+$A26)*(1+Model!F48+$A26)*(Model!F49+E$23)+Model!F20)*(1-Model!F50)/Model!F27 | F26: =(Valuation!$B$51*(1+Model!E48+$A26)*(1+Model!F48+$A26)*(Model!F49+F$23)+Model!F20)*(1-Model!F50)/Model!F27
A27: 0.01 | B27: =(Valuation!$B$51*(1+Model!E48+$A27)*(1+Model!F48+$A27)*(Model!F49+B$23)+Model!F20)*(1-Model!F50)/Model!F27 | C27: =(Valuation!$B$51*(1+Model!E48+$A27)*(1+Model!F48+$A27)*(Model!F49+C$23)+Model!F20)*(1-Model!F50)/Model!F27 | D27: =(Valuation!$B$51*(1+Model!E48+$A27)*(1+Model!F48+$A27)*(Model!F49+D$23)+Model!F20)*(1-Model!F50)/Model!F27 | E27: =(Valuation!$B$51*(1+Model!E48+$A27)*(1+Model!F48+$A27)*(Model!F49+E$23)+Model!F20)*(1-Model!F50)/Model!F27 | F27: =(Valuation!$B$51*(1+Model!E48+$A27)*(1+Model!F48+$A27)*(Model!F49+F$23)+Model!F20)*(1-Model!F50)/Model!F27
A28: 0.02 | B28: =(Valuation!$B$51*(1+Model!E48+$A28)*(1+Model!F48+$A28)*(Model!F49+B$23)+Model!F20)*(1-Model!F50)/Model!F27 | C28: =(Valuation!$B$51*(1+Model!E48+$A28)*(1+Model!F48+$A28)*(Model!F49+C$23)+Model!F20)*(1-Model!F50)/Model!F27 | D28: =(Valuation!$B$51*(1+Model!E48+$A28)*(1+Model!F48+$A28)*(Model!F49+D$23)+Model!F20)*(1-Model!F50)/Model!F27 | E28: =(Valuation!$B$51*(1+Model!E48+$A28)*(1+Model!F48+$A28)*(Model!F49+E$23)+Model!F20)*(1-Model!F50)/Model!F27 | F28: =(Valuation!$B$51*(1+Model!E48+$A28)*(1+Model!F48+$A28)*(Model!F49+F$23)+Model!F20)*(1-Model!F50)/Model!F27
A30: Net interest and the share count are held at the base case in table 3.

Sheet Distribution
A1: MCHP: 12-month distribution (mix of lognormals around each scenario value)
A3: Scenario | B3: Probability | C3: Value at target date | D3: Story
A4: bear | B4: =Valuation!B85 | C4: ='Calc - bear'!$F$71 | D4: =Valuation!J85
A5: base | B5: =Valuation!B86 | C5: ='Calc - base'!$F$71 | D5: =Valuation!J86
A6: bull | B6: =Valuation!B87 | C6: ='Calc - bull'!$F$71 | D6: =Valuation!J87
A8: Probabilities sum to | B8: =SUM(B4:B6)
A9: Spread within each scenario | B9: =Valuation!$B$67
A10: Probability-weighted mean | B10: =($B$4*$C$4+$B$5*$C$5+$B$6*$C$6)*EXP($B$9^2/2)
A12: Quantile | B12: Price
A13: Median (model target) | B13: =SQRT(A60*B60)
A14: 10th percentile | B14: =SQRT(D60*E60)
A15: 25th percentile | B15: =SQRT(G60*H60)
A16: 75th percentile | B16: =SQRT(J60*K60)
A17: 90th percentile | B17: =SQRT(M60*N60)
A19: Each quantile solved by bisection (block: low, high, probability above the midpoint)
A20: Median (model target): low | B20: high | C20: P(above mid) | D20: 10th percentile: low | E20: high | F20: P(above mid) | G20: 25th percentile: low | H20: high | I20: P(above mid) | J20: 75th percentile: low | K20: high | L20: P(above mid) | M20: 90th percentile: low | N20: high | O20: P(above mid)
A21: =MIN($C$4,$C$5,$C$6)*0.2 | B21: =MAX($C$4,$C$5,$C$6)*4 | C21: =SUMPRODUCT($B$4:$B$6,1-NORMSDIST((LN(SQRT(A21*B21))-LN($C$4:$C$6))/$B$9)) | D21: =MIN($C$4,$C$5,$C$6)*0.2 | E21: =MAX($C$4,$C$5,$C$6)*4 | F21: =SUMPRODUCT($B$4:$B$6,1-NORMSDIST((LN(SQRT(D21*E21))-LN($C$4:$C$6))/$B$9)) | G21: =MIN($C$4,$C$5,$C$6)*0.2 | H21: =MAX($C$4,$C$5,$C$6)*4 | I21: =SUMPRODUCT($B$4:$B$6,1-NORMSDIST((LN(SQRT(G21*H21))-LN($C$4:$C$6))/$B$9)) | J21: =MIN($C$4,$C$5,$C$6)*0.2 | K21: =MAX($C$4,$C$5,$C$6)*4 | L21: =SUMPRODUCT($B$4:$B$6,1-NORMSDIST((LN(SQRT(J21*K21))-LN($C$4:$C$6))/$B$9)) | M21: =MIN($C$4,$C$5,$C$6)*0.2 | N21: =MAX($C$4,$C$5,$C$6)*4 | O21: =SUMPRODUCT($B$4:$B$6,1-NORMSDIST((LN(SQRT(M21*N21))-LN($C$4:$C$6))/$B$9))
A22: =IF(C21>0.5,SQRT(A21*B21),A21) | B22: =IF(C21>0.5,B21,SQRT(A21*B21)) | C22: =SUMPRODUCT($B$4:$B$6,1-NORMSDIST((LN(SQRT(A22*B22))-LN($C$4:$C$6))/$B$9)) | D22: =IF(F21>0.9,SQRT(D21*E21),D21) | E22: =IF(F21>0.9,E21,SQRT(D21*E21)) | F22: =SUMPRODUCT($B$4:$B$6,1-NORMSDIST((LN(SQRT(D22*E22))-LN($C$4:$C$6))/$B$9)) | G22: =IF(I21>0.75,SQRT(G21*H21),G21) | H22: =IF(I21>0.75,H21,SQRT(G21*H21)) | I22: =SUMPRODUCT($B$4:$B$6,1-NORMSDIST((LN(SQRT(G22*H22))-LN($C$4:$C$6))/$B$9)) | J22: =IF(L21>0.25,SQRT(J21*K21),J21) | K22: =IF(L21>0.25,K21,SQRT(J21*K21)) | L22: =SUMPRODUCT($B$4:$B$6,1-NORMSDIST((LN(SQRT(J22*K22))-LN($C$4:$C$6))/$B$9)) | M22: =IF(O21>0.09999999999999998,SQRT(M21*N21),M21) | N22: =IF(O21>0.09999999999999998,N21,SQRT(M21*N21)) | O22: =SUMPRODUCT($B$4:$B$6,1-NORMSDIST((LN(SQRT(M22*N22))-LN($C$4:$C$6))/$B$9))
A23: =IF(C22>0.5,SQRT(A22*B22),A22) | B23: =IF(C22>0.5,B22,SQRT(A22*B22)) | C23: =SUMPRODUCT($B$4:$B$6,1-NORMSDIST((LN(SQRT(A23*B23))-LN($C$4:$C$6))/$B$9)) | D23: =IF(F22>0.9,SQRT(D22*E22),D22) | E23: =IF(F22>0.9,E22,SQRT(D22*E22)) | F23: =SUMPRODUCT($B$4:$B$6,1-NORMSDIST((LN(SQRT(D23*E23))-LN($C$4:$C$6))/$B$9)) | G23: =IF(I22>0.75,SQRT(G22*H22),G22) | H23: =IF(I22>0.75,H22,SQRT(G22*H22)) | I23: =SUMPRODUCT($B$4:$B$6,1-NORMSDIST((LN(SQRT(G23*H23))-LN($C$4:$C$6))/$B$9)) | J23: =IF(L22>0.25,SQRT(J22*K22),J22) | K23: =IF(L22>0.25,K22,SQRT(J22*K22)) | L23: =SUMPRODUCT($B$4:$B$6,1-NORMSDIST((LN(SQRT(J23*K23))-LN($C$4:$C$6))/$B$9)) | M23: =IF(O22>0.09999999999999998,SQRT(M22*N22),M22) | N23: =IF(O22>0.09999999999999998,N22,SQRT(M22*N22)) | O23: =SUMPRODUCT($B$4:$B$6,1-NORMSDIST((LN(SQRT(M23*N23))-LN($C$4:$C$6))/$B$9))
A24: =IF(C23>0.5,SQRT(A23*B23),A23) | B24: =IF(C23>0.5,B23,SQRT(A23*B23)) | C24: =SUMPRODUCT($B$4:$B$6,1-NORMSDIST((LN(SQRT(A24*B24))-LN($C$4:$C$6))/$B$9)) | D24: =IF(F23>0.9,SQRT(D23*E23),D23) | E24: =IF(F23>0.9,E23,SQRT(D23*E23)) | F24: =SUMPRODUCT($B$4:$B$6,1-NORMSDIST((LN(SQRT(D24*E24))-LN($C$4:$C$6))/$B$9)) | G24: =IF(I23>0.75,SQRT(G23*H23),G23) | H24: =IF(I23>0.75,H23,SQRT(G23*H23)) | I24: =SUMPRODUCT($B$4:$B$6,1-NORMSDIST((LN(SQRT(G24*H24))-LN($C$4:$C$6))/$B$9)) | J24: =IF(L23>0.25,SQRT(J23*K23),J23) | K24: =IF(L23>0.25,K23,SQRT(J23*K23)) | L24: =SUMPRODUCT($B$4:$B$6,1-NORMSDIST((LN(SQRT(J24*K24))-LN($C$4:$C$6))/$B$9)) | M24: =IF(O23>0.09999999999999998,SQRT(M23*N23),M23) | N24: =IF(O23>0.09999999999999998,N23,SQRT(M23*N23)) | O24: =SUMPRODUCT($B$4:$B$6,1-NORMSDIST((LN(SQRT(M24*N24))-LN($C$4:$C$6))/$B$9))
A25: =IF(C24>0.5,SQRT(A24*B24),A24) | B25: =IF(C24>0.5,B24,SQRT(A24*B24)) | C25: =SUMPRODUCT($B$4:$B$6,1-NORMSDIST((LN(SQRT(A25*B25))-LN($C$4:$C$6))/$B$9)) | D25: =IF(F24>0.9,SQRT(D24*E24),D24) | E25: =IF(F24>0.9,E24,SQRT(D24*E24)) | F25: =SUMPRODUCT($B$4:$B$6,1-NORMSDIST((LN(SQRT(D25*E25))-LN($C$4:$C$6))/$B$9)) | G25: =IF(I24>0.75,SQRT(G24*H24),G24) | H25: =IF(I24>0.75,H24,SQRT(G24*H24)) | I25: =SUMPRODUCT($B$4:$B$6,1-NORMSDIST((LN(SQRT(G25*H25))-LN($C$4:$C$6))/$B$9)) | J25: =IF(L24>0.25,SQRT(J24*K24),J24) | K25: =IF(L24>0.25,K24,SQRT(J24*K24)) | L25: =SUMPRODUCT($B$4:$B$6,1-NORMSDIST((LN(SQRT(J25*K25))-LN($C$4:$C$6))/$B$9)) | M25: =IF(O24>0.09999999999999998,SQRT(M24*N24),M24) | N25: =IF(O24>0.09999999999999998,N24,SQRT(M24*N24)) | O25: =SUMPRODUCT($B$4:$B$6,1-NORMSDIST((LN(SQRT(M25*N25))-LN($C$4:$C$6))/$B$9))
A26: =IF(C25>0.5,SQRT(A25*B25),A25) | B26: =IF(C25>0.5,B25,SQRT(A25*B25)) | C26: =SUMPRODUCT($B$4:$B$6,1-NORMSDIST((LN(SQRT(A26*B26))-LN($C$4:$C$6))/$B$9)) | D26: =IF(F25>0.9,SQRT(D25*E25),D25) | E26: =IF(F25>0.9,E25,SQRT(D25*E25)) | F26: =SUMPRODUCT($B$4:$B$6,1-NORMSDIST((LN(SQRT(D26*E26))-LN($C$4:$C$6))/$B$9)) | G26: =IF(I25>0.75,SQRT(G25*H25),G25) | H26: =IF(I25>0.75,H25,SQRT(G25*H25)) | I26: =SUMPRODUCT($B$4:$B$6,1-NORMSDIST((LN(SQRT(G26*H26))-LN($C$4:$C$6))/$B$9)) | J26: =IF(L25>0.25,SQRT(J25*K25),J25) | K26: =IF(L25>0.25,K25,SQRT(J25*K25)) | L26: =SUMPRODUCT($B$4:$B$6,1-NORMSDIST((LN(SQRT(J26*K26))-LN($C$4:$C$6))/$B$9)) | M26: =IF(O25>0.09999999999999998,SQRT(M25*N25),M25) | N26: =IF(O25>0.09999999999999998,N25,SQRT(M25*N25)) | O26: =SUMPRODUCT($B$4:$B$6,1-NORMSDIST((LN(SQRT(M26*N26))-LN($C$4:$C$6))/$B$9))
A27: =IF(C26>0.5,SQRT(A26*B26),A26) | B27: =IF(C26>0.5,B26,SQRT(A26*B26)) | C27: =SUMPRODUCT($B$4:$B$6,1-NORMSDIST((LN(SQRT(A27*B27))-LN($C$4:$C$6))/$B$9)) | D27: =IF(F26>0.9,SQRT(D26*E26),D26) | E27: =IF(F26>0.9,E26,SQRT(D26*E26)) | F27: =SUMPRODUCT($B$4:$B$6,1-NORMSDIST((LN(SQRT(D27*E27))-LN($C$4:$C$6))/$B$9)) | G27: =IF(I26>0.75,SQRT(G26*H26),G26) | H27: =IF(I26>0.75,H26,SQRT(G26*H26)) | I27: =SUMPRODUCT($B$4:$B$6,1-NORMSDIST((LN(SQRT(G27*H27))-LN($C$4:$C$6))/$B$9)) | J27: =IF(L26>0.25,SQRT(J26*K26),J26) | K27: =IF(L26>0.25,K26,SQRT(J26*K26)) | L27: =SUMPRODUCT($B$4:$B$6,1-NORMSDIST((LN(SQRT(J27*K27))-LN($C$4:$C$6))/$B$9)) | M27: =IF(O26>0.09999999999999998,SQRT(M26*N26),M26) | N27: =IF(O26>0.09999999999999998,N26,SQRT(M26*N26)) | O27: =SUMPRODUCT($B$4:$B$6,1-NORMSDIST((LN(SQRT(M27*N27))-LN($C$4:$C$6))/$B$9))
A28: =IF(C27>0.5,SQRT(A27*B27),A27) | B28: =IF(C27>0.5,B27,SQRT(A27*B27)) | C28: =SUMPRODUCT($B$4:$B$6,1-NORMSDIST((LN(SQRT(A28*B28))-LN($C$4:$C$6))/$B$9)) | D28: =IF(F27>0.9,SQRT(D27*E27),D27) | E28: =IF(F27>0.9,E27,SQRT(D27*E27)) | F28: =SUMPRODUCT($B$4:$B$6,1-NORMSDIST((LN(SQRT(D28*E28))-LN($C$4:$C$6))/$B$9)) | G28: =IF(I27>0.75,SQRT(G27*H27),G27) | H28: =IF(I27>0.75,H27,SQRT(G27*H27)) | I28: =SUMPRODUCT($B$4:$B$6,1-NORMSDIST((LN(SQRT(G28*H28))-LN($C$4:$C$6))/$B$9)) | J28: =IF(L27>0.25,SQRT(J27*K27),J27) | K28: =IF(L27>0.25,K27,SQRT(J27*K27)) | L28: =SUMPRODUCT($B$4:$B$6,1-NORMSDIST((LN(SQRT(J28*K28))-LN($C$4:$C$6))/$B$9)) | M28: =IF(O27>0.09999999999999998,SQRT(M27*N27),M27) | N28: =IF(O27>0.09999999999999998,N27,SQRT(M27*N27)) | O28: =SUMPRODUCT($B$4:$B$6,1-NORMSDIST((LN(SQRT(M28*N28))-LN($C$4:$C$6))/$B$9))
A29: =IF(C28>0.5,SQRT(A28*B28),A28) | B29: =IF(C28>0.5,B28,SQRT(A28*B28)) | C29: =SUMPRODUCT($B$4:$B$6,1-NORMSDIST((LN(SQRT(A29*B29))-LN($C$4:$C$6))/$B$9)) | D29: =IF(F28>0.9,SQRT(D28*E28),D28) | E29: =IF(F28>0.9,E28,SQRT(D28*E28)) | F29: =SUMPRODUCT($B$4:$B$6,1-NORMSDIST((LN(SQRT(D29*E29))-LN($C$4:$C$6))/$B$9)) | G29: =IF(I28>0.75,SQRT(G28*H28),G28) | H29: =IF(I28>0.75,H28,SQRT(G28*H28)) | I29: =SUMPRODUCT($B$4:$B$6,1-NORMSDIST((LN(SQRT(G29*H29))-LN($C$4:$C$6))/$B$9)) | J29: =IF(L28>0.25,SQRT(J28*K28),J28) | K29: =IF(L28>0.25,K28,SQRT(J28*K28)) | L29: =SUMPRODUCT($B$4:$B$6,1-NORMSDIST((LN(SQRT(J29*K29))-LN($C$4:$C$6))/$B$9)) | M29: =IF(O28>0.09999999999999998,SQRT(M28*N28),M28) | N29: =IF(O28>0.09999999999999998,N28,SQRT(M28*N28)) | O29: =SUMPRODUCT($B$4:$B$6,1-NORMSDIST((LN(SQRT(M29*N29))-LN($C$4:$C$6))/$B$9))
A30: =IF(C29>0.5,SQRT(A29*B29),A29) | B30: =IF(C29>0.5,B29,SQRT(A29*B29)) | C30: =SUMPRODUCT($B$4:$B$6,1-NORMSDIST((LN(SQRT(A30*B30))-LN($C$4:$C$6))/$B$9)) | D30: =IF(F29>0.9,SQRT(D29*E29),D29) | E30: =IF(F29>0.9,E29,SQRT(D29*E29)) | F30: =SUMPRODUCT($B$4:$B$6,1-NORMSDIST((LN(SQRT(D30*E30))-LN($C$4:$C$6))/$B$9)) | G30: =IF(I29>0.75,SQRT(G29*H29),G29) | H30: =IF(I29>0.75,H29,SQRT(G29*H29)) | I30: =SUMPRODUCT($B$4:$B$6,1-NORMSDIST((LN(SQRT(G30*H30))-LN($C$4:$C$6))/$B$9)) | J30: =IF(L29>0.25,SQRT(J29*K29),J29) | K30: =IF(L29>0.25,K29,SQRT(J29*K29)) | L30: =SUMPRODUCT($B$4:$B$6,1-NORMSDIST((LN(SQRT(J30*K30))-LN($C$4:$C$6))/$B$9)) | M30: =IF(O29>0.09999999999999998,SQRT(M29*N29),M29) | N30: =IF(O29>0.09999999999999998,N29,SQRT(M29*N29)) | O30: =SUMPRODUCT($B$4:$B$6,1-NORMSDIST((LN(SQRT(M30*N30))-LN($C$4:$C$6))/$B$9))
A31: =IF(C30>0.5,SQRT(A30*B30),A30) | B31: =IF(C30>0.5,B30,SQRT(A30*B30)) | C31: =SUMPRODUCT($B$4:$B$6,1-NORMSDIST((LN(SQRT(A31*B31))-LN($C$4:$C$6))/$B$9)) | D31: =IF(F30>0.9,SQRT(D30*E30),D30) | E31: =IF(F30>0.9,E30,SQRT(D30*E30)) | F31: =SUMPRODUCT($B$4:$B$6,1-NORMSDIST((LN(SQRT(D31*E31))-LN($C$4:$C$6))/$B$9)) | G31: =IF(I30>0.75,SQRT(G30*H30),G30) | H31: =IF(I30>0.75,H30,SQRT(G30*H30)) | I31: =SUMPRODUCT($B$4:$B$6,1-NORMSDIST((LN(SQRT(G31*H31))-LN($C$4:$C$6))/$B$9)) | J31: =IF(L30>0.25,SQRT(J30*K30),J30) | K31: =IF(L30>0.25,K30,SQRT(J30*K30)) | L31: =SUMPRODUCT($B$4:$B$6,1-NORMSDIST((LN(SQRT(J31*K31))-LN($C$4:$C$6))/$B$9)) | M31: =IF(O30>0.09999999999999998,SQRT(M30*N30),M30) | N31: =IF(O30>0.09999999999999998,N30,SQRT(M30*N30)) | O31: =SUMPRODUCT($B$4:$B$6,1-NORMSDIST((LN(SQRT(M31*N31))-LN($C$4:$C$6))/$B$9))
A32: =IF(C31>0.5,SQRT(A31*B31),A31) | B32: =IF(C31>0.5,B31,SQRT(A31*B31)) | C32: =SUMPRODUCT($B$4:$B$6,1-NORMSDIST((LN(SQRT(A32*B32))-LN($C$4:$C$6))/$B$9)) | D32: =IF(F31>0.9,SQRT(D31*E31),D31) | E32: =IF(F31>0.9,E31,SQRT(D31*E31)) | F32: =SUMPRODUCT($B$4:$B$6,1-NORMSDIST((LN(SQRT(D32*E32))-LN($C$4:$C$6))/$B$9)) | G32: =IF(I31>0.75,SQRT(G31*H31),G31) | H32: =IF(I31>0.75,H31,SQRT(G31*H31)) | I32: =SUMPRODUCT($B$4:$B$6,1-NORMSDIST((LN(SQRT(G32*H32))-LN($C$4:$C$6))/$B$9)) | J32: =IF(L31>0.25,SQRT(J31*K31),J31) | K32: =IF(L31>0.25,K31,SQRT(J31*K31)) | L32: =SUMPRODUCT($B$4:$B$6,1-NORMSDIST((LN(SQRT(J32*K32))-LN($C$4:$C$6))/$B$9)) | M32: =IF(O31>0.09999999999999998,SQRT(M31*N31),M31) | N32: =IF(O31>0.09999999999999998,N31,SQRT(M31*N31)) | O32: =SUMPRODUCT($B$4:$B$6,1-NORMSDIST((LN(SQRT(M32*N32))-LN($C$4:$C$6))/$B$9))
A33: =IF(C32>0.5,SQRT(A32*B32),A32) | B33: =IF(C32>0.5,B32,SQRT(A32*B32)) | C33: =SUMPRODUCT($B$4:$B$6,1-NORMSDIST((LN(SQRT(A33*B33))-LN($C$4:$C$6))/$B$9)) | D33: =IF(F32>0.9,SQRT(D32*E32),D32) | E33: =IF(F32>0.9,E32,SQRT(D32*E32)) | F33: =SUMPRODUCT($B$4:$B$6,1-NORMSDIST((LN(SQRT(D33*E33))-LN($C$4:$C$6))/$B$9)) | G33: =IF(I32>0.75,SQRT(G32*H32),G32) | H33: =IF(I32>0.75,H32,SQRT(G32*H32)) | I33: =SUMPRODUCT($B$4:$B$6,1-NORMSDIST((LN(SQRT(G33*H33))-LN($C$4:$C$6))/$B$9)) | J33: =IF(L32>0.25,SQRT(J32*K32),J32) | K33: =IF(L32>0.25,K32,SQRT(J32*K32)) | L33: =SUMPRODUCT($B$4:$B$6,1-NORMSDIST((LN(SQRT(J33*K33))-LN($C$4:$C$6))/$B$9)) | M33: =IF(O32>0.09999999999999998,SQRT(M32*N32),M32) | N33: =IF(O32>0.09999999999999998,N32,SQRT(M32*N32)) | O33: =SUMPRODUCT($B$4:$B$6,1-NORMSDIST((LN(SQRT(M33*N33))-LN($C$4:$C$6))/$B$9))
... A60: =IF(C59>0.5,SQRT(A59*B59),A59) | B60: =IF(C59>0.5,B59,SQRT(A59*B59)) | C60: =SUMPRODUCT($B$4:$B$6,1-NORMSDIST((LN(SQRT(A60*B60))-LN($C$4:$C$6))/$B$9)) | D60: =IF(F59>0.9,SQRT(D59*E59),D59) | E60: =IF(F59>0.9,E59,SQRT(D59*E59)) | F60: =SUMPRODUCT($B$4:$B$6,1-NORMSDIST((LN(SQRT(D60*E60))-LN($C$4:$C$6))/$B$9)) | G60: =IF(I59>0.75,SQRT(G59*H59),G59) | H60: =IF(I59>0.75,H59,SQRT(G59*H59)) | I60: =SUMPRODUCT($B$4:$B$6,1-NORMSDIST((LN(SQRT(G60*H60))-LN($C$4:$C$6))/$B$9)) | J60: =IF(L59>0.25,SQRT(J59*K59),J59) | K60: =IF(L59>0.25,K59,SQRT(J59*K59)) | L60: =SUMPRODUCT($B$4:$B$6,1-NORMSDIST((LN(SQRT(J60*K60))-LN($C$4:$C$6))/$B$9)) | M60: =IF(O59>0.09999999999999998,SQRT(M59*N59),M59) | N60: =IF(O59>0.09999999999999998,N59,SQRT(M59*N59)) | O60: =SUMPRODUCT($B$4:$B$6,1-NORMSDIST((LN(SQRT(M60*N60))-LN($C$4:$C$6))/$B$9))

Sheet Calc - fair value
A1: MCHP engine calculation: fair value (reconciled set, no scenario deltas)
A2: Machinery behind the Valuation and Distribution tabs; drivers come from Model, assumptions from Valuation.
A4: Scenario Growth Δ | B4: 0
A5: Scenario Margin Δ | B5: 0
A6: Scenario Multiple Δ (turns) | B6: 0
A7: Scenario WACC Δ | B7: 0
A8: Scenario Multiple %Δ | B8: 0
A9: Scenario Stated EPS/FCF %Δ | B9: 0
A10: Scenario Custom %Δ | B10: 0
A12: WACC | B12: =Valuation!$B$52+B7
A13: Years from last FY end to target date | B13: =(Valuation!$B$46-Valuation!$B$50)/365.25
A14: Years from last FY end to balance date | B14: =(Valuation!$B$56-Valuation!$B$50)/365.25
A15: Years from last FY end to share count date | B15: =(Valuation!$B$62-Valuation!$B$50)/365.25
A16: Projected years | B16: 3
A18: Projection | B18: Base | C18: =Model!E5 | D18: =Model!F5 | E18: =Model!G5
A19: Year index | B19: 0 | C19: 1 | D19: 2 | E19: 3
A20: Period end | C20: =Valuation!$B$50+ROUND(365.25*C19,0) | D20: =Valuation!$B$50+ROUND(365.25*D19,0) | E20: =Valuation!$B$50+ROUND(365.25*E19,0)
A21: Revenue growth | C21: =Model!E48+$B$4 | D21: =Model!F48+$B$4 | E21: =Model!G48+$B$4
A22: Revenue | B22: =Valuation!$B$51 | C22: =B22*(1+C21) | D22: =C22*(1+D21) | E22: =D22*(1+E21)
A23: EBIT margin | C23: =Model!E49+$B$5 | D23: =Model!F49+$B$5 | E23: =Model!G49+$B$5
A24: EBIT | C24: =C22*C23 | D24: =D22*D23 | E24: =E22*E23
A25: Tax rate | C25: =Model!E50 | D25: =Model!F50 | E25: =Model!G50
A26: NOPAT | C26: =C24*(1-C25) | D26: =D24*(1-D25) | E26: =E24*(1-E25)
A27: D&A | C27: =C22*Model!E51 | D27: =D22*Model!F51 | E27: =E22*Model!G51
A28: Capex | C28: =C22*Model!E52 | D28: =D22*Model!F52 | E28: =E22*Model!G52
A29: Working capital increase | C29: =Model!E53*(C22-B22) | D29: =Model!F53*(D22-C22) | E29: =Model!G53*(E22-D22)
A30: Stock comp | C30: =C22*Model!E54 | D30: =D22*Model!F54 | E30: =E22*Model!G54
A31: Free cash flow to firm | C31: =C26+C27-C28-C29-IF(AND(Valuation!$B$48="adjusted",Valuation!$B$49="cost"),C30*(1-C25),0) | D31: =D26+D27-D28-D29-IF(AND(Valuation!$B$48="adjusted",Valuation!$B$49="cost"),D30*(1-D25),0) | E31: =E26+E27-E28-E29-IF(AND(Valuation!$B$48="adjusted",Valuation!$B$49="cost"),E30*(1-E25),0)
A32: EBITDA | C32: =C24+C27 | D32: =D24+D27 | E32: =E24+E27
A33: Adj. EBITDA | C33: =C24+C27+C22*Model!E58 | D33: =D24+D27+D22*Model!F58 | E33: =E24+E27+E22*Model!G58
A34: Shareholder returns + other uses | C34: =C22*Model!E56+Model!E55+Model!E57 | D34: =D22*Model!F56+Model!F55+Model!F57 | E34: =E22*Model!G56+Model!G55+Model!G57
A35: Share of year after target date | C35: =IF(C19<=$B$13,0,C19-MAX(C19-1,$B$13)) | D35: =IF(D19<=$B$13,0,D19-MAX(D19-1,$B$13)) | E35: =IF(E19<=$B$13,0,E19-MAX(E19-1,$B$13))
A36: PV at target date of FCFF | C36: =IF(C35=0,0,C31*C35/(1+$B$12)^(C19-$B$13)) | D36: =IF(D35=0,0,D31*D35/(1+$B$12)^(D19-$B$13)) | E36: =IF(E35=0,0,E31*E35/(1+$B$12)^(E19-$B$13))
A37: Overlap: balance date to target date | C37: =MAX(0,MIN(C19,$B$13)-MAX(C19-1,$B$14)) | D37: =MAX(0,MIN(D19,$B$13)-MAX(D19-1,$B$14)) | E37: =MAX(0,MIN(E19,$B$13)-MAX(E19-1,$B$14))
A38: NTM weight at target date | C38: =MAX(0,MIN(C19,$B$13+1)-MAX(C19-1,$B$13)) | D38: =MAX(0,MIN(D19,$B$13+1)-MAX(D19-1,$B$13)) | E38: =MAX(0,MIN(E19,$B$13+1)-MAX(E19-1,$B$13))
A39: LTM weight at target date | B39: =MAX(0,MIN(0,$B$13)-MAX(-1,$B$13-1)) | C39: =MAX(0,MIN(C19,$B$13)-MAX(C19-1,$B$13-1)) | D39: =MAX(0,MIN(D19,$B$13)-MAX(D19-1,$B$13-1)) | E39: =MAX(0,MIN(E19,$B$13)-MAX(E19-1,$B$13-1))
A41: Value at the target date
A42: PV of free cash flow after the target date | B42: =SUM($C$36:$E$36)
A43: Terminal value at final year | B43: =IF(Valuation!$B$53="exit_multiple",Valuation!$B$55*E32,E31*(1+Valuation!$B$54)/($B$12-Valuation!$B$54))
A44: PV of terminal value at target date | B44: =B43/(1+$B$12)^($B$16-$B$13)
A45: DCF enterprise value at target date | B45: =B42+B44
A46: Terminal value share of DCF | B46: =B44/B45
A47: Free cash flow earned, balance date to target date | B47: =SUMPRODUCT($C$37:$E$37,$C$31:$E$31)
A48: Shareholder returns + other uses paid | B48: =SUMPRODUCT($C$37:$E$37,$C$34:$E$34)
A49: Interest drag on net debt | B49: =Valuation!$B$59*(1-$C$25)*MAX(Valuation!$B$57,0)*MAX($B$13-$B$14,0)
A50: Net debt at target date | B50: =IF(Valuation!$B$60="",Valuation!$B$57-B47+B49+B48,Valuation!$B$60)
A51: Minority interests | B51: =Valuation!$B$58
A52: Adjustments (probability-weighted) | B52: 0
A53: Diluted shares at target date (M) | B53: =IF(Valuation!$B$64="",Valuation!$B$61*(1+Valuation!$B$63)^MAX($B$13-$B$15,0),Valuation!$B$64)
A54: After-tax interest on target-date net debt | B54: =Valuation!$B$59*(1-$C$25)*MAX(B50,0)
A55: Check: WACC vs terminal growth | B55: =IF(AND(Valuation!$B$53<>"exit_multiple",$B$12<=Valuation!$B$54+0.01),"WACC must exceed terminal growth by 1 point","ok")
A56: Check: projection length | B56: =IF(OR($B$13>=$B$16-1,$B$13+1>$B$16),"add projected years past the target date","ok")
A58: Metric at target date | B58: Next 12 months | C58: Last 12 months
A59: Revenue | B59: =SUMPRODUCT($C$38:$E$38,$C$22:$E$22) | C59: =SUMPRODUCT($C$39:$E$39,$C$22:$E$22)+$B$39*$B$22
A60: EBIT | B60: =SUMPRODUCT($C$38:$E$38,$C$24:$E$24) | C60: =SUMPRODUCT($C$39:$E$39,$C$24:$E$24)
A61: EBITDA | B61: =SUMPRODUCT($C$38:$E$38,$C$32:$E$32) | C61: =SUMPRODUCT($C$39:$E$39,$C$32:$E$32)
A62: Adj. EBITDA | B62: =SUMPRODUCT($C$38:$E$38,$C$33:$E$33) | C62: =SUMPRODUCT($C$39:$E$39,$C$33:$E$33)
A63: NOPAT | B63: =SUMPRODUCT($C$38:$E$38,$C$26:$E$26) | C63: =SUMPRODUCT($C$39:$E$39,$C$26:$E$26)
A64: Free cash flow to firm | B64: =SUMPRODUCT($C$38:$E$38,$C$31:$E$31) | C64: =SUMPRODUCT($C$39:$E$39,$C$31:$E$31)
A66: Valuation method | B66: Metric | C66: Multiple used | D66: Basis | E66: Metric at target date | F66: Value per share | G66: Weight | H66: Metric key | I66: Metric shown (stated per-share figure when used)
A67: DCF (cash flow to target date + terminal) | F67: =((B45)-$B$50-$B$51+$B$52)/$B$53 | G67: =Valuation!$B$65
A68: ="Multiple: "&Valuation!A71&" ("&Valuation!D71&")" | B68: =Valuation!A71 | C68: =IF(B68="FCF yield",Valuation!B71*(1-$B$8),Valuation!B71+IF(B68="EV/sales",0.1,1)*$B$6) | D68: =Valuation!D71 | E68: =IF(D68="ltm",CHOOSE(H68,$C$59,$C$60,$C$61,$C$62,$C$63,$C$64),CHOOSE(H68,$B$59,$B$60,$B$61,$B$62,$B$63,$B$64)) | F68: =IF(OR(B68="EV/EBITDA",B68="EV/sales",B68="EV/EBIT"),((C68*E68)-$B$50-$B$51+$B$52)/$B$53,IF(B68="P/E",IF(Valuation!F71<>"",C68*Valuation!F71*(1+$B$9),C68*(E68-$B$54)/$B$53),IF(Valuation!G71<>"",Valuation!G71*(1+$B$9)/C68,(E68-IF(Valuation!H71,$B$54,0))/C68/$B$53))+$B$52/$B$53) | G68: =Valuation!C71 | H68: =IF(B68="EV/sales",1,IF(B68="EV/EBIT",2,IF(B68="EV/EBITDA",IF(Valuation!E71="adjusted",4,3),IF(B68="P/E",5,6)))) | I68: =IF(AND(B68="P/E",Valuation!F71<>""),Valuation!F71*(1+$B$9),IF(AND(B68="FCF yield",Valuation!G71<>""),Valuation!G71*(1+$B$9),E68))
A69: ="Multiple: "&Valuation!A72&" ("&Valuation!D72&")" | B69: =Valuation!A72 | C69: =IF(B69="FCF yield",Valuation!B72*(1-$B$8),Valuation!B72+IF(B69="EV/sales",0.1,1)*$B$6) | D69: =Valuation!D72 | E69: =IF(D69="ltm",CHOOSE(H69,$C$59,$C$60,$C$61,$C$62,$C$63,$C$64),CHOOSE(H69,$B$59,$B$60,$B$61,$B$62,$B$63,$B$64)) | F69: =IF(OR(B69="EV/EBITDA",B69="EV/sales",B69="EV/EBIT"),((C69*E69)-$B$50-$B$51+$B$52)/$B$53,IF(B69="P/E",IF(Valuation!F72<>"",C69*Valuation!F72*(1+$B$9),C69*(E69-$B$54)/$B$53),IF(Valuation!G72<>"",Valuation!G72*(1+$B$9)/C69,(E69-IF(Valuation!H72,$B$54,0))/C69/$B$53))+$B$52/$B$53) | G69: =Valuation!C72 | H69: =IF(B69="EV/sales",1,IF(B69="EV/EBIT",2,IF(B69="EV/EBITDA",IF(Valuation!E72="adjusted",4,3),IF(B69="P/E",5,6)))) | I69: =IF(AND(B69="P/E",Valuation!F72<>""),Valuation!F72*(1+$B$9),IF(AND(B69="FCF yield",Valuation!G72<>""),Valuation!G72*(1+$B$9),E69))
A70: ="Multiple: "&Valuation!A73&" ("&Valuation!D73&")" | B70: =Valuation!A73 | C70: =IF(B70="FCF yield",Valuation!B73*(1-$B$8),Valuation!B73+IF(B70="EV/sales",0.1,1)*$B$6) | D70: =Valuation!D73 | E70: =IF(D70="ltm",CHOOSE(H70,$C$59,$C$60,$C$61,$C$62,$C$63,$C$64),CHOOSE(H70,$B$59,$B$60,$B$61,$B$62,$B$63,$B$64)) | F70: =IF(OR(B70="EV/EBITDA",B70="EV/sales",B70="EV/EBIT"),((C70*E70)-$B$50-$B$51+$B$52)/$B$53,IF(B70="P/E",IF(Valuation!F73<>"",C70*Valuation!F73*(1+$B$9),C70*(E70-$B$54)/$B$53),IF(Valuation!G73<>"",Valuation!G73*(1+$B$9)/C70,(E70-IF(Valuation!H73,$B$54,0))/C70/$B$53))+$B$52/$B$53) | G70: =Valuation!C73 | H70: =IF(B70="EV/sales",1,IF(B70="EV/EBIT",2,IF(B70="EV/EBITDA",IF(Valuation!E73="adjusted",4,3),IF(B70="P/E",5,6)))) | I70: =IF(AND(B70="P/E",Valuation!F73<>""),Valuation!F73*(1+$B$9),IF(AND(B70="FCF yield",Valuation!G73<>""),Valuation!G73*(1+$B$9),E70))
A71: Value per share at target date (weighted methods) | F71: =SUMPRODUCT(F67:F70,G67:G70)/SUM(G67:G70)

Sheet Calc - bear
A1: MCHP engine calculation: bear scenario
A2: Machinery behind the Valuation and Distribution tabs; drivers come from Model, assumptions from Valuation.
A4: Scenario Growth Δ | B4: =N(Valuation!C85)
A5: Scenario Margin Δ | B5: =N(Valuation!D85)
A6: Scenario Multiple Δ (turns) | B6: =N(Valuation!E85)
A7: Scenario WACC Δ | B7: =N(Valuation!F85)
A8: Scenario Multiple %Δ | B8: =N(Valuation!G85)
A9: Scenario Stated EPS/FCF %Δ | B9: =N(Valuation!H85)
A10: Scenario Custom %Δ | B10: =N(Valuation!I85)
A12: WACC | B12: =Valuation!$B$52+B7
A13: Years from last FY end to target date | B13: =(Valuation!$B$46-Valuation!$B$50)/365.25
A14: Years from last FY end to balance date | B14: =(Valuation!$B$56-Valuation!$B$50)/365.25
A15: Years from last FY end to share count date | B15: =(Valuation!$B$62-Valuation!$B$50)/365.25
A16: Projected years | B16: 3
A18: Projection | B18: Base | C18: =Model!E5 | D18: =Model!F5 | E18: =Model!G5
A19: Year index | B19: 0 | C19: 1 | D19: 2 | E19: 3
A20: Period end | C20: =Valuation!$B$50+ROUND(365.25*C19,0) | D20: =Valuation!$B$50+ROUND(365.25*D19,0) | E20: =Valuation!$B$50+ROUND(365.25*E19,0)
A21: Revenue growth | C21: =Model!E48+$B$4 | D21: =Model!F48+$B$4 | E21: =Model!G48+$B$4
A22: Revenue | B22: =Valuation!$B$51 | C22: =B22*(1+C21) | D22: =C22*(1+D21) | E22: =D22*(1+E21)
A23: EBIT margin | C23: =Model!E49+$B$5 | D23: =Model!F49+$B$5 | E23: =Model!G49+$B$5
A24: EBIT | C24: =C22*C23 | D24: =D22*D23 | E24: =E22*E23
A25: Tax rate | C25: =Model!E50 | D25: =Model!F50 | E25: =Model!G50
A26: NOPAT | C26: =C24*(1-C25) | D26: =D24*(1-D25) | E26: =E24*(1-E25)
A27: D&A | C27: =C22*Model!E51 | D27: =D22*Model!F51 | E27: =E22*Model!G51
A28: Capex | C28: =C22*Model!E52 | D28: =D22*Model!F52 | E28: =E22*Model!G52
A29: Working capital increase | C29: =Model!E53*(C22-B22) | D29: =Model!F53*(D22-C22) | E29: =Model!G53*(E22-D22)
A30: Stock comp | C30: =C22*Model!E54 | D30: =D22*Model!F54 | E30: =E22*Model!G54
A31: Free cash flow to firm | C31: =C26+C27-C28-C29-IF(AND(Valuation!$B$48="adjusted",Valuation!$B$49="cost"),C30*(1-C25),0) | D31: =D26+D27-D28-D29-IF(AND(Valuation!$B$48="adjusted",Valuation!$B$49="cost"),D30*(1-D25),0) | E31: =E26+E27-E28-E29-IF(AND(Valuation!$B$48="adjusted",Valuation!$B$49="cost"),E30*(1-E25),0)
A32: EBITDA | C32: =C24+C27 | D32: =D24+D27 | E32: =E24+E27
A33: Adj. EBITDA | C33: =C24+C27+C22*Model!E58 | D33: =D24+D27+D22*Model!F58 | E33: =E24+E27+E22*Model!G58
A34: Shareholder returns + other uses | C34: =C22*Model!E56+Model!E55+Model!E57 | D34: =D22*Model!F56+Model!F55+Model!F57 | E34: =E22*Model!G56+Model!G55+Model!G57
A35: Share of year after target date | C35: =IF(C19<=$B$13,0,C19-MAX(C19-1,$B$13)) | D35: =IF(D19<=$B$13,0,D19-MAX(D19-1,$B$13)) | E35: =IF(E19<=$B$13,0,E19-MAX(E19-1,$B$13))
A36: PV at target date of FCFF | C36: =IF(C35=0,0,C31*C35/(1+$B$12)^(C19-$B$13)) | D36: =IF(D35=0,0,D31*D35/(1+$B$12)^(D19-$B$13)) | E36: =IF(E35=0,0,E31*E35/(1+$B$12)^(E19-$B$13))
A37: Overlap: balance date to target date | C37: =MAX(0,MIN(C19,$B$13)-MAX(C19-1,$B$14)) | D37: =MAX(0,MIN(D19,$B$13)-MAX(D19-1,$B$14)) | E37: =MAX(0,MIN(E19,$B$13)-MAX(E19-1,$B$14))
A38: NTM weight at target date | C38: =MAX(0,MIN(C19,$B$13+1)-MAX(C19-1,$B$13)) | D38: =MAX(0,MIN(D19,$B$13+1)-MAX(D19-1,$B$13)) | E38: =MAX(0,MIN(E19,$B$13+1)-MAX(E19-1,$B$13))
A39: LTM weight at target date | B39: =MAX(0,MIN(0,$B$13)-MAX(-1,$B$13-1)) | C39: =MAX(0,MIN(C19,$B$13)-MAX(C19-1,$B$13-1)) | D39: =MAX(0,MIN(D19,$B$13)-MAX(D19-1,$B$13-1)) | E39: =MAX(0,MIN(E19,$B$13)-MAX(E19-1,$B$13-1))
A41: Value at the target date
A42: PV of free cash flow after the target date | B42: =SUM($C$36:$E$36)
A43: Terminal value at final year | B43: =IF(Valuation!$B$53="exit_multiple",Valuation!$B$55*E32,E31*(1+Valuation!$B$54)/($B$12-Valuation!$B$54))
A44: PV of terminal value at target date | B44: =B43/(1+$B$12)^($B$16-$B$13)
A45: DCF enterprise value at target date | B45: =B42+B44
A46: Terminal value share of DCF | B46: =B44/B45
A47: Free cash flow earned, balance date to target date | B47: =SUMPRODUCT($C$37:$E$37,$C$31:$E$31)
A48: Shareholder returns + other uses paid | B48: =SUMPRODUCT($C$37:$E$37,$C$34:$E$34)
A49: Interest drag on net debt | B49: =Valuation!$B$59*(1-$C$25)*MAX(Valuation!$B$57,0)*MAX($B$13-$B$14,0)
A50: Net debt at target date | B50: =IF(Valuation!$B$60="",Valuation!$B$57-B47+B49+B48,Valuation!$B$60)
A51: Minority interests | B51: =Valuation!$B$58
A52: Adjustments (probability-weighted) | B52: 0
A53: Diluted shares at target date (M) | B53: =IF(Valuation!$B$64="",Valuation!$B$61*(1+Valuation!$B$63)^MAX($B$13-$B$15,0),Valuation!$B$64)
A54: After-tax interest on target-date net debt | B54: =Valuation!$B$59*(1-$C$25)*MAX(B50,0)
A55: Check: WACC vs terminal growth | B55: =IF(AND(Valuation!$B$53<>"exit_multiple",$B$12<=Valuation!$B$54+0.01),"WACC must exceed terminal growth by 1 point","ok")
A56: Check: projection length | B56: =IF(OR($B$13>=$B$16-1,$B$13+1>$B$16),"add projected years past the target date","ok")
A58: Metric at target date | B58: Next 12 months | C58: Last 12 months
A59: Revenue | B59: =SUMPRODUCT($C$38:$E$38,$C$22:$E$22) | C59: =SUMPRODUCT($C$39:$E$39,$C$22:$E$22)+$B$39*$B$22
A60: EBIT | B60: =SUMPRODUCT($C$38:$E$38,$C$24:$E$24) | C60: =SUMPRODUCT($C$39:$E$39,$C$24:$E$24)
A61: EBITDA | B61: =SUMPRODUCT($C$38:$E$38,$C$32:$E$32) | C61: =SUMPRODUCT($C$39:$E$39,$C$32:$E$32)
A62: Adj. EBITDA | B62: =SUMPRODUCT($C$38:$E$38,$C$33:$E$33) | C62: =SUMPRODUCT($C$39:$E$39,$C$33:$E$33)
A63: NOPAT | B63: =SUMPRODUCT($C$38:$E$38,$C$26:$E$26) | C63: =SUMPRODUCT($C$39:$E$39,$C$26:$E$26)
A64: Free cash flow to firm | B64: =SUMPRODUCT($C$38:$E$38,$C$31:$E$31) | C64: =SUMPRODUCT($C$39:$E$39,$C$31:$E$31)
A66: Valuation method | B66: Metric | C66: Multiple used | D66: Basis | E66: Metric at target date | F66: Value per share | G66: Weight | H66: Metric key | I66: Metric shown (stated per-share figure when used)
A67: DCF (cash flow to target date + terminal) | F67: =((B45)-$B$50-$B$51+$B$52)/$B$53 | G67: =Valuation!$B$65
A68: ="Multiple: "&Valuation!A71&" ("&Valuation!D71&")" | B68: =Valuation!A71 | C68: =IF(B68="FCF yield",Valuation!B71*(1-$B$8),Valuation!B71+IF(B68="EV/sales",0.1,1)*$B$6) | D68: =Valuation!D71 | E68: =IF(D68="ltm",CHOOSE(H68,$C$59,$C$60,$C$61,$C$62,$C$63,$C$64),CHOOSE(H68,$B$59,$B$60,$B$61,$B$62,$B$63,$B$64)) | F68: =IF(OR(B68="EV/EBITDA",B68="EV/sales",B68="EV/EBIT"),((C68*E68)-$B$50-$B$51+$B$52)/$B$53,IF(B68="P/E",IF(Valuation!F71<>"",C68*Valuation!F71*(1+$B$9),C68*(E68-$B$54)/$B$53),IF(Valuation!G71<>"",Valuation!G71*(1+$B$9)/C68,(E68-IF(Valuation!H71,$B$54,0))/C68/$B$53))+$B$52/$B$53) | G68: =Valuation!C71 | H68: =IF(B68="EV/sales",1,IF(B68="EV/EBIT",2,IF(B68="EV/EBITDA",IF(Valuation!E71="adjusted",4,3),IF(B68="P/E",5,6)))) | I68: =IF(AND(B68="P/E",Valuation!F71<>""),Valuation!F71*(1+$B$9),IF(AND(B68="FCF yield",Valuation!G71<>""),Valuation!G71*(1+$B$9),E68))
A69: ="Multiple: "&Valuation!A72&" ("&Valuation!D72&")" | B69: =Valuation!A72 | C69: =IF(B69="FCF yield",Valuation!B72*(1-$B$8),Valuation!B72+IF(B69="EV/sales",0.1,1)*$B$6) | D69: =Valuation!D72 | E69: =IF(D69="ltm",CHOOSE(H69,$C$59,$C$60,$C$61,$C$62,$C$63,$C$64),CHOOSE(H69,$B$59,$B$60,$B$61,$B$62,$B$63,$B$64)) | F69: =IF(OR(B69="EV/EBITDA",B69="EV/sales",B69="EV/EBIT"),((C69*E69)-$B$50-$B$51+$B$52)/$B$53,IF(B69="P/E",IF(Valuation!F72<>"",C69*Valuation!F72*(1+$B$9),C69*(E69-$B$54)/$B$53),IF(Valuation!G72<>"",Valuation!G72*(1+$B$9)/C69,(E69-IF(Valuation!H72,$B$54,0))/C69/$B$53))+$B$52/$B$53) | G69: =Valuation!C72 | H69: =IF(B69="EV/sales",1,IF(B69="EV/EBIT",2,IF(B69="EV/EBITDA",IF(Valuation!E72="adjusted",4,3),IF(B69="P/E",5,6)))) | I69: =IF(AND(B69="P/E",Valuation!F72<>""),Valuation!F72*(1+$B$9),IF(AND(B69="FCF yield",Valuation!G72<>""),Valuation!G72*(1+$B$9),E69))
A70: ="Multiple: "&Valuation!A73&" ("&Valuation!D73&")" | B70: =Valuation!A73 | C70: =IF(B70="FCF yield",Valuation!B73*(1-$B$8),Valuation!B73+IF(B70="EV/sales",0.1,1)*$B$6) | D70: =Valuation!D73 | E70: =IF(D70="ltm",CHOOSE(H70,$C$59,$C$60,$C$61,$C$62,$C$63,$C$64),CHOOSE(H70,$B$59,$B$60,$B$61,$B$62,$B$63,$B$64)) | F70: =IF(OR(B70="EV/EBITDA",B70="EV/sales",B70="EV/EBIT"),((C70*E70)-$B$50-$B$51+$B$52)/$B$53,IF(B70="P/E",IF(Valuation!F73<>"",C70*Valuation!F73*(1+$B$9),C70*(E70-$B$54)/$B$53),IF(Valuation!G73<>"",Valuation!G73*(1+$B$9)/C70,(E70-IF(Valuation!H73,$B$54,0))/C70/$B$53))+$B$52/$B$53) | G70: =Valuation!C73 | H70: =IF(B70="EV/sales",1,IF(B70="EV/EBIT",2,IF(B70="EV/EBITDA",IF(Valuation!E73="adjusted",4,3),IF(B70="P/E",5,6)))) | I70: =IF(AND(B70="P/E",Valuation!F73<>""),Valuation!F73*(1+$B$9),IF(AND(B70="FCF yield",Valuation!G73<>""),Valuation!G73*(1+$B$9),E70))
A71: Value per share at target date (weighted methods) | F71: =SUMPRODUCT(F67:F70,G67:G70)/SUM(G67:G70)

Sheet Calc - base
A1: MCHP engine calculation: base scenario
A2: Machinery behind the Valuation and Distribution tabs; drivers come from Model, assumptions from Valuation.
A4: Scenario Growth Δ | B4: =N(Valuation!C86)
A5: Scenario Margin Δ | B5: =N(Valuation!D86)
A6: Scenario Multiple Δ (turns) | B6: =N(Valuation!E86)
A7: Scenario WACC Δ | B7: =N(Valuation!F86)
A8: Scenario Multiple %Δ | B8: =N(Valuation!G86)
A9: Scenario Stated EPS/FCF %Δ | B9: =N(Valuation!H86)
A10: Scenario Custom %Δ | B10: =N(Valuation!I86)
A12: WACC | B12: =Valuation!$B$52+B7
A13: Years from last FY end to target date | B13: =(Valuation!$B$46-Valuation!$B$50)/365.25
A14: Years from last FY end to balance date | B14: =(Valuation!$B$56-Valuation!$B$50)/365.25
A15: Years from last FY end to share count date | B15: =(Valuation!$B$62-Valuation!$B$50)/365.25
A16: Projected years | B16: 3
A18: Projection | B18: Base | C18: =Model!E5 | D18: =Model!F5 | E18: =Model!G5
A19: Year index | B19: 0 | C19: 1 | D19: 2 | E19: 3
A20: Period end | C20: =Valuation!$B$50+ROUND(365.25*C19,0) | D20: =Valuation!$B$50+ROUND(365.25*D19,0) | E20: =Valuation!$B$50+ROUND(365.25*E19,0)
A21: Revenue growth | C21: =Model!E48+$B$4 | D21: =Model!F48+$B$4 | E21: =Model!G48+$B$4
A22: Revenue | B22: =Valuation!$B$51 | C22: =B22*(1+C21) | D22: =C22*(1+D21) | E22: =D22*(1+E21)
A23: EBIT margin | C23: =Model!E49+$B$5 | D23: =Model!F49+$B$5 | E23: =Model!G49+$B$5
A24: EBIT | C24: =C22*C23 | D24: =D22*D23 | E24: =E22*E23
A25: Tax rate | C25: =Model!E50 | D25: =Model!F50 | E25: =Model!G50
A26: NOPAT | C26: =C24*(1-C25) | D26: =D24*(1-D25) | E26: =E24*(1-E25)
A27: D&A | C27: =C22*Model!E51 | D27: =D22*Model!F51 | E27: =E22*Model!G51
A28: Capex | C28: =C22*Model!E52 | D28: =D22*Model!F52 | E28: =E22*Model!G52
A29: Working capital increase | C29: =Model!E53*(C22-B22) | D29: =Model!F53*(D22-C22) | E29: =Model!G53*(E22-D22)
A30: Stock comp | C30: =C22*Model!E54 | D30: =D22*Model!F54 | E30: =E22*Model!G54
A31: Free cash flow to firm | C31: =C26+C27-C28-C29-IF(AND(Valuation!$B$48="adjusted",Valuation!$B$49="cost"),C30*(1-C25),0) | D31: =D26+D27-D28-D29-IF(AND(Valuation!$B$48="adjusted",Valuation!$B$49="cost"),D30*(1-D25),0) | E31: =E26+E27-E28-E29-IF(AND(Valuation!$B$48="adjusted",Valuation!$B$49="cost"),E30*(1-E25),0)
A32: EBITDA | C32: =C24+C27 | D32: =D24+D27 | E32: =E24+E27
A33: Adj. EBITDA | C33: =C24+C27+C22*Model!E58 | D33: =D24+D27+D22*Model!F58 | E33: =E24+E27+E22*Model!G58
A34: Shareholder returns + other uses | C34: =C22*Model!E56+Model!E55+Model!E57 | D34: =D22*Model!F56+Model!F55+Model!F57 | E34: =E22*Model!G56+Model!G55+Model!G57
A35: Share of year after target date | C35: =IF(C19<=$B$13,0,C19-MAX(C19-1,$B$13)) | D35: =IF(D19<=$B$13,0,D19-MAX(D19-1,$B$13)) | E35: =IF(E19<=$B$13,0,E19-MAX(E19-1,$B$13))
A36: PV at target date of FCFF | C36: =IF(C35=0,0,C31*C35/(1+$B$12)^(C19-$B$13)) | D36: =IF(D35=0,0,D31*D35/(1+$B$12)^(D19-$B$13)) | E36: =IF(E35=0,0,E31*E35/(1+$B$12)^(E19-$B$13))
A37: Overlap: balance date to target date | C37: =MAX(0,MIN(C19,$B$13)-MAX(C19-1,$B$14)) | D37: =MAX(0,MIN(D19,$B$13)-MAX(D19-1,$B$14)) | E37: =MAX(0,MIN(E19,$B$13)-MAX(E19-1,$B$14))
A38: NTM weight at target date | C38: =MAX(0,MIN(C19,$B$13+1)-MAX(C19-1,$B$13)) | D38: =MAX(0,MIN(D19,$B$13+1)-MAX(D19-1,$B$13)) | E38: =MAX(0,MIN(E19,$B$13+1)-MAX(E19-1,$B$13))
A39: LTM weight at target date | B39: =MAX(0,MIN(0,$B$13)-MAX(-1,$B$13-1)) | C39: =MAX(0,MIN(C19,$B$13)-MAX(C19-1,$B$13-1)) | D39: =MAX(0,MIN(D19,$B$13)-MAX(D19-1,$B$13-1)) | E39: =MAX(0,MIN(E19,$B$13)-MAX(E19-1,$B$13-1))
A41: Value at the target date
A42: PV of free cash flow after the target date | B42: =SUM($C$36:$E$36)
A43: Terminal value at final year | B43: =IF(Valuation!$B$53="exit_multiple",Valuation!$B$55*E32,E31*(1+Valuation!$B$54)/($B$12-Valuation!$B$54))
A44: PV of terminal value at target date | B44: =B43/(1+$B$12)^($B$16-$B$13)
A45: DCF enterprise value at target date | B45: =B42+B44
A46: Terminal value share of DCF | B46: =B44/B45
A47: Free cash flow earned, balance date to target date | B47: =SUMPRODUCT($C$37:$E$37,$C$31:$E$31)
A48: Shareholder returns + other uses paid | B48: =SUMPRODUCT($C$37:$E$37,$C$34:$E$34)
A49: Interest drag on net debt | B49: =Valuation!$B$59*(1-$C$25)*MAX(Valuation!$B$57,0)*MAX($B$13-$B$14,0)
A50: Net debt at target date | B50: =IF(Valuation!$B$60="",Valuation!$B$57-B47+B49+B48,Valuation!$B$60)
A51: Minority interests | B51: =Valuation!$B$58
A52: Adjustments (probability-weighted) | B52: 0
A53: Diluted shares at target date (M) | B53: =IF(Valuation!$B$64="",Valuation!$B$61*(1+Valuation!$B$63)^MAX($B$13-$B$15,0),Valuation!$B$64)
A54: After-tax interest on target-date net debt | B54: =Valuation!$B$59*(1-$C$25)*MAX(B50,0)
A55: Check: WACC vs terminal growth | B55: =IF(AND(Valuation!$B$53<>"exit_multiple",$B$12<=Valuation!$B$54+0.01),"WACC must exceed terminal growth by 1 point","ok")
A56: Check: projection length | B56: =IF(OR($B$13>=$B$16-1,$B$13+1>$B$16),"add projected years past the target date","ok")
A58: Metric at target date | B58: Next 12 months | C58: Last 12 months
A59: Revenue | B59: =SUMPRODUCT($C$38:$E$38,$C$22:$E$22) | C59: =SUMPRODUCT($C$39:$E$39,$C$22:$E$22)+$B$39*$B$22
A60: EBIT | B60: =SUMPRODUCT($C$38:$E$38,$C$24:$E$24) | C60: =SUMPRODUCT($C$39:$E$39,$C$24:$E$24)
A61: EBITDA | B61: =SUMPRODUCT($C$38:$E$38,$C$32:$E$32) | C61: =SUMPRODUCT($C$39:$E$39,$C$32:$E$32)
A62: Adj. EBITDA | B62: =SUMPRODUCT($C$38:$E$38,$C$33:$E$33) | C62: =SUMPRODUCT($C$39:$E$39,$C$33:$E$33)
A63: NOPAT | B63: =SUMPRODUCT($C$38:$E$38,$C$26:$E$26) | C63: =SUMPRODUCT($C$39:$E$39,$C$26:$E$26)
A64: Free cash flow to firm | B64: =SUMPRODUCT($C$38:$E$38,$C$31:$E$31) | C64: =SUMPRODUCT($C$39:$E$39,$C$31:$E$31)
A66: Valuation method | B66: Metric | C66: Multiple used | D66: Basis | E66: Metric at target date | F66: Value per share | G66: Weight | H66: Metric key | I66: Metric shown (stated per-share figure when used)
A67: DCF (cash flow to target date + terminal) | F67: =((B45)-$B$50-$B$51+$B$52)/$B$53 | G67: =Valuation!$B$65
A68: ="Multiple: "&Valuation!A71&" ("&Valuation!D71&")" | B68: =Valuation!A71 | C68: =IF(B68="FCF yield",Valuation!B71*(1-$B$8),Valuation!B71+IF(B68="EV/sales",0.1,1)*$B$6) | D68: =Valuation!D71 | E68: =IF(D68="ltm",CHOOSE(H68,$C$59,$C$60,$C$61,$C$62,$C$63,$C$64),CHOOSE(H68,$B$59,$B$60,$B$61,$B$62,$B$63,$B$64)) | F68: =IF(OR(B68="EV/EBITDA",B68="EV/sales",B68="EV/EBIT"),((C68*E68)-$B$50-$B$51+$B$52)/$B$53,IF(B68="P/E",IF(Valuation!F71<>"",C68*Valuation!F71*(1+$B$9),C68*(E68-$B$54)/$B$53),IF(Valuation!G71<>"",Valuation!G71*(1+$B$9)/C68,(E68-IF(Valuation!H71,$B$54,0))/C68/$B$53))+$B$52/$B$53) | G68: =Valuation!C71 | H68: =IF(B68="EV/sales",1,IF(B68="EV/EBIT",2,IF(B68="EV/EBITDA",IF(Valuation!E71="adjusted",4,3),IF(B68="P/E",5,6)))) | I68: =IF(AND(B68="P/E",Valuation!F71<>""),Valuation!F71*(1+$B$9),IF(AND(B68="FCF yield",Valuation!G71<>""),Valuation!G71*(1+$B$9),E68))
A69: ="Multiple: "&Valuation!A72&" ("&Valuation!D72&")" | B69: =Valuation!A72 | C69: =IF(B69="FCF yield",Valuation!B72*(1-$B$8),Valuation!B72+IF(B69="EV/sales",0.1,1)*$B$6) | D69: =Valuation!D72 | E69: =IF(D69="ltm",CHOOSE(H69,$C$59,$C$60,$C$61,$C$62,$C$63,$C$64),CHOOSE(H69,$B$59,$B$60,$B$61,$B$62,$B$63,$B$64)) | F69: =IF(OR(B69="EV/EBITDA",B69="EV/sales",B69="EV/EBIT"),((C69*E69)-$B$50-$B$51+$B$52)/$B$53,IF(B69="P/E",IF(Valuation!F72<>"",C69*Valuation!F72*(1+$B$9),C69*(E69-$B$54)/$B$53),IF(Valuation!G72<>"",Valuation!G72*(1+$B$9)/C69,(E69-IF(Valuation!H72,$B$54,0))/C69/$B$53))+$B$52/$B$53) | G69: =Valuation!C72 | H69: =IF(B69="EV/sales",1,IF(B69="EV/EBIT",2,IF(B69="EV/EBITDA",IF(Valuation!E72="adjusted",4,3),IF(B69="P/E",5,6)))) | I69: =IF(AND(B69="P/E",Valuation!F72<>""),Valuation!F72*(1+$B$9),IF(AND(B69="FCF yield",Valuation!G72<>""),Valuation!G72*(1+$B$9),E69))
A70: ="Multiple: "&Valuation!A73&" ("&Valuation!D73&")" | B70: =Valuation!A73 | C70: =IF(B70="FCF yield",Valuation!B73*(1-$B$8),Valuation!B73+IF(B70="EV/sales",0.1,1)*$B$6) | D70: =Valuation!D73 | E70: =IF(D70="ltm",CHOOSE(H70,$C$59,$C$60,$C$61,$C$62,$C$63,$C$64),CHOOSE(H70,$B$59,$B$60,$B$61,$B$62,$B$63,$B$64)) | F70: =IF(OR(B70="EV/EBITDA",B70="EV/sales",B70="EV/EBIT"),((C70*E70)-$B$50-$B$51+$B$52)/$B$53,IF(B70="P/E",IF(Valuation!F73<>"",C70*Valuation!F73*(1+$B$9),C70*(E70-$B$54)/$B$53),IF(Valuation!G73<>"",Valuation!G73*(1+$B$9)/C70,(E70-IF(Valuation!H73,$B$54,0))/C70/$B$53))+$B$52/$B$53) | G70: =Valuation!C73 | H70: =IF(B70="EV/sales",1,IF(B70="EV/EBIT",2,IF(B70="EV/EBITDA",IF(Valuation!E73="adjusted",4,3),IF(B70="P/E",5,6)))) | I70: =IF(AND(B70="P/E",Valuation!F73<>""),Valuation!F73*(1+$B$9),IF(AND(B70="FCF yield",Valuation!G73<>""),Valuation!G73*(1+$B$9),E70))
A71: Value per share at target date (weighted methods) | F71: =SUMPRODUCT(F67:F70,G67:G70)/SUM(G67:G70)

Sheet Calc - bull
A1: MCHP engine calculation: bull scenario
A2: Machinery behind the Valuation and Distribution tabs; drivers come from Model, assumptions from Valuation.
A4: Scenario Growth Δ | B4: =N(Valuation!C87)
A5: Scenario Margin Δ | B5: =N(Valuation!D87)
A6: Scenario Multiple Δ (turns) | B6: =N(Valuation!E87)
A7: Scenario WACC Δ | B7: =N(Valuation!F87)
A8: Scenario Multiple %Δ | B8: =N(Valuation!G87)
A9: Scenario Stated EPS/FCF %Δ | B9: =N(Valuation!H87)
A10: Scenario Custom %Δ | B10: =N(Valuation!I87)
A12: WACC | B12: =Valuation!$B$52+B7
A13: Years from last FY end to target date | B13: =(Valuation!$B$46-Valuation!$B$50)/365.25
A14: Years from last FY end to balance date | B14: =(Valuation!$B$56-Valuation!$B$50)/365.25
A15: Years from last FY end to share count date | B15: =(Valuation!$B$62-Valuation!$B$50)/365.25
A16: Projected years | B16: 3
A18: Projection | B18: Base | C18: =Model!E5 | D18: =Model!F5 | E18: =Model!G5
A19: Year index | B19: 0 | C19: 1 | D19: 2 | E19: 3
A20: Period end | C20: =Valuation!$B$50+ROUND(365.25*C19,0) | D20: =Valuation!$B$50+ROUND(365.25*D19,0) | E20: =Valuation!$B$50+ROUND(365.25*E19,0)
A21: Revenue growth | C21: =Model!E48+$B$4 | D21: =Model!F48+$B$4 | E21: =Model!G48+$B$4
A22: Revenue | B22: =Valuation!$B$51 | C22: =B22*(1+C21) | D22: =C22*(1+D21) | E22: =D22*(1+E21)
A23: EBIT margin | C23: =Model!E49+$B$5 | D23: =Model!F49+$B$5 | E23: =Model!G49+$B$5
A24: EBIT | C24: =C22*C23 | D24: =D22*D23 | E24: =E22*E23
A25: Tax rate | C25: =Model!E50 | D25: =Model!F50 | E25: =Model!G50
A26: NOPAT | C26: =C24*(1-C25) | D26: =D24*(1-D25) | E26: =E24*(1-E25)
A27: D&A | C27: =C22*Model!E51 | D27: =D22*Model!F51 | E27: =E22*Model!G51
A28: Capex | C28: =C22*Model!E52 | D28: =D22*Model!F52 | E28: =E22*Model!G52
A29: Working capital increase | C29: =Model!E53*(C22-B22) | D29: =Model!F53*(D22-C22) | E29: =Model!G53*(E22-D22)
A30: Stock comp | C30: =C22*Model!E54 | D30: =D22*Model!F54 | E30: =E22*Model!G54
A31: Free cash flow to firm | C31: =C26+C27-C28-C29-IF(AND(Valuation!$B$48="adjusted",Valuation!$B$49="cost"),C30*(1-C25),0) | D31: =D26+D27-D28-D29-IF(AND(Valuation!$B$48="adjusted",Valuation!$B$49="cost"),D30*(1-D25),0) | E31: =E26+E27-E28-E29-IF(AND(Valuation!$B$48="adjusted",Valuation!$B$49="cost"),E30*(1-E25),0)
A32: EBITDA | C32: =C24+C27 | D32: =D24+D27 | E32: =E24+E27
A33: Adj. EBITDA | C33: =C24+C27+C22*Model!E58 | D33: =D24+D27+D22*Model!F58 | E33: =E24+E27+E22*Model!G58
A34: Shareholder returns + other uses | C34: =C22*Model!E56+Model!E55+Model!E57 | D34: =D22*Model!F56+Model!F55+Model!F57 | E34: =E22*Model!G56+Model!G55+Model!G57
A35: Share of year after target date | C35: =IF(C19<=$B$13,0,C19-MAX(C19-1,$B$13)) | D35: =IF(D19<=$B$13,0,D19-MAX(D19-1,$B$13)) | E35: =IF(E19<=$B$13,0,E19-MAX(E19-1,$B$13))
A36: PV at target date of FCFF | C36: =IF(C35=0,0,C31*C35/(1+$B$12)^(C19-$B$13)) | D36: =IF(D35=0,0,D31*D35/(1+$B$12)^(D19-$B$13)) | E36: =IF(E35=0,0,E31*E35/(1+$B$12)^(E19-$B$13))
A37: Overlap: balance date to target date | C37: =MAX(0,MIN(C19,$B$13)-MAX(C19-1,$B$14)) | D37: =MAX(0,MIN(D19,$B$13)-MAX(D19-1,$B$14)) | E37: =MAX(0,MIN(E19,$B$13)-MAX(E19-1,$B$14))
A38: NTM weight at target date | C38: =MAX(0,MIN(C19,$B$13+1)-MAX(C19-1,$B$13)) | D38: =MAX(0,MIN(D19,$B$13+1)-MAX(D19-1,$B$13)) | E38: =MAX(0,MIN(E19,$B$13+1)-MAX(E19-1,$B$13))
A39: LTM weight at target date | B39: =MAX(0,MIN(0,$B$13)-MAX(-1,$B$13-1)) | C39: =MAX(0,MIN(C19,$B$13)-MAX(C19-1,$B$13-1)) | D39: =MAX(0,MIN(D19,$B$13)-MAX(D19-1,$B$13-1)) | E39: =MAX(0,MIN(E19,$B$13)-MAX(E19-1,$B$13-1))
A41: Value at the target date
A42: PV of free cash flow after the target date | B42: =SUM($C$36:$E$36)
A43: Terminal value at final year | B43: =IF(Valuation!$B$53="exit_multiple",Valuation!$B$55*E32,E31*(1+Valuation!$B$54)/($B$12-Valuation!$B$54))
A44: PV of terminal value at target date | B44: =B43/(1+$B$12)^($B$16-$B$13)
A45: DCF enterprise value at target date | B45: =B42+B44
A46: Terminal value share of DCF | B46: =B44/B45
A47: Free cash flow earned, balance date to target date | B47: =SUMPRODUCT($C$37:$E$37,$C$31:$E$31)
A48: Shareholder returns + other uses paid | B48: =SUMPRODUCT($C$37:$E$37,$C$34:$E$34)
A49: Interest drag on net debt | B49: =Valuation!$B$59*(1-$C$25)*MAX(Valuation!$B$57,0)*MAX($B$13-$B$14,0)
A50: Net debt at target date | B50: =IF(Valuation!$B$60="",Valuation!$B$57-B47+B49+B48,Valuation!$B$60)
A51: Minority interests | B51: =Valuation!$B$58
A52: Adjustments (probability-weighted) | B52: 0
A53: Diluted shares at target date (M) | B53: =IF(Valuation!$B$64="",Valuation!$B$61*(1+Valuation!$B$63)^MAX($B$13-$B$15,0),Valuation!$B$64)
A54: After-tax interest on target-date net debt | B54: =Valuation!$B$59*(1-$C$25)*MAX(B50,0)
A55: Check: WACC vs terminal growth | B55: =IF(AND(Valuation!$B$53<>"exit_multiple",$B$12<=Valuation!$B$54+0.01),"WACC must exceed terminal growth by 1 point","ok")
A56: Check: projection length | B56: =IF(OR($B$13>=$B$16-1,$B$13+1>$B$16),"add projected years past the target date","ok")
A58: Metric at target date | B58: Next 12 months | C58: Last 12 months
A59: Revenue | B59: =SUMPRODUCT($C$38:$E$38,$C$22:$E$22) | C59: =SUMPRODUCT($C$39:$E$39,$C$22:$E$22)+$B$39*$B$22
A60: EBIT | B60: =SUMPRODUCT($C$38:$E$38,$C$24:$E$24) | C60: =SUMPRODUCT($C$39:$E$39,$C$24:$E$24)
A61: EBITDA | B61: =SUMPRODUCT($C$38:$E$38,$C$32:$E$32) | C61: =SUMPRODUCT($C$39:$E$39,$C$32:$E$32)
A62: Adj. EBITDA | B62: =SUMPRODUCT($C$38:$E$38,$C$33:$E$33) | C62: =SUMPRODUCT($C$39:$E$39,$C$33:$E$33)
A63: NOPAT | B63: =SUMPRODUCT($C$38:$E$38,$C$26:$E$26) | C63: =SUMPRODUCT($C$39:$E$39,$C$26:$E$26)
A64: Free cash flow to firm | B64: =SUMPRODUCT($C$38:$E$38,$C$31:$E$31) | C64: =SUMPRODUCT($C$39:$E$39,$C$31:$E$31)
A66: Valuation method | B66: Metric | C66: Multiple used | D66: Basis | E66: Metric at target date | F66: Value per share | G66: Weight | H66: Metric key | I66: Metric shown (stated per-share figure when used)
A67: DCF (cash flow to target date + terminal) | F67: =((B45)-$B$50-$B$51+$B$52)/$B$53 | G67: =Valuation!$B$65
A68: ="Multiple: "&Valuation!A71&" ("&Valuation!D71&")" | B68: =Valuation!A71 | C68: =IF(B68="FCF yield",Valuation!B71*(1-$B$8),Valuation!B71+IF(B68="EV/sales",0.1,1)*$B$6) | D68: =Valuation!D71 | E68: =IF(D68="ltm",CHOOSE(H68,$C$59,$C$60,$C$61,$C$62,$C$63,$C$64),CHOOSE(H68,$B$59,$B$60,$B$61,$B$62,$B$63,$B$64)) | F68: =IF(OR(B68="EV/EBITDA",B68="EV/sales",B68="EV/EBIT"),((C68*E68)-$B$50-$B$51+$B$52)/$B$53,IF(B68="P/E",IF(Valuation!F71<>"",C68*Valuation!F71*(1+$B$9),C68*(E68-$B$54)/$B$53),IF(Valuation!G71<>"",Valuation!G71*(1+$B$9)/C68,(E68-IF(Valuation!H71,$B$54,0))/C68/$B$53))+$B$52/$B$53) | G68: =Valuation!C71 | H68: =IF(B68="EV/sales",1,IF(B68="EV/EBIT",2,IF(B68="EV/EBITDA",IF(Valuation!E71="adjusted",4,3),IF(B68="P/E",5,6)))) | I68: =IF(AND(B68="P/E",Valuation!F71<>""),Valuation!F71*(1+$B$9),IF(AND(B68="FCF yield",Valuation!G71<>""),Valuation!G71*(1+$B$9),E68))
A69: ="Multiple: "&Valuation!A72&" ("&Valuation!D72&")" | B69: =Valuation!A72 | C69: =IF(B69="FCF yield",Valuation!B72*(1-$B$8),Valuation!B72+IF(B69="EV/sales",0.1,1)*$B$6) | D69: =Valuation!D72 | E69: =IF(D69="ltm",CHOOSE(H69,$C$59,$C$60,$C$61,$C$62,$C$63,$C$64),CHOOSE(H69,$B$59,$B$60,$B$61,$B$62,$B$63,$B$64)) | F69: =IF(OR(B69="EV/EBITDA",B69="EV/sales",B69="EV/EBIT"),((C69*E69)-$B$50-$B$51+$B$52)/$B$53,IF(B69="P/E",IF(Valuation!F72<>"",C69*Valuation!F72*(1+$B$9),C69*(E69-$B$54)/$B$53),IF(Valuation!G72<>"",Valuation!G72*(1+$B$9)/C69,(E69-IF(Valuation!H72,$B$54,0))/C69/$B$53))+$B$52/$B$53) | G69: =Valuation!C72 | H69: =IF(B69="EV/sales",1,IF(B69="EV/EBIT",2,IF(B69="EV/EBITDA",IF(Valuation!E72="adjusted",4,3),IF(B69="P/E",5,6)))) | I69: =IF(AND(B69="P/E",Valuation!F72<>""),Valuation!F72*(1+$B$9),IF(AND(B69="FCF yield",Valuation!G72<>""),Valuation!G72*(1+$B$9),E69))
A70: ="Multiple: "&Valuation!A73&" ("&Valuation!D73&")" | B70: =Valuation!A73 | C70: =IF(B70="FCF yield",Valuation!B73*(1-$B$8),Valuation!B73+IF(B70="EV/sales",0.1,1)*$B$6) | D70: =Valuation!D73 | E70: =IF(D70="ltm",CHOOSE(H70,$C$59,$C$60,$C$61,$C$62,$C$63,$C$64),CHOOSE(H70,$B$59,$B$60,$B$61,$B$62,$B$63,$B$64)) | F70: =IF(OR(B70="EV/EBITDA",B70="EV/sales",B70="EV/EBIT"),((C70*E70)-$B$50-$B$51+$B$52)/$B$53,IF(B70="P/E",IF(Valuation!F73<>"",C70*Valuation!F73*(1+$B$9),C70*(E70-$B$54)/$B$53),IF(Valuation!G73<>"",Valuation!G73*(1+$B$9)/C70,(E70-IF(Valuation!H73,$B$54,0))/C70/$B$53))+$B$52/$B$53) | G70: =Valuation!C73 | H70: =IF(B70="EV/sales",1,IF(B70="EV/EBIT",2,IF(B70="EV/EBITDA",IF(Valuation!E73="adjusted",4,3),IF(B70="P/E",5,6)))) | I70: =IF(AND(B70="P/E",Valuation!F73<>""),Valuation!F73*(1+$B$9),IF(AND(B70="FCF yield",Valuation!G73<>""),Valuation!G73*(1+$B$9),E70))
A71: Value per share at target date (weighted methods) | F71: =SUMPRODUCT(F67:F70,G67:G70)/SUM(G67:G70)

Sheet Agents
A1: MCHP: each forecaster's own assumption set through the same engine (from model_engine.json, not live)
A3: Set | B3: Fair value | C3: Median | D3: 25th pct | E3: 75th pct | F3: WACC | G3: Y1 growth | H3: Y1 margin | I3: Terminal growth | J3: DCF weight | K3: Years | L3: Multiples | M3: Supervisor's note
A4: agent 1 | B4: 83.192158 | C4: 84.533898 | D4: 62.461174 | E4: 111.43515 | F4: 0.1358 | G4: 0.33568 | H4: 0.3808 | I4: 0 | J4: 0 | K4: 3 | L4: P/E 19.0 (ntm); EV/EBITDA 15.5 (ntm) | M4: EV-based FCF leg (4.8% on EV, $82) carried as a custom leg; EV/EBITDA at 15.5x is the double-counted derating the supervisor harmonised to 16x; lowest NTM EPS ($4.50) with agent 2.
A5: agent 2 | B5: 83.447228 | C5: 83.30371 | D5: 61.494002 | E5: 108.65317 | F5: 0.1357 | G5: 0.33568 | H5: 0.3808 | I5: 0 | J5: 0 | K5: 3 | L5: P/E 19.0 (ntm); FCF yield 0.05 (ntm); EV/EBITDA 15.0 (ntm) | M5: EV/EBITDA at 15x ($75.7) double-counts the derating already in its 19x P/E (supervisor harmonised to 16x); capex at the current ~$90M/yr run-rate, lowest in the run (DCF only).
A6: agent 3 | B6: 85.460861 | C6: 86.477032 | D6: 64.11624 | E6: 113.04421 | F6: 0.1355 | G6: 0.33568 | H6: 0.3808 | I6: 0 | J6: 0 | K6: 3 | L6: P/E 18.5 (ntm); FCF yield 0.0475 (ntm); EV/EBITDA 15.0 (ntm) | M6: Highest FCF leg ($89.7 at a 4.75% yield, below the 5.0% the others and the supervisor use); EV/EBITDA at 15x.
A7: agent 4 | B7: 84.606544 | C7: 84.335744 | D7: 62.794319 | E7: 109.42805 | F7: 0.1358 | G7: 0.33568 | H7: 0.3808 | I7: 0 | J7: 0 | K7: 3 | L7: P/E 18.5 (ntm); FCF yield 0.05 (ntm); EV/EBITDA 14.0 (ntm) | M7: EV/EBITDA at 14x ($73 on FY28 EBITDA) is the harshest double-count; its $4.45 FY28 -> $4.75 NTM EPS roll-forward implies ~14% FY29 growth, which lifts the engine's NTM-based EV/EBITDA leg to ~$78.
A8: agent 5 | B8: 84.787 | C8: 85.915776 | D8: 64.083303 | E8: 112.66885 | F8: 0.1358 | G8: 0.33568 | H8: 0.3808 | I8: 0 | J8: 0 | K8: 3 | L8: P/E 18.5 (ntm); FCF yield 0.052 (ntm); EV/EBITDA 16.0 (ntm) | M8: FY28 FCF $2.6B (35% margin) above the run's $2.45B; otherwise closest to the reconciled set (16x EV/EBITDA, 18.5x on $4.55).
A9: supervisor | B9: 85.323614 | C9: 85.401523 | D9: 63.672571 | E9: 112.18646 | F9: 0.1358 | G9: 0.33568 | H9: 0.3808 | I9: 0 | J9: 0 | K9: 3 | L9: P/E 18.75 (ntm); FCF yield 0.05 (ntm); EV/EBITDA 16.0 (ntm)

Sheet Sources
A1: MCHP: where each input comes from (source numbers point to the list below; F ids to the SEC fact table)
A3: Input | B3: Value | C3: Basis | D3: Sources | E3: SEC fact ids | F3: Derivation
A4: base.revenue FY2026 (Mar-2026) | B4: 4713.1 | C4: reported | E4: F3 | F4: FY ending 2026-03-31 revenue, 10-K filed 2026-05-21. filled in (not stated in this set's original work): the run built from quarterly figures, not the FY2026 base.
A5: base.fy_end | B5: 2026-03-31 | C5: reported | E5: F3 | F5: Last reported fiscal year end. filled in (not stated in this set's original work).
A6: years[FY2027].revenue_growth | B6: 0.33568 | C6: estimate | D6: 3 | E6: F7 | F6: filled in (not stated in this set's original work). FY2027 revenue 6,295.2 = Q1 FY27 actual 1,484.7 (F7) + 3 x Q2 FY27 guided midpoint 1,603.5 ($1,589-1,618M, 8-K Ex. 99.1), i.e. H2 held flat at the Q2 guide; / FY2026 4,713.1 - 1. No forecaster stated full-year FY27 revenue; FY27 sits before the horizon and its only role is the base for FY28.
A7: years[FY2027].ebit_margin (non-GAAP) | B7: 0.3808 | C7: estimate | D7: 3 | F7: filled in (not stated in this set's original work). (Q1 FY27 non-GAAP operating income 521.1 + 3 x 39.0% (Q2 guide 38.5-39.5% midpoint) x 1,603.5) / 6,295.2. Inert for the horizon value (before H).
A8: years[FY2027].tax_rate (non-GAAP) | B8: 0.075 | C8: guidance | D8: 3 | F8: filled in (not stated in this set's original work). FY27 non-GAAP tax guided ~7.5% (Q2 guide $42.2-44.3M on $562.2-590.7M pretax; Q1 actual 7.5%).
A9: years[FY2028].revenue_growth | B9: 0.1755 | C9: estimate | D9: 6 | F9: FY2028 (Mar-2028) revenue 7,400 (forecasters' median of 7,300 / 7,300 / 7,500 / 7,400 / 7,400, not settled by the supervisor; FY28 consensus $7.43B (source 6)) / FY2027 6,295.2 - 1.
A10: years[FY2028].ebit_margin (non-GAAP operating margin) | B10: 0.4 | C10: estimate | D10: 3, 9 | F10: Forecasters' median (the supervisor did not settle this driver): agents 40% / 39.5% / 40% / 40% / 39.5% -> 40%; Q2 FY27 guide 38.5-39.5%, through-cycle model 40%.
A11: years[FY2028].tax_rate (non-GAAP) | B11: 0.08 | C11: estimate | D11: 3 | F11: Supervisor's fair value build: "~8% tax" (an estimate: FY27 guided ~7.5%, ~0.5pp cushion for unguided FY28; citation gate).
A12: years[FY2028].da_pct_rev (depreciation) | B12: 0.0274 | C12: estimate | D12: 3, 8 | F12: Forecasters' median (the supervisor did not settle this driver): depreciation as % of FY28 revenue, agents 0.0274 / 0.0274 / 0.0267 / 0.0400 / 0.0374. With the 40% margin this gives FY28 EBITDA ~3,163 and NTM EBITDA at Sep-2027 ~3,228, the supervisor's "~$3.2B".
A13: years[FY2028].capex_pct_rev | B13: 0.01689 | C13: estimate | D13: 3 | F13: Forecasters' median (the supervisor did not settle this driver): agents 0.0171 / 0.0123 / 0.0160 / 0.0170 / 0.0169 (agent 4 filled from the fact pack). Feeds only the DCF (weight 0).
A14: years[FY2028].nwc_pct_incr_rev | B14: 0.1245 | C14: estimate | F14: filled in (not stated in this set's original work): agent 3's stated ~$150M FY28 working-capital build over its revenue increase (= 0.1245), the only figure in the run. Feeds only the DCF (weight 0).
A15: years[FY2027-28].sbc_pct_rev | B15: 0.0542 | C15: reported | E15: F46, F6 | F15: filled in (not stated in this set's original work). SBC TTM to Jun-2026 277.5 / revenue TTM 5,122.3. Counted once, as a cost in the DCF FCFF (sbc_treatment cost); the P/E and FCF legs are on the company's non-GAAP basis, as the forecaster valued them, with the share count held at its 575M.
A16: years[*].shareholder_returns | B16: 0.0 | C16: judgment | F16: Not used: net debt at the horizon is the supervisor's ~$3.8B, already after ~$1.1B/yr common + preferred dividends and no buybacks.
A17: years[FY2029].revenue_growth | B17: 0.0419 | C17: estimate | D17: 6 | F17: Forecasters' median (the supervisor did not settle this driver): FY29 growth implied by each forecaster's own FY28 -> NTM roll-forward, 0.0419 / 0.0474 / 0.0342 / 0.1385 / 0.0344. The supervisor's NTM EPS of $4.55-4.65 vs FY28 consensus $4.58 is consistent with it.
A18: terminal.growth | B18: 0.0 | C18: judgment | F18: filled in (not stated in this set's original work): no terminal growth in the original work; zero, because the capitalisation rate below is the forecaster's FCF yield, which already nets growth (yield = r - g).
A19: discount_rate.wacc | B19: 0.1358 | C19: estimate | D19: 12 | F19: filled in (not stated in this set's original work): cost of equity 0.1462 = T-bill 0.0412 + beta 2.10 x 5% (the price target's market leg, 2026-09-25); after-tax debt 0.0474 x (1 - 0.075) on net debt and minorities 5,089 vs equity 45,192 (574.30M x $78.69) -> WACC 0.1358
A20: balance.net_debt (2026-06-30) | B20: 5089.0 | C20: reported | D20: 3, 8 | E20: F101, F95, F94 | F20: Long-term debt 5,361.3 - cash 272.3 = 5,089.0 (the run's "$5.09B at Jun-2026").
A21: balance.as_of | B21: 2026-06-30 | C21: reported | D21: 3, 8 | E21: F95, F94 | F21: Balance-sheet date of the 10-Q. filled in (not stated in this set's original work) (date only).
A22: balance.minorities | B22: 0.0 | C22: judgment | F22: filled in (not stated in this set's original work): none in the original work; the Series A mandatory convertible preferred is carried as 23.8M as-converted shares inside the 575M, not as a claim.
A23: balance.interest_rate | B23: 0.0474 | C23: estimate | D23: 3, 8 | F23: FY2028 interest ~$180M (forecasters' median: 180 / 175 / 170 / 180 / 180) / Sep-2027 net debt 3,800. Feeds no leg here (stated EPS, FCF per share and net debt).
A24: balance.net_debt_horizon (Sep-2027) | B24: 3800.0 | C24: estimate | D24: 3, 8 | E24: F101 | F24: $5.09B at Jun-2026 less ~$250-300M/qtr paydown after ~$1.1B/yr common + preferred dividends = ~$3.8B (5.09 - 5 x ~0.26), the supervisor's and every forecaster's figure.
A25: shares.diluted_now (non-GAAP diluted, Q1 FY27) | B25: 574.3 | C25: reported | D25: 3 | E25: F33 | F25: 550.5M GAAP diluted (F33) + 23.8M Series A mandatory-convertible as-converted shares (8-K Ex. 99.1) = 574.3M.
A26: shares.horizon | B26: 575.0 | C26: estimate | D26: 3 | F26: 575M non-GAAP diluted shares, the supervisor's and every forecaster's base for every method; no net buyback or dilution assumed (annual_change 0). More shares issue below ~$62.5 (bear-case drag only).
A27: horizon_multiples[P/E].eps (NTM at Sep-2027, non-GAAP) | B27: 4.6 | C27: estimate | D27: 6 | F27: Supervisor: NTM EPS ~$4.55-4.65 at Sep-2027 (575M shares, ~8% tax, light haircut to consensus): midpoint $4.60. Settled disagreement: agents' $4.50-4.75 left as is, all within ~5% of the consensus roll-forward (~$4.7-4.8).
A28: horizon_multiples[P/E].value | B28: 18.75 | C28: judgment | D28: 12 | F28: Supervisor: 18.5-19x NTM, midpoint 18.75x -> P/E leg 86.25 (gate-verified). Transcribed as the supervisor chose it; the citation gate notes that on NTM EPS the NXPI-ON range is ~13.7-18.5x (TXN ~27.6x, ADI ~24.6x), so 18.5-19x sits at the top of it (on current-year EPS NXPI 15.8x, ON 24.1x).
A29: horizon_multiples[P/E].weight | B29: 0.5 | C29: judgment | F29: The supervisor's leg weight (about 0.5/0.3/0.2).
A30: horizon_multiples[FCF yield].fcf_per_share | B30: 4.26 | C30: estimate | D30: 3 | F30: Supervisor: FY28 FCF ~$2.45-2.6B (after interest, before the ~$111M preferred dividend) over 575M as-converted shares; the verified $85.2 blend input uses $2.45B -> 2.45 / 0.575 = $4.26 (range to $4.52 at $2.6B).
A31: horizon_multiples[FCF yield].value | B31: 0.05 | C31: judgment | D31: 12 | F31: Supervisor: 5.0-5.2% required equity yield; 5.0% with $4.26 gives the $85.2 leg in its verified blend (2.45 / 0.05 / 0.575); no net-debt deduction (equity basis). TTM FCF yield NXPI 4.7%, ON 5.0% (gate rebuild).
A32: horizon_multiples[FCF yield].weight | B32: 0.3 | C32: judgment | F32: The supervisor's leg weight (about 0.5/0.3/0.2).
A33: horizon_multiples[EV/EBITDA].value | B33: 16.0 | C33: judgment | D33: 12 | F33: Supervisor's settled disagreement: harmonised at ~16x, because at 575M shares and ~$3.8B net debt the 18.5-19x P/E implies ~16-17x EBITDA, so the agents' 14-15.5x double-counts the derating.
A34: horizon_multiples[EV/EBITDA].weight | B34: 0.2 | C34: judgment | F34: The supervisor's leg weight (about 0.5/0.3/0.2).
A35: horizon_multiples[EV/EBITDA] metric (NTM EBITDA at Sep-2027) | B35: ~3,200 (engine NTM ~3,228) | C35: estimate | D35: 3, 8 | F35: Supervisor: "~16x on ~$3.2B EBITDA" (non-GAAP op income + depreciation). The engine's NTM EBITDA at Sep-2027 is ~3,228 from the median drivers.
A36: scenarios.bear.prob | B36: 0.2 | C36: judgment | F36: Forecasters' median bear probability (0.2 / 0.22 / 0.2 / 0.2 / 0.2); supervisor: bear weight 20-22% agreed.
A37: scenarios.bear.deltas | B37: {"eps_pct": -0.2444, "ebit_margin": -0.0978, "multiple": -3.5, "multiple_pct": -0.2295} | C37: judgment | F37: Forecasters' median bear deltas (the supervisor kept their scenarios; it agreed the bear weight and mid-2027 peak risk): eps_pct median of -0.2667 / -0.2444 / -0.2340 / -0.2737 / -0.2308, multiple median of -3.5 / -4 / -4 / -3.5 / -3.5; ebit_margin = eps_pct x 40%; multiple_pct = 1 - 18.75 / (18.75 + multiple). Forecasters' median scenario price $52.
A38: scenarios.base.prob | B38: 0.55 | C38: judgment | F38: Forecasters' median base probability (0.55 / 0.53 / 0.55 / 0.55 / 0.55).
A39: scenarios.base.deltas | B39: {} | C39: judgment | F39: Forecasters' median base deltas (the supervisor kept their scenarios; it agreed the bear weight and mid-2027 peak risk): eps_pct median of 0.0111 / 0.0111 / 0.0000 / 0.0000 / 0.0000, multiple median of 0 / 0 / 0.25 / 0 / 0.25; ebit_margin = eps_pct x 40%; multiple_pct = 1 - 18.75 / (18.75 + multiple). Forecasters' median scenario price $87.
A40: scenarios.bull.prob | B40: 0.25 | C40: judgment | F40: Forecasters' median bull probability (0.25 / 0.25 / 0.25 / 0.25 / 0.25).
A41: scenarios.bull.deltas | B41: {"eps_pct": 0.1702, "ebit_margin": 0.0681, "multiple": 3.5, "multiple_pct": 0.1573} | C41: judgment | F41: Forecasters' median bull deltas (the supervisor kept their scenarios; it agreed the bear weight and mid-2027 peak risk): eps_pct median of 0.2222 / 0.1111 / 0.1702 / 0.2000 / 0.1429, multiple median of 3.5 / 4.5 / 3.5 / 2.5 / 4; ebit_margin = eps_pct x 40%; multiple_pct = 1 - 18.75 / (18.75 + multiple). Forecasters' median scenario price $122.
A42: scenario_vol | B42: 0.31 | C42: estimate | F42: filled in (not stated in this set's original work): not stated; least-squares fit of the engine's distribution to the supervisor's own ladder (the forecasters' mean).
A44: # | B44: Source | C44: Date | D44: Link
A45: 1 | B45: Microchip Technology (MCHP) Stock Is Up, What You Need To Know (StockStory via FinancialContent) | C45: 2026-09-25 | D45: https://markets.financialcontent.com/stocks/article/stockstory-2026-9-25-microchip-technology-mchp-stock-is-up-what-you-need-to-know
A46: 2 | B46: Microchip Technology (MCHP) Stock Price & Overview (StockAnalysis) | C46: 2026-09-27 | D46: https://stockanalysis.com/stocks/mchp/
A47: 3 | B47: Microchip Q1 FY2027 results press release (8-K Ex. 99.1) | C47: 2026-08-06 | D47: https://www.sec.gov/Archives/edgar/data/827054/000082705426000037/exhibit991q1fy27.htm
A48: 4 | B48: Microchip at Citi 2026 Global TMT Conference (Investing.com) | C48: 2026-09-09 | D48: https://uk.investing.com/news/stock-market-news/microchip-at-citi-2026-global-tmt-conference-recovery-broadens-93CH-4863475
A49: 5 | B49: Microchip IR Financial Results | C49: 2026-09-27 | D49: https://ir.microchip.com/financial-info/financial-results
A50: 6 | B50: MCHP analyst estimates (StockAnalysis, S&P Global consensus; FY28 EPS $4.58, revenue $7.43B; data updated 2026-09-18) | C50: 2026-09-18 | D50: https://stockanalysis.com/stocks/mchp/forecast/
A51: 7 | B51: MCHP price history (StockAnalysis): 2026-09-25 close $78.69 | C51: 2026-10-14 | D51: https://stockanalysis.com/stocks/mchp/history/
A52: 8 | B52: Microchip Form 10-Q, quarter ended June 30, 2026 (convertible preferred terms, depreciation, buyback authorization) | C52: 2026-08-06 | D52: https://www.sec.gov/Archives/edgar/data/827054/000082705426000038/mchp-20260630.htm
A53: 9 | B53: Microchip at Citi 2026 Global TMT Conference (Investing.com transcript) | C53: 2026-09-09 | D53: https://www.investing.com/news/transcripts/microchip-at-citi-2026-global-tmt-conference-recovery-broadens-93CH-4894731
A54: 10 | B54: Microchip Q1 FY2027 earnings call transcript (Motley Fool) | C54: 2026-08-13 | D54: https://www.fool.com/earnings/call-transcripts/2026/08/13/microchip-mchp-q1-2027-earnings-call-transcript/
A55: 11 | B55: U.S. Treasury daily par yield curve rates, September 2026 (10-yr 5.17% on 2026-09-25) | C55: 2026-09-25 | D55: https://home.treasury.gov/resource-center/data-chart-center/interest-rates/TextView?type=daily_treasury_yield_curve&field_tdr_date_value_month=202609
A56: 12 | B56: NXP Semiconductors Form 10-Q, quarter ended June 28, 2026 (peer rebuild) | C56: 2026-07-28 | D56: https://www.sec.gov/Archives/edgar/data/1413447/000141344726000045/nxpi-20260628.htm
A57: 13 | B57: Microchip Technology Acquires VORAGO Technologies (after the research date; not material) | C57: 2026-10-09 | D57: https://ir.microchip.com/news-events/press-releases/detail/1419/microchip-technology-acquires-vorago-technologies
A59: Fact id | B59: Figure | C59: Value | D59: Filing
A60: F1 | B60: revenue FY ending 2024-03-31 (us-gaap:RevenueFromContractWithCustomerExcludingAssessedTax) | C60: 7634400000 | D60: https://www.sec.gov/Archives/edgar/data/827054/000082705426000016/
A61: F2 | B61: revenue FY ending 2025-03-31 (us-gaap:RevenueFromContractWithCustomerExcludingAssessedTax) | C61: 4401600000 | D61: https://www.sec.gov/Archives/edgar/data/827054/000082705426000016/
A62: F3 | B62: revenue FY ending 2026-03-31 (us-gaap:RevenueFromContractWithCustomerExcludingAssessedTax) | C62: 4713100000 | D62: https://www.sec.gov/Archives/edgar/data/827054/000082705426000016/
A63: F4 | B63: revenue YTD 2026-04-01 to 2026-06-30 | C63: 1484700000 | D63: https://www.sec.gov/Archives/edgar/data/827054/000082705426000038/
A64: F5 | B64: revenue prior-year YTD 2025-04-01 to 2025-06-30 | C64: 1075500000 | D64: https://www.sec.gov/Archives/edgar/data/827054/000082705426000038/
A65: F6 | B65: revenue TTM to 2026-06-30 | C65: 5122300000
A66: F7 | B66: revenue quarter 2026-04-01 to 2026-06-30 | C66: 1484700000 | D66: https://www.sec.gov/Archives/edgar/data/827054/000082705426000038/
A67: F8 | B67: operating_income FY ending 2024-03-31 (us-gaap:OperatingIncomeLoss) | C67: 2571000000 | D67: https://www.sec.gov/Archives/edgar/data/827054/000082705426000016/
A68: F9 | B68: operating_income FY ending 2025-03-31 (us-gaap:OperatingIncomeLoss) | C68: 296300000 | D68: https://www.sec.gov/Archives/edgar/data/827054/000082705426000016/
A69: F10 | B69: operating_income FY ending 2026-03-31 (us-gaap:OperatingIncomeLoss) | C69: 490100000 | D69: https://www.sec.gov/Archives/edgar/data/827054/000082705426000016/
A70: F11 | B70: operating_income YTD 2026-04-01 to 2026-06-30 | C70: 336800000 | D70: https://www.sec.gov/Archives/edgar/data/827054/000082705426000038/
A71: F12 | B71: operating_income prior-year YTD 2025-04-01 to 2025-06-30 | C71: 32100000 | D71: https://www.sec.gov/Archives/edgar/data/827054/000082705426000038/
A72: F13 | B72: operating_income TTM to 2026-06-30 | C72: 794800000
A73: F14 | B73: operating_income quarter 2026-04-01 to 2026-06-30 | C73: 336800000 | D73: https://www.sec.gov/Archives/edgar/data/827054/000082705426000038/
A74: F15 | B74: net_income FY ending 2024-03-31 (us-gaap:NetIncomeLoss) | C74: 1906900000 | D74: https://www.sec.gov/Archives/edgar/data/827054/000082705426000016/
A75: F16 | B75: net_income FY ending 2025-03-31 (us-gaap:NetIncomeLoss) | C75: -500000 | D75: https://www.sec.gov/Archives/edgar/data/827054/000082705426000016/
A76: F17 | B76: net_income FY ending 2026-03-31 (us-gaap:NetIncomeLoss) | C76: 230000000 | D76: https://www.sec.gov/Archives/edgar/data/827054/000082705426000016/
A77: F18 | B77: net_income YTD 2026-04-01 to 2026-06-30 | C77: 229800000 | D77: https://www.sec.gov/Archives/edgar/data/827054/000082705426000038/
A78: F19 | B78: net_income prior-year YTD 2025-04-01 to 2025-06-30 | C78: -18600000 | D78: https://www.sec.gov/Archives/edgar/data/827054/000082705426000038/
A79: F20 | B79: net_income TTM to 2026-06-30 | C79: 478400000
A80: F21 | B80: net_income quarter 2026-04-01 to 2026-06-30 | C80: 229800000 | D80: https://www.sec.gov/Archives/edgar/data/827054/000082705426000038/
A81: F22 | B81: eps_diluted FY ending 2024-03-31 (us-gaap:EarningsPerShareDiluted) | C81: 3.48 | D81: https://www.sec.gov/Archives/edgar/data/827054/000082705426000016/
A82: F23 | B82: eps_diluted FY ending 2025-03-31 (us-gaap:EarningsPerShareDiluted) | C82: -0.01 | D82: https://www.sec.gov/Archives/edgar/data/827054/000082705426000016/
A83: F24 | B83: eps_diluted FY ending 2026-03-31 (us-gaap:EarningsPerShareDiluted) | C83: 0.22 | D83: https://www.sec.gov/Archives/edgar/data/827054/000082705426000016/
A84: F25 | B84: eps_diluted YTD 2026-04-01 to 2026-06-30 | C84: 0.37 | D84: https://www.sec.gov/Archives/edgar/data/827054/000082705426000038/
A85: F26 | B85: eps_diluted prior-year YTD 2025-04-01 to 2025-06-30 | C85: -0.09 | D85: https://www.sec.gov/Archives/edgar/data/827054/000082705426000038/
A86: F27 | B86: eps_diluted quarter 2026-04-01 to 2026-06-30 | C86: 0.37 | D86: https://www.sec.gov/Archives/edgar/data/827054/000082705426000038/
A87: F28 | B87: diluted_shares_wavg FY ending 2024-03-31 (us-gaap:WeightedAverageNumberOfDilutedSharesOutstanding) | C87: 548000000 | D87: https://www.sec.gov/Archives/edgar/data/827054/000082705426000016/
A88: F29 | B88: diluted_shares_wavg FY ending 2025-03-31 (us-gaap:WeightedAverageNumberOfDilutedSharesOutstanding) | C88: 537300000 | D88: https://www.sec.gov/Archives/edgar/data/827054/000082705426000016/
A89: F30 | B89: diluted_shares_wavg FY ending 2026-03-31 (us-gaap:WeightedAverageNumberOfDilutedSharesOutstanding) | C89: 545200000 | D89: https://www.sec.gov/Archives/edgar/data/827054/000082705426000016/
A90: F31 | B90: diluted_shares_wavg YTD 2026-04-01 to 2026-06-30 | C90: 550500000 | D90: https://www.sec.gov/Archives/edgar/data/827054/000082705426000038/
A91: F32 | B91: diluted_shares_wavg prior-year YTD 2025-04-01 to 2025-06-30 | C91: 539200000 | D91: https://www.sec.gov/Archives/edgar/data/827054/000082705426000038/
... A97: F38 | B97: d_and_a prior-year YTD 2025-04-01 to 2025-06-30 | C97: 171100000 | D97: https://www.sec.gov/Archives/edgar/data/827054/000082705426000038/
A98: F39 | B98: d_and_a TTM to 2026-06-30 | C98: 674900000
A99: F40 | B99: d_and_a quarter 2026-04-01 to 2026-06-30 | C99: 156700000 | D99: https://www.sec.gov/Archives/edgar/data/827054/000082705426000038/
A100: F41 | B100: sbc FY ending 2024-03-31 (us-gaap:ShareBasedCompensation) | C100: 177500000 | D100: https://www.sec.gov/Archives/edgar/data/827054/000082705426000016/
A101: F42 | B101: sbc FY ending 2025-03-31 (us-gaap:ShareBasedCompensation) | C101: 180400000 | D101: https://www.sec.gov/Archives/edgar/data/827054/000082705426000016/
A102: F43 | B102: sbc FY ending 2026-03-31 (us-gaap:ShareBasedCompensation) | C102: 255400000 | D102: https://www.sec.gov/Archives/edgar/data/827054/000082705426000016/
A103: F44 | B103: sbc YTD 2026-04-01 to 2026-06-30 | C103: 75000000 | D103: https://www.sec.gov/Archives/edgar/data/827054/000082705426000038/
A104: F45 | B104: sbc prior-year YTD 2025-04-01 to 2025-06-30 | C104: 52900000 | D104: https://www.sec.gov/Archives/edgar/data/827054/000082705426000038/
A105: F46 | B105: sbc TTM to 2026-06-30 | C105: 277500000
A106: F47 | B106: sbc quarter 2026-04-01 to 2026-06-30 | C106: 75000000 | D106: https://www.sec.gov/Archives/edgar/data/827054/000082705426000038/
A107: F48 | B107: cfo FY ending 2024-03-31 (us-gaap:NetCashProvidedByUsedInOperatingActivities) | C107: 2892700000 | D107: https://www.sec.gov/Archives/edgar/data/827054/000082705426000016/
A108: F49 | B108: cfo FY ending 2025-03-31 (us-gaap:NetCashProvidedByUsedInOperatingActivities) | C108: 898100000 | D108: https://www.sec.gov/Archives/edgar/data/827054/000082705426000016/
...
