Workbook

Sheet Summary
A1: BE standard model (trial) · research run 2026-10-23
A2: The supervisor's reconciled assumption set as a live model. Trial: shown beside the blended page target, not used for trade levels until its weight is decided. Edit blue cells on Model (drivers) and Valuation (assumptions).
A3: Price target box | B3: Value
A4: Live price | B4: =IFERROR(GOOGLEFINANCE("BE","price"),Valuation!$B$68)
A5: Price as of | B5: =NOW()
A6: Model target (12-month median) | B6: =Distribution!$B$13
A7: Upside to model target from live price | B7: =B6/B4-1
A8: Research target (12m) (no scenario deltas) | B8: =Valuation!$D$8
A9: Probability-weighted mean | B9: =Distribution!$B$10
A10: 10th percentile | B10: =Distribution!$B$14
A11: 25th percentile | B11: =Distribution!$B$15
A12: 75th percentile | B12: =Distribution!$B$16
A13: 90th percentile | B13: =Distribution!$B$17
A14: Target date | B14: =Valuation!$B$46
A15: Price at the run | B15: =Valuation!$B$68
A16: Blended page target (options 67% + agents 33%, not live) | B16: 172.9057
A17: Supervisor research target (12m) (its own methods) | B17: 185.84
A18: Thesis break price (supervisor) | B18: 150
A19: Supervisor confidence | B19: low
A21: Key estimates | B21: FY2025A | C21: =Model!E5 | D21: =Model!F5
A22: Net sales | B22: =IF(Model!D24="","",Model!D24) | C22: =Model!E24 | D22: =Model!F24
A23: % YoY | B23: =IF(Model!D25="","",Model!D25) | C23: =Model!E25 | D23: =Model!F25
A24: Pretax margin | B24: =IF(Model!D35="","",Model!D35) | C24: =Model!E35 | D24: =Model!F35
A25: Diluted EPS (model) | B25: =IF(Model!D42="","",Model!D42) | C25: =Model!E42 | D25: =Model!F42
A26: % YoY | B26: =IF(Model!D43="","",Model!D43) | C26: =Model!E43 | D26: =Model!F43
A27: Free cash flow to firm | B27: =IF(Model!D52="","",Model!D52) | C27: =Model!E52 | D27: =Model!F52
A28: Guidance midpoint: EPS (non-GAAP) | C28: 3.25
A29: Consensus: EPS (consensus) | D29: 5.31
A31: Valuation method | B31: Value per share | C31: Weight
A32: =Valuation!A4 | B32: =Valuation!D4 | C32: =Valuation!E4
A33: =Valuation!A5 | B33: =Valuation!D5 | C33: =Valuation!E5
A34: =Valuation!A6 | B34: =Valuation!D6 | C34: =Valuation!E6
A35: =Valuation!A7 | B35: =Valuation!D7 | C35: =Valuation!E7
A37: Scenario | B37: Probability | C37: Value at target date | D37: What has to happen
A38: =Distribution!A4 | B38: =Distribution!B4 | C38: =Distribution!C4 | D38: =Distribution!D4
A39: =Distribution!A5 | B39: =Distribution!B5 | C39: =Distribution!C5 | D39: =Distribution!D5
A40: =Distribution!A6 | B40: =Distribution!B6 | C40: =Distribution!C6 | D40: =Distribution!D6
A42: Price at target date | B42: Probability above
A43: =ROUND(Valuation!$B$68*0.7,0) | B43: =SUMPRODUCT(Distribution!$B$4:$B$6,1-NORMSDIST((LN(A43)-LN(Distribution!$C$4:$C$6))/Distribution!$B$9))
A44: =ROUND(Valuation!$B$68*0.8,0) | B44: =SUMPRODUCT(Distribution!$B$4:$B$6,1-NORMSDIST((LN(A44)-LN(Distribution!$C$4:$C$6))/Distribution!$B$9))
A45: =ROUND(Valuation!$B$68*0.9,0) | B45: =SUMPRODUCT(Distribution!$B$4:$B$6,1-NORMSDIST((LN(A45)-LN(Distribution!$C$4:$C$6))/Distribution!$B$9))
A46: =ROUND(Valuation!$B$68*1.0,0) | B46: =SUMPRODUCT(Distribution!$B$4:$B$6,1-NORMSDIST((LN(A46)-LN(Distribution!$C$4:$C$6))/Distribution!$B$9))
A47: =ROUND(Valuation!$B$68*1.1,0) | B47: =SUMPRODUCT(Distribution!$B$4:$B$6,1-NORMSDIST((LN(A47)-LN(Distribution!$C$4:$C$6))/Distribution!$B$9))
A48: =ROUND(Valuation!$B$68*1.2,0) | B48: =SUMPRODUCT(Distribution!$B$4:$B$6,1-NORMSDIST((LN(A48)-LN(Distribution!$C$4:$C$6))/Distribution!$B$9))
A49: =ROUND(Valuation!$B$68*1.3,0) | B49: =SUMPRODUCT(Distribution!$B$4:$B$6,1-NORMSDIST((LN(A49)-LN(Distribution!$C$4:$C$6))/Distribution!$B$9))
A50: =ROUND(Valuation!$B$68*1.5,0) | B50: =SUMPRODUCT(Distribution!$B$4:$B$6,1-NORMSDIST((LN(A50)-LN(Distribution!$C$4:$C$6))/Distribution!$B$9))
A52: Model checks | B52: Status
A53: Scenario probabilities sum to 100% | B53: =IF(ABS(Distribution!B8-1)<0.005,"ok","FLAG: "&TEXT(Distribution!B8,"0.0%"))
A54: WACC exceeds terminal growth by 1 point or more | B54: =IF('Calc - research target (12m)'!B55="ok","ok","FLAG")
A55: Projection runs a full year past the target date | B55: =IF('Calc - research target (12m)'!B56="ok","ok","FLAG")
A56: Method weights add up to more than zero | B56: =IF(SUM(Valuation!E4:E7)>0,"ok","FLAG")
A57: Terminal value under 85% of the DCF | B57: =IF('Calc - research target (12m)'!B46<0.85,"ok","note: "&TEXT('Calc - research target (12m)'!B46,"0%")&" of the DCF is terminal value")
A58: Segment base revenues tie to the last reported net sales (within 2%) | B58: =IF(ABS(Valuation!$B$92/Valuation!$B$51-1)<=0.02,"ok","FLAG")
A59: Matches the engine run at publication (target, research target (12m)) | B59: =IF(AND(ABS(Distribution!$B$13-184.2884)<0.01,ABS(Valuation!$D$8-185.8390)<0.01),"ok","inputs edited since publication")
A60: All checks | B60: =IF(COUNTIF(B53:B59,"ok")=7,"all ok",7-COUNTIF(B53:B59,"ok")&" to look at")

Sheet Model
A1: BE: annual model, base case
A2: (M of US dollars except per share; fiscal years named by the calendar year they end in)
A3: Blue = input · black = formula · green = link to another tab · actuals from SEC filings (fact ids in the last column, links on Sources)
A5: Fiscal year | B5: FY2023A | C5: FY2024A | D5: FY2025A | E5: FY2026E | F5: FY2027E | G5: FY2028E | H5: Source / note
A6: Period end | B6: 45291 | C6: 45657 | D6: 46022 | E6: =IF(DAY(Valuation!$B$50+1)=1,EOMONTH(Valuation!$B$50,12*E7),EDATE(Valuation!$B$50,12*E7)) | F6: =IF(DAY(Valuation!$B$50+1)=1,EOMONTH(Valuation!$B$50,12*F7),EDATE(Valuation!$B$50,12*F7)) | G6: =IF(DAY(Valuation!$B$50+1)=1,EOMONTH(Valuation!$B$50,12*G7),EDATE(Valuation!$B$50,12*G7))
A7: Projection year | B7: -2 | C7: -1 | D7: 0 | E7: 1 | F7: 2 | G7: 3
A10: Segment build (blue = input: revenue growth and EBIT margin by segment and year)
A11: Product | D11: =Valuation!$B$90 | E11: =Valuation!$B$90*(1+E12) | F11: =E11*(1+F12) | G11: =F11*(1+G12)
A12: Revenue growth | E12: 1.5870445 | F12: 0.47660154 | G12: 0.38888889
A13: Segment EBIT | E13: =E11*E14 | F13: =F11*F14 | G13: =G11*G14
A14: EBIT margin | E14: 0.18750719 | F14: 0.22115385 | G14: 0.23953846
A15: Installation, service and electricity | D15: =Valuation!$B$91 | E15: =Valuation!$B$91*(1+E16) | F15: =E15*(1+F16) | G15: =F15*(1+G16)
A16: Revenue growth | E16: 0.13659428 | F16: 0.25 | G16: 0.2
A17: Segment EBIT | E17: =E15*E18 | F17: =F15*F18 | G17: =G15*G18
A18: EBIT margin | E18: 0.067 | F18: 0.08 | G18: 0.09
A19: Total segment revenue (= net sales) | D19: =D11+D15 | E19: =E11+E15 | F19: =F11+F15 | G19: =G11+G15 | H19: base revenues on Valuation (segment build); net sales = this total
A20: Total segment EBIT | E20: =E13+E17 | F20: =F13+F17 | G20: =G13+G17
A21: Corporate / unallocated EBIT (blue = input) | E21: 0 | F21: =E21 | G21: =F21 | H21: years[].corporate_ebit; EBIT = total segment EBIT + corporate
A23: Sales
A24: Net sales | B24: 1268.782 | C24: 1441.394 | D24: 2001.614 | E24: =E19 | F24: =F19 | G24: =G19 | H24: SEC XBRL F1, F2, F3
A25: % YoY | C25: =IF(OR(C24="",B24="",B24=0),"",C24/B24-1) | D25: =IF(OR(D24="",C24="",C24=0),"",D24/C24-1) | E25: =E24/Valuation!$B$51-1 | F25: =F24/E24-1 | G25: =G24/F24-1
A27: Operating profit
A28: EBIT (operating income) | E28: =E20+E21 | F28: =F20+F21 | G28: =G20+G21
A29: EBIT margin | E29: =E28/E24 | F29: =F28/F24 | G29: =G28/G24
A30: D&A | E30: =E24*E64 | F30: =F24*F64 | G30: =G24*G64
A31: EBITDA | E31: =E28+E30 | F31: =F28+F30 | G31: =G28+G30
A32: EBITDA margin | E32: =E31/E24 | F32: =F31/F24 | G32: =G31/G24
A33: Net interest income / (expense) | E33: =-Valuation!$B$59*Valuation!$B$57 | F33: =-Valuation!$B$59*E58 | G33: =-Valuation!$B$59*F58 | H33: rate x prior year-end net debt (memo roll)
A34: Pretax income | B34: -306.043 | C34: -26.357 | D34: -84.404 | E34: =E28+E33 | F34: =F28+F33 | G34: =G28+G33 | H34: SEC XBRL F68, F69, F70
A35: Pretax margin | B35: =B34/B24 | C35: =C34/C24 | D35: =D34/D24 | E35: =E34/E24 | F35: =F34/F24 | G35: =G34/G24
A36: Income tax | B36: 1.894 | C36: 0.846 | D36: 2.736 | E36: =E34*E63 | F36: =F34*F63 | G36: =G34*G63 | H36: SEC XBRL F61, F62, F63
A37: Effective tax rate | B37: =B36/B34 | C37: =C36/C34 | D37: =D36/D34 | E37: =E36/E34 | F37: =F36/F34 | G37: =G36/G34
A38: Net income | B38: -307.937 | C38: -27.203 | D38: -87.14 | E38: =E34-E36 | F38: =F34-F36 | G38: =G34-G36 | H38: SEC XBRL F15, F16, F17
A39: % YoY | C39: =IF(OR(C38="",B38="",B38=0),"",C38/B38-1) | D39: =IF(OR(D38="",C38="",C38=0),"",D38/C38-1) | E39: =IF(OR(D38="",D38=0),"",E38/D38-1) | F39: =IF(OR(E38="",E38=0),"",F38/E38-1) | G39: =IF(OR(F38="",F38=0),"",G38/F38-1)
A40: Diluted shares (M, average) | B40: 212.681 | C40: 227.365 | D40: 240.402 | E40: =Valuation!$B$61*(1+Valuation!$B$63)^(E7-0.5-((Valuation!$B$62-Valuation!$B$50)/365.25)) | F40: =Valuation!$B$61*(1+Valuation!$B$63)^(F7-0.5-((Valuation!$B$62-Valuation!$B$50)/365.25)) | G40: =Valuation!$B$61*(1+Valuation!$B$63)^(G7-0.5-((Valuation!$B$62-Valuation!$B$50)/365.25)) | H40: diluted count rolled at the annual change to mid-year
A41: % YoY | C41: =IF(OR(C40="",B40="",B40=0),"",C40/B40-1) | D41: =IF(OR(D40="",C40="",C40=0),"",D40/C40-1) | E41: =IF(OR(D40="",D40=0),"",E40/D40-1) | F41: =IF(OR(E40="",E40=0),"",F40/E40-1) | G41: =IF(OR(F40="",F40=0),"",G40/F40-1)
A42: Diluted EPS | B42: -1.42 | C42: -0.13 | D42: -0.37 | E42: =E38/E40 | F42: =F38/F40 | G42: =G38/G40 | H42: SEC XBRL F22, F23, F24
A43: % YoY | C43: =IF(OR(C42="",B42="",B42=0),"",C42/B42-1) | D43: =IF(OR(D42="",C42="",C42=0),"",D42/C42-1) | E43: =IF(OR(D42="",D42=0),"",E42/D42-1) | F43: =IF(OR(E42="",E42=0),"",F42/E42-1) | G43: =IF(OR(F42="",F42=0),"",G42/F42-1)
A45: Cash flow
A46: NOPAT (EBIT x (1 - tax)) | E46: =E28*(1-E63) | F46: =F28*(1-F63) | G46: =G28*(1-G63)
A47: + D&A | B47: =B30 | C47: =C30 | D47: =D30 | E47: =E30 | F47: =F30 | G47: =G30
A48: - Capex | B48: 83.739 | C48: 58.852 | D48: 56.759 | E48: =E24*E65 | F48: =F24*F65 | G48: =G24*G65 | H48: SEC XBRL F41, F42, F43
A49: Capex % of sales | B49: =B48/B24 | C49: =C48/C24 | D49: =D48/D24 | E49: =E48/E24 | F49: =F48/F24 | G49: =G48/G24
A50: - Working capital increase | E50: =E66*(E24-Valuation!$B$51) | F50: =F66*(F24-E24) | G50: =G66*(G24-F24)
A51: - Stock comp (adjusted EBIT only) | E51: =IF(AND(Valuation!$B$48="adjusted",Valuation!$B$49="cost"),E55*(1-E63),0) | F51: =IF(AND(Valuation!$B$48="adjusted",Valuation!$B$49="cost"),F55*(1-F63),0) | G51: =IF(AND(Valuation!$B$48="adjusted",Valuation!$B$49="cost"),G55*(1-G63),0)
A52: Free cash flow to firm | E52: =E46+E47-E48-E50-E51 | F52: =F46+F47-F48-F50-F51 | G52: =G46+G47-G48-G50-G51 | H52: what the DCF discounts (Calc tabs)
A53: Operating cash flow (reported) | B53: -372.531 | C53: 91.998 | D53: 113.949 | H53: SEC XBRL F34, F35, F36
A54: FCF (operating cash flow - capex) | B54: =B53-B48 | C54: =C53-C48 | D54: =D53-D48
A55: Stock comp (memo) | E55: =E24*E67 | F55: =F24*F67 | G55: =G24*G67
A56: Buybacks + dividends + other uses | E56: =E24*E69+E68+E70 | F56: =F24*F69+F68+F70 | G56: =G24*G69+G68+G70
A57: % of sales | B57: =B56/B24 | C57: =C56/C24 | D57: =D56/D24 | E57: =E56/E24 | F57: =F56/F24 | G57: =G56/G24
A58: Net debt / (net cash), year end (memo) | E58: =Valuation!$B$57-E52-E33*(1-E63)+E56 | F58: =E58-F52-F33*(1-F63)+F56 | G58: =F58-G52-G33*(1-G63)+G56 | H58: rolled from the balance-date figure; feeds interest only
A60: Drivers (blue = input; a year left black carries the prior year)
A61: Revenue growth | C61: =C25 | D61: =D25 | E61: =E25 | F61: =F25 | G61: =G25 | H61: implied by the segment build (edit the segment rows)
A62: EBIT margin | E62: =E29 | F62: =F29 | G62: =G29 | H62: implied by the segment build and corporate EBIT
A63: Tax rate | B63: =B37 | C63: =C37 | D63: =D37 | E63: 0.05 | F63: 0.1 | G63: 0.15
A64: D&A % revenue | B64: =B30/B24 | C64: =C30/C24 | D64: =D30/D24 | E64: 0.013 | F64: 0.013 | G64: 0.014
A65: Capex % revenue | B65: =B49 | C65: =C49 | D65: =D49 | E65: 0.07264544 | F65: 0.064085083 | G65: 0.045
A66: Working capital % of revenue increase | E66: 0.2 | F66: 0.15 | G66: 0.15
A67: Stock comp % revenue | B67: =B55/B24 | C67: =C55/C24 | D67: =D55/D24 | E67: 0 | F67: =E67 | G67: =F67
A68: Shareholder returns ($) | E68: 0 | F68: =E68 | G68: =F68
A69: Shareholder returns % revenue | B69: =B57 | C69: =C57 | D69: =D57 | E69: 0 | F69: =E69 | G69: =F69
A70: Other uses of cash ($: M&A, investments) | E70: 0 | F70: =E70 | G70: =F70
A71: Adj. EBITDA addback % revenue | E71: 0 | F71: =E71 | G71: =F71
A73: Versus company guidance and street consensus
A74: Guidance: revenue (GAAP), midpoint | E74: =AVERAGE(4400,4600) | H74: 4400 to 4600; as of 2026-10-22; source 14 (Bloom Energy Q3 2026 results (8-K Ex.99.1))
A75: Model vs guidance midpoint | E75: =E24/E74-1 | H75: =IF(E24<4400,"below the guided range",IF(E24>4600,"above the guided range","inside the guided range"))
A76: Guidance: non-GAAP gross margin (non-GAAP), midpoint | E76: =AVERAGE(0.34,0.34) | H76: 0.34 to 0.34; as of 2026-10-22; source 14 (Bloom Energy Q3 2026 results (8-K Ex.99.1))
A77: Guidance: non-GAAP operating income (non-GAAP), midpoint | E77: =AVERAGE(960,1030) | H77: 960 to 1030; as of 2026-10-22; source 14 (Bloom Energy Q3 2026 results (8-K Ex.99.1))
A78: Guidance: EPS diluted (non-GAAP) (non-GAAP), midpoint | E78: =AVERAGE(3.1,3.4) | H78: 3.1 to 3.4; as of 2026-10-22; source 14 (Bloom Energy Q3 2026 results (8-K Ex.99.1))
A79: Consensus: revenue (consensus) | E79: 4530 | H79: as of 2026-10-23; source 25 (Bloom Energy (BE) analyst forecast: 'Revenue Next Year 7.05B)
A80: Model vs consensus | E80: =E24/E79-1
A81: Consensus: revenue (consensus) | F81: 7050 | H81: as of 2026-10-23; source 25 (Bloom Energy (BE) analyst forecast: 'Revenue Next Year 7.05B)
A82: Model vs consensus | F82: =F24/F81-1
A83: Consensus: EPS diluted (consensus) | F83: 5.31 | H83: as of 2026-10-23; source 25 (Bloom Energy (BE) analyst forecast: 'Revenue Next Year 7.05B)
A84: Model vs consensus | F84: =F42/F83-1

Sheet Valuation
A1: BE: valuation and price target derivation
A2: Value per share at the target date = weighted methods below; the 12-month target is the median of the scenario mix (Distribution tab).
A3: Method | B3: Multiple | C3: Metric at target date | D3: Value per share | E3: Weight | F3: Contribution
A4: ='Calc - research target (12m)'!A67 | B4: =IF('Calc - research target (12m)'!C67="","",'Calc - research target (12m)'!C67) | C4: =IF('Calc - research target (12m)'!I67="","",'Calc - research target (12m)'!I67) | D4: ='Calc - research target (12m)'!F67 | E4: ='Calc - research target (12m)'!G67 | F4: =D4*E4/SUM($E$4:$E$7)
A5: ='Calc - research target (12m)'!A68 | B5: =IF('Calc - research target (12m)'!C68="","",'Calc - research target (12m)'!C68) | C5: =IF('Calc - research target (12m)'!I68="","",'Calc - research target (12m)'!I68) | D5: ='Calc - research target (12m)'!F68 | E5: ='Calc - research target (12m)'!G68 | F5: =D5*E5/SUM($E$4:$E$7)
A6: ='Calc - research target (12m)'!A69 | B6: =IF('Calc - research target (12m)'!C69="","",'Calc - research target (12m)'!C69) | C6: =IF('Calc - research target (12m)'!I69="","",'Calc - research target (12m)'!I69) | D6: ='Calc - research target (12m)'!F69 | E6: ='Calc - research target (12m)'!G69 | F6: =D6*E6/SUM($E$4:$E$7)
A7: ='Calc - research target (12m)'!A70 | B7: =IF('Calc - research target (12m)'!C70="","",'Calc - research target (12m)'!C70) | C7: =IF('Calc - research target (12m)'!I70="","",'Calc - research target (12m)'!I70) | D7: ='Calc - research target (12m)'!F70 | E7: ='Calc - research target (12m)'!G70 | F7: =D7*E7/SUM($E$4:$E$7)
A8: Research target (12m) per share | D8: ='Calc - research target (12m)'!$F$71 | F8: =SUM(F4:F7)
A10: 12-month EPS basis (what the P/E is applied to)
A11: Fiscal year | B11: =Model!E5 | C11: =Model!F5 | D11: =Model!G5
A12: Share of the 12 months after the target date | B12: ='Calc - research target (12m)'!C38 | C12: ='Calc - research target (12m)'!D38 | D12: ='Calc - research target (12m)'!E38
A13: Model EPS (Model tab) | B13: =Model!E42 | C13: =Model!F42 | D13: =Model!G42
A14: Model EPS, next 12 months after the target date | B14: =SUMPRODUCT(B12:D12,B13:D13)
A17: DCF build (free cash flow to firm, discounted to the target date)
A18: Fiscal year | B18: =Model!E5 | C18: =Model!F5 | D18: =Model!G5
A19: Free cash flow to firm | B19: ='Calc - research target (12m)'!C31 | C19: ='Calc - research target (12m)'!D31 | D19: ='Calc - research target (12m)'!E31
A20: Share of the year after the target date | B20: ='Calc - research target (12m)'!C35 | C20: ='Calc - research target (12m)'!D35 | D20: ='Calc - research target (12m)'!E35
A21: PV at target date | B21: ='Calc - research target (12m)'!C36 | C21: ='Calc - research target (12m)'!D36 | D21: ='Calc - research target (12m)'!E36
A23: PV of free cash flow after the target date | B23: ='Calc - research target (12m)'!B42
A24: Terminal value (final year) | B24: ='Calc - research target (12m)'!B43
A25: PV of terminal value | B25: ='Calc - research target (12m)'!B44
A26: Enterprise value at target date | B26: ='Calc - research target (12m)'!B45
A27: Terminal value share of DCF | B27: ='Calc - research target (12m)'!B46
A28: Net debt at target date | B28: ='Calc - research target (12m)'!B50
A29: Minority interests | B29: ='Calc - research target (12m)'!B51
A30: Adjustments | B30: ='Calc - research target (12m)'!B52
A31: Diluted shares at target date (M) | B31: ='Calc - research target (12m)'!B53
A32: DCF value per share | B32: ='Calc - research target (12m)'!F67
A33: WACC | B33: ='Calc - research target (12m)'!B12
A43: Assumptions (blue = input; sources on the Sources tab)
A44: Input | B44: Value | C44: Basis / note
A45: Run date (valuation as of) | B45: 46318
A46: Target date (run date + 365 days) | B46: =B45+365 | C46: 12-month horizon
A47: Money unit | B47: $M
A48: EBIT basis (gaap / adjusted) | B48: gaap | C48: gaap = after stock comp
A49: Stock comp treatment (cost / dilution) | B49: cost | C49: used only when EBIT is adjusted
A50: Last reported fiscal year end | B50: 46022
A51: Net sales, last reported year ($M) | B51: 2024
A52: WACC | B52: 0.1 | C52: not used: no DCF leg (Kilian 2026-10-21); a placeholder so the DCF block still computes
A53: Terminal method (gordon / exit_multiple / steady_state) | B53: gordon
A54: Terminal growth | B54: 0.02
A55: Exit EV/EBITDA (exit_multiple only)
A56: Balance-sheet date | B56: 46295
A57: Net debt / (net cash) at balance date ($M) | B57: 16.2 | C57: excludes operating leases
A58: Minority interests + preferred stock | B58: 0
A59: Interest rate on net debt / cash | B59: 0
A60: Net debt at target date (override; blank = bridge)
A61: Diluted shares (M) | B61: 312.4
A62: Share count date | B62: 46314
A63: Annual change in diluted shares | B63: 0.015 | C63: net of buybacks and stock-comp dilution
A64: Shares at target date (override; blank = from annual change)
A65: DCF weight | B65: 0 | C65: Kilian 2026-10-21: 0 unless the name has a DCF leg (dcf_policy)
A66: Sum-of-the-parts weight | B66: 0
A67: Spread within each scenario (lognormal vol) | B67: 0.25
A68: Share price at the run | B68: 193.3 | C68: close used by the run (2026-10-23)
A70: Target multiple | B70: Multiple | C70: Weight | D70: Basis (ntm / ltm) | E70: EBITDA basis | F70: Stated EPS | G70: Stated FCF/share | H70: Levered | I70: Peer basis
A71: P/E | B71: 40 | C71: 0.6 | D71: ntm | E71: gaap | H71: TRUE | I71: Whole-company peers GAAP P/E TTM median 39.9x (GEV 22.8, VRT 43.2, ETN 37.1, GNRC 42.7; src 23). 40x NTM GAAP at the horizon = peer trailing median for ~25-35% FY2029 growth vs peers ~10-20%. The agents' median ~40x sits on non-GAAP earnings, which is ~46x GAAP (40 / 0.87, SBC gap ~13%), so 40x GAAP is ~13% below the agents' multiple. Decided by Kilian 2026-10-26 (40x GAAP, with EV/sales 5.5x).
A72: EV/EBITDA | B72: 26 | C72: 0.2 | D72: ntm | E72: gaap | H72: TRUE | I72: Peer EV/EBITDA TTM: VRT 29.3x, GNRC 18.9x (median 24.1x; GEV, ETN and CAT not computable from their tags; CMI not built this run, src 23). 26x = +2x for growth.
A73: EV/sales | B73: 5.5 | C73: 0.2 | D73: ntm | E73: gaap | H73: TRUE | I73: Peer EV/sales TTM median 5.2x (GEV 5.0, VRT 6.5, ETN 5.4, GNRC 2.7; src 23). 5.5x on a ~24% EBITDA margin; agents used 7.5-10x (median 8x) on 2028 revenue, which at that margin is ~33x EBITDA, above every peer. Decided by Kilian 2026-10-26.
A75: Segment (sum of the parts) | B75: NTM metric | C75: Metric | D75: Multiple | E75: Note
A76: none
A78: Adjustment (equity level) | B78: Value | C78: Probability | D78: Note
A79: none
A81: Custom method | B81: Value per share | C81: Weight | D81: Explanation
A82: none
A84: Scenario | B84: Probability | C84: Growth Δ | D84: Margin Δ | E84: Multiple Δ (turns) | F84: WACC Δ | G84: Multiple %Δ (FCF yield, segments) | H84: Stated EPS/FCF %Δ | I84: Custom methods %Δ | J84: Story
A85: bear | B85: 0.25 | E85: -8 | J85: Agents' bear (probabilities 0.30/0.25/0.26/0.25/0.23, median 0.25): Jupiter slips into 2028 (FERC Dec 3 decision on the rerouted Green Chile lateral, NM air permit) without redeployment, AI-capex digestion, FY2027 guide well below ~$6.8B; scandium/degradation claims raise service cost. Driver form: product_gw -25% (FY2027 1.35 GW, FY2028 1.9 GW), product_gm -3pt; P/E ~32x (agents 25-35x). | K85: driver deltas: product_gw -0.25 %; product_gm -0.03
A86: base | B86: 0.5 | J86: Drivers as set: 1.24 / 1.80 / 2.50 GW at $3,195-3,250/kW, product GM 37-37.5%, capacity 2 GW end-2026 and 3 GW during 2027; revenue $4.52B / $6.55B / $8.97B. Research target (12m) $185.84.
A87: bull | B87: 0.25 | E87: 8 | J87: Agents' bull (0.25 each): Jupiter permit on time, the rest of Oracle's 2.8 GW plus Brookfield/AEP/Aligned awards convert, capacity to 3-4 GW, EPS toward $9-10 on 2028. Driver form: product_gw +20% (FY2028 3.0 GW), product_gm +1pt; P/E ~48x (agents 45-60x). | K87: driver deltas: product_gw +0.2 %; product_gm +0.01
A89: Segment build (segment_build) | B89: Base revenue ($M) | C89: Driver note (growth and EBIT margin by year: Model tab)
A90: Product | B90: 1531.3 | C90: product_gw x product_asp; EBIT = gross profit at product_gm less all operating expenses (opex)
A91: Installation, service and electricity | B91: 492.7 | C91: plain segment: installation 204.1 + service 228.3 + electricity 60.35 (FY2025, src 17); grows with the fleet and large-site installation; EBIT = gross margin (no opex allocated)
A92: Sum of segment base revenues | B92: =SUM(B90:B91) | C92: =IF(ABS(B92/Valuation!$B$51-1)<=0.02,"ties to the last reported net sales (within 2%)","FLAG: does not tie to the last reported net sales")

Sheet Sensitivity
A1: BE: sensitivity tables (bold = current inputs; every cell recalculates from the live model)
A3: DCF value per share: WACC (down) x terminal growth (across)
A4: WACC \ growth | B4: =Valuation!$B$54+(-0.01) | C4: =Valuation!$B$54+(-0.005) | D4: =Valuation!$B$54+(0) | E4: =Valuation!$B$54+(0.005) | F4: =Valuation!$B$54+(0.01)
A5: =Valuation!$B$52+(-0.01) | B5: =IF($A5-B$4<=0.01,"n/a",((SUMPRODUCT('Calc - research target (12m)'!$C$31:$E$31,'Calc - research target (12m)'!$C$35:$E$35,(1+$A5)^(-('Calc - research target (12m)'!$C$19:$E$19-'Calc - research target (12m)'!$B$13)))+'Calc - research target (12m)'!$E$31*(1+B$4)/($A5-B$4)/(1+$A5)^('Calc - research target (12m)'!$B$16-'Calc - research target (12m)'!$B$13))-'Calc - research target (12m)'!$B$50-'Calc - research target (12m)'!$B$51+'Calc - research target (12m)'!$B$52)/'Calc - research target (12m)'!$B$53) | C5: =IF($A5-C$4<=0.01,"n/a",((SUMPRODUCT('Calc - research target (12m)'!$C$31:$E$31,'Calc - research target (12m)'!$C$35:$E$35,(1+$A5)^(-('Calc - research target (12m)'!$C$19:$E$19-'Calc - research target (12m)'!$B$13)))+'Calc - research target (12m)'!$E$31*(1+C$4)/($A5-C$4)/(1+$A5)^('Calc - research target (12m)'!$B$16-'Calc - research target (12m)'!$B$13))-'Calc - research target (12m)'!$B$50-'Calc - research target (12m)'!$B$51+'Calc - research target (12m)'!$B$52)/'Calc - research target (12m)'!$B$53) | D5: =IF($A5-D$4<=0.01,"n/a",((SUMPRODUCT('Calc - research target (12m)'!$C$31:$E$31,'Calc - research target (12m)'!$C$35:$E$35,(1+$A5)^(-('Calc - research target (12m)'!$C$19:$E$19-'Calc - research target (12m)'!$B$13)))+'Calc - research target (12m)'!$E$31*(1+D$4)/($A5-D$4)/(1+$A5)^('Calc - research target (12m)'!$B$16-'Calc - research target (12m)'!$B$13))-'Calc - research target (12m)'!$B$50-'Calc - research target (12m)'!$B$51+'Calc - research target (12m)'!$B$52)/'Calc - research target (12m)'!$B$53) | E5: =IF($A5-E$4<=0.01,"n/a",((SUMPRODUCT('Calc - research target (12m)'!$C$31:$E$31,'Calc - research target (12m)'!$C$35:$E$35,(1+$A5)^(-('Calc - research target (12m)'!$C$19:$E$19-'Calc - research target (12m)'!$B$13)))+'Calc - research target (12m)'!$E$31*(1+E$4)/($A5-E$4)/(1+$A5)^('Calc - research target (12m)'!$B$16-'Calc - research target (12m)'!$B$13))-'Calc - research target (12m)'!$B$50-'Calc - research target (12m)'!$B$51+'Calc - research target (12m)'!$B$52)/'Calc - research target (12m)'!$B$53) | F5: =IF($A5-F$4<=0.01,"n/a",((SUMPRODUCT('Calc - research target (12m)'!$C$31:$E$31,'Calc - research target (12m)'!$C$35:$E$35,(1+$A5)^(-('Calc - research target (12m)'!$C$19:$E$19-'Calc - research target (12m)'!$B$13)))+'Calc - research target (12m)'!$E$31*(1+F$4)/($A5-F$4)/(1+$A5)^('Calc - research target (12m)'!$B$16-'Calc - research target (12m)'!$B$13))-'Calc - research target (12m)'!$B$50-'Calc - research target (12m)'!$B$51+'Calc - research target (12m)'!$B$52)/'Calc - research target (12m)'!$B$53)
A6: =Valuation!$B$52+(-0.005) | B6: =IF($A6-B$4<=0.01,"n/a",((SUMPRODUCT('Calc - research target (12m)'!$C$31:$E$31,'Calc - research target (12m)'!$C$35:$E$35,(1+$A6)^(-('Calc - research target (12m)'!$C$19:$E$19-'Calc - research target (12m)'!$B$13)))+'Calc - research target (12m)'!$E$31*(1+B$4)/($A6-B$4)/(1+$A6)^('Calc - research target (12m)'!$B$16-'Calc - research target (12m)'!$B$13))-'Calc - research target (12m)'!$B$50-'Calc - research target (12m)'!$B$51+'Calc - research target (12m)'!$B$52)/'Calc - research target (12m)'!$B$53) | C6: =IF($A6-C$4<=0.01,"n/a",((SUMPRODUCT('Calc - research target (12m)'!$C$31:$E$31,'Calc - research target (12m)'!$C$35:$E$35,(1+$A6)^(-('Calc - research target (12m)'!$C$19:$E$19-'Calc - research target (12m)'!$B$13)))+'Calc - research target (12m)'!$E$31*(1+C$4)/($A6-C$4)/(1+$A6)^('Calc - research target (12m)'!$B$16-'Calc - research target (12m)'!$B$13))-'Calc - research target (12m)'!$B$50-'Calc - research target (12m)'!$B$51+'Calc - research target (12m)'!$B$52)/'Calc - research target (12m)'!$B$53) | D6: =IF($A6-D$4<=0.01,"n/a",((SUMPRODUCT('Calc - research target (12m)'!$C$31:$E$31,'Calc - research target (12m)'!$C$35:$E$35,(1+$A6)^(-('Calc - research target (12m)'!$C$19:$E$19-'Calc - research target (12m)'!$B$13)))+'Calc - research target (12m)'!$E$31*(1+D$4)/($A6-D$4)/(1+$A6)^('Calc - research target (12m)'!$B$16-'Calc - research target (12m)'!$B$13))-'Calc - research target (12m)'!$B$50-'Calc - research target (12m)'!$B$51+'Calc - research target (12m)'!$B$52)/'Calc - research target (12m)'!$B$53) | E6: =IF($A6-E$4<=0.01,"n/a",((SUMPRODUCT('Calc - research target (12m)'!$C$31:$E$31,'Calc - research target (12m)'!$C$35:$E$35,(1+$A6)^(-('Calc - research target (12m)'!$C$19:$E$19-'Calc - research target (12m)'!$B$13)))+'Calc - research target (12m)'!$E$31*(1+E$4)/($A6-E$4)/(1+$A6)^('Calc - research target (12m)'!$B$16-'Calc - research target (12m)'!$B$13))-'Calc - research target (12m)'!$B$50-'Calc - research target (12m)'!$B$51+'Calc - research target (12m)'!$B$52)/'Calc - research target (12m)'!$B$53) | F6: =IF($A6-F$4<=0.01,"n/a",((SUMPRODUCT('Calc - research target (12m)'!$C$31:$E$31,'Calc - research target (12m)'!$C$35:$E$35,(1+$A6)^(-('Calc - research target (12m)'!$C$19:$E$19-'Calc - research target (12m)'!$B$13)))+'Calc - research target (12m)'!$E$31*(1+F$4)/($A6-F$4)/(1+$A6)^('Calc - research target (12m)'!$B$16-'Calc - research target (12m)'!$B$13))-'Calc - research target (12m)'!$B$50-'Calc - research target (12m)'!$B$51+'Calc - research target (12m)'!$B$52)/'Calc - research target (12m)'!$B$53)
A7: =Valuation!$B$52+(0) | B7: =IF($A7-B$4<=0.01,"n/a",((SUMPRODUCT('Calc - research target (12m)'!$C$31:$E$31,'Calc - research target (12m)'!$C$35:$E$35,(1+$A7)^(-('Calc - research target (12m)'!$C$19:$E$19-'Calc - research target (12m)'!$B$13)))+'Calc - research target (12m)'!$E$31*(1+B$4)/($A7-B$4)/(1+$A7)^('Calc - research target (12m)'!$B$16-'Calc - research target (12m)'!$B$13))-'Calc - research target (12m)'!$B$50-'Calc - research target (12m)'!$B$51+'Calc - research target (12m)'!$B$52)/'Calc - research target (12m)'!$B$53) | C7: =IF($A7-C$4<=0.01,"n/a",((SUMPRODUCT('Calc - research target (12m)'!$C$31:$E$31,'Calc - research target (12m)'!$C$35:$E$35,(1+$A7)^(-('Calc - research target (12m)'!$C$19:$E$19-'Calc - research target (12m)'!$B$13)))+'Calc - research target (12m)'!$E$31*(1+C$4)/($A7-C$4)/(1+$A7)^('Calc - research target (12m)'!$B$16-'Calc - research target (12m)'!$B$13))-'Calc - research target (12m)'!$B$50-'Calc - research target (12m)'!$B$51+'Calc - research target (12m)'!$B$52)/'Calc - research target (12m)'!$B$53) | D7: =IF($A7-D$4<=0.01,"n/a",((SUMPRODUCT('Calc - research target (12m)'!$C$31:$E$31,'Calc - research target (12m)'!$C$35:$E$35,(1+$A7)^(-('Calc - research target (12m)'!$C$19:$E$19-'Calc - research target (12m)'!$B$13)))+'Calc - research target (12m)'!$E$31*(1+D$4)/($A7-D$4)/(1+$A7)^('Calc - research target (12m)'!$B$16-'Calc - research target (12m)'!$B$13))-'Calc - research target (12m)'!$B$50-'Calc - research target (12m)'!$B$51+'Calc - research target (12m)'!$B$52)/'Calc - research target (12m)'!$B$53) | E7: =IF($A7-E$4<=0.01,"n/a",((SUMPRODUCT('Calc - research target (12m)'!$C$31:$E$31,'Calc - research target (12m)'!$C$35:$E$35,(1+$A7)^(-('Calc - research target (12m)'!$C$19:$E$19-'Calc - research target (12m)'!$B$13)))+'Calc - research target (12m)'!$E$31*(1+E$4)/($A7-E$4)/(1+$A7)^('Calc - research target (12m)'!$B$16-'Calc - research target (12m)'!$B$13))-'Calc - research target (12m)'!$B$50-'Calc - research target (12m)'!$B$51+'Calc - research target (12m)'!$B$52)/'Calc - research target (12m)'!$B$53) | F7: =IF($A7-F$4<=0.01,"n/a",((SUMPRODUCT('Calc - research target (12m)'!$C$31:$E$31,'Calc - research target (12m)'!$C$35:$E$35,(1+$A7)^(-('Calc - research target (12m)'!$C$19:$E$19-'Calc - research target (12m)'!$B$13)))+'Calc - research target (12m)'!$E$31*(1+F$4)/($A7-F$4)/(1+$A7)^('Calc - research target (12m)'!$B$16-'Calc - research target (12m)'!$B$13))-'Calc - research target (12m)'!$B$50-'Calc - research target (12m)'!$B$51+'Calc - research target (12m)'!$B$52)/'Calc - research target (12m)'!$B$53)
A8: =Valuation!$B$52+(0.005) | B8: =IF($A8-B$4<=0.01,"n/a",((SUMPRODUCT('Calc - research target (12m)'!$C$31:$E$31,'Calc - research target (12m)'!$C$35:$E$35,(1+$A8)^(-('Calc - research target (12m)'!$C$19:$E$19-'Calc - research target (12m)'!$B$13)))+'Calc - research target (12m)'!$E$31*(1+B$4)/($A8-B$4)/(1+$A8)^('Calc - research target (12m)'!$B$16-'Calc - research target (12m)'!$B$13))-'Calc - research target (12m)'!$B$50-'Calc - research target (12m)'!$B$51+'Calc - research target (12m)'!$B$52)/'Calc - research target (12m)'!$B$53) | C8: =IF($A8-C$4<=0.01,"n/a",((SUMPRODUCT('Calc - research target (12m)'!$C$31:$E$31,'Calc - research target (12m)'!$C$35:$E$35,(1+$A8)^(-('Calc - research target (12m)'!$C$19:$E$19-'Calc - research target (12m)'!$B$13)))+'Calc - research target (12m)'!$E$31*(1+C$4)/($A8-C$4)/(1+$A8)^('Calc - research target (12m)'!$B$16-'Calc - research target (12m)'!$B$13))-'Calc - research target (12m)'!$B$50-'Calc - research target (12m)'!$B$51+'Calc - research target (12m)'!$B$52)/'Calc - research target (12m)'!$B$53) | D8: =IF($A8-D$4<=0.01,"n/a",((SUMPRODUCT('Calc - research target (12m)'!$C$31:$E$31,'Calc - research target (12m)'!$C$35:$E$35,(1+$A8)^(-('Calc - research target (12m)'!$C$19:$E$19-'Calc - research target (12m)'!$B$13)))+'Calc - research target (12m)'!$E$31*(1+D$4)/($A8-D$4)/(1+$A8)^('Calc - research target (12m)'!$B$16-'Calc - research target (12m)'!$B$13))-'Calc - research target (12m)'!$B$50-'Calc - research target (12m)'!$B$51+'Calc - research target (12m)'!$B$52)/'Calc - research target (12m)'!$B$53) | E8: =IF($A8-E$4<=0.01,"n/a",((SUMPRODUCT('Calc - research target (12m)'!$C$31:$E$31,'Calc - research target (12m)'!$C$35:$E$35,(1+$A8)^(-('Calc - research target (12m)'!$C$19:$E$19-'Calc - research target (12m)'!$B$13)))+'Calc - research target (12m)'!$E$31*(1+E$4)/($A8-E$4)/(1+$A8)^('Calc - research target (12m)'!$B$16-'Calc - research target (12m)'!$B$13))-'Calc - research target (12m)'!$B$50-'Calc - research target (12m)'!$B$51+'Calc - research target (12m)'!$B$52)/'Calc - research target (12m)'!$B$53) | F8: =IF($A8-F$4<=0.01,"n/a",((SUMPRODUCT('Calc - research target (12m)'!$C$31:$E$31,'Calc - research target (12m)'!$C$35:$E$35,(1+$A8)^(-('Calc - research target (12m)'!$C$19:$E$19-'Calc - research target (12m)'!$B$13)))+'Calc - research target (12m)'!$E$31*(1+F$4)/($A8-F$4)/(1+$A8)^('Calc - research target (12m)'!$B$16-'Calc - research target (12m)'!$B$13))-'Calc - research target (12m)'!$B$50-'Calc - research target (12m)'!$B$51+'Calc - research target (12m)'!$B$52)/'Calc - research target (12m)'!$B$53)
A9: =Valuation!$B$52+(0.01) | B9: =IF($A9-B$4<=0.01,"n/a",((SUMPRODUCT('Calc - research target (12m)'!$C$31:$E$31,'Calc - research target (12m)'!$C$35:$E$35,(1+$A9)^(-('Calc - research target (12m)'!$C$19:$E$19-'Calc - research target (12m)'!$B$13)))+'Calc - research target (12m)'!$E$31*(1+B$4)/($A9-B$4)/(1+$A9)^('Calc - research target (12m)'!$B$16-'Calc - research target (12m)'!$B$13))-'Calc - research target (12m)'!$B$50-'Calc - research target (12m)'!$B$51+'Calc - research target (12m)'!$B$52)/'Calc - research target (12m)'!$B$53) | C9: =IF($A9-C$4<=0.01,"n/a",((SUMPRODUCT('Calc - research target (12m)'!$C$31:$E$31,'Calc - research target (12m)'!$C$35:$E$35,(1+$A9)^(-('Calc - research target (12m)'!$C$19:$E$19-'Calc - research target (12m)'!$B$13)))+'Calc - research target (12m)'!$E$31*(1+C$4)/($A9-C$4)/(1+$A9)^('Calc - research target (12m)'!$B$16-'Calc - research target (12m)'!$B$13))-'Calc - research target (12m)'!$B$50-'Calc - research target (12m)'!$B$51+'Calc - research target (12m)'!$B$52)/'Calc - research target (12m)'!$B$53) | D9: =IF($A9-D$4<=0.01,"n/a",((SUMPRODUCT('Calc - research target (12m)'!$C$31:$E$31,'Calc - research target (12m)'!$C$35:$E$35,(1+$A9)^(-('Calc - research target (12m)'!$C$19:$E$19-'Calc - research target (12m)'!$B$13)))+'Calc - research target (12m)'!$E$31*(1+D$4)/($A9-D$4)/(1+$A9)^('Calc - research target (12m)'!$B$16-'Calc - research target (12m)'!$B$13))-'Calc - research target (12m)'!$B$50-'Calc - research target (12m)'!$B$51+'Calc - research target (12m)'!$B$52)/'Calc - research target (12m)'!$B$53) | E9: =IF($A9-E$4<=0.01,"n/a",((SUMPRODUCT('Calc - research target (12m)'!$C$31:$E$31,'Calc - research target (12m)'!$C$35:$E$35,(1+$A9)^(-('Calc - research target (12m)'!$C$19:$E$19-'Calc - research target (12m)'!$B$13)))+'Calc - research target (12m)'!$E$31*(1+E$4)/($A9-E$4)/(1+$A9)^('Calc - research target (12m)'!$B$16-'Calc - research target (12m)'!$B$13))-'Calc - research target (12m)'!$B$50-'Calc - research target (12m)'!$B$51+'Calc - research target (12m)'!$B$52)/'Calc - research target (12m)'!$B$53) | F9: =IF($A9-F$4<=0.01,"n/a",((SUMPRODUCT('Calc - research target (12m)'!$C$31:$E$31,'Calc - research target (12m)'!$C$35:$E$35,(1+$A9)^(-('Calc - research target (12m)'!$C$19:$E$19-'Calc - research target (12m)'!$B$13)))+'Calc - research target (12m)'!$E$31*(1+F$4)/($A9-F$4)/(1+$A9)^('Calc - research target (12m)'!$B$16-'Calc - research target (12m)'!$B$13))-'Calc - research target (12m)'!$B$50-'Calc - research target (12m)'!$B$51+'Calc - research target (12m)'!$B$52)/'Calc - research target (12m)'!$B$53)
A11: Research target (12m) per share: P/E multiple (down) x metric at target date (across)
A12: Multiple \ metric | B12: ='Calc - research target (12m)'!$E$68*0.9 | C12: ='Calc - research target (12m)'!$E$68*0.95 | D12: ='Calc - research target (12m)'!$E$68*1.0 | E12: ='Calc - research target (12m)'!$E$68*1.05 | F12: ='Calc - research target (12m)'!$E$68*1.1
A13: =Valuation!$B$71+(-3) | B13: =((SUMPRODUCT('Calc - research target (12m)'!$F$67:$F$70,'Calc - research target (12m)'!$G$67:$G$70)-'Calc - research target (12m)'!$F$68*'Calc - research target (12m)'!$G$68)+'Calc - research target (12m)'!$G$68*($A13*(B$12-'Calc - research target (12m)'!$B$54)/'Calc - research target (12m)'!$B$53+'Calc - research target (12m)'!$B$52/'Calc - research target (12m)'!$B$53))/SUM('Calc - research target (12m)'!$G$67:$G$70) | C13: =((SUMPRODUCT('Calc - research target (12m)'!$F$67:$F$70,'Calc - research target (12m)'!$G$67:$G$70)-'Calc - research target (12m)'!$F$68*'Calc - research target (12m)'!$G$68)+'Calc - research target (12m)'!$G$68*($A13*(C$12-'Calc - research target (12m)'!$B$54)/'Calc - research target (12m)'!$B$53+'Calc - research target (12m)'!$B$52/'Calc - research target (12m)'!$B$53))/SUM('Calc - research target (12m)'!$G$67:$G$70) | D13: =((SUMPRODUCT('Calc - research target (12m)'!$F$67:$F$70,'Calc - research target (12m)'!$G$67:$G$70)-'Calc - research target (12m)'!$F$68*'Calc - research target (12m)'!$G$68)+'Calc - research target (12m)'!$G$68*($A13*(D$12-'Calc - research target (12m)'!$B$54)/'Calc - research target (12m)'!$B$53+'Calc - research target (12m)'!$B$52/'Calc - research target (12m)'!$B$53))/SUM('Calc - research target (12m)'!$G$67:$G$70) | E13: =((SUMPRODUCT('Calc - research target (12m)'!$F$67:$F$70,'Calc - research target (12m)'!$G$67:$G$70)-'Calc - research target (12m)'!$F$68*'Calc - research target (12m)'!$G$68)+'Calc - research target (12m)'!$G$68*($A13*(E$12-'Calc - research target (12m)'!$B$54)/'Calc - research target (12m)'!$B$53+'Calc - research target (12m)'!$B$52/'Calc - research target (12m)'!$B$53))/SUM('Calc - research target (12m)'!$G$67:$G$70) | F13: =((SUMPRODUCT('Calc - research target (12m)'!$F$67:$F$70,'Calc - research target (12m)'!$G$67:$G$70)-'Calc - research target (12m)'!$F$68*'Calc - research target (12m)'!$G$68)+'Calc - research target (12m)'!$G$68*($A13*(F$12-'Calc - research target (12m)'!$B$54)/'Calc - research target (12m)'!$B$53+'Calc - research target (12m)'!$B$52/'Calc - research target (12m)'!$B$53))/SUM('Calc - research target (12m)'!$G$67:$G$70)
A14: =Valuation!$B$71+(-2) | B14: =((SUMPRODUCT('Calc - research target (12m)'!$F$67:$F$70,'Calc - research target (12m)'!$G$67:$G$70)-'Calc - research target (12m)'!$F$68*'Calc - research target (12m)'!$G$68)+'Calc - research target (12m)'!$G$68*($A14*(B$12-'Calc - research target (12m)'!$B$54)/'Calc - research target (12m)'!$B$53+'Calc - research target (12m)'!$B$52/'Calc - research target (12m)'!$B$53))/SUM('Calc - research target (12m)'!$G$67:$G$70) | C14: =((SUMPRODUCT('Calc - research target (12m)'!$F$67:$F$70,'Calc - research target (12m)'!$G$67:$G$70)-'Calc - research target (12m)'!$F$68*'Calc - research target (12m)'!$G$68)+'Calc - research target (12m)'!$G$68*($A14*(C$12-'Calc - research target (12m)'!$B$54)/'Calc - research target (12m)'!$B$53+'Calc - research target (12m)'!$B$52/'Calc - research target (12m)'!$B$53))/SUM('Calc - research target (12m)'!$G$67:$G$70) | D14: =((SUMPRODUCT('Calc - research target (12m)'!$F$67:$F$70,'Calc - research target (12m)'!$G$67:$G$70)-'Calc - research target (12m)'!$F$68*'Calc - research target (12m)'!$G$68)+'Calc - research target (12m)'!$G$68*($A14*(D$12-'Calc - research target (12m)'!$B$54)/'Calc - research target (12m)'!$B$53+'Calc - research target (12m)'!$B$52/'Calc - research target (12m)'!$B$53))/SUM('Calc - research target (12m)'!$G$67:$G$70) | E14: =((SUMPRODUCT('Calc - research target (12m)'!$F$67:$F$70,'Calc - research target (12m)'!$G$67:$G$70)-'Calc - research target (12m)'!$F$68*'Calc - research target (12m)'!$G$68)+'Calc - research target (12m)'!$G$68*($A14*(E$12-'Calc - research target (12m)'!$B$54)/'Calc - research target (12m)'!$B$53+'Calc - research target (12m)'!$B$52/'Calc - research target (12m)'!$B$53))/SUM('Calc - research target (12m)'!$G$67:$G$70) | F14: =((SUMPRODUCT('Calc - research target (12m)'!$F$67:$F$70,'Calc - research target (12m)'!$G$67:$G$70)-'Calc - research target (12m)'!$F$68*'Calc - research target (12m)'!$G$68)+'Calc - research target (12m)'!$G$68*($A14*(F$12-'Calc - research target (12m)'!$B$54)/'Calc - research target (12m)'!$B$53+'Calc - research target (12m)'!$B$52/'Calc - research target (12m)'!$B$53))/SUM('Calc - research target (12m)'!$G$67:$G$70)
A15: =Valuation!$B$71+(-1) | B15: =((SUMPRODUCT('Calc - research target (12m)'!$F$67:$F$70,'Calc - research target (12m)'!$G$67:$G$70)-'Calc - research target (12m)'!$F$68*'Calc - research target (12m)'!$G$68)+'Calc - research target (12m)'!$G$68*($A15*(B$12-'Calc - research target (12m)'!$B$54)/'Calc - research target (12m)'!$B$53+'Calc - research target (12m)'!$B$52/'Calc - research target (12m)'!$B$53))/SUM('Calc - research target (12m)'!$G$67:$G$70) | C15: =((SUMPRODUCT('Calc - research target (12m)'!$F$67:$F$70,'Calc - research target (12m)'!$G$67:$G$70)-'Calc - research target (12m)'!$F$68*'Calc - research target (12m)'!$G$68)+'Calc - research target (12m)'!$G$68*($A15*(C$12-'Calc - research target (12m)'!$B$54)/'Calc - research target (12m)'!$B$53+'Calc - research target (12m)'!$B$52/'Calc - research target (12m)'!$B$53))/SUM('Calc - research target (12m)'!$G$67:$G$70) | D15: =((SUMPRODUCT('Calc - research target (12m)'!$F$67:$F$70,'Calc - research target (12m)'!$G$67:$G$70)-'Calc - research target (12m)'!$F$68*'Calc - research target (12m)'!$G$68)+'Calc - research target (12m)'!$G$68*($A15*(D$12-'Calc - research target (12m)'!$B$54)/'Calc - research target (12m)'!$B$53+'Calc - research target (12m)'!$B$52/'Calc - research target (12m)'!$B$53))/SUM('Calc - research target (12m)'!$G$67:$G$70) | E15: =((SUMPRODUCT('Calc - research target (12m)'!$F$67:$F$70,'Calc - research target (12m)'!$G$67:$G$70)-'Calc - research target (12m)'!$F$68*'Calc - research target (12m)'!$G$68)+'Calc - research target (12m)'!$G$68*($A15*(E$12-'Calc - research target (12m)'!$B$54)/'Calc - research target (12m)'!$B$53+'Calc - research target (12m)'!$B$52/'Calc - research target (12m)'!$B$53))/SUM('Calc - research target (12m)'!$G$67:$G$70) | F15: =((SUMPRODUCT('Calc - research target (12m)'!$F$67:$F$70,'Calc - research target (12m)'!$G$67:$G$70)-'Calc - research target (12m)'!$F$68*'Calc - research target (12m)'!$G$68)+'Calc - research target (12m)'!$G$68*($A15*(F$12-'Calc - research target (12m)'!$B$54)/'Calc - research target (12m)'!$B$53+'Calc - research target (12m)'!$B$52/'Calc - research target (12m)'!$B$53))/SUM('Calc - research target (12m)'!$G$67:$G$70)
A16: =Valuation!$B$71+(0) | B16: =((SUMPRODUCT('Calc - research target (12m)'!$F$67:$F$70,'Calc - research target (12m)'!$G$67:$G$70)-'Calc - research target (12m)'!$F$68*'Calc - research target (12m)'!$G$68)+'Calc - research target (12m)'!$G$68*($A16*(B$12-'Calc - research target (12m)'!$B$54)/'Calc - research target (12m)'!$B$53+'Calc - research target (12m)'!$B$52/'Calc - research target (12m)'!$B$53))/SUM('Calc - research target (12m)'!$G$67:$G$70) | C16: =((SUMPRODUCT('Calc - research target (12m)'!$F$67:$F$70,'Calc - research target (12m)'!$G$67:$G$70)-'Calc - research target (12m)'!$F$68*'Calc - research target (12m)'!$G$68)+'Calc - research target (12m)'!$G$68*($A16*(C$12-'Calc - research target (12m)'!$B$54)/'Calc - research target (12m)'!$B$53+'Calc - research target (12m)'!$B$52/'Calc - research target (12m)'!$B$53))/SUM('Calc - research target (12m)'!$G$67:$G$70) | D16: =((SUMPRODUCT('Calc - research target (12m)'!$F$67:$F$70,'Calc - research target (12m)'!$G$67:$G$70)-'Calc - research target (12m)'!$F$68*'Calc - research target (12m)'!$G$68)+'Calc - research target (12m)'!$G$68*($A16*(D$12-'Calc - research target (12m)'!$B$54)/'Calc - research target (12m)'!$B$53+'Calc - research target (12m)'!$B$52/'Calc - research target (12m)'!$B$53))/SUM('Calc - research target (12m)'!$G$67:$G$70) | E16: =((SUMPRODUCT('Calc - research target (12m)'!$F$67:$F$70,'Calc - research target (12m)'!$G$67:$G$70)-'Calc - research target (12m)'!$F$68*'Calc - research target (12m)'!$G$68)+'Calc - research target (12m)'!$G$68*($A16*(E$12-'Calc - research target (12m)'!$B$54)/'Calc - research target (12m)'!$B$53+'Calc - research target (12m)'!$B$52/'Calc - research target (12m)'!$B$53))/SUM('Calc - research target (12m)'!$G$67:$G$70) | F16: =((SUMPRODUCT('Calc - research target (12m)'!$F$67:$F$70,'Calc - research target (12m)'!$G$67:$G$70)-'Calc - research target (12m)'!$F$68*'Calc - research target (12m)'!$G$68)+'Calc - research target (12m)'!$G$68*($A16*(F$12-'Calc - research target (12m)'!$B$54)/'Calc - research target (12m)'!$B$53+'Calc - research target (12m)'!$B$52/'Calc - research target (12m)'!$B$53))/SUM('Calc - research target (12m)'!$G$67:$G$70)
A17: =Valuation!$B$71+(1) | B17: =((SUMPRODUCT('Calc - research target (12m)'!$F$67:$F$70,'Calc - research target (12m)'!$G$67:$G$70)-'Calc - research target (12m)'!$F$68*'Calc - research target (12m)'!$G$68)+'Calc - research target (12m)'!$G$68*($A17*(B$12-'Calc - research target (12m)'!$B$54)/'Calc - research target (12m)'!$B$53+'Calc - research target (12m)'!$B$52/'Calc - research target (12m)'!$B$53))/SUM('Calc - research target (12m)'!$G$67:$G$70) | C17: =((SUMPRODUCT('Calc - research target (12m)'!$F$67:$F$70,'Calc - research target (12m)'!$G$67:$G$70)-'Calc - research target (12m)'!$F$68*'Calc - research target (12m)'!$G$68)+'Calc - research target (12m)'!$G$68*($A17*(C$12-'Calc - research target (12m)'!$B$54)/'Calc - research target (12m)'!$B$53+'Calc - research target (12m)'!$B$52/'Calc - research target (12m)'!$B$53))/SUM('Calc - research target (12m)'!$G$67:$G$70) | D17: =((SUMPRODUCT('Calc - research target (12m)'!$F$67:$F$70,'Calc - research target (12m)'!$G$67:$G$70)-'Calc - research target (12m)'!$F$68*'Calc - research target (12m)'!$G$68)+'Calc - research target (12m)'!$G$68*($A17*(D$12-'Calc - research target (12m)'!$B$54)/'Calc - research target (12m)'!$B$53+'Calc - research target (12m)'!$B$52/'Calc - research target (12m)'!$B$53))/SUM('Calc - research target (12m)'!$G$67:$G$70) | E17: =((SUMPRODUCT('Calc - research target (12m)'!$F$67:$F$70,'Calc - research target (12m)'!$G$67:$G$70)-'Calc - research target (12m)'!$F$68*'Calc - research target (12m)'!$G$68)+'Calc - research target (12m)'!$G$68*($A17*(E$12-'Calc - research target (12m)'!$B$54)/'Calc - research target (12m)'!$B$53+'Calc - research target (12m)'!$B$52/'Calc - research target (12m)'!$B$53))/SUM('Calc - research target (12m)'!$G$67:$G$70) | F17: =((SUMPRODUCT('Calc - research target (12m)'!$F$67:$F$70,'Calc - research target (12m)'!$G$67:$G$70)-'Calc - research target (12m)'!$F$68*'Calc - research target (12m)'!$G$68)+'Calc - research target (12m)'!$G$68*($A17*(F$12-'Calc - research target (12m)'!$B$54)/'Calc - research target (12m)'!$B$53+'Calc - research target (12m)'!$B$52/'Calc - research target (12m)'!$B$53))/SUM('Calc - research target (12m)'!$G$67:$G$70)
A18: =Valuation!$B$71+(2) | B18: =((SUMPRODUCT('Calc - research target (12m)'!$F$67:$F$70,'Calc - research target (12m)'!$G$67:$G$70)-'Calc - research target (12m)'!$F$68*'Calc - research target (12m)'!$G$68)+'Calc - research target (12m)'!$G$68*($A18*(B$12-'Calc - research target (12m)'!$B$54)/'Calc - research target (12m)'!$B$53+'Calc - research target (12m)'!$B$52/'Calc - research target (12m)'!$B$53))/SUM('Calc - research target (12m)'!$G$67:$G$70) | C18: =((SUMPRODUCT('Calc - research target (12m)'!$F$67:$F$70,'Calc - research target (12m)'!$G$67:$G$70)-'Calc - research target (12m)'!$F$68*'Calc - research target (12m)'!$G$68)+'Calc - research target (12m)'!$G$68*($A18*(C$12-'Calc - research target (12m)'!$B$54)/'Calc - research target (12m)'!$B$53+'Calc - research target (12m)'!$B$52/'Calc - research target (12m)'!$B$53))/SUM('Calc - research target (12m)'!$G$67:$G$70) | D18: =((SUMPRODUCT('Calc - research target (12m)'!$F$67:$F$70,'Calc - research target (12m)'!$G$67:$G$70)-'Calc - research target (12m)'!$F$68*'Calc - research target (12m)'!$G$68)+'Calc - research target (12m)'!$G$68*($A18*(D$12-'Calc - research target (12m)'!$B$54)/'Calc - research target (12m)'!$B$53+'Calc - research target (12m)'!$B$52/'Calc - research target (12m)'!$B$53))/SUM('Calc - research target (12m)'!$G$67:$G$70) | E18: =((SUMPRODUCT('Calc - research target (12m)'!$F$67:$F$70,'Calc - research target (12m)'!$G$67:$G$70)-'Calc - research target (12m)'!$F$68*'Calc - research target (12m)'!$G$68)+'Calc - research target (12m)'!$G$68*($A18*(E$12-'Calc - research target (12m)'!$B$54)/'Calc - research target (12m)'!$B$53+'Calc - research target (12m)'!$B$52/'Calc - research target (12m)'!$B$53))/SUM('Calc - research target (12m)'!$G$67:$G$70) | F18: =((SUMPRODUCT('Calc - research target (12m)'!$F$67:$F$70,'Calc - research target (12m)'!$G$67:$G$70)-'Calc - research target (12m)'!$F$68*'Calc - research target (12m)'!$G$68)+'Calc - research target (12m)'!$G$68*($A18*(F$12-'Calc - research target (12m)'!$B$54)/'Calc - research target (12m)'!$B$53+'Calc - research target (12m)'!$B$52/'Calc - research target (12m)'!$B$53))/SUM('Calc - research target (12m)'!$G$67:$G$70)
A19: =Valuation!$B$71+(3) | B19: =((SUMPRODUCT('Calc - research target (12m)'!$F$67:$F$70,'Calc - research target (12m)'!$G$67:$G$70)-'Calc - research target (12m)'!$F$68*'Calc - research target (12m)'!$G$68)+'Calc - research target (12m)'!$G$68*($A19*(B$12-'Calc - research target (12m)'!$B$54)/'Calc - research target (12m)'!$B$53+'Calc - research target (12m)'!$B$52/'Calc - research target (12m)'!$B$53))/SUM('Calc - research target (12m)'!$G$67:$G$70) | C19: =((SUMPRODUCT('Calc - research target (12m)'!$F$67:$F$70,'Calc - research target (12m)'!$G$67:$G$70)-'Calc - research target (12m)'!$F$68*'Calc - research target (12m)'!$G$68)+'Calc - research target (12m)'!$G$68*($A19*(C$12-'Calc - research target (12m)'!$B$54)/'Calc - research target (12m)'!$B$53+'Calc - research target (12m)'!$B$52/'Calc - research target (12m)'!$B$53))/SUM('Calc - research target (12m)'!$G$67:$G$70) | D19: =((SUMPRODUCT('Calc - research target (12m)'!$F$67:$F$70,'Calc - research target (12m)'!$G$67:$G$70)-'Calc - research target (12m)'!$F$68*'Calc - research target (12m)'!$G$68)+'Calc - research target (12m)'!$G$68*($A19*(D$12-'Calc - research target (12m)'!$B$54)/'Calc - research target (12m)'!$B$53+'Calc - research target (12m)'!$B$52/'Calc - research target (12m)'!$B$53))/SUM('Calc - research target (12m)'!$G$67:$G$70) | E19: =((SUMPRODUCT('Calc - research target (12m)'!$F$67:$F$70,'Calc - research target (12m)'!$G$67:$G$70)-'Calc - research target (12m)'!$F$68*'Calc - research target (12m)'!$G$68)+'Calc - research target (12m)'!$G$68*($A19*(E$12-'Calc - research target (12m)'!$B$54)/'Calc - research target (12m)'!$B$53+'Calc - research target (12m)'!$B$52/'Calc - research target (12m)'!$B$53))/SUM('Calc - research target (12m)'!$G$67:$G$70) | F19: =((SUMPRODUCT('Calc - research target (12m)'!$F$67:$F$70,'Calc - research target (12m)'!$G$67:$G$70)-'Calc - research target (12m)'!$F$68*'Calc - research target (12m)'!$G$68)+'Calc - research target (12m)'!$G$68*($A19*(F$12-'Calc - research target (12m)'!$B$54)/'Calc - research target (12m)'!$B$53+'Calc - research target (12m)'!$B$52/'Calc - research target (12m)'!$B$53))/SUM('Calc - research target (12m)'!$G$67:$G$70)
A22: FY2027E diluted EPS: revenue growth change in every year (down) x EBIT margin change (across)
A23: Growth Δ \ margin Δ | B23: -0.01 | C23: -0.005 | D23: 0 | E23: 0.005 | F23: 0.01
A24: -0.02 | B24: =(Valuation!$B$90*(1+Model!E12+$A24)*(1+Model!F12+$A24)*(Model!F14+B$23)+Valuation!$B$91*(1+Model!E16+$A24)*(1+Model!F16+$A24)*(Model!F18+B$23)+Model!F21+Model!F33)*(1-Model!F63)/Model!F40 | C24: =(Valuation!$B$90*(1+Model!E12+$A24)*(1+Model!F12+$A24)*(Model!F14+C$23)+Valuation!$B$91*(1+Model!E16+$A24)*(1+Model!F16+$A24)*(Model!F18+C$23)+Model!F21+Model!F33)*(1-Model!F63)/Model!F40 | D24: =(Valuation!$B$90*(1+Model!E12+$A24)*(1+Model!F12+$A24)*(Model!F14+D$23)+Valuation!$B$91*(1+Model!E16+$A24)*(1+Model!F16+$A24)*(Model!F18+D$23)+Model!F21+Model!F33)*(1-Model!F63)/Model!F40 | E24: =(Valuation!$B$90*(1+Model!E12+$A24)*(1+Model!F12+$A24)*(Model!F14+E$23)+Valuation!$B$91*(1+Model!E16+$A24)*(1+Model!F16+$A24)*(Model!F18+E$23)+Model!F21+Model!F33)*(1-Model!F63)/Model!F40 | F24: =(Valuation!$B$90*(1+Model!E12+$A24)*(1+Model!F12+$A24)*(Model!F14+F$23)+Valuation!$B$91*(1+Model!E16+$A24)*(1+Model!F16+$A24)*(Model!F18+F$23)+Model!F21+Model!F33)*(1-Model!F63)/Model!F40
A25: -0.01 | B25: =(Valuation!$B$90*(1+Model!E12+$A25)*(1+Model!F12+$A25)*(Model!F14+B$23)+Valuation!$B$91*(1+Model!E16+$A25)*(1+Model!F16+$A25)*(Model!F18+B$23)+Model!F21+Model!F33)*(1-Model!F63)/Model!F40 | C25: =(Valuation!$B$90*(1+Model!E12+$A25)*(1+Model!F12+$A25)*(Model!F14+C$23)+Valuation!$B$91*(1+Model!E16+$A25)*(1+Model!F16+$A25)*(Model!F18+C$23)+Model!F21+Model!F33)*(1-Model!F63)/Model!F40 | D25: =(Valuation!$B$90*(1+Model!E12+$A25)*(1+Model!F12+$A25)*(Model!F14+D$23)+Valuation!$B$91*(1+Model!E16+$A25)*(1+Model!F16+$A25)*(Model!F18+D$23)+Model!F21+Model!F33)*(1-Model!F63)/Model!F40 | E25: =(Valuation!$B$90*(1+Model!E12+$A25)*(1+Model!F12+$A25)*(Model!F14+E$23)+Valuation!$B$91*(1+Model!E16+$A25)*(1+Model!F16+$A25)*(Model!F18+E$23)+Model!F21+Model!F33)*(1-Model!F63)/Model!F40 | F25: =(Valuation!$B$90*(1+Model!E12+$A25)*(1+Model!F12+$A25)*(Model!F14+F$23)+Valuation!$B$91*(1+Model!E16+$A25)*(1+Model!F16+$A25)*(Model!F18+F$23)+Model!F21+Model!F33)*(1-Model!F63)/Model!F40
A26: 0 | B26: =(Valuation!$B$90*(1+Model!E12+$A26)*(1+Model!F12+$A26)*(Model!F14+B$23)+Valuation!$B$91*(1+Model!E16+$A26)*(1+Model!F16+$A26)*(Model!F18+B$23)+Model!F21+Model!F33)*(1-Model!F63)/Model!F40 | C26: =(Valuation!$B$90*(1+Model!E12+$A26)*(1+Model!F12+$A26)*(Model!F14+C$23)+Valuation!$B$91*(1+Model!E16+$A26)*(1+Model!F16+$A26)*(Model!F18+C$23)+Model!F21+Model!F33)*(1-Model!F63)/Model!F40 | D26: =(Valuation!$B$90*(1+Model!E12+$A26)*(1+Model!F12+$A26)*(Model!F14+D$23)+Valuation!$B$91*(1+Model!E16+$A26)*(1+Model!F16+$A26)*(Model!F18+D$23)+Model!F21+Model!F33)*(1-Model!F63)/Model!F40 | E26: =(Valuation!$B$90*(1+Model!E12+$A26)*(1+Model!F12+$A26)*(Model!F14+E$23)+Valuation!$B$91*(1+Model!E16+$A26)*(1+Model!F16+$A26)*(Model!F18+E$23)+Model!F21+Model!F33)*(1-Model!F63)/Model!F40 | F26: =(Valuation!$B$90*(1+Model!E12+$A26)*(1+Model!F12+$A26)*(Model!F14+F$23)+Valuation!$B$91*(1+Model!E16+$A26)*(1+Model!F16+$A26)*(Model!F18+F$23)+Model!F21+Model!F33)*(1-Model!F63)/Model!F40
A27: 0.01 | B27: =(Valuation!$B$90*(1+Model!E12+$A27)*(1+Model!F12+$A27)*(Model!F14+B$23)+Valuation!$B$91*(1+Model!E16+$A27)*(1+Model!F16+$A27)*(Model!F18+B$23)+Model!F21+Model!F33)*(1-Model!F63)/Model!F40 | C27: =(Valuation!$B$90*(1+Model!E12+$A27)*(1+Model!F12+$A27)*(Model!F14+C$23)+Valuation!$B$91*(1+Model!E16+$A27)*(1+Model!F16+$A27)*(Model!F18+C$23)+Model!F21+Model!F33)*(1-Model!F63)/Model!F40 | D27: =(Valuation!$B$90*(1+Model!E12+$A27)*(1+Model!F12+$A27)*(Model!F14+D$23)+Valuation!$B$91*(1+Model!E16+$A27)*(1+Model!F16+$A27)*(Model!F18+D$23)+Model!F21+Model!F33)*(1-Model!F63)/Model!F40 | E27: =(Valuation!$B$90*(1+Model!E12+$A27)*(1+Model!F12+$A27)*(Model!F14+E$23)+Valuation!$B$91*(1+Model!E16+$A27)*(1+Model!F16+$A27)*(Model!F18+E$23)+Model!F21+Model!F33)*(1-Model!F63)/Model!F40 | F27: =(Valuation!$B$90*(1+Model!E12+$A27)*(1+Model!F12+$A27)*(Model!F14+F$23)+Valuation!$B$91*(1+Model!E16+$A27)*(1+Model!F16+$A27)*(Model!F18+F$23)+Model!F21+Model!F33)*(1-Model!F63)/Model!F40
A28: 0.02 | B28: =(Valuation!$B$90*(1+Model!E12+$A28)*(1+Model!F12+$A28)*(Model!F14+B$23)+Valuation!$B$91*(1+Model!E16+$A28)*(1+Model!F16+$A28)*(Model!F18+B$23)+Model!F21+Model!F33)*(1-Model!F63)/Model!F40 | C28: =(Valuation!$B$90*(1+Model!E12+$A28)*(1+Model!F12+$A28)*(Model!F14+C$23)+Valuation!$B$91*(1+Model!E16+$A28)*(1+Model!F16+$A28)*(Model!F18+C$23)+Model!F21+Model!F33)*(1-Model!F63)/Model!F40 | D28: =(Valuation!$B$90*(1+Model!E12+$A28)*(1+Model!F12+$A28)*(Model!F14+D$23)+Valuation!$B$91*(1+Model!E16+$A28)*(1+Model!F16+$A28)*(Model!F18+D$23)+Model!F21+Model!F33)*(1-Model!F63)/Model!F40 | E28: =(Valuation!$B$90*(1+Model!E12+$A28)*(1+Model!F12+$A28)*(Model!F14+E$23)+Valuation!$B$91*(1+Model!E16+$A28)*(1+Model!F16+$A28)*(Model!F18+E$23)+Model!F21+Model!F33)*(1-Model!F63)/Model!F40 | F28: =(Valuation!$B$90*(1+Model!E12+$A28)*(1+Model!F12+$A28)*(Model!F14+F$23)+Valuation!$B$91*(1+Model!E16+$A28)*(1+Model!F16+$A28)*(Model!F18+F$23)+Model!F21+Model!F33)*(1-Model!F63)/Model!F40
A30: Net interest and the share count are held at the base case in table 3.

Sheet Distribution
A1: BE: 12-month distribution (mix of lognormals around each scenario value)
A3: Scenario | B3: Probability | C3: Value at target date | D3: Story
A4: bear | B4: =Valuation!B85 | C4: ='Calc - bear'!$F$71 | D4: =Valuation!J85
A5: base | B5: =Valuation!B86 | C5: ='Calc - base'!$F$71 | D5: =Valuation!J86
A6: bull | B6: =Valuation!B87 | C6: ='Calc - bull'!$F$71 | D6: =Valuation!J87
A8: Probabilities sum to | B8: =SUM(B4:B6)
A9: Spread within each scenario | B9: =Valuation!$B$67
A10: Probability-weighted mean | B10: =($B$4*$C$4+$B$5*$C$5+$B$6*$C$6)*EXP($B$9^2/2)
A12: Quantile | B12: Price
A13: Median (model target) | B13: =SQRT(A60*B60)
A14: 10th percentile | B14: =SQRT(D60*E60)
A15: 25th percentile | B15: =SQRT(G60*H60)
A16: 75th percentile | B16: =SQRT(J60*K60)
A17: 90th percentile | B17: =SQRT(M60*N60)
A19: Each quantile solved by bisection (block: low, high, probability above the midpoint)
A20: Median (model target): low | B20: high | C20: P(above mid) | D20: 10th percentile: low | E20: high | F20: P(above mid) | G20: 25th percentile: low | H20: high | I20: P(above mid) | J20: 75th percentile: low | K20: high | L20: P(above mid) | M20: 90th percentile: low | N20: high | O20: P(above mid)
A21: =MIN($C$4,$C$5,$C$6)*0.2 | B21: =MAX($C$4,$C$5,$C$6)*4 | C21: =SUMPRODUCT($B$4:$B$6,1-NORMSDIST((LN(SQRT(A21*B21))-LN($C$4:$C$6))/$B$9)) | D21: =MIN($C$4,$C$5,$C$6)*0.2 | E21: =MAX($C$4,$C$5,$C$6)*4 | F21: =SUMPRODUCT($B$4:$B$6,1-NORMSDIST((LN(SQRT(D21*E21))-LN($C$4:$C$6))/$B$9)) | G21: =MIN($C$4,$C$5,$C$6)*0.2 | H21: =MAX($C$4,$C$5,$C$6)*4 | I21: =SUMPRODUCT($B$4:$B$6,1-NORMSDIST((LN(SQRT(G21*H21))-LN($C$4:$C$6))/$B$9)) | J21: =MIN($C$4,$C$5,$C$6)*0.2 | K21: =MAX($C$4,$C$5,$C$6)*4 | L21: =SUMPRODUCT($B$4:$B$6,1-NORMSDIST((LN(SQRT(J21*K21))-LN($C$4:$C$6))/$B$9)) | M21: =MIN($C$4,$C$5,$C$6)*0.2 | N21: =MAX($C$4,$C$5,$C$6)*4 | O21: =SUMPRODUCT($B$4:$B$6,1-NORMSDIST((LN(SQRT(M21*N21))-LN($C$4:$C$6))/$B$9))
A22: =IF(C21>0.5,SQRT(A21*B21),A21) | B22: =IF(C21>0.5,B21,SQRT(A21*B21)) | C22: =SUMPRODUCT($B$4:$B$6,1-NORMSDIST((LN(SQRT(A22*B22))-LN($C$4:$C$6))/$B$9)) | D22: =IF(F21>0.9,SQRT(D21*E21),D21) | E22: =IF(F21>0.9,E21,SQRT(D21*E21)) | F22: =SUMPRODUCT($B$4:$B$6,1-NORMSDIST((LN(SQRT(D22*E22))-LN($C$4:$C$6))/$B$9)) | G22: =IF(I21>0.75,SQRT(G21*H21),G21) | H22: =IF(I21>0.75,H21,SQRT(G21*H21)) | I22: =SUMPRODUCT($B$4:$B$6,1-NORMSDIST((LN(SQRT(G22*H22))-LN($C$4:$C$6))/$B$9)) | J22: =IF(L21>0.25,SQRT(J21*K21),J21) | K22: =IF(L21>0.25,K21,SQRT(J21*K21)) | L22: =SUMPRODUCT($B$4:$B$6,1-NORMSDIST((LN(SQRT(J22*K22))-LN($C$4:$C$6))/$B$9)) | M22: =IF(O21>0.09999999999999998,SQRT(M21*N21),M21) | N22: =IF(O21>0.09999999999999998,N21,SQRT(M21*N21)) | O22: =SUMPRODUCT($B$4:$B$6,1-NORMSDIST((LN(SQRT(M22*N22))-LN($C$4:$C$6))/$B$9))
A23: =IF(C22>0.5,SQRT(A22*B22),A22) | B23: =IF(C22>0.5,B22,SQRT(A22*B22)) | C23: =SUMPRODUCT($B$4:$B$6,1-NORMSDIST((LN(SQRT(A23*B23))-LN($C$4:$C$6))/$B$9)) | D23: =IF(F22>0.9,SQRT(D22*E22),D22) | E23: =IF(F22>0.9,E22,SQRT(D22*E22)) | F23: =SUMPRODUCT($B$4:$B$6,1-NORMSDIST((LN(SQRT(D23*E23))-LN($C$4:$C$6))/$B$9)) | G23: =IF(I22>0.75,SQRT(G22*H22),G22) | H23: =IF(I22>0.75,H22,SQRT(G22*H22)) | I23: =SUMPRODUCT($B$4:$B$6,1-NORMSDIST((LN(SQRT(G23*H23))-LN($C$4:$C$6))/$B$9)) | J23: =IF(L22>0.25,SQRT(J22*K22),J22) | K23: =IF(L22>0.25,K22,SQRT(J22*K22)) | L23: =SUMPRODUCT($B$4:$B$6,1-NORMSDIST((LN(SQRT(J23*K23))-LN($C$4:$C$6))/$B$9)) | M23: =IF(O22>0.09999999999999998,SQRT(M22*N22),M22) | N23: =IF(O22>0.09999999999999998,N22,SQRT(M22*N22)) | O23: =SUMPRODUCT($B$4:$B$6,1-NORMSDIST((LN(SQRT(M23*N23))-LN($C$4:$C$6))/$B$9))
A24: =IF(C23>0.5,SQRT(A23*B23),A23) | B24: =IF(C23>0.5,B23,SQRT(A23*B23)) | C24: =SUMPRODUCT($B$4:$B$6,1-NORMSDIST((LN(SQRT(A24*B24))-LN($C$4:$C$6))/$B$9)) | D24: =IF(F23>0.9,SQRT(D23*E23),D23) | E24: =IF(F23>0.9,E23,SQRT(D23*E23)) | F24: =SUMPRODUCT($B$4:$B$6,1-NORMSDIST((LN(SQRT(D24*E24))-LN($C$4:$C$6))/$B$9)) | G24: =IF(I23>0.75,SQRT(G23*H23),G23) | H24: =IF(I23>0.75,H23,SQRT(G23*H23)) | I24: =SUMPRODUCT($B$4:$B$6,1-NORMSDIST((LN(SQRT(G24*H24))-LN($C$4:$C$6))/$B$9)) | J24: =IF(L23>0.25,SQRT(J23*K23),J23) | K24: =IF(L23>0.25,K23,SQRT(J23*K23)) | L24: =SUMPRODUCT($B$4:$B$6,1-NORMSDIST((LN(SQRT(J24*K24))-LN($C$4:$C$6))/$B$9)) | M24: =IF(O23>0.09999999999999998,SQRT(M23*N23),M23) | N24: =IF(O23>0.09999999999999998,N23,SQRT(M23*N23)) | O24: =SUMPRODUCT($B$4:$B$6,1-NORMSDIST((LN(SQRT(M24*N24))-LN($C$4:$C$6))/$B$9))
A25: =IF(C24>0.5,SQRT(A24*B24),A24) | B25: =IF(C24>0.5,B24,SQRT(A24*B24)) | C25: =SUMPRODUCT($B$4:$B$6,1-NORMSDIST((LN(SQRT(A25*B25))-LN($C$4:$C$6))/$B$9)) | D25: =IF(F24>0.9,SQRT(D24*E24),D24) | E25: =IF(F24>0.9,E24,SQRT(D24*E24)) | F25: =SUMPRODUCT($B$4:$B$6,1-NORMSDIST((LN(SQRT(D25*E25))-LN($C$4:$C$6))/$B$9)) | G25: =IF(I24>0.75,SQRT(G24*H24),G24) | H25: =IF(I24>0.75,H24,SQRT(G24*H24)) | I25: =SUMPRODUCT($B$4:$B$6,1-NORMSDIST((LN(SQRT(G25*H25))-LN($C$4:$C$6))/$B$9)) | J25: =IF(L24>0.25,SQRT(J24*K24),J24) | K25: =IF(L24>0.25,K24,SQRT(J24*K24)) | L25: =SUMPRODUCT($B$4:$B$6,1-NORMSDIST((LN(SQRT(J25*K25))-LN($C$4:$C$6))/$B$9)) | M25: =IF(O24>0.09999999999999998,SQRT(M24*N24),M24) | N25: =IF(O24>0.09999999999999998,N24,SQRT(M24*N24)) | O25: =SUMPRODUCT($B$4:$B$6,1-NORMSDIST((LN(SQRT(M25*N25))-LN($C$4:$C$6))/$B$9))
A26: =IF(C25>0.5,SQRT(A25*B25),A25) | B26: =IF(C25>0.5,B25,SQRT(A25*B25)) | C26: =SUMPRODUCT($B$4:$B$6,1-NORMSDIST((LN(SQRT(A26*B26))-LN($C$4:$C$6))/$B$9)) | D26: =IF(F25>0.9,SQRT(D25*E25),D25) | E26: =IF(F25>0.9,E25,SQRT(D25*E25)) | F26: =SUMPRODUCT($B$4:$B$6,1-NORMSDIST((LN(SQRT(D26*E26))-LN($C$4:$C$6))/$B$9)) | G26: =IF(I25>0.75,SQRT(G25*H25),G25) | H26: =IF(I25>0.75,H25,SQRT(G25*H25)) | I26: =SUMPRODUCT($B$4:$B$6,1-NORMSDIST((LN(SQRT(G26*H26))-LN($C$4:$C$6))/$B$9)) | J26: =IF(L25>0.25,SQRT(J25*K25),J25) | K26: =IF(L25>0.25,K25,SQRT(J25*K25)) | L26: =SUMPRODUCT($B$4:$B$6,1-NORMSDIST((LN(SQRT(J26*K26))-LN($C$4:$C$6))/$B$9)) | M26: =IF(O25>0.09999999999999998,SQRT(M25*N25),M25) | N26: =IF(O25>0.09999999999999998,N25,SQRT(M25*N25)) | O26: =SUMPRODUCT($B$4:$B$6,1-NORMSDIST((LN(SQRT(M26*N26))-LN($C$4:$C$6))/$B$9))
A27: =IF(C26>0.5,SQRT(A26*B26),A26) | B27: =IF(C26>0.5,B26,SQRT(A26*B26)) | C27: =SUMPRODUCT($B$4:$B$6,1-NORMSDIST((LN(SQRT(A27*B27))-LN($C$4:$C$6))/$B$9)) | D27: =IF(F26>0.9,SQRT(D26*E26),D26) | E27: =IF(F26>0.9,E26,SQRT(D26*E26)) | F27: =SUMPRODUCT($B$4:$B$6,1-NORMSDIST((LN(SQRT(D27*E27))-LN($C$4:$C$6))/$B$9)) | G27: =IF(I26>0.75,SQRT(G26*H26),G26) | H27: =IF(I26>0.75,H26,SQRT(G26*H26)) | I27: =SUMPRODUCT($B$4:$B$6,1-NORMSDIST((LN(SQRT(G27*H27))-LN($C$4:$C$6))/$B$9)) | J27: =IF(L26>0.25,SQRT(J26*K26),J26) | K27: =IF(L26>0.25,K26,SQRT(J26*K26)) | L27: =SUMPRODUCT($B$4:$B$6,1-NORMSDIST((LN(SQRT(J27*K27))-LN($C$4:$C$6))/$B$9)) | M27: =IF(O26>0.09999999999999998,SQRT(M26*N26),M26) | N27: =IF(O26>0.09999999999999998,N26,SQRT(M26*N26)) | O27: =SUMPRODUCT($B$4:$B$6,1-NORMSDIST((LN(SQRT(M27*N27))-LN($C$4:$C$6))/$B$9))
A28: =IF(C27>0.5,SQRT(A27*B27),A27) | B28: =IF(C27>0.5,B27,SQRT(A27*B27)) | C28: =SUMPRODUCT($B$4:$B$6,1-NORMSDIST((LN(SQRT(A28*B28))-LN($C$4:$C$6))/$B$9)) | D28: =IF(F27>0.9,SQRT(D27*E27),D27) | E28: =IF(F27>0.9,E27,SQRT(D27*E27)) | F28: =SUMPRODUCT($B$4:$B$6,1-NORMSDIST((LN(SQRT(D28*E28))-LN($C$4:$C$6))/$B$9)) | G28: =IF(I27>0.75,SQRT(G27*H27),G27) | H28: =IF(I27>0.75,H27,SQRT(G27*H27)) | I28: =SUMPRODUCT($B$4:$B$6,1-NORMSDIST((LN(SQRT(G28*H28))-LN($C$4:$C$6))/$B$9)) | J28: =IF(L27>0.25,SQRT(J27*K27),J27) | K28: =IF(L27>0.25,K27,SQRT(J27*K27)) | L28: =SUMPRODUCT($B$4:$B$6,1-NORMSDIST((LN(SQRT(J28*K28))-LN($C$4:$C$6))/$B$9)) | M28: =IF(O27>0.09999999999999998,SQRT(M27*N27),M27) | N28: =IF(O27>0.09999999999999998,N27,SQRT(M27*N27)) | O28: =SUMPRODUCT($B$4:$B$6,1-NORMSDIST((LN(SQRT(M28*N28))-LN($C$4:$C$6))/$B$9))
A29: =IF(C28>0.5,SQRT(A28*B28),A28) | B29: =IF(C28>0.5,B28,SQRT(A28*B28)) | C29: =SUMPRODUCT($B$4:$B$6,1-NORMSDIST((LN(SQRT(A29*B29))-LN($C$4:$C$6))/$B$9)) | D29: =IF(F28>0.9,SQRT(D28*E28),D28) | E29: =IF(F28>0.9,E28,SQRT(D28*E28)) | F29: =SUMPRODUCT($B$4:$B$6,1-NORMSDIST((LN(SQRT(D29*E29))-LN($C$4:$C$6))/$B$9)) | G29: =IF(I28>0.75,SQRT(G28*H28),G28) | H29: =IF(I28>0.75,H28,SQRT(G28*H28)) | I29: =SUMPRODUCT($B$4:$B$6,1-NORMSDIST((LN(SQRT(G29*H29))-LN($C$4:$C$6))/$B$9)) | J29: =IF(L28>0.25,SQRT(J28*K28),J28) | K29: =IF(L28>0.25,K28,SQRT(J28*K28)) | L29: =SUMPRODUCT($B$4:$B$6,1-NORMSDIST((LN(SQRT(J29*K29))-LN($C$4:$C$6))/$B$9)) | M29: =IF(O28>0.09999999999999998,SQRT(M28*N28),M28) | N29: =IF(O28>0.09999999999999998,N28,SQRT(M28*N28)) | O29: =SUMPRODUCT($B$4:$B$6,1-NORMSDIST((LN(SQRT(M29*N29))-LN($C$4:$C$6))/$B$9))
A30: =IF(C29>0.5,SQRT(A29*B29),A29) | B30: =IF(C29>0.5,B29,SQRT(A29*B29)) | C30: =SUMPRODUCT($B$4:$B$6,1-NORMSDIST((LN(SQRT(A30*B30))-LN($C$4:$C$6))/$B$9)) | D30: =IF(F29>0.9,SQRT(D29*E29),D29) | E30: =IF(F29>0.9,E29,SQRT(D29*E29)) | F30: =SUMPRODUCT($B$4:$B$6,1-NORMSDIST((LN(SQRT(D30*E30))-LN($C$4:$C$6))/$B$9)) | G30: =IF(I29>0.75,SQRT(G29*H29),G29) | H30: =IF(I29>0.75,H29,SQRT(G29*H29)) | I30: =SUMPRODUCT($B$4:$B$6,1-NORMSDIST((LN(SQRT(G30*H30))-LN($C$4:$C$6))/$B$9)) | J30: =IF(L29>0.25,SQRT(J29*K29),J29) | K30: =IF(L29>0.25,K29,SQRT(J29*K29)) | L30: =SUMPRODUCT($B$4:$B$6,1-NORMSDIST((LN(SQRT(J30*K30))-LN($C$4:$C$6))/$B$9)) | M30: =IF(O29>0.09999999999999998,SQRT(M29*N29),M29) | N30: =IF(O29>0.09999999999999998,N29,SQRT(M29*N29)) | O30: =SUMPRODUCT($B$4:$B$6,1-NORMSDIST((LN(SQRT(M30*N30))-LN($C$4:$C$6))/$B$9))
A31: =IF(C30>0.5,SQRT(A30*B30),A30) | B31: =IF(C30>0.5,B30,SQRT(A30*B30)) | C31: =SUMPRODUCT($B$4:$B$6,1-NORMSDIST((LN(SQRT(A31*B31))-LN($C$4:$C$6))/$B$9)) | D31: =IF(F30>0.9,SQRT(D30*E30),D30) | E31: =IF(F30>0.9,E30,SQRT(D30*E30)) | F31: =SUMPRODUCT($B$4:$B$6,1-NORMSDIST((LN(SQRT(D31*E31))-LN($C$4:$C$6))/$B$9)) | G31: =IF(I30>0.75,SQRT(G30*H30),G30) | H31: =IF(I30>0.75,H30,SQRT(G30*H30)) | I31: =SUMPRODUCT($B$4:$B$6,1-NORMSDIST((LN(SQRT(G31*H31))-LN($C$4:$C$6))/$B$9)) | J31: =IF(L30>0.25,SQRT(J30*K30),J30) | K31: =IF(L30>0.25,K30,SQRT(J30*K30)) | L31: =SUMPRODUCT($B$4:$B$6,1-NORMSDIST((LN(SQRT(J31*K31))-LN($C$4:$C$6))/$B$9)) | M31: =IF(O30>0.09999999999999998,SQRT(M30*N30),M30) | N31: =IF(O30>0.09999999999999998,N30,SQRT(M30*N30)) | O31: =SUMPRODUCT($B$4:$B$6,1-NORMSDIST((LN(SQRT(M31*N31))-LN($C$4:$C$6))/$B$9))
A32: =IF(C31>0.5,SQRT(A31*B31),A31) | B32: =IF(C31>0.5,B31,SQRT(A31*B31)) | C32: =SUMPRODUCT($B$4:$B$6,1-NORMSDIST((LN(SQRT(A32*B32))-LN($C$4:$C$6))/$B$9)) | D32: =IF(F31>0.9,SQRT(D31*E31),D31) | E32: =IF(F31>0.9,E31,SQRT(D31*E31)) | F32: =SUMPRODUCT($B$4:$B$6,1-NORMSDIST((LN(SQRT(D32*E32))-LN($C$4:$C$6))/$B$9)) | G32: =IF(I31>0.75,SQRT(G31*H31),G31) | H32: =IF(I31>0.75,H31,SQRT(G31*H31)) | I32: =SUMPRODUCT($B$4:$B$6,1-NORMSDIST((LN(SQRT(G32*H32))-LN($C$4:$C$6))/$B$9)) | J32: =IF(L31>0.25,SQRT(J31*K31),J31) | K32: =IF(L31>0.25,K31,SQRT(J31*K31)) | L32: =SUMPRODUCT($B$4:$B$6,1-NORMSDIST((LN(SQRT(J32*K32))-LN($C$4:$C$6))/$B$9)) | M32: =IF(O31>0.09999999999999998,SQRT(M31*N31),M31) | N32: =IF(O31>0.09999999999999998,N31,SQRT(M31*N31)) | O32: =SUMPRODUCT($B$4:$B$6,1-NORMSDIST((LN(SQRT(M32*N32))-LN($C$4:$C$6))/$B$9))
A33: =IF(C32>0.5,SQRT(A32*B32),A32) | B33: =IF(C32>0.5,B32,SQRT(A32*B32)) | C33: =SUMPRODUCT($B$4:$B$6,1-NORMSDIST((LN(SQRT(A33*B33))-LN($C$4:$C$6))/$B$9)) | D33: =IF(F32>0.9,SQRT(D32*E32),D32) | E33: =IF(F32>0.9,E32,SQRT(D32*E32)) | F33: =SUMPRODUCT($B$4:$B$6,1-NORMSDIST((LN(SQRT(D33*E33))-LN($C$4:$C$6))/$B$9)) | G33: =IF(I32>0.75,SQRT(G32*H32),G32) | H33: =IF(I32>0.75,H32,SQRT(G32*H32)) | I33: =SUMPRODUCT($B$4:$B$6,1-NORMSDIST((LN(SQRT(G33*H33))-LN($C$4:$C$6))/$B$9)) | J33: =IF(L32>0.25,SQRT(J32*K32),J32) | K33: =IF(L32>0.25,K32,SQRT(J32*K32)) | L33: =SUMPRODUCT($B$4:$B$6,1-NORMSDIST((LN(SQRT(J33*K33))-LN($C$4:$C$6))/$B$9)) | M33: =IF(O32>0.09999999999999998,SQRT(M32*N32),M32) | N33: =IF(O32>0.09999999999999998,N32,SQRT(M32*N32)) | O33: =SUMPRODUCT($B$4:$B$6,1-NORMSDIST((LN(SQRT(M33*N33))-LN($C$4:$C$6))/$B$9))
... A60: =IF(C59>0.5,SQRT(A59*B59),A59) | B60: =IF(C59>0.5,B59,SQRT(A59*B59)) | C60: =SUMPRODUCT($B$4:$B$6,1-NORMSDIST((LN(SQRT(A60*B60))-LN($C$4:$C$6))/$B$9)) | D60: =IF(F59>0.9,SQRT(D59*E59),D59) | E60: =IF(F59>0.9,E59,SQRT(D59*E59)) | F60: =SUMPRODUCT($B$4:$B$6,1-NORMSDIST((LN(SQRT(D60*E60))-LN($C$4:$C$6))/$B$9)) | G60: =IF(I59>0.75,SQRT(G59*H59),G59) | H60: =IF(I59>0.75,H59,SQRT(G59*H59)) | I60: =SUMPRODUCT($B$4:$B$6,1-NORMSDIST((LN(SQRT(G60*H60))-LN($C$4:$C$6))/$B$9)) | J60: =IF(L59>0.25,SQRT(J59*K59),J59) | K60: =IF(L59>0.25,K59,SQRT(J59*K59)) | L60: =SUMPRODUCT($B$4:$B$6,1-NORMSDIST((LN(SQRT(J60*K60))-LN($C$4:$C$6))/$B$9)) | M60: =IF(O59>0.09999999999999998,SQRT(M59*N59),M59) | N60: =IF(O59>0.09999999999999998,N59,SQRT(M59*N59)) | O60: =SUMPRODUCT($B$4:$B$6,1-NORMSDIST((LN(SQRT(M60*N60))-LN($C$4:$C$6))/$B$9))

Sheet Calc - research target (12m)
A1: BE engine calculation: research target (12m) (reconciled set, no scenario deltas)
A2: Machinery behind the Valuation and Distribution tabs; drivers come from Model, assumptions from Valuation.
A4: Scenario Growth Δ | B4: 0
A5: Scenario Margin Δ | B5: 0
A6: Scenario Multiple Δ (turns) | B6: 0
A7: Scenario WACC Δ | B7: 0
A8: Scenario Multiple %Δ | B8: 0
A9: Scenario Stated EPS/FCF %Δ | B9: 0
A10: Scenario Custom %Δ | B10: 0
A12: WACC | B12: =Valuation!$B$52+B7
A13: Years from last FY end to target date | B13: =(Valuation!$B$46-Valuation!$B$50)/365.25
A14: Years from last FY end to balance date | B14: =(Valuation!$B$56-Valuation!$B$50)/365.25
A15: Years from last FY end to share count date | B15: =(Valuation!$B$62-Valuation!$B$50)/365.25
A16: Projected years | B16: 3
A18: Projection | B18: Base | C18: =Model!E5 | D18: =Model!F5 | E18: =Model!G5
A19: Year index | B19: 0 | C19: 1 | D19: 2 | E19: 3
A20: Period end | C20: =Valuation!$B$50+ROUND(365.25*C19,0) | D20: =Valuation!$B$50+ROUND(365.25*D19,0) | E20: =Valuation!$B$50+ROUND(365.25*E19,0)
A21: Revenue growth | C21: =C22/B22-1 | D21: =D22/C22-1 | E21: =E22/D22-1
A22: Revenue | B22: =Valuation!$B$51 | C22: =C139 | D22: =D139 | E22: =E139
A23: EBIT margin | C23: =C24/C22 | D23: =D24/D22 | E23: =E24/E22
A24: EBIT | C24: =C142 | D24: =D142 | E24: =E142
A25: Tax rate | C25: =Model!E63 | D25: =Model!F63 | E25: =Model!G63
A26: NOPAT | C26: =C24*(1-C25) | D26: =D24*(1-D25) | E26: =E24*(1-E25)
A27: D&A | C27: =C22*(Model!E64) | D27: =D22*(Model!F64) | E27: =E22*(Model!G64)
A28: Capex | C28: =C22*(Model!E65) | D28: =D22*(Model!F65) | E28: =E22*(Model!G65)
A29: Working capital increase | C29: =(Model!E66)*(C22-B22) | D29: =(Model!F66)*(D22-C22) | E29: =(Model!G66)*(E22-D22)
A30: Stock comp | C30: =C22*(Model!E67) | D30: =D22*(Model!F67) | E30: =E22*(Model!G67)
A31: Free cash flow to firm | C31: =C26+C27-C28-C29-IF(AND(Valuation!$B$48="adjusted",Valuation!$B$49="cost"),C30*(1-C25),0) | D31: =D26+D27-D28-D29-IF(AND(Valuation!$B$48="adjusted",Valuation!$B$49="cost"),D30*(1-D25),0) | E31: =E26+E27-E28-E29-IF(AND(Valuation!$B$48="adjusted",Valuation!$B$49="cost"),E30*(1-E25),0)
A32: EBITDA | C32: =C24+C27 | D32: =D24+D27 | E32: =E24+E27
A33: Adj. EBITDA | C33: =C24+C27+C22*(Model!E71) | D33: =D24+D27+D22*(Model!F71) | E33: =E24+E27+E22*(Model!G71)
A34: Shareholder returns + other uses | C34: =C22*Model!E69+Model!E68+Model!E70 | D34: =D22*Model!F69+Model!F68+Model!F70 | E34: =E22*Model!G69+Model!G68+Model!G70
A35: Share of year after target date | C35: =IF(C19<=$B$13,0,C19-MAX(C19-1,$B$13)) | D35: =IF(D19<=$B$13,0,D19-MAX(D19-1,$B$13)) | E35: =IF(E19<=$B$13,0,E19-MAX(E19-1,$B$13))
A36: PV at target date of FCFF | C36: =IF(C35=0,0,C31*C35/(1+$B$12)^(C19-$B$13)) | D36: =IF(D35=0,0,D31*D35/(1+$B$12)^(D19-$B$13)) | E36: =IF(E35=0,0,E31*E35/(1+$B$12)^(E19-$B$13))
A37: Overlap: balance date to target date | C37: =MAX(0,MIN(C19,$B$13)-MAX(C19-1,$B$14)) | D37: =MAX(0,MIN(D19,$B$13)-MAX(D19-1,$B$14)) | E37: =MAX(0,MIN(E19,$B$13)-MAX(E19-1,$B$14))
A38: NTM weight at target date | C38: =MAX(0,MIN(C19,$B$13+1)-MAX(C19-1,$B$13)) | D38: =MAX(0,MIN(D19,$B$13+1)-MAX(D19-1,$B$13)) | E38: =MAX(0,MIN(E19,$B$13+1)-MAX(E19-1,$B$13))
A39: LTM weight at target date | B39: =MAX(0,MIN(0,$B$13)-MAX(-1,$B$13-1)) | C39: =MAX(0,MIN(C19,$B$13)-MAX(C19-1,$B$13-1)) | D39: =MAX(0,MIN(D19,$B$13)-MAX(D19-1,$B$13-1)) | E39: =MAX(0,MIN(E19,$B$13)-MAX(E19-1,$B$13-1))
A41: Value at the target date
A42: PV of free cash flow after the target date | B42: =SUM($C$36:$E$36)
A43: Terminal value at final year | B43: =IF(Valuation!$B$53="exit_multiple",Valuation!$B$55*E32,E31*(1+Valuation!$B$54)/($B$12-Valuation!$B$54))
A44: PV of terminal value at target date | B44: =B43/(1+$B$12)^($B$16-$B$13)
A45: DCF enterprise value at target date | B45: =B42+B44
A46: Terminal value share of DCF | B46: =B44/B45
A47: Free cash flow earned, balance date to target date | B47: =SUMPRODUCT($C$37:$E$37,$C$31:$E$31)
A48: Shareholder returns + other uses paid | B48: =SUMPRODUCT($C$37:$E$37,$C$34:$E$34)
A49: Interest drag on net debt | B49: =Valuation!$B$59*(1-$C$25)*MAX(Valuation!$B$57,0)*MAX($B$13-$B$14,0)
A50: Net debt at target date | B50: =IF(Valuation!$B$60="",Valuation!$B$57-B47+B49+B48,Valuation!$B$60)
A51: Minority interests | B51: =Valuation!$B$58
A52: Adjustments (probability-weighted) | B52: =0
A53: Diluted shares at target date (M) | B53: =IF(Valuation!$B$64="",Valuation!$B$61*(1+Valuation!$B$63)^MAX($B$13-$B$15,0),Valuation!$B$64)
A54: After-tax interest on target-date net debt | B54: =Valuation!$B$59*(1-$C$25)*MAX(B50,0)
A55: Check: WACC vs terminal growth | B55: =IF(AND(Valuation!$B$53<>"exit_multiple",$B$12<=Valuation!$B$54+0.01),"WACC must exceed terminal growth by 1 point","ok")
A56: Check: projection length | B56: =IF(OR($B$13>=$B$16-1,$B$13+1>$B$16),"add projected years past the target date","ok")
A58: Metric at target date | B58: Next 12 months | C58: Last 12 months
A59: Revenue | B59: =SUMPRODUCT($C$38:$E$38,$C$22:$E$22) | C59: =SUMPRODUCT($C$39:$E$39,$C$22:$E$22)+$B$39*$B$22
A60: EBIT | B60: =SUMPRODUCT($C$38:$E$38,$C$24:$E$24) | C60: =SUMPRODUCT($C$39:$E$39,$C$24:$E$24)
A61: EBITDA | B61: =SUMPRODUCT($C$38:$E$38,$C$32:$E$32) | C61: =SUMPRODUCT($C$39:$E$39,$C$32:$E$32)
A62: Adj. EBITDA | B62: =SUMPRODUCT($C$38:$E$38,$C$33:$E$33) | C62: =SUMPRODUCT($C$39:$E$39,$C$33:$E$33)
A63: NOPAT | B63: =SUMPRODUCT($C$38:$E$38,$C$26:$E$26) | C63: =SUMPRODUCT($C$39:$E$39,$C$26:$E$26)
A64: Free cash flow to firm | B64: =SUMPRODUCT($C$38:$E$38,$C$31:$E$31) | C64: =SUMPRODUCT($C$39:$E$39,$C$31:$E$31)
A66: Valuation method | B66: Metric | C66: Multiple used | D66: Basis | E66: Metric at target date | F66: Value per share | G66: Weight | H66: Metric key | I66: Metric shown (stated per-share figure when used)
A67: DCF (cash flow to target date + terminal) | F67: =((B45)-$B$50-$B$51+$B$52)/$B$53 | G67: =Valuation!$B$65
A68: ="Multiple: "&Valuation!A71&" ("&Valuation!D71&")" | B68: =Valuation!A71 | C68: =IF(B68="FCF yield",(Valuation!B71)*(1-$B$8),(Valuation!B71)+IF(B68="EV/sales",0.1,1)*$B$6) | D68: =Valuation!D71 | E68: =IF(D68="ltm",CHOOSE(H68,$C$59,$C$60,$C$61,$C$62,$C$63,$C$64),CHOOSE(H68,$B$59,$B$60,$B$61,$B$62,$B$63,$B$64)) | F68: =IF(OR(B68="EV/EBITDA",B68="EV/sales",B68="EV/EBIT"),((C68*E68)-$B$50-$B$51+$B$52)/$B$53,IF(B68="P/E",IF(Valuation!F71<>"",C68*(Valuation!F71)*(1+$B$9),C68*(E68-$B$54)/$B$53),IF(Valuation!G71<>"",(Valuation!G71)*(1+$B$9)/C68,(E68-IF(Valuation!H71,$B$54,0))/C68/$B$53))+$B$52/$B$53) | G68: =Valuation!C71 | H68: =IF(B68="EV/sales",1,IF(B68="EV/EBIT",2,IF(B68="EV/EBITDA",IF(Valuation!E71="adjusted",4,3),IF(B68="P/E",5,6)))) | I68: =IF(AND(B68="P/E",Valuation!F71<>""),(Valuation!F71)*(1+$B$9),IF(AND(B68="FCF yield",Valuation!G71<>""),(Valuation!G71)*(1+$B$9),E68))
A69: ="Multiple: "&Valuation!A72&" ("&Valuation!D72&")" | B69: =Valuation!A72 | C69: =IF(B69="FCF yield",(Valuation!B72)*(1-$B$8),(Valuation!B72)+IF(B69="EV/sales",0.1,1)*$B$6) | D69: =Valuation!D72 | E69: =IF(D69="ltm",CHOOSE(H69,$C$59,$C$60,$C$61,$C$62,$C$63,$C$64),CHOOSE(H69,$B$59,$B$60,$B$61,$B$62,$B$63,$B$64)) | F69: =IF(OR(B69="EV/EBITDA",B69="EV/sales",B69="EV/EBIT"),((C69*E69)-$B$50-$B$51+$B$52)/$B$53,IF(B69="P/E",IF(Valuation!F72<>"",C69*(Valuation!F72)*(1+$B$9),C69*(E69-$B$54)/$B$53),IF(Valuation!G72<>"",(Valuation!G72)*(1+$B$9)/C69,(E69-IF(Valuation!H72,$B$54,0))/C69/$B$53))+$B$52/$B$53) | G69: =Valuation!C72 | H69: =IF(B69="EV/sales",1,IF(B69="EV/EBIT",2,IF(B69="EV/EBITDA",IF(Valuation!E72="adjusted",4,3),IF(B69="P/E",5,6)))) | I69: =IF(AND(B69="P/E",Valuation!F72<>""),(Valuation!F72)*(1+$B$9),IF(AND(B69="FCF yield",Valuation!G72<>""),(Valuation!G72)*(1+$B$9),E69))
A70: ="Multiple: "&Valuation!A73&" ("&Valuation!D73&")" | B70: =Valuation!A73 | C70: =IF(B70="FCF yield",(Valuation!B73)*(1-$B$8),(Valuation!B73)+IF(B70="EV/sales",0.1,1)*$B$6) | D70: =Valuation!D73 | E70: =IF(D70="ltm",CHOOSE(H70,$C$59,$C$60,$C$61,$C$62,$C$63,$C$64),CHOOSE(H70,$B$59,$B$60,$B$61,$B$62,$B$63,$B$64)) | F70: =IF(OR(B70="EV/EBITDA",B70="EV/sales",B70="EV/EBIT"),((C70*E70)-$B$50-$B$51+$B$52)/$B$53,IF(B70="P/E",IF(Valuation!F73<>"",C70*(Valuation!F73)*(1+$B$9),C70*(E70-$B$54)/$B$53),IF(Valuation!G73<>"",(Valuation!G73)*(1+$B$9)/C70,(E70-IF(Valuation!H73,$B$54,0))/C70/$B$53))+$B$52/$B$53) | G70: =Valuation!C73 | H70: =IF(B70="EV/sales",1,IF(B70="EV/EBIT",2,IF(B70="EV/EBITDA",IF(Valuation!E73="adjusted",4,3),IF(B70="P/E",5,6)))) | I70: =IF(AND(B70="P/E",Valuation!F73<>""),(Valuation!F73)*(1+$B$9),IF(AND(B70="FCF yield",Valuation!G73<>""),(Valuation!G73)*(1+$B$9),E70))
A71: Value per share at target date (weighted methods) | F71: =SUMPRODUCT(F67:F70,G67:G70)/SUM(G67:G70)
A129: Segment build (model_engine.seg_build): revenue and EBIT are the segment sums plus corporate EBIT
A130: Segment | B130: Base | C130: =Model!E5 | D130: =Model!F5 | E130: =Model!G5
A131: Product: revenue growth | C131: =Model!E12+$B$4 | D131: =Model!F12+$B$4 | E131: =Model!G12+$B$4
A132: Product: revenue | B132: =Valuation!$B$90 | C132: =B132*(1+C131) | D132: =C132*(1+D131) | E132: =D132*(1+E131)
A133: Product: EBIT margin | C133: =Model!E14+$B$5 | D133: =Model!F14+$B$5 | E133: =Model!G14+$B$5
A134: Product: EBIT | C134: =C132*C133 | D134: =D132*D133 | E134: =E132*E133
A135: Installation, service and electricity: revenue growth | C135: =Model!E16+$B$4 | D135: =Model!F16+$B$4 | E135: =Model!G16+$B$4
A136: Installation, service and electricity: revenue | B136: =Valuation!$B$91 | C136: =B136*(1+C135) | D136: =C136*(1+D135) | E136: =D136*(1+E135)
A137: Installation, service and electricity: EBIT margin | C137: =Model!E18+$B$5 | D137: =Model!F18+$B$5 | E137: =Model!G18+$B$5
A138: Installation, service and electricity: EBIT | C138: =C136*C137 | D138: =D136*D137 | E138: =E136*E137
A139: Total segment revenue | C139: =C132+C136 | D139: =D132+D136 | E139: =E132+E136
A140: Total segment EBIT | C140: =C134+C138 | D140: =D134+D138 | E140: =E134+E138
A141: Corporate / unallocated EBIT | C141: =Model!E21 | D141: =Model!F21 | E141: =Model!G21
A142: EBIT (segments + corporate) | C142: =C140+C141 | D142: =D140+D141 | E142: =E140+E141

Sheet Calc - bear
A1: BE engine calculation: bear scenario
A2: Machinery behind the Valuation and Distribution tabs; drivers come from Model, assumptions from Valuation.
A4: Scenario Growth Δ | B4: =N(Valuation!C85)
A5: Scenario Margin Δ | B5: =N(Valuation!D85)
A6: Scenario Multiple Δ (turns) | B6: =N(Valuation!E85)
A7: Scenario WACC Δ | B7: =N(Valuation!F85)
A8: Scenario Multiple %Δ | B8: =N(Valuation!G85)
A9: Scenario Stated EPS/FCF %Δ | B9: =N(Valuation!H85)
A10: Scenario Custom %Δ | B10: =N(Valuation!I85)
A12: WACC | B12: =Valuation!$B$52+B7
A13: Years from last FY end to target date | B13: =(Valuation!$B$46-Valuation!$B$50)/365.25
A14: Years from last FY end to balance date | B14: =(Valuation!$B$56-Valuation!$B$50)/365.25
A15: Years from last FY end to share count date | B15: =(Valuation!$B$62-Valuation!$B$50)/365.25
A16: Projected years | B16: 3
A18: Projection | B18: Base | C18: =Model!E5 | D18: =Model!F5 | E18: =Model!G5
A19: Year index | B19: 0 | C19: 1 | D19: 2 | E19: 3
A20: Period end | C20: =Valuation!$B$50+ROUND(365.25*C19,0) | D20: =Valuation!$B$50+ROUND(365.25*D19,0) | E20: =Valuation!$B$50+ROUND(365.25*E19,0)
A21: Revenue growth | C21: =C22/B22-1 | D21: =D22/C22-1 | E21: =E22/D22-1
A22: Revenue | B22: =Valuation!$B$51 | C22: =C139 | D22: =D139 | E22: =E139
A23: EBIT margin | C23: =C24/C22 | D23: =D24/D22 | E23: =E24/E22
A24: EBIT | C24: =C142 | D24: =D142 | E24: =E142
A25: Tax rate | C25: =Model!E63 | D25: =Model!F63 | E25: =Model!G63
A26: NOPAT | C26: =C24*(1-C25) | D26: =D24*(1-D25) | E26: =E24*(1-E25)
A27: D&A | C27: =C22*(Model!E64) | D27: =D22*(Model!F64) | E27: =E22*(Model!G64)
A28: Capex | C28: =C22*(Model!E65+$B$250) | D28: =D22*(Model!F65+$B$251) | E28: =E22*(Model!G65)
A29: Working capital increase | C29: =(Model!E66)*(C22-B22) | D29: =(Model!F66)*(D22-C22) | E29: =(Model!G66)*(E22-D22)
A30: Stock comp | C30: =C22*(Model!E67) | D30: =D22*(Model!F67) | E30: =E22*(Model!G67)
A31: Free cash flow to firm | C31: =C26+C27-C28-C29-IF(AND(Valuation!$B$48="adjusted",Valuation!$B$49="cost"),C30*(1-C25),0) | D31: =D26+D27-D28-D29-IF(AND(Valuation!$B$48="adjusted",Valuation!$B$49="cost"),D30*(1-D25),0) | E31: =E26+E27-E28-E29-IF(AND(Valuation!$B$48="adjusted",Valuation!$B$49="cost"),E30*(1-E25),0)
A32: EBITDA | C32: =C24+C27 | D32: =D24+D27 | E32: =E24+E27
A33: Adj. EBITDA | C33: =C24+C27+C22*(Model!E71) | D33: =D24+D27+D22*(Model!F71) | E33: =E24+E27+E22*(Model!G71)
A34: Shareholder returns + other uses | C34: =C22*Model!E69+Model!E68+Model!E70 | D34: =D22*Model!F69+Model!F68+Model!F70 | E34: =E22*Model!G69+Model!G68+Model!G70
A35: Share of year after target date | C35: =IF(C19<=$B$13,0,C19-MAX(C19-1,$B$13)) | D35: =IF(D19<=$B$13,0,D19-MAX(D19-1,$B$13)) | E35: =IF(E19<=$B$13,0,E19-MAX(E19-1,$B$13))
A36: PV at target date of FCFF | C36: =IF(C35=0,0,C31*C35/(1+$B$12)^(C19-$B$13)) | D36: =IF(D35=0,0,D31*D35/(1+$B$12)^(D19-$B$13)) | E36: =IF(E35=0,0,E31*E35/(1+$B$12)^(E19-$B$13))
A37: Overlap: balance date to target date | C37: =MAX(0,MIN(C19,$B$13)-MAX(C19-1,$B$14)) | D37: =MAX(0,MIN(D19,$B$13)-MAX(D19-1,$B$14)) | E37: =MAX(0,MIN(E19,$B$13)-MAX(E19-1,$B$14))
A38: NTM weight at target date | C38: =MAX(0,MIN(C19,$B$13+1)-MAX(C19-1,$B$13)) | D38: =MAX(0,MIN(D19,$B$13+1)-MAX(D19-1,$B$13)) | E38: =MAX(0,MIN(E19,$B$13+1)-MAX(E19-1,$B$13))
A39: LTM weight at target date | B39: =MAX(0,MIN(0,$B$13)-MAX(-1,$B$13-1)) | C39: =MAX(0,MIN(C19,$B$13)-MAX(C19-1,$B$13-1)) | D39: =MAX(0,MIN(D19,$B$13)-MAX(D19-1,$B$13-1)) | E39: =MAX(0,MIN(E19,$B$13)-MAX(E19-1,$B$13-1))
A41: Value at the target date
A42: PV of free cash flow after the target date | B42: =SUM($C$36:$E$36)
A43: Terminal value at final year | B43: =IF(Valuation!$B$53="exit_multiple",Valuation!$B$55*E32,E31*(1+Valuation!$B$54)/($B$12-Valuation!$B$54))
A44: PV of terminal value at target date | B44: =B43/(1+$B$12)^($B$16-$B$13)
A45: DCF enterprise value at target date | B45: =B42+B44
A46: Terminal value share of DCF | B46: =B44/B45
A47: Free cash flow earned, balance date to target date | B47: =SUMPRODUCT($C$37:$E$37,$C$31:$E$31)
A48: Shareholder returns + other uses paid | B48: =SUMPRODUCT($C$37:$E$37,$C$34:$E$34)
A49: Interest drag on net debt | B49: =Valuation!$B$59*(1-$C$25)*MAX(Valuation!$B$57,0)*MAX($B$13-$B$14,0)
A50: Net debt at target date | B50: =IF(Valuation!$B$60="",Valuation!$B$57-B47+B49+B48,Valuation!$B$60)
A51: Minority interests | B51: =Valuation!$B$58
A52: Adjustments (probability-weighted) | B52: =0
A53: Diluted shares at target date (M) | B53: =IF(Valuation!$B$64="",Valuation!$B$61*(1+Valuation!$B$63)^MAX($B$13-$B$15,0),Valuation!$B$64)
A54: After-tax interest on target-date net debt | B54: =Valuation!$B$59*(1-$C$25)*MAX(B50,0)
A55: Check: WACC vs terminal growth | B55: =IF(AND(Valuation!$B$53<>"exit_multiple",$B$12<=Valuation!$B$54+0.01),"WACC must exceed terminal growth by 1 point","ok")
A56: Check: projection length | B56: =IF(OR($B$13>=$B$16-1,$B$13+1>$B$16),"add projected years past the target date","ok")
A58: Metric at target date | B58: Next 12 months | C58: Last 12 months
A59: Revenue | B59: =SUMPRODUCT($C$38:$E$38,$C$22:$E$22) | C59: =SUMPRODUCT($C$39:$E$39,$C$22:$E$22)+$B$39*$B$22
A60: EBIT | B60: =SUMPRODUCT($C$38:$E$38,$C$24:$E$24) | C60: =SUMPRODUCT($C$39:$E$39,$C$24:$E$24)
A61: EBITDA | B61: =SUMPRODUCT($C$38:$E$38,$C$32:$E$32) | C61: =SUMPRODUCT($C$39:$E$39,$C$32:$E$32)
A62: Adj. EBITDA | B62: =SUMPRODUCT($C$38:$E$38,$C$33:$E$33) | C62: =SUMPRODUCT($C$39:$E$39,$C$33:$E$33)
A63: NOPAT | B63: =SUMPRODUCT($C$38:$E$38,$C$26:$E$26) | C63: =SUMPRODUCT($C$39:$E$39,$C$26:$E$26)
A64: Free cash flow to firm | B64: =SUMPRODUCT($C$38:$E$38,$C$31:$E$31) | C64: =SUMPRODUCT($C$39:$E$39,$C$31:$E$31)
A66: Valuation method | B66: Metric | C66: Multiple used | D66: Basis | E66: Metric at target date | F66: Value per share | G66: Weight | H66: Metric key | I66: Metric shown (stated per-share figure when used)
A67: DCF (cash flow to target date + terminal) | F67: =((B45)-$B$50-$B$51+$B$52)/$B$53 | G67: =Valuation!$B$65
A68: ="Multiple: "&Valuation!A71&" ("&Valuation!D71&")" | B68: =Valuation!A71 | C68: =IF(B68="FCF yield",(Valuation!B71)*(1-$B$8),(Valuation!B71)+IF(B68="EV/sales",0.1,1)*$B$6) | D68: =Valuation!D71 | E68: =IF(D68="ltm",CHOOSE(H68,$C$59,$C$60,$C$61,$C$62,$C$63,$C$64),CHOOSE(H68,$B$59,$B$60,$B$61,$B$62,$B$63,$B$64)) | F68: =IF(OR(B68="EV/EBITDA",B68="EV/sales",B68="EV/EBIT"),((C68*E68)-$B$50-$B$51+$B$52)/$B$53,IF(B68="P/E",IF(Valuation!F71<>"",C68*(Valuation!F71)*(1+$B$9),C68*(E68-$B$54)/$B$53),IF(Valuation!G71<>"",(Valuation!G71)*(1+$B$9)/C68,(E68-IF(Valuation!H71,$B$54,0))/C68/$B$53))+$B$52/$B$53) | G68: =Valuation!C71 | H68: =IF(B68="EV/sales",1,IF(B68="EV/EBIT",2,IF(B68="EV/EBITDA",IF(Valuation!E71="adjusted",4,3),IF(B68="P/E",5,6)))) | I68: =IF(AND(B68="P/E",Valuation!F71<>""),(Valuation!F71)*(1+$B$9),IF(AND(B68="FCF yield",Valuation!G71<>""),(Valuation!G71)*(1+$B$9),E68))
A69: ="Multiple: "&Valuation!A72&" ("&Valuation!D72&")" | B69: =Valuation!A72 | C69: =IF(B69="FCF yield",(Valuation!B72)*(1-$B$8),(Valuation!B72)+IF(B69="EV/sales",0.1,1)*$B$6) | D69: =Valuation!D72 | E69: =IF(D69="ltm",CHOOSE(H69,$C$59,$C$60,$C$61,$C$62,$C$63,$C$64),CHOOSE(H69,$B$59,$B$60,$B$61,$B$62,$B$63,$B$64)) | F69: =IF(OR(B69="EV/EBITDA",B69="EV/sales",B69="EV/EBIT"),((C69*E69)-$B$50-$B$51+$B$52)/$B$53,IF(B69="P/E",IF(Valuation!F72<>"",C69*(Valuation!F72)*(1+$B$9),C69*(E69-$B$54)/$B$53),IF(Valuation!G72<>"",(Valuation!G72)*(1+$B$9)/C69,(E69-IF(Valuation!H72,$B$54,0))/C69/$B$53))+$B$52/$B$53) | G69: =Valuation!C72 | H69: =IF(B69="EV/sales",1,IF(B69="EV/EBIT",2,IF(B69="EV/EBITDA",IF(Valuation!E72="adjusted",4,3),IF(B69="P/E",5,6)))) | I69: =IF(AND(B69="P/E",Valuation!F72<>""),(Valuation!F72)*(1+$B$9),IF(AND(B69="FCF yield",Valuation!G72<>""),(Valuation!G72)*(1+$B$9),E69))
A70: ="Multiple: "&Valuation!A73&" ("&Valuation!D73&")" | B70: =Valuation!A73 | C70: =IF(B70="FCF yield",(Valuation!B73)*(1-$B$8),(Valuation!B73)+IF(B70="EV/sales",0.1,1)*$B$6) | D70: =Valuation!D73 | E70: =IF(D70="ltm",CHOOSE(H70,$C$59,$C$60,$C$61,$C$62,$C$63,$C$64),CHOOSE(H70,$B$59,$B$60,$B$61,$B$62,$B$63,$B$64)) | F70: =IF(OR(B70="EV/EBITDA",B70="EV/sales",B70="EV/EBIT"),((C70*E70)-$B$50-$B$51+$B$52)/$B$53,IF(B70="P/E",IF(Valuation!F73<>"",C70*(Valuation!F73)*(1+$B$9),C70*(E70-$B$54)/$B$53),IF(Valuation!G73<>"",(Valuation!G73)*(1+$B$9)/C70,(E70-IF(Valuation!H73,$B$54,0))/C70/$B$53))+$B$52/$B$53) | G70: =Valuation!C73 | H70: =IF(B70="EV/sales",1,IF(B70="EV/EBIT",2,IF(B70="EV/EBITDA",IF(Valuation!E73="adjusted",4,3),IF(B70="P/E",5,6)))) | I70: =IF(AND(B70="P/E",Valuation!F73<>""),(Valuation!F73)*(1+$B$9),IF(AND(B70="FCF yield",Valuation!G73<>""),(Valuation!G73)*(1+$B$9),E70))
A71: Value per share at target date (weighted methods) | F71: =SUMPRODUCT(F67:F70,G67:G70)/SUM(G67:G70)
A129: Segment build (model_engine.seg_build): revenue and EBIT are the segment sums plus corporate EBIT
A130: Segment | B130: Base | C130: =Model!E5 | D130: =Model!F5 | E130: =Model!G5
A131: Product: revenue growth | C131: =Model!E12+$B$4+$B$252 | D131: =Model!F12+$B$4 | E131: =Model!G12+$B$4
A132: Product: revenue | B132: =Valuation!$B$90 | C132: =B132*(1+C131) | D132: =C132*(1+D131) | E132: =D132*(1+E131)
A133: Product: EBIT margin | C133: =Model!E14+$B$5+$B$253 | D133: =Model!F14+$B$5+$B$254 | E133: =Model!G14+$B$5+$B$255
A134: Product: EBIT | C134: =C132*C133 | D134: =D132*D133 | E134: =E132*E133
A135: Installation, service and electricity: revenue growth | C135: =Model!E16+$B$4 | D135: =Model!F16+$B$4 | E135: =Model!G16+$B$4
A136: Installation, service and electricity: revenue | B136: =Valuation!$B$91 | C136: =B136*(1+C135) | D136: =C136*(1+D135) | E136: =D136*(1+E135)
A137: Installation, service and electricity: EBIT margin | C137: =Model!E18+$B$5 | D137: =Model!F18+$B$5 | E137: =Model!G18+$B$5
A138: Installation, service and electricity: EBIT | C138: =C136*C137 | D138: =D136*D137 | E138: =E136*E137
A139: Total segment revenue | C139: =C132+C136 | D139: =D132+D136 | E139: =E132+E136
A140: Total segment EBIT | C140: =C134+C138 | D140: =D134+D138 | E140: =E134+E138
A141: Corporate / unallocated EBIT | C141: =Model!E21 | D141: =Model!F21 | E141: =Model!G21
A142: EBIT (segments + corporate) | C142: =C140+C141 | D142: =D140+D141 | E142: =E140+E141
A249: Driver scenario shifts: line-item changes model_drivers.py resolves from this scenario's driver deltas (added to the Model tab inputs)
A250: Capex % revenue, year 1 | B250: 0.0077537324
A251: Capex % revenue, year 2 | B251: 0.0054863258
A252: Product: revenue growth, year 1 | B252: -0.64676113
A253: Product: EBIT margin, year 1 | B253: -0.090830935
A254: Product: EBIT margin, year 2 | B254: -0.081282051
A255: Product: EBIT margin, year 3 | B255: -0.073487179

Sheet Calc - base
A1: BE engine calculation: base scenario
A2: Machinery behind the Valuation and Distribution tabs; drivers come from Model, assumptions from Valuation.
A4: Scenario Growth Δ | B4: =N(Valuation!C86)
A5: Scenario Margin Δ | B5: =N(Valuation!D86)
A6: Scenario Multiple Δ (turns) | B6: =N(Valuation!E86)
A7: Scenario WACC Δ | B7: =N(Valuation!F86)
A8: Scenario Multiple %Δ | B8: =N(Valuation!G86)
A9: Scenario Stated EPS/FCF %Δ | B9: =N(Valuation!H86)
A10: Scenario Custom %Δ | B10: =N(Valuation!I86)
A12: WACC | B12: =Valuation!$B$52+B7
A13: Years from last FY end to target date | B13: =(Valuation!$B$46-Valuation!$B$50)/365.25
A14: Years from last FY end to balance date | B14: =(Valuation!$B$56-Valuation!$B$50)/365.25
A15: Years from last FY end to share count date | B15: =(Valuation!$B$62-Valuation!$B$50)/365.25
A16: Projected years | B16: 3
A18: Projection | B18: Base | C18: =Model!E5 | D18: =Model!F5 | E18: =Model!G5
A19: Year index | B19: 0 | C19: 1 | D19: 2 | E19: 3
A20: Period end | C20: =Valuation!$B$50+ROUND(365.25*C19,0) | D20: =Valuation!$B$50+ROUND(365.25*D19,0) | E20: =Valuation!$B$50+ROUND(365.25*E19,0)
A21: Revenue growth | C21: =C22/B22-1 | D21: =D22/C22-1 | E21: =E22/D22-1
A22: Revenue | B22: =Valuation!$B$51 | C22: =C139 | D22: =D139 | E22: =E139
A23: EBIT margin | C23: =C24/C22 | D23: =D24/D22 | E23: =E24/E22
A24: EBIT | C24: =C142 | D24: =D142 | E24: =E142
A25: Tax rate | C25: =Model!E63 | D25: =Model!F63 | E25: =Model!G63
A26: NOPAT | C26: =C24*(1-C25) | D26: =D24*(1-D25) | E26: =E24*(1-E25)
A27: D&A | C27: =C22*(Model!E64) | D27: =D22*(Model!F64) | E27: =E22*(Model!G64)
A28: Capex | C28: =C22*(Model!E65) | D28: =D22*(Model!F65) | E28: =E22*(Model!G65)
A29: Working capital increase | C29: =(Model!E66)*(C22-B22) | D29: =(Model!F66)*(D22-C22) | E29: =(Model!G66)*(E22-D22)
A30: Stock comp | C30: =C22*(Model!E67) | D30: =D22*(Model!F67) | E30: =E22*(Model!G67)
A31: Free cash flow to firm | C31: =C26+C27-C28-C29-IF(AND(Valuation!$B$48="adjusted",Valuation!$B$49="cost"),C30*(1-C25),0) | D31: =D26+D27-D28-D29-IF(AND(Valuation!$B$48="adjusted",Valuation!$B$49="cost"),D30*(1-D25),0) | E31: =E26+E27-E28-E29-IF(AND(Valuation!$B$48="adjusted",Valuation!$B$49="cost"),E30*(1-E25),0)
A32: EBITDA | C32: =C24+C27 | D32: =D24+D27 | E32: =E24+E27
A33: Adj. EBITDA | C33: =C24+C27+C22*(Model!E71) | D33: =D24+D27+D22*(Model!F71) | E33: =E24+E27+E22*(Model!G71)
A34: Shareholder returns + other uses | C34: =C22*Model!E69+Model!E68+Model!E70 | D34: =D22*Model!F69+Model!F68+Model!F70 | E34: =E22*Model!G69+Model!G68+Model!G70
A35: Share of year after target date | C35: =IF(C19<=$B$13,0,C19-MAX(C19-1,$B$13)) | D35: =IF(D19<=$B$13,0,D19-MAX(D19-1,$B$13)) | E35: =IF(E19<=$B$13,0,E19-MAX(E19-1,$B$13))
A36: PV at target date of FCFF | C36: =IF(C35=0,0,C31*C35/(1+$B$12)^(C19-$B$13)) | D36: =IF(D35=0,0,D31*D35/(1+$B$12)^(D19-$B$13)) | E36: =IF(E35=0,0,E31*E35/(1+$B$12)^(E19-$B$13))
A37: Overlap: balance date to target date | C37: =MAX(0,MIN(C19,$B$13)-MAX(C19-1,$B$14)) | D37: =MAX(0,MIN(D19,$B$13)-MAX(D19-1,$B$14)) | E37: =MAX(0,MIN(E19,$B$13)-MAX(E19-1,$B$14))
A38: NTM weight at target date | C38: =MAX(0,MIN(C19,$B$13+1)-MAX(C19-1,$B$13)) | D38: =MAX(0,MIN(D19,$B$13+1)-MAX(D19-1,$B$13)) | E38: =MAX(0,MIN(E19,$B$13+1)-MAX(E19-1,$B$13))
A39: LTM weight at target date | B39: =MAX(0,MIN(0,$B$13)-MAX(-1,$B$13-1)) | C39: =MAX(0,MIN(C19,$B$13)-MAX(C19-1,$B$13-1)) | D39: =MAX(0,MIN(D19,$B$13)-MAX(D19-1,$B$13-1)) | E39: =MAX(0,MIN(E19,$B$13)-MAX(E19-1,$B$13-1))
A41: Value at the target date
A42: PV of free cash flow after the target date | B42: =SUM($C$36:$E$36)
A43: Terminal value at final year | B43: =IF(Valuation!$B$53="exit_multiple",Valuation!$B$55*E32,E31*(1+Valuation!$B$54)/($B$12-Valuation!$B$54))
A44: PV of terminal value at target date | B44: =B43/(1+$B$12)^($B$16-$B$13)
A45: DCF enterprise value at target date | B45: =B42+B44
A46: Terminal value share of DCF | B46: =B44/B45
A47: Free cash flow earned, balance date to target date | B47: =SUMPRODUCT($C$37:$E$37,$C$31:$E$31)
A48: Shareholder returns + other uses paid | B48: =SUMPRODUCT($C$37:$E$37,$C$34:$E$34)
A49: Interest drag on net debt | B49: =Valuation!$B$59*(1-$C$25)*MAX(Valuation!$B$57,0)*MAX($B$13-$B$14,0)
A50: Net debt at target date | B50: =IF(Valuation!$B$60="",Valuation!$B$57-B47+B49+B48,Valuation!$B$60)
A51: Minority interests | B51: =Valuation!$B$58
A52: Adjustments (probability-weighted) | B52: =0
A53: Diluted shares at target date (M) | B53: =IF(Valuation!$B$64="",Valuation!$B$61*(1+Valuation!$B$63)^MAX($B$13-$B$15,0),Valuation!$B$64)
A54: After-tax interest on target-date net debt | B54: =Valuation!$B$59*(1-$C$25)*MAX(B50,0)
A55: Check: WACC vs terminal growth | B55: =IF(AND(Valuation!$B$53<>"exit_multiple",$B$12<=Valuation!$B$54+0.01),"WACC must exceed terminal growth by 1 point","ok")
A56: Check: projection length | B56: =IF(OR($B$13>=$B$16-1,$B$13+1>$B$16),"add projected years past the target date","ok")
A58: Metric at target date | B58: Next 12 months | C58: Last 12 months
A59: Revenue | B59: =SUMPRODUCT($C$38:$E$38,$C$22:$E$22) | C59: =SUMPRODUCT($C$39:$E$39,$C$22:$E$22)+$B$39*$B$22
A60: EBIT | B60: =SUMPRODUCT($C$38:$E$38,$C$24:$E$24) | C60: =SUMPRODUCT($C$39:$E$39,$C$24:$E$24)
A61: EBITDA | B61: =SUMPRODUCT($C$38:$E$38,$C$32:$E$32) | C61: =SUMPRODUCT($C$39:$E$39,$C$32:$E$32)
A62: Adj. EBITDA | B62: =SUMPRODUCT($C$38:$E$38,$C$33:$E$33) | C62: =SUMPRODUCT($C$39:$E$39,$C$33:$E$33)
A63: NOPAT | B63: =SUMPRODUCT($C$38:$E$38,$C$26:$E$26) | C63: =SUMPRODUCT($C$39:$E$39,$C$26:$E$26)
A64: Free cash flow to firm | B64: =SUMPRODUCT($C$38:$E$38,$C$31:$E$31) | C64: =SUMPRODUCT($C$39:$E$39,$C$31:$E$31)
A66: Valuation method | B66: Metric | C66: Multiple used | D66: Basis | E66: Metric at target date | F66: Value per share | G66: Weight | H66: Metric key | I66: Metric shown (stated per-share figure when used)
A67: DCF (cash flow to target date + terminal) | F67: =((B45)-$B$50-$B$51+$B$52)/$B$53 | G67: =Valuation!$B$65
A68: ="Multiple: "&Valuation!A71&" ("&Valuation!D71&")" | B68: =Valuation!A71 | C68: =IF(B68="FCF yield",(Valuation!B71)*(1-$B$8),(Valuation!B71)+IF(B68="EV/sales",0.1,1)*$B$6) | D68: =Valuation!D71 | E68: =IF(D68="ltm",CHOOSE(H68,$C$59,$C$60,$C$61,$C$62,$C$63,$C$64),CHOOSE(H68,$B$59,$B$60,$B$61,$B$62,$B$63,$B$64)) | F68: =IF(OR(B68="EV/EBITDA",B68="EV/sales",B68="EV/EBIT"),((C68*E68)-$B$50-$B$51+$B$52)/$B$53,IF(B68="P/E",IF(Valuation!F71<>"",C68*(Valuation!F71)*(1+$B$9),C68*(E68-$B$54)/$B$53),IF(Valuation!G71<>"",(Valuation!G71)*(1+$B$9)/C68,(E68-IF(Valuation!H71,$B$54,0))/C68/$B$53))+$B$52/$B$53) | G68: =Valuation!C71 | H68: =IF(B68="EV/sales",1,IF(B68="EV/EBIT",2,IF(B68="EV/EBITDA",IF(Valuation!E71="adjusted",4,3),IF(B68="P/E",5,6)))) | I68: =IF(AND(B68="P/E",Valuation!F71<>""),(Valuation!F71)*(1+$B$9),IF(AND(B68="FCF yield",Valuation!G71<>""),(Valuation!G71)*(1+$B$9),E68))
A69: ="Multiple: "&Valuation!A72&" ("&Valuation!D72&")" | B69: =Valuation!A72 | C69: =IF(B69="FCF yield",(Valuation!B72)*(1-$B$8),(Valuation!B72)+IF(B69="EV/sales",0.1,1)*$B$6) | D69: =Valuation!D72 | E69: =IF(D69="ltm",CHOOSE(H69,$C$59,$C$60,$C$61,$C$62,$C$63,$C$64),CHOOSE(H69,$B$59,$B$60,$B$61,$B$62,$B$63,$B$64)) | F69: =IF(OR(B69="EV/EBITDA",B69="EV/sales",B69="EV/EBIT"),((C69*E69)-$B$50-$B$51+$B$52)/$B$53,IF(B69="P/E",IF(Valuation!F72<>"",C69*(Valuation!F72)*(1+$B$9),C69*(E69-$B$54)/$B$53),IF(Valuation!G72<>"",(Valuation!G72)*(1+$B$9)/C69,(E69-IF(Valuation!H72,$B$54,0))/C69/$B$53))+$B$52/$B$53) | G69: =Valuation!C72 | H69: =IF(B69="EV/sales",1,IF(B69="EV/EBIT",2,IF(B69="EV/EBITDA",IF(Valuation!E72="adjusted",4,3),IF(B69="P/E",5,6)))) | I69: =IF(AND(B69="P/E",Valuation!F72<>""),(Valuation!F72)*(1+$B$9),IF(AND(B69="FCF yield",Valuation!G72<>""),(Valuation!G72)*(1+$B$9),E69))
A70: ="Multiple: "&Valuation!A73&" ("&Valuation!D73&")" | B70: =Valuation!A73 | C70: =IF(B70="FCF yield",(Valuation!B73)*(1-$B$8),(Valuation!B73)+IF(B70="EV/sales",0.1,1)*$B$6) | D70: =Valuation!D73 | E70: =IF(D70="ltm",CHOOSE(H70,$C$59,$C$60,$C$61,$C$62,$C$63,$C$64),CHOOSE(H70,$B$59,$B$60,$B$61,$B$62,$B$63,$B$64)) | F70: =IF(OR(B70="EV/EBITDA",B70="EV/sales",B70="EV/EBIT"),((C70*E70)-$B$50-$B$51+$B$52)/$B$53,IF(B70="P/E",IF(Valuation!F73<>"",C70*(Valuation!F73)*(1+$B$9),C70*(E70-$B$54)/$B$53),IF(Valuation!G73<>"",(Valuation!G73)*(1+$B$9)/C70,(E70-IF(Valuation!H73,$B$54,0))/C70/$B$53))+$B$52/$B$53) | G70: =Valuation!C73 | H70: =IF(B70="EV/sales",1,IF(B70="EV/EBIT",2,IF(B70="EV/EBITDA",IF(Valuation!E73="adjusted",4,3),IF(B70="P/E",5,6)))) | I70: =IF(AND(B70="P/E",Valuation!F73<>""),(Valuation!F73)*(1+$B$9),IF(AND(B70="FCF yield",Valuation!G73<>""),(Valuation!G73)*(1+$B$9),E70))
A71: Value per share at target date (weighted methods) | F71: =SUMPRODUCT(F67:F70,G67:G70)/SUM(G67:G70)
A129: Segment build (model_engine.seg_build): revenue and EBIT are the segment sums plus corporate EBIT
A130: Segment | B130: Base | C130: =Model!E5 | D130: =Model!F5 | E130: =Model!G5
A131: Product: revenue growth | C131: =Model!E12+$B$4 | D131: =Model!F12+$B$4 | E131: =Model!G12+$B$4
A132: Product: revenue | B132: =Valuation!$B$90 | C132: =B132*(1+C131) | D132: =C132*(1+D131) | E132: =D132*(1+E131)
A133: Product: EBIT margin | C133: =Model!E14+$B$5 | D133: =Model!F14+$B$5 | E133: =Model!G14+$B$5
A134: Product: EBIT | C134: =C132*C133 | D134: =D132*D133 | E134: =E132*E133
A135: Installation, service and electricity: revenue growth | C135: =Model!E16+$B$4 | D135: =Model!F16+$B$4 | E135: =Model!G16+$B$4
A136: Installation, service and electricity: revenue | B136: =Valuation!$B$91 | C136: =B136*(1+C135) | D136: =C136*(1+D135) | E136: =D136*(1+E135)
A137: Installation, service and electricity: EBIT margin | C137: =Model!E18+$B$5 | D137: =Model!F18+$B$5 | E137: =Model!G18+$B$5
A138: Installation, service and electricity: EBIT | C138: =C136*C137 | D138: =D136*D137 | E138: =E136*E137
A139: Total segment revenue | C139: =C132+C136 | D139: =D132+D136 | E139: =E132+E136
A140: Total segment EBIT | C140: =C134+C138 | D140: =D134+D138 | E140: =E134+E138
A141: Corporate / unallocated EBIT | C141: =Model!E21 | D141: =Model!F21 | E141: =Model!G21
A142: EBIT (segments + corporate) | C142: =C140+C141 | D142: =D140+D141 | E142: =E140+E141

Sheet Calc - bull
A1: BE engine calculation: bull scenario
A2: Machinery behind the Valuation and Distribution tabs; drivers come from Model, assumptions from Valuation.
A4: Scenario Growth Δ | B4: =N(Valuation!C87)
A5: Scenario Margin Δ | B5: =N(Valuation!D87)
A6: Scenario Multiple Δ (turns) | B6: =N(Valuation!E87)
A7: Scenario WACC Δ | B7: =N(Valuation!F87)
A8: Scenario Multiple %Δ | B8: =N(Valuation!G87)
A9: Scenario Stated EPS/FCF %Δ | B9: =N(Valuation!H87)
A10: Scenario Custom %Δ | B10: =N(Valuation!I87)
A12: WACC | B12: =Valuation!$B$52+B7
A13: Years from last FY end to target date | B13: =(Valuation!$B$46-Valuation!$B$50)/365.25
A14: Years from last FY end to balance date | B14: =(Valuation!$B$56-Valuation!$B$50)/365.25
A15: Years from last FY end to share count date | B15: =(Valuation!$B$62-Valuation!$B$50)/365.25
A16: Projected years | B16: 3
A18: Projection | B18: Base | C18: =Model!E5 | D18: =Model!F5 | E18: =Model!G5
A19: Year index | B19: 0 | C19: 1 | D19: 2 | E19: 3
A20: Period end | C20: =Valuation!$B$50+ROUND(365.25*C19,0) | D20: =Valuation!$B$50+ROUND(365.25*D19,0) | E20: =Valuation!$B$50+ROUND(365.25*E19,0)
A21: Revenue growth | C21: =C22/B22-1 | D21: =D22/C22-1 | E21: =E22/D22-1
A22: Revenue | B22: =Valuation!$B$51 | C22: =C139 | D22: =D139 | E22: =E139
A23: EBIT margin | C23: =C24/C22 | D23: =D24/D22 | E23: =E24/E22
A24: EBIT | C24: =C142 | D24: =D142 | E24: =E142
A25: Tax rate | C25: =Model!E63 | D25: =Model!F63 | E25: =Model!G63
A26: NOPAT | C26: =C24*(1-C25) | D26: =D24*(1-D25) | E26: =E24*(1-E25)
A27: D&A | C27: =C22*(Model!E64) | D27: =D22*(Model!F64) | E27: =E22*(Model!G64)
A28: Capex | C28: =C22*(Model!E65+$B$250) | D28: =D22*(Model!F65+$B$251) | E28: =E22*(Model!G65)
A29: Working capital increase | C29: =(Model!E66)*(C22-B22) | D29: =(Model!F66)*(D22-C22) | E29: =(Model!G66)*(E22-D22)
A30: Stock comp | C30: =C22*(Model!E67) | D30: =D22*(Model!F67) | E30: =E22*(Model!G67)
A31: Free cash flow to firm | C31: =C26+C27-C28-C29-IF(AND(Valuation!$B$48="adjusted",Valuation!$B$49="cost"),C30*(1-C25),0) | D31: =D26+D27-D28-D29-IF(AND(Valuation!$B$48="adjusted",Valuation!$B$49="cost"),D30*(1-D25),0) | E31: =E26+E27-E28-E29-IF(AND(Valuation!$B$48="adjusted",Valuation!$B$49="cost"),E30*(1-E25),0)
A32: EBITDA | C32: =C24+C27 | D32: =D24+D27 | E32: =E24+E27
A33: Adj. EBITDA | C33: =C24+C27+C22*(Model!E71) | D33: =D24+D27+D22*(Model!F71) | E33: =E24+E27+E22*(Model!G71)
A34: Shareholder returns + other uses | C34: =C22*Model!E69+Model!E68+Model!E70 | D34: =D22*Model!F69+Model!F68+Model!F70 | E34: =E22*Model!G69+Model!G68+Model!G70
A35: Share of year after target date | C35: =IF(C19<=$B$13,0,C19-MAX(C19-1,$B$13)) | D35: =IF(D19<=$B$13,0,D19-MAX(D19-1,$B$13)) | E35: =IF(E19<=$B$13,0,E19-MAX(E19-1,$B$13))
A36: PV at target date of FCFF | C36: =IF(C35=0,0,C31*C35/(1+$B$12)^(C19-$B$13)) | D36: =IF(D35=0,0,D31*D35/(1+$B$12)^(D19-$B$13)) | E36: =IF(E35=0,0,E31*E35/(1+$B$12)^(E19-$B$13))
A37: Overlap: balance date to target date | C37: =MAX(0,MIN(C19,$B$13)-MAX(C19-1,$B$14)) | D37: =MAX(0,MIN(D19,$B$13)-MAX(D19-1,$B$14)) | E37: =MAX(0,MIN(E19,$B$13)-MAX(E19-1,$B$14))
A38: NTM weight at target date | C38: =MAX(0,MIN(C19,$B$13+1)-MAX(C19-1,$B$13)) | D38: =MAX(0,MIN(D19,$B$13+1)-MAX(D19-1,$B$13)) | E38: =MAX(0,MIN(E19,$B$13+1)-MAX(E19-1,$B$13))
A39: LTM weight at target date | B39: =MAX(0,MIN(0,$B$13)-MAX(-1,$B$13-1)) | C39: =MAX(0,MIN(C19,$B$13)-MAX(C19-1,$B$13-1)) | D39: =MAX(0,MIN(D19,$B$13)-MAX(D19-1,$B$13-1)) | E39: =MAX(0,MIN(E19,$B$13)-MAX(E19-1,$B$13-1))
A41: Value at the target date
A42: PV of free cash flow after the target date | B42: =SUM($C$36:$E$36)
A43: Terminal value at final year | B43: =IF(Valuation!$B$53="exit_multiple",Valuation!$B$55*E32,E31*(1+Valuation!$B$54)/($B$12-Valuation!$B$54))
A44: PV of terminal value at target date | B44: =B43/(1+$B$12)^($B$16-$B$13)
A45: DCF enterprise value at target date | B45: =B42+B44
A46: Terminal value share of DCF | B46: =B44/B45
A47: Free cash flow earned, balance date to target date | B47: =SUMPRODUCT($C$37:$E$37,$C$31:$E$31)
A48: Shareholder returns + other uses paid | B48: =SUMPRODUCT($C$37:$E$37,$C$34:$E$34)
A49: Interest drag on net debt | B49: =Valuation!$B$59*(1-$C$25)*MAX(Valuation!$B$57,0)*MAX($B$13-$B$14,0)
A50: Net debt at target date | B50: =IF(Valuation!$B$60="",Valuation!$B$57-B47+B49+B48,Valuation!$B$60)
A51: Minority interests | B51: =Valuation!$B$58
A52: Adjustments (probability-weighted) | B52: =0
A53: Diluted shares at target date (M) | B53: =IF(Valuation!$B$64="",Valuation!$B$61*(1+Valuation!$B$63)^MAX($B$13-$B$15,0),Valuation!$B$64)
A54: After-tax interest on target-date net debt | B54: =Valuation!$B$59*(1-$C$25)*MAX(B50,0)
A55: Check: WACC vs terminal growth | B55: =IF(AND(Valuation!$B$53<>"exit_multiple",$B$12<=Valuation!$B$54+0.01),"WACC must exceed terminal growth by 1 point","ok")
A56: Check: projection length | B56: =IF(OR($B$13>=$B$16-1,$B$13+1>$B$16),"add projected years past the target date","ok")
A58: Metric at target date | B58: Next 12 months | C58: Last 12 months
A59: Revenue | B59: =SUMPRODUCT($C$38:$E$38,$C$22:$E$22) | C59: =SUMPRODUCT($C$39:$E$39,$C$22:$E$22)+$B$39*$B$22
A60: EBIT | B60: =SUMPRODUCT($C$38:$E$38,$C$24:$E$24) | C60: =SUMPRODUCT($C$39:$E$39,$C$24:$E$24)
A61: EBITDA | B61: =SUMPRODUCT($C$38:$E$38,$C$32:$E$32) | C61: =SUMPRODUCT($C$39:$E$39,$C$32:$E$32)
A62: Adj. EBITDA | B62: =SUMPRODUCT($C$38:$E$38,$C$33:$E$33) | C62: =SUMPRODUCT($C$39:$E$39,$C$33:$E$33)
A63: NOPAT | B63: =SUMPRODUCT($C$38:$E$38,$C$26:$E$26) | C63: =SUMPRODUCT($C$39:$E$39,$C$26:$E$26)
A64: Free cash flow to firm | B64: =SUMPRODUCT($C$38:$E$38,$C$31:$E$31) | C64: =SUMPRODUCT($C$39:$E$39,$C$31:$E$31)
A66: Valuation method | B66: Metric | C66: Multiple used | D66: Basis | E66: Metric at target date | F66: Value per share | G66: Weight | H66: Metric key | I66: Metric shown (stated per-share figure when used)
A67: DCF (cash flow to target date + terminal) | F67: =((B45)-$B$50-$B$51+$B$52)/$B$53 | G67: =Valuation!$B$65
A68: ="Multiple: "&Valuation!A71&" ("&Valuation!D71&")" | B68: =Valuation!A71 | C68: =IF(B68="FCF yield",(Valuation!B71)*(1-$B$8),(Valuation!B71)+IF(B68="EV/sales",0.1,1)*$B$6) | D68: =Valuation!D71 | E68: =IF(D68="ltm",CHOOSE(H68,$C$59,$C$60,$C$61,$C$62,$C$63,$C$64),CHOOSE(H68,$B$59,$B$60,$B$61,$B$62,$B$63,$B$64)) | F68: =IF(OR(B68="EV/EBITDA",B68="EV/sales",B68="EV/EBIT"),((C68*E68)-$B$50-$B$51+$B$52)/$B$53,IF(B68="P/E",IF(Valuation!F71<>"",C68*(Valuation!F71)*(1+$B$9),C68*(E68-$B$54)/$B$53),IF(Valuation!G71<>"",(Valuation!G71)*(1+$B$9)/C68,(E68-IF(Valuation!H71,$B$54,0))/C68/$B$53))+$B$52/$B$53) | G68: =Valuation!C71 | H68: =IF(B68="EV/sales",1,IF(B68="EV/EBIT",2,IF(B68="EV/EBITDA",IF(Valuation!E71="adjusted",4,3),IF(B68="P/E",5,6)))) | I68: =IF(AND(B68="P/E",Valuation!F71<>""),(Valuation!F71)*(1+$B$9),IF(AND(B68="FCF yield",Valuation!G71<>""),(Valuation!G71)*(1+$B$9),E68))
A69: ="Multiple: "&Valuation!A72&" ("&Valuation!D72&")" | B69: =Valuation!A72 | C69: =IF(B69="FCF yield",(Valuation!B72)*(1-$B$8),(Valuation!B72)+IF(B69="EV/sales",0.1,1)*$B$6) | D69: =Valuation!D72 | E69: =IF(D69="ltm",CHOOSE(H69,$C$59,$C$60,$C$61,$C$62,$C$63,$C$64),CHOOSE(H69,$B$59,$B$60,$B$61,$B$62,$B$63,$B$64)) | F69: =IF(OR(B69="EV/EBITDA",B69="EV/sales",B69="EV/EBIT"),((C69*E69)-$B$50-$B$51+$B$52)/$B$53,IF(B69="P/E",IF(Valuation!F72<>"",C69*(Valuation!F72)*(1+$B$9),C69*(E69-$B$54)/$B$53),IF(Valuation!G72<>"",(Valuation!G72)*(1+$B$9)/C69,(E69-IF(Valuation!H72,$B$54,0))/C69/$B$53))+$B$52/$B$53) | G69: =Valuation!C72 | H69: =IF(B69="EV/sales",1,IF(B69="EV/EBIT",2,IF(B69="EV/EBITDA",IF(Valuation!E72="adjusted",4,3),IF(B69="P/E",5,6)))) | I69: =IF(AND(B69="P/E",Valuation!F72<>""),(Valuation!F72)*(1+$B$9),IF(AND(B69="FCF yield",Valuation!G72<>""),(Valuation!G72)*(1+$B$9),E69))
A70: ="Multiple: "&Valuation!A73&" ("&Valuation!D73&")" | B70: =Valuation!A73 | C70: =IF(B70="FCF yield",(Valuation!B73)*(1-$B$8),(Valuation!B73)+IF(B70="EV/sales",0.1,1)*$B$6) | D70: =Valuation!D73 | E70: =IF(D70="ltm",CHOOSE(H70,$C$59,$C$60,$C$61,$C$62,$C$63,$C$64),CHOOSE(H70,$B$59,$B$60,$B$61,$B$62,$B$63,$B$64)) | F70: =IF(OR(B70="EV/EBITDA",B70="EV/sales",B70="EV/EBIT"),((C70*E70)-$B$50-$B$51+$B$52)/$B$53,IF(B70="P/E",IF(Valuation!F73<>"",C70*(Valuation!F73)*(1+$B$9),C70*(E70-$B$54)/$B$53),IF(Valuation!G73<>"",(Valuation!G73)*(1+$B$9)/C70,(E70-IF(Valuation!H73,$B$54,0))/C70/$B$53))+$B$52/$B$53) | G70: =Valuation!C73 | H70: =IF(B70="EV/sales",1,IF(B70="EV/EBIT",2,IF(B70="EV/EBITDA",IF(Valuation!E73="adjusted",4,3),IF(B70="P/E",5,6)))) | I70: =IF(AND(B70="P/E",Valuation!F73<>""),(Valuation!F73)*(1+$B$9),IF(AND(B70="FCF yield",Valuation!G73<>""),(Valuation!G73)*(1+$B$9),E70))
A71: Value per share at target date (weighted methods) | F71: =SUMPRODUCT(F67:F70,G67:G70)/SUM(G67:G70)
A129: Segment build (model_engine.seg_build): revenue and EBIT are the segment sums plus corporate EBIT
A130: Segment | B130: Base | C130: =Model!E5 | D130: =Model!F5 | E130: =Model!G5
A131: Product: revenue growth | C131: =Model!E12+$B$4+$B$252 | D131: =Model!F12+$B$4 | E131: =Model!G12+$B$4
A132: Product: revenue | B132: =Valuation!$B$90 | C132: =B132*(1+C131) | D132: =C132*(1+D131) | E132: =D132*(1+E131)
A133: Product: EBIT margin | C133: =Model!E14+$B$5+$B$253 | D133: =Model!F14+$B$5+$B$254 | E133: =Model!G14+$B$5+$B$255
A134: Product: EBIT | C134: =C132*C133 | D134: =D132*D133 | E134: =E132*E133
A135: Installation, service and electricity: revenue growth | C135: =Model!E16+$B$4 | D135: =Model!F16+$B$4 | E135: =Model!G16+$B$4
A136: Installation, service and electricity: revenue | B136: =Valuation!$B$91 | C136: =B136*(1+C135) | D136: =C136*(1+D135) | E136: =D136*(1+E135)
A137: Installation, service and electricity: EBIT margin | C137: =Model!E18+$B$5 | D137: =Model!F18+$B$5 | E137: =Model!G18+$B$5
A138: Installation, service and electricity: EBIT | C138: =C136*C137 | D138: =D136*D137 | E138: =E136*E137
A139: Total segment revenue | C139: =C132+C136 | D139: =D132+D136 | E139: =E132+E136
A140: Total segment EBIT | C140: =C134+C138 | D140: =D134+D138 | E140: =E134+E138
A141: Corporate / unallocated EBIT | C141: =Model!E21 | D141: =Model!F21 | E141: =Model!G21
A142: EBIT (segments + corporate) | C142: =C140+C141 | D142: =D140+D141 | E142: =E140+E141
A249: Driver scenario shifts: line-item changes model_drivers.py resolves from this scenario's driver deltas (added to the Model tab inputs)
A250: Capex % revenue, year 1 | B250: -0.0041220043
A251: Capex % revenue, year 2 | B251: -0.0028924112
A252: Product: revenue growth, year 1 | B252: 0.51740891
A253: Product: EBIT margin, year 1 | B253: 0.040415468
A254: Product: EBIT margin, year 2 | B254: 0.035641026
A255: Product: EBIT margin, year 3 | B255: 0.03174359

Sheet Agents
A1: BE: each forecaster's own assumption set through the same engine (from model_engine.json, not live)
A3: Set | B3: Research target (12m) | C3: Median | D3: 25th pct | E3: 75th pct | F3: WACC | G3: Y1 growth | H3: Y1 margin | I3: Terminal growth | J3: DCF weight | K3: Years | L3: Multiples | M3: Supervisor's note
A4: supervisor | B4: 185.83898 | C4: 184.28836 | D4: 119.82003 | E4: 249.35895 | J4: 0 | K4: 3 | L4: P/E 40.0 (ntm); EV/EBITDA 26.0 (ntm); EV/sales 5.5 (ntm)
A5: agent_1 | M5: engine error: no model_inputs found
A6: agent_2 | M6: engine error: no model_inputs found
A7: agent_3 | M7: engine error: no model_inputs found
A8: agent_4 | M8: engine error: no model_inputs found
A9: agent_5 | M9: engine error: no model_inputs found

Sheet Sources
A1: BE: where each input comes from (source numbers point to the list below; F ids to the SEC fact table)
A3: Input | B3: Value | C3: Basis | D3: Sources | E3: SEC fact ids | F3: Derivation
A4: driver:product_gw | B4: Energy Server product volume recognized (acceptances): 0.494 -> 1.24/1.8/2.5 GW per year (estimate) | C4: estimate | D4: 6, 13, 14, 16, 17, 18, 24 | F4: Base = FY2025 product revenue $1,531.3M / product_asp $3,100/kW = 0.494 GW (Bloom does not disclose acceptances, so the base is derived). FY2026 = YTD product $2,662.3M + Q4 ~$1,300M = $3,962M / $3,195 = 1.24 GW. Q4 ~$1,300M is a judgment: Q3 $1,073.6M x ~1.21, faster than the Q2->Q3 step of 1.148 (at 1.148 Q4 would be ~$1,232M and FY2026 ~$3,895M = 1.22 GW), for the 2 GW line coming on stream; total FY2026 $4.52B sits inside the raised $4.4-4.6B guide. 36Kr's 1.14-1.25 GW was tied to the superseded $3.9-4.2B guide, so it is context, not a check. FY2027 = 1.80 GW: 90% of the 2 GW run-rate reached at end-2026; 3% under the agents' FY2027 implied median 1.86 (1.78 / 1.80 / 1.86 / 1.88 / 1.88) because the full year runs at the 2 GW ceiling and Jupiter (2.4 GW) timing depends on the Dec 3, 2026 FERC decision (src 6) and the NM air permit. FY2028 = 2.50 GW = 83% of the 3 GW run-rate (factory_gw during 2027, decided by Kilian 2026-10-26), in line with the agents' FY2028 implied median 2.51 (their ~$9.0B revenue). spread = FY2027 views only.
A5: driver:product_asp | B5: Product revenue per kW recognized: 3100.0 -> 3195.0/3250.0/3250.0 $/kW (judgment estimate, flagged) | C5: estimate | D5: 13, 16, 24, 25 | F5: Judgment estimate (flagged, confidence low); no filing or cited source states a $/kW figure. Base FY2025 $3,100/kW is set, so base volume = $1,531.3M / 3,100 = 0.494 GW. FY2026 $3,195 = 3,100 x 1.031 (judgment: +3% for lead-time pricing during the turbine shortage), giving $3,962M / 3,195 = 1.24 GW. FY2027-28 $3,250 (+1.7%; judgment: big-order pricing, Oracle 2.4 GW and AEP 1 GW, 10-K src 16). Cross-check against the only third-party figure: 36Kr estimates ~308 MW shipped in Q2-2026 and assumes ASP down ~5% YoY; Q2 product revenue $935.4M / 308 MW = ~$3,040/kW (36Kr itself states no $/kW). The set's $3,195 is 5% above that and has +3% YoY where 36Kr assumes -5%. Variant at the 36Kr-implied $3,040/kW for FY2026-28 (FY2026 volume 1.30 GW for the same revenue): research target (12m) $168.99 (-9.1%); open judgment call for Kilian. Post-print FY2027 consensus revenue $7.05B (src 25) is 7.1% above the set's $6.55B. No agent states a $/kW figure.
A6: driver:product_gm | B6: Product gross margin (GAAP): 0.3516 -> 0.37/0.375/0.37 fraction (estimate) | C6: estimate | D6: 13, 14, 17, 18 | F6: Base = 538.4 / 1,531.3 = 35.16%. YTD-2026 = (2,662.3 - 1,690.2) / 2,662.3 = 36.5%; Q3 37.9%. FY2026 37.0% (Q4 ~38%). FY2027 37.5% on 2 GW scale. FY2028 37.0%: the new capacity and big-order pricing give back ~50bp. Agents state total non-GAAP GM ~34-35% (median 34.75%); this build gives total GAAP GM 34.4% FY2027 (~35.1% non-GAAP, +~0.7pt SBC in cost of revenue, src 14), inside their range.
A7: driver:opex | B7: GAAP operating expenses (R&D + S&M + G&A, incl. SBC): 514.6 -> 723.0/900.0/1060.0 $M (estimate) | C7: estimate | D7: 14, 17, 18 | E7: F10 | F7: Base = 587.4 - 72.8 = 514.6. FY2026 = YTD 518.4 + Q4 ~205 (Q3 +7%) = 723. FY2027 +24% and FY2028 +18% (headcount for 2x then 3x volume; R&D on new products): opex/revenue 16.0% -> 13.7% -> 11.8%. agent_3's 22%->24% non-GAAP operating margin: the build gives ~24% non-GAAP FY2027 (GAAP 20.7% + ~3.6pt SBC), so opex sits at its view.
A8: driver:factory_gw | B8: Fremont annual production capacity run-rate (year end): 1.0 -> 2.0/3.0/3.0 GW (estimate) | C8: estimate | D8: 15, 16 | E8: F46 | F8: Base 1 GW and FY2026 2 GW from the 10-K plan (reaffirmed in the Q3 release's 'invest ... to build the capabilities and capacity needed to scale', src 14). FY2027 3 GW: an estimate, not announced; needed for the agents' ~$9B FY2028 revenue (2.5 GW shipped at 83% utilization) and feasible in 6-9 months for ~$125M (10-K).
A9: base.revenue | B9: 2024.0 | C9: reported | D9: 17 | E9: F3 | F9: FY2025 total revenue $2,024.0M (Ex.99.1); XBRL F3 $2,001.6M is contract revenue only (excludes ~$22M of lease electricity).
A10: segment_build: Installation, service and electricity | B10: 492.7 -> 560 / 700 / 840; EBIT margin 6.7% / 8% / 9% | C10: estimate | D10: 17, 18, 13, 14 | F10: Base 204.1 + 228.3 + 60.35 (src 17). YTD-2026 389.9 (Q1 97.7, Q2 129.95, Q3 162.2) + Q4 ~170 = 560; +25% FY2027 and +20% FY2028 with the fleet; gross margin YTD (389.9-363.9)/389.9 = 6.7%, rising with service scale (FY2025 9.9%).
A11: tax_rate | B11: 5% / 10% / 15% | C11: estimate | D11: 15 | E11: F66, F73 | F11: YTD-2026 tax $2.7M on $524.3M pretax (0.5%) with NOLs; rising as NOLs are used. Variant: 21% from FY2027 cuts the P/E leg ~8%.
A12: da_pct_rev | B12: 1.3% / 1.3% / 1.4% | C12: estimate | D12: 14 | F12: Q3-2026 D&A $13.8M on $1,235.8M (1.1%); capacity adds lift it slightly.
A13: nwc_pct_incr_rev | B13: 20% / 15% / 15% | C13: estimate | D13: 14, 15 | E13: F39, F20 | F13: Contract assets $178.9M -> $792.8M and inventory $643.3M -> $927.7M in 9 months (src 14) on revenue +$1.8B annualized; YTD CFO $272.9M vs net income $521.5M.
A14: balance.net_debt | B14: 16.2 | C14: estimate | D14: 15 | E14: F75, F78, F79 | F14: Estimate (computed, not reported). 10-Q 2026-09-30 debt table (USD M, unpaid principal): 0% converts due Nov 2030 2,500.0 + 3.0% Green Notes due Jun 2029 22.771 + Korean JV 4.6% term loan 2.95 = 2,525.7; cash 2,486.7 (F75). The 2030 converts are carried as debt at principal (the value sits below their $194.97 conversion price). The 2029 Green Notes (conversion price $20.84, deep in the money) are treated as equity (their 1.09M shares are in shares.diluted_now), so their 22.8 is left out. Net debt = 2,500.0 + 2.95 - 2,486.7 = 16.2. The JV loan is counted once: F78 (2.95) and F79 ShortTermBorrowings (3.0) tag the same loan, the balance sheet's only current debt. Restricted cash (0.9 + 20.6) and financing obligations (42.8 + 142.2, sale-leaseback) are excluded. Cross-check: secfacts F83 -7.3 uses carrying values (2,476.4 + 3.0 - 2,486.7) with converts at carrying value and the JV loan counted twice.
A15: shares.diluted_now | B15: 312.4 | C15: estimate | D15: 14, 15 | E15: F81, F33 | F15: Estimate for converts-as-debt (computed, not reported). Shares outstanding 295.66M at 2026-10-19 (10-Q cover, F81) + 15.61M options and awards (Q3 treasury-method dilution, 10-Q Note 15 EPS table) + 1.09M if-converted shares of the 2029 Green Notes ($22.771M x 47.9795 per $1,000) = 312.4M. The 2030 notes' 12.82M shares ($2,500M x 5.129 per $1,000; 10-Q Note 8) are excluded because those notes are carried as debt. Cross-check: Q3 diluted weighted average 324.29M (F33; basic 294.76 + converts 13.92 + awards 15.61) - 12.82 = 311.47M. annual_change +1.5% for SBC dilution (estimate).
A16: horizon_multiples P/E | B16: 40.0 | C16: judgment | D16: 23 | F16: Whole-company peers GAAP P/E TTM median 39.9x (GEV 22.8, VRT 43.2, ETN 37.1, GNRC 42.7; src 23). 40x NTM GAAP at the horizon = peer trailing median for ~25-35% FY2029 growth vs peers ~10-20%. The agents' median ~40x sits on non-GAAP earnings, which is ~46x GAAP (40 / 0.87, SBC gap ~13%), so 40x GAAP is ~13% below the agents' multiple. Decided by Kilian 2026-10-26 (40x GAAP, with EV/sales 5.5x).
A17: horizon_multiples EV/EBITDA | B17: 26.0 | C17: judgment | D17: 23 | F17: Peer EV/EBITDA TTM: VRT 29.3x, GNRC 18.9x (median 24.1x; GEV, ETN and CAT not computable from their tags; CMI not built this run, src 23). 26x = +2x for growth.
A18: horizon_multiples EV/sales | B18: 5.5 | C18: judgment | D18: 23 | F18: Peer EV/sales TTM median 5.2x (GEV 5.0, VRT 6.5, ETN 5.4, GNRC 2.7; src 23). 5.5x on a ~24% EBITDA margin; agents used 7.5-10x (median 8x) on 2028 revenue, which at that margin is ~33x EBITDA, above every peer. Decided by Kilian 2026-10-26.
A20: # | B20: Source | C20: Date | D20: Link
A21: 1 | B21: New Mexico Denies Reconsideration of Project Jupiter Gas Pipeline (Pipeline & Gas Journal) | C21: 2026-07 | D21: https://pgjonline.com/news/2026/july/new-mexico-denies-reconsideration-of-project-jupiter-gas-pipeline
A22: 2 | B22: Commissioner of Public Lands letter re informal request for reconsideration (NM State Land Office) | C22: 2026-07-14 | D22: https://www.nmstatelands.org/wp-content/uploads/2026/07/2026-07-14-Letter-re-Informal-Request-for-Reconsideration_Final.pdf
A23: 3 | B23: NM state land commissioner rejects application for gas pipeline to power Project Jupiter data center (Source NM) | C23: 2026-03-31 | D23: https://sourcenm.com/2026/03/31/nm-state-land-commissioner-rejects-application-for-gas-pipeline-to-power-project-jupiter-data-center/
A24: 4 | B24: BLM issues rights-of-way for Green Chile Natural Gas Pipeline | C24: 2026-05-06 | D24: https://www.blm.gov/press-release/blm-issues-rights-way-green-chile-natural-gas-pipeline
A25: 5 | B25: Transwestern Pipeline Company; Notice of Availability of the EA for the Proposed Green Chile Project, docket CP26-80-000 (Federal Register 2026-18455, official GPO copy on govinfo) | C25: 2026-09-10 | D25: https://www.govinfo.gov/content/pkg/FR-2026-09-10/html/2026-18455.htm
A26: 6 | B26: Transwestern; Notice of Schedule for the EA for the Green Chile Project: EA Sep 4, 2026; 90-day federal authorization decision deadline Dec 3, 2026 (Federal Register 2026-15286, govinfo) | C26: 2026-07-29 | D26: https://www.govinfo.gov/content/pkg/FR-2026-07-29/html/2026-15286.htm
A27: 7 | B27: Energy Transfer's Green Chile Natural Gas Lateral Loses Fast Track, Delaying AI Fuel Supply (NGI) [not opened at the gate (405); not relied on] | C27: 2026 | D27: https://naturalgasintel.com/news/energy-transfers-green-chile-natural-gas-lateral-loses-fast-track-delaying-ai-fuel-supply/
A28: 8 | B28: Project Jupiter hearing examiner bows out: Max Shepherd recusal order dated Aug 22; Sep 14 hearing paused by the Supreme Court stay (Albuquerque Journal) | C28: 2026-08-24 | D28: https://www.abqjournal.com/news/project-jupiter-hearing-examiner-bows-out/3108469
A29: 9 | B29: New Mexico Supreme Court lifts stays on Project Jupiter; NMED must appoint a new hearing examiner (Albuquerque Journal) | C29: 2026-09-17 | D29: https://www.abqjournal.com/business/new-mexico-supreme-court-lifts-stays-on-project-jupiter-dealing-setback-to-opponents/3124024
A30: 10 | B30: Attorney general backs Project Jupiter court challenges (Organ Mountain News) | C30: 2026-09 | D30: https://www.organmountainnews.com/raul-torrez-project-jupiter-water-air-permitting-supreme-court-2026/
A31: 11 | B31: Oracle sends force majeure notice on its New Mexico Stargate data center (TechCrunch) | C31: 2026-09-24 | D31: https://techcrunch.com/2026/09/24/oracle-sends-force-majeure-notice-on-its-new-mexico-stargate-data-center/
A32: 12 | B32: Morgan Stanley says Bloom can withstand an Oracle project delay (TheStreet) [403 at the gate; unverified, not used by any figure] | C32: 2026-09 | D32: https://www.thestreet.com/investing/stocks/morgan-stanley-says-bloom-can-withstand-an-oracle-project-delay
... A47: 27 | B47: BE daily closes 2026-04-22 to 2026-10-23 (Twelve Data time series: close $288.70 on 2026-09-25, $163.75 on 2026-07-29, $193.30 on 2026-10-23) | C47: 2026-10-26 | D47: https://api.twelvedata.com/time_series?symbol=BE&interval=1day&start_date=2026-04-22&end_date=2026-10-24
A49: Fact id | B49: Figure | C49: Value | D49: Filing
A50: F1 | B50: revenue FY ending 2023-12-31 (us-gaap:RevenueFromContractWithCustomerExcludingAssessedTax) | C50: 1268782000 | D50: https://www.sec.gov/Archives/edgar/data/1664703/000162828026006516/
A51: F2 | B51: revenue FY ending 2024-12-31 (us-gaap:RevenueFromContractWithCustomerExcludingAssessedTax) | C51: 1441394000 | D51: https://www.sec.gov/Archives/edgar/data/1664703/000162828026006516/
A52: F3 | B52: revenue FY ending 2025-12-31 (us-gaap:RevenueFromContractWithCustomerExcludingAssessedTax) | C52: 2001614000 | D52: https://www.sec.gov/Archives/edgar/data/1664703/000162828026006516/
A53: F4 | B53: revenue YTD 2026-01-01 to 2026-09-30 | C53: 3038175000 | D53: https://www.sec.gov/Archives/edgar/data/1664703/000162828026066931/
A54: F5 | B54: revenue prior-year YTD 2025-01-01 to 2025-09-30 | C54: 1228849000 | D54: https://www.sec.gov/Archives/edgar/data/1664703/000162828026066931/
A55: F6 | B55: revenue TTM to 2026-09-30 | C55: 3810940000
A56: F7 | B56: revenue quarter 2026-07-01 to 2026-09-30 | C56: 1231028000 | D56: https://www.sec.gov/Archives/edgar/data/1664703/000162828026066931/
A57: F8 | B57: operating_income FY ending 2023-12-31 (us-gaap:OperatingIncomeLoss) | C57: -208907000 | D57: https://www.sec.gov/Archives/edgar/data/1664703/000162828026006516/
A58: F9 | B58: operating_income FY ending 2024-12-31 (us-gaap:OperatingIncomeLoss) | C58: 22909000 | D58: https://www.sec.gov/Archives/edgar/data/1664703/000162828026006516/
A59: F10 | B59: operating_income FY ending 2025-12-31 (us-gaap:OperatingIncomeLoss) | C59: 72802000 | D59: https://www.sec.gov/Archives/edgar/data/1664703/000162828026006516/
A60: F11 | B60: operating_income YTD 2026-01-01 to 2026-09-30 | C60: 479876000 | D60: https://www.sec.gov/Archives/edgar/data/1664703/000162828026066931/
A61: F12 | B61: operating_income prior-year YTD 2025-01-01 to 2025-09-30 | C61: -14727000 | D61: https://www.sec.gov/Archives/edgar/data/1664703/000162828026066931/
A62: F13 | B62: operating_income TTM to 2026-09-30 | C62: 567405000
A63: F14 | B63: operating_income quarter 2026-07-01 to 2026-09-30 | C63: 225449000 | D63: https://www.sec.gov/Archives/edgar/data/1664703/000162828026066931/
A64: F15 | B64: net_income FY ending 2023-12-31 (us-gaap:ProfitLoss) | C64: -307937000 | D64: https://www.sec.gov/Archives/edgar/data/1664703/000162828026006516/
A65: F16 | B65: net_income FY ending 2024-12-31 (us-gaap:ProfitLoss) | C65: -27203000 | D65: https://www.sec.gov/Archives/edgar/data/1664703/000162828026006516/
A66: F17 | B66: net_income FY ending 2025-12-31 (us-gaap:ProfitLoss) | C66: -87140000 | D66: https://www.sec.gov/Archives/edgar/data/1664703/000162828026006516/
A67: F18 | B67: net_income YTD 2026-01-01 to 2026-09-30 | C67: 521523000 | D67: https://www.sec.gov/Archives/edgar/data/1664703/000162828026066931/
A68: F19 | B68: net_income prior-year YTD 2025-01-01 to 2025-09-30 | C68: -88566000 | D68: https://www.sec.gov/Archives/edgar/data/1664703/000162828026066931/
A69: F20 | B69: net_income TTM to 2026-09-30 | C69: 522949000
A70: F21 | B70: net_income quarter 2026-07-01 to 2026-09-30 | C70: 248976000 | D70: https://www.sec.gov/Archives/edgar/data/1664703/000162828026066931/
A71: F22 | B71: eps_diluted FY ending 2023-12-31 (us-gaap:EarningsPerShareDiluted) | C71: -1.42 | D71: https://www.sec.gov/Archives/edgar/data/1664703/000162828026006516/
A72: F23 | B72: eps_diluted FY ending 2024-12-31 (us-gaap:EarningsPerShareDiluted) | C72: -0.13 | D72: https://www.sec.gov/Archives/edgar/data/1664703/000162828026006516/
A73: F24 | B73: eps_diluted FY ending 2025-12-31 (us-gaap:EarningsPerShareDiluted) | C73: -0.37 | D73: https://www.sec.gov/Archives/edgar/data/1664703/000162828026006516/
A74: F25 | B74: eps_diluted YTD 2026-01-01 to 2026-09-30 | C74: 1.64 | D74: https://www.sec.gov/Archives/edgar/data/1664703/000162828026066931/
A75: F26 | B75: eps_diluted prior-year YTD 2025-01-01 to 2025-09-30 | C75: -0.38 | D75: https://www.sec.gov/Archives/edgar/data/1664703/000162828026066931/
A76: F27 | B76: eps_diluted quarter 2026-07-01 to 2026-09-30 | C76: 0.78 | D76: https://www.sec.gov/Archives/edgar/data/1664703/000162828026066931/
A77: F28 | B77: diluted_shares_wavg FY ending 2023-12-31 (us-gaap:WeightedAverageNumberOfDilutedSharesOutstanding) | C77: 212681000 | D77: https://www.sec.gov/Archives/edgar/data/1664703/000162828026006516/
A78: F29 | B78: diluted_shares_wavg FY ending 2024-12-31 (us-gaap:WeightedAverageNumberOfDilutedSharesOutstanding) | C78: 227365000 | D78: https://www.sec.gov/Archives/edgar/data/1664703/000162828026006516/
A79: F30 | B79: diluted_shares_wavg FY ending 2025-12-31 (us-gaap:WeightedAverageNumberOfDilutedSharesOutstanding) | C79: 240402000 | D79: https://www.sec.gov/Archives/edgar/data/1664703/000162828026006516/
A80: F31 | B80: diluted_shares_wavg YTD 2026-01-01 to 2026-09-30 | C80: 323307000 | D80: https://www.sec.gov/Archives/edgar/data/1664703/000162828026066931/
A81: F32 | B81: diluted_shares_wavg prior-year YTD 2025-01-01 to 2025-09-30 | C81: 232579000 | D81: https://www.sec.gov/Archives/edgar/data/1664703/000162828026066931/
... A87: F38 | B87: cfo prior-year YTD 2025-01-01 to 2025-09-30 | C87: -304124000 | D87: https://www.sec.gov/Archives/edgar/data/1664703/000162828026066931/
A88: F39 | B88: cfo TTM to 2026-09-30 | C88: 690968000
A89: F40 | B89: cfo quarter 2026-01-01 to 2026-03-31 | C89: 73610000 | D89: https://www.sec.gov/Archives/edgar/data/1664703/000162828026028021/
A90: F41 | B90: capex FY ending 2023-12-31 (us-gaap:PaymentsToAcquirePropertyPlantAndEquipment) | C90: 83739000 | D90: https://www.sec.gov/Archives/edgar/data/1664703/000162828026006516/
A91: F42 | B91: capex FY ending 2024-12-31 (us-gaap:PaymentsToAcquirePropertyPlantAndEquipment) | C91: 58852000 | D91: https://www.sec.gov/Archives/edgar/data/1664703/000162828026006516/
A92: F43 | B92: capex FY ending 2025-12-31 (us-gaap:PaymentsToAcquirePropertyPlantAndEquipment) | C92: 56759000 | D92: https://www.sec.gov/Archives/edgar/data/1664703/000162828026006516/
A93: F44 | B93: capex YTD 2026-01-01 to 2026-09-30 | C93: 231310000 | D93: https://www.sec.gov/Archives/edgar/data/1664703/000162828026066931/
A94: F45 | B94: capex prior-year YTD 2025-01-01 to 2025-09-30 | C94: 33805000 | D94: https://www.sec.gov/Archives/edgar/data/1664703/000162828026066931/
A95: F46 | B95: capex TTM to 2026-09-30 | C95: 254264000
A96: F47 | B96: capex quarter 2026-01-01 to 2026-03-31 | C96: 26182000 | D96: https://www.sec.gov/Archives/edgar/data/1664703/000162828026028021/
A97: F48 | B97: dividends_paid FY ending 2023-12-31 (us-gaap:PaymentsOfDividends) | C97: 0 | D97: https://www.sec.gov/Archives/edgar/data/1664703/000162828026006516/
A98: F49 | B98: dividends_paid FY ending 2024-12-31 (us-gaap:PaymentsOfDividends) | C98: 1468000 | D98: https://www.sec.gov/Archives/edgar/data/1664703/000162828026006516/
A99: F50 | B99: dividends_paid FY ending 2025-12-31 (us-gaap:PaymentsOfDividends) | C99: 947000 | D99: https://www.sec.gov/Archives/edgar/data/1664703/000162828026006516/
A100: F51 | B100: dividends_paid YTD 2026-01-01 to 2026-09-30 | C100: 925000 | D100: https://www.sec.gov/Archives/edgar/data/1664703/000162828026066931/
A101: F52 | B101: dividends_paid prior-year YTD 2025-01-01 to 2025-09-30 | C101: 947000 | D101: https://www.sec.gov/Archives/edgar/data/1664703/000162828026066931/
A102: F53 | B102: dividends_paid TTM to 2026-09-30 | C102: 925000
A103: F54 | B103: interest_expense FY ending 2023-12-31 (us-gaap:InterestExpenseNonoperating) | C103: 108299000 | D103: https://www.sec.gov/Archives/edgar/data/1664703/000162828026006516/
A104: F55 | B104: interest_expense FY ending 2024-12-31 (us-gaap:InterestExpenseNonoperating) | C104: 62636000 | D104: https://www.sec.gov/Archives/edgar/data/1664703/000162828026006516/
A105: F56 | B105: interest_expense FY ending 2025-12-31 (us-gaap:InterestExpenseNonoperating) | C105: 53888000 | D105: https://www.sec.gov/Archives/edgar/data/1664703/000162828026006516/
A106: F57 | B106: interest_expense YTD 2026-01-01 to 2026-09-30 | C106: 25035000 | D106: https://www.sec.gov/Archives/edgar/data/1664703/000162828026066931/
A107: F58 | B107: interest_expense prior-year YTD 2025-01-01 to 2025-09-30 | C107: 43241000 | D107: https://www.sec.gov/Archives/edgar/data/1664703/000162828026066931/
A108: F59 | B108: interest_expense TTM to 2026-09-30 | C108: 35682000
A109: F60 | B109: interest_expense quarter 2026-07-01 to 2026-09-30 | C109: 7525000 | D109: https://www.sec.gov/Archives/edgar/data/1664703/000162828026066931/
A110: F61 | B110: income_tax FY ending 2023-12-31 (us-gaap:IncomeTaxExpenseBenefit) | C110: 1894000 | D110: https://www.sec.gov/Archives/edgar/data/1664703/000162828026006516/
A111: F62 | B111: income_tax FY ending 2024-12-31 (us-gaap:IncomeTaxExpenseBenefit) | C111: 846000 | D111: https://www.sec.gov/Archives/edgar/data/1664703/000162828026006516/
A112: F63 | B112: income_tax FY ending 2025-12-31 (us-gaap:IncomeTaxExpenseBenefit) | C112: 2736000 | D112: https://www.sec.gov/Archives/edgar/data/1664703/000162828026006516/
A113: F64 | B113: income_tax YTD 2026-01-01 to 2026-09-30 | C113: 2732000 | D113: https://www.sec.gov/Archives/edgar/data/1664703/000162828026066931/
A114: F65 | B114: income_tax prior-year YTD 2025-01-01 to 2025-09-30 | C114: 1784000 | D114: https://www.sec.gov/Archives/edgar/data/1664703/000162828026066931/
A115: F66 | B115: income_tax TTM to 2026-09-30 | C115: 3684000
A116: F67 | B116: income_tax quarter 2026-07-01 to 2026-09-30 | C116: 817000 | D116: https://www.sec.gov/Archives/edgar/data/1664703/000162828026066931/
A117: F68 | B117: pretax_income FY ending 2023-12-31 (us-gaap:IncomeLossFromContinuingOperationsBeforeIncomeTaxesExtraordinaryItemsNoncontrollingInterest) | C117: -306043000 | D117: https://www.sec.gov/Archives/edgar/data/1664703/000162828026006516/
A118: F69 | B118: pretax_income FY ending 2024-12-31 (us-gaap:IncomeLossFromContinuingOperationsBeforeIncomeTaxesExtraordinaryItemsNoncontrollingInterest) | C118: -26357000 | D118: https://www.sec.gov/Archives/edgar/data/1664703/000162828026006516/
A119: F70 | B119: pretax_income FY ending 2025-12-31 (us-gaap:IncomeLossFromContinuingOperationsBeforeIncomeTaxesExtraordinaryItemsNoncontrollingInterest) | C119: -84404000 | D119: https://www.sec.gov/Archives/edgar/data/1664703/000162828026006516/
A120: F71 | B120: pretax_income YTD 2026-01-01 to 2026-09-30 | C120: 524255000 | D120: https://www.sec.gov/Archives/edgar/data/1664703/000162828026066931/
A121: F72 | B121: pretax_income prior-year YTD 2025-01-01 to 2025-09-30 | C121: -86782000 | D121: https://www.sec.gov/Archives/edgar/data/1664703/000162828026066931/
A122: F73 | B122: pretax_income TTM to 2026-09-30 | C122: 526633000
...
