Workbook

Sheet Summary
A1: NFLX standard model (trial) · research run 2026-10-23
A2: The supervisor's reconciled assumption set as a live model. Trial: shown beside the blended page target, not used for trade levels until its weight is decided. Edit blue cells on Model (drivers) and Valuation (assumptions).
A3: Price target box | B3: Value
A4: Live price | B4: =IFERROR(GOOGLEFINANCE("NFLX","price"),Valuation!$B$66)
A5: Price as of | B5: =NOW()
A6: Model target (12-month median) | B6: =Distribution!$B$13
A7: Upside to model target from live price | B7: =B6/B4-1
A8: Research target (12m) (no scenario deltas) | B8: =Valuation!$D$6
A9: Probability-weighted mean | B9: =Distribution!$B$10
A10: 10th percentile | B10: =Distribution!$B$14
A11: 25th percentile | B11: =Distribution!$B$15
A12: 75th percentile | B12: =Distribution!$B$16
A13: 90th percentile | B13: =Distribution!$B$17
A14: Target date | B14: =Valuation!$B$44
A15: Price at the run | B15: =Valuation!$B$66
A16: Blended page target (options 67% + agents 33%, not live) | B16: 72.4507
A17: Supervisor research target (12m) (its own methods) | B17: 76.22
A18: Thesis break price (supervisor) | B18: 48
A19: Supervisor confidence | B19: low
A21: Key estimates | B21: FY2025A | C21: =Model!E5 | D21: =Model!F5
A22: Net sales | B22: =IF(Model!D11="","",Model!D11) | C22: =Model!E11 | D22: =Model!F11
A23: % YoY | B23: =IF(Model!D12="","",Model!D12) | C23: =Model!E12 | D23: =Model!F12
A24: Pretax margin | B24: =IF(Model!D22="","",Model!D22) | C24: =Model!E22 | D24: =Model!F22
A25: Diluted EPS (model) | B25: =IF(Model!D29="","",Model!D29) | C25: =Model!E29 | D25: =Model!F29
A26: % YoY | B26: =IF(Model!D30="","",Model!D30) | C26: =Model!E30 | D26: =Model!F30
A27: Free cash flow to firm | B27: =IF(Model!D39="","",Model!D39) | C27: =Model!E39 | D27: =Model!F39
A28: Consensus: EPS (Zacks consensus (pre-print)) | D28: 3.8
A30: Valuation method | B30: Value per share | C30: Weight
A31: =Valuation!A4 | B31: =Valuation!D4 | C31: =Valuation!E4
A32: =Valuation!A5 | B32: =Valuation!D5 | C32: =Valuation!E5
A34: Scenario | B34: Probability | C34: Value at target date | D34: What has to happen
A35: =Distribution!A4 | B35: =Distribution!B4 | C35: =Distribution!C4 | D35: =Distribution!D4
A36: =Distribution!A5 | B36: =Distribution!B5 | C36: =Distribution!C5 | D36: =Distribution!D5
A37: =Distribution!A6 | B37: =Distribution!B6 | C37: =Distribution!C6 | D37: =Distribution!D6
A39: Price at target date | B39: Probability above
A40: =ROUND(Valuation!$B$66*0.7,0) | B40: =SUMPRODUCT(Distribution!$B$4:$B$6,1-NORMSDIST((LN(A40)-LN(Distribution!$C$4:$C$6))/Distribution!$B$9))
A41: =ROUND(Valuation!$B$66*0.8,0) | B41: =SUMPRODUCT(Distribution!$B$4:$B$6,1-NORMSDIST((LN(A41)-LN(Distribution!$C$4:$C$6))/Distribution!$B$9))
A42: =ROUND(Valuation!$B$66*0.9,0) | B42: =SUMPRODUCT(Distribution!$B$4:$B$6,1-NORMSDIST((LN(A42)-LN(Distribution!$C$4:$C$6))/Distribution!$B$9))
A43: =ROUND(Valuation!$B$66*1.0,0) | B43: =SUMPRODUCT(Distribution!$B$4:$B$6,1-NORMSDIST((LN(A43)-LN(Distribution!$C$4:$C$6))/Distribution!$B$9))
A44: =ROUND(Valuation!$B$66*1.1,0) | B44: =SUMPRODUCT(Distribution!$B$4:$B$6,1-NORMSDIST((LN(A44)-LN(Distribution!$C$4:$C$6))/Distribution!$B$9))
A45: =ROUND(Valuation!$B$66*1.2,0) | B45: =SUMPRODUCT(Distribution!$B$4:$B$6,1-NORMSDIST((LN(A45)-LN(Distribution!$C$4:$C$6))/Distribution!$B$9))
A46: =ROUND(Valuation!$B$66*1.3,0) | B46: =SUMPRODUCT(Distribution!$B$4:$B$6,1-NORMSDIST((LN(A46)-LN(Distribution!$C$4:$C$6))/Distribution!$B$9))
A47: =ROUND(Valuation!$B$66*1.5,0) | B47: =SUMPRODUCT(Distribution!$B$4:$B$6,1-NORMSDIST((LN(A47)-LN(Distribution!$C$4:$C$6))/Distribution!$B$9))
A49: Model checks | B49: Status
A50: Scenario probabilities sum to 100% | B50: =IF(ABS(Distribution!B8-1)<0.005,"ok","FLAG: "&TEXT(Distribution!B8,"0.0%"))
A51: WACC exceeds terminal growth by 1 point or more | B51: =IF('Calc - research target (12m)'!B55="ok","ok","FLAG")
A52: Projection runs a full year past the target date | B52: =IF('Calc - research target (12m)'!B56="ok","ok","FLAG")
A53: Method weights add up to more than zero | B53: =IF(SUM(Valuation!E4:E5)>0,"ok","FLAG")
A54: Terminal value under 85% of the DCF | B54: =IF('Calc - research target (12m)'!B46<0.85,"ok","note: "&TEXT('Calc - research target (12m)'!B46,"0%")&" of the DCF is terminal value")
A55: Matches the engine run at publication (target, research target (12m)) | B55: =IF(AND(ABS(Distribution!$B$13-75.4724)<0.01,ABS(Valuation!$D$6-76.2197)<0.01),"ok","inputs edited since publication")
A56: All checks | B56: =IF(COUNTIF(B50:B55,"ok")=6,"all ok",6-COUNTIF(B50:B55,"ok")&" to look at")

Sheet Model
A1: NFLX: annual model, base case
A2: (M of US dollars except per share; fiscal years named by the calendar year they end in)
A3: Blue = input · black = formula · green = link to another tab · actuals from SEC filings (fact ids in the last column, links on Sources)
A5: Fiscal year | B5: FY2023A | C5: FY2024A | D5: FY2025A | E5: FY2026E | F5: FY2027E | G5: FY2028E | H5: Source / note
A6: Period end | B6: 45291 | C6: 45657 | D6: 46022 | E6: =IF(DAY(Valuation!$B$48+1)=1,EOMONTH(Valuation!$B$48,12*E7),EDATE(Valuation!$B$48,12*E7)) | F6: =IF(DAY(Valuation!$B$48+1)=1,EOMONTH(Valuation!$B$48,12*F7),EDATE(Valuation!$B$48,12*F7)) | G6: =IF(DAY(Valuation!$B$48+1)=1,EOMONTH(Valuation!$B$48,12*G7),EDATE(Valuation!$B$48,12*G7))
A7: Projection year | B7: -2 | C7: -1 | D7: 0 | E7: 1 | F7: 2 | G7: 3
A10: Sales
A11: Net sales | B11: 33723.297 | C11: 39000.966 | D11: 45183.036 | E11: =Valuation!$B$49*(1+E48) | F11: =E11*(1+F48) | G11: =F11*(1+G48) | H11: SEC XBRL F1, F2, F3
A12: % YoY | C12: =IF(OR(C11="",B11="",B11=0),"",C11/B11-1) | D12: =IF(OR(D11="",C11="",C11=0),"",D11/C11-1) | E12: =E11/Valuation!$B$49-1 | F12: =F11/E11-1 | G12: =G11/F11-1
A14: Operating profit
A15: EBIT (operating income) | E15: =E11*E49 | F15: =F11*F49 | G15: =G11*G49
A16: EBIT margin | E16: =E15/E11 | F16: =F15/F11 | G16: =G15/G11
A17: D&A | B17: 356.947 | C17: 328.914 | D17: 333.389 | E17: =E11*E51 | F17: =F11*F51 | G17: =G11*G51 | H17: SEC XBRL F34, F35, F36
A18: EBITDA | E18: =E15+E17 | F18: =F15+F17 | G18: =G15+G17
A19: EBITDA margin | E19: =E18/E11 | F19: =F18/F11 | G19: =G18/G11
A20: Net interest income / (expense) | E20: =-Valuation!$B$57*Valuation!$B$55 | F20: =-Valuation!$B$57*E45 | G20: =-Valuation!$B$57*F45 | H20: rate x prior year-end net debt (memo roll)
A21: Pretax income | B21: 6205.405 | C21: 9965.657 | D21: 12722.552 | E21: =E15+E20 | F21: =F15+F20 | G21: =G15+G20 | H21: SEC XBRL F83, F84, F85
A22: Pretax margin | B22: =B21/B11 | C22: =C21/C11 | D22: =D21/D11 | E22: =E21/E11 | F22: =F21/F11 | G22: =G21/G11
A23: Income tax | B23: 797.415 | C23: 1254.026 | D23: 1741.351 | E23: =E21*E50 | F23: =F21*F50 | G23: =G21*G50 | H23: SEC XBRL F76, F77, F78
A24: Effective tax rate | B24: =B23/B21 | C24: =C23/C21 | D24: =D23/D21 | E24: =E23/E21 | F24: =F23/F21 | G24: =G23/G21
A25: Net income | B25: 5407.99 | C25: 8711.631 | D25: 10981.201 | E25: =E21-E23 | F25: =F21-F23 | G25: =G21-G23 | H25: SEC XBRL F15, F16, F17
A26: % YoY | C26: =IF(OR(C25="",B25="",B25=0),"",C25/B25-1) | D26: =IF(OR(D25="",C25="",C25=0),"",D25/C25-1) | E26: =IF(OR(D25="",D25=0),"",E25/D25-1) | F26: =IF(OR(E25="",E25=0),"",F25/E25-1) | G26: =IF(OR(F25="",F25=0),"",G25/F25-1)
A27: Diluted shares (M, average) | B27: 4494.966 | C27: 4392.608 | D27: 4343.863 | E27: =Valuation!$B$59*(1+Valuation!$B$61)^(E7-0.5-((Valuation!$B$60-Valuation!$B$48)/365.25)) | F27: =Valuation!$B$59*(1+Valuation!$B$61)^(F7-0.5-((Valuation!$B$60-Valuation!$B$48)/365.25)) | G27: =Valuation!$B$59*(1+Valuation!$B$61)^(G7-0.5-((Valuation!$B$60-Valuation!$B$48)/365.25)) | H27: diluted count rolled at the annual change to mid-year
A28: % YoY | C28: =IF(OR(C27="",B27="",B27=0),"",C27/B27-1) | D28: =IF(OR(D27="",C27="",C27=0),"",D27/C27-1) | E28: =IF(OR(D27="",D27=0),"",E27/D27-1) | F28: =IF(OR(E27="",E27=0),"",F27/E27-1) | G28: =IF(OR(F27="",F27=0),"",G27/F27-1)
A29: Diluted EPS | B29: 1.2 | C29: 1.98 | D29: 2.53 | E29: =E25/E27 | F29: =F25/F27 | G29: =G25/G27 | H29: SEC XBRL F22, F23, F24
A30: % YoY | C30: =IF(OR(C29="",B29="",B29=0),"",C29/B29-1) | D30: =IF(OR(D29="",C29="",C29=0),"",D29/C29-1) | E30: =IF(OR(D29="",D29=0),"",E29/D29-1) | F30: =IF(OR(E29="",E29=0),"",F29/E29-1) | G30: =IF(OR(F29="",F29=0),"",G29/F29-1)
A32: Cash flow
A33: NOPAT (EBIT x (1 - tax)) | E33: =E15*(1-E50) | F33: =F15*(1-F50) | G33: =G15*(1-G50)
A34: + D&A | B34: =B17 | C34: =C17 | D34: =D17 | E34: =E17 | F34: =F17 | G34: =G17
A35: - Capex | B35: 348.552 | C35: 439.538 | D35: 688.22 | E35: =E11*E52 | F35: =F11*F52 | G35: =G11*G52 | H35: SEC XBRL F55, F56, F57
A36: Capex % of sales | B36: =B35/B11 | C36: =C35/C11 | D36: =D35/D11 | E36: =E35/E11 | F36: =F35/F11 | G36: =G35/G11
A37: - Working capital increase | E37: =E53*(E11-Valuation!$B$49) | F37: =F53*(F11-E11) | G37: =G53*(G11-F11)
A38: - Stock comp (adjusted EBIT only) | E38: =IF(AND(Valuation!$B$46="adjusted",Valuation!$B$47="cost"),E42*(1-E50),0) | F38: =IF(AND(Valuation!$B$46="adjusted",Valuation!$B$47="cost"),F42*(1-F50),0) | G38: =IF(AND(Valuation!$B$46="adjusted",Valuation!$B$47="cost"),G42*(1-G50),0)
A39: Free cash flow to firm | E39: =E33+E34-E35-E37-E38 | F39: =F33+F34-F35-F37-F38 | G39: =G33+G34-G35-G37-G38 | H39: what the DCF discounts (Calc tabs)
A40: Operating cash flow (reported) | B40: 7274.301 | C40: 7361.364 | D40: 10149.273 | H40: SEC XBRL F48, F49, F50
A41: FCF (operating cash flow - capex) | B41: =B40-B35 | C41: =C40-C35 | D41: =D40-D35
A42: Stock comp (memo) | B42: 339.368 | C42: 272.588 | D42: 368.449 | E42: =E11*E54 | F42: =F11*F54 | G42: =G11*G54 | H42: SEC XBRL F41, F42, F43
A43: Buybacks + dividends + other uses | E43: =E11*E56+E55+E57 | F43: =F11*F56+F55+F57 | G43: =G11*G56+G55+G57
A44: % of sales | B44: =B43/B11 | C44: =C43/C11 | D44: =D43/D11 | E44: =E43/E11 | F44: =F43/F11 | G44: =G43/G11
A45: Net debt / (net cash), year end (memo) | E45: =Valuation!$B$55-E39-E20*(1-E50)+E43 | F45: =E45-F39-F20*(1-F50)+F43 | G45: =F45-G39-G20*(1-G50)+G43 | H45: rolled from the balance-date figure; feeds interest only
A47: Drivers (blue = input; a year left black carries the prior year)
A48: Revenue growth | C48: =C12 | D48: =D12 | E48: 0.13095633 | F48: 0.10209393 | G48: 0.085569189
A49: EBIT margin | E49: 0.31499022 | F49: 0.32396967 | G49: 0.32743392
A50: Tax rate | B50: =B24 | C50: =C24 | D50: =D24 | E50: 0.155 | F50: 0.155 | G50: 0.155
A51: D&A % revenue | B51: =B17/B11 | C51: =C17/C11 | D51: =D17/D11 | E51: 0.008 | F51: 0.008 | G51: 0.008
A52: Capex % revenue | B52: =B36 | C52: =C36 | D52: =D36 | E52: 0.054225049 | F52: 0.053838503 | G52: 0.053660429
A53: Working capital % of revenue increase | E53: 0 | F53: 0 | G53: 0
A54: Stock comp % revenue | B54: =B42/B11 | C54: =C42/C11 | D54: =D42/D11 | E54: 0.01 | F54: 0.01 | G54: 0.01
A55: Shareholder returns ($) | E55: 0 | F55: 0 | G55: 0
A56: Shareholder returns % revenue | B56: =B44 | C56: =C44 | D56: =D44 | E56: 0 | F56: 0 | G56: 0
A57: Other uses of cash ($: M&A, investments) | E57: 0 | F57: 0 | G57: 0
A58: Adj. EBITDA addback % revenue | E58: 0 | F58: 0 | G58: 0
A60: Versus company guidance and street consensus
A61: Guidance: revenue (GAAP), midpoint | E61: =AVERAGE(51100,51100) | H61: 5.11e+04 to 5.11e+04; as of 2026-10-20; source 1 (Netflix Q3 2026 shareholder letter (8-K Ex. 99.1))
A62: Model vs guidance midpoint | E62: =E11/E61-1 | H62: =IF(E11<51100,"below the guided range",IF(E11>51100,"above the guided range","inside the guided range"))
A63: Guidance: operating margin (GAAP), midpoint | E63: =AVERAGE(0.315,0.315) | H63: 0.315 to 0.315; as of 2026-10-20; source 1 (Netflix Q3 2026 shareholder letter (8-K Ex. 99.1))
A64: Guidance: free cash flow (non-GAAP), midpoint | E64: =AVERAGE(12000,12000) | H64: 1.2e+04 to 1.2e+04; as of 2026-10-20; source 1 (Netflix Q3 2026 shareholder letter (8-K Ex. 99.1))
A65: Consensus: EPS diluted (Zacks consensus (pre-print)) | F65: 3.8 | H65: as of 2026-10-20; source 6 (Nasdaq/Zacks NFLX earnings forecast)
A66: Model vs consensus | F66: =F29/F65-1
A67: Consensus: EPS diluted (Zacks consensus (pre-print)) | G67: 4.52 | H67: as of 2026-10-20; source 6 (Nasdaq/Zacks NFLX earnings forecast)
A68: Model vs consensus | G68: =G29/G67-1

Sheet Valuation
A1: NFLX: valuation and price target derivation
A2: Value per share at the target date = weighted methods below; the 12-month target is the median of the scenario mix (Distribution tab).
A3: Method | B3: Multiple | C3: Metric at target date | D3: Value per share | E3: Weight | F3: Contribution
A4: ='Calc - research target (12m)'!A67 | B4: =IF('Calc - research target (12m)'!C67="","",'Calc - research target (12m)'!C67) | C4: =IF('Calc - research target (12m)'!I67="","",'Calc - research target (12m)'!I67) | D4: ='Calc - research target (12m)'!F67 | E4: ='Calc - research target (12m)'!G67 | F4: =D4*E4/SUM($E$4:$E$5)
A5: ='Calc - research target (12m)'!A68 | B5: =IF('Calc - research target (12m)'!C68="","",'Calc - research target (12m)'!C68) | C5: =IF('Calc - research target (12m)'!I68="","",'Calc - research target (12m)'!I68) | D5: ='Calc - research target (12m)'!F68 | E5: ='Calc - research target (12m)'!G68 | F5: =D5*E5/SUM($E$4:$E$5)
A6: Research target (12m) per share | D6: ='Calc - research target (12m)'!$F$69 | F6: =SUM(F4:F5)
A8: 12-month EPS basis (what the P/E is applied to)
A9: Fiscal year | B9: =Model!E5 | C9: =Model!F5 | D9: =Model!G5
A10: Share of the 12 months after the target date | B10: ='Calc - research target (12m)'!C38 | C10: ='Calc - research target (12m)'!D38 | D10: ='Calc - research target (12m)'!E38
A11: Model EPS (Model tab) | B11: =Model!E29 | C11: =Model!F29 | D11: =Model!G29
A12: Model EPS, next 12 months after the target date | B12: =SUMPRODUCT(B10:D10,B11:D11)
A15: DCF build (free cash flow to firm, discounted to the target date)
A16: Fiscal year | B16: =Model!E5 | C16: =Model!F5 | D16: =Model!G5
A17: Free cash flow to firm | B17: ='Calc - research target (12m)'!C31 | C17: ='Calc - research target (12m)'!D31 | D17: ='Calc - research target (12m)'!E31
A18: Share of the year after the target date | B18: ='Calc - research target (12m)'!C35 | C18: ='Calc - research target (12m)'!D35 | D18: ='Calc - research target (12m)'!E35
A19: PV at target date | B19: ='Calc - research target (12m)'!C36 | C19: ='Calc - research target (12m)'!D36 | D19: ='Calc - research target (12m)'!E36
A21: PV of free cash flow after the target date | B21: ='Calc - research target (12m)'!B42
A22: Terminal value (final year) | B22: ='Calc - research target (12m)'!B43
A23: PV of terminal value | B23: ='Calc - research target (12m)'!B44
A24: Enterprise value at target date | B24: ='Calc - research target (12m)'!B45
A25: Terminal value share of DCF | B25: ='Calc - research target (12m)'!B46
A26: Net debt at target date | B26: ='Calc - research target (12m)'!B50
A27: Minority interests | B27: ='Calc - research target (12m)'!B51
A28: Adjustments | B28: ='Calc - research target (12m)'!B52
A29: Diluted shares at target date (M) | B29: ='Calc - research target (12m)'!B53
A30: DCF value per share | B30: ='Calc - research target (12m)'!F67
A31: WACC | B31: ='Calc - research target (12m)'!B12
A41: Assumptions (blue = input; sources on the Sources tab)
A42: Input | B42: Value | C42: Basis / note
A43: Run date (valuation as of) | B43: 46318
A44: Target date (run date + 365 days) | B44: =B43+365 | C44: 12-month horizon
A45: Money unit | B45: $M
A46: EBIT basis (gaap / adjusted) | B46: gaap | C46: gaap = after stock comp
A47: Stock comp treatment (cost / dilution) | B47: cost | C47: used only when EBIT is adjusted
A48: Last reported fiscal year end | B48: 46022
A49: Net sales, last reported year ($M) | B49: 45183
A50: WACC | B50: 0.094 | C50: Cost of equity 9.62% = 10y UST 5.12% (Treasury par curve 2026-10-20) + beta 1.0 x ERP 4.5%; beta between the 2y (0.92) and 3y (1.04) weekly regressions vs SPY, 5y (1.41) set aside as 2022-dominated; after-tax cost of debt 4.73% (5.6% x 0.845) at 5.3% weight -> 9.36%, rounded 9.4%.
A51: Terminal method (gordon / exit_multiple / steady_state) | B51: gordon
A52: Terminal growth | B52: 0.03
A53: Exit EV/EBITDA (exit_multiple only)
A54: Balance-sheet date | B54: 46295
A55: Net debt / (net cash) at balance date ($M) | B55: 7114 | C55: excludes operating leases
A56: Minority interests + preferred stock | B56: 0
A57: Interest rate on net debt / cash | B57: 0.056
A58: Net debt at target date (override; blank = bridge) | B58: 7500
A59: Diluted shares (M) | B59: 4195.1
A60: Share count date | B60: 46295
A61: Annual change in diluted shares | B61: -0.03 | C61: net of buybacks and stock-comp dilution
A62: Shares at target date (override; blank = from annual change)
A63: DCF weight | B63: 0 | C63: Kilian 2026-10-21: 0 unless the name has a DCF leg (dcf_policy)
A64: Sum-of-the-parts weight | B64: 0
A65: Spread within each scenario (lognormal vol) | B65: 0.15
A66: Share price at the run | B66: 65.85 | C66: close used by the run (2026-10-23)
A68: Target multiple | B68: Multiple | C68: Weight | D68: Basis (ntm / ltm) | E68: EBITDA basis | F68: Stated EPS | G68: Stated FCF/share | H68: Levered | I68: Peer basis
A69: P/E | B69: 19.07 | C69: 0.8 | D69: ntm | E69: gaap | H69: TRUE | I69: 6-peer NTM P/E median 21.82x on one EPS basis with NFLX (2026-10-23 closes; peers.md 'Rebuilt FY1 basis'): DIS 16.5, SONY 17.9, META 19.6, GOOGL 24.0, AMZN 26.6, SPOT 36.3 (flag: 6 peers). NFLX own 18.44x. Exit 19.07x = median x (own / median)^0.8 (default rule, Kilian card 2026-10-26 12:16Z). FOXA, WMG, TKO, TME (China), ROKU, PSKY out.
A71: Segment (sum of the parts) | B71: NTM metric | C71: Metric | D71: Multiple | E71: Note
A72: none
A74: Adjustment (equity level) | B74: Value | C74: Probability | D74: Note
A75: Probability-weighted large M&A value leakage | B75: -4000 | C75: 0.2 | D75: ~$83B WBD agreement signed in late 2025 and abandoned; WBD now owned by Skydance (closed 2026-10-06). 20% chance of a large deal destroying ~$4B over the horizon.
A77: Custom method | B77: Value per share | C77: Weight | D77: Explanation
A78: none
A80: Scenario | B80: Probability | C80: Growth Δ | D80: Margin Δ | E80: Multiple Δ (turns) | F80: WACC Δ | G80: Multiple %Δ (FCF yield, segments) | H80: Stated EPS/FCF %Δ | I80: Custom methods %Δ | J80: Story
A81: bear | B81: 0.25 | E81: -4 | F81: 0.005 | J81: Engagement keeps sliding to YouTube/creator and AI video; the closed Paramount-WBD (Skydance) combination bids up content and sports and pulls licensed titles; price rises meet churn; FY27 growth ~7%, ads stall near $3.3B, margin ~31-32%; P/E ~15x (exit 19.07x - 4; DIS 16.5x on the same basis). | K81: driver deltas: sub_rev -0.04 %; ad_rev -0.15 %; content_amort +0.01 %; other_opex -0.03 %
A82: base | B82: 0.5 | J82: FY27 revenue +10.2% (~$56.3B: subscription +8.3%, ads ~$3.9B), content amortization +9%, other costs +9.5% underlying -> GAAP margin 32.4% FY27, 32.7% FY28; NTM P/E 19.07x (peer refresh 2026-10-26).
A83: bull | B83: 0.25 | E83: 3 | J83: Ad-tech rollout and the 15-country 2027 launch lift ads above $4.5B, churn keeps improving and the January annual engagement report shows per-member hours stabilising; re-rates to ~22x (exit 19.07x + 3; peer median 21.8x). | K83: driver deltas: sub_rev +0.015 %; ad_rev +0.15 %

Sheet Sensitivity
A1: NFLX: sensitivity tables (bold = current inputs; every cell recalculates from the live model)
A3: DCF value per share: WACC (down) x terminal growth (across)
A4: WACC \ growth | B4: =Valuation!$B$52+(-0.01) | C4: =Valuation!$B$52+(-0.005) | D4: =Valuation!$B$52+(0) | E4: =Valuation!$B$52+(0.005) | F4: =Valuation!$B$52+(0.01)
A5: =Valuation!$B$50+(-0.01) | B5: =IF($A5-B$4<=0.01,"n/a",((SUMPRODUCT('Calc - research target (12m)'!$C$31:$E$31,'Calc - research target (12m)'!$C$35:$E$35,(1+$A5)^(-('Calc - research target (12m)'!$C$19:$E$19-'Calc - research target (12m)'!$B$13)))+'Calc - research target (12m)'!$E$31*(1+B$4)/($A5-B$4)/(1+$A5)^('Calc - research target (12m)'!$B$16-'Calc - research target (12m)'!$B$13))-'Calc - research target (12m)'!$B$50-'Calc - research target (12m)'!$B$51+'Calc - research target (12m)'!$B$52)/'Calc - research target (12m)'!$B$53) | C5: =IF($A5-C$4<=0.01,"n/a",((SUMPRODUCT('Calc - research target (12m)'!$C$31:$E$31,'Calc - research target (12m)'!$C$35:$E$35,(1+$A5)^(-('Calc - research target (12m)'!$C$19:$E$19-'Calc - research target (12m)'!$B$13)))+'Calc - research target (12m)'!$E$31*(1+C$4)/($A5-C$4)/(1+$A5)^('Calc - research target (12m)'!$B$16-'Calc - research target (12m)'!$B$13))-'Calc - research target (12m)'!$B$50-'Calc - research target (12m)'!$B$51+'Calc - research target (12m)'!$B$52)/'Calc - research target (12m)'!$B$53) | D5: =IF($A5-D$4<=0.01,"n/a",((SUMPRODUCT('Calc - research target (12m)'!$C$31:$E$31,'Calc - research target (12m)'!$C$35:$E$35,(1+$A5)^(-('Calc - research target (12m)'!$C$19:$E$19-'Calc - research target (12m)'!$B$13)))+'Calc - research target (12m)'!$E$31*(1+D$4)/($A5-D$4)/(1+$A5)^('Calc - research target (12m)'!$B$16-'Calc - research target (12m)'!$B$13))-'Calc - research target (12m)'!$B$50-'Calc - research target (12m)'!$B$51+'Calc - research target (12m)'!$B$52)/'Calc - research target (12m)'!$B$53) | E5: =IF($A5-E$4<=0.01,"n/a",((SUMPRODUCT('Calc - research target (12m)'!$C$31:$E$31,'Calc - research target (12m)'!$C$35:$E$35,(1+$A5)^(-('Calc - research target (12m)'!$C$19:$E$19-'Calc - research target (12m)'!$B$13)))+'Calc - research target (12m)'!$E$31*(1+E$4)/($A5-E$4)/(1+$A5)^('Calc - research target (12m)'!$B$16-'Calc - research target (12m)'!$B$13))-'Calc - research target (12m)'!$B$50-'Calc - research target (12m)'!$B$51+'Calc - research target (12m)'!$B$52)/'Calc - research target (12m)'!$B$53) | F5: =IF($A5-F$4<=0.01,"n/a",((SUMPRODUCT('Calc - research target (12m)'!$C$31:$E$31,'Calc - research target (12m)'!$C$35:$E$35,(1+$A5)^(-('Calc - research target (12m)'!$C$19:$E$19-'Calc - research target (12m)'!$B$13)))+'Calc - research target (12m)'!$E$31*(1+F$4)/($A5-F$4)/(1+$A5)^('Calc - research target (12m)'!$B$16-'Calc - research target (12m)'!$B$13))-'Calc - research target (12m)'!$B$50-'Calc - research target (12m)'!$B$51+'Calc - research target (12m)'!$B$52)/'Calc - research target (12m)'!$B$53)
A6: =Valuation!$B$50+(-0.005) | B6: =IF($A6-B$4<=0.01,"n/a",((SUMPRODUCT('Calc - research target (12m)'!$C$31:$E$31,'Calc - research target (12m)'!$C$35:$E$35,(1+$A6)^(-('Calc - research target (12m)'!$C$19:$E$19-'Calc - research target (12m)'!$B$13)))+'Calc - research target (12m)'!$E$31*(1+B$4)/($A6-B$4)/(1+$A6)^('Calc - research target (12m)'!$B$16-'Calc - research target (12m)'!$B$13))-'Calc - research target (12m)'!$B$50-'Calc - research target (12m)'!$B$51+'Calc - research target (12m)'!$B$52)/'Calc - research target (12m)'!$B$53) | C6: =IF($A6-C$4<=0.01,"n/a",((SUMPRODUCT('Calc - research target (12m)'!$C$31:$E$31,'Calc - research target (12m)'!$C$35:$E$35,(1+$A6)^(-('Calc - research target (12m)'!$C$19:$E$19-'Calc - research target (12m)'!$B$13)))+'Calc - research target (12m)'!$E$31*(1+C$4)/($A6-C$4)/(1+$A6)^('Calc - research target (12m)'!$B$16-'Calc - research target (12m)'!$B$13))-'Calc - research target (12m)'!$B$50-'Calc - research target (12m)'!$B$51+'Calc - research target (12m)'!$B$52)/'Calc - research target (12m)'!$B$53) | D6: =IF($A6-D$4<=0.01,"n/a",((SUMPRODUCT('Calc - research target (12m)'!$C$31:$E$31,'Calc - research target (12m)'!$C$35:$E$35,(1+$A6)^(-('Calc - research target (12m)'!$C$19:$E$19-'Calc - research target (12m)'!$B$13)))+'Calc - research target (12m)'!$E$31*(1+D$4)/($A6-D$4)/(1+$A6)^('Calc - research target (12m)'!$B$16-'Calc - research target (12m)'!$B$13))-'Calc - research target (12m)'!$B$50-'Calc - research target (12m)'!$B$51+'Calc - research target (12m)'!$B$52)/'Calc - research target (12m)'!$B$53) | E6: =IF($A6-E$4<=0.01,"n/a",((SUMPRODUCT('Calc - research target (12m)'!$C$31:$E$31,'Calc - research target (12m)'!$C$35:$E$35,(1+$A6)^(-('Calc - research target (12m)'!$C$19:$E$19-'Calc - research target (12m)'!$B$13)))+'Calc - research target (12m)'!$E$31*(1+E$4)/($A6-E$4)/(1+$A6)^('Calc - research target (12m)'!$B$16-'Calc - research target (12m)'!$B$13))-'Calc - research target (12m)'!$B$50-'Calc - research target (12m)'!$B$51+'Calc - research target (12m)'!$B$52)/'Calc - research target (12m)'!$B$53) | F6: =IF($A6-F$4<=0.01,"n/a",((SUMPRODUCT('Calc - research target (12m)'!$C$31:$E$31,'Calc - research target (12m)'!$C$35:$E$35,(1+$A6)^(-('Calc - research target (12m)'!$C$19:$E$19-'Calc - research target (12m)'!$B$13)))+'Calc - research target (12m)'!$E$31*(1+F$4)/($A6-F$4)/(1+$A6)^('Calc - research target (12m)'!$B$16-'Calc - research target (12m)'!$B$13))-'Calc - research target (12m)'!$B$50-'Calc - research target (12m)'!$B$51+'Calc - research target (12m)'!$B$52)/'Calc - research target (12m)'!$B$53)
A7: =Valuation!$B$50+(0) | B7: =IF($A7-B$4<=0.01,"n/a",((SUMPRODUCT('Calc - research target (12m)'!$C$31:$E$31,'Calc - research target (12m)'!$C$35:$E$35,(1+$A7)^(-('Calc - research target (12m)'!$C$19:$E$19-'Calc - research target (12m)'!$B$13)))+'Calc - research target (12m)'!$E$31*(1+B$4)/($A7-B$4)/(1+$A7)^('Calc - research target (12m)'!$B$16-'Calc - research target (12m)'!$B$13))-'Calc - research target (12m)'!$B$50-'Calc - research target (12m)'!$B$51+'Calc - research target (12m)'!$B$52)/'Calc - research target (12m)'!$B$53) | C7: =IF($A7-C$4<=0.01,"n/a",((SUMPRODUCT('Calc - research target (12m)'!$C$31:$E$31,'Calc - research target (12m)'!$C$35:$E$35,(1+$A7)^(-('Calc - research target (12m)'!$C$19:$E$19-'Calc - research target (12m)'!$B$13)))+'Calc - research target (12m)'!$E$31*(1+C$4)/($A7-C$4)/(1+$A7)^('Calc - research target (12m)'!$B$16-'Calc - research target (12m)'!$B$13))-'Calc - research target (12m)'!$B$50-'Calc - research target (12m)'!$B$51+'Calc - research target (12m)'!$B$52)/'Calc - research target (12m)'!$B$53) | D7: =IF($A7-D$4<=0.01,"n/a",((SUMPRODUCT('Calc - research target (12m)'!$C$31:$E$31,'Calc - research target (12m)'!$C$35:$E$35,(1+$A7)^(-('Calc - research target (12m)'!$C$19:$E$19-'Calc - research target (12m)'!$B$13)))+'Calc - research target (12m)'!$E$31*(1+D$4)/($A7-D$4)/(1+$A7)^('Calc - research target (12m)'!$B$16-'Calc - research target (12m)'!$B$13))-'Calc - research target (12m)'!$B$50-'Calc - research target (12m)'!$B$51+'Calc - research target (12m)'!$B$52)/'Calc - research target (12m)'!$B$53) | E7: =IF($A7-E$4<=0.01,"n/a",((SUMPRODUCT('Calc - research target (12m)'!$C$31:$E$31,'Calc - research target (12m)'!$C$35:$E$35,(1+$A7)^(-('Calc - research target (12m)'!$C$19:$E$19-'Calc - research target (12m)'!$B$13)))+'Calc - research target (12m)'!$E$31*(1+E$4)/($A7-E$4)/(1+$A7)^('Calc - research target (12m)'!$B$16-'Calc - research target (12m)'!$B$13))-'Calc - research target (12m)'!$B$50-'Calc - research target (12m)'!$B$51+'Calc - research target (12m)'!$B$52)/'Calc - research target (12m)'!$B$53) | F7: =IF($A7-F$4<=0.01,"n/a",((SUMPRODUCT('Calc - research target (12m)'!$C$31:$E$31,'Calc - research target (12m)'!$C$35:$E$35,(1+$A7)^(-('Calc - research target (12m)'!$C$19:$E$19-'Calc - research target (12m)'!$B$13)))+'Calc - research target (12m)'!$E$31*(1+F$4)/($A7-F$4)/(1+$A7)^('Calc - research target (12m)'!$B$16-'Calc - research target (12m)'!$B$13))-'Calc - research target (12m)'!$B$50-'Calc - research target (12m)'!$B$51+'Calc - research target (12m)'!$B$52)/'Calc - research target (12m)'!$B$53)
A8: =Valuation!$B$50+(0.005) | B8: =IF($A8-B$4<=0.01,"n/a",((SUMPRODUCT('Calc - research target (12m)'!$C$31:$E$31,'Calc - research target (12m)'!$C$35:$E$35,(1+$A8)^(-('Calc - research target (12m)'!$C$19:$E$19-'Calc - research target (12m)'!$B$13)))+'Calc - research target (12m)'!$E$31*(1+B$4)/($A8-B$4)/(1+$A8)^('Calc - research target (12m)'!$B$16-'Calc - research target (12m)'!$B$13))-'Calc - research target (12m)'!$B$50-'Calc - research target (12m)'!$B$51+'Calc - research target (12m)'!$B$52)/'Calc - research target (12m)'!$B$53) | C8: =IF($A8-C$4<=0.01,"n/a",((SUMPRODUCT('Calc - research target (12m)'!$C$31:$E$31,'Calc - research target (12m)'!$C$35:$E$35,(1+$A8)^(-('Calc - research target (12m)'!$C$19:$E$19-'Calc - research target (12m)'!$B$13)))+'Calc - research target (12m)'!$E$31*(1+C$4)/($A8-C$4)/(1+$A8)^('Calc - research target (12m)'!$B$16-'Calc - research target (12m)'!$B$13))-'Calc - research target (12m)'!$B$50-'Calc - research target (12m)'!$B$51+'Calc - research target (12m)'!$B$52)/'Calc - research target (12m)'!$B$53) | D8: =IF($A8-D$4<=0.01,"n/a",((SUMPRODUCT('Calc - research target (12m)'!$C$31:$E$31,'Calc - research target (12m)'!$C$35:$E$35,(1+$A8)^(-('Calc - research target (12m)'!$C$19:$E$19-'Calc - research target (12m)'!$B$13)))+'Calc - research target (12m)'!$E$31*(1+D$4)/($A8-D$4)/(1+$A8)^('Calc - research target (12m)'!$B$16-'Calc - research target (12m)'!$B$13))-'Calc - research target (12m)'!$B$50-'Calc - research target (12m)'!$B$51+'Calc - research target (12m)'!$B$52)/'Calc - research target (12m)'!$B$53) | E8: =IF($A8-E$4<=0.01,"n/a",((SUMPRODUCT('Calc - research target (12m)'!$C$31:$E$31,'Calc - research target (12m)'!$C$35:$E$35,(1+$A8)^(-('Calc - research target (12m)'!$C$19:$E$19-'Calc - research target (12m)'!$B$13)))+'Calc - research target (12m)'!$E$31*(1+E$4)/($A8-E$4)/(1+$A8)^('Calc - research target (12m)'!$B$16-'Calc - research target (12m)'!$B$13))-'Calc - research target (12m)'!$B$50-'Calc - research target (12m)'!$B$51+'Calc - research target (12m)'!$B$52)/'Calc - research target (12m)'!$B$53) | F8: =IF($A8-F$4<=0.01,"n/a",((SUMPRODUCT('Calc - research target (12m)'!$C$31:$E$31,'Calc - research target (12m)'!$C$35:$E$35,(1+$A8)^(-('Calc - research target (12m)'!$C$19:$E$19-'Calc - research target (12m)'!$B$13)))+'Calc - research target (12m)'!$E$31*(1+F$4)/($A8-F$4)/(1+$A8)^('Calc - research target (12m)'!$B$16-'Calc - research target (12m)'!$B$13))-'Calc - research target (12m)'!$B$50-'Calc - research target (12m)'!$B$51+'Calc - research target (12m)'!$B$52)/'Calc - research target (12m)'!$B$53)
A9: =Valuation!$B$50+(0.01) | B9: =IF($A9-B$4<=0.01,"n/a",((SUMPRODUCT('Calc - research target (12m)'!$C$31:$E$31,'Calc - research target (12m)'!$C$35:$E$35,(1+$A9)^(-('Calc - research target (12m)'!$C$19:$E$19-'Calc - research target (12m)'!$B$13)))+'Calc - research target (12m)'!$E$31*(1+B$4)/($A9-B$4)/(1+$A9)^('Calc - research target (12m)'!$B$16-'Calc - research target (12m)'!$B$13))-'Calc - research target (12m)'!$B$50-'Calc - research target (12m)'!$B$51+'Calc - research target (12m)'!$B$52)/'Calc - research target (12m)'!$B$53) | C9: =IF($A9-C$4<=0.01,"n/a",((SUMPRODUCT('Calc - research target (12m)'!$C$31:$E$31,'Calc - research target (12m)'!$C$35:$E$35,(1+$A9)^(-('Calc - research target (12m)'!$C$19:$E$19-'Calc - research target (12m)'!$B$13)))+'Calc - research target (12m)'!$E$31*(1+C$4)/($A9-C$4)/(1+$A9)^('Calc - research target (12m)'!$B$16-'Calc - research target (12m)'!$B$13))-'Calc - research target (12m)'!$B$50-'Calc - research target (12m)'!$B$51+'Calc - research target (12m)'!$B$52)/'Calc - research target (12m)'!$B$53) | D9: =IF($A9-D$4<=0.01,"n/a",((SUMPRODUCT('Calc - research target (12m)'!$C$31:$E$31,'Calc - research target (12m)'!$C$35:$E$35,(1+$A9)^(-('Calc - research target (12m)'!$C$19:$E$19-'Calc - research target (12m)'!$B$13)))+'Calc - research target (12m)'!$E$31*(1+D$4)/($A9-D$4)/(1+$A9)^('Calc - research target (12m)'!$B$16-'Calc - research target (12m)'!$B$13))-'Calc - research target (12m)'!$B$50-'Calc - research target (12m)'!$B$51+'Calc - research target (12m)'!$B$52)/'Calc - research target (12m)'!$B$53) | E9: =IF($A9-E$4<=0.01,"n/a",((SUMPRODUCT('Calc - research target (12m)'!$C$31:$E$31,'Calc - research target (12m)'!$C$35:$E$35,(1+$A9)^(-('Calc - research target (12m)'!$C$19:$E$19-'Calc - research target (12m)'!$B$13)))+'Calc - research target (12m)'!$E$31*(1+E$4)/($A9-E$4)/(1+$A9)^('Calc - research target (12m)'!$B$16-'Calc - research target (12m)'!$B$13))-'Calc - research target (12m)'!$B$50-'Calc - research target (12m)'!$B$51+'Calc - research target (12m)'!$B$52)/'Calc - research target (12m)'!$B$53) | F9: =IF($A9-F$4<=0.01,"n/a",((SUMPRODUCT('Calc - research target (12m)'!$C$31:$E$31,'Calc - research target (12m)'!$C$35:$E$35,(1+$A9)^(-('Calc - research target (12m)'!$C$19:$E$19-'Calc - research target (12m)'!$B$13)))+'Calc - research target (12m)'!$E$31*(1+F$4)/($A9-F$4)/(1+$A9)^('Calc - research target (12m)'!$B$16-'Calc - research target (12m)'!$B$13))-'Calc - research target (12m)'!$B$50-'Calc - research target (12m)'!$B$51+'Calc - research target (12m)'!$B$52)/'Calc - research target (12m)'!$B$53)
A11: Research target (12m) per share: P/E multiple (down) x metric at target date (across)
A12: Multiple \ metric | B12: ='Calc - research target (12m)'!$E$68*0.9 | C12: ='Calc - research target (12m)'!$E$68*0.95 | D12: ='Calc - research target (12m)'!$E$68*1.0 | E12: ='Calc - research target (12m)'!$E$68*1.05 | F12: ='Calc - research target (12m)'!$E$68*1.1
A13: =Valuation!$B$69+(-3) | B13: =((SUMPRODUCT('Calc - research target (12m)'!$F$67:$F$68,'Calc - research target (12m)'!$G$67:$G$68)-'Calc - research target (12m)'!$F$68*'Calc - research target (12m)'!$G$68)+'Calc - research target (12m)'!$G$68*($A13*(B$12-'Calc - research target (12m)'!$B$54)/'Calc - research target (12m)'!$B$53+'Calc - research target (12m)'!$B$52/'Calc - research target (12m)'!$B$53))/SUM('Calc - research target (12m)'!$G$67:$G$68) | C13: =((SUMPRODUCT('Calc - research target (12m)'!$F$67:$F$68,'Calc - research target (12m)'!$G$67:$G$68)-'Calc - research target (12m)'!$F$68*'Calc - research target (12m)'!$G$68)+'Calc - research target (12m)'!$G$68*($A13*(C$12-'Calc - research target (12m)'!$B$54)/'Calc - research target (12m)'!$B$53+'Calc - research target (12m)'!$B$52/'Calc - research target (12m)'!$B$53))/SUM('Calc - research target (12m)'!$G$67:$G$68) | D13: =((SUMPRODUCT('Calc - research target (12m)'!$F$67:$F$68,'Calc - research target (12m)'!$G$67:$G$68)-'Calc - research target (12m)'!$F$68*'Calc - research target (12m)'!$G$68)+'Calc - research target (12m)'!$G$68*($A13*(D$12-'Calc - research target (12m)'!$B$54)/'Calc - research target (12m)'!$B$53+'Calc - research target (12m)'!$B$52/'Calc - research target (12m)'!$B$53))/SUM('Calc - research target (12m)'!$G$67:$G$68) | E13: =((SUMPRODUCT('Calc - research target (12m)'!$F$67:$F$68,'Calc - research target (12m)'!$G$67:$G$68)-'Calc - research target (12m)'!$F$68*'Calc - research target (12m)'!$G$68)+'Calc - research target (12m)'!$G$68*($A13*(E$12-'Calc - research target (12m)'!$B$54)/'Calc - research target (12m)'!$B$53+'Calc - research target (12m)'!$B$52/'Calc - research target (12m)'!$B$53))/SUM('Calc - research target (12m)'!$G$67:$G$68) | F13: =((SUMPRODUCT('Calc - research target (12m)'!$F$67:$F$68,'Calc - research target (12m)'!$G$67:$G$68)-'Calc - research target (12m)'!$F$68*'Calc - research target (12m)'!$G$68)+'Calc - research target (12m)'!$G$68*($A13*(F$12-'Calc - research target (12m)'!$B$54)/'Calc - research target (12m)'!$B$53+'Calc - research target (12m)'!$B$52/'Calc - research target (12m)'!$B$53))/SUM('Calc - research target (12m)'!$G$67:$G$68)
A14: =Valuation!$B$69+(-2) | B14: =((SUMPRODUCT('Calc - research target (12m)'!$F$67:$F$68,'Calc - research target (12m)'!$G$67:$G$68)-'Calc - research target (12m)'!$F$68*'Calc - research target (12m)'!$G$68)+'Calc - research target (12m)'!$G$68*($A14*(B$12-'Calc - research target (12m)'!$B$54)/'Calc - research target (12m)'!$B$53+'Calc - research target (12m)'!$B$52/'Calc - research target (12m)'!$B$53))/SUM('Calc - research target (12m)'!$G$67:$G$68) | C14: =((SUMPRODUCT('Calc - research target (12m)'!$F$67:$F$68,'Calc - research target (12m)'!$G$67:$G$68)-'Calc - research target (12m)'!$F$68*'Calc - research target (12m)'!$G$68)+'Calc - research target (12m)'!$G$68*($A14*(C$12-'Calc - research target (12m)'!$B$54)/'Calc - research target (12m)'!$B$53+'Calc - research target (12m)'!$B$52/'Calc - research target (12m)'!$B$53))/SUM('Calc - research target (12m)'!$G$67:$G$68) | D14: =((SUMPRODUCT('Calc - research target (12m)'!$F$67:$F$68,'Calc - research target (12m)'!$G$67:$G$68)-'Calc - research target (12m)'!$F$68*'Calc - research target (12m)'!$G$68)+'Calc - research target (12m)'!$G$68*($A14*(D$12-'Calc - research target (12m)'!$B$54)/'Calc - research target (12m)'!$B$53+'Calc - research target (12m)'!$B$52/'Calc - research target (12m)'!$B$53))/SUM('Calc - research target (12m)'!$G$67:$G$68) | E14: =((SUMPRODUCT('Calc - research target (12m)'!$F$67:$F$68,'Calc - research target (12m)'!$G$67:$G$68)-'Calc - research target (12m)'!$F$68*'Calc - research target (12m)'!$G$68)+'Calc - research target (12m)'!$G$68*($A14*(E$12-'Calc - research target (12m)'!$B$54)/'Calc - research target (12m)'!$B$53+'Calc - research target (12m)'!$B$52/'Calc - research target (12m)'!$B$53))/SUM('Calc - research target (12m)'!$G$67:$G$68) | F14: =((SUMPRODUCT('Calc - research target (12m)'!$F$67:$F$68,'Calc - research target (12m)'!$G$67:$G$68)-'Calc - research target (12m)'!$F$68*'Calc - research target (12m)'!$G$68)+'Calc - research target (12m)'!$G$68*($A14*(F$12-'Calc - research target (12m)'!$B$54)/'Calc - research target (12m)'!$B$53+'Calc - research target (12m)'!$B$52/'Calc - research target (12m)'!$B$53))/SUM('Calc - research target (12m)'!$G$67:$G$68)
A15: =Valuation!$B$69+(-1) | B15: =((SUMPRODUCT('Calc - research target (12m)'!$F$67:$F$68,'Calc - research target (12m)'!$G$67:$G$68)-'Calc - research target (12m)'!$F$68*'Calc - research target (12m)'!$G$68)+'Calc - research target (12m)'!$G$68*($A15*(B$12-'Calc - research target (12m)'!$B$54)/'Calc - research target (12m)'!$B$53+'Calc - research target (12m)'!$B$52/'Calc - research target (12m)'!$B$53))/SUM('Calc - research target (12m)'!$G$67:$G$68) | C15: =((SUMPRODUCT('Calc - research target (12m)'!$F$67:$F$68,'Calc - research target (12m)'!$G$67:$G$68)-'Calc - research target (12m)'!$F$68*'Calc - research target (12m)'!$G$68)+'Calc - research target (12m)'!$G$68*($A15*(C$12-'Calc - research target (12m)'!$B$54)/'Calc - research target (12m)'!$B$53+'Calc - research target (12m)'!$B$52/'Calc - research target (12m)'!$B$53))/SUM('Calc - research target (12m)'!$G$67:$G$68) | D15: =((SUMPRODUCT('Calc - research target (12m)'!$F$67:$F$68,'Calc - research target (12m)'!$G$67:$G$68)-'Calc - research target (12m)'!$F$68*'Calc - research target (12m)'!$G$68)+'Calc - research target (12m)'!$G$68*($A15*(D$12-'Calc - research target (12m)'!$B$54)/'Calc - research target (12m)'!$B$53+'Calc - research target (12m)'!$B$52/'Calc - research target (12m)'!$B$53))/SUM('Calc - research target (12m)'!$G$67:$G$68) | E15: =((SUMPRODUCT('Calc - research target (12m)'!$F$67:$F$68,'Calc - research target (12m)'!$G$67:$G$68)-'Calc - research target (12m)'!$F$68*'Calc - research target (12m)'!$G$68)+'Calc - research target (12m)'!$G$68*($A15*(E$12-'Calc - research target (12m)'!$B$54)/'Calc - research target (12m)'!$B$53+'Calc - research target (12m)'!$B$52/'Calc - research target (12m)'!$B$53))/SUM('Calc - research target (12m)'!$G$67:$G$68) | F15: =((SUMPRODUCT('Calc - research target (12m)'!$F$67:$F$68,'Calc - research target (12m)'!$G$67:$G$68)-'Calc - research target (12m)'!$F$68*'Calc - research target (12m)'!$G$68)+'Calc - research target (12m)'!$G$68*($A15*(F$12-'Calc - research target (12m)'!$B$54)/'Calc - research target (12m)'!$B$53+'Calc - research target (12m)'!$B$52/'Calc - research target (12m)'!$B$53))/SUM('Calc - research target (12m)'!$G$67:$G$68)
A16: =Valuation!$B$69+(0) | B16: =((SUMPRODUCT('Calc - research target (12m)'!$F$67:$F$68,'Calc - research target (12m)'!$G$67:$G$68)-'Calc - research target (12m)'!$F$68*'Calc - research target (12m)'!$G$68)+'Calc - research target (12m)'!$G$68*($A16*(B$12-'Calc - research target (12m)'!$B$54)/'Calc - research target (12m)'!$B$53+'Calc - research target (12m)'!$B$52/'Calc - research target (12m)'!$B$53))/SUM('Calc - research target (12m)'!$G$67:$G$68) | C16: =((SUMPRODUCT('Calc - research target (12m)'!$F$67:$F$68,'Calc - research target (12m)'!$G$67:$G$68)-'Calc - research target (12m)'!$F$68*'Calc - research target (12m)'!$G$68)+'Calc - research target (12m)'!$G$68*($A16*(C$12-'Calc - research target (12m)'!$B$54)/'Calc - research target (12m)'!$B$53+'Calc - research target (12m)'!$B$52/'Calc - research target (12m)'!$B$53))/SUM('Calc - research target (12m)'!$G$67:$G$68) | D16: =((SUMPRODUCT('Calc - research target (12m)'!$F$67:$F$68,'Calc - research target (12m)'!$G$67:$G$68)-'Calc - research target (12m)'!$F$68*'Calc - research target (12m)'!$G$68)+'Calc - research target (12m)'!$G$68*($A16*(D$12-'Calc - research target (12m)'!$B$54)/'Calc - research target (12m)'!$B$53+'Calc - research target (12m)'!$B$52/'Calc - research target (12m)'!$B$53))/SUM('Calc - research target (12m)'!$G$67:$G$68) | E16: =((SUMPRODUCT('Calc - research target (12m)'!$F$67:$F$68,'Calc - research target (12m)'!$G$67:$G$68)-'Calc - research target (12m)'!$F$68*'Calc - research target (12m)'!$G$68)+'Calc - research target (12m)'!$G$68*($A16*(E$12-'Calc - research target (12m)'!$B$54)/'Calc - research target (12m)'!$B$53+'Calc - research target (12m)'!$B$52/'Calc - research target (12m)'!$B$53))/SUM('Calc - research target (12m)'!$G$67:$G$68) | F16: =((SUMPRODUCT('Calc - research target (12m)'!$F$67:$F$68,'Calc - research target (12m)'!$G$67:$G$68)-'Calc - research target (12m)'!$F$68*'Calc - research target (12m)'!$G$68)+'Calc - research target (12m)'!$G$68*($A16*(F$12-'Calc - research target (12m)'!$B$54)/'Calc - research target (12m)'!$B$53+'Calc - research target (12m)'!$B$52/'Calc - research target (12m)'!$B$53))/SUM('Calc - research target (12m)'!$G$67:$G$68)
A17: =Valuation!$B$69+(1) | B17: =((SUMPRODUCT('Calc - research target (12m)'!$F$67:$F$68,'Calc - research target (12m)'!$G$67:$G$68)-'Calc - research target (12m)'!$F$68*'Calc - research target (12m)'!$G$68)+'Calc - research target (12m)'!$G$68*($A17*(B$12-'Calc - research target (12m)'!$B$54)/'Calc - research target (12m)'!$B$53+'Calc - research target (12m)'!$B$52/'Calc - research target (12m)'!$B$53))/SUM('Calc - research target (12m)'!$G$67:$G$68) | C17: =((SUMPRODUCT('Calc - research target (12m)'!$F$67:$F$68,'Calc - research target (12m)'!$G$67:$G$68)-'Calc - research target (12m)'!$F$68*'Calc - research target (12m)'!$G$68)+'Calc - research target (12m)'!$G$68*($A17*(C$12-'Calc - research target (12m)'!$B$54)/'Calc - research target (12m)'!$B$53+'Calc - research target (12m)'!$B$52/'Calc - research target (12m)'!$B$53))/SUM('Calc - research target (12m)'!$G$67:$G$68) | D17: =((SUMPRODUCT('Calc - research target (12m)'!$F$67:$F$68,'Calc - research target (12m)'!$G$67:$G$68)-'Calc - research target (12m)'!$F$68*'Calc - research target (12m)'!$G$68)+'Calc - research target (12m)'!$G$68*($A17*(D$12-'Calc - research target (12m)'!$B$54)/'Calc - research target (12m)'!$B$53+'Calc - research target (12m)'!$B$52/'Calc - research target (12m)'!$B$53))/SUM('Calc - research target (12m)'!$G$67:$G$68) | E17: =((SUMPRODUCT('Calc - research target (12m)'!$F$67:$F$68,'Calc - research target (12m)'!$G$67:$G$68)-'Calc - research target (12m)'!$F$68*'Calc - research target (12m)'!$G$68)+'Calc - research target (12m)'!$G$68*($A17*(E$12-'Calc - research target (12m)'!$B$54)/'Calc - research target (12m)'!$B$53+'Calc - research target (12m)'!$B$52/'Calc - research target (12m)'!$B$53))/SUM('Calc - research target (12m)'!$G$67:$G$68) | F17: =((SUMPRODUCT('Calc - research target (12m)'!$F$67:$F$68,'Calc - research target (12m)'!$G$67:$G$68)-'Calc - research target (12m)'!$F$68*'Calc - research target (12m)'!$G$68)+'Calc - research target (12m)'!$G$68*($A17*(F$12-'Calc - research target (12m)'!$B$54)/'Calc - research target (12m)'!$B$53+'Calc - research target (12m)'!$B$52/'Calc - research target (12m)'!$B$53))/SUM('Calc - research target (12m)'!$G$67:$G$68)
A18: =Valuation!$B$69+(2) | B18: =((SUMPRODUCT('Calc - research target (12m)'!$F$67:$F$68,'Calc - research target (12m)'!$G$67:$G$68)-'Calc - research target (12m)'!$F$68*'Calc - research target (12m)'!$G$68)+'Calc - research target (12m)'!$G$68*($A18*(B$12-'Calc - research target (12m)'!$B$54)/'Calc - research target (12m)'!$B$53+'Calc - research target (12m)'!$B$52/'Calc - research target (12m)'!$B$53))/SUM('Calc - research target (12m)'!$G$67:$G$68) | C18: =((SUMPRODUCT('Calc - research target (12m)'!$F$67:$F$68,'Calc - research target (12m)'!$G$67:$G$68)-'Calc - research target (12m)'!$F$68*'Calc - research target (12m)'!$G$68)+'Calc - research target (12m)'!$G$68*($A18*(C$12-'Calc - research target (12m)'!$B$54)/'Calc - research target (12m)'!$B$53+'Calc - research target (12m)'!$B$52/'Calc - research target (12m)'!$B$53))/SUM('Calc - research target (12m)'!$G$67:$G$68) | D18: =((SUMPRODUCT('Calc - research target (12m)'!$F$67:$F$68,'Calc - research target (12m)'!$G$67:$G$68)-'Calc - research target (12m)'!$F$68*'Calc - research target (12m)'!$G$68)+'Calc - research target (12m)'!$G$68*($A18*(D$12-'Calc - research target (12m)'!$B$54)/'Calc - research target (12m)'!$B$53+'Calc - research target (12m)'!$B$52/'Calc - research target (12m)'!$B$53))/SUM('Calc - research target (12m)'!$G$67:$G$68) | E18: =((SUMPRODUCT('Calc - research target (12m)'!$F$67:$F$68,'Calc - research target (12m)'!$G$67:$G$68)-'Calc - research target (12m)'!$F$68*'Calc - research target (12m)'!$G$68)+'Calc - research target (12m)'!$G$68*($A18*(E$12-'Calc - research target (12m)'!$B$54)/'Calc - research target (12m)'!$B$53+'Calc - research target (12m)'!$B$52/'Calc - research target (12m)'!$B$53))/SUM('Calc - research target (12m)'!$G$67:$G$68) | F18: =((SUMPRODUCT('Calc - research target (12m)'!$F$67:$F$68,'Calc - research target (12m)'!$G$67:$G$68)-'Calc - research target (12m)'!$F$68*'Calc - research target (12m)'!$G$68)+'Calc - research target (12m)'!$G$68*($A18*(F$12-'Calc - research target (12m)'!$B$54)/'Calc - research target (12m)'!$B$53+'Calc - research target (12m)'!$B$52/'Calc - research target (12m)'!$B$53))/SUM('Calc - research target (12m)'!$G$67:$G$68)
A19: =Valuation!$B$69+(3) | B19: =((SUMPRODUCT('Calc - research target (12m)'!$F$67:$F$68,'Calc - research target (12m)'!$G$67:$G$68)-'Calc - research target (12m)'!$F$68*'Calc - research target (12m)'!$G$68)+'Calc - research target (12m)'!$G$68*($A19*(B$12-'Calc - research target (12m)'!$B$54)/'Calc - research target (12m)'!$B$53+'Calc - research target (12m)'!$B$52/'Calc - research target (12m)'!$B$53))/SUM('Calc - research target (12m)'!$G$67:$G$68) | C19: =((SUMPRODUCT('Calc - research target (12m)'!$F$67:$F$68,'Calc - research target (12m)'!$G$67:$G$68)-'Calc - research target (12m)'!$F$68*'Calc - research target (12m)'!$G$68)+'Calc - research target (12m)'!$G$68*($A19*(C$12-'Calc - research target (12m)'!$B$54)/'Calc - research target (12m)'!$B$53+'Calc - research target (12m)'!$B$52/'Calc - research target (12m)'!$B$53))/SUM('Calc - research target (12m)'!$G$67:$G$68) | D19: =((SUMPRODUCT('Calc - research target (12m)'!$F$67:$F$68,'Calc - research target (12m)'!$G$67:$G$68)-'Calc - research target (12m)'!$F$68*'Calc - research target (12m)'!$G$68)+'Calc - research target (12m)'!$G$68*($A19*(D$12-'Calc - research target (12m)'!$B$54)/'Calc - research target (12m)'!$B$53+'Calc - research target (12m)'!$B$52/'Calc - research target (12m)'!$B$53))/SUM('Calc - research target (12m)'!$G$67:$G$68) | E19: =((SUMPRODUCT('Calc - research target (12m)'!$F$67:$F$68,'Calc - research target (12m)'!$G$67:$G$68)-'Calc - research target (12m)'!$F$68*'Calc - research target (12m)'!$G$68)+'Calc - research target (12m)'!$G$68*($A19*(E$12-'Calc - research target (12m)'!$B$54)/'Calc - research target (12m)'!$B$53+'Calc - research target (12m)'!$B$52/'Calc - research target (12m)'!$B$53))/SUM('Calc - research target (12m)'!$G$67:$G$68) | F19: =((SUMPRODUCT('Calc - research target (12m)'!$F$67:$F$68,'Calc - research target (12m)'!$G$67:$G$68)-'Calc - research target (12m)'!$F$68*'Calc - research target (12m)'!$G$68)+'Calc - research target (12m)'!$G$68*($A19*(F$12-'Calc - research target (12m)'!$B$54)/'Calc - research target (12m)'!$B$53+'Calc - research target (12m)'!$B$52/'Calc - research target (12m)'!$B$53))/SUM('Calc - research target (12m)'!$G$67:$G$68)
A22: FY2027E diluted EPS: revenue growth change in every year (down) x EBIT margin change (across)
A23: Growth Δ \ margin Δ | B23: -0.01 | C23: -0.005 | D23: 0 | E23: 0.005 | F23: 0.01
A24: -0.02 | B24: =(Valuation!$B$49*(1+Model!E48+$A24)*(1+Model!F48+$A24)*(Model!F49+B$23)+Model!F20)*(1-Model!F50)/Model!F27 | C24: =(Valuation!$B$49*(1+Model!E48+$A24)*(1+Model!F48+$A24)*(Model!F49+C$23)+Model!F20)*(1-Model!F50)/Model!F27 | D24: =(Valuation!$B$49*(1+Model!E48+$A24)*(1+Model!F48+$A24)*(Model!F49+D$23)+Model!F20)*(1-Model!F50)/Model!F27 | E24: =(Valuation!$B$49*(1+Model!E48+$A24)*(1+Model!F48+$A24)*(Model!F49+E$23)+Model!F20)*(1-Model!F50)/Model!F27 | F24: =(Valuation!$B$49*(1+Model!E48+$A24)*(1+Model!F48+$A24)*(Model!F49+F$23)+Model!F20)*(1-Model!F50)/Model!F27
A25: -0.01 | B25: =(Valuation!$B$49*(1+Model!E48+$A25)*(1+Model!F48+$A25)*(Model!F49+B$23)+Model!F20)*(1-Model!F50)/Model!F27 | C25: =(Valuation!$B$49*(1+Model!E48+$A25)*(1+Model!F48+$A25)*(Model!F49+C$23)+Model!F20)*(1-Model!F50)/Model!F27 | D25: =(Valuation!$B$49*(1+Model!E48+$A25)*(1+Model!F48+$A25)*(Model!F49+D$23)+Model!F20)*(1-Model!F50)/Model!F27 | E25: =(Valuation!$B$49*(1+Model!E48+$A25)*(1+Model!F48+$A25)*(Model!F49+E$23)+Model!F20)*(1-Model!F50)/Model!F27 | F25: =(Valuation!$B$49*(1+Model!E48+$A25)*(1+Model!F48+$A25)*(Model!F49+F$23)+Model!F20)*(1-Model!F50)/Model!F27
A26: 0 | B26: =(Valuation!$B$49*(1+Model!E48+$A26)*(1+Model!F48+$A26)*(Model!F49+B$23)+Model!F20)*(1-Model!F50)/Model!F27 | C26: =(Valuation!$B$49*(1+Model!E48+$A26)*(1+Model!F48+$A26)*(Model!F49+C$23)+Model!F20)*(1-Model!F50)/Model!F27 | D26: =(Valuation!$B$49*(1+Model!E48+$A26)*(1+Model!F48+$A26)*(Model!F49+D$23)+Model!F20)*(1-Model!F50)/Model!F27 | E26: =(Valuation!$B$49*(1+Model!E48+$A26)*(1+Model!F48+$A26)*(Model!F49+E$23)+Model!F20)*(1-Model!F50)/Model!F27 | F26: =(Valuation!$B$49*(1+Model!E48+$A26)*(1+Model!F48+$A26)*(Model!F49+F$23)+Model!F20)*(1-Model!F50)/Model!F27
A27: 0.01 | B27: =(Valuation!$B$49*(1+Model!E48+$A27)*(1+Model!F48+$A27)*(Model!F49+B$23)+Model!F20)*(1-Model!F50)/Model!F27 | C27: =(Valuation!$B$49*(1+Model!E48+$A27)*(1+Model!F48+$A27)*(Model!F49+C$23)+Model!F20)*(1-Model!F50)/Model!F27 | D27: =(Valuation!$B$49*(1+Model!E48+$A27)*(1+Model!F48+$A27)*(Model!F49+D$23)+Model!F20)*(1-Model!F50)/Model!F27 | E27: =(Valuation!$B$49*(1+Model!E48+$A27)*(1+Model!F48+$A27)*(Model!F49+E$23)+Model!F20)*(1-Model!F50)/Model!F27 | F27: =(Valuation!$B$49*(1+Model!E48+$A27)*(1+Model!F48+$A27)*(Model!F49+F$23)+Model!F20)*(1-Model!F50)/Model!F27
A28: 0.02 | B28: =(Valuation!$B$49*(1+Model!E48+$A28)*(1+Model!F48+$A28)*(Model!F49+B$23)+Model!F20)*(1-Model!F50)/Model!F27 | C28: =(Valuation!$B$49*(1+Model!E48+$A28)*(1+Model!F48+$A28)*(Model!F49+C$23)+Model!F20)*(1-Model!F50)/Model!F27 | D28: =(Valuation!$B$49*(1+Model!E48+$A28)*(1+Model!F48+$A28)*(Model!F49+D$23)+Model!F20)*(1-Model!F50)/Model!F27 | E28: =(Valuation!$B$49*(1+Model!E48+$A28)*(1+Model!F48+$A28)*(Model!F49+E$23)+Model!F20)*(1-Model!F50)/Model!F27 | F28: =(Valuation!$B$49*(1+Model!E48+$A28)*(1+Model!F48+$A28)*(Model!F49+F$23)+Model!F20)*(1-Model!F50)/Model!F27
A30: Net interest and the share count are held at the base case in table 3.

Sheet Distribution
A1: NFLX: 12-month distribution (mix of lognormals around each scenario value)
A3: Scenario | B3: Probability | C3: Value at target date | D3: Story
A4: bear | B4: =Valuation!B81 | C4: ='Calc - bear'!$F$69 | D4: =Valuation!J81
A5: base | B5: =Valuation!B82 | C5: ='Calc - base'!$F$69 | D5: =Valuation!J82
A6: bull | B6: =Valuation!B83 | C6: ='Calc - bull'!$F$69 | D6: =Valuation!J83
A8: Probabilities sum to | B8: =SUM(B4:B6)
A9: Spread within each scenario | B9: =Valuation!$B$65
A10: Probability-weighted mean | B10: =($B$4*$C$4+$B$5*$C$5+$B$6*$C$6)*EXP($B$9^2/2)
A12: Quantile | B12: Price
A13: Median (model target) | B13: =SQRT(A60*B60)
A14: 10th percentile | B14: =SQRT(D60*E60)
A15: 25th percentile | B15: =SQRT(G60*H60)
A16: 75th percentile | B16: =SQRT(J60*K60)
A17: 90th percentile | B17: =SQRT(M60*N60)
A19: Each quantile solved by bisection (block: low, high, probability above the midpoint)
A20: Median (model target): low | B20: high | C20: P(above mid) | D20: 10th percentile: low | E20: high | F20: P(above mid) | G20: 25th percentile: low | H20: high | I20: P(above mid) | J20: 75th percentile: low | K20: high | L20: P(above mid) | M20: 90th percentile: low | N20: high | O20: P(above mid)
A21: =MIN($C$4,$C$5,$C$6)*0.2 | B21: =MAX($C$4,$C$5,$C$6)*4 | C21: =SUMPRODUCT($B$4:$B$6,1-NORMSDIST((LN(SQRT(A21*B21))-LN($C$4:$C$6))/$B$9)) | D21: =MIN($C$4,$C$5,$C$6)*0.2 | E21: =MAX($C$4,$C$5,$C$6)*4 | F21: =SUMPRODUCT($B$4:$B$6,1-NORMSDIST((LN(SQRT(D21*E21))-LN($C$4:$C$6))/$B$9)) | G21: =MIN($C$4,$C$5,$C$6)*0.2 | H21: =MAX($C$4,$C$5,$C$6)*4 | I21: =SUMPRODUCT($B$4:$B$6,1-NORMSDIST((LN(SQRT(G21*H21))-LN($C$4:$C$6))/$B$9)) | J21: =MIN($C$4,$C$5,$C$6)*0.2 | K21: =MAX($C$4,$C$5,$C$6)*4 | L21: =SUMPRODUCT($B$4:$B$6,1-NORMSDIST((LN(SQRT(J21*K21))-LN($C$4:$C$6))/$B$9)) | M21: =MIN($C$4,$C$5,$C$6)*0.2 | N21: =MAX($C$4,$C$5,$C$6)*4 | O21: =SUMPRODUCT($B$4:$B$6,1-NORMSDIST((LN(SQRT(M21*N21))-LN($C$4:$C$6))/$B$9))
A22: =IF(C21>0.5,SQRT(A21*B21),A21) | B22: =IF(C21>0.5,B21,SQRT(A21*B21)) | C22: =SUMPRODUCT($B$4:$B$6,1-NORMSDIST((LN(SQRT(A22*B22))-LN($C$4:$C$6))/$B$9)) | D22: =IF(F21>0.9,SQRT(D21*E21),D21) | E22: =IF(F21>0.9,E21,SQRT(D21*E21)) | F22: =SUMPRODUCT($B$4:$B$6,1-NORMSDIST((LN(SQRT(D22*E22))-LN($C$4:$C$6))/$B$9)) | G22: =IF(I21>0.75,SQRT(G21*H21),G21) | H22: =IF(I21>0.75,H21,SQRT(G21*H21)) | I22: =SUMPRODUCT($B$4:$B$6,1-NORMSDIST((LN(SQRT(G22*H22))-LN($C$4:$C$6))/$B$9)) | J22: =IF(L21>0.25,SQRT(J21*K21),J21) | K22: =IF(L21>0.25,K21,SQRT(J21*K21)) | L22: =SUMPRODUCT($B$4:$B$6,1-NORMSDIST((LN(SQRT(J22*K22))-LN($C$4:$C$6))/$B$9)) | M22: =IF(O21>0.09999999999999998,SQRT(M21*N21),M21) | N22: =IF(O21>0.09999999999999998,N21,SQRT(M21*N21)) | O22: =SUMPRODUCT($B$4:$B$6,1-NORMSDIST((LN(SQRT(M22*N22))-LN($C$4:$C$6))/$B$9))
A23: =IF(C22>0.5,SQRT(A22*B22),A22) | B23: =IF(C22>0.5,B22,SQRT(A22*B22)) | C23: =SUMPRODUCT($B$4:$B$6,1-NORMSDIST((LN(SQRT(A23*B23))-LN($C$4:$C$6))/$B$9)) | D23: =IF(F22>0.9,SQRT(D22*E22),D22) | E23: =IF(F22>0.9,E22,SQRT(D22*E22)) | F23: =SUMPRODUCT($B$4:$B$6,1-NORMSDIST((LN(SQRT(D23*E23))-LN($C$4:$C$6))/$B$9)) | G23: =IF(I22>0.75,SQRT(G22*H22),G22) | H23: =IF(I22>0.75,H22,SQRT(G22*H22)) | I23: =SUMPRODUCT($B$4:$B$6,1-NORMSDIST((LN(SQRT(G23*H23))-LN($C$4:$C$6))/$B$9)) | J23: =IF(L22>0.25,SQRT(J22*K22),J22) | K23: =IF(L22>0.25,K22,SQRT(J22*K22)) | L23: =SUMPRODUCT($B$4:$B$6,1-NORMSDIST((LN(SQRT(J23*K23))-LN($C$4:$C$6))/$B$9)) | M23: =IF(O22>0.09999999999999998,SQRT(M22*N22),M22) | N23: =IF(O22>0.09999999999999998,N22,SQRT(M22*N22)) | O23: =SUMPRODUCT($B$4:$B$6,1-NORMSDIST((LN(SQRT(M23*N23))-LN($C$4:$C$6))/$B$9))
A24: =IF(C23>0.5,SQRT(A23*B23),A23) | B24: =IF(C23>0.5,B23,SQRT(A23*B23)) | C24: =SUMPRODUCT($B$4:$B$6,1-NORMSDIST((LN(SQRT(A24*B24))-LN($C$4:$C$6))/$B$9)) | D24: =IF(F23>0.9,SQRT(D23*E23),D23) | E24: =IF(F23>0.9,E23,SQRT(D23*E23)) | F24: =SUMPRODUCT($B$4:$B$6,1-NORMSDIST((LN(SQRT(D24*E24))-LN($C$4:$C$6))/$B$9)) | G24: =IF(I23>0.75,SQRT(G23*H23),G23) | H24: =IF(I23>0.75,H23,SQRT(G23*H23)) | I24: =SUMPRODUCT($B$4:$B$6,1-NORMSDIST((LN(SQRT(G24*H24))-LN($C$4:$C$6))/$B$9)) | J24: =IF(L23>0.25,SQRT(J23*K23),J23) | K24: =IF(L23>0.25,K23,SQRT(J23*K23)) | L24: =SUMPRODUCT($B$4:$B$6,1-NORMSDIST((LN(SQRT(J24*K24))-LN($C$4:$C$6))/$B$9)) | M24: =IF(O23>0.09999999999999998,SQRT(M23*N23),M23) | N24: =IF(O23>0.09999999999999998,N23,SQRT(M23*N23)) | O24: =SUMPRODUCT($B$4:$B$6,1-NORMSDIST((LN(SQRT(M24*N24))-LN($C$4:$C$6))/$B$9))
A25: =IF(C24>0.5,SQRT(A24*B24),A24) | B25: =IF(C24>0.5,B24,SQRT(A24*B24)) | C25: =SUMPRODUCT($B$4:$B$6,1-NORMSDIST((LN(SQRT(A25*B25))-LN($C$4:$C$6))/$B$9)) | D25: =IF(F24>0.9,SQRT(D24*E24),D24) | E25: =IF(F24>0.9,E24,SQRT(D24*E24)) | F25: =SUMPRODUCT($B$4:$B$6,1-NORMSDIST((LN(SQRT(D25*E25))-LN($C$4:$C$6))/$B$9)) | G25: =IF(I24>0.75,SQRT(G24*H24),G24) | H25: =IF(I24>0.75,H24,SQRT(G24*H24)) | I25: =SUMPRODUCT($B$4:$B$6,1-NORMSDIST((LN(SQRT(G25*H25))-LN($C$4:$C$6))/$B$9)) | J25: =IF(L24>0.25,SQRT(J24*K24),J24) | K25: =IF(L24>0.25,K24,SQRT(J24*K24)) | L25: =SUMPRODUCT($B$4:$B$6,1-NORMSDIST((LN(SQRT(J25*K25))-LN($C$4:$C$6))/$B$9)) | M25: =IF(O24>0.09999999999999998,SQRT(M24*N24),M24) | N25: =IF(O24>0.09999999999999998,N24,SQRT(M24*N24)) | O25: =SUMPRODUCT($B$4:$B$6,1-NORMSDIST((LN(SQRT(M25*N25))-LN($C$4:$C$6))/$B$9))
A26: =IF(C25>0.5,SQRT(A25*B25),A25) | B26: =IF(C25>0.5,B25,SQRT(A25*B25)) | C26: =SUMPRODUCT($B$4:$B$6,1-NORMSDIST((LN(SQRT(A26*B26))-LN($C$4:$C$6))/$B$9)) | D26: =IF(F25>0.9,SQRT(D25*E25),D25) | E26: =IF(F25>0.9,E25,SQRT(D25*E25)) | F26: =SUMPRODUCT($B$4:$B$6,1-NORMSDIST((LN(SQRT(D26*E26))-LN($C$4:$C$6))/$B$9)) | G26: =IF(I25>0.75,SQRT(G25*H25),G25) | H26: =IF(I25>0.75,H25,SQRT(G25*H25)) | I26: =SUMPRODUCT($B$4:$B$6,1-NORMSDIST((LN(SQRT(G26*H26))-LN($C$4:$C$6))/$B$9)) | J26: =IF(L25>0.25,SQRT(J25*K25),J25) | K26: =IF(L25>0.25,K25,SQRT(J25*K25)) | L26: =SUMPRODUCT($B$4:$B$6,1-NORMSDIST((LN(SQRT(J26*K26))-LN($C$4:$C$6))/$B$9)) | M26: =IF(O25>0.09999999999999998,SQRT(M25*N25),M25) | N26: =IF(O25>0.09999999999999998,N25,SQRT(M25*N25)) | O26: =SUMPRODUCT($B$4:$B$6,1-NORMSDIST((LN(SQRT(M26*N26))-LN($C$4:$C$6))/$B$9))
A27: =IF(C26>0.5,SQRT(A26*B26),A26) | B27: =IF(C26>0.5,B26,SQRT(A26*B26)) | C27: =SUMPRODUCT($B$4:$B$6,1-NORMSDIST((LN(SQRT(A27*B27))-LN($C$4:$C$6))/$B$9)) | D27: =IF(F26>0.9,SQRT(D26*E26),D26) | E27: =IF(F26>0.9,E26,SQRT(D26*E26)) | F27: =SUMPRODUCT($B$4:$B$6,1-NORMSDIST((LN(SQRT(D27*E27))-LN($C$4:$C$6))/$B$9)) | G27: =IF(I26>0.75,SQRT(G26*H26),G26) | H27: =IF(I26>0.75,H26,SQRT(G26*H26)) | I27: =SUMPRODUCT($B$4:$B$6,1-NORMSDIST((LN(SQRT(G27*H27))-LN($C$4:$C$6))/$B$9)) | J27: =IF(L26>0.25,SQRT(J26*K26),J26) | K27: =IF(L26>0.25,K26,SQRT(J26*K26)) | L27: =SUMPRODUCT($B$4:$B$6,1-NORMSDIST((LN(SQRT(J27*K27))-LN($C$4:$C$6))/$B$9)) | M27: =IF(O26>0.09999999999999998,SQRT(M26*N26),M26) | N27: =IF(O26>0.09999999999999998,N26,SQRT(M26*N26)) | O27: =SUMPRODUCT($B$4:$B$6,1-NORMSDIST((LN(SQRT(M27*N27))-LN($C$4:$C$6))/$B$9))
A28: =IF(C27>0.5,SQRT(A27*B27),A27) | B28: =IF(C27>0.5,B27,SQRT(A27*B27)) | C28: =SUMPRODUCT($B$4:$B$6,1-NORMSDIST((LN(SQRT(A28*B28))-LN($C$4:$C$6))/$B$9)) | D28: =IF(F27>0.9,SQRT(D27*E27),D27) | E28: =IF(F27>0.9,E27,SQRT(D27*E27)) | F28: =SUMPRODUCT($B$4:$B$6,1-NORMSDIST((LN(SQRT(D28*E28))-LN($C$4:$C$6))/$B$9)) | G28: =IF(I27>0.75,SQRT(G27*H27),G27) | H28: =IF(I27>0.75,H27,SQRT(G27*H27)) | I28: =SUMPRODUCT($B$4:$B$6,1-NORMSDIST((LN(SQRT(G28*H28))-LN($C$4:$C$6))/$B$9)) | J28: =IF(L27>0.25,SQRT(J27*K27),J27) | K28: =IF(L27>0.25,K27,SQRT(J27*K27)) | L28: =SUMPRODUCT($B$4:$B$6,1-NORMSDIST((LN(SQRT(J28*K28))-LN($C$4:$C$6))/$B$9)) | M28: =IF(O27>0.09999999999999998,SQRT(M27*N27),M27) | N28: =IF(O27>0.09999999999999998,N27,SQRT(M27*N27)) | O28: =SUMPRODUCT($B$4:$B$6,1-NORMSDIST((LN(SQRT(M28*N28))-LN($C$4:$C$6))/$B$9))
A29: =IF(C28>0.5,SQRT(A28*B28),A28) | B29: =IF(C28>0.5,B28,SQRT(A28*B28)) | C29: =SUMPRODUCT($B$4:$B$6,1-NORMSDIST((LN(SQRT(A29*B29))-LN($C$4:$C$6))/$B$9)) | D29: =IF(F28>0.9,SQRT(D28*E28),D28) | E29: =IF(F28>0.9,E28,SQRT(D28*E28)) | F29: =SUMPRODUCT($B$4:$B$6,1-NORMSDIST((LN(SQRT(D29*E29))-LN($C$4:$C$6))/$B$9)) | G29: =IF(I28>0.75,SQRT(G28*H28),G28) | H29: =IF(I28>0.75,H28,SQRT(G28*H28)) | I29: =SUMPRODUCT($B$4:$B$6,1-NORMSDIST((LN(SQRT(G29*H29))-LN($C$4:$C$6))/$B$9)) | J29: =IF(L28>0.25,SQRT(J28*K28),J28) | K29: =IF(L28>0.25,K28,SQRT(J28*K28)) | L29: =SUMPRODUCT($B$4:$B$6,1-NORMSDIST((LN(SQRT(J29*K29))-LN($C$4:$C$6))/$B$9)) | M29: =IF(O28>0.09999999999999998,SQRT(M28*N28),M28) | N29: =IF(O28>0.09999999999999998,N28,SQRT(M28*N28)) | O29: =SUMPRODUCT($B$4:$B$6,1-NORMSDIST((LN(SQRT(M29*N29))-LN($C$4:$C$6))/$B$9))
A30: =IF(C29>0.5,SQRT(A29*B29),A29) | B30: =IF(C29>0.5,B29,SQRT(A29*B29)) | C30: =SUMPRODUCT($B$4:$B$6,1-NORMSDIST((LN(SQRT(A30*B30))-LN($C$4:$C$6))/$B$9)) | D30: =IF(F29>0.9,SQRT(D29*E29),D29) | E30: =IF(F29>0.9,E29,SQRT(D29*E29)) | F30: =SUMPRODUCT($B$4:$B$6,1-NORMSDIST((LN(SQRT(D30*E30))-LN($C$4:$C$6))/$B$9)) | G30: =IF(I29>0.75,SQRT(G29*H29),G29) | H30: =IF(I29>0.75,H29,SQRT(G29*H29)) | I30: =SUMPRODUCT($B$4:$B$6,1-NORMSDIST((LN(SQRT(G30*H30))-LN($C$4:$C$6))/$B$9)) | J30: =IF(L29>0.25,SQRT(J29*K29),J29) | K30: =IF(L29>0.25,K29,SQRT(J29*K29)) | L30: =SUMPRODUCT($B$4:$B$6,1-NORMSDIST((LN(SQRT(J30*K30))-LN($C$4:$C$6))/$B$9)) | M30: =IF(O29>0.09999999999999998,SQRT(M29*N29),M29) | N30: =IF(O29>0.09999999999999998,N29,SQRT(M29*N29)) | O30: =SUMPRODUCT($B$4:$B$6,1-NORMSDIST((LN(SQRT(M30*N30))-LN($C$4:$C$6))/$B$9))
A31: =IF(C30>0.5,SQRT(A30*B30),A30) | B31: =IF(C30>0.5,B30,SQRT(A30*B30)) | C31: =SUMPRODUCT($B$4:$B$6,1-NORMSDIST((LN(SQRT(A31*B31))-LN($C$4:$C$6))/$B$9)) | D31: =IF(F30>0.9,SQRT(D30*E30),D30) | E31: =IF(F30>0.9,E30,SQRT(D30*E30)) | F31: =SUMPRODUCT($B$4:$B$6,1-NORMSDIST((LN(SQRT(D31*E31))-LN($C$4:$C$6))/$B$9)) | G31: =IF(I30>0.75,SQRT(G30*H30),G30) | H31: =IF(I30>0.75,H30,SQRT(G30*H30)) | I31: =SUMPRODUCT($B$4:$B$6,1-NORMSDIST((LN(SQRT(G31*H31))-LN($C$4:$C$6))/$B$9)) | J31: =IF(L30>0.25,SQRT(J30*K30),J30) | K31: =IF(L30>0.25,K30,SQRT(J30*K30)) | L31: =SUMPRODUCT($B$4:$B$6,1-NORMSDIST((LN(SQRT(J31*K31))-LN($C$4:$C$6))/$B$9)) | M31: =IF(O30>0.09999999999999998,SQRT(M30*N30),M30) | N31: =IF(O30>0.09999999999999998,N30,SQRT(M30*N30)) | O31: =SUMPRODUCT($B$4:$B$6,1-NORMSDIST((LN(SQRT(M31*N31))-LN($C$4:$C$6))/$B$9))
A32: =IF(C31>0.5,SQRT(A31*B31),A31) | B32: =IF(C31>0.5,B31,SQRT(A31*B31)) | C32: =SUMPRODUCT($B$4:$B$6,1-NORMSDIST((LN(SQRT(A32*B32))-LN($C$4:$C$6))/$B$9)) | D32: =IF(F31>0.9,SQRT(D31*E31),D31) | E32: =IF(F31>0.9,E31,SQRT(D31*E31)) | F32: =SUMPRODUCT($B$4:$B$6,1-NORMSDIST((LN(SQRT(D32*E32))-LN($C$4:$C$6))/$B$9)) | G32: =IF(I31>0.75,SQRT(G31*H31),G31) | H32: =IF(I31>0.75,H31,SQRT(G31*H31)) | I32: =SUMPRODUCT($B$4:$B$6,1-NORMSDIST((LN(SQRT(G32*H32))-LN($C$4:$C$6))/$B$9)) | J32: =IF(L31>0.25,SQRT(J31*K31),J31) | K32: =IF(L31>0.25,K31,SQRT(J31*K31)) | L32: =SUMPRODUCT($B$4:$B$6,1-NORMSDIST((LN(SQRT(J32*K32))-LN($C$4:$C$6))/$B$9)) | M32: =IF(O31>0.09999999999999998,SQRT(M31*N31),M31) | N32: =IF(O31>0.09999999999999998,N31,SQRT(M31*N31)) | O32: =SUMPRODUCT($B$4:$B$6,1-NORMSDIST((LN(SQRT(M32*N32))-LN($C$4:$C$6))/$B$9))
A33: =IF(C32>0.5,SQRT(A32*B32),A32) | B33: =IF(C32>0.5,B32,SQRT(A32*B32)) | C33: =SUMPRODUCT($B$4:$B$6,1-NORMSDIST((LN(SQRT(A33*B33))-LN($C$4:$C$6))/$B$9)) | D33: =IF(F32>0.9,SQRT(D32*E32),D32) | E33: =IF(F32>0.9,E32,SQRT(D32*E32)) | F33: =SUMPRODUCT($B$4:$B$6,1-NORMSDIST((LN(SQRT(D33*E33))-LN($C$4:$C$6))/$B$9)) | G33: =IF(I32>0.75,SQRT(G32*H32),G32) | H33: =IF(I32>0.75,H32,SQRT(G32*H32)) | I33: =SUMPRODUCT($B$4:$B$6,1-NORMSDIST((LN(SQRT(G33*H33))-LN($C$4:$C$6))/$B$9)) | J33: =IF(L32>0.25,SQRT(J32*K32),J32) | K33: =IF(L32>0.25,K32,SQRT(J32*K32)) | L33: =SUMPRODUCT($B$4:$B$6,1-NORMSDIST((LN(SQRT(J33*K33))-LN($C$4:$C$6))/$B$9)) | M33: =IF(O32>0.09999999999999998,SQRT(M32*N32),M32) | N33: =IF(O32>0.09999999999999998,N32,SQRT(M32*N32)) | O33: =SUMPRODUCT($B$4:$B$6,1-NORMSDIST((LN(SQRT(M33*N33))-LN($C$4:$C$6))/$B$9))
... A60: =IF(C59>0.5,SQRT(A59*B59),A59) | B60: =IF(C59>0.5,B59,SQRT(A59*B59)) | C60: =SUMPRODUCT($B$4:$B$6,1-NORMSDIST((LN(SQRT(A60*B60))-LN($C$4:$C$6))/$B$9)) | D60: =IF(F59>0.9,SQRT(D59*E59),D59) | E60: =IF(F59>0.9,E59,SQRT(D59*E59)) | F60: =SUMPRODUCT($B$4:$B$6,1-NORMSDIST((LN(SQRT(D60*E60))-LN($C$4:$C$6))/$B$9)) | G60: =IF(I59>0.75,SQRT(G59*H59),G59) | H60: =IF(I59>0.75,H59,SQRT(G59*H59)) | I60: =SUMPRODUCT($B$4:$B$6,1-NORMSDIST((LN(SQRT(G60*H60))-LN($C$4:$C$6))/$B$9)) | J60: =IF(L59>0.25,SQRT(J59*K59),J59) | K60: =IF(L59>0.25,K59,SQRT(J59*K59)) | L60: =SUMPRODUCT($B$4:$B$6,1-NORMSDIST((LN(SQRT(J60*K60))-LN($C$4:$C$6))/$B$9)) | M60: =IF(O59>0.09999999999999998,SQRT(M59*N59),M59) | N60: =IF(O59>0.09999999999999998,N59,SQRT(M59*N59)) | O60: =SUMPRODUCT($B$4:$B$6,1-NORMSDIST((LN(SQRT(M60*N60))-LN($C$4:$C$6))/$B$9))

Sheet Calc - research target (12m)
A1: NFLX engine calculation: research target (12m) (reconciled set, no scenario deltas)
A2: Machinery behind the Valuation and Distribution tabs; drivers come from Model, assumptions from Valuation.
A4: Scenario Growth Δ | B4: 0
A5: Scenario Margin Δ | B5: 0
A6: Scenario Multiple Δ (turns) | B6: 0
A7: Scenario WACC Δ | B7: 0
A8: Scenario Multiple %Δ | B8: 0
A9: Scenario Stated EPS/FCF %Δ | B9: 0
A10: Scenario Custom %Δ | B10: 0
A12: WACC | B12: =Valuation!$B$50+B7
A13: Years from last FY end to target date | B13: =(Valuation!$B$44-Valuation!$B$48)/365.25
A14: Years from last FY end to balance date | B14: =(Valuation!$B$54-Valuation!$B$48)/365.25
A15: Years from last FY end to share count date | B15: =(Valuation!$B$60-Valuation!$B$48)/365.25
A16: Projected years | B16: 3
A18: Projection | B18: Base | C18: =Model!E5 | D18: =Model!F5 | E18: =Model!G5
A19: Year index | B19: 0 | C19: 1 | D19: 2 | E19: 3
A20: Period end | C20: =Valuation!$B$48+ROUND(365.25*C19,0) | D20: =Valuation!$B$48+ROUND(365.25*D19,0) | E20: =Valuation!$B$48+ROUND(365.25*E19,0)
A21: Revenue growth | C21: =Model!E48+$B$4 | D21: =Model!F48+$B$4 | E21: =Model!G48+$B$4
A22: Revenue | B22: =Valuation!$B$49 | C22: =B22*(1+C21) | D22: =C22*(1+D21) | E22: =D22*(1+E21)
A23: EBIT margin | C23: =Model!E49+$B$5 | D23: =Model!F49+$B$5 | E23: =Model!G49+$B$5
A24: EBIT | C24: =C22*C23 | D24: =D22*D23 | E24: =E22*E23
A25: Tax rate | C25: =Model!E50 | D25: =Model!F50 | E25: =Model!G50
A26: NOPAT | C26: =C24*(1-C25) | D26: =D24*(1-D25) | E26: =E24*(1-E25)
A27: D&A | C27: =C22*(Model!E51) | D27: =D22*(Model!F51) | E27: =E22*(Model!G51)
A28: Capex | C28: =C22*(Model!E52) | D28: =D22*(Model!F52) | E28: =E22*(Model!G52)
A29: Working capital increase | C29: =(Model!E53)*(C22-B22) | D29: =(Model!F53)*(D22-C22) | E29: =(Model!G53)*(E22-D22)
A30: Stock comp | C30: =C22*(Model!E54) | D30: =D22*(Model!F54) | E30: =E22*(Model!G54)
A31: Free cash flow to firm | C31: =C26+C27-C28-C29-IF(AND(Valuation!$B$46="adjusted",Valuation!$B$47="cost"),C30*(1-C25),0) | D31: =D26+D27-D28-D29-IF(AND(Valuation!$B$46="adjusted",Valuation!$B$47="cost"),D30*(1-D25),0) | E31: =E26+E27-E28-E29-IF(AND(Valuation!$B$46="adjusted",Valuation!$B$47="cost"),E30*(1-E25),0)
A32: EBITDA | C32: =C24+C27 | D32: =D24+D27 | E32: =E24+E27
A33: Adj. EBITDA | C33: =C24+C27+C22*(Model!E58) | D33: =D24+D27+D22*(Model!F58) | E33: =E24+E27+E22*(Model!G58)
A34: Shareholder returns + other uses | C34: =C22*Model!E56+Model!E55+Model!E57 | D34: =D22*Model!F56+Model!F55+Model!F57 | E34: =E22*Model!G56+Model!G55+Model!G57
A35: Share of year after target date | C35: =IF(C19<=$B$13,0,C19-MAX(C19-1,$B$13)) | D35: =IF(D19<=$B$13,0,D19-MAX(D19-1,$B$13)) | E35: =IF(E19<=$B$13,0,E19-MAX(E19-1,$B$13))
A36: PV at target date of FCFF | C36: =IF(C35=0,0,C31*C35/(1+$B$12)^(C19-$B$13)) | D36: =IF(D35=0,0,D31*D35/(1+$B$12)^(D19-$B$13)) | E36: =IF(E35=0,0,E31*E35/(1+$B$12)^(E19-$B$13))
A37: Overlap: balance date to target date | C37: =MAX(0,MIN(C19,$B$13)-MAX(C19-1,$B$14)) | D37: =MAX(0,MIN(D19,$B$13)-MAX(D19-1,$B$14)) | E37: =MAX(0,MIN(E19,$B$13)-MAX(E19-1,$B$14))
A38: NTM weight at target date | C38: =MAX(0,MIN(C19,$B$13+1)-MAX(C19-1,$B$13)) | D38: =MAX(0,MIN(D19,$B$13+1)-MAX(D19-1,$B$13)) | E38: =MAX(0,MIN(E19,$B$13+1)-MAX(E19-1,$B$13))
A39: LTM weight at target date | B39: =MAX(0,MIN(0,$B$13)-MAX(-1,$B$13-1)) | C39: =MAX(0,MIN(C19,$B$13)-MAX(C19-1,$B$13-1)) | D39: =MAX(0,MIN(D19,$B$13)-MAX(D19-1,$B$13-1)) | E39: =MAX(0,MIN(E19,$B$13)-MAX(E19-1,$B$13-1))
A41: Value at the target date
A42: PV of free cash flow after the target date | B42: =SUM($C$36:$E$36)
A43: Terminal value at final year | B43: =IF(Valuation!$B$51="exit_multiple",Valuation!$B$53*E32,E31*(1+Valuation!$B$52)/($B$12-Valuation!$B$52))
A44: PV of terminal value at target date | B44: =B43/(1+$B$12)^($B$16-$B$13)
A45: DCF enterprise value at target date | B45: =B42+B44
A46: Terminal value share of DCF | B46: =B44/B45
A47: Free cash flow earned, balance date to target date | B47: =SUMPRODUCT($C$37:$E$37,$C$31:$E$31)
A48: Shareholder returns + other uses paid | B48: =SUMPRODUCT($C$37:$E$37,$C$34:$E$34)
A49: Interest drag on net debt | B49: =Valuation!$B$57*(1-$C$25)*MAX(Valuation!$B$55,0)*MAX($B$13-$B$14,0)
A50: Net debt at target date | B50: =IF(Valuation!$B$58="",Valuation!$B$55-B47+B49+B48,Valuation!$B$58)
A51: Minority interests | B51: =Valuation!$B$56
A52: Adjustments (probability-weighted) | B52: =(Valuation!B75)*Valuation!C75+0
A53: Diluted shares at target date (M) | B53: =IF(Valuation!$B$62="",Valuation!$B$59*(1+Valuation!$B$61)^MAX($B$13-$B$15,0),Valuation!$B$62)
A54: After-tax interest on target-date net debt | B54: =Valuation!$B$57*(1-$C$25)*MAX(B50,0)
A55: Check: WACC vs terminal growth | B55: =IF(AND(Valuation!$B$51<>"exit_multiple",$B$12<=Valuation!$B$52+0.01),"WACC must exceed terminal growth by 1 point","ok")
A56: Check: projection length | B56: =IF(OR($B$13>=$B$16-1,$B$13+1>$B$16),"add projected years past the target date","ok")
A58: Metric at target date | B58: Next 12 months | C58: Last 12 months
A59: Revenue | B59: =SUMPRODUCT($C$38:$E$38,$C$22:$E$22) | C59: =SUMPRODUCT($C$39:$E$39,$C$22:$E$22)+$B$39*$B$22
A60: EBIT | B60: =SUMPRODUCT($C$38:$E$38,$C$24:$E$24) | C60: =SUMPRODUCT($C$39:$E$39,$C$24:$E$24)
A61: EBITDA | B61: =SUMPRODUCT($C$38:$E$38,$C$32:$E$32) | C61: =SUMPRODUCT($C$39:$E$39,$C$32:$E$32)
A62: Adj. EBITDA | B62: =SUMPRODUCT($C$38:$E$38,$C$33:$E$33) | C62: =SUMPRODUCT($C$39:$E$39,$C$33:$E$33)
A63: NOPAT | B63: =SUMPRODUCT($C$38:$E$38,$C$26:$E$26) | C63: =SUMPRODUCT($C$39:$E$39,$C$26:$E$26)
A64: Free cash flow to firm | B64: =SUMPRODUCT($C$38:$E$38,$C$31:$E$31) | C64: =SUMPRODUCT($C$39:$E$39,$C$31:$E$31)
A66: Valuation method | B66: Metric | C66: Multiple used | D66: Basis | E66: Metric at target date | F66: Value per share | G66: Weight | H66: Metric key | I66: Metric shown (stated per-share figure when used)
A67: DCF (cash flow to target date + terminal) | F67: =((B45)-$B$50-$B$51+$B$52)/$B$53 | G67: =Valuation!$B$63
A68: ="Multiple: "&Valuation!A69&" ("&Valuation!D69&")" | B68: =Valuation!A69 | C68: =IF(B68="FCF yield",(Valuation!B69)*(1-$B$8),(Valuation!B69)+IF(B68="EV/sales",0.1,1)*$B$6) | D68: =Valuation!D69 | E68: =IF(D68="ltm",CHOOSE(H68,$C$59,$C$60,$C$61,$C$62,$C$63,$C$64),CHOOSE(H68,$B$59,$B$60,$B$61,$B$62,$B$63,$B$64)) | F68: =IF(OR(B68="EV/EBITDA",B68="EV/sales",B68="EV/EBIT"),((C68*E68)-$B$50-$B$51+$B$52)/$B$53,IF(B68="P/E",IF(Valuation!F69<>"",C68*(Valuation!F69)*(1+$B$9),C68*(E68-$B$54)/$B$53),IF(Valuation!G69<>"",(Valuation!G69)*(1+$B$9)/C68,(E68-IF(Valuation!H69,$B$54,0))/C68/$B$53))+$B$52/$B$53) | G68: =Valuation!C69 | H68: =IF(B68="EV/sales",1,IF(B68="EV/EBIT",2,IF(B68="EV/EBITDA",IF(Valuation!E69="adjusted",4,3),IF(B68="P/E",5,6)))) | I68: =IF(AND(B68="P/E",Valuation!F69<>""),(Valuation!F69)*(1+$B$9),IF(AND(B68="FCF yield",Valuation!G69<>""),(Valuation!G69)*(1+$B$9),E68))
A69: Value per share at target date (weighted methods) | F69: =SUMPRODUCT(F67:F68,G67:G68)/SUM(G67:G68)

Sheet Calc - bear
A1: NFLX engine calculation: bear scenario
A2: Machinery behind the Valuation and Distribution tabs; drivers come from Model, assumptions from Valuation.
A4: Scenario Growth Δ | B4: =N(Valuation!C81)
A5: Scenario Margin Δ | B5: =N(Valuation!D81)
A6: Scenario Multiple Δ (turns) | B6: =N(Valuation!E81)
A7: Scenario WACC Δ | B7: =N(Valuation!F81)
A8: Scenario Multiple %Δ | B8: =N(Valuation!G81)
A9: Scenario Stated EPS/FCF %Δ | B9: =N(Valuation!H81)
A10: Scenario Custom %Δ | B10: =N(Valuation!I81)
A12: WACC | B12: =Valuation!$B$50+B7
A13: Years from last FY end to target date | B13: =(Valuation!$B$44-Valuation!$B$48)/365.25
A14: Years from last FY end to balance date | B14: =(Valuation!$B$54-Valuation!$B$48)/365.25
A15: Years from last FY end to share count date | B15: =(Valuation!$B$60-Valuation!$B$48)/365.25
A16: Projected years | B16: 3
A18: Projection | B18: Base | C18: =Model!E5 | D18: =Model!F5 | E18: =Model!G5
A19: Year index | B19: 0 | C19: 1 | D19: 2 | E19: 3
A20: Period end | C20: =Valuation!$B$48+ROUND(365.25*C19,0) | D20: =Valuation!$B$48+ROUND(365.25*D19,0) | E20: =Valuation!$B$48+ROUND(365.25*E19,0)
A21: Revenue growth | C21: =Model!E48+$B$4+$B$250 | D21: =Model!F48+$B$4+$B$253 | E21: =Model!G48+$B$4+$B$256
A22: Revenue | B22: =Valuation!$B$49 | C22: =B22*(1+C21) | D22: =C22*(1+D21) | E22: =D22*(1+E21)
A23: EBIT margin | C23: =Model!E49+$B$5+$B$251 | D23: =Model!F49+$B$5+$B$254 | E23: =Model!G49+$B$5+$B$257
A24: EBIT | C24: =C22*C23 | D24: =D22*D23 | E24: =E22*E23
A25: Tax rate | C25: =Model!E50 | D25: =Model!F50 | E25: =Model!G50
A26: NOPAT | C26: =C24*(1-C25) | D26: =D24*(1-D25) | E26: =E24*(1-E25)
A27: D&A | C27: =C22*(Model!E51) | D27: =D22*(Model!F51) | E27: =E22*(Model!G51)
A28: Capex | C28: =C22*(Model!E52+$B$252) | D28: =D22*(Model!F52+$B$255) | E28: =E22*(Model!G52+$B$258)
A29: Working capital increase | C29: =(Model!E53)*(C22-B22) | D29: =(Model!F53)*(D22-C22) | E29: =(Model!G53)*(E22-D22)
A30: Stock comp | C30: =C22*(Model!E54) | D30: =D22*(Model!F54) | E30: =E22*(Model!G54)
A31: Free cash flow to firm | C31: =C26+C27-C28-C29-IF(AND(Valuation!$B$46="adjusted",Valuation!$B$47="cost"),C30*(1-C25),0) | D31: =D26+D27-D28-D29-IF(AND(Valuation!$B$46="adjusted",Valuation!$B$47="cost"),D30*(1-D25),0) | E31: =E26+E27-E28-E29-IF(AND(Valuation!$B$46="adjusted",Valuation!$B$47="cost"),E30*(1-E25),0)
A32: EBITDA | C32: =C24+C27 | D32: =D24+D27 | E32: =E24+E27
A33: Adj. EBITDA | C33: =C24+C27+C22*(Model!E58) | D33: =D24+D27+D22*(Model!F58) | E33: =E24+E27+E22*(Model!G58)
A34: Shareholder returns + other uses | C34: =C22*Model!E56+Model!E55+Model!E57 | D34: =D22*Model!F56+Model!F55+Model!F57 | E34: =E22*Model!G56+Model!G55+Model!G57
A35: Share of year after target date | C35: =IF(C19<=$B$13,0,C19-MAX(C19-1,$B$13)) | D35: =IF(D19<=$B$13,0,D19-MAX(D19-1,$B$13)) | E35: =IF(E19<=$B$13,0,E19-MAX(E19-1,$B$13))
A36: PV at target date of FCFF | C36: =IF(C35=0,0,C31*C35/(1+$B$12)^(C19-$B$13)) | D36: =IF(D35=0,0,D31*D35/(1+$B$12)^(D19-$B$13)) | E36: =IF(E35=0,0,E31*E35/(1+$B$12)^(E19-$B$13))
A37: Overlap: balance date to target date | C37: =MAX(0,MIN(C19,$B$13)-MAX(C19-1,$B$14)) | D37: =MAX(0,MIN(D19,$B$13)-MAX(D19-1,$B$14)) | E37: =MAX(0,MIN(E19,$B$13)-MAX(E19-1,$B$14))
A38: NTM weight at target date | C38: =MAX(0,MIN(C19,$B$13+1)-MAX(C19-1,$B$13)) | D38: =MAX(0,MIN(D19,$B$13+1)-MAX(D19-1,$B$13)) | E38: =MAX(0,MIN(E19,$B$13+1)-MAX(E19-1,$B$13))
A39: LTM weight at target date | B39: =MAX(0,MIN(0,$B$13)-MAX(-1,$B$13-1)) | C39: =MAX(0,MIN(C19,$B$13)-MAX(C19-1,$B$13-1)) | D39: =MAX(0,MIN(D19,$B$13)-MAX(D19-1,$B$13-1)) | E39: =MAX(0,MIN(E19,$B$13)-MAX(E19-1,$B$13-1))
A41: Value at the target date
A42: PV of free cash flow after the target date | B42: =SUM($C$36:$E$36)
A43: Terminal value at final year | B43: =IF(Valuation!$B$51="exit_multiple",Valuation!$B$53*E32,E31*(1+Valuation!$B$52)/($B$12-Valuation!$B$52))
A44: PV of terminal value at target date | B44: =B43/(1+$B$12)^($B$16-$B$13)
A45: DCF enterprise value at target date | B45: =B42+B44
A46: Terminal value share of DCF | B46: =B44/B45
A47: Free cash flow earned, balance date to target date | B47: =SUMPRODUCT($C$37:$E$37,$C$31:$E$31)
A48: Shareholder returns + other uses paid | B48: =SUMPRODUCT($C$37:$E$37,$C$34:$E$34)
A49: Interest drag on net debt | B49: =Valuation!$B$57*(1-$C$25)*MAX(Valuation!$B$55,0)*MAX($B$13-$B$14,0)
A50: Net debt at target date | B50: =IF(Valuation!$B$58="",Valuation!$B$55-B47+B49+B48,Valuation!$B$58)
A51: Minority interests | B51: =Valuation!$B$56
A52: Adjustments (probability-weighted) | B52: =(Valuation!B75)*Valuation!C75+0
A53: Diluted shares at target date (M) | B53: =IF(Valuation!$B$62="",Valuation!$B$59*(1+Valuation!$B$61)^MAX($B$13-$B$15,0),Valuation!$B$62)
A54: After-tax interest on target-date net debt | B54: =Valuation!$B$57*(1-$C$25)*MAX(B50,0)
A55: Check: WACC vs terminal growth | B55: =IF(AND(Valuation!$B$51<>"exit_multiple",$B$12<=Valuation!$B$52+0.01),"WACC must exceed terminal growth by 1 point","ok")
A56: Check: projection length | B56: =IF(OR($B$13>=$B$16-1,$B$13+1>$B$16),"add projected years past the target date","ok")
A58: Metric at target date | B58: Next 12 months | C58: Last 12 months
A59: Revenue | B59: =SUMPRODUCT($C$38:$E$38,$C$22:$E$22) | C59: =SUMPRODUCT($C$39:$E$39,$C$22:$E$22)+$B$39*$B$22
A60: EBIT | B60: =SUMPRODUCT($C$38:$E$38,$C$24:$E$24) | C60: =SUMPRODUCT($C$39:$E$39,$C$24:$E$24)
A61: EBITDA | B61: =SUMPRODUCT($C$38:$E$38,$C$32:$E$32) | C61: =SUMPRODUCT($C$39:$E$39,$C$32:$E$32)
A62: Adj. EBITDA | B62: =SUMPRODUCT($C$38:$E$38,$C$33:$E$33) | C62: =SUMPRODUCT($C$39:$E$39,$C$33:$E$33)
A63: NOPAT | B63: =SUMPRODUCT($C$38:$E$38,$C$26:$E$26) | C63: =SUMPRODUCT($C$39:$E$39,$C$26:$E$26)
A64: Free cash flow to firm | B64: =SUMPRODUCT($C$38:$E$38,$C$31:$E$31) | C64: =SUMPRODUCT($C$39:$E$39,$C$31:$E$31)
A66: Valuation method | B66: Metric | C66: Multiple used | D66: Basis | E66: Metric at target date | F66: Value per share | G66: Weight | H66: Metric key | I66: Metric shown (stated per-share figure when used)
A67: DCF (cash flow to target date + terminal) | F67: =((B45)-$B$50-$B$51+$B$52)/$B$53 | G67: =Valuation!$B$63
A68: ="Multiple: "&Valuation!A69&" ("&Valuation!D69&")" | B68: =Valuation!A69 | C68: =IF(B68="FCF yield",(Valuation!B69)*(1-$B$8),(Valuation!B69)+IF(B68="EV/sales",0.1,1)*$B$6) | D68: =Valuation!D69 | E68: =IF(D68="ltm",CHOOSE(H68,$C$59,$C$60,$C$61,$C$62,$C$63,$C$64),CHOOSE(H68,$B$59,$B$60,$B$61,$B$62,$B$63,$B$64)) | F68: =IF(OR(B68="EV/EBITDA",B68="EV/sales",B68="EV/EBIT"),((C68*E68)-$B$50-$B$51+$B$52)/$B$53,IF(B68="P/E",IF(Valuation!F69<>"",C68*(Valuation!F69)*(1+$B$9),C68*(E68-$B$54)/$B$53),IF(Valuation!G69<>"",(Valuation!G69)*(1+$B$9)/C68,(E68-IF(Valuation!H69,$B$54,0))/C68/$B$53))+$B$52/$B$53) | G68: =Valuation!C69 | H68: =IF(B68="EV/sales",1,IF(B68="EV/EBIT",2,IF(B68="EV/EBITDA",IF(Valuation!E69="adjusted",4,3),IF(B68="P/E",5,6)))) | I68: =IF(AND(B68="P/E",Valuation!F69<>""),(Valuation!F69)*(1+$B$9),IF(AND(B68="FCF yield",Valuation!G69<>""),(Valuation!G69)*(1+$B$9),E68))
A69: Value per share at target date (weighted methods) | F69: =SUMPRODUCT(F67:F68,G67:G68)/SUM(G67:G68)
A249: Driver scenario shifts: line-item changes model_drivers.py resolves from this scenario's driver deltas (added to the Model tab inputs)
A250: Revenue growth, year 1 | B250: -0.051811522
A251: EBIT margin, year 1 | B251: -0.026118007
A252: Capex % revenue, year 1 | B252: 0.0020603753
A253: Revenue growth, year 2 | B253: -0.0020853197
A254: EBIT margin, year 2 | B254: -0.027137659
A255: Capex % revenue, year 2 | B255: 0.002107673
A256: Revenue growth, year 3 | B256: -0.0016740987
A257: EBIT margin, year 3 | B257: -0.028079277
A258: Capex % revenue, year 3 | B258: 0.0021536723

Sheet Calc - base
A1: NFLX engine calculation: base scenario
A2: Machinery behind the Valuation and Distribution tabs; drivers come from Model, assumptions from Valuation.
A4: Scenario Growth Δ | B4: =N(Valuation!C82)
A5: Scenario Margin Δ | B5: =N(Valuation!D82)
A6: Scenario Multiple Δ (turns) | B6: =N(Valuation!E82)
A7: Scenario WACC Δ | B7: =N(Valuation!F82)
A8: Scenario Multiple %Δ | B8: =N(Valuation!G82)
A9: Scenario Stated EPS/FCF %Δ | B9: =N(Valuation!H82)
A10: Scenario Custom %Δ | B10: =N(Valuation!I82)
A12: WACC | B12: =Valuation!$B$50+B7
A13: Years from last FY end to target date | B13: =(Valuation!$B$44-Valuation!$B$48)/365.25
A14: Years from last FY end to balance date | B14: =(Valuation!$B$54-Valuation!$B$48)/365.25
A15: Years from last FY end to share count date | B15: =(Valuation!$B$60-Valuation!$B$48)/365.25
A16: Projected years | B16: 3
A18: Projection | B18: Base | C18: =Model!E5 | D18: =Model!F5 | E18: =Model!G5
A19: Year index | B19: 0 | C19: 1 | D19: 2 | E19: 3
A20: Period end | C20: =Valuation!$B$48+ROUND(365.25*C19,0) | D20: =Valuation!$B$48+ROUND(365.25*D19,0) | E20: =Valuation!$B$48+ROUND(365.25*E19,0)
A21: Revenue growth | C21: =Model!E48+$B$4 | D21: =Model!F48+$B$4 | E21: =Model!G48+$B$4
A22: Revenue | B22: =Valuation!$B$49 | C22: =B22*(1+C21) | D22: =C22*(1+D21) | E22: =D22*(1+E21)
A23: EBIT margin | C23: =Model!E49+$B$5 | D23: =Model!F49+$B$5 | E23: =Model!G49+$B$5
A24: EBIT | C24: =C22*C23 | D24: =D22*D23 | E24: =E22*E23
A25: Tax rate | C25: =Model!E50 | D25: =Model!F50 | E25: =Model!G50
A26: NOPAT | C26: =C24*(1-C25) | D26: =D24*(1-D25) | E26: =E24*(1-E25)
A27: D&A | C27: =C22*(Model!E51) | D27: =D22*(Model!F51) | E27: =E22*(Model!G51)
A28: Capex | C28: =C22*(Model!E52) | D28: =D22*(Model!F52) | E28: =E22*(Model!G52)
A29: Working capital increase | C29: =(Model!E53)*(C22-B22) | D29: =(Model!F53)*(D22-C22) | E29: =(Model!G53)*(E22-D22)
A30: Stock comp | C30: =C22*(Model!E54) | D30: =D22*(Model!F54) | E30: =E22*(Model!G54)
A31: Free cash flow to firm | C31: =C26+C27-C28-C29-IF(AND(Valuation!$B$46="adjusted",Valuation!$B$47="cost"),C30*(1-C25),0) | D31: =D26+D27-D28-D29-IF(AND(Valuation!$B$46="adjusted",Valuation!$B$47="cost"),D30*(1-D25),0) | E31: =E26+E27-E28-E29-IF(AND(Valuation!$B$46="adjusted",Valuation!$B$47="cost"),E30*(1-E25),0)
A32: EBITDA | C32: =C24+C27 | D32: =D24+D27 | E32: =E24+E27
A33: Adj. EBITDA | C33: =C24+C27+C22*(Model!E58) | D33: =D24+D27+D22*(Model!F58) | E33: =E24+E27+E22*(Model!G58)
A34: Shareholder returns + other uses | C34: =C22*Model!E56+Model!E55+Model!E57 | D34: =D22*Model!F56+Model!F55+Model!F57 | E34: =E22*Model!G56+Model!G55+Model!G57
A35: Share of year after target date | C35: =IF(C19<=$B$13,0,C19-MAX(C19-1,$B$13)) | D35: =IF(D19<=$B$13,0,D19-MAX(D19-1,$B$13)) | E35: =IF(E19<=$B$13,0,E19-MAX(E19-1,$B$13))
A36: PV at target date of FCFF | C36: =IF(C35=0,0,C31*C35/(1+$B$12)^(C19-$B$13)) | D36: =IF(D35=0,0,D31*D35/(1+$B$12)^(D19-$B$13)) | E36: =IF(E35=0,0,E31*E35/(1+$B$12)^(E19-$B$13))
A37: Overlap: balance date to target date | C37: =MAX(0,MIN(C19,$B$13)-MAX(C19-1,$B$14)) | D37: =MAX(0,MIN(D19,$B$13)-MAX(D19-1,$B$14)) | E37: =MAX(0,MIN(E19,$B$13)-MAX(E19-1,$B$14))
A38: NTM weight at target date | C38: =MAX(0,MIN(C19,$B$13+1)-MAX(C19-1,$B$13)) | D38: =MAX(0,MIN(D19,$B$13+1)-MAX(D19-1,$B$13)) | E38: =MAX(0,MIN(E19,$B$13+1)-MAX(E19-1,$B$13))
A39: LTM weight at target date | B39: =MAX(0,MIN(0,$B$13)-MAX(-1,$B$13-1)) | C39: =MAX(0,MIN(C19,$B$13)-MAX(C19-1,$B$13-1)) | D39: =MAX(0,MIN(D19,$B$13)-MAX(D19-1,$B$13-1)) | E39: =MAX(0,MIN(E19,$B$13)-MAX(E19-1,$B$13-1))
A41: Value at the target date
A42: PV of free cash flow after the target date | B42: =SUM($C$36:$E$36)
A43: Terminal value at final year | B43: =IF(Valuation!$B$51="exit_multiple",Valuation!$B$53*E32,E31*(1+Valuation!$B$52)/($B$12-Valuation!$B$52))
A44: PV of terminal value at target date | B44: =B43/(1+$B$12)^($B$16-$B$13)
A45: DCF enterprise value at target date | B45: =B42+B44
A46: Terminal value share of DCF | B46: =B44/B45
A47: Free cash flow earned, balance date to target date | B47: =SUMPRODUCT($C$37:$E$37,$C$31:$E$31)
A48: Shareholder returns + other uses paid | B48: =SUMPRODUCT($C$37:$E$37,$C$34:$E$34)
A49: Interest drag on net debt | B49: =Valuation!$B$57*(1-$C$25)*MAX(Valuation!$B$55,0)*MAX($B$13-$B$14,0)
A50: Net debt at target date | B50: =IF(Valuation!$B$58="",Valuation!$B$55-B47+B49+B48,Valuation!$B$58)
A51: Minority interests | B51: =Valuation!$B$56
A52: Adjustments (probability-weighted) | B52: =(Valuation!B75)*Valuation!C75+0
A53: Diluted shares at target date (M) | B53: =IF(Valuation!$B$62="",Valuation!$B$59*(1+Valuation!$B$61)^MAX($B$13-$B$15,0),Valuation!$B$62)
A54: After-tax interest on target-date net debt | B54: =Valuation!$B$57*(1-$C$25)*MAX(B50,0)
A55: Check: WACC vs terminal growth | B55: =IF(AND(Valuation!$B$51<>"exit_multiple",$B$12<=Valuation!$B$52+0.01),"WACC must exceed terminal growth by 1 point","ok")
A56: Check: projection length | B56: =IF(OR($B$13>=$B$16-1,$B$13+1>$B$16),"add projected years past the target date","ok")
A58: Metric at target date | B58: Next 12 months | C58: Last 12 months
A59: Revenue | B59: =SUMPRODUCT($C$38:$E$38,$C$22:$E$22) | C59: =SUMPRODUCT($C$39:$E$39,$C$22:$E$22)+$B$39*$B$22
A60: EBIT | B60: =SUMPRODUCT($C$38:$E$38,$C$24:$E$24) | C60: =SUMPRODUCT($C$39:$E$39,$C$24:$E$24)
A61: EBITDA | B61: =SUMPRODUCT($C$38:$E$38,$C$32:$E$32) | C61: =SUMPRODUCT($C$39:$E$39,$C$32:$E$32)
A62: Adj. EBITDA | B62: =SUMPRODUCT($C$38:$E$38,$C$33:$E$33) | C62: =SUMPRODUCT($C$39:$E$39,$C$33:$E$33)
A63: NOPAT | B63: =SUMPRODUCT($C$38:$E$38,$C$26:$E$26) | C63: =SUMPRODUCT($C$39:$E$39,$C$26:$E$26)
A64: Free cash flow to firm | B64: =SUMPRODUCT($C$38:$E$38,$C$31:$E$31) | C64: =SUMPRODUCT($C$39:$E$39,$C$31:$E$31)
A66: Valuation method | B66: Metric | C66: Multiple used | D66: Basis | E66: Metric at target date | F66: Value per share | G66: Weight | H66: Metric key | I66: Metric shown (stated per-share figure when used)
A67: DCF (cash flow to target date + terminal) | F67: =((B45)-$B$50-$B$51+$B$52)/$B$53 | G67: =Valuation!$B$63
A68: ="Multiple: "&Valuation!A69&" ("&Valuation!D69&")" | B68: =Valuation!A69 | C68: =IF(B68="FCF yield",(Valuation!B69)*(1-$B$8),(Valuation!B69)+IF(B68="EV/sales",0.1,1)*$B$6) | D68: =Valuation!D69 | E68: =IF(D68="ltm",CHOOSE(H68,$C$59,$C$60,$C$61,$C$62,$C$63,$C$64),CHOOSE(H68,$B$59,$B$60,$B$61,$B$62,$B$63,$B$64)) | F68: =IF(OR(B68="EV/EBITDA",B68="EV/sales",B68="EV/EBIT"),((C68*E68)-$B$50-$B$51+$B$52)/$B$53,IF(B68="P/E",IF(Valuation!F69<>"",C68*(Valuation!F69)*(1+$B$9),C68*(E68-$B$54)/$B$53),IF(Valuation!G69<>"",(Valuation!G69)*(1+$B$9)/C68,(E68-IF(Valuation!H69,$B$54,0))/C68/$B$53))+$B$52/$B$53) | G68: =Valuation!C69 | H68: =IF(B68="EV/sales",1,IF(B68="EV/EBIT",2,IF(B68="EV/EBITDA",IF(Valuation!E69="adjusted",4,3),IF(B68="P/E",5,6)))) | I68: =IF(AND(B68="P/E",Valuation!F69<>""),(Valuation!F69)*(1+$B$9),IF(AND(B68="FCF yield",Valuation!G69<>""),(Valuation!G69)*(1+$B$9),E68))
A69: Value per share at target date (weighted methods) | F69: =SUMPRODUCT(F67:F68,G67:G68)/SUM(G67:G68)

Sheet Calc - bull
A1: NFLX engine calculation: bull scenario
A2: Machinery behind the Valuation and Distribution tabs; drivers come from Model, assumptions from Valuation.
A4: Scenario Growth Δ | B4: =N(Valuation!C83)
A5: Scenario Margin Δ | B5: =N(Valuation!D83)
A6: Scenario Multiple Δ (turns) | B6: =N(Valuation!E83)
A7: Scenario WACC Δ | B7: =N(Valuation!F83)
A8: Scenario Multiple %Δ | B8: =N(Valuation!G83)
A9: Scenario Stated EPS/FCF %Δ | B9: =N(Valuation!H83)
A10: Scenario Custom %Δ | B10: =N(Valuation!I83)
A12: WACC | B12: =Valuation!$B$50+B7
A13: Years from last FY end to target date | B13: =(Valuation!$B$44-Valuation!$B$48)/365.25
A14: Years from last FY end to balance date | B14: =(Valuation!$B$54-Valuation!$B$48)/365.25
A15: Years from last FY end to share count date | B15: =(Valuation!$B$60-Valuation!$B$48)/365.25
A16: Projected years | B16: 3
A18: Projection | B18: Base | C18: =Model!E5 | D18: =Model!F5 | E18: =Model!G5
A19: Year index | B19: 0 | C19: 1 | D19: 2 | E19: 3
A20: Period end | C20: =Valuation!$B$48+ROUND(365.25*C19,0) | D20: =Valuation!$B$48+ROUND(365.25*D19,0) | E20: =Valuation!$B$48+ROUND(365.25*E19,0)
A21: Revenue growth | C21: =Model!E48+$B$4+$B$250 | D21: =Model!F48+$B$4+$B$253 | E21: =Model!G48+$B$4+$B$256
A22: Revenue | B22: =Valuation!$B$49 | C22: =B22*(1+C21) | D22: =C22*(1+D21) | E22: =D22*(1+E21)
A23: EBIT margin | C23: =Model!E49+$B$5+$B$251 | D23: =Model!F49+$B$5+$B$254 | E23: =Model!G49+$B$5+$B$257
A24: EBIT | C24: =C22*C23 | D24: =D22*D23 | E24: =E22*E23
A25: Tax rate | C25: =Model!E50 | D25: =Model!F50 | E25: =Model!G50
A26: NOPAT | C26: =C24*(1-C25) | D26: =D24*(1-D25) | E26: =E24*(1-E25)
A27: D&A | C27: =C22*(Model!E51) | D27: =D22*(Model!F51) | E27: =E22*(Model!G51)
A28: Capex | C28: =C22*(Model!E52+$B$252) | D28: =D22*(Model!F52+$B$255) | E28: =E22*(Model!G52+$B$258)
A29: Working capital increase | C29: =(Model!E53)*(C22-B22) | D29: =(Model!F53)*(D22-C22) | E29: =(Model!G53)*(E22-D22)
A30: Stock comp | C30: =C22*(Model!E54) | D30: =D22*(Model!F54) | E30: =E22*(Model!G54)
A31: Free cash flow to firm | C31: =C26+C27-C28-C29-IF(AND(Valuation!$B$46="adjusted",Valuation!$B$47="cost"),C30*(1-C25),0) | D31: =D26+D27-D28-D29-IF(AND(Valuation!$B$46="adjusted",Valuation!$B$47="cost"),D30*(1-D25),0) | E31: =E26+E27-E28-E29-IF(AND(Valuation!$B$46="adjusted",Valuation!$B$47="cost"),E30*(1-E25),0)
A32: EBITDA | C32: =C24+C27 | D32: =D24+D27 | E32: =E24+E27
A33: Adj. EBITDA | C33: =C24+C27+C22*(Model!E58) | D33: =D24+D27+D22*(Model!F58) | E33: =E24+E27+E22*(Model!G58)
A34: Shareholder returns + other uses | C34: =C22*Model!E56+Model!E55+Model!E57 | D34: =D22*Model!F56+Model!F55+Model!F57 | E34: =E22*Model!G56+Model!G55+Model!G57
A35: Share of year after target date | C35: =IF(C19<=$B$13,0,C19-MAX(C19-1,$B$13)) | D35: =IF(D19<=$B$13,0,D19-MAX(D19-1,$B$13)) | E35: =IF(E19<=$B$13,0,E19-MAX(E19-1,$B$13))
A36: PV at target date of FCFF | C36: =IF(C35=0,0,C31*C35/(1+$B$12)^(C19-$B$13)) | D36: =IF(D35=0,0,D31*D35/(1+$B$12)^(D19-$B$13)) | E36: =IF(E35=0,0,E31*E35/(1+$B$12)^(E19-$B$13))
A37: Overlap: balance date to target date | C37: =MAX(0,MIN(C19,$B$13)-MAX(C19-1,$B$14)) | D37: =MAX(0,MIN(D19,$B$13)-MAX(D19-1,$B$14)) | E37: =MAX(0,MIN(E19,$B$13)-MAX(E19-1,$B$14))
A38: NTM weight at target date | C38: =MAX(0,MIN(C19,$B$13+1)-MAX(C19-1,$B$13)) | D38: =MAX(0,MIN(D19,$B$13+1)-MAX(D19-1,$B$13)) | E38: =MAX(0,MIN(E19,$B$13+1)-MAX(E19-1,$B$13))
A39: LTM weight at target date | B39: =MAX(0,MIN(0,$B$13)-MAX(-1,$B$13-1)) | C39: =MAX(0,MIN(C19,$B$13)-MAX(C19-1,$B$13-1)) | D39: =MAX(0,MIN(D19,$B$13)-MAX(D19-1,$B$13-1)) | E39: =MAX(0,MIN(E19,$B$13)-MAX(E19-1,$B$13-1))
A41: Value at the target date
A42: PV of free cash flow after the target date | B42: =SUM($C$36:$E$36)
A43: Terminal value at final year | B43: =IF(Valuation!$B$51="exit_multiple",Valuation!$B$53*E32,E31*(1+Valuation!$B$52)/($B$12-Valuation!$B$52))
A44: PV of terminal value at target date | B44: =B43/(1+$B$12)^($B$16-$B$13)
A45: DCF enterprise value at target date | B45: =B42+B44
A46: Terminal value share of DCF | B46: =B44/B45
A47: Free cash flow earned, balance date to target date | B47: =SUMPRODUCT($C$37:$E$37,$C$31:$E$31)
A48: Shareholder returns + other uses paid | B48: =SUMPRODUCT($C$37:$E$37,$C$34:$E$34)
A49: Interest drag on net debt | B49: =Valuation!$B$57*(1-$C$25)*MAX(Valuation!$B$55,0)*MAX($B$13-$B$14,0)
A50: Net debt at target date | B50: =IF(Valuation!$B$58="",Valuation!$B$55-B47+B49+B48,Valuation!$B$58)
A51: Minority interests | B51: =Valuation!$B$56
A52: Adjustments (probability-weighted) | B52: =(Valuation!B75)*Valuation!C75+0
A53: Diluted shares at target date (M) | B53: =IF(Valuation!$B$62="",Valuation!$B$59*(1+Valuation!$B$61)^MAX($B$13-$B$15,0),Valuation!$B$62)
A54: After-tax interest on target-date net debt | B54: =Valuation!$B$57*(1-$C$25)*MAX(B50,0)
A55: Check: WACC vs terminal growth | B55: =IF(AND(Valuation!$B$51<>"exit_multiple",$B$12<=Valuation!$B$52+0.01),"WACC must exceed terminal growth by 1 point","ok")
A56: Check: projection length | B56: =IF(OR($B$13>=$B$16-1,$B$13+1>$B$16),"add projected years past the target date","ok")
A58: Metric at target date | B58: Next 12 months | C58: Last 12 months
A59: Revenue | B59: =SUMPRODUCT($C$38:$E$38,$C$22:$E$22) | C59: =SUMPRODUCT($C$39:$E$39,$C$22:$E$22)+$B$39*$B$22
A60: EBIT | B60: =SUMPRODUCT($C$38:$E$38,$C$24:$E$24) | C60: =SUMPRODUCT($C$39:$E$39,$C$24:$E$24)
A61: EBITDA | B61: =SUMPRODUCT($C$38:$E$38,$C$32:$E$32) | C61: =SUMPRODUCT($C$39:$E$39,$C$32:$E$32)
A62: Adj. EBITDA | B62: =SUMPRODUCT($C$38:$E$38,$C$33:$E$33) | C62: =SUMPRODUCT($C$39:$E$39,$C$33:$E$33)
A63: NOPAT | B63: =SUMPRODUCT($C$38:$E$38,$C$26:$E$26) | C63: =SUMPRODUCT($C$39:$E$39,$C$26:$E$26)
A64: Free cash flow to firm | B64: =SUMPRODUCT($C$38:$E$38,$C$31:$E$31) | C64: =SUMPRODUCT($C$39:$E$39,$C$31:$E$31)
A66: Valuation method | B66: Metric | C66: Multiple used | D66: Basis | E66: Metric at target date | F66: Value per share | G66: Weight | H66: Metric key | I66: Metric shown (stated per-share figure when used)
A67: DCF (cash flow to target date + terminal) | F67: =((B45)-$B$50-$B$51+$B$52)/$B$53 | G67: =Valuation!$B$63
A68: ="Multiple: "&Valuation!A69&" ("&Valuation!D69&")" | B68: =Valuation!A69 | C68: =IF(B68="FCF yield",(Valuation!B69)*(1-$B$8),(Valuation!B69)+IF(B68="EV/sales",0.1,1)*$B$6) | D68: =Valuation!D69 | E68: =IF(D68="ltm",CHOOSE(H68,$C$59,$C$60,$C$61,$C$62,$C$63,$C$64),CHOOSE(H68,$B$59,$B$60,$B$61,$B$62,$B$63,$B$64)) | F68: =IF(OR(B68="EV/EBITDA",B68="EV/sales",B68="EV/EBIT"),((C68*E68)-$B$50-$B$51+$B$52)/$B$53,IF(B68="P/E",IF(Valuation!F69<>"",C68*(Valuation!F69)*(1+$B$9),C68*(E68-$B$54)/$B$53),IF(Valuation!G69<>"",(Valuation!G69)*(1+$B$9)/C68,(E68-IF(Valuation!H69,$B$54,0))/C68/$B$53))+$B$52/$B$53) | G68: =Valuation!C69 | H68: =IF(B68="EV/sales",1,IF(B68="EV/EBIT",2,IF(B68="EV/EBITDA",IF(Valuation!E69="adjusted",4,3),IF(B68="P/E",5,6)))) | I68: =IF(AND(B68="P/E",Valuation!F69<>""),(Valuation!F69)*(1+$B$9),IF(AND(B68="FCF yield",Valuation!G69<>""),(Valuation!G69)*(1+$B$9),E68))
A69: Value per share at target date (weighted methods) | F69: =SUMPRODUCT(F67:F68,G67:G68)/SUM(G67:G68)
A249: Driver scenario shifts: line-item changes model_drivers.py resolves from this scenario's driver deltas (added to the Model tab inputs)
A250: Revenue growth, year 1 | B250: 0.025031538
A251: EBIT margin, year 1 | B251: 0.01483307
A252: Capex % revenue, year 1 | B252: -0.00076275642
A253: Revenue growth, year 2 | B253: 0.0023891321
A254: EBIT margin, year 2 | B254: 0.016069302
A255: Capex % revenue, year 2 | B255: -0.00082811435
A256: Revenue growth, year 3 | B256: 0.0019102298
A257: EBIT margin, year 3 | B257: 0.017140281
A258: Capex % revenue, year 3 | B258: -0.00088331766

Sheet Agents
A1: NFLX: each forecaster's own assumption set through the same engine (from model_engine.json, not live)
A3: Set | B3: Research target (12m) | C3: Median | D3: 25th pct | E3: 75th pct | F3: WACC | G3: Y1 growth | H3: Y1 margin | I3: Terminal growth | J3: DCF weight | K3: Years | L3: Multiples | M3: Supervisor's note
A4: agent 1 | B4: 73.955551 | C4: 73.061049 | D4: 57.247642 | E4: 88.462135 | F4: 0.093 | I4: 0.03 | J4: 0 | K4: 5 | L4: P/E 18.0 (ntm); EV/EBITDA 14.0 (ntm) | M4: Sound four-region build. Paramount-WBD still pending in its risks and catalysts (FCC/UK reviews, 2027-06-04 outside date), but the deal closed 2026-10-06. EV/EBITDA at 0.25 weight is untested judgment. [5 projected years (over the 3-year cap)]
A5: agent 2 | B5: 75.188586 | C5: 74.731074 | D5: 59.157639 | E5: 90.894664 | F5: 0.096 | I5: 0.03 | J5: 0 | K5: 5 | L5: P/E 18.0 (ntm) | M5: Correct on the Paramount-WBD closing (AP). Shares -3.5% and WACC 9.6% sit at the edges of the group, each argued. [5 projected years (over the 3-year cap)]
A6: agent 3 | B6: 74.760854 | C6: 73.839687 | D6: 58.002804 | E6: 90.79952 | F6: 0.095 | I6: 0.03 | J6: 0 | K6: 5 | L6: P/E 18.0 (ntm) | M6: Stale Paramount-WBD fact (outside date, $7B fee). NTM EPS label arithmetic: 0.73+0.93+0.98+0.98 = 3.62, not 3.56. The -$15B x 0.15 M&A overpayment is unsupported in size. [5 projected years (over the 3-year cap)]
A7: agent 4 | B7: 75.384573 | C7: 74.855548 | D7: 59.416188 | E7: 88.851728 | F7: 0.092 | H7: 0.315 | I7: 0.03 | J7: 0 | K7: 5 | L7: P/E 18.0 (ntm); EV/EBITDA 14.0 (ntm) | M7: Correct on the closing (WBD S-8 POS). The UCAN FY27 growth cut to 7% rests partly on a PPC Land newsletter ('merge into one streaming giant, 200M subs') not confirmed at a primary source. 11-name peer median includes LYV, CMCSA and ROKU. [5 projected years (over the 3-year cap)]
A8: agent 5 | B8: 76.087771 | C8: 75.623419 | D8: 59.884462 | E8: 91.965329 | F8: 0.094 | I8: 0.03 | J8: 0 | K8: 5 | L8: P/E 18.0 (ntm) | M8: Stale Kalshi-based Paramount-WBD probability (0.65, July 2026), resolved by the 2026-10-06 closing. FY30 margin 36.5% is the highest in the group. Bull multiple +4 turns. [5 projected years (over the 3-year cap)]
A9: supervisor | B9: 76.219651 | C9: 75.472402 | D9: 61.172785 | E9: 88.670685 | F9: 0.094 | G9: 0.13095633 | H9: 0.31499022 | I9: 0.03 | J9: 0 | K9: 3 | L9: P/E 19.07 (ntm)

Sheet Sources
A1: NFLX: where each input comes from (source numbers point to the list below; F ids to the SEC fact table)
A3: Input | B3: Value | C3: Basis | D3: Sources | E3: SEC fact ids | F3: Derivation
A4: Base revenue FY2025 | B4: $45,183.0M | C4: reported | D4: 2, 9 | E4: F3 | F4: 10-K FY2025 total revenue (F3).
A5: Regional base revenue FY2025 | B5: UCAN 19,957.2; EMEA 14,514.6; LATAM 5,357.5; APAC 5,353.7 ($M) | C5: reported | D5: 2 | E5: F3 | F5: 10-K FY2025 streaming revenues by region ($K): UCAN 19,957,152; EMEA 14,514,646; LATAM 5,357,521; APAC 5,353,717; total 45,183,036 = F3 (opened by the gate 2026-10-21).
A6: FY2026 revenue growth by region | B6: UCAN +11.4%, EMEA +12.7%, LATAM +17.6%, APAC +15.1% (total $51,053M, +13.0%) | C6: estimate | D6: 1 | E6: F3 | F6: 19,957.2x1.114 + 14,514.6x1.127 + 5,357.5x1.176 + 5,353.7x1.151 = 22,232 + 16,358 + 6,300 + 6,162 = 51,053 vs the Q3 letter FY2026 outlook $51.1B (+13%); split follows Q3 regional growth (UCAN 11%, EMEA 11%/9% FXN, LATAM 17%, APAC 12%/15% FXN). Derived split (estimate), not guidance: the letter guides only the total, and the regional mix is Q1-Q3 actuals plus Q4 = Q4'25 x growth. [gate 2026-10-21]
A7: FY2027 revenue growth by region | B7: UCAN +9.0%, EMEA +10.0%, LATAM +12.0%, APAC +13.5% (total ~$56.3B, +10.2%) | C7: estimate | D7: 1, 8, 15 | F7: Increment 22,232x9% + 16,358x10% + 6,300x12% + 6,162x13.5% = 2,001 + 1,636 + 756 + 832 = 5,225 on 51,053 = +10.2%. CFO on the Q3 call: 'We look to sustain double-digit revenue growth'; ad tier in 15 new countries in 2027 (Q3 letter). ~1.1% under the pre-print $56.96B street revenue figure (StockAnalysis 'Revenue Next Year', source 15; Nasdaq/Zacks gives EPS only). [gate 2026-10-21]
A8: FY2028-FY2030 revenue growth by region | B8: UCAN 7.5/6.5/5.5%; EMEA 8.5/7.5/6.5%; LATAM 10/9/8%; APAC 12/10.5/9% | C8: judgment | D8: 1 | F8: Fade of ~1-1.5pt a year toward a steady state before the 3% terminal; UCAN slowest (penetration, YouTube share of TV), APAC fastest.
A9: GAAP EBIT margin path (after SBC) | B9: 31.5% FY26, 33.0% FY27, 34.1% FY28, 35.0% FY29, 35.7% FY30 | C9: estimate | D9: 1, 8, 3, 4 | E9: F10, F3 | F9: FY26 31.5% = Q3 letter outlook (incl. ~120bp Q4 headcount charge, ~0.3pt of the year). FY27 +1.5pt: charge does not recur, layoff savings unquantified ('We are not going to specifically quantify the expense impact in 2027', CFO), 'steadily growing margin each year'. FY28-30 trimmed 0.2/0.3/0.3pt from round 1's 34.3/35.3/36.0% for the Paramount-WBD combination that closed 2026-10-06 (WBD 8-K item 2.01): one owner of HBO Max, Paramount+ and two studios bidding for content and sports, and licensed titles at risk. FY2025 29.5% = F10/F3 13,326.6/45,183.0.
A10: Tax rate | B10: 15.5% | C10: estimate | D10: 9, 1 | E10: F78, F85 | F10: FY2025 ETR 1,741.4/12,722.6 = 13.7% (F78/F85); TTM ~17% lifted by the taxed WBD termination fee; 15.5% allows for rising global minimum tax.
A11: D&A (PP&E only) % revenue | B11: 0.8% | C11: estimate | D11: 9, 1 | E11: F39, F6 | F11: Derived ratio (estimate): TTM D&A 372.4 / TTM revenue 48,370.8 = 0.77% (F39/F6); 9M 2026 306.2 / 37,683.9 = 0.81% (Q3 letter). 0.8% used; content amortisation sits inside EBIT. [gate 2026-10-21]
A12: Capex incl. content cash over amortisation, % revenue | B12: 7.5% FY26, 4.8% FY27, 4.6% FY28, 4.3% FY29, 4.0% FY30 | C12: estimate | D12: 1, 9 | E12: F57, F60 | F12: Q3 letter 9M 2026: additions to content assets 14,934.2 vs amortisation 12,764.7 = gap 2,169.6 (1.17x); PP&E purchases 693.5. FY26: content gap ~2.4B + PP&E ~0.95B + Q4 real-estate outflow ~0.5B (implied by the FCF outlook cut from $12.5B to ~$12.0B, "due primarily to the expected closing of a real estate transaction in Q4") = ~3.85B = 7.5% of 51.05B. FY27+ toward the ~1.1x guide: gap ~3% + PP&E ~1.8% = 4.8% of revenue, easing to 4.0% as amortisation catches up. [gate 2026-10-21: FY26 corrected from 6.2%, which its own components did not reach (6.6% before the real-estate outflow); FY26 cash flow falls before the 2027-10-20 horizon, so the engine value is unchanged]
A13: SBC | B13: ~1% of revenue, costed in GAAP EBIT (counted once) | C13: estimate | D13: 9, 1 | E13: F46 | F13: Derived ratio (estimate): TTM SBC 487.3 (F46) / TTM revenue 48,370.8 (F6) = 1.0%; 9M 2026 405.4 / 37,683.9 = 1.08% (Q3 letter); FY2025 368.4 / 45,183.0 = 0.82%. ~1% used; no add-back (counted once in GAAP EBIT); share count change is net of issuance. [gate 2026-10-21]
A14: WACC | B14: 9.4% | C14: estimate | D14: 5, 9, 10 | E14: F74 | F14: Cost of equity 5.12% (10y UST, Treasury par curve 2026-10-20, opened) + beta 1.0 x ERP 4.5% = 9.62%. Beta: weekly NFLX vs SPY regressions (round-1 supervisor scratch and agents 2-5 independently) 0.91-0.92 2y, 1.04 3y, 1.40-1.43 5y (2022-dominated). Debt: TTM interest 847.5 (F74) / ~15.1B = 5.6% x (1-0.155) = 4.73%; weights 94.7% equity (64.89 x 4,195M = 272.2B) / 5.3% debt (15.13B) -> 9.36%, rounded 9.4%.
A15: Terminal growth | B15: 3.0% (Gordon on FY2030) | C15: judgment | F15: Nominal-GDP-like after FY30 growth of ~6.6%; held at 3% for the attention-share and content-cost risks in long_dated_review.
A16: Net debt now / at horizon | B16: $7,114M (2026-09-30) / $7,500M | C16: estimate | D16: 1 | F16: Q3 letter: cash 8,194.3, debt 15,132.4 on the balance sheet (letter text says $15.3B), net debt 7,113.9. Horizon: FCF (~$12B FY26 guide) returned via buybacks ($22.3B authorisation left), plus the Q4 real-estate outflow: ~$7.5B (estimate).
A17: Diluted shares now and annual change | B17: 4,195.1M; -3.0% a year | C17: estimate | D17: 1, 9 | E17: F28, F29, F30, F67 | F17: Q3 diluted weighted 4,195,127K (Q3 letter). Q3 bought 63.9M shares for $4.8B (avg ~$75). ~$12B a year at ~$65-70 retires ~4.3%, less ~0.9%/yr issuance (FY2024->FY2025 diluted only -1.1%, F29/F30, when buybacks were $9.1B at ~2x today's price) -> ~-3.3%; -3.0% allows for part of FCF going to the real-estate deal and debt maturities.
A18: Horizon P/E (NTM GAAP) | B18: 19.07x | C18: judgment | D18: 6, 7, 19, 20, 21, 22, 23, 24, 25, 26, 27, 28, 29, 30, 31 | E18: DIS.pe_ntm_rb, SONY.pe_ntm_rb, META.pe_ntm_rb, GOOGL.pe_ntm_rb, AMZN.pe_ntm_rb, SPOT.pe_ntm_rb, NFLX.pe_ntm_rb | F18: Six peers on one EPS basis with NFLX (GAAP/IFRS, SBC costed, one-offs and stake marks out; Zacks actuals checked against each company's GAAP diluted EPS, peers.md 'EPS basis' and 'Rebuilt FY1 basis'). FY1 = reported quarters + remaining quarterly consensus for every name but SONY (yearly FY3/2027 consensus; its quarterly page has 2 rows of 1 estimate); NTM = fiscal-year blend (weight = days from last filed quarter to FY end / 365); Yahoo 2026-10-23 closes. DIS 16.50 (112.52 / 6.820: Zacks is Disney adjusted EPS, less acquisition amortization 4 x 0.13, 8-K ex. 99.1), SONY 17.86 (26.08 / 1.460, IFRS, USD per ADR), META 19.64 (642.62 / (0.252 x 29.14 + 0.748 x 33.93 = 32.723); FY1 = 7.31 + 6.18 + 7.40 + Q4 8.25), GOOGL 24.00 (320.21 / (0.504 x 11.679 + 0.496 x 15.03 = 13.341); FY1 ex equity-securities gains from 10-Q XBRL), AMZN 26.63 (248.00 / (0.504 x 8.00 + 0.496 x 10.65 = 9.314)), SPOT 36.28 (584.22 / (0.252 x 12.79 + 0.748 x 17.22 = 16.103); USD: Q3 Zacks 2.85 = 6-K EUR 2.48 x 1.149; FY1 less the Q1 EUR 184M Exchangeable Notes fair-value gain, 0.79 a share after tax, Q1 6-K). Median (19.64 + 24.00) / 2 = 21.82x. NFLX own NTM on the same basis: 65.85 / (0.252 x 3.04 + 0.748 x 3.75 = 3.571) = 18.44x (FY2026 3.04 = Zacks actuals 0.70 + 0.80 + 0.87 + Q4 0.67; the yearly 3.59 still carries the Q1 one-off, GAAP Q1 1.23). Exit multiple by the default rule (METHOD.md Peer comparables, Kilian card 2026-10-26 12:16Z): median x (own / median)^0.8 = 21.82 x (18.44 / 21.82)^0.8 = 19.07x. k = 0.8 kept: NFLX's own multiple sits on a clean (one-off-free) EPS base and its earnings are not contracted. Context: 2-year consensus EPS CAGR NFLX 20.7% vs peer median 21.1%, so growth does not explain the gap; the rule keeps ~80% of it, as the WRDS test finds gaps persist. Replaces 18.0x on the old set (FOXA, WMG, TKO in) per Kilian 2026-10-26 06:07Z. [gate 2026-10-26: rounds 1-3 fixed SPOT Q1 Exchangeable Notes mark; rounds 1-2 fixed GOOGL period/stake gains, DIS adjusted EPS and NFLX's FY2026 one-off; earlier growth-line values 18.7x / 19.2x superseded by the 12:16Z rule]
A19: M&A value leakage adjustment | B19: -$4,000M x 0.20 | C19: judgment | D19: 3, 8 | F19: Netflix signed an ~$83B WBD agreement in late 2025 and withdrew; WBD is now owned by Skydance (8-K 2026-10-06), so the largest target is gone; nothing on M&A on the Q3 call. 20% chance over the horizon of a deal destroying ~$4B (~1.4% of EV).
A20: Capex (driver-linked) | B20: 0.10 x content_amort + 1.9% of revenue | C20: estimate | D20: 1, 9 | E20: F57, F60 | F20: Content cash over amortization at the ~1.1x guide (Q3 2026 letter) + PP&E ~1.9% of revenue (9M26 693.5 / 37,683.9 = 1.84%). FY26 real-estate outflow (~0.5B) not modeled: net_debt_horizon is stated, so capex does not move the P/E leg.
A21: driver:sub_rev | B21: Subscription (streaming ex-ads) revenue: 4.368e+04 -> 4.84e+04/5.242e+04/5.609e+04 (estimate) | C21: estimate | F21: Base 45,183.0 - 1,500 = 43,683 (ads are a floor, so subscription is a ceiling within ~1%). FY26 51,100 - 2,700 = 48,400 (+10.8%; letter: "subscription revenue growth has outperformed our expectations"). FY27 +8.3%, FY28 +7.0%: subscription growth ran ~+13.8% in FY25 (FY24 ads ~0.6B = 1.5B / 2.5x, both letter figures are bounds; FY24 sub ~39,001.0 (F2) - 600 = 38,401; 43,683 / 38,401 = +13.8%) and +10.8% in FY26, ~3pt deceleration as the 2025-26 price rises lap; FY27 -2.5pt, FY28 -1.3pt. Members x ARM not citable: Netflix stopped quarterly member counts in 2025 (only the "325M paid memberships" milestone, Q4 2025 letter).
A22: driver:ad_rev | B22: Advertising revenue: 1,500 -> 2,700/3,900/5,050 (estimate) | C22: estimate | F22: FY26 2,700 (primary guide, +80%). FY27 3,900 = +44% (supervisor base story; ad tier into 15 new countries from March 2027, Q3 2026 letter; WARC: Netflix share of global CTV ad spend 3.7% 2025 -> 9.2% 2027). FY28 5,050 = +29.5% (agent DCF path 1.5B x 1.8 x 1.44 x 1.3).
A23: driver:content_amort | B23: Content amortization: 1.642e+04 -> 1.8e+04/1.962e+04/2.119e+04 (estimate) | C23: estimate | F23: FY26 18,000 = 9M 12,764.7 + Q4 ~5,235 (+9.9% y/y on 4,764.2), i.e. +9.6% vs the "~10% in 2026" guide (Q4 2025 letter). FY27 +9%, FY28 +8%: cash content additions 9M26 14,934.2 vs 12,039.4 (+24%) and the ~1.1x cash/amortization ratio (FY26 cash ~19.8B, +16% on FY25 17,096.6) mean amortization keeps growing near revenue, not below it; FY24-26 amortization growth +7.8%/+7.3%/+9.6% while revenue growth fell 16% -> 13%.
A24: driver:other_opex | B24: Other operating costs (cost of revenues ex-amortization + marketing + tech & dev + G&A): 1.543e+04 -> 1.7e+04/1.845e+04/1.993e+04 (estimate) | C24: estimate | F24: FY26 17,004 = 51,100 - 31.5% x 51,100 (guide, 16,096.5) - 18,000 (content_amort): +10.2% reported, +13.7% ex the FY25 Brazil 619 and the ~153 Q4 headcount charge (~30bp of FY26 revenue, Q3 2026 letter); 9M26 12,311.0 vs 11,104.4 (+10.9%; +17.4% ex Brazil). FY27 = (17,004 - 153) x 1.095 = 18,452: growth slows from ~14% underlying as the headcount cut lands, but savings are reinvested ("enable us to continue to aggressively invest", Q3 letter). FY28 +8%.
A26: # | B26: Source | C26: Date | D26: Link
A27: 1 | B27: Netflix Q3 2026 shareholder letter (8-K Ex. 99.1) | C27: 2026-10-20 | D27: https://www.sec.gov/Archives/edgar/data/1065280/000106528026000290/ex991_q326.htm
A28: 2 | B28: Netflix 10-K FY2025 | C28: 2026-01-23 | D28: https://www.sec.gov/Archives/edgar/data/1065280/000106528026000034/nflx-20251231.htm
A29: 3 | B29: Warner Bros. Discovery 8-K: completion of merger with Skydance Corporation (items 2.01, 3.01, 5.01) | C29: 2026-10-06 | D29: https://www.sec.gov/Archives/edgar/data/1437107/000119312526415055/d200872d8k.htm
A30: 4 | B30: AP: Judge approves Paramount's settlement with states over Warner buyout, allowing merger to soon close (via NY1) | C30: 2026-09-30 | D30: https://ny1.com/nyc/all-boroughs/ap-top-news/2026/09/30/judge-approves-paramounts-settlement-with-states-over-warner-buyout-allowing-merger-to-soon-close
A31: 5 | B31: US Treasury daily par yield curve rates 2026 | C31: 2026-10-20 | D31: https://home.treasury.gov/resource-center/data-chart-center/interest-rates/daily-treasury-rates.csv/2026/all?type=daily_treasury_yield_curve&field_tdr_date_value=2026&page&_format=csv
A32: 6 | B32: Nasdaq/Zacks NFLX earnings forecast | C32: 2026-10-20 | D32: https://api.nasdaq.com/api/analyst/NFLX/earnings-forecast
A33: 7 | B33: Nasdaq/Zacks peer earnings forecasts (DIS, META, AMZN, GOOGL, SPOT, TKO, WMG, FOXA) | C33: 2026-10-20 | D33: https://api.nasdaq.com/api/analyst/META/earnings-forecast
A34: 8 | B34: Netflix Q3 2026 earnings call transcript (Investing.com) | C34: 2026-10-20 | D34: https://www.investing.com/news/transcripts/earnings-call-transcript-netflix-beats-q3-2026-estimates-but-shares-fall-after-hours-93CH-4961240
A35: 9 | B35: SEC XBRL company facts, Netflix (run fact pack facts.md) | C35: 2026-10-20 | D35: https://data.sec.gov/api/xbrl/companyfacts/CIK0001065280.json
A36: 10 | B36: Yahoo Finance chart feed, NFLX (regularMarketPrice 68.69 = 2026-10-20 close; fulldayPrice 64.89 = extended-hours price), record retrieved 2026-10-20 23:12Z and saved as runs/2026-10-20/NFLX/work_agent_2/y_NFLX.json; close also confirmed by Twelve Data daily series | C36: 2026-10-20 | D36: https://query1.finance.yahoo.com/v8/finance/chart/NFLX
A37: 11 | B37: Warner Bros. Discovery EDGAR filing index (S-8 POS and 25-NSE 2026-10-06, 15-12G 2026-10-16) | C37: 2026-10-16 | D37: https://data.sec.gov/submissions/CIK0001437107.json
A38: 12 | B38: Run peer comps table peers.md (peers.py: trailing multiples from SEC XBRL via secfacts.py; NTM P/E = Yahoo close / NTM fiscal-year blend of Nasdaq.com/Zacks consensus EPS); cited by fact id | C38: 2026-10-20 | D38: runs/2026-10-20/NFLX/peers.md
... A57: 31 | B57: METHOD.md Peer comparables: exit multiple = peer median x (own/median)^0.8 (Kilian card 2026-10-26 12:16Z; WRDS test wrds/results/exit_multiple_shrink/README.md) | C57: 2026-10-26 | D57: METHOD.md
A59: Fact id | B59: Figure | C59: Value | D59: Filing
A60: F1 | B60: revenue FY ending 2023-12-31 (us-gaap:Revenues) | C60: 33723297000 | D60: https://www.sec.gov/Archives/edgar/data/1065280/000106528026000034/
A61: F2 | B61: revenue FY ending 2024-12-31 (us-gaap:Revenues) | C61: 39000966000 | D61: https://www.sec.gov/Archives/edgar/data/1065280/000106528026000034/
A62: F3 | B62: revenue FY ending 2025-12-31 (us-gaap:Revenues) | C62: 45183036000 | D62: https://www.sec.gov/Archives/edgar/data/1065280/000106528026000034/
A63: F4 | B63: revenue YTD 2026-01-01 to 2026-09-30 | C63: 37683871000 | D63: https://www.sec.gov/Archives/edgar/data/1065280/000106528026000291/
A64: F5 | B64: revenue prior-year YTD 2025-01-01 to 2025-09-30 | C64: 33132274000 | D64: https://www.sec.gov/Archives/edgar/data/1065280/000106528026000291/
A65: F6 | B65: revenue TTM to 2026-09-30 | C65: 49734633000
A66: F7 | B66: revenue quarter 2026-07-01 to 2026-09-30 | C66: 12874176000 | D66: https://www.sec.gov/Archives/edgar/data/1065280/000106528026000291/
A67: F8 | B67: operating_income FY ending 2023-12-31 (us-gaap:OperatingIncomeLoss) | C67: 6954003000 | D67: https://www.sec.gov/Archives/edgar/data/1065280/000106528026000034/
A68: F9 | B68: operating_income FY ending 2024-12-31 (us-gaap:OperatingIncomeLoss) | C68: 10417614000 | D68: https://www.sec.gov/Archives/edgar/data/1065280/000106528026000034/
A69: F10 | B69: operating_income FY ending 2025-12-31 (us-gaap:OperatingIncomeLoss) | C69: 13326603000 | D69: https://www.sec.gov/Archives/edgar/data/1065280/000106528026000034/
A70: F11 | B70: operating_income YTD 2026-01-01 to 2026-09-30 | C70: 12608207000 | D70: https://www.sec.gov/Archives/edgar/data/1065280/000106528026000291/
A71: F12 | B71: operating_income prior-year YTD 2025-01-01 to 2025-09-30 | C71: 10369940000 | D71: https://www.sec.gov/Archives/edgar/data/1065280/000106528026000291/
A72: F13 | B72: operating_income TTM to 2026-09-30 | C72: 15564870000
A73: F14 | B73: operating_income quarter 2026-07-01 to 2026-09-30 | C73: 4458600000 | D73: https://www.sec.gov/Archives/edgar/data/1065280/000106528026000291/
A74: F15 | B74: net_income FY ending 2023-12-31 (us-gaap:NetIncomeLoss) | C74: 5407990000 | D74: https://www.sec.gov/Archives/edgar/data/1065280/000106528026000034/
A75: F16 | B75: net_income FY ending 2024-12-31 (us-gaap:NetIncomeLoss) | C75: 8711631000 | D75: https://www.sec.gov/Archives/edgar/data/1065280/000106528026000034/
A76: F17 | B76: net_income FY ending 2025-12-31 (us-gaap:NetIncomeLoss) | C76: 10981201000 | D76: https://www.sec.gov/Archives/edgar/data/1065280/000106528026000034/
A77: F18 | B77: net_income YTD 2026-01-01 to 2026-09-30 | C77: 12348132000 | D77: https://www.sec.gov/Archives/edgar/data/1065280/000106528026000291/
A78: F19 | B78: net_income prior-year YTD 2025-01-01 to 2025-09-30 | C78: 8562680000 | D78: https://www.sec.gov/Archives/edgar/data/1065280/000106528026000291/
A79: F20 | B79: net_income TTM to 2026-09-30 | C79: 14766653000
A80: F21 | B80: net_income quarter 2026-07-01 to 2026-09-30 | C80: 3663927000 | D80: https://www.sec.gov/Archives/edgar/data/1065280/000106528026000291/
A81: F22 | B81: eps_diluted FY ending 2023-12-31 (us-gaap:EarningsPerShareDiluted) | C81: 1.2 | D81: https://www.sec.gov/Archives/edgar/data/1065280/000106528026000034/
A82: F23 | B82: eps_diluted FY ending 2024-12-31 (us-gaap:EarningsPerShareDiluted) | C82: 1.98 | D82: https://www.sec.gov/Archives/edgar/data/1065280/000106528026000034/
A83: F24 | B83: eps_diluted FY ending 2025-12-31 (us-gaap:EarningsPerShareDiluted) | C83: 2.53 | D83: https://www.sec.gov/Archives/edgar/data/1065280/000106528026000034/
A84: F25 | B84: eps_diluted YTD 2026-01-01 to 2026-09-30 | C84: 2.9 | D84: https://www.sec.gov/Archives/edgar/data/1065280/000106528026000291/
A85: F26 | B85: eps_diluted prior-year YTD 2025-01-01 to 2025-09-30 | C85: 1.97 | D85: https://www.sec.gov/Archives/edgar/data/1065280/000106528026000291/
A86: F27 | B86: eps_diluted quarter 2026-07-01 to 2026-09-30 | C86: 0.87 | D86: https://www.sec.gov/Archives/edgar/data/1065280/000106528026000291/
A87: F28 | B87: diluted_shares_wavg FY ending 2023-12-31 (us-gaap:WeightedAverageNumberOfDilutedSharesOutstanding) | C87: 4494966000 | D87: https://www.sec.gov/Archives/edgar/data/1065280/000106528026000034/
A88: F29 | B88: diluted_shares_wavg FY ending 2024-12-31 (us-gaap:WeightedAverageNumberOfDilutedSharesOutstanding) | C88: 4392608000 | D88: https://www.sec.gov/Archives/edgar/data/1065280/000106528026000034/
A89: F30 | B89: diluted_shares_wavg FY ending 2025-12-31 (us-gaap:WeightedAverageNumberOfDilutedSharesOutstanding) | C89: 4343863000 | D89: https://www.sec.gov/Archives/edgar/data/1065280/000106528026000034/
A90: F31 | B90: diluted_shares_wavg YTD 2026-01-01 to 2026-09-30 | C90: 4251298000 | D90: https://www.sec.gov/Archives/edgar/data/1065280/000106528026000291/
A91: F32 | B91: diluted_shares_wavg prior-year YTD 2025-01-01 to 2025-09-30 | C91: 4352844000 | D91: https://www.sec.gov/Archives/edgar/data/1065280/000106528026000291/
... A97: F38 | B97: d_and_a prior-year YTD 2025-01-01 to 2025-09-30 | C97: 247406000 | D97: https://www.sec.gov/Archives/edgar/data/1065280/000106528026000291/
A98: F39 | B98: d_and_a TTM to 2026-09-30 | C98: 392188000
A99: F40 | B99: d_and_a quarter 2026-07-01 to 2026-09-30 | C99: 107100000 | D99: https://www.sec.gov/Archives/edgar/data/1065280/000106528026000291/
A100: F41 | B100: sbc FY ending 2023-12-31 (us-gaap:ShareBasedCompensation) | C100: 339368000 | D100: https://www.sec.gov/Archives/edgar/data/1065280/000106528026000034/
A101: F42 | B101: sbc FY ending 2024-12-31 (us-gaap:ShareBasedCompensation) | C101: 272588000 | D101: https://www.sec.gov/Archives/edgar/data/1065280/000106528026000034/
A102: F43 | B102: sbc FY ending 2025-12-31 (us-gaap:ShareBasedCompensation) | C102: 368449000 | D102: https://www.sec.gov/Archives/edgar/data/1065280/000106528026000034/
A103: F44 | B103: sbc YTD 2026-01-01 to 2026-09-30 | C103: 405440000 | D103: https://www.sec.gov/Archives/edgar/data/1065280/000106528026000291/
A104: F45 | B104: sbc prior-year YTD 2025-01-01 to 2025-09-30 | C104: 233825000 | D104: https://www.sec.gov/Archives/edgar/data/1065280/000106528026000291/
A105: F46 | B105: sbc TTM to 2026-09-30 | C105: 540064000
A106: F47 | B106: sbc quarter 2026-07-01 to 2026-09-30 | C106: 133723000 | D106: https://www.sec.gov/Archives/edgar/data/1065280/000106528026000291/
A107: F48 | B107: cfo FY ending 2023-12-31 (us-gaap:NetCashProvidedByUsedInOperatingActivities) | C107: 7274301000 | D107: https://www.sec.gov/Archives/edgar/data/1065280/000106528026000034/
A108: F49 | B108: cfo FY ending 2024-12-31 (us-gaap:NetCashProvidedByUsedInOperatingActivities) | C108: 7361364000 | D108: https://www.sec.gov/Archives/edgar/data/1065280/000106528026000034/
A109: F50 | B109: cfo FY ending 2025-12-31 (us-gaap:NetCashProvidedByUsedInOperatingActivities) | C109: 10149273000 | D109: https://www.sec.gov/Archives/edgar/data/1065280/000106528026000034/
A110: F51 | B110: cfo YTD 2026-01-01 to 2026-09-30 | C110: 10196296000 | D110: https://www.sec.gov/Archives/edgar/data/1065280/000106528026000291/
A111: F52 | B111: cfo prior-year YTD 2025-01-01 to 2025-09-30 | C111: 8037631000 | D111: https://www.sec.gov/Archives/edgar/data/1065280/000106528026000291/
A112: F53 | B112: cfo TTM to 2026-09-30 | C112: 12307938000
A113: F54 | B113: cfo quarter 2026-07-01 to 2026-09-30 | C113: 3162279000 | D113: https://www.sec.gov/Archives/edgar/data/1065280/000106528026000291/
A114: F55 | B114: capex FY ending 2023-12-31 (us-gaap:PaymentsToAcquirePropertyPlantAndEquipment) | C114: 348552000 | D114: https://www.sec.gov/Archives/edgar/data/1065280/000106528026000034/
A115: F56 | B115: capex FY ending 2024-12-31 (us-gaap:PaymentsToAcquirePropertyPlantAndEquipment) | C115: 439538000 | D115: https://www.sec.gov/Archives/edgar/data/1065280/000106528026000034/
A116: F57 | B116: capex FY ending 2025-12-31 (us-gaap:PaymentsToAcquirePropertyPlantAndEquipment) | C116: 688220000 | D116: https://www.sec.gov/Archives/edgar/data/1065280/000106528026000034/
A117: F58 | B117: capex YTD 2026-01-01 to 2026-09-30 | C117: 693540000 | D117: https://www.sec.gov/Archives/edgar/data/1065280/000106528026000291/
A118: F59 | B118: capex prior-year YTD 2025-01-01 to 2025-09-30 | C118: 448885000 | D118: https://www.sec.gov/Archives/edgar/data/1065280/000106528026000291/
A119: F60 | B119: capex TTM to 2026-09-30 | C119: 932875000
A120: F61 | B120: capex quarter 2026-07-01 to 2026-09-30 | C120: 278766000 | D120: https://www.sec.gov/Archives/edgar/data/1065280/000106528026000291/
A121: F62 | B121: buybacks FY ending 2023-12-31 (us-gaap:PaymentsForRepurchaseOfCommonStock) | C121: 6045347000 | D121: https://www.sec.gov/Archives/edgar/data/1065280/000106528026000034/
A122: F63 | B122: buybacks FY ending 2024-12-31 (us-gaap:PaymentsForRepurchaseOfCommonStock) | C122: 6263746000 | D122: https://www.sec.gov/Archives/edgar/data/1065280/000106528026000034/
A123: F64 | B123: buybacks FY ending 2025-12-31 (us-gaap:PaymentsForRepurchaseOfCommonStock) | C123: 9127167000 | D123: https://www.sec.gov/Archives/edgar/data/1065280/000106528026000034/
A124: F65 | B124: buybacks YTD 2026-01-01 to 2026-09-30 | C124: 10781716000 | D124: https://www.sec.gov/Archives/edgar/data/1065280/000106528026000291/
A125: F66 | B125: buybacks prior-year YTD 2025-01-01 to 2025-09-30 | C125: 7047608000 | D125: https://www.sec.gov/Archives/edgar/data/1065280/000106528026000291/
A126: F67 | B126: buybacks TTM to 2026-09-30 | C126: 12861275000
...
