Workbook

Sheet Summary
A1: AMAT standard model (trial) · research run 2026-10-23
A2: The supervisor's reconciled assumption set as a live model. Trial: shown beside the blended page target, not used for trade levels until its weight is decided. Edit blue cells on Model (drivers) and Valuation (assumptions).
A3: Price target box | B3: Value
A4: Live price | B4: =IFERROR(GOOGLEFINANCE("AMAT","price"),Valuation!$B$66)
A5: Price as of | B5: =NOW()
A6: Model target (12-month median) | B6: =Distribution!$B$13
A7: Upside to model target from live price | B7: =B6/B4-1
A8: Research target (12m) (no scenario deltas) | B8: =Valuation!$D$6
A9: Probability-weighted mean | B9: =Distribution!$B$10
A10: 10th percentile | B10: =Distribution!$B$14
A11: 25th percentile | B11: =Distribution!$B$15
A12: 75th percentile | B12: =Distribution!$B$16
A13: 90th percentile | B13: =Distribution!$B$17
A14: Target date | B14: =Valuation!$B$44
A15: Price at the run | B15: =Valuation!$B$66
A16: Blended page target (options 67% + agents 33%, not live) | B16: 407.0897
A17: Supervisor research target (12m) (its own methods) | B17: 443.36
A18: Thesis break price (supervisor) | B18: 335
A19: Supervisor confidence | B19: medium
A21: Key estimates | B21: FY2025A | C21: =Model!E5 | D21: =Model!F5
A22: Net sales | B22: =IF(Model!D11="","",Model!D11) | C22: =Model!E11 | D22: =Model!F11
A23: % YoY | B23: =IF(Model!D12="","",Model!D12) | C23: =Model!E12 | D23: =Model!F12
A24: Pretax margin | B24: =IF(Model!D22="","",Model!D22) | C24: =Model!E22 | D24: =Model!F22
A25: Diluted EPS (model) | B25: =IF(Model!D29="","",Model!D29) | C25: =Model!E29 | D25: =Model!F29
A26: % YoY | B26: =IF(Model!D30="","",Model!D30) | C26: =Model!E30 | D26: =Model!F30
A27: Free cash flow to firm | B27: =IF(Model!D39="","",Model!D39) | C27: =Model!E39 | D27: =Model!F39
A28: Consensus: EPS (non-GAAP) | C28: 13.18
A29: Consensus: EPS (non-GAAP) | D29: 18.43
A31: Valuation method | B31: Value per share | C31: Weight
A32: =Valuation!A4 | B32: =Valuation!D4 | C32: =Valuation!E4
A33: =Valuation!A5 | B33: =Valuation!D5 | C33: =Valuation!E5
A35: Scenario | B35: Probability | C35: Value at target date | D35: What has to happen
A36: =Distribution!A4 | B36: =Distribution!B4 | C36: =Distribution!C4 | D36: =Distribution!D4
A37: =Distribution!A5 | B37: =Distribution!B5 | C37: =Distribution!C5 | D37: =Distribution!D5
A38: =Distribution!A6 | B38: =Distribution!B6 | C38: =Distribution!C6 | D38: =Distribution!D6
A40: Price at target date | B40: Probability above
A41: =ROUND(Valuation!$B$66*0.7,0) | B41: =SUMPRODUCT(Distribution!$B$4:$B$6,1-NORMSDIST((LN(A41)-LN(Distribution!$C$4:$C$6))/Distribution!$B$9))
A42: =ROUND(Valuation!$B$66*0.8,0) | B42: =SUMPRODUCT(Distribution!$B$4:$B$6,1-NORMSDIST((LN(A42)-LN(Distribution!$C$4:$C$6))/Distribution!$B$9))
A43: =ROUND(Valuation!$B$66*0.9,0) | B43: =SUMPRODUCT(Distribution!$B$4:$B$6,1-NORMSDIST((LN(A43)-LN(Distribution!$C$4:$C$6))/Distribution!$B$9))
A44: =ROUND(Valuation!$B$66*1.0,0) | B44: =SUMPRODUCT(Distribution!$B$4:$B$6,1-NORMSDIST((LN(A44)-LN(Distribution!$C$4:$C$6))/Distribution!$B$9))
A45: =ROUND(Valuation!$B$66*1.1,0) | B45: =SUMPRODUCT(Distribution!$B$4:$B$6,1-NORMSDIST((LN(A45)-LN(Distribution!$C$4:$C$6))/Distribution!$B$9))
A46: =ROUND(Valuation!$B$66*1.2,0) | B46: =SUMPRODUCT(Distribution!$B$4:$B$6,1-NORMSDIST((LN(A46)-LN(Distribution!$C$4:$C$6))/Distribution!$B$9))
A47: =ROUND(Valuation!$B$66*1.3,0) | B47: =SUMPRODUCT(Distribution!$B$4:$B$6,1-NORMSDIST((LN(A47)-LN(Distribution!$C$4:$C$6))/Distribution!$B$9))
A48: =ROUND(Valuation!$B$66*1.5,0) | B48: =SUMPRODUCT(Distribution!$B$4:$B$6,1-NORMSDIST((LN(A48)-LN(Distribution!$C$4:$C$6))/Distribution!$B$9))
A50: Model checks | B50: Status
A51: Scenario probabilities sum to 100% | B51: =IF(ABS(Distribution!B8-1)<0.005,"ok","FLAG: "&TEXT(Distribution!B8,"0.0%"))
A52: WACC exceeds terminal growth by 1 point or more | B52: =IF('Calc - research target (12m)'!B55="ok","ok","FLAG")
A53: Projection runs a full year past the target date | B53: =IF('Calc - research target (12m)'!B56="ok","ok","FLAG")
A54: Method weights add up to more than zero | B54: =IF(SUM(Valuation!E4:E5)>0,"ok","FLAG")
A55: Terminal value under 85% of the DCF | B55: =IF('Calc - research target (12m)'!B46<0.85,"ok","note: "&TEXT('Calc - research target (12m)'!B46,"0%")&" of the DCF is terminal value")
A56: Matches the engine run at publication (target, research target (12m)) | B56: =IF(AND(ABS(Distribution!$B$13-453.4421)<0.01,ABS(Valuation!$D$6-443.3563)<0.01),"ok","inputs edited since publication")
A57: All checks | B57: =IF(COUNTIF(B51:B56,"ok")=6,"all ok",6-COUNTIF(B51:B56,"ok")&" to look at")

Sheet Model
A1: AMAT: annual model, base case
A2: (M of US dollars except per share; fiscal years named by the calendar year they end in)
A3: Blue = input · black = formula · green = link to another tab · actuals from SEC filings (fact ids in the last column, links on Sources)
A5: Fiscal year | B5: FY2023A | C5: FY2024A | D5: FY2025A | E5: FY2026E | F5: FY2027E | G5: FY2028E | H5: Source / note
A6: Period end | B6: 45228 | C6: 45592 | D6: 45956 | E6: =IF(DAY(Valuation!$B$48+1)=1,EOMONTH(Valuation!$B$48,12*E7),EDATE(Valuation!$B$48,12*E7)) | F6: =IF(DAY(Valuation!$B$48+1)=1,EOMONTH(Valuation!$B$48,12*F7),EDATE(Valuation!$B$48,12*F7)) | G6: =IF(DAY(Valuation!$B$48+1)=1,EOMONTH(Valuation!$B$48,12*G7),EDATE(Valuation!$B$48,12*G7))
A7: Projection year | B7: -2 | C7: -1 | D7: 0 | E7: 1 | F7: 2 | G7: 3
A10: Sales
A11: Net sales | B11: 26517 | C11: 27176 | D11: 28368 | E11: =Valuation!$B$49*(1+E48) | F11: =E11*(1+F48) | G11: =F11*(1+G48) | H11: SEC XBRL F1, F2, F3
A12: % YoY | C12: =IF(OR(C11="",B11="",B11=0),"",C11/B11-1) | D12: =IF(OR(D11="",C11="",C11=0),"",D11/C11-1) | E12: =E11/Valuation!$B$49-1 | F12: =F11/E11-1 | G12: =G11/F11-1
A14: Operating profit
A15: EBIT (operating income) | E15: =E11*E49 | F15: =F11*F49 | G15: =G11*G49
A16: EBIT margin | E16: =E15/E11 | F16: =F15/F11 | G16: =G15/G11
A17: D&A | B17: 515 | C17: 392 | D17: 435 | E17: =E11*E51 | F17: =F11*F51 | G17: =G11*G51 | H17: SEC XBRL F34, F35, F36
A18: EBITDA | E18: =E15+E17 | F18: =F15+F17 | G18: =G15+G17
A19: EBITDA margin | E19: =E18/E11 | F19: =F18/F11 | G19: =G18/G11
A20: Net interest income / (expense) | E20: =-Valuation!$B$57*Valuation!$B$55 | F20: =-Valuation!$B$57*E45 | G20: =-Valuation!$B$57*F45 | H20: rate x prior year-end net debt (memo roll)
A21: Pretax income | B21: 7716 | C21: 8152 | D21: 9271 | E21: =E15+E20 | F21: =F15+F20 | G21: =G15+G20 | H21: SEC XBRL F90, F91, F92
A22: Pretax margin | B22: =B21/B11 | C22: =C21/C11 | D22: =D21/D11 | E22: =E21/E11 | F22: =F21/F11 | G22: =G21/G11
A23: Income tax | B23: 860 | C23: 975 | D23: 2273 | E23: =E21*E50 | F23: =F21*F50 | G23: =G21*G50 | H23: SEC XBRL F83, F84, F85
A24: Effective tax rate | B24: =B23/B21 | C24: =C23/C21 | D24: =D23/D21 | E24: =E23/E21 | F24: =F23/F21 | G24: =G23/G21
A25: Net income | B25: 6856 | C25: 7177 | D25: 6998 | E25: =E21-E23 | F25: =F21-F23 | G25: =G21-G23 | H25: SEC XBRL F15, F16, F17
A26: % YoY | C26: =IF(OR(C25="",B25="",B25=0),"",C25/B25-1) | D26: =IF(OR(D25="",C25="",C25=0),"",D25/C25-1) | E26: =IF(OR(D25="",D25=0),"",E25/D25-1) | F26: =IF(OR(E25="",E25=0),"",F25/E25-1) | G26: =IF(OR(F25="",F25=0),"",G25/F25-1)
A27: Diluted shares (M, average) | B27: 845 | C27: 834 | D27: 808 | E27: =Valuation!$B$59*(1+Valuation!$B$61)^(E7-0.5-((Valuation!$B$60-Valuation!$B$48)/365.25)) | F27: =Valuation!$B$59*(1+Valuation!$B$61)^(F7-0.5-((Valuation!$B$60-Valuation!$B$48)/365.25)) | G27: =Valuation!$B$59*(1+Valuation!$B$61)^(G7-0.5-((Valuation!$B$60-Valuation!$B$48)/365.25)) | H27: diluted count rolled at the annual change to mid-year
A28: % YoY | C28: =IF(OR(C27="",B27="",B27=0),"",C27/B27-1) | D28: =IF(OR(D27="",C27="",C27=0),"",D27/C27-1) | E28: =IF(OR(D27="",D27=0),"",E27/D27-1) | F28: =IF(OR(E27="",E27=0),"",F27/E27-1) | G28: =IF(OR(F27="",F27=0),"",G27/F27-1)
A29: Diluted EPS | B29: 8.11 | C29: 8.61 | D29: 8.66 | E29: =E25/E27 | F29: =F25/F27 | G29: =G25/G27 | H29: SEC XBRL F22, F23, F24
A30: % YoY | C30: =IF(OR(C29="",B29="",B29=0),"",C29/B29-1) | D30: =IF(OR(D29="",C29="",C29=0),"",D29/C29-1) | E30: =IF(OR(D29="",D29=0),"",E29/D29-1) | F30: =IF(OR(E29="",E29=0),"",F29/E29-1) | G30: =IF(OR(F29="",F29=0),"",G29/F29-1)
A32: Cash flow
A33: NOPAT (EBIT x (1 - tax)) | E33: =E15*(1-E50) | F33: =F15*(1-F50) | G33: =G15*(1-G50)
A34: + D&A | B34: =B17 | C34: =C17 | D34: =D17 | E34: =E17 | F34: =F17 | G34: =G17
A35: - Capex | B35: 1106 | C35: 1190 | D35: 2260 | E35: =E11*E52 | F35: =F11*F52 | G35: =G11*G52 | H35: SEC XBRL F55, F56, F57
A36: Capex % of sales | B36: =B35/B11 | C36: =C35/C11 | D36: =D35/D11 | E36: =E35/E11 | F36: =F35/F11 | G36: =G35/G11
A37: - Working capital increase | E37: =E53*(E11-Valuation!$B$49) | F37: =F53*(F11-E11) | G37: =G53*(G11-F11)
A38: - Stock comp (adjusted EBIT only) | E38: =IF(AND(Valuation!$B$46="adjusted",Valuation!$B$47="cost"),E42*(1-E50),0) | F38: =IF(AND(Valuation!$B$46="adjusted",Valuation!$B$47="cost"),F42*(1-F50),0) | G38: =IF(AND(Valuation!$B$46="adjusted",Valuation!$B$47="cost"),G42*(1-G50),0)
A39: Free cash flow to firm | E39: =E33+E34-E35-E37-E38 | F39: =F33+F34-F35-F37-F38 | G39: =G33+G34-G35-G37-G38 | H39: what the DCF discounts (Calc tabs)
A40: Operating cash flow (reported) | B40: 8700 | C40: 8677 | D40: 7958 | H40: SEC XBRL F48, F49, F50
A41: FCF (operating cash flow - capex) | B41: =B40-B35 | C41: =C40-C35 | D41: =D40-D35
A42: Stock comp (memo) | B42: 490 | C42: 577 | D42: 668 | E42: =E11*E54 | F42: =F11*F54 | G42: =G11*G54 | H42: SEC XBRL F41, F42, F43
A43: Buybacks + dividends + other uses | B43: 3164 | C43: 5015 | D43: 6279 | E43: =E11*E56+E55+E57 | F43: =F11*F56+F55+F57 | G43: =G11*G56+G55+G57 | H43: SEC XBRL F62, F69, F63, F70, F64, F71
A44: % of sales | B44: =B43/B11 | C44: =C43/C11 | D44: =D43/D11 | E44: =E43/E11 | F44: =F43/F11 | G44: =G43/G11
A45: Net debt / (net cash), year end (memo) | E45: =Valuation!$B$55-E39-E20*(1-E50)+E43 | F45: =E45-F39-F20*(1-F50)+F43 | G45: =F45-G39-G20*(1-G50)+G43 | H45: rolled from the balance-date figure; feeds interest only
A47: Drivers (blue = input; a year left black carries the prior year)
A48: Revenue growth | C48: =C12 | D48: =D12 | E48: 0.20868718 | F48: 0.1911865 | G48: 0.2149428
A49: EBIT margin | E49: 0.32936909 | F49: 0.34803097 | G49: 0.36757969
A50: Tax rate | B50: =B24 | C50: =C24 | D50: =D24 | E50: 0.11 | F50: =E50 | G50: =F50
A51: D&A % revenue | B51: =B17/B11 | C51: =C17/C11 | D51: =D17/D11 | E51: 0.0171 | F51: =E51 | G51: =F51
A52: Capex % revenue | B52: =B36 | C52: =C36 | D52: =D36 | E52: 0.0899 | F52: =E52 | G52: =F52
A53: Working capital % of revenue increase | E53: 0.0896 | F53: =E53 | G53: =F53
A54: Stock comp % revenue | B54: =B42/B11 | C54: =C42/C11 | D54: =D42/D11 | E54: 0.0227 | F54: =E54 | G54: =F54
A55: Shareholder returns ($) | E55: 3543 | F55: =E55 | G55: =F55
A56: Shareholder returns % revenue | B56: =B44 | C56: =C44 | D56: =D44 | E56: 0 | F56: =E56 | G56: =F56
A57: Other uses of cash ($: M&A, investments) | E57: 0 | F57: =E57 | G57: =F57
A58: Adj. EBITDA addback % revenue | E58: 0 | F58: =E58 | G58: =F58
A60: Versus company guidance and street consensus
A61: Consensus: EPS diluted (non-GAAP) | E61: 13.18 | H61: as of 2026-09-30; source 8 (MarketScreener AMAT finances, id 4850 (FY27 EPS $18.43, FY28)
A62: Model vs consensus | E62: =E29/E61-1
A63: Consensus: EPS diluted (non-GAAP) | F63: 18.43 | H63: as of 2026-09-29; source 8 (MarketScreener AMAT finances, id 4850 (FY27 EPS $18.43, FY28)
A64: Model vs consensus | F64: =F29/F63-1
A65: Consensus: EPS diluted (non-GAAP) | G65: 23.85 | H65: as of 2026-09-29; source 8 (MarketScreener AMAT finances, id 4850 (FY27 EPS $18.43, FY28)
A66: Model vs consensus | G66: =G29/G65-1
A67: Consensus: revenue (GAAP) | F67: 46170 | H67: as of 2026-09-29; source 8 (MarketScreener AMAT finances, id 4850 (FY27 EPS $18.43, FY28)
A68: Model vs consensus | F68: =F11/F67-1
A69: Consensus: revenue (GAAP) | G69: 55520 | H69: as of 2026-09-29; source 8 (MarketScreener AMAT finances, id 4850 (FY27 EPS $18.43, FY28)
A70: Model vs consensus | G70: =G11/G69-1
A71: Consensus: net income (non-GAAP) | G71: 18489 | H71: as of 2026-10-15; source 8 (MarketScreener AMAT finances, id 4850 (FY27 EPS $18.43, FY28)
A72: Consensus: free cash flow (company definition (operating cash flow less capex)) | F72: 10600 | H72: as of 2026-09-30; source 8 (MarketScreener AMAT finances, id 4850 (FY27 EPS $18.43, FY28)
A73: Consensus: free cash flow (company definition (operating cash flow less capex)) | G73: 13970 | H73: as of 2026-09-29; source 8 (MarketScreener AMAT finances, id 4850 (FY27 EPS $18.43, FY28)

Sheet Valuation
A1: AMAT: valuation and price target derivation
A2: Value per share at the target date = weighted methods below; the 12-month target is the median of the scenario mix (Distribution tab).
A3: Method | B3: Multiple | C3: Metric at target date | D3: Value per share | E3: Weight | F3: Contribution
A4: ='Calc - research target (12m)'!A67 | B4: =IF('Calc - research target (12m)'!C67="","",'Calc - research target (12m)'!C67) | C4: =IF('Calc - research target (12m)'!I67="","",'Calc - research target (12m)'!I67) | D4: ='Calc - research target (12m)'!F67 | E4: ='Calc - research target (12m)'!G67 | F4: =D4*E4/SUM($E$4:$E$5)
A5: ='Calc - research target (12m)'!A68 | B5: =IF('Calc - research target (12m)'!C68="","",'Calc - research target (12m)'!C68) | C5: =IF('Calc - research target (12m)'!I68="","",'Calc - research target (12m)'!I68) | D5: ='Calc - research target (12m)'!F68 | E5: ='Calc - research target (12m)'!G68 | F5: =D5*E5/SUM($E$4:$E$5)
A6: Research target (12m) per share | D6: ='Calc - research target (12m)'!$F$69 | F6: =SUM(F4:F5)
A8: 12-month EPS basis (what the P/E is applied to)
A9: Fiscal year | B9: =Model!E5 | C9: =Model!F5 | D9: =Model!G5
A10: Share of the 12 months after the target date | B10: ='Calc - research target (12m)'!C38 | C10: ='Calc - research target (12m)'!D38 | D10: ='Calc - research target (12m)'!E38
A11: Model EPS (Model tab) | B11: =Model!E29 | C11: =Model!F29 | D11: =Model!G29
A12: Model EPS, next 12 months after the target date | B12: =SUMPRODUCT(B10:D10,B11:D11)
A15: DCF build (free cash flow to firm, discounted to the target date)
A16: Fiscal year | B16: =Model!E5 | C16: =Model!F5 | D16: =Model!G5
A17: Free cash flow to firm | B17: ='Calc - research target (12m)'!C31 | C17: ='Calc - research target (12m)'!D31 | D17: ='Calc - research target (12m)'!E31
A18: Share of the year after the target date | B18: ='Calc - research target (12m)'!C35 | C18: ='Calc - research target (12m)'!D35 | D18: ='Calc - research target (12m)'!E35
A19: PV at target date | B19: ='Calc - research target (12m)'!C36 | C19: ='Calc - research target (12m)'!D36 | D19: ='Calc - research target (12m)'!E36
A21: PV of free cash flow after the target date | B21: ='Calc - research target (12m)'!B42
A22: Terminal value (final year) | B22: ='Calc - research target (12m)'!B43
A23: PV of terminal value | B23: ='Calc - research target (12m)'!B44
A24: Enterprise value at target date | B24: ='Calc - research target (12m)'!B45
A25: Terminal value share of DCF | B25: ='Calc - research target (12m)'!B46
A26: Net debt at target date | B26: ='Calc - research target (12m)'!B50
A27: Minority interests | B27: ='Calc - research target (12m)'!B51
A28: Adjustments | B28: ='Calc - research target (12m)'!B52
A29: Diluted shares at target date (M) | B29: ='Calc - research target (12m)'!B53
A30: DCF value per share | B30: ='Calc - research target (12m)'!F67
A31: WACC | B31: ='Calc - research target (12m)'!B12
A41: Assumptions (blue = input; sources on the Sources tab)
A42: Input | B42: Value | C42: Basis / note
A43: Run date (valuation as of) | B43: 46318
A44: Target date (run date + 365 days) | B44: =B43+365 | C44: 12-month horizon
A45: Money unit | B45: $M
A46: EBIT basis (gaap / adjusted) | B46: adjusted | C46: gaap = after stock comp
A47: Stock comp treatment (cost / dilution) | B47: dilution | C47: used only when EBIT is adjusted
A48: Last reported fiscal year end | B48: 45956
A49: Net sales, last reported year ($M) | B49: 28368
A50: WACC | B50: 0.1364 | C50: filled in (not stated in this set's original work): cost of equity 0.1364 = T-bill 0.0412 + premium 0.0952 (beta 1.90 on the 5.00% market premium, the price target's market leg, 2026-09-29); after-tax debt 0.0423 x (1 - 0.110) on net debt and minorities 0 vs equity 409,608 (800.00M x $512.01) -> WACC 0.1364
A51: Terminal method (gordon / exit_multiple / steady_state) | B51: gordon
A52: Terminal growth | B52: 0.02
A53: Exit EV/EBITDA (exit_multiple only)
A54: Balance-sheet date | B54: 46229
A55: Net debt / (net cash) at balance date ($M) | B55: 0 | C55: excludes operating leases
A56: Minority interests + preferred stock | B56: 0
A57: Interest rate on net debt / cash | B57: 0.0423
A58: Net debt at target date (override; blank = bridge)
A59: Diluted shares (M) | B59: 800
A60: Share count date | B60: 46229
A61: Annual change in diluted shares | B61: -0.0106 | C61: net of buybacks and stock-comp dilution
A62: Shares at target date (override; blank = from annual change) | B62: 790
A63: DCF weight | B63: 0 | C63: Kilian 2026-10-21: 0 unless the name has a DCF leg (dcf_policy)
A64: Sum-of-the-parts weight | B64: 0
A65: Spread within each scenario (lognormal vol) | B65: 0.15
A66: Share price at the run | B66: 377.24 | C66: close used by the run (2026-10-23)
A68: Target multiple | B68: Multiple | C68: Weight | D68: Basis (ntm / ltm) | E68: EBITDA basis | F68: Stated EPS | G68: Stated FCF/share | H68: Levered | I68: Peer basis
A69: P/E | B69: 21.13 | C69: 1 | D69: ntm | E69: gaap | H69: TRUE | I69: Peer table 2026-10-23 (Kilian's approved WFE set, 2026-10-26), every row re-based to AMAT's EPS basis (stock comp a cost; acquired amortization out): median calendar-NTM P/E 22.615x of 10 front-end equipment makers (Lam Research 22.73, KLA 25.07, ASML (ADR) 26.66, Onto Innovation 18.02, Nova 25.48, Tokyo Electron 22.11, ASM International 22.50, Kokusai Electric 20.26, SCREEN Holdings 15.60, Lasertec 30.65). AMAT itself 20.77x ($377.24 / $18.16 Zacks NTM, which equals AMAT's non-GAAP basis: Q3 FY26 3.50 = 3.50). Multiple = the peer median, no discount (Kilian card 2026-10-26 06:24Z 'Peer median'). [driver model: NTM EPS computed from the drivers (NTM NOPAT / horizon shares).] Was 22.5x (agents' 21-23.5x band, no peer table). EXIT k=0.8 (2026-10-26T12:28Z): Exit-multiple rule (Kilian card 2026-10-26 12:16Z; METHOD.md Peer comparables): exit = peer median x (own NTM multiple / peer median)^k, k = 0.8. Peer median 22.615x; own 20.77x: AMAT $377.24 / Zacks NTM $18.16 (= AMAT non-GAAP basis: Q3 FY26 3.50 = 3.50) = 20.77x (comps_summary.amat_fwd_pe). 22.615 x (20.77 / 22.615)^0.8 = 22.615 x 0.9342 = 21.13x (was 22.62x).
A71: Segment (sum of the parts) | B71: NTM metric | C71: Metric | D71: Multiple | E71: Note
A72: none
A74: Adjustment (equity level) | B74: Value | C74: Probability | D74: Note
A75: Net cash, Q3 FY26 10-Q (2026-07-26) | B75: 7957 | C75: 1 | D75: cash 7,037 + short-term investments 2,196 + long-term investments 5,268 - short-term debt 1,299 - long-term debt 5,245 = 7,957 ($10.03/share on 793.6M shares; post-gate figure). Carried here, not in balance.net_debt, so it is added once to every leg, as the forecasters add net cash per share to each leg.
A77: Custom method | B77: Value per share | C77: Weight | D77: Explanation
A78: none
A80: Scenario | B80: Probability | C80: Growth Δ | D80: Margin Δ | E80: Multiple Δ (turns) | F80: WACC Δ | G80: Multiple %Δ (FCF yield, segments) | H80: Stated EPS/FCF %Δ | I80: Custom methods %Δ | J80: Story
A81: bear | B81: 0.25 | E81: -6 | G81: -0.3636 | J81: Forecasters' median bear (the supervisor did not restate scenarios): a real 2027-28 WFE downturn (customer capex cuts, AI-capex digestion, the Affiliates Rule returning on Nov 10, 2026 unless extended); NTM EPS -20% (~$18.2) and the multiple -6 turns (16.5x). The supervisor's thesis break is $335 (~15x a ~$22.8 NTM EPS). Driver restatement: the -20% NTM EPS = WFE -15% vs path (2027-28 digestion), AGS -3% (Affiliates Rule: China service/parts, company ~$600M/yr at risk), GM -1 pt; multiple -6 turns kept. | K81: driver deltas: wfe -0.15 %; ags -0.03 %; gm -0.01
A82: base | B82: 0.5 | E82: 0.5 | G82: 0.0217 | J82: [exit k=0.8 2026-10-26: P/E 22.62x -> 21.13x] Forecasters' median base: SEMI's path holds (2028 WFE raised to $220B), FY28 expectations +4.55% (~$23.8, about the $23.85 consensus) at 23x NTM. Driver model: SEMI 2028 $220B is now in the wfe driver, so the old +4.55% EPS delta is dropped; multiple +0.5 kept.
A83: bull | B83: 0.25 | E83: 7 | G83: 0.2373 | J83: Forecasters' median bull: the upcycle extends into 2028-29, FY28 EPS +20% (~$27.3) and the multiple +7 turns (29.5x). Driver restatement: the +20% EPS = WFE +10% (Lam Oct 21 >$200B 2027 / sell-side +28-33%), share +4% (GAA, HBM, packaging), GM +1 pt (agent_1 low 50s); FY28 revenue ~$55.5B = consensus. Multiple +7 kept. | K83: driver deltas: wfe +0.1 %; shr +0.04 %; gm +0.01

Sheet Sensitivity
A1: AMAT: sensitivity tables (bold = current inputs; every cell recalculates from the live model)
A3: DCF value per share: WACC (down) x terminal growth (across)
A4: WACC \ growth | B4: =Valuation!$B$52+(-0.01) | C4: =Valuation!$B$52+(-0.005) | D4: =Valuation!$B$52+(0) | E4: =Valuation!$B$52+(0.005) | F4: =Valuation!$B$52+(0.01)
A5: =Valuation!$B$50+(-0.01) | B5: =IF($A5-B$4<=0.01,"n/a",((SUMPRODUCT('Calc - research target (12m)'!$C$31:$E$31,'Calc - research target (12m)'!$C$35:$E$35,(1+$A5)^(-('Calc - research target (12m)'!$C$19:$E$19-'Calc - research target (12m)'!$B$13)))+'Calc - research target (12m)'!$E$31*(1+B$4)/($A5-B$4)/(1+$A5)^('Calc - research target (12m)'!$B$16-'Calc - research target (12m)'!$B$13))-'Calc - research target (12m)'!$B$50-'Calc - research target (12m)'!$B$51+'Calc - research target (12m)'!$B$52)/'Calc - research target (12m)'!$B$53) | C5: =IF($A5-C$4<=0.01,"n/a",((SUMPRODUCT('Calc - research target (12m)'!$C$31:$E$31,'Calc - research target (12m)'!$C$35:$E$35,(1+$A5)^(-('Calc - research target (12m)'!$C$19:$E$19-'Calc - research target (12m)'!$B$13)))+'Calc - research target (12m)'!$E$31*(1+C$4)/($A5-C$4)/(1+$A5)^('Calc - research target (12m)'!$B$16-'Calc - research target (12m)'!$B$13))-'Calc - research target (12m)'!$B$50-'Calc - research target (12m)'!$B$51+'Calc - research target (12m)'!$B$52)/'Calc - research target (12m)'!$B$53) | D5: =IF($A5-D$4<=0.01,"n/a",((SUMPRODUCT('Calc - research target (12m)'!$C$31:$E$31,'Calc - research target (12m)'!$C$35:$E$35,(1+$A5)^(-('Calc - research target (12m)'!$C$19:$E$19-'Calc - research target (12m)'!$B$13)))+'Calc - research target (12m)'!$E$31*(1+D$4)/($A5-D$4)/(1+$A5)^('Calc - research target (12m)'!$B$16-'Calc - research target (12m)'!$B$13))-'Calc - research target (12m)'!$B$50-'Calc - research target (12m)'!$B$51+'Calc - research target (12m)'!$B$52)/'Calc - research target (12m)'!$B$53) | E5: =IF($A5-E$4<=0.01,"n/a",((SUMPRODUCT('Calc - research target (12m)'!$C$31:$E$31,'Calc - research target (12m)'!$C$35:$E$35,(1+$A5)^(-('Calc - research target (12m)'!$C$19:$E$19-'Calc - research target (12m)'!$B$13)))+'Calc - research target (12m)'!$E$31*(1+E$4)/($A5-E$4)/(1+$A5)^('Calc - research target (12m)'!$B$16-'Calc - research target (12m)'!$B$13))-'Calc - research target (12m)'!$B$50-'Calc - research target (12m)'!$B$51+'Calc - research target (12m)'!$B$52)/'Calc - research target (12m)'!$B$53) | F5: =IF($A5-F$4<=0.01,"n/a",((SUMPRODUCT('Calc - research target (12m)'!$C$31:$E$31,'Calc - research target (12m)'!$C$35:$E$35,(1+$A5)^(-('Calc - research target (12m)'!$C$19:$E$19-'Calc - research target (12m)'!$B$13)))+'Calc - research target (12m)'!$E$31*(1+F$4)/($A5-F$4)/(1+$A5)^('Calc - research target (12m)'!$B$16-'Calc - research target (12m)'!$B$13))-'Calc - research target (12m)'!$B$50-'Calc - research target (12m)'!$B$51+'Calc - research target (12m)'!$B$52)/'Calc - research target (12m)'!$B$53)
A6: =Valuation!$B$50+(-0.005) | B6: =IF($A6-B$4<=0.01,"n/a",((SUMPRODUCT('Calc - research target (12m)'!$C$31:$E$31,'Calc - research target (12m)'!$C$35:$E$35,(1+$A6)^(-('Calc - research target (12m)'!$C$19:$E$19-'Calc - research target (12m)'!$B$13)))+'Calc - research target (12m)'!$E$31*(1+B$4)/($A6-B$4)/(1+$A6)^('Calc - research target (12m)'!$B$16-'Calc - research target (12m)'!$B$13))-'Calc - research target (12m)'!$B$50-'Calc - research target (12m)'!$B$51+'Calc - research target (12m)'!$B$52)/'Calc - research target (12m)'!$B$53) | C6: =IF($A6-C$4<=0.01,"n/a",((SUMPRODUCT('Calc - research target (12m)'!$C$31:$E$31,'Calc - research target (12m)'!$C$35:$E$35,(1+$A6)^(-('Calc - research target (12m)'!$C$19:$E$19-'Calc - research target (12m)'!$B$13)))+'Calc - research target (12m)'!$E$31*(1+C$4)/($A6-C$4)/(1+$A6)^('Calc - research target (12m)'!$B$16-'Calc - research target (12m)'!$B$13))-'Calc - research target (12m)'!$B$50-'Calc - research target (12m)'!$B$51+'Calc - research target (12m)'!$B$52)/'Calc - research target (12m)'!$B$53) | D6: =IF($A6-D$4<=0.01,"n/a",((SUMPRODUCT('Calc - research target (12m)'!$C$31:$E$31,'Calc - research target (12m)'!$C$35:$E$35,(1+$A6)^(-('Calc - research target (12m)'!$C$19:$E$19-'Calc - research target (12m)'!$B$13)))+'Calc - research target (12m)'!$E$31*(1+D$4)/($A6-D$4)/(1+$A6)^('Calc - research target (12m)'!$B$16-'Calc - research target (12m)'!$B$13))-'Calc - research target (12m)'!$B$50-'Calc - research target (12m)'!$B$51+'Calc - research target (12m)'!$B$52)/'Calc - research target (12m)'!$B$53) | E6: =IF($A6-E$4<=0.01,"n/a",((SUMPRODUCT('Calc - research target (12m)'!$C$31:$E$31,'Calc - research target (12m)'!$C$35:$E$35,(1+$A6)^(-('Calc - research target (12m)'!$C$19:$E$19-'Calc - research target (12m)'!$B$13)))+'Calc - research target (12m)'!$E$31*(1+E$4)/($A6-E$4)/(1+$A6)^('Calc - research target (12m)'!$B$16-'Calc - research target (12m)'!$B$13))-'Calc - research target (12m)'!$B$50-'Calc - research target (12m)'!$B$51+'Calc - research target (12m)'!$B$52)/'Calc - research target (12m)'!$B$53) | F6: =IF($A6-F$4<=0.01,"n/a",((SUMPRODUCT('Calc - research target (12m)'!$C$31:$E$31,'Calc - research target (12m)'!$C$35:$E$35,(1+$A6)^(-('Calc - research target (12m)'!$C$19:$E$19-'Calc - research target (12m)'!$B$13)))+'Calc - research target (12m)'!$E$31*(1+F$4)/($A6-F$4)/(1+$A6)^('Calc - research target (12m)'!$B$16-'Calc - research target (12m)'!$B$13))-'Calc - research target (12m)'!$B$50-'Calc - research target (12m)'!$B$51+'Calc - research target (12m)'!$B$52)/'Calc - research target (12m)'!$B$53)
A7: =Valuation!$B$50+(0) | B7: =IF($A7-B$4<=0.01,"n/a",((SUMPRODUCT('Calc - research target (12m)'!$C$31:$E$31,'Calc - research target (12m)'!$C$35:$E$35,(1+$A7)^(-('Calc - research target (12m)'!$C$19:$E$19-'Calc - research target (12m)'!$B$13)))+'Calc - research target (12m)'!$E$31*(1+B$4)/($A7-B$4)/(1+$A7)^('Calc - research target (12m)'!$B$16-'Calc - research target (12m)'!$B$13))-'Calc - research target (12m)'!$B$50-'Calc - research target (12m)'!$B$51+'Calc - research target (12m)'!$B$52)/'Calc - research target (12m)'!$B$53) | C7: =IF($A7-C$4<=0.01,"n/a",((SUMPRODUCT('Calc - research target (12m)'!$C$31:$E$31,'Calc - research target (12m)'!$C$35:$E$35,(1+$A7)^(-('Calc - research target (12m)'!$C$19:$E$19-'Calc - research target (12m)'!$B$13)))+'Calc - research target (12m)'!$E$31*(1+C$4)/($A7-C$4)/(1+$A7)^('Calc - research target (12m)'!$B$16-'Calc - research target (12m)'!$B$13))-'Calc - research target (12m)'!$B$50-'Calc - research target (12m)'!$B$51+'Calc - research target (12m)'!$B$52)/'Calc - research target (12m)'!$B$53) | D7: =IF($A7-D$4<=0.01,"n/a",((SUMPRODUCT('Calc - research target (12m)'!$C$31:$E$31,'Calc - research target (12m)'!$C$35:$E$35,(1+$A7)^(-('Calc - research target (12m)'!$C$19:$E$19-'Calc - research target (12m)'!$B$13)))+'Calc - research target (12m)'!$E$31*(1+D$4)/($A7-D$4)/(1+$A7)^('Calc - research target (12m)'!$B$16-'Calc - research target (12m)'!$B$13))-'Calc - research target (12m)'!$B$50-'Calc - research target (12m)'!$B$51+'Calc - research target (12m)'!$B$52)/'Calc - research target (12m)'!$B$53) | E7: =IF($A7-E$4<=0.01,"n/a",((SUMPRODUCT('Calc - research target (12m)'!$C$31:$E$31,'Calc - research target (12m)'!$C$35:$E$35,(1+$A7)^(-('Calc - research target (12m)'!$C$19:$E$19-'Calc - research target (12m)'!$B$13)))+'Calc - research target (12m)'!$E$31*(1+E$4)/($A7-E$4)/(1+$A7)^('Calc - research target (12m)'!$B$16-'Calc - research target (12m)'!$B$13))-'Calc - research target (12m)'!$B$50-'Calc - research target (12m)'!$B$51+'Calc - research target (12m)'!$B$52)/'Calc - research target (12m)'!$B$53) | F7: =IF($A7-F$4<=0.01,"n/a",((SUMPRODUCT('Calc - research target (12m)'!$C$31:$E$31,'Calc - research target (12m)'!$C$35:$E$35,(1+$A7)^(-('Calc - research target (12m)'!$C$19:$E$19-'Calc - research target (12m)'!$B$13)))+'Calc - research target (12m)'!$E$31*(1+F$4)/($A7-F$4)/(1+$A7)^('Calc - research target (12m)'!$B$16-'Calc - research target (12m)'!$B$13))-'Calc - research target (12m)'!$B$50-'Calc - research target (12m)'!$B$51+'Calc - research target (12m)'!$B$52)/'Calc - research target (12m)'!$B$53)
A8: =Valuation!$B$50+(0.005) | B8: =IF($A8-B$4<=0.01,"n/a",((SUMPRODUCT('Calc - research target (12m)'!$C$31:$E$31,'Calc - research target (12m)'!$C$35:$E$35,(1+$A8)^(-('Calc - research target (12m)'!$C$19:$E$19-'Calc - research target (12m)'!$B$13)))+'Calc - research target (12m)'!$E$31*(1+B$4)/($A8-B$4)/(1+$A8)^('Calc - research target (12m)'!$B$16-'Calc - research target (12m)'!$B$13))-'Calc - research target (12m)'!$B$50-'Calc - research target (12m)'!$B$51+'Calc - research target (12m)'!$B$52)/'Calc - research target (12m)'!$B$53) | C8: =IF($A8-C$4<=0.01,"n/a",((SUMPRODUCT('Calc - research target (12m)'!$C$31:$E$31,'Calc - research target (12m)'!$C$35:$E$35,(1+$A8)^(-('Calc - research target (12m)'!$C$19:$E$19-'Calc - research target (12m)'!$B$13)))+'Calc - research target (12m)'!$E$31*(1+C$4)/($A8-C$4)/(1+$A8)^('Calc - research target (12m)'!$B$16-'Calc - research target (12m)'!$B$13))-'Calc - research target (12m)'!$B$50-'Calc - research target (12m)'!$B$51+'Calc - research target (12m)'!$B$52)/'Calc - research target (12m)'!$B$53) | D8: =IF($A8-D$4<=0.01,"n/a",((SUMPRODUCT('Calc - research target (12m)'!$C$31:$E$31,'Calc - research target (12m)'!$C$35:$E$35,(1+$A8)^(-('Calc - research target (12m)'!$C$19:$E$19-'Calc - research target (12m)'!$B$13)))+'Calc - research target (12m)'!$E$31*(1+D$4)/($A8-D$4)/(1+$A8)^('Calc - research target (12m)'!$B$16-'Calc - research target (12m)'!$B$13))-'Calc - research target (12m)'!$B$50-'Calc - research target (12m)'!$B$51+'Calc - research target (12m)'!$B$52)/'Calc - research target (12m)'!$B$53) | E8: =IF($A8-E$4<=0.01,"n/a",((SUMPRODUCT('Calc - research target (12m)'!$C$31:$E$31,'Calc - research target (12m)'!$C$35:$E$35,(1+$A8)^(-('Calc - research target (12m)'!$C$19:$E$19-'Calc - research target (12m)'!$B$13)))+'Calc - research target (12m)'!$E$31*(1+E$4)/($A8-E$4)/(1+$A8)^('Calc - research target (12m)'!$B$16-'Calc - research target (12m)'!$B$13))-'Calc - research target (12m)'!$B$50-'Calc - research target (12m)'!$B$51+'Calc - research target (12m)'!$B$52)/'Calc - research target (12m)'!$B$53) | F8: =IF($A8-F$4<=0.01,"n/a",((SUMPRODUCT('Calc - research target (12m)'!$C$31:$E$31,'Calc - research target (12m)'!$C$35:$E$35,(1+$A8)^(-('Calc - research target (12m)'!$C$19:$E$19-'Calc - research target (12m)'!$B$13)))+'Calc - research target (12m)'!$E$31*(1+F$4)/($A8-F$4)/(1+$A8)^('Calc - research target (12m)'!$B$16-'Calc - research target (12m)'!$B$13))-'Calc - research target (12m)'!$B$50-'Calc - research target (12m)'!$B$51+'Calc - research target (12m)'!$B$52)/'Calc - research target (12m)'!$B$53)
A9: =Valuation!$B$50+(0.01) | B9: =IF($A9-B$4<=0.01,"n/a",((SUMPRODUCT('Calc - research target (12m)'!$C$31:$E$31,'Calc - research target (12m)'!$C$35:$E$35,(1+$A9)^(-('Calc - research target (12m)'!$C$19:$E$19-'Calc - research target (12m)'!$B$13)))+'Calc - research target (12m)'!$E$31*(1+B$4)/($A9-B$4)/(1+$A9)^('Calc - research target (12m)'!$B$16-'Calc - research target (12m)'!$B$13))-'Calc - research target (12m)'!$B$50-'Calc - research target (12m)'!$B$51+'Calc - research target (12m)'!$B$52)/'Calc - research target (12m)'!$B$53) | C9: =IF($A9-C$4<=0.01,"n/a",((SUMPRODUCT('Calc - research target (12m)'!$C$31:$E$31,'Calc - research target (12m)'!$C$35:$E$35,(1+$A9)^(-('Calc - research target (12m)'!$C$19:$E$19-'Calc - research target (12m)'!$B$13)))+'Calc - research target (12m)'!$E$31*(1+C$4)/($A9-C$4)/(1+$A9)^('Calc - research target (12m)'!$B$16-'Calc - research target (12m)'!$B$13))-'Calc - research target (12m)'!$B$50-'Calc - research target (12m)'!$B$51+'Calc - research target (12m)'!$B$52)/'Calc - research target (12m)'!$B$53) | D9: =IF($A9-D$4<=0.01,"n/a",((SUMPRODUCT('Calc - research target (12m)'!$C$31:$E$31,'Calc - research target (12m)'!$C$35:$E$35,(1+$A9)^(-('Calc - research target (12m)'!$C$19:$E$19-'Calc - research target (12m)'!$B$13)))+'Calc - research target (12m)'!$E$31*(1+D$4)/($A9-D$4)/(1+$A9)^('Calc - research target (12m)'!$B$16-'Calc - research target (12m)'!$B$13))-'Calc - research target (12m)'!$B$50-'Calc - research target (12m)'!$B$51+'Calc - research target (12m)'!$B$52)/'Calc - research target (12m)'!$B$53) | E9: =IF($A9-E$4<=0.01,"n/a",((SUMPRODUCT('Calc - research target (12m)'!$C$31:$E$31,'Calc - research target (12m)'!$C$35:$E$35,(1+$A9)^(-('Calc - research target (12m)'!$C$19:$E$19-'Calc - research target (12m)'!$B$13)))+'Calc - research target (12m)'!$E$31*(1+E$4)/($A9-E$4)/(1+$A9)^('Calc - research target (12m)'!$B$16-'Calc - research target (12m)'!$B$13))-'Calc - research target (12m)'!$B$50-'Calc - research target (12m)'!$B$51+'Calc - research target (12m)'!$B$52)/'Calc - research target (12m)'!$B$53) | F9: =IF($A9-F$4<=0.01,"n/a",((SUMPRODUCT('Calc - research target (12m)'!$C$31:$E$31,'Calc - research target (12m)'!$C$35:$E$35,(1+$A9)^(-('Calc - research target (12m)'!$C$19:$E$19-'Calc - research target (12m)'!$B$13)))+'Calc - research target (12m)'!$E$31*(1+F$4)/($A9-F$4)/(1+$A9)^('Calc - research target (12m)'!$B$16-'Calc - research target (12m)'!$B$13))-'Calc - research target (12m)'!$B$50-'Calc - research target (12m)'!$B$51+'Calc - research target (12m)'!$B$52)/'Calc - research target (12m)'!$B$53)
A11: Research target (12m) per share: P/E multiple (down) x metric at target date (across)
A12: Multiple \ metric | B12: ='Calc - research target (12m)'!$E$68*0.9 | C12: ='Calc - research target (12m)'!$E$68*0.95 | D12: ='Calc - research target (12m)'!$E$68*1.0 | E12: ='Calc - research target (12m)'!$E$68*1.05 | F12: ='Calc - research target (12m)'!$E$68*1.1
A13: =Valuation!$B$69+(-3) | B13: =((SUMPRODUCT('Calc - research target (12m)'!$F$67:$F$68,'Calc - research target (12m)'!$G$67:$G$68)-'Calc - research target (12m)'!$F$68*'Calc - research target (12m)'!$G$68)+'Calc - research target (12m)'!$G$68*($A13*(B$12-'Calc - research target (12m)'!$B$54)/'Calc - research target (12m)'!$B$53+'Calc - research target (12m)'!$B$52/'Calc - research target (12m)'!$B$53))/SUM('Calc - research target (12m)'!$G$67:$G$68) | C13: =((SUMPRODUCT('Calc - research target (12m)'!$F$67:$F$68,'Calc - research target (12m)'!$G$67:$G$68)-'Calc - research target (12m)'!$F$68*'Calc - research target (12m)'!$G$68)+'Calc - research target (12m)'!$G$68*($A13*(C$12-'Calc - research target (12m)'!$B$54)/'Calc - research target (12m)'!$B$53+'Calc - research target (12m)'!$B$52/'Calc - research target (12m)'!$B$53))/SUM('Calc - research target (12m)'!$G$67:$G$68) | D13: =((SUMPRODUCT('Calc - research target (12m)'!$F$67:$F$68,'Calc - research target (12m)'!$G$67:$G$68)-'Calc - research target (12m)'!$F$68*'Calc - research target (12m)'!$G$68)+'Calc - research target (12m)'!$G$68*($A13*(D$12-'Calc - research target (12m)'!$B$54)/'Calc - research target (12m)'!$B$53+'Calc - research target (12m)'!$B$52/'Calc - research target (12m)'!$B$53))/SUM('Calc - research target (12m)'!$G$67:$G$68) | E13: =((SUMPRODUCT('Calc - research target (12m)'!$F$67:$F$68,'Calc - research target (12m)'!$G$67:$G$68)-'Calc - research target (12m)'!$F$68*'Calc - research target (12m)'!$G$68)+'Calc - research target (12m)'!$G$68*($A13*(E$12-'Calc - research target (12m)'!$B$54)/'Calc - research target (12m)'!$B$53+'Calc - research target (12m)'!$B$52/'Calc - research target (12m)'!$B$53))/SUM('Calc - research target (12m)'!$G$67:$G$68) | F13: =((SUMPRODUCT('Calc - research target (12m)'!$F$67:$F$68,'Calc - research target (12m)'!$G$67:$G$68)-'Calc - research target (12m)'!$F$68*'Calc - research target (12m)'!$G$68)+'Calc - research target (12m)'!$G$68*($A13*(F$12-'Calc - research target (12m)'!$B$54)/'Calc - research target (12m)'!$B$53+'Calc - research target (12m)'!$B$52/'Calc - research target (12m)'!$B$53))/SUM('Calc - research target (12m)'!$G$67:$G$68)
A14: =Valuation!$B$69+(-2) | B14: =((SUMPRODUCT('Calc - research target (12m)'!$F$67:$F$68,'Calc - research target (12m)'!$G$67:$G$68)-'Calc - research target (12m)'!$F$68*'Calc - research target (12m)'!$G$68)+'Calc - research target (12m)'!$G$68*($A14*(B$12-'Calc - research target (12m)'!$B$54)/'Calc - research target (12m)'!$B$53+'Calc - research target (12m)'!$B$52/'Calc - research target (12m)'!$B$53))/SUM('Calc - research target (12m)'!$G$67:$G$68) | C14: =((SUMPRODUCT('Calc - research target (12m)'!$F$67:$F$68,'Calc - research target (12m)'!$G$67:$G$68)-'Calc - research target (12m)'!$F$68*'Calc - research target (12m)'!$G$68)+'Calc - research target (12m)'!$G$68*($A14*(C$12-'Calc - research target (12m)'!$B$54)/'Calc - research target (12m)'!$B$53+'Calc - research target (12m)'!$B$52/'Calc - research target (12m)'!$B$53))/SUM('Calc - research target (12m)'!$G$67:$G$68) | D14: =((SUMPRODUCT('Calc - research target (12m)'!$F$67:$F$68,'Calc - research target (12m)'!$G$67:$G$68)-'Calc - research target (12m)'!$F$68*'Calc - research target (12m)'!$G$68)+'Calc - research target (12m)'!$G$68*($A14*(D$12-'Calc - research target (12m)'!$B$54)/'Calc - research target (12m)'!$B$53+'Calc - research target (12m)'!$B$52/'Calc - research target (12m)'!$B$53))/SUM('Calc - research target (12m)'!$G$67:$G$68) | E14: =((SUMPRODUCT('Calc - research target (12m)'!$F$67:$F$68,'Calc - research target (12m)'!$G$67:$G$68)-'Calc - research target (12m)'!$F$68*'Calc - research target (12m)'!$G$68)+'Calc - research target (12m)'!$G$68*($A14*(E$12-'Calc - research target (12m)'!$B$54)/'Calc - research target (12m)'!$B$53+'Calc - research target (12m)'!$B$52/'Calc - research target (12m)'!$B$53))/SUM('Calc - research target (12m)'!$G$67:$G$68) | F14: =((SUMPRODUCT('Calc - research target (12m)'!$F$67:$F$68,'Calc - research target (12m)'!$G$67:$G$68)-'Calc - research target (12m)'!$F$68*'Calc - research target (12m)'!$G$68)+'Calc - research target (12m)'!$G$68*($A14*(F$12-'Calc - research target (12m)'!$B$54)/'Calc - research target (12m)'!$B$53+'Calc - research target (12m)'!$B$52/'Calc - research target (12m)'!$B$53))/SUM('Calc - research target (12m)'!$G$67:$G$68)
A15: =Valuation!$B$69+(-1) | B15: =((SUMPRODUCT('Calc - research target (12m)'!$F$67:$F$68,'Calc - research target (12m)'!$G$67:$G$68)-'Calc - research target (12m)'!$F$68*'Calc - research target (12m)'!$G$68)+'Calc - research target (12m)'!$G$68*($A15*(B$12-'Calc - research target (12m)'!$B$54)/'Calc - research target (12m)'!$B$53+'Calc - research target (12m)'!$B$52/'Calc - research target (12m)'!$B$53))/SUM('Calc - research target (12m)'!$G$67:$G$68) | C15: =((SUMPRODUCT('Calc - research target (12m)'!$F$67:$F$68,'Calc - research target (12m)'!$G$67:$G$68)-'Calc - research target (12m)'!$F$68*'Calc - research target (12m)'!$G$68)+'Calc - research target (12m)'!$G$68*($A15*(C$12-'Calc - research target (12m)'!$B$54)/'Calc - research target (12m)'!$B$53+'Calc - research target (12m)'!$B$52/'Calc - research target (12m)'!$B$53))/SUM('Calc - research target (12m)'!$G$67:$G$68) | D15: =((SUMPRODUCT('Calc - research target (12m)'!$F$67:$F$68,'Calc - research target (12m)'!$G$67:$G$68)-'Calc - research target (12m)'!$F$68*'Calc - research target (12m)'!$G$68)+'Calc - research target (12m)'!$G$68*($A15*(D$12-'Calc - research target (12m)'!$B$54)/'Calc - research target (12m)'!$B$53+'Calc - research target (12m)'!$B$52/'Calc - research target (12m)'!$B$53))/SUM('Calc - research target (12m)'!$G$67:$G$68) | E15: =((SUMPRODUCT('Calc - research target (12m)'!$F$67:$F$68,'Calc - research target (12m)'!$G$67:$G$68)-'Calc - research target (12m)'!$F$68*'Calc - research target (12m)'!$G$68)+'Calc - research target (12m)'!$G$68*($A15*(E$12-'Calc - research target (12m)'!$B$54)/'Calc - research target (12m)'!$B$53+'Calc - research target (12m)'!$B$52/'Calc - research target (12m)'!$B$53))/SUM('Calc - research target (12m)'!$G$67:$G$68) | F15: =((SUMPRODUCT('Calc - research target (12m)'!$F$67:$F$68,'Calc - research target (12m)'!$G$67:$G$68)-'Calc - research target (12m)'!$F$68*'Calc - research target (12m)'!$G$68)+'Calc - research target (12m)'!$G$68*($A15*(F$12-'Calc - research target (12m)'!$B$54)/'Calc - research target (12m)'!$B$53+'Calc - research target (12m)'!$B$52/'Calc - research target (12m)'!$B$53))/SUM('Calc - research target (12m)'!$G$67:$G$68)
A16: =Valuation!$B$69+(0) | B16: =((SUMPRODUCT('Calc - research target (12m)'!$F$67:$F$68,'Calc - research target (12m)'!$G$67:$G$68)-'Calc - research target (12m)'!$F$68*'Calc - research target (12m)'!$G$68)+'Calc - research target (12m)'!$G$68*($A16*(B$12-'Calc - research target (12m)'!$B$54)/'Calc - research target (12m)'!$B$53+'Calc - research target (12m)'!$B$52/'Calc - research target (12m)'!$B$53))/SUM('Calc - research target (12m)'!$G$67:$G$68) | C16: =((SUMPRODUCT('Calc - research target (12m)'!$F$67:$F$68,'Calc - research target (12m)'!$G$67:$G$68)-'Calc - research target (12m)'!$F$68*'Calc - research target (12m)'!$G$68)+'Calc - research target (12m)'!$G$68*($A16*(C$12-'Calc - research target (12m)'!$B$54)/'Calc - research target (12m)'!$B$53+'Calc - research target (12m)'!$B$52/'Calc - research target (12m)'!$B$53))/SUM('Calc - research target (12m)'!$G$67:$G$68) | D16: =((SUMPRODUCT('Calc - research target (12m)'!$F$67:$F$68,'Calc - research target (12m)'!$G$67:$G$68)-'Calc - research target (12m)'!$F$68*'Calc - research target (12m)'!$G$68)+'Calc - research target (12m)'!$G$68*($A16*(D$12-'Calc - research target (12m)'!$B$54)/'Calc - research target (12m)'!$B$53+'Calc - research target (12m)'!$B$52/'Calc - research target (12m)'!$B$53))/SUM('Calc - research target (12m)'!$G$67:$G$68) | E16: =((SUMPRODUCT('Calc - research target (12m)'!$F$67:$F$68,'Calc - research target (12m)'!$G$67:$G$68)-'Calc - research target (12m)'!$F$68*'Calc - research target (12m)'!$G$68)+'Calc - research target (12m)'!$G$68*($A16*(E$12-'Calc - research target (12m)'!$B$54)/'Calc - research target (12m)'!$B$53+'Calc - research target (12m)'!$B$52/'Calc - research target (12m)'!$B$53))/SUM('Calc - research target (12m)'!$G$67:$G$68) | F16: =((SUMPRODUCT('Calc - research target (12m)'!$F$67:$F$68,'Calc - research target (12m)'!$G$67:$G$68)-'Calc - research target (12m)'!$F$68*'Calc - research target (12m)'!$G$68)+'Calc - research target (12m)'!$G$68*($A16*(F$12-'Calc - research target (12m)'!$B$54)/'Calc - research target (12m)'!$B$53+'Calc - research target (12m)'!$B$52/'Calc - research target (12m)'!$B$53))/SUM('Calc - research target (12m)'!$G$67:$G$68)
A17: =Valuation!$B$69+(1) | B17: =((SUMPRODUCT('Calc - research target (12m)'!$F$67:$F$68,'Calc - research target (12m)'!$G$67:$G$68)-'Calc - research target (12m)'!$F$68*'Calc - research target (12m)'!$G$68)+'Calc - research target (12m)'!$G$68*($A17*(B$12-'Calc - research target (12m)'!$B$54)/'Calc - research target (12m)'!$B$53+'Calc - research target (12m)'!$B$52/'Calc - research target (12m)'!$B$53))/SUM('Calc - research target (12m)'!$G$67:$G$68) | C17: =((SUMPRODUCT('Calc - research target (12m)'!$F$67:$F$68,'Calc - research target (12m)'!$G$67:$G$68)-'Calc - research target (12m)'!$F$68*'Calc - research target (12m)'!$G$68)+'Calc - research target (12m)'!$G$68*($A17*(C$12-'Calc - research target (12m)'!$B$54)/'Calc - research target (12m)'!$B$53+'Calc - research target (12m)'!$B$52/'Calc - research target (12m)'!$B$53))/SUM('Calc - research target (12m)'!$G$67:$G$68) | D17: =((SUMPRODUCT('Calc - research target (12m)'!$F$67:$F$68,'Calc - research target (12m)'!$G$67:$G$68)-'Calc - research target (12m)'!$F$68*'Calc - research target (12m)'!$G$68)+'Calc - research target (12m)'!$G$68*($A17*(D$12-'Calc - research target (12m)'!$B$54)/'Calc - research target (12m)'!$B$53+'Calc - research target (12m)'!$B$52/'Calc - research target (12m)'!$B$53))/SUM('Calc - research target (12m)'!$G$67:$G$68) | E17: =((SUMPRODUCT('Calc - research target (12m)'!$F$67:$F$68,'Calc - research target (12m)'!$G$67:$G$68)-'Calc - research target (12m)'!$F$68*'Calc - research target (12m)'!$G$68)+'Calc - research target (12m)'!$G$68*($A17*(E$12-'Calc - research target (12m)'!$B$54)/'Calc - research target (12m)'!$B$53+'Calc - research target (12m)'!$B$52/'Calc - research target (12m)'!$B$53))/SUM('Calc - research target (12m)'!$G$67:$G$68) | F17: =((SUMPRODUCT('Calc - research target (12m)'!$F$67:$F$68,'Calc - research target (12m)'!$G$67:$G$68)-'Calc - research target (12m)'!$F$68*'Calc - research target (12m)'!$G$68)+'Calc - research target (12m)'!$G$68*($A17*(F$12-'Calc - research target (12m)'!$B$54)/'Calc - research target (12m)'!$B$53+'Calc - research target (12m)'!$B$52/'Calc - research target (12m)'!$B$53))/SUM('Calc - research target (12m)'!$G$67:$G$68)
A18: =Valuation!$B$69+(2) | B18: =((SUMPRODUCT('Calc - research target (12m)'!$F$67:$F$68,'Calc - research target (12m)'!$G$67:$G$68)-'Calc - research target (12m)'!$F$68*'Calc - research target (12m)'!$G$68)+'Calc - research target (12m)'!$G$68*($A18*(B$12-'Calc - research target (12m)'!$B$54)/'Calc - research target (12m)'!$B$53+'Calc - research target (12m)'!$B$52/'Calc - research target (12m)'!$B$53))/SUM('Calc - research target (12m)'!$G$67:$G$68) | C18: =((SUMPRODUCT('Calc - research target (12m)'!$F$67:$F$68,'Calc - research target (12m)'!$G$67:$G$68)-'Calc - research target (12m)'!$F$68*'Calc - research target (12m)'!$G$68)+'Calc - research target (12m)'!$G$68*($A18*(C$12-'Calc - research target (12m)'!$B$54)/'Calc - research target (12m)'!$B$53+'Calc - research target (12m)'!$B$52/'Calc - research target (12m)'!$B$53))/SUM('Calc - research target (12m)'!$G$67:$G$68) | D18: =((SUMPRODUCT('Calc - research target (12m)'!$F$67:$F$68,'Calc - research target (12m)'!$G$67:$G$68)-'Calc - research target (12m)'!$F$68*'Calc - research target (12m)'!$G$68)+'Calc - research target (12m)'!$G$68*($A18*(D$12-'Calc - research target (12m)'!$B$54)/'Calc - research target (12m)'!$B$53+'Calc - research target (12m)'!$B$52/'Calc - research target (12m)'!$B$53))/SUM('Calc - research target (12m)'!$G$67:$G$68) | E18: =((SUMPRODUCT('Calc - research target (12m)'!$F$67:$F$68,'Calc - research target (12m)'!$G$67:$G$68)-'Calc - research target (12m)'!$F$68*'Calc - research target (12m)'!$G$68)+'Calc - research target (12m)'!$G$68*($A18*(E$12-'Calc - research target (12m)'!$B$54)/'Calc - research target (12m)'!$B$53+'Calc - research target (12m)'!$B$52/'Calc - research target (12m)'!$B$53))/SUM('Calc - research target (12m)'!$G$67:$G$68) | F18: =((SUMPRODUCT('Calc - research target (12m)'!$F$67:$F$68,'Calc - research target (12m)'!$G$67:$G$68)-'Calc - research target (12m)'!$F$68*'Calc - research target (12m)'!$G$68)+'Calc - research target (12m)'!$G$68*($A18*(F$12-'Calc - research target (12m)'!$B$54)/'Calc - research target (12m)'!$B$53+'Calc - research target (12m)'!$B$52/'Calc - research target (12m)'!$B$53))/SUM('Calc - research target (12m)'!$G$67:$G$68)
A19: =Valuation!$B$69+(3) | B19: =((SUMPRODUCT('Calc - research target (12m)'!$F$67:$F$68,'Calc - research target (12m)'!$G$67:$G$68)-'Calc - research target (12m)'!$F$68*'Calc - research target (12m)'!$G$68)+'Calc - research target (12m)'!$G$68*($A19*(B$12-'Calc - research target (12m)'!$B$54)/'Calc - research target (12m)'!$B$53+'Calc - research target (12m)'!$B$52/'Calc - research target (12m)'!$B$53))/SUM('Calc - research target (12m)'!$G$67:$G$68) | C19: =((SUMPRODUCT('Calc - research target (12m)'!$F$67:$F$68,'Calc - research target (12m)'!$G$67:$G$68)-'Calc - research target (12m)'!$F$68*'Calc - research target (12m)'!$G$68)+'Calc - research target (12m)'!$G$68*($A19*(C$12-'Calc - research target (12m)'!$B$54)/'Calc - research target (12m)'!$B$53+'Calc - research target (12m)'!$B$52/'Calc - research target (12m)'!$B$53))/SUM('Calc - research target (12m)'!$G$67:$G$68) | D19: =((SUMPRODUCT('Calc - research target (12m)'!$F$67:$F$68,'Calc - research target (12m)'!$G$67:$G$68)-'Calc - research target (12m)'!$F$68*'Calc - research target (12m)'!$G$68)+'Calc - research target (12m)'!$G$68*($A19*(D$12-'Calc - research target (12m)'!$B$54)/'Calc - research target (12m)'!$B$53+'Calc - research target (12m)'!$B$52/'Calc - research target (12m)'!$B$53))/SUM('Calc - research target (12m)'!$G$67:$G$68) | E19: =((SUMPRODUCT('Calc - research target (12m)'!$F$67:$F$68,'Calc - research target (12m)'!$G$67:$G$68)-'Calc - research target (12m)'!$F$68*'Calc - research target (12m)'!$G$68)+'Calc - research target (12m)'!$G$68*($A19*(E$12-'Calc - research target (12m)'!$B$54)/'Calc - research target (12m)'!$B$53+'Calc - research target (12m)'!$B$52/'Calc - research target (12m)'!$B$53))/SUM('Calc - research target (12m)'!$G$67:$G$68) | F19: =((SUMPRODUCT('Calc - research target (12m)'!$F$67:$F$68,'Calc - research target (12m)'!$G$67:$G$68)-'Calc - research target (12m)'!$F$68*'Calc - research target (12m)'!$G$68)+'Calc - research target (12m)'!$G$68*($A19*(F$12-'Calc - research target (12m)'!$B$54)/'Calc - research target (12m)'!$B$53+'Calc - research target (12m)'!$B$52/'Calc - research target (12m)'!$B$53))/SUM('Calc - research target (12m)'!$G$67:$G$68)
A22: FY2027E diluted EPS: revenue growth change in every year (down) x EBIT margin change (across)
A23: Growth Δ \ margin Δ | B23: -0.01 | C23: -0.005 | D23: 0 | E23: 0.005 | F23: 0.01
A24: -0.02 | B24: =(Valuation!$B$49*(1+Model!E48+$A24)*(1+Model!F48+$A24)*(Model!F49+B$23)+Model!F20)*(1-Model!F50)/Model!F27 | C24: =(Valuation!$B$49*(1+Model!E48+$A24)*(1+Model!F48+$A24)*(Model!F49+C$23)+Model!F20)*(1-Model!F50)/Model!F27 | D24: =(Valuation!$B$49*(1+Model!E48+$A24)*(1+Model!F48+$A24)*(Model!F49+D$23)+Model!F20)*(1-Model!F50)/Model!F27 | E24: =(Valuation!$B$49*(1+Model!E48+$A24)*(1+Model!F48+$A24)*(Model!F49+E$23)+Model!F20)*(1-Model!F50)/Model!F27 | F24: =(Valuation!$B$49*(1+Model!E48+$A24)*(1+Model!F48+$A24)*(Model!F49+F$23)+Model!F20)*(1-Model!F50)/Model!F27
A25: -0.01 | B25: =(Valuation!$B$49*(1+Model!E48+$A25)*(1+Model!F48+$A25)*(Model!F49+B$23)+Model!F20)*(1-Model!F50)/Model!F27 | C25: =(Valuation!$B$49*(1+Model!E48+$A25)*(1+Model!F48+$A25)*(Model!F49+C$23)+Model!F20)*(1-Model!F50)/Model!F27 | D25: =(Valuation!$B$49*(1+Model!E48+$A25)*(1+Model!F48+$A25)*(Model!F49+D$23)+Model!F20)*(1-Model!F50)/Model!F27 | E25: =(Valuation!$B$49*(1+Model!E48+$A25)*(1+Model!F48+$A25)*(Model!F49+E$23)+Model!F20)*(1-Model!F50)/Model!F27 | F25: =(Valuation!$B$49*(1+Model!E48+$A25)*(1+Model!F48+$A25)*(Model!F49+F$23)+Model!F20)*(1-Model!F50)/Model!F27
A26: 0 | B26: =(Valuation!$B$49*(1+Model!E48+$A26)*(1+Model!F48+$A26)*(Model!F49+B$23)+Model!F20)*(1-Model!F50)/Model!F27 | C26: =(Valuation!$B$49*(1+Model!E48+$A26)*(1+Model!F48+$A26)*(Model!F49+C$23)+Model!F20)*(1-Model!F50)/Model!F27 | D26: =(Valuation!$B$49*(1+Model!E48+$A26)*(1+Model!F48+$A26)*(Model!F49+D$23)+Model!F20)*(1-Model!F50)/Model!F27 | E26: =(Valuation!$B$49*(1+Model!E48+$A26)*(1+Model!F48+$A26)*(Model!F49+E$23)+Model!F20)*(1-Model!F50)/Model!F27 | F26: =(Valuation!$B$49*(1+Model!E48+$A26)*(1+Model!F48+$A26)*(Model!F49+F$23)+Model!F20)*(1-Model!F50)/Model!F27
A27: 0.01 | B27: =(Valuation!$B$49*(1+Model!E48+$A27)*(1+Model!F48+$A27)*(Model!F49+B$23)+Model!F20)*(1-Model!F50)/Model!F27 | C27: =(Valuation!$B$49*(1+Model!E48+$A27)*(1+Model!F48+$A27)*(Model!F49+C$23)+Model!F20)*(1-Model!F50)/Model!F27 | D27: =(Valuation!$B$49*(1+Model!E48+$A27)*(1+Model!F48+$A27)*(Model!F49+D$23)+Model!F20)*(1-Model!F50)/Model!F27 | E27: =(Valuation!$B$49*(1+Model!E48+$A27)*(1+Model!F48+$A27)*(Model!F49+E$23)+Model!F20)*(1-Model!F50)/Model!F27 | F27: =(Valuation!$B$49*(1+Model!E48+$A27)*(1+Model!F48+$A27)*(Model!F49+F$23)+Model!F20)*(1-Model!F50)/Model!F27
A28: 0.02 | B28: =(Valuation!$B$49*(1+Model!E48+$A28)*(1+Model!F48+$A28)*(Model!F49+B$23)+Model!F20)*(1-Model!F50)/Model!F27 | C28: =(Valuation!$B$49*(1+Model!E48+$A28)*(1+Model!F48+$A28)*(Model!F49+C$23)+Model!F20)*(1-Model!F50)/Model!F27 | D28: =(Valuation!$B$49*(1+Model!E48+$A28)*(1+Model!F48+$A28)*(Model!F49+D$23)+Model!F20)*(1-Model!F50)/Model!F27 | E28: =(Valuation!$B$49*(1+Model!E48+$A28)*(1+Model!F48+$A28)*(Model!F49+E$23)+Model!F20)*(1-Model!F50)/Model!F27 | F28: =(Valuation!$B$49*(1+Model!E48+$A28)*(1+Model!F48+$A28)*(Model!F49+F$23)+Model!F20)*(1-Model!F50)/Model!F27
A30: Net interest and the share count are held at the base case in table 3.

Sheet Distribution
A1: AMAT: 12-month distribution (mix of lognormals around each scenario value)
A3: Scenario | B3: Probability | C3: Value at target date | D3: Story
A4: bear | B4: =Valuation!B81 | C4: ='Calc - bear'!$F$69 | D4: =Valuation!J81
A5: base | B5: =Valuation!B82 | C5: ='Calc - base'!$F$69 | D5: =Valuation!J82
A6: bull | B6: =Valuation!B83 | C6: ='Calc - bull'!$F$69 | D6: =Valuation!J83
A8: Probabilities sum to | B8: =SUM(B4:B6)
A9: Spread within each scenario | B9: =Valuation!$B$65
A10: Probability-weighted mean | B10: =($B$4*$C$4+$B$5*$C$5+$B$6*$C$6)*EXP($B$9^2/2)
A12: Quantile | B12: Price
A13: Median (model target) | B13: =SQRT(A60*B60)
A14: 10th percentile | B14: =SQRT(D60*E60)
A15: 25th percentile | B15: =SQRT(G60*H60)
A16: 75th percentile | B16: =SQRT(J60*K60)
A17: 90th percentile | B17: =SQRT(M60*N60)
A19: Each quantile solved by bisection (block: low, high, probability above the midpoint)
A20: Median (model target): low | B20: high | C20: P(above mid) | D20: 10th percentile: low | E20: high | F20: P(above mid) | G20: 25th percentile: low | H20: high | I20: P(above mid) | J20: 75th percentile: low | K20: high | L20: P(above mid) | M20: 90th percentile: low | N20: high | O20: P(above mid)
A21: =MIN($C$4,$C$5,$C$6)*0.2 | B21: =MAX($C$4,$C$5,$C$6)*4 | C21: =SUMPRODUCT($B$4:$B$6,1-NORMSDIST((LN(SQRT(A21*B21))-LN($C$4:$C$6))/$B$9)) | D21: =MIN($C$4,$C$5,$C$6)*0.2 | E21: =MAX($C$4,$C$5,$C$6)*4 | F21: =SUMPRODUCT($B$4:$B$6,1-NORMSDIST((LN(SQRT(D21*E21))-LN($C$4:$C$6))/$B$9)) | G21: =MIN($C$4,$C$5,$C$6)*0.2 | H21: =MAX($C$4,$C$5,$C$6)*4 | I21: =SUMPRODUCT($B$4:$B$6,1-NORMSDIST((LN(SQRT(G21*H21))-LN($C$4:$C$6))/$B$9)) | J21: =MIN($C$4,$C$5,$C$6)*0.2 | K21: =MAX($C$4,$C$5,$C$6)*4 | L21: =SUMPRODUCT($B$4:$B$6,1-NORMSDIST((LN(SQRT(J21*K21))-LN($C$4:$C$6))/$B$9)) | M21: =MIN($C$4,$C$5,$C$6)*0.2 | N21: =MAX($C$4,$C$5,$C$6)*4 | O21: =SUMPRODUCT($B$4:$B$6,1-NORMSDIST((LN(SQRT(M21*N21))-LN($C$4:$C$6))/$B$9))
A22: =IF(C21>0.5,SQRT(A21*B21),A21) | B22: =IF(C21>0.5,B21,SQRT(A21*B21)) | C22: =SUMPRODUCT($B$4:$B$6,1-NORMSDIST((LN(SQRT(A22*B22))-LN($C$4:$C$6))/$B$9)) | D22: =IF(F21>0.9,SQRT(D21*E21),D21) | E22: =IF(F21>0.9,E21,SQRT(D21*E21)) | F22: =SUMPRODUCT($B$4:$B$6,1-NORMSDIST((LN(SQRT(D22*E22))-LN($C$4:$C$6))/$B$9)) | G22: =IF(I21>0.75,SQRT(G21*H21),G21) | H22: =IF(I21>0.75,H21,SQRT(G21*H21)) | I22: =SUMPRODUCT($B$4:$B$6,1-NORMSDIST((LN(SQRT(G22*H22))-LN($C$4:$C$6))/$B$9)) | J22: =IF(L21>0.25,SQRT(J21*K21),J21) | K22: =IF(L21>0.25,K21,SQRT(J21*K21)) | L22: =SUMPRODUCT($B$4:$B$6,1-NORMSDIST((LN(SQRT(J22*K22))-LN($C$4:$C$6))/$B$9)) | M22: =IF(O21>0.09999999999999998,SQRT(M21*N21),M21) | N22: =IF(O21>0.09999999999999998,N21,SQRT(M21*N21)) | O22: =SUMPRODUCT($B$4:$B$6,1-NORMSDIST((LN(SQRT(M22*N22))-LN($C$4:$C$6))/$B$9))
A23: =IF(C22>0.5,SQRT(A22*B22),A22) | B23: =IF(C22>0.5,B22,SQRT(A22*B22)) | C23: =SUMPRODUCT($B$4:$B$6,1-NORMSDIST((LN(SQRT(A23*B23))-LN($C$4:$C$6))/$B$9)) | D23: =IF(F22>0.9,SQRT(D22*E22),D22) | E23: =IF(F22>0.9,E22,SQRT(D22*E22)) | F23: =SUMPRODUCT($B$4:$B$6,1-NORMSDIST((LN(SQRT(D23*E23))-LN($C$4:$C$6))/$B$9)) | G23: =IF(I22>0.75,SQRT(G22*H22),G22) | H23: =IF(I22>0.75,H22,SQRT(G22*H22)) | I23: =SUMPRODUCT($B$4:$B$6,1-NORMSDIST((LN(SQRT(G23*H23))-LN($C$4:$C$6))/$B$9)) | J23: =IF(L22>0.25,SQRT(J22*K22),J22) | K23: =IF(L22>0.25,K22,SQRT(J22*K22)) | L23: =SUMPRODUCT($B$4:$B$6,1-NORMSDIST((LN(SQRT(J23*K23))-LN($C$4:$C$6))/$B$9)) | M23: =IF(O22>0.09999999999999998,SQRT(M22*N22),M22) | N23: =IF(O22>0.09999999999999998,N22,SQRT(M22*N22)) | O23: =SUMPRODUCT($B$4:$B$6,1-NORMSDIST((LN(SQRT(M23*N23))-LN($C$4:$C$6))/$B$9))
A24: =IF(C23>0.5,SQRT(A23*B23),A23) | B24: =IF(C23>0.5,B23,SQRT(A23*B23)) | C24: =SUMPRODUCT($B$4:$B$6,1-NORMSDIST((LN(SQRT(A24*B24))-LN($C$4:$C$6))/$B$9)) | D24: =IF(F23>0.9,SQRT(D23*E23),D23) | E24: =IF(F23>0.9,E23,SQRT(D23*E23)) | F24: =SUMPRODUCT($B$4:$B$6,1-NORMSDIST((LN(SQRT(D24*E24))-LN($C$4:$C$6))/$B$9)) | G24: =IF(I23>0.75,SQRT(G23*H23),G23) | H24: =IF(I23>0.75,H23,SQRT(G23*H23)) | I24: =SUMPRODUCT($B$4:$B$6,1-NORMSDIST((LN(SQRT(G24*H24))-LN($C$4:$C$6))/$B$9)) | J24: =IF(L23>0.25,SQRT(J23*K23),J23) | K24: =IF(L23>0.25,K23,SQRT(J23*K23)) | L24: =SUMPRODUCT($B$4:$B$6,1-NORMSDIST((LN(SQRT(J24*K24))-LN($C$4:$C$6))/$B$9)) | M24: =IF(O23>0.09999999999999998,SQRT(M23*N23),M23) | N24: =IF(O23>0.09999999999999998,N23,SQRT(M23*N23)) | O24: =SUMPRODUCT($B$4:$B$6,1-NORMSDIST((LN(SQRT(M24*N24))-LN($C$4:$C$6))/$B$9))
A25: =IF(C24>0.5,SQRT(A24*B24),A24) | B25: =IF(C24>0.5,B24,SQRT(A24*B24)) | C25: =SUMPRODUCT($B$4:$B$6,1-NORMSDIST((LN(SQRT(A25*B25))-LN($C$4:$C$6))/$B$9)) | D25: =IF(F24>0.9,SQRT(D24*E24),D24) | E25: =IF(F24>0.9,E24,SQRT(D24*E24)) | F25: =SUMPRODUCT($B$4:$B$6,1-NORMSDIST((LN(SQRT(D25*E25))-LN($C$4:$C$6))/$B$9)) | G25: =IF(I24>0.75,SQRT(G24*H24),G24) | H25: =IF(I24>0.75,H24,SQRT(G24*H24)) | I25: =SUMPRODUCT($B$4:$B$6,1-NORMSDIST((LN(SQRT(G25*H25))-LN($C$4:$C$6))/$B$9)) | J25: =IF(L24>0.25,SQRT(J24*K24),J24) | K25: =IF(L24>0.25,K24,SQRT(J24*K24)) | L25: =SUMPRODUCT($B$4:$B$6,1-NORMSDIST((LN(SQRT(J25*K25))-LN($C$4:$C$6))/$B$9)) | M25: =IF(O24>0.09999999999999998,SQRT(M24*N24),M24) | N25: =IF(O24>0.09999999999999998,N24,SQRT(M24*N24)) | O25: =SUMPRODUCT($B$4:$B$6,1-NORMSDIST((LN(SQRT(M25*N25))-LN($C$4:$C$6))/$B$9))
A26: =IF(C25>0.5,SQRT(A25*B25),A25) | B26: =IF(C25>0.5,B25,SQRT(A25*B25)) | C26: =SUMPRODUCT($B$4:$B$6,1-NORMSDIST((LN(SQRT(A26*B26))-LN($C$4:$C$6))/$B$9)) | D26: =IF(F25>0.9,SQRT(D25*E25),D25) | E26: =IF(F25>0.9,E25,SQRT(D25*E25)) | F26: =SUMPRODUCT($B$4:$B$6,1-NORMSDIST((LN(SQRT(D26*E26))-LN($C$4:$C$6))/$B$9)) | G26: =IF(I25>0.75,SQRT(G25*H25),G25) | H26: =IF(I25>0.75,H25,SQRT(G25*H25)) | I26: =SUMPRODUCT($B$4:$B$6,1-NORMSDIST((LN(SQRT(G26*H26))-LN($C$4:$C$6))/$B$9)) | J26: =IF(L25>0.25,SQRT(J25*K25),J25) | K26: =IF(L25>0.25,K25,SQRT(J25*K25)) | L26: =SUMPRODUCT($B$4:$B$6,1-NORMSDIST((LN(SQRT(J26*K26))-LN($C$4:$C$6))/$B$9)) | M26: =IF(O25>0.09999999999999998,SQRT(M25*N25),M25) | N26: =IF(O25>0.09999999999999998,N25,SQRT(M25*N25)) | O26: =SUMPRODUCT($B$4:$B$6,1-NORMSDIST((LN(SQRT(M26*N26))-LN($C$4:$C$6))/$B$9))
A27: =IF(C26>0.5,SQRT(A26*B26),A26) | B27: =IF(C26>0.5,B26,SQRT(A26*B26)) | C27: =SUMPRODUCT($B$4:$B$6,1-NORMSDIST((LN(SQRT(A27*B27))-LN($C$4:$C$6))/$B$9)) | D27: =IF(F26>0.9,SQRT(D26*E26),D26) | E27: =IF(F26>0.9,E26,SQRT(D26*E26)) | F27: =SUMPRODUCT($B$4:$B$6,1-NORMSDIST((LN(SQRT(D27*E27))-LN($C$4:$C$6))/$B$9)) | G27: =IF(I26>0.75,SQRT(G26*H26),G26) | H27: =IF(I26>0.75,H26,SQRT(G26*H26)) | I27: =SUMPRODUCT($B$4:$B$6,1-NORMSDIST((LN(SQRT(G27*H27))-LN($C$4:$C$6))/$B$9)) | J27: =IF(L26>0.25,SQRT(J26*K26),J26) | K27: =IF(L26>0.25,K26,SQRT(J26*K26)) | L27: =SUMPRODUCT($B$4:$B$6,1-NORMSDIST((LN(SQRT(J27*K27))-LN($C$4:$C$6))/$B$9)) | M27: =IF(O26>0.09999999999999998,SQRT(M26*N26),M26) | N27: =IF(O26>0.09999999999999998,N26,SQRT(M26*N26)) | O27: =SUMPRODUCT($B$4:$B$6,1-NORMSDIST((LN(SQRT(M27*N27))-LN($C$4:$C$6))/$B$9))
A28: =IF(C27>0.5,SQRT(A27*B27),A27) | B28: =IF(C27>0.5,B27,SQRT(A27*B27)) | C28: =SUMPRODUCT($B$4:$B$6,1-NORMSDIST((LN(SQRT(A28*B28))-LN($C$4:$C$6))/$B$9)) | D28: =IF(F27>0.9,SQRT(D27*E27),D27) | E28: =IF(F27>0.9,E27,SQRT(D27*E27)) | F28: =SUMPRODUCT($B$4:$B$6,1-NORMSDIST((LN(SQRT(D28*E28))-LN($C$4:$C$6))/$B$9)) | G28: =IF(I27>0.75,SQRT(G27*H27),G27) | H28: =IF(I27>0.75,H27,SQRT(G27*H27)) | I28: =SUMPRODUCT($B$4:$B$6,1-NORMSDIST((LN(SQRT(G28*H28))-LN($C$4:$C$6))/$B$9)) | J28: =IF(L27>0.25,SQRT(J27*K27),J27) | K28: =IF(L27>0.25,K27,SQRT(J27*K27)) | L28: =SUMPRODUCT($B$4:$B$6,1-NORMSDIST((LN(SQRT(J28*K28))-LN($C$4:$C$6))/$B$9)) | M28: =IF(O27>0.09999999999999998,SQRT(M27*N27),M27) | N28: =IF(O27>0.09999999999999998,N27,SQRT(M27*N27)) | O28: =SUMPRODUCT($B$4:$B$6,1-NORMSDIST((LN(SQRT(M28*N28))-LN($C$4:$C$6))/$B$9))
A29: =IF(C28>0.5,SQRT(A28*B28),A28) | B29: =IF(C28>0.5,B28,SQRT(A28*B28)) | C29: =SUMPRODUCT($B$4:$B$6,1-NORMSDIST((LN(SQRT(A29*B29))-LN($C$4:$C$6))/$B$9)) | D29: =IF(F28>0.9,SQRT(D28*E28),D28) | E29: =IF(F28>0.9,E28,SQRT(D28*E28)) | F29: =SUMPRODUCT($B$4:$B$6,1-NORMSDIST((LN(SQRT(D29*E29))-LN($C$4:$C$6))/$B$9)) | G29: =IF(I28>0.75,SQRT(G28*H28),G28) | H29: =IF(I28>0.75,H28,SQRT(G28*H28)) | I29: =SUMPRODUCT($B$4:$B$6,1-NORMSDIST((LN(SQRT(G29*H29))-LN($C$4:$C$6))/$B$9)) | J29: =IF(L28>0.25,SQRT(J28*K28),J28) | K29: =IF(L28>0.25,K28,SQRT(J28*K28)) | L29: =SUMPRODUCT($B$4:$B$6,1-NORMSDIST((LN(SQRT(J29*K29))-LN($C$4:$C$6))/$B$9)) | M29: =IF(O28>0.09999999999999998,SQRT(M28*N28),M28) | N29: =IF(O28>0.09999999999999998,N28,SQRT(M28*N28)) | O29: =SUMPRODUCT($B$4:$B$6,1-NORMSDIST((LN(SQRT(M29*N29))-LN($C$4:$C$6))/$B$9))
A30: =IF(C29>0.5,SQRT(A29*B29),A29) | B30: =IF(C29>0.5,B29,SQRT(A29*B29)) | C30: =SUMPRODUCT($B$4:$B$6,1-NORMSDIST((LN(SQRT(A30*B30))-LN($C$4:$C$6))/$B$9)) | D30: =IF(F29>0.9,SQRT(D29*E29),D29) | E30: =IF(F29>0.9,E29,SQRT(D29*E29)) | F30: =SUMPRODUCT($B$4:$B$6,1-NORMSDIST((LN(SQRT(D30*E30))-LN($C$4:$C$6))/$B$9)) | G30: =IF(I29>0.75,SQRT(G29*H29),G29) | H30: =IF(I29>0.75,H29,SQRT(G29*H29)) | I30: =SUMPRODUCT($B$4:$B$6,1-NORMSDIST((LN(SQRT(G30*H30))-LN($C$4:$C$6))/$B$9)) | J30: =IF(L29>0.25,SQRT(J29*K29),J29) | K30: =IF(L29>0.25,K29,SQRT(J29*K29)) | L30: =SUMPRODUCT($B$4:$B$6,1-NORMSDIST((LN(SQRT(J30*K30))-LN($C$4:$C$6))/$B$9)) | M30: =IF(O29>0.09999999999999998,SQRT(M29*N29),M29) | N30: =IF(O29>0.09999999999999998,N29,SQRT(M29*N29)) | O30: =SUMPRODUCT($B$4:$B$6,1-NORMSDIST((LN(SQRT(M30*N30))-LN($C$4:$C$6))/$B$9))
A31: =IF(C30>0.5,SQRT(A30*B30),A30) | B31: =IF(C30>0.5,B30,SQRT(A30*B30)) | C31: =SUMPRODUCT($B$4:$B$6,1-NORMSDIST((LN(SQRT(A31*B31))-LN($C$4:$C$6))/$B$9)) | D31: =IF(F30>0.9,SQRT(D30*E30),D30) | E31: =IF(F30>0.9,E30,SQRT(D30*E30)) | F31: =SUMPRODUCT($B$4:$B$6,1-NORMSDIST((LN(SQRT(D31*E31))-LN($C$4:$C$6))/$B$9)) | G31: =IF(I30>0.75,SQRT(G30*H30),G30) | H31: =IF(I30>0.75,H30,SQRT(G30*H30)) | I31: =SUMPRODUCT($B$4:$B$6,1-NORMSDIST((LN(SQRT(G31*H31))-LN($C$4:$C$6))/$B$9)) | J31: =IF(L30>0.25,SQRT(J30*K30),J30) | K31: =IF(L30>0.25,K30,SQRT(J30*K30)) | L31: =SUMPRODUCT($B$4:$B$6,1-NORMSDIST((LN(SQRT(J31*K31))-LN($C$4:$C$6))/$B$9)) | M31: =IF(O30>0.09999999999999998,SQRT(M30*N30),M30) | N31: =IF(O30>0.09999999999999998,N30,SQRT(M30*N30)) | O31: =SUMPRODUCT($B$4:$B$6,1-NORMSDIST((LN(SQRT(M31*N31))-LN($C$4:$C$6))/$B$9))
A32: =IF(C31>0.5,SQRT(A31*B31),A31) | B32: =IF(C31>0.5,B31,SQRT(A31*B31)) | C32: =SUMPRODUCT($B$4:$B$6,1-NORMSDIST((LN(SQRT(A32*B32))-LN($C$4:$C$6))/$B$9)) | D32: =IF(F31>0.9,SQRT(D31*E31),D31) | E32: =IF(F31>0.9,E31,SQRT(D31*E31)) | F32: =SUMPRODUCT($B$4:$B$6,1-NORMSDIST((LN(SQRT(D32*E32))-LN($C$4:$C$6))/$B$9)) | G32: =IF(I31>0.75,SQRT(G31*H31),G31) | H32: =IF(I31>0.75,H31,SQRT(G31*H31)) | I32: =SUMPRODUCT($B$4:$B$6,1-NORMSDIST((LN(SQRT(G32*H32))-LN($C$4:$C$6))/$B$9)) | J32: =IF(L31>0.25,SQRT(J31*K31),J31) | K32: =IF(L31>0.25,K31,SQRT(J31*K31)) | L32: =SUMPRODUCT($B$4:$B$6,1-NORMSDIST((LN(SQRT(J32*K32))-LN($C$4:$C$6))/$B$9)) | M32: =IF(O31>0.09999999999999998,SQRT(M31*N31),M31) | N32: =IF(O31>0.09999999999999998,N31,SQRT(M31*N31)) | O32: =SUMPRODUCT($B$4:$B$6,1-NORMSDIST((LN(SQRT(M32*N32))-LN($C$4:$C$6))/$B$9))
A33: =IF(C32>0.5,SQRT(A32*B32),A32) | B33: =IF(C32>0.5,B32,SQRT(A32*B32)) | C33: =SUMPRODUCT($B$4:$B$6,1-NORMSDIST((LN(SQRT(A33*B33))-LN($C$4:$C$6))/$B$9)) | D33: =IF(F32>0.9,SQRT(D32*E32),D32) | E33: =IF(F32>0.9,E32,SQRT(D32*E32)) | F33: =SUMPRODUCT($B$4:$B$6,1-NORMSDIST((LN(SQRT(D33*E33))-LN($C$4:$C$6))/$B$9)) | G33: =IF(I32>0.75,SQRT(G32*H32),G32) | H33: =IF(I32>0.75,H32,SQRT(G32*H32)) | I33: =SUMPRODUCT($B$4:$B$6,1-NORMSDIST((LN(SQRT(G33*H33))-LN($C$4:$C$6))/$B$9)) | J33: =IF(L32>0.25,SQRT(J32*K32),J32) | K33: =IF(L32>0.25,K32,SQRT(J32*K32)) | L33: =SUMPRODUCT($B$4:$B$6,1-NORMSDIST((LN(SQRT(J33*K33))-LN($C$4:$C$6))/$B$9)) | M33: =IF(O32>0.09999999999999998,SQRT(M32*N32),M32) | N33: =IF(O32>0.09999999999999998,N32,SQRT(M32*N32)) | O33: =SUMPRODUCT($B$4:$B$6,1-NORMSDIST((LN(SQRT(M33*N33))-LN($C$4:$C$6))/$B$9))
... A60: =IF(C59>0.5,SQRT(A59*B59),A59) | B60: =IF(C59>0.5,B59,SQRT(A59*B59)) | C60: =SUMPRODUCT($B$4:$B$6,1-NORMSDIST((LN(SQRT(A60*B60))-LN($C$4:$C$6))/$B$9)) | D60: =IF(F59>0.9,SQRT(D59*E59),D59) | E60: =IF(F59>0.9,E59,SQRT(D59*E59)) | F60: =SUMPRODUCT($B$4:$B$6,1-NORMSDIST((LN(SQRT(D60*E60))-LN($C$4:$C$6))/$B$9)) | G60: =IF(I59>0.75,SQRT(G59*H59),G59) | H60: =IF(I59>0.75,H59,SQRT(G59*H59)) | I60: =SUMPRODUCT($B$4:$B$6,1-NORMSDIST((LN(SQRT(G60*H60))-LN($C$4:$C$6))/$B$9)) | J60: =IF(L59>0.25,SQRT(J59*K59),J59) | K60: =IF(L59>0.25,K59,SQRT(J59*K59)) | L60: =SUMPRODUCT($B$4:$B$6,1-NORMSDIST((LN(SQRT(J60*K60))-LN($C$4:$C$6))/$B$9)) | M60: =IF(O59>0.09999999999999998,SQRT(M59*N59),M59) | N60: =IF(O59>0.09999999999999998,N59,SQRT(M59*N59)) | O60: =SUMPRODUCT($B$4:$B$6,1-NORMSDIST((LN(SQRT(M60*N60))-LN($C$4:$C$6))/$B$9))

Sheet Calc - research target (12m)
A1: AMAT engine calculation: research target (12m) (reconciled set, no scenario deltas)
A2: Machinery behind the Valuation and Distribution tabs; drivers come from Model, assumptions from Valuation.
A4: Scenario Growth Δ | B4: 0
A5: Scenario Margin Δ | B5: 0
A6: Scenario Multiple Δ (turns) | B6: 0
A7: Scenario WACC Δ | B7: 0
A8: Scenario Multiple %Δ | B8: 0
A9: Scenario Stated EPS/FCF %Δ | B9: 0
A10: Scenario Custom %Δ | B10: 0
A12: WACC | B12: =Valuation!$B$50+B7
A13: Years from last FY end to target date | B13: =(Valuation!$B$44-Valuation!$B$48)/365.25
A14: Years from last FY end to balance date | B14: =(Valuation!$B$54-Valuation!$B$48)/365.25
A15: Years from last FY end to share count date | B15: =(Valuation!$B$60-Valuation!$B$48)/365.25
A16: Projected years | B16: 3
A18: Projection | B18: Base | C18: =Model!E5 | D18: =Model!F5 | E18: =Model!G5
A19: Year index | B19: 0 | C19: 1 | D19: 2 | E19: 3
A20: Period end | C20: =Valuation!$B$48+ROUND(365.25*C19,0) | D20: =Valuation!$B$48+ROUND(365.25*D19,0) | E20: =Valuation!$B$48+ROUND(365.25*E19,0)
A21: Revenue growth | C21: =Model!E48+$B$4 | D21: =Model!F48+$B$4 | E21: =Model!G48+$B$4
A22: Revenue | B22: =Valuation!$B$49 | C22: =B22*(1+C21) | D22: =C22*(1+D21) | E22: =D22*(1+E21)
A23: EBIT margin | C23: =Model!E49+$B$5 | D23: =Model!F49+$B$5 | E23: =Model!G49+$B$5
A24: EBIT | C24: =C22*C23 | D24: =D22*D23 | E24: =E22*E23
A25: Tax rate | C25: =Model!E50 | D25: =Model!F50 | E25: =Model!G50
A26: NOPAT | C26: =C24*(1-C25) | D26: =D24*(1-D25) | E26: =E24*(1-E25)
A27: D&A | C27: =C22*(Model!E51) | D27: =D22*(Model!F51) | E27: =E22*(Model!G51)
A28: Capex | C28: =C22*(Model!E52) | D28: =D22*(Model!F52) | E28: =E22*(Model!G52)
A29: Working capital increase | C29: =(Model!E53)*(C22-B22) | D29: =(Model!F53)*(D22-C22) | E29: =(Model!G53)*(E22-D22)
A30: Stock comp | C30: =C22*(Model!E54) | D30: =D22*(Model!F54) | E30: =E22*(Model!G54)
A31: Free cash flow to firm | C31: =C26+C27-C28-C29-IF(AND(Valuation!$B$46="adjusted",Valuation!$B$47="cost"),C30*(1-C25),0) | D31: =D26+D27-D28-D29-IF(AND(Valuation!$B$46="adjusted",Valuation!$B$47="cost"),D30*(1-D25),0) | E31: =E26+E27-E28-E29-IF(AND(Valuation!$B$46="adjusted",Valuation!$B$47="cost"),E30*(1-E25),0)
A32: EBITDA | C32: =C24+C27 | D32: =D24+D27 | E32: =E24+E27
A33: Adj. EBITDA | C33: =C24+C27+C22*(Model!E58) | D33: =D24+D27+D22*(Model!F58) | E33: =E24+E27+E22*(Model!G58)
A34: Shareholder returns + other uses | C34: =C22*Model!E56+Model!E55+Model!E57 | D34: =D22*Model!F56+Model!F55+Model!F57 | E34: =E22*Model!G56+Model!G55+Model!G57
A35: Share of year after target date | C35: =IF(C19<=$B$13,0,C19-MAX(C19-1,$B$13)) | D35: =IF(D19<=$B$13,0,D19-MAX(D19-1,$B$13)) | E35: =IF(E19<=$B$13,0,E19-MAX(E19-1,$B$13))
A36: PV at target date of FCFF | C36: =IF(C35=0,0,C31*C35/(1+$B$12)^(C19-$B$13)) | D36: =IF(D35=0,0,D31*D35/(1+$B$12)^(D19-$B$13)) | E36: =IF(E35=0,0,E31*E35/(1+$B$12)^(E19-$B$13))
A37: Overlap: balance date to target date | C37: =MAX(0,MIN(C19,$B$13)-MAX(C19-1,$B$14)) | D37: =MAX(0,MIN(D19,$B$13)-MAX(D19-1,$B$14)) | E37: =MAX(0,MIN(E19,$B$13)-MAX(E19-1,$B$14))
A38: NTM weight at target date | C38: =MAX(0,MIN(C19,$B$13+1)-MAX(C19-1,$B$13)) | D38: =MAX(0,MIN(D19,$B$13+1)-MAX(D19-1,$B$13)) | E38: =MAX(0,MIN(E19,$B$13+1)-MAX(E19-1,$B$13))
A39: LTM weight at target date | B39: =MAX(0,MIN(0,$B$13)-MAX(-1,$B$13-1)) | C39: =MAX(0,MIN(C19,$B$13)-MAX(C19-1,$B$13-1)) | D39: =MAX(0,MIN(D19,$B$13)-MAX(D19-1,$B$13-1)) | E39: =MAX(0,MIN(E19,$B$13)-MAX(E19-1,$B$13-1))
A41: Value at the target date
A42: PV of free cash flow after the target date | B42: =SUM($C$36:$E$36)
A43: Terminal value at final year | B43: =IF(Valuation!$B$51="exit_multiple",Valuation!$B$53*E32,E31*(1+Valuation!$B$52)/($B$12-Valuation!$B$52))
A44: PV of terminal value at target date | B44: =B43/(1+$B$12)^($B$16-$B$13)
A45: DCF enterprise value at target date | B45: =B42+B44
A46: Terminal value share of DCF | B46: =B44/B45
A47: Free cash flow earned, balance date to target date | B47: =SUMPRODUCT($C$37:$E$37,$C$31:$E$31)
A48: Shareholder returns + other uses paid | B48: =SUMPRODUCT($C$37:$E$37,$C$34:$E$34)
A49: Interest drag on net debt | B49: =Valuation!$B$57*(1-$C$25)*MAX(Valuation!$B$55,0)*MAX($B$13-$B$14,0)
A50: Net debt at target date | B50: =IF(Valuation!$B$58="",Valuation!$B$55-B47+B49+B48,Valuation!$B$58)
A51: Minority interests | B51: =Valuation!$B$56
A52: Adjustments (probability-weighted) | B52: =(Valuation!B75)*Valuation!C75+0
A53: Diluted shares at target date (M) | B53: =IF(Valuation!$B$62="",Valuation!$B$59*(1+Valuation!$B$61)^MAX($B$13-$B$15,0),Valuation!$B$62)
A54: After-tax interest on target-date net debt | B54: =Valuation!$B$57*(1-$C$25)*MAX(B50,0)
A55: Check: WACC vs terminal growth | B55: =IF(AND(Valuation!$B$51<>"exit_multiple",$B$12<=Valuation!$B$52+0.01),"WACC must exceed terminal growth by 1 point","ok")
A56: Check: projection length | B56: =IF(OR($B$13>=$B$16-1,$B$13+1>$B$16),"add projected years past the target date","ok")
A58: Metric at target date | B58: Next 12 months | C58: Last 12 months
A59: Revenue | B59: =SUMPRODUCT($C$38:$E$38,$C$22:$E$22) | C59: =SUMPRODUCT($C$39:$E$39,$C$22:$E$22)+$B$39*$B$22
A60: EBIT | B60: =SUMPRODUCT($C$38:$E$38,$C$24:$E$24) | C60: =SUMPRODUCT($C$39:$E$39,$C$24:$E$24)
A61: EBITDA | B61: =SUMPRODUCT($C$38:$E$38,$C$32:$E$32) | C61: =SUMPRODUCT($C$39:$E$39,$C$32:$E$32)
A62: Adj. EBITDA | B62: =SUMPRODUCT($C$38:$E$38,$C$33:$E$33) | C62: =SUMPRODUCT($C$39:$E$39,$C$33:$E$33)
A63: NOPAT | B63: =SUMPRODUCT($C$38:$E$38,$C$26:$E$26) | C63: =SUMPRODUCT($C$39:$E$39,$C$26:$E$26)
A64: Free cash flow to firm | B64: =SUMPRODUCT($C$38:$E$38,$C$31:$E$31) | C64: =SUMPRODUCT($C$39:$E$39,$C$31:$E$31)
A66: Valuation method | B66: Metric | C66: Multiple used | D66: Basis | E66: Metric at target date | F66: Value per share | G66: Weight | H66: Metric key | I66: Metric shown (stated per-share figure when used)
A67: DCF (cash flow to target date + terminal) | F67: =((B45)-$B$50-$B$51+$B$52)/$B$53 | G67: =Valuation!$B$63
A68: ="Multiple: "&Valuation!A69&" ("&Valuation!D69&")" | B68: =Valuation!A69 | C68: =IF(B68="FCF yield",(Valuation!B69)*(1-$B$8),(Valuation!B69)+IF(B68="EV/sales",0.1,1)*$B$6) | D68: =Valuation!D69 | E68: =IF(D68="ltm",CHOOSE(H68,$C$59,$C$60,$C$61,$C$62,$C$63,$C$64),CHOOSE(H68,$B$59,$B$60,$B$61,$B$62,$B$63,$B$64)) | F68: =IF(OR(B68="EV/EBITDA",B68="EV/sales",B68="EV/EBIT"),((C68*E68)-$B$50-$B$51+$B$52)/$B$53,IF(B68="P/E",IF(Valuation!F69<>"",C68*(Valuation!F69)*(1+$B$9),C68*(E68-$B$54)/$B$53),IF(Valuation!G69<>"",(Valuation!G69)*(1+$B$9)/C68,(E68-IF(Valuation!H69,$B$54,0))/C68/$B$53))+$B$52/$B$53) | G68: =Valuation!C69 | H68: =IF(B68="EV/sales",1,IF(B68="EV/EBIT",2,IF(B68="EV/EBITDA",IF(Valuation!E69="adjusted",4,3),IF(B68="P/E",5,6)))) | I68: =IF(AND(B68="P/E",Valuation!F69<>""),(Valuation!F69)*(1+$B$9),IF(AND(B68="FCF yield",Valuation!G69<>""),(Valuation!G69)*(1+$B$9),E68))
A69: Value per share at target date (weighted methods) | F69: =SUMPRODUCT(F67:F68,G67:G68)/SUM(G67:G68)

Sheet Calc - bear
A1: AMAT engine calculation: bear scenario
A2: Machinery behind the Valuation and Distribution tabs; drivers come from Model, assumptions from Valuation.
A4: Scenario Growth Δ | B4: =N(Valuation!C81)
A5: Scenario Margin Δ | B5: =N(Valuation!D81)
A6: Scenario Multiple Δ (turns) | B6: =N(Valuation!E81)
A7: Scenario WACC Δ | B7: =N(Valuation!F81)
A8: Scenario Multiple %Δ | B8: =N(Valuation!G81)
A9: Scenario Stated EPS/FCF %Δ | B9: =N(Valuation!H81)
A10: Scenario Custom %Δ | B10: =N(Valuation!I81)
A12: WACC | B12: =Valuation!$B$50+B7
A13: Years from last FY end to target date | B13: =(Valuation!$B$44-Valuation!$B$48)/365.25
A14: Years from last FY end to balance date | B14: =(Valuation!$B$54-Valuation!$B$48)/365.25
A15: Years from last FY end to share count date | B15: =(Valuation!$B$60-Valuation!$B$48)/365.25
A16: Projected years | B16: 3
A18: Projection | B18: Base | C18: =Model!E5 | D18: =Model!F5 | E18: =Model!G5
A19: Year index | B19: 0 | C19: 1 | D19: 2 | E19: 3
A20: Period end | C20: =Valuation!$B$48+ROUND(365.25*C19,0) | D20: =Valuation!$B$48+ROUND(365.25*D19,0) | E20: =Valuation!$B$48+ROUND(365.25*E19,0)
A21: Revenue growth | C21: =Model!E48+$B$4+$B$250 | D21: =Model!F48+$B$4+$B$252 | E21: =Model!G48+$B$4+$B$254
A22: Revenue | B22: =Valuation!$B$49 | C22: =B22*(1+C21) | D22: =C22*(1+D21) | E22: =D22*(1+E21)
A23: EBIT margin | C23: =Model!E49+$B$5+$B$251 | D23: =Model!F49+$B$5+$B$253 | E23: =Model!G49+$B$5+$B$255
A24: EBIT | C24: =C22*C23 | D24: =D22*D23 | E24: =E22*E23
A25: Tax rate | C25: =Model!E50 | D25: =Model!F50 | E25: =Model!G50
A26: NOPAT | C26: =C24*(1-C25) | D26: =D24*(1-D25) | E26: =E24*(1-E25)
A27: D&A | C27: =C22*(Model!E51) | D27: =D22*(Model!F51) | E27: =E22*(Model!G51)
A28: Capex | C28: =C22*(Model!E52) | D28: =D22*(Model!F52) | E28: =E22*(Model!G52)
A29: Working capital increase | C29: =(Model!E53)*(C22-B22) | D29: =(Model!F53)*(D22-C22) | E29: =(Model!G53)*(E22-D22)
A30: Stock comp | C30: =C22*(Model!E54) | D30: =D22*(Model!F54) | E30: =E22*(Model!G54)
A31: Free cash flow to firm | C31: =C26+C27-C28-C29-IF(AND(Valuation!$B$46="adjusted",Valuation!$B$47="cost"),C30*(1-C25),0) | D31: =D26+D27-D28-D29-IF(AND(Valuation!$B$46="adjusted",Valuation!$B$47="cost"),D30*(1-D25),0) | E31: =E26+E27-E28-E29-IF(AND(Valuation!$B$46="adjusted",Valuation!$B$47="cost"),E30*(1-E25),0)
A32: EBITDA | C32: =C24+C27 | D32: =D24+D27 | E32: =E24+E27
A33: Adj. EBITDA | C33: =C24+C27+C22*(Model!E58) | D33: =D24+D27+D22*(Model!F58) | E33: =E24+E27+E22*(Model!G58)
A34: Shareholder returns + other uses | C34: =C22*Model!E56+Model!E55+Model!E57 | D34: =D22*Model!F56+Model!F55+Model!F57 | E34: =E22*Model!G56+Model!G55+Model!G57
A35: Share of year after target date | C35: =IF(C19<=$B$13,0,C19-MAX(C19-1,$B$13)) | D35: =IF(D19<=$B$13,0,D19-MAX(D19-1,$B$13)) | E35: =IF(E19<=$B$13,0,E19-MAX(E19-1,$B$13))
A36: PV at target date of FCFF | C36: =IF(C35=0,0,C31*C35/(1+$B$12)^(C19-$B$13)) | D36: =IF(D35=0,0,D31*D35/(1+$B$12)^(D19-$B$13)) | E36: =IF(E35=0,0,E31*E35/(1+$B$12)^(E19-$B$13))
A37: Overlap: balance date to target date | C37: =MAX(0,MIN(C19,$B$13)-MAX(C19-1,$B$14)) | D37: =MAX(0,MIN(D19,$B$13)-MAX(D19-1,$B$14)) | E37: =MAX(0,MIN(E19,$B$13)-MAX(E19-1,$B$14))
A38: NTM weight at target date | C38: =MAX(0,MIN(C19,$B$13+1)-MAX(C19-1,$B$13)) | D38: =MAX(0,MIN(D19,$B$13+1)-MAX(D19-1,$B$13)) | E38: =MAX(0,MIN(E19,$B$13+1)-MAX(E19-1,$B$13))
A39: LTM weight at target date | B39: =MAX(0,MIN(0,$B$13)-MAX(-1,$B$13-1)) | C39: =MAX(0,MIN(C19,$B$13)-MAX(C19-1,$B$13-1)) | D39: =MAX(0,MIN(D19,$B$13)-MAX(D19-1,$B$13-1)) | E39: =MAX(0,MIN(E19,$B$13)-MAX(E19-1,$B$13-1))
A41: Value at the target date
A42: PV of free cash flow after the target date | B42: =SUM($C$36:$E$36)
A43: Terminal value at final year | B43: =IF(Valuation!$B$51="exit_multiple",Valuation!$B$53*E32,E31*(1+Valuation!$B$52)/($B$12-Valuation!$B$52))
A44: PV of terminal value at target date | B44: =B43/(1+$B$12)^($B$16-$B$13)
A45: DCF enterprise value at target date | B45: =B42+B44
A46: Terminal value share of DCF | B46: =B44/B45
A47: Free cash flow earned, balance date to target date | B47: =SUMPRODUCT($C$37:$E$37,$C$31:$E$31)
A48: Shareholder returns + other uses paid | B48: =SUMPRODUCT($C$37:$E$37,$C$34:$E$34)
A49: Interest drag on net debt | B49: =Valuation!$B$57*(1-$C$25)*MAX(Valuation!$B$55,0)*MAX($B$13-$B$14,0)
A50: Net debt at target date | B50: =IF(Valuation!$B$58="",Valuation!$B$55-B47+B49+B48,Valuation!$B$58)
A51: Minority interests | B51: =Valuation!$B$56
A52: Adjustments (probability-weighted) | B52: =(Valuation!B75)*Valuation!C75+0
A53: Diluted shares at target date (M) | B53: =IF(Valuation!$B$62="",Valuation!$B$59*(1+Valuation!$B$61)^MAX($B$13-$B$15,0),Valuation!$B$62)
A54: After-tax interest on target-date net debt | B54: =Valuation!$B$57*(1-$C$25)*MAX(B50,0)
A55: Check: WACC vs terminal growth | B55: =IF(AND(Valuation!$B$51<>"exit_multiple",$B$12<=Valuation!$B$52+0.01),"WACC must exceed terminal growth by 1 point","ok")
A56: Check: projection length | B56: =IF(OR($B$13>=$B$16-1,$B$13+1>$B$16),"add projected years past the target date","ok")
A58: Metric at target date | B58: Next 12 months | C58: Last 12 months
A59: Revenue | B59: =SUMPRODUCT($C$38:$E$38,$C$22:$E$22) | C59: =SUMPRODUCT($C$39:$E$39,$C$22:$E$22)+$B$39*$B$22
A60: EBIT | B60: =SUMPRODUCT($C$38:$E$38,$C$24:$E$24) | C60: =SUMPRODUCT($C$39:$E$39,$C$24:$E$24)
A61: EBITDA | B61: =SUMPRODUCT($C$38:$E$38,$C$32:$E$32) | C61: =SUMPRODUCT($C$39:$E$39,$C$32:$E$32)
A62: Adj. EBITDA | B62: =SUMPRODUCT($C$38:$E$38,$C$33:$E$33) | C62: =SUMPRODUCT($C$39:$E$39,$C$33:$E$33)
A63: NOPAT | B63: =SUMPRODUCT($C$38:$E$38,$C$26:$E$26) | C63: =SUMPRODUCT($C$39:$E$39,$C$26:$E$26)
A64: Free cash flow to firm | B64: =SUMPRODUCT($C$38:$E$38,$C$31:$E$31) | C64: =SUMPRODUCT($C$39:$E$39,$C$31:$E$31)
A66: Valuation method | B66: Metric | C66: Multiple used | D66: Basis | E66: Metric at target date | F66: Value per share | G66: Weight | H66: Metric key | I66: Metric shown (stated per-share figure when used)
A67: DCF (cash flow to target date + terminal) | F67: =((B45)-$B$50-$B$51+$B$52)/$B$53 | G67: =Valuation!$B$63
A68: ="Multiple: "&Valuation!A69&" ("&Valuation!D69&")" | B68: =Valuation!A69 | C68: =IF(B68="FCF yield",(Valuation!B69)*(1-$B$8),(Valuation!B69)+IF(B68="EV/sales",0.1,1)*$B$6) | D68: =Valuation!D69 | E68: =IF(D68="ltm",CHOOSE(H68,$C$59,$C$60,$C$61,$C$62,$C$63,$C$64),CHOOSE(H68,$B$59,$B$60,$B$61,$B$62,$B$63,$B$64)) | F68: =IF(OR(B68="EV/EBITDA",B68="EV/sales",B68="EV/EBIT"),((C68*E68)-$B$50-$B$51+$B$52)/$B$53,IF(B68="P/E",IF(Valuation!F69<>"",C68*(Valuation!F69)*(1+$B$9),C68*(E68-$B$54)/$B$53),IF(Valuation!G69<>"",(Valuation!G69)*(1+$B$9)/C68,(E68-IF(Valuation!H69,$B$54,0))/C68/$B$53))+$B$52/$B$53) | G68: =Valuation!C69 | H68: =IF(B68="EV/sales",1,IF(B68="EV/EBIT",2,IF(B68="EV/EBITDA",IF(Valuation!E69="adjusted",4,3),IF(B68="P/E",5,6)))) | I68: =IF(AND(B68="P/E",Valuation!F69<>""),(Valuation!F69)*(1+$B$9),IF(AND(B68="FCF yield",Valuation!G69<>""),(Valuation!G69)*(1+$B$9),E68))
A69: Value per share at target date (weighted methods) | F69: =SUMPRODUCT(F67:F68,G67:G68)/SUM(G67:G68)
A249: Driver scenario shifts: line-item changes model_drivers.py resolves from this scenario's driver deltas (added to the Model tab inputs)
A250: Revenue growth, year 1 | B250: -0.14625094
A251: EBIT margin, year 1 | B251: -0.033546218
A252: Revenue growth, year 2 | B252: -0.0030547314
A253: EBIT margin, year 2 | B253: -0.03220747
A254: Revenue growth, year 3 | B254: -0.0045128697
A255: EBIT margin, year 3 | B255: -0.03033758

Sheet Calc - base
A1: AMAT engine calculation: base scenario
A2: Machinery behind the Valuation and Distribution tabs; drivers come from Model, assumptions from Valuation.
A4: Scenario Growth Δ | B4: =N(Valuation!C82)
A5: Scenario Margin Δ | B5: =N(Valuation!D82)
A6: Scenario Multiple Δ (turns) | B6: =N(Valuation!E82)
A7: Scenario WACC Δ | B7: =N(Valuation!F82)
A8: Scenario Multiple %Δ | B8: =N(Valuation!G82)
A9: Scenario Stated EPS/FCF %Δ | B9: =N(Valuation!H82)
A10: Scenario Custom %Δ | B10: =N(Valuation!I82)
A12: WACC | B12: =Valuation!$B$50+B7
A13: Years from last FY end to target date | B13: =(Valuation!$B$44-Valuation!$B$48)/365.25
A14: Years from last FY end to balance date | B14: =(Valuation!$B$54-Valuation!$B$48)/365.25
A15: Years from last FY end to share count date | B15: =(Valuation!$B$60-Valuation!$B$48)/365.25
A16: Projected years | B16: 3
A18: Projection | B18: Base | C18: =Model!E5 | D18: =Model!F5 | E18: =Model!G5
A19: Year index | B19: 0 | C19: 1 | D19: 2 | E19: 3
A20: Period end | C20: =Valuation!$B$48+ROUND(365.25*C19,0) | D20: =Valuation!$B$48+ROUND(365.25*D19,0) | E20: =Valuation!$B$48+ROUND(365.25*E19,0)
A21: Revenue growth | C21: =Model!E48+$B$4 | D21: =Model!F48+$B$4 | E21: =Model!G48+$B$4
A22: Revenue | B22: =Valuation!$B$49 | C22: =B22*(1+C21) | D22: =C22*(1+D21) | E22: =D22*(1+E21)
A23: EBIT margin | C23: =Model!E49+$B$5 | D23: =Model!F49+$B$5 | E23: =Model!G49+$B$5
A24: EBIT | C24: =C22*C23 | D24: =D22*D23 | E24: =E22*E23
A25: Tax rate | C25: =Model!E50 | D25: =Model!F50 | E25: =Model!G50
A26: NOPAT | C26: =C24*(1-C25) | D26: =D24*(1-D25) | E26: =E24*(1-E25)
A27: D&A | C27: =C22*(Model!E51) | D27: =D22*(Model!F51) | E27: =E22*(Model!G51)
A28: Capex | C28: =C22*(Model!E52) | D28: =D22*(Model!F52) | E28: =E22*(Model!G52)
A29: Working capital increase | C29: =(Model!E53)*(C22-B22) | D29: =(Model!F53)*(D22-C22) | E29: =(Model!G53)*(E22-D22)
A30: Stock comp | C30: =C22*(Model!E54) | D30: =D22*(Model!F54) | E30: =E22*(Model!G54)
A31: Free cash flow to firm | C31: =C26+C27-C28-C29-IF(AND(Valuation!$B$46="adjusted",Valuation!$B$47="cost"),C30*(1-C25),0) | D31: =D26+D27-D28-D29-IF(AND(Valuation!$B$46="adjusted",Valuation!$B$47="cost"),D30*(1-D25),0) | E31: =E26+E27-E28-E29-IF(AND(Valuation!$B$46="adjusted",Valuation!$B$47="cost"),E30*(1-E25),0)
A32: EBITDA | C32: =C24+C27 | D32: =D24+D27 | E32: =E24+E27
A33: Adj. EBITDA | C33: =C24+C27+C22*(Model!E58) | D33: =D24+D27+D22*(Model!F58) | E33: =E24+E27+E22*(Model!G58)
A34: Shareholder returns + other uses | C34: =C22*Model!E56+Model!E55+Model!E57 | D34: =D22*Model!F56+Model!F55+Model!F57 | E34: =E22*Model!G56+Model!G55+Model!G57
A35: Share of year after target date | C35: =IF(C19<=$B$13,0,C19-MAX(C19-1,$B$13)) | D35: =IF(D19<=$B$13,0,D19-MAX(D19-1,$B$13)) | E35: =IF(E19<=$B$13,0,E19-MAX(E19-1,$B$13))
A36: PV at target date of FCFF | C36: =IF(C35=0,0,C31*C35/(1+$B$12)^(C19-$B$13)) | D36: =IF(D35=0,0,D31*D35/(1+$B$12)^(D19-$B$13)) | E36: =IF(E35=0,0,E31*E35/(1+$B$12)^(E19-$B$13))
A37: Overlap: balance date to target date | C37: =MAX(0,MIN(C19,$B$13)-MAX(C19-1,$B$14)) | D37: =MAX(0,MIN(D19,$B$13)-MAX(D19-1,$B$14)) | E37: =MAX(0,MIN(E19,$B$13)-MAX(E19-1,$B$14))
A38: NTM weight at target date | C38: =MAX(0,MIN(C19,$B$13+1)-MAX(C19-1,$B$13)) | D38: =MAX(0,MIN(D19,$B$13+1)-MAX(D19-1,$B$13)) | E38: =MAX(0,MIN(E19,$B$13+1)-MAX(E19-1,$B$13))
A39: LTM weight at target date | B39: =MAX(0,MIN(0,$B$13)-MAX(-1,$B$13-1)) | C39: =MAX(0,MIN(C19,$B$13)-MAX(C19-1,$B$13-1)) | D39: =MAX(0,MIN(D19,$B$13)-MAX(D19-1,$B$13-1)) | E39: =MAX(0,MIN(E19,$B$13)-MAX(E19-1,$B$13-1))
A41: Value at the target date
A42: PV of free cash flow after the target date | B42: =SUM($C$36:$E$36)
A43: Terminal value at final year | B43: =IF(Valuation!$B$51="exit_multiple",Valuation!$B$53*E32,E31*(1+Valuation!$B$52)/($B$12-Valuation!$B$52))
A44: PV of terminal value at target date | B44: =B43/(1+$B$12)^($B$16-$B$13)
A45: DCF enterprise value at target date | B45: =B42+B44
A46: Terminal value share of DCF | B46: =B44/B45
A47: Free cash flow earned, balance date to target date | B47: =SUMPRODUCT($C$37:$E$37,$C$31:$E$31)
A48: Shareholder returns + other uses paid | B48: =SUMPRODUCT($C$37:$E$37,$C$34:$E$34)
A49: Interest drag on net debt | B49: =Valuation!$B$57*(1-$C$25)*MAX(Valuation!$B$55,0)*MAX($B$13-$B$14,0)
A50: Net debt at target date | B50: =IF(Valuation!$B$58="",Valuation!$B$55-B47+B49+B48,Valuation!$B$58)
A51: Minority interests | B51: =Valuation!$B$56
A52: Adjustments (probability-weighted) | B52: =(Valuation!B75)*Valuation!C75+0
A53: Diluted shares at target date (M) | B53: =IF(Valuation!$B$62="",Valuation!$B$59*(1+Valuation!$B$61)^MAX($B$13-$B$15,0),Valuation!$B$62)
A54: After-tax interest on target-date net debt | B54: =Valuation!$B$57*(1-$C$25)*MAX(B50,0)
A55: Check: WACC vs terminal growth | B55: =IF(AND(Valuation!$B$51<>"exit_multiple",$B$12<=Valuation!$B$52+0.01),"WACC must exceed terminal growth by 1 point","ok")
A56: Check: projection length | B56: =IF(OR($B$13>=$B$16-1,$B$13+1>$B$16),"add projected years past the target date","ok")
A58: Metric at target date | B58: Next 12 months | C58: Last 12 months
A59: Revenue | B59: =SUMPRODUCT($C$38:$E$38,$C$22:$E$22) | C59: =SUMPRODUCT($C$39:$E$39,$C$22:$E$22)+$B$39*$B$22
A60: EBIT | B60: =SUMPRODUCT($C$38:$E$38,$C$24:$E$24) | C60: =SUMPRODUCT($C$39:$E$39,$C$24:$E$24)
A61: EBITDA | B61: =SUMPRODUCT($C$38:$E$38,$C$32:$E$32) | C61: =SUMPRODUCT($C$39:$E$39,$C$32:$E$32)
A62: Adj. EBITDA | B62: =SUMPRODUCT($C$38:$E$38,$C$33:$E$33) | C62: =SUMPRODUCT($C$39:$E$39,$C$33:$E$33)
A63: NOPAT | B63: =SUMPRODUCT($C$38:$E$38,$C$26:$E$26) | C63: =SUMPRODUCT($C$39:$E$39,$C$26:$E$26)
A64: Free cash flow to firm | B64: =SUMPRODUCT($C$38:$E$38,$C$31:$E$31) | C64: =SUMPRODUCT($C$39:$E$39,$C$31:$E$31)
A66: Valuation method | B66: Metric | C66: Multiple used | D66: Basis | E66: Metric at target date | F66: Value per share | G66: Weight | H66: Metric key | I66: Metric shown (stated per-share figure when used)
A67: DCF (cash flow to target date + terminal) | F67: =((B45)-$B$50-$B$51+$B$52)/$B$53 | G67: =Valuation!$B$63
A68: ="Multiple: "&Valuation!A69&" ("&Valuation!D69&")" | B68: =Valuation!A69 | C68: =IF(B68="FCF yield",(Valuation!B69)*(1-$B$8),(Valuation!B69)+IF(B68="EV/sales",0.1,1)*$B$6) | D68: =Valuation!D69 | E68: =IF(D68="ltm",CHOOSE(H68,$C$59,$C$60,$C$61,$C$62,$C$63,$C$64),CHOOSE(H68,$B$59,$B$60,$B$61,$B$62,$B$63,$B$64)) | F68: =IF(OR(B68="EV/EBITDA",B68="EV/sales",B68="EV/EBIT"),((C68*E68)-$B$50-$B$51+$B$52)/$B$53,IF(B68="P/E",IF(Valuation!F69<>"",C68*(Valuation!F69)*(1+$B$9),C68*(E68-$B$54)/$B$53),IF(Valuation!G69<>"",(Valuation!G69)*(1+$B$9)/C68,(E68-IF(Valuation!H69,$B$54,0))/C68/$B$53))+$B$52/$B$53) | G68: =Valuation!C69 | H68: =IF(B68="EV/sales",1,IF(B68="EV/EBIT",2,IF(B68="EV/EBITDA",IF(Valuation!E69="adjusted",4,3),IF(B68="P/E",5,6)))) | I68: =IF(AND(B68="P/E",Valuation!F69<>""),(Valuation!F69)*(1+$B$9),IF(AND(B68="FCF yield",Valuation!G69<>""),(Valuation!G69)*(1+$B$9),E68))
A69: Value per share at target date (weighted methods) | F69: =SUMPRODUCT(F67:F68,G67:G68)/SUM(G67:G68)

Sheet Calc - bull
A1: AMAT engine calculation: bull scenario
A2: Machinery behind the Valuation and Distribution tabs; drivers come from Model, assumptions from Valuation.
A4: Scenario Growth Δ | B4: =N(Valuation!C83)
A5: Scenario Margin Δ | B5: =N(Valuation!D83)
A6: Scenario Multiple Δ (turns) | B6: =N(Valuation!E83)
A7: Scenario WACC Δ | B7: =N(Valuation!F83)
A8: Scenario Multiple %Δ | B8: =N(Valuation!G83)
A9: Scenario Stated EPS/FCF %Δ | B9: =N(Valuation!H83)
A10: Scenario Custom %Δ | B10: =N(Valuation!I83)
A12: WACC | B12: =Valuation!$B$50+B7
A13: Years from last FY end to target date | B13: =(Valuation!$B$44-Valuation!$B$48)/365.25
A14: Years from last FY end to balance date | B14: =(Valuation!$B$54-Valuation!$B$48)/365.25
A15: Years from last FY end to share count date | B15: =(Valuation!$B$60-Valuation!$B$48)/365.25
A16: Projected years | B16: 3
A18: Projection | B18: Base | C18: =Model!E5 | D18: =Model!F5 | E18: =Model!G5
A19: Year index | B19: 0 | C19: 1 | D19: 2 | E19: 3
A20: Period end | C20: =Valuation!$B$48+ROUND(365.25*C19,0) | D20: =Valuation!$B$48+ROUND(365.25*D19,0) | E20: =Valuation!$B$48+ROUND(365.25*E19,0)
A21: Revenue growth | C21: =Model!E48+$B$4+$B$250 | D21: =Model!F48+$B$4+$B$252 | E21: =Model!G48+$B$4+$B$254
A22: Revenue | B22: =Valuation!$B$49 | C22: =B22*(1+C21) | D22: =C22*(1+D21) | E22: =D22*(1+E21)
A23: EBIT margin | C23: =Model!E49+$B$5+$B$251 | D23: =Model!F49+$B$5+$B$253 | E23: =Model!G49+$B$5+$B$255
A24: EBIT | C24: =C22*C23 | D24: =D22*D23 | E24: =E22*E23
A25: Tax rate | C25: =Model!E50 | D25: =Model!F50 | E25: =Model!G50
A26: NOPAT | C26: =C24*(1-C25) | D26: =D24*(1-D25) | E26: =E24*(1-E25)
A27: D&A | C27: =C22*(Model!E51) | D27: =D22*(Model!F51) | E27: =E22*(Model!G51)
A28: Capex | C28: =C22*(Model!E52) | D28: =D22*(Model!F52) | E28: =E22*(Model!G52)
A29: Working capital increase | C29: =(Model!E53)*(C22-B22) | D29: =(Model!F53)*(D22-C22) | E29: =(Model!G53)*(E22-D22)
A30: Stock comp | C30: =C22*(Model!E54) | D30: =D22*(Model!F54) | E30: =E22*(Model!G54)
A31: Free cash flow to firm | C31: =C26+C27-C28-C29-IF(AND(Valuation!$B$46="adjusted",Valuation!$B$47="cost"),C30*(1-C25),0) | D31: =D26+D27-D28-D29-IF(AND(Valuation!$B$46="adjusted",Valuation!$B$47="cost"),D30*(1-D25),0) | E31: =E26+E27-E28-E29-IF(AND(Valuation!$B$46="adjusted",Valuation!$B$47="cost"),E30*(1-E25),0)
A32: EBITDA | C32: =C24+C27 | D32: =D24+D27 | E32: =E24+E27
A33: Adj. EBITDA | C33: =C24+C27+C22*(Model!E58) | D33: =D24+D27+D22*(Model!F58) | E33: =E24+E27+E22*(Model!G58)
A34: Shareholder returns + other uses | C34: =C22*Model!E56+Model!E55+Model!E57 | D34: =D22*Model!F56+Model!F55+Model!F57 | E34: =E22*Model!G56+Model!G55+Model!G57
A35: Share of year after target date | C35: =IF(C19<=$B$13,0,C19-MAX(C19-1,$B$13)) | D35: =IF(D19<=$B$13,0,D19-MAX(D19-1,$B$13)) | E35: =IF(E19<=$B$13,0,E19-MAX(E19-1,$B$13))
A36: PV at target date of FCFF | C36: =IF(C35=0,0,C31*C35/(1+$B$12)^(C19-$B$13)) | D36: =IF(D35=0,0,D31*D35/(1+$B$12)^(D19-$B$13)) | E36: =IF(E35=0,0,E31*E35/(1+$B$12)^(E19-$B$13))
A37: Overlap: balance date to target date | C37: =MAX(0,MIN(C19,$B$13)-MAX(C19-1,$B$14)) | D37: =MAX(0,MIN(D19,$B$13)-MAX(D19-1,$B$14)) | E37: =MAX(0,MIN(E19,$B$13)-MAX(E19-1,$B$14))
A38: NTM weight at target date | C38: =MAX(0,MIN(C19,$B$13+1)-MAX(C19-1,$B$13)) | D38: =MAX(0,MIN(D19,$B$13+1)-MAX(D19-1,$B$13)) | E38: =MAX(0,MIN(E19,$B$13+1)-MAX(E19-1,$B$13))
A39: LTM weight at target date | B39: =MAX(0,MIN(0,$B$13)-MAX(-1,$B$13-1)) | C39: =MAX(0,MIN(C19,$B$13)-MAX(C19-1,$B$13-1)) | D39: =MAX(0,MIN(D19,$B$13)-MAX(D19-1,$B$13-1)) | E39: =MAX(0,MIN(E19,$B$13)-MAX(E19-1,$B$13-1))
A41: Value at the target date
A42: PV of free cash flow after the target date | B42: =SUM($C$36:$E$36)
A43: Terminal value at final year | B43: =IF(Valuation!$B$51="exit_multiple",Valuation!$B$53*E32,E31*(1+Valuation!$B$52)/($B$12-Valuation!$B$52))
A44: PV of terminal value at target date | B44: =B43/(1+$B$12)^($B$16-$B$13)
A45: DCF enterprise value at target date | B45: =B42+B44
A46: Terminal value share of DCF | B46: =B44/B45
A47: Free cash flow earned, balance date to target date | B47: =SUMPRODUCT($C$37:$E$37,$C$31:$E$31)
A48: Shareholder returns + other uses paid | B48: =SUMPRODUCT($C$37:$E$37,$C$34:$E$34)
A49: Interest drag on net debt | B49: =Valuation!$B$57*(1-$C$25)*MAX(Valuation!$B$55,0)*MAX($B$13-$B$14,0)
A50: Net debt at target date | B50: =IF(Valuation!$B$58="",Valuation!$B$55-B47+B49+B48,Valuation!$B$58)
A51: Minority interests | B51: =Valuation!$B$56
A52: Adjustments (probability-weighted) | B52: =(Valuation!B75)*Valuation!C75+0
A53: Diluted shares at target date (M) | B53: =IF(Valuation!$B$62="",Valuation!$B$59*(1+Valuation!$B$61)^MAX($B$13-$B$15,0),Valuation!$B$62)
A54: After-tax interest on target-date net debt | B54: =Valuation!$B$57*(1-$C$25)*MAX(B50,0)
A55: Check: WACC vs terminal growth | B55: =IF(AND(Valuation!$B$51<>"exit_multiple",$B$12<=Valuation!$B$52+0.01),"WACC must exceed terminal growth by 1 point","ok")
A56: Check: projection length | B56: =IF(OR($B$13>=$B$16-1,$B$13+1>$B$16),"add projected years past the target date","ok")
A58: Metric at target date | B58: Next 12 months | C58: Last 12 months
A59: Revenue | B59: =SUMPRODUCT($C$38:$E$38,$C$22:$E$22) | C59: =SUMPRODUCT($C$39:$E$39,$C$22:$E$22)+$B$39*$B$22
A60: EBIT | B60: =SUMPRODUCT($C$38:$E$38,$C$24:$E$24) | C60: =SUMPRODUCT($C$39:$E$39,$C$24:$E$24)
A61: EBITDA | B61: =SUMPRODUCT($C$38:$E$38,$C$32:$E$32) | C61: =SUMPRODUCT($C$39:$E$39,$C$32:$E$32)
A62: Adj. EBITDA | B62: =SUMPRODUCT($C$38:$E$38,$C$33:$E$33) | C62: =SUMPRODUCT($C$39:$E$39,$C$33:$E$33)
A63: NOPAT | B63: =SUMPRODUCT($C$38:$E$38,$C$26:$E$26) | C63: =SUMPRODUCT($C$39:$E$39,$C$26:$E$26)
A64: Free cash flow to firm | B64: =SUMPRODUCT($C$38:$E$38,$C$31:$E$31) | C64: =SUMPRODUCT($C$39:$E$39,$C$31:$E$31)
A66: Valuation method | B66: Metric | C66: Multiple used | D66: Basis | E66: Metric at target date | F66: Value per share | G66: Weight | H66: Metric key | I66: Metric shown (stated per-share figure when used)
A67: DCF (cash flow to target date + terminal) | F67: =((B45)-$B$50-$B$51+$B$52)/$B$53 | G67: =Valuation!$B$63
A68: ="Multiple: "&Valuation!A69&" ("&Valuation!D69&")" | B68: =Valuation!A69 | C68: =IF(B68="FCF yield",(Valuation!B69)*(1-$B$8),(Valuation!B69)+IF(B68="EV/sales",0.1,1)*$B$6) | D68: =Valuation!D69 | E68: =IF(D68="ltm",CHOOSE(H68,$C$59,$C$60,$C$61,$C$62,$C$63,$C$64),CHOOSE(H68,$B$59,$B$60,$B$61,$B$62,$B$63,$B$64)) | F68: =IF(OR(B68="EV/EBITDA",B68="EV/sales",B68="EV/EBIT"),((C68*E68)-$B$50-$B$51+$B$52)/$B$53,IF(B68="P/E",IF(Valuation!F69<>"",C68*(Valuation!F69)*(1+$B$9),C68*(E68-$B$54)/$B$53),IF(Valuation!G69<>"",(Valuation!G69)*(1+$B$9)/C68,(E68-IF(Valuation!H69,$B$54,0))/C68/$B$53))+$B$52/$B$53) | G68: =Valuation!C69 | H68: =IF(B68="EV/sales",1,IF(B68="EV/EBIT",2,IF(B68="EV/EBITDA",IF(Valuation!E69="adjusted",4,3),IF(B68="P/E",5,6)))) | I68: =IF(AND(B68="P/E",Valuation!F69<>""),(Valuation!F69)*(1+$B$9),IF(AND(B68="FCF yield",Valuation!G69<>""),(Valuation!G69)*(1+$B$9),E68))
A69: Value per share at target date (weighted methods) | F69: =SUMPRODUCT(F67:F68,G67:G68)/SUM(G67:G68)
A249: Driver scenario shifts: line-item changes model_drivers.py resolves from this scenario's driver deltas (added to the Model tab inputs)
A250: Revenue growth, year 1 | B250: 0.13349221
A251: EBIT margin, year 1 | B251: 0.027012602
A252: Revenue growth, year 2 | B252: 0.0026874489
A253: EBIT margin, year 2 | B253: 0.026031714
A254: Revenue growth, year 3 | B254: 0.0040643938
A255: EBIT margin, year 3 | B255: 0.024671429

Sheet Agents
A1: AMAT: each forecaster's own assumption set through the same engine (from model_engine.json, not live)
A3: Set | B3: Research target (12m) | C3: Median | D3: 25th pct | E3: 75th pct | F3: WACC | G3: Y1 growth | H3: Y1 margin | I3: Terminal growth | J3: DCF weight | K3: Years | L3: Multiples | M3: Supervisor's note
A4: supervisor | B4: 443.35626 | C4: 453.44211 | D4: 334.76901 | E4: 578.20975 | F4: 0.1364 | G4: 0.20868718 | H4: 0.32936909 | I4: 0.02 | J4: 0 | K4: 3 | L4: P/E 21.13 (ntm)
A5: agent_1 | M5: engine error: no model_inputs found
A6: agent_2 | M6: engine error: no model_inputs found
A7: agent_3 | M7: engine error: no model_inputs found
A8: agent_4 | M8: engine error: no model_inputs found
A9: agent_5 | M9: engine error: no model_inputs found

Sheet Sources
A1: AMAT: where each input comes from (source numbers point to the list below; F ids to the SEC fact table)
A3: Input | B3: Value | C3: Basis | D3: Sources | E3: SEC fact ids | F3: Derivation
A4: Base year revenue FY2025 (fy_end 2025-10-26) | B4: 28368.0 | C4: reported | E4: F3 | F4: filled in (not stated in this set's original work): 10-K FY2025 revenue 28,368 (F3).
A5: FY2026 revenue growth | B5: 0.2087 | C5: driver | D5: 10, 9 | E5: F3, F6 | F5: Computed from drivers (driver_build.years): revenue = wfe x shr x 1000 + ags + 1185; EBIT = rev x gm - opex; see drivers[]. Was: Not settled by the supervisor; Q3 FY26 8-K outlook (source 10) and 10-Q nine months (source 9), as in every forecaster set: FY2026 revenue 34,287 = nine months to 2026-07-26 24,037 (10-Q; F6 derivation) + Q4 FY26 outlook midpoint 10,250 (Q3 FY26 8-K Ex. 99.1); growth 34,287 / 28,368 - 1 = 0.2087.
A6: FY2027 revenue growth | B6: 0.3474 | C6: driver | D6: 8 | F6: Computed from drivers (driver_build.years): revenue = wfe x shr x 1000 + ags + 1185; EBIT = rev x gm - opex; see drivers[]. Was: Not settled by the supervisor: forecasters' median FY27 consensus revenue $46.2B (MarketScreener, source 8; 46,312M on 2026-10-15). Growth 46,200 / 34,287 - 1 = 0.3474.
A7: FY2028 revenue growth | B7: 0.2013 | C7: driver | D7: 8 | F7: Computed from drivers (driver_build.years): revenue = wfe x shr x 1000 + ags + 1185; EBIT = rev x gm - opex; see drivers[]. Was: Not settled by the supervisor: forecasters' median FY28 revenue $55.5B (consensus; 55,857M on 2026-10-15). Growth 55,500 / 46,200 - 1 = 0.2013.
A8: FY2026 EBIT margin (non-GAAP) | B8: 0.3343 | C8: driver | D8: 10 | E8: F33 | F8: Computed from drivers (driver_build.years): revenue = wfe x shr x 1000 + ags + 1185; EBIT = rev x gm - opex; see drivers[]. Was: Not settled by the supervisor; agent_1's cited FY26 EPS, used in every forecaster set. FY26 non-GAAP EPS $12.75 (9M $8.73 + Q4 outlook midpoint $4.02, Q3 FY26 8-K Ex. 99.1) x 800M diluted shares (F33) = 10,200 net income / 34,287 revenue = 0.2975 net margin; / (1 - 0.11 non-GAAP tax) = 0.3343. Interest income on net cash is ignored (it is small against operating income).
A9: FY2027 EBIT margin (non-GAAP) | B9: 0.3551 | C9: driver | D9: 8 | F9: Computed from drivers (driver_build.years): revenue = wfe x shr x 1000 + ags + 1185; EBIT = rev x gm - opex; see drivers[]. Was: Not settled by the supervisor: forecasters' median (agents 1, 3, 4, 5) consensus FY27 net income $14.6B. Net margin 14,600 / 46,200 = 0.3160; / (1 - 0.11) = 0.3551.
A10: FY2028 EBIT margin (non-GAAP) | B10: 0.3643 | C10: driver | D10: 8, 1 | F10: Computed from drivers (driver_build.years): revenue = wfe x shr x 1000 + ags + 1185; EBIT = rev x gm - opex; see drivers[]. Was: Supervisor: NTM EPS ~$22.8 (23.85 x 0.955 = 22.78) x 790M (forecasters' median share count) = 17,996 net income. Net margin 17,996 / 55,500 = 0.3243; / (1 - 0.11) = 0.3643.
A11: Tax rate (non-GAAP, all years) | B11: 0.11 | C11: reported | D11: 10 | F11: Not settled by the supervisor: forecasters' median non-GAAP tax rate 11.0% (agents 1 and 3 cite it from the Q3 FY26 8-K Ex. 99.1, source 10; the other three sets were filled in with it).
A12: D&A % revenue | B12: 0.0171 | C12: reported | E12: F39, F6 | F12: filled in (not stated in this set's original work): TTM D&A 527 (F39) / TTM revenue 30,837 (F6) = 0.0171.
A13: Capex % revenue | B13: 0.0899 | C13: reported | E13: F60, F6 | F13: filled in (not stated in this set's original work): TTM capex 2,773 (F60) / TTM revenue 30,837 (F6) = 0.0899 (elevated facilities capex, which the forecasters expect to continue).
A14: Working capital % of incremental revenue | B14: 0.0896 | C14: estimate | D14: 10 | E14: F39, F60, F6 | F14: Not settled by the supervisor: forecasters' median working-capital driver 0.0896 (agents' values 0.2087, 0.0594, 0.0776, 0.0896, 0.1392; each derived from that set's stated FCF conversion or margin). D&A and capex are filled in (not stated in this set's original work).
A15: Stock comp % revenue (memo; sbc_treatment dilution) | B15: 0.0227 | C15: reported | E15: F46, F6 | F15: filled in (not stated in this set's original work): TTM SBC 701 (F46) / 30,837 (F6) = 0.0227. Counted once: the set's EPS is non-GAAP and the share count (800M -> 790M) is net of buybacks and stock-comp issuance, so FCFF does not deduct SBC again.
A16: Shareholder returns per year (dividends + buybacks) | B16: 3543.0 | C16: reported | E16: F67, F74 | F16: filled in (not stated in this set's original work): TTM buybacks 2,028 (F67) + dividends 1,515 (F74) = 3,543; only moves the DCF leg's net-cash bridge.
A17: Terminal growth | B17: 0.02 | C17: judgment | F17: filled in (not stated in this set's original work): the run states no terminal growth; 0.02 is the engine's default. It only affects the DCF leg (weight 0) and the reverse-DCF WACC.
A18: WACC | B18: 0.1364 | C18: estimate | F18: filled in (not stated in this set's original work): cost of equity 0.1364 = T-bill 0.0412 + premium 0.0952 (beta 1.90 on the 5.00% market premium, the price target's market leg, 2026-09-29); after-tax debt 0.0423 x (1 - 0.110) on net debt and minorities 0 vs equity 409,608 (800.00M x $512.01) -> WACC 0.1364
A19: Balance-sheet date | B19: 2026-07-26 | C19: reported | D19: 9 | E19: F97 | F19: Q3 FY26 10-Q balance sheet (quarter ended 2026-07-26), the date of the net cash the set adds.
A20: Net cash (equity adjustment) | B20: 7957.0 | C20: reported | D20: 9 | E20: F97, F98, F99, F101 | F20: Supervisor's fair value: + $10.0/share net cash (10-Q, July 26, 2026: cash and investments 14,501 less debt 6,544 = 7,957 on 793.6M shares). 10-Q: cash 7,037 (F97) + short-term investments 2,196 (F98) + long-term investments 5,268 (10-Q; not in the fact pack's tags) - short-term debt 1,299 (F101) - long-term debt 5,245 (F99) = 7,957 = $10.03/share on 793.6M shares (F103). The fact pack's F105 (-1,490) is narrower: it leaves out the long-term investments and adds F100 (1,199, the current notes, which agent_3 reads as inside the 1,299 short-term debt). In the engine 7,957 / 790M horizon shares = $10.07/share, $0.04 above the $10.03 the set adds.
A21: balance.net_debt | B21: 0.0 | C21: judgment | F21: Set to 0 because the 7,957 net cash is carried as an equity adjustment (counting it in both places would add it twice in the DCF leg).
A22: Interest rate on debt | B22: 0.0423 | C22: reported | E22: F81, F99, F101 | F22: filled in (not stated in this set's original work): TTM interest expense 277 (F81) / debt 6,544 (F101 1,299 + F99 5,245) = 0.0423; unused while AMAT holds net cash.
A23: Diluted shares now | B23: 800.0 | C23: reported | D23: 9 | E23: F33 | F23: Not settled by the supervisor: forecasters' median 800M diluted in FQ3 (F33).
A24: Diluted shares at horizon | B24: 790.0 | C24: estimate | D24: 9 | E24: F33, F103 | F24: Not settled by the supervisor (it divides net cash by 793.6M shares outstanding): forecasters' median ~790M at the horizon.
A25: Shares annual change | B25: -0.0106 | C25: estimate | E25: F33 | F25: Derived: (790 / 800)^(1 / 1.177 years from 2026-07-26 to 2027-09-29) - 1 = -0.0106; shares.horizon 790 is what the engine uses.
A26: P/E: NTM EPS at Sep-2027 (FY28) | B26: None | C26: driver | D26: 8, 1, 2 | F26: Computed by the engine from the driver-led projection (NTM NOPAT at Sep-2027 / 790M horizon shares); was the stated 22.78 (FY28 consensus 23.85 x 0.955).
A27: P/E: multiple | B27: 21.13 | C27: estimate | D27: 12, 16, 20, 24, 28, 32, 35, 39, 43, 46 | F27: Exit-multiple rule (Kilian card 2026-10-26 12:16Z; METHOD.md Peer comparables): exit = peer median x (own NTM multiple / peer median)^k, k = 0.8. Peer median 22.615x (unchanged, gated 2026-10-26: see the rest of this derivation). Own multiple 20.77x on the peers' basis: AMAT $377.24 / Zacks NTM $18.16 (= AMAT non-GAAP basis: Q3 FY26 3.50 = 3.50) = 20.77x (comps_summary.amat_fwd_pe). Exit = 22.615 x (20.77 / 22.615)^0.8 = 22.615 x 0.9342 = 21.13x (was 22.62x). PREVIOUS DERIVATION: Median of the 10 re-based peer calendar-NTM P/E rows below (2026-10-23 closes): sorted 15.60, 18.02, 20.26, 22.11, 22.50, 22.73, 25.07, 25.48, 26.66, 30.65; median = (22.50 + 22.73) / 2 = 22.615 -> 22.62x. Each row reconciles its provider EPS to the company's own GAAP and adjusted figures and re-bases to AMAT's non-GAAP basis (Q3 FY26 8-K Ex. 99.1: AMAT excludes acquired-intangible amortization, integration/deal costs, legal settlement, restructuring, strategic-investment gains/losses and tax items; stock comp stays a cost). Two rows move: ASM International 22.84 -> 22.50 and Kokusai 21.37 -> 20.26 (acquisition-related charges added back), the rest are already on AMAT's basis. Was 22.5x (supervisor judgment inside the agents' 21-23.5x band). AMAT's own 20.77x (-8% to the median) is not carried: Kilian picked the median on the card of 2026-10-26 06:24Z.
A28: P/E: weight | B28: 1.0 | C28: judgment | F28: The supervisor's fair value is a single P/E build plus net cash.
A29: Scenario bear: probability and deltas | B29: {"prob": 0.25, "multiple": -6.0, "eps_pct": -0.2, "multiple_pct": -0.3636} | C29: judgment | F29: Forecasters' median bear: p 0.25 (0.27/0.23/0.25/0.25/0.25), -6 turns (-4.5/-7/-6/-6.5/-5.5), EPS -20% (-20.45/-12.77/-20.93/-15.91/-20%). FCF multiple_pct for the record only (no FCF leg).
A30: Scenario base: probability and deltas | B30: {"prob": 0.5, "multiple": 0.5, "eps_pct": 0.0455, "multiple_pct": 0.0217} | C30: judgment | F30: Forecasters' median base: p 0.50, +0.5 turn (0/+0.5/0/+0.5/+0.5), EPS +4.55% (+4.55/0/+4.65/+4.55/+2.22%).
A31: Scenario bull: probability and deltas | B31: {"prob": 0.25, "multiple": 7.0, "eps_pct": 0.2, "multiple_pct": 0.2373} | C31: judgment | F31: Forecasters' median bull: p 0.25, +7 turns (7/7/8.5/8.5/7), EPS +20% (+20.45/+10.64/+20.93/+15.91/+20%).
A32: Scenario vol (within-scenario) | B32: 0.15 | C32: judgment | F32: filled in (not stated in this set's original work): engine default 0.15. The original work states only total-distribution spreads (lognormal sigmas of ~0.42-0.60 around the whole ladder), which include the bear/base/bull spread.
A33: reference (guidance and consensus) | B33: see reference | C33: consensus | D33: 8, 10 | F33: Only figures the run's files cite, with their dates: the Q4 FY26 outlook (8-K Ex. 99.1) and MarketScreener consensus; Yahoo and StockAnalysis figures are not in the supervisor's sources and are left out.
A34: Other revenue (Corporate and Other incl. Display), all years | B34: 1185.0 | C34: reported | D34: 9 | F34: 10-K FY2025 (acc 0001628280-25-056742) segment revenue table and Q4 FY25 8-K Ex. 99.1 (acc 0001628280-25-051998): Corporate and Other FY2025 1,185 (Display 1.06B); 10-Q Q3 FY26 (source 9) 9M FY26 Other 886 + Q3 rate 294 = ~1,180 FY26; held flat (plain constant in driver_build, ~2-3% of revenue).
A35: driver:wfe | B35: Wafer fab equipment market, calendar year (SEMI): 116.9 -> 143.9/175.3/220 (primary) | C35: primary | F35: 2026-2027 = agents' median (all five cite SEMI July: 143.9 / 175.3). 2028: the four-agent median is SEMI July ~$200B (+14.1%); I take SEMI's own later figure, $220B (Sept 1, agent_5 and the supervisor's source review: "That reason is out of date"), because it is the same industry body superseding its July number. Check vs later evidence: Lam Research Oct 21 call (adhoc amat_review.md) puts 2026 WFE at mid-$150B and 2027 preliminary >$200B (+29%); that is a peer management view (not taken at face value), carried as the bull move and as a judgment call. Consensus FY27 revenue $46.2B implies ~+42% Semiconductor Systems growth, i.e. WFE well above SEMI or a share gain; not adopted.
A36: driver:shr | B36: AMAT Semiconductor Systems revenue / SEMI WFE (FY26 segment basis): 0.1839 -> 0.1827/0.1827/0.1827 (estimate) | C36: estimate | F36: FY2025 recast to the FY2026 segment basis: original 9M FY25 SS 16,038 (20,798 - Q4 4,760) vs recast 16,562 -> 200mm reclass 524 per 9M (~175/qtr); Q4 FY25 assumed the same 175 -> FY25 SS 20,798 + 699 = 21,497, AGS 6,385 - 699 = 5,686 (estimate on filing figures; the FY2026 10-K will restate FY25 exactly). Base 21,497 / 116.9B = 0.18389. FY2026 SS = 9M 18,146 + Q4 8,151 (Q4 total 10,250 midpoint - AGS ~1,800 (Q3 1,781 + ~1%) - Other 299 (FY Other held at 1,185 less 9M 886; Q3 was 294)) = 26,297 / 143.9 = 0.18275 (share ~flat vs FY25 on SEMI's series: SS +22.3% vs WFE +23.1%). FY27-28 held flat = agents' median (agents 1, 3, 4: "roughly flat" / Castellano "flat ~19-20%" on his own WFE basis); share gains are the agents' bull story only.
A37: driver:ags | B37: Applied Global Services revenue (installed-base services, spares, upgrades; FY26 segment basis): 5,686 -> 6,805/7,622/8,232 (estimate) | C37: estimate | F37: FY2025 recast to the FY2026 segment basis: original 9M FY25 SS 16,038 (20,798 - Q4 4,760) vs recast 16,562 -> 200mm reclass 524 per 9M (~175/qtr); Q4 FY25 assumed the same 175 -> FY25 SS 20,798 + 699 = 21,497, AGS 6,385 - 699 = 5,686 (estimate on filing figures; the FY2026 10-K will restate FY25 exactly). FY2026 = 9M 5,005 + Q4 ~1,800 (Q3 1,781 + ~1%) = 6,805 (+19.7% on 5,686; 9M +18.2% recast). FY27 +12% = 7,622 and FY28 +8% = 8,232: fades from FY26's utilization-led ~+19% toward the FY23-25 CAGR of +5.5% (5,732 -> 6,385, 10-K) as the installed base keeps growing with WFE. No agent states an AGS number (fewer than 2 views; the supervisor states none).
A38: driver:gm | B38: Non-GAAP gross margin: 0.4877 -> 0.5004/0.506/0.508 (estimate) | C38: estimate | F38: FY2026 = (11,992 + Q4 10,250 x 50.4% Q3 rate) / 34,287 = 50.04% (no GM guide). FY27 50.6%, FY28 50.8%: +0.2 pt/yr from the Q3 50.4% run-rate. History is +1.2 pt/yr (47.6% FY24 -> 48.8% FY25 -> ~50.0% FY26; 13 straight quarters of y/y expansion); I take less because agent_1 frames "low 50s" as the bull case and fewer than 2 agents state a base number.
A39: driver:opex | B39: Non-GAAP operating expenses (RD&E + marketing & selling + G&A): 5,273 -> 5,865/6,452/6,968 (estimate) | C39: estimate | F39: FY2026 = 4,253 + Q4 1,612; Q4 backed out of the $4.02 EPS guide: 4.02 x ~798M = 3,208 net / (1 - 11%) = 3,604 pre-tax - ~50 other income (Q3: 3.50 x 800 / 0.89 = 3,146 vs OI 3,096; the Q3 8-K's reported non-GAAP pre-tax is 3,141, i.e. ~45) = 3,554 OI; Q4 GP 10,250 x 50.4% = 5,166 -> opex 1,612. FY26 +11.2% (FY25 +5.4% on FY24 5,002). FY27 +10% = 6,452 (RD&E +22% y/y in Q3), FY28 +8% = 6,968. Consensus FY27 (EPS 18.43 on $46.2B) implies ~6.9B at a 50.5% GM; mine is lower at lower revenue.
A40: Peer NTM P/E: Lam Research (LRCX) | B40: 22.73 | C40: estimate | D40: 12, 13, 14, 15 | F40: USD 230.1 close 2026-10-23 / AMAT-basis NTM EPS 10.123 = 22.73x (provider basis 22.73x). NTM from 2026-10-23 = w x FY1 + (1 - w) x FY2, w = days to FY1 end (2027-06-30) / 365 = 0.6849; FY1 9.48, FY2 11.52; provider NTM EPS 10.123 re-based to AMAT's EPS basis (non-GAAP: stock comp a cost; acquired-intangible amortization, deal/restructuring costs, investment gains and tax items excluded) = 10.123 (factor 1) = 10.123. Provider check: Zacks actual Sep-2026 quarter EPS 2.20 = Lam's non-GAAP 2.20 (GAAP 2.19; Q1 FY27 8-K Ex. 99.1). Lam's adjustments are acquired-intangible amortization, deferred-comp (EDC) revaluation that nets to ~0 and a tax-law item; stock comp stays in. AMAT's basis also excludes acquisition amortization and tax items and keeps stock comp, so AMAT-basis EPS = 2.20 = Zacks: factor 1.000. Growth FY2/FY1 +21.5%. Consensus: Zacks via Nasdaq.com.
A41: Peer NTM P/E: KLA (KLAC) | B41: 25.07 | C41: estimate | D41: 16, 17, 18, 19 | F41: USD 145.61 close 2026-10-23 / AMAT-basis NTM EPS 5.808 = 25.07x (provider basis 25.07x). NTM from 2026-10-23 = w x FY1 + (1 - w) x FY2, w = days to FY1 end (2027-06-30) / 365 = 0.6849; FY1 5.43, FY2 6.63; provider NTM EPS 5.808 re-based to AMAT's EPS basis (non-GAAP: stock comp a cost; acquired-intangible amortization, deal/restructuring costs, investment gains and tax items excluded) = 5.808 (factor 1) = 5.808. Provider check: Zacks actual Jun-2026 quarter EPS 1.05 = KLA's non-GAAP 1.05 (GAAP 1.04; Q4 FY26 8-K Ex. 99.1). KLA's adjustments are acquisition-related charges, restructuring, impairment and discrete tax items; stock comp stays in, as at AMAT: factor 1.000. Post 10:1 split of 2026-06-12 on both price and EPS. Growth FY2/FY1 +22.1%. Consensus: Zacks via Nasdaq.com.
A42: Peer NTM P/E: ASML (ADR) (ASML) | B42: 26.66 | C42: estimate | D42: 20, 21, 22, 23 | F42: USD 1,571.8 close 2026-10-23 / AMAT-basis NTM EPS 58.965 = 26.66x (provider basis 26.66x). NTM from 2026-10-23 = w x FY1 + (1 - w) x FY2, w = days to FY1 end (2026-12-31) / 365 = 0.1890; FY1 46.03, FY2 61.98; provider NTM EPS 58.965 re-based to AMAT's EPS basis (non-GAAP: stock comp a cost; acquired-intangible amortization, deal/restructuring costs, investment gains and tax items excluded) = 58.965 (factor 1) = 58.965. Provider check: Zacks actual Sep-2026 quarter EPS $14.89 per ADR = ASML's US GAAP basic EPS EUR 12.95 (Q3 2026 release) at ~1.15 USD/EUR; ASML publishes no adjusted EPS, stock comp is a cost. AMAT would also strip acquired-intangible amortization, which is small at ASML: factor 1.000. Growth FY2/FY1 +34.7%. Consensus: Zacks via Nasdaq.com.
A43: Peer NTM P/E: Onto Innovation (ONTO) | B43: 18.02 | C43: estimate | D43: 24, 25, 26, 27 | F43: USD 198.68 close 2026-10-23 / AMAT-basis NTM EPS 11.024 = 18.02x (provider basis 18.02x). NTM from 2026-10-23 = w x FY1 + (1 - w) x FY2, w = days to FY1 end (2026-12-31) / 365 = 0.1890; FY1 8.04, FY2 11.72; provider NTM EPS 11.024 re-based to AMAT's EPS basis (non-GAAP: stock comp a cost; acquired-intangible amortization, deal/restructuring costs, investment gains and tax items excluded) = 11.024 (factor 1) = 11.024. Provider check: Zacks actual Jun-2026 quarter EPS 1.93 = Onto's non-GAAP 1.93 (GAAP 1.21; Q2 2026 8-K Ex. 99.1). The 0.72 gap is M&A expenses 0.17, restructuring 0.31, intangible amortization 0.39, tax -0.15; no stock-comp add-back. AMAT excludes the same kinds of items (acquisition amortization, integration/deal costs, restructuring, tax effects) and keeps stock comp: factor 1.000. Growth FY2/FY1 +45.8%. Consensus: Zacks via Nasdaq.com.
A44: Peer NTM P/E: Nova (NVMI) | B44: 25.48 | C44: estimate | D44: 28, 29, 30, 31 | F44: USD 311.35 close 2026-10-23 / AMAT-basis NTM EPS 12.217 = 25.48x (provider basis 25.48x). NTM from 2026-10-23 = w x FY1 + (1 - w) x FY2, w = days to FY1 end (2026-12-31) / 365 = 0.1890; FY1 9.89, FY2 12.76; provider NTM EPS 12.217 re-based to AMAT's EPS basis (non-GAAP: stock comp a cost; acquired-intangible amortization, deal/restructuring costs, investment gains and tax items excluded) = 12.217 x 1.0000 = 12.217. Provider check: Nova's non-GAAP (Q2 2026 6-K) adds back stock comp, acquired amortization, debt-cost amortization and lease/loan revaluation: GAAP 2.20 / non-GAAP 2.51 (Q2), 2.04 / 2.33 (Q1). Zacks actual 2.35 / 2.15 = non-GAAP less after-tax stock comp: 2.51 - 6,764 x (1 - 14.7%) / 34,450 = 2.34; 2.33 - 7,305 x (1 - 16.0%) / 34,439 = 2.15 (tax = the quarter's tax effect / total adjustments, 1,970 / 13,419 and 2,104 / 13,110). So Zacks keeps stock comp as a cost and strips acquired amortization, as AMAT does. Left as Zacks treats them: debt-cost amortization (~0.02 a share a quarter after tax, under 1%) and FX revaluation of leases/loans, which swings sign (-6,955K a year earlier). Factor 1.000. Growth FY2/FY1 +29.0%. Consensus: Zacks via Nasdaq.com.
A45: Peer NTM P/E: Tokyo Electron (8035.T) | B45: 22.11 | C45: estimate | D45: 32, 33, 34 | F45: JPY 9,458.0 close 2026-10-23 / AMAT-basis NTM EPS 427.864 = 22.11x (provider basis 22.11x). NTM from 2026-10-23 = w x FY1 + (1 - w) x FY2, w = days to FY1 end (2027-03-31) / 365 = 0.4356; FY1 344.9, FY2 491.9; provider NTM EPS 427.864 re-based to AMAT's EPS basis (non-GAAP: stock comp a cost; acquired-intangible amortization, deal/restructuring costs, investment gains and tax items excluded) = 427.864 (factor 1) = 427.864. Provider check: MarketScreener FY3/26 actual EPS 250.9 = Tokyo Electron's reported J-GAAP EPS JPY 1,254.57 / 5 (5:1 split 2026-09-29; Yahoo split record), so the series is reported and split-adjusted; price is post-split. J-GAAP expenses stock comp; acquired-intangible amortization is negligible: factor 1.000. Growth FY2/FY1 +42.6%. Home listing, local currency on both sides (no FX); consensus: MarketScreener.
A46: Peer NTM P/E: ASM International (ASM.AS) | B46: 22.5 | C46: estimate | D46: 35, 36, 37, 38 | F46: EUR 699.8 close 2026-10-23 / AMAT-basis NTM EPS 31.096 = 22.50x (provider basis 22.84x). NTM from 2026-10-23 = w x FY1 + (1 - w) x FY2, w = days to FY1 end (2026-12-31) / 365 = 0.1890; FY1 23.27, FY2 32.35; provider NTM EPS 30.634 re-based to AMAT's EPS basis (non-GAAP: stock comp a cost; acquired-intangible amortization, deal/restructuring costs, investment gains and tax items excluded) = 30.634 +0.463 = 31.096. Provider check: MarketScreener FY2025 actual EPS 14.70 vs reported ~14.77 (net earnings EUR 723.7M), i.e. reported IFRS. ASM's adjusted net earnings exceed reported by EUR 7.5M a quarter (Q1 2026 246.0 vs 238.5; Q2 292.9 vs 285.4). Per the release's Annex 3 that gap is purchase-price amortization (Reno, LPE, Axus) plus Axus-deal retention stock comp and the Axus earn-out fair-value change, less tax; ASM's own estimate of the total net impact is EUR 26.8M for 2026 and 21.7M for 2027. All of it is acquisition-related, which AMAT's basis excludes (acquired amortization; integration and deal costs). NTM add-back = 0.189 x 26.8 + 0.811 x 21.7 = EUR 22.66M / 48.95M shares (Q2 285.4 / EPS 5.83) = EUR 0.463. If the Axus retention stock comp (3.7 of ~8.7 pre-tax in Q2) were instead kept as a cost, the add-back would be ~EUR 0.26 and the row 22.65x; the median would be 22.69x instead of 22.62x. Growth FY2/FY1 +39.0%. Home listing, local currency on both sides (no FX); consensus: MarketScreener.
A47: Peer NTM P/E: Kokusai Electric (6525.T) | B47: 20.26 | C47: estimate | D47: 39, 40, 41, 42 | F47: JPY 6,822.0 close 2026-10-23 / AMAT-basis NTM EPS 336.784 = 20.26x (provider basis 21.37x). NTM from 2026-10-23 = w x FY1 + (1 - w) x FY2, w = days to FY1 end (2027-03-31) / 365 = 0.4356; FY1 250.2, FY2 372.5; provider NTM EPS 319.224 re-based to AMAT's EPS basis (non-GAAP: stock comp a cost; acquired-intangible amortization, deal/restructuring costs, investment gains and tax items excluded) = 319.224 +17.560 = 336.784. Provider check: MarketScreener FY3/26 actual EPS 129 = Kokusai's reported IFRS basic EPS 129.00 (net income 30,099M); its own adjusted net income is 34,095M (146 a share). AMAT's basis adds back acquired amortization but keeps stock comp: PPA amortization 5,905M a year (1,476M a quarter; Q1 FY27/3 briefing p.32), after tax at the net-income reconciliation's rate 1,764 / 5,760 = 30.6% (5,760 = -508 + 368 + 5,905 - 5): 5,905 x (1 - 0.306) = 4,097M / 233.3M shares (30,099 / 129) = JPY 17.56 added. Kokusai's stock-comp add-back is -5M (nil). Growth FY2/FY1 +48.9%. Home listing, local currency on both sides (no FX); consensus: MarketScreener.
A48: Peer NTM P/E: SCREEN Holdings (7735.T) | B48: 15.6 | C48: estimate | D48: 43, 44, 45 | F48: JPY 11,630.0 close 2026-10-23 / AMAT-basis NTM EPS 745.716 = 15.60x (provider basis 15.60x). NTM from 2026-10-23 = w x FY1 + (1 - w) x FY2, w = days to FY1 end (2027-03-31) / 365 = 0.4356; FY1 626.8, FY2 837.5; provider NTM EPS 745.716 re-based to AMAT's EPS basis (non-GAAP: stock comp a cost; acquired-intangible amortization, deal/restructuring costs, investment gains and tax items excluded) = 745.716 (factor 1) = 745.716. Provider check: MarketScreener FY3/26 actual EPS 486.6 = SCREEN's reported J-GAAP net income JPY 92,003M / 189M shares, already on the post-split count (2:1 split 2026-03-30; Yahoo split record); price is post-split. Stock comp expensed, negligible acquired amortization: factor 1.000. Growth FY2/FY1 +33.6%. Home listing, local currency on both sides (no FX); consensus: MarketScreener.
A49: Peer NTM P/E: Lasertec (6920.T) | B49: 30.65 | C49: estimate | D49: 46, 47, 48 | F49: JPY 38,040.0 close 2026-10-23 / AMAT-basis NTM EPS 1241.192 = 30.65x (provider basis 30.65x). NTM from 2026-10-23 = w x FY1 + (1 - w) x FY2, w = days to FY1 end (2027-06-30) / 365 = 0.6849; FY1 1118.0, FY2 1509.0; provider NTM EPS 1241.192 re-based to AMAT's EPS basis (non-GAAP: stock comp a cost; acquired-intangible amortization, deal/restructuring costs, investment gains and tax items excluded) = 1241.192 (factor 1) = 1241.192. Provider check: MarketScreener FY6/26 actual EPS 863 = Lasertec's reported J-GAAP EPS 863.76; no splits, no acquisitions, stock comp expensed: factor 1.000. Growth FY2/FY1 +35.0%. Home listing, local currency on both sides (no FX); consensus: MarketScreener.
A51: # | B51: Source | C51: Date | D51: Link
A52: 1 | B52: Digitimes: SEMI lifts 2028 wafer fab equipment forecast to US$220 billion | C52: 2026-09-01 | D52: https://www.digitimes.com/news/a20260901VL214/semicon-taiwan-wafer-fab-equipment-forecast-semi.html
A53: 2 | B53: SEMI mid-year equipment forecast, Yahoo Finance syndication of the SEMI release (WFE +23.1% to $143.9B in 2026, +21.8% in 2027, +14.1% in 2028 to ~$200B); the semi.org page returned HTTP 403 | C53: 2026-07-14 | D53: https://finance.yahoo.com/technology/articles/global-semiconductor-equipment-sales-forecast-140000150.html
A54: 3 | B54: NBC News: U.S. and China agree to extend trade truce through Jan. 10, Bessent says | C54: 2026-09-23 | D54: https://www.nbcnews.com/business/economy/us-china-extend-trade-truce-trump-rcna599525
A55: 4 | B55: Yahoo Finance: US, China to extend trade war truce by 2 months | C55: 2026-09 | D55: https://finance.yahoo.com/economy/policy/articles/us-china-extend-trade-war-145500229.html
A56: 5 | B56: MarketBeat: MU Q4 2026 earnings report 9/30/2026 (actuals pending) | C56: 2026-09-30 | D56: https://www.marketbeat.com/earnings/reports/2026-9-30-micron-technology-inc-stock/
A57: 6 | B57: Micron to report fiscal fourth quarter results on September 30, 2026 | C57: 2026-08-26 | D57: https://www.globenewswire.com/news-release/2026/08/26/3351673/14450/en/micron-technology-to-report-fiscal-fourth-quarter-results-on-september-30-2026.html
A58: 7 | B58: Twelve Data AMAT quote (Sep 30 intraday ~$509.46; prev close $512.01); daily closes Jun 30 $723.00, Sep 16 $415.38 (Twelve Data time series) | C58: 2026-09-30 | D58: https://twelvedata.com
A59: 8 | B59: MarketScreener AMAT finances, id 4850 (FY27 EPS $18.43, FY28 $23.85; net sales 46,312M / 55,857M on 2026-10-15) | C59: 2026-09-29 | D59: https://www.marketscreener.com/quote/stock/APPLIED-MATERIALS-INC-4850/finances/
A60: 9 | B60: Applied Materials Form 10-Q, quarter ended July 26, 2026 (balance sheet: cash 7,037, ST inv 2,196, LT inv 5,268, ST debt 1,299, LT debt 5,245; equity investments 2,421; 793,597,443 shares) | C60: 2026-08-20 | D60: https://www.sec.gov/Archives/edgar/data/6951/000162828026058235/amat-20260726.htm
A61: 10 | B61: Applied Materials Q3 FY2026 results, 8-K Ex. 99.1 (China 28%; FCF; Q4 FY26 outlook) | C61: 2026-08-13 | D61: https://www.sec.gov/Archives/edgar/data/0000006951/000162828026056699/exhibit991q32026earningsre.htm
A62: 11 | B62: Applied Materials 8-K, Item 2.02, Nov 13, 2025 (FQ4 FY25 results date, basis for 'mid-November') | C62: 2025-11-13 | D62: https://www.sec.gov/Archives/edgar/data/6951/000162828025051998/amat-20251113.htm
A63: 12 | B63: Nasdaq.com analyst earnings forecast (Zacks consensus EPS), LRCX: FY ending 2027-06-30 $9.48 (15 est.), FY ending 2028-06-30 $11.52 (10 est.); snapshot data/estimates/LRCX.json retrieved 2026-10-26 | C63: 2026-10-26 | D63: https://api.nasdaq.com/api/analyst/LRCX/earnings-forecast
... A99: 48 | B99: Simply Wall St Lasertec: EPS 863.76 for the year to 2026-06-30 | C99: 2026-10-26 | D99: https://simplywall.st/stocks/mx/semiconductors/bmv-6920-n/lasertec-shares
A101: Fact id | B101: Figure | C101: Value | D101: Filing
A102: F1 | B102: revenue FY ending 2023-10-29 (us-gaap:RevenueFromContractWithCustomerExcludingAssessedTax) | C102: 26517000000 | D102: https://www.sec.gov/Archives/edgar/data/6951/000162828025056742/
A103: F2 | B103: revenue FY ending 2024-10-27 (us-gaap:RevenueFromContractWithCustomerExcludingAssessedTax) | C103: 27176000000 | D103: https://www.sec.gov/Archives/edgar/data/6951/000162828025056742/
A104: F3 | B104: revenue FY ending 2025-10-26 (us-gaap:RevenueFromContractWithCustomerExcludingAssessedTax) | C104: 28368000000 | D104: https://www.sec.gov/Archives/edgar/data/6951/000162828025056742/
A105: F4 | B105: revenue YTD 2025-10-27 to 2026-07-26 | C105: 24037000000 | D105: https://www.sec.gov/Archives/edgar/data/6951/000162828026058235/
A106: F5 | B106: revenue prior-year YTD 2024-10-28 to 2025-07-27 | C106: 21568000000 | D106: https://www.sec.gov/Archives/edgar/data/6951/000162828026058235/
A107: F6 | B107: revenue TTM to 2026-07-26 | C107: 30837000000
A108: F7 | B108: revenue quarter 2026-04-27 to 2026-07-26 | C108: 9115000000 | D108: https://www.sec.gov/Archives/edgar/data/6951/000162828026058235/
A109: F8 | B109: operating_income FY ending 2023-10-29 (us-gaap:OperatingIncomeLoss) | C109: 7654000000 | D109: https://www.sec.gov/Archives/edgar/data/6951/000162828025056742/
A110: F9 | B110: operating_income FY ending 2024-10-27 (us-gaap:OperatingIncomeLoss) | C110: 7867000000 | D110: https://www.sec.gov/Archives/edgar/data/6951/000162828025056742/
A111: F10 | B111: operating_income FY ending 2025-10-26 (us-gaap:OperatingIncomeLoss) | C111: 8289000000 | D111: https://www.sec.gov/Archives/edgar/data/6951/000162828025056742/
A112: F11 | B112: operating_income YTD 2025-10-27 to 2026-07-26 | C112: 7429000000 | D112: https://www.sec.gov/Archives/edgar/data/6951/000162828026058235/
A113: F12 | B113: operating_income prior-year YTD 2024-10-28 to 2025-07-27 | C113: 6577000000 | D113: https://www.sec.gov/Archives/edgar/data/6951/000162828026058235/
A114: F13 | B114: operating_income TTM to 2026-07-26 | C114: 9141000000
A115: F14 | B115: operating_income quarter 2026-04-27 to 2026-07-26 | C115: 3075000000 | D115: https://www.sec.gov/Archives/edgar/data/6951/000162828026058235/
A116: F15 | B116: net_income FY ending 2023-10-29 (us-gaap:NetIncomeLoss) | C116: 6856000000 | D116: https://www.sec.gov/Archives/edgar/data/6951/000162828025056742/
A117: F16 | B117: net_income FY ending 2024-10-27 (us-gaap:NetIncomeLoss) | C117: 7177000000 | D117: https://www.sec.gov/Archives/edgar/data/6951/000162828025056742/
A118: F17 | B118: net_income FY ending 2025-10-26 (us-gaap:NetIncomeLoss) | C118: 6998000000 | D118: https://www.sec.gov/Archives/edgar/data/6951/000162828025056742/
A119: F18 | B119: net_income YTD 2025-10-27 to 2026-07-26 | C119: 7370000000 | D119: https://www.sec.gov/Archives/edgar/data/6951/000162828026058235/
A120: F19 | B120: net_income prior-year YTD 2024-10-28 to 2025-07-27 | C120: 5101000000 | D120: https://www.sec.gov/Archives/edgar/data/6951/000162828026058235/
A121: F20 | B121: net_income TTM to 2026-07-26 | C121: 9267000000
A122: F21 | B122: net_income quarter 2026-04-27 to 2026-07-26 | C122: 2538000000 | D122: https://www.sec.gov/Archives/edgar/data/6951/000162828026058235/
A123: F22 | B123: eps_diluted FY ending 2023-10-29 (us-gaap:EarningsPerShareDiluted) | C123: 8.11 | D123: https://www.sec.gov/Archives/edgar/data/6951/000162828025056742/
A124: F23 | B124: eps_diluted FY ending 2024-10-27 (us-gaap:EarningsPerShareDiluted) | C124: 8.61 | D124: https://www.sec.gov/Archives/edgar/data/6951/000162828025056742/
A125: F24 | B125: eps_diluted FY ending 2025-10-26 (us-gaap:EarningsPerShareDiluted) | C125: 8.66 | D125: https://www.sec.gov/Archives/edgar/data/6951/000162828025056742/
A126: F25 | B126: eps_diluted YTD 2025-10-27 to 2026-07-26 | C126: 9.22 | D126: https://www.sec.gov/Archives/edgar/data/6951/000162828026058235/
A127: F26 | B127: eps_diluted prior-year YTD 2024-10-28 to 2025-07-27 | C127: 6.29 | D127: https://www.sec.gov/Archives/edgar/data/6951/000162828026058235/
A128: F27 | B128: eps_diluted quarter 2026-04-27 to 2026-07-26 | C128: 3.17 | D128: https://www.sec.gov/Archives/edgar/data/6951/000162828026058235/
A129: F28 | B129: diluted_shares_wavg FY ending 2023-10-29 (us-gaap:WeightedAverageNumberOfDilutedSharesOutstanding) | C129: 845000000 | D129: https://www.sec.gov/Archives/edgar/data/6951/000162828025056742/
A130: F29 | B130: diluted_shares_wavg FY ending 2024-10-27 (us-gaap:WeightedAverageNumberOfDilutedSharesOutstanding) | C130: 834000000 | D130: https://www.sec.gov/Archives/edgar/data/6951/000162828025056742/
A131: F30 | B131: diluted_shares_wavg FY ending 2025-10-26 (us-gaap:WeightedAverageNumberOfDilutedSharesOutstanding) | C131: 808000000 | D131: https://www.sec.gov/Archives/edgar/data/6951/000162828025056742/
A132: F31 | B132: diluted_shares_wavg YTD 2025-10-27 to 2026-07-26 | C132: 799000000 | D132: https://www.sec.gov/Archives/edgar/data/6951/000162828026058235/
A133: F32 | B133: diluted_shares_wavg prior-year YTD 2024-10-28 to 2025-07-27 | C133: 811000000 | D133: https://www.sec.gov/Archives/edgar/data/6951/000162828026058235/
... A139: F38 | B139: d_and_a prior-year YTD 2024-10-28 to 2025-07-27 | C139: 321000000 | D139: https://www.sec.gov/Archives/edgar/data/6951/000162828026058235/
A140: F39 | B140: d_and_a TTM to 2026-07-26 | C140: 527000000
A141: F40 | B141: d_and_a quarter 2026-04-27 to 2026-07-26 | C141: 151000000 | D141: https://www.sec.gov/Archives/edgar/data/6951/000162828026058235/
A142: F41 | B142: sbc FY ending 2023-10-29 (us-gaap:ShareBasedCompensation) | C142: 490000000 | D142: https://www.sec.gov/Archives/edgar/data/6951/000162828025056742/
A143: F42 | B143: sbc FY ending 2024-10-27 (us-gaap:ShareBasedCompensation) | C143: 577000000 | D143: https://www.sec.gov/Archives/edgar/data/6951/000162828025056742/
...
