Workbook

Sheet Summary
A1: BKNG standard model (trial) · research run 2026-10-23
A2: The supervisor's reconciled assumption set as a live model. Trial: shown beside the blended page target, not used for trade levels until its weight is decided. Edit blue cells on Model (drivers) and Valuation (assumptions).
A3: Price target box | B3: Value
A4: Live price | B4: =IFERROR(GOOGLEFINANCE("BKNG","price"),Valuation!$B$67)
A5: Price as of | B5: =NOW()
A6: Model target (12-month median) | B6: =Distribution!$B$13
A7: Upside to model target from live price | B7: =B6/B4-1
A8: Research target (12m) (no scenario deltas) | B8: =Valuation!$D$7
A9: Probability-weighted mean | B9: =Distribution!$B$10
A10: 10th percentile | B10: =Distribution!$B$14
A11: 25th percentile | B11: =Distribution!$B$15
A12: 75th percentile | B12: =Distribution!$B$16
A13: 90th percentile | B13: =Distribution!$B$17
A14: Target date | B14: =Valuation!$B$45
A15: Price at the run | B15: =Valuation!$B$67
A16: Blended page target (options 67% + agents 33%, not live) | B16: 166.2408
A17: Supervisor research target (12m) (its own methods) | B17: 183.29
A18: Thesis break price (supervisor) | B18: 118
A19: Supervisor confidence | B19: low
A21: Key estimates | B21: FY2025A | C21: =Model!E5 | D21: =Model!F5
A22: Net sales | B22: =IF(Model!D11="","",Model!D11) | C22: =Model!E11 | D22: =Model!F11
A23: % YoY | B23: =IF(Model!D12="","",Model!D12) | C23: =Model!E12 | D23: =Model!F12
A24: Pretax margin | B24: =IF(Model!D22="","",Model!D22) | C24: =Model!E22 | D24: =Model!F22
A25: Diluted EPS (model) | B25: =IF(Model!D29="","",Model!D29) | C25: =Model!E29 | D25: =Model!F29
A26: % YoY | B26: =IF(Model!D30="","",Model!D30) | C26: =Model!E30 | D26: =Model!F30
A27: Free cash flow to firm | B27: =IF(Model!D39="","",Model!D39) | C27: =Model!E39 | D27: =Model!F39
A28: Guidance midpoint: EPS (adjusted (non-GAAP) EPS)
A29: Consensus: EPS (adjusted (non-GAAP), post-split) | C29: 10.45
A30: Consensus: EPS (adjusted (non-GAAP), post-split) | D30: 12.37
A32: Valuation method | B32: Value per share | C32: Weight
A33: =Valuation!A4 | B33: =Valuation!D4 | C33: =Valuation!E4
A34: =Valuation!A5 | B34: =Valuation!D5 | C34: =Valuation!E5
A35: =Valuation!A6 | B35: =Valuation!D6 | C35: =Valuation!E6
A37: Scenario | B37: Probability | C37: Value at target date | D37: What has to happen
A38: =Distribution!A4 | B38: =Distribution!B4 | C38: =Distribution!C4 | D38: =Distribution!D4
A39: =Distribution!A5 | B39: =Distribution!B5 | C39: =Distribution!C5 | D39: =Distribution!D5
A40: =Distribution!A6 | B40: =Distribution!B6 | C40: =Distribution!C6 | D40: =Distribution!D6
A42: Price at target date | B42: Probability above
A43: =ROUND(Valuation!$B$67*0.7,0) | B43: =SUMPRODUCT(Distribution!$B$4:$B$6,1-NORMSDIST((LN(A43)-LN(Distribution!$C$4:$C$6))/Distribution!$B$9))
A44: =ROUND(Valuation!$B$67*0.8,0) | B44: =SUMPRODUCT(Distribution!$B$4:$B$6,1-NORMSDIST((LN(A44)-LN(Distribution!$C$4:$C$6))/Distribution!$B$9))
A45: =ROUND(Valuation!$B$67*0.9,0) | B45: =SUMPRODUCT(Distribution!$B$4:$B$6,1-NORMSDIST((LN(A45)-LN(Distribution!$C$4:$C$6))/Distribution!$B$9))
A46: =ROUND(Valuation!$B$67*1.0,0) | B46: =SUMPRODUCT(Distribution!$B$4:$B$6,1-NORMSDIST((LN(A46)-LN(Distribution!$C$4:$C$6))/Distribution!$B$9))
A47: =ROUND(Valuation!$B$67*1.1,0) | B47: =SUMPRODUCT(Distribution!$B$4:$B$6,1-NORMSDIST((LN(A47)-LN(Distribution!$C$4:$C$6))/Distribution!$B$9))
A48: =ROUND(Valuation!$B$67*1.2,0) | B48: =SUMPRODUCT(Distribution!$B$4:$B$6,1-NORMSDIST((LN(A48)-LN(Distribution!$C$4:$C$6))/Distribution!$B$9))
A49: =ROUND(Valuation!$B$67*1.3,0) | B49: =SUMPRODUCT(Distribution!$B$4:$B$6,1-NORMSDIST((LN(A49)-LN(Distribution!$C$4:$C$6))/Distribution!$B$9))
A50: =ROUND(Valuation!$B$67*1.5,0) | B50: =SUMPRODUCT(Distribution!$B$4:$B$6,1-NORMSDIST((LN(A50)-LN(Distribution!$C$4:$C$6))/Distribution!$B$9))
A52: Model checks | B52: Status
A53: Scenario probabilities sum to 100% | B53: =IF(ABS(Distribution!B8-1)<0.005,"ok","FLAG: "&TEXT(Distribution!B8,"0.0%"))
A54: WACC exceeds terminal growth by 1 point or more | B54: =IF('Calc - research target (12m)'!B55="ok","ok","FLAG")
A55: Projection runs a full year past the target date | B55: =IF('Calc - research target (12m)'!B56="ok","ok","FLAG")
A56: Method weights add up to more than zero | B56: =IF(SUM(Valuation!E4:E6)>0,"ok","FLAG")
A57: Terminal value under 85% of the DCF | B57: =IF('Calc - research target (12m)'!B46<0.85,"ok","note: "&TEXT('Calc - research target (12m)'!B46,"0%")&" of the DCF is terminal value")
A58: Matches the engine run at publication (target, research target (12m)) | B58: =IF(AND(ABS(Distribution!$B$13-170.2395)<0.01,ABS(Valuation!$D$7-183.2852)<0.01),"ok","inputs edited since publication")
A59: All checks | B59: =IF(COUNTIF(B53:B58,"ok")=6,"all ok",6-COUNTIF(B53:B58,"ok")&" to look at")

Sheet Model
A1: BKNG: annual model, base case
A2: (M of US dollars except per share; fiscal years named by the calendar year they end in)
A3: Blue = input · black = formula · green = link to another tab · actuals from SEC filings (fact ids in the last column, links on Sources)
A5: Fiscal year | B5: FY2023A | C5: FY2024A | D5: FY2025A | E5: FY2026E | F5: FY2027E | G5: FY2028E | H5: Source / note
A6: Period end | B6: 45291 | C6: 45657 | D6: 46022 | E6: =IF(DAY(Valuation!$B$49+1)=1,EOMONTH(Valuation!$B$49,12*E7),EDATE(Valuation!$B$49,12*E7)) | F6: =IF(DAY(Valuation!$B$49+1)=1,EOMONTH(Valuation!$B$49,12*F7),EDATE(Valuation!$B$49,12*F7)) | G6: =IF(DAY(Valuation!$B$49+1)=1,EOMONTH(Valuation!$B$49,12*G7),EDATE(Valuation!$B$49,12*G7))
A7: Projection year | B7: -2 | C7: -1 | D7: 0 | E7: 1 | F7: 2 | G7: 3
A10: Sales
A11: Net sales | B11: 21365 | C11: 23739 | D11: 26917 | E11: =Valuation!$B$50*(1+E48) | F11: =E11*(1+F48) | G11: =F11*(1+G48) | H11: SEC XBRL F1, F2, F3
A12: % YoY | C12: =IF(OR(C11="",B11="",B11=0),"",C11/B11-1) | D12: =IF(OR(D11="",C11="",C11=0),"",D11/C11-1) | E12: =E11/Valuation!$B$50-1 | F12: =F11/E11-1 | G12: =G11/F11-1
A14: Operating profit
A15: EBIT (operating income) | E15: =E11*E49 | F15: =F11*F49 | G15: =G11*G49
A16: EBIT margin | E16: =E15/E11 | F16: =F15/F11 | G16: =G15/G11
A17: D&A | B17: 504 | C17: 591 | D17: 623 | E17: =E11*E51 | F17: =F11*F51 | G17: =G11*G51 | H17: SEC XBRL F27, F28, F29
A18: EBITDA | E18: =E15+E17 | F18: =F15+F17 | G18: =G15+G17
A19: EBITDA margin | E19: =E18/E11 | F19: =F18/F11 | G19: =G18/G11
A20: Net interest income / (expense) | E20: =-Valuation!$B$58*Valuation!$B$56 | F20: =-Valuation!$B$58*E45 | G20: =-Valuation!$B$58*F45 | H20: rate x prior year-end net debt (memo roll)
A21: Pretax income | B21: 5481 | C21: 7292 | D21: 6832 | E21: =E15+E20 | F21: =F15+F20 | G21: =G15+G20 | H21: SEC XBRL F76, F77, F78
A22: Pretax margin | B22: =B21/B11 | C22: =C21/C11 | D22: =D21/D11 | E22: =E21/E11 | F22: =F21/F11 | G22: =G21/G11
A23: Income tax | B23: 1192 | C23: 1410 | D23: 1428 | E23: =E21*E50 | F23: =F21*F50 | G23: =G21*G50 | H23: SEC XBRL F69, F70, F71
A24: Effective tax rate | B24: =B23/B21 | C24: =C23/C21 | D24: =D23/D21 | E24: =E23/E21 | F24: =F23/F21 | G24: =G23/G21
A25: Net income | E25: =E21-E23 | F25: =F21-F23 | G25: =G21-G23
A26: % YoY | C26: =IF(OR(C25="",B25="",B25=0),"",C25/B25-1) | D26: =IF(OR(D25="",C25="",C25=0),"",D25/C25-1) | E26: =IF(OR(D25="",D25=0),"",E25/D25-1) | F26: =IF(OR(E25="",E25=0),"",F25/E25-1) | G26: =IF(OR(F25="",F25=0),"",G25/F25-1)
A27: Diluted shares (M, average) | B27: 36.53 | C27: 34.064 | D27: 32.639 | E27: =Valuation!$B$60*(1+Valuation!$B$62)^(E7-0.5-((Valuation!$B$61-Valuation!$B$49)/365.25)) | F27: =Valuation!$B$60*(1+Valuation!$B$62)^(F7-0.5-((Valuation!$B$61-Valuation!$B$49)/365.25)) | G27: =Valuation!$B$60*(1+Valuation!$B$62)^(G7-0.5-((Valuation!$B$61-Valuation!$B$49)/365.25)) | H27: diluted count rolled at the annual change to mid-year
A28: % YoY | C28: =IF(OR(C27="",B27="",B27=0),"",C27/B27-1) | D28: =IF(OR(D27="",C27="",C27=0),"",D27/C27-1) | E28: =IF(OR(D27="",D27=0),"",E27/D27-1) | F28: =IF(OR(E27="",E27=0),"",F27/E27-1) | G28: =IF(OR(F27="",F27=0),"",G27/F27-1)
A29: Diluted EPS | B29: 117.4 | C29: 172.69 | D29: 165.57 | E29: =E25/E27 | F29: =F25/F27 | G29: =G25/G27 | H29: SEC XBRL F15, F16, F17
A30: % YoY | C30: =IF(OR(C29="",B29="",B29=0),"",C29/B29-1) | D30: =IF(OR(D29="",C29="",C29=0),"",D29/C29-1) | E30: =IF(OR(D29="",D29=0),"",E29/D29-1) | F30: =IF(OR(E29="",E29=0),"",F29/E29-1) | G30: =IF(OR(F29="",F29=0),"",G29/F29-1)
A32: Cash flow
A33: NOPAT (EBIT x (1 - tax)) | E33: =E15*(1-E50) | F33: =F15*(1-F50) | G33: =G15*(1-G50)
A34: + D&A | B34: =B17 | C34: =C17 | D34: =D17 | E34: =E17 | F34: =F17 | G34: =G17
A35: - Capex | B35: 345 | C35: 429 | D35: 322 | E35: =E11*E52 | F35: =F11*F52 | G35: =G11*G52 | H35: SEC XBRL F41, F42, F43
A36: Capex % of sales | B36: =B35/B11 | C36: =C35/C11 | D36: =D35/D11 | E36: =E35/E11 | F36: =F35/F11 | G36: =G35/G11
A37: - Working capital increase | E37: =E53*(E11-Valuation!$B$50) | F37: =F53*(F11-E11) | G37: =G53*(G11-F11)
A38: - Stock comp (adjusted EBIT only) | E38: =IF(AND(Valuation!$B$47="adjusted",Valuation!$B$48="cost"),E42*(1-E50),0) | F38: =IF(AND(Valuation!$B$47="adjusted",Valuation!$B$48="cost"),F42*(1-F50),0) | G38: =IF(AND(Valuation!$B$47="adjusted",Valuation!$B$48="cost"),G42*(1-G50),0)
A39: Free cash flow to firm | E39: =E33+E34-E35-E37-E38 | F39: =F33+F34-F35-F37-F38 | G39: =G33+G34-G35-G37-G38 | H39: what the DCF discounts (Calc tabs)
A40: Operating cash flow (reported) | B40: 7344 | C40: 8323 | D40: 9409 | H40: SEC XBRL F34, F35, F36
A41: FCF (operating cash flow - capex) | B41: =B40-B35 | C41: =C40-C35 | D41: =D40-D35
A42: Stock comp (memo) | E42: =E11*E54 | F42: =F11*F54 | G42: =G11*G54
A43: Buybacks + dividends + other uses | B43: 10377 | C43: 7683 | D43: 7688 | E43: =E11*E56+E55+E57 | F43: =F11*F56+F55+F57 | G43: =G11*G56+G55+G57 | H43: SEC XBRL F48, F55, F49, F56, F50, F57
A44: % of sales | B44: =B43/B11 | C44: =C43/C11 | D44: =D43/D11 | E44: =E43/E11 | F44: =F43/F11 | G44: =G43/G11
A45: Net debt / (net cash), year end (memo) | E45: =Valuation!$B$56-E39-E20*(1-E50)+E43 | F45: =E45-F39-F20*(1-F50)+F43 | G45: =F45-G39-G20*(1-G50)+G43 | H45: rolled from the balance-date figure; feeds interest only
A47: Drivers (blue = input; a year left black carries the prior year)
A48: Revenue growth | C48: =C12 | D48: =D12 | E48: 0.077711093 | F48: 0.074181006 | G48: 0.074792142
A49: EBIT margin | E49: 0.32468049 | F49: 0.3259 | G49: 0.32552111
A50: Tax rate | B50: =B24 | C50: =C24 | D50: =D24 | E50: 0.224 | F50: =E50 | G50: =F50
A51: D&A % revenue | B51: =B17/B11 | C51: =C17/C11 | D51: =D17/D11 | E51: 0.02 | F51: =E51 | G51: =F51
A52: Capex % revenue | B52: =B36 | C52: =C36 | D52: =D36 | E52: 0.0113 | F52: =E52 | G52: =F52
A53: Working capital % of revenue increase | E53: 0 | F53: =E53 | G53: =F53
A54: Stock comp % revenue | B54: =B42/B11 | C54: =C42/C11 | D54: =D42/D11 | E54: 0.02 | F54: =E54 | G54: =F54
A55: Shareholder returns ($) | E55: 10000 | F55: =E55 | G55: =F55
A56: Shareholder returns % revenue | B56: =B44 | C56: =C44 | D56: =D44 | E56: 0 | F56: =E56 | G56: =F56
A57: Other uses of cash ($: M&A, investments) | E57: 0 | F57: =E57 | G57: =F57
A58: Adj. EBITDA addback % revenue | E58: 0 | F58: =E58 | G58: =F58
A60: Versus company guidance and street consensus
A61: Guidance: adj EPS growth (adjusted (non-GAAP) EPS), midpoint | H61: as of 2026-08-04; source 1 (Booking Holdings Q2 2026 earnings release (8-K Ex.99.1; Q3/F)
A62: Consensus: adj EPS (adjusted (non-GAAP), post-split) | E62: 10.45 | H62: as of 2026-09-24; source 10 (StockAnalysis BKNG forecast (FY26 $10.45; 36 analysts; avg P)
A63: Consensus: adj EPS (adjusted (non-GAAP), post-split) | F63: 12.37 | H63: as of 2026-09-24; source 10 (StockAnalysis BKNG forecast (FY26 $10.45; 36 analysts; avg P)

Sheet Valuation
A1: BKNG: valuation and price target derivation
A2: Value per share at the target date = weighted methods below; the 12-month target is the median of the scenario mix (Distribution tab).
A3: Method | B3: Multiple | C3: Metric at target date | D3: Value per share | E3: Weight | F3: Contribution
A4: ='Calc - research target (12m)'!A67 | B4: =IF('Calc - research target (12m)'!C67="","",'Calc - research target (12m)'!C67) | C4: =IF('Calc - research target (12m)'!I67="","",'Calc - research target (12m)'!I67) | D4: ='Calc - research target (12m)'!F67 | E4: ='Calc - research target (12m)'!G67 | F4: =D4*E4/SUM($E$4:$E$6)
A5: ='Calc - research target (12m)'!A68 | B5: =IF('Calc - research target (12m)'!C68="","",'Calc - research target (12m)'!C68) | C5: =IF('Calc - research target (12m)'!I68="","",'Calc - research target (12m)'!I68) | D5: ='Calc - research target (12m)'!F68 | E5: ='Calc - research target (12m)'!G68 | F5: =D5*E5/SUM($E$4:$E$6)
A6: ='Calc - research target (12m)'!A69 | B6: =IF('Calc - research target (12m)'!C69="","",'Calc - research target (12m)'!C69) | C6: =IF('Calc - research target (12m)'!I69="","",'Calc - research target (12m)'!I69) | D6: ='Calc - research target (12m)'!F69 | E6: ='Calc - research target (12m)'!G69 | F6: =D6*E6/SUM($E$4:$E$6)
A7: Research target (12m) per share | D7: ='Calc - research target (12m)'!$F$70 | F7: =SUM(F4:F6)
A9: 12-month EPS basis (what the P/E is applied to)
A10: Fiscal year | B10: =Model!E5 | C10: =Model!F5 | D10: =Model!G5
A11: Share of the 12 months after the target date | B11: ='Calc - research target (12m)'!C38 | C11: ='Calc - research target (12m)'!D38 | D11: ='Calc - research target (12m)'!E38
A12: Model EPS (Model tab) | B12: =Model!E29 | C12: =Model!F29 | D12: =Model!G29
A13: Model EPS, next 12 months after the target date | B13: =SUMPRODUCT(B11:D11,B12:D12)
A14: Stated next-12-month EPS used by the P/E method (consensus basis, cited) | B14: =Valuation!F70 | C14: =B14/B13-1 | D14: vs model EPS
A16: DCF build (free cash flow to firm, discounted to the target date)
A17: Fiscal year | B17: =Model!E5 | C17: =Model!F5 | D17: =Model!G5
A18: Free cash flow to firm | B18: ='Calc - research target (12m)'!C31 | C18: ='Calc - research target (12m)'!D31 | D18: ='Calc - research target (12m)'!E31
A19: Share of the year after the target date | B19: ='Calc - research target (12m)'!C35 | C19: ='Calc - research target (12m)'!D35 | D19: ='Calc - research target (12m)'!E35
A20: PV at target date | B20: ='Calc - research target (12m)'!C36 | C20: ='Calc - research target (12m)'!D36 | D20: ='Calc - research target (12m)'!E36
A22: PV of free cash flow after the target date | B22: ='Calc - research target (12m)'!B42
A23: Terminal value (final year) | B23: ='Calc - research target (12m)'!B43
A24: PV of terminal value | B24: ='Calc - research target (12m)'!B44
A25: Enterprise value at target date | B25: ='Calc - research target (12m)'!B45
A26: Terminal value share of DCF | B26: ='Calc - research target (12m)'!B46
A27: Net debt at target date | B27: ='Calc - research target (12m)'!B50
A28: Minority interests | B28: ='Calc - research target (12m)'!B51
A29: Adjustments | B29: ='Calc - research target (12m)'!B52
A30: Diluted shares at target date (M) | B30: ='Calc - research target (12m)'!B53
A31: DCF value per share | B31: ='Calc - research target (12m)'!F67
A32: WACC | B32: ='Calc - research target (12m)'!B12
A42: Assumptions (blue = input; sources on the Sources tab)
A43: Input | B43: Value | C43: Basis / note
A44: Run date (valuation as of) | B44: 46318
A45: Target date (run date + 365 days) | B45: =B44+365 | C45: 12-month horizon
A46: Money unit | B46: $M
A47: EBIT basis (gaap / adjusted) | B47: gaap | C47: gaap = after stock comp
A48: Stock comp treatment (cost / dilution) | B48: cost | C48: used only when EBIT is adjusted
A49: Last reported fiscal year end | B49: 46022
A50: Net sales, last reported year ($M) | B50: 26917
A51: WACC | B51: 0.0864 | C51: filled in (not stated in this set's original work): cost of equity 0.0875 = T-bill 0.0420 + beta 0.91 x 5% (the price target's market leg, 2026-10-02); after-tax debt 0.0550 x (1 - 0.224) on net debt and minorities 2,966 vs equity 119,488 (751.40M x $159.02) -> WACC 0.0864
A52: Terminal method (gordon / exit_multiple / steady_state) | B52: gordon
A53: Terminal growth | B53: 0.03
A54: Exit EV/EBITDA (exit_multiple only)
A55: Balance-sheet date | B55: 46203
A56: Net debt / (net cash) at balance date ($M) | B56: 2966 | C56: excludes operating leases
A57: Minority interests + preferred stock | B57: 0
A58: Interest rate on net debt / cash | B58: 0.055
A59: Net debt at target date (override; blank = bridge) | B59: 2966
A60: Diluted shares (M) | B60: 751.4
A61: Share count date | B61: 46230
A62: Annual change in diluted shares | B62: -0.06 | C62: net of buybacks and stock-comp dilution
A63: Shares at target date (override; blank = from annual change) | B63: 702.95689
A64: DCF weight | B64: 0 | C64: Kilian 2026-10-21: 0 unless the name has a DCF leg (dcf_policy)
A65: Sum-of-the-parts weight | B65: 0
A66: Spread within each scenario (lognormal vol) | B66: 0.275
A67: Share price at the run | B67: 155.83 | C67: close used by the run (2026-10-23)
A69: Target multiple | B69: Multiple | C69: Weight | D69: Basis (ntm / ltm) | E69: EBITDA basis | F69: Stated EPS | G69: Stated FCF/share | H69: Levered | I69: Peer basis
A70: P/E | B70: 13.32 | C70: 0.6 | D70: ntm | E70: gaap | F70: 13.127745 | H70: TRUE | I70: Peer refresh 2026-10-26: median of EXPE 14.54x, Amadeus 14.78x (adjusted), ABNB 28.16x = 14.78x NTM P/E on BKNG's basis (adjusted EPS, SBC in costs; calendar NTM at the 2026-10-23 close); 3 peers (peer_count_flag). BKNG trades at 12.98x. Per-share figure computed from the drivers (driver_build.set). EXIT k=0.8 (2026-10-26T12:28Z): Exit-multiple rule (Kilian card 2026-10-26 12:16Z; METHOD.md Peer comparables): exit = peer median x (own NTM multiple / peer median)^k, k = 0.8. Peer median 14.78x; own 12.98x: BKNG $155.83 / calendar-NTM Zacks adj EPS $12.0046 = 12.98x (row 'BKNG own NTM P/E (same basis)'). 14.78 x (12.98 / 14.78)^0.8 = 14.78 x 0.9013 = 13.32x (was 14.78x). The FCF-yield leg (8%, today's TTM yield) already sits at BKNG's own level and has no peer median; unchanged.
A71: FCF yield | B71: 0.08 | C71: 0.4 | D71: ntm | E71: gaap | G71: 15.673651 | H71: TRUE | I71: Supervisor: ~8% (today's TTM FCF yield, no re-rating) on ~$15.8 NTM FCF per share before SBC; consistent with agent 3's 7.5% after SBC. No net-debt deduction. Per-share figure now computed from the drivers (driver_build.set).
A73: Segment (sum of the parts) | B73: NTM metric | C73: Metric | D73: Multiple | E73: Note
A74: none
A76: Adjustment (equity level) | B76: Value | C76: Probability | D76: Note
A77: none
A79: Custom method | B79: Value per share | C79: Weight | D79: Explanation
A80: none
A82: Scenario | B82: Probability | C82: Growth Δ | D82: Margin Δ | E82: Multiple Δ (turns) | F82: WACC Δ | G82: Multiple %Δ (FCF yield, segments) | H82: Stated EPS/FCF %Δ | I82: Custom methods %Δ | J82: Story
A83: bear | B83: 0.25 | E83: -4.25 | G83: -0.5076 | J83: Forecasters' median bear (their $110-120; the supervisor set no scenarios of its own): AI agents (Muse/Expedia, Google, ChatGPT) take share or force take-rate and marketing concessions, oil/Middle East and the Fed hiking cycle slow travel, and the legal tail builds (FTC/Priceline, Dutch and German parity claims, CNMC $472M accrued). NTM EPS ~$11.5 at ~10.0x = ~$115. Driver restatement: room nights -4.5% (agent 4 'low single digits'), take rate -2% (agents 2, 3, 5 'take-rate concessions'), marketing +20bp of GB (agents 1, 3, 4 'push marketing costs up'); multiple deltas kept. | K83: driver deltas: rn -0.045 %; take -0.02 %; mkt +0.002
A84: base | B84: 0.5 | E84: -0.25 | G84: -0.0828 | J84: [exit k=0.8 2026-10-26: P/E 14.78x -> 13.32x] Forecasters' median base (their $175-186): low-to-mid-teens EPS compounding, about half of it from the ~6%/yr share shrink; the AI overhang persists but does not deepen; ~14.0x on ~$13.1 NTM EPS = ~$183. This sits below the reconciled fair value ($191), as every forecaster's base scenario sits below its own fair value.
A85: bull | B85: 0.25 | E85: 3.25 | G85: 0.1619 | J85: Forecasters' median bull (their $228-255): travel normalises, Booking proves a supply partner to AI agents, and the multiple re-rates to ~17.5x on ~$13.45 NTM EPS (~$238). Driver restatement: room nights +1.5% (travel normalises, agents 1, 5), other opex -40bp (transformation savings land, agent 1); multiple deltas kept. | K85: driver deltas: rn +0.015 %; opex -0.004

Sheet Sensitivity
A1: BKNG: sensitivity tables (bold = current inputs; every cell recalculates from the live model)
A3: DCF value per share: WACC (down) x terminal growth (across)
A4: WACC \ growth | B4: =Valuation!$B$53+(-0.01) | C4: =Valuation!$B$53+(-0.005) | D4: =Valuation!$B$53+(0) | E4: =Valuation!$B$53+(0.005) | F4: =Valuation!$B$53+(0.01)
A5: =Valuation!$B$51+(-0.01) | B5: =IF($A5-B$4<=0.01,"n/a",((SUMPRODUCT('Calc - research target (12m)'!$C$31:$E$31,'Calc - research target (12m)'!$C$35:$E$35,(1+$A5)^(-('Calc - research target (12m)'!$C$19:$E$19-'Calc - research target (12m)'!$B$13)))+'Calc - research target (12m)'!$E$31*(1+B$4)/($A5-B$4)/(1+$A5)^('Calc - research target (12m)'!$B$16-'Calc - research target (12m)'!$B$13))-'Calc - research target (12m)'!$B$50-'Calc - research target (12m)'!$B$51+'Calc - research target (12m)'!$B$52)/'Calc - research target (12m)'!$B$53) | C5: =IF($A5-C$4<=0.01,"n/a",((SUMPRODUCT('Calc - research target (12m)'!$C$31:$E$31,'Calc - research target (12m)'!$C$35:$E$35,(1+$A5)^(-('Calc - research target (12m)'!$C$19:$E$19-'Calc - research target (12m)'!$B$13)))+'Calc - research target (12m)'!$E$31*(1+C$4)/($A5-C$4)/(1+$A5)^('Calc - research target (12m)'!$B$16-'Calc - research target (12m)'!$B$13))-'Calc - research target (12m)'!$B$50-'Calc - research target (12m)'!$B$51+'Calc - research target (12m)'!$B$52)/'Calc - research target (12m)'!$B$53) | D5: =IF($A5-D$4<=0.01,"n/a",((SUMPRODUCT('Calc - research target (12m)'!$C$31:$E$31,'Calc - research target (12m)'!$C$35:$E$35,(1+$A5)^(-('Calc - research target (12m)'!$C$19:$E$19-'Calc - research target (12m)'!$B$13)))+'Calc - research target (12m)'!$E$31*(1+D$4)/($A5-D$4)/(1+$A5)^('Calc - research target (12m)'!$B$16-'Calc - research target (12m)'!$B$13))-'Calc - research target (12m)'!$B$50-'Calc - research target (12m)'!$B$51+'Calc - research target (12m)'!$B$52)/'Calc - research target (12m)'!$B$53) | E5: =IF($A5-E$4<=0.01,"n/a",((SUMPRODUCT('Calc - research target (12m)'!$C$31:$E$31,'Calc - research target (12m)'!$C$35:$E$35,(1+$A5)^(-('Calc - research target (12m)'!$C$19:$E$19-'Calc - research target (12m)'!$B$13)))+'Calc - research target (12m)'!$E$31*(1+E$4)/($A5-E$4)/(1+$A5)^('Calc - research target (12m)'!$B$16-'Calc - research target (12m)'!$B$13))-'Calc - research target (12m)'!$B$50-'Calc - research target (12m)'!$B$51+'Calc - research target (12m)'!$B$52)/'Calc - research target (12m)'!$B$53) | F5: =IF($A5-F$4<=0.01,"n/a",((SUMPRODUCT('Calc - research target (12m)'!$C$31:$E$31,'Calc - research target (12m)'!$C$35:$E$35,(1+$A5)^(-('Calc - research target (12m)'!$C$19:$E$19-'Calc - research target (12m)'!$B$13)))+'Calc - research target (12m)'!$E$31*(1+F$4)/($A5-F$4)/(1+$A5)^('Calc - research target (12m)'!$B$16-'Calc - research target (12m)'!$B$13))-'Calc - research target (12m)'!$B$50-'Calc - research target (12m)'!$B$51+'Calc - research target (12m)'!$B$52)/'Calc - research target (12m)'!$B$53)
A6: =Valuation!$B$51+(-0.005) | B6: =IF($A6-B$4<=0.01,"n/a",((SUMPRODUCT('Calc - research target (12m)'!$C$31:$E$31,'Calc - research target (12m)'!$C$35:$E$35,(1+$A6)^(-('Calc - research target (12m)'!$C$19:$E$19-'Calc - research target (12m)'!$B$13)))+'Calc - research target (12m)'!$E$31*(1+B$4)/($A6-B$4)/(1+$A6)^('Calc - research target (12m)'!$B$16-'Calc - research target (12m)'!$B$13))-'Calc - research target (12m)'!$B$50-'Calc - research target (12m)'!$B$51+'Calc - research target (12m)'!$B$52)/'Calc - research target (12m)'!$B$53) | C6: =IF($A6-C$4<=0.01,"n/a",((SUMPRODUCT('Calc - research target (12m)'!$C$31:$E$31,'Calc - research target (12m)'!$C$35:$E$35,(1+$A6)^(-('Calc - research target (12m)'!$C$19:$E$19-'Calc - research target (12m)'!$B$13)))+'Calc - research target (12m)'!$E$31*(1+C$4)/($A6-C$4)/(1+$A6)^('Calc - research target (12m)'!$B$16-'Calc - research target (12m)'!$B$13))-'Calc - research target (12m)'!$B$50-'Calc - research target (12m)'!$B$51+'Calc - research target (12m)'!$B$52)/'Calc - research target (12m)'!$B$53) | D6: =IF($A6-D$4<=0.01,"n/a",((SUMPRODUCT('Calc - research target (12m)'!$C$31:$E$31,'Calc - research target (12m)'!$C$35:$E$35,(1+$A6)^(-('Calc - research target (12m)'!$C$19:$E$19-'Calc - research target (12m)'!$B$13)))+'Calc - research target (12m)'!$E$31*(1+D$4)/($A6-D$4)/(1+$A6)^('Calc - research target (12m)'!$B$16-'Calc - research target (12m)'!$B$13))-'Calc - research target (12m)'!$B$50-'Calc - research target (12m)'!$B$51+'Calc - research target (12m)'!$B$52)/'Calc - research target (12m)'!$B$53) | E6: =IF($A6-E$4<=0.01,"n/a",((SUMPRODUCT('Calc - research target (12m)'!$C$31:$E$31,'Calc - research target (12m)'!$C$35:$E$35,(1+$A6)^(-('Calc - research target (12m)'!$C$19:$E$19-'Calc - research target (12m)'!$B$13)))+'Calc - research target (12m)'!$E$31*(1+E$4)/($A6-E$4)/(1+$A6)^('Calc - research target (12m)'!$B$16-'Calc - research target (12m)'!$B$13))-'Calc - research target (12m)'!$B$50-'Calc - research target (12m)'!$B$51+'Calc - research target (12m)'!$B$52)/'Calc - research target (12m)'!$B$53) | F6: =IF($A6-F$4<=0.01,"n/a",((SUMPRODUCT('Calc - research target (12m)'!$C$31:$E$31,'Calc - research target (12m)'!$C$35:$E$35,(1+$A6)^(-('Calc - research target (12m)'!$C$19:$E$19-'Calc - research target (12m)'!$B$13)))+'Calc - research target (12m)'!$E$31*(1+F$4)/($A6-F$4)/(1+$A6)^('Calc - research target (12m)'!$B$16-'Calc - research target (12m)'!$B$13))-'Calc - research target (12m)'!$B$50-'Calc - research target (12m)'!$B$51+'Calc - research target (12m)'!$B$52)/'Calc - research target (12m)'!$B$53)
A7: =Valuation!$B$51+(0) | B7: =IF($A7-B$4<=0.01,"n/a",((SUMPRODUCT('Calc - research target (12m)'!$C$31:$E$31,'Calc - research target (12m)'!$C$35:$E$35,(1+$A7)^(-('Calc - research target (12m)'!$C$19:$E$19-'Calc - research target (12m)'!$B$13)))+'Calc - research target (12m)'!$E$31*(1+B$4)/($A7-B$4)/(1+$A7)^('Calc - research target (12m)'!$B$16-'Calc - research target (12m)'!$B$13))-'Calc - research target (12m)'!$B$50-'Calc - research target (12m)'!$B$51+'Calc - research target (12m)'!$B$52)/'Calc - research target (12m)'!$B$53) | C7: =IF($A7-C$4<=0.01,"n/a",((SUMPRODUCT('Calc - research target (12m)'!$C$31:$E$31,'Calc - research target (12m)'!$C$35:$E$35,(1+$A7)^(-('Calc - research target (12m)'!$C$19:$E$19-'Calc - research target (12m)'!$B$13)))+'Calc - research target (12m)'!$E$31*(1+C$4)/($A7-C$4)/(1+$A7)^('Calc - research target (12m)'!$B$16-'Calc - research target (12m)'!$B$13))-'Calc - research target (12m)'!$B$50-'Calc - research target (12m)'!$B$51+'Calc - research target (12m)'!$B$52)/'Calc - research target (12m)'!$B$53) | D7: =IF($A7-D$4<=0.01,"n/a",((SUMPRODUCT('Calc - research target (12m)'!$C$31:$E$31,'Calc - research target (12m)'!$C$35:$E$35,(1+$A7)^(-('Calc - research target (12m)'!$C$19:$E$19-'Calc - research target (12m)'!$B$13)))+'Calc - research target (12m)'!$E$31*(1+D$4)/($A7-D$4)/(1+$A7)^('Calc - research target (12m)'!$B$16-'Calc - research target (12m)'!$B$13))-'Calc - research target (12m)'!$B$50-'Calc - research target (12m)'!$B$51+'Calc - research target (12m)'!$B$52)/'Calc - research target (12m)'!$B$53) | E7: =IF($A7-E$4<=0.01,"n/a",((SUMPRODUCT('Calc - research target (12m)'!$C$31:$E$31,'Calc - research target (12m)'!$C$35:$E$35,(1+$A7)^(-('Calc - research target (12m)'!$C$19:$E$19-'Calc - research target (12m)'!$B$13)))+'Calc - research target (12m)'!$E$31*(1+E$4)/($A7-E$4)/(1+$A7)^('Calc - research target (12m)'!$B$16-'Calc - research target (12m)'!$B$13))-'Calc - research target (12m)'!$B$50-'Calc - research target (12m)'!$B$51+'Calc - research target (12m)'!$B$52)/'Calc - research target (12m)'!$B$53) | F7: =IF($A7-F$4<=0.01,"n/a",((SUMPRODUCT('Calc - research target (12m)'!$C$31:$E$31,'Calc - research target (12m)'!$C$35:$E$35,(1+$A7)^(-('Calc - research target (12m)'!$C$19:$E$19-'Calc - research target (12m)'!$B$13)))+'Calc - research target (12m)'!$E$31*(1+F$4)/($A7-F$4)/(1+$A7)^('Calc - research target (12m)'!$B$16-'Calc - research target (12m)'!$B$13))-'Calc - research target (12m)'!$B$50-'Calc - research target (12m)'!$B$51+'Calc - research target (12m)'!$B$52)/'Calc - research target (12m)'!$B$53)
A8: =Valuation!$B$51+(0.005) | B8: =IF($A8-B$4<=0.01,"n/a",((SUMPRODUCT('Calc - research target (12m)'!$C$31:$E$31,'Calc - research target (12m)'!$C$35:$E$35,(1+$A8)^(-('Calc - research target (12m)'!$C$19:$E$19-'Calc - research target (12m)'!$B$13)))+'Calc - research target (12m)'!$E$31*(1+B$4)/($A8-B$4)/(1+$A8)^('Calc - research target (12m)'!$B$16-'Calc - research target (12m)'!$B$13))-'Calc - research target (12m)'!$B$50-'Calc - research target (12m)'!$B$51+'Calc - research target (12m)'!$B$52)/'Calc - research target (12m)'!$B$53) | C8: =IF($A8-C$4<=0.01,"n/a",((SUMPRODUCT('Calc - research target (12m)'!$C$31:$E$31,'Calc - research target (12m)'!$C$35:$E$35,(1+$A8)^(-('Calc - research target (12m)'!$C$19:$E$19-'Calc - research target (12m)'!$B$13)))+'Calc - research target (12m)'!$E$31*(1+C$4)/($A8-C$4)/(1+$A8)^('Calc - research target (12m)'!$B$16-'Calc - research target (12m)'!$B$13))-'Calc - research target (12m)'!$B$50-'Calc - research target (12m)'!$B$51+'Calc - research target (12m)'!$B$52)/'Calc - research target (12m)'!$B$53) | D8: =IF($A8-D$4<=0.01,"n/a",((SUMPRODUCT('Calc - research target (12m)'!$C$31:$E$31,'Calc - research target (12m)'!$C$35:$E$35,(1+$A8)^(-('Calc - research target (12m)'!$C$19:$E$19-'Calc - research target (12m)'!$B$13)))+'Calc - research target (12m)'!$E$31*(1+D$4)/($A8-D$4)/(1+$A8)^('Calc - research target (12m)'!$B$16-'Calc - research target (12m)'!$B$13))-'Calc - research target (12m)'!$B$50-'Calc - research target (12m)'!$B$51+'Calc - research target (12m)'!$B$52)/'Calc - research target (12m)'!$B$53) | E8: =IF($A8-E$4<=0.01,"n/a",((SUMPRODUCT('Calc - research target (12m)'!$C$31:$E$31,'Calc - research target (12m)'!$C$35:$E$35,(1+$A8)^(-('Calc - research target (12m)'!$C$19:$E$19-'Calc - research target (12m)'!$B$13)))+'Calc - research target (12m)'!$E$31*(1+E$4)/($A8-E$4)/(1+$A8)^('Calc - research target (12m)'!$B$16-'Calc - research target (12m)'!$B$13))-'Calc - research target (12m)'!$B$50-'Calc - research target (12m)'!$B$51+'Calc - research target (12m)'!$B$52)/'Calc - research target (12m)'!$B$53) | F8: =IF($A8-F$4<=0.01,"n/a",((SUMPRODUCT('Calc - research target (12m)'!$C$31:$E$31,'Calc - research target (12m)'!$C$35:$E$35,(1+$A8)^(-('Calc - research target (12m)'!$C$19:$E$19-'Calc - research target (12m)'!$B$13)))+'Calc - research target (12m)'!$E$31*(1+F$4)/($A8-F$4)/(1+$A8)^('Calc - research target (12m)'!$B$16-'Calc - research target (12m)'!$B$13))-'Calc - research target (12m)'!$B$50-'Calc - research target (12m)'!$B$51+'Calc - research target (12m)'!$B$52)/'Calc - research target (12m)'!$B$53)
A9: =Valuation!$B$51+(0.01) | B9: =IF($A9-B$4<=0.01,"n/a",((SUMPRODUCT('Calc - research target (12m)'!$C$31:$E$31,'Calc - research target (12m)'!$C$35:$E$35,(1+$A9)^(-('Calc - research target (12m)'!$C$19:$E$19-'Calc - research target (12m)'!$B$13)))+'Calc - research target (12m)'!$E$31*(1+B$4)/($A9-B$4)/(1+$A9)^('Calc - research target (12m)'!$B$16-'Calc - research target (12m)'!$B$13))-'Calc - research target (12m)'!$B$50-'Calc - research target (12m)'!$B$51+'Calc - research target (12m)'!$B$52)/'Calc - research target (12m)'!$B$53) | C9: =IF($A9-C$4<=0.01,"n/a",((SUMPRODUCT('Calc - research target (12m)'!$C$31:$E$31,'Calc - research target (12m)'!$C$35:$E$35,(1+$A9)^(-('Calc - research target (12m)'!$C$19:$E$19-'Calc - research target (12m)'!$B$13)))+'Calc - research target (12m)'!$E$31*(1+C$4)/($A9-C$4)/(1+$A9)^('Calc - research target (12m)'!$B$16-'Calc - research target (12m)'!$B$13))-'Calc - research target (12m)'!$B$50-'Calc - research target (12m)'!$B$51+'Calc - research target (12m)'!$B$52)/'Calc - research target (12m)'!$B$53) | D9: =IF($A9-D$4<=0.01,"n/a",((SUMPRODUCT('Calc - research target (12m)'!$C$31:$E$31,'Calc - research target (12m)'!$C$35:$E$35,(1+$A9)^(-('Calc - research target (12m)'!$C$19:$E$19-'Calc - research target (12m)'!$B$13)))+'Calc - research target (12m)'!$E$31*(1+D$4)/($A9-D$4)/(1+$A9)^('Calc - research target (12m)'!$B$16-'Calc - research target (12m)'!$B$13))-'Calc - research target (12m)'!$B$50-'Calc - research target (12m)'!$B$51+'Calc - research target (12m)'!$B$52)/'Calc - research target (12m)'!$B$53) | E9: =IF($A9-E$4<=0.01,"n/a",((SUMPRODUCT('Calc - research target (12m)'!$C$31:$E$31,'Calc - research target (12m)'!$C$35:$E$35,(1+$A9)^(-('Calc - research target (12m)'!$C$19:$E$19-'Calc - research target (12m)'!$B$13)))+'Calc - research target (12m)'!$E$31*(1+E$4)/($A9-E$4)/(1+$A9)^('Calc - research target (12m)'!$B$16-'Calc - research target (12m)'!$B$13))-'Calc - research target (12m)'!$B$50-'Calc - research target (12m)'!$B$51+'Calc - research target (12m)'!$B$52)/'Calc - research target (12m)'!$B$53) | F9: =IF($A9-F$4<=0.01,"n/a",((SUMPRODUCT('Calc - research target (12m)'!$C$31:$E$31,'Calc - research target (12m)'!$C$35:$E$35,(1+$A9)^(-('Calc - research target (12m)'!$C$19:$E$19-'Calc - research target (12m)'!$B$13)))+'Calc - research target (12m)'!$E$31*(1+F$4)/($A9-F$4)/(1+$A9)^('Calc - research target (12m)'!$B$16-'Calc - research target (12m)'!$B$13))-'Calc - research target (12m)'!$B$50-'Calc - research target (12m)'!$B$51+'Calc - research target (12m)'!$B$52)/'Calc - research target (12m)'!$B$53)
A11: Research target (12m) per share: P/E multiple (down) x stated EPS (across)
A12: Multiple \ metric | B12: =Valuation!F70*0.9 | C12: =Valuation!F70*0.95 | D12: =Valuation!F70*1.0 | E12: =Valuation!F70*1.05 | F12: =Valuation!F70*1.1
A13: =Valuation!$B$70+(-3) | B13: =((SUMPRODUCT('Calc - research target (12m)'!$F$67:$F$69,'Calc - research target (12m)'!$G$67:$G$69)-'Calc - research target (12m)'!$F$68*'Calc - research target (12m)'!$G$68)+'Calc - research target (12m)'!$G$68*($A13*B$12+'Calc - research target (12m)'!$B$52/'Calc - research target (12m)'!$B$53))/SUM('Calc - research target (12m)'!$G$67:$G$69) | C13: =((SUMPRODUCT('Calc - research target (12m)'!$F$67:$F$69,'Calc - research target (12m)'!$G$67:$G$69)-'Calc - research target (12m)'!$F$68*'Calc - research target (12m)'!$G$68)+'Calc - research target (12m)'!$G$68*($A13*C$12+'Calc - research target (12m)'!$B$52/'Calc - research target (12m)'!$B$53))/SUM('Calc - research target (12m)'!$G$67:$G$69) | D13: =((SUMPRODUCT('Calc - research target (12m)'!$F$67:$F$69,'Calc - research target (12m)'!$G$67:$G$69)-'Calc - research target (12m)'!$F$68*'Calc - research target (12m)'!$G$68)+'Calc - research target (12m)'!$G$68*($A13*D$12+'Calc - research target (12m)'!$B$52/'Calc - research target (12m)'!$B$53))/SUM('Calc - research target (12m)'!$G$67:$G$69) | E13: =((SUMPRODUCT('Calc - research target (12m)'!$F$67:$F$69,'Calc - research target (12m)'!$G$67:$G$69)-'Calc - research target (12m)'!$F$68*'Calc - research target (12m)'!$G$68)+'Calc - research target (12m)'!$G$68*($A13*E$12+'Calc - research target (12m)'!$B$52/'Calc - research target (12m)'!$B$53))/SUM('Calc - research target (12m)'!$G$67:$G$69) | F13: =((SUMPRODUCT('Calc - research target (12m)'!$F$67:$F$69,'Calc - research target (12m)'!$G$67:$G$69)-'Calc - research target (12m)'!$F$68*'Calc - research target (12m)'!$G$68)+'Calc - research target (12m)'!$G$68*($A13*F$12+'Calc - research target (12m)'!$B$52/'Calc - research target (12m)'!$B$53))/SUM('Calc - research target (12m)'!$G$67:$G$69)
A14: =Valuation!$B$70+(-2) | B14: =((SUMPRODUCT('Calc - research target (12m)'!$F$67:$F$69,'Calc - research target (12m)'!$G$67:$G$69)-'Calc - research target (12m)'!$F$68*'Calc - research target (12m)'!$G$68)+'Calc - research target (12m)'!$G$68*($A14*B$12+'Calc - research target (12m)'!$B$52/'Calc - research target (12m)'!$B$53))/SUM('Calc - research target (12m)'!$G$67:$G$69) | C14: =((SUMPRODUCT('Calc - research target (12m)'!$F$67:$F$69,'Calc - research target (12m)'!$G$67:$G$69)-'Calc - research target (12m)'!$F$68*'Calc - research target (12m)'!$G$68)+'Calc - research target (12m)'!$G$68*($A14*C$12+'Calc - research target (12m)'!$B$52/'Calc - research target (12m)'!$B$53))/SUM('Calc - research target (12m)'!$G$67:$G$69) | D14: =((SUMPRODUCT('Calc - research target (12m)'!$F$67:$F$69,'Calc - research target (12m)'!$G$67:$G$69)-'Calc - research target (12m)'!$F$68*'Calc - research target (12m)'!$G$68)+'Calc - research target (12m)'!$G$68*($A14*D$12+'Calc - research target (12m)'!$B$52/'Calc - research target (12m)'!$B$53))/SUM('Calc - research target (12m)'!$G$67:$G$69) | E14: =((SUMPRODUCT('Calc - research target (12m)'!$F$67:$F$69,'Calc - research target (12m)'!$G$67:$G$69)-'Calc - research target (12m)'!$F$68*'Calc - research target (12m)'!$G$68)+'Calc - research target (12m)'!$G$68*($A14*E$12+'Calc - research target (12m)'!$B$52/'Calc - research target (12m)'!$B$53))/SUM('Calc - research target (12m)'!$G$67:$G$69) | F14: =((SUMPRODUCT('Calc - research target (12m)'!$F$67:$F$69,'Calc - research target (12m)'!$G$67:$G$69)-'Calc - research target (12m)'!$F$68*'Calc - research target (12m)'!$G$68)+'Calc - research target (12m)'!$G$68*($A14*F$12+'Calc - research target (12m)'!$B$52/'Calc - research target (12m)'!$B$53))/SUM('Calc - research target (12m)'!$G$67:$G$69)
A15: =Valuation!$B$70+(-1) | B15: =((SUMPRODUCT('Calc - research target (12m)'!$F$67:$F$69,'Calc - research target (12m)'!$G$67:$G$69)-'Calc - research target (12m)'!$F$68*'Calc - research target (12m)'!$G$68)+'Calc - research target (12m)'!$G$68*($A15*B$12+'Calc - research target (12m)'!$B$52/'Calc - research target (12m)'!$B$53))/SUM('Calc - research target (12m)'!$G$67:$G$69) | C15: =((SUMPRODUCT('Calc - research target (12m)'!$F$67:$F$69,'Calc - research target (12m)'!$G$67:$G$69)-'Calc - research target (12m)'!$F$68*'Calc - research target (12m)'!$G$68)+'Calc - research target (12m)'!$G$68*($A15*C$12+'Calc - research target (12m)'!$B$52/'Calc - research target (12m)'!$B$53))/SUM('Calc - research target (12m)'!$G$67:$G$69) | D15: =((SUMPRODUCT('Calc - research target (12m)'!$F$67:$F$69,'Calc - research target (12m)'!$G$67:$G$69)-'Calc - research target (12m)'!$F$68*'Calc - research target (12m)'!$G$68)+'Calc - research target (12m)'!$G$68*($A15*D$12+'Calc - research target (12m)'!$B$52/'Calc - research target (12m)'!$B$53))/SUM('Calc - research target (12m)'!$G$67:$G$69) | E15: =((SUMPRODUCT('Calc - research target (12m)'!$F$67:$F$69,'Calc - research target (12m)'!$G$67:$G$69)-'Calc - research target (12m)'!$F$68*'Calc - research target (12m)'!$G$68)+'Calc - research target (12m)'!$G$68*($A15*E$12+'Calc - research target (12m)'!$B$52/'Calc - research target (12m)'!$B$53))/SUM('Calc - research target (12m)'!$G$67:$G$69) | F15: =((SUMPRODUCT('Calc - research target (12m)'!$F$67:$F$69,'Calc - research target (12m)'!$G$67:$G$69)-'Calc - research target (12m)'!$F$68*'Calc - research target (12m)'!$G$68)+'Calc - research target (12m)'!$G$68*($A15*F$12+'Calc - research target (12m)'!$B$52/'Calc - research target (12m)'!$B$53))/SUM('Calc - research target (12m)'!$G$67:$G$69)
A16: =Valuation!$B$70+(0) | B16: =((SUMPRODUCT('Calc - research target (12m)'!$F$67:$F$69,'Calc - research target (12m)'!$G$67:$G$69)-'Calc - research target (12m)'!$F$68*'Calc - research target (12m)'!$G$68)+'Calc - research target (12m)'!$G$68*($A16*B$12+'Calc - research target (12m)'!$B$52/'Calc - research target (12m)'!$B$53))/SUM('Calc - research target (12m)'!$G$67:$G$69) | C16: =((SUMPRODUCT('Calc - research target (12m)'!$F$67:$F$69,'Calc - research target (12m)'!$G$67:$G$69)-'Calc - research target (12m)'!$F$68*'Calc - research target (12m)'!$G$68)+'Calc - research target (12m)'!$G$68*($A16*C$12+'Calc - research target (12m)'!$B$52/'Calc - research target (12m)'!$B$53))/SUM('Calc - research target (12m)'!$G$67:$G$69) | D16: =((SUMPRODUCT('Calc - research target (12m)'!$F$67:$F$69,'Calc - research target (12m)'!$G$67:$G$69)-'Calc - research target (12m)'!$F$68*'Calc - research target (12m)'!$G$68)+'Calc - research target (12m)'!$G$68*($A16*D$12+'Calc - research target (12m)'!$B$52/'Calc - research target (12m)'!$B$53))/SUM('Calc - research target (12m)'!$G$67:$G$69) | E16: =((SUMPRODUCT('Calc - research target (12m)'!$F$67:$F$69,'Calc - research target (12m)'!$G$67:$G$69)-'Calc - research target (12m)'!$F$68*'Calc - research target (12m)'!$G$68)+'Calc - research target (12m)'!$G$68*($A16*E$12+'Calc - research target (12m)'!$B$52/'Calc - research target (12m)'!$B$53))/SUM('Calc - research target (12m)'!$G$67:$G$69) | F16: =((SUMPRODUCT('Calc - research target (12m)'!$F$67:$F$69,'Calc - research target (12m)'!$G$67:$G$69)-'Calc - research target (12m)'!$F$68*'Calc - research target (12m)'!$G$68)+'Calc - research target (12m)'!$G$68*($A16*F$12+'Calc - research target (12m)'!$B$52/'Calc - research target (12m)'!$B$53))/SUM('Calc - research target (12m)'!$G$67:$G$69)
A17: =Valuation!$B$70+(1) | B17: =((SUMPRODUCT('Calc - research target (12m)'!$F$67:$F$69,'Calc - research target (12m)'!$G$67:$G$69)-'Calc - research target (12m)'!$F$68*'Calc - research target (12m)'!$G$68)+'Calc - research target (12m)'!$G$68*($A17*B$12+'Calc - research target (12m)'!$B$52/'Calc - research target (12m)'!$B$53))/SUM('Calc - research target (12m)'!$G$67:$G$69) | C17: =((SUMPRODUCT('Calc - research target (12m)'!$F$67:$F$69,'Calc - research target (12m)'!$G$67:$G$69)-'Calc - research target (12m)'!$F$68*'Calc - research target (12m)'!$G$68)+'Calc - research target (12m)'!$G$68*($A17*C$12+'Calc - research target (12m)'!$B$52/'Calc - research target (12m)'!$B$53))/SUM('Calc - research target (12m)'!$G$67:$G$69) | D17: =((SUMPRODUCT('Calc - research target (12m)'!$F$67:$F$69,'Calc - research target (12m)'!$G$67:$G$69)-'Calc - research target (12m)'!$F$68*'Calc - research target (12m)'!$G$68)+'Calc - research target (12m)'!$G$68*($A17*D$12+'Calc - research target (12m)'!$B$52/'Calc - research target (12m)'!$B$53))/SUM('Calc - research target (12m)'!$G$67:$G$69) | E17: =((SUMPRODUCT('Calc - research target (12m)'!$F$67:$F$69,'Calc - research target (12m)'!$G$67:$G$69)-'Calc - research target (12m)'!$F$68*'Calc - research target (12m)'!$G$68)+'Calc - research target (12m)'!$G$68*($A17*E$12+'Calc - research target (12m)'!$B$52/'Calc - research target (12m)'!$B$53))/SUM('Calc - research target (12m)'!$G$67:$G$69) | F17: =((SUMPRODUCT('Calc - research target (12m)'!$F$67:$F$69,'Calc - research target (12m)'!$G$67:$G$69)-'Calc - research target (12m)'!$F$68*'Calc - research target (12m)'!$G$68)+'Calc - research target (12m)'!$G$68*($A17*F$12+'Calc - research target (12m)'!$B$52/'Calc - research target (12m)'!$B$53))/SUM('Calc - research target (12m)'!$G$67:$G$69)
A18: =Valuation!$B$70+(2) | B18: =((SUMPRODUCT('Calc - research target (12m)'!$F$67:$F$69,'Calc - research target (12m)'!$G$67:$G$69)-'Calc - research target (12m)'!$F$68*'Calc - research target (12m)'!$G$68)+'Calc - research target (12m)'!$G$68*($A18*B$12+'Calc - research target (12m)'!$B$52/'Calc - research target (12m)'!$B$53))/SUM('Calc - research target (12m)'!$G$67:$G$69) | C18: =((SUMPRODUCT('Calc - research target (12m)'!$F$67:$F$69,'Calc - research target (12m)'!$G$67:$G$69)-'Calc - research target (12m)'!$F$68*'Calc - research target (12m)'!$G$68)+'Calc - research target (12m)'!$G$68*($A18*C$12+'Calc - research target (12m)'!$B$52/'Calc - research target (12m)'!$B$53))/SUM('Calc - research target (12m)'!$G$67:$G$69) | D18: =((SUMPRODUCT('Calc - research target (12m)'!$F$67:$F$69,'Calc - research target (12m)'!$G$67:$G$69)-'Calc - research target (12m)'!$F$68*'Calc - research target (12m)'!$G$68)+'Calc - research target (12m)'!$G$68*($A18*D$12+'Calc - research target (12m)'!$B$52/'Calc - research target (12m)'!$B$53))/SUM('Calc - research target (12m)'!$G$67:$G$69) | E18: =((SUMPRODUCT('Calc - research target (12m)'!$F$67:$F$69,'Calc - research target (12m)'!$G$67:$G$69)-'Calc - research target (12m)'!$F$68*'Calc - research target (12m)'!$G$68)+'Calc - research target (12m)'!$G$68*($A18*E$12+'Calc - research target (12m)'!$B$52/'Calc - research target (12m)'!$B$53))/SUM('Calc - research target (12m)'!$G$67:$G$69) | F18: =((SUMPRODUCT('Calc - research target (12m)'!$F$67:$F$69,'Calc - research target (12m)'!$G$67:$G$69)-'Calc - research target (12m)'!$F$68*'Calc - research target (12m)'!$G$68)+'Calc - research target (12m)'!$G$68*($A18*F$12+'Calc - research target (12m)'!$B$52/'Calc - research target (12m)'!$B$53))/SUM('Calc - research target (12m)'!$G$67:$G$69)
A19: =Valuation!$B$70+(3) | B19: =((SUMPRODUCT('Calc - research target (12m)'!$F$67:$F$69,'Calc - research target (12m)'!$G$67:$G$69)-'Calc - research target (12m)'!$F$68*'Calc - research target (12m)'!$G$68)+'Calc - research target (12m)'!$G$68*($A19*B$12+'Calc - research target (12m)'!$B$52/'Calc - research target (12m)'!$B$53))/SUM('Calc - research target (12m)'!$G$67:$G$69) | C19: =((SUMPRODUCT('Calc - research target (12m)'!$F$67:$F$69,'Calc - research target (12m)'!$G$67:$G$69)-'Calc - research target (12m)'!$F$68*'Calc - research target (12m)'!$G$68)+'Calc - research target (12m)'!$G$68*($A19*C$12+'Calc - research target (12m)'!$B$52/'Calc - research target (12m)'!$B$53))/SUM('Calc - research target (12m)'!$G$67:$G$69) | D19: =((SUMPRODUCT('Calc - research target (12m)'!$F$67:$F$69,'Calc - research target (12m)'!$G$67:$G$69)-'Calc - research target (12m)'!$F$68*'Calc - research target (12m)'!$G$68)+'Calc - research target (12m)'!$G$68*($A19*D$12+'Calc - research target (12m)'!$B$52/'Calc - research target (12m)'!$B$53))/SUM('Calc - research target (12m)'!$G$67:$G$69) | E19: =((SUMPRODUCT('Calc - research target (12m)'!$F$67:$F$69,'Calc - research target (12m)'!$G$67:$G$69)-'Calc - research target (12m)'!$F$68*'Calc - research target (12m)'!$G$68)+'Calc - research target (12m)'!$G$68*($A19*E$12+'Calc - research target (12m)'!$B$52/'Calc - research target (12m)'!$B$53))/SUM('Calc - research target (12m)'!$G$67:$G$69) | F19: =((SUMPRODUCT('Calc - research target (12m)'!$F$67:$F$69,'Calc - research target (12m)'!$G$67:$G$69)-'Calc - research target (12m)'!$F$68*'Calc - research target (12m)'!$G$68)+'Calc - research target (12m)'!$G$68*($A19*F$12+'Calc - research target (12m)'!$B$52/'Calc - research target (12m)'!$B$53))/SUM('Calc - research target (12m)'!$G$67:$G$69)
A22: FY2027E diluted EPS: revenue growth change in every year (down) x EBIT margin change (across)
A23: Growth Δ \ margin Δ | B23: -0.01 | C23: -0.005 | D23: 0 | E23: 0.005 | F23: 0.01
A24: -0.02 | B24: =(Valuation!$B$50*(1+Model!E48+$A24)*(1+Model!F48+$A24)*(Model!F49+B$23)+Model!F20)*(1-Model!F50)/Model!F27 | C24: =(Valuation!$B$50*(1+Model!E48+$A24)*(1+Model!F48+$A24)*(Model!F49+C$23)+Model!F20)*(1-Model!F50)/Model!F27 | D24: =(Valuation!$B$50*(1+Model!E48+$A24)*(1+Model!F48+$A24)*(Model!F49+D$23)+Model!F20)*(1-Model!F50)/Model!F27 | E24: =(Valuation!$B$50*(1+Model!E48+$A24)*(1+Model!F48+$A24)*(Model!F49+E$23)+Model!F20)*(1-Model!F50)/Model!F27 | F24: =(Valuation!$B$50*(1+Model!E48+$A24)*(1+Model!F48+$A24)*(Model!F49+F$23)+Model!F20)*(1-Model!F50)/Model!F27
A25: -0.01 | B25: =(Valuation!$B$50*(1+Model!E48+$A25)*(1+Model!F48+$A25)*(Model!F49+B$23)+Model!F20)*(1-Model!F50)/Model!F27 | C25: =(Valuation!$B$50*(1+Model!E48+$A25)*(1+Model!F48+$A25)*(Model!F49+C$23)+Model!F20)*(1-Model!F50)/Model!F27 | D25: =(Valuation!$B$50*(1+Model!E48+$A25)*(1+Model!F48+$A25)*(Model!F49+D$23)+Model!F20)*(1-Model!F50)/Model!F27 | E25: =(Valuation!$B$50*(1+Model!E48+$A25)*(1+Model!F48+$A25)*(Model!F49+E$23)+Model!F20)*(1-Model!F50)/Model!F27 | F25: =(Valuation!$B$50*(1+Model!E48+$A25)*(1+Model!F48+$A25)*(Model!F49+F$23)+Model!F20)*(1-Model!F50)/Model!F27
A26: 0 | B26: =(Valuation!$B$50*(1+Model!E48+$A26)*(1+Model!F48+$A26)*(Model!F49+B$23)+Model!F20)*(1-Model!F50)/Model!F27 | C26: =(Valuation!$B$50*(1+Model!E48+$A26)*(1+Model!F48+$A26)*(Model!F49+C$23)+Model!F20)*(1-Model!F50)/Model!F27 | D26: =(Valuation!$B$50*(1+Model!E48+$A26)*(1+Model!F48+$A26)*(Model!F49+D$23)+Model!F20)*(1-Model!F50)/Model!F27 | E26: =(Valuation!$B$50*(1+Model!E48+$A26)*(1+Model!F48+$A26)*(Model!F49+E$23)+Model!F20)*(1-Model!F50)/Model!F27 | F26: =(Valuation!$B$50*(1+Model!E48+$A26)*(1+Model!F48+$A26)*(Model!F49+F$23)+Model!F20)*(1-Model!F50)/Model!F27
A27: 0.01 | B27: =(Valuation!$B$50*(1+Model!E48+$A27)*(1+Model!F48+$A27)*(Model!F49+B$23)+Model!F20)*(1-Model!F50)/Model!F27 | C27: =(Valuation!$B$50*(1+Model!E48+$A27)*(1+Model!F48+$A27)*(Model!F49+C$23)+Model!F20)*(1-Model!F50)/Model!F27 | D27: =(Valuation!$B$50*(1+Model!E48+$A27)*(1+Model!F48+$A27)*(Model!F49+D$23)+Model!F20)*(1-Model!F50)/Model!F27 | E27: =(Valuation!$B$50*(1+Model!E48+$A27)*(1+Model!F48+$A27)*(Model!F49+E$23)+Model!F20)*(1-Model!F50)/Model!F27 | F27: =(Valuation!$B$50*(1+Model!E48+$A27)*(1+Model!F48+$A27)*(Model!F49+F$23)+Model!F20)*(1-Model!F50)/Model!F27
A28: 0.02 | B28: =(Valuation!$B$50*(1+Model!E48+$A28)*(1+Model!F48+$A28)*(Model!F49+B$23)+Model!F20)*(1-Model!F50)/Model!F27 | C28: =(Valuation!$B$50*(1+Model!E48+$A28)*(1+Model!F48+$A28)*(Model!F49+C$23)+Model!F20)*(1-Model!F50)/Model!F27 | D28: =(Valuation!$B$50*(1+Model!E48+$A28)*(1+Model!F48+$A28)*(Model!F49+D$23)+Model!F20)*(1-Model!F50)/Model!F27 | E28: =(Valuation!$B$50*(1+Model!E48+$A28)*(1+Model!F48+$A28)*(Model!F49+E$23)+Model!F20)*(1-Model!F50)/Model!F27 | F28: =(Valuation!$B$50*(1+Model!E48+$A28)*(1+Model!F48+$A28)*(Model!F49+F$23)+Model!F20)*(1-Model!F50)/Model!F27
A30: Net interest and the share count are held at the base case in table 3.

Sheet Distribution
A1: BKNG: 12-month distribution (mix of lognormals around each scenario value)
A3: Scenario | B3: Probability | C3: Value at target date | D3: Story
A4: bear | B4: =Valuation!B83 | C4: ='Calc - bear'!$F$70 | D4: =Valuation!J83
A5: base | B5: =Valuation!B84 | C5: ='Calc - base'!$F$70 | D5: =Valuation!J84
A6: bull | B6: =Valuation!B85 | C6: ='Calc - bull'!$F$70 | D6: =Valuation!J85
A8: Probabilities sum to | B8: =SUM(B4:B6)
A9: Spread within each scenario | B9: =Valuation!$B$66
A10: Probability-weighted mean | B10: =($B$4*$C$4+$B$5*$C$5+$B$6*$C$6)*EXP($B$9^2/2)
A12: Quantile | B12: Price
A13: Median (model target) | B13: =SQRT(A60*B60)
A14: 10th percentile | B14: =SQRT(D60*E60)
A15: 25th percentile | B15: =SQRT(G60*H60)
A16: 75th percentile | B16: =SQRT(J60*K60)
A17: 90th percentile | B17: =SQRT(M60*N60)
A19: Each quantile solved by bisection (block: low, high, probability above the midpoint)
A20: Median (model target): low | B20: high | C20: P(above mid) | D20: 10th percentile: low | E20: high | F20: P(above mid) | G20: 25th percentile: low | H20: high | I20: P(above mid) | J20: 75th percentile: low | K20: high | L20: P(above mid) | M20: 90th percentile: low | N20: high | O20: P(above mid)
A21: =MIN($C$4,$C$5,$C$6)*0.2 | B21: =MAX($C$4,$C$5,$C$6)*4 | C21: =SUMPRODUCT($B$4:$B$6,1-NORMSDIST((LN(SQRT(A21*B21))-LN($C$4:$C$6))/$B$9)) | D21: =MIN($C$4,$C$5,$C$6)*0.2 | E21: =MAX($C$4,$C$5,$C$6)*4 | F21: =SUMPRODUCT($B$4:$B$6,1-NORMSDIST((LN(SQRT(D21*E21))-LN($C$4:$C$6))/$B$9)) | G21: =MIN($C$4,$C$5,$C$6)*0.2 | H21: =MAX($C$4,$C$5,$C$6)*4 | I21: =SUMPRODUCT($B$4:$B$6,1-NORMSDIST((LN(SQRT(G21*H21))-LN($C$4:$C$6))/$B$9)) | J21: =MIN($C$4,$C$5,$C$6)*0.2 | K21: =MAX($C$4,$C$5,$C$6)*4 | L21: =SUMPRODUCT($B$4:$B$6,1-NORMSDIST((LN(SQRT(J21*K21))-LN($C$4:$C$6))/$B$9)) | M21: =MIN($C$4,$C$5,$C$6)*0.2 | N21: =MAX($C$4,$C$5,$C$6)*4 | O21: =SUMPRODUCT($B$4:$B$6,1-NORMSDIST((LN(SQRT(M21*N21))-LN($C$4:$C$6))/$B$9))
A22: =IF(C21>0.5,SQRT(A21*B21),A21) | B22: =IF(C21>0.5,B21,SQRT(A21*B21)) | C22: =SUMPRODUCT($B$4:$B$6,1-NORMSDIST((LN(SQRT(A22*B22))-LN($C$4:$C$6))/$B$9)) | D22: =IF(F21>0.9,SQRT(D21*E21),D21) | E22: =IF(F21>0.9,E21,SQRT(D21*E21)) | F22: =SUMPRODUCT($B$4:$B$6,1-NORMSDIST((LN(SQRT(D22*E22))-LN($C$4:$C$6))/$B$9)) | G22: =IF(I21>0.75,SQRT(G21*H21),G21) | H22: =IF(I21>0.75,H21,SQRT(G21*H21)) | I22: =SUMPRODUCT($B$4:$B$6,1-NORMSDIST((LN(SQRT(G22*H22))-LN($C$4:$C$6))/$B$9)) | J22: =IF(L21>0.25,SQRT(J21*K21),J21) | K22: =IF(L21>0.25,K21,SQRT(J21*K21)) | L22: =SUMPRODUCT($B$4:$B$6,1-NORMSDIST((LN(SQRT(J22*K22))-LN($C$4:$C$6))/$B$9)) | M22: =IF(O21>0.09999999999999998,SQRT(M21*N21),M21) | N22: =IF(O21>0.09999999999999998,N21,SQRT(M21*N21)) | O22: =SUMPRODUCT($B$4:$B$6,1-NORMSDIST((LN(SQRT(M22*N22))-LN($C$4:$C$6))/$B$9))
A23: =IF(C22>0.5,SQRT(A22*B22),A22) | B23: =IF(C22>0.5,B22,SQRT(A22*B22)) | C23: =SUMPRODUCT($B$4:$B$6,1-NORMSDIST((LN(SQRT(A23*B23))-LN($C$4:$C$6))/$B$9)) | D23: =IF(F22>0.9,SQRT(D22*E22),D22) | E23: =IF(F22>0.9,E22,SQRT(D22*E22)) | F23: =SUMPRODUCT($B$4:$B$6,1-NORMSDIST((LN(SQRT(D23*E23))-LN($C$4:$C$6))/$B$9)) | G23: =IF(I22>0.75,SQRT(G22*H22),G22) | H23: =IF(I22>0.75,H22,SQRT(G22*H22)) | I23: =SUMPRODUCT($B$4:$B$6,1-NORMSDIST((LN(SQRT(G23*H23))-LN($C$4:$C$6))/$B$9)) | J23: =IF(L22>0.25,SQRT(J22*K22),J22) | K23: =IF(L22>0.25,K22,SQRT(J22*K22)) | L23: =SUMPRODUCT($B$4:$B$6,1-NORMSDIST((LN(SQRT(J23*K23))-LN($C$4:$C$6))/$B$9)) | M23: =IF(O22>0.09999999999999998,SQRT(M22*N22),M22) | N23: =IF(O22>0.09999999999999998,N22,SQRT(M22*N22)) | O23: =SUMPRODUCT($B$4:$B$6,1-NORMSDIST((LN(SQRT(M23*N23))-LN($C$4:$C$6))/$B$9))
A24: =IF(C23>0.5,SQRT(A23*B23),A23) | B24: =IF(C23>0.5,B23,SQRT(A23*B23)) | C24: =SUMPRODUCT($B$4:$B$6,1-NORMSDIST((LN(SQRT(A24*B24))-LN($C$4:$C$6))/$B$9)) | D24: =IF(F23>0.9,SQRT(D23*E23),D23) | E24: =IF(F23>0.9,E23,SQRT(D23*E23)) | F24: =SUMPRODUCT($B$4:$B$6,1-NORMSDIST((LN(SQRT(D24*E24))-LN($C$4:$C$6))/$B$9)) | G24: =IF(I23>0.75,SQRT(G23*H23),G23) | H24: =IF(I23>0.75,H23,SQRT(G23*H23)) | I24: =SUMPRODUCT($B$4:$B$6,1-NORMSDIST((LN(SQRT(G24*H24))-LN($C$4:$C$6))/$B$9)) | J24: =IF(L23>0.25,SQRT(J23*K23),J23) | K24: =IF(L23>0.25,K23,SQRT(J23*K23)) | L24: =SUMPRODUCT($B$4:$B$6,1-NORMSDIST((LN(SQRT(J24*K24))-LN($C$4:$C$6))/$B$9)) | M24: =IF(O23>0.09999999999999998,SQRT(M23*N23),M23) | N24: =IF(O23>0.09999999999999998,N23,SQRT(M23*N23)) | O24: =SUMPRODUCT($B$4:$B$6,1-NORMSDIST((LN(SQRT(M24*N24))-LN($C$4:$C$6))/$B$9))
A25: =IF(C24>0.5,SQRT(A24*B24),A24) | B25: =IF(C24>0.5,B24,SQRT(A24*B24)) | C25: =SUMPRODUCT($B$4:$B$6,1-NORMSDIST((LN(SQRT(A25*B25))-LN($C$4:$C$6))/$B$9)) | D25: =IF(F24>0.9,SQRT(D24*E24),D24) | E25: =IF(F24>0.9,E24,SQRT(D24*E24)) | F25: =SUMPRODUCT($B$4:$B$6,1-NORMSDIST((LN(SQRT(D25*E25))-LN($C$4:$C$6))/$B$9)) | G25: =IF(I24>0.75,SQRT(G24*H24),G24) | H25: =IF(I24>0.75,H24,SQRT(G24*H24)) | I25: =SUMPRODUCT($B$4:$B$6,1-NORMSDIST((LN(SQRT(G25*H25))-LN($C$4:$C$6))/$B$9)) | J25: =IF(L24>0.25,SQRT(J24*K24),J24) | K25: =IF(L24>0.25,K24,SQRT(J24*K24)) | L25: =SUMPRODUCT($B$4:$B$6,1-NORMSDIST((LN(SQRT(J25*K25))-LN($C$4:$C$6))/$B$9)) | M25: =IF(O24>0.09999999999999998,SQRT(M24*N24),M24) | N25: =IF(O24>0.09999999999999998,N24,SQRT(M24*N24)) | O25: =SUMPRODUCT($B$4:$B$6,1-NORMSDIST((LN(SQRT(M25*N25))-LN($C$4:$C$6))/$B$9))
A26: =IF(C25>0.5,SQRT(A25*B25),A25) | B26: =IF(C25>0.5,B25,SQRT(A25*B25)) | C26: =SUMPRODUCT($B$4:$B$6,1-NORMSDIST((LN(SQRT(A26*B26))-LN($C$4:$C$6))/$B$9)) | D26: =IF(F25>0.9,SQRT(D25*E25),D25) | E26: =IF(F25>0.9,E25,SQRT(D25*E25)) | F26: =SUMPRODUCT($B$4:$B$6,1-NORMSDIST((LN(SQRT(D26*E26))-LN($C$4:$C$6))/$B$9)) | G26: =IF(I25>0.75,SQRT(G25*H25),G25) | H26: =IF(I25>0.75,H25,SQRT(G25*H25)) | I26: =SUMPRODUCT($B$4:$B$6,1-NORMSDIST((LN(SQRT(G26*H26))-LN($C$4:$C$6))/$B$9)) | J26: =IF(L25>0.25,SQRT(J25*K25),J25) | K26: =IF(L25>0.25,K25,SQRT(J25*K25)) | L26: =SUMPRODUCT($B$4:$B$6,1-NORMSDIST((LN(SQRT(J26*K26))-LN($C$4:$C$6))/$B$9)) | M26: =IF(O25>0.09999999999999998,SQRT(M25*N25),M25) | N26: =IF(O25>0.09999999999999998,N25,SQRT(M25*N25)) | O26: =SUMPRODUCT($B$4:$B$6,1-NORMSDIST((LN(SQRT(M26*N26))-LN($C$4:$C$6))/$B$9))
A27: =IF(C26>0.5,SQRT(A26*B26),A26) | B27: =IF(C26>0.5,B26,SQRT(A26*B26)) | C27: =SUMPRODUCT($B$4:$B$6,1-NORMSDIST((LN(SQRT(A27*B27))-LN($C$4:$C$6))/$B$9)) | D27: =IF(F26>0.9,SQRT(D26*E26),D26) | E27: =IF(F26>0.9,E26,SQRT(D26*E26)) | F27: =SUMPRODUCT($B$4:$B$6,1-NORMSDIST((LN(SQRT(D27*E27))-LN($C$4:$C$6))/$B$9)) | G27: =IF(I26>0.75,SQRT(G26*H26),G26) | H27: =IF(I26>0.75,H26,SQRT(G26*H26)) | I27: =SUMPRODUCT($B$4:$B$6,1-NORMSDIST((LN(SQRT(G27*H27))-LN($C$4:$C$6))/$B$9)) | J27: =IF(L26>0.25,SQRT(J26*K26),J26) | K27: =IF(L26>0.25,K26,SQRT(J26*K26)) | L27: =SUMPRODUCT($B$4:$B$6,1-NORMSDIST((LN(SQRT(J27*K27))-LN($C$4:$C$6))/$B$9)) | M27: =IF(O26>0.09999999999999998,SQRT(M26*N26),M26) | N27: =IF(O26>0.09999999999999998,N26,SQRT(M26*N26)) | O27: =SUMPRODUCT($B$4:$B$6,1-NORMSDIST((LN(SQRT(M27*N27))-LN($C$4:$C$6))/$B$9))
A28: =IF(C27>0.5,SQRT(A27*B27),A27) | B28: =IF(C27>0.5,B27,SQRT(A27*B27)) | C28: =SUMPRODUCT($B$4:$B$6,1-NORMSDIST((LN(SQRT(A28*B28))-LN($C$4:$C$6))/$B$9)) | D28: =IF(F27>0.9,SQRT(D27*E27),D27) | E28: =IF(F27>0.9,E27,SQRT(D27*E27)) | F28: =SUMPRODUCT($B$4:$B$6,1-NORMSDIST((LN(SQRT(D28*E28))-LN($C$4:$C$6))/$B$9)) | G28: =IF(I27>0.75,SQRT(G27*H27),G27) | H28: =IF(I27>0.75,H27,SQRT(G27*H27)) | I28: =SUMPRODUCT($B$4:$B$6,1-NORMSDIST((LN(SQRT(G28*H28))-LN($C$4:$C$6))/$B$9)) | J28: =IF(L27>0.25,SQRT(J27*K27),J27) | K28: =IF(L27>0.25,K27,SQRT(J27*K27)) | L28: =SUMPRODUCT($B$4:$B$6,1-NORMSDIST((LN(SQRT(J28*K28))-LN($C$4:$C$6))/$B$9)) | M28: =IF(O27>0.09999999999999998,SQRT(M27*N27),M27) | N28: =IF(O27>0.09999999999999998,N27,SQRT(M27*N27)) | O28: =SUMPRODUCT($B$4:$B$6,1-NORMSDIST((LN(SQRT(M28*N28))-LN($C$4:$C$6))/$B$9))
A29: =IF(C28>0.5,SQRT(A28*B28),A28) | B29: =IF(C28>0.5,B28,SQRT(A28*B28)) | C29: =SUMPRODUCT($B$4:$B$6,1-NORMSDIST((LN(SQRT(A29*B29))-LN($C$4:$C$6))/$B$9)) | D29: =IF(F28>0.9,SQRT(D28*E28),D28) | E29: =IF(F28>0.9,E28,SQRT(D28*E28)) | F29: =SUMPRODUCT($B$4:$B$6,1-NORMSDIST((LN(SQRT(D29*E29))-LN($C$4:$C$6))/$B$9)) | G29: =IF(I28>0.75,SQRT(G28*H28),G28) | H29: =IF(I28>0.75,H28,SQRT(G28*H28)) | I29: =SUMPRODUCT($B$4:$B$6,1-NORMSDIST((LN(SQRT(G29*H29))-LN($C$4:$C$6))/$B$9)) | J29: =IF(L28>0.25,SQRT(J28*K28),J28) | K29: =IF(L28>0.25,K28,SQRT(J28*K28)) | L29: =SUMPRODUCT($B$4:$B$6,1-NORMSDIST((LN(SQRT(J29*K29))-LN($C$4:$C$6))/$B$9)) | M29: =IF(O28>0.09999999999999998,SQRT(M28*N28),M28) | N29: =IF(O28>0.09999999999999998,N28,SQRT(M28*N28)) | O29: =SUMPRODUCT($B$4:$B$6,1-NORMSDIST((LN(SQRT(M29*N29))-LN($C$4:$C$6))/$B$9))
A30: =IF(C29>0.5,SQRT(A29*B29),A29) | B30: =IF(C29>0.5,B29,SQRT(A29*B29)) | C30: =SUMPRODUCT($B$4:$B$6,1-NORMSDIST((LN(SQRT(A30*B30))-LN($C$4:$C$6))/$B$9)) | D30: =IF(F29>0.9,SQRT(D29*E29),D29) | E30: =IF(F29>0.9,E29,SQRT(D29*E29)) | F30: =SUMPRODUCT($B$4:$B$6,1-NORMSDIST((LN(SQRT(D30*E30))-LN($C$4:$C$6))/$B$9)) | G30: =IF(I29>0.75,SQRT(G29*H29),G29) | H30: =IF(I29>0.75,H29,SQRT(G29*H29)) | I30: =SUMPRODUCT($B$4:$B$6,1-NORMSDIST((LN(SQRT(G30*H30))-LN($C$4:$C$6))/$B$9)) | J30: =IF(L29>0.25,SQRT(J29*K29),J29) | K30: =IF(L29>0.25,K29,SQRT(J29*K29)) | L30: =SUMPRODUCT($B$4:$B$6,1-NORMSDIST((LN(SQRT(J30*K30))-LN($C$4:$C$6))/$B$9)) | M30: =IF(O29>0.09999999999999998,SQRT(M29*N29),M29) | N30: =IF(O29>0.09999999999999998,N29,SQRT(M29*N29)) | O30: =SUMPRODUCT($B$4:$B$6,1-NORMSDIST((LN(SQRT(M30*N30))-LN($C$4:$C$6))/$B$9))
A31: =IF(C30>0.5,SQRT(A30*B30),A30) | B31: =IF(C30>0.5,B30,SQRT(A30*B30)) | C31: =SUMPRODUCT($B$4:$B$6,1-NORMSDIST((LN(SQRT(A31*B31))-LN($C$4:$C$6))/$B$9)) | D31: =IF(F30>0.9,SQRT(D30*E30),D30) | E31: =IF(F30>0.9,E30,SQRT(D30*E30)) | F31: =SUMPRODUCT($B$4:$B$6,1-NORMSDIST((LN(SQRT(D31*E31))-LN($C$4:$C$6))/$B$9)) | G31: =IF(I30>0.75,SQRT(G30*H30),G30) | H31: =IF(I30>0.75,H30,SQRT(G30*H30)) | I31: =SUMPRODUCT($B$4:$B$6,1-NORMSDIST((LN(SQRT(G31*H31))-LN($C$4:$C$6))/$B$9)) | J31: =IF(L30>0.25,SQRT(J30*K30),J30) | K31: =IF(L30>0.25,K30,SQRT(J30*K30)) | L31: =SUMPRODUCT($B$4:$B$6,1-NORMSDIST((LN(SQRT(J31*K31))-LN($C$4:$C$6))/$B$9)) | M31: =IF(O30>0.09999999999999998,SQRT(M30*N30),M30) | N31: =IF(O30>0.09999999999999998,N30,SQRT(M30*N30)) | O31: =SUMPRODUCT($B$4:$B$6,1-NORMSDIST((LN(SQRT(M31*N31))-LN($C$4:$C$6))/$B$9))
A32: =IF(C31>0.5,SQRT(A31*B31),A31) | B32: =IF(C31>0.5,B31,SQRT(A31*B31)) | C32: =SUMPRODUCT($B$4:$B$6,1-NORMSDIST((LN(SQRT(A32*B32))-LN($C$4:$C$6))/$B$9)) | D32: =IF(F31>0.9,SQRT(D31*E31),D31) | E32: =IF(F31>0.9,E31,SQRT(D31*E31)) | F32: =SUMPRODUCT($B$4:$B$6,1-NORMSDIST((LN(SQRT(D32*E32))-LN($C$4:$C$6))/$B$9)) | G32: =IF(I31>0.75,SQRT(G31*H31),G31) | H32: =IF(I31>0.75,H31,SQRT(G31*H31)) | I32: =SUMPRODUCT($B$4:$B$6,1-NORMSDIST((LN(SQRT(G32*H32))-LN($C$4:$C$6))/$B$9)) | J32: =IF(L31>0.25,SQRT(J31*K31),J31) | K32: =IF(L31>0.25,K31,SQRT(J31*K31)) | L32: =SUMPRODUCT($B$4:$B$6,1-NORMSDIST((LN(SQRT(J32*K32))-LN($C$4:$C$6))/$B$9)) | M32: =IF(O31>0.09999999999999998,SQRT(M31*N31),M31) | N32: =IF(O31>0.09999999999999998,N31,SQRT(M31*N31)) | O32: =SUMPRODUCT($B$4:$B$6,1-NORMSDIST((LN(SQRT(M32*N32))-LN($C$4:$C$6))/$B$9))
A33: =IF(C32>0.5,SQRT(A32*B32),A32) | B33: =IF(C32>0.5,B32,SQRT(A32*B32)) | C33: =SUMPRODUCT($B$4:$B$6,1-NORMSDIST((LN(SQRT(A33*B33))-LN($C$4:$C$6))/$B$9)) | D33: =IF(F32>0.9,SQRT(D32*E32),D32) | E33: =IF(F32>0.9,E32,SQRT(D32*E32)) | F33: =SUMPRODUCT($B$4:$B$6,1-NORMSDIST((LN(SQRT(D33*E33))-LN($C$4:$C$6))/$B$9)) | G33: =IF(I32>0.75,SQRT(G32*H32),G32) | H33: =IF(I32>0.75,H32,SQRT(G32*H32)) | I33: =SUMPRODUCT($B$4:$B$6,1-NORMSDIST((LN(SQRT(G33*H33))-LN($C$4:$C$6))/$B$9)) | J33: =IF(L32>0.25,SQRT(J32*K32),J32) | K33: =IF(L32>0.25,K32,SQRT(J32*K32)) | L33: =SUMPRODUCT($B$4:$B$6,1-NORMSDIST((LN(SQRT(J33*K33))-LN($C$4:$C$6))/$B$9)) | M33: =IF(O32>0.09999999999999998,SQRT(M32*N32),M32) | N33: =IF(O32>0.09999999999999998,N32,SQRT(M32*N32)) | O33: =SUMPRODUCT($B$4:$B$6,1-NORMSDIST((LN(SQRT(M33*N33))-LN($C$4:$C$6))/$B$9))
... A60: =IF(C59>0.5,SQRT(A59*B59),A59) | B60: =IF(C59>0.5,B59,SQRT(A59*B59)) | C60: =SUMPRODUCT($B$4:$B$6,1-NORMSDIST((LN(SQRT(A60*B60))-LN($C$4:$C$6))/$B$9)) | D60: =IF(F59>0.9,SQRT(D59*E59),D59) | E60: =IF(F59>0.9,E59,SQRT(D59*E59)) | F60: =SUMPRODUCT($B$4:$B$6,1-NORMSDIST((LN(SQRT(D60*E60))-LN($C$4:$C$6))/$B$9)) | G60: =IF(I59>0.75,SQRT(G59*H59),G59) | H60: =IF(I59>0.75,H59,SQRT(G59*H59)) | I60: =SUMPRODUCT($B$4:$B$6,1-NORMSDIST((LN(SQRT(G60*H60))-LN($C$4:$C$6))/$B$9)) | J60: =IF(L59>0.25,SQRT(J59*K59),J59) | K60: =IF(L59>0.25,K59,SQRT(J59*K59)) | L60: =SUMPRODUCT($B$4:$B$6,1-NORMSDIST((LN(SQRT(J60*K60))-LN($C$4:$C$6))/$B$9)) | M60: =IF(O59>0.09999999999999998,SQRT(M59*N59),M59) | N60: =IF(O59>0.09999999999999998,N59,SQRT(M59*N59)) | O60: =SUMPRODUCT($B$4:$B$6,1-NORMSDIST((LN(SQRT(M60*N60))-LN($C$4:$C$6))/$B$9))

Sheet Calc - research target (12m)
A1: BKNG engine calculation: research target (12m) (reconciled set, no scenario deltas)
A2: Machinery behind the Valuation and Distribution tabs; drivers come from Model, assumptions from Valuation.
A4: Scenario Growth Δ | B4: 0
A5: Scenario Margin Δ | B5: 0
A6: Scenario Multiple Δ (turns) | B6: 0
A7: Scenario WACC Δ | B7: 0
A8: Scenario Multiple %Δ | B8: 0
A9: Scenario Stated EPS/FCF %Δ | B9: 0
A10: Scenario Custom %Δ | B10: 0
A12: WACC | B12: =Valuation!$B$51+B7
A13: Years from last FY end to target date | B13: =(Valuation!$B$45-Valuation!$B$49)/365.25
A14: Years from last FY end to balance date | B14: =(Valuation!$B$55-Valuation!$B$49)/365.25
A15: Years from last FY end to share count date | B15: =(Valuation!$B$61-Valuation!$B$49)/365.25
A16: Projected years | B16: 3
A18: Projection | B18: Base | C18: =Model!E5 | D18: =Model!F5 | E18: =Model!G5
A19: Year index | B19: 0 | C19: 1 | D19: 2 | E19: 3
A20: Period end | C20: =Valuation!$B$49+ROUND(365.25*C19,0) | D20: =Valuation!$B$49+ROUND(365.25*D19,0) | E20: =Valuation!$B$49+ROUND(365.25*E19,0)
A21: Revenue growth | C21: =Model!E48+$B$4 | D21: =Model!F48+$B$4 | E21: =Model!G48+$B$4
A22: Revenue | B22: =Valuation!$B$50 | C22: =B22*(1+C21) | D22: =C22*(1+D21) | E22: =D22*(1+E21)
A23: EBIT margin | C23: =Model!E49+$B$5 | D23: =Model!F49+$B$5 | E23: =Model!G49+$B$5
A24: EBIT | C24: =C22*C23 | D24: =D22*D23 | E24: =E22*E23
A25: Tax rate | C25: =Model!E50 | D25: =Model!F50 | E25: =Model!G50
A26: NOPAT | C26: =C24*(1-C25) | D26: =D24*(1-D25) | E26: =E24*(1-E25)
A27: D&A | C27: =C22*(Model!E51) | D27: =D22*(Model!F51) | E27: =E22*(Model!G51)
A28: Capex | C28: =C22*(Model!E52) | D28: =D22*(Model!F52) | E28: =E22*(Model!G52)
A29: Working capital increase | C29: =(Model!E53)*(C22-B22) | D29: =(Model!F53)*(D22-C22) | E29: =(Model!G53)*(E22-D22)
A30: Stock comp | C30: =C22*(Model!E54) | D30: =D22*(Model!F54) | E30: =E22*(Model!G54)
A31: Free cash flow to firm | C31: =C26+C27-C28-C29-IF(AND(Valuation!$B$47="adjusted",Valuation!$B$48="cost"),C30*(1-C25),0) | D31: =D26+D27-D28-D29-IF(AND(Valuation!$B$47="adjusted",Valuation!$B$48="cost"),D30*(1-D25),0) | E31: =E26+E27-E28-E29-IF(AND(Valuation!$B$47="adjusted",Valuation!$B$48="cost"),E30*(1-E25),0)
A32: EBITDA | C32: =C24+C27 | D32: =D24+D27 | E32: =E24+E27
A33: Adj. EBITDA | C33: =C24+C27+C22*(Model!E58) | D33: =D24+D27+D22*(Model!F58) | E33: =E24+E27+E22*(Model!G58)
A34: Shareholder returns + other uses | C34: =C22*Model!E56+Model!E55+Model!E57 | D34: =D22*Model!F56+Model!F55+Model!F57 | E34: =E22*Model!G56+Model!G55+Model!G57
A35: Share of year after target date | C35: =IF(C19<=$B$13,0,C19-MAX(C19-1,$B$13)) | D35: =IF(D19<=$B$13,0,D19-MAX(D19-1,$B$13)) | E35: =IF(E19<=$B$13,0,E19-MAX(E19-1,$B$13))
A36: PV at target date of FCFF | C36: =IF(C35=0,0,C31*C35/(1+$B$12)^(C19-$B$13)) | D36: =IF(D35=0,0,D31*D35/(1+$B$12)^(D19-$B$13)) | E36: =IF(E35=0,0,E31*E35/(1+$B$12)^(E19-$B$13))
A37: Overlap: balance date to target date | C37: =MAX(0,MIN(C19,$B$13)-MAX(C19-1,$B$14)) | D37: =MAX(0,MIN(D19,$B$13)-MAX(D19-1,$B$14)) | E37: =MAX(0,MIN(E19,$B$13)-MAX(E19-1,$B$14))
A38: NTM weight at target date | C38: =MAX(0,MIN(C19,$B$13+1)-MAX(C19-1,$B$13)) | D38: =MAX(0,MIN(D19,$B$13+1)-MAX(D19-1,$B$13)) | E38: =MAX(0,MIN(E19,$B$13+1)-MAX(E19-1,$B$13))
A39: LTM weight at target date | B39: =MAX(0,MIN(0,$B$13)-MAX(-1,$B$13-1)) | C39: =MAX(0,MIN(C19,$B$13)-MAX(C19-1,$B$13-1)) | D39: =MAX(0,MIN(D19,$B$13)-MAX(D19-1,$B$13-1)) | E39: =MAX(0,MIN(E19,$B$13)-MAX(E19-1,$B$13-1))
A41: Value at the target date
A42: PV of free cash flow after the target date | B42: =SUM($C$36:$E$36)
A43: Terminal value at final year | B43: =IF(Valuation!$B$52="exit_multiple",Valuation!$B$54*E32,E31*(1+Valuation!$B$53)/($B$12-Valuation!$B$53))
A44: PV of terminal value at target date | B44: =B43/(1+$B$12)^($B$16-$B$13)
A45: DCF enterprise value at target date | B45: =B42+B44
A46: Terminal value share of DCF | B46: =B44/B45
A47: Free cash flow earned, balance date to target date | B47: =SUMPRODUCT($C$37:$E$37,$C$31:$E$31)
A48: Shareholder returns + other uses paid | B48: =SUMPRODUCT($C$37:$E$37,$C$34:$E$34)
A49: Interest drag on net debt | B49: =Valuation!$B$58*(1-$C$25)*MAX(Valuation!$B$56,0)*MAX($B$13-$B$14,0)
A50: Net debt at target date | B50: =IF(Valuation!$B$59="",Valuation!$B$56-B47+B49+B48,Valuation!$B$59)
A51: Minority interests | B51: =Valuation!$B$57
A52: Adjustments (probability-weighted) | B52: =0
A53: Diluted shares at target date (M) | B53: =IF(Valuation!$B$63="",Valuation!$B$60*(1+Valuation!$B$62)^MAX($B$13-$B$15,0),Valuation!$B$63)
A54: After-tax interest on target-date net debt | B54: =Valuation!$B$58*(1-$C$25)*MAX(B50,0)
A55: Check: WACC vs terminal growth | B55: =IF(AND(Valuation!$B$52<>"exit_multiple",$B$12<=Valuation!$B$53+0.01),"WACC must exceed terminal growth by 1 point","ok")
A56: Check: projection length | B56: =IF(OR($B$13>=$B$16-1,$B$13+1>$B$16),"add projected years past the target date","ok")
A58: Metric at target date | B58: Next 12 months | C58: Last 12 months
A59: Revenue | B59: =SUMPRODUCT($C$38:$E$38,$C$22:$E$22) | C59: =SUMPRODUCT($C$39:$E$39,$C$22:$E$22)+$B$39*$B$22
A60: EBIT | B60: =SUMPRODUCT($C$38:$E$38,$C$24:$E$24) | C60: =SUMPRODUCT($C$39:$E$39,$C$24:$E$24)
A61: EBITDA | B61: =SUMPRODUCT($C$38:$E$38,$C$32:$E$32) | C61: =SUMPRODUCT($C$39:$E$39,$C$32:$E$32)
A62: Adj. EBITDA | B62: =SUMPRODUCT($C$38:$E$38,$C$33:$E$33) | C62: =SUMPRODUCT($C$39:$E$39,$C$33:$E$33)
A63: NOPAT | B63: =SUMPRODUCT($C$38:$E$38,$C$26:$E$26) | C63: =SUMPRODUCT($C$39:$E$39,$C$26:$E$26)
A64: Free cash flow to firm | B64: =SUMPRODUCT($C$38:$E$38,$C$31:$E$31) | C64: =SUMPRODUCT($C$39:$E$39,$C$31:$E$31)
A66: Valuation method | B66: Metric | C66: Multiple used | D66: Basis | E66: Metric at target date | F66: Value per share | G66: Weight | H66: Metric key | I66: Metric shown (stated per-share figure when used)
A67: DCF (cash flow to target date + terminal) | F67: =((B45)-$B$50-$B$51+$B$52)/$B$53 | G67: =Valuation!$B$64
A68: ="Multiple: "&Valuation!A70&" ("&Valuation!D70&")" | B68: =Valuation!A70 | C68: =IF(B68="FCF yield",(Valuation!B70)*(1-$B$8),(Valuation!B70)+IF(B68="EV/sales",0.1,1)*$B$6) | D68: =Valuation!D70 | E68: =IF(D68="ltm",CHOOSE(H68,$C$59,$C$60,$C$61,$C$62,$C$63,$C$64),CHOOSE(H68,$B$59,$B$60,$B$61,$B$62,$B$63,$B$64)) | F68: =IF(OR(B68="EV/EBITDA",B68="EV/sales",B68="EV/EBIT"),((C68*E68)-$B$50-$B$51+$B$52)/$B$53,IF(B68="P/E",IF(Valuation!F70<>"",C68*(Valuation!F70)*(1+$B$9),C68*(E68-$B$54)/$B$53),IF(Valuation!G70<>"",(Valuation!G70)*(1+$B$9)/C68,(E68-IF(Valuation!H70,$B$54,0))/C68/$B$53))+$B$52/$B$53) | G68: =Valuation!C70 | H68: =IF(B68="EV/sales",1,IF(B68="EV/EBIT",2,IF(B68="EV/EBITDA",IF(Valuation!E70="adjusted",4,3),IF(B68="P/E",5,6)))) | I68: =IF(AND(B68="P/E",Valuation!F70<>""),(Valuation!F70)*(1+$B$9),IF(AND(B68="FCF yield",Valuation!G70<>""),(Valuation!G70)*(1+$B$9),E68))
A69: ="Multiple: "&Valuation!A71&" ("&Valuation!D71&")" | B69: =Valuation!A71 | C69: =IF(B69="FCF yield",(Valuation!B71)*(1-$B$8),(Valuation!B71)+IF(B69="EV/sales",0.1,1)*$B$6) | D69: =Valuation!D71 | E69: =IF(D69="ltm",CHOOSE(H69,$C$59,$C$60,$C$61,$C$62,$C$63,$C$64),CHOOSE(H69,$B$59,$B$60,$B$61,$B$62,$B$63,$B$64)) | F69: =IF(OR(B69="EV/EBITDA",B69="EV/sales",B69="EV/EBIT"),((C69*E69)-$B$50-$B$51+$B$52)/$B$53,IF(B69="P/E",IF(Valuation!F71<>"",C69*(Valuation!F71)*(1+$B$9),C69*(E69-$B$54)/$B$53),IF(Valuation!G71<>"",(Valuation!G71)*(1+$B$9)/C69,(E69-IF(Valuation!H71,$B$54,0))/C69/$B$53))+$B$52/$B$53) | G69: =Valuation!C71 | H69: =IF(B69="EV/sales",1,IF(B69="EV/EBIT",2,IF(B69="EV/EBITDA",IF(Valuation!E71="adjusted",4,3),IF(B69="P/E",5,6)))) | I69: =IF(AND(B69="P/E",Valuation!F71<>""),(Valuation!F71)*(1+$B$9),IF(AND(B69="FCF yield",Valuation!G71<>""),(Valuation!G71)*(1+$B$9),E69))
A70: Value per share at target date (weighted methods) | F70: =SUMPRODUCT(F67:F69,G67:G69)/SUM(G67:G69)

Sheet Calc - bear
A1: BKNG engine calculation: bear scenario
A2: Machinery behind the Valuation and Distribution tabs; drivers come from Model, assumptions from Valuation.
A4: Scenario Growth Δ | B4: =N(Valuation!C83)
A5: Scenario Margin Δ | B5: =N(Valuation!D83)
A6: Scenario Multiple Δ (turns) | B6: =N(Valuation!E83)
A7: Scenario WACC Δ | B7: =N(Valuation!F83)
A8: Scenario Multiple %Δ | B8: =N(Valuation!G83)
A9: Scenario Stated EPS/FCF %Δ | B9: =N(Valuation!H83)
A10: Scenario Custom %Δ | B10: =N(Valuation!I83)
A12: WACC | B12: =Valuation!$B$51+B7
A13: Years from last FY end to target date | B13: =(Valuation!$B$45-Valuation!$B$49)/365.25
A14: Years from last FY end to balance date | B14: =(Valuation!$B$55-Valuation!$B$49)/365.25
A15: Years from last FY end to share count date | B15: =(Valuation!$B$61-Valuation!$B$49)/365.25
A16: Projected years | B16: 3
A18: Projection | B18: Base | C18: =Model!E5 | D18: =Model!F5 | E18: =Model!G5
A19: Year index | B19: 0 | C19: 1 | D19: 2 | E19: 3
A20: Period end | C20: =Valuation!$B$49+ROUND(365.25*C19,0) | D20: =Valuation!$B$49+ROUND(365.25*D19,0) | E20: =Valuation!$B$49+ROUND(365.25*E19,0)
A21: Revenue growth | C21: =Model!E48+$B$4+$B$250 | D21: =Model!F48+$B$4 | E21: =Model!G48+$B$4
A22: Revenue | B22: =Valuation!$B$50 | C22: =B22*(1+C21) | D22: =C22*(1+D21) | E22: =D22*(1+E21)
A23: EBIT margin | C23: =Model!E49+$B$5+$B$251 | D23: =Model!F49+$B$5+$B$252 | E23: =Model!G49+$B$5+$B$253
A24: EBIT | C24: =C22*C23 | D24: =D22*D23 | E24: =E22*E23
A25: Tax rate | C25: =Model!E50 | D25: =Model!F50 | E25: =Model!G50
A26: NOPAT | C26: =C24*(1-C25) | D26: =D24*(1-D25) | E26: =E24*(1-E25)
A27: D&A | C27: =C22*(Model!E51) | D27: =D22*(Model!F51) | E27: =E22*(Model!G51)
A28: Capex | C28: =C22*(Model!E52) | D28: =D22*(Model!F52) | E28: =E22*(Model!G52)
A29: Working capital increase | C29: =(Model!E53)*(C22-B22) | D29: =(Model!F53)*(D22-C22) | E29: =(Model!G53)*(E22-D22)
A30: Stock comp | C30: =C22*(Model!E54) | D30: =D22*(Model!F54) | E30: =E22*(Model!G54)
A31: Free cash flow to firm | C31: =C26+C27-C28-C29-IF(AND(Valuation!$B$47="adjusted",Valuation!$B$48="cost"),C30*(1-C25),0) | D31: =D26+D27-D28-D29-IF(AND(Valuation!$B$47="adjusted",Valuation!$B$48="cost"),D30*(1-D25),0) | E31: =E26+E27-E28-E29-IF(AND(Valuation!$B$47="adjusted",Valuation!$B$48="cost"),E30*(1-E25),0)
A32: EBITDA | C32: =C24+C27 | D32: =D24+D27 | E32: =E24+E27
A33: Adj. EBITDA | C33: =C24+C27+C22*(Model!E58) | D33: =D24+D27+D22*(Model!F58) | E33: =E24+E27+E22*(Model!G58)
A34: Shareholder returns + other uses | C34: =C22*Model!E56+Model!E55+Model!E57 | D34: =D22*Model!F56+Model!F55+Model!F57 | E34: =E22*Model!G56+Model!G55+Model!G57
A35: Share of year after target date | C35: =IF(C19<=$B$13,0,C19-MAX(C19-1,$B$13)) | D35: =IF(D19<=$B$13,0,D19-MAX(D19-1,$B$13)) | E35: =IF(E19<=$B$13,0,E19-MAX(E19-1,$B$13))
A36: PV at target date of FCFF | C36: =IF(C35=0,0,C31*C35/(1+$B$12)^(C19-$B$13)) | D36: =IF(D35=0,0,D31*D35/(1+$B$12)^(D19-$B$13)) | E36: =IF(E35=0,0,E31*E35/(1+$B$12)^(E19-$B$13))
A37: Overlap: balance date to target date | C37: =MAX(0,MIN(C19,$B$13)-MAX(C19-1,$B$14)) | D37: =MAX(0,MIN(D19,$B$13)-MAX(D19-1,$B$14)) | E37: =MAX(0,MIN(E19,$B$13)-MAX(E19-1,$B$14))
A38: NTM weight at target date | C38: =MAX(0,MIN(C19,$B$13+1)-MAX(C19-1,$B$13)) | D38: =MAX(0,MIN(D19,$B$13+1)-MAX(D19-1,$B$13)) | E38: =MAX(0,MIN(E19,$B$13+1)-MAX(E19-1,$B$13))
A39: LTM weight at target date | B39: =MAX(0,MIN(0,$B$13)-MAX(-1,$B$13-1)) | C39: =MAX(0,MIN(C19,$B$13)-MAX(C19-1,$B$13-1)) | D39: =MAX(0,MIN(D19,$B$13)-MAX(D19-1,$B$13-1)) | E39: =MAX(0,MIN(E19,$B$13)-MAX(E19-1,$B$13-1))
A41: Value at the target date
A42: PV of free cash flow after the target date | B42: =SUM($C$36:$E$36)
A43: Terminal value at final year | B43: =IF(Valuation!$B$52="exit_multiple",Valuation!$B$54*E32,E31*(1+Valuation!$B$53)/($B$12-Valuation!$B$53))
A44: PV of terminal value at target date | B44: =B43/(1+$B$12)^($B$16-$B$13)
A45: DCF enterprise value at target date | B45: =B42+B44
A46: Terminal value share of DCF | B46: =B44/B45
A47: Free cash flow earned, balance date to target date | B47: =SUMPRODUCT($C$37:$E$37,$C$31:$E$31)
A48: Shareholder returns + other uses paid | B48: =SUMPRODUCT($C$37:$E$37,$C$34:$E$34)
A49: Interest drag on net debt | B49: =Valuation!$B$58*(1-$C$25)*MAX(Valuation!$B$56,0)*MAX($B$13-$B$14,0)
A50: Net debt at target date | B50: =IF(Valuation!$B$59="",Valuation!$B$56-B47+B49+B48,Valuation!$B$59)
A51: Minority interests | B51: =Valuation!$B$57
A52: Adjustments (probability-weighted) | B52: =0
A53: Diluted shares at target date (M) | B53: =IF(Valuation!$B$63="",Valuation!$B$60*(1+Valuation!$B$62)^MAX($B$13-$B$15,0),Valuation!$B$63)
A54: After-tax interest on target-date net debt | B54: =Valuation!$B$58*(1-$C$25)*MAX(B50,0)
A55: Check: WACC vs terminal growth | B55: =IF(AND(Valuation!$B$52<>"exit_multiple",$B$12<=Valuation!$B$53+0.01),"WACC must exceed terminal growth by 1 point","ok")
A56: Check: projection length | B56: =IF(OR($B$13>=$B$16-1,$B$13+1>$B$16),"add projected years past the target date","ok")
A58: Metric at target date | B58: Next 12 months | C58: Last 12 months
A59: Revenue | B59: =SUMPRODUCT($C$38:$E$38,$C$22:$E$22) | C59: =SUMPRODUCT($C$39:$E$39,$C$22:$E$22)+$B$39*$B$22
A60: EBIT | B60: =SUMPRODUCT($C$38:$E$38,$C$24:$E$24) | C60: =SUMPRODUCT($C$39:$E$39,$C$24:$E$24)
A61: EBITDA | B61: =SUMPRODUCT($C$38:$E$38,$C$32:$E$32) | C61: =SUMPRODUCT($C$39:$E$39,$C$32:$E$32)
A62: Adj. EBITDA | B62: =SUMPRODUCT($C$38:$E$38,$C$33:$E$33) | C62: =SUMPRODUCT($C$39:$E$39,$C$33:$E$33)
A63: NOPAT | B63: =SUMPRODUCT($C$38:$E$38,$C$26:$E$26) | C63: =SUMPRODUCT($C$39:$E$39,$C$26:$E$26)
A64: Free cash flow to firm | B64: =SUMPRODUCT($C$38:$E$38,$C$31:$E$31) | C64: =SUMPRODUCT($C$39:$E$39,$C$31:$E$31)
A66: Valuation method | B66: Metric | C66: Multiple used | D66: Basis | E66: Metric at target date | F66: Value per share | G66: Weight | H66: Metric key | I66: Metric shown (stated per-share figure when used)
A67: DCF (cash flow to target date + terminal) | F67: =((B45)-$B$50-$B$51+$B$52)/$B$53 | G67: =Valuation!$B$64
A68: ="Multiple: "&Valuation!A70&" ("&Valuation!D70&")" | B68: =Valuation!A70 | C68: =IF(B68="FCF yield",(Valuation!B70)*(1-$B$8),(Valuation!B70)+IF(B68="EV/sales",0.1,1)*$B$6) | D68: =Valuation!D70 | E68: =IF(D68="ltm",CHOOSE(H68,$C$59,$C$60,$C$61,$C$62,$C$63,$C$64),CHOOSE(H68,$B$59,$B$60,$B$61,$B$62,$B$63,$B$64)) | F68: =IF(OR(B68="EV/EBITDA",B68="EV/sales",B68="EV/EBIT"),((C68*E68)-$B$50-$B$51+$B$52)/$B$53,IF(B68="P/E",IF(Valuation!F70<>"",C68*(Valuation!F70+$B$254)*(1+$B$9),C68*(E68-$B$54)/$B$53),IF(Valuation!G70<>"",(Valuation!G70)*(1+$B$9)/C68,(E68-IF(Valuation!H70,$B$54,0))/C68/$B$53))+$B$52/$B$53) | G68: =Valuation!C70 | H68: =IF(B68="EV/sales",1,IF(B68="EV/EBIT",2,IF(B68="EV/EBITDA",IF(Valuation!E70="adjusted",4,3),IF(B68="P/E",5,6)))) | I68: =IF(AND(B68="P/E",Valuation!F70<>""),(Valuation!F70+$B$254)*(1+$B$9),IF(AND(B68="FCF yield",Valuation!G70<>""),(Valuation!G70)*(1+$B$9),E68))
A69: ="Multiple: "&Valuation!A71&" ("&Valuation!D71&")" | B69: =Valuation!A71 | C69: =IF(B69="FCF yield",(Valuation!B71)*(1-$B$8),(Valuation!B71)+IF(B69="EV/sales",0.1,1)*$B$6) | D69: =Valuation!D71 | E69: =IF(D69="ltm",CHOOSE(H69,$C$59,$C$60,$C$61,$C$62,$C$63,$C$64),CHOOSE(H69,$B$59,$B$60,$B$61,$B$62,$B$63,$B$64)) | F69: =IF(OR(B69="EV/EBITDA",B69="EV/sales",B69="EV/EBIT"),((C69*E69)-$B$50-$B$51+$B$52)/$B$53,IF(B69="P/E",IF(Valuation!F71<>"",C69*(Valuation!F71)*(1+$B$9),C69*(E69-$B$54)/$B$53),IF(Valuation!G71<>"",(Valuation!G71+$B$255)*(1+$B$9)/C69,(E69-IF(Valuation!H71,$B$54,0))/C69/$B$53))+$B$52/$B$53) | G69: =Valuation!C71 | H69: =IF(B69="EV/sales",1,IF(B69="EV/EBIT",2,IF(B69="EV/EBITDA",IF(Valuation!E71="adjusted",4,3),IF(B69="P/E",5,6)))) | I69: =IF(AND(B69="P/E",Valuation!F71<>""),(Valuation!F71)*(1+$B$9),IF(AND(B69="FCF yield",Valuation!G71<>""),(Valuation!G71+$B$255)*(1+$B$9),E69))
A70: Value per share at target date (weighted methods) | F70: =SUMPRODUCT(F67:F69,G67:G69)/SUM(G67:G69)
A249: Driver scenario shifts: line-item changes model_drivers.py resolves from this scenario's driver deltas (added to the Model tab inputs)
A250: Revenue growth, year 1 | B250: -0.069081281
A251: EBIT margin, year 1 | B251: -0.020555997
A252: EBIT margin, year 2 | B252: -0.020549887
A253: EBIT margin, year 3 | B253: -0.020549396
A254: Stated EPS, multiple 1 | B254: -1.5482764
A255: Stated FCF/share, multiple 2 | B255: -1.8485154

Sheet Calc - base
A1: BKNG engine calculation: base scenario
A2: Machinery behind the Valuation and Distribution tabs; drivers come from Model, assumptions from Valuation.
A4: Scenario Growth Δ | B4: =N(Valuation!C84)
A5: Scenario Margin Δ | B5: =N(Valuation!D84)
A6: Scenario Multiple Δ (turns) | B6: =N(Valuation!E84)
A7: Scenario WACC Δ | B7: =N(Valuation!F84)
A8: Scenario Multiple %Δ | B8: =N(Valuation!G84)
A9: Scenario Stated EPS/FCF %Δ | B9: =N(Valuation!H84)
A10: Scenario Custom %Δ | B10: =N(Valuation!I84)
A12: WACC | B12: =Valuation!$B$51+B7
A13: Years from last FY end to target date | B13: =(Valuation!$B$45-Valuation!$B$49)/365.25
A14: Years from last FY end to balance date | B14: =(Valuation!$B$55-Valuation!$B$49)/365.25
A15: Years from last FY end to share count date | B15: =(Valuation!$B$61-Valuation!$B$49)/365.25
A16: Projected years | B16: 3
A18: Projection | B18: Base | C18: =Model!E5 | D18: =Model!F5 | E18: =Model!G5
A19: Year index | B19: 0 | C19: 1 | D19: 2 | E19: 3
A20: Period end | C20: =Valuation!$B$49+ROUND(365.25*C19,0) | D20: =Valuation!$B$49+ROUND(365.25*D19,0) | E20: =Valuation!$B$49+ROUND(365.25*E19,0)
A21: Revenue growth | C21: =Model!E48+$B$4 | D21: =Model!F48+$B$4 | E21: =Model!G48+$B$4
A22: Revenue | B22: =Valuation!$B$50 | C22: =B22*(1+C21) | D22: =C22*(1+D21) | E22: =D22*(1+E21)
A23: EBIT margin | C23: =Model!E49+$B$5 | D23: =Model!F49+$B$5 | E23: =Model!G49+$B$5
A24: EBIT | C24: =C22*C23 | D24: =D22*D23 | E24: =E22*E23
A25: Tax rate | C25: =Model!E50 | D25: =Model!F50 | E25: =Model!G50
A26: NOPAT | C26: =C24*(1-C25) | D26: =D24*(1-D25) | E26: =E24*(1-E25)
A27: D&A | C27: =C22*(Model!E51) | D27: =D22*(Model!F51) | E27: =E22*(Model!G51)
A28: Capex | C28: =C22*(Model!E52) | D28: =D22*(Model!F52) | E28: =E22*(Model!G52)
A29: Working capital increase | C29: =(Model!E53)*(C22-B22) | D29: =(Model!F53)*(D22-C22) | E29: =(Model!G53)*(E22-D22)
A30: Stock comp | C30: =C22*(Model!E54) | D30: =D22*(Model!F54) | E30: =E22*(Model!G54)
A31: Free cash flow to firm | C31: =C26+C27-C28-C29-IF(AND(Valuation!$B$47="adjusted",Valuation!$B$48="cost"),C30*(1-C25),0) | D31: =D26+D27-D28-D29-IF(AND(Valuation!$B$47="adjusted",Valuation!$B$48="cost"),D30*(1-D25),0) | E31: =E26+E27-E28-E29-IF(AND(Valuation!$B$47="adjusted",Valuation!$B$48="cost"),E30*(1-E25),0)
A32: EBITDA | C32: =C24+C27 | D32: =D24+D27 | E32: =E24+E27
A33: Adj. EBITDA | C33: =C24+C27+C22*(Model!E58) | D33: =D24+D27+D22*(Model!F58) | E33: =E24+E27+E22*(Model!G58)
A34: Shareholder returns + other uses | C34: =C22*Model!E56+Model!E55+Model!E57 | D34: =D22*Model!F56+Model!F55+Model!F57 | E34: =E22*Model!G56+Model!G55+Model!G57
A35: Share of year after target date | C35: =IF(C19<=$B$13,0,C19-MAX(C19-1,$B$13)) | D35: =IF(D19<=$B$13,0,D19-MAX(D19-1,$B$13)) | E35: =IF(E19<=$B$13,0,E19-MAX(E19-1,$B$13))
A36: PV at target date of FCFF | C36: =IF(C35=0,0,C31*C35/(1+$B$12)^(C19-$B$13)) | D36: =IF(D35=0,0,D31*D35/(1+$B$12)^(D19-$B$13)) | E36: =IF(E35=0,0,E31*E35/(1+$B$12)^(E19-$B$13))
A37: Overlap: balance date to target date | C37: =MAX(0,MIN(C19,$B$13)-MAX(C19-1,$B$14)) | D37: =MAX(0,MIN(D19,$B$13)-MAX(D19-1,$B$14)) | E37: =MAX(0,MIN(E19,$B$13)-MAX(E19-1,$B$14))
A38: NTM weight at target date | C38: =MAX(0,MIN(C19,$B$13+1)-MAX(C19-1,$B$13)) | D38: =MAX(0,MIN(D19,$B$13+1)-MAX(D19-1,$B$13)) | E38: =MAX(0,MIN(E19,$B$13+1)-MAX(E19-1,$B$13))
A39: LTM weight at target date | B39: =MAX(0,MIN(0,$B$13)-MAX(-1,$B$13-1)) | C39: =MAX(0,MIN(C19,$B$13)-MAX(C19-1,$B$13-1)) | D39: =MAX(0,MIN(D19,$B$13)-MAX(D19-1,$B$13-1)) | E39: =MAX(0,MIN(E19,$B$13)-MAX(E19-1,$B$13-1))
A41: Value at the target date
A42: PV of free cash flow after the target date | B42: =SUM($C$36:$E$36)
A43: Terminal value at final year | B43: =IF(Valuation!$B$52="exit_multiple",Valuation!$B$54*E32,E31*(1+Valuation!$B$53)/($B$12-Valuation!$B$53))
A44: PV of terminal value at target date | B44: =B43/(1+$B$12)^($B$16-$B$13)
A45: DCF enterprise value at target date | B45: =B42+B44
A46: Terminal value share of DCF | B46: =B44/B45
A47: Free cash flow earned, balance date to target date | B47: =SUMPRODUCT($C$37:$E$37,$C$31:$E$31)
A48: Shareholder returns + other uses paid | B48: =SUMPRODUCT($C$37:$E$37,$C$34:$E$34)
A49: Interest drag on net debt | B49: =Valuation!$B$58*(1-$C$25)*MAX(Valuation!$B$56,0)*MAX($B$13-$B$14,0)
A50: Net debt at target date | B50: =IF(Valuation!$B$59="",Valuation!$B$56-B47+B49+B48,Valuation!$B$59)
A51: Minority interests | B51: =Valuation!$B$57
A52: Adjustments (probability-weighted) | B52: =0
A53: Diluted shares at target date (M) | B53: =IF(Valuation!$B$63="",Valuation!$B$60*(1+Valuation!$B$62)^MAX($B$13-$B$15,0),Valuation!$B$63)
A54: After-tax interest on target-date net debt | B54: =Valuation!$B$58*(1-$C$25)*MAX(B50,0)
A55: Check: WACC vs terminal growth | B55: =IF(AND(Valuation!$B$52<>"exit_multiple",$B$12<=Valuation!$B$53+0.01),"WACC must exceed terminal growth by 1 point","ok")
A56: Check: projection length | B56: =IF(OR($B$13>=$B$16-1,$B$13+1>$B$16),"add projected years past the target date","ok")
A58: Metric at target date | B58: Next 12 months | C58: Last 12 months
A59: Revenue | B59: =SUMPRODUCT($C$38:$E$38,$C$22:$E$22) | C59: =SUMPRODUCT($C$39:$E$39,$C$22:$E$22)+$B$39*$B$22
A60: EBIT | B60: =SUMPRODUCT($C$38:$E$38,$C$24:$E$24) | C60: =SUMPRODUCT($C$39:$E$39,$C$24:$E$24)
A61: EBITDA | B61: =SUMPRODUCT($C$38:$E$38,$C$32:$E$32) | C61: =SUMPRODUCT($C$39:$E$39,$C$32:$E$32)
A62: Adj. EBITDA | B62: =SUMPRODUCT($C$38:$E$38,$C$33:$E$33) | C62: =SUMPRODUCT($C$39:$E$39,$C$33:$E$33)
A63: NOPAT | B63: =SUMPRODUCT($C$38:$E$38,$C$26:$E$26) | C63: =SUMPRODUCT($C$39:$E$39,$C$26:$E$26)
A64: Free cash flow to firm | B64: =SUMPRODUCT($C$38:$E$38,$C$31:$E$31) | C64: =SUMPRODUCT($C$39:$E$39,$C$31:$E$31)
A66: Valuation method | B66: Metric | C66: Multiple used | D66: Basis | E66: Metric at target date | F66: Value per share | G66: Weight | H66: Metric key | I66: Metric shown (stated per-share figure when used)
A67: DCF (cash flow to target date + terminal) | F67: =((B45)-$B$50-$B$51+$B$52)/$B$53 | G67: =Valuation!$B$64
A68: ="Multiple: "&Valuation!A70&" ("&Valuation!D70&")" | B68: =Valuation!A70 | C68: =IF(B68="FCF yield",(Valuation!B70)*(1-$B$8),(Valuation!B70)+IF(B68="EV/sales",0.1,1)*$B$6) | D68: =Valuation!D70 | E68: =IF(D68="ltm",CHOOSE(H68,$C$59,$C$60,$C$61,$C$62,$C$63,$C$64),CHOOSE(H68,$B$59,$B$60,$B$61,$B$62,$B$63,$B$64)) | F68: =IF(OR(B68="EV/EBITDA",B68="EV/sales",B68="EV/EBIT"),((C68*E68)-$B$50-$B$51+$B$52)/$B$53,IF(B68="P/E",IF(Valuation!F70<>"",C68*(Valuation!F70)*(1+$B$9),C68*(E68-$B$54)/$B$53),IF(Valuation!G70<>"",(Valuation!G70)*(1+$B$9)/C68,(E68-IF(Valuation!H70,$B$54,0))/C68/$B$53))+$B$52/$B$53) | G68: =Valuation!C70 | H68: =IF(B68="EV/sales",1,IF(B68="EV/EBIT",2,IF(B68="EV/EBITDA",IF(Valuation!E70="adjusted",4,3),IF(B68="P/E",5,6)))) | I68: =IF(AND(B68="P/E",Valuation!F70<>""),(Valuation!F70)*(1+$B$9),IF(AND(B68="FCF yield",Valuation!G70<>""),(Valuation!G70)*(1+$B$9),E68))
A69: ="Multiple: "&Valuation!A71&" ("&Valuation!D71&")" | B69: =Valuation!A71 | C69: =IF(B69="FCF yield",(Valuation!B71)*(1-$B$8),(Valuation!B71)+IF(B69="EV/sales",0.1,1)*$B$6) | D69: =Valuation!D71 | E69: =IF(D69="ltm",CHOOSE(H69,$C$59,$C$60,$C$61,$C$62,$C$63,$C$64),CHOOSE(H69,$B$59,$B$60,$B$61,$B$62,$B$63,$B$64)) | F69: =IF(OR(B69="EV/EBITDA",B69="EV/sales",B69="EV/EBIT"),((C69*E69)-$B$50-$B$51+$B$52)/$B$53,IF(B69="P/E",IF(Valuation!F71<>"",C69*(Valuation!F71)*(1+$B$9),C69*(E69-$B$54)/$B$53),IF(Valuation!G71<>"",(Valuation!G71)*(1+$B$9)/C69,(E69-IF(Valuation!H71,$B$54,0))/C69/$B$53))+$B$52/$B$53) | G69: =Valuation!C71 | H69: =IF(B69="EV/sales",1,IF(B69="EV/EBIT",2,IF(B69="EV/EBITDA",IF(Valuation!E71="adjusted",4,3),IF(B69="P/E",5,6)))) | I69: =IF(AND(B69="P/E",Valuation!F71<>""),(Valuation!F71)*(1+$B$9),IF(AND(B69="FCF yield",Valuation!G71<>""),(Valuation!G71)*(1+$B$9),E69))
A70: Value per share at target date (weighted methods) | F70: =SUMPRODUCT(F67:F69,G67:G69)/SUM(G67:G69)

Sheet Calc - bull
A1: BKNG engine calculation: bull scenario
A2: Machinery behind the Valuation and Distribution tabs; drivers come from Model, assumptions from Valuation.
A4: Scenario Growth Δ | B4: =N(Valuation!C85)
A5: Scenario Margin Δ | B5: =N(Valuation!D85)
A6: Scenario Multiple Δ (turns) | B6: =N(Valuation!E85)
A7: Scenario WACC Δ | B7: =N(Valuation!F85)
A8: Scenario Multiple %Δ | B8: =N(Valuation!G85)
A9: Scenario Stated EPS/FCF %Δ | B9: =N(Valuation!H85)
A10: Scenario Custom %Δ | B10: =N(Valuation!I85)
A12: WACC | B12: =Valuation!$B$51+B7
A13: Years from last FY end to target date | B13: =(Valuation!$B$45-Valuation!$B$49)/365.25
A14: Years from last FY end to balance date | B14: =(Valuation!$B$55-Valuation!$B$49)/365.25
A15: Years from last FY end to share count date | B15: =(Valuation!$B$61-Valuation!$B$49)/365.25
A16: Projected years | B16: 3
A18: Projection | B18: Base | C18: =Model!E5 | D18: =Model!F5 | E18: =Model!G5
A19: Year index | B19: 0 | C19: 1 | D19: 2 | E19: 3
A20: Period end | C20: =Valuation!$B$49+ROUND(365.25*C19,0) | D20: =Valuation!$B$49+ROUND(365.25*D19,0) | E20: =Valuation!$B$49+ROUND(365.25*E19,0)
A21: Revenue growth | C21: =Model!E48+$B$4+$B$250 | D21: =Model!F48+$B$4 | E21: =Model!G48+$B$4
A22: Revenue | B22: =Valuation!$B$50 | C22: =B22*(1+C21) | D22: =C22*(1+D21) | E22: =D22*(1+E21)
A23: EBIT margin | C23: =Model!E49+$B$5+$B$251 | D23: =Model!F49+$B$5+$B$252 | E23: =Model!G49+$B$5+$B$253
A24: EBIT | C24: =C22*C23 | D24: =D22*D23 | E24: =E22*E23
A25: Tax rate | C25: =Model!E50 | D25: =Model!F50 | E25: =Model!G50
A26: NOPAT | C26: =C24*(1-C25) | D26: =D24*(1-D25) | E26: =E24*(1-E25)
A27: D&A | C27: =C22*(Model!E51) | D27: =D22*(Model!F51) | E27: =E22*(Model!G51)
A28: Capex | C28: =C22*(Model!E52) | D28: =D22*(Model!F52) | E28: =E22*(Model!G52)
A29: Working capital increase | C29: =(Model!E53)*(C22-B22) | D29: =(Model!F53)*(D22-C22) | E29: =(Model!G53)*(E22-D22)
A30: Stock comp | C30: =C22*(Model!E54) | D30: =D22*(Model!F54) | E30: =E22*(Model!G54)
A31: Free cash flow to firm | C31: =C26+C27-C28-C29-IF(AND(Valuation!$B$47="adjusted",Valuation!$B$48="cost"),C30*(1-C25),0) | D31: =D26+D27-D28-D29-IF(AND(Valuation!$B$47="adjusted",Valuation!$B$48="cost"),D30*(1-D25),0) | E31: =E26+E27-E28-E29-IF(AND(Valuation!$B$47="adjusted",Valuation!$B$48="cost"),E30*(1-E25),0)
A32: EBITDA | C32: =C24+C27 | D32: =D24+D27 | E32: =E24+E27
A33: Adj. EBITDA | C33: =C24+C27+C22*(Model!E58) | D33: =D24+D27+D22*(Model!F58) | E33: =E24+E27+E22*(Model!G58)
A34: Shareholder returns + other uses | C34: =C22*Model!E56+Model!E55+Model!E57 | D34: =D22*Model!F56+Model!F55+Model!F57 | E34: =E22*Model!G56+Model!G55+Model!G57
A35: Share of year after target date | C35: =IF(C19<=$B$13,0,C19-MAX(C19-1,$B$13)) | D35: =IF(D19<=$B$13,0,D19-MAX(D19-1,$B$13)) | E35: =IF(E19<=$B$13,0,E19-MAX(E19-1,$B$13))
A36: PV at target date of FCFF | C36: =IF(C35=0,0,C31*C35/(1+$B$12)^(C19-$B$13)) | D36: =IF(D35=0,0,D31*D35/(1+$B$12)^(D19-$B$13)) | E36: =IF(E35=0,0,E31*E35/(1+$B$12)^(E19-$B$13))
A37: Overlap: balance date to target date | C37: =MAX(0,MIN(C19,$B$13)-MAX(C19-1,$B$14)) | D37: =MAX(0,MIN(D19,$B$13)-MAX(D19-1,$B$14)) | E37: =MAX(0,MIN(E19,$B$13)-MAX(E19-1,$B$14))
A38: NTM weight at target date | C38: =MAX(0,MIN(C19,$B$13+1)-MAX(C19-1,$B$13)) | D38: =MAX(0,MIN(D19,$B$13+1)-MAX(D19-1,$B$13)) | E38: =MAX(0,MIN(E19,$B$13+1)-MAX(E19-1,$B$13))
A39: LTM weight at target date | B39: =MAX(0,MIN(0,$B$13)-MAX(-1,$B$13-1)) | C39: =MAX(0,MIN(C19,$B$13)-MAX(C19-1,$B$13-1)) | D39: =MAX(0,MIN(D19,$B$13)-MAX(D19-1,$B$13-1)) | E39: =MAX(0,MIN(E19,$B$13)-MAX(E19-1,$B$13-1))
A41: Value at the target date
A42: PV of free cash flow after the target date | B42: =SUM($C$36:$E$36)
A43: Terminal value at final year | B43: =IF(Valuation!$B$52="exit_multiple",Valuation!$B$54*E32,E31*(1+Valuation!$B$53)/($B$12-Valuation!$B$53))
A44: PV of terminal value at target date | B44: =B43/(1+$B$12)^($B$16-$B$13)
A45: DCF enterprise value at target date | B45: =B42+B44
A46: Terminal value share of DCF | B46: =B44/B45
A47: Free cash flow earned, balance date to target date | B47: =SUMPRODUCT($C$37:$E$37,$C$31:$E$31)
A48: Shareholder returns + other uses paid | B48: =SUMPRODUCT($C$37:$E$37,$C$34:$E$34)
A49: Interest drag on net debt | B49: =Valuation!$B$58*(1-$C$25)*MAX(Valuation!$B$56,0)*MAX($B$13-$B$14,0)
A50: Net debt at target date | B50: =IF(Valuation!$B$59="",Valuation!$B$56-B47+B49+B48,Valuation!$B$59)
A51: Minority interests | B51: =Valuation!$B$57
A52: Adjustments (probability-weighted) | B52: =0
A53: Diluted shares at target date (M) | B53: =IF(Valuation!$B$63="",Valuation!$B$60*(1+Valuation!$B$62)^MAX($B$13-$B$15,0),Valuation!$B$63)
A54: After-tax interest on target-date net debt | B54: =Valuation!$B$58*(1-$C$25)*MAX(B50,0)
A55: Check: WACC vs terminal growth | B55: =IF(AND(Valuation!$B$52<>"exit_multiple",$B$12<=Valuation!$B$53+0.01),"WACC must exceed terminal growth by 1 point","ok")
A56: Check: projection length | B56: =IF(OR($B$13>=$B$16-1,$B$13+1>$B$16),"add projected years past the target date","ok")
A58: Metric at target date | B58: Next 12 months | C58: Last 12 months
A59: Revenue | B59: =SUMPRODUCT($C$38:$E$38,$C$22:$E$22) | C59: =SUMPRODUCT($C$39:$E$39,$C$22:$E$22)+$B$39*$B$22
A60: EBIT | B60: =SUMPRODUCT($C$38:$E$38,$C$24:$E$24) | C60: =SUMPRODUCT($C$39:$E$39,$C$24:$E$24)
A61: EBITDA | B61: =SUMPRODUCT($C$38:$E$38,$C$32:$E$32) | C61: =SUMPRODUCT($C$39:$E$39,$C$32:$E$32)
A62: Adj. EBITDA | B62: =SUMPRODUCT($C$38:$E$38,$C$33:$E$33) | C62: =SUMPRODUCT($C$39:$E$39,$C$33:$E$33)
A63: NOPAT | B63: =SUMPRODUCT($C$38:$E$38,$C$26:$E$26) | C63: =SUMPRODUCT($C$39:$E$39,$C$26:$E$26)
A64: Free cash flow to firm | B64: =SUMPRODUCT($C$38:$E$38,$C$31:$E$31) | C64: =SUMPRODUCT($C$39:$E$39,$C$31:$E$31)
A66: Valuation method | B66: Metric | C66: Multiple used | D66: Basis | E66: Metric at target date | F66: Value per share | G66: Weight | H66: Metric key | I66: Metric shown (stated per-share figure when used)
A67: DCF (cash flow to target date + terminal) | F67: =((B45)-$B$50-$B$51+$B$52)/$B$53 | G67: =Valuation!$B$64
A68: ="Multiple: "&Valuation!A70&" ("&Valuation!D70&")" | B68: =Valuation!A70 | C68: =IF(B68="FCF yield",(Valuation!B70)*(1-$B$8),(Valuation!B70)+IF(B68="EV/sales",0.1,1)*$B$6) | D68: =Valuation!D70 | E68: =IF(D68="ltm",CHOOSE(H68,$C$59,$C$60,$C$61,$C$62,$C$63,$C$64),CHOOSE(H68,$B$59,$B$60,$B$61,$B$62,$B$63,$B$64)) | F68: =IF(OR(B68="EV/EBITDA",B68="EV/sales",B68="EV/EBIT"),((C68*E68)-$B$50-$B$51+$B$52)/$B$53,IF(B68="P/E",IF(Valuation!F70<>"",C68*(Valuation!F70+$B$254)*(1+$B$9),C68*(E68-$B$54)/$B$53),IF(Valuation!G70<>"",(Valuation!G70)*(1+$B$9)/C68,(E68-IF(Valuation!H70,$B$54,0))/C68/$B$53))+$B$52/$B$53) | G68: =Valuation!C70 | H68: =IF(B68="EV/sales",1,IF(B68="EV/EBIT",2,IF(B68="EV/EBITDA",IF(Valuation!E70="adjusted",4,3),IF(B68="P/E",5,6)))) | I68: =IF(AND(B68="P/E",Valuation!F70<>""),(Valuation!F70+$B$254)*(1+$B$9),IF(AND(B68="FCF yield",Valuation!G70<>""),(Valuation!G70)*(1+$B$9),E68))
A69: ="Multiple: "&Valuation!A71&" ("&Valuation!D71&")" | B69: =Valuation!A71 | C69: =IF(B69="FCF yield",(Valuation!B71)*(1-$B$8),(Valuation!B71)+IF(B69="EV/sales",0.1,1)*$B$6) | D69: =Valuation!D71 | E69: =IF(D69="ltm",CHOOSE(H69,$C$59,$C$60,$C$61,$C$62,$C$63,$C$64),CHOOSE(H69,$B$59,$B$60,$B$61,$B$62,$B$63,$B$64)) | F69: =IF(OR(B69="EV/EBITDA",B69="EV/sales",B69="EV/EBIT"),((C69*E69)-$B$50-$B$51+$B$52)/$B$53,IF(B69="P/E",IF(Valuation!F71<>"",C69*(Valuation!F71)*(1+$B$9),C69*(E69-$B$54)/$B$53),IF(Valuation!G71<>"",(Valuation!G71+$B$255)*(1+$B$9)/C69,(E69-IF(Valuation!H71,$B$54,0))/C69/$B$53))+$B$52/$B$53) | G69: =Valuation!C71 | H69: =IF(B69="EV/sales",1,IF(B69="EV/EBIT",2,IF(B69="EV/EBITDA",IF(Valuation!E71="adjusted",4,3),IF(B69="P/E",5,6)))) | I69: =IF(AND(B69="P/E",Valuation!F71<>""),(Valuation!F71)*(1+$B$9),IF(AND(B69="FCF yield",Valuation!G71<>""),(Valuation!G71+$B$255)*(1+$B$9),E69))
A70: Value per share at target date (weighted methods) | F70: =SUMPRODUCT(F67:F69,G67:G69)/SUM(G67:G69)
A249: Driver scenario shifts: line-item changes model_drivers.py resolves from this scenario's driver deltas (added to the Model tab inputs)
A250: Revenue growth, year 1 | B250: 0.016165666
A251: EBIT margin, year 1 | B251: 0.004
A252: EBIT margin, year 2 | B252: 0.004
A253: EBIT margin, year 3 | B253: 0.004
A254: Stated EPS, multiple 1 | B254: 0.34594696
A255: Stated FCF/share, multiple 2 | B255: 0.41303245

Sheet Agents
A1: BKNG: each forecaster's own assumption set through the same engine (from model_engine.json, not live)
A3: Set | B3: Research target (12m) | C3: Median | D3: 25th pct | E3: 75th pct | F3: WACC | G3: Y1 growth | H3: Y1 margin | I3: Terminal growth | J3: DCF weight | K3: Years | L3: Multiples | M3: Supervisor's note
A4: supervisor | B4: 183.28519 | C4: 170.23954 | D4: 128.3913 | E4: 218.65608 | F4: 0.0864 | G4: 0.077711093 | H4: 0.32468049 | I4: 0.03 | J4: 0 | K4: 3 | L4: P/E 13.32 (ntm); FCF yield 0.08 (ntm)
A5: agent_1 | M5: engine error: no model_inputs found
A6: agent_2 | M6: engine error: no model_inputs found
A7: agent_3 | M7: engine error: no model_inputs found
A8: agent_4 | M8: engine error: no model_inputs found
A9: agent_5 | M9: engine error: no model_inputs found

Sheet Sources
A1: BKNG: where each input comes from (source numbers point to the list below; F ids to the SEC fact table)
A3: Input | B3: Value | C3: Basis | D3: Sources | E3: SEC fact ids | F3: Derivation
A4: Base revenue FY2025 | B4: $26,917M | C4: reported | E4: F3 | F4: filled in (not stated in this set's original work): FY2025 us-gaap:Revenues from the 10-K (fact pack F3).
A5: FY2026 revenue growth | B5: driver-determined: rn x gbrn x take (drivers) | C5: driver | D5: 1 | F5: Now computed from drivers (rn, gbrn, take, mkt, opex, sh), each cited to the FY2025 10-K / Q2 2026 10-Q in drivers[]. Old: The supervisor did not settle revenue growth, so this is the forecasters' median of their backfilled sets (1: 0.08, 2: 0.08, 3: 0.08, 4: 0.08, 5: 0.08). The supervisor's key drivers cite the FY26 guide (low-to-mid-teens EPS growth) and a Q3 bookings guide of +5-7% CC in line with Expedia.
A6: FY2027 revenue growth | B6: driver-determined: rn x gbrn x take (drivers) | C6: driver | D6: 1, 3, 4 | F6: Now computed from drivers (rn, gbrn, take, mkt, opex, sh), each cited to the FY2025 10-K / Q2 2026 10-Q in drivers[]. Old: The supervisor did not settle revenue growth, so this is the forecasters' median of their backfilled sets (1: 0.075, 2: 0.08, 3: 0.065, 4: 0.08, 5: 0.08). The supervisor's key drivers cite the FY26 guide (low-to-mid-teens EPS growth) and a Q3 bookings guide of +5-7% CC in line with Expedia.
A7: FY2028 revenue growth | B7: driver-determined: rn x gbrn x take (drivers) | C7: driver | D7: 1 | F7: Now computed from drivers (rn, gbrn, take, mkt, opex, sh), each cited to the FY2025 10-K / Q2 2026 10-Q in drivers[]. Old: The supervisor did not settle revenue growth, so this is the forecasters' median of their backfilled sets (1: 0.075, 2: 0.075, 3: 0.05, 4: 0.06, 5: 0.075). The supervisor's key drivers cite the FY26 guide (low-to-mid-teens EPS growth) and a Q3 bookings guide of +5-7% CC in line with Expedia.
A8: EBIT margin (GAAP, after SBC), all years | B8: driver-determined: 1 - mkt/take - opex - 0.0246 (FY2025 impairment 457 + transformation 205 / 26,917, 10-K) | C8: driver | D8: 2 | E8: F13, F6 | F8: Now computed from drivers (rn, gbrn, take, mkt, opex, sh), each cited to the FY2025 10-K / Q2 2026 10-Q in drivers[]. Old: filled in (not stated in this set's original work): TTM GAAP operating income to 2026-06-30 / TTM revenue = 9,284 / 28,241 = 32.9%, held flat. No forecaster or the supervisor states a margin path; the forecasters' sets all hold it flat.
A9: Tax rate | B9: 0.224 | C9: reported | D9: 2 | E9: F74, F81 | F9: filled in (not stated in this set's original work): TTM income tax / TTM pretax income to 2026-06-30 = 2,082 / 9,291 = 22.4% (FY2025 was 1,428 / 6,832 = 20.9%, F71/F78).
A10: D&A % revenue | B10: 0.02 | C10: reported | D10: 2 | E10: F32, F6 | F10: filled in (not stated in this set's original work): TTM D&A / TTM revenue = 571 / 28,241 = 2.0%.
A11: Capex % revenue | B11: 0.0113 | C11: reported | D11: 2 | E11: F46, F6 | F11: filled in (not stated in this set's original work): TTM capex / TTM revenue = 320 / 28,241 = 1.13%.
A12: Working capital % of revenue increase | B12: 0.0 | C12: judgment | F12: filled in (not stated in this set's original work): the fact pack has no working-capital tags. Agents 1 and 3 cite the deferred-merchant-bookings swing ($10.1B at Q2 vs $5.3B at year-end; $4.2B H1 inflow), which is seasonal, so no annual float is assumed (conservative for the diagnostic DCF).
A13: SBC % revenue | B13: 0.020 | C13: reported | D13: 2 | E13: F6 | F13: Supervisor: '10-Q (SBC $281M H1)'; reported SBC ~$0.56-0.6B/yr. H1 2026 SBC $281M (10-Q) annualised = $562M / TTM revenue 28,241 = 2.0%. Not deducted again: EBIT is GAAP after SBC.
A14: Shareholder returns per year | B14: $10,000M | C14: estimate | D14: 1, 2 | E14: F60 | F14: The supervisor did not settle the cash amount (its key drivers give ~6%/yr net shrink, 44M retired in H1, $14.5B authorization), so this is the forecasters' median: agents 1-4 state ~$10B FCF less ~$1.3B dividends, all returned (dividends TTM $1,281M, F60).
A15: Terminal growth (Gordon) | B15: 0.03 | C15: judgment | F15: filled in (not stated in this set's original work): no terminal growth is stated in this run's work. Taken from the low end of the 3-5% long-run FCF growth the share price implies, a figure agent_1 cites (its source 14, Quality Stocks Substack, 2026-09-14). The low end is used because a perpetual rate above ~3% nominal is hard to defend.
A16: WACC | B16: 0.0864 | C16: estimate | E16: F89, F67, F88 | F16: filled in (not stated in this set's original work): cost of equity 0.0875 = T-bill 0.0420 + beta 0.91 x 5% (the price target's market leg, 2026-10-02); after-tax debt 0.0550 x (1 - 0.224) on net debt and minorities 2,966 vs equity 119,488 (751.40M x $159.02) -> WACC 0.0864
A17: Net debt at balance date | B17: $2,966M (2026-06-30) | C17: reported | D17: 2 | E17: F89, F88, F83 | F17: Supervisor fair-value reason: 'no net-debt double count'. Net debt is ~$3B at Q2 and seasonally flattered (agents). Fact pack: 20,180 - 17,214 = 2,966 (F89).
A18: Net debt at horizon | B18: $2,966M | C18: estimate | D18: 1, 2 | E18: F89 | F18: filled in (not stated in this set's original work): held at today's level. The agents state that ~$10B of FCF is returned in full (~$1.3B dividends plus buybacks), so net debt stays roughly flat. Q2 net debt is seasonally flattered by merchant float (~$1.5B at YE25, per agents 1 and 3). This affects only the zero-weight DCF leg.
A19: Interest rate on net debt | B19: 0.055 | C19: reported | D19: 2 | E19: F67, F88 | F19: filled in (not stated in this set's original work): TTM interest expense / total debt = 1,103 / 20,180 = 5.5%.
A20: Minorities | B20: 0 | C20: reported | D20: 2 | F20: filled in (not stated in this set's original work): no noncontrolling interest in the fact pack or in any agent file.
A21: Shares now | B21: 751.4M at 2026-07-27 | C21: reported | D21: 2 | E21: F87 | F21: 10-Q cover count, the base every agent uses (Q2 diluted weighted average was 770M, F26; the agents treat that figure as lagging).
A22: Annual share change | B22: -0.06 | C22: estimate | D22: 2, 1 | F22: Supervisor key drivers: '~6%/yr net shrink' from 751.4M on Jul 27, 2026.
A23: Shares at horizon (Oct 2027) | B23: driver-determined: interpolated from driver sh | C23: driver | D23: 2, 1 | E23: F87 | F23: Now computed from drivers (rn, gbrn, take, mkt, opex, sh), each cited to the FY2025 10-K / Q2 2026 10-Q in drivers[]. Old: Supervisor cross-check: '~708M shares' at Oct 2027 (the agents' range was 705-715M).
A24: NTM adj EPS at Oct 2027 (P/E leg eps) | B24: driver-determined: driver_build.set expression (see driver_build.note) | C24: driver | D24: 10, 1 | F24: Now computed from drivers (rn, gbrn, take, mkt, opex, sh), each cited to the FY2025 10-K / Q2 2026 10-Q in drivers[]. Old: Supervisor cross-check '~$13.1 NTM EPS at Oct 2027' (FY27 consensus $12.37 less a 2.5-5% haircut, mean ~3.7%; FY28 ~+12.5-13%). Agents' range is $12.75-13.25.
A25: FY2027 consensus adj EPS | B25: $12.37 | C25: consensus | D25: 10 | F25: StockAnalysis, Sep 24, 2026. The supervisor's Oct 2 re-check could not re-confirm the FY27 row (immaterial).
A26: FY2027 haircut to consensus | B26: 2.5-5% (mean ~3.7%) | C26: judgment | D26: 1, 3, 4 | F26: Supervisor disagreement resolution: a 2.5-5% range is defensible; the mean stands.
A27: EXPE consensus EPS FY2026 / FY2027 | B27: $17.35 (8 est.) / $20.47 (10 est.) | C27: consensus | D27: 12, 21 | F27: Nasdaq.com earnings forecast (Zacks consensus), yearly rows; snapshot data/estimates/EXPE.json retrieved 2026-10-26. Basis: Zacks's EXPE EPS is Expedia's adjusted EPS with SBC expensed, not the company's adjusted figure: Zacks Q4-25 $3.10 vs company adjusted $3.78 and GAAP $1.60; $3.78 less after-tax SBC 105 x (1 - 0.21) / 126.394M = $0.66 gives $3.12, within $0.02 of Zacks. So this consensus is already on BKNG's basis (adjusted, SBC in costs) and needs no restatement.
A28: ABNB consensus EPS FY2026 / FY2027 | B28: $5.29 (14 est.) / $6.30 (15 est.) | C28: consensus | D28: 13, 23, 25 | F28: Nasdaq.com earnings forecast (Zacks consensus), yearly rows; snapshot data/estimates/ABNB.json retrieved 2026-10-26. Basis: GAAP. Zacks's Q2-26 actual $1.37 = GAAP $816M / 597.0M diluted shares (10-Q). Airbnb publishes no adjusted EPS, so GAAP is its only earnings measure; SBC is in costs as for BKNG, and the items BKNG's adjusted EPS removes (acquired-intangible amortisation, impairments, debt FX remeasurement, convertible marks) are not material for Airbnb, so GAAP is the nearest available match to BKNG's basis. ABNB is the high outlier and does not set the median either way (EXPE and Amadeus alone give 14.66x). Evidence that GAAP is close to BKNG's basis for Airbnb: in FY2025 the item types BKNG's adjusted EPS removes were small at Airbnb (impairments $30M = 1.2% of net income; other non-operating $112M = 4.5%; no goodwill or intangible impairment; 10-K XBRL, source 25), so Airbnb's GAAP EPS would sit at most ~6% from an adjusted figure, while ABNB's EPS would have to be ~90% higher to change the median.
A29: BKNG consensus adj EPS FY2026 / FY2027 | B29: $10.48 (16 est.) / $12.36 (16 est.) | C29: consensus | D29: 15, 22 | F29: Nasdaq.com earnings forecast (Zacks consensus), yearly rows; snapshot data/estimates/BKNG.json retrieved 2026-10-26. Basis: company adjusted EPS (SBC stays in costs): Zacks Q4-25 $1.95 = adjusted $48.80 / 25 (GAAP would be $1.77).
A30: Zacks reported EPS actual, EXPE Q4-25 (consensus basis check) | B30: $3.10 | C30: reported | D30: 21 | F30: Nasdaq.com earnings-surprise table: the actual Zacks records for the quarter (aggregator; Zacks keeps its consensus on the same basis). Used only to identify the consensus EPS basis against the company's own figures.
A31: Zacks reported EPS actual, BKNG Q4-25 (consensus basis check) | B31: $1.95 | C31: reported | D31: 22 | F31: Nasdaq.com earnings-surprise table: the actual Zacks records for the quarter (aggregator; Zacks keeps its consensus on the same basis). Used only to identify the consensus EPS basis against the company's own figures.
A32: Zacks reported EPS actual, ABNB Q2-26 (consensus basis check) | B32: $1.37 | C32: reported | D32: 23 | F32: Nasdaq.com earnings-surprise table: the actual Zacks records for the quarter (aggregator; Zacks keeps its consensus on the same basis). Used only to identify the consensus EPS basis against the company's own figures.
A33: ABNB FY2025 items of the kinds BKNG adjusts out | B33: net income $2,511M; goodwill, intangible and long-lived asset impairment $0; equity-security impairment $30M (1.2% of net income); other non-operating expense $112M (4.5%) | C33: reported | D33: 25 | F33: Airbnb FY2025 10-K XBRL (accession 0001559720-26-000004): GoodwillImpairmentLoss 0, ImpairmentOfIntangibleAssetsExcludingGoodwill 0, ImpairmentOfLongLivedAssetsHeldForUse 0, EquitySecuritiesWithoutReadilyDeterminableFairValueImpairmentLossAnnualAmount 30, OtherNonoperatingIncomeExpense -112, NetIncomeLoss 2,511 ($M); 30 / 2,511 = 1.2%, 112 / 2,511 = 4.5%.
A34: EXPE Q4 2025 EPS: adjusted / GAAP / SBC | B34: $3.78 adjusted; $1.60 GAAP diluted; SBC $105M ($0.82/sh); adjusted shares 126,394k | C34: reported | D34: 18 | F34: Expedia Q4/FY2025 release (8-K Ex.99.1), adjusted net income reconciliation, three months ended 2025-12-31.
A35: BKNG Q4 2025 adjusted EPS (pre-split) | B35: $48.80 pre-split = $1.952 post 25-for-1 split (2026-04-02) | C35: reported | D35: 19, 2 | F35: Booking Q4/FY2025 release (8-K Ex.99.1, 2026-02-18) adjusted EPS $48.80 (GAAP $44.22); split 25-for-1 effective 2026-04-02 (Q2 2026 10-Q equity note); 48.80 / 25 = 1.952.
... A39: BKNG adjusted EPS treatment of SBC | B39: no stock-based compensation add-back (FY2025 SBC $613M in personnel expense) | C39: reported | D39: 19 | F39: Booking Q4/FY2025 earnings release (8-K Ex.99.1), net income to adjusted net income reconciliation (items a-m) and income statement footnote.
A40: EXPE price 2026-10-23 close | B40: 289.01 | C40: reported | D40: 20 | E40: EXPE.price | F40: peers.py table (Yahoo chart feed last close).
A41: ABNB price 2026-10-23 close | B41: 172.01 | C41: reported | D41: 20 | E41: ABNB.price | F41: peers.py table (Yahoo chart feed last close).
A42: BKNG price 2026-10-23 close | B42: 155.83 | C42: reported | D42: 20 | F42: Yahoo chart feed, https://query1.finance.yahoo.com/v8/finance/chart/BKNG?range=5d&interval=1d, regularMarketPrice.
A43: Peer EXPE NTM P/E (Zacks basis, SBC expensed) | B43: 14.54x | C43: estimate | D43: 12, 21, 18, 20 | E43: EXPE.price | F43: Price $289.01 (2026-10-23 close, peers.py EXPE.price). Zacks consensus EPS FY26 $17.35, FY27 $20.47; calendar NTM from the 2026-10-23 close = 0.189 x FY2026 + 0.811 x FY2027 = $19.88 -> 14.54x. Zacks's EXPE basis is adjusted EPS with SBC expensed (see 'EXPE consensus EPS' and the Q4-25 basis check), the same as BKNG's adjusted EPS, so no restatement. Gate fix 2026-10-26: an earlier version restated this to 17.19x by deducting SBC a second time.
A44: Peer Amadeus (AMS.MC) NTM P/E (adjusted basis) | B44: 14.78x | C44: estimate | D44: 16, 17 | F44: Home listing (BME, EUR; the AMADY ADR has no Nasdaq consensus rows). Price EUR 56.60 (2026-10-23 close, MarketScreener). MarketScreener consensus EPS 2026e EUR 3.257, 2027e EUR 3.683 (22 analysts); calendar NTM from the 2026-10-23 close = 0.189 x FY2026 + 0.811 x FY2027 (69 of 365 days left in FY2026) = EUR 3.6025 -> 15.71x. MarketScreener's EPS is Amadeus's reported (IFRS) basis: its 2025 figure 3.01 equals reported diluted EPS in the FY2025 release, where adjusted diluted EPS is 3.20 (adjusted profit excludes items such as purchase-price amortisation, as BKNG's adjusted EPS excludes intangibles amortisation; neither adds back SBC, so adjusted is BKNG's basis). Restated with the FY25 ratio 3.20 / 3.01 = 1.0631: EUR 3.8299 -> 56.60 / 3.8299 = 14.78x.
A45: Peer ABNB NTM P/E | B45: 28.16x | C45: estimate | D45: 13, 20, 25 | E45: ABNB.price | F45: Price $172.01 (2026-10-23 close, peers.py ABNB.price). Zacks consensus EPS FY26 $5.29, FY27 $6.30; calendar NTM from the 2026-10-23 close = 0.189 x FY2026 + 0.811 x FY2027 (69 of 365 days left in FY2026) = $6.1091 -> 28.16x. Basis GAAP (see 'ABNB consensus EPS'): Airbnb has no adjusted EPS; SBC in costs as for BKNG.
A46: BKNG own NTM P/E (same basis) | B46: 12.98x | C46: estimate | D46: 15, 20 | F46: Price $155.83 (2026-10-23 close). Zacks consensus adj EPS FY26 $10.48, FY27 $12.36; calendar NTM from the 2026-10-23 close = 0.189 x FY2026 + 0.811 x FY2027 (69 of 365 days left in FY2026) = $12.0046 -> 12.98x.
A47: NTM P/E | B47: 13.32x | C47: estimate | D47: 12, 13, 16, 25 | F47: Exit-multiple rule (Kilian card 2026-10-26 12:16Z; METHOD.md Peer comparables): exit = peer median x (own NTM multiple / peer median)^k, k = 0.8. Peer median 14.78x (unchanged, gated 2026-10-26: see the rest of this derivation). Own multiple 12.98x on the peers' basis: BKNG $155.83 / calendar-NTM Zacks adj EPS $12.0046 = 12.98x (row 'BKNG own NTM P/E (same basis)'). Exit = 14.78 x (12.98 / 14.78)^0.8 = 14.78 x 0.9013 = 13.32x (was 14.78x). The FCF-yield leg (8%, today's TTM yield) already sits at BKNG's own level and has no peer median; unchanged. PREVIOUS DERIVATION: Median of the approved OTA/travel-tech set (Kilian 2026-10-26 06:07Z; card 06:20Z 'peer median') on BKNG's EPS basis (adjusted, SBC in costs), calendar NTM at the 2026-10-23 close: EXPE 14.54x, Amadeus 14.78x, ABNB 28.16x -> median 14.78x. Set at the median: no persistence case on evidence for BKNG's own 12.98x discount. Old: 14.25x (supervisor's 14-14.5x, own trading level, no peer basis). UBER is out of the set: mobility and delivery, and its consensus is GAAP including investment marks and tax one-offs (Zacks Q3-25 $3.11 vs $0.67 consensus), so it is not on BKNG's basis. ABNB is on GAAP, which sits within ~6% of an adjusted figure for Airbnb (FY2025 10-K: impairments 1.2%, other non-operating 4.5% of net income; see 'ABNB FY2025 items'), so the median is on one basis in substance; ABNB is the high outlier and does not set it.
A48: FCF per share NTM at Oct 2027 (FCF leg) | B48: driver-determined: driver_build.set expression | C48: driver | D48: 1, 2 | F48: Now computed from drivers (rn, gbrn, take, mkt, opex, sh), each cited to the FY2025 10-K / Q2 2026 10-Q in drivers[]. Old: Supervisor: '~$11.2B NTM FCF / ~708M shares = ~$15.8'.
A49: NTM FCF at Oct 2027 | B49: driver-determined: adj NI x 1.2225 from drivers | C49: driver | D49: 1 | E49: F91 | F49: Now computed from drivers (rn, gbrn, take, mkt, opex, sh), each cited to the FY2025 10-K / Q2 2026 10-Q in drivers[]. Old: Supervisor cross-check, between agent 1's $11.4B and agents 2/4 ($11.0B / $10.75B); TTM FCF to Q2 2026 is $9,539M (F91).
A50: FCF yield | B50: 8% | C50: judgment | D50: 1, 2 | F50: Supervisor: '~8% on ~$16 FCF/share'; today's TTM yield, no re-rating.
A51: Leg weights | B51: P/E 0.6, FCF yield 0.4, DCF 0 | C51: judgment | F51: Supervisor fair_value.reason: 'a 60/40 blend gives ~$191' (P/E / FCF yield); no DCF in the original work.
A52: Scenario bear | B52: price $115, prob 0.25, deltas {"eps_pct": -0.1221, "multiple": -4.25, "multiple_pct": -0.5076} | C52: judgment | D52: 10, 1, 11 | F52: Scenario price and probability are the forecasters' median of their own scenarios (the supervisor set none); story EPS and multiple are the forecasters' medians too. P/E leg: NTM EPS $11.5 (eps_pct vs $13.1) x 10.0x (multiple delta vs 14.25x) = $115.0. The FCF-yield leg is scaled by eps_pct and its yield moved by multiple_pct so the blend lands on the stated $115 (FCF leg $115.0); the story gives no separate FCF-yield figure. Peer refresh 2026-10-26: the multiple delta -4.25x is kept as argued in x-turns and now applies to the 14.78x base multiple (P/E leg multiple 10.53x); the forecasters' stated scenario prices above are their own, at the old 14.25x base.
A53: Scenario base | B53: price $183, prob 0.5, deltas {"multiple": -0.25, "multiple_pct": -0.0828} | C53: judgment | D53: 10, 1, 11 | F53: Scenario price and probability are the forecasters' median of their own scenarios (the supervisor set none); story EPS and multiple are the forecasters' medians too. P/E leg: NTM EPS $13.1 (eps_pct vs $13.1) x 14.0x (multiple delta vs 14.25x) = $183.4. The FCF-yield leg is scaled by eps_pct and its yield moved by multiple_pct so the blend lands on the stated $183 (FCF leg $182.4); the story gives no separate FCF-yield figure. Peer refresh 2026-10-26: the multiple delta -0.25x is kept as argued in x-turns and now applies to the 14.78x base multiple (P/E leg multiple 14.53x); the forecasters' stated scenario prices above are their own, at the old 14.25x base.
A54: Scenario bull | B54: price $238, prob 0.25, deltas {"eps_pct": 0.0267, "multiple": 3.25, "multiple_pct": 0.1619} | C54: judgment | D54: 10, 1, 11 | F54: Scenario price and probability are the forecasters' median of their own scenarios (the supervisor set none); story EPS and multiple are the forecasters' medians too. P/E leg: NTM EPS $13.45 (eps_pct vs $13.1) x 17.5x (multiple delta vs 14.25x) = $235.4. The FCF-yield leg is scaled by eps_pct and its yield moved by multiple_pct so the blend lands on the stated $238 (FCF leg $241.9); the story gives no separate FCF-yield figure. Peer refresh 2026-10-26: the multiple delta +3.25x is kept as argued in x-turns and now applies to the 14.78x base multiple (P/E leg multiple 18.03x); the forecasters' stated scenario prices above are their own, at the old 14.25x base.
A55: scenario_vol (within-scenario spread) | B55: 0.275 | C55: judgment | D55: 10, 1, 11 | F55: Supervisor: the stock's vol is ~37-39% (sizing reason; its ladder is the agents' mean, median ~$174), so 0.38 is taken as the total. The scenarios and spread are the forecasters' median because the supervisor did not set its own. Between-scenario log spread of the stated prices = 0.262; within = sqrt(total^2 - between^2) = 0.275.
A56: driver:rn | B56: Room nights reserved (all brands): 1,235 -> 1,294/1,359/1,427 (estimate) | C56: estimate | F56: FY26 = H1 662 (10-Q) + H2 2025 608 (1,235 - 627) x 1.04 (Q3 guide midpoint +4%, Q4 assumed alike) = 1,294.3 (+4.8%). FY27 and FY28 +5%/yr = the agents' 'mid-single-digit room nights' (agents 1 and 4 base; median of stated views). Variant: +3%/yr after FY26 (Middle East/oil, Fed hikes; agent 4 bear 'low single digits') = FY28 1,373 (-3.8%), FV $184.4 (-3.3%).
A57: driver:gbrn | B57: Gross bookings per room night (total gross bookings incl. car/flights / room nights): 150.7 -> 156.1/159.2/162.4 (estimate) | C57: estimate | F57: FY26 GB = H1 104,716 + H2 2025 92,701 (186,107 - 93,406) x 1.05 (Q3 GB guide midpoint) = 202,052 / 1,294.3 = $156.11 (+3.6%, H1 FX tailwind). FY27/FY28 +2%/yr = Q2 2026 constant-currency ADR +2% (10-Q), no FX. No agent states a per-night number; agent 2 implies GB about 1pt ahead of room nights in Q3 (GB +4-6% vs RN +3-5%). Variant: +1%/yr (ADR flat cc as in FY2025, 10-K) = FV $187.5 (-1.7%).
A58: driver:take | B58: Take rate (total revenues / total gross bookings): 0.1446 -> 0.1436/0.144/0.1445 (estimate) | C58: estimate | F58: FY26 revenue = H1 12,884 (F6 inputs) + H2 2025 15,357 x 1.05 (Q3 revenue guide +4-6%, agent 1 citing [1]) = 29,009 / GB 202,052 = 14.36% (booking-window timing: GB grew ahead of revenue in H1). FY27 14.40%, FY28 14.45%: back toward the FY2025 level as merchant mix rises (63% -> 70% -> 73%). No agent states a number; agents 2, 3, 5 name take-rate concessions as a bear risk only.
A59: driver:mkt | B59: Marketing expense (performance + brand) % of gross bookings: 0.04399 -> 0.04461/0.045/0.0455 (estimate) | C59: estimate | F59: FY26 = H1 4,439 + H2 GB 97,336 x 4.70% (H2 2025 4,270/92,701 = 4.61%, +0.1pt as in Q2) = 9,014 / 202,052 = 4.46%. FY27 4.50%, FY28 4.55%: +5bp/yr drift for AI channels (agents 1, 3, 4 name rising acquisition cost, no number). Variant: 4.7% from FY27 (the page add-condition level) = FV $184.7 (-3.2%).
A60: driver:opex | B60: Other operating expense ex marketing, ex impairment and transformation costs, % of revenue (GAAP, incl. SBC and D&A): 0.3434 -> 0.34/0.337/0.335 (estimate) | C60: estimate | F60: FY26 = (H1 4,674 + H2 2025 5,574 x 1.05 - one-offs ~662 as in FY2025) / 29,009 = 34.0%; this reproduces the FY26 adj EPS guide (~$10.36 vs consensus $10.45 [10]). FY27 33.7%, FY28 33.5%: about a third of the $650M savings run-rate kept (rest reinvested). Variant: flat 34.0% = FV $188.3 (-1.3%); full $650M savings kept (32.3% FY28) = FV $196.4 (+3.0%).
A61: driver:sh | B61: Diluted weighted-average shares (post-split): 816 -> 767/721/677.7 (estimate) | C61: estimate | F61: -6%/yr net shrink (supervisor key drivers; agents 1, 3, 4, 5): 815.975 x 0.94 = 767.0 (Q2 770 F26, H1 782 check), 721.0, 677.7. Horizon point count (Oct 2027) = FY27 avg - 5/12 x (FY27 - FY28) = 703M vs agents' 705-715M and supervisor 708M: mine is a diluted-average path from FY2025, theirs runs from the 751M cover count at ~5%/yr. Variant 708M at horizon: FCF leg -0.8%.
A63: # | B63: Source | C63: Date | D63: Link
A64: 1 | B64: Booking Holdings Q2 2026 earnings release (8-K Ex.99.1; Q3/FY guide table) | C64: 2026-08-04 | D64: https://www.sec.gov/Archives/edgar/data/1075531/000107553126000036/q2-26bkngearningsrelease.htm
A65: 2 | B65: Booking Holdings Form 10-Q, Q2 2026 (legal note: FTC, Dutch foundations, German suits, CNMC $472M; UTB $313M; Innovation Box; SBC; equity statement) | C65: 2026-08-04 | D65: https://www.sec.gov/Archives/edgar/data/1075531/000107553126000037/bkng-20260630.htm
A66: 3 | B66: Expedia Group Q2 2026 earnings release (Q3 gross bookings +5-7%, FY +8-9%) | C66: 2026-08-05 | D66: https://www.sec.gov/Archives/edgar/data/1324424/000132442426000051/earningsrelease-q22026.htm
A67: 4 | B67: Airbnb Q2 2026 shareholder letter (Q3 GBV mid-teens, nights low double digits) | C67: 2026-08-06 | D67: https://www.sec.gov/Archives/edgar/data/1559720/000119312526337928/d70413dex991.htm
A68: 5 | B68: SEC EDGAR submissions index for BKNG (last 8-K Aug 4) | C68: 2026-10-02 | D68: https://data.sec.gov/submissions/CIK0001075531.json
A69: 6 | B69: Booking Holdings press-release RSS feed (latest Sep 29; Q2 webcast notice Jul 7) | C69: 2026-10-02 | D69: https://www.bookingholdings.com/press-releases/feed/
A70: 7 | B70: TechCrunch: Meta's AI agent Muse is now the No. 2 app in the US | C70: 2026-09-10 | D70: https://techcrunch.com/2026/09/10/metas-ai-agent-muse-is-now-the-no-2-app-in-the-us/
A71: 8 | B71: Meta Muse: 2.5M downloads in 13 days (Sensor Tower, via borncity) | C71: 2026-09 | D71: https://borncity.com/news/meta-muse-ki-agent-erreicht-25-millionen-downloads-in-13-tagen/
A72: 9 | B72: Hospitality Net: Google ships agentic booking (10 launch partners) | C72: 2026-08-28 | D72: https://www.hospitalitynet.org/news/4134140/
A73: 10 | B73: StockAnalysis BKNG forecast (FY26 $10.45; 36 analysts; avg PT $238.78) | C73: 2026-09-24 | D73: https://stockanalysis.com/stocks/bkng/forecast/
A74: 11 | B74: Twelve Data: IGV monthly Nov 2025-Oct 2026; BKNG monthly 2018-2020; BKNG daily to Oct 2 | C74: 2026-10-02 | D74: https://api.twelvedata.com/time_series
A75: 12 | B75: Nasdaq.com analyst earnings forecast, EXPE (Zacks consensus EPS: FY26 $17.35 n=8, FY27 $20.47 n=10) | C75: 2026-10-26 | D75: https://api.nasdaq.com/api/analyst/EXPE/earnings-forecast
... A88: 25 | B88: SEC XBRL companyfacts, Airbnb (CIK 1559720): Q2 2026 10-Q (filed 2026-08-06) net income $816M, diluted weighted shares 597.0M; FY2025 10-K (accession 0001559720-26-000004) net income $2,511M, goodwill / intangible / long-lived impairment $0, equity-security impairment $30M, other non-operating expense $112M | C88: 2026-10-26 | D88: https://data.sec.gov/api/xbrl/companyfacts/CIK0001559720.json
A90: Fact id | B90: Figure | C90: Value | D90: Filing
A91: F1 | B91: revenue FY ending 2023-12-31 (us-gaap:Revenues) | C91: 21365000000 | D91: https://www.sec.gov/Archives/edgar/data/1075531/000107553126000009/
A92: F2 | B92: revenue FY ending 2024-12-31 (us-gaap:Revenues) | C92: 23739000000 | D92: https://www.sec.gov/Archives/edgar/data/1075531/000107553126000009/
A93: F3 | B93: revenue FY ending 2025-12-31 (us-gaap:Revenues) | C93: 26917000000 | D93: https://www.sec.gov/Archives/edgar/data/1075531/000107553126000009/
A94: F4 | B94: revenue YTD 2026-01-01 to 2026-06-30 | C94: 12884000000 | D94: https://www.sec.gov/Archives/edgar/data/1075531/000107553126000037/
A95: F5 | B95: revenue prior-year YTD 2025-01-01 to 2025-06-30 | C95: 11560000000 | D95: https://www.sec.gov/Archives/edgar/data/1075531/000107553126000037/
A96: F6 | B96: revenue TTM to 2026-06-30 | C96: 28241000000
A97: F7 | B97: revenue quarter 2026-04-01 to 2026-06-30 | C97: 7352000000 | D97: https://www.sec.gov/Archives/edgar/data/1075531/000107553126000037/
A98: F8 | B98: operating_income FY ending 2023-12-31 (us-gaap:OperatingIncomeLoss) | C98: 5835000000 | D98: https://www.sec.gov/Archives/edgar/data/1075531/000107553126000009/
A99: F9 | B99: operating_income FY ending 2024-12-31 (us-gaap:OperatingIncomeLoss) | C99: 7555000000 | D99: https://www.sec.gov/Archives/edgar/data/1075531/000107553126000009/
A100: F10 | B100: operating_income FY ending 2025-12-31 (us-gaap:OperatingIncomeLoss) | C100: 8825000000 | D100: https://www.sec.gov/Archives/edgar/data/1075531/000107553126000009/
A101: F11 | B101: operating_income YTD 2026-01-01 to 2026-06-30 | C101: 3771000000 | D101: https://www.sec.gov/Archives/edgar/data/1075531/000107553126000037/
A102: F12 | B102: operating_income prior-year YTD 2025-01-01 to 2025-06-30 | C102: 3312000000 | D102: https://www.sec.gov/Archives/edgar/data/1075531/000107553126000037/
A103: F13 | B103: operating_income TTM to 2026-06-30 | C103: 9284000000
A104: F14 | B104: operating_income quarter 2026-04-01 to 2026-06-30 | C104: 2500000000 | D104: https://www.sec.gov/Archives/edgar/data/1075531/000107553126000037/
A105: F15 | B105: eps_diluted FY ending 2023-12-31 (us-gaap:EarningsPerShareDiluted) | C105: 117.4 | D105: https://www.sec.gov/Archives/edgar/data/1075531/000107553126000009/
A106: F16 | B106: eps_diluted FY ending 2024-12-31 (us-gaap:EarningsPerShareDiluted) | C106: 172.69 | D106: https://www.sec.gov/Archives/edgar/data/1075531/000107553126000009/
A107: F17 | B107: eps_diluted FY ending 2025-12-31 (us-gaap:EarningsPerShareDiluted) | C107: 165.57 | D107: https://www.sec.gov/Archives/edgar/data/1075531/000107553126000009/
A108: F18 | B108: eps_diluted YTD 2026-01-01 to 2026-06-30 | C108: 3.88 | D108: https://www.sec.gov/Archives/edgar/data/1075531/000107553126000037/
A109: F19 | B109: eps_diluted prior-year YTD 2025-01-01 to 2025-06-30 | C109: 1.5 | D109: https://www.sec.gov/Archives/edgar/data/1075531/000107553126000037/
A110: F20 | B110: eps_diluted quarter 2026-04-01 to 2026-06-30 | C110: 2.53 | D110: https://www.sec.gov/Archives/edgar/data/1075531/000107553126000037/
A111: F21 | B111: diluted_shares_wavg FY ending 2023-12-31 (us-gaap:WeightedAverageNumberOfDilutedSharesOutstanding) | C111: 36530000 | D111: https://www.sec.gov/Archives/edgar/data/1075531/000107553126000009/
A112: F22 | B112: diluted_shares_wavg FY ending 2024-12-31 (us-gaap:WeightedAverageNumberOfDilutedSharesOutstanding) | C112: 34064000 | D112: https://www.sec.gov/Archives/edgar/data/1075531/000107553126000009/
A113: F23 | B113: diluted_shares_wavg FY ending 2025-12-31 (us-gaap:WeightedAverageNumberOfDilutedSharesOutstanding) | C113: 32639000 | D113: https://www.sec.gov/Archives/edgar/data/1075531/000107553126000009/
A114: F24 | B114: diluted_shares_wavg YTD 2026-01-01 to 2026-06-30 | C114: 782000000 | D114: https://www.sec.gov/Archives/edgar/data/1075531/000107553126000037/
A115: F25 | B115: diluted_shares_wavg prior-year YTD 2025-01-01 to 2025-06-30 | C115: 821000000 | D115: https://www.sec.gov/Archives/edgar/data/1075531/000107553126000037/
... A121: F31 | B121: d_and_a prior-year YTD 2025-01-01 to 2025-06-30 | C121: 312000000 | D121: https://www.sec.gov/Archives/edgar/data/1075531/000107553126000037/
A122: F32 | B122: d_and_a TTM to 2026-06-30 | C122: 571000000
A123: F33 | B123: d_and_a quarter 2026-01-01 to 2026-03-31 | C123: 131000000 | D123: https://www.sec.gov/Archives/edgar/data/1075531/000107553126000025/
...
