Workbook

Sheet Summary
A1: GOOGL standard model (trial) · research run 2026-10-23
A2: The supervisor's reconciled assumption set as a live model. Trial: shown beside the blended page target, not used for trade levels until its weight is decided. Edit blue cells on Model (drivers) and Valuation (assumptions).
A3: Price target box | B3: Value
A4: Live price | B4: =IFERROR(GOOGLEFINANCE("GOOGL","price"),Valuation!$B$67)
A5: Price as of | B5: =NOW()
A6: Model target (12-month median) | B6: =Distribution!$B$13
A7: Upside to model target from live price | B7: =B6/B4-1
A8: Research target (12m) (no scenario deltas) | B8: =Valuation!$D$7
A9: Probability-weighted mean | B9: =Distribution!$B$10
A10: 10th percentile | B10: =Distribution!$B$14
A11: 25th percentile | B11: =Distribution!$B$15
A12: 75th percentile | B12: =Distribution!$B$16
A13: 90th percentile | B13: =Distribution!$B$17
A14: Target date | B14: =Valuation!$B$45
A15: Price at the run | B15: =Valuation!$B$67
A16: Blended page target (options 67% + agents 33%, not live) | B16: 335.2598
A17: Supervisor research target (12m) (its own methods) | B17: 323.03
A18: Thesis break price (supervisor) | B18: 250
A19: Supervisor confidence | B19: medium
A21: Key estimates | B21: FY2025A | C21: =Model!E5 | D21: =Model!F5
A22: Net sales | B22: =IF(Model!D32="","",Model!D32) | C22: =Model!E32 | D22: =Model!F32
A23: % YoY | B23: =IF(Model!D33="","",Model!D33) | C23: =Model!E33 | D23: =Model!F33
A24: Pretax margin | B24: =IF(Model!D43="","",Model!D43) | C24: =Model!E43 | D24: =Model!F43
A25: Diluted EPS (model) | B25: =IF(Model!D50="","",Model!D50) | C25: =Model!E50 | D25: =Model!F50
A26: % YoY | B26: =IF(Model!D51="","",Model!D51) | C26: =Model!E51 | D26: =Model!F51
A27: Free cash flow to firm | B27: =IF(Model!D60="","",Model!D60) | C27: =Model!E60 | D27: =Model!F60
A28: Consensus: EPS (GAAP (consensus excludes equity-security) | D28: 14.95
A30: Valuation method | B30: Value per share | C30: Weight
A31: =Valuation!A4 | B31: =Valuation!D4 | C31: =Valuation!E4
A32: =Valuation!A5 | B32: =Valuation!D5 | C32: =Valuation!E5
A33: =Valuation!A6 | B33: =Valuation!D6 | C33: =Valuation!E6
A35: Scenario | B35: Probability | C35: Value at target date | D35: What has to happen
A36: =Distribution!A4 | B36: =Distribution!B4 | C36: =Distribution!C4 | D36: =Distribution!D4
A37: =Distribution!A5 | B37: =Distribution!B5 | C37: =Distribution!C5 | D37: =Distribution!D5
A38: =Distribution!A6 | B38: =Distribution!B6 | C38: =Distribution!C6 | D38: =Distribution!D6
A40: Price at target date | B40: Probability above
A41: =ROUND(Valuation!$B$67*0.7,0) | B41: =SUMPRODUCT(Distribution!$B$4:$B$6,1-NORMSDIST((LN(A41)-LN(Distribution!$C$4:$C$6))/Distribution!$B$9))
A42: =ROUND(Valuation!$B$67*0.8,0) | B42: =SUMPRODUCT(Distribution!$B$4:$B$6,1-NORMSDIST((LN(A42)-LN(Distribution!$C$4:$C$6))/Distribution!$B$9))
A43: =ROUND(Valuation!$B$67*0.9,0) | B43: =SUMPRODUCT(Distribution!$B$4:$B$6,1-NORMSDIST((LN(A43)-LN(Distribution!$C$4:$C$6))/Distribution!$B$9))
A44: =ROUND(Valuation!$B$67*1.0,0) | B44: =SUMPRODUCT(Distribution!$B$4:$B$6,1-NORMSDIST((LN(A44)-LN(Distribution!$C$4:$C$6))/Distribution!$B$9))
A45: =ROUND(Valuation!$B$67*1.1,0) | B45: =SUMPRODUCT(Distribution!$B$4:$B$6,1-NORMSDIST((LN(A45)-LN(Distribution!$C$4:$C$6))/Distribution!$B$9))
A46: =ROUND(Valuation!$B$67*1.2,0) | B46: =SUMPRODUCT(Distribution!$B$4:$B$6,1-NORMSDIST((LN(A46)-LN(Distribution!$C$4:$C$6))/Distribution!$B$9))
A47: =ROUND(Valuation!$B$67*1.3,0) | B47: =SUMPRODUCT(Distribution!$B$4:$B$6,1-NORMSDIST((LN(A47)-LN(Distribution!$C$4:$C$6))/Distribution!$B$9))
A48: =ROUND(Valuation!$B$67*1.5,0) | B48: =SUMPRODUCT(Distribution!$B$4:$B$6,1-NORMSDIST((LN(A48)-LN(Distribution!$C$4:$C$6))/Distribution!$B$9))
A50: Model checks | B50: Status
A51: Scenario probabilities sum to 100% | B51: =IF(ABS(Distribution!B8-1)<0.005,"ok","FLAG: "&TEXT(Distribution!B8,"0.0%"))
A52: WACC exceeds terminal growth by 1 point or more | B52: =IF('Calc - research target (12m)'!B55="ok","ok","FLAG")
A53: Projection runs a full year past the target date | B53: =IF('Calc - research target (12m)'!B56="ok","ok","FLAG")
A54: Method weights add up to more than zero | B54: =IF(SUM(Valuation!E4:E6)>0,"ok","FLAG")
A55: Terminal value under 85% of the DCF | B55: =IF('Calc - research target (12m)'!B46<0.85,"ok","note: "&TEXT('Calc - research target (12m)'!B46,"0%")&" of the DCF is terminal value")
A56: Segment base revenues tie to the last reported net sales (within 2%) | B56: =IF(ABS(Valuation!$B$107/Valuation!$B$50-1)<=0.02,"ok","FLAG")
A57: Matches the engine run at publication (target, research target (12m)) | B57: =IF(AND(ABS(Distribution!$B$13-317.6465)<0.01,ABS(Valuation!$D$7-323.0327)<0.01),"ok","inputs edited since publication")
A58: All checks | B58: =IF(COUNTIF(B51:B57,"ok")=7,"all ok",7-COUNTIF(B51:B57,"ok")&" to look at")

Sheet Model
A1: GOOGL: annual model, base case
A2: (M of US dollars except per share; fiscal years named by the calendar year they end in)
A3: Blue = input · black = formula · green = link to another tab · actuals from SEC filings (fact ids in the last column, links on Sources)
A5: Fiscal year | B5: FY2023A | C5: FY2024A | D5: FY2025A | E5: FY2026E | F5: FY2027E | G5: FY2028E | H5: Source / note
A6: Period end | B6: 45291 | C6: 45657 | D6: 46022 | E6: =IF(DAY(Valuation!$B$49+1)=1,EOMONTH(Valuation!$B$49,12*E7),EDATE(Valuation!$B$49,12*E7)) | F6: =IF(DAY(Valuation!$B$49+1)=1,EOMONTH(Valuation!$B$49,12*F7),EDATE(Valuation!$B$49,12*F7)) | G6: =IF(DAY(Valuation!$B$49+1)=1,EOMONTH(Valuation!$B$49,12*G7),EDATE(Valuation!$B$49,12*G7))
A7: Projection year | B7: -2 | C7: -1 | D7: 0 | E7: 1 | F7: 2 | G7: 3
A10: Segment build (blue = input: revenue growth and EBIT margin by segment and year)
A11: Google Search & other | D11: =Valuation!$B$103 | E11: =Valuation!$B$103*(1+E12) | F11: =E11*(1+F12) | G11: =F11*(1+G12)
A12: Revenue growth | E12: 0.1592 | F12: 0.11234783 | G12: 0.10214392
A13: Segment EBIT | E13: =E11*E14 | F13: =F11*F14 | G13: =G11*G14
A14: EBIT margin | E14: 0.43 | F14: 0.445 | G14: 0.46
A15: Google Services other (YouTube ads, Network, subscriptions/platforms/devices, hedging) | D15: =Valuation!$B$104 | E15: =Valuation!$B$104*(1+E16) | F15: =E15*(1+F16) | G15: =F15*(1+G16)
A16: Revenue growth | E16: 0.1 | F16: 0.09 | G16: 0.08
A17: Segment EBIT | E17: =E15*E18 | F17: =F15*F18 | G17: =G15*G18
A18: EBIT margin | E18: 0.43 | F18: 0.445 | G18: 0.46
A19: Google Cloud | D19: =Valuation!$B$105 | E19: =Valuation!$B$105*(1+E20) | F19: =E19*(1+F20) | G19: =F19*(1+G20)
A20: Revenue growth | E20: 0.73709769 | F20: 0.61258531 | G20: 0.20404999
A21: Segment EBIT | E21: =E19*E22 | F21: =F19*F22 | G21: =G19*G22
A22: EBIT margin | E22: 0.35 | F22: 0.37 | G22: 0.39
A23: Other Bets | D23: =Valuation!$B$106 | E23: =Valuation!$B$106*(1+E24) | F23: =E23*(1+F24) | G23: =F23*(1+G24)
A24: Revenue growth | E24: 0 | F24: 0 | G24: 0
A25: Segment EBIT | E25: =E23*E26 | F25: =F23*F26 | G25: =G23*G26
A26: EBIT margin | E26: -5.0748211 | F26: -5.0748211 | G26: -5.0748211
A27: Total segment revenue (= net sales) | D27: =D11+D15+D19+D23 | E27: =E11+E15+E19+E23 | F27: =F11+F15+F19+F23 | G27: =G11+G15+G19+G23 | H27: base revenues on Valuation (segment build); net sales = this total
A28: Total segment EBIT | E28: =E13+E17+E21+E25 | F28: =F13+F17+F21+F25 | G28: =G13+G17+G21+G25
A29: Corporate / unallocated EBIT (blue = input) | E29: -26108.965 | F29: -43294.923 | G29: -67958.964 | H29: years[].corporate_ebit; EBIT = total segment EBIT + corporate
A31: Sales
A32: Net sales | B32: 307394 | C32: 350018 | D32: 402836 | E32: =E27 | F32: =F27 | G32: =G27 | H32: SEC XBRL F1, F2, F3
A33: % YoY | C33: =IF(OR(C32="",B32="",B32=0),"",C32/B32-1) | D33: =IF(OR(D32="",C32="",C32=0),"",D32/C32-1) | E33: =E32/Valuation!$B$50-1 | F33: =F32/E32-1 | G33: =G32/F32-1
A35: Operating profit
A36: EBIT (operating income) | E36: =E28+E29 | F36: =F28+F29 | G36: =G28+G29
A37: EBIT margin | E37: =E36/E32 | F37: =F36/F32 | G37: =G36/G32
A38: D&A | E38: =E32*E72 | F38: =F32*F72 | G38: =G32*G72
A39: EBITDA | E39: =E36+E38 | F39: =F36+F38 | G39: =G36+G38
A40: EBITDA margin | E40: =E39/E32 | F40: =F39/F32 | G40: =G39/G32
A41: Net interest income / (expense) | E41: =-Valuation!$B$58*Valuation!$B$56 | F41: =-Valuation!$B$58*E66 | G41: =-Valuation!$B$58*F66 | H41: rate x prior year-end net debt (memo roll)
A42: Pretax income | B42: 85717 | C42: 119815 | D42: 158826 | E42: =E36+E41 | F42: =F36+F41 | G42: =G36+G41 | H42: SEC XBRL F83, F84, F85
A43: Pretax margin | B43: =B42/B32 | C43: =C42/C32 | D43: =D42/D32 | E43: =E42/E32 | F43: =F42/F32 | G43: =G42/G32
A44: Income tax | B44: 11922 | C44: 19697 | D44: 26656 | E44: =E42*E71 | F44: =F42*F71 | G44: =G42*G71 | H44: SEC XBRL F76, F77, F78
A45: Effective tax rate | B45: =B44/B42 | C45: =C44/C42 | D45: =D44/D42 | E45: =E44/E42 | F45: =F44/F42 | G45: =G44/G42
A46: Net income | B46: 73795 | C46: 100118 | D46: 132170 | E46: =E42-E44 | F46: =F42-F44 | G46: =G42-G44 | H46: SEC XBRL F15, F16, F17
A47: % YoY | C47: =IF(OR(C46="",B46="",B46=0),"",C46/B46-1) | D47: =IF(OR(D46="",C46="",C46=0),"",D46/C46-1) | E47: =IF(OR(D46="",D46=0),"",E46/D46-1) | F47: =IF(OR(E46="",E46=0),"",F46/E46-1) | G47: =IF(OR(F46="",F46=0),"",G46/F46-1)
A48: Diluted shares (M, average) | B48: 12722 | C48: 12447 | D48: 12230 | E48: =Valuation!$B$60*(1+Valuation!$B$62)^(E7-0.5-((Valuation!$B$61-Valuation!$B$49)/365.25)) | F48: =Valuation!$B$60*(1+Valuation!$B$62)^(F7-0.5-((Valuation!$B$61-Valuation!$B$49)/365.25)) | G48: =Valuation!$B$60*(1+Valuation!$B$62)^(G7-0.5-((Valuation!$B$61-Valuation!$B$49)/365.25)) | H48: diluted count rolled at the annual change to mid-year
A49: % YoY | C49: =IF(OR(C48="",B48="",B48=0),"",C48/B48-1) | D49: =IF(OR(D48="",C48="",C48=0),"",D48/C48-1) | E49: =IF(OR(D48="",D48=0),"",E48/D48-1) | F49: =IF(OR(E48="",E48=0),"",F48/E48-1) | G49: =IF(OR(F48="",F48=0),"",G48/F48-1)
A50: Diluted EPS | B50: 5.8 | C50: 8.04 | D50: 10.81 | E50: =E46/E48 | F50: =F46/F48 | G50: =G46/G48 | H50: SEC XBRL F22, F23, F24
A51: % YoY | C51: =IF(OR(C50="",B50="",B50=0),"",C50/B50-1) | D51: =IF(OR(D50="",C50="",C50=0),"",D50/C50-1) | E51: =IF(OR(D50="",D50=0),"",E50/D50-1) | F51: =IF(OR(E50="",E50=0),"",F50/E50-1) | G51: =IF(OR(F50="",F50=0),"",G50/F50-1)
A53: Cash flow
A54: NOPAT (EBIT x (1 - tax)) | E54: =E36*(1-E71) | F54: =F36*(1-F71) | G54: =G36*(1-G71)
A55: + D&A | B55: =B38 | C55: =C38 | D55: =D38 | E55: =E38 | F55: =F38 | G55: =G38
A56: - Capex | B56: 32251 | C56: 52535 | D56: 91447 | E56: =E32*E73 | F56: =F32*F73 | G56: =G32*G73 | H56: SEC XBRL F48, F49, F50
A57: Capex % of sales | B57: =B56/B32 | C57: =C56/C32 | D57: =D56/D32 | E57: =E56/E32 | F57: =F56/F32 | G57: =G56/G32
A58: - Working capital increase | E58: =E74*(E32-Valuation!$B$50) | F58: =F74*(F32-E32) | G58: =G74*(G32-F32)
A59: - Stock comp (adjusted EBIT only) | E59: =IF(AND(Valuation!$B$47="adjusted",Valuation!$B$48="cost"),E63*(1-E71),0) | F59: =IF(AND(Valuation!$B$47="adjusted",Valuation!$B$48="cost"),F63*(1-F71),0) | G59: =IF(AND(Valuation!$B$47="adjusted",Valuation!$B$48="cost"),G63*(1-G71),0)
A60: Free cash flow to firm | E60: =E54+E55-E56-E58-E59 | F60: =F54+F55-F56-F58-F59 | G60: =G54+G55-G56-G58-G59 | H60: what the DCF discounts (Calc tabs)
A61: Operating cash flow (reported) | B61: 101746 | C61: 125299 | D61: 164713 | H61: SEC XBRL F41, F42, F43
A62: FCF (operating cash flow - capex) | B62: =B61-B56 | C62: =C61-C56 | D62: =D61-D56
A63: Stock comp (memo) | B63: 22460 | C63: 22785 | D63: 24953 | E63: =E32*E75 | F63: =F32*F75 | G63: =G32*G75 | H63: SEC XBRL F34, F35, F36
A64: Buybacks + dividends + other uses | B64: 61504 | C64: 69585 | D64: 55758 | E64: =E32*E77+E76+E78 | F64: =F32*F77+F76+F78 | G64: =G32*G77+G76+G78 | H64: SEC XBRL F55, F62, F56, F63, F57, F64
A65: % of sales | B65: =B64/B32 | C65: =C64/C32 | D65: =D64/D32 | E65: =E64/E32 | F65: =F64/F32 | G65: =G64/G32
A66: Net debt / (net cash), year end (memo) | E66: =Valuation!$B$56-E60-E41*(1-E71)+E64 | F66: =E66-F60-F41*(1-F71)+F64 | G66: =F66-G60-G41*(1-G71)+G64 | H66: rolled from the balance-date figure; feeds interest only
A68: Drivers (blue = input; a year left black carries the prior year)
A69: Revenue growth | C69: =C33 | D69: =D33 | E69: =E33 | F69: =F33 | G69: =G33 | H69: implied by the segment build (edit the segment rows)
A70: EBIT margin | E70: =E37 | F70: =F37 | G70: =G37 | H70: implied by the segment build and corporate EBIT
A71: Tax rate | B71: =B45 | C71: =C45 | D71: =D45 | E71: 0.17 | F71: =E71 | G71: =F71
A72: D&A % revenue | B72: =B38/B32 | C72: =C38/C32 | D72: =D38/D32 | E72: 0.065447804 | F72: 0.088116933 | G72: 0.11716699
A73: Capex % revenue | B73: =B57 | C73: =C57 | D73: =D57 | E73: 0.40513821 | F73: 0.50410392 | G73: 0.50550434
A74: Working capital % of revenue increase | E74: 0 | F74: =E74 | G74: =F74
A75: Stock comp % revenue | B75: =B63/B32 | C75: =C63/C32 | D75: =D63/D32 | E75: 0.063129 | F75: =E75 | G75: =F75
A76: Shareholder returns ($) | E76: 0 | F76: =E76 | G76: =F76
A77: Shareholder returns % revenue | B77: =B65 | C77: =C65 | D77: =D65 | E77: 0 | F77: =E77 | G77: =F77
A78: Other uses of cash ($: M&A, investments) | E78: 0 | F78: =E78 | G78: =F78
A79: Adj. EBITDA addback % revenue | E79: 0 | F79: =E79 | G79: =F79
A81: Versus company guidance and street consensus
A82: Guidance: capex (company guidance ($M)), midpoint | E82: =AVERAGE(195000.0,205000.0) | H82: 1.95e+05 to 2.05e+05; as of 2026-07-22; source 5 (Alphabet Q2 2026 earnings call transcript (IR PDF))
A83: Consensus: EPS diluted (GAAP (consensus excludes equity-security gains)) | F83: 14.95 | H83: as of 2026-10-06; source 8, 9 (Yahoo Finance GOOGL analysis (consensus EPS, trend))
A84: Model vs consensus | F84: =F50/F83-1
A85: Consensus: EPS diluted (GAAP (consensus excludes equity-security gains)) | G85: 17.89 | H85: as of 2026-10-06; source 9 (MarketScreener Alphabet finances (EPS, capex, FCF, EBIT, EBI)
A86: Model vs consensus | G86: =G50/G85-1
A87: Consensus: revenue (GAAP ($M)) | F87: 615038 | H87: as of 2026-10-06; source 9 (MarketScreener Alphabet finances (EPS, capex, FCF, EBIT, EBI)
A88: Model vs consensus | F88: =F32/F87-1
A89: Consensus: revenue (GAAP ($M)) | G89: 734199 | H89: as of 2026-10-06; source 9 (MarketScreener Alphabet finances (EPS, capex, FCF, EBIT, EBI)
A90: Model vs consensus | G90: =G32/G89-1
A91: Consensus: EBIT margin (GAAP; EBIT $216,996M / sales $615,038M) | F91: 0.352817 | H91: as of 2026-10-06; source 9 (MarketScreener Alphabet finances (EPS, capex, FCF, EBIT, EBI)
A92: Model vs consensus | F92: =(F37-F91)*10000
A93: Consensus: EBIT margin (GAAP; EBIT $263,325M / sales $734,199M) | G93: 0.358656 | H93: as of 2026-10-06; source 9 (MarketScreener Alphabet finances (EPS, capex, FCF, EBIT, EBI)
A94: Model vs consensus | G94: =(G37-G93)*10000
A95: Consensus: EBITDA ($M) | F95: 298668 | H95: as of 2026-10-06; source 9 (MarketScreener Alphabet finances (EPS, capex, FCF, EBIT, EBI)
A96: Consensus: capex ($M) | F96: 300979 | H96: as of 2026-10-06; source 9 (MarketScreener Alphabet finances (EPS, capex, FCF, EBIT, EBI)
A97: Consensus: capex ($M) | G97: 339451 | H97: as of 2026-10-06; source 9 (MarketScreener Alphabet finances (EPS, capex, FCF, EBIT, EBI)
A98: Consensus: free cash flow ($M) | E98: 8448 | H98: as of 2026-10-06; source 9 (MarketScreener Alphabet finances (EPS, capex, FCF, EBIT, EBI)
A99: Consensus: free cash flow ($M) | F99: -36658 | H99: as of 2026-10-06; source 9 (MarketScreener Alphabet finances (EPS, capex, FCF, EBIT, EBI)

Sheet Valuation
A1: GOOGL: valuation and price target derivation
A2: Value per share at the target date = weighted methods below; the 12-month target is the median of the scenario mix (Distribution tab).
A3: Method | B3: Multiple | C3: Metric at target date | D3: Value per share | E3: Weight | F3: Contribution
A4: ='Calc - research target (12m)'!A67 | B4: =IF('Calc - research target (12m)'!C67="","",'Calc - research target (12m)'!C67) | C4: =IF('Calc - research target (12m)'!I67="","",'Calc - research target (12m)'!I67) | D4: ='Calc - research target (12m)'!F67 | E4: ='Calc - research target (12m)'!G67 | F4: =D4*E4/SUM($E$4:$E$6)
A5: ='Calc - research target (12m)'!A68 | B5: =IF('Calc - research target (12m)'!C68="","",'Calc - research target (12m)'!C68) | C5: =IF('Calc - research target (12m)'!I68="","",'Calc - research target (12m)'!I68) | D5: ='Calc - research target (12m)'!F68 | E5: ='Calc - research target (12m)'!G68 | F5: =D5*E5/SUM($E$4:$E$6)
A6: ='Calc - research target (12m)'!A69 | B6: =IF('Calc - research target (12m)'!C69="","",'Calc - research target (12m)'!C69) | C6: =IF('Calc - research target (12m)'!I69="","",'Calc - research target (12m)'!I69) | D6: ='Calc - research target (12m)'!F69 | E6: ='Calc - research target (12m)'!G69 | F6: =D6*E6/SUM($E$4:$E$6)
A7: Research target (12m) per share | D7: ='Calc - research target (12m)'!$F$70 | F7: =SUM(F4:F6)
A9: 12-month EPS basis (what the P/E is applied to)
A10: Fiscal year | B10: =Model!E5 | C10: =Model!F5 | D10: =Model!G5
A11: Share of the 12 months after the target date | B11: ='Calc - research target (12m)'!C38 | C11: ='Calc - research target (12m)'!D38 | D11: ='Calc - research target (12m)'!E38
A12: Model EPS (Model tab) | B12: =Model!E50 | C12: =Model!F50 | D12: =Model!G50
A13: Model EPS, next 12 months after the target date | B13: =SUMPRODUCT(B11:D11,B12:D12)
A14: Stated next-12-month EPS used by the P/E method (consensus basis, cited) | B14: =Valuation!F70 | C14: =B14/B13-1 | D14: vs model EPS
A16: DCF build (free cash flow to firm, discounted to the target date)
A17: Fiscal year | B17: =Model!E5 | C17: =Model!F5 | D17: =Model!G5
A18: Free cash flow to firm | B18: ='Calc - research target (12m)'!C31 | C18: ='Calc - research target (12m)'!D31 | D18: ='Calc - research target (12m)'!E31
A19: Share of the year after the target date | B19: ='Calc - research target (12m)'!C35 | C19: ='Calc - research target (12m)'!D35 | D19: ='Calc - research target (12m)'!E35
A20: PV at target date | B20: ='Calc - research target (12m)'!C36 | C20: ='Calc - research target (12m)'!D36 | D20: ='Calc - research target (12m)'!E36
A22: PV of free cash flow after the target date | B22: ='Calc - research target (12m)'!B42
A23: Terminal value (final year) | B23: ='Calc - research target (12m)'!B43
A24: PV of terminal value | B24: ='Calc - research target (12m)'!B44
A25: Enterprise value at target date | B25: ='Calc - research target (12m)'!B45
A26: Terminal value share of DCF | B26: ='Calc - research target (12m)'!B46
A27: Net debt at target date | B27: ='Calc - research target (12m)'!B50
A28: Minority interests | B28: ='Calc - research target (12m)'!B51
A29: Adjustments | B29: ='Calc - research target (12m)'!B52
A30: Diluted shares at target date (M) | B30: ='Calc - research target (12m)'!B53
A31: DCF value per share | B31: ='Calc - research target (12m)'!F67
A32: WACC | B32: ='Calc - research target (12m)'!B12
A42: Assumptions (blue = input; sources on the Sources tab)
A43: Input | B43: Value | C43: Basis / note
A44: Run date (valuation as of) | B44: 46318
A45: Target date (run date + 365 days) | B45: =B44+365 | C45: 12-month horizon
A46: Money unit | B46: $M
A47: EBIT basis (gaap / adjusted) | B47: gaap | C47: gaap = after stock comp
A48: Stock comp treatment (cost / dilution) | B48: cost | C48: used only when EBIT is adjusted
A49: Last reported fiscal year end | B49: 46022
A50: Net sales, last reported year ($M) | B50: 402836
A51: WACC | B51: 0.09 | C51: filled in (not stated in this set's original work): agent_1's stated ~9% roll-forward rate (mega-cap cost of equity), the only discount rate in the run. Its basis: mega-cap cost of equity at about 32% realised vol, less the $0.22 quarterly dividend (about 0.25% yield). Alphabet holds net cash (6/30: cash + debt securities $155.4B vs debt $100.2B), so the cost of equity is used as the WACC.
A52: Terminal method (gordon / exit_multiple / steady_state) | B52: exit_multiple
A53: Terminal growth | B53: 0.02
A54: Exit EV/EBITDA (exit_multiple only) | B54: 10.5
A55: Balance-sheet date | B55: 46203
A56: Net debt / (net cash) at balance date ($M) | B56: -55247 | C56: excludes operating leases
A57: Minority interests + preferred stock | B57: 0
A58: Interest rate on net debt / cash | B58: 0.022483
A59: Net debt at target date (override; blank = bridge) | B59: 0
A60: Diluted shares (M) | B60: 12309
A61: Share count date | B61: 46203
A62: Annual change in diluted shares | B62: 0 | C62: net of buybacks and stock-comp dilution
A63: Shares at target date (override; blank = from annual change) | B63: 12423
A64: DCF weight | B64: 0 | C64: Kilian 2026-10-21: 0 unless the name has a DCF leg (dcf_policy)
A65: Sum-of-the-parts weight | B65: 0.5
A66: Spread within each scenario (lognormal vol) | B66: 0.2116
A67: Share price at the run | B67: 320.21 | C67: close used by the run (2026-10-23)
A69: Target multiple | B69: Multiple | C69: Weight | D69: Basis (ntm / ltm) | E69: EBITDA basis | F69: Stated EPS | G69: Stated FCF/share | H69: Levered | I69: Peer basis
A70: P/E | B70: 21.2 | C70: 0.5 | D70: ntm | E70: gaap | F70: 14.602897 | H70: TRUE | I70: Refreshed 5-name set (Kilian 2026-10-26 06:07Z): MSFT, AMZN, META, RDDT, APP; Nasdaq.com/Zacks consensus EPS calendarized to CY2027 at the 2026-10-23 close: MSFT 24.45x, AMZN 23.29x, RDDT 20.79x, META 18.94x, APP 13.08x -> median 20.8x, no premium. CY2027 is the base round's basis (next calendar year from the price date, applied to CY2028E at the Oct-2027 horizon, the same 69-day lead). Peer count flag: 5 (under 10). EXIT k=0.8 (2026-10-26T12:28Z): Exit-multiple rule (Kilian card 2026-10-26 12:16Z; METHOD.md Peer comparables): exit = peer median x (own NTM multiple / peer median)^k, k = 0.8. Peer median 20.8x; own 21.3x: GOOGL $320.21 / CY2027 Zacks consensus EPS $15.03 = 21.30x, the CY2027 basis of this leg (FY2027 used because FY2026 consensus carries stake gains; same figure as the AMZN round's peer row). 20.8 x (21.3 / 20.8)^0.8 = 20.8 x 1.0192 = 21.2x (was 20.8x). SOTP segment multiples (Services 18.25x, Cloud 23.3x) stay at their peer medians: a segment has no own traded multiple (rule: no meaningful own multiple -> peer median).
A72: Segment (sum of the parts) | B72: NTM metric | C72: Metric | D72: Multiple | E72: Note
A73: Google Services: CY2028E after-tax OI x ad/consumer-platform peers | B73: 157419.57 | D73: 18.25 | E73: Search & other + YouTube ads, Network, subscriptions/platforms/devices: segment_build FY2028 OI (margin 46%) less its revenue share of the capex-vintage depreciation above the H1-26 intensity, x (1 - 17%). Driver-linked (driver_build.set).
A74: Google Cloud: CY2028E after-tax OI x cloud peers | B74: 54536.214 | D74: 23.3 | E74: Google Cloud: segment_build FY2028 OI (margin 39%) less its revenue share of the excess depreciation, x (1 - 17%). Driver-linked.
A75: Alphabet-level costs: CY2028E after tax x the Services multiple | B75: -24070 | D75: 18.25 | E75: Alphabet-level costs FY2028 -$29.0B (segment_build corporate_ebit constant, estimate) x (1 - 17%) = -$24.07B.
A76: Other Bets: CY2028E after-tax loss x the P/E multiple (Waymo / Isomorphic add-backs in adjustments) | B76: -6474 | D76: 20.8 | E76: Other Bets FY2028 -$7.80B (run-rate, segment_build) x (1 - 17%) = -$6.474B.
A78: Adjustment (equity level) | B78: Value | C78: Probability | D78: Note
A79: Net financial assets at the horizon (supervisor) | B79: 187300 | C79: 1 | D79: Net cash rolled to Oct 2027 on consensus FCF $17.0B + other marketable equity $7.063B x 0.85 + SpaceX $94.1B x 0.75 + non-marketable $131.461B x 0.70 = $185.6B. Carries the net cash, so net debt at the horizon is set to 0.
A80: post-research adjustment 2026-10-19 (once-over): accrued fines and settlements | B80: -17356 | C80: 1 | D80: Accrued fines and settlements $17.356B at 6/30 (10-Q R65), not deducted from net cash in the run: -17,356.
A81: post-research adjustment 2026-10-19 (once-over): SpaceX re-marked to the 2026-10-16 close | B81: -10207.5 | C81: 1 | D81: 551,189,500 shares (13F at 6/30, $94.176B = $170.86/sh) x $146.03 (10-16 close) = $80.49B, -$13.61B; x 0.75 (the run's SpaceX haircut) = -10,207.5.
A82: post-research adjustment 2026-10-19 (once-over): $20.0B private-company funding commitment | B82: -6000 | C82: 1 | D82: Future capital funding commitment with a private company $20.0B (10-Q R14), an investing outflow not in FCF; at the run's 0.70 stake haircut the loss is 30%: -20,000 x 0.30 = -6,000.
A83: post-research adjustment 2026-10-19 (once-over): finance lease liabilities | B83: -2590 | C83: 1 | D83: Finance lease liabilities $2.590B (XBRL) not deducted: -2,590. Operating leases stay out (rent is in EPS).
A84: post-research adjustment 2026-10-19 (once-over): SBC creep shares removed (counted once) | B84: 0 | C84: 1 | D84: Value 0: the item is in the share count. Shares at the horizon 12,400M -> 12,350M (12,309 Q2 diluted + 38M preferred at the maximum rate; the +50M net SBC creep is removed because SBC is a cost in GAAP EPS). P/E leg effect +$0.06 x 0.6 = +$0.04.
A85: Anthropic stake estimate 2026-10-19 | B85: 51210 | C85: 1 | D85: Labelled estimate (not a filing figure). After-tax, after-lock-up value of Alphabet's Anthropic stake at a $1.5T IPO valuation $124.71B minus the part of the $131.461B non-marketable line already counted (Anthropic carrying value, est. $105B, x 0.70 = $73.50B) = +$51.21B (+$4.15/share on 12,350M). Stake 11.28% fully diluted at the IPO (est.) x $1,500B = $169.22B; less 10.37% lock-up discount (Finnerty, 65% vol, 0.5 yr) = $151.67B; less 21% tax on the gain over an est. $23.3B cost = -$26.96B. Range +$22.7B to +$76.0B. Variant (Polymarket first-day close, $1.92T): +$86.9B. The unfunded $20.0B milestone commitment stays in its own once-over line. See file:///mnt/project-files/valuation/runs/2026-10-06/GOOGL/anthropic_stake_2026-10-19.md
A86: Waymo / Other Bets SOTP 2026-10-19 | B86: 158066 | C86: 1 | D86: Peer refresh 2026-10-26: the loss add-back moves with the P/E multiple 21.7x -> 20.8x: 4.207 x 20.8 = $87.51B + stake $70.56B = $158.07B (was $161.85B). The SOTP leg values Other Bets at the same 20.8x, so the add-back cancels there too. Labelled estimate (not a filing figure). Consensus GAAP EPS carries Other Bets losses, so the P/E leg values Waymo as a negative. SOTP bridge: (a) add back Waymo's share of the Other Bets loss: H1 2026 Other Bets loss $3.899B x 2 = $7.80B run-rate (10-Q) x 65% Waymo share (est.) = $5.07B pre-tax, x (1 - 17%) = $4.21B after tax, x 21.7 = +$91.29B; (b) plus Alphabet's Waymo stake: ~80% fully diluted (est.) x ($126B post-money Feb 2026 round, Waymo blog, less est. $12B Waymo cash already in consolidated net cash) x (1 - 20% haircut) - 20% x $12B cash attributable to outside holders = +$70.56B; (c) minus non-marketable line: $0 (Waymo is a consolidated VIE, not a non-marketable security). Total +$161.85B = +$13.11/share on 12,350M. Non-Waymo bets (Verily, Wing, X, Calico, GFiber) stay as consensus EPS treats them. Range +$121.5B to +$194.4B (+$9.84 to +$15.74/share). Variant (robotaxi scenario view, Waymo equity ~$62B vs $126B round): +$129.1B (+$10.45/share). See file:///mnt/project-files/valuation/runs/2026-10-06/GOOGL/anthropic_stake_2026-10-19.md
A87: remaining items 2026-10-19: conglomerate overlay 10% on non-core stakes (est.) | B87: -28970 | C87: 1 | D87: Labelled estimate (conglomerate discount requested 2026-10-19 21:33Z). 10% overlay on the non-core stakes after the model's own haircuts: Anthropic 124.71 + other non-marketable (131.461 - 105) x 0.70 = 18.52 + SpaceX 94.1 x 0.75 - 10.21 = 60.37 + other marketable (87.063 - 80.0) x 0.85 = 6.00 + Waymo stake 70.56 + Isomorphic stake 9.52 = $289.68B; x 10% = -$28.97B (-$2.35/share on 12,350M, both legs). Not applied to the core P/E, net cash or the Waymo loss add-back. Variants: 0 (Villalonga 2004 / Campa-Kedia 2002: no discount once selection is controlled) to -$5.86 (25% on stakes) to -$7.71 (25% on stakes and the Waymo add-back). See file:///mnt/project-files/valuation/runs/2026-10-06/GOOGL/remaining_items_2026-10-19.md
A88: remaining items 2026-10-19: pre-horizon stock comp, RSU tax-withholding cash (15 months) | B88: -30140 | C88: 1 | D88: SBC counted once (METHOD.md rule of 2026-10-12): before the horizon it is counted here as withholding cash; after the horizon it is the cost in CY2028 GAAP EPS. Consensus FCF (CFO less capex) adds SBC back, and RSU tax withholding is a financing outflow, so the ~15 months from 6/30/26 to the 2027-10-06 horizon are otherwise charged nowhere. Net payments related to stock-based award activities H1 2026 $12.056B (Q2 10-Q cash flow) x 2.5 half-years = -$30.14B (-$2.44/share, P/E leg only: the cross-check legs value at 6/30 with no roll-forward). Not also counted: SBC-creep shares (removed in the once-over) and ATM dilution (the $40B ATM is 'primarily intended to be used to meet tax obligations associated with employee equity grants', Q2 10-Q). See file:///mnt/project-files/valuation/runs/2026-10-06/GOOGL/remaining_items_2026-10-19.md
A89: remaining items 2026-10-19: legal remedies, probability-weighted (EU DMA fine, DOJ search appeal, ad tech) | B89: -15800 | C89: 1 | D89: EU DMA fine EUR 890M (EC 2026-07-23, EUR 460M Search + EUR 430M Play; not in the $17.356B accrued at 6/30: the Q2 10-Q says 'we cannot reasonably estimate a probable loss') x EUR/USD 1.1212 = -$998M (hard figure); DOJ search appeal, probability-weighted (est.): 0.15 x +1% EPS (Google wins) - 0.15 x 2% EPS (payment ban on remand) on 21.7 x $17.54 = -$0.57/share = -$7,052M; ad tech expected costs (est.): AdX divestiture on appeal 0.07 x $25B + Texas states $2.5B + private follow-on $3.0B + EU structural 0.05 x $10B = -$7,750M. Total -$15,800M (-$1.28/share, both legs). Variant: -5% EPS in the payment-ban case makes the DOJ piece 0.15 x 3.81 - 0.15 x 19.03 = -$2.28/share. See file:///mnt/project-files/valuation/runs/2026-10-06/GOOGL/remaining_items_2026-10-19.md
A90: remaining items 2026-10-19: Isomorphic Labs stake + loss add-back (est.) | B90: 16426 | C90: 1 | D90: Peer refresh 2026-10-26: loss add-back 0.4 x 0.83 x 20.8 = $6.906B + stake $9.52B = $16.426B (was $16.724B). Labelled estimate. Consensus EPS capitalises Isomorphic's loss inside Other Bets at -21.7x (the Waymo SOTP adds back only Waymo's 65%). Stake: 80% ownership (est.) x ($17.5B prior valuation (Crypto Briefing 2026-10-08) - $2B cash (est.)) x (1 - 20% haircut, as Waymo) - 20% x $2B = $9.52B; loss add-back: 2026 loss ~$0.4B (est. from the UK accounts: FY2025 loss GBP 159.4M, FY2024 GBP 74.8M) x (1 - 17%) x 21.7 = $7.20B; total +$16,724M (+$1.35/share P/E leg; +$1.07 cross-check; +$1.24 on fair value). Variant: the $40B talks (Bloomberg 2026-10-08, not closed) -> stake $23.92B, +$2.42 on fair value. See file:///mnt/project-files/valuation/runs/2026-10-06/GOOGL/remaining_items_2026-10-19.md
... A92: remaining items 2026-10-19: GFiber divestiture cash + note | B92: 3300 | C92: 1 | D92: At close (expected late 2026) Alphabet receives $1.5B cash, a $2.0B note receivable and a 49.99% equity interest (Q2 10-Q Note 8); not in consensus FCF or net financial assets. Cash $1.5B + note $2.0B x 0.9 (haircut, est.) = +$3,300M (+$0.27/share, both legs). The 49.99% equity-method share flows through post-close EPS, so it is not added. See file:///mnt/project-files/valuation/runs/2026-10-06/GOOGL/remaining_items_2026-10-19.md
A94: Custom method | B94: Value per share | C94: Weight | D94: Explanation
A95: none
A97: Scenario | B97: Probability | C97: Growth Δ | D97: Margin Δ | E97: Multiple Δ (turns) | F97: WACC Δ | G97: Multiple %Δ (FCF yield, segments) | H97: Stated EPS/FCF %Δ | I97: Custom methods %Δ | J97: Story
A98: bear | B98: 0.22 | E98: -5.3 | G98: -0.2548 | J98: Stated $252. CY2028 EPS cut to ~$15.5 (capex near the standing view's high case of consensus +39%, and margins flat instead of 35.3% to 35.9%) x 15.5x (between ORCL 17.9x and APP 13.9x on the reconciled set) + ~$12 of stakes after a deeper mark-down = ~$252. Driver restatement (driver_models 2026-10-22): paid clicks -3%, Cloud conversion -10%, capex +25% in every projected year (toward the high case; depreciation and the cash roll both move), multiple -6.2, cross-check -25.6% as before. Peer refresh 2026-10-26: P/E level kept at 15.5x (delta -5.30 on 20.8x); the SOTP parts move -25.48% (same proportion); the cross-check custom leg is gone. | K98: driver deltas: paid_clicks -0.03 %; cloud_conv -0.1 %; capex +0.25 %
A99: base | B99: 0.53 | J99: [exit k=0.8 2026-10-26: P/E 20.8x -> 21.2x] Stated $370. Equals the reconciled fair value: 0.6 x P/E leg $395.6 (21.7x x $17.54 + $14.97) + 0.4 x $332.4 (mean of the agents' sourcing-corrected SOTP/EV legs $349.9, $327.1, $320.3) = $370.3. Peer refresh 2026-10-26: 0.5 x P/E leg (20.8x) + 0.5 x SOTP leg (Services 18.25x, Cloud 23.3x, Alphabet costs 18.25x, Other Bets 20.8x).
A100: bull | B100: 0.25 | E100: 3.2 | G100: 0.1538 | J100: Stated $474. CY2028 EPS ~$19 (TPU system revenue lands mostly in 2027, as the CFO said on the Q2 call, and the backlog converts) x 24x (mega-cap median 24.4x) + ~$18 of stakes = ~$474. Driver restatement (driver_models 2026-10-22): TPU system revenue converts the backlog faster (Cloud conversion +15%), paid clicks +2%, multiple +2.3, cross-check +44.0% as before. Peer refresh 2026-10-26: P/E level kept at 24.0x (delta +3.20 on 20.8x); the SOTP parts move +15.38% (same proportion); the cross-check custom leg is gone. | K100: driver deltas: paid_clicks +0.02 %; cloud_conv +0.15 %
A102: Segment build (segment_build) | B102: Base revenue ($M) | C102: Driver note (growth and EBIT margin by year: Model tab)
A103: Google Search & other | B103: 224532
A104: Google Services other (YouTube ads, Network, subscriptions/platforms/devices, hedging) | B104: 118062
A105: Google Cloud | B105: 58705
A106: Other Bets | B106: 1537
A107: Sum of segment base revenues | B107: =SUM(B103:B106) | C107: =IF(ABS(B107/Valuation!$B$50-1)<=0.02,"ties to the last reported net sales (within 2%)","FLAG: does not tie to the last reported net sales")

Sheet Sensitivity
A1: GOOGL: sensitivity tables (bold = current inputs; every cell recalculates from the live model)
A3: DCF value per share: WACC (down) x exit EV/EBITDA multiple (across)
A4: WACC \ exit multiple | B4: =Valuation!$B$54+(-2) | C4: =Valuation!$B$54+(-1) | D4: =Valuation!$B$54+(0) | E4: =Valuation!$B$54+(1) | F4: =Valuation!$B$54+(2)
A5: =Valuation!$B$51+(-0.01) | B5: =((SUMPRODUCT('Calc - research target (12m)'!$C$31:$E$31,'Calc - research target (12m)'!$C$35:$E$35,(1+$A5)^(-('Calc - research target (12m)'!$C$19:$E$19-'Calc - research target (12m)'!$B$13)))+B$4*'Calc - research target (12m)'!$E$32/(1+$A5)^('Calc - research target (12m)'!$B$16-'Calc - research target (12m)'!$B$13))-'Calc - research target (12m)'!$B$50-'Calc - research target (12m)'!$B$51+'Calc - research target (12m)'!$B$52)/'Calc - research target (12m)'!$B$53 | C5: =((SUMPRODUCT('Calc - research target (12m)'!$C$31:$E$31,'Calc - research target (12m)'!$C$35:$E$35,(1+$A5)^(-('Calc - research target (12m)'!$C$19:$E$19-'Calc - research target (12m)'!$B$13)))+C$4*'Calc - research target (12m)'!$E$32/(1+$A5)^('Calc - research target (12m)'!$B$16-'Calc - research target (12m)'!$B$13))-'Calc - research target (12m)'!$B$50-'Calc - research target (12m)'!$B$51+'Calc - research target (12m)'!$B$52)/'Calc - research target (12m)'!$B$53 | D5: =((SUMPRODUCT('Calc - research target (12m)'!$C$31:$E$31,'Calc - research target (12m)'!$C$35:$E$35,(1+$A5)^(-('Calc - research target (12m)'!$C$19:$E$19-'Calc - research target (12m)'!$B$13)))+D$4*'Calc - research target (12m)'!$E$32/(1+$A5)^('Calc - research target (12m)'!$B$16-'Calc - research target (12m)'!$B$13))-'Calc - research target (12m)'!$B$50-'Calc - research target (12m)'!$B$51+'Calc - research target (12m)'!$B$52)/'Calc - research target (12m)'!$B$53 | E5: =((SUMPRODUCT('Calc - research target (12m)'!$C$31:$E$31,'Calc - research target (12m)'!$C$35:$E$35,(1+$A5)^(-('Calc - research target (12m)'!$C$19:$E$19-'Calc - research target (12m)'!$B$13)))+E$4*'Calc - research target (12m)'!$E$32/(1+$A5)^('Calc - research target (12m)'!$B$16-'Calc - research target (12m)'!$B$13))-'Calc - research target (12m)'!$B$50-'Calc - research target (12m)'!$B$51+'Calc - research target (12m)'!$B$52)/'Calc - research target (12m)'!$B$53 | F5: =((SUMPRODUCT('Calc - research target (12m)'!$C$31:$E$31,'Calc - research target (12m)'!$C$35:$E$35,(1+$A5)^(-('Calc - research target (12m)'!$C$19:$E$19-'Calc - research target (12m)'!$B$13)))+F$4*'Calc - research target (12m)'!$E$32/(1+$A5)^('Calc - research target (12m)'!$B$16-'Calc - research target (12m)'!$B$13))-'Calc - research target (12m)'!$B$50-'Calc - research target (12m)'!$B$51+'Calc - research target (12m)'!$B$52)/'Calc - research target (12m)'!$B$53
A6: =Valuation!$B$51+(-0.005) | B6: =((SUMPRODUCT('Calc - research target (12m)'!$C$31:$E$31,'Calc - research target (12m)'!$C$35:$E$35,(1+$A6)^(-('Calc - research target (12m)'!$C$19:$E$19-'Calc - research target (12m)'!$B$13)))+B$4*'Calc - research target (12m)'!$E$32/(1+$A6)^('Calc - research target (12m)'!$B$16-'Calc - research target (12m)'!$B$13))-'Calc - research target (12m)'!$B$50-'Calc - research target (12m)'!$B$51+'Calc - research target (12m)'!$B$52)/'Calc - research target (12m)'!$B$53 | C6: =((SUMPRODUCT('Calc - research target (12m)'!$C$31:$E$31,'Calc - research target (12m)'!$C$35:$E$35,(1+$A6)^(-('Calc - research target (12m)'!$C$19:$E$19-'Calc - research target (12m)'!$B$13)))+C$4*'Calc - research target (12m)'!$E$32/(1+$A6)^('Calc - research target (12m)'!$B$16-'Calc - research target (12m)'!$B$13))-'Calc - research target (12m)'!$B$50-'Calc - research target (12m)'!$B$51+'Calc - research target (12m)'!$B$52)/'Calc - research target (12m)'!$B$53 | D6: =((SUMPRODUCT('Calc - research target (12m)'!$C$31:$E$31,'Calc - research target (12m)'!$C$35:$E$35,(1+$A6)^(-('Calc - research target (12m)'!$C$19:$E$19-'Calc - research target (12m)'!$B$13)))+D$4*'Calc - research target (12m)'!$E$32/(1+$A6)^('Calc - research target (12m)'!$B$16-'Calc - research target (12m)'!$B$13))-'Calc - research target (12m)'!$B$50-'Calc - research target (12m)'!$B$51+'Calc - research target (12m)'!$B$52)/'Calc - research target (12m)'!$B$53 | E6: =((SUMPRODUCT('Calc - research target (12m)'!$C$31:$E$31,'Calc - research target (12m)'!$C$35:$E$35,(1+$A6)^(-('Calc - research target (12m)'!$C$19:$E$19-'Calc - research target (12m)'!$B$13)))+E$4*'Calc - research target (12m)'!$E$32/(1+$A6)^('Calc - research target (12m)'!$B$16-'Calc - research target (12m)'!$B$13))-'Calc - research target (12m)'!$B$50-'Calc - research target (12m)'!$B$51+'Calc - research target (12m)'!$B$52)/'Calc - research target (12m)'!$B$53 | F6: =((SUMPRODUCT('Calc - research target (12m)'!$C$31:$E$31,'Calc - research target (12m)'!$C$35:$E$35,(1+$A6)^(-('Calc - research target (12m)'!$C$19:$E$19-'Calc - research target (12m)'!$B$13)))+F$4*'Calc - research target (12m)'!$E$32/(1+$A6)^('Calc - research target (12m)'!$B$16-'Calc - research target (12m)'!$B$13))-'Calc - research target (12m)'!$B$50-'Calc - research target (12m)'!$B$51+'Calc - research target (12m)'!$B$52)/'Calc - research target (12m)'!$B$53
A7: =Valuation!$B$51+(0) | B7: =((SUMPRODUCT('Calc - research target (12m)'!$C$31:$E$31,'Calc - research target (12m)'!$C$35:$E$35,(1+$A7)^(-('Calc - research target (12m)'!$C$19:$E$19-'Calc - research target (12m)'!$B$13)))+B$4*'Calc - research target (12m)'!$E$32/(1+$A7)^('Calc - research target (12m)'!$B$16-'Calc - research target (12m)'!$B$13))-'Calc - research target (12m)'!$B$50-'Calc - research target (12m)'!$B$51+'Calc - research target (12m)'!$B$52)/'Calc - research target (12m)'!$B$53 | C7: =((SUMPRODUCT('Calc - research target (12m)'!$C$31:$E$31,'Calc - research target (12m)'!$C$35:$E$35,(1+$A7)^(-('Calc - research target (12m)'!$C$19:$E$19-'Calc - research target (12m)'!$B$13)))+C$4*'Calc - research target (12m)'!$E$32/(1+$A7)^('Calc - research target (12m)'!$B$16-'Calc - research target (12m)'!$B$13))-'Calc - research target (12m)'!$B$50-'Calc - research target (12m)'!$B$51+'Calc - research target (12m)'!$B$52)/'Calc - research target (12m)'!$B$53 | D7: =((SUMPRODUCT('Calc - research target (12m)'!$C$31:$E$31,'Calc - research target (12m)'!$C$35:$E$35,(1+$A7)^(-('Calc - research target (12m)'!$C$19:$E$19-'Calc - research target (12m)'!$B$13)))+D$4*'Calc - research target (12m)'!$E$32/(1+$A7)^('Calc - research target (12m)'!$B$16-'Calc - research target (12m)'!$B$13))-'Calc - research target (12m)'!$B$50-'Calc - research target (12m)'!$B$51+'Calc - research target (12m)'!$B$52)/'Calc - research target (12m)'!$B$53 | E7: =((SUMPRODUCT('Calc - research target (12m)'!$C$31:$E$31,'Calc - research target (12m)'!$C$35:$E$35,(1+$A7)^(-('Calc - research target (12m)'!$C$19:$E$19-'Calc - research target (12m)'!$B$13)))+E$4*'Calc - research target (12m)'!$E$32/(1+$A7)^('Calc - research target (12m)'!$B$16-'Calc - research target (12m)'!$B$13))-'Calc - research target (12m)'!$B$50-'Calc - research target (12m)'!$B$51+'Calc - research target (12m)'!$B$52)/'Calc - research target (12m)'!$B$53 | F7: =((SUMPRODUCT('Calc - research target (12m)'!$C$31:$E$31,'Calc - research target (12m)'!$C$35:$E$35,(1+$A7)^(-('Calc - research target (12m)'!$C$19:$E$19-'Calc - research target (12m)'!$B$13)))+F$4*'Calc - research target (12m)'!$E$32/(1+$A7)^('Calc - research target (12m)'!$B$16-'Calc - research target (12m)'!$B$13))-'Calc - research target (12m)'!$B$50-'Calc - research target (12m)'!$B$51+'Calc - research target (12m)'!$B$52)/'Calc - research target (12m)'!$B$53
A8: =Valuation!$B$51+(0.005) | B8: =((SUMPRODUCT('Calc - research target (12m)'!$C$31:$E$31,'Calc - research target (12m)'!$C$35:$E$35,(1+$A8)^(-('Calc - research target (12m)'!$C$19:$E$19-'Calc - research target (12m)'!$B$13)))+B$4*'Calc - research target (12m)'!$E$32/(1+$A8)^('Calc - research target (12m)'!$B$16-'Calc - research target (12m)'!$B$13))-'Calc - research target (12m)'!$B$50-'Calc - research target (12m)'!$B$51+'Calc - research target (12m)'!$B$52)/'Calc - research target (12m)'!$B$53 | C8: =((SUMPRODUCT('Calc - research target (12m)'!$C$31:$E$31,'Calc - research target (12m)'!$C$35:$E$35,(1+$A8)^(-('Calc - research target (12m)'!$C$19:$E$19-'Calc - research target (12m)'!$B$13)))+C$4*'Calc - research target (12m)'!$E$32/(1+$A8)^('Calc - research target (12m)'!$B$16-'Calc - research target (12m)'!$B$13))-'Calc - research target (12m)'!$B$50-'Calc - research target (12m)'!$B$51+'Calc - research target (12m)'!$B$52)/'Calc - research target (12m)'!$B$53 | D8: =((SUMPRODUCT('Calc - research target (12m)'!$C$31:$E$31,'Calc - research target (12m)'!$C$35:$E$35,(1+$A8)^(-('Calc - research target (12m)'!$C$19:$E$19-'Calc - research target (12m)'!$B$13)))+D$4*'Calc - research target (12m)'!$E$32/(1+$A8)^('Calc - research target (12m)'!$B$16-'Calc - research target (12m)'!$B$13))-'Calc - research target (12m)'!$B$50-'Calc - research target (12m)'!$B$51+'Calc - research target (12m)'!$B$52)/'Calc - research target (12m)'!$B$53 | E8: =((SUMPRODUCT('Calc - research target (12m)'!$C$31:$E$31,'Calc - research target (12m)'!$C$35:$E$35,(1+$A8)^(-('Calc - research target (12m)'!$C$19:$E$19-'Calc - research target (12m)'!$B$13)))+E$4*'Calc - research target (12m)'!$E$32/(1+$A8)^('Calc - research target (12m)'!$B$16-'Calc - research target (12m)'!$B$13))-'Calc - research target (12m)'!$B$50-'Calc - research target (12m)'!$B$51+'Calc - research target (12m)'!$B$52)/'Calc - research target (12m)'!$B$53 | F8: =((SUMPRODUCT('Calc - research target (12m)'!$C$31:$E$31,'Calc - research target (12m)'!$C$35:$E$35,(1+$A8)^(-('Calc - research target (12m)'!$C$19:$E$19-'Calc - research target (12m)'!$B$13)))+F$4*'Calc - research target (12m)'!$E$32/(1+$A8)^('Calc - research target (12m)'!$B$16-'Calc - research target (12m)'!$B$13))-'Calc - research target (12m)'!$B$50-'Calc - research target (12m)'!$B$51+'Calc - research target (12m)'!$B$52)/'Calc - research target (12m)'!$B$53
A9: =Valuation!$B$51+(0.01) | B9: =((SUMPRODUCT('Calc - research target (12m)'!$C$31:$E$31,'Calc - research target (12m)'!$C$35:$E$35,(1+$A9)^(-('Calc - research target (12m)'!$C$19:$E$19-'Calc - research target (12m)'!$B$13)))+B$4*'Calc - research target (12m)'!$E$32/(1+$A9)^('Calc - research target (12m)'!$B$16-'Calc - research target (12m)'!$B$13))-'Calc - research target (12m)'!$B$50-'Calc - research target (12m)'!$B$51+'Calc - research target (12m)'!$B$52)/'Calc - research target (12m)'!$B$53 | C9: =((SUMPRODUCT('Calc - research target (12m)'!$C$31:$E$31,'Calc - research target (12m)'!$C$35:$E$35,(1+$A9)^(-('Calc - research target (12m)'!$C$19:$E$19-'Calc - research target (12m)'!$B$13)))+C$4*'Calc - research target (12m)'!$E$32/(1+$A9)^('Calc - research target (12m)'!$B$16-'Calc - research target (12m)'!$B$13))-'Calc - research target (12m)'!$B$50-'Calc - research target (12m)'!$B$51+'Calc - research target (12m)'!$B$52)/'Calc - research target (12m)'!$B$53 | D9: =((SUMPRODUCT('Calc - research target (12m)'!$C$31:$E$31,'Calc - research target (12m)'!$C$35:$E$35,(1+$A9)^(-('Calc - research target (12m)'!$C$19:$E$19-'Calc - research target (12m)'!$B$13)))+D$4*'Calc - research target (12m)'!$E$32/(1+$A9)^('Calc - research target (12m)'!$B$16-'Calc - research target (12m)'!$B$13))-'Calc - research target (12m)'!$B$50-'Calc - research target (12m)'!$B$51+'Calc - research target (12m)'!$B$52)/'Calc - research target (12m)'!$B$53 | E9: =((SUMPRODUCT('Calc - research target (12m)'!$C$31:$E$31,'Calc - research target (12m)'!$C$35:$E$35,(1+$A9)^(-('Calc - research target (12m)'!$C$19:$E$19-'Calc - research target (12m)'!$B$13)))+E$4*'Calc - research target (12m)'!$E$32/(1+$A9)^('Calc - research target (12m)'!$B$16-'Calc - research target (12m)'!$B$13))-'Calc - research target (12m)'!$B$50-'Calc - research target (12m)'!$B$51+'Calc - research target (12m)'!$B$52)/'Calc - research target (12m)'!$B$53 | F9: =((SUMPRODUCT('Calc - research target (12m)'!$C$31:$E$31,'Calc - research target (12m)'!$C$35:$E$35,(1+$A9)^(-('Calc - research target (12m)'!$C$19:$E$19-'Calc - research target (12m)'!$B$13)))+F$4*'Calc - research target (12m)'!$E$32/(1+$A9)^('Calc - research target (12m)'!$B$16-'Calc - research target (12m)'!$B$13))-'Calc - research target (12m)'!$B$50-'Calc - research target (12m)'!$B$51+'Calc - research target (12m)'!$B$52)/'Calc - research target (12m)'!$B$53
A11: Research target (12m) per share: P/E multiple (down) x stated EPS (across)
A12: Multiple \ metric | B12: =Valuation!F70*0.9 | C12: =Valuation!F70*0.95 | D12: =Valuation!F70*1.0 | E12: =Valuation!F70*1.05 | F12: =Valuation!F70*1.1
A13: =Valuation!$B$70+(-3) | B13: =((SUMPRODUCT('Calc - research target (12m)'!$F$67:$F$69,'Calc - research target (12m)'!$G$67:$G$69)-'Calc - research target (12m)'!$F$68*'Calc - research target (12m)'!$G$68)+'Calc - research target (12m)'!$G$68*($A13*B$12+'Calc - research target (12m)'!$B$52/'Calc - research target (12m)'!$B$53))/SUM('Calc - research target (12m)'!$G$67:$G$69) | C13: =((SUMPRODUCT('Calc - research target (12m)'!$F$67:$F$69,'Calc - research target (12m)'!$G$67:$G$69)-'Calc - research target (12m)'!$F$68*'Calc - research target (12m)'!$G$68)+'Calc - research target (12m)'!$G$68*($A13*C$12+'Calc - research target (12m)'!$B$52/'Calc - research target (12m)'!$B$53))/SUM('Calc - research target (12m)'!$G$67:$G$69) | D13: =((SUMPRODUCT('Calc - research target (12m)'!$F$67:$F$69,'Calc - research target (12m)'!$G$67:$G$69)-'Calc - research target (12m)'!$F$68*'Calc - research target (12m)'!$G$68)+'Calc - research target (12m)'!$G$68*($A13*D$12+'Calc - research target (12m)'!$B$52/'Calc - research target (12m)'!$B$53))/SUM('Calc - research target (12m)'!$G$67:$G$69) | E13: =((SUMPRODUCT('Calc - research target (12m)'!$F$67:$F$69,'Calc - research target (12m)'!$G$67:$G$69)-'Calc - research target (12m)'!$F$68*'Calc - research target (12m)'!$G$68)+'Calc - research target (12m)'!$G$68*($A13*E$12+'Calc - research target (12m)'!$B$52/'Calc - research target (12m)'!$B$53))/SUM('Calc - research target (12m)'!$G$67:$G$69) | F13: =((SUMPRODUCT('Calc - research target (12m)'!$F$67:$F$69,'Calc - research target (12m)'!$G$67:$G$69)-'Calc - research target (12m)'!$F$68*'Calc - research target (12m)'!$G$68)+'Calc - research target (12m)'!$G$68*($A13*F$12+'Calc - research target (12m)'!$B$52/'Calc - research target (12m)'!$B$53))/SUM('Calc - research target (12m)'!$G$67:$G$69)
A14: =Valuation!$B$70+(-2) | B14: =((SUMPRODUCT('Calc - research target (12m)'!$F$67:$F$69,'Calc - research target (12m)'!$G$67:$G$69)-'Calc - research target (12m)'!$F$68*'Calc - research target (12m)'!$G$68)+'Calc - research target (12m)'!$G$68*($A14*B$12+'Calc - research target (12m)'!$B$52/'Calc - research target (12m)'!$B$53))/SUM('Calc - research target (12m)'!$G$67:$G$69) | C14: =((SUMPRODUCT('Calc - research target (12m)'!$F$67:$F$69,'Calc - research target (12m)'!$G$67:$G$69)-'Calc - research target (12m)'!$F$68*'Calc - research target (12m)'!$G$68)+'Calc - research target (12m)'!$G$68*($A14*C$12+'Calc - research target (12m)'!$B$52/'Calc - research target (12m)'!$B$53))/SUM('Calc - research target (12m)'!$G$67:$G$69) | D14: =((SUMPRODUCT('Calc - research target (12m)'!$F$67:$F$69,'Calc - research target (12m)'!$G$67:$G$69)-'Calc - research target (12m)'!$F$68*'Calc - research target (12m)'!$G$68)+'Calc - research target (12m)'!$G$68*($A14*D$12+'Calc - research target (12m)'!$B$52/'Calc - research target (12m)'!$B$53))/SUM('Calc - research target (12m)'!$G$67:$G$69) | E14: =((SUMPRODUCT('Calc - research target (12m)'!$F$67:$F$69,'Calc - research target (12m)'!$G$67:$G$69)-'Calc - research target (12m)'!$F$68*'Calc - research target (12m)'!$G$68)+'Calc - research target (12m)'!$G$68*($A14*E$12+'Calc - research target (12m)'!$B$52/'Calc - research target (12m)'!$B$53))/SUM('Calc - research target (12m)'!$G$67:$G$69) | F14: =((SUMPRODUCT('Calc - research target (12m)'!$F$67:$F$69,'Calc - research target (12m)'!$G$67:$G$69)-'Calc - research target (12m)'!$F$68*'Calc - research target (12m)'!$G$68)+'Calc - research target (12m)'!$G$68*($A14*F$12+'Calc - research target (12m)'!$B$52/'Calc - research target (12m)'!$B$53))/SUM('Calc - research target (12m)'!$G$67:$G$69)
A15: =Valuation!$B$70+(-1) | B15: =((SUMPRODUCT('Calc - research target (12m)'!$F$67:$F$69,'Calc - research target (12m)'!$G$67:$G$69)-'Calc - research target (12m)'!$F$68*'Calc - research target (12m)'!$G$68)+'Calc - research target (12m)'!$G$68*($A15*B$12+'Calc - research target (12m)'!$B$52/'Calc - research target (12m)'!$B$53))/SUM('Calc - research target (12m)'!$G$67:$G$69) | C15: =((SUMPRODUCT('Calc - research target (12m)'!$F$67:$F$69,'Calc - research target (12m)'!$G$67:$G$69)-'Calc - research target (12m)'!$F$68*'Calc - research target (12m)'!$G$68)+'Calc - research target (12m)'!$G$68*($A15*C$12+'Calc - research target (12m)'!$B$52/'Calc - research target (12m)'!$B$53))/SUM('Calc - research target (12m)'!$G$67:$G$69) | D15: =((SUMPRODUCT('Calc - research target (12m)'!$F$67:$F$69,'Calc - research target (12m)'!$G$67:$G$69)-'Calc - research target (12m)'!$F$68*'Calc - research target (12m)'!$G$68)+'Calc - research target (12m)'!$G$68*($A15*D$12+'Calc - research target (12m)'!$B$52/'Calc - research target (12m)'!$B$53))/SUM('Calc - research target (12m)'!$G$67:$G$69) | E15: =((SUMPRODUCT('Calc - research target (12m)'!$F$67:$F$69,'Calc - research target (12m)'!$G$67:$G$69)-'Calc - research target (12m)'!$F$68*'Calc - research target (12m)'!$G$68)+'Calc - research target (12m)'!$G$68*($A15*E$12+'Calc - research target (12m)'!$B$52/'Calc - research target (12m)'!$B$53))/SUM('Calc - research target (12m)'!$G$67:$G$69) | F15: =((SUMPRODUCT('Calc - research target (12m)'!$F$67:$F$69,'Calc - research target (12m)'!$G$67:$G$69)-'Calc - research target (12m)'!$F$68*'Calc - research target (12m)'!$G$68)+'Calc - research target (12m)'!$G$68*($A15*F$12+'Calc - research target (12m)'!$B$52/'Calc - research target (12m)'!$B$53))/SUM('Calc - research target (12m)'!$G$67:$G$69)
A16: =Valuation!$B$70+(0) | B16: =((SUMPRODUCT('Calc - research target (12m)'!$F$67:$F$69,'Calc - research target (12m)'!$G$67:$G$69)-'Calc - research target (12m)'!$F$68*'Calc - research target (12m)'!$G$68)+'Calc - research target (12m)'!$G$68*($A16*B$12+'Calc - research target (12m)'!$B$52/'Calc - research target (12m)'!$B$53))/SUM('Calc - research target (12m)'!$G$67:$G$69) | C16: =((SUMPRODUCT('Calc - research target (12m)'!$F$67:$F$69,'Calc - research target (12m)'!$G$67:$G$69)-'Calc - research target (12m)'!$F$68*'Calc - research target (12m)'!$G$68)+'Calc - research target (12m)'!$G$68*($A16*C$12+'Calc - research target (12m)'!$B$52/'Calc - research target (12m)'!$B$53))/SUM('Calc - research target (12m)'!$G$67:$G$69) | D16: =((SUMPRODUCT('Calc - research target (12m)'!$F$67:$F$69,'Calc - research target (12m)'!$G$67:$G$69)-'Calc - research target (12m)'!$F$68*'Calc - research target (12m)'!$G$68)+'Calc - research target (12m)'!$G$68*($A16*D$12+'Calc - research target (12m)'!$B$52/'Calc - research target (12m)'!$B$53))/SUM('Calc - research target (12m)'!$G$67:$G$69) | E16: =((SUMPRODUCT('Calc - research target (12m)'!$F$67:$F$69,'Calc - research target (12m)'!$G$67:$G$69)-'Calc - research target (12m)'!$F$68*'Calc - research target (12m)'!$G$68)+'Calc - research target (12m)'!$G$68*($A16*E$12+'Calc - research target (12m)'!$B$52/'Calc - research target (12m)'!$B$53))/SUM('Calc - research target (12m)'!$G$67:$G$69) | F16: =((SUMPRODUCT('Calc - research target (12m)'!$F$67:$F$69,'Calc - research target (12m)'!$G$67:$G$69)-'Calc - research target (12m)'!$F$68*'Calc - research target (12m)'!$G$68)+'Calc - research target (12m)'!$G$68*($A16*F$12+'Calc - research target (12m)'!$B$52/'Calc - research target (12m)'!$B$53))/SUM('Calc - research target (12m)'!$G$67:$G$69)
A17: =Valuation!$B$70+(1) | B17: =((SUMPRODUCT('Calc - research target (12m)'!$F$67:$F$69,'Calc - research target (12m)'!$G$67:$G$69)-'Calc - research target (12m)'!$F$68*'Calc - research target (12m)'!$G$68)+'Calc - research target (12m)'!$G$68*($A17*B$12+'Calc - research target (12m)'!$B$52/'Calc - research target (12m)'!$B$53))/SUM('Calc - research target (12m)'!$G$67:$G$69) | C17: =((SUMPRODUCT('Calc - research target (12m)'!$F$67:$F$69,'Calc - research target (12m)'!$G$67:$G$69)-'Calc - research target (12m)'!$F$68*'Calc - research target (12m)'!$G$68)+'Calc - research target (12m)'!$G$68*($A17*C$12+'Calc - research target (12m)'!$B$52/'Calc - research target (12m)'!$B$53))/SUM('Calc - research target (12m)'!$G$67:$G$69) | D17: =((SUMPRODUCT('Calc - research target (12m)'!$F$67:$F$69,'Calc - research target (12m)'!$G$67:$G$69)-'Calc - research target (12m)'!$F$68*'Calc - research target (12m)'!$G$68)+'Calc - research target (12m)'!$G$68*($A17*D$12+'Calc - research target (12m)'!$B$52/'Calc - research target (12m)'!$B$53))/SUM('Calc - research target (12m)'!$G$67:$G$69) | E17: =((SUMPRODUCT('Calc - research target (12m)'!$F$67:$F$69,'Calc - research target (12m)'!$G$67:$G$69)-'Calc - research target (12m)'!$F$68*'Calc - research target (12m)'!$G$68)+'Calc - research target (12m)'!$G$68*($A17*E$12+'Calc - research target (12m)'!$B$52/'Calc - research target (12m)'!$B$53))/SUM('Calc - research target (12m)'!$G$67:$G$69) | F17: =((SUMPRODUCT('Calc - research target (12m)'!$F$67:$F$69,'Calc - research target (12m)'!$G$67:$G$69)-'Calc - research target (12m)'!$F$68*'Calc - research target (12m)'!$G$68)+'Calc - research target (12m)'!$G$68*($A17*F$12+'Calc - research target (12m)'!$B$52/'Calc - research target (12m)'!$B$53))/SUM('Calc - research target (12m)'!$G$67:$G$69)
A18: =Valuation!$B$70+(2) | B18: =((SUMPRODUCT('Calc - research target (12m)'!$F$67:$F$69,'Calc - research target (12m)'!$G$67:$G$69)-'Calc - research target (12m)'!$F$68*'Calc - research target (12m)'!$G$68)+'Calc - research target (12m)'!$G$68*($A18*B$12+'Calc - research target (12m)'!$B$52/'Calc - research target (12m)'!$B$53))/SUM('Calc - research target (12m)'!$G$67:$G$69) | C18: =((SUMPRODUCT('Calc - research target (12m)'!$F$67:$F$69,'Calc - research target (12m)'!$G$67:$G$69)-'Calc - research target (12m)'!$F$68*'Calc - research target (12m)'!$G$68)+'Calc - research target (12m)'!$G$68*($A18*C$12+'Calc - research target (12m)'!$B$52/'Calc - research target (12m)'!$B$53))/SUM('Calc - research target (12m)'!$G$67:$G$69) | D18: =((SUMPRODUCT('Calc - research target (12m)'!$F$67:$F$69,'Calc - research target (12m)'!$G$67:$G$69)-'Calc - research target (12m)'!$F$68*'Calc - research target (12m)'!$G$68)+'Calc - research target (12m)'!$G$68*($A18*D$12+'Calc - research target (12m)'!$B$52/'Calc - research target (12m)'!$B$53))/SUM('Calc - research target (12m)'!$G$67:$G$69) | E18: =((SUMPRODUCT('Calc - research target (12m)'!$F$67:$F$69,'Calc - research target (12m)'!$G$67:$G$69)-'Calc - research target (12m)'!$F$68*'Calc - research target (12m)'!$G$68)+'Calc - research target (12m)'!$G$68*($A18*E$12+'Calc - research target (12m)'!$B$52/'Calc - research target (12m)'!$B$53))/SUM('Calc - research target (12m)'!$G$67:$G$69) | F18: =((SUMPRODUCT('Calc - research target (12m)'!$F$67:$F$69,'Calc - research target (12m)'!$G$67:$G$69)-'Calc - research target (12m)'!$F$68*'Calc - research target (12m)'!$G$68)+'Calc - research target (12m)'!$G$68*($A18*F$12+'Calc - research target (12m)'!$B$52/'Calc - research target (12m)'!$B$53))/SUM('Calc - research target (12m)'!$G$67:$G$69)
A19: =Valuation!$B$70+(3) | B19: =((SUMPRODUCT('Calc - research target (12m)'!$F$67:$F$69,'Calc - research target (12m)'!$G$67:$G$69)-'Calc - research target (12m)'!$F$68*'Calc - research target (12m)'!$G$68)+'Calc - research target (12m)'!$G$68*($A19*B$12+'Calc - research target (12m)'!$B$52/'Calc - research target (12m)'!$B$53))/SUM('Calc - research target (12m)'!$G$67:$G$69) | C19: =((SUMPRODUCT('Calc - research target (12m)'!$F$67:$F$69,'Calc - research target (12m)'!$G$67:$G$69)-'Calc - research target (12m)'!$F$68*'Calc - research target (12m)'!$G$68)+'Calc - research target (12m)'!$G$68*($A19*C$12+'Calc - research target (12m)'!$B$52/'Calc - research target (12m)'!$B$53))/SUM('Calc - research target (12m)'!$G$67:$G$69) | D19: =((SUMPRODUCT('Calc - research target (12m)'!$F$67:$F$69,'Calc - research target (12m)'!$G$67:$G$69)-'Calc - research target (12m)'!$F$68*'Calc - research target (12m)'!$G$68)+'Calc - research target (12m)'!$G$68*($A19*D$12+'Calc - research target (12m)'!$B$52/'Calc - research target (12m)'!$B$53))/SUM('Calc - research target (12m)'!$G$67:$G$69) | E19: =((SUMPRODUCT('Calc - research target (12m)'!$F$67:$F$69,'Calc - research target (12m)'!$G$67:$G$69)-'Calc - research target (12m)'!$F$68*'Calc - research target (12m)'!$G$68)+'Calc - research target (12m)'!$G$68*($A19*E$12+'Calc - research target (12m)'!$B$52/'Calc - research target (12m)'!$B$53))/SUM('Calc - research target (12m)'!$G$67:$G$69) | F19: =((SUMPRODUCT('Calc - research target (12m)'!$F$67:$F$69,'Calc - research target (12m)'!$G$67:$G$69)-'Calc - research target (12m)'!$F$68*'Calc - research target (12m)'!$G$68)+'Calc - research target (12m)'!$G$68*($A19*F$12+'Calc - research target (12m)'!$B$52/'Calc - research target (12m)'!$B$53))/SUM('Calc - research target (12m)'!$G$67:$G$69)
A22: FY2027E diluted EPS: revenue growth change in every year (down) x EBIT margin change (across)
A23: Growth Δ \ margin Δ | B23: -0.01 | C23: -0.005 | D23: 0 | E23: 0.005 | F23: 0.01
A24: -0.02 | B24: =(Valuation!$B$103*(1+Model!E12+$A24)*(1+Model!F12+$A24)*(Model!F14+B$23)+Valuation!$B$104*(1+Model!E16+$A24)*(1+Model!F16+$A24)*(Model!F18+B$23)+Valuation!$B$105*(1+Model!E20+$A24)*(1+Model!F20+$A24)*(Model!F22+B$23)+Valuation!$B$106*(1+Model!E24+$A24)*(1+Model!F24+$A24)*(Model!F26+B$23)+Model!F29+Model!F41)*(1-Model!F71)/Model!F48 | C24: =(Valuation!$B$103*(1+Model!E12+$A24)*(1+Model!F12+$A24)*(Model!F14+C$23)+Valuation!$B$104*(1+Model!E16+$A24)*(1+Model!F16+$A24)*(Model!F18+C$23)+Valuation!$B$105*(1+Model!E20+$A24)*(1+Model!F20+$A24)*(Model!F22+C$23)+Valuation!$B$106*(1+Model!E24+$A24)*(1+Model!F24+$A24)*(Model!F26+C$23)+Model!F29+Model!F41)*(1-Model!F71)/Model!F48 | D24: =(Valuation!$B$103*(1+Model!E12+$A24)*(1+Model!F12+$A24)*(Model!F14+D$23)+Valuation!$B$104*(1+Model!E16+$A24)*(1+Model!F16+$A24)*(Model!F18+D$23)+Valuation!$B$105*(1+Model!E20+$A24)*(1+Model!F20+$A24)*(Model!F22+D$23)+Valuation!$B$106*(1+Model!E24+$A24)*(1+Model!F24+$A24)*(Model!F26+D$23)+Model!F29+Model!F41)*(1-Model!F71)/Model!F48 | E24: =(Valuation!$B$103*(1+Model!E12+$A24)*(1+Model!F12+$A24)*(Model!F14+E$23)+Valuation!$B$104*(1+Model!E16+$A24)*(1+Model!F16+$A24)*(Model!F18+E$23)+Valuation!$B$105*(1+Model!E20+$A24)*(1+Model!F20+$A24)*(Model!F22+E$23)+Valuation!$B$106*(1+Model!E24+$A24)*(1+Model!F24+$A24)*(Model!F26+E$23)+Model!F29+Model!F41)*(1-Model!F71)/Model!F48 | F24: =(Valuation!$B$103*(1+Model!E12+$A24)*(1+Model!F12+$A24)*(Model!F14+F$23)+Valuation!$B$104*(1+Model!E16+$A24)*(1+Model!F16+$A24)*(Model!F18+F$23)+Valuation!$B$105*(1+Model!E20+$A24)*(1+Model!F20+$A24)*(Model!F22+F$23)+Valuation!$B$106*(1+Model!E24+$A24)*(1+Model!F24+$A24)*(Model!F26+F$23)+Model!F29+Model!F41)*(1-Model!F71)/Model!F48
A25: -0.01 | B25: =(Valuation!$B$103*(1+Model!E12+$A25)*(1+Model!F12+$A25)*(Model!F14+B$23)+Valuation!$B$104*(1+Model!E16+$A25)*(1+Model!F16+$A25)*(Model!F18+B$23)+Valuation!$B$105*(1+Model!E20+$A25)*(1+Model!F20+$A25)*(Model!F22+B$23)+Valuation!$B$106*(1+Model!E24+$A25)*(1+Model!F24+$A25)*(Model!F26+B$23)+Model!F29+Model!F41)*(1-Model!F71)/Model!F48 | C25: =(Valuation!$B$103*(1+Model!E12+$A25)*(1+Model!F12+$A25)*(Model!F14+C$23)+Valuation!$B$104*(1+Model!E16+$A25)*(1+Model!F16+$A25)*(Model!F18+C$23)+Valuation!$B$105*(1+Model!E20+$A25)*(1+Model!F20+$A25)*(Model!F22+C$23)+Valuation!$B$106*(1+Model!E24+$A25)*(1+Model!F24+$A25)*(Model!F26+C$23)+Model!F29+Model!F41)*(1-Model!F71)/Model!F48 | D25: =(Valuation!$B$103*(1+Model!E12+$A25)*(1+Model!F12+$A25)*(Model!F14+D$23)+Valuation!$B$104*(1+Model!E16+$A25)*(1+Model!F16+$A25)*(Model!F18+D$23)+Valuation!$B$105*(1+Model!E20+$A25)*(1+Model!F20+$A25)*(Model!F22+D$23)+Valuation!$B$106*(1+Model!E24+$A25)*(1+Model!F24+$A25)*(Model!F26+D$23)+Model!F29+Model!F41)*(1-Model!F71)/Model!F48 | E25: =(Valuation!$B$103*(1+Model!E12+$A25)*(1+Model!F12+$A25)*(Model!F14+E$23)+Valuation!$B$104*(1+Model!E16+$A25)*(1+Model!F16+$A25)*(Model!F18+E$23)+Valuation!$B$105*(1+Model!E20+$A25)*(1+Model!F20+$A25)*(Model!F22+E$23)+Valuation!$B$106*(1+Model!E24+$A25)*(1+Model!F24+$A25)*(Model!F26+E$23)+Model!F29+Model!F41)*(1-Model!F71)/Model!F48 | F25: =(Valuation!$B$103*(1+Model!E12+$A25)*(1+Model!F12+$A25)*(Model!F14+F$23)+Valuation!$B$104*(1+Model!E16+$A25)*(1+Model!F16+$A25)*(Model!F18+F$23)+Valuation!$B$105*(1+Model!E20+$A25)*(1+Model!F20+$A25)*(Model!F22+F$23)+Valuation!$B$106*(1+Model!E24+$A25)*(1+Model!F24+$A25)*(Model!F26+F$23)+Model!F29+Model!F41)*(1-Model!F71)/Model!F48
A26: 0 | B26: =(Valuation!$B$103*(1+Model!E12+$A26)*(1+Model!F12+$A26)*(Model!F14+B$23)+Valuation!$B$104*(1+Model!E16+$A26)*(1+Model!F16+$A26)*(Model!F18+B$23)+Valuation!$B$105*(1+Model!E20+$A26)*(1+Model!F20+$A26)*(Model!F22+B$23)+Valuation!$B$106*(1+Model!E24+$A26)*(1+Model!F24+$A26)*(Model!F26+B$23)+Model!F29+Model!F41)*(1-Model!F71)/Model!F48 | C26: =(Valuation!$B$103*(1+Model!E12+$A26)*(1+Model!F12+$A26)*(Model!F14+C$23)+Valuation!$B$104*(1+Model!E16+$A26)*(1+Model!F16+$A26)*(Model!F18+C$23)+Valuation!$B$105*(1+Model!E20+$A26)*(1+Model!F20+$A26)*(Model!F22+C$23)+Valuation!$B$106*(1+Model!E24+$A26)*(1+Model!F24+$A26)*(Model!F26+C$23)+Model!F29+Model!F41)*(1-Model!F71)/Model!F48 | D26: =(Valuation!$B$103*(1+Model!E12+$A26)*(1+Model!F12+$A26)*(Model!F14+D$23)+Valuation!$B$104*(1+Model!E16+$A26)*(1+Model!F16+$A26)*(Model!F18+D$23)+Valuation!$B$105*(1+Model!E20+$A26)*(1+Model!F20+$A26)*(Model!F22+D$23)+Valuation!$B$106*(1+Model!E24+$A26)*(1+Model!F24+$A26)*(Model!F26+D$23)+Model!F29+Model!F41)*(1-Model!F71)/Model!F48 | E26: =(Valuation!$B$103*(1+Model!E12+$A26)*(1+Model!F12+$A26)*(Model!F14+E$23)+Valuation!$B$104*(1+Model!E16+$A26)*(1+Model!F16+$A26)*(Model!F18+E$23)+Valuation!$B$105*(1+Model!E20+$A26)*(1+Model!F20+$A26)*(Model!F22+E$23)+Valuation!$B$106*(1+Model!E24+$A26)*(1+Model!F24+$A26)*(Model!F26+E$23)+Model!F29+Model!F41)*(1-Model!F71)/Model!F48 | F26: =(Valuation!$B$103*(1+Model!E12+$A26)*(1+Model!F12+$A26)*(Model!F14+F$23)+Valuation!$B$104*(1+Model!E16+$A26)*(1+Model!F16+$A26)*(Model!F18+F$23)+Valuation!$B$105*(1+Model!E20+$A26)*(1+Model!F20+$A26)*(Model!F22+F$23)+Valuation!$B$106*(1+Model!E24+$A26)*(1+Model!F24+$A26)*(Model!F26+F$23)+Model!F29+Model!F41)*(1-Model!F71)/Model!F48
A27: 0.01 | B27: =(Valuation!$B$103*(1+Model!E12+$A27)*(1+Model!F12+$A27)*(Model!F14+B$23)+Valuation!$B$104*(1+Model!E16+$A27)*(1+Model!F16+$A27)*(Model!F18+B$23)+Valuation!$B$105*(1+Model!E20+$A27)*(1+Model!F20+$A27)*(Model!F22+B$23)+Valuation!$B$106*(1+Model!E24+$A27)*(1+Model!F24+$A27)*(Model!F26+B$23)+Model!F29+Model!F41)*(1-Model!F71)/Model!F48 | C27: =(Valuation!$B$103*(1+Model!E12+$A27)*(1+Model!F12+$A27)*(Model!F14+C$23)+Valuation!$B$104*(1+Model!E16+$A27)*(1+Model!F16+$A27)*(Model!F18+C$23)+Valuation!$B$105*(1+Model!E20+$A27)*(1+Model!F20+$A27)*(Model!F22+C$23)+Valuation!$B$106*(1+Model!E24+$A27)*(1+Model!F24+$A27)*(Model!F26+C$23)+Model!F29+Model!F41)*(1-Model!F71)/Model!F48 | D27: =(Valuation!$B$103*(1+Model!E12+$A27)*(1+Model!F12+$A27)*(Model!F14+D$23)+Valuation!$B$104*(1+Model!E16+$A27)*(1+Model!F16+$A27)*(Model!F18+D$23)+Valuation!$B$105*(1+Model!E20+$A27)*(1+Model!F20+$A27)*(Model!F22+D$23)+Valuation!$B$106*(1+Model!E24+$A27)*(1+Model!F24+$A27)*(Model!F26+D$23)+Model!F29+Model!F41)*(1-Model!F71)/Model!F48 | E27: =(Valuation!$B$103*(1+Model!E12+$A27)*(1+Model!F12+$A27)*(Model!F14+E$23)+Valuation!$B$104*(1+Model!E16+$A27)*(1+Model!F16+$A27)*(Model!F18+E$23)+Valuation!$B$105*(1+Model!E20+$A27)*(1+Model!F20+$A27)*(Model!F22+E$23)+Valuation!$B$106*(1+Model!E24+$A27)*(1+Model!F24+$A27)*(Model!F26+E$23)+Model!F29+Model!F41)*(1-Model!F71)/Model!F48 | F27: =(Valuation!$B$103*(1+Model!E12+$A27)*(1+Model!F12+$A27)*(Model!F14+F$23)+Valuation!$B$104*(1+Model!E16+$A27)*(1+Model!F16+$A27)*(Model!F18+F$23)+Valuation!$B$105*(1+Model!E20+$A27)*(1+Model!F20+$A27)*(Model!F22+F$23)+Valuation!$B$106*(1+Model!E24+$A27)*(1+Model!F24+$A27)*(Model!F26+F$23)+Model!F29+Model!F41)*(1-Model!F71)/Model!F48
A28: 0.02 | B28: =(Valuation!$B$103*(1+Model!E12+$A28)*(1+Model!F12+$A28)*(Model!F14+B$23)+Valuation!$B$104*(1+Model!E16+$A28)*(1+Model!F16+$A28)*(Model!F18+B$23)+Valuation!$B$105*(1+Model!E20+$A28)*(1+Model!F20+$A28)*(Model!F22+B$23)+Valuation!$B$106*(1+Model!E24+$A28)*(1+Model!F24+$A28)*(Model!F26+B$23)+Model!F29+Model!F41)*(1-Model!F71)/Model!F48 | C28: =(Valuation!$B$103*(1+Model!E12+$A28)*(1+Model!F12+$A28)*(Model!F14+C$23)+Valuation!$B$104*(1+Model!E16+$A28)*(1+Model!F16+$A28)*(Model!F18+C$23)+Valuation!$B$105*(1+Model!E20+$A28)*(1+Model!F20+$A28)*(Model!F22+C$23)+Valuation!$B$106*(1+Model!E24+$A28)*(1+Model!F24+$A28)*(Model!F26+C$23)+Model!F29+Model!F41)*(1-Model!F71)/Model!F48 | D28: =(Valuation!$B$103*(1+Model!E12+$A28)*(1+Model!F12+$A28)*(Model!F14+D$23)+Valuation!$B$104*(1+Model!E16+$A28)*(1+Model!F16+$A28)*(Model!F18+D$23)+Valuation!$B$105*(1+Model!E20+$A28)*(1+Model!F20+$A28)*(Model!F22+D$23)+Valuation!$B$106*(1+Model!E24+$A28)*(1+Model!F24+$A28)*(Model!F26+D$23)+Model!F29+Model!F41)*(1-Model!F71)/Model!F48 | E28: =(Valuation!$B$103*(1+Model!E12+$A28)*(1+Model!F12+$A28)*(Model!F14+E$23)+Valuation!$B$104*(1+Model!E16+$A28)*(1+Model!F16+$A28)*(Model!F18+E$23)+Valuation!$B$105*(1+Model!E20+$A28)*(1+Model!F20+$A28)*(Model!F22+E$23)+Valuation!$B$106*(1+Model!E24+$A28)*(1+Model!F24+$A28)*(Model!F26+E$23)+Model!F29+Model!F41)*(1-Model!F71)/Model!F48 | F28: =(Valuation!$B$103*(1+Model!E12+$A28)*(1+Model!F12+$A28)*(Model!F14+F$23)+Valuation!$B$104*(1+Model!E16+$A28)*(1+Model!F16+$A28)*(Model!F18+F$23)+Valuation!$B$105*(1+Model!E20+$A28)*(1+Model!F20+$A28)*(Model!F22+F$23)+Valuation!$B$106*(1+Model!E24+$A28)*(1+Model!F24+$A28)*(Model!F26+F$23)+Model!F29+Model!F41)*(1-Model!F71)/Model!F48
A30: Net interest and the share count are held at the base case in table 3.

Sheet Distribution
A1: GOOGL: 12-month distribution (mix of lognormals around each scenario value)
A3: Scenario | B3: Probability | C3: Value at target date | D3: Story
A4: bear | B4: =Valuation!B98 | C4: ='Calc - bear'!$F$70 | D4: =Valuation!J98
A5: base | B5: =Valuation!B99 | C5: ='Calc - base'!$F$70 | D5: =Valuation!J99
A6: bull | B6: =Valuation!B100 | C6: ='Calc - bull'!$F$70 | D6: =Valuation!J100
A8: Probabilities sum to | B8: =SUM(B4:B6)
A9: Spread within each scenario | B9: =Valuation!$B$66
A10: Probability-weighted mean | B10: =($B$4*$C$4+$B$5*$C$5+$B$6*$C$6)*EXP($B$9^2/2)
A12: Quantile | B12: Price
A13: Median (model target) | B13: =SQRT(A60*B60)
A14: 10th percentile | B14: =SQRT(D60*E60)
A15: 25th percentile | B15: =SQRT(G60*H60)
A16: 75th percentile | B16: =SQRT(J60*K60)
A17: 90th percentile | B17: =SQRT(M60*N60)
A19: Each quantile solved by bisection (block: low, high, probability above the midpoint)
A20: Median (model target): low | B20: high | C20: P(above mid) | D20: 10th percentile: low | E20: high | F20: P(above mid) | G20: 25th percentile: low | H20: high | I20: P(above mid) | J20: 75th percentile: low | K20: high | L20: P(above mid) | M20: 90th percentile: low | N20: high | O20: P(above mid)
A21: =MIN($C$4,$C$5,$C$6)*0.2 | B21: =MAX($C$4,$C$5,$C$6)*4 | C21: =SUMPRODUCT($B$4:$B$6,1-NORMSDIST((LN(SQRT(A21*B21))-LN($C$4:$C$6))/$B$9)) | D21: =MIN($C$4,$C$5,$C$6)*0.2 | E21: =MAX($C$4,$C$5,$C$6)*4 | F21: =SUMPRODUCT($B$4:$B$6,1-NORMSDIST((LN(SQRT(D21*E21))-LN($C$4:$C$6))/$B$9)) | G21: =MIN($C$4,$C$5,$C$6)*0.2 | H21: =MAX($C$4,$C$5,$C$6)*4 | I21: =SUMPRODUCT($B$4:$B$6,1-NORMSDIST((LN(SQRT(G21*H21))-LN($C$4:$C$6))/$B$9)) | J21: =MIN($C$4,$C$5,$C$6)*0.2 | K21: =MAX($C$4,$C$5,$C$6)*4 | L21: =SUMPRODUCT($B$4:$B$6,1-NORMSDIST((LN(SQRT(J21*K21))-LN($C$4:$C$6))/$B$9)) | M21: =MIN($C$4,$C$5,$C$6)*0.2 | N21: =MAX($C$4,$C$5,$C$6)*4 | O21: =SUMPRODUCT($B$4:$B$6,1-NORMSDIST((LN(SQRT(M21*N21))-LN($C$4:$C$6))/$B$9))
A22: =IF(C21>0.5,SQRT(A21*B21),A21) | B22: =IF(C21>0.5,B21,SQRT(A21*B21)) | C22: =SUMPRODUCT($B$4:$B$6,1-NORMSDIST((LN(SQRT(A22*B22))-LN($C$4:$C$6))/$B$9)) | D22: =IF(F21>0.9,SQRT(D21*E21),D21) | E22: =IF(F21>0.9,E21,SQRT(D21*E21)) | F22: =SUMPRODUCT($B$4:$B$6,1-NORMSDIST((LN(SQRT(D22*E22))-LN($C$4:$C$6))/$B$9)) | G22: =IF(I21>0.75,SQRT(G21*H21),G21) | H22: =IF(I21>0.75,H21,SQRT(G21*H21)) | I22: =SUMPRODUCT($B$4:$B$6,1-NORMSDIST((LN(SQRT(G22*H22))-LN($C$4:$C$6))/$B$9)) | J22: =IF(L21>0.25,SQRT(J21*K21),J21) | K22: =IF(L21>0.25,K21,SQRT(J21*K21)) | L22: =SUMPRODUCT($B$4:$B$6,1-NORMSDIST((LN(SQRT(J22*K22))-LN($C$4:$C$6))/$B$9)) | M22: =IF(O21>0.09999999999999998,SQRT(M21*N21),M21) | N22: =IF(O21>0.09999999999999998,N21,SQRT(M21*N21)) | O22: =SUMPRODUCT($B$4:$B$6,1-NORMSDIST((LN(SQRT(M22*N22))-LN($C$4:$C$6))/$B$9))
A23: =IF(C22>0.5,SQRT(A22*B22),A22) | B23: =IF(C22>0.5,B22,SQRT(A22*B22)) | C23: =SUMPRODUCT($B$4:$B$6,1-NORMSDIST((LN(SQRT(A23*B23))-LN($C$4:$C$6))/$B$9)) | D23: =IF(F22>0.9,SQRT(D22*E22),D22) | E23: =IF(F22>0.9,E22,SQRT(D22*E22)) | F23: =SUMPRODUCT($B$4:$B$6,1-NORMSDIST((LN(SQRT(D23*E23))-LN($C$4:$C$6))/$B$9)) | G23: =IF(I22>0.75,SQRT(G22*H22),G22) | H23: =IF(I22>0.75,H22,SQRT(G22*H22)) | I23: =SUMPRODUCT($B$4:$B$6,1-NORMSDIST((LN(SQRT(G23*H23))-LN($C$4:$C$6))/$B$9)) | J23: =IF(L22>0.25,SQRT(J22*K22),J22) | K23: =IF(L22>0.25,K22,SQRT(J22*K22)) | L23: =SUMPRODUCT($B$4:$B$6,1-NORMSDIST((LN(SQRT(J23*K23))-LN($C$4:$C$6))/$B$9)) | M23: =IF(O22>0.09999999999999998,SQRT(M22*N22),M22) | N23: =IF(O22>0.09999999999999998,N22,SQRT(M22*N22)) | O23: =SUMPRODUCT($B$4:$B$6,1-NORMSDIST((LN(SQRT(M23*N23))-LN($C$4:$C$6))/$B$9))
A24: =IF(C23>0.5,SQRT(A23*B23),A23) | B24: =IF(C23>0.5,B23,SQRT(A23*B23)) | C24: =SUMPRODUCT($B$4:$B$6,1-NORMSDIST((LN(SQRT(A24*B24))-LN($C$4:$C$6))/$B$9)) | D24: =IF(F23>0.9,SQRT(D23*E23),D23) | E24: =IF(F23>0.9,E23,SQRT(D23*E23)) | F24: =SUMPRODUCT($B$4:$B$6,1-NORMSDIST((LN(SQRT(D24*E24))-LN($C$4:$C$6))/$B$9)) | G24: =IF(I23>0.75,SQRT(G23*H23),G23) | H24: =IF(I23>0.75,H23,SQRT(G23*H23)) | I24: =SUMPRODUCT($B$4:$B$6,1-NORMSDIST((LN(SQRT(G24*H24))-LN($C$4:$C$6))/$B$9)) | J24: =IF(L23>0.25,SQRT(J23*K23),J23) | K24: =IF(L23>0.25,K23,SQRT(J23*K23)) | L24: =SUMPRODUCT($B$4:$B$6,1-NORMSDIST((LN(SQRT(J24*K24))-LN($C$4:$C$6))/$B$9)) | M24: =IF(O23>0.09999999999999998,SQRT(M23*N23),M23) | N24: =IF(O23>0.09999999999999998,N23,SQRT(M23*N23)) | O24: =SUMPRODUCT($B$4:$B$6,1-NORMSDIST((LN(SQRT(M24*N24))-LN($C$4:$C$6))/$B$9))
A25: =IF(C24>0.5,SQRT(A24*B24),A24) | B25: =IF(C24>0.5,B24,SQRT(A24*B24)) | C25: =SUMPRODUCT($B$4:$B$6,1-NORMSDIST((LN(SQRT(A25*B25))-LN($C$4:$C$6))/$B$9)) | D25: =IF(F24>0.9,SQRT(D24*E24),D24) | E25: =IF(F24>0.9,E24,SQRT(D24*E24)) | F25: =SUMPRODUCT($B$4:$B$6,1-NORMSDIST((LN(SQRT(D25*E25))-LN($C$4:$C$6))/$B$9)) | G25: =IF(I24>0.75,SQRT(G24*H24),G24) | H25: =IF(I24>0.75,H24,SQRT(G24*H24)) | I25: =SUMPRODUCT($B$4:$B$6,1-NORMSDIST((LN(SQRT(G25*H25))-LN($C$4:$C$6))/$B$9)) | J25: =IF(L24>0.25,SQRT(J24*K24),J24) | K25: =IF(L24>0.25,K24,SQRT(J24*K24)) | L25: =SUMPRODUCT($B$4:$B$6,1-NORMSDIST((LN(SQRT(J25*K25))-LN($C$4:$C$6))/$B$9)) | M25: =IF(O24>0.09999999999999998,SQRT(M24*N24),M24) | N25: =IF(O24>0.09999999999999998,N24,SQRT(M24*N24)) | O25: =SUMPRODUCT($B$4:$B$6,1-NORMSDIST((LN(SQRT(M25*N25))-LN($C$4:$C$6))/$B$9))
A26: =IF(C25>0.5,SQRT(A25*B25),A25) | B26: =IF(C25>0.5,B25,SQRT(A25*B25)) | C26: =SUMPRODUCT($B$4:$B$6,1-NORMSDIST((LN(SQRT(A26*B26))-LN($C$4:$C$6))/$B$9)) | D26: =IF(F25>0.9,SQRT(D25*E25),D25) | E26: =IF(F25>0.9,E25,SQRT(D25*E25)) | F26: =SUMPRODUCT($B$4:$B$6,1-NORMSDIST((LN(SQRT(D26*E26))-LN($C$4:$C$6))/$B$9)) | G26: =IF(I25>0.75,SQRT(G25*H25),G25) | H26: =IF(I25>0.75,H25,SQRT(G25*H25)) | I26: =SUMPRODUCT($B$4:$B$6,1-NORMSDIST((LN(SQRT(G26*H26))-LN($C$4:$C$6))/$B$9)) | J26: =IF(L25>0.25,SQRT(J25*K25),J25) | K26: =IF(L25>0.25,K25,SQRT(J25*K25)) | L26: =SUMPRODUCT($B$4:$B$6,1-NORMSDIST((LN(SQRT(J26*K26))-LN($C$4:$C$6))/$B$9)) | M26: =IF(O25>0.09999999999999998,SQRT(M25*N25),M25) | N26: =IF(O25>0.09999999999999998,N25,SQRT(M25*N25)) | O26: =SUMPRODUCT($B$4:$B$6,1-NORMSDIST((LN(SQRT(M26*N26))-LN($C$4:$C$6))/$B$9))
A27: =IF(C26>0.5,SQRT(A26*B26),A26) | B27: =IF(C26>0.5,B26,SQRT(A26*B26)) | C27: =SUMPRODUCT($B$4:$B$6,1-NORMSDIST((LN(SQRT(A27*B27))-LN($C$4:$C$6))/$B$9)) | D27: =IF(F26>0.9,SQRT(D26*E26),D26) | E27: =IF(F26>0.9,E26,SQRT(D26*E26)) | F27: =SUMPRODUCT($B$4:$B$6,1-NORMSDIST((LN(SQRT(D27*E27))-LN($C$4:$C$6))/$B$9)) | G27: =IF(I26>0.75,SQRT(G26*H26),G26) | H27: =IF(I26>0.75,H26,SQRT(G26*H26)) | I27: =SUMPRODUCT($B$4:$B$6,1-NORMSDIST((LN(SQRT(G27*H27))-LN($C$4:$C$6))/$B$9)) | J27: =IF(L26>0.25,SQRT(J26*K26),J26) | K27: =IF(L26>0.25,K26,SQRT(J26*K26)) | L27: =SUMPRODUCT($B$4:$B$6,1-NORMSDIST((LN(SQRT(J27*K27))-LN($C$4:$C$6))/$B$9)) | M27: =IF(O26>0.09999999999999998,SQRT(M26*N26),M26) | N27: =IF(O26>0.09999999999999998,N26,SQRT(M26*N26)) | O27: =SUMPRODUCT($B$4:$B$6,1-NORMSDIST((LN(SQRT(M27*N27))-LN($C$4:$C$6))/$B$9))
A28: =IF(C27>0.5,SQRT(A27*B27),A27) | B28: =IF(C27>0.5,B27,SQRT(A27*B27)) | C28: =SUMPRODUCT($B$4:$B$6,1-NORMSDIST((LN(SQRT(A28*B28))-LN($C$4:$C$6))/$B$9)) | D28: =IF(F27>0.9,SQRT(D27*E27),D27) | E28: =IF(F27>0.9,E27,SQRT(D27*E27)) | F28: =SUMPRODUCT($B$4:$B$6,1-NORMSDIST((LN(SQRT(D28*E28))-LN($C$4:$C$6))/$B$9)) | G28: =IF(I27>0.75,SQRT(G27*H27),G27) | H28: =IF(I27>0.75,H27,SQRT(G27*H27)) | I28: =SUMPRODUCT($B$4:$B$6,1-NORMSDIST((LN(SQRT(G28*H28))-LN($C$4:$C$6))/$B$9)) | J28: =IF(L27>0.25,SQRT(J27*K27),J27) | K28: =IF(L27>0.25,K27,SQRT(J27*K27)) | L28: =SUMPRODUCT($B$4:$B$6,1-NORMSDIST((LN(SQRT(J28*K28))-LN($C$4:$C$6))/$B$9)) | M28: =IF(O27>0.09999999999999998,SQRT(M27*N27),M27) | N28: =IF(O27>0.09999999999999998,N27,SQRT(M27*N27)) | O28: =SUMPRODUCT($B$4:$B$6,1-NORMSDIST((LN(SQRT(M28*N28))-LN($C$4:$C$6))/$B$9))
A29: =IF(C28>0.5,SQRT(A28*B28),A28) | B29: =IF(C28>0.5,B28,SQRT(A28*B28)) | C29: =SUMPRODUCT($B$4:$B$6,1-NORMSDIST((LN(SQRT(A29*B29))-LN($C$4:$C$6))/$B$9)) | D29: =IF(F28>0.9,SQRT(D28*E28),D28) | E29: =IF(F28>0.9,E28,SQRT(D28*E28)) | F29: =SUMPRODUCT($B$4:$B$6,1-NORMSDIST((LN(SQRT(D29*E29))-LN($C$4:$C$6))/$B$9)) | G29: =IF(I28>0.75,SQRT(G28*H28),G28) | H29: =IF(I28>0.75,H28,SQRT(G28*H28)) | I29: =SUMPRODUCT($B$4:$B$6,1-NORMSDIST((LN(SQRT(G29*H29))-LN($C$4:$C$6))/$B$9)) | J29: =IF(L28>0.25,SQRT(J28*K28),J28) | K29: =IF(L28>0.25,K28,SQRT(J28*K28)) | L29: =SUMPRODUCT($B$4:$B$6,1-NORMSDIST((LN(SQRT(J29*K29))-LN($C$4:$C$6))/$B$9)) | M29: =IF(O28>0.09999999999999998,SQRT(M28*N28),M28) | N29: =IF(O28>0.09999999999999998,N28,SQRT(M28*N28)) | O29: =SUMPRODUCT($B$4:$B$6,1-NORMSDIST((LN(SQRT(M29*N29))-LN($C$4:$C$6))/$B$9))
A30: =IF(C29>0.5,SQRT(A29*B29),A29) | B30: =IF(C29>0.5,B29,SQRT(A29*B29)) | C30: =SUMPRODUCT($B$4:$B$6,1-NORMSDIST((LN(SQRT(A30*B30))-LN($C$4:$C$6))/$B$9)) | D30: =IF(F29>0.9,SQRT(D29*E29),D29) | E30: =IF(F29>0.9,E29,SQRT(D29*E29)) | F30: =SUMPRODUCT($B$4:$B$6,1-NORMSDIST((LN(SQRT(D30*E30))-LN($C$4:$C$6))/$B$9)) | G30: =IF(I29>0.75,SQRT(G29*H29),G29) | H30: =IF(I29>0.75,H29,SQRT(G29*H29)) | I30: =SUMPRODUCT($B$4:$B$6,1-NORMSDIST((LN(SQRT(G30*H30))-LN($C$4:$C$6))/$B$9)) | J30: =IF(L29>0.25,SQRT(J29*K29),J29) | K30: =IF(L29>0.25,K29,SQRT(J29*K29)) | L30: =SUMPRODUCT($B$4:$B$6,1-NORMSDIST((LN(SQRT(J30*K30))-LN($C$4:$C$6))/$B$9)) | M30: =IF(O29>0.09999999999999998,SQRT(M29*N29),M29) | N30: =IF(O29>0.09999999999999998,N29,SQRT(M29*N29)) | O30: =SUMPRODUCT($B$4:$B$6,1-NORMSDIST((LN(SQRT(M30*N30))-LN($C$4:$C$6))/$B$9))
A31: =IF(C30>0.5,SQRT(A30*B30),A30) | B31: =IF(C30>0.5,B30,SQRT(A30*B30)) | C31: =SUMPRODUCT($B$4:$B$6,1-NORMSDIST((LN(SQRT(A31*B31))-LN($C$4:$C$6))/$B$9)) | D31: =IF(F30>0.9,SQRT(D30*E30),D30) | E31: =IF(F30>0.9,E30,SQRT(D30*E30)) | F31: =SUMPRODUCT($B$4:$B$6,1-NORMSDIST((LN(SQRT(D31*E31))-LN($C$4:$C$6))/$B$9)) | G31: =IF(I30>0.75,SQRT(G30*H30),G30) | H31: =IF(I30>0.75,H30,SQRT(G30*H30)) | I31: =SUMPRODUCT($B$4:$B$6,1-NORMSDIST((LN(SQRT(G31*H31))-LN($C$4:$C$6))/$B$9)) | J31: =IF(L30>0.25,SQRT(J30*K30),J30) | K31: =IF(L30>0.25,K30,SQRT(J30*K30)) | L31: =SUMPRODUCT($B$4:$B$6,1-NORMSDIST((LN(SQRT(J31*K31))-LN($C$4:$C$6))/$B$9)) | M31: =IF(O30>0.09999999999999998,SQRT(M30*N30),M30) | N31: =IF(O30>0.09999999999999998,N30,SQRT(M30*N30)) | O31: =SUMPRODUCT($B$4:$B$6,1-NORMSDIST((LN(SQRT(M31*N31))-LN($C$4:$C$6))/$B$9))
A32: =IF(C31>0.5,SQRT(A31*B31),A31) | B32: =IF(C31>0.5,B31,SQRT(A31*B31)) | C32: =SUMPRODUCT($B$4:$B$6,1-NORMSDIST((LN(SQRT(A32*B32))-LN($C$4:$C$6))/$B$9)) | D32: =IF(F31>0.9,SQRT(D31*E31),D31) | E32: =IF(F31>0.9,E31,SQRT(D31*E31)) | F32: =SUMPRODUCT($B$4:$B$6,1-NORMSDIST((LN(SQRT(D32*E32))-LN($C$4:$C$6))/$B$9)) | G32: =IF(I31>0.75,SQRT(G31*H31),G31) | H32: =IF(I31>0.75,H31,SQRT(G31*H31)) | I32: =SUMPRODUCT($B$4:$B$6,1-NORMSDIST((LN(SQRT(G32*H32))-LN($C$4:$C$6))/$B$9)) | J32: =IF(L31>0.25,SQRT(J31*K31),J31) | K32: =IF(L31>0.25,K31,SQRT(J31*K31)) | L32: =SUMPRODUCT($B$4:$B$6,1-NORMSDIST((LN(SQRT(J32*K32))-LN($C$4:$C$6))/$B$9)) | M32: =IF(O31>0.09999999999999998,SQRT(M31*N31),M31) | N32: =IF(O31>0.09999999999999998,N31,SQRT(M31*N31)) | O32: =SUMPRODUCT($B$4:$B$6,1-NORMSDIST((LN(SQRT(M32*N32))-LN($C$4:$C$6))/$B$9))
A33: =IF(C32>0.5,SQRT(A32*B32),A32) | B33: =IF(C32>0.5,B32,SQRT(A32*B32)) | C33: =SUMPRODUCT($B$4:$B$6,1-NORMSDIST((LN(SQRT(A33*B33))-LN($C$4:$C$6))/$B$9)) | D33: =IF(F32>0.9,SQRT(D32*E32),D32) | E33: =IF(F32>0.9,E32,SQRT(D32*E32)) | F33: =SUMPRODUCT($B$4:$B$6,1-NORMSDIST((LN(SQRT(D33*E33))-LN($C$4:$C$6))/$B$9)) | G33: =IF(I32>0.75,SQRT(G32*H32),G32) | H33: =IF(I32>0.75,H32,SQRT(G32*H32)) | I33: =SUMPRODUCT($B$4:$B$6,1-NORMSDIST((LN(SQRT(G33*H33))-LN($C$4:$C$6))/$B$9)) | J33: =IF(L32>0.25,SQRT(J32*K32),J32) | K33: =IF(L32>0.25,K32,SQRT(J32*K32)) | L33: =SUMPRODUCT($B$4:$B$6,1-NORMSDIST((LN(SQRT(J33*K33))-LN($C$4:$C$6))/$B$9)) | M33: =IF(O32>0.09999999999999998,SQRT(M32*N32),M32) | N33: =IF(O32>0.09999999999999998,N32,SQRT(M32*N32)) | O33: =SUMPRODUCT($B$4:$B$6,1-NORMSDIST((LN(SQRT(M33*N33))-LN($C$4:$C$6))/$B$9))
... A60: =IF(C59>0.5,SQRT(A59*B59),A59) | B60: =IF(C59>0.5,B59,SQRT(A59*B59)) | C60: =SUMPRODUCT($B$4:$B$6,1-NORMSDIST((LN(SQRT(A60*B60))-LN($C$4:$C$6))/$B$9)) | D60: =IF(F59>0.9,SQRT(D59*E59),D59) | E60: =IF(F59>0.9,E59,SQRT(D59*E59)) | F60: =SUMPRODUCT($B$4:$B$6,1-NORMSDIST((LN(SQRT(D60*E60))-LN($C$4:$C$6))/$B$9)) | G60: =IF(I59>0.75,SQRT(G59*H59),G59) | H60: =IF(I59>0.75,H59,SQRT(G59*H59)) | I60: =SUMPRODUCT($B$4:$B$6,1-NORMSDIST((LN(SQRT(G60*H60))-LN($C$4:$C$6))/$B$9)) | J60: =IF(L59>0.25,SQRT(J59*K59),J59) | K60: =IF(L59>0.25,K59,SQRT(J59*K59)) | L60: =SUMPRODUCT($B$4:$B$6,1-NORMSDIST((LN(SQRT(J60*K60))-LN($C$4:$C$6))/$B$9)) | M60: =IF(O59>0.09999999999999998,SQRT(M59*N59),M59) | N60: =IF(O59>0.09999999999999998,N59,SQRT(M59*N59)) | O60: =SUMPRODUCT($B$4:$B$6,1-NORMSDIST((LN(SQRT(M60*N60))-LN($C$4:$C$6))/$B$9))

Sheet Calc - research target (12m)
A1: GOOGL engine calculation: research target (12m) (reconciled set, no scenario deltas)
A2: Machinery behind the Valuation and Distribution tabs; drivers come from Model, assumptions from Valuation.
A4: Scenario Growth Δ | B4: 0
A5: Scenario Margin Δ | B5: 0
A6: Scenario Multiple Δ (turns) | B6: 0
A7: Scenario WACC Δ | B7: 0
A8: Scenario Multiple %Δ | B8: 0
A9: Scenario Stated EPS/FCF %Δ | B9: 0
A10: Scenario Custom %Δ | B10: 0
A12: WACC | B12: =Valuation!$B$51+B7
A13: Years from last FY end to target date | B13: =(Valuation!$B$45-Valuation!$B$49)/365.25
A14: Years from last FY end to balance date | B14: =(Valuation!$B$55-Valuation!$B$49)/365.25
A15: Years from last FY end to share count date | B15: =(Valuation!$B$61-Valuation!$B$49)/365.25
A16: Projected years | B16: 3
A18: Projection | B18: Base | C18: =Model!E5 | D18: =Model!F5 | E18: =Model!G5
A19: Year index | B19: 0 | C19: 1 | D19: 2 | E19: 3
A20: Period end | C20: =Valuation!$B$49+ROUND(365.25*C19,0) | D20: =Valuation!$B$49+ROUND(365.25*D19,0) | E20: =Valuation!$B$49+ROUND(365.25*E19,0)
A21: Revenue growth | C21: =C22/B22-1 | D21: =D22/C22-1 | E21: =E22/D22-1
A22: Revenue | B22: =Valuation!$B$50 | C22: =C147 | D22: =D147 | E22: =E147
A23: EBIT margin | C23: =C24/C22 | D23: =D24/D22 | E23: =E24/E22
A24: EBIT | C24: =C150 | D24: =D150 | E24: =E150
A25: Tax rate | C25: =Model!E71 | D25: =Model!F71 | E25: =Model!G71
A26: NOPAT | C26: =C24*(1-C25) | D26: =D24*(1-D25) | E26: =E24*(1-E25)
A27: D&A | C27: =C22*(Model!E72) | D27: =D22*(Model!F72) | E27: =E22*(Model!G72)
A28: Capex | C28: =C22*(Model!E73) | D28: =D22*(Model!F73) | E28: =E22*(Model!G73)
A29: Working capital increase | C29: =(Model!E74)*(C22-B22) | D29: =(Model!F74)*(D22-C22) | E29: =(Model!G74)*(E22-D22)
A30: Stock comp | C30: =C22*(Model!E75) | D30: =D22*(Model!F75) | E30: =E22*(Model!G75)
A31: Free cash flow to firm | C31: =C26+C27-C28-C29-IF(AND(Valuation!$B$47="adjusted",Valuation!$B$48="cost"),C30*(1-C25),0) | D31: =D26+D27-D28-D29-IF(AND(Valuation!$B$47="adjusted",Valuation!$B$48="cost"),D30*(1-D25),0) | E31: =E26+E27-E28-E29-IF(AND(Valuation!$B$47="adjusted",Valuation!$B$48="cost"),E30*(1-E25),0)
A32: EBITDA | C32: =C24+C27 | D32: =D24+D27 | E32: =E24+E27
A33: Adj. EBITDA | C33: =C24+C27+C22*(Model!E79) | D33: =D24+D27+D22*(Model!F79) | E33: =E24+E27+E22*(Model!G79)
A34: Shareholder returns + other uses | C34: =C22*Model!E77+Model!E76+Model!E78 | D34: =D22*Model!F77+Model!F76+Model!F78 | E34: =E22*Model!G77+Model!G76+Model!G78
A35: Share of year after target date | C35: =IF(C19<=$B$13,0,C19-MAX(C19-1,$B$13)) | D35: =IF(D19<=$B$13,0,D19-MAX(D19-1,$B$13)) | E35: =IF(E19<=$B$13,0,E19-MAX(E19-1,$B$13))
A36: PV at target date of FCFF | C36: =IF(C35=0,0,C31*C35/(1+$B$12)^(C19-$B$13)) | D36: =IF(D35=0,0,D31*D35/(1+$B$12)^(D19-$B$13)) | E36: =IF(E35=0,0,E31*E35/(1+$B$12)^(E19-$B$13))
A37: Overlap: balance date to target date | C37: =MAX(0,MIN(C19,$B$13)-MAX(C19-1,$B$14)) | D37: =MAX(0,MIN(D19,$B$13)-MAX(D19-1,$B$14)) | E37: =MAX(0,MIN(E19,$B$13)-MAX(E19-1,$B$14))
A38: NTM weight at target date | C38: =MAX(0,MIN(C19,$B$13+1)-MAX(C19-1,$B$13)) | D38: =MAX(0,MIN(D19,$B$13+1)-MAX(D19-1,$B$13)) | E38: =MAX(0,MIN(E19,$B$13+1)-MAX(E19-1,$B$13))
A39: LTM weight at target date | B39: =MAX(0,MIN(0,$B$13)-MAX(-1,$B$13-1)) | C39: =MAX(0,MIN(C19,$B$13)-MAX(C19-1,$B$13-1)) | D39: =MAX(0,MIN(D19,$B$13)-MAX(D19-1,$B$13-1)) | E39: =MAX(0,MIN(E19,$B$13)-MAX(E19-1,$B$13-1))
A41: Value at the target date
A42: PV of free cash flow after the target date | B42: =SUM($C$36:$E$36)
A43: Terminal value at final year | B43: =IF(Valuation!$B$52="exit_multiple",Valuation!$B$54*E32,E31*(1+Valuation!$B$53)/($B$12-Valuation!$B$53))
A44: PV of terminal value at target date | B44: =B43/(1+$B$12)^($B$16-$B$13)
A45: DCF enterprise value at target date | B45: =B42+B44
A46: Terminal value share of DCF | B46: =B44/B45
A47: Free cash flow earned, balance date to target date | B47: =SUMPRODUCT($C$37:$E$37,$C$31:$E$31)
A48: Shareholder returns + other uses paid | B48: =SUMPRODUCT($C$37:$E$37,$C$34:$E$34)
A49: Interest drag on net debt | B49: =Valuation!$B$58*(1-$C$25)*MAX(Valuation!$B$56,0)*MAX($B$13-$B$14,0)
A50: Net debt at target date | B50: =IF(Valuation!$B$59="",Valuation!$B$56-B47+B49+B48,Valuation!$B$59)
A51: Minority interests | B51: =Valuation!$B$57
A52: Adjustments (probability-weighted) | B52: =(Valuation!B79)*Valuation!C79+(Valuation!B80)*Valuation!C80+(Valuation!B81)*Valuation!C81+(Valuation!B82)*Valuation!C82+(Valuation!B83)*Valuation!C83+(Valuation!B84)*Valuation!C84+(Valuation!B85)*Valuation!C85+(Valuation!B86)*Valuation!C86+(Valuation!B87)*Valuation!C87+(Valuation!B88)*Valuation!C88+(Valuation!B89)*Valuation!C89+(Valuation!B90)*Valuation!C90+(Valuation!B91)*Valuation!C91+(Valuation!B92)*Valuation!C92+0
A53: Diluted shares at target date (M) | B53: =IF(Valuation!$B$63="",Valuation!$B$60*(1+Valuation!$B$62)^MAX($B$13-$B$15,0),Valuation!$B$63)
A54: After-tax interest on target-date net debt | B54: =Valuation!$B$58*(1-$C$25)*MAX(B50,0)
A55: Check: WACC vs terminal growth | B55: =IF(AND(Valuation!$B$52<>"exit_multiple",$B$12<=Valuation!$B$53+0.01),"WACC must exceed terminal growth by 1 point","ok")
A56: Check: projection length | B56: =IF(OR($B$13>=$B$16-1,$B$13+1>$B$16),"add projected years past the target date","ok")
A58: Metric at target date | B58: Next 12 months | C58: Last 12 months
A59: Revenue | B59: =SUMPRODUCT($C$38:$E$38,$C$22:$E$22) | C59: =SUMPRODUCT($C$39:$E$39,$C$22:$E$22)+$B$39*$B$22
A60: EBIT | B60: =SUMPRODUCT($C$38:$E$38,$C$24:$E$24) | C60: =SUMPRODUCT($C$39:$E$39,$C$24:$E$24)
A61: EBITDA | B61: =SUMPRODUCT($C$38:$E$38,$C$32:$E$32) | C61: =SUMPRODUCT($C$39:$E$39,$C$32:$E$32)
A62: Adj. EBITDA | B62: =SUMPRODUCT($C$38:$E$38,$C$33:$E$33) | C62: =SUMPRODUCT($C$39:$E$39,$C$33:$E$33)
A63: NOPAT | B63: =SUMPRODUCT($C$38:$E$38,$C$26:$E$26) | C63: =SUMPRODUCT($C$39:$E$39,$C$26:$E$26)
A64: Free cash flow to firm | B64: =SUMPRODUCT($C$38:$E$38,$C$31:$E$31) | C64: =SUMPRODUCT($C$39:$E$39,$C$31:$E$31)
A66: Valuation method | B66: Metric | C66: Multiple used | D66: Basis | E66: Metric at target date | F66: Value per share | G66: Weight | H66: Metric key | I66: Metric shown (stated per-share figure when used)
A67: DCF (cash flow to target date + terminal) | F67: =((B45)-$B$50-$B$51+$B$52)/$B$53 | G67: =Valuation!$B$64
A68: ="Multiple: "&Valuation!A70&" ("&Valuation!D70&")" | B68: =Valuation!A70 | C68: =IF(B68="FCF yield",(Valuation!B70)*(1-$B$8),(Valuation!B70)+IF(B68="EV/sales",0.1,1)*$B$6) | D68: =Valuation!D70 | E68: =IF(D68="ltm",CHOOSE(H68,$C$59,$C$60,$C$61,$C$62,$C$63,$C$64),CHOOSE(H68,$B$59,$B$60,$B$61,$B$62,$B$63,$B$64)) | F68: =IF(OR(B68="EV/EBITDA",B68="EV/sales",B68="EV/EBIT"),((C68*E68)-$B$50-$B$51+$B$52)/$B$53,IF(B68="P/E",IF(Valuation!F70<>"",C68*(Valuation!F70)*(1+$B$9),C68*(E68-$B$54)/$B$53),IF(Valuation!G70<>"",(Valuation!G70)*(1+$B$9)/C68,(E68-IF(Valuation!H70,$B$54,0))/C68/$B$53))+$B$52/$B$53) | G68: =Valuation!C70 | H68: =IF(B68="EV/sales",1,IF(B68="EV/EBIT",2,IF(B68="EV/EBITDA",IF(Valuation!E70="adjusted",4,3),IF(B68="P/E",5,6)))) | I68: =IF(AND(B68="P/E",Valuation!F70<>""),(Valuation!F70)*(1+$B$9),IF(AND(B68="FCF yield",Valuation!G70<>""),(Valuation!G70)*(1+$B$9),E68))
A69: Sum of the parts | F69: =((((Valuation!B73)*(Valuation!D73)+(Valuation!B74)*(Valuation!D74)+(Valuation!B75)*(Valuation!D75)+(Valuation!B76)*(Valuation!D76))*(1+$B$8))-$B$50-$B$51+$B$52)/$B$53 | G69: =Valuation!$B$65
A70: Value per share at target date (weighted methods) | F70: =SUMPRODUCT(F67:F69,G67:G69)/SUM(G67:G69)
A129: Segment build (model_engine.seg_build): revenue and EBIT are the segment sums plus corporate EBIT
A130: Segment | B130: Base | C130: =Model!E5 | D130: =Model!F5 | E130: =Model!G5
A131: Google Search & other: revenue growth | C131: =Model!E12+$B$4 | D131: =Model!F12+$B$4 | E131: =Model!G12+$B$4
A132: Google Search & other: revenue | B132: =Valuation!$B$103 | C132: =B132*(1+C131) | D132: =C132*(1+D131) | E132: =D132*(1+E131)
A133: Google Search & other: EBIT margin | C133: =Model!E14+$B$5 | D133: =Model!F14+$B$5 | E133: =Model!G14+$B$5
A134: Google Search & other: EBIT | C134: =C132*C133 | D134: =D132*D133 | E134: =E132*E133
A135: Google Services other (YouTube ads, Netw: revenue growth | C135: =Model!E16+$B$4 | D135: =Model!F16+$B$4 | E135: =Model!G16+$B$4
A136: Google Services other (YouTube ads, Netw: revenue | B136: =Valuation!$B$104 | C136: =B136*(1+C135) | D136: =C136*(1+D135) | E136: =D136*(1+E135)
A137: Google Services other (YouTube ads, Netw: EBIT margin | C137: =Model!E18+$B$5 | D137: =Model!F18+$B$5 | E137: =Model!G18+$B$5
A138: Google Services other (YouTube ads, Netw: EBIT | C138: =C136*C137 | D138: =D136*D137 | E138: =E136*E137
A139: Google Cloud: revenue growth | C139: =Model!E20+$B$4 | D139: =Model!F20+$B$4 | E139: =Model!G20+$B$4
A140: Google Cloud: revenue | B140: =Valuation!$B$105 | C140: =B140*(1+C139) | D140: =C140*(1+D139) | E140: =D140*(1+E139)
A141: Google Cloud: EBIT margin | C141: =Model!E22+$B$5 | D141: =Model!F22+$B$5 | E141: =Model!G22+$B$5
A142: Google Cloud: EBIT | C142: =C140*C141 | D142: =D140*D141 | E142: =E140*E141
A143: Other Bets: revenue growth | C143: =Model!E24+$B$4 | D143: =Model!F24+$B$4 | E143: =Model!G24+$B$4
A144: Other Bets: revenue | B144: =Valuation!$B$106 | C144: =B144*(1+C143) | D144: =C144*(1+D143) | E144: =D144*(1+E143)
A145: Other Bets: EBIT margin | C145: =Model!E26+$B$5 | D145: =Model!F26+$B$5 | E145: =Model!G26+$B$5
A146: Other Bets: EBIT | C146: =C144*C145 | D146: =D144*D145 | E146: =E144*E145
A147: Total segment revenue | C147: =C132+C136+C140+C144 | D147: =D132+D136+D140+D144 | E147: =E132+E136+E140+E144
A148: Total segment EBIT | C148: =C134+C138+C142+C146 | D148: =D134+D138+D142+D146 | E148: =E134+E138+E142+E146
A149: Corporate / unallocated EBIT | C149: =Model!E29 | D149: =Model!F29 | E149: =Model!G29
A150: EBIT (segments + corporate) | C150: =C148+C149 | D150: =D148+D149 | E150: =E148+E149

Sheet Calc - bear
A1: GOOGL engine calculation: bear scenario
A2: Machinery behind the Valuation and Distribution tabs; drivers come from Model, assumptions from Valuation.
A4: Scenario Growth Δ | B4: =N(Valuation!C98)
A5: Scenario Margin Δ | B5: =N(Valuation!D98)
A6: Scenario Multiple Δ (turns) | B6: =N(Valuation!E98)
A7: Scenario WACC Δ | B7: =N(Valuation!F98)
A8: Scenario Multiple %Δ | B8: =N(Valuation!G98)
A9: Scenario Stated EPS/FCF %Δ | B9: =N(Valuation!H98)
A10: Scenario Custom %Δ | B10: =N(Valuation!I98)
A12: WACC | B12: =Valuation!$B$51+B7
A13: Years from last FY end to target date | B13: =(Valuation!$B$45-Valuation!$B$49)/365.25
A14: Years from last FY end to balance date | B14: =(Valuation!$B$55-Valuation!$B$49)/365.25
A15: Years from last FY end to share count date | B15: =(Valuation!$B$61-Valuation!$B$49)/365.25
A16: Projected years | B16: 3
A18: Projection | B18: Base | C18: =Model!E5 | D18: =Model!F5 | E18: =Model!G5
A19: Year index | B19: 0 | C19: 1 | D19: 2 | E19: 3
A20: Period end | C20: =Valuation!$B$49+ROUND(365.25*C19,0) | D20: =Valuation!$B$49+ROUND(365.25*D19,0) | E20: =Valuation!$B$49+ROUND(365.25*E19,0)
A21: Revenue growth | C21: =C22/B22-1 | D21: =D22/C22-1 | E21: =E22/D22-1
A22: Revenue | B22: =Valuation!$B$50 | C22: =C147 | D22: =D147 | E22: =E147
A23: EBIT margin | C23: =C24/C22 | D23: =D24/D22 | E23: =E24/E22
A24: EBIT | C24: =C150 | D24: =D150 | E24: =E150
A25: Tax rate | C25: =Model!E71 | D25: =Model!F71 | E25: =Model!G71
A26: NOPAT | C26: =C24*(1-C25) | D26: =D24*(1-D25) | E26: =E24*(1-E25)
A27: D&A | C27: =C22*(Model!E72+$B$250) | D27: =D22*(Model!F72+$B$252) | E27: =E22*(Model!G72+$B$254)
A28: Capex | C28: =C22*(Model!E73+$B$251) | D28: =D22*(Model!F73+$B$253) | E28: =E22*(Model!G73+$B$255)
A29: Working capital increase | C29: =(Model!E74)*(C22-B22) | D29: =(Model!F74)*(D22-C22) | E29: =(Model!G74)*(E22-D22)
A30: Stock comp | C30: =C22*(Model!E75) | D30: =D22*(Model!F75) | E30: =E22*(Model!G75)
A31: Free cash flow to firm | C31: =C26+C27-C28-C29-IF(AND(Valuation!$B$47="adjusted",Valuation!$B$48="cost"),C30*(1-C25),0) | D31: =D26+D27-D28-D29-IF(AND(Valuation!$B$47="adjusted",Valuation!$B$48="cost"),D30*(1-D25),0) | E31: =E26+E27-E28-E29-IF(AND(Valuation!$B$47="adjusted",Valuation!$B$48="cost"),E30*(1-E25),0)
A32: EBITDA | C32: =C24+C27 | D32: =D24+D27 | E32: =E24+E27
A33: Adj. EBITDA | C33: =C24+C27+C22*(Model!E79) | D33: =D24+D27+D22*(Model!F79) | E33: =E24+E27+E22*(Model!G79)
A34: Shareholder returns + other uses | C34: =C22*Model!E77+Model!E76+Model!E78 | D34: =D22*Model!F77+Model!F76+Model!F78 | E34: =E22*Model!G77+Model!G76+Model!G78
A35: Share of year after target date | C35: =IF(C19<=$B$13,0,C19-MAX(C19-1,$B$13)) | D35: =IF(D19<=$B$13,0,D19-MAX(D19-1,$B$13)) | E35: =IF(E19<=$B$13,0,E19-MAX(E19-1,$B$13))
A36: PV at target date of FCFF | C36: =IF(C35=0,0,C31*C35/(1+$B$12)^(C19-$B$13)) | D36: =IF(D35=0,0,D31*D35/(1+$B$12)^(D19-$B$13)) | E36: =IF(E35=0,0,E31*E35/(1+$B$12)^(E19-$B$13))
A37: Overlap: balance date to target date | C37: =MAX(0,MIN(C19,$B$13)-MAX(C19-1,$B$14)) | D37: =MAX(0,MIN(D19,$B$13)-MAX(D19-1,$B$14)) | E37: =MAX(0,MIN(E19,$B$13)-MAX(E19-1,$B$14))
A38: NTM weight at target date | C38: =MAX(0,MIN(C19,$B$13+1)-MAX(C19-1,$B$13)) | D38: =MAX(0,MIN(D19,$B$13+1)-MAX(D19-1,$B$13)) | E38: =MAX(0,MIN(E19,$B$13+1)-MAX(E19-1,$B$13))
A39: LTM weight at target date | B39: =MAX(0,MIN(0,$B$13)-MAX(-1,$B$13-1)) | C39: =MAX(0,MIN(C19,$B$13)-MAX(C19-1,$B$13-1)) | D39: =MAX(0,MIN(D19,$B$13)-MAX(D19-1,$B$13-1)) | E39: =MAX(0,MIN(E19,$B$13)-MAX(E19-1,$B$13-1))
A41: Value at the target date
A42: PV of free cash flow after the target date | B42: =SUM($C$36:$E$36)
A43: Terminal value at final year | B43: =IF(Valuation!$B$52="exit_multiple",Valuation!$B$54*E32,E31*(1+Valuation!$B$53)/($B$12-Valuation!$B$53))
A44: PV of terminal value at target date | B44: =B43/(1+$B$12)^($B$16-$B$13)
A45: DCF enterprise value at target date | B45: =B42+B44
A46: Terminal value share of DCF | B46: =B44/B45
A47: Free cash flow earned, balance date to target date | B47: =SUMPRODUCT($C$37:$E$37,$C$31:$E$31)
A48: Shareholder returns + other uses paid | B48: =SUMPRODUCT($C$37:$E$37,$C$34:$E$34)
A49: Interest drag on net debt | B49: =Valuation!$B$58*(1-$C$25)*MAX(Valuation!$B$56,0)*MAX($B$13-$B$14,0)
A50: Net debt at target date | B50: =IF(Valuation!$B$59="",Valuation!$B$56-B47+B49+B48,Valuation!$B$59)
A51: Minority interests | B51: =Valuation!$B$57
A52: Adjustments (probability-weighted) | B52: =(Valuation!B79+$B$261)*Valuation!C79+(Valuation!B80)*Valuation!C80+(Valuation!B81)*Valuation!C81+(Valuation!B82)*Valuation!C82+(Valuation!B83)*Valuation!C83+(Valuation!B84)*Valuation!C84+(Valuation!B85)*Valuation!C85+(Valuation!B86)*Valuation!C86+(Valuation!B87)*Valuation!C87+(Valuation!B88)*Valuation!C88+(Valuation!B89)*Valuation!C89+(Valuation!B90)*Valuation!C90+(Valuation!B91)*Valuation!C91+(Valuation!B92)*Valuation!C92+0
A53: Diluted shares at target date (M) | B53: =IF(Valuation!$B$63="",Valuation!$B$60*(1+Valuation!$B$62)^MAX($B$13-$B$15,0),Valuation!$B$63)
A54: After-tax interest on target-date net debt | B54: =Valuation!$B$58*(1-$C$25)*MAX(B50,0)
A55: Check: WACC vs terminal growth | B55: =IF(AND(Valuation!$B$52<>"exit_multiple",$B$12<=Valuation!$B$53+0.01),"WACC must exceed terminal growth by 1 point","ok")
A56: Check: projection length | B56: =IF(OR($B$13>=$B$16-1,$B$13+1>$B$16),"add projected years past the target date","ok")
A58: Metric at target date | B58: Next 12 months | C58: Last 12 months
A59: Revenue | B59: =SUMPRODUCT($C$38:$E$38,$C$22:$E$22) | C59: =SUMPRODUCT($C$39:$E$39,$C$22:$E$22)+$B$39*$B$22
A60: EBIT | B60: =SUMPRODUCT($C$38:$E$38,$C$24:$E$24) | C60: =SUMPRODUCT($C$39:$E$39,$C$24:$E$24)
A61: EBITDA | B61: =SUMPRODUCT($C$38:$E$38,$C$32:$E$32) | C61: =SUMPRODUCT($C$39:$E$39,$C$32:$E$32)
A62: Adj. EBITDA | B62: =SUMPRODUCT($C$38:$E$38,$C$33:$E$33) | C62: =SUMPRODUCT($C$39:$E$39,$C$33:$E$33)
A63: NOPAT | B63: =SUMPRODUCT($C$38:$E$38,$C$26:$E$26) | C63: =SUMPRODUCT($C$39:$E$39,$C$26:$E$26)
A64: Free cash flow to firm | B64: =SUMPRODUCT($C$38:$E$38,$C$31:$E$31) | C64: =SUMPRODUCT($C$39:$E$39,$C$31:$E$31)
A66: Valuation method | B66: Metric | C66: Multiple used | D66: Basis | E66: Metric at target date | F66: Value per share | G66: Weight | H66: Metric key | I66: Metric shown (stated per-share figure when used)
A67: DCF (cash flow to target date + terminal) | F67: =((B45)-$B$50-$B$51+$B$52)/$B$53 | G67: =Valuation!$B$64
A68: ="Multiple: "&Valuation!A70&" ("&Valuation!D70&")" | B68: =Valuation!A70 | C68: =IF(B68="FCF yield",(Valuation!B70)*(1-$B$8),(Valuation!B70)+IF(B68="EV/sales",0.1,1)*$B$6) | D68: =Valuation!D70 | E68: =IF(D68="ltm",CHOOSE(H68,$C$59,$C$60,$C$61,$C$62,$C$63,$C$64),CHOOSE(H68,$B$59,$B$60,$B$61,$B$62,$B$63,$B$64)) | F68: =IF(OR(B68="EV/EBITDA",B68="EV/sales",B68="EV/EBIT"),((C68*E68)-$B$50-$B$51+$B$52)/$B$53,IF(B68="P/E",IF(Valuation!F70<>"",C68*(Valuation!F70+$B$262)*(1+$B$9),C68*(E68-$B$54)/$B$53),IF(Valuation!G70<>"",(Valuation!G70)*(1+$B$9)/C68,(E68-IF(Valuation!H70,$B$54,0))/C68/$B$53))+$B$52/$B$53) | G68: =Valuation!C70 | H68: =IF(B68="EV/sales",1,IF(B68="EV/EBIT",2,IF(B68="EV/EBITDA",IF(Valuation!E70="adjusted",4,3),IF(B68="P/E",5,6)))) | I68: =IF(AND(B68="P/E",Valuation!F70<>""),(Valuation!F70+$B$262)*(1+$B$9),IF(AND(B68="FCF yield",Valuation!G70<>""),(Valuation!G70)*(1+$B$9),E68))
A69: Sum of the parts | F69: =((((Valuation!B73+$B$263)*(Valuation!D73)+(Valuation!B74+$B$264)*(Valuation!D74)+(Valuation!B75)*(Valuation!D75)+(Valuation!B76)*(Valuation!D76))*(1+$B$8))-$B$50-$B$51+$B$52)/$B$53 | G69: =Valuation!$B$65
A70: Value per share at target date (weighted methods) | F70: =SUMPRODUCT(F67:F69,G67:G69)/SUM(G67:G69)
A129: Segment build (model_engine.seg_build): revenue and EBIT are the segment sums plus corporate EBIT
A130: Segment | B130: Base | C130: =Model!E5 | D130: =Model!F5 | E130: =Model!G5
A131: Google Search & other: revenue growth | C131: =Model!E12+$B$4+$B$256 | D131: =Model!F12+$B$4 | E131: =Model!G12+$B$4
A132: Google Search & other: revenue | B132: =Valuation!$B$103 | C132: =B132*(1+C131) | D132: =C132*(1+D131) | E132: =D132*(1+E131)
A133: Google Search & other: EBIT margin | C133: =Model!E14+$B$5 | D133: =Model!F14+$B$5 | E133: =Model!G14+$B$5
A134: Google Search & other: EBIT | C134: =C132*C133 | D134: =D132*D133 | E134: =E132*E133
A135: Google Services other (YouTube ads, Netw: revenue growth | C135: =Model!E16+$B$4 | D135: =Model!F16+$B$4 | E135: =Model!G16+$B$4
A136: Google Services other (YouTube ads, Netw: revenue | B136: =Valuation!$B$104 | C136: =B136*(1+C135) | D136: =C136*(1+D135) | E136: =D136*(1+E135)
A137: Google Services other (YouTube ads, Netw: EBIT margin | C137: =Model!E18+$B$5 | D137: =Model!F18+$B$5 | E137: =Model!G18+$B$5
A138: Google Services other (YouTube ads, Netw: EBIT | C138: =C136*C137 | D138: =D136*D137 | E138: =E136*E137
A139: Google Cloud: revenue growth | C139: =Model!E20+$B$4+$B$257 | D139: =Model!F20+$B$4 | E139: =Model!G20+$B$4
A140: Google Cloud: revenue | B140: =Valuation!$B$105 | C140: =B140*(1+C139) | D140: =C140*(1+D139) | E140: =D140*(1+E139)
A141: Google Cloud: EBIT margin | C141: =Model!E22+$B$5 | D141: =Model!F22+$B$5 | E141: =Model!G22+$B$5
A142: Google Cloud: EBIT | C142: =C140*C141 | D142: =D140*D141 | E142: =E140*E141
A143: Other Bets: revenue growth | C143: =Model!E24+$B$4 | D143: =Model!F24+$B$4 | E143: =Model!G24+$B$4
A144: Other Bets: revenue | B144: =Valuation!$B$106 | C144: =B144*(1+C143) | D144: =C144*(1+D143) | E144: =D144*(1+E143)
A145: Other Bets: EBIT margin | C145: =Model!E26+$B$5 | D145: =Model!F26+$B$5 | E145: =Model!G26+$B$5
A146: Other Bets: EBIT | C146: =C144*C145 | D146: =D144*D145 | E146: =E144*E145
A147: Total segment revenue | C147: =C132+C136+C140+C144 | D147: =D132+D136+D140+D144 | E147: =E132+E136+E140+E144
A148: Total segment EBIT | C148: =C134+C138+C142+C146 | D148: =D134+D138+D142+D146 | E148: =E134+E138+E142+E146
A149: Corporate / unallocated EBIT | C149: =Model!E29+$B$258 | D149: =Model!F29+$B$259 | E149: =Model!G29+$B$260
A150: EBIT (segments + corporate) | C150: =C148+C149 | D150: =D148+D149 | E150: =E148+E149
A249: Driver scenario shifts: line-item changes model_drivers.py resolves from this scenario's driver deltas (added to the Model tab inputs)
A250: D&A % revenue, year 1 | B250: 0.007091619
A251: Capex % revenue, year 1 | B251: 0.12045528
A252: D&A % revenue, year 2 | B252: 0.017321392
A253: Capex % revenue, year 2 | B253: 0.15371343
A254: D&A % revenue, year 3 | B254: 0.028282865
A255: Capex % revenue, year 3 | B255: 0.15527969
A256: Google Search & other: revenue growth, year 1 | B256: -0.034776
A257: Google Cloud: revenue growth, year 1 | B257: -0.17370977
A258: Corporate EBIT, year 1 | B258: -3259.7505
A259: Corporate EBIT, year 2 | B259: -9178.6369
A260: Corporate EBIT, year 3 | B260: -16457.35
A261: Adjustment 1 value | B261: -106433.56
... A264: Segment 2 NTM metric | B264: -9647.7663

Sheet Calc - base
A1: GOOGL engine calculation: base scenario
A2: Machinery behind the Valuation and Distribution tabs; drivers come from Model, assumptions from Valuation.
A4: Scenario Growth Δ | B4: =N(Valuation!C99)
A5: Scenario Margin Δ | B5: =N(Valuation!D99)
A6: Scenario Multiple Δ (turns) | B6: =N(Valuation!E99)
A7: Scenario WACC Δ | B7: =N(Valuation!F99)
A8: Scenario Multiple %Δ | B8: =N(Valuation!G99)
A9: Scenario Stated EPS/FCF %Δ | B9: =N(Valuation!H99)
A10: Scenario Custom %Δ | B10: =N(Valuation!I99)
A12: WACC | B12: =Valuation!$B$51+B7
A13: Years from last FY end to target date | B13: =(Valuation!$B$45-Valuation!$B$49)/365.25
A14: Years from last FY end to balance date | B14: =(Valuation!$B$55-Valuation!$B$49)/365.25
A15: Years from last FY end to share count date | B15: =(Valuation!$B$61-Valuation!$B$49)/365.25
A16: Projected years | B16: 3
A18: Projection | B18: Base | C18: =Model!E5 | D18: =Model!F5 | E18: =Model!G5
A19: Year index | B19: 0 | C19: 1 | D19: 2 | E19: 3
A20: Period end | C20: =Valuation!$B$49+ROUND(365.25*C19,0) | D20: =Valuation!$B$49+ROUND(365.25*D19,0) | E20: =Valuation!$B$49+ROUND(365.25*E19,0)
A21: Revenue growth | C21: =C22/B22-1 | D21: =D22/C22-1 | E21: =E22/D22-1
A22: Revenue | B22: =Valuation!$B$50 | C22: =C147 | D22: =D147 | E22: =E147
A23: EBIT margin | C23: =C24/C22 | D23: =D24/D22 | E23: =E24/E22
A24: EBIT | C24: =C150 | D24: =D150 | E24: =E150
A25: Tax rate | C25: =Model!E71 | D25: =Model!F71 | E25: =Model!G71
A26: NOPAT | C26: =C24*(1-C25) | D26: =D24*(1-D25) | E26: =E24*(1-E25)
A27: D&A | C27: =C22*(Model!E72) | D27: =D22*(Model!F72) | E27: =E22*(Model!G72)
A28: Capex | C28: =C22*(Model!E73) | D28: =D22*(Model!F73) | E28: =E22*(Model!G73)
A29: Working capital increase | C29: =(Model!E74)*(C22-B22) | D29: =(Model!F74)*(D22-C22) | E29: =(Model!G74)*(E22-D22)
A30: Stock comp | C30: =C22*(Model!E75) | D30: =D22*(Model!F75) | E30: =E22*(Model!G75)
A31: Free cash flow to firm | C31: =C26+C27-C28-C29-IF(AND(Valuation!$B$47="adjusted",Valuation!$B$48="cost"),C30*(1-C25),0) | D31: =D26+D27-D28-D29-IF(AND(Valuation!$B$47="adjusted",Valuation!$B$48="cost"),D30*(1-D25),0) | E31: =E26+E27-E28-E29-IF(AND(Valuation!$B$47="adjusted",Valuation!$B$48="cost"),E30*(1-E25),0)
A32: EBITDA | C32: =C24+C27 | D32: =D24+D27 | E32: =E24+E27
A33: Adj. EBITDA | C33: =C24+C27+C22*(Model!E79) | D33: =D24+D27+D22*(Model!F79) | E33: =E24+E27+E22*(Model!G79)
A34: Shareholder returns + other uses | C34: =C22*Model!E77+Model!E76+Model!E78 | D34: =D22*Model!F77+Model!F76+Model!F78 | E34: =E22*Model!G77+Model!G76+Model!G78
A35: Share of year after target date | C35: =IF(C19<=$B$13,0,C19-MAX(C19-1,$B$13)) | D35: =IF(D19<=$B$13,0,D19-MAX(D19-1,$B$13)) | E35: =IF(E19<=$B$13,0,E19-MAX(E19-1,$B$13))
A36: PV at target date of FCFF | C36: =IF(C35=0,0,C31*C35/(1+$B$12)^(C19-$B$13)) | D36: =IF(D35=0,0,D31*D35/(1+$B$12)^(D19-$B$13)) | E36: =IF(E35=0,0,E31*E35/(1+$B$12)^(E19-$B$13))
A37: Overlap: balance date to target date | C37: =MAX(0,MIN(C19,$B$13)-MAX(C19-1,$B$14)) | D37: =MAX(0,MIN(D19,$B$13)-MAX(D19-1,$B$14)) | E37: =MAX(0,MIN(E19,$B$13)-MAX(E19-1,$B$14))
A38: NTM weight at target date | C38: =MAX(0,MIN(C19,$B$13+1)-MAX(C19-1,$B$13)) | D38: =MAX(0,MIN(D19,$B$13+1)-MAX(D19-1,$B$13)) | E38: =MAX(0,MIN(E19,$B$13+1)-MAX(E19-1,$B$13))
A39: LTM weight at target date | B39: =MAX(0,MIN(0,$B$13)-MAX(-1,$B$13-1)) | C39: =MAX(0,MIN(C19,$B$13)-MAX(C19-1,$B$13-1)) | D39: =MAX(0,MIN(D19,$B$13)-MAX(D19-1,$B$13-1)) | E39: =MAX(0,MIN(E19,$B$13)-MAX(E19-1,$B$13-1))
A41: Value at the target date
A42: PV of free cash flow after the target date | B42: =SUM($C$36:$E$36)
A43: Terminal value at final year | B43: =IF(Valuation!$B$52="exit_multiple",Valuation!$B$54*E32,E31*(1+Valuation!$B$53)/($B$12-Valuation!$B$53))
A44: PV of terminal value at target date | B44: =B43/(1+$B$12)^($B$16-$B$13)
A45: DCF enterprise value at target date | B45: =B42+B44
A46: Terminal value share of DCF | B46: =B44/B45
A47: Free cash flow earned, balance date to target date | B47: =SUMPRODUCT($C$37:$E$37,$C$31:$E$31)
A48: Shareholder returns + other uses paid | B48: =SUMPRODUCT($C$37:$E$37,$C$34:$E$34)
A49: Interest drag on net debt | B49: =Valuation!$B$58*(1-$C$25)*MAX(Valuation!$B$56,0)*MAX($B$13-$B$14,0)
A50: Net debt at target date | B50: =IF(Valuation!$B$59="",Valuation!$B$56-B47+B49+B48,Valuation!$B$59)
A51: Minority interests | B51: =Valuation!$B$57
A52: Adjustments (probability-weighted) | B52: =(Valuation!B79)*Valuation!C79+(Valuation!B80)*Valuation!C80+(Valuation!B81)*Valuation!C81+(Valuation!B82)*Valuation!C82+(Valuation!B83)*Valuation!C83+(Valuation!B84)*Valuation!C84+(Valuation!B85)*Valuation!C85+(Valuation!B86)*Valuation!C86+(Valuation!B87)*Valuation!C87+(Valuation!B88)*Valuation!C88+(Valuation!B89)*Valuation!C89+(Valuation!B90)*Valuation!C90+(Valuation!B91)*Valuation!C91+(Valuation!B92)*Valuation!C92+0
A53: Diluted shares at target date (M) | B53: =IF(Valuation!$B$63="",Valuation!$B$60*(1+Valuation!$B$62)^MAX($B$13-$B$15,0),Valuation!$B$63)
A54: After-tax interest on target-date net debt | B54: =Valuation!$B$58*(1-$C$25)*MAX(B50,0)
A55: Check: WACC vs terminal growth | B55: =IF(AND(Valuation!$B$52<>"exit_multiple",$B$12<=Valuation!$B$53+0.01),"WACC must exceed terminal growth by 1 point","ok")
A56: Check: projection length | B56: =IF(OR($B$13>=$B$16-1,$B$13+1>$B$16),"add projected years past the target date","ok")
A58: Metric at target date | B58: Next 12 months | C58: Last 12 months
A59: Revenue | B59: =SUMPRODUCT($C$38:$E$38,$C$22:$E$22) | C59: =SUMPRODUCT($C$39:$E$39,$C$22:$E$22)+$B$39*$B$22
A60: EBIT | B60: =SUMPRODUCT($C$38:$E$38,$C$24:$E$24) | C60: =SUMPRODUCT($C$39:$E$39,$C$24:$E$24)
A61: EBITDA | B61: =SUMPRODUCT($C$38:$E$38,$C$32:$E$32) | C61: =SUMPRODUCT($C$39:$E$39,$C$32:$E$32)
A62: Adj. EBITDA | B62: =SUMPRODUCT($C$38:$E$38,$C$33:$E$33) | C62: =SUMPRODUCT($C$39:$E$39,$C$33:$E$33)
A63: NOPAT | B63: =SUMPRODUCT($C$38:$E$38,$C$26:$E$26) | C63: =SUMPRODUCT($C$39:$E$39,$C$26:$E$26)
A64: Free cash flow to firm | B64: =SUMPRODUCT($C$38:$E$38,$C$31:$E$31) | C64: =SUMPRODUCT($C$39:$E$39,$C$31:$E$31)
A66: Valuation method | B66: Metric | C66: Multiple used | D66: Basis | E66: Metric at target date | F66: Value per share | G66: Weight | H66: Metric key | I66: Metric shown (stated per-share figure when used)
A67: DCF (cash flow to target date + terminal) | F67: =((B45)-$B$50-$B$51+$B$52)/$B$53 | G67: =Valuation!$B$64
A68: ="Multiple: "&Valuation!A70&" ("&Valuation!D70&")" | B68: =Valuation!A70 | C68: =IF(B68="FCF yield",(Valuation!B70)*(1-$B$8),(Valuation!B70)+IF(B68="EV/sales",0.1,1)*$B$6) | D68: =Valuation!D70 | E68: =IF(D68="ltm",CHOOSE(H68,$C$59,$C$60,$C$61,$C$62,$C$63,$C$64),CHOOSE(H68,$B$59,$B$60,$B$61,$B$62,$B$63,$B$64)) | F68: =IF(OR(B68="EV/EBITDA",B68="EV/sales",B68="EV/EBIT"),((C68*E68)-$B$50-$B$51+$B$52)/$B$53,IF(B68="P/E",IF(Valuation!F70<>"",C68*(Valuation!F70)*(1+$B$9),C68*(E68-$B$54)/$B$53),IF(Valuation!G70<>"",(Valuation!G70)*(1+$B$9)/C68,(E68-IF(Valuation!H70,$B$54,0))/C68/$B$53))+$B$52/$B$53) | G68: =Valuation!C70 | H68: =IF(B68="EV/sales",1,IF(B68="EV/EBIT",2,IF(B68="EV/EBITDA",IF(Valuation!E70="adjusted",4,3),IF(B68="P/E",5,6)))) | I68: =IF(AND(B68="P/E",Valuation!F70<>""),(Valuation!F70)*(1+$B$9),IF(AND(B68="FCF yield",Valuation!G70<>""),(Valuation!G70)*(1+$B$9),E68))
A69: Sum of the parts | F69: =((((Valuation!B73)*(Valuation!D73)+(Valuation!B74)*(Valuation!D74)+(Valuation!B75)*(Valuation!D75)+(Valuation!B76)*(Valuation!D76))*(1+$B$8))-$B$50-$B$51+$B$52)/$B$53 | G69: =Valuation!$B$65
A70: Value per share at target date (weighted methods) | F70: =SUMPRODUCT(F67:F69,G67:G69)/SUM(G67:G69)
A129: Segment build (model_engine.seg_build): revenue and EBIT are the segment sums plus corporate EBIT
A130: Segment | B130: Base | C130: =Model!E5 | D130: =Model!F5 | E130: =Model!G5
A131: Google Search & other: revenue growth | C131: =Model!E12+$B$4 | D131: =Model!F12+$B$4 | E131: =Model!G12+$B$4
A132: Google Search & other: revenue | B132: =Valuation!$B$103 | C132: =B132*(1+C131) | D132: =C132*(1+D131) | E132: =D132*(1+E131)
A133: Google Search & other: EBIT margin | C133: =Model!E14+$B$5 | D133: =Model!F14+$B$5 | E133: =Model!G14+$B$5
A134: Google Search & other: EBIT | C134: =C132*C133 | D134: =D132*D133 | E134: =E132*E133
A135: Google Services other (YouTube ads, Netw: revenue growth | C135: =Model!E16+$B$4 | D135: =Model!F16+$B$4 | E135: =Model!G16+$B$4
A136: Google Services other (YouTube ads, Netw: revenue | B136: =Valuation!$B$104 | C136: =B136*(1+C135) | D136: =C136*(1+D135) | E136: =D136*(1+E135)
A137: Google Services other (YouTube ads, Netw: EBIT margin | C137: =Model!E18+$B$5 | D137: =Model!F18+$B$5 | E137: =Model!G18+$B$5
A138: Google Services other (YouTube ads, Netw: EBIT | C138: =C136*C137 | D138: =D136*D137 | E138: =E136*E137
A139: Google Cloud: revenue growth | C139: =Model!E20+$B$4 | D139: =Model!F20+$B$4 | E139: =Model!G20+$B$4
A140: Google Cloud: revenue | B140: =Valuation!$B$105 | C140: =B140*(1+C139) | D140: =C140*(1+D139) | E140: =D140*(1+E139)
A141: Google Cloud: EBIT margin | C141: =Model!E22+$B$5 | D141: =Model!F22+$B$5 | E141: =Model!G22+$B$5
A142: Google Cloud: EBIT | C142: =C140*C141 | D142: =D140*D141 | E142: =E140*E141
A143: Other Bets: revenue growth | C143: =Model!E24+$B$4 | D143: =Model!F24+$B$4 | E143: =Model!G24+$B$4
A144: Other Bets: revenue | B144: =Valuation!$B$106 | C144: =B144*(1+C143) | D144: =C144*(1+D143) | E144: =D144*(1+E143)
A145: Other Bets: EBIT margin | C145: =Model!E26+$B$5 | D145: =Model!F26+$B$5 | E145: =Model!G26+$B$5
A146: Other Bets: EBIT | C146: =C144*C145 | D146: =D144*D145 | E146: =E144*E145
A147: Total segment revenue | C147: =C132+C136+C140+C144 | D147: =D132+D136+D140+D144 | E147: =E132+E136+E140+E144
A148: Total segment EBIT | C148: =C134+C138+C142+C146 | D148: =D134+D138+D142+D146 | E148: =E134+E138+E142+E146
A149: Corporate / unallocated EBIT | C149: =Model!E29 | D149: =Model!F29 | E149: =Model!G29
A150: EBIT (segments + corporate) | C150: =C148+C149 | D150: =D148+D149 | E150: =E148+E149

Sheet Calc - bull
A1: GOOGL engine calculation: bull scenario
A2: Machinery behind the Valuation and Distribution tabs; drivers come from Model, assumptions from Valuation.
A4: Scenario Growth Δ | B4: =N(Valuation!C100)
A5: Scenario Margin Δ | B5: =N(Valuation!D100)
A6: Scenario Multiple Δ (turns) | B6: =N(Valuation!E100)
A7: Scenario WACC Δ | B7: =N(Valuation!F100)
A8: Scenario Multiple %Δ | B8: =N(Valuation!G100)
A9: Scenario Stated EPS/FCF %Δ | B9: =N(Valuation!H100)
A10: Scenario Custom %Δ | B10: =N(Valuation!I100)
A12: WACC | B12: =Valuation!$B$51+B7
A13: Years from last FY end to target date | B13: =(Valuation!$B$45-Valuation!$B$49)/365.25
A14: Years from last FY end to balance date | B14: =(Valuation!$B$55-Valuation!$B$49)/365.25
A15: Years from last FY end to share count date | B15: =(Valuation!$B$61-Valuation!$B$49)/365.25
A16: Projected years | B16: 3
A18: Projection | B18: Base | C18: =Model!E5 | D18: =Model!F5 | E18: =Model!G5
A19: Year index | B19: 0 | C19: 1 | D19: 2 | E19: 3
A20: Period end | C20: =Valuation!$B$49+ROUND(365.25*C19,0) | D20: =Valuation!$B$49+ROUND(365.25*D19,0) | E20: =Valuation!$B$49+ROUND(365.25*E19,0)
A21: Revenue growth | C21: =C22/B22-1 | D21: =D22/C22-1 | E21: =E22/D22-1
A22: Revenue | B22: =Valuation!$B$50 | C22: =C147 | D22: =D147 | E22: =E147
A23: EBIT margin | C23: =C24/C22 | D23: =D24/D22 | E23: =E24/E22
A24: EBIT | C24: =C150 | D24: =D150 | E24: =E150
A25: Tax rate | C25: =Model!E71 | D25: =Model!F71 | E25: =Model!G71
A26: NOPAT | C26: =C24*(1-C25) | D26: =D24*(1-D25) | E26: =E24*(1-E25)
A27: D&A | C27: =C22*(Model!E72+$B$250) | D27: =D22*(Model!F72+$B$252) | E27: =E22*(Model!G72+$B$254)
A28: Capex | C28: =C22*(Model!E73+$B$251) | D28: =D22*(Model!F73+$B$253) | E28: =E22*(Model!G73+$B$255)
A29: Working capital increase | C29: =(Model!E74)*(C22-B22) | D29: =(Model!F74)*(D22-C22) | E29: =(Model!G74)*(E22-D22)
A30: Stock comp | C30: =C22*(Model!E75) | D30: =D22*(Model!F75) | E30: =E22*(Model!G75)
A31: Free cash flow to firm | C31: =C26+C27-C28-C29-IF(AND(Valuation!$B$47="adjusted",Valuation!$B$48="cost"),C30*(1-C25),0) | D31: =D26+D27-D28-D29-IF(AND(Valuation!$B$47="adjusted",Valuation!$B$48="cost"),D30*(1-D25),0) | E31: =E26+E27-E28-E29-IF(AND(Valuation!$B$47="adjusted",Valuation!$B$48="cost"),E30*(1-E25),0)
A32: EBITDA | C32: =C24+C27 | D32: =D24+D27 | E32: =E24+E27
A33: Adj. EBITDA | C33: =C24+C27+C22*(Model!E79) | D33: =D24+D27+D22*(Model!F79) | E33: =E24+E27+E22*(Model!G79)
A34: Shareholder returns + other uses | C34: =C22*Model!E77+Model!E76+Model!E78 | D34: =D22*Model!F77+Model!F76+Model!F78 | E34: =E22*Model!G77+Model!G76+Model!G78
A35: Share of year after target date | C35: =IF(C19<=$B$13,0,C19-MAX(C19-1,$B$13)) | D35: =IF(D19<=$B$13,0,D19-MAX(D19-1,$B$13)) | E35: =IF(E19<=$B$13,0,E19-MAX(E19-1,$B$13))
A36: PV at target date of FCFF | C36: =IF(C35=0,0,C31*C35/(1+$B$12)^(C19-$B$13)) | D36: =IF(D35=0,0,D31*D35/(1+$B$12)^(D19-$B$13)) | E36: =IF(E35=0,0,E31*E35/(1+$B$12)^(E19-$B$13))
A37: Overlap: balance date to target date | C37: =MAX(0,MIN(C19,$B$13)-MAX(C19-1,$B$14)) | D37: =MAX(0,MIN(D19,$B$13)-MAX(D19-1,$B$14)) | E37: =MAX(0,MIN(E19,$B$13)-MAX(E19-1,$B$14))
A38: NTM weight at target date | C38: =MAX(0,MIN(C19,$B$13+1)-MAX(C19-1,$B$13)) | D38: =MAX(0,MIN(D19,$B$13+1)-MAX(D19-1,$B$13)) | E38: =MAX(0,MIN(E19,$B$13+1)-MAX(E19-1,$B$13))
A39: LTM weight at target date | B39: =MAX(0,MIN(0,$B$13)-MAX(-1,$B$13-1)) | C39: =MAX(0,MIN(C19,$B$13)-MAX(C19-1,$B$13-1)) | D39: =MAX(0,MIN(D19,$B$13)-MAX(D19-1,$B$13-1)) | E39: =MAX(0,MIN(E19,$B$13)-MAX(E19-1,$B$13-1))
A41: Value at the target date
A42: PV of free cash flow after the target date | B42: =SUM($C$36:$E$36)
A43: Terminal value at final year | B43: =IF(Valuation!$B$52="exit_multiple",Valuation!$B$54*E32,E31*(1+Valuation!$B$53)/($B$12-Valuation!$B$53))
A44: PV of terminal value at target date | B44: =B43/(1+$B$12)^($B$16-$B$13)
A45: DCF enterprise value at target date | B45: =B42+B44
A46: Terminal value share of DCF | B46: =B44/B45
A47: Free cash flow earned, balance date to target date | B47: =SUMPRODUCT($C$37:$E$37,$C$31:$E$31)
A48: Shareholder returns + other uses paid | B48: =SUMPRODUCT($C$37:$E$37,$C$34:$E$34)
A49: Interest drag on net debt | B49: =Valuation!$B$58*(1-$C$25)*MAX(Valuation!$B$56,0)*MAX($B$13-$B$14,0)
A50: Net debt at target date | B50: =IF(Valuation!$B$59="",Valuation!$B$56-B47+B49+B48,Valuation!$B$59)
A51: Minority interests | B51: =Valuation!$B$57
A52: Adjustments (probability-weighted) | B52: =(Valuation!B79)*Valuation!C79+(Valuation!B80)*Valuation!C80+(Valuation!B81)*Valuation!C81+(Valuation!B82)*Valuation!C82+(Valuation!B83)*Valuation!C83+(Valuation!B84)*Valuation!C84+(Valuation!B85)*Valuation!C85+(Valuation!B86)*Valuation!C86+(Valuation!B87)*Valuation!C87+(Valuation!B88)*Valuation!C88+(Valuation!B89)*Valuation!C89+(Valuation!B90)*Valuation!C90+(Valuation!B91)*Valuation!C91+(Valuation!B92)*Valuation!C92+0
A53: Diluted shares at target date (M) | B53: =IF(Valuation!$B$63="",Valuation!$B$60*(1+Valuation!$B$62)^MAX($B$13-$B$15,0),Valuation!$B$63)
A54: After-tax interest on target-date net debt | B54: =Valuation!$B$58*(1-$C$25)*MAX(B50,0)
A55: Check: WACC vs terminal growth | B55: =IF(AND(Valuation!$B$52<>"exit_multiple",$B$12<=Valuation!$B$53+0.01),"WACC must exceed terminal growth by 1 point","ok")
A56: Check: projection length | B56: =IF(OR($B$13>=$B$16-1,$B$13+1>$B$16),"add projected years past the target date","ok")
A58: Metric at target date | B58: Next 12 months | C58: Last 12 months
A59: Revenue | B59: =SUMPRODUCT($C$38:$E$38,$C$22:$E$22) | C59: =SUMPRODUCT($C$39:$E$39,$C$22:$E$22)+$B$39*$B$22
A60: EBIT | B60: =SUMPRODUCT($C$38:$E$38,$C$24:$E$24) | C60: =SUMPRODUCT($C$39:$E$39,$C$24:$E$24)
A61: EBITDA | B61: =SUMPRODUCT($C$38:$E$38,$C$32:$E$32) | C61: =SUMPRODUCT($C$39:$E$39,$C$32:$E$32)
A62: Adj. EBITDA | B62: =SUMPRODUCT($C$38:$E$38,$C$33:$E$33) | C62: =SUMPRODUCT($C$39:$E$39,$C$33:$E$33)
A63: NOPAT | B63: =SUMPRODUCT($C$38:$E$38,$C$26:$E$26) | C63: =SUMPRODUCT($C$39:$E$39,$C$26:$E$26)
A64: Free cash flow to firm | B64: =SUMPRODUCT($C$38:$E$38,$C$31:$E$31) | C64: =SUMPRODUCT($C$39:$E$39,$C$31:$E$31)
A66: Valuation method | B66: Metric | C66: Multiple used | D66: Basis | E66: Metric at target date | F66: Value per share | G66: Weight | H66: Metric key | I66: Metric shown (stated per-share figure when used)
A67: DCF (cash flow to target date + terminal) | F67: =((B45)-$B$50-$B$51+$B$52)/$B$53 | G67: =Valuation!$B$64
A68: ="Multiple: "&Valuation!A70&" ("&Valuation!D70&")" | B68: =Valuation!A70 | C68: =IF(B68="FCF yield",(Valuation!B70)*(1-$B$8),(Valuation!B70)+IF(B68="EV/sales",0.1,1)*$B$6) | D68: =Valuation!D70 | E68: =IF(D68="ltm",CHOOSE(H68,$C$59,$C$60,$C$61,$C$62,$C$63,$C$64),CHOOSE(H68,$B$59,$B$60,$B$61,$B$62,$B$63,$B$64)) | F68: =IF(OR(B68="EV/EBITDA",B68="EV/sales",B68="EV/EBIT"),((C68*E68)-$B$50-$B$51+$B$52)/$B$53,IF(B68="P/E",IF(Valuation!F70<>"",C68*(Valuation!F70+$B$261)*(1+$B$9),C68*(E68-$B$54)/$B$53),IF(Valuation!G70<>"",(Valuation!G70)*(1+$B$9)/C68,(E68-IF(Valuation!H70,$B$54,0))/C68/$B$53))+$B$52/$B$53) | G68: =Valuation!C70 | H68: =IF(B68="EV/sales",1,IF(B68="EV/EBIT",2,IF(B68="EV/EBITDA",IF(Valuation!E70="adjusted",4,3),IF(B68="P/E",5,6)))) | I68: =IF(AND(B68="P/E",Valuation!F70<>""),(Valuation!F70+$B$261)*(1+$B$9),IF(AND(B68="FCF yield",Valuation!G70<>""),(Valuation!G70)*(1+$B$9),E68))
A69: Sum of the parts | F69: =((((Valuation!B73+$B$262)*(Valuation!D73)+(Valuation!B74+$B$263)*(Valuation!D74)+(Valuation!B75)*(Valuation!D75)+(Valuation!B76)*(Valuation!D76))*(1+$B$8))-$B$50-$B$51+$B$52)/$B$53 | G69: =Valuation!$B$65
A70: Value per share at target date (weighted methods) | F70: =SUMPRODUCT(F67:F69,G67:G69)/SUM(G67:G69)
A129: Segment build (model_engine.seg_build): revenue and EBIT are the segment sums plus corporate EBIT
A130: Segment | B130: Base | C130: =Model!E5 | D130: =Model!F5 | E130: =Model!G5
A131: Google Search & other: revenue growth | C131: =Model!E12+$B$4+$B$256 | D131: =Model!F12+$B$4 | E131: =Model!G12+$B$4
A132: Google Search & other: revenue | B132: =Valuation!$B$103 | C132: =B132*(1+C131) | D132: =C132*(1+D131) | E132: =D132*(1+E131)
A133: Google Search & other: EBIT margin | C133: =Model!E14+$B$5 | D133: =Model!F14+$B$5 | E133: =Model!G14+$B$5
A134: Google Search & other: EBIT | C134: =C132*C133 | D134: =D132*D133 | E134: =E132*E133
A135: Google Services other (YouTube ads, Netw: revenue growth | C135: =Model!E16+$B$4 | D135: =Model!F16+$B$4 | E135: =Model!G16+$B$4
A136: Google Services other (YouTube ads, Netw: revenue | B136: =Valuation!$B$104 | C136: =B136*(1+C135) | D136: =C136*(1+D135) | E136: =D136*(1+E135)
A137: Google Services other (YouTube ads, Netw: EBIT margin | C137: =Model!E18+$B$5 | D137: =Model!F18+$B$5 | E137: =Model!G18+$B$5
A138: Google Services other (YouTube ads, Netw: EBIT | C138: =C136*C137 | D138: =D136*D137 | E138: =E136*E137
A139: Google Cloud: revenue growth | C139: =Model!E20+$B$4+$B$257 | D139: =Model!F20+$B$4 | E139: =Model!G20+$B$4
A140: Google Cloud: revenue | B140: =Valuation!$B$105 | C140: =B140*(1+C139) | D140: =C140*(1+D139) | E140: =D140*(1+E139)
A141: Google Cloud: EBIT margin | C141: =Model!E22+$B$5 | D141: =Model!F22+$B$5 | E141: =Model!G22+$B$5
A142: Google Cloud: EBIT | C142: =C140*C141 | D142: =D140*D141 | E142: =E140*E141
A143: Other Bets: revenue growth | C143: =Model!E24+$B$4 | D143: =Model!F24+$B$4 | E143: =Model!G24+$B$4
A144: Other Bets: revenue | B144: =Valuation!$B$106 | C144: =B144*(1+C143) | D144: =C144*(1+D143) | E144: =D144*(1+E143)
A145: Other Bets: EBIT margin | C145: =Model!E26+$B$5 | D145: =Model!F26+$B$5 | E145: =Model!G26+$B$5
A146: Other Bets: EBIT | C146: =C144*C145 | D146: =D144*D145 | E146: =E144*E145
A147: Total segment revenue | C147: =C132+C136+C140+C144 | D147: =D132+D136+D140+D144 | E147: =E132+E136+E140+E144
A148: Total segment EBIT | C148: =C134+C138+C142+C146 | D148: =D134+D138+D142+D146 | E148: =E134+E138+E142+E146
A149: Corporate / unallocated EBIT | C149: =Model!E29+$B$258 | D149: =Model!F29+$B$259 | E149: =Model!G29+$B$260
A150: EBIT (segments + corporate) | C150: =C148+C149 | D150: =D148+D149 | E150: =E148+E149
A249: Driver scenario shifts: line-item changes model_drivers.py resolves from this scenario's driver deltas (added to the Model tab inputs)
A250: D&A % revenue, year 1 | B250: -0.002609705
A251: Capex % revenue, year 1 | B251: -0.016154724
A252: D&A % revenue, year 2 | B252: -0.0042768553
A253: Capex % revenue, year 2 | B253: -0.024467256
A254: D&A % revenue, year 3 | B254: -0.0059746344
A255: Capex % revenue, year 3 | B255: -0.025776916
A256: Google Search & other: revenue growth, year 1 | B256: 0.023184
A257: Google Cloud: revenue growth, year 1 | B257: 0.26056465
A258: Corporate EBIT, year 1 | B258: 1212.6903
A259: Corporate EBIT, year 2 | B259: 1801.5394
A260: Corporate EBIT, year 3 | B260: 2134.2405
A261: Stated EPS, multiple 1 | B261: 1.1126052
... A263: Segment 2 NTM metric | B263: 9313.3278

Sheet Agents
A1: GOOGL: each forecaster's own assumption set through the same engine (from model_engine.json, not live)
A3: Set | B3: Research target (12m) | C3: Median | D3: 25th pct | E3: 75th pct | F3: WACC | G3: Y1 growth | H3: Y1 margin | I3: Terminal growth | J3: DCF weight | K3: Years | L3: Multiples | M3: Supervisor's note
A4: supervisor | B4: 323.03273 | C4: 317.64649 | D4: 253.29508 | E4: 383.85712 | F4: 0.09 | J4: 0 | K4: 3 | L4: P/E 21.2 (ntm)
A5: agent_1 | M5: engine error: no model_inputs found
A6: agent_2 | M6: engine error: no model_inputs found
A7: agent_3 | M7: engine error: no model_inputs found

Sheet Sources
A1: GOOGL: where each input comes from (source numbers point to the list below; F ids to the SEC fact table)
A3: Input | B3: Value | C3: Basis | D3: Sources | E3: SEC fact ids | F3: Derivation
A4: Base revenue FY2025 (fiscal year ended 2025-12-31) | B4: $402,836M | C4: reported | D4: 1, 3 | E4: F3 | F4: filled in (not stated in this set's original work): 10-K filed 2026-02-05, us-gaap:Revenues (fact pack F3).
A5: FY2026 revenue growth | B5: 23.05% | C5: estimate | D5: 1, 3 | E5: F6 | F5: filled in (not stated in this set's original work): H1-2026 year-on-year growth held for the full year: YTD to 2026-06-30 $229,692M / prior-year YTD $186,662M - 1 = 23.05% (F6 derivation) -> FY2026 revenue $495,699M. FY2026 ends before the horizon, so it enters no leg.
A6: FY2027 revenue (consensus) | B6: $615,038M (growth 24.07%) | C6: consensus | D6: 9 | F6: Supervisor-cited consensus: MarketScreener consensus 2027 sales $615,038M (supervisor disagreements evidence, 2026-10-06; the same page as this set's EPS); growth = 615,038 / FY2026 revenue - 1.
A7: FY2028 revenue (consensus) | B7: $734,199M (growth 19.37%) | C7: consensus | D7: 9 | F7: Supervisor-cited consensus: MarketScreener consensus 2028 sales $734,199M, as cited by the supervisor (disagreements evidence) from the same page; growth = 734,199 / 615,038 - 1.
A8: EBIT margin FY2026 / FY2027 / FY2028 (consensus, GAAP after stock comp) | B8: 34.4% / 35.28% / 35.87% | C8: consensus | D8: 9 | F8: filled in (not stated in this set's original work): FY2026 34.4% is the consensus margin agent_3 cites (MarketScreener); FY2027 $216,996M / $615,038M and FY2028 $263,325M / $734,199M are the MarketScreener EBIT and sales the supervisor cites. The set's P/E leg uses its own stated EPS, so these margins move only the DCF diagnostic and the Model tab.
A9: Tax rate | B9: 17.00% | C9: estimate | D9: 1, 3 | F9: Supervisor's 17% (capex D&A derivation): Q2-25 $5,737M / $33,933M = 16.9%, H1-25 $12,986M / $75,722M = 17.1% (8-K, XBRL). Not settled as a separate driver; the agents use 17-18%.
A10: D&A % revenue FY2027 / FY2028 | B10: 13.28% / 16.28% | C10: consensus | D10: 9 | F10: filled in (not stated in this set's original work): consensus EBITDA less EBIT (MarketScreener, as cited in the run): 2027 $298,668M - $216,996M = $81,672M; 2028 $382,826M - $263,325M = $119,501M; over the consensus sales above.
A11: D&A % revenue FY2026 | B11: 13.84% | C11: estimate | D11: 9 | F11: filled in (not stated in this set's original work): no 2026 D&A figure in the run or the fact pack; set so FY2026 FCFF equals consensus 2026 FCF $8,448M (MarketScreener, cited by the supervisor): D&A = 8,448 - NOPAT 141,532 + capex 201,700 = $68,616M (includes other non-cash items). Pre-horizon year: no effect on any leg.
A12: Capex % revenue FY2026 / FY2027 / FY2028 | B12: 40.69% / 48.94% / 46.23% | C12: consensus | D12: 9 | F12: filled in (not stated in this set's original work): consensus capex $201.7B (2026, agent_3), $300,979M (2027) and $339,451M (2028) (MarketScreener, supervisor), over the revenue above. 2026 sits inside the $195-205B guide (Q2 call).
A13: Working capital % of revenue increase | B13: 0% | C13: judgment | F13: filled in (not stated in this set's original work): no working-capital figure in the run; 0. Check: FY2027 NOPAT + D&A - capex on consensus is about -$39B against consensus 2027 FCF of -$36,658M, so working capital is a small item.
A14: Stock comp % revenue (information only; EBIT is GAAP after stock comp) | B14: 6.31% | C14: reported | D14: 1, 3 | E14: F39, F6 | F14: filled in (not stated in this set's original work): TTM stock comp $28,147M (F39) / TTM revenue $445,866M (F6). Counted once, as a cost inside GAAP EPS and EBIT (sbc_treatment cost); not used by the engine with ebit_basis gaap.
A15: Interest rate on net debt / cash | B15: 2.25% | C15: reported | D15: 1, 3 | E15: F74, F97 | F15: filled in (not stated in this set's original work): TTM interest expense $2,252M (F74) / total debt $100,164M (F97). Unused while net debt is negative or set at the horizon.
A16: Discount rate (WACC) | B16: 9.0% | C16: judgment | F16: filled in (not stated in this set's original work): agent_1's stated ~9% roll-forward rate (mega-cap cost of equity), the only discount rate in the run. Its basis: mega-cap cost of equity at about 32% realised vol, less the $0.22 quarterly dividend (about 0.25% yield). Alphabet holds net cash (6/30: cash + debt securities $155.4B vs debt $100.2B), so the cost of equity is used as the WACC. This set has no DCF, so dcf_weight is 0 and the rate only drives the DCF diagnostic and the reverse DCF.
A17: Terminal value (diagnostic only) | B17: exit EV/EBITDA 10.5x | C17: judgment | D17: 9, 27, 26 | F17: filled in (not stated in this set's original work): the supervisor's filing-based US-7 EV/EBITDA median 10.5x (citation audit; agent_3's multiple) on FY2028 EBITDA. No terminal growth is stated anywhere in the run.
A18: P/E multiple | B18: 21.2x | C18: estimate | D18: 29, 30, 31, 32, 33, 36, 37, 45, 46, 47, 48, 49, 50, 51, 52, 53, 54, 55, 56, 57, 58, 59 | E18: MSFT.price, AMZN.price, META.price, RDDT.price, APP.price | F18: Exit-multiple rule (Kilian card 2026-10-26 12:16Z; METHOD.md Peer comparables): exit = peer median x (own NTM multiple / peer median)^k, k = 0.8. Peer median 20.8x (unchanged, gated 2026-10-26: see the rest of this derivation). Own multiple 21.3x on the peers' basis: GOOGL $320.21 / CY2027 Zacks consensus EPS $15.03 = 21.30x, the CY2027 basis of this leg (FY2027 used because FY2026 consensus carries stake gains; same figure as the AMZN round's peer row). Exit = 20.8 x (21.3 / 20.8)^0.8 = 20.8 x 1.0192 = 21.2x (was 20.8x). SOTP segment multiples (Services 18.25x, Cloud 23.3x) stay at their peer medians: a segment has no own traded multiple (rule: no meaningful own multiple -> peer median). PREVIOUS DERIVATION: Peer refresh 2026-10-26 (Kilian 06:07Z: apply the approved set): median of the 5-name set's CY2027 P/E at the 2026-10-23 close; MSFT 524.51 / (0.5 x FY Jun-27 19.65 + 0.5 x FY Jun-28 23.25 = 21.450) = 24.45x; AMZN 248.0 / (CY2027 10.65) = 23.29x; META 642.62 / (CY2027 33.93) = 18.94x; RDDT 144.25 / (CY2027 6.94) = 20.79x; APP 260.25 / (CY2027 19.9) = 13.08x -> median 20.8x (was 21.7x on the 11-name 10-06 set). No premium or discount: no persistence case. EPS: Nasdaq.com / Zacks consensus by fiscal year (retrieved 2026-10-26); prices: 2026-10-23 closes (peers.md ids). EPS basis (per-row reconciliation to filings in comps_review.basis_check): GAAP diluted EPS with stock comp as a cost, excluding investment marks and one-offs (MSFT OpenAI items, AMZN Anthropic marks, META settlement / one-off tax), GOOGL's basis; RDDT, APP, NFLX equal GAAP; ORCL mixed but the Cloud median does not depend on it.
A19: Stated EPS at the horizon (CY2028E) | B19: $17.54 | C19: estimate | D19: 9, 13, 5, 25 | F19: Settled (disagreements 3 and 5): CY2028 consensus $17.89 (MarketScreener) less $0.35 of extra D&A from the standing view's capex base (consensus +10%, ~$331B vs $300.979B; servers 6 years per 10-K). Like-for-like CY2028 at the horizon, not NTM.
A20: Net financial assets at the horizon (adjustment) | B20: $185,600M | C20: estimate | D20: 2, 3, 9, 1 | E20: F90, F91, F92, F93 | F20: Settled (disagreement 4): net cash 6/30 55.911 + 99.500 - 98.165 - 1.999 = 55.247; + H2-26 consensus FCF (8.448 - (84.859 - 80.598)) = +4.187; + 0.75 x 2027 FCF (-36.658) = -27.494; - common dividends 0.22 x 12.23 x 5 = -13.453; - preferred 0.0625 x 19.0 x 1.25 = -1.484 -> 16.99. Plus (87.063 - 80.0) x 0.85 = 6.00; SpaceX 94.1 x 0.75 = 70.58; non-marketable 131.461 x 0.70 = 92.02. Total $185.6B ($14.97/share on 12.40B; $15.03 on 12.35B).
A21: Balance: net debt at 2026-06-30 / at the horizon | B21: -$55,247M / $0 (override) | C21: reported | D21: 3 | E21: F90, F92, F93 | F21: 6/30 net cash $55,247M (supervisor, XBRL; F90, F92, F93). Net debt at the horizon is 0 in the bridge because the supervisor's $17.0B horizon net cash sits inside the net-financial-assets adjustment (counted once).
A22: Diluted shares now / at the horizon | B22: 12,309M / 12,350M | C22: estimate | D22: 1, 6, 2, 3 | E22: F33 | F22: Supervisor: Q2 diluted 12,309M (F33) + ~38M mandatory preferred at the maximum rate + ~50M net SBC creep = ~12.40B. post-research adjustment 2026-10-19 (once-over): the 50M SBC creep is removed (SBC is already a cost in GAAP consensus EPS; counted once) -> 12,309 + 38 = 12,347 ~ 12,350M. Source: once-over item 4, file:///mnt/project-files/valuation/runs/2026-10-06/GOOGL/once_over_2026-10-19.md; https://data.sec.gov/api/xbrl/companyfacts/CIK0001652044.json.
A23: Cross-check custom leg | B23: replaced 2026-10-26 by the SOTP leg (was $329.88 / $334.12, weight 0.4) | C23: estimate | D23: 1, 2, 3, 9 | F23: Peer refresh 2026-10-26: the custom cross-check leg (agents' SOTP / EV mean) is replaced by an explicit SOTP leg (see SOTP rows). Supervisor: mean of the agents' sourcing-corrected legs $349.9 / $327.1 / $320.3 = $332.4. post-research adjustment 2026-10-19 (once-over): -1.40 (fines, 17.356 / 12.40) - 0.91 (SpaceX, mean of -1.03 / -0.88 / -0.83) - 0.21 (finance leases, 2.59 / 12.40) = $329.88. Sources: https://www.sec.gov/Archives/edgar/data/1652044/000165204426000071/ (R65), https://www.sec.gov/Archives/edgar/data/1652044/000165204426000073/information_table.xml, https://data.sec.gov/api/xbrl/companyfacts/CIK0001652044.json; file:///mnt/project-files/valuation/runs/2026-10-06/GOOGL/once_over_2026-10-19.md.
A24: post-research adjustment 2026-10-19 (once-over): accrued fines and settlements | B24: -$17,356M | C24: reported | D24: 2 | F24: "Accrued fines and settlements" $17.356B at 6/30 (10-Q R65; includes the Android fine paid July 2026 at $5.2B, the EC ad-tech charge $3.5B and PriceRunner $2.1B, R19), not deducted from net cash in the run. Effect -17.356 / 12.40 = -$1.40/share on both legs (if consensus 2026 FCF already includes the July $5.2B, -12.156 / 12.40 = -$0.98; unverified). Source: https://www.sec.gov/Archives/edgar/data/1652044/000165204426000071/ (R65, R19); file:///mnt/project-files/valuation/runs/2026-10-06/GOOGL/once_over_2026-10-19.md.
A25: post-research adjustment 2026-10-19 (once-over): SpaceX stake re-marked to the 2026-10-16 close | B25: -$13,610M before haircut; -$10,207.5M after the run's 0.75 | C25: estimate | D25: 2 | F25: 13F at 6/30: 551,189,500 shares, $94,176,237,970 ($170.86/sh). 2026-10-16 close $146.03 (Twelve Data, Nasdaq SPCX; a market price, not an SEC figure): 551,189,500 x 146.03 = $80.49B, -$13.61B against the $94.1B the run carries (-$13.69B against the 13F's $94.176B). P/E leg: -13.61 x 0.75 / 12.40 = -$0.82 x 0.6 = -$0.49; cross-check legs mean -$0.91 x 0.4 = -$0.36; total -$0.86. Source: https://www.sec.gov/Archives/edgar/data/1652044/000165204426000073/information_table.xml; file:///mnt/project-files/valuation/runs/2026-10-06/GOOGL/once_over_2026-10-19.md.
A26: post-research adjustment 2026-10-19 (once-over): $20.0B private-company funding commitment | B26: -$6,000M (= -20,000 x 0.30) | C26: estimate | D26: 2 | F26: Filing figure: "future capital funding commitments with a private company" $20.0B at 6/30 (10-Q R14, contingent on milestones through 2030, an equity derivative), an investing outflow not in FCF. Derived (estimate): at the run's 0.70 stake haircut the loss is 30%: -20,000 x 0.30 = -6,000; -20 x 0.30 / 12.40 = -$0.48 x 0.6 = -$0.29 (P/E leg only). The investee is not named. Source: https://www.sec.gov/Archives/edgar/data/1652044/000165204426000071/R14.htm; file:///mnt/project-files/valuation/runs/2026-10-06/GOOGL/once_over_2026-10-19.md.
A27: post-research adjustment 2026-10-19 (once-over): finance lease liabilities | B27: -$2,590M | C27: reported | D27: 3 | F27: Finance lease liabilities $2.590B (XBRL), not deducted: -2.59 / 12.40 = -$0.21/share on both legs. Operating leases ($18.037B) stay out because rent is in EPS. Source: https://data.sec.gov/api/xbrl/companyfacts/CIK0001652044.json; file:///mnt/project-files/valuation/runs/2026-10-06/GOOGL/once_over_2026-10-19.md.
A28: post-research adjustment 2026-10-19 (once-over): SBC creep shares removed | B28: shares at the horizon 12,400M -> 12,350M | C28: estimate | D28: 3 | E28: F33 | F28: SBC is a cost in GAAP consensus EPS ($15.2B in H1 2026, XBRL), so the supervisor's +50M net SBC creep counts it twice. Removing it: 185.6 / 12.35 = $15.03 vs $14.97 = +$0.06 x 0.6 = +$0.04. Source: https://data.sec.gov/api/xbrl/companyfacts/CIK0001652044.json; file:///mnt/project-files/valuation/runs/2026-10-06/GOOGL/once_over_2026-10-19.md.
A29: Scenario vol (within each scenario) | B29: 21.2% | C29: estimate | D29: 26 | F29: filled in (not stated in this set's original work): fitted (before the once-over items) so the engine's 12-month mixture best matches the supervisor's own 15-strike ladder (least squares on P(close >= K)).
A30: Scenario bear | B30: $206.99 at p 0.22 (engine, peer refresh 2026-10-26; was $252.0 stated 10-06, $227.23 before this refresh) | C30: estimate | D30: 9, 13, 5 | F30: Peer refresh 2026-10-26: current engine values bear $206.99 / base $320.11 / bull $392.82 (model_engine.py check on this set; deltas: drivers as 2026-10-22, P/E levels 15.5x / 20.8x / 24.0x, SOTP parts -25.48% / 0 / +15.38%). The $252 / $370 / $474 below are the 10-06 stated values, history only. This set's own scenario: CY2028 EPS cut to ~$15.5 (capex near the standing view's high case of consensus +39%, and margins flat instead of 35.3% to 35.9%) x 15.5x (between ORCL 17.9x and APP 13.9x on the reconciled set) + ~$12 of stakes after a deeper mark-down = ~$252. Engine deltas {"eps_pct": -0.116306, "multiple": -6.2, "custom_pct": -0.2564} (stated EPS and multiple from the story; the second leg scaled so the blend equals the stated price); engine value $252.00. After the post-research adjustment 2026-10-19 (once-over) items every scenario sits $2.5-3.2 lower. Peer refresh 2026-10-26: multiple level kept (15.5x): delta -5.30 on 20.8x, SOTP parts -25.48%; custom_pct removed with the custom leg.
A31: Scenario base | B31: $320.11 at p 0.53 (engine, peer refresh 2026-10-26; was $370.0 stated 10-06, $338.72 before this refresh) | C31: estimate | D31: 9, 13, 5 | F31: Peer refresh 2026-10-26: current engine values bear $206.99 / base $320.11 / bull $392.82 (model_engine.py check on this set; deltas: drivers as 2026-10-22, P/E levels 15.5x / 20.8x / 24.0x, SOTP parts -25.48% / 0 / +15.38%). The $252 / $370 / $474 below are the 10-06 stated values, history only. This set's own scenario: Equals the reconciled fair value: 0.6 x P/E leg $395.6 (21.7x x $17.54 + $14.97) + 0.4 x $332.4 (mean of the agents' sourcing-corrected SOTP/EV legs $349.9, $327.1, $320.3) = $370.3. Engine deltas {} (no deltas (equals the set's fair value)); engine value $370.31. After the post-research adjustment 2026-10-19 (once-over) items every scenario sits $2.5-3.2 lower.
A32: Scenario bull | B32: $392.82 at p 0.25 (engine, peer refresh 2026-10-26; was $474.0 stated 10-06, $433.65 before this refresh) | C32: estimate | D32: 9, 13, 5 | F32: Peer refresh 2026-10-26: current engine values bear $206.99 / base $320.11 / bull $392.82 (model_engine.py check on this set; deltas: drivers as 2026-10-22, P/E levels 15.5x / 20.8x / 24.0x, SOTP parts -25.48% / 0 / +15.38%). The $252 / $370 / $474 below are the 10-06 stated values, history only. This set's own scenario: CY2028 EPS ~$19 (TPU system revenue lands mostly in 2027, as the CFO said on the Q2 call, and the backlog converts) x 24x (mega-cap median 24.4x) + ~$18 of stakes = ~$474. Engine deltas {"eps_pct": 0.083238, "multiple": 2.3, "custom_pct": 0.43968} (stated EPS and multiple from the story; the second leg scaled so the blend equals the stated price); engine value $474.00. After the post-research adjustment 2026-10-19 (once-over) items every scenario sits $2.5-3.2 lower. Peer refresh 2026-10-26: multiple level kept (24.0x): delta +3.20 on 20.8x, SOTP parts +15.38%; custom_pct removed with the custom leg.
A33: Anthropic stake estimate 2026-10-19: Google's investments in Anthropic (cost basis) | B33: ~$23.3B (est.): ~$3.3B 2023-25 + $10.0B Apr 2026 + $10.0B milestone tranche Q2 2026 (inferred) | C33: estimate | D33: 2 | F33: 2023 ~$300-550M (FT/WSJ via press); Oct 2023 $2B ($500M upfront + $1.5B over time, convertible note; Anthropic representative / Bloomberg via https://www.verdict.co.uk/google-investing-2bn-in-anthropic/, 2023-10-30); Jan 2025 $1B (FT via https://siliconrepublic.com/start-ups/google-anthropic-1bn-investment, 2025-01-22); Fortune 2026-07-22: "an initial $300 million investment ... has since grown to $13.3 billion", with "commitments of up to $30 billion more" (so the $13.3B includes the funded $10B of the April 2026 deal; inference) (https://fortune.com/2026/07/22/anthropic-spacex-investments-google-earnings-biggest-ever-profit-quarter/). Q1 10-Q: 'In March 2026, we committed to a $40.0 billion investment in a private company' (EDGAR full-text search); note 5: 'a $10.0 billion capital commitment and $30.0 billion of future capital funding contingent upon ... milestones through 2030' (https://www.sec.gov/Archives/edgar/data/1652044/000165204426000048/goog-20260331.htm); Q2 10-Q: remaining contingent commitment $20.0B at 6/30 and measurement-alternative cost +$18.15B in Q2 (29,489 -> 47,642) -> about $20B funded in Q2 (inference). Estimate: 13.3 + 10.0 = $23.3B.
A34: Anthropic stake estimate 2026-10-19: Anthropic valuation used (base) | B34: $1,500B IPO valuation (reported investor discussions); variant $1,924B | C34: estimate | F34: Reuters, via Investing.com 2026-10-15: investors at the 2026-10-14 investor day discussed ~$1.5T for the planned November IPO, down from ~$2T (https://www.investing.com/news/stock-market-news/some-investors-push-anthropic-to-cut-ipo-valuation-to-15-trillion--report-4952696). Company target per IFR ~$2T, raise up to $100B (https://www.ifre.com/equities/2499407/anthropic-pushes-ahead-with-mid-november-ipo). Last private round: Series H $65B at $965B post, 2026-05-28 (https://www.anthropic.com/news/series-h). Market-implied (Polymarket, prices read 2026-10-19, labelled as probabilities): pricing valuation E = $1.74T given an IPO, first-day close E = $1.96T, P(no IPO by end-2027) 3.5-4.3%; mixed with $965B if no IPO: $1.71T / $1.92T (https://gamma-api.polymarket.com/public-search?q=anthropic%20ipo).
A35: Anthropic stake estimate 2026-10-19: Google fully diluted ownership at the IPO | B35: 11.28% (est.; range 9.75-12.49%) | C35: estimate | D35: 2 | F35: Start 14% (NYT from Anthropic's court filings, 2025-03; "owns a 14% stake ... holds no voting rights", "can own only up to 15%": https://www.tipranks.com/news/the-fly/google-owns-14-stake-in-anthropic-holds-no-voting-rights-ny-times-reports, 2025-03-12). Dilution path: Series E 3.5/61.5 (https://www.anthropic.com/news/anthropic-raises-series-e-at-usd61-5b-post-money-valuation), F 13/183 (https://www.anthropic.com/news/anthropic-raises-series-f-at-usd183b-post-money-valuation), G 30/380 (GIC 2026-02-12, https://www.gic.com.sg/uploads/2026/02/GIC-Leads-Series-G-in-Anthropic.pdf) -> 11.30%; + Google $10B (and Amazon $5B) at a $350B valuation (Anthropic via TechCrunch 2026-04-24, https://techcrunch.com/2026/04/24/google-to-invest-up-to-40b-in-anthropic-in-cash-and-compute/; Bloomberg) -> 13.40%; Series H $50B new money at $965B -> 12.71%; + $10B milestone tranche at the H price -> 13.60% (14.75% if at the G price). Filing cross-check: Anthropic carrying est. $105B / $965B = 10.9%. Pre-IPO estimate 12.5% (between the two). Then x 0.95 for the 5% Public Benefit Fund (Anthropic 2026-10-18, subject to stockholder approval; https://www.anthropic.com/news/public-benefit-fund) x (1 - $75B est. primary / $1,500B) = 11.28%.
A36: Anthropic stake estimate 2026-10-19: lock-up / illiquidity discount | B36: 10.37% (range 9.6-14.4%) | C36: estimate | F36: Finnerty (2012) average-strike put, 65% vol, 0.5 year (a standard 180-day lock-up; terms not reported): 10.37%; 1 year (orderly sale of a ~11% block) 14.36%. Vol basis: SpaceX (SPCX) realized vol since its 2026-06-12 IPO 67% ex first week (82% incl.), Twelve Data daily closes to 2026-10-19; SPCX priced at $135, closed day one $160.95, fell to $108.37 (2026-07-31), $147.97 on 2026-10-19.
A37: Anthropic stake estimate 2026-10-19: Anthropic carrying value already in the non-marketable line | B37: ~$105B (est.; range $87.9-116B) x 0.70 = $73.50B already counted | C37: estimate | D37: 2, 3 | F37: Q2 10-Q: measurement-alternative $124.259B 'primarily consist[s] of our investment in a private company'; $87.9B remeasured in Q2 (Series H 2026-05-28); Q2 gross upward adjustments $77.544B; cumulative upward 80,792 -> 85,732 implies ~$72.6B of upward adjustments left with SpaceX's reclass (carried ~$73.5B = 551.19M sh x ~$133, close to the $135 IPO price). Low = remeasured amount $87.9B; high = $124.3B less ~$8B other private holdings; central $105B. Press attributes the Q1 ($36.9B) and Q2 ($99.0B) gains mainly to Anthropic and SpaceX (Fortune 2026-04-30, 2026-07-22); no filing names Anthropic.
A38: Anthropic stake estimate 2026-10-19 | B38: +$51,210M (+$4.15/share P/E leg; +$4.10 cross-check; +$4.13 on fair value); range +$22.7B to +$76.0B | C38: estimate | D38: 2 | F38: 11.28% x $1,500B = $169.22B; x (1 - 0.1037) = $151.67B; tax 0.21 x (151.67 - 23.3) = $26.96B -> $124.71B after tax; minus 105 x 0.70 = $73.50B already counted -> +$51.21B / 12,350M = +$4.15 x 0.6 = +$2.49; cross-check leg +$4.10 x 0.4 = +$1.64; total +$4.13. Variant at $1.92T: +$86.9B (+$7.03 P/E leg, +$7.05 on fair value). Low/high: 9.75%/1-yr discount/carry $116B -> +$22.7B; 12.49%/carry $87.9B -> +$76.0B. Full write-up: file:///mnt/project-files/valuation/runs/2026-10-06/GOOGL/anthropic_stake_2026-10-19.md
A39: Waymo / Other Bets SOTP 2026-10-19: Waymo funding rounds and valuations | B39: Feb 2026 $16.0B at $126B post-money; Oct 2024 $5.6B at >$45B; Jun 2021 $2.5B (undisclosed); Jul 2020 $3.2B at ~$30B | C39: reported | F39: Waymo blog 2026-02-02: 'raised a $16 billion investment round valuing the company at $126 billion post-money', led by Dragoneer, DST Global and Sequoia, 'Alphabet's strong sustained support as our majority investor' (https://waymo.com/blog/2026/02/waymo-raises-usd16-billion-investment-round). Alphabet ~$13B of it per Bloomberg, reported (https://news.bloomberglaw.com/private-equity/waymo-raises-16-billion-from-alphabet-others-to-expand-service, 2026-02-02); Q1 10-Q: 'the significant majority of which was funded by Alphabet' (https://www.sec.gov/Archives/edgar/data/1652044/000165204426000048/goog-20260331.htm). Oct 2024 $5.6B led by Alphabet, valued at more than $45B (Electrek 2024-11-01, https://electrek.co/2024/11/01/waymo-is-now-valued-at-a-staggering-45-billion/). 2021 $2.5B, Alphabet among the investors, valuation not stated (Waymo blog 2021-06-16, https://waymo.com/blog/2021/06/transforming-mobility-with-confidence.html). 2020: first external round closed at $3.2B in July 2020 at a $30B valuation (Global Venturing 2021-06-17, https://globalventuring.com/corporate/waymo-drives-through-to-2-5bn-round/).
A40: Waymo / Other Bets SOTP 2026-10-19: Alphabet fully diluted ownership of Waymo | B40: ~80% (est.; range 75-85%) | C40: estimate | D40: 2 | F40: Dilution path (estimate; terms of 2020/2021 not disclosed): 2020 $3.2B at ~$30B with ~10% from Alphabet -> 90.4%; 2021 $2.5B at an assumed flat $30B pre with ~20% from Alphabet -> 85.0%; 2024 $5.6B at $45B post with ~$4.6B from Alphabet -> 84.6%; 2026 $16B at $126B post with ~$13B from Alphabet -> 84.2% basic; x 0.95 for employee equity (Waymo Bet PSUs, Q1 10-Q exhibit 10.03; $2.1B valuation-based Waymo comp charge in Q4 2025, 10-K) -> ~80%. Filing cross-check: noncontrolling interests in consolidated subsidiaries $3.4B (12/31/25) -> $7.1B (6/30/26) (Q2 10-Q, https://www.sec.gov/Archives/edgar/data/1652044/000165204426000071/goog-20260630.htm), up $3.7B, consistent with ~$3B of outside money in the Feb round.
A41: Waymo / Other Bets SOTP 2026-10-19: Waymo operating scale | B41: >500k paid rides/week, 14 US cities (Sep 2026); 15M rides in 2025; fleet >4,000; revenue run-rate ~$355M (Feb 2026, third-party est.) | C41: reported | F41: Waymo blog 2026-02-02: 'more than 400,000 rides provided every week across six major U.S. metropolitan areas'; 'in 2025 alone ... 15 million rides'; 20+ more cities planned in 2026 incl. Tokyo and London (https://waymo.com/blog/2026/02/waymo-raises-usd16-billion-investment-round). 500,000 paid rides/week across 10 cities (TechCrunch 2026-03-27, https://techcrunch.com/2026/03/27/waymo-skyrocketing-ridership-in-one-chart/). Paid rides in Denver, San Diego and Tampa from 2026-09-01, 14 cities, fleet >4,000, >500k rides/week (https://driveteslacanada.ca/news/waymo-driverless-rides-denver-san-diego-tampa/, 2026-09-01). Target 1M paid rides/week by end-2026 (co-CEO, https://uk.finance.yahoo.com/news/waymo-eyes-1-million-paid-152612311.html). Revenue not disclosed; Sacra estimate $355M annualized Feb 2026, ~$15-17 per ride (https://sacra.com/c/waymo/), labelled third-party estimate.
A42: Waymo / Other Bets SOTP 2026-10-19: Other Bets operating loss and Waymo's share | B42: Q1 2026 -$2.100B, Q2 2026 -$1.799B (run-rate -$7.80B); FY2025 -$7.515B incl. $2.1B Waymo comp charge; Waymo share ~65% (est.) | C42: estimate | D42: 1, 2 | F42: Segment note: Other Bets operating loss FY2023 -$4,095M, FY2024 -$4,444M, FY2025 -$7,515M (10-K, https://www.sec.gov/Archives/edgar/data/1652044/000165204426000018/goog-20251231.htm; FY2025 'included a $2.1 billion employee compensation charge recognized in the fourth quarter for Waymo'); Q1 2026 -$2,100M (Q1 10-Q); Q2 2026 -$1,799M, H1 -$3,899M; Other Bets revenue Q2 $382M (Q2 10-Q / 8-K). TTM to Q2 2026 -$8.94B, -$6.84B ex the charge. Waymo is not reported separately; 65% (range 55-75%) is an estimate (Waymo is the largest and scaling bet; the rest are Verily, Wing, X, Calico and GFiber, which is being divested for $1.5B cash + $2.0B note + 49.99% equity, Q2 10-Q). Waymo pre-tax loss $5.07B, after tax at 17% $4.21B.
A43: Waymo / Other Bets SOTP 2026-10-19: haircut and cash | B43: 20% haircut on Alphabet's share of Waymo EV (range 10-30%); Waymo cash est. $12B (range 8-16) already in consolidated net cash | C43: estimate | F43: Haircut: the $126B mark is 8.5 months old; about $13B of the $16B came from Alphabet itself, so only ~$3B was priced by outside investors; new-money terms likely carry preferences; no liquidity; competition (Tesla, Zoox). Partly offset by growth since (400k -> 500k+ rides/week, 6 -> 14 cities). No tax haircut: Waymo is a consolidated subsidiary held as a going concern. Cash: ~$2B pre-round + $16B raised - ~$4B burn Feb-Oct 2026 (op. loss less non-cash SBC plus fleet capex, est.) ~ $12-14B; $12B used.
A44: Waymo / Other Bets SOTP 2026-10-19 | B44: +$158,066M (loss add-back 4.207 x 20.8 = $87.51B + stake $70.56B; was +$161,850M at 21.7x); +$12.72/share on 12,423M on both legs | C44: estimate | D44: 2 | F44: Peer refresh 2026-10-26: add-back 7.798 x 0.65 x 0.83 x 20.8 = $87.51B (4.207 x 20.8); stake $70.56B unchanged -> $158.07B. Add-back 7.798 x 0.65 x 0.83 x 21.7 = $91.29B; stake 0.80 x (126 - 12) x 0.80 - 0.20 x 12 = $70.56B; non-marketable line $0 -> +$161.85B / 12,350M = +$13.11 x 0.6 = +$7.86; cross-check +$4.86 x 0.4 = +$1.94. Variant (scenario view): 2030 run-rate rides/week 2M/6M/15M at $15/ride (+$0/1/3B licensing) at 5x/15x/20x sales, p 0.30/0.45/0.25, discounted 4 yrs at 15% = $65.3B, less ~$15B PV of interim burn = EV $50.3B (equity ~$62B vs the $126B round); stake value 0.80 x 50.3 - 0.20 x 12 = $37.8B -> increment +$129.1B (+$10.45/share). What the round needs: ~$10.5B EBIT by 2032 at 25x and 15% (~$35B revenue, ~45M rides/week at $15, or licensing/international). Full write-up: file:///mnt/project-files/valuation/runs/2026-10-06/GOOGL/anthropic_stake_2026-10-19.md
A45: remaining items 2026-10-19: conglomerate discount evidence | B45: Berger & Ofek (1995) ~15% average diversification discount; Villalonga (2004) diversification premium on Census BITS data; Campa & Kedia (2002) discount falls once self-selection is controlled; listed holdcos: SoftBank ~49% (FY-end March 2026), Naspers/Prosus ~43% combined (Aug 2026) | C45: reported | F45: Graham, Lemmon & Wolf (Duke): 'Berger and Ofek (1995) find that U.S. conglomerates are priced at approximately a 15% discount on average' (https://people.duke.edu/~jgraham/GrahamLemmonWolf.pdf). Villalonga, JF 59(2) 2004, abstract: 'Using these data on a sample that yields a discount according to segment data, I find a diversification premium'; its introduction cites Campa and Kedia (2002) on selection bias (https://pages.stern.nyu.edu/~bvillalo/Villalonga_DivPremium_JF2004.pdf). SoftBank: NAV JPY 40.1T vs market cap JPY 20.3T at FY-end March 2026, 'Der Abschlag: 49 Prozent' (https://www.kapitalmarktexperten.de/softbank-aktie-49-prozent-abschlag-auf-nav-bestaetigt/, 2026-07-01). Naspers/Prosus: 'the combined discount stayed at around 43%', peak ~65% before the 2022 buybacks (https://www.vermoegenszentrum.ch/en/stock-exchange-and-markets/news/naspers-and-prosus-step-efforts-shrink-net-asset-value-discount, 2026-08-27). All read 2026-10-19.
A46: remaining items 2026-10-19: conglomerate overlay 10% on non-core stakes | B46: -$28,970M (-$2.35/share on 12,350M, both legs; -$2.35 on fair value); variants $0 to -$7.71/share | C46: estimate | F46: Post-haircut non-core stakes ($B): Anthropic after tax and lock-up 124.71 (adjustment 'Anthropic stake estimate 2026-10-19'); other non-marketable (131.461 - 105) x 0.70 = 18.52; SpaceX 94.1 x 0.75 - 10.21 (once-over re-mark) = 60.37; other marketable (87.063 - 80.0) x 0.85 = 6.00; Waymo stake 70.56 (Waymo SOTP part b); Isomorphic stake 9.52 (row below). Total 289.68 x 10% = 28.97 -> -$28,970M; / 12,350M = -$2.35 on the P/E leg and -$2.35 in the cross-check custom leg -> -$2.35 on fair value. Why 10%: tax (i) and illiquidity (ii) are already deducted stake by stake (Anthropic -26%, SpaceX x0.75, private book x0.70, other marketable x0.85, Waymo x0.80), (iii) holdco costs and leverage are small for Alphabet (net cash, no holdco layer), so only (iv) capital-allocation/agency cost remains, for which Berger-Ofek's ~15% is the cleanest estimate and the later literature (Campa-Kedia, Villalonga) says it is smaller. Effective total factors: SpaceX 0.75 x 0.9 = 0.675; private book 0.70 x 0.9 = 0.63; Waymo 0.80 x 0.9 = 0.72 of EV. Not applied to the core P/E (peer-median multiple), net cash or the Waymo loss add-back (a correction to the core multiple). Write-up: file:///mnt/project-files/valuation/runs/2026-10-06/GOOGL/remaining_items_2026-10-19.md
A47: remaining items 2026-10-19: pre-horizon stock comp: RSU tax-withholding cash | B47: -$30,140M (-$2.44/share P/E leg; 0 cross-check; -$1.46 on fair value) | C47: estimate | F47: Q2 10-Q cash flow, financing: 'Net payments related to stock-based award activities' six months 2026 (12,056) [$M] (https://www.sec.gov/Archives/edgar/data/1652044/000165204426000071/goog-20260630.htm). x 2.5 half-years (6/30/26 to the 2027-10-06 horizon, ~15 months) = $30.14B; / 12,350M = $2.44 x 0.6 = -$1.46 on fair value. Why it is uncharged: the P/E leg rolls net cash to the horizon on consensus FCF (CFO less capex; CFO adds SBC back, 'Stock-based compensation expense 14,708' H1 2026) and withholding is a financing outflow, while CY2028 EPS carries SBC only from the horizon on. The 142M treasury-method RSU shares cover only comp recognised by 6/30 ('$59.1 billion of unrecognized compensation cost related to unvested RSUs and PSUs', Note 13). SBC counted once (METHOD.md 2026-10-12): pre-horizon as withholding cash here, post-horizon as the cost in GAAP EPS; the +50M SBC-creep shares stay removed and the $40B ATM ('primarily intended to be used to meet tax obligations associated with employee equity grants', Q2 10-Q) is not counted as dilution. Cross-check: cost basis H1 total SBC expense $15.2B (Note 13) x 2.5 x (1 - 21% tax deduction) = $30.0B. Read 2026-10-19.
A48: remaining items 2026-10-19: EU DMA fine (not accrued at 6/30) | B48: EUR 890M = $998M (EUR 460M Search self-preferencing + EUR 430M Play anti-steering, decided 2026-07-23) | C48: reported | F48: Pearl Cohen 2026-07-30: the EC fined Google EUR 890 million on 2026-07-23, EUR 460M for self-preferencing in Google Search and EUR 430M for Google Play anti-steering; 60 days to comply, periodic penalties up to 5% of worldwide turnover possible (https://www.pearlcohen.com/european-commission-fines-google-e890-million-for-digital-markets-act-breaches/). The Q2 10-Q, filed the same day, still says of the DMA investigations 'we cannot reasonably estimate a probable loss' (https://www.sec.gov/Archives/edgar/data/1652044/000165204426000071/goog-20260630.htm), so it is not in the $17.356B accrued fines deducted in the once-over. Unit conversion: 0.89 x EUR/USD 1.1212 (Twelve Data, 2026-10-19 close 1.12113) = $0.998B. Read 2026-10-19.
A49: remaining items 2026-10-19: DOJ search appeal, probability-weighted | B49: -$7,052M (-$0.57/share, both legs) | C49: estimate | F49: Status (reported): final judgment December 2025 (default payments allowed, data-sharing and syndication remedies); Google appealed January 2026, stay denied as premature; DOJ and states appealed February 2026 (Q2 10-Q Note 10, https://www.sec.gov/Archives/edgar/data/1652044/000165204426000071/goog-20260630.htm). Google's opening brief 2026-05-22 challenges liability (https://ppc.land/google-asks-appeals-court-to-throw-out-its-entire-search-monopoly-loss/). DOJ 2026-07-28 brief asks the D.C. Circuit to vacate the denial of a payment ban and remand; no Chrome/Android divestiture sought; Google pays 'over $26 billion annually' for defaults (https://www.courthousenews.com/doj-urges-dc-circuit-to-beef-up-remedies-in-google-monopoly-ruling/, 2026-07-29). Parties asked for argument as soon as Dec. 9 (https://www.law360.com/articles/2533918/doj-google-want-dc-circ-priority-for-search-appeal, 2026-10-05). Scenarios (est.): affirmed p 0.60 -> 0; remand without ban p 0.10 -> 0; Google wins p 0.15 -> +1% CY2028 EPS = 17.54 x 0.01 x 21.7 = +$3.81; payment ban p 0.15 -> -2% EPS = -$7.61. Weighted 0.15 x 3.81 - 0.15 x 7.61 = -$0.57/share x 12,350M = -$7,052M. Read 2026-10-19.
A50: remaining items 2026-10-19: ad tech, expected costs | B50: -$7,750M (-$0.63/share, both legs) | C50: estimate | F50: Status (reported): 2026-09-02 order rejected AdX divestiture ('structural remedies are neither realistic nor needed') and the open-source auction, imposed six years of global behavioural remedies with a monitor and technical committee, rejected the 50% revenue escrow; joint proposed final judgment due 2026-10-02 (https://ppc.land/google-faces-six-year-worldwide-ad-tech-decree-instead-of-adx-sale/, 2026-09-17). Texas-led states' trial follows the DOJ remedy decision; Alphabet 'cannot estimate a possible loss' (Q2 10-Q Note 10, https://www.sec.gov/Archives/edgar/data/1652044/000165204426000071/goog-20260630.htm). EC ad tech fine (EUR 2.95B / $3.5B charge) already accrued; complainants 'no longer expect a divestiture' (https://thenextweb.com/news/brussels-google-adtech-breakup-alone-brinkema, 2026-09-04). Network revenue Q2 2026 $7,303M vs $7,354M (Q2 10-Q). Expected costs (est.): AdX divestiture on appeal p 0.07 x $25B lost value (AdX/DFP profit ~$2.9B = Network run-rate $28.5B (H1 $14.274B x 2) x ~30% kept after publisher payouts (the 10-Q: most Network advertiser revenue is paid out as TAC) x ~34% margin, x 21.7 = ~$63B, sold at a forced ~40% loss) = $1.75B; Texas states' penalties/settlement $2.5B; private publisher/advertiser follow-on damages $3.0B; EU structural remedy p 0.05 x $10B = $0.5B; total $7.75B / 12,350M = $0.63. Read 2026-10-19.
A51: remaining items 2026-10-19: legal remedies, probability-weighted | B51: -$15,800M (-$1.28/share P/E leg; -$1.28 cross-check; -$1.28 on fair value) | C51: estimate | F51: DMA -998 (hard) + DOJ search -7,052 (est.) + ad tech -7,750 (est.) = -$15,800M; / 12,350M = -$1.28 on both legs. Write-up: file:///mnt/project-files/valuation/runs/2026-10-06/GOOGL/remaining_items_2026-10-19.md
A52: remaining items 2026-10-19: Isomorphic Labs funding, valuation and losses | B52: Series B $2.1B (May 2026); prior valuation ~$17.5B; talks at >= $40B, possibly $50B (Bloomberg 2026-10-08, not closed); FY2025 loss GBP 159.4M (FY2024 GBP 74.8M); headcount avg 225 (2025), ~427 (March 2026) | C52: reported | F52: Crypto Briefing 2026-10-08: 'in early talks to raise money at a valuation of at least $40 billion', could reach $50B; previously valued at roughly $17.5 billion; $2.1 billion Series B in May 2026 (https://cryptobriefing.com/isomorphic-labs-funding-40-billion-valuation/). RuntimeWire 2026-10-08 citing Bloomberg: at least $40B, 'could reach $50 billion', 'the financing has not closed', raised $2.1B about five months earlier (https://runtimewire.com/article/isomorphic-labs-40-billion-valuation-funding-talks). Isomorphic Labs Limited (UK 13223825) full accounts FY2025, filed 2026-10-02: loss for the year GBP 159,416,384 (2024: GBP 74,767,042), administration expenses GBP 250.7M, no turnover, average headcount 225 (2024: 125); GBP 402.4M of new shares issued to its parent on 2026-06-12 (https://find-and-update.company-information.service.gov.uk/company/13223825/filing-history). Revelio Labs: ~427 employees as of March 2026 (https://www.reveliolabs.com/companies/isomorphic-laboratories/employees). Isomorphic sits in Other Bets (FY2025 10-K, https://www.sec.gov/Archives/edgar/data/1652044/000165204426000018/goog-20251231.htm). Q2 2026 'Sale of interest in consolidated entities' $558M (Q2 10-Q equity statement). Read 2026-10-19.
A53: remaining items 2026-10-19: Isomorphic Labs stake + loss add-back | B53: +$16,426M (loss add-back 0.332 x 20.8 = $6.906B + stake $9.52B; was +$16,724M at 21.7x); +$1.32/share on 12,423M on both legs; variant +$2.42 (10-19, history) | C53: estimate | F53: Peer refresh 2026-10-26: loss add-back 0.4 x 0.83 x 20.8 = $6.906B + stake $9.52B. Stake: 0.80 x (17.5 - 2.0) x (1 - 0.20) - 0.20 x 2.0 = $9.52B. Ownership ~80% (est., range 75-90%): wholly owned at the 2021 spin-out; outside money in the $0.6B (2025) and $2.1B (2026) rounds was a minority (Alphabet, GV and CapitalG took part; Q2 2026 sale of interest in all consolidated entities only $558M), plus employee equity. Cash ~$2B (est.): $0.6B + $2.1B raised less ~$0.5B burn since March 2025. Haircut 20% as for Waymo (stale and partly insider-priced mark). Loss add-back: 2026 loss ~$0.4B (est.) = FY2025 GBP 159.4M x ~2 (loss and headcount roughly doubled in 2025; ~427 staff by March 2026) x GBP/USD 1.33 = ~$0.42B; 0.4 x (1 - 0.17) x 21.7 = $7.20B, taken from the 35% of the Other Bets loss the Waymo SOTP leaves capitalised (no overlap). Total 9.52 + 7.20 = $16.724B / 12,350M = +$1.35 x 0.6 = +$0.81. Cross-check: agent_1 9.52 / 12.30 x 1.09 = +0.84; agent_2 (0.4 x 0.83 x 18 + 9.52) / 12.35 = +1.25; agent_3 (0.4 x 10.5 + 9.52) / 12.35 = +1.11; mean +$1.07 x 0.4 = +$0.43. Fair value +$1.24. Write-up: file:///mnt/project-files/valuation/runs/2026-10-06/GOOGL/remaining_items_2026-10-19.md
A54: remaining items 2026-10-19: diluted shares at 6/30 (point in time) | B54: 12,423M (12,230M outstanding + 142M RSU + 50.5M preferred at ~$381) vs 12,350M; -$1.08 on fair value | C54: estimate | F54: Q2 10-Q (https://www.sec.gov/Archives/edgar/data/1652044/000165204426000071/goog-20260630.htm): 12,230M Class A, B and C shares issued and outstanding at 6/30 (balance sheet); Q2 diluted computation: basic 12,151M + RSUs and other contingently issuable 142M + preferred 16M (if-converted, weighted) = 12,309M (Note 12); 385M depositary shares = 19.25M mandatory convertible preferred, split evenly, rates 2.2520-2.8160 (Series A) and 2.2740-2.8420 (Series B), conversion ~2029-05-15 (Note 11); June 4 offering plus a 28M-share private placement to a Berkshire Hathaway affiliate. Preferred shares at the model fair value ~$381: 19.25M x $1,000 / $381 = 50.5M (est.; max 54.5M at <= ~$355, min 43.6M at >= ~$444). 12,230 + 142 + 50.5 = 12,422.5 -> 12,423M (+73M, +0.59%). Effect: P/E leg adjustments over 12,423M instead of 12,350M (on the old $362.51B: -$0.17 x 0.6 = -$0.10); cross-check legs (agent_1 12.30B, agents 2 and 3 12.35B) mean -0.72% x $338.84 = -$2.43 x 0.4 = -$0.97; total -$1.08. Read 2026-10-19.
A55: remaining items 2026-10-19: GFiber divestiture cash + note | B55: +$3,300M (+$0.27/share, both legs) | C55: estimate | F55: Q2 10-Q Note 8 (https://www.sec.gov/Archives/edgar/data/1652044/000165204426000071/goog-20260630.htm): 'Upon closing, we expect to receive $1.5 billion in cash, a $2.0 billion note receivable, and a 49.99% equity interest'; close expected late 2026; held for sale, PP&E $7.1B, no impairment. 1.5 + 2.0 x 0.9 (note haircut, est.) = $3.3B / 12,350M = +$0.27 on both legs. The 49.99% equity-method share flows through post-close EPS, so it is not added. Read 2026-10-19.
A56: Driver build (driver_models 2026-10-22) | B56: 5 drivers: paid_clicks, cpc, cloud_backlog, cloud_conv, capex | C56: estimate | D56: 1, 2, 3, 5, 9 | E56: F3, F7, F48, F49, F50, F53 | F56: Search & other = 224,532 x clicks/100 x CPC/100; Cloud = opening backlog x conversion; Services other and Other Bets plain; EBIT = segment margins x revenue + Other Bets + Alphabet-level - (capex-vintage depreciation - 5.92% x revenue); CY2028 EPS = (FY2028 EBIT + OI&E ex-gains 0) x (1 - 17%) / 12,423M replaces the stated $17.54. OI&E ex-gains 0: H1-26 interest income $2,811M x 2 ~ $5.6B vs interest expense Q2 $1,278M x 4 ~ $5.1B (10-Q, F75), falling cash after 2027 FCF.
A57: driver:paid_clicks | B57: Google Search & other paid clicks: 100 -> 112/121/129.4 (estimate) | C57: estimate | F57: Index only (Alphabet discloses % changes, not levels). FY2026 +12% = H1 +13% (10-Q) with H2 at ~+11% (CFO, Q2 call: Q3 laps the Search acceleration; run evidence agent_1); FY2027 +8%, FY2028 +7%: fade toward the FY2025 rate (+6%, 10-K) as AI Overviews/AI Mode volume gains annualise.
A58: driver:cpc | B58: Google Search & other cost-per-click: 100 -> 103.5/106.6/109.8 (estimate) | C58: estimate | F58: FY2026 +3.5% = H1 +4% / Q2 +3% (10-Q); FY2027-28 +3%/yr = the Q2 rate held (Tinuiti Q2 CPC +1% is context only per the citation gate; Meta/Amazon ad growth +27%/+26% taking incremental share, agent_2 evidence).
A59: driver:cloud_backlog | B59: Google Cloud backlog (remaining performance obligations) at the start of the year: 93.2 -> 242.8/577/660 (estimate) | C59: estimate | F59: base = YE2024 and y1 = YE2025 are filing values (opening backlog of FY2025 / FY2026). y2 (YE2026) = 519.5 + H2-26 bookings at book-to-bill 2.0 x H2 Cloud revenue ~57.2 - 57.2 = 576.7 ~ 577 (Q2 implied book-to-bill (519.5 - 467.6 + 24.8) / 24.8 = 3.1, FY2025 (242.8 - 93.2 + 58.7) / 58.7 = 3.5: 2.0 assumes the Anthropic-size deals do not repeat). y3 (YE2027) = 577 + 2027 revenue 164 x (1.5 - 1) = 659 ~ 660.
A60: driver:cloud_conv | B60: Google Cloud revenue / opening backlog: 0.6299 -> 0.42/0.285/0.3 (estimate) | C60: estimate | F60: y1: FY2026 Cloud = H1 44.8 + Q3 ~27.2 + Q4 ~30.0 (Q2 x 1.10, x 1.10 q/q, below Q2 +82% y/y momentum) = ~102.0 / 242.8 = 0.42. y2: ~164 / 577 = 0.285 (>50% of 513.9 in 24 months, 10-Q, ~= 140 from the Q2 backlog in 2027 as TPU system sales land mostly in 2027 per the CFO, plus ~25 from later bookings/consumption). y3: ~198 / 660 = 0.30 (H1-28 tail of the Q2 backlog ~70 x 2 plus newer contracts).
A61: driver:capex | B61: Capital expenditures (purchases of property and equipment): 91.45 -> 200/301/339.5 (estimate) | C61: estimate | F61: FY2026 = guide midpoint (H2 implied 119.4 vs H1 80.6; Q2 alone 44.9); FY2027-28 = consensus (the CFO says 2027 will "increase significantly"). Depreciation = capex vintages, 60% servers and network equipment over 6 years (10-K: servers and network equipment generally six years; 60% = the 10-Q share of technical infrastructure assets that are servers and network equipment, 12/31/25 and 6/30/26) and 40% data centre land, buildings and related assets over 15 years (estimate; 10-K buildings seven to 40 years, land not depreciated), half-year convention, all vintages still in life (2011 onward), scaled by k = 0.693 (placed-in-service lag) fitted to FY2025 depreciation $21,136M (10-K cash flow); the segment margins carry the H1-26 intensity (13,586 / 229,692 = 5.92% of revenue, Q2 10-Q) and the excess is charged at Alphabet level.
A62: SOTP: Google Services multiple | B62: 18.25x | C62: estimate | D62: 31, 32, 33, 34, 36, 37, 45, 46, 47, 48, 49, 50, 51, 52, 53, 54, 55, 56, 57, 58, 59 | E62: META.price, RDDT.price, APP.price, NFLX.price | F62: Median CY2027 P/E of the ad / consumer-platform peers at the 2026-10-23 close: META 642.62 / 33.93 = 18.94x; RDDT 144.25 / 6.94 = 20.79x; APP 260.25 / 19.9 = 13.08x; NFLX 65.85 / 3.75 = 17.56x -> median 18.25x (mean of the middle two). Same EPS source and basis as the P/E leg. EPS basis (per-row reconciliation to filings in comps_review.basis_check): GAAP diluted EPS with stock comp as a cost, excluding investment marks and one-offs (MSFT OpenAI items, AMZN Anthropic marks, META settlement / one-off tax), GOOGL's basis; RDDT, APP, NFLX equal GAAP; ORCL mixed but the Cloud median does not depend on it.
A63: SOTP: Google Cloud multiple | B63: 23.3x | C63: estimate | D63: 29, 30, 35, 36, 37, 45, 46, 47, 48, 49, 50, 51, 52, 53, 54, 55, 56, 57, 58, 59 | E63: MSFT.price, AMZN.price, ORCL.price | F63: Median CY2027 P/E of the cloud proxies at the 2026-10-23 close: MSFT 524.51 / (0.5 x FY Jun-27 19.65 + 0.5 x FY Jun-28 23.25 = 21.450) = 24.45x; AMZN 248.0 / (CY2027 10.65) = 23.29x; ORCL 126.16 / (5/12 x FY May-27 6.73 + 7/12 x FY May-28 9.16 = 8.148) = 15.48x -> median 23.3x (AMZN). Whole-company P/Es: no pure-play hyperscaler trades. EPS basis (per-row reconciliation to filings in comps_review.basis_check): GAAP diluted EPS with stock comp as a cost, excluding investment marks and one-offs (MSFT OpenAI items, AMZN Anthropic marks, META settlement / one-off tax), GOOGL's basis; RDDT, APP, NFLX equal GAAP; ORCL mixed but the Cloud median does not depend on it.
A64: SOTP: Services and Cloud CY2028E after-tax OI (driver-linked) | B64: $157.4B / $54.5B (base drivers) | C64: estimate | D64: 2, 37 | F64: Same earnings as the P/E leg's CY2028E EPS ($181.4B after tax / 12,423M = $14.60), split by segment: Services OI = (Search 319,092 + Services other 152,881) x 46% = 217,107; Cloud OI = 198,001 x 39% = 77,220 (segment_build FY2028). The capex-vintage depreciation above the H1-26 intensity (5.915% of revenue; FY2028 excess $38,958M) sits in Alphabet-level corporate_ebit in the set; here it is charged to the segments by revenue share (Services 471,973 / 669,973 = 70.4% -> 27,444; Cloud 29.6% -> 11,514), because the set's baseline depreciation is a flat % of every segment's revenue. After tax x 0.83: Services (217,107 - 27,444) x 0.83 = 157,420; Cloud (77,220 - 11,514) x 0.83 = 54,536. Alphabet-level -29,000 x 0.83 = -24,070 and Other Bets -7,800 x 0.83 = -6,474 complete the $181.4B.
A65: SOTP: Alphabet-level costs and Other Bets parts | B65: -$24,070M x 18.25x; -$6,474M x 20.8x | C65: estimate | D65: 2, 37 | F65: Alphabet-level costs FY2028 -$29.0B (set constant) x 0.83 at the Services multiple 18.25x (README spec). Other Bets FY2028 -$7.8B run-rate (H1-26 loss $3.899B x 2, 10-Q) x 0.83 at the P/E multiple 20.8x so the Waymo and Isomorphic add-backs (at 20.8x) cancel; their stakes stay in adjustments, not double counted. SpaceX and Anthropic stay in adjustments (equity level, both legs).
A66: Leg weights: P/E 0.5, SOTP 0.5 | B66: 0.5 / 0.5 (was P/E 0.6 / agents' cross-check 0.4) | C66: judgment | D66: 37 | F66: Kilian 2026-10-26 06:07Z: 'googl should have a p/e and sotp leg like amzn'; AMZN carries 0.425 / 0.425 (equal). Judgment, no evidence: an SOTP leg cannot be backtested without segment consensus (empirical-weights). The SOTP replaces the custom leg (mean of the 10-06 agents' SOTP/EV legs, $334.12, kept under replaced_custom_2026_10_26 for the record).
A68: # | B68: Source | C68: Date | D68: Link
A69: 1 | B69: Alphabet Q2 2026 earnings release (8-K Ex. 99.1) | C69: 2026-07-22 | D69: https://www.sec.gov/Archives/edgar/data/1652044/000165204426000066/googexhibit991q22026.htm
A70: 2 | B70: Alphabet Form 10-Q, quarter ended 2026-06-30 | C70: 2026-07-23 | D70: https://www.sec.gov/Archives/edgar/data/1652044/000165204426000071/goog-20260630.htm
A71: 3 | B71: SEC XBRL company facts, Alphabet (CIK 1652044) | C71: 2026-10-06 | D71: https://data.sec.gov/api/xbrl/companyfacts/CIK0001652044.json
A72: 4 | B72: EDGAR submissions, Alphabet (no 8-K since 2026-08-10) | C72: 2026-10-06 | D72: https://data.sec.gov/submissions/CIK0001652044.json
A73: 5 | B73: Alphabet Q2 2026 earnings call transcript (IR PDF) | C73: 2026-07-22 | D73: https://s206.q4cdn.com/479360582/files/doc_events/2026/Jul/22/2026_Q2_Earnings_Transcript.pdf
A74: 6 | B74: Alphabet 8-K: mandatory convertible preferred and capped calls | C74: 2026-06-05 | D74: https://www.sec.gov/Archives/edgar/data/1652044/000119312526259830/d36818d8k.htm
A75: 7 | B75: Alphabet announces date of Q3 2026 results call (Oct 28, 1:30pm PT) | C75: 2026-10-06 | D75: https://abc.xyz/investor/news/news-details/2026/Alphabet-Announces-Date-of-Third-Quarter-2026-Financial-Results-Conference-Call-2026-8tpGZsLS6v/default.aspx
A76: 8 | B76: Yahoo Finance GOOGL analysis (consensus EPS, trend) | C76: 2026-10-06 | D76: https://finance.yahoo.com/quote/GOOGL/analysis/
A77: 9 | B77: MarketScreener Alphabet finances (EPS, capex, FCF, EBIT, EBITDA consensus) | C77: 2026-10-06 | D77: https://www.marketscreener.com/quote/stock/ALPHABET-INC-24203373/finances/
A78: 10 | B78: Stock Analysis GOOGL forecast (close $347.68; 2027+ EPS behind 'Pro') | C78: 2026-10-06 | D78: https://stockanalysis.com/stocks/googl/forecast/
A79: 11 | B79: 24/7 Wall St: FY2027 EPS $14.4741 -> $15.1008 in 90 days | C79: 2026-10-05 | D79: https://247wallst.com/investing/2026/10/05/the-ai-boom-could-make-this-magnificent-7-stock-a-much-bigger-business/
A80: 12 | B80: Stock Analysis ORCL / CRM / RDDT forecasts (S&P Global adjusted EPS) | C80: 2026-10-06 | D80: https://stockanalysis.com/stocks/orcl/forecast/
... A127: 59 | B127: Nasdaq.com earnings-surprise, ORCL (Zacks reported EPS by quarter) | C127: 2026-10-26 | D127: https://api.nasdaq.com/api/company/ORCL/earnings-surprise
A129: Fact id | B129: Figure | C129: Value | D129: Filing
A130: F1 | B130: revenue FY ending 2023-12-31 (us-gaap:Revenues) | C130: 307394000000 | D130: https://www.sec.gov/Archives/edgar/data/1652044/000165204426000018/
A131: F2 | B131: revenue FY ending 2024-12-31 (us-gaap:Revenues) | C131: 350018000000 | D131: https://www.sec.gov/Archives/edgar/data/1652044/000165204426000018/
A132: F3 | B132: revenue FY ending 2025-12-31 (us-gaap:Revenues) | C132: 402836000000 | D132: https://www.sec.gov/Archives/edgar/data/1652044/000165204426000018/
A133: F4 | B133: revenue YTD 2026-01-01 to 2026-06-30 | C133: 229692000000 | D133: https://www.sec.gov/Archives/edgar/data/1652044/000165204426000071/
A134: F5 | B134: revenue prior-year YTD 2025-01-01 to 2025-06-30 | C134: 186662000000 | D134: https://www.sec.gov/Archives/edgar/data/1652044/000165204426000071/
A135: F6 | B135: revenue TTM to 2026-06-30 | C135: 445866000000
A136: F7 | B136: revenue quarter 2026-04-01 to 2026-06-30 | C136: 119796000000 | D136: https://www.sec.gov/Archives/edgar/data/1652044/000165204426000071/
A137: F8 | B137: operating_income FY ending 2023-12-31 (us-gaap:OperatingIncomeLoss) | C137: 84293000000 | D137: https://www.sec.gov/Archives/edgar/data/1652044/000165204426000018/
A138: F9 | B138: operating_income FY ending 2024-12-31 (us-gaap:OperatingIncomeLoss) | C138: 112390000000 | D138: https://www.sec.gov/Archives/edgar/data/1652044/000165204426000018/
A139: F10 | B139: operating_income FY ending 2025-12-31 (us-gaap:OperatingIncomeLoss) | C139: 129039000000 | D139: https://www.sec.gov/Archives/edgar/data/1652044/000165204426000018/
A140: F11 | B140: operating_income YTD 2026-01-01 to 2026-06-30 | C140: 80466000000 | D140: https://www.sec.gov/Archives/edgar/data/1652044/000165204426000071/
A141: F12 | B141: operating_income prior-year YTD 2025-01-01 to 2025-06-30 | C141: 61877000000 | D141: https://www.sec.gov/Archives/edgar/data/1652044/000165204426000071/
A142: F13 | B142: operating_income TTM to 2026-06-30 | C142: 147628000000
A143: F14 | B143: operating_income quarter 2026-04-01 to 2026-06-30 | C143: 40770000000 | D143: https://www.sec.gov/Archives/edgar/data/1652044/000165204426000071/
A144: F15 | B144: net_income FY ending 2023-12-31 (us-gaap:NetIncomeLoss) | C144: 73795000000 | D144: https://www.sec.gov/Archives/edgar/data/1652044/000165204426000018/
A145: F16 | B145: net_income FY ending 2024-12-31 (us-gaap:NetIncomeLoss) | C145: 100118000000 | D145: https://www.sec.gov/Archives/edgar/data/1652044/000165204426000018/
A146: F17 | B146: net_income FY ending 2025-12-31 (us-gaap:NetIncomeLoss) | C146: 132170000000 | D146: https://www.sec.gov/Archives/edgar/data/1652044/000165204426000018/
A147: F18 | B147: net_income YTD 2026-01-01 to 2026-06-30 | C147: 174771000000 | D147: https://www.sec.gov/Archives/edgar/data/1652044/000165204426000071/
A148: F19 | B148: net_income prior-year YTD 2025-01-01 to 2025-06-30 | C148: 62736000000 | D148: https://www.sec.gov/Archives/edgar/data/1652044/000165204426000071/
A149: F20 | B149: net_income TTM to 2026-06-30 | C149: 244205000000
...
