Workbook

Sheet Summary
A1: CRDO standard model (trial) · research run 2026-10-26
A2: The supervisor's reconciled assumption set as a live model. Trial: shown beside the blended page target, not used for trade levels until its weight is decided. Edit blue cells on Model (drivers) and Valuation (assumptions).
A3: Price target box | B3: Value
A4: Live price | B4: =IFERROR(GOOGLEFINANCE("CRDO","price"),Valuation!$B$67)
A5: Price as of | B5: =NOW()
A6: Model target (12-month median) | B6: =Distribution!$B$13
A7: Upside to model target from live price | B7: =B6/B4-1
A8: Research target (12m) (no scenario deltas) | B8: =Valuation!$D$7
A9: Probability-weighted mean | B9: =Distribution!$B$10
A10: 10th percentile | B10: =Distribution!$B$14
A11: 25th percentile | B11: =Distribution!$B$15
A12: 75th percentile | B12: =Distribution!$B$16
A13: 90th percentile | B13: =Distribution!$B$17
A14: Target date | B14: =Valuation!$B$45
A15: Price at the run | B15: =Valuation!$B$67
A16: Blended page target (options 67% + agents 33%, not live) | B16: 157.7201
A17: Supervisor research target (12m) (its own methods) | B17: 223
A18: Thesis break price (supervisor) | B18: 125
A19: Supervisor confidence | B19: low
A21: Key estimates | B21: FY2026A | C21: =Model!E5 | D21: =Model!F5
A22: Net sales | B22: =IF(Model!D24="","",Model!D24) | C22: =Model!E24 | D22: =Model!F24
A23: % YoY | B23: =IF(Model!D25="","",Model!D25) | C23: =Model!E25 | D23: =Model!F25
A24: Pretax margin | B24: =IF(Model!D35="","",Model!D35) | C24: =Model!E35 | D24: =Model!F35
A25: Diluted EPS (model) | B25: =IF(Model!D42="","",Model!D42) | C25: =Model!E42 | D25: =Model!F42
A26: % YoY | B26: =IF(Model!D43="","",Model!D43) | C26: =Model!E43 | D26: =Model!F43
A27: Free cash flow to firm | B27: =IF(Model!D52="","",Model!D52) | C27: =Model!E52 | D27: =Model!F52
A28: Consensus: EPS (consensus) | C28: 6.31
A29: Consensus: EPS (consensus) | D29: 9.7
A30: Consensus: EPS (consensus) | C30: 5.02
A31: Consensus: EPS (consensus) | D31: 8.3
A33: Valuation method | B33: Value per share | C33: Weight
A34: =Valuation!A4 | B34: =Valuation!D4 | C34: =Valuation!E4
A35: =Valuation!A5 | B35: =Valuation!D5 | C35: =Valuation!E5
A36: =Valuation!A6 | B36: =Valuation!D6 | C36: =Valuation!E6
A38: Scenario | B38: Probability | C38: Value at target date | D38: What has to happen
A39: =Distribution!A4 | B39: =Distribution!B4 | C39: =Distribution!C4 | D39: =Distribution!D4
A40: =Distribution!A5 | B40: =Distribution!B5 | C40: =Distribution!C5 | D40: =Distribution!D5
A41: =Distribution!A6 | B41: =Distribution!B6 | C41: =Distribution!C6 | D41: =Distribution!D6
A43: Price at target date | B43: Probability above
A44: =ROUND(Valuation!$B$67*0.7,0) | B44: =SUMPRODUCT(Distribution!$B$4:$B$6,1-NORMSDIST((LN(A44)-LN(Distribution!$C$4:$C$6))/Distribution!$B$9))
A45: =ROUND(Valuation!$B$67*0.8,0) | B45: =SUMPRODUCT(Distribution!$B$4:$B$6,1-NORMSDIST((LN(A45)-LN(Distribution!$C$4:$C$6))/Distribution!$B$9))
A46: =ROUND(Valuation!$B$67*0.9,0) | B46: =SUMPRODUCT(Distribution!$B$4:$B$6,1-NORMSDIST((LN(A46)-LN(Distribution!$C$4:$C$6))/Distribution!$B$9))
A47: =ROUND(Valuation!$B$67*1.0,0) | B47: =SUMPRODUCT(Distribution!$B$4:$B$6,1-NORMSDIST((LN(A47)-LN(Distribution!$C$4:$C$6))/Distribution!$B$9))
A48: =ROUND(Valuation!$B$67*1.1,0) | B48: =SUMPRODUCT(Distribution!$B$4:$B$6,1-NORMSDIST((LN(A48)-LN(Distribution!$C$4:$C$6))/Distribution!$B$9))
A49: =ROUND(Valuation!$B$67*1.2,0) | B49: =SUMPRODUCT(Distribution!$B$4:$B$6,1-NORMSDIST((LN(A49)-LN(Distribution!$C$4:$C$6))/Distribution!$B$9))
A50: =ROUND(Valuation!$B$67*1.3,0) | B50: =SUMPRODUCT(Distribution!$B$4:$B$6,1-NORMSDIST((LN(A50)-LN(Distribution!$C$4:$C$6))/Distribution!$B$9))
A51: =ROUND(Valuation!$B$67*1.5,0) | B51: =SUMPRODUCT(Distribution!$B$4:$B$6,1-NORMSDIST((LN(A51)-LN(Distribution!$C$4:$C$6))/Distribution!$B$9))
A53: Model checks | B53: Status
A54: Scenario probabilities sum to 100% | B54: =IF(ABS(Distribution!B8-1)<0.005,"ok","FLAG: "&TEXT(Distribution!B8,"0.0%"))
A55: WACC exceeds terminal growth by 1 point or more | B55: =IF('Calc - research target (12m)'!B55="ok","ok","FLAG")
A56: Projection runs a full year past the target date | B56: =IF('Calc - research target (12m)'!B56="ok","ok","FLAG")
A57: Method weights add up to more than zero | B57: =IF(SUM(Valuation!E4:E6)>0,"ok","FLAG")
A58: Terminal value under 85% of the DCF | B58: =IF('Calc - research target (12m)'!B46<0.85,"ok","note: "&TEXT('Calc - research target (12m)'!B46,"0%")&" of the DCF is terminal value")
A59: Segment base revenues tie to the last reported net sales (within 2%) | B59: =IF(ABS(Valuation!$B$90/Valuation!$B$50-1)<=0.02,"ok","FLAG")
A60: Matches the engine run at publication (target, research target (12m)) | B60: =IF(AND(ABS(Distribution!$B$13-218.6091)<0.01,ABS(Valuation!$D$7-223.0035)<0.01),"ok","inputs edited since publication")
A61: All checks | B61: =IF(COUNTIF(B54:B60,"ok")=7,"all ok",7-COUNTIF(B54:B60,"ok")&" to look at")

Sheet Model
A1: CRDO: annual model, base case
A2: (M of US dollars except per share; fiscal years named by the calendar year they end in)
A3: Blue = input · black = formula · green = link to another tab · actuals from SEC filings (fact ids in the last column, links on Sources)
A5: Fiscal year | B5: FY2024A | C5: FY2025A | D5: FY2026A | E5: FY2027E | F5: FY2028E | G5: FY2029E | H5: Source / note
A6: Period end | B6: 45409 | C6: 45780 | D6: 46144 | E6: =IF(DAY(Valuation!$B$49+1)=1,EOMONTH(Valuation!$B$49,12*E7),EDATE(Valuation!$B$49,12*E7)) | F6: =IF(DAY(Valuation!$B$49+1)=1,EOMONTH(Valuation!$B$49,12*F7),EDATE(Valuation!$B$49,12*F7)) | G6: =IF(DAY(Valuation!$B$49+1)=1,EOMONTH(Valuation!$B$49,12*G7),EDATE(Valuation!$B$49,12*G7))
A7: Projection year | B7: -2 | C7: -1 | D7: 0 | E7: 1 | F7: 2 | G7: 3
A10: Segment build (blue = input: revenue growth and EBIT margin by segment and year)
A11: Copper (AECs, electrical ICs, IP) | D11: =Valuation!$B$88 | E11: =Valuation!$B$88*(1+E12) | F11: =E11*(1+F12) | G11: =F11*(1+G12)
A12: Revenue growth | E12: 0.47438544 | F12: 0.473397 | G12: 0.23148148
A13: Segment EBIT | E13: =E11*E14 | F13: =F11*F14 | G13: =G11*G14
A14: EBIT margin | E14: 0.51800117 | F14: 0.51924896 | G14: 0.51665305
A15: Optical (DSPs, SiPh PICs, ZF optics, ALC) | D15: =Valuation!$B$89 | E15: =Valuation!$B$89*(1+E16) | F15: =E15*(1+F16) | G15: =F15*(1+G16)
A16: Revenue growth | E16: 9.3332967 | F16: 0.76 | G16: 0.30600426
A17: Segment EBIT | E17: =E15*E18 | F17: =F15*F18 | G17: =G15*G18
A18: EBIT margin | E18: 0.47800117 | F18: 0.46424896 | G18: 0.45665305
A19: Total segment revenue (= net sales) | D19: =D11+D15 | E19: =E11+E15 | F19: =F11+F15 | G19: =G11+G15 | H19: base revenues on Valuation (segment build); net sales = this total
A20: Total segment EBIT | E20: =E13+E17 | F20: =F13+F17 | G20: =G13+G17
A21: Corporate / unallocated EBIT (blue = input) | E21: 0 | F21: =E21 | G21: =F21 | H21: years[].corporate_ebit; EBIT = total segment EBIT + corporate
A23: Sales
A24: Net sales | B24: 192.97 | C24: 436.775 | D24: 1335.116 | E24: =E19 | F24: =F19 | G24: =G19 | H24: SEC XBRL F1, F2, F3
A25: % YoY | C25: =IF(OR(C24="",B24="",B24=0),"",C24/B24-1) | D25: =IF(OR(D24="",C24="",C24=0),"",D24/C24-1) | E25: =E24/Valuation!$B$50-1 | F25: =F24/E24-1 | G25: =G24/F24-1
A27: Operating profit
A28: EBIT (operating income) | E28: =E20+E21 | F28: =F20+F21 | G28: =G20+G21
A29: EBIT margin | E29: =E28/E24 | F29: =F28/F24 | G29: =G28/G24
A30: D&A | B30: 13.771 | C30: 21.938 | D30: 34.637 | E30: =E24*E64 | F30: =F24*F64 | G30: =G24*G64 | H30: SEC XBRL F34, F35, F36
A31: EBITDA | E31: =E28+E30 | F31: =F28+F30 | G31: =G28+G30
A32: EBITDA margin | E32: =E31/E24 | F32: =F31/F24 | G32: =G31/G24
A33: Net interest income / (expense) | E33: =-Valuation!$B$58*Valuation!$B$56 | F33: =-Valuation!$B$58*E58 | G33: =-Valuation!$B$58*F58 | H33: rate x prior year-end net debt (memo roll)
A34: Pretax income | B34: -22.745 | C34: 54.87 | D34: 475.435 | E34: =E28+E33 | F34: =F28+F33 | G34: =G28+G33 | H34: SEC XBRL F69, F70, F71
A35: Pretax margin | B35: =B34/B24 | C35: =C34/C24 | D35: =D34/D24 | E35: =E34/E24 | F35: =F34/F24 | G35: =G34/G24
A36: Income tax | B36: 5.624 | C36: 2.687 | D36: 3.156 | E36: =E34*E63 | F36: =F34*F63 | G36: =G34*G63 | H36: SEC XBRL F62, F63, F64
A37: Effective tax rate | B37: =B36/B34 | C37: =C36/C34 | D37: =D36/D34 | E37: =E36/E34 | F37: =F36/F34 | G37: =G36/G34
A38: Net income | B38: -28.369 | C38: 52.183 | D38: 472.279 | E38: =E34-E36 | F38: =F34-F36 | G38: =G34-G36 | H38: SEC XBRL F15, F16, F17
A39: % YoY | C39: =IF(OR(C38="",B38="",B38=0),"",C38/B38-1) | D39: =IF(OR(D38="",C38="",C38=0),"",D38/C38-1) | E39: =IF(OR(D38="",D38=0),"",E38/D38-1) | F39: =IF(OR(E38="",E38=0),"",F38/E38-1) | G39: =IF(OR(F38="",F38=0),"",G38/F38-1)
A40: Diluted shares (M, average) | B40: 155.091 | C40: 181.158 | D40: 188.232 | E40: =Valuation!$B$60*(1+Valuation!$B$62)^(E7-0.5-((Valuation!$B$61-Valuation!$B$49)/365.25)) | F40: =Valuation!$B$60*(1+Valuation!$B$62)^(F7-0.5-((Valuation!$B$61-Valuation!$B$49)/365.25)) | G40: =Valuation!$B$60*(1+Valuation!$B$62)^(G7-0.5-((Valuation!$B$61-Valuation!$B$49)/365.25)) | H40: diluted count rolled at the annual change to mid-year
A41: % YoY | C41: =IF(OR(C40="",B40="",B40=0),"",C40/B40-1) | D41: =IF(OR(D40="",C40="",C40=0),"",D40/C40-1) | E41: =IF(OR(D40="",D40=0),"",E40/D40-1) | F41: =IF(OR(E40="",E40=0),"",F40/E40-1) | G41: =IF(OR(F40="",F40=0),"",G40/F40-1)
A42: Diluted EPS | B42: -0.18 | C42: 0.29 | D42: 2.51 | E42: =E38/E40 | F42: =F38/F40 | G42: =G38/G40 | H42: SEC XBRL F22, F23, F24
A43: % YoY | C43: =IF(OR(C42="",B42="",B42=0),"",C42/B42-1) | D43: =IF(OR(D42="",C42="",C42=0),"",D42/C42-1) | E43: =IF(OR(D42="",D42=0),"",E42/D42-1) | F43: =IF(OR(E42="",E42=0),"",F42/E42-1) | G43: =IF(OR(F42="",F42=0),"",G42/F42-1)
A45: Cash flow
A46: NOPAT (EBIT x (1 - tax)) | E46: =E28*(1-E63) | F46: =F28*(1-F63) | G46: =G28*(1-G63)
A47: + D&A | B47: =B30 | C47: =C30 | D47: =D30 | E47: =E30 | F47: =F30 | G47: =G30
A48: - Capex | B48: 15.652 | C48: 36.061 | D48: 57.296 | E48: =E24*E65 | F48: =F24*F65 | G48: =G24*G65 | H48: SEC XBRL F55, F56, F57
A49: Capex % of sales | B49: =B48/B24 | C49: =C48/C24 | D49: =D48/D24 | E49: =E48/E24 | F49: =F48/F24 | G49: =G48/G24
A50: - Working capital increase | E50: =E66*(E24-Valuation!$B$50) | F50: =F66*(F24-E24) | G50: =G66*(G24-F24)
A51: - Stock comp (adjusted EBIT only) | E51: =IF(AND(Valuation!$B$47="adjusted",Valuation!$B$48="cost"),E55*(1-E63),0) | F51: =IF(AND(Valuation!$B$47="adjusted",Valuation!$B$48="cost"),F55*(1-F63),0) | G51: =IF(AND(Valuation!$B$47="adjusted",Valuation!$B$48="cost"),G55*(1-G63),0)
A52: Free cash flow to firm | E52: =E46+E47-E48-E50-E51 | F52: =F46+F47-F48-F50-F51 | G52: =G46+G47-G48-G50-G51 | H52: what the DCF discounts (Calc tabs)
A53: Operating cash flow (reported) | B53: 32.737 | C53: 65.083 | D53: 464.292 | H53: SEC XBRL F48, F49, F50
A54: FCF (operating cash flow - capex) | B54: =B53-B48 | C54: =C53-C48 | D54: =D53-D48
A55: Stock comp (memo) | B55: 39.022 | C55: 77.355 | D55: 182.638 | E55: =E24*E67 | F55: =F24*F67 | G55: =G24*G67 | H55: SEC XBRL F41, F42, F43
A56: Buybacks + dividends + other uses | E56: =E24*E69+E68+E70 | F56: =F24*F69+F68+F70 | G56: =G24*G69+G68+G70
A57: % of sales | B57: =B56/B24 | C57: =C56/C24 | D57: =D56/D24 | E57: =E56/E24 | F57: =F56/F24 | G57: =G56/G24
A58: Net debt / (net cash), year end (memo) | E58: =Valuation!$B$56-E52-E33*(1-E63)+E56 | F58: =E58-F52-F33*(1-F63)+F56 | G58: =F58-G52-G33*(1-G63)+G56 | H58: rolled from the balance-date figure; feeds interest only
A60: Drivers (blue = input; a year left black carries the prior year)
A61: Revenue growth | C61: =C25 | D61: =D25 | E61: =E25 | F61: =F25 | G61: =G25 | H61: implied by the segment build (edit the segment rows)
A62: EBIT margin | E62: =E29 | F62: =F29 | G62: =G29 | H62: implied by the segment build and corporate EBIT
A63: Tax rate | B63: =B37 | C63: =C37 | D63: =D37 | E63: 0.01 | F63: 0.15 | G63: 0.15
A64: D&A % revenue | B64: =B30/B24 | C64: =C30/C24 | D64: =D30/D24 | E64: 0.025 | F64: =E64 | G64: =F64
A65: Capex % revenue | B65: =B49 | C65: =C49 | D65: =D49 | E65: 0.04 | F65: =E65 | G65: =F65
A66: Working capital % of revenue increase | E66: 0.25 | F66: =E66 | G66: =F66
A67: Stock comp % revenue | B67: =B55/B24 | C67: =C55/C24 | D67: =D55/D24 | E67: 0.14 | F67: =E67 | G67: =F67
A68: Shareholder returns ($) | E68: 0 | F68: =E68 | G68: =F68
A69: Shareholder returns % revenue | B69: =B57 | C69: =C57 | D69: =D57 | E69: 0 | F69: =E69 | G69: =F69
A70: Other uses of cash ($: M&A, investments) | E70: 102.4 | F70: 0 | G70: =F70
A71: Adj. EBITDA addback % revenue | E71: 0 | F71: =E71 | G71: =F71
A73: Versus company guidance and street consensus
A74: Guidance: revenue growth (GAAP revenue y/y), midpoint | E74: 0.85 | H74: as of 2026-09-01; source 22 (Credo (CRDO) Q1 FY2027 earnings call transcript (Motley Fool)
A75: Model vs guidance midpoint | E75: =(E25-E74)*10000
A76: Guidance: optical revenue ($M), midpoint | E76: 600 | H76: as of 2026-09-01; source 22 (Credo (CRDO) Q1 FY2027 earnings call transcript (Motley Fool)
A77: Guidance: non-GAAP operating expense growth (non-GAAP), midpoint | E77: =AVERAGE(0.55,0.55) | H77: 0.55 to 0.55; as of 2026-09-01; source 22 (Credo (CRDO) Q1 FY2027 earnings call transcript (Motley Fool)
A78: Guidance: non-GAAP net margin (non-GAAP), midpoint | E78: =AVERAGE(0.5,0.5) | H78: 0.5 to 0.5; as of 2026-09-01; source 22 (Credo (CRDO) Q1 FY2027 earnings call transcript (Motley Fool)
A79: Consensus: revenue (consensus) | E79: 2500 | H79: as of 2026-10-26; source 3 (CRDO Stock Forecast & Price Targets - StockAnalysis (S&P Glo)
A80: Model vs consensus | E80: =E24/E79-1
A81: Consensus: EPS non-GAAP (consensus) | E81: 6.31 | H81: as of 2026-10-26; source 3 (CRDO Stock Forecast & Price Targets - StockAnalysis (S&P Glo)
A82: Consensus: revenue (consensus) | F82: 3880 | H82: as of 2026-10-26; source 3 (CRDO Stock Forecast & Price Targets - StockAnalysis (S&P Glo)
A83: Model vs consensus | F83: =F24/F82-1
A84: Consensus: EPS non-GAAP (consensus) | F84: 9.7 | H84: as of 2026-09-21; source 1 (Credo Technology Crashed for 3 Months: This Wall Street Pro )
A85: Consensus: EPS (Zacks) (consensus) | E85: 5.02 | H85: as of 2026-10-26; source 28 (Nasdaq.com analyst earnings forecast for CRDO (Zacks consens)
A86: Consensus: EPS (Zacks) (consensus) | F86: 8.3 | H86: as of 2026-10-26; source 28 (Nasdaq.com analyst earnings forecast for CRDO (Zacks consens)

Sheet Valuation
A1: CRDO: valuation and price target derivation
A2: Value per share at the target date = weighted methods below; the 12-month target is the median of the scenario mix (Distribution tab).
A3: Method | B3: Multiple | C3: Metric at target date | D3: Value per share | E3: Weight | F3: Contribution
A4: ='Calc - research target (12m)'!A67 | B4: =IF('Calc - research target (12m)'!C67="","",'Calc - research target (12m)'!C67) | C4: =IF('Calc - research target (12m)'!I67="","",'Calc - research target (12m)'!I67) | D4: ='Calc - research target (12m)'!F67 | E4: ='Calc - research target (12m)'!G67 | F4: =D4*E4/SUM($E$4:$E$6)
A5: ='Calc - research target (12m)'!A68 | B5: =IF('Calc - research target (12m)'!C68="","",'Calc - research target (12m)'!C68) | C5: =IF('Calc - research target (12m)'!I68="","",'Calc - research target (12m)'!I68) | D5: ='Calc - research target (12m)'!F68 | E5: ='Calc - research target (12m)'!G68 | F5: =D5*E5/SUM($E$4:$E$6)
A6: ='Calc - research target (12m)'!A69 | B6: =IF('Calc - research target (12m)'!C69="","",'Calc - research target (12m)'!C69) | C6: =IF('Calc - research target (12m)'!I69="","",'Calc - research target (12m)'!I69) | D6: ='Calc - research target (12m)'!F69 | E6: ='Calc - research target (12m)'!G69 | F6: =D6*E6/SUM($E$4:$E$6)
A7: Research target (12m) per share | D7: ='Calc - research target (12m)'!$F$70 | F7: =SUM(F4:F6)
A9: 12-month EPS basis (what the P/E is applied to)
A10: Fiscal year | B10: =Model!E5 | C10: =Model!F5 | D10: =Model!G5
A11: Share of the 12 months after the target date | B11: ='Calc - research target (12m)'!C38 | C11: ='Calc - research target (12m)'!D38 | D11: ='Calc - research target (12m)'!E38
A12: Model EPS (Model tab) | B12: =Model!E42 | C12: =Model!F42 | D12: =Model!G42
A13: Model EPS, next 12 months after the target date | B13: =SUMPRODUCT(B11:D11,B12:D12)
A16: DCF build (free cash flow to firm, discounted to the target date)
A17: Fiscal year | B17: =Model!E5 | C17: =Model!F5 | D17: =Model!G5
A18: Free cash flow to firm | B18: ='Calc - research target (12m)'!C31 | C18: ='Calc - research target (12m)'!D31 | D18: ='Calc - research target (12m)'!E31
A19: Share of the year after the target date | B19: ='Calc - research target (12m)'!C35 | C19: ='Calc - research target (12m)'!D35 | D19: ='Calc - research target (12m)'!E35
A20: PV at target date | B20: ='Calc - research target (12m)'!C36 | C20: ='Calc - research target (12m)'!D36 | D20: ='Calc - research target (12m)'!E36
A22: PV of free cash flow after the target date | B22: ='Calc - research target (12m)'!B42
A23: Terminal value (final year) | B23: ='Calc - research target (12m)'!B43
A24: PV of terminal value | B24: ='Calc - research target (12m)'!B44
A25: Enterprise value at target date | B25: ='Calc - research target (12m)'!B45
A26: Terminal value share of DCF | B26: ='Calc - research target (12m)'!B46
A27: Net debt at target date | B27: ='Calc - research target (12m)'!B50
A28: Minority interests | B28: ='Calc - research target (12m)'!B51
A29: Adjustments | B29: ='Calc - research target (12m)'!B52
A30: Diluted shares at target date (M) | B30: ='Calc - research target (12m)'!B53
A31: DCF value per share | B31: ='Calc - research target (12m)'!F67
A32: WACC | B32: ='Calc - research target (12m)'!B12
A42: Assumptions (blue = input; sources on the Sources tab)
A43: Input | B43: Value | C43: Basis / note
A44: Run date (valuation as of) | B44: 46321
A45: Target date (run date + 365 days) | B45: =B44+365 | C45: 12-month horizon
A46: Money unit | B46: $M
A47: EBIT basis (gaap / adjusted) | B47: adjusted | C47: gaap = after stock comp
A48: Stock comp treatment (cost / dilution) | B48: dilution | C48: used only when EBIT is adjusted
A49: Last reported fiscal year end | B49: 46144
A50: Net sales, last reported year ($M) | B50: 1335.116
A51: WACC | B51: 0.1 | C51: not used: no DCF leg (Kilian 2026-10-21); a placeholder so the DCF block still computes
A52: Terminal method (gordon / exit_multiple / steady_state) | B52: gordon
A53: Terminal growth | B53: 0.02
A54: Exit EV/EBITDA (exit_multiple only)
A55: Balance-sheet date | B55: 46235
A56: Net debt / (net cash) at balance date ($M) | B56: -764.3 | C56: excludes operating leases
A57: Minority interests + preferred stock | B57: 0
A58: Interest rate on net debt / cash | B58: 0.04
A59: Net debt at target date (override; blank = bridge)
A60: Diluted shares (M) | B60: 200
A61: Share count date | B61: 46326
A62: Annual change in diluted shares | B62: 0.015 | C62: net of buybacks and stock-comp dilution
A63: Shares at target date (override; blank = from annual change)
A64: DCF weight | B64: 0 | C64: Kilian 2026-10-21: 0 unless the name has a DCF leg (dcf_policy)
A65: Sum-of-the-parts weight | B65: 0
A66: Spread within each scenario (lognormal vol) | B66: 0.25
A67: Share price at the run | B67: 151.15 | C67: close used by the run (2026-10-26)
A69: Target multiple | B69: Multiple | C69: Weight | D69: Basis (ntm / ltm) | E69: EBITDA basis | F69: Stated EPS | G69: Stated FCF/share | H69: Levered | I69: Peer basis
A70: P/E | B70: 23.5 | C70: 0.7 | D70: ntm | E70: gaap | H70: TRUE | I70: Agents' median 23.5x (21-24x) NTM; 32% below the 34.5x median P/E NTM of 11 filing-based peers (peers.md: ALAB 70.9, MRVL 50.3, ANET 40.7, LITE 38.2, MTSI 36.7, CIEN 34.5, RMBS 32.8 thin, AAOI 31.7 thin, COHR 24.1, AVGO 20.5, FN 18.0; 36.7x without the two thin-coverage names). Discount for a 43%-of-revenue direct customer, 84% top-4 concentration, Marvell 1.6T AEC competition and growth slowing to ~30% after FY28. EPS = model NOPAT (non-GAAP EBIT after tax, 15% minimum tax from FY28) / shares, driver-linked.
A71: EV/sales | B71: 11 | C71: 0.3 | D71: ntm | E71: gaap | H71: TRUE | I71: Agents' median 11x (9-11.5x) NTM sales. Cross-check only: peers.py has no NTM revenue consensus for the peers (EPS-only snapshots), so no peer median on this basis; flagged.
A73: Segment (sum of the parts) | B73: NTM metric | C73: Metric | D73: Multiple | E73: Note
A74: none
A76: Adjustment (equity level) | B76: Value | C76: Probability | D76: Note
A77: none
A79: Custom method | B79: Value per share | C79: Weight | D79: Explanation
A80: none
A82: Scenario | B82: Probability | C82: Growth Δ | D82: Margin Δ | E82: Multiple Δ (turns) | F82: WACC Δ | G82: Multiple %Δ (FCF yield, segments) | H82: Stated EPS/FCF %Δ | I82: Custom methods %Δ | J82: Story
A83: bear | B83: 0.25 | E83: -8 | J83: Agents 1-5 bear (probabilities 0.25-0.33, median 0.25; values $100-120, median $110): the top end customer (33%; likely Amazon Trainium, the 43% direct customer) dual-sources 1.6T AECs to Marvell at 15-20% lower prices and/or hyperscalers digest 2027 capex; the H2 FY27 ramp slips. Restated as drivers: top_customer_pct 0.33 -> 0.21 (add -0.12: that customer's revenue -46%, total -15.2%, the rest unchanged), copper_tam and optical_tam -10% (capex digestion), gm_copper and gm_optical -3pt (agent_2: 62-64%); P/E -8 turns to 15.5x (agents 14-18x). | K83: driver deltas: top_customer_pct -0.12; copper_tam -0.1 %; optical_tam -0.1 %; gm_copper -0.03; gm_optical -0.03
A84: base | B84: 0.5 | J84: Copper = Big-4 capex x 0.60% attach x Credo share (42.7%, held FY28-29); optical = LightCounting AI-cluster optics ($36.3B / $63.9B / $83.4B) x 1.708%; top customer held at 33%. Revenue $2,500M / $3,861M / $4,836M (optical $620M / $1,091M / $1,425M); blended GM 68.0% / 66.9% / 66.2%; opex $430M / $640M / $790M; 15% minimum tax from FY28; 23.5x NTM EPS / 11x NTM sales.
A85: bull | B85: 0.25 | E85: 3.5 | J85: Agents 1-5 bull (probabilities 0.22-0.25; values $345-380): Amazon Trn3 ramps strongly, Microsoft/Meta/Oracle and neoclouds broaden the base (3-4 customers >10%), optics pass a $1B run-rate, ALC/OmniConnect start; hyperscaler 2027 capex ~$1.2-1.3T. Restated: optical_share +15% (FY28 optical ~$1.4B), copper_share +5% (Credo holds 1.6T share), top_customer_pct +0.02 (Trn3: that customer +10%, total +3.1%), copper_tam and optical_tam +10%, gm +0.5pt both; P/E +3.5 turns to 27x. | K85: driver deltas: top_customer_pct +0.02; copper_tam +0.1 %; optical_tam +0.1 %; copper_share +0.05 %; optical_share +0.15 %; gm_copper +0.005; gm_optical +0.005
A87: Segment build (segment_build) | B87: Base revenue ($M) | C87: Driver note (growth and EBIT margin by year: Model tab)
A88: Copper (AECs, electrical ICs, IP) | B88: 1275.116 | C88: revenue = copper_tam ($B) x copper_share x 1000 x 0.67 / (1 - top_customer_pct); EBIT = revenue x gm_copper - opex x copper share of driven revenue
A89: Optical (DSPs, SiPh PICs, ZF optics, ALC) | B89: 60 | C89: revenue = optical_tam ($B) x optical_share x 1000 x 0.67 / (1 - top_customer_pct); EBIT = revenue x gm_optical - opex x optical share of driven revenue
A90: Sum of segment base revenues | B90: =SUM(B88:B89) | C90: =IF(ABS(B90/Valuation!$B$50-1)<=0.02,"ties to the last reported net sales (within 2%)","FLAG: does not tie to the last reported net sales")

Sheet Sensitivity
A1: CRDO: sensitivity tables (bold = current inputs; every cell recalculates from the live model)
A3: DCF value per share: WACC (down) x terminal growth (across)
A4: WACC \ growth | B4: =Valuation!$B$53+(-0.01) | C4: =Valuation!$B$53+(-0.005) | D4: =Valuation!$B$53+(0) | E4: =Valuation!$B$53+(0.005) | F4: =Valuation!$B$53+(0.01)
A5: =Valuation!$B$51+(-0.01) | B5: =IF($A5-B$4<=0.01,"n/a",((SUMPRODUCT('Calc - research target (12m)'!$C$31:$E$31,'Calc - research target (12m)'!$C$35:$E$35,(1+$A5)^(-('Calc - research target (12m)'!$C$19:$E$19-'Calc - research target (12m)'!$B$13)))+'Calc - research target (12m)'!$E$31*(1+B$4)/($A5-B$4)/(1+$A5)^('Calc - research target (12m)'!$B$16-'Calc - research target (12m)'!$B$13))-'Calc - research target (12m)'!$B$50-'Calc - research target (12m)'!$B$51+'Calc - research target (12m)'!$B$52)/'Calc - research target (12m)'!$B$53) | C5: =IF($A5-C$4<=0.01,"n/a",((SUMPRODUCT('Calc - research target (12m)'!$C$31:$E$31,'Calc - research target (12m)'!$C$35:$E$35,(1+$A5)^(-('Calc - research target (12m)'!$C$19:$E$19-'Calc - research target (12m)'!$B$13)))+'Calc - research target (12m)'!$E$31*(1+C$4)/($A5-C$4)/(1+$A5)^('Calc - research target (12m)'!$B$16-'Calc - research target (12m)'!$B$13))-'Calc - research target (12m)'!$B$50-'Calc - research target (12m)'!$B$51+'Calc - research target (12m)'!$B$52)/'Calc - research target (12m)'!$B$53) | D5: =IF($A5-D$4<=0.01,"n/a",((SUMPRODUCT('Calc - research target (12m)'!$C$31:$E$31,'Calc - research target (12m)'!$C$35:$E$35,(1+$A5)^(-('Calc - research target (12m)'!$C$19:$E$19-'Calc - research target (12m)'!$B$13)))+'Calc - research target (12m)'!$E$31*(1+D$4)/($A5-D$4)/(1+$A5)^('Calc - research target (12m)'!$B$16-'Calc - research target (12m)'!$B$13))-'Calc - research target (12m)'!$B$50-'Calc - research target (12m)'!$B$51+'Calc - research target (12m)'!$B$52)/'Calc - research target (12m)'!$B$53) | E5: =IF($A5-E$4<=0.01,"n/a",((SUMPRODUCT('Calc - research target (12m)'!$C$31:$E$31,'Calc - research target (12m)'!$C$35:$E$35,(1+$A5)^(-('Calc - research target (12m)'!$C$19:$E$19-'Calc - research target (12m)'!$B$13)))+'Calc - research target (12m)'!$E$31*(1+E$4)/($A5-E$4)/(1+$A5)^('Calc - research target (12m)'!$B$16-'Calc - research target (12m)'!$B$13))-'Calc - research target (12m)'!$B$50-'Calc - research target (12m)'!$B$51+'Calc - research target (12m)'!$B$52)/'Calc - research target (12m)'!$B$53) | F5: =IF($A5-F$4<=0.01,"n/a",((SUMPRODUCT('Calc - research target (12m)'!$C$31:$E$31,'Calc - research target (12m)'!$C$35:$E$35,(1+$A5)^(-('Calc - research target (12m)'!$C$19:$E$19-'Calc - research target (12m)'!$B$13)))+'Calc - research target (12m)'!$E$31*(1+F$4)/($A5-F$4)/(1+$A5)^('Calc - research target (12m)'!$B$16-'Calc - research target (12m)'!$B$13))-'Calc - research target (12m)'!$B$50-'Calc - research target (12m)'!$B$51+'Calc - research target (12m)'!$B$52)/'Calc - research target (12m)'!$B$53)
A6: =Valuation!$B$51+(-0.005) | B6: =IF($A6-B$4<=0.01,"n/a",((SUMPRODUCT('Calc - research target (12m)'!$C$31:$E$31,'Calc - research target (12m)'!$C$35:$E$35,(1+$A6)^(-('Calc - research target (12m)'!$C$19:$E$19-'Calc - research target (12m)'!$B$13)))+'Calc - research target (12m)'!$E$31*(1+B$4)/($A6-B$4)/(1+$A6)^('Calc - research target (12m)'!$B$16-'Calc - research target (12m)'!$B$13))-'Calc - research target (12m)'!$B$50-'Calc - research target (12m)'!$B$51+'Calc - research target (12m)'!$B$52)/'Calc - research target (12m)'!$B$53) | C6: =IF($A6-C$4<=0.01,"n/a",((SUMPRODUCT('Calc - research target (12m)'!$C$31:$E$31,'Calc - research target (12m)'!$C$35:$E$35,(1+$A6)^(-('Calc - research target (12m)'!$C$19:$E$19-'Calc - research target (12m)'!$B$13)))+'Calc - research target (12m)'!$E$31*(1+C$4)/($A6-C$4)/(1+$A6)^('Calc - research target (12m)'!$B$16-'Calc - research target (12m)'!$B$13))-'Calc - research target (12m)'!$B$50-'Calc - research target (12m)'!$B$51+'Calc - research target (12m)'!$B$52)/'Calc - research target (12m)'!$B$53) | D6: =IF($A6-D$4<=0.01,"n/a",((SUMPRODUCT('Calc - research target (12m)'!$C$31:$E$31,'Calc - research target (12m)'!$C$35:$E$35,(1+$A6)^(-('Calc - research target (12m)'!$C$19:$E$19-'Calc - research target (12m)'!$B$13)))+'Calc - research target (12m)'!$E$31*(1+D$4)/($A6-D$4)/(1+$A6)^('Calc - research target (12m)'!$B$16-'Calc - research target (12m)'!$B$13))-'Calc - research target (12m)'!$B$50-'Calc - research target (12m)'!$B$51+'Calc - research target (12m)'!$B$52)/'Calc - research target (12m)'!$B$53) | E6: =IF($A6-E$4<=0.01,"n/a",((SUMPRODUCT('Calc - research target (12m)'!$C$31:$E$31,'Calc - research target (12m)'!$C$35:$E$35,(1+$A6)^(-('Calc - research target (12m)'!$C$19:$E$19-'Calc - research target (12m)'!$B$13)))+'Calc - research target (12m)'!$E$31*(1+E$4)/($A6-E$4)/(1+$A6)^('Calc - research target (12m)'!$B$16-'Calc - research target (12m)'!$B$13))-'Calc - research target (12m)'!$B$50-'Calc - research target (12m)'!$B$51+'Calc - research target (12m)'!$B$52)/'Calc - research target (12m)'!$B$53) | F6: =IF($A6-F$4<=0.01,"n/a",((SUMPRODUCT('Calc - research target (12m)'!$C$31:$E$31,'Calc - research target (12m)'!$C$35:$E$35,(1+$A6)^(-('Calc - research target (12m)'!$C$19:$E$19-'Calc - research target (12m)'!$B$13)))+'Calc - research target (12m)'!$E$31*(1+F$4)/($A6-F$4)/(1+$A6)^('Calc - research target (12m)'!$B$16-'Calc - research target (12m)'!$B$13))-'Calc - research target (12m)'!$B$50-'Calc - research target (12m)'!$B$51+'Calc - research target (12m)'!$B$52)/'Calc - research target (12m)'!$B$53)
A7: =Valuation!$B$51+(0) | B7: =IF($A7-B$4<=0.01,"n/a",((SUMPRODUCT('Calc - research target (12m)'!$C$31:$E$31,'Calc - research target (12m)'!$C$35:$E$35,(1+$A7)^(-('Calc - research target (12m)'!$C$19:$E$19-'Calc - research target (12m)'!$B$13)))+'Calc - research target (12m)'!$E$31*(1+B$4)/($A7-B$4)/(1+$A7)^('Calc - research target (12m)'!$B$16-'Calc - research target (12m)'!$B$13))-'Calc - research target (12m)'!$B$50-'Calc - research target (12m)'!$B$51+'Calc - research target (12m)'!$B$52)/'Calc - research target (12m)'!$B$53) | C7: =IF($A7-C$4<=0.01,"n/a",((SUMPRODUCT('Calc - research target (12m)'!$C$31:$E$31,'Calc - research target (12m)'!$C$35:$E$35,(1+$A7)^(-('Calc - research target (12m)'!$C$19:$E$19-'Calc - research target (12m)'!$B$13)))+'Calc - research target (12m)'!$E$31*(1+C$4)/($A7-C$4)/(1+$A7)^('Calc - research target (12m)'!$B$16-'Calc - research target (12m)'!$B$13))-'Calc - research target (12m)'!$B$50-'Calc - research target (12m)'!$B$51+'Calc - research target (12m)'!$B$52)/'Calc - research target (12m)'!$B$53) | D7: =IF($A7-D$4<=0.01,"n/a",((SUMPRODUCT('Calc - research target (12m)'!$C$31:$E$31,'Calc - research target (12m)'!$C$35:$E$35,(1+$A7)^(-('Calc - research target (12m)'!$C$19:$E$19-'Calc - research target (12m)'!$B$13)))+'Calc - research target (12m)'!$E$31*(1+D$4)/($A7-D$4)/(1+$A7)^('Calc - research target (12m)'!$B$16-'Calc - research target (12m)'!$B$13))-'Calc - research target (12m)'!$B$50-'Calc - research target (12m)'!$B$51+'Calc - research target (12m)'!$B$52)/'Calc - research target (12m)'!$B$53) | E7: =IF($A7-E$4<=0.01,"n/a",((SUMPRODUCT('Calc - research target (12m)'!$C$31:$E$31,'Calc - research target (12m)'!$C$35:$E$35,(1+$A7)^(-('Calc - research target (12m)'!$C$19:$E$19-'Calc - research target (12m)'!$B$13)))+'Calc - research target (12m)'!$E$31*(1+E$4)/($A7-E$4)/(1+$A7)^('Calc - research target (12m)'!$B$16-'Calc - research target (12m)'!$B$13))-'Calc - research target (12m)'!$B$50-'Calc - research target (12m)'!$B$51+'Calc - research target (12m)'!$B$52)/'Calc - research target (12m)'!$B$53) | F7: =IF($A7-F$4<=0.01,"n/a",((SUMPRODUCT('Calc - research target (12m)'!$C$31:$E$31,'Calc - research target (12m)'!$C$35:$E$35,(1+$A7)^(-('Calc - research target (12m)'!$C$19:$E$19-'Calc - research target (12m)'!$B$13)))+'Calc - research target (12m)'!$E$31*(1+F$4)/($A7-F$4)/(1+$A7)^('Calc - research target (12m)'!$B$16-'Calc - research target (12m)'!$B$13))-'Calc - research target (12m)'!$B$50-'Calc - research target (12m)'!$B$51+'Calc - research target (12m)'!$B$52)/'Calc - research target (12m)'!$B$53)
A8: =Valuation!$B$51+(0.005) | B8: =IF($A8-B$4<=0.01,"n/a",((SUMPRODUCT('Calc - research target (12m)'!$C$31:$E$31,'Calc - research target (12m)'!$C$35:$E$35,(1+$A8)^(-('Calc - research target (12m)'!$C$19:$E$19-'Calc - research target (12m)'!$B$13)))+'Calc - research target (12m)'!$E$31*(1+B$4)/($A8-B$4)/(1+$A8)^('Calc - research target (12m)'!$B$16-'Calc - research target (12m)'!$B$13))-'Calc - research target (12m)'!$B$50-'Calc - research target (12m)'!$B$51+'Calc - research target (12m)'!$B$52)/'Calc - research target (12m)'!$B$53) | C8: =IF($A8-C$4<=0.01,"n/a",((SUMPRODUCT('Calc - research target (12m)'!$C$31:$E$31,'Calc - research target (12m)'!$C$35:$E$35,(1+$A8)^(-('Calc - research target (12m)'!$C$19:$E$19-'Calc - research target (12m)'!$B$13)))+'Calc - research target (12m)'!$E$31*(1+C$4)/($A8-C$4)/(1+$A8)^('Calc - research target (12m)'!$B$16-'Calc - research target (12m)'!$B$13))-'Calc - research target (12m)'!$B$50-'Calc - research target (12m)'!$B$51+'Calc - research target (12m)'!$B$52)/'Calc - research target (12m)'!$B$53) | D8: =IF($A8-D$4<=0.01,"n/a",((SUMPRODUCT('Calc - research target (12m)'!$C$31:$E$31,'Calc - research target (12m)'!$C$35:$E$35,(1+$A8)^(-('Calc - research target (12m)'!$C$19:$E$19-'Calc - research target (12m)'!$B$13)))+'Calc - research target (12m)'!$E$31*(1+D$4)/($A8-D$4)/(1+$A8)^('Calc - research target (12m)'!$B$16-'Calc - research target (12m)'!$B$13))-'Calc - research target (12m)'!$B$50-'Calc - research target (12m)'!$B$51+'Calc - research target (12m)'!$B$52)/'Calc - research target (12m)'!$B$53) | E8: =IF($A8-E$4<=0.01,"n/a",((SUMPRODUCT('Calc - research target (12m)'!$C$31:$E$31,'Calc - research target (12m)'!$C$35:$E$35,(1+$A8)^(-('Calc - research target (12m)'!$C$19:$E$19-'Calc - research target (12m)'!$B$13)))+'Calc - research target (12m)'!$E$31*(1+E$4)/($A8-E$4)/(1+$A8)^('Calc - research target (12m)'!$B$16-'Calc - research target (12m)'!$B$13))-'Calc - research target (12m)'!$B$50-'Calc - research target (12m)'!$B$51+'Calc - research target (12m)'!$B$52)/'Calc - research target (12m)'!$B$53) | F8: =IF($A8-F$4<=0.01,"n/a",((SUMPRODUCT('Calc - research target (12m)'!$C$31:$E$31,'Calc - research target (12m)'!$C$35:$E$35,(1+$A8)^(-('Calc - research target (12m)'!$C$19:$E$19-'Calc - research target (12m)'!$B$13)))+'Calc - research target (12m)'!$E$31*(1+F$4)/($A8-F$4)/(1+$A8)^('Calc - research target (12m)'!$B$16-'Calc - research target (12m)'!$B$13))-'Calc - research target (12m)'!$B$50-'Calc - research target (12m)'!$B$51+'Calc - research target (12m)'!$B$52)/'Calc - research target (12m)'!$B$53)
A9: =Valuation!$B$51+(0.01) | B9: =IF($A9-B$4<=0.01,"n/a",((SUMPRODUCT('Calc - research target (12m)'!$C$31:$E$31,'Calc - research target (12m)'!$C$35:$E$35,(1+$A9)^(-('Calc - research target (12m)'!$C$19:$E$19-'Calc - research target (12m)'!$B$13)))+'Calc - research target (12m)'!$E$31*(1+B$4)/($A9-B$4)/(1+$A9)^('Calc - research target (12m)'!$B$16-'Calc - research target (12m)'!$B$13))-'Calc - research target (12m)'!$B$50-'Calc - research target (12m)'!$B$51+'Calc - research target (12m)'!$B$52)/'Calc - research target (12m)'!$B$53) | C9: =IF($A9-C$4<=0.01,"n/a",((SUMPRODUCT('Calc - research target (12m)'!$C$31:$E$31,'Calc - research target (12m)'!$C$35:$E$35,(1+$A9)^(-('Calc - research target (12m)'!$C$19:$E$19-'Calc - research target (12m)'!$B$13)))+'Calc - research target (12m)'!$E$31*(1+C$4)/($A9-C$4)/(1+$A9)^('Calc - research target (12m)'!$B$16-'Calc - research target (12m)'!$B$13))-'Calc - research target (12m)'!$B$50-'Calc - research target (12m)'!$B$51+'Calc - research target (12m)'!$B$52)/'Calc - research target (12m)'!$B$53) | D9: =IF($A9-D$4<=0.01,"n/a",((SUMPRODUCT('Calc - research target (12m)'!$C$31:$E$31,'Calc - research target (12m)'!$C$35:$E$35,(1+$A9)^(-('Calc - research target (12m)'!$C$19:$E$19-'Calc - research target (12m)'!$B$13)))+'Calc - research target (12m)'!$E$31*(1+D$4)/($A9-D$4)/(1+$A9)^('Calc - research target (12m)'!$B$16-'Calc - research target (12m)'!$B$13))-'Calc - research target (12m)'!$B$50-'Calc - research target (12m)'!$B$51+'Calc - research target (12m)'!$B$52)/'Calc - research target (12m)'!$B$53) | E9: =IF($A9-E$4<=0.01,"n/a",((SUMPRODUCT('Calc - research target (12m)'!$C$31:$E$31,'Calc - research target (12m)'!$C$35:$E$35,(1+$A9)^(-('Calc - research target (12m)'!$C$19:$E$19-'Calc - research target (12m)'!$B$13)))+'Calc - research target (12m)'!$E$31*(1+E$4)/($A9-E$4)/(1+$A9)^('Calc - research target (12m)'!$B$16-'Calc - research target (12m)'!$B$13))-'Calc - research target (12m)'!$B$50-'Calc - research target (12m)'!$B$51+'Calc - research target (12m)'!$B$52)/'Calc - research target (12m)'!$B$53) | F9: =IF($A9-F$4<=0.01,"n/a",((SUMPRODUCT('Calc - research target (12m)'!$C$31:$E$31,'Calc - research target (12m)'!$C$35:$E$35,(1+$A9)^(-('Calc - research target (12m)'!$C$19:$E$19-'Calc - research target (12m)'!$B$13)))+'Calc - research target (12m)'!$E$31*(1+F$4)/($A9-F$4)/(1+$A9)^('Calc - research target (12m)'!$B$16-'Calc - research target (12m)'!$B$13))-'Calc - research target (12m)'!$B$50-'Calc - research target (12m)'!$B$51+'Calc - research target (12m)'!$B$52)/'Calc - research target (12m)'!$B$53)
A11: Research target (12m) per share: P/E multiple (down) x metric at target date (across)
A12: Multiple \ metric | B12: ='Calc - research target (12m)'!$E$68*0.9 | C12: ='Calc - research target (12m)'!$E$68*0.95 | D12: ='Calc - research target (12m)'!$E$68*1.0 | E12: ='Calc - research target (12m)'!$E$68*1.05 | F12: ='Calc - research target (12m)'!$E$68*1.1
A13: =Valuation!$B$70+(-3) | B13: =((SUMPRODUCT('Calc - research target (12m)'!$F$67:$F$69,'Calc - research target (12m)'!$G$67:$G$69)-'Calc - research target (12m)'!$F$68*'Calc - research target (12m)'!$G$68)+'Calc - research target (12m)'!$G$68*($A13*(B$12-'Calc - research target (12m)'!$B$54)/'Calc - research target (12m)'!$B$53+'Calc - research target (12m)'!$B$52/'Calc - research target (12m)'!$B$53))/SUM('Calc - research target (12m)'!$G$67:$G$69) | C13: =((SUMPRODUCT('Calc - research target (12m)'!$F$67:$F$69,'Calc - research target (12m)'!$G$67:$G$69)-'Calc - research target (12m)'!$F$68*'Calc - research target (12m)'!$G$68)+'Calc - research target (12m)'!$G$68*($A13*(C$12-'Calc - research target (12m)'!$B$54)/'Calc - research target (12m)'!$B$53+'Calc - research target (12m)'!$B$52/'Calc - research target (12m)'!$B$53))/SUM('Calc - research target (12m)'!$G$67:$G$69) | D13: =((SUMPRODUCT('Calc - research target (12m)'!$F$67:$F$69,'Calc - research target (12m)'!$G$67:$G$69)-'Calc - research target (12m)'!$F$68*'Calc - research target (12m)'!$G$68)+'Calc - research target (12m)'!$G$68*($A13*(D$12-'Calc - research target (12m)'!$B$54)/'Calc - research target (12m)'!$B$53+'Calc - research target (12m)'!$B$52/'Calc - research target (12m)'!$B$53))/SUM('Calc - research target (12m)'!$G$67:$G$69) | E13: =((SUMPRODUCT('Calc - research target (12m)'!$F$67:$F$69,'Calc - research target (12m)'!$G$67:$G$69)-'Calc - research target (12m)'!$F$68*'Calc - research target (12m)'!$G$68)+'Calc - research target (12m)'!$G$68*($A13*(E$12-'Calc - research target (12m)'!$B$54)/'Calc - research target (12m)'!$B$53+'Calc - research target (12m)'!$B$52/'Calc - research target (12m)'!$B$53))/SUM('Calc - research target (12m)'!$G$67:$G$69) | F13: =((SUMPRODUCT('Calc - research target (12m)'!$F$67:$F$69,'Calc - research target (12m)'!$G$67:$G$69)-'Calc - research target (12m)'!$F$68*'Calc - research target (12m)'!$G$68)+'Calc - research target (12m)'!$G$68*($A13*(F$12-'Calc - research target (12m)'!$B$54)/'Calc - research target (12m)'!$B$53+'Calc - research target (12m)'!$B$52/'Calc - research target (12m)'!$B$53))/SUM('Calc - research target (12m)'!$G$67:$G$69)
A14: =Valuation!$B$70+(-2) | B14: =((SUMPRODUCT('Calc - research target (12m)'!$F$67:$F$69,'Calc - research target (12m)'!$G$67:$G$69)-'Calc - research target (12m)'!$F$68*'Calc - research target (12m)'!$G$68)+'Calc - research target (12m)'!$G$68*($A14*(B$12-'Calc - research target (12m)'!$B$54)/'Calc - research target (12m)'!$B$53+'Calc - research target (12m)'!$B$52/'Calc - research target (12m)'!$B$53))/SUM('Calc - research target (12m)'!$G$67:$G$69) | C14: =((SUMPRODUCT('Calc - research target (12m)'!$F$67:$F$69,'Calc - research target (12m)'!$G$67:$G$69)-'Calc - research target (12m)'!$F$68*'Calc - research target (12m)'!$G$68)+'Calc - research target (12m)'!$G$68*($A14*(C$12-'Calc - research target (12m)'!$B$54)/'Calc - research target (12m)'!$B$53+'Calc - research target (12m)'!$B$52/'Calc - research target (12m)'!$B$53))/SUM('Calc - research target (12m)'!$G$67:$G$69) | D14: =((SUMPRODUCT('Calc - research target (12m)'!$F$67:$F$69,'Calc - research target (12m)'!$G$67:$G$69)-'Calc - research target (12m)'!$F$68*'Calc - research target (12m)'!$G$68)+'Calc - research target (12m)'!$G$68*($A14*(D$12-'Calc - research target (12m)'!$B$54)/'Calc - research target (12m)'!$B$53+'Calc - research target (12m)'!$B$52/'Calc - research target (12m)'!$B$53))/SUM('Calc - research target (12m)'!$G$67:$G$69) | E14: =((SUMPRODUCT('Calc - research target (12m)'!$F$67:$F$69,'Calc - research target (12m)'!$G$67:$G$69)-'Calc - research target (12m)'!$F$68*'Calc - research target (12m)'!$G$68)+'Calc - research target (12m)'!$G$68*($A14*(E$12-'Calc - research target (12m)'!$B$54)/'Calc - research target (12m)'!$B$53+'Calc - research target (12m)'!$B$52/'Calc - research target (12m)'!$B$53))/SUM('Calc - research target (12m)'!$G$67:$G$69) | F14: =((SUMPRODUCT('Calc - research target (12m)'!$F$67:$F$69,'Calc - research target (12m)'!$G$67:$G$69)-'Calc - research target (12m)'!$F$68*'Calc - research target (12m)'!$G$68)+'Calc - research target (12m)'!$G$68*($A14*(F$12-'Calc - research target (12m)'!$B$54)/'Calc - research target (12m)'!$B$53+'Calc - research target (12m)'!$B$52/'Calc - research target (12m)'!$B$53))/SUM('Calc - research target (12m)'!$G$67:$G$69)
A15: =Valuation!$B$70+(-1) | B15: =((SUMPRODUCT('Calc - research target (12m)'!$F$67:$F$69,'Calc - research target (12m)'!$G$67:$G$69)-'Calc - research target (12m)'!$F$68*'Calc - research target (12m)'!$G$68)+'Calc - research target (12m)'!$G$68*($A15*(B$12-'Calc - research target (12m)'!$B$54)/'Calc - research target (12m)'!$B$53+'Calc - research target (12m)'!$B$52/'Calc - research target (12m)'!$B$53))/SUM('Calc - research target (12m)'!$G$67:$G$69) | C15: =((SUMPRODUCT('Calc - research target (12m)'!$F$67:$F$69,'Calc - research target (12m)'!$G$67:$G$69)-'Calc - research target (12m)'!$F$68*'Calc - research target (12m)'!$G$68)+'Calc - research target (12m)'!$G$68*($A15*(C$12-'Calc - research target (12m)'!$B$54)/'Calc - research target (12m)'!$B$53+'Calc - research target (12m)'!$B$52/'Calc - research target (12m)'!$B$53))/SUM('Calc - research target (12m)'!$G$67:$G$69) | D15: =((SUMPRODUCT('Calc - research target (12m)'!$F$67:$F$69,'Calc - research target (12m)'!$G$67:$G$69)-'Calc - research target (12m)'!$F$68*'Calc - research target (12m)'!$G$68)+'Calc - research target (12m)'!$G$68*($A15*(D$12-'Calc - research target (12m)'!$B$54)/'Calc - research target (12m)'!$B$53+'Calc - research target (12m)'!$B$52/'Calc - research target (12m)'!$B$53))/SUM('Calc - research target (12m)'!$G$67:$G$69) | E15: =((SUMPRODUCT('Calc - research target (12m)'!$F$67:$F$69,'Calc - research target (12m)'!$G$67:$G$69)-'Calc - research target (12m)'!$F$68*'Calc - research target (12m)'!$G$68)+'Calc - research target (12m)'!$G$68*($A15*(E$12-'Calc - research target (12m)'!$B$54)/'Calc - research target (12m)'!$B$53+'Calc - research target (12m)'!$B$52/'Calc - research target (12m)'!$B$53))/SUM('Calc - research target (12m)'!$G$67:$G$69) | F15: =((SUMPRODUCT('Calc - research target (12m)'!$F$67:$F$69,'Calc - research target (12m)'!$G$67:$G$69)-'Calc - research target (12m)'!$F$68*'Calc - research target (12m)'!$G$68)+'Calc - research target (12m)'!$G$68*($A15*(F$12-'Calc - research target (12m)'!$B$54)/'Calc - research target (12m)'!$B$53+'Calc - research target (12m)'!$B$52/'Calc - research target (12m)'!$B$53))/SUM('Calc - research target (12m)'!$G$67:$G$69)
A16: =Valuation!$B$70+(0) | B16: =((SUMPRODUCT('Calc - research target (12m)'!$F$67:$F$69,'Calc - research target (12m)'!$G$67:$G$69)-'Calc - research target (12m)'!$F$68*'Calc - research target (12m)'!$G$68)+'Calc - research target (12m)'!$G$68*($A16*(B$12-'Calc - research target (12m)'!$B$54)/'Calc - research target (12m)'!$B$53+'Calc - research target (12m)'!$B$52/'Calc - research target (12m)'!$B$53))/SUM('Calc - research target (12m)'!$G$67:$G$69) | C16: =((SUMPRODUCT('Calc - research target (12m)'!$F$67:$F$69,'Calc - research target (12m)'!$G$67:$G$69)-'Calc - research target (12m)'!$F$68*'Calc - research target (12m)'!$G$68)+'Calc - research target (12m)'!$G$68*($A16*(C$12-'Calc - research target (12m)'!$B$54)/'Calc - research target (12m)'!$B$53+'Calc - research target (12m)'!$B$52/'Calc - research target (12m)'!$B$53))/SUM('Calc - research target (12m)'!$G$67:$G$69) | D16: =((SUMPRODUCT('Calc - research target (12m)'!$F$67:$F$69,'Calc - research target (12m)'!$G$67:$G$69)-'Calc - research target (12m)'!$F$68*'Calc - research target (12m)'!$G$68)+'Calc - research target (12m)'!$G$68*($A16*(D$12-'Calc - research target (12m)'!$B$54)/'Calc - research target (12m)'!$B$53+'Calc - research target (12m)'!$B$52/'Calc - research target (12m)'!$B$53))/SUM('Calc - research target (12m)'!$G$67:$G$69) | E16: =((SUMPRODUCT('Calc - research target (12m)'!$F$67:$F$69,'Calc - research target (12m)'!$G$67:$G$69)-'Calc - research target (12m)'!$F$68*'Calc - research target (12m)'!$G$68)+'Calc - research target (12m)'!$G$68*($A16*(E$12-'Calc - research target (12m)'!$B$54)/'Calc - research target (12m)'!$B$53+'Calc - research target (12m)'!$B$52/'Calc - research target (12m)'!$B$53))/SUM('Calc - research target (12m)'!$G$67:$G$69) | F16: =((SUMPRODUCT('Calc - research target (12m)'!$F$67:$F$69,'Calc - research target (12m)'!$G$67:$G$69)-'Calc - research target (12m)'!$F$68*'Calc - research target (12m)'!$G$68)+'Calc - research target (12m)'!$G$68*($A16*(F$12-'Calc - research target (12m)'!$B$54)/'Calc - research target (12m)'!$B$53+'Calc - research target (12m)'!$B$52/'Calc - research target (12m)'!$B$53))/SUM('Calc - research target (12m)'!$G$67:$G$69)
A17: =Valuation!$B$70+(1) | B17: =((SUMPRODUCT('Calc - research target (12m)'!$F$67:$F$69,'Calc - research target (12m)'!$G$67:$G$69)-'Calc - research target (12m)'!$F$68*'Calc - research target (12m)'!$G$68)+'Calc - research target (12m)'!$G$68*($A17*(B$12-'Calc - research target (12m)'!$B$54)/'Calc - research target (12m)'!$B$53+'Calc - research target (12m)'!$B$52/'Calc - research target (12m)'!$B$53))/SUM('Calc - research target (12m)'!$G$67:$G$69) | C17: =((SUMPRODUCT('Calc - research target (12m)'!$F$67:$F$69,'Calc - research target (12m)'!$G$67:$G$69)-'Calc - research target (12m)'!$F$68*'Calc - research target (12m)'!$G$68)+'Calc - research target (12m)'!$G$68*($A17*(C$12-'Calc - research target (12m)'!$B$54)/'Calc - research target (12m)'!$B$53+'Calc - research target (12m)'!$B$52/'Calc - research target (12m)'!$B$53))/SUM('Calc - research target (12m)'!$G$67:$G$69) | D17: =((SUMPRODUCT('Calc - research target (12m)'!$F$67:$F$69,'Calc - research target (12m)'!$G$67:$G$69)-'Calc - research target (12m)'!$F$68*'Calc - research target (12m)'!$G$68)+'Calc - research target (12m)'!$G$68*($A17*(D$12-'Calc - research target (12m)'!$B$54)/'Calc - research target (12m)'!$B$53+'Calc - research target (12m)'!$B$52/'Calc - research target (12m)'!$B$53))/SUM('Calc - research target (12m)'!$G$67:$G$69) | E17: =((SUMPRODUCT('Calc - research target (12m)'!$F$67:$F$69,'Calc - research target (12m)'!$G$67:$G$69)-'Calc - research target (12m)'!$F$68*'Calc - research target (12m)'!$G$68)+'Calc - research target (12m)'!$G$68*($A17*(E$12-'Calc - research target (12m)'!$B$54)/'Calc - research target (12m)'!$B$53+'Calc - research target (12m)'!$B$52/'Calc - research target (12m)'!$B$53))/SUM('Calc - research target (12m)'!$G$67:$G$69) | F17: =((SUMPRODUCT('Calc - research target (12m)'!$F$67:$F$69,'Calc - research target (12m)'!$G$67:$G$69)-'Calc - research target (12m)'!$F$68*'Calc - research target (12m)'!$G$68)+'Calc - research target (12m)'!$G$68*($A17*(F$12-'Calc - research target (12m)'!$B$54)/'Calc - research target (12m)'!$B$53+'Calc - research target (12m)'!$B$52/'Calc - research target (12m)'!$B$53))/SUM('Calc - research target (12m)'!$G$67:$G$69)
A18: =Valuation!$B$70+(2) | B18: =((SUMPRODUCT('Calc - research target (12m)'!$F$67:$F$69,'Calc - research target (12m)'!$G$67:$G$69)-'Calc - research target (12m)'!$F$68*'Calc - research target (12m)'!$G$68)+'Calc - research target (12m)'!$G$68*($A18*(B$12-'Calc - research target (12m)'!$B$54)/'Calc - research target (12m)'!$B$53+'Calc - research target (12m)'!$B$52/'Calc - research target (12m)'!$B$53))/SUM('Calc - research target (12m)'!$G$67:$G$69) | C18: =((SUMPRODUCT('Calc - research target (12m)'!$F$67:$F$69,'Calc - research target (12m)'!$G$67:$G$69)-'Calc - research target (12m)'!$F$68*'Calc - research target (12m)'!$G$68)+'Calc - research target (12m)'!$G$68*($A18*(C$12-'Calc - research target (12m)'!$B$54)/'Calc - research target (12m)'!$B$53+'Calc - research target (12m)'!$B$52/'Calc - research target (12m)'!$B$53))/SUM('Calc - research target (12m)'!$G$67:$G$69) | D18: =((SUMPRODUCT('Calc - research target (12m)'!$F$67:$F$69,'Calc - research target (12m)'!$G$67:$G$69)-'Calc - research target (12m)'!$F$68*'Calc - research target (12m)'!$G$68)+'Calc - research target (12m)'!$G$68*($A18*(D$12-'Calc - research target (12m)'!$B$54)/'Calc - research target (12m)'!$B$53+'Calc - research target (12m)'!$B$52/'Calc - research target (12m)'!$B$53))/SUM('Calc - research target (12m)'!$G$67:$G$69) | E18: =((SUMPRODUCT('Calc - research target (12m)'!$F$67:$F$69,'Calc - research target (12m)'!$G$67:$G$69)-'Calc - research target (12m)'!$F$68*'Calc - research target (12m)'!$G$68)+'Calc - research target (12m)'!$G$68*($A18*(E$12-'Calc - research target (12m)'!$B$54)/'Calc - research target (12m)'!$B$53+'Calc - research target (12m)'!$B$52/'Calc - research target (12m)'!$B$53))/SUM('Calc - research target (12m)'!$G$67:$G$69) | F18: =((SUMPRODUCT('Calc - research target (12m)'!$F$67:$F$69,'Calc - research target (12m)'!$G$67:$G$69)-'Calc - research target (12m)'!$F$68*'Calc - research target (12m)'!$G$68)+'Calc - research target (12m)'!$G$68*($A18*(F$12-'Calc - research target (12m)'!$B$54)/'Calc - research target (12m)'!$B$53+'Calc - research target (12m)'!$B$52/'Calc - research target (12m)'!$B$53))/SUM('Calc - research target (12m)'!$G$67:$G$69)
A19: =Valuation!$B$70+(3) | B19: =((SUMPRODUCT('Calc - research target (12m)'!$F$67:$F$69,'Calc - research target (12m)'!$G$67:$G$69)-'Calc - research target (12m)'!$F$68*'Calc - research target (12m)'!$G$68)+'Calc - research target (12m)'!$G$68*($A19*(B$12-'Calc - research target (12m)'!$B$54)/'Calc - research target (12m)'!$B$53+'Calc - research target (12m)'!$B$52/'Calc - research target (12m)'!$B$53))/SUM('Calc - research target (12m)'!$G$67:$G$69) | C19: =((SUMPRODUCT('Calc - research target (12m)'!$F$67:$F$69,'Calc - research target (12m)'!$G$67:$G$69)-'Calc - research target (12m)'!$F$68*'Calc - research target (12m)'!$G$68)+'Calc - research target (12m)'!$G$68*($A19*(C$12-'Calc - research target (12m)'!$B$54)/'Calc - research target (12m)'!$B$53+'Calc - research target (12m)'!$B$52/'Calc - research target (12m)'!$B$53))/SUM('Calc - research target (12m)'!$G$67:$G$69) | D19: =((SUMPRODUCT('Calc - research target (12m)'!$F$67:$F$69,'Calc - research target (12m)'!$G$67:$G$69)-'Calc - research target (12m)'!$F$68*'Calc - research target (12m)'!$G$68)+'Calc - research target (12m)'!$G$68*($A19*(D$12-'Calc - research target (12m)'!$B$54)/'Calc - research target (12m)'!$B$53+'Calc - research target (12m)'!$B$52/'Calc - research target (12m)'!$B$53))/SUM('Calc - research target (12m)'!$G$67:$G$69) | E19: =((SUMPRODUCT('Calc - research target (12m)'!$F$67:$F$69,'Calc - research target (12m)'!$G$67:$G$69)-'Calc - research target (12m)'!$F$68*'Calc - research target (12m)'!$G$68)+'Calc - research target (12m)'!$G$68*($A19*(E$12-'Calc - research target (12m)'!$B$54)/'Calc - research target (12m)'!$B$53+'Calc - research target (12m)'!$B$52/'Calc - research target (12m)'!$B$53))/SUM('Calc - research target (12m)'!$G$67:$G$69) | F19: =((SUMPRODUCT('Calc - research target (12m)'!$F$67:$F$69,'Calc - research target (12m)'!$G$67:$G$69)-'Calc - research target (12m)'!$F$68*'Calc - research target (12m)'!$G$68)+'Calc - research target (12m)'!$G$68*($A19*(F$12-'Calc - research target (12m)'!$B$54)/'Calc - research target (12m)'!$B$53+'Calc - research target (12m)'!$B$52/'Calc - research target (12m)'!$B$53))/SUM('Calc - research target (12m)'!$G$67:$G$69)
A22: FY2028E diluted EPS: revenue growth change in every year (down) x EBIT margin change (across)
A23: Growth Δ \ margin Δ | B23: -0.01 | C23: -0.005 | D23: 0 | E23: 0.005 | F23: 0.01
A24: -0.02 | B24: =(Valuation!$B$88*(1+Model!E12+$A24)*(1+Model!F12+$A24)*(Model!F14+B$23)+Valuation!$B$89*(1+Model!E16+$A24)*(1+Model!F16+$A24)*(Model!F18+B$23)+Model!F21+Model!F33)*(1-Model!F63)/Model!F40 | C24: =(Valuation!$B$88*(1+Model!E12+$A24)*(1+Model!F12+$A24)*(Model!F14+C$23)+Valuation!$B$89*(1+Model!E16+$A24)*(1+Model!F16+$A24)*(Model!F18+C$23)+Model!F21+Model!F33)*(1-Model!F63)/Model!F40 | D24: =(Valuation!$B$88*(1+Model!E12+$A24)*(1+Model!F12+$A24)*(Model!F14+D$23)+Valuation!$B$89*(1+Model!E16+$A24)*(1+Model!F16+$A24)*(Model!F18+D$23)+Model!F21+Model!F33)*(1-Model!F63)/Model!F40 | E24: =(Valuation!$B$88*(1+Model!E12+$A24)*(1+Model!F12+$A24)*(Model!F14+E$23)+Valuation!$B$89*(1+Model!E16+$A24)*(1+Model!F16+$A24)*(Model!F18+E$23)+Model!F21+Model!F33)*(1-Model!F63)/Model!F40 | F24: =(Valuation!$B$88*(1+Model!E12+$A24)*(1+Model!F12+$A24)*(Model!F14+F$23)+Valuation!$B$89*(1+Model!E16+$A24)*(1+Model!F16+$A24)*(Model!F18+F$23)+Model!F21+Model!F33)*(1-Model!F63)/Model!F40
A25: -0.01 | B25: =(Valuation!$B$88*(1+Model!E12+$A25)*(1+Model!F12+$A25)*(Model!F14+B$23)+Valuation!$B$89*(1+Model!E16+$A25)*(1+Model!F16+$A25)*(Model!F18+B$23)+Model!F21+Model!F33)*(1-Model!F63)/Model!F40 | C25: =(Valuation!$B$88*(1+Model!E12+$A25)*(1+Model!F12+$A25)*(Model!F14+C$23)+Valuation!$B$89*(1+Model!E16+$A25)*(1+Model!F16+$A25)*(Model!F18+C$23)+Model!F21+Model!F33)*(1-Model!F63)/Model!F40 | D25: =(Valuation!$B$88*(1+Model!E12+$A25)*(1+Model!F12+$A25)*(Model!F14+D$23)+Valuation!$B$89*(1+Model!E16+$A25)*(1+Model!F16+$A25)*(Model!F18+D$23)+Model!F21+Model!F33)*(1-Model!F63)/Model!F40 | E25: =(Valuation!$B$88*(1+Model!E12+$A25)*(1+Model!F12+$A25)*(Model!F14+E$23)+Valuation!$B$89*(1+Model!E16+$A25)*(1+Model!F16+$A25)*(Model!F18+E$23)+Model!F21+Model!F33)*(1-Model!F63)/Model!F40 | F25: =(Valuation!$B$88*(1+Model!E12+$A25)*(1+Model!F12+$A25)*(Model!F14+F$23)+Valuation!$B$89*(1+Model!E16+$A25)*(1+Model!F16+$A25)*(Model!F18+F$23)+Model!F21+Model!F33)*(1-Model!F63)/Model!F40
A26: 0 | B26: =(Valuation!$B$88*(1+Model!E12+$A26)*(1+Model!F12+$A26)*(Model!F14+B$23)+Valuation!$B$89*(1+Model!E16+$A26)*(1+Model!F16+$A26)*(Model!F18+B$23)+Model!F21+Model!F33)*(1-Model!F63)/Model!F40 | C26: =(Valuation!$B$88*(1+Model!E12+$A26)*(1+Model!F12+$A26)*(Model!F14+C$23)+Valuation!$B$89*(1+Model!E16+$A26)*(1+Model!F16+$A26)*(Model!F18+C$23)+Model!F21+Model!F33)*(1-Model!F63)/Model!F40 | D26: =(Valuation!$B$88*(1+Model!E12+$A26)*(1+Model!F12+$A26)*(Model!F14+D$23)+Valuation!$B$89*(1+Model!E16+$A26)*(1+Model!F16+$A26)*(Model!F18+D$23)+Model!F21+Model!F33)*(1-Model!F63)/Model!F40 | E26: =(Valuation!$B$88*(1+Model!E12+$A26)*(1+Model!F12+$A26)*(Model!F14+E$23)+Valuation!$B$89*(1+Model!E16+$A26)*(1+Model!F16+$A26)*(Model!F18+E$23)+Model!F21+Model!F33)*(1-Model!F63)/Model!F40 | F26: =(Valuation!$B$88*(1+Model!E12+$A26)*(1+Model!F12+$A26)*(Model!F14+F$23)+Valuation!$B$89*(1+Model!E16+$A26)*(1+Model!F16+$A26)*(Model!F18+F$23)+Model!F21+Model!F33)*(1-Model!F63)/Model!F40
A27: 0.01 | B27: =(Valuation!$B$88*(1+Model!E12+$A27)*(1+Model!F12+$A27)*(Model!F14+B$23)+Valuation!$B$89*(1+Model!E16+$A27)*(1+Model!F16+$A27)*(Model!F18+B$23)+Model!F21+Model!F33)*(1-Model!F63)/Model!F40 | C27: =(Valuation!$B$88*(1+Model!E12+$A27)*(1+Model!F12+$A27)*(Model!F14+C$23)+Valuation!$B$89*(1+Model!E16+$A27)*(1+Model!F16+$A27)*(Model!F18+C$23)+Model!F21+Model!F33)*(1-Model!F63)/Model!F40 | D27: =(Valuation!$B$88*(1+Model!E12+$A27)*(1+Model!F12+$A27)*(Model!F14+D$23)+Valuation!$B$89*(1+Model!E16+$A27)*(1+Model!F16+$A27)*(Model!F18+D$23)+Model!F21+Model!F33)*(1-Model!F63)/Model!F40 | E27: =(Valuation!$B$88*(1+Model!E12+$A27)*(1+Model!F12+$A27)*(Model!F14+E$23)+Valuation!$B$89*(1+Model!E16+$A27)*(1+Model!F16+$A27)*(Model!F18+E$23)+Model!F21+Model!F33)*(1-Model!F63)/Model!F40 | F27: =(Valuation!$B$88*(1+Model!E12+$A27)*(1+Model!F12+$A27)*(Model!F14+F$23)+Valuation!$B$89*(1+Model!E16+$A27)*(1+Model!F16+$A27)*(Model!F18+F$23)+Model!F21+Model!F33)*(1-Model!F63)/Model!F40
A28: 0.02 | B28: =(Valuation!$B$88*(1+Model!E12+$A28)*(1+Model!F12+$A28)*(Model!F14+B$23)+Valuation!$B$89*(1+Model!E16+$A28)*(1+Model!F16+$A28)*(Model!F18+B$23)+Model!F21+Model!F33)*(1-Model!F63)/Model!F40 | C28: =(Valuation!$B$88*(1+Model!E12+$A28)*(1+Model!F12+$A28)*(Model!F14+C$23)+Valuation!$B$89*(1+Model!E16+$A28)*(1+Model!F16+$A28)*(Model!F18+C$23)+Model!F21+Model!F33)*(1-Model!F63)/Model!F40 | D28: =(Valuation!$B$88*(1+Model!E12+$A28)*(1+Model!F12+$A28)*(Model!F14+D$23)+Valuation!$B$89*(1+Model!E16+$A28)*(1+Model!F16+$A28)*(Model!F18+D$23)+Model!F21+Model!F33)*(1-Model!F63)/Model!F40 | E28: =(Valuation!$B$88*(1+Model!E12+$A28)*(1+Model!F12+$A28)*(Model!F14+E$23)+Valuation!$B$89*(1+Model!E16+$A28)*(1+Model!F16+$A28)*(Model!F18+E$23)+Model!F21+Model!F33)*(1-Model!F63)/Model!F40 | F28: =(Valuation!$B$88*(1+Model!E12+$A28)*(1+Model!F12+$A28)*(Model!F14+F$23)+Valuation!$B$89*(1+Model!E16+$A28)*(1+Model!F16+$A28)*(Model!F18+F$23)+Model!F21+Model!F33)*(1-Model!F63)/Model!F40
A30: Net interest and the share count are held at the base case in table 3.

Sheet Distribution
A1: CRDO: 12-month distribution (mix of lognormals around each scenario value)
A3: Scenario | B3: Probability | C3: Value at target date | D3: Story
A4: bear | B4: =Valuation!B83 | C4: ='Calc - bear'!$F$70 | D4: =Valuation!J83
A5: base | B5: =Valuation!B84 | C5: ='Calc - base'!$F$70 | D5: =Valuation!J84
A6: bull | B6: =Valuation!B85 | C6: ='Calc - bull'!$F$70 | D6: =Valuation!J85
A8: Probabilities sum to | B8: =SUM(B4:B6)
A9: Spread within each scenario | B9: =Valuation!$B$66
A10: Probability-weighted mean | B10: =($B$4*$C$4+$B$5*$C$5+$B$6*$C$6)*EXP($B$9^2/2)
A12: Quantile | B12: Price
A13: Median (model target) | B13: =SQRT(A60*B60)
A14: 10th percentile | B14: =SQRT(D60*E60)
A15: 25th percentile | B15: =SQRT(G60*H60)
A16: 75th percentile | B16: =SQRT(J60*K60)
A17: 90th percentile | B17: =SQRT(M60*N60)
A19: Each quantile solved by bisection (block: low, high, probability above the midpoint)
A20: Median (model target): low | B20: high | C20: P(above mid) | D20: 10th percentile: low | E20: high | F20: P(above mid) | G20: 25th percentile: low | H20: high | I20: P(above mid) | J20: 75th percentile: low | K20: high | L20: P(above mid) | M20: 90th percentile: low | N20: high | O20: P(above mid)
A21: =MIN($C$4,$C$5,$C$6)*0.2 | B21: =MAX($C$4,$C$5,$C$6)*4 | C21: =SUMPRODUCT($B$4:$B$6,1-NORMSDIST((LN(SQRT(A21*B21))-LN($C$4:$C$6))/$B$9)) | D21: =MIN($C$4,$C$5,$C$6)*0.2 | E21: =MAX($C$4,$C$5,$C$6)*4 | F21: =SUMPRODUCT($B$4:$B$6,1-NORMSDIST((LN(SQRT(D21*E21))-LN($C$4:$C$6))/$B$9)) | G21: =MIN($C$4,$C$5,$C$6)*0.2 | H21: =MAX($C$4,$C$5,$C$6)*4 | I21: =SUMPRODUCT($B$4:$B$6,1-NORMSDIST((LN(SQRT(G21*H21))-LN($C$4:$C$6))/$B$9)) | J21: =MIN($C$4,$C$5,$C$6)*0.2 | K21: =MAX($C$4,$C$5,$C$6)*4 | L21: =SUMPRODUCT($B$4:$B$6,1-NORMSDIST((LN(SQRT(J21*K21))-LN($C$4:$C$6))/$B$9)) | M21: =MIN($C$4,$C$5,$C$6)*0.2 | N21: =MAX($C$4,$C$5,$C$6)*4 | O21: =SUMPRODUCT($B$4:$B$6,1-NORMSDIST((LN(SQRT(M21*N21))-LN($C$4:$C$6))/$B$9))
A22: =IF(C21>0.5,SQRT(A21*B21),A21) | B22: =IF(C21>0.5,B21,SQRT(A21*B21)) | C22: =SUMPRODUCT($B$4:$B$6,1-NORMSDIST((LN(SQRT(A22*B22))-LN($C$4:$C$6))/$B$9)) | D22: =IF(F21>0.9,SQRT(D21*E21),D21) | E22: =IF(F21>0.9,E21,SQRT(D21*E21)) | F22: =SUMPRODUCT($B$4:$B$6,1-NORMSDIST((LN(SQRT(D22*E22))-LN($C$4:$C$6))/$B$9)) | G22: =IF(I21>0.75,SQRT(G21*H21),G21) | H22: =IF(I21>0.75,H21,SQRT(G21*H21)) | I22: =SUMPRODUCT($B$4:$B$6,1-NORMSDIST((LN(SQRT(G22*H22))-LN($C$4:$C$6))/$B$9)) | J22: =IF(L21>0.25,SQRT(J21*K21),J21) | K22: =IF(L21>0.25,K21,SQRT(J21*K21)) | L22: =SUMPRODUCT($B$4:$B$6,1-NORMSDIST((LN(SQRT(J22*K22))-LN($C$4:$C$6))/$B$9)) | M22: =IF(O21>0.09999999999999998,SQRT(M21*N21),M21) | N22: =IF(O21>0.09999999999999998,N21,SQRT(M21*N21)) | O22: =SUMPRODUCT($B$4:$B$6,1-NORMSDIST((LN(SQRT(M22*N22))-LN($C$4:$C$6))/$B$9))
A23: =IF(C22>0.5,SQRT(A22*B22),A22) | B23: =IF(C22>0.5,B22,SQRT(A22*B22)) | C23: =SUMPRODUCT($B$4:$B$6,1-NORMSDIST((LN(SQRT(A23*B23))-LN($C$4:$C$6))/$B$9)) | D23: =IF(F22>0.9,SQRT(D22*E22),D22) | E23: =IF(F22>0.9,E22,SQRT(D22*E22)) | F23: =SUMPRODUCT($B$4:$B$6,1-NORMSDIST((LN(SQRT(D23*E23))-LN($C$4:$C$6))/$B$9)) | G23: =IF(I22>0.75,SQRT(G22*H22),G22) | H23: =IF(I22>0.75,H22,SQRT(G22*H22)) | I23: =SUMPRODUCT($B$4:$B$6,1-NORMSDIST((LN(SQRT(G23*H23))-LN($C$4:$C$6))/$B$9)) | J23: =IF(L22>0.25,SQRT(J22*K22),J22) | K23: =IF(L22>0.25,K22,SQRT(J22*K22)) | L23: =SUMPRODUCT($B$4:$B$6,1-NORMSDIST((LN(SQRT(J23*K23))-LN($C$4:$C$6))/$B$9)) | M23: =IF(O22>0.09999999999999998,SQRT(M22*N22),M22) | N23: =IF(O22>0.09999999999999998,N22,SQRT(M22*N22)) | O23: =SUMPRODUCT($B$4:$B$6,1-NORMSDIST((LN(SQRT(M23*N23))-LN($C$4:$C$6))/$B$9))
A24: =IF(C23>0.5,SQRT(A23*B23),A23) | B24: =IF(C23>0.5,B23,SQRT(A23*B23)) | C24: =SUMPRODUCT($B$4:$B$6,1-NORMSDIST((LN(SQRT(A24*B24))-LN($C$4:$C$6))/$B$9)) | D24: =IF(F23>0.9,SQRT(D23*E23),D23) | E24: =IF(F23>0.9,E23,SQRT(D23*E23)) | F24: =SUMPRODUCT($B$4:$B$6,1-NORMSDIST((LN(SQRT(D24*E24))-LN($C$4:$C$6))/$B$9)) | G24: =IF(I23>0.75,SQRT(G23*H23),G23) | H24: =IF(I23>0.75,H23,SQRT(G23*H23)) | I24: =SUMPRODUCT($B$4:$B$6,1-NORMSDIST((LN(SQRT(G24*H24))-LN($C$4:$C$6))/$B$9)) | J24: =IF(L23>0.25,SQRT(J23*K23),J23) | K24: =IF(L23>0.25,K23,SQRT(J23*K23)) | L24: =SUMPRODUCT($B$4:$B$6,1-NORMSDIST((LN(SQRT(J24*K24))-LN($C$4:$C$6))/$B$9)) | M24: =IF(O23>0.09999999999999998,SQRT(M23*N23),M23) | N24: =IF(O23>0.09999999999999998,N23,SQRT(M23*N23)) | O24: =SUMPRODUCT($B$4:$B$6,1-NORMSDIST((LN(SQRT(M24*N24))-LN($C$4:$C$6))/$B$9))
A25: =IF(C24>0.5,SQRT(A24*B24),A24) | B25: =IF(C24>0.5,B24,SQRT(A24*B24)) | C25: =SUMPRODUCT($B$4:$B$6,1-NORMSDIST((LN(SQRT(A25*B25))-LN($C$4:$C$6))/$B$9)) | D25: =IF(F24>0.9,SQRT(D24*E24),D24) | E25: =IF(F24>0.9,E24,SQRT(D24*E24)) | F25: =SUMPRODUCT($B$4:$B$6,1-NORMSDIST((LN(SQRT(D25*E25))-LN($C$4:$C$6))/$B$9)) | G25: =IF(I24>0.75,SQRT(G24*H24),G24) | H25: =IF(I24>0.75,H24,SQRT(G24*H24)) | I25: =SUMPRODUCT($B$4:$B$6,1-NORMSDIST((LN(SQRT(G25*H25))-LN($C$4:$C$6))/$B$9)) | J25: =IF(L24>0.25,SQRT(J24*K24),J24) | K25: =IF(L24>0.25,K24,SQRT(J24*K24)) | L25: =SUMPRODUCT($B$4:$B$6,1-NORMSDIST((LN(SQRT(J25*K25))-LN($C$4:$C$6))/$B$9)) | M25: =IF(O24>0.09999999999999998,SQRT(M24*N24),M24) | N25: =IF(O24>0.09999999999999998,N24,SQRT(M24*N24)) | O25: =SUMPRODUCT($B$4:$B$6,1-NORMSDIST((LN(SQRT(M25*N25))-LN($C$4:$C$6))/$B$9))
A26: =IF(C25>0.5,SQRT(A25*B25),A25) | B26: =IF(C25>0.5,B25,SQRT(A25*B25)) | C26: =SUMPRODUCT($B$4:$B$6,1-NORMSDIST((LN(SQRT(A26*B26))-LN($C$4:$C$6))/$B$9)) | D26: =IF(F25>0.9,SQRT(D25*E25),D25) | E26: =IF(F25>0.9,E25,SQRT(D25*E25)) | F26: =SUMPRODUCT($B$4:$B$6,1-NORMSDIST((LN(SQRT(D26*E26))-LN($C$4:$C$6))/$B$9)) | G26: =IF(I25>0.75,SQRT(G25*H25),G25) | H26: =IF(I25>0.75,H25,SQRT(G25*H25)) | I26: =SUMPRODUCT($B$4:$B$6,1-NORMSDIST((LN(SQRT(G26*H26))-LN($C$4:$C$6))/$B$9)) | J26: =IF(L25>0.25,SQRT(J25*K25),J25) | K26: =IF(L25>0.25,K25,SQRT(J25*K25)) | L26: =SUMPRODUCT($B$4:$B$6,1-NORMSDIST((LN(SQRT(J26*K26))-LN($C$4:$C$6))/$B$9)) | M26: =IF(O25>0.09999999999999998,SQRT(M25*N25),M25) | N26: =IF(O25>0.09999999999999998,N25,SQRT(M25*N25)) | O26: =SUMPRODUCT($B$4:$B$6,1-NORMSDIST((LN(SQRT(M26*N26))-LN($C$4:$C$6))/$B$9))
A27: =IF(C26>0.5,SQRT(A26*B26),A26) | B27: =IF(C26>0.5,B26,SQRT(A26*B26)) | C27: =SUMPRODUCT($B$4:$B$6,1-NORMSDIST((LN(SQRT(A27*B27))-LN($C$4:$C$6))/$B$9)) | D27: =IF(F26>0.9,SQRT(D26*E26),D26) | E27: =IF(F26>0.9,E26,SQRT(D26*E26)) | F27: =SUMPRODUCT($B$4:$B$6,1-NORMSDIST((LN(SQRT(D27*E27))-LN($C$4:$C$6))/$B$9)) | G27: =IF(I26>0.75,SQRT(G26*H26),G26) | H27: =IF(I26>0.75,H26,SQRT(G26*H26)) | I27: =SUMPRODUCT($B$4:$B$6,1-NORMSDIST((LN(SQRT(G27*H27))-LN($C$4:$C$6))/$B$9)) | J27: =IF(L26>0.25,SQRT(J26*K26),J26) | K27: =IF(L26>0.25,K26,SQRT(J26*K26)) | L27: =SUMPRODUCT($B$4:$B$6,1-NORMSDIST((LN(SQRT(J27*K27))-LN($C$4:$C$6))/$B$9)) | M27: =IF(O26>0.09999999999999998,SQRT(M26*N26),M26) | N27: =IF(O26>0.09999999999999998,N26,SQRT(M26*N26)) | O27: =SUMPRODUCT($B$4:$B$6,1-NORMSDIST((LN(SQRT(M27*N27))-LN($C$4:$C$6))/$B$9))
A28: =IF(C27>0.5,SQRT(A27*B27),A27) | B28: =IF(C27>0.5,B27,SQRT(A27*B27)) | C28: =SUMPRODUCT($B$4:$B$6,1-NORMSDIST((LN(SQRT(A28*B28))-LN($C$4:$C$6))/$B$9)) | D28: =IF(F27>0.9,SQRT(D27*E27),D27) | E28: =IF(F27>0.9,E27,SQRT(D27*E27)) | F28: =SUMPRODUCT($B$4:$B$6,1-NORMSDIST((LN(SQRT(D28*E28))-LN($C$4:$C$6))/$B$9)) | G28: =IF(I27>0.75,SQRT(G27*H27),G27) | H28: =IF(I27>0.75,H27,SQRT(G27*H27)) | I28: =SUMPRODUCT($B$4:$B$6,1-NORMSDIST((LN(SQRT(G28*H28))-LN($C$4:$C$6))/$B$9)) | J28: =IF(L27>0.25,SQRT(J27*K27),J27) | K28: =IF(L27>0.25,K27,SQRT(J27*K27)) | L28: =SUMPRODUCT($B$4:$B$6,1-NORMSDIST((LN(SQRT(J28*K28))-LN($C$4:$C$6))/$B$9)) | M28: =IF(O27>0.09999999999999998,SQRT(M27*N27),M27) | N28: =IF(O27>0.09999999999999998,N27,SQRT(M27*N27)) | O28: =SUMPRODUCT($B$4:$B$6,1-NORMSDIST((LN(SQRT(M28*N28))-LN($C$4:$C$6))/$B$9))
A29: =IF(C28>0.5,SQRT(A28*B28),A28) | B29: =IF(C28>0.5,B28,SQRT(A28*B28)) | C29: =SUMPRODUCT($B$4:$B$6,1-NORMSDIST((LN(SQRT(A29*B29))-LN($C$4:$C$6))/$B$9)) | D29: =IF(F28>0.9,SQRT(D28*E28),D28) | E29: =IF(F28>0.9,E28,SQRT(D28*E28)) | F29: =SUMPRODUCT($B$4:$B$6,1-NORMSDIST((LN(SQRT(D29*E29))-LN($C$4:$C$6))/$B$9)) | G29: =IF(I28>0.75,SQRT(G28*H28),G28) | H29: =IF(I28>0.75,H28,SQRT(G28*H28)) | I29: =SUMPRODUCT($B$4:$B$6,1-NORMSDIST((LN(SQRT(G29*H29))-LN($C$4:$C$6))/$B$9)) | J29: =IF(L28>0.25,SQRT(J28*K28),J28) | K29: =IF(L28>0.25,K28,SQRT(J28*K28)) | L29: =SUMPRODUCT($B$4:$B$6,1-NORMSDIST((LN(SQRT(J29*K29))-LN($C$4:$C$6))/$B$9)) | M29: =IF(O28>0.09999999999999998,SQRT(M28*N28),M28) | N29: =IF(O28>0.09999999999999998,N28,SQRT(M28*N28)) | O29: =SUMPRODUCT($B$4:$B$6,1-NORMSDIST((LN(SQRT(M29*N29))-LN($C$4:$C$6))/$B$9))
A30: =IF(C29>0.5,SQRT(A29*B29),A29) | B30: =IF(C29>0.5,B29,SQRT(A29*B29)) | C30: =SUMPRODUCT($B$4:$B$6,1-NORMSDIST((LN(SQRT(A30*B30))-LN($C$4:$C$6))/$B$9)) | D30: =IF(F29>0.9,SQRT(D29*E29),D29) | E30: =IF(F29>0.9,E29,SQRT(D29*E29)) | F30: =SUMPRODUCT($B$4:$B$6,1-NORMSDIST((LN(SQRT(D30*E30))-LN($C$4:$C$6))/$B$9)) | G30: =IF(I29>0.75,SQRT(G29*H29),G29) | H30: =IF(I29>0.75,H29,SQRT(G29*H29)) | I30: =SUMPRODUCT($B$4:$B$6,1-NORMSDIST((LN(SQRT(G30*H30))-LN($C$4:$C$6))/$B$9)) | J30: =IF(L29>0.25,SQRT(J29*K29),J29) | K30: =IF(L29>0.25,K29,SQRT(J29*K29)) | L30: =SUMPRODUCT($B$4:$B$6,1-NORMSDIST((LN(SQRT(J30*K30))-LN($C$4:$C$6))/$B$9)) | M30: =IF(O29>0.09999999999999998,SQRT(M29*N29),M29) | N30: =IF(O29>0.09999999999999998,N29,SQRT(M29*N29)) | O30: =SUMPRODUCT($B$4:$B$6,1-NORMSDIST((LN(SQRT(M30*N30))-LN($C$4:$C$6))/$B$9))
A31: =IF(C30>0.5,SQRT(A30*B30),A30) | B31: =IF(C30>0.5,B30,SQRT(A30*B30)) | C31: =SUMPRODUCT($B$4:$B$6,1-NORMSDIST((LN(SQRT(A31*B31))-LN($C$4:$C$6))/$B$9)) | D31: =IF(F30>0.9,SQRT(D30*E30),D30) | E31: =IF(F30>0.9,E30,SQRT(D30*E30)) | F31: =SUMPRODUCT($B$4:$B$6,1-NORMSDIST((LN(SQRT(D31*E31))-LN($C$4:$C$6))/$B$9)) | G31: =IF(I30>0.75,SQRT(G30*H30),G30) | H31: =IF(I30>0.75,H30,SQRT(G30*H30)) | I31: =SUMPRODUCT($B$4:$B$6,1-NORMSDIST((LN(SQRT(G31*H31))-LN($C$4:$C$6))/$B$9)) | J31: =IF(L30>0.25,SQRT(J30*K30),J30) | K31: =IF(L30>0.25,K30,SQRT(J30*K30)) | L31: =SUMPRODUCT($B$4:$B$6,1-NORMSDIST((LN(SQRT(J31*K31))-LN($C$4:$C$6))/$B$9)) | M31: =IF(O30>0.09999999999999998,SQRT(M30*N30),M30) | N31: =IF(O30>0.09999999999999998,N30,SQRT(M30*N30)) | O31: =SUMPRODUCT($B$4:$B$6,1-NORMSDIST((LN(SQRT(M31*N31))-LN($C$4:$C$6))/$B$9))
A32: =IF(C31>0.5,SQRT(A31*B31),A31) | B32: =IF(C31>0.5,B31,SQRT(A31*B31)) | C32: =SUMPRODUCT($B$4:$B$6,1-NORMSDIST((LN(SQRT(A32*B32))-LN($C$4:$C$6))/$B$9)) | D32: =IF(F31>0.9,SQRT(D31*E31),D31) | E32: =IF(F31>0.9,E31,SQRT(D31*E31)) | F32: =SUMPRODUCT($B$4:$B$6,1-NORMSDIST((LN(SQRT(D32*E32))-LN($C$4:$C$6))/$B$9)) | G32: =IF(I31>0.75,SQRT(G31*H31),G31) | H32: =IF(I31>0.75,H31,SQRT(G31*H31)) | I32: =SUMPRODUCT($B$4:$B$6,1-NORMSDIST((LN(SQRT(G32*H32))-LN($C$4:$C$6))/$B$9)) | J32: =IF(L31>0.25,SQRT(J31*K31),J31) | K32: =IF(L31>0.25,K31,SQRT(J31*K31)) | L32: =SUMPRODUCT($B$4:$B$6,1-NORMSDIST((LN(SQRT(J32*K32))-LN($C$4:$C$6))/$B$9)) | M32: =IF(O31>0.09999999999999998,SQRT(M31*N31),M31) | N32: =IF(O31>0.09999999999999998,N31,SQRT(M31*N31)) | O32: =SUMPRODUCT($B$4:$B$6,1-NORMSDIST((LN(SQRT(M32*N32))-LN($C$4:$C$6))/$B$9))
A33: =IF(C32>0.5,SQRT(A32*B32),A32) | B33: =IF(C32>0.5,B32,SQRT(A32*B32)) | C33: =SUMPRODUCT($B$4:$B$6,1-NORMSDIST((LN(SQRT(A33*B33))-LN($C$4:$C$6))/$B$9)) | D33: =IF(F32>0.9,SQRT(D32*E32),D32) | E33: =IF(F32>0.9,E32,SQRT(D32*E32)) | F33: =SUMPRODUCT($B$4:$B$6,1-NORMSDIST((LN(SQRT(D33*E33))-LN($C$4:$C$6))/$B$9)) | G33: =IF(I32>0.75,SQRT(G32*H32),G32) | H33: =IF(I32>0.75,H32,SQRT(G32*H32)) | I33: =SUMPRODUCT($B$4:$B$6,1-NORMSDIST((LN(SQRT(G33*H33))-LN($C$4:$C$6))/$B$9)) | J33: =IF(L32>0.25,SQRT(J32*K32),J32) | K33: =IF(L32>0.25,K32,SQRT(J32*K32)) | L33: =SUMPRODUCT($B$4:$B$6,1-NORMSDIST((LN(SQRT(J33*K33))-LN($C$4:$C$6))/$B$9)) | M33: =IF(O32>0.09999999999999998,SQRT(M32*N32),M32) | N33: =IF(O32>0.09999999999999998,N32,SQRT(M32*N32)) | O33: =SUMPRODUCT($B$4:$B$6,1-NORMSDIST((LN(SQRT(M33*N33))-LN($C$4:$C$6))/$B$9))
... A60: =IF(C59>0.5,SQRT(A59*B59),A59) | B60: =IF(C59>0.5,B59,SQRT(A59*B59)) | C60: =SUMPRODUCT($B$4:$B$6,1-NORMSDIST((LN(SQRT(A60*B60))-LN($C$4:$C$6))/$B$9)) | D60: =IF(F59>0.9,SQRT(D59*E59),D59) | E60: =IF(F59>0.9,E59,SQRT(D59*E59)) | F60: =SUMPRODUCT($B$4:$B$6,1-NORMSDIST((LN(SQRT(D60*E60))-LN($C$4:$C$6))/$B$9)) | G60: =IF(I59>0.75,SQRT(G59*H59),G59) | H60: =IF(I59>0.75,H59,SQRT(G59*H59)) | I60: =SUMPRODUCT($B$4:$B$6,1-NORMSDIST((LN(SQRT(G60*H60))-LN($C$4:$C$6))/$B$9)) | J60: =IF(L59>0.25,SQRT(J59*K59),J59) | K60: =IF(L59>0.25,K59,SQRT(J59*K59)) | L60: =SUMPRODUCT($B$4:$B$6,1-NORMSDIST((LN(SQRT(J60*K60))-LN($C$4:$C$6))/$B$9)) | M60: =IF(O59>0.09999999999999998,SQRT(M59*N59),M59) | N60: =IF(O59>0.09999999999999998,N59,SQRT(M59*N59)) | O60: =SUMPRODUCT($B$4:$B$6,1-NORMSDIST((LN(SQRT(M60*N60))-LN($C$4:$C$6))/$B$9))

Sheet Calc - research target (12m)
A1: CRDO engine calculation: research target (12m) (reconciled set, no scenario deltas)
A2: Machinery behind the Valuation and Distribution tabs; drivers come from Model, assumptions from Valuation.
A4: Scenario Growth Δ | B4: 0
A5: Scenario Margin Δ | B5: 0
A6: Scenario Multiple Δ (turns) | B6: 0
A7: Scenario WACC Δ | B7: 0
A8: Scenario Multiple %Δ | B8: 0
A9: Scenario Stated EPS/FCF %Δ | B9: 0
A10: Scenario Custom %Δ | B10: 0
A12: WACC | B12: =Valuation!$B$51+B7
A13: Years from last FY end to target date | B13: =(Valuation!$B$45-Valuation!$B$49)/365.25
A14: Years from last FY end to balance date | B14: =(Valuation!$B$55-Valuation!$B$49)/365.25
A15: Years from last FY end to share count date | B15: =(Valuation!$B$61-Valuation!$B$49)/365.25
A16: Projected years | B16: 3
A18: Projection | B18: Base | C18: =Model!E5 | D18: =Model!F5 | E18: =Model!G5
A19: Year index | B19: 0 | C19: 1 | D19: 2 | E19: 3
A20: Period end | C20: =Valuation!$B$49+ROUND(365.25*C19,0) | D20: =Valuation!$B$49+ROUND(365.25*D19,0) | E20: =Valuation!$B$49+ROUND(365.25*E19,0)
A21: Revenue growth | C21: =C22/B22-1 | D21: =D22/C22-1 | E21: =E22/D22-1
A22: Revenue | B22: =Valuation!$B$50 | C22: =C139 | D22: =D139 | E22: =E139
A23: EBIT margin | C23: =C24/C22 | D23: =D24/D22 | E23: =E24/E22
A24: EBIT | C24: =C142 | D24: =D142 | E24: =E142
A25: Tax rate | C25: =Model!E63 | D25: =Model!F63 | E25: =Model!G63
A26: NOPAT | C26: =C24*(1-C25) | D26: =D24*(1-D25) | E26: =E24*(1-E25)
A27: D&A | C27: =C22*(Model!E64) | D27: =D22*(Model!F64) | E27: =E22*(Model!G64)
A28: Capex | C28: =C22*(Model!E65) | D28: =D22*(Model!F65) | E28: =E22*(Model!G65)
A29: Working capital increase | C29: =(Model!E66)*(C22-B22) | D29: =(Model!F66)*(D22-C22) | E29: =(Model!G66)*(E22-D22)
A30: Stock comp | C30: =C22*(Model!E67) | D30: =D22*(Model!F67) | E30: =E22*(Model!G67)
A31: Free cash flow to firm | C31: =C26+C27-C28-C29-IF(AND(Valuation!$B$47="adjusted",Valuation!$B$48="cost"),C30*(1-C25),0) | D31: =D26+D27-D28-D29-IF(AND(Valuation!$B$47="adjusted",Valuation!$B$48="cost"),D30*(1-D25),0) | E31: =E26+E27-E28-E29-IF(AND(Valuation!$B$47="adjusted",Valuation!$B$48="cost"),E30*(1-E25),0)
A32: EBITDA | C32: =C24+C27 | D32: =D24+D27 | E32: =E24+E27
A33: Adj. EBITDA | C33: =C24+C27+C22*(Model!E71) | D33: =D24+D27+D22*(Model!F71) | E33: =E24+E27+E22*(Model!G71)
A34: Shareholder returns + other uses | C34: =C22*Model!E69+Model!E68+Model!E70 | D34: =D22*Model!F69+Model!F68+Model!F70 | E34: =E22*Model!G69+Model!G68+Model!G70
A35: Share of year after target date | C35: =IF(C19<=$B$13,0,C19-MAX(C19-1,$B$13)) | D35: =IF(D19<=$B$13,0,D19-MAX(D19-1,$B$13)) | E35: =IF(E19<=$B$13,0,E19-MAX(E19-1,$B$13))
A36: PV at target date of FCFF | C36: =IF(C35=0,0,C31*C35/(1+$B$12)^(C19-$B$13)) | D36: =IF(D35=0,0,D31*D35/(1+$B$12)^(D19-$B$13)) | E36: =IF(E35=0,0,E31*E35/(1+$B$12)^(E19-$B$13))
A37: Overlap: balance date to target date | C37: =MAX(0,MIN(C19,$B$13)-MAX(C19-1,$B$14)) | D37: =MAX(0,MIN(D19,$B$13)-MAX(D19-1,$B$14)) | E37: =MAX(0,MIN(E19,$B$13)-MAX(E19-1,$B$14))
A38: NTM weight at target date | C38: =MAX(0,MIN(C19,$B$13+1)-MAX(C19-1,$B$13)) | D38: =MAX(0,MIN(D19,$B$13+1)-MAX(D19-1,$B$13)) | E38: =MAX(0,MIN(E19,$B$13+1)-MAX(E19-1,$B$13))
A39: LTM weight at target date | B39: =MAX(0,MIN(0,$B$13)-MAX(-1,$B$13-1)) | C39: =MAX(0,MIN(C19,$B$13)-MAX(C19-1,$B$13-1)) | D39: =MAX(0,MIN(D19,$B$13)-MAX(D19-1,$B$13-1)) | E39: =MAX(0,MIN(E19,$B$13)-MAX(E19-1,$B$13-1))
A41: Value at the target date
A42: PV of free cash flow after the target date | B42: =SUM($C$36:$E$36)
A43: Terminal value at final year | B43: =IF(Valuation!$B$52="exit_multiple",Valuation!$B$54*E32,E31*(1+Valuation!$B$53)/($B$12-Valuation!$B$53))
A44: PV of terminal value at target date | B44: =B43/(1+$B$12)^($B$16-$B$13)
A45: DCF enterprise value at target date | B45: =B42+B44
A46: Terminal value share of DCF | B46: =B44/B45
A47: Free cash flow earned, balance date to target date | B47: =SUMPRODUCT($C$37:$E$37,$C$31:$E$31)
A48: Shareholder returns + other uses paid | B48: =SUMPRODUCT($C$37:$E$37,$C$34:$E$34)
A49: Interest drag on net debt | B49: =Valuation!$B$58*(1-$C$25)*MAX(Valuation!$B$56,0)*MAX($B$13-$B$14,0)
A50: Net debt at target date | B50: =IF(Valuation!$B$59="",Valuation!$B$56-B47+B49+B48,Valuation!$B$59)
A51: Minority interests | B51: =Valuation!$B$57
A52: Adjustments (probability-weighted) | B52: =0
A53: Diluted shares at target date (M) | B53: =IF(Valuation!$B$63="",Valuation!$B$60*(1+Valuation!$B$62)^MAX($B$13-$B$15,0),Valuation!$B$63)
A54: After-tax interest on target-date net debt | B54: =Valuation!$B$58*(1-$C$25)*MAX(B50,0)
A55: Check: WACC vs terminal growth | B55: =IF(AND(Valuation!$B$52<>"exit_multiple",$B$12<=Valuation!$B$53+0.01),"WACC must exceed terminal growth by 1 point","ok")
A56: Check: projection length | B56: =IF(OR($B$13>=$B$16-1,$B$13+1>$B$16),"add projected years past the target date","ok")
A58: Metric at target date | B58: Next 12 months | C58: Last 12 months
A59: Revenue | B59: =SUMPRODUCT($C$38:$E$38,$C$22:$E$22) | C59: =SUMPRODUCT($C$39:$E$39,$C$22:$E$22)+$B$39*$B$22
A60: EBIT | B60: =SUMPRODUCT($C$38:$E$38,$C$24:$E$24) | C60: =SUMPRODUCT($C$39:$E$39,$C$24:$E$24)
A61: EBITDA | B61: =SUMPRODUCT($C$38:$E$38,$C$32:$E$32) | C61: =SUMPRODUCT($C$39:$E$39,$C$32:$E$32)
A62: Adj. EBITDA | B62: =SUMPRODUCT($C$38:$E$38,$C$33:$E$33) | C62: =SUMPRODUCT($C$39:$E$39,$C$33:$E$33)
A63: NOPAT | B63: =SUMPRODUCT($C$38:$E$38,$C$26:$E$26) | C63: =SUMPRODUCT($C$39:$E$39,$C$26:$E$26)
A64: Free cash flow to firm | B64: =SUMPRODUCT($C$38:$E$38,$C$31:$E$31) | C64: =SUMPRODUCT($C$39:$E$39,$C$31:$E$31)
A66: Valuation method | B66: Metric | C66: Multiple used | D66: Basis | E66: Metric at target date | F66: Value per share | G66: Weight | H66: Metric key | I66: Metric shown (stated per-share figure when used)
A67: DCF (cash flow to target date + terminal) | F67: =((B45)-$B$50-$B$51+$B$52)/$B$53 | G67: =Valuation!$B$64
A68: ="Multiple: "&Valuation!A70&" ("&Valuation!D70&")" | B68: =Valuation!A70 | C68: =IF(B68="FCF yield",(Valuation!B70)*(1-$B$8),(Valuation!B70)+IF(B68="EV/sales",0.1,1)*$B$6) | D68: =Valuation!D70 | E68: =IF(D68="ltm",CHOOSE(H68,$C$59,$C$60,$C$61,$C$62,$C$63,$C$64),CHOOSE(H68,$B$59,$B$60,$B$61,$B$62,$B$63,$B$64)) | F68: =IF(OR(B68="EV/EBITDA",B68="EV/sales",B68="EV/EBIT"),((C68*E68)-$B$50-$B$51+$B$52)/$B$53,IF(B68="P/E",IF(Valuation!F70<>"",C68*(Valuation!F70)*(1+$B$9),C68*(E68-$B$54)/$B$53),IF(Valuation!G70<>"",(Valuation!G70)*(1+$B$9)/C68,(E68-IF(Valuation!H70,$B$54,0))/C68/$B$53))+$B$52/$B$53) | G68: =Valuation!C70 | H68: =IF(B68="EV/sales",1,IF(B68="EV/EBIT",2,IF(B68="EV/EBITDA",IF(Valuation!E70="adjusted",4,3),IF(B68="P/E",5,6)))) | I68: =IF(AND(B68="P/E",Valuation!F70<>""),(Valuation!F70)*(1+$B$9),IF(AND(B68="FCF yield",Valuation!G70<>""),(Valuation!G70)*(1+$B$9),E68))
A69: ="Multiple: "&Valuation!A71&" ("&Valuation!D71&")" | B69: =Valuation!A71 | C69: =IF(B69="FCF yield",(Valuation!B71)*(1-$B$8),(Valuation!B71)+IF(B69="EV/sales",0.1,1)*$B$6) | D69: =Valuation!D71 | E69: =IF(D69="ltm",CHOOSE(H69,$C$59,$C$60,$C$61,$C$62,$C$63,$C$64),CHOOSE(H69,$B$59,$B$60,$B$61,$B$62,$B$63,$B$64)) | F69: =IF(OR(B69="EV/EBITDA",B69="EV/sales",B69="EV/EBIT"),((C69*E69)-$B$50-$B$51+$B$52)/$B$53,IF(B69="P/E",IF(Valuation!F71<>"",C69*(Valuation!F71)*(1+$B$9),C69*(E69-$B$54)/$B$53),IF(Valuation!G71<>"",(Valuation!G71)*(1+$B$9)/C69,(E69-IF(Valuation!H71,$B$54,0))/C69/$B$53))+$B$52/$B$53) | G69: =Valuation!C71 | H69: =IF(B69="EV/sales",1,IF(B69="EV/EBIT",2,IF(B69="EV/EBITDA",IF(Valuation!E71="adjusted",4,3),IF(B69="P/E",5,6)))) | I69: =IF(AND(B69="P/E",Valuation!F71<>""),(Valuation!F71)*(1+$B$9),IF(AND(B69="FCF yield",Valuation!G71<>""),(Valuation!G71)*(1+$B$9),E69))
A70: Value per share at target date (weighted methods) | F70: =SUMPRODUCT(F67:F69,G67:G69)/SUM(G67:G69)
A129: Segment build (model_engine.seg_build): revenue and EBIT are the segment sums plus corporate EBIT
A130: Segment | B130: Base | C130: =Model!E5 | D130: =Model!F5 | E130: =Model!G5
A131: Copper (AECs, electrical ICs, IP): revenue growth | C131: =Model!E12+$B$4 | D131: =Model!F12+$B$4 | E131: =Model!G12+$B$4
A132: Copper (AECs, electrical ICs, IP): revenue | B132: =Valuation!$B$88 | C132: =B132*(1+C131) | D132: =C132*(1+D131) | E132: =D132*(1+E131)
A133: Copper (AECs, electrical ICs, IP): EBIT margin | C133: =Model!E14+$B$5 | D133: =Model!F14+$B$5 | E133: =Model!G14+$B$5
A134: Copper (AECs, electrical ICs, IP): EBIT | C134: =C132*C133 | D134: =D132*D133 | E134: =E132*E133
A135: Optical (DSPs, SiPh PICs, ZF optics, ALC: revenue growth | C135: =Model!E16+$B$4 | D135: =Model!F16+$B$4 | E135: =Model!G16+$B$4
A136: Optical (DSPs, SiPh PICs, ZF optics, ALC: revenue | B136: =Valuation!$B$89 | C136: =B136*(1+C135) | D136: =C136*(1+D135) | E136: =D136*(1+E135)
A137: Optical (DSPs, SiPh PICs, ZF optics, ALC: EBIT margin | C137: =Model!E18+$B$5 | D137: =Model!F18+$B$5 | E137: =Model!G18+$B$5
A138: Optical (DSPs, SiPh PICs, ZF optics, ALC: EBIT | C138: =C136*C137 | D138: =D136*D137 | E138: =E136*E137
A139: Total segment revenue | C139: =C132+C136 | D139: =D132+D136 | E139: =E132+E136
A140: Total segment EBIT | C140: =C134+C138 | D140: =D134+D138 | E140: =E134+E138
A141: Corporate / unallocated EBIT | C141: =Model!E21 | D141: =Model!F21 | E141: =Model!G21
A142: EBIT (segments + corporate) | C142: =C140+C141 | D142: =D140+D141 | E142: =E140+E141

Sheet Calc - bear
A1: CRDO engine calculation: bear scenario
A2: Machinery behind the Valuation and Distribution tabs; drivers come from Model, assumptions from Valuation.
A4: Scenario Growth Δ | B4: =N(Valuation!C83)
A5: Scenario Margin Δ | B5: =N(Valuation!D83)
A6: Scenario Multiple Δ (turns) | B6: =N(Valuation!E83)
A7: Scenario WACC Δ | B7: =N(Valuation!F83)
A8: Scenario Multiple %Δ | B8: =N(Valuation!G83)
A9: Scenario Stated EPS/FCF %Δ | B9: =N(Valuation!H83)
A10: Scenario Custom %Δ | B10: =N(Valuation!I83)
A12: WACC | B12: =Valuation!$B$51+B7
A13: Years from last FY end to target date | B13: =(Valuation!$B$45-Valuation!$B$49)/365.25
A14: Years from last FY end to balance date | B14: =(Valuation!$B$55-Valuation!$B$49)/365.25
A15: Years from last FY end to share count date | B15: =(Valuation!$B$61-Valuation!$B$49)/365.25
A16: Projected years | B16: 3
A18: Projection | B18: Base | C18: =Model!E5 | D18: =Model!F5 | E18: =Model!G5
A19: Year index | B19: 0 | C19: 1 | D19: 2 | E19: 3
A20: Period end | C20: =Valuation!$B$49+ROUND(365.25*C19,0) | D20: =Valuation!$B$49+ROUND(365.25*D19,0) | E20: =Valuation!$B$49+ROUND(365.25*E19,0)
A21: Revenue growth | C21: =C22/B22-1 | D21: =D22/C22-1 | E21: =E22/D22-1
A22: Revenue | B22: =Valuation!$B$50 | C22: =C139 | D22: =D139 | E22: =E139
A23: EBIT margin | C23: =C24/C22 | D23: =D24/D22 | E23: =E24/E22
A24: EBIT | C24: =C142 | D24: =D142 | E24: =E142
A25: Tax rate | C25: =Model!E63 | D25: =Model!F63 | E25: =Model!G63
A26: NOPAT | C26: =C24*(1-C25) | D26: =D24*(1-D25) | E26: =E24*(1-E25)
A27: D&A | C27: =C22*(Model!E64) | D27: =D22*(Model!F64) | E27: =E22*(Model!G64)
A28: Capex | C28: =C22*(Model!E65) | D28: =D22*(Model!F65) | E28: =E22*(Model!G65)
A29: Working capital increase | C29: =(Model!E66)*(C22-B22) | D29: =(Model!F66)*(D22-C22) | E29: =(Model!G66)*(E22-D22)
A30: Stock comp | C30: =C22*(Model!E67) | D30: =D22*(Model!F67) | E30: =E22*(Model!G67)
A31: Free cash flow to firm | C31: =C26+C27-C28-C29-IF(AND(Valuation!$B$47="adjusted",Valuation!$B$48="cost"),C30*(1-C25),0) | D31: =D26+D27-D28-D29-IF(AND(Valuation!$B$47="adjusted",Valuation!$B$48="cost"),D30*(1-D25),0) | E31: =E26+E27-E28-E29-IF(AND(Valuation!$B$47="adjusted",Valuation!$B$48="cost"),E30*(1-E25),0)
A32: EBITDA | C32: =C24+C27 | D32: =D24+D27 | E32: =E24+E27
A33: Adj. EBITDA | C33: =C24+C27+C22*(Model!E71) | D33: =D24+D27+D22*(Model!F71) | E33: =E24+E27+E22*(Model!G71)
A34: Shareholder returns + other uses | C34: =C22*Model!E69+Model!E68+Model!E70 | D34: =D22*Model!F69+Model!F68+Model!F70 | E34: =E22*Model!G69+Model!G68+Model!G70
A35: Share of year after target date | C35: =IF(C19<=$B$13,0,C19-MAX(C19-1,$B$13)) | D35: =IF(D19<=$B$13,0,D19-MAX(D19-1,$B$13)) | E35: =IF(E19<=$B$13,0,E19-MAX(E19-1,$B$13))
A36: PV at target date of FCFF | C36: =IF(C35=0,0,C31*C35/(1+$B$12)^(C19-$B$13)) | D36: =IF(D35=0,0,D31*D35/(1+$B$12)^(D19-$B$13)) | E36: =IF(E35=0,0,E31*E35/(1+$B$12)^(E19-$B$13))
A37: Overlap: balance date to target date | C37: =MAX(0,MIN(C19,$B$13)-MAX(C19-1,$B$14)) | D37: =MAX(0,MIN(D19,$B$13)-MAX(D19-1,$B$14)) | E37: =MAX(0,MIN(E19,$B$13)-MAX(E19-1,$B$14))
A38: NTM weight at target date | C38: =MAX(0,MIN(C19,$B$13+1)-MAX(C19-1,$B$13)) | D38: =MAX(0,MIN(D19,$B$13+1)-MAX(D19-1,$B$13)) | E38: =MAX(0,MIN(E19,$B$13+1)-MAX(E19-1,$B$13))
A39: LTM weight at target date | B39: =MAX(0,MIN(0,$B$13)-MAX(-1,$B$13-1)) | C39: =MAX(0,MIN(C19,$B$13)-MAX(C19-1,$B$13-1)) | D39: =MAX(0,MIN(D19,$B$13)-MAX(D19-1,$B$13-1)) | E39: =MAX(0,MIN(E19,$B$13)-MAX(E19-1,$B$13-1))
A41: Value at the target date
A42: PV of free cash flow after the target date | B42: =SUM($C$36:$E$36)
A43: Terminal value at final year | B43: =IF(Valuation!$B$52="exit_multiple",Valuation!$B$54*E32,E31*(1+Valuation!$B$53)/($B$12-Valuation!$B$53))
A44: PV of terminal value at target date | B44: =B43/(1+$B$12)^($B$16-$B$13)
A45: DCF enterprise value at target date | B45: =B42+B44
A46: Terminal value share of DCF | B46: =B44/B45
A47: Free cash flow earned, balance date to target date | B47: =SUMPRODUCT($C$37:$E$37,$C$31:$E$31)
A48: Shareholder returns + other uses paid | B48: =SUMPRODUCT($C$37:$E$37,$C$34:$E$34)
A49: Interest drag on net debt | B49: =Valuation!$B$58*(1-$C$25)*MAX(Valuation!$B$56,0)*MAX($B$13-$B$14,0)
A50: Net debt at target date | B50: =IF(Valuation!$B$59="",Valuation!$B$56-B47+B49+B48,Valuation!$B$59)
A51: Minority interests | B51: =Valuation!$B$57
A52: Adjustments (probability-weighted) | B52: =0
A53: Diluted shares at target date (M) | B53: =IF(Valuation!$B$63="",Valuation!$B$60*(1+Valuation!$B$62)^MAX($B$13-$B$15,0),Valuation!$B$63)
A54: After-tax interest on target-date net debt | B54: =Valuation!$B$58*(1-$C$25)*MAX(B50,0)
A55: Check: WACC vs terminal growth | B55: =IF(AND(Valuation!$B$52<>"exit_multiple",$B$12<=Valuation!$B$53+0.01),"WACC must exceed terminal growth by 1 point","ok")
A56: Check: projection length | B56: =IF(OR($B$13>=$B$16-1,$B$13+1>$B$16),"add projected years past the target date","ok")
A58: Metric at target date | B58: Next 12 months | C58: Last 12 months
A59: Revenue | B59: =SUMPRODUCT($C$38:$E$38,$C$22:$E$22) | C59: =SUMPRODUCT($C$39:$E$39,$C$22:$E$22)+$B$39*$B$22
A60: EBIT | B60: =SUMPRODUCT($C$38:$E$38,$C$24:$E$24) | C60: =SUMPRODUCT($C$39:$E$39,$C$24:$E$24)
A61: EBITDA | B61: =SUMPRODUCT($C$38:$E$38,$C$32:$E$32) | C61: =SUMPRODUCT($C$39:$E$39,$C$32:$E$32)
A62: Adj. EBITDA | B62: =SUMPRODUCT($C$38:$E$38,$C$33:$E$33) | C62: =SUMPRODUCT($C$39:$E$39,$C$33:$E$33)
A63: NOPAT | B63: =SUMPRODUCT($C$38:$E$38,$C$26:$E$26) | C63: =SUMPRODUCT($C$39:$E$39,$C$26:$E$26)
A64: Free cash flow to firm | B64: =SUMPRODUCT($C$38:$E$38,$C$31:$E$31) | C64: =SUMPRODUCT($C$39:$E$39,$C$31:$E$31)
A66: Valuation method | B66: Metric | C66: Multiple used | D66: Basis | E66: Metric at target date | F66: Value per share | G66: Weight | H66: Metric key | I66: Metric shown (stated per-share figure when used)
A67: DCF (cash flow to target date + terminal) | F67: =((B45)-$B$50-$B$51+$B$52)/$B$53 | G67: =Valuation!$B$64
A68: ="Multiple: "&Valuation!A70&" ("&Valuation!D70&")" | B68: =Valuation!A70 | C68: =IF(B68="FCF yield",(Valuation!B70)*(1-$B$8),(Valuation!B70)+IF(B68="EV/sales",0.1,1)*$B$6) | D68: =Valuation!D70 | E68: =IF(D68="ltm",CHOOSE(H68,$C$59,$C$60,$C$61,$C$62,$C$63,$C$64),CHOOSE(H68,$B$59,$B$60,$B$61,$B$62,$B$63,$B$64)) | F68: =IF(OR(B68="EV/EBITDA",B68="EV/sales",B68="EV/EBIT"),((C68*E68)-$B$50-$B$51+$B$52)/$B$53,IF(B68="P/E",IF(Valuation!F70<>"",C68*(Valuation!F70)*(1+$B$9),C68*(E68-$B$54)/$B$53),IF(Valuation!G70<>"",(Valuation!G70)*(1+$B$9)/C68,(E68-IF(Valuation!H70,$B$54,0))/C68/$B$53))+$B$52/$B$53) | G68: =Valuation!C70 | H68: =IF(B68="EV/sales",1,IF(B68="EV/EBIT",2,IF(B68="EV/EBITDA",IF(Valuation!E70="adjusted",4,3),IF(B68="P/E",5,6)))) | I68: =IF(AND(B68="P/E",Valuation!F70<>""),(Valuation!F70)*(1+$B$9),IF(AND(B68="FCF yield",Valuation!G70<>""),(Valuation!G70)*(1+$B$9),E68))
A69: ="Multiple: "&Valuation!A71&" ("&Valuation!D71&")" | B69: =Valuation!A71 | C69: =IF(B69="FCF yield",(Valuation!B71)*(1-$B$8),(Valuation!B71)+IF(B69="EV/sales",0.1,1)*$B$6) | D69: =Valuation!D71 | E69: =IF(D69="ltm",CHOOSE(H69,$C$59,$C$60,$C$61,$C$62,$C$63,$C$64),CHOOSE(H69,$B$59,$B$60,$B$61,$B$62,$B$63,$B$64)) | F69: =IF(OR(B69="EV/EBITDA",B69="EV/sales",B69="EV/EBIT"),((C69*E69)-$B$50-$B$51+$B$52)/$B$53,IF(B69="P/E",IF(Valuation!F71<>"",C69*(Valuation!F71)*(1+$B$9),C69*(E69-$B$54)/$B$53),IF(Valuation!G71<>"",(Valuation!G71)*(1+$B$9)/C69,(E69-IF(Valuation!H71,$B$54,0))/C69/$B$53))+$B$52/$B$53) | G69: =Valuation!C71 | H69: =IF(B69="EV/sales",1,IF(B69="EV/EBIT",2,IF(B69="EV/EBITDA",IF(Valuation!E71="adjusted",4,3),IF(B69="P/E",5,6)))) | I69: =IF(AND(B69="P/E",Valuation!F71<>""),(Valuation!F71)*(1+$B$9),IF(AND(B69="FCF yield",Valuation!G71<>""),(Valuation!G71)*(1+$B$9),E69))
A70: Value per share at target date (weighted methods) | F70: =SUMPRODUCT(F67:F69,G67:G69)/SUM(G67:G69)
A129: Segment build (model_engine.seg_build): revenue and EBIT are the segment sums plus corporate EBIT
A130: Segment | B130: Base | C130: =Model!E5 | D130: =Model!F5 | E130: =Model!G5
A131: Copper (AECs, electrical ICs, IP): revenue growth | C131: =Model!E12+$B$4+$B$250 | D131: =Model!F12+$B$4 | E131: =Model!G12+$B$4
A132: Copper (AECs, electrical ICs, IP): revenue | B132: =Valuation!$B$88 | C132: =B132*(1+C131) | D132: =C132*(1+D131) | E132: =D132*(1+E131)
A133: Copper (AECs, electrical ICs, IP): EBIT margin | C133: =Model!E14+$B$5+$B$251 | D133: =Model!F14+$B$5+$B$252 | E133: =Model!G14+$B$5+$B$253
A134: Copper (AECs, electrical ICs, IP): EBIT | C134: =C132*C133 | D134: =D132*D133 | E134: =E132*E133
A135: Optical (DSPs, SiPh PICs, ZF optics, ALC: revenue growth | C135: =Model!E16+$B$4+$B$254 | D135: =Model!F16+$B$4 | E135: =Model!G16+$B$4
A136: Optical (DSPs, SiPh PICs, ZF optics, ALC: revenue | B136: =Valuation!$B$89 | C136: =B136*(1+C135) | D136: =C136*(1+D135) | E136: =D136*(1+E135)
A137: Optical (DSPs, SiPh PICs, ZF optics, ALC: EBIT margin | C137: =Model!E18+$B$5+$B$255 | D137: =Model!F18+$B$5+$B$256 | E137: =Model!G18+$B$5+$B$257
A138: Optical (DSPs, SiPh PICs, ZF optics, ALC: EBIT | C138: =C136*C137 | D138: =D136*D137 | E138: =E136*E137
A139: Total segment revenue | C139: =C132+C136 | D139: =D132+D136 | E139: =E132+E136
A140: Total segment EBIT | C140: =C134+C138 | D140: =D134+D138 | E140: =E134+E138
A141: Corporate / unallocated EBIT | C141: =Model!E21 | D141: =Model!F21 | E141: =Model!G21
A142: EBIT (segments + corporate) | C142: =C140+C141 | D142: =D140+D141 | E142: =E140+E141
A249: Driver scenario shifts: line-item changes model_drivers.py resolves from this scenario's driver deltas (added to the Model tab inputs)
A250: Copper (AECs, electrical ICs, IP): revenue growth, year 1 | B250: -0.3490001
A251: Copper (AECs, electrical ICs, IP): EBIT margin, year 1 | B251: -0.083339603
A252: Copper (AECs, electrical ICs, IP): EBIT margin, year 2 | B252: -0.081402063
A253: Copper (AECs, electrical ICs, IP): EBIT margin, year 3 | B253: -0.080656515
A254: Optical (DSPs, SiPh PICs, ZF optics, ALC: revenue growth, year 1 | B254: -2.4459829
A255: Optical (DSPs, SiPh PICs, ZF optics, ALC: EBIT margin, year 1 | B255: -0.083339603
A256: Optical (DSPs, SiPh PICs, ZF optics, ALC: EBIT margin, year 2 | B256: -0.081402063
A257: Optical (DSPs, SiPh PICs, ZF optics, ALC: EBIT margin, year 3 | B257: -0.080656515

Sheet Calc - base
A1: CRDO engine calculation: base scenario
A2: Machinery behind the Valuation and Distribution tabs; drivers come from Model, assumptions from Valuation.
A4: Scenario Growth Δ | B4: =N(Valuation!C84)
A5: Scenario Margin Δ | B5: =N(Valuation!D84)
A6: Scenario Multiple Δ (turns) | B6: =N(Valuation!E84)
A7: Scenario WACC Δ | B7: =N(Valuation!F84)
A8: Scenario Multiple %Δ | B8: =N(Valuation!G84)
A9: Scenario Stated EPS/FCF %Δ | B9: =N(Valuation!H84)
A10: Scenario Custom %Δ | B10: =N(Valuation!I84)
A12: WACC | B12: =Valuation!$B$51+B7
A13: Years from last FY end to target date | B13: =(Valuation!$B$45-Valuation!$B$49)/365.25
A14: Years from last FY end to balance date | B14: =(Valuation!$B$55-Valuation!$B$49)/365.25
A15: Years from last FY end to share count date | B15: =(Valuation!$B$61-Valuation!$B$49)/365.25
A16: Projected years | B16: 3
A18: Projection | B18: Base | C18: =Model!E5 | D18: =Model!F5 | E18: =Model!G5
A19: Year index | B19: 0 | C19: 1 | D19: 2 | E19: 3
A20: Period end | C20: =Valuation!$B$49+ROUND(365.25*C19,0) | D20: =Valuation!$B$49+ROUND(365.25*D19,0) | E20: =Valuation!$B$49+ROUND(365.25*E19,0)
A21: Revenue growth | C21: =C22/B22-1 | D21: =D22/C22-1 | E21: =E22/D22-1
A22: Revenue | B22: =Valuation!$B$50 | C22: =C139 | D22: =D139 | E22: =E139
A23: EBIT margin | C23: =C24/C22 | D23: =D24/D22 | E23: =E24/E22
A24: EBIT | C24: =C142 | D24: =D142 | E24: =E142
A25: Tax rate | C25: =Model!E63 | D25: =Model!F63 | E25: =Model!G63
A26: NOPAT | C26: =C24*(1-C25) | D26: =D24*(1-D25) | E26: =E24*(1-E25)
A27: D&A | C27: =C22*(Model!E64) | D27: =D22*(Model!F64) | E27: =E22*(Model!G64)
A28: Capex | C28: =C22*(Model!E65) | D28: =D22*(Model!F65) | E28: =E22*(Model!G65)
A29: Working capital increase | C29: =(Model!E66)*(C22-B22) | D29: =(Model!F66)*(D22-C22) | E29: =(Model!G66)*(E22-D22)
A30: Stock comp | C30: =C22*(Model!E67) | D30: =D22*(Model!F67) | E30: =E22*(Model!G67)
A31: Free cash flow to firm | C31: =C26+C27-C28-C29-IF(AND(Valuation!$B$47="adjusted",Valuation!$B$48="cost"),C30*(1-C25),0) | D31: =D26+D27-D28-D29-IF(AND(Valuation!$B$47="adjusted",Valuation!$B$48="cost"),D30*(1-D25),0) | E31: =E26+E27-E28-E29-IF(AND(Valuation!$B$47="adjusted",Valuation!$B$48="cost"),E30*(1-E25),0)
A32: EBITDA | C32: =C24+C27 | D32: =D24+D27 | E32: =E24+E27
A33: Adj. EBITDA | C33: =C24+C27+C22*(Model!E71) | D33: =D24+D27+D22*(Model!F71) | E33: =E24+E27+E22*(Model!G71)
A34: Shareholder returns + other uses | C34: =C22*Model!E69+Model!E68+Model!E70 | D34: =D22*Model!F69+Model!F68+Model!F70 | E34: =E22*Model!G69+Model!G68+Model!G70
A35: Share of year after target date | C35: =IF(C19<=$B$13,0,C19-MAX(C19-1,$B$13)) | D35: =IF(D19<=$B$13,0,D19-MAX(D19-1,$B$13)) | E35: =IF(E19<=$B$13,0,E19-MAX(E19-1,$B$13))
A36: PV at target date of FCFF | C36: =IF(C35=0,0,C31*C35/(1+$B$12)^(C19-$B$13)) | D36: =IF(D35=0,0,D31*D35/(1+$B$12)^(D19-$B$13)) | E36: =IF(E35=0,0,E31*E35/(1+$B$12)^(E19-$B$13))
A37: Overlap: balance date to target date | C37: =MAX(0,MIN(C19,$B$13)-MAX(C19-1,$B$14)) | D37: =MAX(0,MIN(D19,$B$13)-MAX(D19-1,$B$14)) | E37: =MAX(0,MIN(E19,$B$13)-MAX(E19-1,$B$14))
A38: NTM weight at target date | C38: =MAX(0,MIN(C19,$B$13+1)-MAX(C19-1,$B$13)) | D38: =MAX(0,MIN(D19,$B$13+1)-MAX(D19-1,$B$13)) | E38: =MAX(0,MIN(E19,$B$13+1)-MAX(E19-1,$B$13))
A39: LTM weight at target date | B39: =MAX(0,MIN(0,$B$13)-MAX(-1,$B$13-1)) | C39: =MAX(0,MIN(C19,$B$13)-MAX(C19-1,$B$13-1)) | D39: =MAX(0,MIN(D19,$B$13)-MAX(D19-1,$B$13-1)) | E39: =MAX(0,MIN(E19,$B$13)-MAX(E19-1,$B$13-1))
A41: Value at the target date
A42: PV of free cash flow after the target date | B42: =SUM($C$36:$E$36)
A43: Terminal value at final year | B43: =IF(Valuation!$B$52="exit_multiple",Valuation!$B$54*E32,E31*(1+Valuation!$B$53)/($B$12-Valuation!$B$53))
A44: PV of terminal value at target date | B44: =B43/(1+$B$12)^($B$16-$B$13)
A45: DCF enterprise value at target date | B45: =B42+B44
A46: Terminal value share of DCF | B46: =B44/B45
A47: Free cash flow earned, balance date to target date | B47: =SUMPRODUCT($C$37:$E$37,$C$31:$E$31)
A48: Shareholder returns + other uses paid | B48: =SUMPRODUCT($C$37:$E$37,$C$34:$E$34)
A49: Interest drag on net debt | B49: =Valuation!$B$58*(1-$C$25)*MAX(Valuation!$B$56,0)*MAX($B$13-$B$14,0)
A50: Net debt at target date | B50: =IF(Valuation!$B$59="",Valuation!$B$56-B47+B49+B48,Valuation!$B$59)
A51: Minority interests | B51: =Valuation!$B$57
A52: Adjustments (probability-weighted) | B52: =0
A53: Diluted shares at target date (M) | B53: =IF(Valuation!$B$63="",Valuation!$B$60*(1+Valuation!$B$62)^MAX($B$13-$B$15,0),Valuation!$B$63)
A54: After-tax interest on target-date net debt | B54: =Valuation!$B$58*(1-$C$25)*MAX(B50,0)
A55: Check: WACC vs terminal growth | B55: =IF(AND(Valuation!$B$52<>"exit_multiple",$B$12<=Valuation!$B$53+0.01),"WACC must exceed terminal growth by 1 point","ok")
A56: Check: projection length | B56: =IF(OR($B$13>=$B$16-1,$B$13+1>$B$16),"add projected years past the target date","ok")
A58: Metric at target date | B58: Next 12 months | C58: Last 12 months
A59: Revenue | B59: =SUMPRODUCT($C$38:$E$38,$C$22:$E$22) | C59: =SUMPRODUCT($C$39:$E$39,$C$22:$E$22)+$B$39*$B$22
A60: EBIT | B60: =SUMPRODUCT($C$38:$E$38,$C$24:$E$24) | C60: =SUMPRODUCT($C$39:$E$39,$C$24:$E$24)
A61: EBITDA | B61: =SUMPRODUCT($C$38:$E$38,$C$32:$E$32) | C61: =SUMPRODUCT($C$39:$E$39,$C$32:$E$32)
A62: Adj. EBITDA | B62: =SUMPRODUCT($C$38:$E$38,$C$33:$E$33) | C62: =SUMPRODUCT($C$39:$E$39,$C$33:$E$33)
A63: NOPAT | B63: =SUMPRODUCT($C$38:$E$38,$C$26:$E$26) | C63: =SUMPRODUCT($C$39:$E$39,$C$26:$E$26)
A64: Free cash flow to firm | B64: =SUMPRODUCT($C$38:$E$38,$C$31:$E$31) | C64: =SUMPRODUCT($C$39:$E$39,$C$31:$E$31)
A66: Valuation method | B66: Metric | C66: Multiple used | D66: Basis | E66: Metric at target date | F66: Value per share | G66: Weight | H66: Metric key | I66: Metric shown (stated per-share figure when used)
A67: DCF (cash flow to target date + terminal) | F67: =((B45)-$B$50-$B$51+$B$52)/$B$53 | G67: =Valuation!$B$64
A68: ="Multiple: "&Valuation!A70&" ("&Valuation!D70&")" | B68: =Valuation!A70 | C68: =IF(B68="FCF yield",(Valuation!B70)*(1-$B$8),(Valuation!B70)+IF(B68="EV/sales",0.1,1)*$B$6) | D68: =Valuation!D70 | E68: =IF(D68="ltm",CHOOSE(H68,$C$59,$C$60,$C$61,$C$62,$C$63,$C$64),CHOOSE(H68,$B$59,$B$60,$B$61,$B$62,$B$63,$B$64)) | F68: =IF(OR(B68="EV/EBITDA",B68="EV/sales",B68="EV/EBIT"),((C68*E68)-$B$50-$B$51+$B$52)/$B$53,IF(B68="P/E",IF(Valuation!F70<>"",C68*(Valuation!F70)*(1+$B$9),C68*(E68-$B$54)/$B$53),IF(Valuation!G70<>"",(Valuation!G70)*(1+$B$9)/C68,(E68-IF(Valuation!H70,$B$54,0))/C68/$B$53))+$B$52/$B$53) | G68: =Valuation!C70 | H68: =IF(B68="EV/sales",1,IF(B68="EV/EBIT",2,IF(B68="EV/EBITDA",IF(Valuation!E70="adjusted",4,3),IF(B68="P/E",5,6)))) | I68: =IF(AND(B68="P/E",Valuation!F70<>""),(Valuation!F70)*(1+$B$9),IF(AND(B68="FCF yield",Valuation!G70<>""),(Valuation!G70)*(1+$B$9),E68))
A69: ="Multiple: "&Valuation!A71&" ("&Valuation!D71&")" | B69: =Valuation!A71 | C69: =IF(B69="FCF yield",(Valuation!B71)*(1-$B$8),(Valuation!B71)+IF(B69="EV/sales",0.1,1)*$B$6) | D69: =Valuation!D71 | E69: =IF(D69="ltm",CHOOSE(H69,$C$59,$C$60,$C$61,$C$62,$C$63,$C$64),CHOOSE(H69,$B$59,$B$60,$B$61,$B$62,$B$63,$B$64)) | F69: =IF(OR(B69="EV/EBITDA",B69="EV/sales",B69="EV/EBIT"),((C69*E69)-$B$50-$B$51+$B$52)/$B$53,IF(B69="P/E",IF(Valuation!F71<>"",C69*(Valuation!F71)*(1+$B$9),C69*(E69-$B$54)/$B$53),IF(Valuation!G71<>"",(Valuation!G71)*(1+$B$9)/C69,(E69-IF(Valuation!H71,$B$54,0))/C69/$B$53))+$B$52/$B$53) | G69: =Valuation!C71 | H69: =IF(B69="EV/sales",1,IF(B69="EV/EBIT",2,IF(B69="EV/EBITDA",IF(Valuation!E71="adjusted",4,3),IF(B69="P/E",5,6)))) | I69: =IF(AND(B69="P/E",Valuation!F71<>""),(Valuation!F71)*(1+$B$9),IF(AND(B69="FCF yield",Valuation!G71<>""),(Valuation!G71)*(1+$B$9),E69))
A70: Value per share at target date (weighted methods) | F70: =SUMPRODUCT(F67:F69,G67:G69)/SUM(G67:G69)
A129: Segment build (model_engine.seg_build): revenue and EBIT are the segment sums plus corporate EBIT
A130: Segment | B130: Base | C130: =Model!E5 | D130: =Model!F5 | E130: =Model!G5
A131: Copper (AECs, electrical ICs, IP): revenue growth | C131: =Model!E12+$B$4 | D131: =Model!F12+$B$4 | E131: =Model!G12+$B$4
A132: Copper (AECs, electrical ICs, IP): revenue | B132: =Valuation!$B$88 | C132: =B132*(1+C131) | D132: =C132*(1+D131) | E132: =D132*(1+E131)
A133: Copper (AECs, electrical ICs, IP): EBIT margin | C133: =Model!E14+$B$5 | D133: =Model!F14+$B$5 | E133: =Model!G14+$B$5
A134: Copper (AECs, electrical ICs, IP): EBIT | C134: =C132*C133 | D134: =D132*D133 | E134: =E132*E133
A135: Optical (DSPs, SiPh PICs, ZF optics, ALC: revenue growth | C135: =Model!E16+$B$4 | D135: =Model!F16+$B$4 | E135: =Model!G16+$B$4
A136: Optical (DSPs, SiPh PICs, ZF optics, ALC: revenue | B136: =Valuation!$B$89 | C136: =B136*(1+C135) | D136: =C136*(1+D135) | E136: =D136*(1+E135)
A137: Optical (DSPs, SiPh PICs, ZF optics, ALC: EBIT margin | C137: =Model!E18+$B$5 | D137: =Model!F18+$B$5 | E137: =Model!G18+$B$5
A138: Optical (DSPs, SiPh PICs, ZF optics, ALC: EBIT | C138: =C136*C137 | D138: =D136*D137 | E138: =E136*E137
A139: Total segment revenue | C139: =C132+C136 | D139: =D132+D136 | E139: =E132+E136
A140: Total segment EBIT | C140: =C134+C138 | D140: =D134+D138 | E140: =E134+E138
A141: Corporate / unallocated EBIT | C141: =Model!E21 | D141: =Model!F21 | E141: =Model!G21
A142: EBIT (segments + corporate) | C142: =C140+C141 | D142: =D140+D141 | E142: =E140+E141

Sheet Calc - bull
A1: CRDO engine calculation: bull scenario
A2: Machinery behind the Valuation and Distribution tabs; drivers come from Model, assumptions from Valuation.
A4: Scenario Growth Δ | B4: =N(Valuation!C85)
A5: Scenario Margin Δ | B5: =N(Valuation!D85)
A6: Scenario Multiple Δ (turns) | B6: =N(Valuation!E85)
A7: Scenario WACC Δ | B7: =N(Valuation!F85)
A8: Scenario Multiple %Δ | B8: =N(Valuation!G85)
A9: Scenario Stated EPS/FCF %Δ | B9: =N(Valuation!H85)
A10: Scenario Custom %Δ | B10: =N(Valuation!I85)
A12: WACC | B12: =Valuation!$B$51+B7
A13: Years from last FY end to target date | B13: =(Valuation!$B$45-Valuation!$B$49)/365.25
A14: Years from last FY end to balance date | B14: =(Valuation!$B$55-Valuation!$B$49)/365.25
A15: Years from last FY end to share count date | B15: =(Valuation!$B$61-Valuation!$B$49)/365.25
A16: Projected years | B16: 3
A18: Projection | B18: Base | C18: =Model!E5 | D18: =Model!F5 | E18: =Model!G5
A19: Year index | B19: 0 | C19: 1 | D19: 2 | E19: 3
A20: Period end | C20: =Valuation!$B$49+ROUND(365.25*C19,0) | D20: =Valuation!$B$49+ROUND(365.25*D19,0) | E20: =Valuation!$B$49+ROUND(365.25*E19,0)
A21: Revenue growth | C21: =C22/B22-1 | D21: =D22/C22-1 | E21: =E22/D22-1
A22: Revenue | B22: =Valuation!$B$50 | C22: =C139 | D22: =D139 | E22: =E139
A23: EBIT margin | C23: =C24/C22 | D23: =D24/D22 | E23: =E24/E22
A24: EBIT | C24: =C142 | D24: =D142 | E24: =E142
A25: Tax rate | C25: =Model!E63 | D25: =Model!F63 | E25: =Model!G63
A26: NOPAT | C26: =C24*(1-C25) | D26: =D24*(1-D25) | E26: =E24*(1-E25)
A27: D&A | C27: =C22*(Model!E64) | D27: =D22*(Model!F64) | E27: =E22*(Model!G64)
A28: Capex | C28: =C22*(Model!E65) | D28: =D22*(Model!F65) | E28: =E22*(Model!G65)
A29: Working capital increase | C29: =(Model!E66)*(C22-B22) | D29: =(Model!F66)*(D22-C22) | E29: =(Model!G66)*(E22-D22)
A30: Stock comp | C30: =C22*(Model!E67) | D30: =D22*(Model!F67) | E30: =E22*(Model!G67)
A31: Free cash flow to firm | C31: =C26+C27-C28-C29-IF(AND(Valuation!$B$47="adjusted",Valuation!$B$48="cost"),C30*(1-C25),0) | D31: =D26+D27-D28-D29-IF(AND(Valuation!$B$47="adjusted",Valuation!$B$48="cost"),D30*(1-D25),0) | E31: =E26+E27-E28-E29-IF(AND(Valuation!$B$47="adjusted",Valuation!$B$48="cost"),E30*(1-E25),0)
A32: EBITDA | C32: =C24+C27 | D32: =D24+D27 | E32: =E24+E27
A33: Adj. EBITDA | C33: =C24+C27+C22*(Model!E71) | D33: =D24+D27+D22*(Model!F71) | E33: =E24+E27+E22*(Model!G71)
A34: Shareholder returns + other uses | C34: =C22*Model!E69+Model!E68+Model!E70 | D34: =D22*Model!F69+Model!F68+Model!F70 | E34: =E22*Model!G69+Model!G68+Model!G70
A35: Share of year after target date | C35: =IF(C19<=$B$13,0,C19-MAX(C19-1,$B$13)) | D35: =IF(D19<=$B$13,0,D19-MAX(D19-1,$B$13)) | E35: =IF(E19<=$B$13,0,E19-MAX(E19-1,$B$13))
A36: PV at target date of FCFF | C36: =IF(C35=0,0,C31*C35/(1+$B$12)^(C19-$B$13)) | D36: =IF(D35=0,0,D31*D35/(1+$B$12)^(D19-$B$13)) | E36: =IF(E35=0,0,E31*E35/(1+$B$12)^(E19-$B$13))
A37: Overlap: balance date to target date | C37: =MAX(0,MIN(C19,$B$13)-MAX(C19-1,$B$14)) | D37: =MAX(0,MIN(D19,$B$13)-MAX(D19-1,$B$14)) | E37: =MAX(0,MIN(E19,$B$13)-MAX(E19-1,$B$14))
A38: NTM weight at target date | C38: =MAX(0,MIN(C19,$B$13+1)-MAX(C19-1,$B$13)) | D38: =MAX(0,MIN(D19,$B$13+1)-MAX(D19-1,$B$13)) | E38: =MAX(0,MIN(E19,$B$13+1)-MAX(E19-1,$B$13))
A39: LTM weight at target date | B39: =MAX(0,MIN(0,$B$13)-MAX(-1,$B$13-1)) | C39: =MAX(0,MIN(C19,$B$13)-MAX(C19-1,$B$13-1)) | D39: =MAX(0,MIN(D19,$B$13)-MAX(D19-1,$B$13-1)) | E39: =MAX(0,MIN(E19,$B$13)-MAX(E19-1,$B$13-1))
A41: Value at the target date
A42: PV of free cash flow after the target date | B42: =SUM($C$36:$E$36)
A43: Terminal value at final year | B43: =IF(Valuation!$B$52="exit_multiple",Valuation!$B$54*E32,E31*(1+Valuation!$B$53)/($B$12-Valuation!$B$53))
A44: PV of terminal value at target date | B44: =B43/(1+$B$12)^($B$16-$B$13)
A45: DCF enterprise value at target date | B45: =B42+B44
A46: Terminal value share of DCF | B46: =B44/B45
A47: Free cash flow earned, balance date to target date | B47: =SUMPRODUCT($C$37:$E$37,$C$31:$E$31)
A48: Shareholder returns + other uses paid | B48: =SUMPRODUCT($C$37:$E$37,$C$34:$E$34)
A49: Interest drag on net debt | B49: =Valuation!$B$58*(1-$C$25)*MAX(Valuation!$B$56,0)*MAX($B$13-$B$14,0)
A50: Net debt at target date | B50: =IF(Valuation!$B$59="",Valuation!$B$56-B47+B49+B48,Valuation!$B$59)
A51: Minority interests | B51: =Valuation!$B$57
A52: Adjustments (probability-weighted) | B52: =0
A53: Diluted shares at target date (M) | B53: =IF(Valuation!$B$63="",Valuation!$B$60*(1+Valuation!$B$62)^MAX($B$13-$B$15,0),Valuation!$B$63)
A54: After-tax interest on target-date net debt | B54: =Valuation!$B$58*(1-$C$25)*MAX(B50,0)
A55: Check: WACC vs terminal growth | B55: =IF(AND(Valuation!$B$52<>"exit_multiple",$B$12<=Valuation!$B$53+0.01),"WACC must exceed terminal growth by 1 point","ok")
A56: Check: projection length | B56: =IF(OR($B$13>=$B$16-1,$B$13+1>$B$16),"add projected years past the target date","ok")
A58: Metric at target date | B58: Next 12 months | C58: Last 12 months
A59: Revenue | B59: =SUMPRODUCT($C$38:$E$38,$C$22:$E$22) | C59: =SUMPRODUCT($C$39:$E$39,$C$22:$E$22)+$B$39*$B$22
A60: EBIT | B60: =SUMPRODUCT($C$38:$E$38,$C$24:$E$24) | C60: =SUMPRODUCT($C$39:$E$39,$C$24:$E$24)
A61: EBITDA | B61: =SUMPRODUCT($C$38:$E$38,$C$32:$E$32) | C61: =SUMPRODUCT($C$39:$E$39,$C$32:$E$32)
A62: Adj. EBITDA | B62: =SUMPRODUCT($C$38:$E$38,$C$33:$E$33) | C62: =SUMPRODUCT($C$39:$E$39,$C$33:$E$33)
A63: NOPAT | B63: =SUMPRODUCT($C$38:$E$38,$C$26:$E$26) | C63: =SUMPRODUCT($C$39:$E$39,$C$26:$E$26)
A64: Free cash flow to firm | B64: =SUMPRODUCT($C$38:$E$38,$C$31:$E$31) | C64: =SUMPRODUCT($C$39:$E$39,$C$31:$E$31)
A66: Valuation method | B66: Metric | C66: Multiple used | D66: Basis | E66: Metric at target date | F66: Value per share | G66: Weight | H66: Metric key | I66: Metric shown (stated per-share figure when used)
A67: DCF (cash flow to target date + terminal) | F67: =((B45)-$B$50-$B$51+$B$52)/$B$53 | G67: =Valuation!$B$64
A68: ="Multiple: "&Valuation!A70&" ("&Valuation!D70&")" | B68: =Valuation!A70 | C68: =IF(B68="FCF yield",(Valuation!B70)*(1-$B$8),(Valuation!B70)+IF(B68="EV/sales",0.1,1)*$B$6) | D68: =Valuation!D70 | E68: =IF(D68="ltm",CHOOSE(H68,$C$59,$C$60,$C$61,$C$62,$C$63,$C$64),CHOOSE(H68,$B$59,$B$60,$B$61,$B$62,$B$63,$B$64)) | F68: =IF(OR(B68="EV/EBITDA",B68="EV/sales",B68="EV/EBIT"),((C68*E68)-$B$50-$B$51+$B$52)/$B$53,IF(B68="P/E",IF(Valuation!F70<>"",C68*(Valuation!F70)*(1+$B$9),C68*(E68-$B$54)/$B$53),IF(Valuation!G70<>"",(Valuation!G70)*(1+$B$9)/C68,(E68-IF(Valuation!H70,$B$54,0))/C68/$B$53))+$B$52/$B$53) | G68: =Valuation!C70 | H68: =IF(B68="EV/sales",1,IF(B68="EV/EBIT",2,IF(B68="EV/EBITDA",IF(Valuation!E70="adjusted",4,3),IF(B68="P/E",5,6)))) | I68: =IF(AND(B68="P/E",Valuation!F70<>""),(Valuation!F70)*(1+$B$9),IF(AND(B68="FCF yield",Valuation!G70<>""),(Valuation!G70)*(1+$B$9),E68))
A69: ="Multiple: "&Valuation!A71&" ("&Valuation!D71&")" | B69: =Valuation!A71 | C69: =IF(B69="FCF yield",(Valuation!B71)*(1-$B$8),(Valuation!B71)+IF(B69="EV/sales",0.1,1)*$B$6) | D69: =Valuation!D71 | E69: =IF(D69="ltm",CHOOSE(H69,$C$59,$C$60,$C$61,$C$62,$C$63,$C$64),CHOOSE(H69,$B$59,$B$60,$B$61,$B$62,$B$63,$B$64)) | F69: =IF(OR(B69="EV/EBITDA",B69="EV/sales",B69="EV/EBIT"),((C69*E69)-$B$50-$B$51+$B$52)/$B$53,IF(B69="P/E",IF(Valuation!F71<>"",C69*(Valuation!F71)*(1+$B$9),C69*(E69-$B$54)/$B$53),IF(Valuation!G71<>"",(Valuation!G71)*(1+$B$9)/C69,(E69-IF(Valuation!H71,$B$54,0))/C69/$B$53))+$B$52/$B$53) | G69: =Valuation!C71 | H69: =IF(B69="EV/sales",1,IF(B69="EV/EBIT",2,IF(B69="EV/EBITDA",IF(Valuation!E71="adjusted",4,3),IF(B69="P/E",5,6)))) | I69: =IF(AND(B69="P/E",Valuation!F71<>""),(Valuation!F71)*(1+$B$9),IF(AND(B69="FCF yield",Valuation!G71<>""),(Valuation!G71)*(1+$B$9),E69))
A70: Value per share at target date (weighted methods) | F70: =SUMPRODUCT(F67:F69,G67:G69)/SUM(G67:G69)
A129: Segment build (model_engine.seg_build): revenue and EBIT are the segment sums plus corporate EBIT
A130: Segment | B130: Base | C130: =Model!E5 | D130: =Model!F5 | E130: =Model!G5
A131: Copper (AECs, electrical ICs, IP): revenue growth | C131: =Model!E12+$B$4+$B$250 | D131: =Model!F12+$B$4 | E131: =Model!G12+$B$4
A132: Copper (AECs, electrical ICs, IP): revenue | B132: =Valuation!$B$88 | C132: =B132*(1+C131) | D132: =C132*(1+D131) | E132: =D132*(1+E131)
A133: Copper (AECs, electrical ICs, IP): EBIT margin | C133: =Model!E14+$B$5+$B$251 | D133: =Model!F14+$B$5+$B$252 | E133: =Model!G14+$B$5+$B$253
A134: Copper (AECs, electrical ICs, IP): EBIT | C134: =C132*C133 | D134: =D132*D133 | E134: =E132*E133
A135: Optical (DSPs, SiPh PICs, ZF optics, ALC: revenue growth | C135: =Model!E16+$B$4+$B$254 | D135: =Model!F16+$B$4 | E135: =Model!G16+$B$4
A136: Optical (DSPs, SiPh PICs, ZF optics, ALC: revenue | B136: =Valuation!$B$89 | C136: =B136*(1+C135) | D136: =C136*(1+D135) | E136: =D136*(1+E135)
A137: Optical (DSPs, SiPh PICs, ZF optics, ALC: EBIT margin | C137: =Model!E18+$B$5+$B$255 | D137: =Model!F18+$B$5+$B$256 | E137: =Model!G18+$B$5+$B$257
A138: Optical (DSPs, SiPh PICs, ZF optics, ALC: EBIT | C138: =C136*C137 | D138: =D136*D137 | E138: =E136*E137
A139: Total segment revenue | C139: =C132+C136 | D139: =D132+D136 | E139: =E132+E136
A140: Total segment EBIT | C140: =C134+C138 | D140: =D134+D138 | E140: =E134+E138
A141: Corporate / unallocated EBIT | C141: =Model!E21 | D141: =Model!F21 | E141: =Model!G21
A142: EBIT (segments + corporate) | C142: =C140+C141 | D142: =D140+D141 | E142: =E140+E141
A249: Driver scenario shifts: line-item changes model_drivers.py resolves from this scenario's driver deltas (added to the Model tab inputs)
A250: Copper (AECs, electrical ICs, IP): revenue growth, year 1 | B250: 0.28092713
A251: Copper (AECs, electrical ICs, IP): EBIT margin, year 1 | B251: 0.035860911
A252: Copper (AECs, electrical ICs, IP): EBIT margin, year 2 | B252: 0.035176437
A253: Copper (AECs, electrical ICs, IP): EBIT margin, year 3 | B253: 0.034888051
A254: Optical (DSPs, SiPh PICs, ZF optics, ALC: revenue growth, year 1 | B254: 3.1405273
A255: Optical (DSPs, SiPh PICs, ZF optics, ALC: EBIT margin, year 1 | B255: 0.035860911
A256: Optical (DSPs, SiPh PICs, ZF optics, ALC: EBIT margin, year 2 | B256: 0.035176437
A257: Optical (DSPs, SiPh PICs, ZF optics, ALC: EBIT margin, year 3 | B257: 0.034888051

Sheet Agents
A1: CRDO: each forecaster's own assumption set through the same engine (from model_engine.json, not live)
A3: Set | B3: Research target (12m) | C3: Median | D3: 25th pct | E3: 75th pct | F3: WACC | G3: Y1 growth | H3: Y1 margin | I3: Terminal growth | J3: DCF weight | K3: Years | L3: Multiples | M3: Supervisor's note
A4: supervisor | B4: 223.00346 | C4: 218.60906 | D4: 152.59879 | E4: 284.26892 | J4: 0 | K4: 3 | L4: P/E 23.5 (ntm); EV/sales 11.0 (ntm)
A5: agent_1 | M5: engine error: no model_inputs found
A6: agent_2 | M6: engine error: no model_inputs found
A7: agent_3 | M7: engine error: no model_inputs found
A8: agent_4 | M8: engine error: no model_inputs found
A9: agent_5 | M9: engine error: no model_inputs found

Sheet Sources
A1: CRDO: where each input comes from (source numbers point to the list below; F ids to the SEC fact table)
A3: Input | B3: Value | C3: Basis | D3: Sources | E3: SEC fact ids | F3: Derivation
A4: driver:copper_tam | B4: base 2.46; [4.398, 6.48, 7.98] ($B) | C4: estimate | D4: 23, 24, 25, 26, 12, 22, 33 | F4: Big-4 capex path (project AI-capex build [src 23]: CY2025 $410B, CY2026 $733B, CY2027 $1,080B, CY2028 $1,330B; confirmed parts [src 24-26]) x a copper attach of 0.60% of capex (estimate). No citable copper TAM: Credo's FY2026 10-K has no market-opportunity figure [src 12]; management calls ALC, scale-up and OmniConnect 'multibillion dollar' opportunities without a copper figure [src 22]. TAM = Big-4 capex x 0.60%: CY2025 410 x 0.006 = $2.46B; CY2026 733 x 0.006 = $4.398B; CY2027 1,080 x 0.006 = $6.48B; CY2028 1,330 x 0.006 = $7.98B. The 0.60% attach is set so that Credo's FY2026 copper revenue (~$1,275M, see segment base) is ~52% of it: Credo created the AEC category and is its main supplier, but holds a minority of electrical retimers/PHYs (PCIe retimers, line-card PHYs) where larger vendors compete. Cross-check: LightCounting puts optics sales to the top five cloud providers at 2.7% of their capex in 2025 (Lightwave 2026-03-10 on the 'Optics for AI Clusters' report [src 33]), so copper at 0.6% is ~1/5 of the optics spend (0.6 / 2.7 = 0.22). The attach level cancels in revenue (copper_share is calibrated to it); what moves value is the capex growth and the share trend. Fiscal/calendar alignment: Credo's FY n runs May n-1 to April n (FY2026 ended 2026-05-02), so 8 of its 12 months fall in CY n-1; FY n is paired with CY n-1 (FY26 = CY2025, FY27 = CY2026, FY28 = CY2027, FY29 = CY2028), as in the old capture_bps set: Credo ships cables, chips and modules to ODMs and module makers a quarter or two before the racks are capitalised. Variant view: attach rising with AEC penetration at 1.6T and scale-up (e.g. 0.6% -> 0.7% by CY2028) would lift FY29 copper ~17% at the same share; Street CY2027 Big-4 capex ~$930B [src 23] would cut FY28 copper ~14%.
A5: driver:copper_share | B5: base 0.51834; [0.42747, 0.42747, 0.42747] (fraction) | C5: estimate | D5: 3, 22, 12 | F5: FY28-29 held at the FY27 share (Kilian 2026-10-27 17:21Z): copper revenue grows with the Big-4 capex path. FY27 1,880 / 4,398 = 42.75%; FY28 6,480 x 42.747% = $2,770M; FY29 7,980 x 42.747% = $3,411M. Why hold rather than erode: AECs remain the largest business, Credo has 5 hyperscaler relationships, added a new 10% customer and management says AEC penetration within existing customers is rising [src 22]; the reported Marvell/Amphenol 1.6T AEC competition at the top customer (agents 1-5) is carried by the bear case's top_customer_pct cut, so eroding the base as well would count it twice; and with no citable copper TAM the share trend is judgment either way. Variant view: the earlier eroded path (40.25% FY28, 38.90% FY29, which followed the forecasters' median total revenue under the old optical path) applied to the current set gives research target (12m) 208.29 (-6.6%). FY28 total revenue is now $3,861M vs the agents' median $3,700M and StockAnalysis consensus $3.88B [src 3]. ALC is placed in optical (it carries light over fiber with micro-LED emitters), OmniConnect gearboxes (electrical, first revenue FY28 [src 22]) here. Bear: dual-sourcing at the top customer is carried by top_customer_pct, not here.
A6: driver:gm_copper | B6: base 0.68288; [0.69, 0.685, 0.68] (fraction) | C6: estimate | D6: 13, 10, 22, 30 | F6: Not disclosed by line. Base solved from the FY2026 blended non-GAAP gross margin 68.14% ($909.8M / $1,335.1M, Q4 FY26 release reconciliation [src 13]) with optical at 65% and 4.49% of revenue. FY27 blended guide 'broadly consistent with fiscal year 26 levels' [src 22]; Q1 FY27 68.0%, Q2 guide 67-69% [src 10]. Base (0.6814 - 0.04494 x 0.65) / 0.95506 = 68.29%. FY27 69.0%: with optical at 24.8% of revenue (620 / 2,500) at 65%, 0.752 x 0.69 + 0.248 x 0.65 = 68.0% = the guide ('broadly consistent' with 68.1%) and Q1. Copper edges up 0.7pt on 1.6T AEC mix and scale; FY28 68.5% and FY29 68.0% as Marvell 1.6T pricing (15-20% lower, agents 1-5) bites. IP licensing (cost 1.4% of IP revenue in FY25, i.e. ~99% margin [src 30]) sits here but was only 2.9% of FY25 revenue and is no longer split out. Variant view: if optics are as rich as copper the split is ~68%/68% and only the blended level matters; see gm_optical.
A7: driver:optical_tam | B7: base 16.5; [36.3, 63.888, 83.438] ($B) | C7: estimate | D7: 31, 32, 33, 22 | F7: CY2026 16.5 x 2.20 = $36.3B; CY2027 36.3 x 1.76 = $63.888B; CY2028: LightCounting's optics-to-capex ratio (Kilian 2026-10-27 17:21Z, replacing the straight-line interpolation of growth rates): optics sales to the top five cloud providers were 2.7% of their capex in 2025 and 3.1% in 2026, rising to 4.1% by 2031 (Lightwave 2026-03-10 on LightCounting's 'Optics for AI Clusters' [src 33]); linear between 2026 and 2031 (+0.2pt a year) gives 3.3% in 2027 and 3.5% in 2028. CY2028 growth = (Big-4 capex 1,330 / 1,080) x (3.5% / 3.3%) = 1.2315 x 1.0606 = 1.306; 63.888 x 1.306 = $83.438B. Cross-check: the pluggable transceiver market grows from 60 million units in 2026 to 175 million by 2030 (CEO quoting market forecasters, Q1 FY27 call [src 22]), (175/60)^(1/4) - 1 = +30.7% a year in units. CY2026-27 keep LightCounting's published growth rates (+120%, +76%) because they are published figures; the same ratio method would give +57% for 2027 (1,080/733 x 3.3/3.1), so the 2027 step is the richer of the two. Fiscal/calendar alignment: Credo's FY n runs May n-1 to April n (FY2026 ended 2026-05-02), so 8 of its 12 months fall in CY n-1; FY n is paired with CY n-1 (FY26 = CY2025, FY27 = CY2026, FY28 = CY2027, FY29 = CY2028), as in the old capture_bps set: Credo ships cables, chips and modules to ODMs and module makers a quarter or two before the racks are capitalised. Variants: CY2028 tied to Big-4 capex growth alone (+23%, $78.7B) gives research target (12m) 220.69 (-1.0%); the earlier straight-line interpolation of LightCounting growth rates (+62%, $103.5B) gives 232.78 (+4.4%). LightCounting's 2026 growth forecast was raised from +60% (January [src 31]) to +120% (October [src 32]). Vintage gap: our CY2026 $36.3B (16.5 x 2.20, October vintage) is above the $26B for 2026 in LightCounting's January vintage as quoted by POET [src 31] (36.3 / 26 - 1 = +40%); the October +120% is the newer figure, so it is used.
A8: driver:optical_share | B8: base 0.0036364; [0.01708, 0.01708, 0.01708] (fraction) | C8: estimate | D8: 22, 15, 13 | F8: Base: FY2026 optical revenue ~$60M (estimate, segment base row) / $16.5B = 0.364%. FY27: optical revenue $620M vs the guide 'more than $600 million of optical revenue in fiscal 27', with ZeroFlap optics, SiPh PICs and optical DSPs each >$100M [src 22] (see guidance_check: optical revenue FY2027) / CY2026 $36.3B = 1.708%. FY28-29 held at 1.708%. FY27 620 / 36,300 = 1.708%: the >$600M floor x the record (Credo's one annual floor guide on file, FY26 >200%, beat by +2.8%: 600 x 1.028 = $617M), rounded to $620M. FY28-29 held at the FY27 share (Credo grows with LightCounting's market): FY28 63.888 x 1.708% = $1,091M; FY29 83.438 x 1.708% = $1,425M. Support: optical DSP record revenue in Q1, design wins with 2 major players for next-generation ramps in FY28 (possibly late FY27), DustPhotonics PICs ramping throughout FY27 (so a full year of PIC revenue in FY28: our inference, not a management statement), ALC first revenue FY28 [src 22]. Against: no optical revenue disclosure yet; ZeroFlap optics are engaged, not yet ramped. Agents: >$600M delivered (agents 2-5); passing a $1B run-rate is the agents' bull (agent 3), so the base stays near $1.1B in FY28. Variant view: share rising to 2.0% in FY28 (design-win ramps) adds ~$190M FY28 revenue; the bull uses +15%.
A9: driver:gm_optical | B9: base 0.65; [0.65, 0.63, 0.62] (fraction) | C9: estimate | D9: 22, 13, 10 | F9: Not disclosed by line. Evidence: management guides FY27 blended GM 'broadly consistent with fiscal year 26 levels' while optics go from ~5% to ~25% of revenue [src 22]; Q1 FY27 68.0% with the first PIC revenue [src 22]. Component DSPs and PICs are chip-level products; ZeroFlap optics are complete transceivers (hardware, firmware and software [src 22]) and ALC a cable system, which carry more bill of materials. If optics ran far below the company average, the FY27 blend could only stay ~68% with a large rise in copper margin; a flat blend while optics grow 10x implies optics near the average. Base and FY27 65% (DSP- and PIC-heavy mix, 3pt below copper); FY28 63% and FY29 62% as ZeroFlap transceivers and ALC (systems) rise in the optical mix. Blended GM then 68.0% (FY27), 66.9% (FY28: (2,770 x 68.5% + 1,091 x 63%) / 3,861), 66.2% (FY29: (3,411 x 68.0% + 1,425 x 62%) / 4,836) vs the old flat 67.5%. Variant view: transceiver-heavy optics at 60/57/55% give research target (12m) -3.0%; optics held at 65% +1.2%.
A10: driver:opex | B10: base 270.945; [430.0, 640.0, 790.0] ($M) | C10: estimate | D10: 13, 10, 22 | F10: Base: FY2026 non-GAAP operating expenses $270.9M (Q4 FY26 release reconciliation [src 13]). Q1 FY27 $95.2M (above the $86-90M guide), Q2 guide $100-105M [src 10]; FY27 guide "increase approximately 55% year-over-year" [src 22]. FY27 $430M = 270.9 x 1.55 = $419.9M guide x (1 + 1.91% record median overspend (median of the 8 quarters' actual vs guide mid, (0.0186 + 0.0196) / 2); 3 of the last 3 quarters above the range) = $428M, rounded up for Q1 $95.2M + Q2 ~$103M leaving ~$232M for H2. FY28 $640M (+49%) and FY29 $790M (+23%): opex growing a little below revenue (FY26 opex +60.6% vs revenue +205.7% [src 13]; FY27 guide +55% vs >85%). Agents stated net margins, not opex: their FY28 median ~48.5% (agents 2/3/5) at 1% tax and 67.5% GM implies opex of 0.675 - 0.485 / 0.99 = 18.5% of revenue (~$685M on $3,700M) if that margin contains no interest income, or ~19.6% (~$725M) if ~1.1pt of interest income on net cash is netted out first (the engine carries no interest income, so ~19.6% is the like-for-like figure). I depart from it: agents 5 and 1 say the margin haircut is for concentration and Marvell pricing, which this set now carries in top_customer_pct (bear), copper_share and gm_copper; repeating it in opex would count it twice. Effect on the research target (12m) (engine, old structure): opex [430, 725, 900] gives 214.45 vs 221.18 (-3.0%); [430, 685, 900] gives 215.92 (-2.4%). Variant view: R&D for NPO, ALC, OmniConnect and 3.2T could keep opex growth near 55% (FY28 ~$665M).
A11: driver:top_customer_pct | B11: base 0.33; [0.33, 0.33, 0.33] (fraction) | C11: filing | D11: 12, 11, 22 | F11: FY2026 10-K end-customer table: Customer D 33%, Customer B 32%, Customer E 19% (direct-billing basis Customer A 49%) [src 12]. Q1 FY27 10-Q end-customer table: D 33%, C 28%, E 13%, F 10% (direct basis A 43%, 57% of receivables) [src 11]; CFO: 'our largest customer was a third of our revenue at 33%' [src 22]. Base 0.33 (FY26) and held at 0.33 in FY27-29 (Q1 FY27 33%; management expects 3-4 customers above 10% [src 22], i.e. diversification comes through the other customers, which the shares carry). Formula: each segment's revenue = TAM x share x 1000 x (1 - 0.33) / (1 - top_customer_pct). At the base path the factor is 1. Moving the driver to T means the top customer buys less (or more) while every other customer stays as the TAM x share build says: total revenue scales by 0.67 / (1 - T) and the top customer's revenue by T x 0.67 / (0.33 x (1 - T)). Bear: T 0.33 -> 0.21 cuts total revenue 15.2% and the top customer's revenue 46% (a 1.6T AEC dual-source to Marvell at 15-20% lower prices, agents 1-5). The top customer's product mix is not disclosed; the term applies to copper and optical alike (the CFO says these hyperscalers buy more than AECs [src 22]). Variant view: on the direct-billing basis (43%) the same customer-loss story is larger; the end-customer basis is used because the sourcing decision is the end customer's.
A12: base.revenue | B12: 1335.116 | C12: reported | D12: 12, 13 | E12: F3 | F12: FY2026 (52 weeks to 2026-05-02) revenue $1,335,116K.
A13: segment_build[Copper (AECs, electrical ICs, IP)].base_revenue | B13: 1275.116 | C13: estimate | D13: 12, 30, 22 | E13: F3, F2 | F13: Credo files one segment and no product-line split [src 12]. FY2026 copper = total $1,335.1M less optical ~$60M = $1,275.1M (95.5%). Bounds: the FY26 10-K says the AEC ramp 'contributed over 99% of the increase in revenue' ($898.3M) [src 12], so non-AEC revenue rose at most ~$9M in FY26; the FY25 10-K says AECs were over 95% of the $267.1M product-sales increase and FY24 product sales were $145.0M, with product engineering services $12.1M and IP license $12.5M in FY25 [src 30]. So FY26 non-AEC revenue (optical DSPs, electrical ICs, services, IP) was at most ~$192M (145.0 + 13.4 + 24.6 + 9.0) and AECs at least ~$1,143M. AECs remain the largest business [src 22]. Copper here = AECs + retimers/line-card PHYs/SerDes chiplets + product engineering services + IP licensing.
A14: segment_build[Optical (DSPs, SiPh PICs, ZF optics, ALC)].base_revenue | B14: 60.0 | C14: estimate | D14: 12, 30, 22 | E14: F3 | F14: FY2026 optical ~$60M (4.5% of revenue): optical DSPs were the only optical line in volume in FY26 (ZeroFlap optics early; SiPh PIC revenue began in Q1 FY27 after the DustPhotonics acquisition closed 2026-05-28 [src 11, 22]). Optical DSPs share the <=~$192M non-AEC pool (see copper row) with retimers, line-card PHYs, chiplets, services and IP; ~1/3 of that pool is taken (estimate). Not disclosed; flagged.
A15: years.tax_rate FY2027 | B15: 0.01 | C15: estimate | D15: 13, 10 | E15: F64, F68 | F15: Non-GAAP effective tax: FY26 (669.3 pretax = 638.8 non-GAAP operating income + 30.4 other income; NI 661.5) = 1.15% [src 13]; Q1 FY27 (230.6 + 8.1 other income = 238.7; NI 236.3) = 1.0% [src 10, 22].
A16: years.tax_rate FY2028-FY2029 | B16: 0.15 | C16: estimate | D16: 12 | F16: 10-K risk factors: "We expect we may be subject to legislation based on the OECD's 15% global minimum tax regime in our fiscal year 2028" [src 12]. Set at the 15% minimum (estimate; US income already taxed at 21% and HK/Cayman profits topped up). Judgment card for Kilian: ~1% (agents, apparently consensus) gives research target (12m) +11%.
A17: years.da_pct_rev | B17: 0.025 | C17: estimate | D17: 12 | E17: F36, F3 | F17: FY26 D&A $34.6M / revenue $1,335.1M = 2.6%; rounded to 2.5% as revenue scales (cash-flow only: EBIT is non-GAAP).
A18: years.capex_pct_rev | B18: 0.04 | C18: estimate | D18: 12, 11 | E18: F57, F60, F6 | F18: FY26 capex $57.3M / $1,335.1M = 4.3%; TTM to 2026-08-01 $61.8M / $1,591.0M = 3.9%. 4% (fabless).
A19: years.nwc_pct_incr_rev | B19: 0.25 | C19: estimate | D19: 13, 11 | F19: FY26 working capital (receivables +71.2, inventories +160.8, other current assets +43.6, less payables +51.2, accrued and other current liabilities +38.2) = +$186.2M on +$898.3M revenue = 20.7% [src 13]; Q1 FY27 receivables +54.5, inventories +61.5 (10-Q cash flow statement) on +$42M sequential revenue as inventory built for the H2 ramp [src 11]. 25% keeps conversion weak through FY27-28 as agents 1-5 argue; horizon net cash comes out ~$1.97B vs the agents' ~$1.8B (agents 1/2/4/5; agent_3 $1.7B).
A20: years.sbc_pct_rev | B20: 0.14 | C20: reported | D20: 12, 11 | E20: F43, F47 | F20: FY26 SBC $182.6M / $1,335.1M = 13.7%; Q1 FY27 $88.0M / $479.0M = 18.4%. Shown for reference: with ebit_basis adjusted and sbc_treatment dilution, SBC enters through the share count.
A21: years.other_uses FY2027 | B21: 102.4 | C21: reported | D21: 11 | F21: 10-Q: Credo "will pay $102.4 million of refundable deposits within fiscal 2027" under a manufacturing supply capacity reservation agreement with an assembly subcontractor [src 11]. Refundable, but out of cash before the horizon.
A22: balance.net_debt | B22: -764.3 | C22: reported | D22: 11, 10 | E22: F76, F77, F80 | F22: Cash $466.9M + short-term investments $297.4M at 2026-08-01, no borrowings on the balance sheet (after the $735.6M DustPhotonics outlay) [src 11]; net debt = -$764.3M.
A23: balance.interest_rate | B23: 0.04 | C23: estimate | D23: 13 | F23: FY26 other income $30.4M on average cash and investments of ~$0.9B (~3.4-4%); not used while net cash is positive (the engine adds no interest income), which understates EPS by ~1% of revenue.
A24: shares.diluted_now | B24: 200.0 | C24: estimate | D24: 22, 10 | E24: F33, F79 | F24: Q2 FY27 "diluted weighted average share count to be approximately 200 million shares" [src 22]; Q1 FY27 non-GAAP weighted-average diluted shares 197.5M (197,505K, release reconciliation) [src 10]; includes DustPhotonics shares. Management's stated Q2 share count, used as today's count (estimate).
A25: shares.annual_change | B25: 0.015 | C25: estimate | D25: 11, 34 | E25: F47 | F25: SBC ~$352M a year (Q1 FY27 $88.0M x 4) / ~$147 = ~2.4M shares (1.2%) plus part of the up to ~3.21M DustPhotonics earn-out shares, issued on financial milestones whose timing is not disclosed (Credo release [src 34]); ~0.6M a year assumed in the window (judgment), no buyback: 2.4M + 0.6M = 3.0M / 200M = +1.5% a year. Variant: all 3.21M issued within the year gives +2.8% -> 205.6M at the horizon (200 x 1.028; (2.4M + 3.21M) / 200M = 2.8%) (agents 199-205M, median 200M).
A26: horizon_multiples[P/E].value | B26: 23.5 | C26: estimate | D26: 27 | E26: ALAB.pe_ntm, MRVL.pe_ntm, AVGO.pe_ntm, COHR.pe_ntm, LITE.pe_ntm, AAOI.pe_ntm, MTSI.pe_ntm, FN.pe_ntm, CIEN.pe_ntm, ANET.pe_ntm, RMBS.pe_ntm | F26: Agents' median P/E on Sep-2027 NTM EPS: 23.5x (agent_1 23.5, agent_2 24, agent_3 21, agent_4 22, agent_5 24). Peer median P/E NTM 34.5x across 11 filing-based peers (36.7x without thin-coverage AAOI and RMBS) [src 27]; 23.5x = -32%, for customer concentration (43% direct customer, 84% top four [src 11]), Marvell 1.6T AEC pricing and slower growth after FY28. CRDO itself trades ~18.6x the StockAnalysis FY27/FY28 blend [src 3] and ~22x on Zacks consensus EPS (FY27 $5.02 / FY28 $8.30 via Nasdaq.com [src 28]); Zacks does not state whether that EPS is GAAP or adjusted (its FY27 $5.02 is ~20% below the StockAnalysis non-GAAP $6.31), so the ~22x is on an unstated basis, not comparable with the non-GAAP 18.6x, and is shown for reference only.
A27: horizon_multiples[P/E].weight | B27: 0.7 | C27: judgment | F27: Agents weighted P/E 0.45-0.5, EV/sales 0.2-0.25, DCF 0.25-0.3. The DCF leg is gone (no-DCF rule, Kilian 2026-10-21); P/E and EV/sales keep their ratio: 0.5 / (0.5 + 0.2) = 0.71 -> 0.7. Untested weight.
A28: horizon_multiples[EV/sales].value | B28: 11.0 | C28: estimate | F28: Agents' median EV/NTM sales 11x (agent_1 10x, agent_2 11x, agent_3 11x, agent_4 9x, agent_5 11.5x). No peer NTM sales median: the peer snapshots carry EPS only (flag).
A29: horizon_multiples[EV/sales].weight | B29: 0.3 | C29: judgment | F29: Rest of the multiple weight (see P/E weight).
A30: scenario_vol | B30: 0.25 | C30: judgment | F30: Within-scenario spread for a 2.9-beta name with ~96% realised volatility (priors); 0.15 default is too tight for a stock that fell 52% peak to trough in 2026.
A31: scenarios | B31: bear 0.25 / base 0.5 / bull 0.25 | C31: estimate | D31: 11, 22 | F31: Agents' scenario probabilities: bear 0.27/0.33/0.25/0.25/0.25 (median 0.25), base 0.48/0.45/0.5/0.5/0.5 (0.5), bull 0.25/0.22/0.25/0.25/0.25 (0.25). Driver moves restate the agents' stories: bear = top_customer_pct add -0.12 (top customer revenue -46%), TAMs -10%, gm -3pt both, P/E -8; bull = optical_share +15%, copper_share +5%, top_customer_pct +0.02, TAMs +10%, gm +0.5pt both, P/E +3.5 (see scenarios.*.story).
A33: # | B33: Source | C33: Date | D33: Link
A34: 1 | B34: Credo Technology Crashed for 3 Months: This Wall Street Pro Says It's About to Double - 24/7 Wall St. | C34: 2026-09-21 | D34: https://247wallst.com/investing/2026/09/21/credo-technology-crashed-for-3-months-this-wall-street-pro-says-its-about-to-double/
A35: 2 | B35: Credo Is Entering Its Hardest Test - Seeking Alpha (HTTP 403; its consensus figures could not be verified and are not used) | C35: 2026-09 | D35: https://seekingalpha.com/article/4940940-credo-is-entering-its-hardest-test
A36: 3 | B36: CRDO Stock Forecast & Price Targets - StockAnalysis (S&P Global consensus: FY27 revenue $2.50B / EPS $6.31; next year (FY28) revenue $3.88B / EPS $9.71; page updated 2026-10-05) | C36: 2026-10-26 | D36: https://stockanalysis.com/stocks/crdo/forecast/
A37: 4 | B37: Credo Technology Group Holding Ltd (CRDO) - Quantitative Forecast & Factor Scores - AL Capital Advisory | C37: 2026-09-26 | D37: https://alcapitaladvisory.com/research/equities/crdo.html
A38: 5 | B38: Credo Technology Group Holding Ltd earnings date - TipRanks | C38: 2026-09 | D38: https://www.tipranks.com/stocks/crdo/earnings
A39: 6 | B39: Why is Credo Technology stock rallying today? (Mizuho note) - Investing.com | C39: 2026-09-25 | D39: https://ca.investing.com/news/stock-market-news/why-is-credo-technology-stock-rallying-today-93CH-4846693
A40: 7 | B40: A 9-Day Winning Streak Has Credo Technology Stock Up 41% - Trefis | C40: 2026-09-26 | D40: https://www.trefis.com/stock/crdo/articles/616737/a-9-day-winning-streak-has-credo-technology-stock-up-41/2026-09-26
A41: 8 | B41: 6 Hyperscalers Are Projected to Spend $1.3 Trillion on Capex in 2027 - Motley Fool | C41: 2026-09-06 | D41: https://www.fool.com/investing/2026/09/06/hyperscalers-driving-ai-capex-cash-flow/
A42: 9 | B42: Moody's: Hyperscaler capex forecasts close in on $1trn by 2027 - DCD (HTTP 403; not read, not used) | C42: 2026 | D42: https://www.datacenterdynamics.com/en/news/moodys-hyperscaler-capex-forecasts-marked-up-by-85bn-to-close-in-on-1trn-by-2027/
A43: 10 | B43: Credo Reports First Quarter of Fiscal Year 2027 Financial Results (8-K Ex-99.1) | C43: 2026-09-01 | D43: https://www.sec.gov/Archives/edgar/data/0001807794/000162828026059795/credoq12027ex-991.htm
A44: 11 | B44: Credo Form 10-Q for the quarter ended 2026-08-01 | C44: 2026-09-02 | D44: https://www.sec.gov/Archives/edgar/data/1807794/000162828026060111/crdo-20260801.htm
A45: 12 | B45: Credo Form 10-K for fiscal 2026 (ended 2026-05-02) | C45: 2026-06-15 | D45: https://www.sec.gov/Archives/edgar/data/1807794/000162828026043303/crdo-20260502.htm
... A67: 34 | B67: Credo press release, 'Credo Agrees to Acquire DustPhotonics': $750M cash and ~0.92M shares upfront, plus up to ~3.21M additional shares on certain financial milestones | C67: 2026-04-13 | D67: https://investors.credosemi.com/news-events/news/news-details/2026/Credo-Agrees-to-Acquire-DustPhotonics-Accelerating-Expansion-into-Silicon-Photonics-and-Next-Generation-Optical-Connectivity/default.aspx
A69: Fact id | B69: Figure | C69: Value | D69: Filing
A70: F1 | B70: revenue FY ending 2024-04-27 (us-gaap:RevenueFromContractWithCustomerExcludingAssessedTax) | C70: 192970000 | D70: https://www.sec.gov/Archives/edgar/data/1807794/000162828026043303/
A71: F2 | B71: revenue FY ending 2025-05-03 (us-gaap:RevenueFromContractWithCustomerExcludingAssessedTax) | C71: 436775000 | D71: https://www.sec.gov/Archives/edgar/data/1807794/000162828026043303/
A72: F3 | B72: revenue FY ending 2026-05-02 (us-gaap:RevenueFromContractWithCustomerExcludingAssessedTax) | C72: 1335116000 | D72: https://www.sec.gov/Archives/edgar/data/1807794/000162828026043303/
A73: F4 | B73: revenue YTD 2026-05-03 to 2026-08-01 | C73: 479003000 | D73: https://www.sec.gov/Archives/edgar/data/1807794/000162828026060111/
A74: F5 | B74: revenue prior-year YTD 2025-05-04 to 2025-08-02 | C74: 223074000 | D74: https://www.sec.gov/Archives/edgar/data/1807794/000162828026060111/
A75: F6 | B75: revenue TTM to 2026-08-01 | C75: 1591045000
A76: F7 | B76: revenue quarter 2026-05-03 to 2026-08-01 | C76: 479003000 | D76: https://www.sec.gov/Archives/edgar/data/1807794/000162828026060111/
A77: F8 | B77: operating_income FY ending 2024-04-27 (us-gaap:OperatingIncomeLoss) | C77: -37058000 | D77: https://www.sec.gov/Archives/edgar/data/1807794/000162828026043303/
A78: F9 | B78: operating_income FY ending 2025-05-03 (us-gaap:OperatingIncomeLoss) | C78: 37124000 | D78: https://www.sec.gov/Archives/edgar/data/1807794/000162828026043303/
A79: F10 | B79: operating_income FY ending 2026-05-02 (us-gaap:OperatingIncomeLoss) | C79: 445005000 | D79: https://www.sec.gov/Archives/edgar/data/1807794/000162828026043303/
A80: F11 | B80: operating_income YTD 2026-05-03 to 2026-08-01 | C80: 120700000 | D80: https://www.sec.gov/Archives/edgar/data/1807794/000162828026060111/
A81: F12 | B81: operating_income prior-year YTD 2025-05-04 to 2025-08-02 | C81: 60742000 | D81: https://www.sec.gov/Archives/edgar/data/1807794/000162828026060111/
A82: F13 | B82: operating_income TTM to 2026-08-01 | C82: 504963000
A83: F14 | B83: operating_income quarter 2026-05-03 to 2026-08-01 | C83: 120700000 | D83: https://www.sec.gov/Archives/edgar/data/1807794/000162828026060111/
A84: F15 | B84: net_income FY ending 2024-04-27 (us-gaap:NetIncomeLoss) | C84: -28369000 | D84: https://www.sec.gov/Archives/edgar/data/1807794/000162828026043303/
A85: F16 | B85: net_income FY ending 2025-05-03 (us-gaap:NetIncomeLoss) | C85: 52183000 | D85: https://www.sec.gov/Archives/edgar/data/1807794/000162828026043303/
A86: F17 | B86: net_income FY ending 2026-05-02 (us-gaap:NetIncomeLoss) | C86: 472279000 | D86: https://www.sec.gov/Archives/edgar/data/1807794/000162828026043303/
A87: F18 | B87: net_income YTD 2026-05-03 to 2026-08-01 | C87: 129425000 | D87: https://www.sec.gov/Archives/edgar/data/1807794/000162828026060111/
A88: F19 | B88: net_income prior-year YTD 2025-05-04 to 2025-08-02 | C88: 63399000 | D88: https://www.sec.gov/Archives/edgar/data/1807794/000162828026060111/
A89: F20 | B89: net_income TTM to 2026-08-01 | C89: 538305000
A90: F21 | B90: net_income quarter 2026-05-03 to 2026-08-01 | C90: 129425000 | D90: https://www.sec.gov/Archives/edgar/data/1807794/000162828026060111/
A91: F22 | B91: eps_diluted FY ending 2024-04-27 (us-gaap:EarningsPerShareDiluted) | C91: -0.18 | D91: https://www.sec.gov/Archives/edgar/data/1807794/000162828026043303/
A92: F23 | B92: eps_diluted FY ending 2025-05-03 (us-gaap:EarningsPerShareDiluted) | C92: 0.29 | D92: https://www.sec.gov/Archives/edgar/data/1807794/000162828026043303/
A93: F24 | B93: eps_diluted FY ending 2026-05-02 (us-gaap:EarningsPerShareDiluted) | C93: 2.51 | D93: https://www.sec.gov/Archives/edgar/data/1807794/000162828026043303/
A94: F25 | B94: eps_diluted YTD 2026-05-03 to 2026-08-01 | C94: 0.67 | D94: https://www.sec.gov/Archives/edgar/data/1807794/000162828026060111/
A95: F26 | B95: eps_diluted prior-year YTD 2025-05-04 to 2025-08-02 | C95: 0.34 | D95: https://www.sec.gov/Archives/edgar/data/1807794/000162828026060111/
A96: F27 | B96: eps_diluted quarter 2026-05-03 to 2026-08-01 | C96: 0.67 | D96: https://www.sec.gov/Archives/edgar/data/1807794/000162828026060111/
A97: F28 | B97: diluted_shares_wavg FY ending 2024-04-27 (us-gaap:WeightedAverageNumberOfDilutedSharesOutstanding) | C97: 155091000 | D97: https://www.sec.gov/Archives/edgar/data/1807794/000162828026043303/
A98: F29 | B98: diluted_shares_wavg FY ending 2025-05-03 (us-gaap:WeightedAverageNumberOfDilutedSharesOutstanding) | C98: 181158000 | D98: https://www.sec.gov/Archives/edgar/data/1807794/000162828026043303/
A99: F30 | B99: diluted_shares_wavg FY ending 2026-05-02 (us-gaap:WeightedAverageNumberOfDilutedSharesOutstanding) | C99: 188232000 | D99: https://www.sec.gov/Archives/edgar/data/1807794/000162828026043303/
A100: F31 | B100: diluted_shares_wavg YTD 2026-05-03 to 2026-08-01 | C100: 194378000 | D100: https://www.sec.gov/Archives/edgar/data/1807794/000162828026060111/
A101: F32 | B101: diluted_shares_wavg prior-year YTD 2025-05-04 to 2025-08-02 | C101: 184577000 | D101: https://www.sec.gov/Archives/edgar/data/1807794/000162828026060111/
... A107: F38 | B107: d_and_a prior-year YTD 2025-05-04 to 2025-08-02 | C107: 5460000 | D107: https://www.sec.gov/Archives/edgar/data/1807794/000162828026060111/
A108: F39 | B108: d_and_a TTM to 2026-08-01 | C108: 37783000
A109: F40 | B109: d_and_a quarter 2026-05-03 to 2026-08-01 | C109: 8606000 | D109: https://www.sec.gov/Archives/edgar/data/1807794/000162828026060111/
A110: F41 | B110: sbc FY ending 2024-04-27 (us-gaap:ShareBasedCompensation) | C110: 39022000 | D110: https://www.sec.gov/Archives/edgar/data/1807794/000162828026043303/
A111: F42 | B111: sbc FY ending 2025-05-03 (us-gaap:ShareBasedCompensation) | C111: 77355000 | D111: https://www.sec.gov/Archives/edgar/data/1807794/000162828026043303/
A112: F43 | B112: sbc FY ending 2026-05-02 (us-gaap:ShareBasedCompensation) | C112: 182638000 | D112: https://www.sec.gov/Archives/edgar/data/1807794/000162828026043303/
A113: F44 | B113: sbc YTD 2026-05-03 to 2026-08-01 | C113: 87979000 | D113: https://www.sec.gov/Archives/edgar/data/1807794/000162828026060111/
A114: F45 | B114: sbc prior-year YTD 2025-05-04 to 2025-08-02 | C114: 35455000 | D114: https://www.sec.gov/Archives/edgar/data/1807794/000162828026060111/
A115: F46 | B115: sbc TTM to 2026-08-01 | C115: 235162000
A116: F47 | B116: sbc quarter 2026-05-03 to 2026-08-01 | C116: 87979000 | D116: https://www.sec.gov/Archives/edgar/data/1807794/000162828026060111/
A117: F48 | B117: cfo FY ending 2024-04-27 (us-gaap:NetCashProvidedByUsedInOperatingActivities) | C117: 32737000 | D117: https://www.sec.gov/Archives/edgar/data/1807794/000162828026043303/
A118: F49 | B118: cfo FY ending 2025-05-03 (us-gaap:NetCashProvidedByUsedInOperatingActivities) | C118: 65083000 | D118: https://www.sec.gov/Archives/edgar/data/1807794/000162828026043303/
A119: F50 | B119: cfo FY ending 2026-05-02 (us-gaap:NetCashProvidedByUsedInOperatingActivities) | C119: 464292000 | D119: https://www.sec.gov/Archives/edgar/data/1807794/000162828026043303/
A120: F51 | B120: cfo YTD 2026-05-03 to 2026-08-01 | C120: 90231000 | D120: https://www.sec.gov/Archives/edgar/data/1807794/000162828026060111/
A121: F52 | B121: cfo prior-year YTD 2025-05-04 to 2025-08-02 | C121: 54168000 | D121: https://www.sec.gov/Archives/edgar/data/1807794/000162828026060111/
A122: F53 | B122: cfo TTM to 2026-08-01 | C122: 500355000
A123: F54 | B123: cfo quarter 2026-05-03 to 2026-08-01 | C123: 90231000 | D123: https://www.sec.gov/Archives/edgar/data/1807794/000162828026060111/
A124: F55 | B124: capex FY ending 2024-04-27 (us-gaap:PaymentsToAcquirePropertyPlantAndEquipment) | C124: 15652000 | D124: https://www.sec.gov/Archives/edgar/data/1807794/000162828026043303/
A125: F56 | B125: capex FY ending 2025-05-03 (us-gaap:PaymentsToAcquirePropertyPlantAndEquipment) | C125: 36061000 | D125: https://www.sec.gov/Archives/edgar/data/1807794/000162828026043303/
A126: F57 | B126: capex FY ending 2026-05-02 (us-gaap:PaymentsToAcquirePropertyPlantAndEquipment) | C126: 57296000 | D126: https://www.sec.gov/Archives/edgar/data/1807794/000162828026043303/
A127: F58 | B127: capex YTD 2026-05-03 to 2026-08-01 | C127: 7282000 | D127: https://www.sec.gov/Archives/edgar/data/1807794/000162828026060111/
A128: F59 | B128: capex prior-year YTD 2025-05-04 to 2025-08-02 | C128: 2821000 | D128: https://www.sec.gov/Archives/edgar/data/1807794/000162828026060111/
A129: F60 | B129: capex TTM to 2026-08-01 | C129: 61757000
...
