Workbook

Sheet Summary
A1: AMZN standard model (trial) · research run 2026-10-23
A2: The supervisor's reconciled assumption set as a live model. Trial: shown beside the blended page target, not used for trade levels until its weight is decided. Edit blue cells on Model (drivers) and Valuation (assumptions).
A3: Price target box | B3: Value
A4: Live price | B4: =IFERROR(GOOGLEFINANCE("AMZN","price"),Valuation!$B$67)
A5: Price as of | B5: =NOW()
A6: Model target (12-month median) | B6: =Distribution!$B$13
A7: Upside to model target from live price | B7: =B6/B4-1
A8: Research target (12m) (no scenario deltas) | B8: =Valuation!$D$7
A9: Probability-weighted mean | B9: =Distribution!$B$10
A10: 10th percentile | B10: =Distribution!$B$14
A11: 25th percentile | B11: =Distribution!$B$15
A12: 75th percentile | B12: =Distribution!$B$16
A13: 90th percentile | B13: =Distribution!$B$17
A14: Target date | B14: =Valuation!$B$45
A15: Price at the run | B15: =Valuation!$B$67
A16: Blended page target (options 67% + agents 33%, not live) | B16: 265.6556
A17: Supervisor research target (12m) (its own methods) | B17: 266.05
A18: Thesis break price (supervisor) | B18: 188
A19: Supervisor confidence | B19: low
A21: Key estimates | B21: FY2025A | C21: =Model!E5 | D21: =Model!F5
A22: Net sales | B22: =IF(Model!D24="","",Model!D24) | C22: =Model!E24 | D22: =Model!F24
A23: % YoY | B23: =IF(Model!D25="","",Model!D25) | C23: =Model!E25 | D23: =Model!F25
A24: Pretax margin | B24: =IF(Model!D35="","",Model!D35) | C24: =Model!E35 | D24: =Model!F35
A25: Diluted EPS (model) | B25: =IF(Model!D42="","",Model!D42) | C25: =Model!E42 | D25: =Model!F42
A26: % YoY | B26: =IF(Model!D43="","",Model!D43) | C26: =Model!E43 | D26: =Model!F43
A27: Free cash flow to firm | B27: =IF(Model!D52="","",Model!D52) | C27: =Model!E52 | D27: =Model!F52
A28: Consensus: EPS (GAAP (consensus; excludes mark-to-market) | D28: 10.51
A30: Valuation method | B30: Value per share | C30: Weight
A31: =Valuation!A4 | B31: =Valuation!D4 | C31: =Valuation!E4
A32: =Valuation!A5 | B32: =Valuation!D5 | C32: =Valuation!E5
A33: =Valuation!A6 | B33: =Valuation!D6 | C33: =Valuation!E6
A35: Scenario | B35: Probability | C35: Value at target date | D35: What has to happen
A36: =Distribution!A4 | B36: =Distribution!B4 | C36: =Distribution!C4 | D36: =Distribution!D4
A37: =Distribution!A5 | B37: =Distribution!B5 | C37: =Distribution!C5 | D37: =Distribution!D5
A38: =Distribution!A6 | B38: =Distribution!B6 | C38: =Distribution!C6 | D38: =Distribution!D6
A40: Price at target date | B40: Probability above
A41: =ROUND(Valuation!$B$67*0.7,0) | B41: =SUMPRODUCT(Distribution!$B$4:$B$6,1-NORMSDIST((LN(A41)-LN(Distribution!$C$4:$C$6))/Distribution!$B$9))
A42: =ROUND(Valuation!$B$67*0.8,0) | B42: =SUMPRODUCT(Distribution!$B$4:$B$6,1-NORMSDIST((LN(A42)-LN(Distribution!$C$4:$C$6))/Distribution!$B$9))
A43: =ROUND(Valuation!$B$67*0.9,0) | B43: =SUMPRODUCT(Distribution!$B$4:$B$6,1-NORMSDIST((LN(A43)-LN(Distribution!$C$4:$C$6))/Distribution!$B$9))
A44: =ROUND(Valuation!$B$67*1.0,0) | B44: =SUMPRODUCT(Distribution!$B$4:$B$6,1-NORMSDIST((LN(A44)-LN(Distribution!$C$4:$C$6))/Distribution!$B$9))
A45: =ROUND(Valuation!$B$67*1.1,0) | B45: =SUMPRODUCT(Distribution!$B$4:$B$6,1-NORMSDIST((LN(A45)-LN(Distribution!$C$4:$C$6))/Distribution!$B$9))
A46: =ROUND(Valuation!$B$67*1.2,0) | B46: =SUMPRODUCT(Distribution!$B$4:$B$6,1-NORMSDIST((LN(A46)-LN(Distribution!$C$4:$C$6))/Distribution!$B$9))
A47: =ROUND(Valuation!$B$67*1.3,0) | B47: =SUMPRODUCT(Distribution!$B$4:$B$6,1-NORMSDIST((LN(A47)-LN(Distribution!$C$4:$C$6))/Distribution!$B$9))
A48: =ROUND(Valuation!$B$67*1.5,0) | B48: =SUMPRODUCT(Distribution!$B$4:$B$6,1-NORMSDIST((LN(A48)-LN(Distribution!$C$4:$C$6))/Distribution!$B$9))
A50: Model checks | B50: Status
A51: Scenario probabilities sum to 100% | B51: =IF(ABS(Distribution!B8-1)<0.005,"ok","FLAG: "&TEXT(Distribution!B8,"0.0%"))
A52: WACC exceeds terminal growth by 1 point or more | B52: =IF('Calc - research target (12m)'!B55="ok","ok","FLAG")
A53: Projection runs a full year past the target date | B53: =IF('Calc - research target (12m)'!B56="ok","ok","FLAG")
A54: Method weights add up to more than zero | B54: =IF(SUM(Valuation!E4:E6)>0,"ok","FLAG")
A55: Terminal value under 85% of the DCF | B55: =IF('Calc - research target (12m)'!B46<0.85,"ok","note: "&TEXT('Calc - research target (12m)'!B46,"0%")&" of the DCF is terminal value")
A56: Segment base revenues tie to the last reported net sales (within 2%) | B56: =IF(ABS(Valuation!$B$101/Valuation!$B$50-1)<=0.02,"ok","FLAG")
A57: Matches the engine run at publication (target, research target (12m)) | B57: =IF(AND(ABS(Distribution!$B$13-258.6785)<0.01,ABS(Valuation!$D$7-266.0514)<0.01),"ok","inputs edited since publication")
A58: All checks | B58: =IF(COUNTIF(B51:B57,"ok")=7,"all ok",7-COUNTIF(B51:B57,"ok")&" to look at")

Sheet Model
A1: AMZN: annual model, base case
A2: (M of US dollars except per share; fiscal years named by the calendar year they end in)
A3: Blue = input · black = formula · green = link to another tab · actuals from SEC filings (fact ids in the last column, links on Sources)
A5: Fiscal year | B5: FY2023A | C5: FY2024A | D5: FY2025A | E5: FY2026E | F5: FY2027E | G5: FY2028E | H5: Source / note
A6: Period end | B6: 45291 | C6: 45657 | D6: 46022 | E6: =IF(DAY(Valuation!$B$49+1)=1,EOMONTH(Valuation!$B$49,12*E7),EDATE(Valuation!$B$49,12*E7)) | F6: =IF(DAY(Valuation!$B$49+1)=1,EOMONTH(Valuation!$B$49,12*F7),EDATE(Valuation!$B$49,12*F7)) | G6: =IF(DAY(Valuation!$B$49+1)=1,EOMONTH(Valuation!$B$49,12*G7),EDATE(Valuation!$B$49,12*G7))
A7: Projection year | B7: -2 | C7: -1 | D7: 0 | E7: 1 | F7: 2 | G7: 3
A10: Segment build (blue = input: revenue growth and EBIT margin by segment and year)
A11: AWS | D11: =Valuation!$B$99 | E11: =Valuation!$B$99*(1+E12) | F11: =E11*(1+F12) | G11: =F11*(1+G12)
A12: Revenue growth | E12: 0.34992415 | F12: 0.35009192 | G12: 0.25209242
A13: Segment EBIT | E13: =E11*E14 | F13: =F11*F14 | G13: =G11*G14
A14: EBIT margin | E14: 0.35653922 | F14: 0.33059331 | G14: 0.31842317
A15: North America + International | D15: =Valuation!$B$100 | E15: =Valuation!$B$100*(1+E16) | F15: =E15*(1+F16) | G15: =F15*(1+G16)
A16: Revenue growth | E16: 0.13097268 | F16: 0.095405096 | G16: 0.09407798
A17: Segment EBIT | E17: =E15*E18 | F17: =F15*F18 | G17: =G15*G18
A18: EBIT margin | E18: 0.065627402 | F18: 0.071738884 | G18: 0.077246006
A19: Total segment revenue (= net sales) | D19: =D11+D15 | E19: =E11+E15 | F19: =F11+F15 | G19: =G11+G15 | H19: base revenues on Valuation (segment build); net sales = this total
A20: Total segment EBIT | E20: =E13+E17 | F20: =F13+F17 | G20: =G13+G17
A21: Corporate / unallocated EBIT (blue = input) | E21: 0 | F21: =E21 | G21: =F21 | H21: years[].corporate_ebit; EBIT = total segment EBIT + corporate
A23: Sales
A24: Net sales | B24: 574785 | C24: 637959 | D24: 716924 | E24: =E19 | F24: =F19 | G24: =G19 | H24: SEC XBRL F1, F2, F3
A25: % YoY | C25: =IF(OR(C24="",B24="",B24=0),"",C24/B24-1) | D25: =IF(OR(D24="",C24="",C24=0),"",D24/C24-1) | E25: =E24/Valuation!$B$50-1 | F25: =F24/E24-1 | G25: =G24/F24-1
A27: Operating profit
A28: EBIT (operating income) | E28: =E20+E21 | F28: =F20+F21 | G28: =G20+G21
A29: EBIT margin | E29: =E28/E24 | F29: =F28/F24 | G29: =G28/G24
A30: D&A | B30: 48663 | C30: 52795 | D30: 65756 | E30: =E24*E64 | F30: =F24*F64 | G30: =G24*G64 | H30: SEC XBRL F34, F35, F36
A31: EBITDA | E31: =E28+E30 | F31: =F28+F30 | G31: =G28+G30
A32: EBITDA margin | E32: =E31/E24 | F32: =F31/F24 | G32: =G31/G24
A33: Net interest income / (expense) | E33: =-Valuation!$B$58*Valuation!$B$56 | F33: =-Valuation!$B$58*E58 | G33: =-Valuation!$B$58*F58 | H33: rate x prior year-end net debt (memo roll)
A34: Pretax income | B34: 37557 | C34: 68614 | D34: 97311 | E34: =E28+E33 | F34: =F28+F33 | G34: =G28+G33 | H34: SEC XBRL F76, F77, F78
A35: Pretax margin | B35: =B34/B24 | C35: =C34/C24 | D35: =D34/D24 | E35: =E34/E24 | F35: =F34/F24 | G35: =G34/G24
A36: Income tax | B36: 7120 | C36: 9265 | D36: 19087 | E36: =E34*E63 | F36: =F34*F63 | G36: =G34*G63 | H36: SEC XBRL F69, F70, F71
A37: Effective tax rate | B37: =B36/B34 | C37: =C36/C34 | D37: =D36/D34 | E37: =E36/E34 | F37: =F36/F34 | G37: =G36/G34
A38: Net income | B38: 30425 | C38: 59248 | D38: 77670 | E38: =E34-E36 | F38: =F34-F36 | G38: =G34-G36 | H38: SEC XBRL F15, F16, F17
A39: % YoY | C39: =IF(OR(C38="",B38="",B38=0),"",C38/B38-1) | D39: =IF(OR(D38="",C38="",C38=0),"",D38/C38-1) | E39: =IF(OR(D38="",D38=0),"",E38/D38-1) | F39: =IF(OR(E38="",E38=0),"",F38/E38-1) | G39: =IF(OR(F38="",F38=0),"",G38/F38-1)
A40: Diluted shares (M, average) | B40: 10492 | C40: 10721 | D40: 10827 | E40: =Valuation!$B$60*(1+Valuation!$B$62)^(E7-0.5-((Valuation!$B$61-Valuation!$B$49)/365.25)) | F40: =Valuation!$B$60*(1+Valuation!$B$62)^(F7-0.5-((Valuation!$B$61-Valuation!$B$49)/365.25)) | G40: =Valuation!$B$60*(1+Valuation!$B$62)^(G7-0.5-((Valuation!$B$61-Valuation!$B$49)/365.25)) | H40: diluted count rolled at the annual change to mid-year
A41: % YoY | C41: =IF(OR(C40="",B40="",B40=0),"",C40/B40-1) | D41: =IF(OR(D40="",C40="",C40=0),"",D40/C40-1) | E41: =IF(OR(D40="",D40=0),"",E40/D40-1) | F41: =IF(OR(E40="",E40=0),"",F40/E40-1) | G41: =IF(OR(F40="",F40=0),"",G40/F40-1)
A42: Diluted EPS | B42: 2.9 | C42: 5.53 | D42: 7.17 | E42: =E38/E40 | F42: =F38/F40 | G42: =G38/G40 | H42: SEC XBRL F22, F23, F24
A43: % YoY | C43: =IF(OR(C42="",B42="",B42=0),"",C42/B42-1) | D43: =IF(OR(D42="",C42="",C42=0),"",D42/C42-1) | E43: =IF(OR(D42="",D42=0),"",E42/D42-1) | F43: =IF(OR(E42="",E42=0),"",F42/E42-1) | G43: =IF(OR(F42="",F42=0),"",G42/F42-1)
A45: Cash flow
A46: NOPAT (EBIT x (1 - tax)) | E46: =E28*(1-E63) | F46: =F28*(1-F63) | G46: =G28*(1-G63)
A47: + D&A | B47: =B30 | C47: =C30 | D47: =D30 | E47: =E30 | F47: =F30 | G47: =G30
A48: - Capex | B48: 52729 | C48: 82999 | D48: 131819 | E48: =E24*E65 | F48: =F24*F65 | G48: =G24*G65 | H48: SEC XBRL F55, F56, F57
A49: Capex % of sales | B49: =B48/B24 | C49: =C48/C24 | D49: =D48/D24 | E49: =E48/E24 | F49: =F48/F24 | G49: =G48/G24
A50: - Working capital increase | E50: =E66*(E24-Valuation!$B$50) | F50: =F66*(F24-E24) | G50: =G66*(G24-F24)
A51: - Stock comp (adjusted EBIT only) | E51: =IF(AND(Valuation!$B$47="adjusted",Valuation!$B$48="cost"),E55*(1-E63),0) | F51: =IF(AND(Valuation!$B$47="adjusted",Valuation!$B$48="cost"),F55*(1-F63),0) | G51: =IF(AND(Valuation!$B$47="adjusted",Valuation!$B$48="cost"),G55*(1-G63),0)
A52: Free cash flow to firm | E52: =E46+E47-E48-E50-E51 | F52: =F46+F47-F48-F50-F51 | G52: =G46+G47-G48-G50-G51 | H52: what the DCF discounts (Calc tabs)
A53: Operating cash flow (reported) | B53: 84946 | C53: 115877 | D53: 139514 | H53: SEC XBRL F48, F49, F50
A54: FCF (operating cash flow - capex) | B54: =B53-B48 | C54: =C53-C48 | D54: =D53-D48
A55: Stock comp (memo) | B55: 24023 | C55: 22011 | D55: 19467 | E55: =E24*E67 | F55: =F24*F67 | G55: =G24*G67 | H55: SEC XBRL F41, F42, F43
A56: Buybacks + dividends + other uses | E56: =E24*E69+E68+E70 | F56: =F24*F69+F68+F70 | G56: =G24*G69+G68+G70
A57: % of sales | B57: =B56/B24 | C57: =C56/C24 | D57: =D56/D24 | E57: =E56/E24 | F57: =F56/F24 | G57: =G56/G24
A58: Net debt / (net cash), year end (memo) | E58: =Valuation!$B$56-E52-E33*(1-E63)+E56 | F58: =E58-F52-F33*(1-F63)+F56 | G58: =F58-G52-G33*(1-G63)+G56 | H58: rolled from the balance-date figure; feeds interest only
A60: Drivers (blue = input; a year left black carries the prior year)
A61: Revenue growth | C61: =C25 | D61: =D25 | E61: =E25 | F61: =F25 | G61: =G25 | H61: implied by the segment build (edit the segment rows)
A62: EBIT margin | E62: =E29 | F62: =F29 | G62: =G29 | H62: implied by the segment build and corporate EBIT
A63: Tax rate | B63: =B37 | C63: =C37 | D63: =D37 | E63: 0.21 | F63: =E63 | G63: =F63
A64: D&A % revenue | B64: =B30/B24 | C64: =C30/C24 | D64: =D30/D24 | E64: 0.10412196 | F64: 0.1189196 | G64: 0.13083863
A65: Capex % revenue | B65: =B49 | C65: =C49 | D65: =D49 | E65: 0.2656 | F65: 0.2927 | G65: 0.2706
A66: Working capital % of revenue increase | E66: 0 | F66: =E66 | G66: =F66
A67: Stock comp % revenue | B67: =B55/B24 | C67: =C55/C24 | D67: =D55/D24 | E67: 0.024899 | F67: =E67 | G67: =F67
A68: Shareholder returns ($) | E68: 0 | F68: =E68 | G68: =F68
A69: Shareholder returns % revenue | B69: =B57 | C69: =C57 | D69: =D57 | E69: 0 | F69: =E69 | G69: =F69
A70: Other uses of cash ($: M&A, investments) | E70: 0 | F70: =E70 | G70: =F70
A71: Adj. EBITDA addback % revenue | E71: 0 | F71: =E71 | G71: =F71
A73: Versus company guidance and street consensus
A74: Guidance: capex (cash capex, approximate ($M)), midpoint | E74: =AVERAGE(220000.0,220000.0) | H74: 2.2e+05 to 2.2e+05; as of 2026-07-30; source 27 (Amazon Q2 2026 earnings call transcript (~$220B 2026 cash ca)
A75: Consensus: EPS diluted (GAAP (consensus; excludes mark-to-market gains)) | F75: 10.51 | H75: as of 2026-10-06; source 5, 4 (Yahoo Finance AMZN analysis: FY27 $10.51 (52), EPS trend, re)
A76: Model vs consensus | F76: =F42/F75-1
A77: Consensus: EPS diluted (GAAP (consensus)) | G77: 13.81 | H77: as of 2026-10-06; source 4 (MarketScreener Amazon finances: EPS 2027 $10.51 / 2028 $13.8)
A78: Model vs consensus | G78: =G42/G77-1
A79: Consensus: revenue (GAAP ($M)) | E79: 828300 | H79: as of 2026-10-06; source 4 (MarketScreener Amazon finances: EPS 2027 $10.51 / 2028 $13.8)
A80: Model vs consensus | E80: =E24/E79-1
A81: Consensus: revenue (GAAP ($M)) | F81: 947900 | H81: as of 2026-10-06; source 4 (MarketScreener Amazon finances: EPS 2027 $10.51 / 2028 $13.8)
A82: Model vs consensus | F82: =F24/F81-1
A83: Consensus: revenue (GAAP ($M)) | G83: 1097400 | H83: as of 2026-10-06; source 4 (MarketScreener Amazon finances: EPS 2027 $10.51 / 2028 $13.8)
A84: Model vs consensus | G84: =G24/G83-1
A85: Consensus: EBIT margin (GAAP; EBIT $182.7B / sales $1,097.4B) | G85: 0.166484 | H85: as of 2026-10-06; source 4 (MarketScreener Amazon finances: EPS 2027 $10.51 / 2028 $13.8)
A86: Model vs consensus | G86: =(G29-G85)*10000
A87: Consensus: capex ($M) | F87: 277400 | H87: as of 2026-10-06; source 4 (MarketScreener Amazon finances: EPS 2027 $10.51 / 2028 $13.8)
A88: Consensus: capex ($M) | G88: 296900 | H88: as of 2026-10-06; source 4 (MarketScreener Amazon finances: EPS 2027 $10.51 / 2028 $13.8)

Sheet Valuation
A1: AMZN: valuation and price target derivation
A2: Value per share at the target date = weighted methods below; the 12-month target is the median of the scenario mix (Distribution tab).
A3: Method | B3: Multiple | C3: Metric at target date | D3: Value per share | E3: Weight | F3: Contribution
A4: ='Calc - research target (12m)'!A67 | B4: =IF('Calc - research target (12m)'!C67="","",'Calc - research target (12m)'!C67) | C4: =IF('Calc - research target (12m)'!I67="","",'Calc - research target (12m)'!I67) | D4: ='Calc - research target (12m)'!F67 | E4: ='Calc - research target (12m)'!G67 | F4: =D4*E4/SUM($E$4:$E$6)
A5: ='Calc - research target (12m)'!A68 | B5: =IF('Calc - research target (12m)'!C68="","",'Calc - research target (12m)'!C68) | C5: =IF('Calc - research target (12m)'!I68="","",'Calc - research target (12m)'!I68) | D5: ='Calc - research target (12m)'!F68 | E5: ='Calc - research target (12m)'!G68 | F5: =D5*E5/SUM($E$4:$E$6)
A6: ='Calc - research target (12m)'!A69 | B6: =IF('Calc - research target (12m)'!C69="","",'Calc - research target (12m)'!C69) | C6: =IF('Calc - research target (12m)'!I69="","",'Calc - research target (12m)'!I69) | D6: ='Calc - research target (12m)'!F69 | E6: ='Calc - research target (12m)'!G69 | F6: =D6*E6/SUM($E$4:$E$6)
A7: Research target (12m) per share | D7: ='Calc - research target (12m)'!$F$70 | F7: =SUM(F4:F6)
A9: 12-month EPS basis (what the P/E is applied to)
A10: Fiscal year | B10: =Model!E5 | C10: =Model!F5 | D10: =Model!G5
A11: Share of the 12 months after the target date | B11: ='Calc - research target (12m)'!C38 | C11: ='Calc - research target (12m)'!D38 | D11: ='Calc - research target (12m)'!E38
A12: Model EPS (Model tab) | B12: =Model!E42 | C12: =Model!F42 | D12: =Model!G42
A13: Model EPS, next 12 months after the target date | B13: =SUMPRODUCT(B11:D11,B12:D12)
A14: Stated next-12-month EPS used by the P/E method (consensus basis, cited) | B14: =Valuation!F70 | C14: =B14/B13-1 | D14: vs model EPS
A16: DCF build (free cash flow to firm, discounted to the target date)
A17: Fiscal year | B17: =Model!E5 | C17: =Model!F5 | D17: =Model!G5
A18: Free cash flow to firm | B18: ='Calc - research target (12m)'!C31 | C18: ='Calc - research target (12m)'!D31 | D18: ='Calc - research target (12m)'!E31
A19: Share of the year after the target date | B19: ='Calc - research target (12m)'!C35 | C19: ='Calc - research target (12m)'!D35 | D19: ='Calc - research target (12m)'!E35
A20: PV at target date | B20: ='Calc - research target (12m)'!C36 | C20: ='Calc - research target (12m)'!D36 | D20: ='Calc - research target (12m)'!E36
A22: PV of free cash flow after the target date | B22: ='Calc - research target (12m)'!B42
A23: Terminal value (final year) | B23: ='Calc - research target (12m)'!B43
A24: PV of terminal value | B24: ='Calc - research target (12m)'!B44
A25: Enterprise value at target date | B25: ='Calc - research target (12m)'!B45
A26: Terminal value share of DCF | B26: ='Calc - research target (12m)'!B46
A27: Net debt at target date | B27: ='Calc - research target (12m)'!B50
A28: Minority interests | B28: ='Calc - research target (12m)'!B51
A29: Adjustments | B29: ='Calc - research target (12m)'!B52
A30: Diluted shares at target date (M) | B30: ='Calc - research target (12m)'!B53
A31: DCF value per share | B31: ='Calc - research target (12m)'!F67
A32: WACC | B32: ='Calc - research target (12m)'!B12
A42: Assumptions (blue = input; sources on the Sources tab)
A43: Input | B43: Value | C43: Basis / note
A44: Run date (valuation as of) | B44: 46318
A45: Target date (run date + 365 days) | B45: =B44+365 | C45: 12-month horizon
A46: Money unit | B46: $M
A47: EBIT basis (gaap / adjusted) | B47: gaap | C47: gaap = after stock comp
A48: Stock comp treatment (cost / dilution) | B48: cost | C48: used only when EBIT is adjusted
A49: Last reported fiscal year end | B49: 46022
A50: Net sales, last reported year ($M) | B50: 716924
A51: WACC | B51: 0.1044 | C51: filled in (not stated in this set's original work): agent_3's stated 10.44% WACC (cost of equity 5.31% + 1.31 x 4.20% = 10.79%; debt at 5.6% pre-tax, 21% tax), the only discount rate in the run. The supervisor gave the DCF no weight, so it is a diagnostic only (dcf_weight 0).
A52: Terminal method (gordon / exit_multiple / steady_state) | B52: gordon
A53: Terminal growth | B53: 0.035
A54: Exit EV/EBITDA (exit_multiple only)
A55: Balance-sheet date | B55: 46203
A56: Net debt / (net cash) at balance date ($M) | B56: 10332 | C56: excludes operating leases
A57: Minority interests + preferred stock | B57: 0
A58: Interest rate on net debt / cash | B58: 0.024985
A59: Net debt at target date (override; blank = bridge) | B59: 58364
A60: Diluted shares (M) | B60: 10903
A61: Share count date | B61: 46203
A62: Annual change in diluted shares | B62: 0.009 | C62: net of buybacks and stock-comp dilution
A63: Shares at target date (override; blank = from annual change)
A64: DCF weight | B64: 0 | C64: Kilian 2026-10-21: 0 unless the name has a DCF leg (dcf_policy)
A65: Sum-of-the-parts weight | B65: 0.425
A66: Spread within each scenario (lognormal vol) | B66: 0.221
A67: Share price at the run | B67: 248 | C67: close used by the run (2026-10-23)
A69: Target multiple | B69: Multiple | C69: Weight | D69: Basis (ntm / ltm) | E69: EBITDA basis | F69: Stated EPS | G69: Stated FCF/share | H69: Levered | I69: Peer basis
A70: P/E | B70: 22.88 | C70: 0.425 | D70: ntm | E70: gaap | F70: 11.402101 | H70: TRUE | I70: Peer refresh 2026-10-26 (Kilian 06:07Z; METHOD.md Peer comparables): CY2027 P/E at the Oct 23, 2026 close, the base round's basis. P/E leg set MSFT, GOOGL, META (3 names, peer_count_flag): MSFT 24.45x (524.51 / 21.45 = 0.500 x FY2027-06 19.65 + 0.500 x FY2028-06 23.25), GOOGL 21.3x (320.21 / 15.03), META 18.94x (642.62 / 33.93); median 21.3x, used as is (no premium: AMZN's EPS growth after the horizon, FY2029 vs FY2028 consensus +11.7%, 3 analysts, is not above the peers', so the base round's case for 23x no longer holds). AMZN's own CY2027 P/E 23.29x. Out: BABA, PDD (China), CPNG (Korea; loss base). GOOGL on FY2027 EPS (its FY2026 consensus carries stake gains). Applied to NTM EPS at the Oct-2027 horizon. EXIT k=0.8 (2026-10-26T12:28Z): Exit-multiple rule (Kilian card 2026-10-26 12:16Z; METHOD.md Peer comparables): exit = peer median x (own NTM multiple / peer median)^k, k = 0.8. Peer median 21.3x; own 23.29x: AMZN $248.00 / CY2027 Zacks consensus EPS $10.65 = 23.29x (same basis as the peer rows). 21.3 x (23.29 / 21.3)^0.8 = 21.3 x 1.0741 = 22.88x (was 21.3x). SOTP segment multiples (AWS 21.3x, ads 19.87x, stores 37.56x) stay at their peer medians: a segment has no own traded multiple (rule: no meaningful own multiple -> peer median).
A72: Segment (sum of the parts) | B72: NTM metric | C72: Metric | D72: Multiple | E72: Note
A73: AWS: NTM after-tax OI x 21.3 | B73: 71507.488 | D73: 21.3 | E73: NTM after-tax AWS OI at the 2027-10-23 horizon (0.189 x FY2027 + 0.811 x FY2028 driver EBIT, x 0.79) x 21.3x = median CY2027 P/E of the cloud peers MSFT 24.45x (524.51 / 21.45 = 0.500 x FY2027-06 19.65 + 0.500 x FY2028-06 23.25), ORCL 17.55x (126.16 / 7.1902: Zacks 8.1475 = 0.417 x FY2027-05 6.73 + 0.583 x FY2028-05 9.16, re-based to GAAP after stock comp x 0.8825), GOOGL 21.3x (320.21 / 15.03). Was 25x (anchored on MSFT); no premium kept: ORCL's low multiple is part of the approved set and no persistence evidence for an AWS premium over the median is on file. Variant: MSFT's 24.45x alone, +$10.2 on the research target (12m).
A74: Advertising (in North America + International): NTM after-tax OI x 19.87 | B74: 46408.947 | D74: 19.87 | E74: Advertising OI = 0.5 x ads_rev (50% ad margin, flagged estimate in driver stores_m), NTM after-tax, x 19.87x = median CY2027 P/E of the ad-platform peers META 18.94x (642.62 / 33.93), GOOGL 21.3x (320.21 / 15.03), RDDT 20.79x (144.25 / 6.94), APP 13.08x (260.25 / 19.9). New part (2026-10-26): the segment's earnings are ~98% advertising on the driver split, so the retail median applies to stores only (METHOD.md: a segment-only comp values that segment only).
A75: Stores ex-advertising (North America + International, reported basis incl. venture losses): NTM after-tax OI x 37.56 | B75: 853.38485 | D75: 37.56 | E75: Stores ex-advertising OI = stores_m x stores_rev (reported basis, incl. Leo and Zoox losses), NTM after-tax, x 37.56x = median CY2027 P/E of the approved retail/commerce peers WMT 37.56x (119.89 / 3.1917 = 0.083 x FY2027-01 2.88 + 0.917 x FY2028-01 3.22), COST 42.8x (1003.32 / 23.4433 = 0.667 x FY2027-08 22.7 + 0.333 x FY2028-08 24.93), MELI 32.8x (1810.15 / 55.19), SE 16.55x (74.63 / 4.51), SHOP 91.67x (168.68 / 1.84). Out: BABA, PDD (China), CPNG (Korea). SE has 2 EPS estimates (thin).
A76: Venture loss add-back: basis correction 22.88x -> 37.56x | B76: 46388.8 | D76: 1 | E76: The Leo and Zoox loss add-backs are capitalised at the P/E leg's 22.88x (adjustments; exit k=0.8 2026-10-26, was 21.3x); on this leg their losses sit inside the stores part at 37.56x, so the add-back is re-based: -(2,500 + 1,500) x 0.79 x (22.88 - 37.56) = +$46,389M. Entered as metric x 1.0.
A78: Adjustment (equity level) | B78: Value | C78: Probability | D78: Note
A79: Anthropic stake at a $1.5T IPO, after tax and lock-up (AMZN deep model 2026-10-19) | B79: 183692.36 | C79: 1 | D79: Labelled estimate. 19.5% pre-IPO fully diluted (filing-implied 190.4 / 965 = 19.73%; press ~21%) x 0.95 Public Benefit Fund x (1 - $75B primary / $1.5T) = 17.60% x $1.5T; tax 24% on the gain over $18.0B cash invested; lock-up/blockage discount 10.37% (Finnerty, 65% vol, 0.5 yr). Replaces the SOTP's $149.0B after-tax carrying value. Engine stakes formula at base: gross $263,980M, tax $59,035M, value $183,692M; entered as an adjustment so the Sheet lays it out (scenario swing carried in eps_pct / multiple_pct, see the scenario rows).
A80: OpenAI Series C stake at the last priced round (AMZN deep model 2026-10-19) | B80: 49999.62 | C80: 1 | D80: $15.0B + $35.0B Series C (10-Q), priced in the $122B round at $730B pre / $852B post (March 2026); August 2026 $7B employee sale at $852B. 50 / 852 = 5.87%. Value = cost $50.0B; no tax. Engine stakes formula at base: gross $50,000M, tax $0M, value $50,000M; entered as an adjustment so the Sheet lays it out (scenario swing carried in eps_pct / multiple_pct, see the scenario rows).
A81: Amazon Leo: loss add-back (AMZN deep model 2026-10-19) | B81: 45188 | C81: 1 | D81: Consensus EPS carries Leo's losses; est. $2.5B pre-tax in the NTM year at the horizon (range 1.5-4.0) x 0.79 x 22.88 (P/E leg multiple, exit k=0.8 2026-10-26; was 21.3x, before that 23x) = +$45.2B, so the core is valued ex-Leo (playbook loss-making venture rule). On the SOTP leg the basis correction re-bases it to the stores multiple.
A82: Amazon Leo: own value, scenario-weighted (AMZN deep model 2026-10-19) | B82: 13000 | C82: 1 | D82: 2030 scenarios (bear p.35 $2.0B revenue, ~2x sales; base p.45 $6.7B, 20x EBIT at 25%; bull p.20 $14.0B, 22x EBIT at 35%) = $38.1B, discounted 3 years at 15% = $25.0B, less ~$12B PV of remaining build and pre-scale burn = ~$13B (est.).
A83: Zoox: loss add-back (AMZN deep model 2026-10-19) | B83: 27112.8 | C83: 1 | D83: Est. $1.5B pre-tax yearly loss (range 1.0-2.0; ~5,000 staff x ~$0.3M fully loaded plus fleet) x 0.79 x 22.88 (exit k=0.8 2026-10-26; was 21.3x, before that 23x) = +$27.1B.
A84: Zoox: own value, scenario-weighted (AMZN deep model 2026-10-19) | B84: 9000 | C84: 1 | D84: Bear p.40 $2B, base p.45 $10B, bull p.15 $40B = $11.3B (Waymo $126B post-money at 2,500-3,000 vehicles vs Zoox 105) x (1 - 20% haircut) = ~$9.0B (est.).
A85: Globalstar acquisition, implied EV incl. debt (AMZN deep model 2026-10-19) | B85: -10900 | C85: 1 | D85: 10-Q: ~$10.9B including debt, $90 cash or 0.3210 AMZN shares, cash capped at 40%, close 2027. Deducted on both legs (was SOTP only); its spectrum value sits in the Leo scenarios; no Globalstar shares in the count.
A86: Other equity investments and warrants (AMZN deep model 2026-10-19) | B86: 4636 | C86: 1 | D86: Private equity investments $122.3B - Anthropic preferred $92.5B - OpenAI $28.7B = $1.1B, + warrants $4.3B + equity-method $0.4B = $5.8B (10-Q) x 0.80 for tax and liquidity = +$4.6B. Marketable equity ($4.7B) is already in cash and marketable securities, so it stays in net debt. Not in the run.
A87: Legal remedies, probability-weighted (AMZN deep model 2026-10-19) | B87: -32278.663 | C87: 1 | D87: Driver-built (peer refresh 2026-10-26): FTC monopolization p(liability) 0.35 x (0.8 x 3% + 0.2 x 10%) = 0.044 of the retail+ads value, now the SOTP's Advertising (19.87x) + Stores (37.56x) parts on the driver metrics (~$954B; was 22x on $1,025B) = -$14.7B; ad-auction suit: damages 0.5 x $8B = -$4.0B, forward pricing 0.4 x 50% x $2.9B/yr x 0.79 x 19.87 = -$9.1B (was 22x, -$10.1B); California AG and consumer class actions -$4.0B; EU -$0.45B. Total -$32.3B. Driver formula constant $17,584M = the base round's $18,560M (set from the rounded total -$34.35B) - 10,080 + 9,104; the exact fixed pieces sum to $17,553M (4,000 + 9,104 + 4,000 + 449), a $31M rounding residue kept (removing it leaves the base horizon value at $256.82 and moves the bull case by +$0.01).
A88: Conglomerate overlay 10% on non-core parts (AMZN deep model 2026-10-19) | B88: -26033 | C88: 1 | D88: 10% x post-haircut non-core parts $260.3B (Anthropic 183.7 after tax and lock-up, OpenAI 50.0, other investments 4.6, Leo 13.0, Zoox 9.0); tax and lock-up already deducted and no holdco layer, so only the agency part remains (Berger & Ofek 13-15% less the self-selection evidence; listed holdcos 34-49% bundle tax and illiquidity).
A90: Custom method | B90: Value per share | C90: Weight | D90: Explanation
A91: none
A93: Scenario | B93: Probability | C93: Growth Δ | D93: Margin Δ | E93: Multiple Δ (turns) | F93: WACC Δ | G93: Multiple %Δ (FCF yield, segments) | H93: Stated EPS/FCF %Δ | I93: Custom methods %Δ | J93: Story
A94: bear | B94: 0.25 | E94: -5.5 | G94: -0.265604 | H94: -0.035317 | J94: Driver restatement 2026-10-22: AWS turnover -8% (2027 AWS growth ~24%, the story's low-to-mid 20s), AWS EBITDA margin -2 pts (2027 capex lifting D&A), ads -4%; P/E 17.5x and segment multiples -24% kept; the Anthropic ~$1.0T re-mark rides in eps_pct (the old operating eps_pct -12.2% is now the driver moves) and multiple_pct. AI-capex digestion or a lab customer stumble (forecasters' median bear $195): AWS growth toward the low-to-mid 20s while 2027 capex lifts D&A; ~17.5x on NTM EPS ~$11 as ORCL trades, segment multiples cut by the same 24%, and Anthropic prices at ~$1.0T instead of $1.5T (stakes x 0.67). Sheet layout (no stake scenarios): the stake re-mark (-6.95/share) rides in eps_pct -0.121932 -> -0.153619 (P/E leg) and multiple_pct -0.239130 -> -0.265604 (SOTP leg); every leg value is unchanged. | K94: driver deltas: aws_turn -0.08 %; aws_ebitda_m -0.02; ads_rev -0.04 %
A95: base | B95: 0.5 | J95: [exit k=0.8 2026-10-26: P/E 21.3x -> 22.88x] Equals the reconciled fair value: consensus broadly delivered, AWS ~30% on reserved capacity and the $496B backlog, 23x NTM EPS; Anthropic IPO at ~$1.5T; ventures at their scenario values.
A96: bull | B96: 0.25 | E96: 2.5 | G96: 0.129685 | H96: 0.019296 | J96: Driver restatement 2026-10-22: AWS turnover +6% (2027 AWS ~43%, the story's 35%+), AWS EBITDA margin +1.5 pts (Trainium), ads +3%; 25.5x and segment multiples +11% kept; the Anthropic ~$1.92T re-mark rides in eps_pct (stake part only) and multiple_pct. AWS holds 35%+ with Trainium, FCF inflects (forecasters' median bull $350 before stakes): ~25.5x on NTM EPS ~$13.75, segment multiples +11%, Anthropic at ~$1.92T (Polymarket first-day-close variant; stakes x 1.28). Sheet layout (no stake scenarios): the stake re-mark (+5.53/share) rides in eps_pct +0.097585 -> +0.114898 (P/E leg) and multiple_pct +0.108696 -> +0.129685 (SOTP leg); every leg value is unchanged. | K96: driver deltas: aws_turn +0.06 %; aws_ebitda_m +0.015; ads_rev +0.03 %
A98: Segment build (segment_build) | B98: Base revenue ($M) | C98: Driver note (growth and EBIT margin by year: Model tab)
A99: AWS | B99: 128725
A100: North America + International | B100: 588199
A101: Sum of segment base revenues | B101: =SUM(B99:B100) | C101: =IF(ABS(B101/Valuation!$B$50-1)<=0.02,"ties to the last reported net sales (within 2%)","FLAG: does not tie to the last reported net sales")

Sheet Sensitivity
A1: AMZN: sensitivity tables (bold = current inputs; every cell recalculates from the live model)
A3: DCF value per share: WACC (down) x terminal growth (across)
A4: WACC \ growth | B4: =Valuation!$B$53+(-0.01) | C4: =Valuation!$B$53+(-0.005) | D4: =Valuation!$B$53+(0) | E4: =Valuation!$B$53+(0.005) | F4: =Valuation!$B$53+(0.01)
A5: =Valuation!$B$51+(-0.01) | B5: =IF($A5-B$4<=0.01,"n/a",((SUMPRODUCT('Calc - research target (12m)'!$C$31:$E$31,'Calc - research target (12m)'!$C$35:$E$35,(1+$A5)^(-('Calc - research target (12m)'!$C$19:$E$19-'Calc - research target (12m)'!$B$13)))+'Calc - research target (12m)'!$E$31*(1+B$4)/($A5-B$4)/(1+$A5)^('Calc - research target (12m)'!$B$16-'Calc - research target (12m)'!$B$13))-'Calc - research target (12m)'!$B$50-'Calc - research target (12m)'!$B$51+'Calc - research target (12m)'!$B$52)/'Calc - research target (12m)'!$B$53) | C5: =IF($A5-C$4<=0.01,"n/a",((SUMPRODUCT('Calc - research target (12m)'!$C$31:$E$31,'Calc - research target (12m)'!$C$35:$E$35,(1+$A5)^(-('Calc - research target (12m)'!$C$19:$E$19-'Calc - research target (12m)'!$B$13)))+'Calc - research target (12m)'!$E$31*(1+C$4)/($A5-C$4)/(1+$A5)^('Calc - research target (12m)'!$B$16-'Calc - research target (12m)'!$B$13))-'Calc - research target (12m)'!$B$50-'Calc - research target (12m)'!$B$51+'Calc - research target (12m)'!$B$52)/'Calc - research target (12m)'!$B$53) | D5: =IF($A5-D$4<=0.01,"n/a",((SUMPRODUCT('Calc - research target (12m)'!$C$31:$E$31,'Calc - research target (12m)'!$C$35:$E$35,(1+$A5)^(-('Calc - research target (12m)'!$C$19:$E$19-'Calc - research target (12m)'!$B$13)))+'Calc - research target (12m)'!$E$31*(1+D$4)/($A5-D$4)/(1+$A5)^('Calc - research target (12m)'!$B$16-'Calc - research target (12m)'!$B$13))-'Calc - research target (12m)'!$B$50-'Calc - research target (12m)'!$B$51+'Calc - research target (12m)'!$B$52)/'Calc - research target (12m)'!$B$53) | E5: =IF($A5-E$4<=0.01,"n/a",((SUMPRODUCT('Calc - research target (12m)'!$C$31:$E$31,'Calc - research target (12m)'!$C$35:$E$35,(1+$A5)^(-('Calc - research target (12m)'!$C$19:$E$19-'Calc - research target (12m)'!$B$13)))+'Calc - research target (12m)'!$E$31*(1+E$4)/($A5-E$4)/(1+$A5)^('Calc - research target (12m)'!$B$16-'Calc - research target (12m)'!$B$13))-'Calc - research target (12m)'!$B$50-'Calc - research target (12m)'!$B$51+'Calc - research target (12m)'!$B$52)/'Calc - research target (12m)'!$B$53) | F5: =IF($A5-F$4<=0.01,"n/a",((SUMPRODUCT('Calc - research target (12m)'!$C$31:$E$31,'Calc - research target (12m)'!$C$35:$E$35,(1+$A5)^(-('Calc - research target (12m)'!$C$19:$E$19-'Calc - research target (12m)'!$B$13)))+'Calc - research target (12m)'!$E$31*(1+F$4)/($A5-F$4)/(1+$A5)^('Calc - research target (12m)'!$B$16-'Calc - research target (12m)'!$B$13))-'Calc - research target (12m)'!$B$50-'Calc - research target (12m)'!$B$51+'Calc - research target (12m)'!$B$52)/'Calc - research target (12m)'!$B$53)
A6: =Valuation!$B$51+(-0.005) | B6: =IF($A6-B$4<=0.01,"n/a",((SUMPRODUCT('Calc - research target (12m)'!$C$31:$E$31,'Calc - research target (12m)'!$C$35:$E$35,(1+$A6)^(-('Calc - research target (12m)'!$C$19:$E$19-'Calc - research target (12m)'!$B$13)))+'Calc - research target (12m)'!$E$31*(1+B$4)/($A6-B$4)/(1+$A6)^('Calc - research target (12m)'!$B$16-'Calc - research target (12m)'!$B$13))-'Calc - research target (12m)'!$B$50-'Calc - research target (12m)'!$B$51+'Calc - research target (12m)'!$B$52)/'Calc - research target (12m)'!$B$53) | C6: =IF($A6-C$4<=0.01,"n/a",((SUMPRODUCT('Calc - research target (12m)'!$C$31:$E$31,'Calc - research target (12m)'!$C$35:$E$35,(1+$A6)^(-('Calc - research target (12m)'!$C$19:$E$19-'Calc - research target (12m)'!$B$13)))+'Calc - research target (12m)'!$E$31*(1+C$4)/($A6-C$4)/(1+$A6)^('Calc - research target (12m)'!$B$16-'Calc - research target (12m)'!$B$13))-'Calc - research target (12m)'!$B$50-'Calc - research target (12m)'!$B$51+'Calc - research target (12m)'!$B$52)/'Calc - research target (12m)'!$B$53) | D6: =IF($A6-D$4<=0.01,"n/a",((SUMPRODUCT('Calc - research target (12m)'!$C$31:$E$31,'Calc - research target (12m)'!$C$35:$E$35,(1+$A6)^(-('Calc - research target (12m)'!$C$19:$E$19-'Calc - research target (12m)'!$B$13)))+'Calc - research target (12m)'!$E$31*(1+D$4)/($A6-D$4)/(1+$A6)^('Calc - research target (12m)'!$B$16-'Calc - research target (12m)'!$B$13))-'Calc - research target (12m)'!$B$50-'Calc - research target (12m)'!$B$51+'Calc - research target (12m)'!$B$52)/'Calc - research target (12m)'!$B$53) | E6: =IF($A6-E$4<=0.01,"n/a",((SUMPRODUCT('Calc - research target (12m)'!$C$31:$E$31,'Calc - research target (12m)'!$C$35:$E$35,(1+$A6)^(-('Calc - research target (12m)'!$C$19:$E$19-'Calc - research target (12m)'!$B$13)))+'Calc - research target (12m)'!$E$31*(1+E$4)/($A6-E$4)/(1+$A6)^('Calc - research target (12m)'!$B$16-'Calc - research target (12m)'!$B$13))-'Calc - research target (12m)'!$B$50-'Calc - research target (12m)'!$B$51+'Calc - research target (12m)'!$B$52)/'Calc - research target (12m)'!$B$53) | F6: =IF($A6-F$4<=0.01,"n/a",((SUMPRODUCT('Calc - research target (12m)'!$C$31:$E$31,'Calc - research target (12m)'!$C$35:$E$35,(1+$A6)^(-('Calc - research target (12m)'!$C$19:$E$19-'Calc - research target (12m)'!$B$13)))+'Calc - research target (12m)'!$E$31*(1+F$4)/($A6-F$4)/(1+$A6)^('Calc - research target (12m)'!$B$16-'Calc - research target (12m)'!$B$13))-'Calc - research target (12m)'!$B$50-'Calc - research target (12m)'!$B$51+'Calc - research target (12m)'!$B$52)/'Calc - research target (12m)'!$B$53)
A7: =Valuation!$B$51+(0) | B7: =IF($A7-B$4<=0.01,"n/a",((SUMPRODUCT('Calc - research target (12m)'!$C$31:$E$31,'Calc - research target (12m)'!$C$35:$E$35,(1+$A7)^(-('Calc - research target (12m)'!$C$19:$E$19-'Calc - research target (12m)'!$B$13)))+'Calc - research target (12m)'!$E$31*(1+B$4)/($A7-B$4)/(1+$A7)^('Calc - research target (12m)'!$B$16-'Calc - research target (12m)'!$B$13))-'Calc - research target (12m)'!$B$50-'Calc - research target (12m)'!$B$51+'Calc - research target (12m)'!$B$52)/'Calc - research target (12m)'!$B$53) | C7: =IF($A7-C$4<=0.01,"n/a",((SUMPRODUCT('Calc - research target (12m)'!$C$31:$E$31,'Calc - research target (12m)'!$C$35:$E$35,(1+$A7)^(-('Calc - research target (12m)'!$C$19:$E$19-'Calc - research target (12m)'!$B$13)))+'Calc - research target (12m)'!$E$31*(1+C$4)/($A7-C$4)/(1+$A7)^('Calc - research target (12m)'!$B$16-'Calc - research target (12m)'!$B$13))-'Calc - research target (12m)'!$B$50-'Calc - research target (12m)'!$B$51+'Calc - research target (12m)'!$B$52)/'Calc - research target (12m)'!$B$53) | D7: =IF($A7-D$4<=0.01,"n/a",((SUMPRODUCT('Calc - research target (12m)'!$C$31:$E$31,'Calc - research target (12m)'!$C$35:$E$35,(1+$A7)^(-('Calc - research target (12m)'!$C$19:$E$19-'Calc - research target (12m)'!$B$13)))+'Calc - research target (12m)'!$E$31*(1+D$4)/($A7-D$4)/(1+$A7)^('Calc - research target (12m)'!$B$16-'Calc - research target (12m)'!$B$13))-'Calc - research target (12m)'!$B$50-'Calc - research target (12m)'!$B$51+'Calc - research target (12m)'!$B$52)/'Calc - research target (12m)'!$B$53) | E7: =IF($A7-E$4<=0.01,"n/a",((SUMPRODUCT('Calc - research target (12m)'!$C$31:$E$31,'Calc - research target (12m)'!$C$35:$E$35,(1+$A7)^(-('Calc - research target (12m)'!$C$19:$E$19-'Calc - research target (12m)'!$B$13)))+'Calc - research target (12m)'!$E$31*(1+E$4)/($A7-E$4)/(1+$A7)^('Calc - research target (12m)'!$B$16-'Calc - research target (12m)'!$B$13))-'Calc - research target (12m)'!$B$50-'Calc - research target (12m)'!$B$51+'Calc - research target (12m)'!$B$52)/'Calc - research target (12m)'!$B$53) | F7: =IF($A7-F$4<=0.01,"n/a",((SUMPRODUCT('Calc - research target (12m)'!$C$31:$E$31,'Calc - research target (12m)'!$C$35:$E$35,(1+$A7)^(-('Calc - research target (12m)'!$C$19:$E$19-'Calc - research target (12m)'!$B$13)))+'Calc - research target (12m)'!$E$31*(1+F$4)/($A7-F$4)/(1+$A7)^('Calc - research target (12m)'!$B$16-'Calc - research target (12m)'!$B$13))-'Calc - research target (12m)'!$B$50-'Calc - research target (12m)'!$B$51+'Calc - research target (12m)'!$B$52)/'Calc - research target (12m)'!$B$53)
A8: =Valuation!$B$51+(0.005) | B8: =IF($A8-B$4<=0.01,"n/a",((SUMPRODUCT('Calc - research target (12m)'!$C$31:$E$31,'Calc - research target (12m)'!$C$35:$E$35,(1+$A8)^(-('Calc - research target (12m)'!$C$19:$E$19-'Calc - research target (12m)'!$B$13)))+'Calc - research target (12m)'!$E$31*(1+B$4)/($A8-B$4)/(1+$A8)^('Calc - research target (12m)'!$B$16-'Calc - research target (12m)'!$B$13))-'Calc - research target (12m)'!$B$50-'Calc - research target (12m)'!$B$51+'Calc - research target (12m)'!$B$52)/'Calc - research target (12m)'!$B$53) | C8: =IF($A8-C$4<=0.01,"n/a",((SUMPRODUCT('Calc - research target (12m)'!$C$31:$E$31,'Calc - research target (12m)'!$C$35:$E$35,(1+$A8)^(-('Calc - research target (12m)'!$C$19:$E$19-'Calc - research target (12m)'!$B$13)))+'Calc - research target (12m)'!$E$31*(1+C$4)/($A8-C$4)/(1+$A8)^('Calc - research target (12m)'!$B$16-'Calc - research target (12m)'!$B$13))-'Calc - research target (12m)'!$B$50-'Calc - research target (12m)'!$B$51+'Calc - research target (12m)'!$B$52)/'Calc - research target (12m)'!$B$53) | D8: =IF($A8-D$4<=0.01,"n/a",((SUMPRODUCT('Calc - research target (12m)'!$C$31:$E$31,'Calc - research target (12m)'!$C$35:$E$35,(1+$A8)^(-('Calc - research target (12m)'!$C$19:$E$19-'Calc - research target (12m)'!$B$13)))+'Calc - research target (12m)'!$E$31*(1+D$4)/($A8-D$4)/(1+$A8)^('Calc - research target (12m)'!$B$16-'Calc - research target (12m)'!$B$13))-'Calc - research target (12m)'!$B$50-'Calc - research target (12m)'!$B$51+'Calc - research target (12m)'!$B$52)/'Calc - research target (12m)'!$B$53) | E8: =IF($A8-E$4<=0.01,"n/a",((SUMPRODUCT('Calc - research target (12m)'!$C$31:$E$31,'Calc - research target (12m)'!$C$35:$E$35,(1+$A8)^(-('Calc - research target (12m)'!$C$19:$E$19-'Calc - research target (12m)'!$B$13)))+'Calc - research target (12m)'!$E$31*(1+E$4)/($A8-E$4)/(1+$A8)^('Calc - research target (12m)'!$B$16-'Calc - research target (12m)'!$B$13))-'Calc - research target (12m)'!$B$50-'Calc - research target (12m)'!$B$51+'Calc - research target (12m)'!$B$52)/'Calc - research target (12m)'!$B$53) | F8: =IF($A8-F$4<=0.01,"n/a",((SUMPRODUCT('Calc - research target (12m)'!$C$31:$E$31,'Calc - research target (12m)'!$C$35:$E$35,(1+$A8)^(-('Calc - research target (12m)'!$C$19:$E$19-'Calc - research target (12m)'!$B$13)))+'Calc - research target (12m)'!$E$31*(1+F$4)/($A8-F$4)/(1+$A8)^('Calc - research target (12m)'!$B$16-'Calc - research target (12m)'!$B$13))-'Calc - research target (12m)'!$B$50-'Calc - research target (12m)'!$B$51+'Calc - research target (12m)'!$B$52)/'Calc - research target (12m)'!$B$53)
A9: =Valuation!$B$51+(0.01) | B9: =IF($A9-B$4<=0.01,"n/a",((SUMPRODUCT('Calc - research target (12m)'!$C$31:$E$31,'Calc - research target (12m)'!$C$35:$E$35,(1+$A9)^(-('Calc - research target (12m)'!$C$19:$E$19-'Calc - research target (12m)'!$B$13)))+'Calc - research target (12m)'!$E$31*(1+B$4)/($A9-B$4)/(1+$A9)^('Calc - research target (12m)'!$B$16-'Calc - research target (12m)'!$B$13))-'Calc - research target (12m)'!$B$50-'Calc - research target (12m)'!$B$51+'Calc - research target (12m)'!$B$52)/'Calc - research target (12m)'!$B$53) | C9: =IF($A9-C$4<=0.01,"n/a",((SUMPRODUCT('Calc - research target (12m)'!$C$31:$E$31,'Calc - research target (12m)'!$C$35:$E$35,(1+$A9)^(-('Calc - research target (12m)'!$C$19:$E$19-'Calc - research target (12m)'!$B$13)))+'Calc - research target (12m)'!$E$31*(1+C$4)/($A9-C$4)/(1+$A9)^('Calc - research target (12m)'!$B$16-'Calc - research target (12m)'!$B$13))-'Calc - research target (12m)'!$B$50-'Calc - research target (12m)'!$B$51+'Calc - research target (12m)'!$B$52)/'Calc - research target (12m)'!$B$53) | D9: =IF($A9-D$4<=0.01,"n/a",((SUMPRODUCT('Calc - research target (12m)'!$C$31:$E$31,'Calc - research target (12m)'!$C$35:$E$35,(1+$A9)^(-('Calc - research target (12m)'!$C$19:$E$19-'Calc - research target (12m)'!$B$13)))+'Calc - research target (12m)'!$E$31*(1+D$4)/($A9-D$4)/(1+$A9)^('Calc - research target (12m)'!$B$16-'Calc - research target (12m)'!$B$13))-'Calc - research target (12m)'!$B$50-'Calc - research target (12m)'!$B$51+'Calc - research target (12m)'!$B$52)/'Calc - research target (12m)'!$B$53) | E9: =IF($A9-E$4<=0.01,"n/a",((SUMPRODUCT('Calc - research target (12m)'!$C$31:$E$31,'Calc - research target (12m)'!$C$35:$E$35,(1+$A9)^(-('Calc - research target (12m)'!$C$19:$E$19-'Calc - research target (12m)'!$B$13)))+'Calc - research target (12m)'!$E$31*(1+E$4)/($A9-E$4)/(1+$A9)^('Calc - research target (12m)'!$B$16-'Calc - research target (12m)'!$B$13))-'Calc - research target (12m)'!$B$50-'Calc - research target (12m)'!$B$51+'Calc - research target (12m)'!$B$52)/'Calc - research target (12m)'!$B$53) | F9: =IF($A9-F$4<=0.01,"n/a",((SUMPRODUCT('Calc - research target (12m)'!$C$31:$E$31,'Calc - research target (12m)'!$C$35:$E$35,(1+$A9)^(-('Calc - research target (12m)'!$C$19:$E$19-'Calc - research target (12m)'!$B$13)))+'Calc - research target (12m)'!$E$31*(1+F$4)/($A9-F$4)/(1+$A9)^('Calc - research target (12m)'!$B$16-'Calc - research target (12m)'!$B$13))-'Calc - research target (12m)'!$B$50-'Calc - research target (12m)'!$B$51+'Calc - research target (12m)'!$B$52)/'Calc - research target (12m)'!$B$53)
A11: Research target (12m) per share: P/E multiple (down) x stated EPS (across)
A12: Multiple \ metric | B12: =Valuation!F70*0.9 | C12: =Valuation!F70*0.95 | D12: =Valuation!F70*1.0 | E12: =Valuation!F70*1.05 | F12: =Valuation!F70*1.1
A13: =Valuation!$B$70+(-3) | B13: =((SUMPRODUCT('Calc - research target (12m)'!$F$67:$F$69,'Calc - research target (12m)'!$G$67:$G$69)-'Calc - research target (12m)'!$F$68*'Calc - research target (12m)'!$G$68)+'Calc - research target (12m)'!$G$68*($A13*B$12+'Calc - research target (12m)'!$B$52/'Calc - research target (12m)'!$B$53))/SUM('Calc - research target (12m)'!$G$67:$G$69) | C13: =((SUMPRODUCT('Calc - research target (12m)'!$F$67:$F$69,'Calc - research target (12m)'!$G$67:$G$69)-'Calc - research target (12m)'!$F$68*'Calc - research target (12m)'!$G$68)+'Calc - research target (12m)'!$G$68*($A13*C$12+'Calc - research target (12m)'!$B$52/'Calc - research target (12m)'!$B$53))/SUM('Calc - research target (12m)'!$G$67:$G$69) | D13: =((SUMPRODUCT('Calc - research target (12m)'!$F$67:$F$69,'Calc - research target (12m)'!$G$67:$G$69)-'Calc - research target (12m)'!$F$68*'Calc - research target (12m)'!$G$68)+'Calc - research target (12m)'!$G$68*($A13*D$12+'Calc - research target (12m)'!$B$52/'Calc - research target (12m)'!$B$53))/SUM('Calc - research target (12m)'!$G$67:$G$69) | E13: =((SUMPRODUCT('Calc - research target (12m)'!$F$67:$F$69,'Calc - research target (12m)'!$G$67:$G$69)-'Calc - research target (12m)'!$F$68*'Calc - research target (12m)'!$G$68)+'Calc - research target (12m)'!$G$68*($A13*E$12+'Calc - research target (12m)'!$B$52/'Calc - research target (12m)'!$B$53))/SUM('Calc - research target (12m)'!$G$67:$G$69) | F13: =((SUMPRODUCT('Calc - research target (12m)'!$F$67:$F$69,'Calc - research target (12m)'!$G$67:$G$69)-'Calc - research target (12m)'!$F$68*'Calc - research target (12m)'!$G$68)+'Calc - research target (12m)'!$G$68*($A13*F$12+'Calc - research target (12m)'!$B$52/'Calc - research target (12m)'!$B$53))/SUM('Calc - research target (12m)'!$G$67:$G$69)
A14: =Valuation!$B$70+(-2) | B14: =((SUMPRODUCT('Calc - research target (12m)'!$F$67:$F$69,'Calc - research target (12m)'!$G$67:$G$69)-'Calc - research target (12m)'!$F$68*'Calc - research target (12m)'!$G$68)+'Calc - research target (12m)'!$G$68*($A14*B$12+'Calc - research target (12m)'!$B$52/'Calc - research target (12m)'!$B$53))/SUM('Calc - research target (12m)'!$G$67:$G$69) | C14: =((SUMPRODUCT('Calc - research target (12m)'!$F$67:$F$69,'Calc - research target (12m)'!$G$67:$G$69)-'Calc - research target (12m)'!$F$68*'Calc - research target (12m)'!$G$68)+'Calc - research target (12m)'!$G$68*($A14*C$12+'Calc - research target (12m)'!$B$52/'Calc - research target (12m)'!$B$53))/SUM('Calc - research target (12m)'!$G$67:$G$69) | D14: =((SUMPRODUCT('Calc - research target (12m)'!$F$67:$F$69,'Calc - research target (12m)'!$G$67:$G$69)-'Calc - research target (12m)'!$F$68*'Calc - research target (12m)'!$G$68)+'Calc - research target (12m)'!$G$68*($A14*D$12+'Calc - research target (12m)'!$B$52/'Calc - research target (12m)'!$B$53))/SUM('Calc - research target (12m)'!$G$67:$G$69) | E14: =((SUMPRODUCT('Calc - research target (12m)'!$F$67:$F$69,'Calc - research target (12m)'!$G$67:$G$69)-'Calc - research target (12m)'!$F$68*'Calc - research target (12m)'!$G$68)+'Calc - research target (12m)'!$G$68*($A14*E$12+'Calc - research target (12m)'!$B$52/'Calc - research target (12m)'!$B$53))/SUM('Calc - research target (12m)'!$G$67:$G$69) | F14: =((SUMPRODUCT('Calc - research target (12m)'!$F$67:$F$69,'Calc - research target (12m)'!$G$67:$G$69)-'Calc - research target (12m)'!$F$68*'Calc - research target (12m)'!$G$68)+'Calc - research target (12m)'!$G$68*($A14*F$12+'Calc - research target (12m)'!$B$52/'Calc - research target (12m)'!$B$53))/SUM('Calc - research target (12m)'!$G$67:$G$69)
A15: =Valuation!$B$70+(-1) | B15: =((SUMPRODUCT('Calc - research target (12m)'!$F$67:$F$69,'Calc - research target (12m)'!$G$67:$G$69)-'Calc - research target (12m)'!$F$68*'Calc - research target (12m)'!$G$68)+'Calc - research target (12m)'!$G$68*($A15*B$12+'Calc - research target (12m)'!$B$52/'Calc - research target (12m)'!$B$53))/SUM('Calc - research target (12m)'!$G$67:$G$69) | C15: =((SUMPRODUCT('Calc - research target (12m)'!$F$67:$F$69,'Calc - research target (12m)'!$G$67:$G$69)-'Calc - research target (12m)'!$F$68*'Calc - research target (12m)'!$G$68)+'Calc - research target (12m)'!$G$68*($A15*C$12+'Calc - research target (12m)'!$B$52/'Calc - research target (12m)'!$B$53))/SUM('Calc - research target (12m)'!$G$67:$G$69) | D15: =((SUMPRODUCT('Calc - research target (12m)'!$F$67:$F$69,'Calc - research target (12m)'!$G$67:$G$69)-'Calc - research target (12m)'!$F$68*'Calc - research target (12m)'!$G$68)+'Calc - research target (12m)'!$G$68*($A15*D$12+'Calc - research target (12m)'!$B$52/'Calc - research target (12m)'!$B$53))/SUM('Calc - research target (12m)'!$G$67:$G$69) | E15: =((SUMPRODUCT('Calc - research target (12m)'!$F$67:$F$69,'Calc - research target (12m)'!$G$67:$G$69)-'Calc - research target (12m)'!$F$68*'Calc - research target (12m)'!$G$68)+'Calc - research target (12m)'!$G$68*($A15*E$12+'Calc - research target (12m)'!$B$52/'Calc - research target (12m)'!$B$53))/SUM('Calc - research target (12m)'!$G$67:$G$69) | F15: =((SUMPRODUCT('Calc - research target (12m)'!$F$67:$F$69,'Calc - research target (12m)'!$G$67:$G$69)-'Calc - research target (12m)'!$F$68*'Calc - research target (12m)'!$G$68)+'Calc - research target (12m)'!$G$68*($A15*F$12+'Calc - research target (12m)'!$B$52/'Calc - research target (12m)'!$B$53))/SUM('Calc - research target (12m)'!$G$67:$G$69)
A16: =Valuation!$B$70+(0) | B16: =((SUMPRODUCT('Calc - research target (12m)'!$F$67:$F$69,'Calc - research target (12m)'!$G$67:$G$69)-'Calc - research target (12m)'!$F$68*'Calc - research target (12m)'!$G$68)+'Calc - research target (12m)'!$G$68*($A16*B$12+'Calc - research target (12m)'!$B$52/'Calc - research target (12m)'!$B$53))/SUM('Calc - research target (12m)'!$G$67:$G$69) | C16: =((SUMPRODUCT('Calc - research target (12m)'!$F$67:$F$69,'Calc - research target (12m)'!$G$67:$G$69)-'Calc - research target (12m)'!$F$68*'Calc - research target (12m)'!$G$68)+'Calc - research target (12m)'!$G$68*($A16*C$12+'Calc - research target (12m)'!$B$52/'Calc - research target (12m)'!$B$53))/SUM('Calc - research target (12m)'!$G$67:$G$69) | D16: =((SUMPRODUCT('Calc - research target (12m)'!$F$67:$F$69,'Calc - research target (12m)'!$G$67:$G$69)-'Calc - research target (12m)'!$F$68*'Calc - research target (12m)'!$G$68)+'Calc - research target (12m)'!$G$68*($A16*D$12+'Calc - research target (12m)'!$B$52/'Calc - research target (12m)'!$B$53))/SUM('Calc - research target (12m)'!$G$67:$G$69) | E16: =((SUMPRODUCT('Calc - research target (12m)'!$F$67:$F$69,'Calc - research target (12m)'!$G$67:$G$69)-'Calc - research target (12m)'!$F$68*'Calc - research target (12m)'!$G$68)+'Calc - research target (12m)'!$G$68*($A16*E$12+'Calc - research target (12m)'!$B$52/'Calc - research target (12m)'!$B$53))/SUM('Calc - research target (12m)'!$G$67:$G$69) | F16: =((SUMPRODUCT('Calc - research target (12m)'!$F$67:$F$69,'Calc - research target (12m)'!$G$67:$G$69)-'Calc - research target (12m)'!$F$68*'Calc - research target (12m)'!$G$68)+'Calc - research target (12m)'!$G$68*($A16*F$12+'Calc - research target (12m)'!$B$52/'Calc - research target (12m)'!$B$53))/SUM('Calc - research target (12m)'!$G$67:$G$69)
A17: =Valuation!$B$70+(1) | B17: =((SUMPRODUCT('Calc - research target (12m)'!$F$67:$F$69,'Calc - research target (12m)'!$G$67:$G$69)-'Calc - research target (12m)'!$F$68*'Calc - research target (12m)'!$G$68)+'Calc - research target (12m)'!$G$68*($A17*B$12+'Calc - research target (12m)'!$B$52/'Calc - research target (12m)'!$B$53))/SUM('Calc - research target (12m)'!$G$67:$G$69) | C17: =((SUMPRODUCT('Calc - research target (12m)'!$F$67:$F$69,'Calc - research target (12m)'!$G$67:$G$69)-'Calc - research target (12m)'!$F$68*'Calc - research target (12m)'!$G$68)+'Calc - research target (12m)'!$G$68*($A17*C$12+'Calc - research target (12m)'!$B$52/'Calc - research target (12m)'!$B$53))/SUM('Calc - research target (12m)'!$G$67:$G$69) | D17: =((SUMPRODUCT('Calc - research target (12m)'!$F$67:$F$69,'Calc - research target (12m)'!$G$67:$G$69)-'Calc - research target (12m)'!$F$68*'Calc - research target (12m)'!$G$68)+'Calc - research target (12m)'!$G$68*($A17*D$12+'Calc - research target (12m)'!$B$52/'Calc - research target (12m)'!$B$53))/SUM('Calc - research target (12m)'!$G$67:$G$69) | E17: =((SUMPRODUCT('Calc - research target (12m)'!$F$67:$F$69,'Calc - research target (12m)'!$G$67:$G$69)-'Calc - research target (12m)'!$F$68*'Calc - research target (12m)'!$G$68)+'Calc - research target (12m)'!$G$68*($A17*E$12+'Calc - research target (12m)'!$B$52/'Calc - research target (12m)'!$B$53))/SUM('Calc - research target (12m)'!$G$67:$G$69) | F17: =((SUMPRODUCT('Calc - research target (12m)'!$F$67:$F$69,'Calc - research target (12m)'!$G$67:$G$69)-'Calc - research target (12m)'!$F$68*'Calc - research target (12m)'!$G$68)+'Calc - research target (12m)'!$G$68*($A17*F$12+'Calc - research target (12m)'!$B$52/'Calc - research target (12m)'!$B$53))/SUM('Calc - research target (12m)'!$G$67:$G$69)
A18: =Valuation!$B$70+(2) | B18: =((SUMPRODUCT('Calc - research target (12m)'!$F$67:$F$69,'Calc - research target (12m)'!$G$67:$G$69)-'Calc - research target (12m)'!$F$68*'Calc - research target (12m)'!$G$68)+'Calc - research target (12m)'!$G$68*($A18*B$12+'Calc - research target (12m)'!$B$52/'Calc - research target (12m)'!$B$53))/SUM('Calc - research target (12m)'!$G$67:$G$69) | C18: =((SUMPRODUCT('Calc - research target (12m)'!$F$67:$F$69,'Calc - research target (12m)'!$G$67:$G$69)-'Calc - research target (12m)'!$F$68*'Calc - research target (12m)'!$G$68)+'Calc - research target (12m)'!$G$68*($A18*C$12+'Calc - research target (12m)'!$B$52/'Calc - research target (12m)'!$B$53))/SUM('Calc - research target (12m)'!$G$67:$G$69) | D18: =((SUMPRODUCT('Calc - research target (12m)'!$F$67:$F$69,'Calc - research target (12m)'!$G$67:$G$69)-'Calc - research target (12m)'!$F$68*'Calc - research target (12m)'!$G$68)+'Calc - research target (12m)'!$G$68*($A18*D$12+'Calc - research target (12m)'!$B$52/'Calc - research target (12m)'!$B$53))/SUM('Calc - research target (12m)'!$G$67:$G$69) | E18: =((SUMPRODUCT('Calc - research target (12m)'!$F$67:$F$69,'Calc - research target (12m)'!$G$67:$G$69)-'Calc - research target (12m)'!$F$68*'Calc - research target (12m)'!$G$68)+'Calc - research target (12m)'!$G$68*($A18*E$12+'Calc - research target (12m)'!$B$52/'Calc - research target (12m)'!$B$53))/SUM('Calc - research target (12m)'!$G$67:$G$69) | F18: =((SUMPRODUCT('Calc - research target (12m)'!$F$67:$F$69,'Calc - research target (12m)'!$G$67:$G$69)-'Calc - research target (12m)'!$F$68*'Calc - research target (12m)'!$G$68)+'Calc - research target (12m)'!$G$68*($A18*F$12+'Calc - research target (12m)'!$B$52/'Calc - research target (12m)'!$B$53))/SUM('Calc - research target (12m)'!$G$67:$G$69)
A19: =Valuation!$B$70+(3) | B19: =((SUMPRODUCT('Calc - research target (12m)'!$F$67:$F$69,'Calc - research target (12m)'!$G$67:$G$69)-'Calc - research target (12m)'!$F$68*'Calc - research target (12m)'!$G$68)+'Calc - research target (12m)'!$G$68*($A19*B$12+'Calc - research target (12m)'!$B$52/'Calc - research target (12m)'!$B$53))/SUM('Calc - research target (12m)'!$G$67:$G$69) | C19: =((SUMPRODUCT('Calc - research target (12m)'!$F$67:$F$69,'Calc - research target (12m)'!$G$67:$G$69)-'Calc - research target (12m)'!$F$68*'Calc - research target (12m)'!$G$68)+'Calc - research target (12m)'!$G$68*($A19*C$12+'Calc - research target (12m)'!$B$52/'Calc - research target (12m)'!$B$53))/SUM('Calc - research target (12m)'!$G$67:$G$69) | D19: =((SUMPRODUCT('Calc - research target (12m)'!$F$67:$F$69,'Calc - research target (12m)'!$G$67:$G$69)-'Calc - research target (12m)'!$F$68*'Calc - research target (12m)'!$G$68)+'Calc - research target (12m)'!$G$68*($A19*D$12+'Calc - research target (12m)'!$B$52/'Calc - research target (12m)'!$B$53))/SUM('Calc - research target (12m)'!$G$67:$G$69) | E19: =((SUMPRODUCT('Calc - research target (12m)'!$F$67:$F$69,'Calc - research target (12m)'!$G$67:$G$69)-'Calc - research target (12m)'!$F$68*'Calc - research target (12m)'!$G$68)+'Calc - research target (12m)'!$G$68*($A19*E$12+'Calc - research target (12m)'!$B$52/'Calc - research target (12m)'!$B$53))/SUM('Calc - research target (12m)'!$G$67:$G$69) | F19: =((SUMPRODUCT('Calc - research target (12m)'!$F$67:$F$69,'Calc - research target (12m)'!$G$67:$G$69)-'Calc - research target (12m)'!$F$68*'Calc - research target (12m)'!$G$68)+'Calc - research target (12m)'!$G$68*($A19*F$12+'Calc - research target (12m)'!$B$52/'Calc - research target (12m)'!$B$53))/SUM('Calc - research target (12m)'!$G$67:$G$69)
A22: FY2027E diluted EPS: revenue growth change in every year (down) x EBIT margin change (across)
A23: Growth Δ \ margin Δ | B23: -0.01 | C23: -0.005 | D23: 0 | E23: 0.005 | F23: 0.01
A24: -0.02 | B24: =(Valuation!$B$99*(1+Model!E12+$A24)*(1+Model!F12+$A24)*(Model!F14+B$23)+Valuation!$B$100*(1+Model!E16+$A24)*(1+Model!F16+$A24)*(Model!F18+B$23)+Model!F21+Model!F33)*(1-Model!F63)/Model!F40 | C24: =(Valuation!$B$99*(1+Model!E12+$A24)*(1+Model!F12+$A24)*(Model!F14+C$23)+Valuation!$B$100*(1+Model!E16+$A24)*(1+Model!F16+$A24)*(Model!F18+C$23)+Model!F21+Model!F33)*(1-Model!F63)/Model!F40 | D24: =(Valuation!$B$99*(1+Model!E12+$A24)*(1+Model!F12+$A24)*(Model!F14+D$23)+Valuation!$B$100*(1+Model!E16+$A24)*(1+Model!F16+$A24)*(Model!F18+D$23)+Model!F21+Model!F33)*(1-Model!F63)/Model!F40 | E24: =(Valuation!$B$99*(1+Model!E12+$A24)*(1+Model!F12+$A24)*(Model!F14+E$23)+Valuation!$B$100*(1+Model!E16+$A24)*(1+Model!F16+$A24)*(Model!F18+E$23)+Model!F21+Model!F33)*(1-Model!F63)/Model!F40 | F24: =(Valuation!$B$99*(1+Model!E12+$A24)*(1+Model!F12+$A24)*(Model!F14+F$23)+Valuation!$B$100*(1+Model!E16+$A24)*(1+Model!F16+$A24)*(Model!F18+F$23)+Model!F21+Model!F33)*(1-Model!F63)/Model!F40
A25: -0.01 | B25: =(Valuation!$B$99*(1+Model!E12+$A25)*(1+Model!F12+$A25)*(Model!F14+B$23)+Valuation!$B$100*(1+Model!E16+$A25)*(1+Model!F16+$A25)*(Model!F18+B$23)+Model!F21+Model!F33)*(1-Model!F63)/Model!F40 | C25: =(Valuation!$B$99*(1+Model!E12+$A25)*(1+Model!F12+$A25)*(Model!F14+C$23)+Valuation!$B$100*(1+Model!E16+$A25)*(1+Model!F16+$A25)*(Model!F18+C$23)+Model!F21+Model!F33)*(1-Model!F63)/Model!F40 | D25: =(Valuation!$B$99*(1+Model!E12+$A25)*(1+Model!F12+$A25)*(Model!F14+D$23)+Valuation!$B$100*(1+Model!E16+$A25)*(1+Model!F16+$A25)*(Model!F18+D$23)+Model!F21+Model!F33)*(1-Model!F63)/Model!F40 | E25: =(Valuation!$B$99*(1+Model!E12+$A25)*(1+Model!F12+$A25)*(Model!F14+E$23)+Valuation!$B$100*(1+Model!E16+$A25)*(1+Model!F16+$A25)*(Model!F18+E$23)+Model!F21+Model!F33)*(1-Model!F63)/Model!F40 | F25: =(Valuation!$B$99*(1+Model!E12+$A25)*(1+Model!F12+$A25)*(Model!F14+F$23)+Valuation!$B$100*(1+Model!E16+$A25)*(1+Model!F16+$A25)*(Model!F18+F$23)+Model!F21+Model!F33)*(1-Model!F63)/Model!F40
A26: 0 | B26: =(Valuation!$B$99*(1+Model!E12+$A26)*(1+Model!F12+$A26)*(Model!F14+B$23)+Valuation!$B$100*(1+Model!E16+$A26)*(1+Model!F16+$A26)*(Model!F18+B$23)+Model!F21+Model!F33)*(1-Model!F63)/Model!F40 | C26: =(Valuation!$B$99*(1+Model!E12+$A26)*(1+Model!F12+$A26)*(Model!F14+C$23)+Valuation!$B$100*(1+Model!E16+$A26)*(1+Model!F16+$A26)*(Model!F18+C$23)+Model!F21+Model!F33)*(1-Model!F63)/Model!F40 | D26: =(Valuation!$B$99*(1+Model!E12+$A26)*(1+Model!F12+$A26)*(Model!F14+D$23)+Valuation!$B$100*(1+Model!E16+$A26)*(1+Model!F16+$A26)*(Model!F18+D$23)+Model!F21+Model!F33)*(1-Model!F63)/Model!F40 | E26: =(Valuation!$B$99*(1+Model!E12+$A26)*(1+Model!F12+$A26)*(Model!F14+E$23)+Valuation!$B$100*(1+Model!E16+$A26)*(1+Model!F16+$A26)*(Model!F18+E$23)+Model!F21+Model!F33)*(1-Model!F63)/Model!F40 | F26: =(Valuation!$B$99*(1+Model!E12+$A26)*(1+Model!F12+$A26)*(Model!F14+F$23)+Valuation!$B$100*(1+Model!E16+$A26)*(1+Model!F16+$A26)*(Model!F18+F$23)+Model!F21+Model!F33)*(1-Model!F63)/Model!F40
A27: 0.01 | B27: =(Valuation!$B$99*(1+Model!E12+$A27)*(1+Model!F12+$A27)*(Model!F14+B$23)+Valuation!$B$100*(1+Model!E16+$A27)*(1+Model!F16+$A27)*(Model!F18+B$23)+Model!F21+Model!F33)*(1-Model!F63)/Model!F40 | C27: =(Valuation!$B$99*(1+Model!E12+$A27)*(1+Model!F12+$A27)*(Model!F14+C$23)+Valuation!$B$100*(1+Model!E16+$A27)*(1+Model!F16+$A27)*(Model!F18+C$23)+Model!F21+Model!F33)*(1-Model!F63)/Model!F40 | D27: =(Valuation!$B$99*(1+Model!E12+$A27)*(1+Model!F12+$A27)*(Model!F14+D$23)+Valuation!$B$100*(1+Model!E16+$A27)*(1+Model!F16+$A27)*(Model!F18+D$23)+Model!F21+Model!F33)*(1-Model!F63)/Model!F40 | E27: =(Valuation!$B$99*(1+Model!E12+$A27)*(1+Model!F12+$A27)*(Model!F14+E$23)+Valuation!$B$100*(1+Model!E16+$A27)*(1+Model!F16+$A27)*(Model!F18+E$23)+Model!F21+Model!F33)*(1-Model!F63)/Model!F40 | F27: =(Valuation!$B$99*(1+Model!E12+$A27)*(1+Model!F12+$A27)*(Model!F14+F$23)+Valuation!$B$100*(1+Model!E16+$A27)*(1+Model!F16+$A27)*(Model!F18+F$23)+Model!F21+Model!F33)*(1-Model!F63)/Model!F40
A28: 0.02 | B28: =(Valuation!$B$99*(1+Model!E12+$A28)*(1+Model!F12+$A28)*(Model!F14+B$23)+Valuation!$B$100*(1+Model!E16+$A28)*(1+Model!F16+$A28)*(Model!F18+B$23)+Model!F21+Model!F33)*(1-Model!F63)/Model!F40 | C28: =(Valuation!$B$99*(1+Model!E12+$A28)*(1+Model!F12+$A28)*(Model!F14+C$23)+Valuation!$B$100*(1+Model!E16+$A28)*(1+Model!F16+$A28)*(Model!F18+C$23)+Model!F21+Model!F33)*(1-Model!F63)/Model!F40 | D28: =(Valuation!$B$99*(1+Model!E12+$A28)*(1+Model!F12+$A28)*(Model!F14+D$23)+Valuation!$B$100*(1+Model!E16+$A28)*(1+Model!F16+$A28)*(Model!F18+D$23)+Model!F21+Model!F33)*(1-Model!F63)/Model!F40 | E28: =(Valuation!$B$99*(1+Model!E12+$A28)*(1+Model!F12+$A28)*(Model!F14+E$23)+Valuation!$B$100*(1+Model!E16+$A28)*(1+Model!F16+$A28)*(Model!F18+E$23)+Model!F21+Model!F33)*(1-Model!F63)/Model!F40 | F28: =(Valuation!$B$99*(1+Model!E12+$A28)*(1+Model!F12+$A28)*(Model!F14+F$23)+Valuation!$B$100*(1+Model!E16+$A28)*(1+Model!F16+$A28)*(Model!F18+F$23)+Model!F21+Model!F33)*(1-Model!F63)/Model!F40
A30: Net interest and the share count are held at the base case in table 3.

Sheet Distribution
A1: AMZN: 12-month distribution (mix of lognormals around each scenario value)
A3: Scenario | B3: Probability | C3: Value at target date | D3: Story
A4: bear | B4: =Valuation!B94 | C4: ='Calc - bear'!$F$70 | D4: =Valuation!J94
A5: base | B5: =Valuation!B95 | C5: ='Calc - base'!$F$70 | D5: =Valuation!J95
A6: bull | B6: =Valuation!B96 | C6: ='Calc - bull'!$F$70 | D6: =Valuation!J96
A8: Probabilities sum to | B8: =SUM(B4:B6)
A9: Spread within each scenario | B9: =Valuation!$B$66
A10: Probability-weighted mean | B10: =($B$4*$C$4+$B$5*$C$5+$B$6*$C$6)*EXP($B$9^2/2)
A12: Quantile | B12: Price
A13: Median (model target) | B13: =SQRT(A60*B60)
A14: 10th percentile | B14: =SQRT(D60*E60)
A15: 25th percentile | B15: =SQRT(G60*H60)
A16: 75th percentile | B16: =SQRT(J60*K60)
A17: 90th percentile | B17: =SQRT(M60*N60)
A19: Each quantile solved by bisection (block: low, high, probability above the midpoint)
A20: Median (model target): low | B20: high | C20: P(above mid) | D20: 10th percentile: low | E20: high | F20: P(above mid) | G20: 25th percentile: low | H20: high | I20: P(above mid) | J20: 75th percentile: low | K20: high | L20: P(above mid) | M20: 90th percentile: low | N20: high | O20: P(above mid)
A21: =MIN($C$4,$C$5,$C$6)*0.2 | B21: =MAX($C$4,$C$5,$C$6)*4 | C21: =SUMPRODUCT($B$4:$B$6,1-NORMSDIST((LN(SQRT(A21*B21))-LN($C$4:$C$6))/$B$9)) | D21: =MIN($C$4,$C$5,$C$6)*0.2 | E21: =MAX($C$4,$C$5,$C$6)*4 | F21: =SUMPRODUCT($B$4:$B$6,1-NORMSDIST((LN(SQRT(D21*E21))-LN($C$4:$C$6))/$B$9)) | G21: =MIN($C$4,$C$5,$C$6)*0.2 | H21: =MAX($C$4,$C$5,$C$6)*4 | I21: =SUMPRODUCT($B$4:$B$6,1-NORMSDIST((LN(SQRT(G21*H21))-LN($C$4:$C$6))/$B$9)) | J21: =MIN($C$4,$C$5,$C$6)*0.2 | K21: =MAX($C$4,$C$5,$C$6)*4 | L21: =SUMPRODUCT($B$4:$B$6,1-NORMSDIST((LN(SQRT(J21*K21))-LN($C$4:$C$6))/$B$9)) | M21: =MIN($C$4,$C$5,$C$6)*0.2 | N21: =MAX($C$4,$C$5,$C$6)*4 | O21: =SUMPRODUCT($B$4:$B$6,1-NORMSDIST((LN(SQRT(M21*N21))-LN($C$4:$C$6))/$B$9))
A22: =IF(C21>0.5,SQRT(A21*B21),A21) | B22: =IF(C21>0.5,B21,SQRT(A21*B21)) | C22: =SUMPRODUCT($B$4:$B$6,1-NORMSDIST((LN(SQRT(A22*B22))-LN($C$4:$C$6))/$B$9)) | D22: =IF(F21>0.9,SQRT(D21*E21),D21) | E22: =IF(F21>0.9,E21,SQRT(D21*E21)) | F22: =SUMPRODUCT($B$4:$B$6,1-NORMSDIST((LN(SQRT(D22*E22))-LN($C$4:$C$6))/$B$9)) | G22: =IF(I21>0.75,SQRT(G21*H21),G21) | H22: =IF(I21>0.75,H21,SQRT(G21*H21)) | I22: =SUMPRODUCT($B$4:$B$6,1-NORMSDIST((LN(SQRT(G22*H22))-LN($C$4:$C$6))/$B$9)) | J22: =IF(L21>0.25,SQRT(J21*K21),J21) | K22: =IF(L21>0.25,K21,SQRT(J21*K21)) | L22: =SUMPRODUCT($B$4:$B$6,1-NORMSDIST((LN(SQRT(J22*K22))-LN($C$4:$C$6))/$B$9)) | M22: =IF(O21>0.09999999999999998,SQRT(M21*N21),M21) | N22: =IF(O21>0.09999999999999998,N21,SQRT(M21*N21)) | O22: =SUMPRODUCT($B$4:$B$6,1-NORMSDIST((LN(SQRT(M22*N22))-LN($C$4:$C$6))/$B$9))
A23: =IF(C22>0.5,SQRT(A22*B22),A22) | B23: =IF(C22>0.5,B22,SQRT(A22*B22)) | C23: =SUMPRODUCT($B$4:$B$6,1-NORMSDIST((LN(SQRT(A23*B23))-LN($C$4:$C$6))/$B$9)) | D23: =IF(F22>0.9,SQRT(D22*E22),D22) | E23: =IF(F22>0.9,E22,SQRT(D22*E22)) | F23: =SUMPRODUCT($B$4:$B$6,1-NORMSDIST((LN(SQRT(D23*E23))-LN($C$4:$C$6))/$B$9)) | G23: =IF(I22>0.75,SQRT(G22*H22),G22) | H23: =IF(I22>0.75,H22,SQRT(G22*H22)) | I23: =SUMPRODUCT($B$4:$B$6,1-NORMSDIST((LN(SQRT(G23*H23))-LN($C$4:$C$6))/$B$9)) | J23: =IF(L22>0.25,SQRT(J22*K22),J22) | K23: =IF(L22>0.25,K22,SQRT(J22*K22)) | L23: =SUMPRODUCT($B$4:$B$6,1-NORMSDIST((LN(SQRT(J23*K23))-LN($C$4:$C$6))/$B$9)) | M23: =IF(O22>0.09999999999999998,SQRT(M22*N22),M22) | N23: =IF(O22>0.09999999999999998,N22,SQRT(M22*N22)) | O23: =SUMPRODUCT($B$4:$B$6,1-NORMSDIST((LN(SQRT(M23*N23))-LN($C$4:$C$6))/$B$9))
A24: =IF(C23>0.5,SQRT(A23*B23),A23) | B24: =IF(C23>0.5,B23,SQRT(A23*B23)) | C24: =SUMPRODUCT($B$4:$B$6,1-NORMSDIST((LN(SQRT(A24*B24))-LN($C$4:$C$6))/$B$9)) | D24: =IF(F23>0.9,SQRT(D23*E23),D23) | E24: =IF(F23>0.9,E23,SQRT(D23*E23)) | F24: =SUMPRODUCT($B$4:$B$6,1-NORMSDIST((LN(SQRT(D24*E24))-LN($C$4:$C$6))/$B$9)) | G24: =IF(I23>0.75,SQRT(G23*H23),G23) | H24: =IF(I23>0.75,H23,SQRT(G23*H23)) | I24: =SUMPRODUCT($B$4:$B$6,1-NORMSDIST((LN(SQRT(G24*H24))-LN($C$4:$C$6))/$B$9)) | J24: =IF(L23>0.25,SQRT(J23*K23),J23) | K24: =IF(L23>0.25,K23,SQRT(J23*K23)) | L24: =SUMPRODUCT($B$4:$B$6,1-NORMSDIST((LN(SQRT(J24*K24))-LN($C$4:$C$6))/$B$9)) | M24: =IF(O23>0.09999999999999998,SQRT(M23*N23),M23) | N24: =IF(O23>0.09999999999999998,N23,SQRT(M23*N23)) | O24: =SUMPRODUCT($B$4:$B$6,1-NORMSDIST((LN(SQRT(M24*N24))-LN($C$4:$C$6))/$B$9))
A25: =IF(C24>0.5,SQRT(A24*B24),A24) | B25: =IF(C24>0.5,B24,SQRT(A24*B24)) | C25: =SUMPRODUCT($B$4:$B$6,1-NORMSDIST((LN(SQRT(A25*B25))-LN($C$4:$C$6))/$B$9)) | D25: =IF(F24>0.9,SQRT(D24*E24),D24) | E25: =IF(F24>0.9,E24,SQRT(D24*E24)) | F25: =SUMPRODUCT($B$4:$B$6,1-NORMSDIST((LN(SQRT(D25*E25))-LN($C$4:$C$6))/$B$9)) | G25: =IF(I24>0.75,SQRT(G24*H24),G24) | H25: =IF(I24>0.75,H24,SQRT(G24*H24)) | I25: =SUMPRODUCT($B$4:$B$6,1-NORMSDIST((LN(SQRT(G25*H25))-LN($C$4:$C$6))/$B$9)) | J25: =IF(L24>0.25,SQRT(J24*K24),J24) | K25: =IF(L24>0.25,K24,SQRT(J24*K24)) | L25: =SUMPRODUCT($B$4:$B$6,1-NORMSDIST((LN(SQRT(J25*K25))-LN($C$4:$C$6))/$B$9)) | M25: =IF(O24>0.09999999999999998,SQRT(M24*N24),M24) | N25: =IF(O24>0.09999999999999998,N24,SQRT(M24*N24)) | O25: =SUMPRODUCT($B$4:$B$6,1-NORMSDIST((LN(SQRT(M25*N25))-LN($C$4:$C$6))/$B$9))
A26: =IF(C25>0.5,SQRT(A25*B25),A25) | B26: =IF(C25>0.5,B25,SQRT(A25*B25)) | C26: =SUMPRODUCT($B$4:$B$6,1-NORMSDIST((LN(SQRT(A26*B26))-LN($C$4:$C$6))/$B$9)) | D26: =IF(F25>0.9,SQRT(D25*E25),D25) | E26: =IF(F25>0.9,E25,SQRT(D25*E25)) | F26: =SUMPRODUCT($B$4:$B$6,1-NORMSDIST((LN(SQRT(D26*E26))-LN($C$4:$C$6))/$B$9)) | G26: =IF(I25>0.75,SQRT(G25*H25),G25) | H26: =IF(I25>0.75,H25,SQRT(G25*H25)) | I26: =SUMPRODUCT($B$4:$B$6,1-NORMSDIST((LN(SQRT(G26*H26))-LN($C$4:$C$6))/$B$9)) | J26: =IF(L25>0.25,SQRT(J25*K25),J25) | K26: =IF(L25>0.25,K25,SQRT(J25*K25)) | L26: =SUMPRODUCT($B$4:$B$6,1-NORMSDIST((LN(SQRT(J26*K26))-LN($C$4:$C$6))/$B$9)) | M26: =IF(O25>0.09999999999999998,SQRT(M25*N25),M25) | N26: =IF(O25>0.09999999999999998,N25,SQRT(M25*N25)) | O26: =SUMPRODUCT($B$4:$B$6,1-NORMSDIST((LN(SQRT(M26*N26))-LN($C$4:$C$6))/$B$9))
A27: =IF(C26>0.5,SQRT(A26*B26),A26) | B27: =IF(C26>0.5,B26,SQRT(A26*B26)) | C27: =SUMPRODUCT($B$4:$B$6,1-NORMSDIST((LN(SQRT(A27*B27))-LN($C$4:$C$6))/$B$9)) | D27: =IF(F26>0.9,SQRT(D26*E26),D26) | E27: =IF(F26>0.9,E26,SQRT(D26*E26)) | F27: =SUMPRODUCT($B$4:$B$6,1-NORMSDIST((LN(SQRT(D27*E27))-LN($C$4:$C$6))/$B$9)) | G27: =IF(I26>0.75,SQRT(G26*H26),G26) | H27: =IF(I26>0.75,H26,SQRT(G26*H26)) | I27: =SUMPRODUCT($B$4:$B$6,1-NORMSDIST((LN(SQRT(G27*H27))-LN($C$4:$C$6))/$B$9)) | J27: =IF(L26>0.25,SQRT(J26*K26),J26) | K27: =IF(L26>0.25,K26,SQRT(J26*K26)) | L27: =SUMPRODUCT($B$4:$B$6,1-NORMSDIST((LN(SQRT(J27*K27))-LN($C$4:$C$6))/$B$9)) | M27: =IF(O26>0.09999999999999998,SQRT(M26*N26),M26) | N27: =IF(O26>0.09999999999999998,N26,SQRT(M26*N26)) | O27: =SUMPRODUCT($B$4:$B$6,1-NORMSDIST((LN(SQRT(M27*N27))-LN($C$4:$C$6))/$B$9))
A28: =IF(C27>0.5,SQRT(A27*B27),A27) | B28: =IF(C27>0.5,B27,SQRT(A27*B27)) | C28: =SUMPRODUCT($B$4:$B$6,1-NORMSDIST((LN(SQRT(A28*B28))-LN($C$4:$C$6))/$B$9)) | D28: =IF(F27>0.9,SQRT(D27*E27),D27) | E28: =IF(F27>0.9,E27,SQRT(D27*E27)) | F28: =SUMPRODUCT($B$4:$B$6,1-NORMSDIST((LN(SQRT(D28*E28))-LN($C$4:$C$6))/$B$9)) | G28: =IF(I27>0.75,SQRT(G27*H27),G27) | H28: =IF(I27>0.75,H27,SQRT(G27*H27)) | I28: =SUMPRODUCT($B$4:$B$6,1-NORMSDIST((LN(SQRT(G28*H28))-LN($C$4:$C$6))/$B$9)) | J28: =IF(L27>0.25,SQRT(J27*K27),J27) | K28: =IF(L27>0.25,K27,SQRT(J27*K27)) | L28: =SUMPRODUCT($B$4:$B$6,1-NORMSDIST((LN(SQRT(J28*K28))-LN($C$4:$C$6))/$B$9)) | M28: =IF(O27>0.09999999999999998,SQRT(M27*N27),M27) | N28: =IF(O27>0.09999999999999998,N27,SQRT(M27*N27)) | O28: =SUMPRODUCT($B$4:$B$6,1-NORMSDIST((LN(SQRT(M28*N28))-LN($C$4:$C$6))/$B$9))
A29: =IF(C28>0.5,SQRT(A28*B28),A28) | B29: =IF(C28>0.5,B28,SQRT(A28*B28)) | C29: =SUMPRODUCT($B$4:$B$6,1-NORMSDIST((LN(SQRT(A29*B29))-LN($C$4:$C$6))/$B$9)) | D29: =IF(F28>0.9,SQRT(D28*E28),D28) | E29: =IF(F28>0.9,E28,SQRT(D28*E28)) | F29: =SUMPRODUCT($B$4:$B$6,1-NORMSDIST((LN(SQRT(D29*E29))-LN($C$4:$C$6))/$B$9)) | G29: =IF(I28>0.75,SQRT(G28*H28),G28) | H29: =IF(I28>0.75,H28,SQRT(G28*H28)) | I29: =SUMPRODUCT($B$4:$B$6,1-NORMSDIST((LN(SQRT(G29*H29))-LN($C$4:$C$6))/$B$9)) | J29: =IF(L28>0.25,SQRT(J28*K28),J28) | K29: =IF(L28>0.25,K28,SQRT(J28*K28)) | L29: =SUMPRODUCT($B$4:$B$6,1-NORMSDIST((LN(SQRT(J29*K29))-LN($C$4:$C$6))/$B$9)) | M29: =IF(O28>0.09999999999999998,SQRT(M28*N28),M28) | N29: =IF(O28>0.09999999999999998,N28,SQRT(M28*N28)) | O29: =SUMPRODUCT($B$4:$B$6,1-NORMSDIST((LN(SQRT(M29*N29))-LN($C$4:$C$6))/$B$9))
A30: =IF(C29>0.5,SQRT(A29*B29),A29) | B30: =IF(C29>0.5,B29,SQRT(A29*B29)) | C30: =SUMPRODUCT($B$4:$B$6,1-NORMSDIST((LN(SQRT(A30*B30))-LN($C$4:$C$6))/$B$9)) | D30: =IF(F29>0.9,SQRT(D29*E29),D29) | E30: =IF(F29>0.9,E29,SQRT(D29*E29)) | F30: =SUMPRODUCT($B$4:$B$6,1-NORMSDIST((LN(SQRT(D30*E30))-LN($C$4:$C$6))/$B$9)) | G30: =IF(I29>0.75,SQRT(G29*H29),G29) | H30: =IF(I29>0.75,H29,SQRT(G29*H29)) | I30: =SUMPRODUCT($B$4:$B$6,1-NORMSDIST((LN(SQRT(G30*H30))-LN($C$4:$C$6))/$B$9)) | J30: =IF(L29>0.25,SQRT(J29*K29),J29) | K30: =IF(L29>0.25,K29,SQRT(J29*K29)) | L30: =SUMPRODUCT($B$4:$B$6,1-NORMSDIST((LN(SQRT(J30*K30))-LN($C$4:$C$6))/$B$9)) | M30: =IF(O29>0.09999999999999998,SQRT(M29*N29),M29) | N30: =IF(O29>0.09999999999999998,N29,SQRT(M29*N29)) | O30: =SUMPRODUCT($B$4:$B$6,1-NORMSDIST((LN(SQRT(M30*N30))-LN($C$4:$C$6))/$B$9))
A31: =IF(C30>0.5,SQRT(A30*B30),A30) | B31: =IF(C30>0.5,B30,SQRT(A30*B30)) | C31: =SUMPRODUCT($B$4:$B$6,1-NORMSDIST((LN(SQRT(A31*B31))-LN($C$4:$C$6))/$B$9)) | D31: =IF(F30>0.9,SQRT(D30*E30),D30) | E31: =IF(F30>0.9,E30,SQRT(D30*E30)) | F31: =SUMPRODUCT($B$4:$B$6,1-NORMSDIST((LN(SQRT(D31*E31))-LN($C$4:$C$6))/$B$9)) | G31: =IF(I30>0.75,SQRT(G30*H30),G30) | H31: =IF(I30>0.75,H30,SQRT(G30*H30)) | I31: =SUMPRODUCT($B$4:$B$6,1-NORMSDIST((LN(SQRT(G31*H31))-LN($C$4:$C$6))/$B$9)) | J31: =IF(L30>0.25,SQRT(J30*K30),J30) | K31: =IF(L30>0.25,K30,SQRT(J30*K30)) | L31: =SUMPRODUCT($B$4:$B$6,1-NORMSDIST((LN(SQRT(J31*K31))-LN($C$4:$C$6))/$B$9)) | M31: =IF(O30>0.09999999999999998,SQRT(M30*N30),M30) | N31: =IF(O30>0.09999999999999998,N30,SQRT(M30*N30)) | O31: =SUMPRODUCT($B$4:$B$6,1-NORMSDIST((LN(SQRT(M31*N31))-LN($C$4:$C$6))/$B$9))
A32: =IF(C31>0.5,SQRT(A31*B31),A31) | B32: =IF(C31>0.5,B31,SQRT(A31*B31)) | C32: =SUMPRODUCT($B$4:$B$6,1-NORMSDIST((LN(SQRT(A32*B32))-LN($C$4:$C$6))/$B$9)) | D32: =IF(F31>0.9,SQRT(D31*E31),D31) | E32: =IF(F31>0.9,E31,SQRT(D31*E31)) | F32: =SUMPRODUCT($B$4:$B$6,1-NORMSDIST((LN(SQRT(D32*E32))-LN($C$4:$C$6))/$B$9)) | G32: =IF(I31>0.75,SQRT(G31*H31),G31) | H32: =IF(I31>0.75,H31,SQRT(G31*H31)) | I32: =SUMPRODUCT($B$4:$B$6,1-NORMSDIST((LN(SQRT(G32*H32))-LN($C$4:$C$6))/$B$9)) | J32: =IF(L31>0.25,SQRT(J31*K31),J31) | K32: =IF(L31>0.25,K31,SQRT(J31*K31)) | L32: =SUMPRODUCT($B$4:$B$6,1-NORMSDIST((LN(SQRT(J32*K32))-LN($C$4:$C$6))/$B$9)) | M32: =IF(O31>0.09999999999999998,SQRT(M31*N31),M31) | N32: =IF(O31>0.09999999999999998,N31,SQRT(M31*N31)) | O32: =SUMPRODUCT($B$4:$B$6,1-NORMSDIST((LN(SQRT(M32*N32))-LN($C$4:$C$6))/$B$9))
A33: =IF(C32>0.5,SQRT(A32*B32),A32) | B33: =IF(C32>0.5,B32,SQRT(A32*B32)) | C33: =SUMPRODUCT($B$4:$B$6,1-NORMSDIST((LN(SQRT(A33*B33))-LN($C$4:$C$6))/$B$9)) | D33: =IF(F32>0.9,SQRT(D32*E32),D32) | E33: =IF(F32>0.9,E32,SQRT(D32*E32)) | F33: =SUMPRODUCT($B$4:$B$6,1-NORMSDIST((LN(SQRT(D33*E33))-LN($C$4:$C$6))/$B$9)) | G33: =IF(I32>0.75,SQRT(G32*H32),G32) | H33: =IF(I32>0.75,H32,SQRT(G32*H32)) | I33: =SUMPRODUCT($B$4:$B$6,1-NORMSDIST((LN(SQRT(G33*H33))-LN($C$4:$C$6))/$B$9)) | J33: =IF(L32>0.25,SQRT(J32*K32),J32) | K33: =IF(L32>0.25,K32,SQRT(J32*K32)) | L33: =SUMPRODUCT($B$4:$B$6,1-NORMSDIST((LN(SQRT(J33*K33))-LN($C$4:$C$6))/$B$9)) | M33: =IF(O32>0.09999999999999998,SQRT(M32*N32),M32) | N33: =IF(O32>0.09999999999999998,N32,SQRT(M32*N32)) | O33: =SUMPRODUCT($B$4:$B$6,1-NORMSDIST((LN(SQRT(M33*N33))-LN($C$4:$C$6))/$B$9))
... A60: =IF(C59>0.5,SQRT(A59*B59),A59) | B60: =IF(C59>0.5,B59,SQRT(A59*B59)) | C60: =SUMPRODUCT($B$4:$B$6,1-NORMSDIST((LN(SQRT(A60*B60))-LN($C$4:$C$6))/$B$9)) | D60: =IF(F59>0.9,SQRT(D59*E59),D59) | E60: =IF(F59>0.9,E59,SQRT(D59*E59)) | F60: =SUMPRODUCT($B$4:$B$6,1-NORMSDIST((LN(SQRT(D60*E60))-LN($C$4:$C$6))/$B$9)) | G60: =IF(I59>0.75,SQRT(G59*H59),G59) | H60: =IF(I59>0.75,H59,SQRT(G59*H59)) | I60: =SUMPRODUCT($B$4:$B$6,1-NORMSDIST((LN(SQRT(G60*H60))-LN($C$4:$C$6))/$B$9)) | J60: =IF(L59>0.25,SQRT(J59*K59),J59) | K60: =IF(L59>0.25,K59,SQRT(J59*K59)) | L60: =SUMPRODUCT($B$4:$B$6,1-NORMSDIST((LN(SQRT(J60*K60))-LN($C$4:$C$6))/$B$9)) | M60: =IF(O59>0.09999999999999998,SQRT(M59*N59),M59) | N60: =IF(O59>0.09999999999999998,N59,SQRT(M59*N59)) | O60: =SUMPRODUCT($B$4:$B$6,1-NORMSDIST((LN(SQRT(M60*N60))-LN($C$4:$C$6))/$B$9))

Sheet Calc - research target (12m)
A1: AMZN engine calculation: research target (12m) (reconciled set, no scenario deltas)
A2: Machinery behind the Valuation and Distribution tabs; drivers come from Model, assumptions from Valuation.
A4: Scenario Growth Δ | B4: 0
A5: Scenario Margin Δ | B5: 0
A6: Scenario Multiple Δ (turns) | B6: 0
A7: Scenario WACC Δ | B7: 0
A8: Scenario Multiple %Δ | B8: 0
A9: Scenario Stated EPS/FCF %Δ | B9: 0
A10: Scenario Custom %Δ | B10: 0
A12: WACC | B12: =Valuation!$B$51+B7
A13: Years from last FY end to target date | B13: =(Valuation!$B$45-Valuation!$B$49)/365.25
A14: Years from last FY end to balance date | B14: =(Valuation!$B$55-Valuation!$B$49)/365.25
A15: Years from last FY end to share count date | B15: =(Valuation!$B$61-Valuation!$B$49)/365.25
A16: Projected years | B16: 3
A18: Projection | B18: Base | C18: =Model!E5 | D18: =Model!F5 | E18: =Model!G5
A19: Year index | B19: 0 | C19: 1 | D19: 2 | E19: 3
A20: Period end | C20: =Valuation!$B$49+ROUND(365.25*C19,0) | D20: =Valuation!$B$49+ROUND(365.25*D19,0) | E20: =Valuation!$B$49+ROUND(365.25*E19,0)
A21: Revenue growth | C21: =C22/B22-1 | D21: =D22/C22-1 | E21: =E22/D22-1
A22: Revenue | B22: =Valuation!$B$50 | C22: =C139 | D22: =D139 | E22: =E139
A23: EBIT margin | C23: =C24/C22 | D23: =D24/D22 | E23: =E24/E22
A24: EBIT | C24: =C142 | D24: =D142 | E24: =E142
A25: Tax rate | C25: =Model!E63 | D25: =Model!F63 | E25: =Model!G63
A26: NOPAT | C26: =C24*(1-C25) | D26: =D24*(1-D25) | E26: =E24*(1-E25)
A27: D&A | C27: =C22*(Model!E64) | D27: =D22*(Model!F64) | E27: =E22*(Model!G64)
A28: Capex | C28: =C22*(Model!E65) | D28: =D22*(Model!F65) | E28: =E22*(Model!G65)
A29: Working capital increase | C29: =(Model!E66)*(C22-B22) | D29: =(Model!F66)*(D22-C22) | E29: =(Model!G66)*(E22-D22)
A30: Stock comp | C30: =C22*(Model!E67) | D30: =D22*(Model!F67) | E30: =E22*(Model!G67)
A31: Free cash flow to firm | C31: =C26+C27-C28-C29-IF(AND(Valuation!$B$47="adjusted",Valuation!$B$48="cost"),C30*(1-C25),0) | D31: =D26+D27-D28-D29-IF(AND(Valuation!$B$47="adjusted",Valuation!$B$48="cost"),D30*(1-D25),0) | E31: =E26+E27-E28-E29-IF(AND(Valuation!$B$47="adjusted",Valuation!$B$48="cost"),E30*(1-E25),0)
A32: EBITDA | C32: =C24+C27 | D32: =D24+D27 | E32: =E24+E27
A33: Adj. EBITDA | C33: =C24+C27+C22*(Model!E71) | D33: =D24+D27+D22*(Model!F71) | E33: =E24+E27+E22*(Model!G71)
A34: Shareholder returns + other uses | C34: =C22*Model!E69+Model!E68+Model!E70 | D34: =D22*Model!F69+Model!F68+Model!F70 | E34: =E22*Model!G69+Model!G68+Model!G70
A35: Share of year after target date | C35: =IF(C19<=$B$13,0,C19-MAX(C19-1,$B$13)) | D35: =IF(D19<=$B$13,0,D19-MAX(D19-1,$B$13)) | E35: =IF(E19<=$B$13,0,E19-MAX(E19-1,$B$13))
A36: PV at target date of FCFF | C36: =IF(C35=0,0,C31*C35/(1+$B$12)^(C19-$B$13)) | D36: =IF(D35=0,0,D31*D35/(1+$B$12)^(D19-$B$13)) | E36: =IF(E35=0,0,E31*E35/(1+$B$12)^(E19-$B$13))
A37: Overlap: balance date to target date | C37: =MAX(0,MIN(C19,$B$13)-MAX(C19-1,$B$14)) | D37: =MAX(0,MIN(D19,$B$13)-MAX(D19-1,$B$14)) | E37: =MAX(0,MIN(E19,$B$13)-MAX(E19-1,$B$14))
A38: NTM weight at target date | C38: =MAX(0,MIN(C19,$B$13+1)-MAX(C19-1,$B$13)) | D38: =MAX(0,MIN(D19,$B$13+1)-MAX(D19-1,$B$13)) | E38: =MAX(0,MIN(E19,$B$13+1)-MAX(E19-1,$B$13))
A39: LTM weight at target date | B39: =MAX(0,MIN(0,$B$13)-MAX(-1,$B$13-1)) | C39: =MAX(0,MIN(C19,$B$13)-MAX(C19-1,$B$13-1)) | D39: =MAX(0,MIN(D19,$B$13)-MAX(D19-1,$B$13-1)) | E39: =MAX(0,MIN(E19,$B$13)-MAX(E19-1,$B$13-1))
A41: Value at the target date
A42: PV of free cash flow after the target date | B42: =SUM($C$36:$E$36)
A43: Terminal value at final year | B43: =IF(Valuation!$B$52="exit_multiple",Valuation!$B$54*E32,E31*(1+Valuation!$B$53)/($B$12-Valuation!$B$53))
A44: PV of terminal value at target date | B44: =B43/(1+$B$12)^($B$16-$B$13)
A45: DCF enterprise value at target date | B45: =B42+B44
A46: Terminal value share of DCF | B46: =B44/B45
A47: Free cash flow earned, balance date to target date | B47: =SUMPRODUCT($C$37:$E$37,$C$31:$E$31)
A48: Shareholder returns + other uses paid | B48: =SUMPRODUCT($C$37:$E$37,$C$34:$E$34)
A49: Interest drag on net debt | B49: =Valuation!$B$58*(1-$C$25)*MAX(Valuation!$B$56,0)*MAX($B$13-$B$14,0)
A50: Net debt at target date | B50: =IF(Valuation!$B$59="",Valuation!$B$56-B47+B49+B48,Valuation!$B$59)
A51: Minority interests | B51: =Valuation!$B$57
A52: Adjustments (probability-weighted) | B52: =(Valuation!B79)*Valuation!C79+(Valuation!B80)*Valuation!C80+(Valuation!B81)*Valuation!C81+(Valuation!B82)*Valuation!C82+(Valuation!B83)*Valuation!C83+(Valuation!B84)*Valuation!C84+(Valuation!B85)*Valuation!C85+(Valuation!B86)*Valuation!C86+(Valuation!B87)*Valuation!C87+(Valuation!B88)*Valuation!C88+0
A53: Diluted shares at target date (M) | B53: =IF(Valuation!$B$63="",Valuation!$B$60*(1+Valuation!$B$62)^MAX($B$13-$B$15,0),Valuation!$B$63)
A54: After-tax interest on target-date net debt | B54: =Valuation!$B$58*(1-$C$25)*MAX(B50,0)
A55: Check: WACC vs terminal growth | B55: =IF(AND(Valuation!$B$52<>"exit_multiple",$B$12<=Valuation!$B$53+0.01),"WACC must exceed terminal growth by 1 point","ok")
A56: Check: projection length | B56: =IF(OR($B$13>=$B$16-1,$B$13+1>$B$16),"add projected years past the target date","ok")
A58: Metric at target date | B58: Next 12 months | C58: Last 12 months
A59: Revenue | B59: =SUMPRODUCT($C$38:$E$38,$C$22:$E$22) | C59: =SUMPRODUCT($C$39:$E$39,$C$22:$E$22)+$B$39*$B$22
A60: EBIT | B60: =SUMPRODUCT($C$38:$E$38,$C$24:$E$24) | C60: =SUMPRODUCT($C$39:$E$39,$C$24:$E$24)
A61: EBITDA | B61: =SUMPRODUCT($C$38:$E$38,$C$32:$E$32) | C61: =SUMPRODUCT($C$39:$E$39,$C$32:$E$32)
A62: Adj. EBITDA | B62: =SUMPRODUCT($C$38:$E$38,$C$33:$E$33) | C62: =SUMPRODUCT($C$39:$E$39,$C$33:$E$33)
A63: NOPAT | B63: =SUMPRODUCT($C$38:$E$38,$C$26:$E$26) | C63: =SUMPRODUCT($C$39:$E$39,$C$26:$E$26)
A64: Free cash flow to firm | B64: =SUMPRODUCT($C$38:$E$38,$C$31:$E$31) | C64: =SUMPRODUCT($C$39:$E$39,$C$31:$E$31)
A66: Valuation method | B66: Metric | C66: Multiple used | D66: Basis | E66: Metric at target date | F66: Value per share | G66: Weight | H66: Metric key | I66: Metric shown (stated per-share figure when used)
A67: DCF (cash flow to target date + terminal) | F67: =((B45)-$B$50-$B$51+$B$52)/$B$53 | G67: =Valuation!$B$64
A68: ="Multiple: "&Valuation!A70&" ("&Valuation!D70&")" | B68: =Valuation!A70 | C68: =IF(B68="FCF yield",(Valuation!B70)*(1-$B$8),(Valuation!B70)+IF(B68="EV/sales",0.1,1)*$B$6) | D68: =Valuation!D70 | E68: =IF(D68="ltm",CHOOSE(H68,$C$59,$C$60,$C$61,$C$62,$C$63,$C$64),CHOOSE(H68,$B$59,$B$60,$B$61,$B$62,$B$63,$B$64)) | F68: =IF(OR(B68="EV/EBITDA",B68="EV/sales",B68="EV/EBIT"),((C68*E68)-$B$50-$B$51+$B$52)/$B$53,IF(B68="P/E",IF(Valuation!F70<>"",C68*(Valuation!F70)*(1+$B$9),C68*(E68-$B$54)/$B$53),IF(Valuation!G70<>"",(Valuation!G70)*(1+$B$9)/C68,(E68-IF(Valuation!H70,$B$54,0))/C68/$B$53))+$B$52/$B$53) | G68: =Valuation!C70 | H68: =IF(B68="EV/sales",1,IF(B68="EV/EBIT",2,IF(B68="EV/EBITDA",IF(Valuation!E70="adjusted",4,3),IF(B68="P/E",5,6)))) | I68: =IF(AND(B68="P/E",Valuation!F70<>""),(Valuation!F70)*(1+$B$9),IF(AND(B68="FCF yield",Valuation!G70<>""),(Valuation!G70)*(1+$B$9),E68))
A69: Sum of the parts | F69: =((((Valuation!B73)*(Valuation!D73)+(Valuation!B74)*(Valuation!D74)+(Valuation!B75)*(Valuation!D75)+(Valuation!B76)*(Valuation!D76))*(1+$B$8))-$B$50-$B$51+$B$52)/$B$53 | G69: =Valuation!$B$65
A70: Value per share at target date (weighted methods) | F70: =SUMPRODUCT(F67:F69,G67:G69)/SUM(G67:G69)
A129: Segment build (model_engine.seg_build): revenue and EBIT are the segment sums plus corporate EBIT
A130: Segment | B130: Base | C130: =Model!E5 | D130: =Model!F5 | E130: =Model!G5
A131: AWS: revenue growth | C131: =Model!E12+$B$4 | D131: =Model!F12+$B$4 | E131: =Model!G12+$B$4
A132: AWS: revenue | B132: =Valuation!$B$99 | C132: =B132*(1+C131) | D132: =C132*(1+D131) | E132: =D132*(1+E131)
A133: AWS: EBIT margin | C133: =Model!E14+$B$5 | D133: =Model!F14+$B$5 | E133: =Model!G14+$B$5
A134: AWS: EBIT | C134: =C132*C133 | D134: =D132*D133 | E134: =E132*E133
A135: North America + International: revenue growth | C135: =Model!E16+$B$4 | D135: =Model!F16+$B$4 | E135: =Model!G16+$B$4
A136: North America + International: revenue | B136: =Valuation!$B$100 | C136: =B136*(1+C135) | D136: =C136*(1+D135) | E136: =D136*(1+E135)
A137: North America + International: EBIT margin | C137: =Model!E18+$B$5 | D137: =Model!F18+$B$5 | E137: =Model!G18+$B$5
A138: North America + International: EBIT | C138: =C136*C137 | D138: =D136*D137 | E138: =E136*E137
A139: Total segment revenue | C139: =C132+C136 | D139: =D132+D136 | E139: =E132+E136
A140: Total segment EBIT | C140: =C134+C138 | D140: =D134+D138 | E140: =E134+E138
A141: Corporate / unallocated EBIT | C141: =Model!E21 | D141: =Model!F21 | E141: =Model!G21
A142: EBIT (segments + corporate) | C142: =C140+C141 | D142: =D140+D141 | E142: =E140+E141

Sheet Calc - bear
A1: AMZN engine calculation: bear scenario
A2: Machinery behind the Valuation and Distribution tabs; drivers come from Model, assumptions from Valuation.
A4: Scenario Growth Δ | B4: =N(Valuation!C94)
A5: Scenario Margin Δ | B5: =N(Valuation!D94)
A6: Scenario Multiple Δ (turns) | B6: =N(Valuation!E94)
A7: Scenario WACC Δ | B7: =N(Valuation!F94)
A8: Scenario Multiple %Δ | B8: =N(Valuation!G94)
A9: Scenario Stated EPS/FCF %Δ | B9: =N(Valuation!H94)
A10: Scenario Custom %Δ | B10: =N(Valuation!I94)
A12: WACC | B12: =Valuation!$B$51+B7
A13: Years from last FY end to target date | B13: =(Valuation!$B$45-Valuation!$B$49)/365.25
A14: Years from last FY end to balance date | B14: =(Valuation!$B$55-Valuation!$B$49)/365.25
A15: Years from last FY end to share count date | B15: =(Valuation!$B$61-Valuation!$B$49)/365.25
A16: Projected years | B16: 3
A18: Projection | B18: Base | C18: =Model!E5 | D18: =Model!F5 | E18: =Model!G5
A19: Year index | B19: 0 | C19: 1 | D19: 2 | E19: 3
A20: Period end | C20: =Valuation!$B$49+ROUND(365.25*C19,0) | D20: =Valuation!$B$49+ROUND(365.25*D19,0) | E20: =Valuation!$B$49+ROUND(365.25*E19,0)
A21: Revenue growth | C21: =C22/B22-1 | D21: =D22/C22-1 | E21: =E22/D22-1
A22: Revenue | B22: =Valuation!$B$50 | C22: =C139 | D22: =D139 | E22: =E139
A23: EBIT margin | C23: =C24/C22 | D23: =D24/D22 | E23: =E24/E22
A24: EBIT | C24: =C142 | D24: =D142 | E24: =E142
A25: Tax rate | C25: =Model!E63 | D25: =Model!F63 | E25: =Model!G63
A26: NOPAT | C26: =C24*(1-C25) | D26: =D24*(1-D25) | E26: =E24*(1-E25)
A27: D&A | C27: =C22*(Model!E64+$B$250) | D27: =D22*(Model!F64+$B$251) | E27: =E22*(Model!G64+$B$252)
A28: Capex | C28: =C22*(Model!E65) | D28: =D22*(Model!F65) | E28: =E22*(Model!G65)
A29: Working capital increase | C29: =(Model!E66)*(C22-B22) | D29: =(Model!F66)*(D22-C22) | E29: =(Model!G66)*(E22-D22)
A30: Stock comp | C30: =C22*(Model!E67) | D30: =D22*(Model!F67) | E30: =E22*(Model!G67)
A31: Free cash flow to firm | C31: =C26+C27-C28-C29-IF(AND(Valuation!$B$47="adjusted",Valuation!$B$48="cost"),C30*(1-C25),0) | D31: =D26+D27-D28-D29-IF(AND(Valuation!$B$47="adjusted",Valuation!$B$48="cost"),D30*(1-D25),0) | E31: =E26+E27-E28-E29-IF(AND(Valuation!$B$47="adjusted",Valuation!$B$48="cost"),E30*(1-E25),0)
A32: EBITDA | C32: =C24+C27 | D32: =D24+D27 | E32: =E24+E27
A33: Adj. EBITDA | C33: =C24+C27+C22*(Model!E71) | D33: =D24+D27+D22*(Model!F71) | E33: =E24+E27+E22*(Model!G71)
A34: Shareholder returns + other uses | C34: =C22*Model!E69+Model!E68+Model!E70 | D34: =D22*Model!F69+Model!F68+Model!F70 | E34: =E22*Model!G69+Model!G68+Model!G70
A35: Share of year after target date | C35: =IF(C19<=$B$13,0,C19-MAX(C19-1,$B$13)) | D35: =IF(D19<=$B$13,0,D19-MAX(D19-1,$B$13)) | E35: =IF(E19<=$B$13,0,E19-MAX(E19-1,$B$13))
A36: PV at target date of FCFF | C36: =IF(C35=0,0,C31*C35/(1+$B$12)^(C19-$B$13)) | D36: =IF(D35=0,0,D31*D35/(1+$B$12)^(D19-$B$13)) | E36: =IF(E35=0,0,E31*E35/(1+$B$12)^(E19-$B$13))
A37: Overlap: balance date to target date | C37: =MAX(0,MIN(C19,$B$13)-MAX(C19-1,$B$14)) | D37: =MAX(0,MIN(D19,$B$13)-MAX(D19-1,$B$14)) | E37: =MAX(0,MIN(E19,$B$13)-MAX(E19-1,$B$14))
A38: NTM weight at target date | C38: =MAX(0,MIN(C19,$B$13+1)-MAX(C19-1,$B$13)) | D38: =MAX(0,MIN(D19,$B$13+1)-MAX(D19-1,$B$13)) | E38: =MAX(0,MIN(E19,$B$13+1)-MAX(E19-1,$B$13))
A39: LTM weight at target date | B39: =MAX(0,MIN(0,$B$13)-MAX(-1,$B$13-1)) | C39: =MAX(0,MIN(C19,$B$13)-MAX(C19-1,$B$13-1)) | D39: =MAX(0,MIN(D19,$B$13)-MAX(D19-1,$B$13-1)) | E39: =MAX(0,MIN(E19,$B$13)-MAX(E19-1,$B$13-1))
A41: Value at the target date
A42: PV of free cash flow after the target date | B42: =SUM($C$36:$E$36)
A43: Terminal value at final year | B43: =IF(Valuation!$B$52="exit_multiple",Valuation!$B$54*E32,E31*(1+Valuation!$B$53)/($B$12-Valuation!$B$53))
A44: PV of terminal value at target date | B44: =B43/(1+$B$12)^($B$16-$B$13)
A45: DCF enterprise value at target date | B45: =B42+B44
A46: Terminal value share of DCF | B46: =B44/B45
A47: Free cash flow earned, balance date to target date | B47: =SUMPRODUCT($C$37:$E$37,$C$31:$E$31)
A48: Shareholder returns + other uses paid | B48: =SUMPRODUCT($C$37:$E$37,$C$34:$E$34)
A49: Interest drag on net debt | B49: =Valuation!$B$58*(1-$C$25)*MAX(Valuation!$B$56,0)*MAX($B$13-$B$14,0)
A50: Net debt at target date | B50: =IF(Valuation!$B$59="",Valuation!$B$56-B47+B49+B48,Valuation!$B$59)
A51: Minority interests | B51: =Valuation!$B$57
A52: Adjustments (probability-weighted) | B52: =(Valuation!B79)*Valuation!C79+(Valuation!B80)*Valuation!C80+(Valuation!B81)*Valuation!C81+(Valuation!B82)*Valuation!C82+(Valuation!B83)*Valuation!C83+(Valuation!B84)*Valuation!C84+(Valuation!B85)*Valuation!C85+(Valuation!B86)*Valuation!C86+(Valuation!B87+$B$263)*Valuation!C87+(Valuation!B88)*Valuation!C88+0
A53: Diluted shares at target date (M) | B53: =IF(Valuation!$B$63="",Valuation!$B$60*(1+Valuation!$B$62)^MAX($B$13-$B$15,0),Valuation!$B$63)
A54: After-tax interest on target-date net debt | B54: =Valuation!$B$58*(1-$C$25)*MAX(B50,0)
A55: Check: WACC vs terminal growth | B55: =IF(AND(Valuation!$B$52<>"exit_multiple",$B$12<=Valuation!$B$53+0.01),"WACC must exceed terminal growth by 1 point","ok")
A56: Check: projection length | B56: =IF(OR($B$13>=$B$16-1,$B$13+1>$B$16),"add projected years past the target date","ok")
A58: Metric at target date | B58: Next 12 months | C58: Last 12 months
A59: Revenue | B59: =SUMPRODUCT($C$38:$E$38,$C$22:$E$22) | C59: =SUMPRODUCT($C$39:$E$39,$C$22:$E$22)+$B$39*$B$22
A60: EBIT | B60: =SUMPRODUCT($C$38:$E$38,$C$24:$E$24) | C60: =SUMPRODUCT($C$39:$E$39,$C$24:$E$24)
A61: EBITDA | B61: =SUMPRODUCT($C$38:$E$38,$C$32:$E$32) | C61: =SUMPRODUCT($C$39:$E$39,$C$32:$E$32)
A62: Adj. EBITDA | B62: =SUMPRODUCT($C$38:$E$38,$C$33:$E$33) | C62: =SUMPRODUCT($C$39:$E$39,$C$33:$E$33)
A63: NOPAT | B63: =SUMPRODUCT($C$38:$E$38,$C$26:$E$26) | C63: =SUMPRODUCT($C$39:$E$39,$C$26:$E$26)
A64: Free cash flow to firm | B64: =SUMPRODUCT($C$38:$E$38,$C$31:$E$31) | C64: =SUMPRODUCT($C$39:$E$39,$C$31:$E$31)
A66: Valuation method | B66: Metric | C66: Multiple used | D66: Basis | E66: Metric at target date | F66: Value per share | G66: Weight | H66: Metric key | I66: Metric shown (stated per-share figure when used)
A67: DCF (cash flow to target date + terminal) | F67: =((B45)-$B$50-$B$51+$B$52)/$B$53 | G67: =Valuation!$B$64
A68: ="Multiple: "&Valuation!A70&" ("&Valuation!D70&")" | B68: =Valuation!A70 | C68: =IF(B68="FCF yield",(Valuation!B70)*(1-$B$8),(Valuation!B70)+IF(B68="EV/sales",0.1,1)*$B$6) | D68: =Valuation!D70 | E68: =IF(D68="ltm",CHOOSE(H68,$C$59,$C$60,$C$61,$C$62,$C$63,$C$64),CHOOSE(H68,$B$59,$B$60,$B$61,$B$62,$B$63,$B$64)) | F68: =IF(OR(B68="EV/EBITDA",B68="EV/sales",B68="EV/EBIT"),((C68*E68)-$B$50-$B$51+$B$52)/$B$53,IF(B68="P/E",IF(Valuation!F70<>"",C68*(Valuation!F70+$B$264)*(1+$B$9),C68*(E68-$B$54)/$B$53),IF(Valuation!G70<>"",(Valuation!G70)*(1+$B$9)/C68,(E68-IF(Valuation!H70,$B$54,0))/C68/$B$53))+$B$52/$B$53) | G68: =Valuation!C70 | H68: =IF(B68="EV/sales",1,IF(B68="EV/EBIT",2,IF(B68="EV/EBITDA",IF(Valuation!E70="adjusted",4,3),IF(B68="P/E",5,6)))) | I68: =IF(AND(B68="P/E",Valuation!F70<>""),(Valuation!F70+$B$264)*(1+$B$9),IF(AND(B68="FCF yield",Valuation!G70<>""),(Valuation!G70)*(1+$B$9),E68))
A69: Sum of the parts | F69: =((((Valuation!B73+$B$265)*(Valuation!D73)+(Valuation!B74+$B$266)*(Valuation!D74)+(Valuation!B75)*(Valuation!D75)+(Valuation!B76)*(Valuation!D76))*(1+$B$8))-$B$50-$B$51+$B$52)/$B$53 | G69: =Valuation!$B$65
A70: Value per share at target date (weighted methods) | F70: =SUMPRODUCT(F67:F69,G67:G69)/SUM(G67:G69)
A129: Segment build (model_engine.seg_build): revenue and EBIT are the segment sums plus corporate EBIT
A130: Segment | B130: Base | C130: =Model!E5 | D130: =Model!F5 | E130: =Model!G5
A131: AWS: revenue growth | C131: =Model!E12+$B$4+$B$253 | D131: =Model!F12+$B$4 | E131: =Model!G12+$B$4
A132: AWS: revenue | B132: =Valuation!$B$99 | C132: =B132*(1+C131) | D132: =C132*(1+D131) | E132: =D132*(1+E131)
A133: AWS: EBIT margin | C133: =Model!E14+$B$5+$B$254 | D133: =Model!F14+$B$5+$B$255 | E133: =Model!G14+$B$5+$B$256
A134: AWS: EBIT | C134: =C132*C133 | D134: =D132*D133 | E134: =E132*E133
A135: North America + International: revenue growth | C135: =Model!E16+$B$4+$B$257 | D135: =Model!F16+$B$4+$B$259 | E135: =Model!G16+$B$4+$B$261
A136: North America + International: revenue | B136: =Valuation!$B$100 | C136: =B136*(1+C135) | D136: =C136*(1+D135) | E136: =D136*(1+E135)
A137: North America + International: EBIT margin | C137: =Model!E18+$B$5+$B$258 | D137: =Model!F18+$B$5+$B$260 | E137: =Model!G18+$B$5+$B$262
A138: North America + International: EBIT | C138: =C136*C137 | D138: =D136*D137 | E138: =E136*E137
A139: Total segment revenue | C139: =C132+C136 | D139: =D132+D136 | E139: =E132+E136
A140: Total segment EBIT | C140: =C134+C138 | D140: =D134+D138 | E140: =E134+E138
A141: Corporate / unallocated EBIT | C141: =Model!E21 | D141: =Model!F21 | E141: =Model!G21
A142: EBIT (segments + corporate) | C142: =C140+C141 | D142: =D140+D141 | E142: =E140+E141
A249: Driver scenario shifts: line-item changes model_drivers.py resolves from this scenario's driver deltas (added to the Model tab inputs)
A250: D&A % revenue, year 1 | B250: 0.0018814364
A251: D&A % revenue, year 2 | B251: 0.0025634887
A252: D&A % revenue, year 3 | B252: 0.0031462622
A253: AWS: revenue growth, year 1 | B253: -0.10799393
A254: AWS: EBIT margin, year 1 | B254: -0.038648764
A255: AWS: EBIT margin, year 2 | B255: -0.042122321
A256: AWS: EBIT margin, year 3 | B256: -0.044484942
A257: North America + International: revenue growth, year 1 | B257: -0.0058100745
A258: North America + International: EBIT margin, year 1 | B258: -0.0022429977
A259: North America + International: revenue growth, year 2 | B259: -0.00054007925
A260: North America + International: EBIT margin, year 2 | B260: -0.0024237846
A261: North America + International: revenue growth, year 3 | B261: -0.00048632141
... A266: Segment 2 NTM metric | B266: -1856.3579

Sheet Calc - base
A1: AMZN engine calculation: base scenario
A2: Machinery behind the Valuation and Distribution tabs; drivers come from Model, assumptions from Valuation.
A4: Scenario Growth Δ | B4: =N(Valuation!C95)
A5: Scenario Margin Δ | B5: =N(Valuation!D95)
A6: Scenario Multiple Δ (turns) | B6: =N(Valuation!E95)
A7: Scenario WACC Δ | B7: =N(Valuation!F95)
A8: Scenario Multiple %Δ | B8: =N(Valuation!G95)
A9: Scenario Stated EPS/FCF %Δ | B9: =N(Valuation!H95)
A10: Scenario Custom %Δ | B10: =N(Valuation!I95)
A12: WACC | B12: =Valuation!$B$51+B7
A13: Years from last FY end to target date | B13: =(Valuation!$B$45-Valuation!$B$49)/365.25
A14: Years from last FY end to balance date | B14: =(Valuation!$B$55-Valuation!$B$49)/365.25
A15: Years from last FY end to share count date | B15: =(Valuation!$B$61-Valuation!$B$49)/365.25
A16: Projected years | B16: 3
A18: Projection | B18: Base | C18: =Model!E5 | D18: =Model!F5 | E18: =Model!G5
A19: Year index | B19: 0 | C19: 1 | D19: 2 | E19: 3
A20: Period end | C20: =Valuation!$B$49+ROUND(365.25*C19,0) | D20: =Valuation!$B$49+ROUND(365.25*D19,0) | E20: =Valuation!$B$49+ROUND(365.25*E19,0)
A21: Revenue growth | C21: =C22/B22-1 | D21: =D22/C22-1 | E21: =E22/D22-1
A22: Revenue | B22: =Valuation!$B$50 | C22: =C139 | D22: =D139 | E22: =E139
A23: EBIT margin | C23: =C24/C22 | D23: =D24/D22 | E23: =E24/E22
A24: EBIT | C24: =C142 | D24: =D142 | E24: =E142
A25: Tax rate | C25: =Model!E63 | D25: =Model!F63 | E25: =Model!G63
A26: NOPAT | C26: =C24*(1-C25) | D26: =D24*(1-D25) | E26: =E24*(1-E25)
A27: D&A | C27: =C22*(Model!E64) | D27: =D22*(Model!F64) | E27: =E22*(Model!G64)
A28: Capex | C28: =C22*(Model!E65) | D28: =D22*(Model!F65) | E28: =E22*(Model!G65)
A29: Working capital increase | C29: =(Model!E66)*(C22-B22) | D29: =(Model!F66)*(D22-C22) | E29: =(Model!G66)*(E22-D22)
A30: Stock comp | C30: =C22*(Model!E67) | D30: =D22*(Model!F67) | E30: =E22*(Model!G67)
A31: Free cash flow to firm | C31: =C26+C27-C28-C29-IF(AND(Valuation!$B$47="adjusted",Valuation!$B$48="cost"),C30*(1-C25),0) | D31: =D26+D27-D28-D29-IF(AND(Valuation!$B$47="adjusted",Valuation!$B$48="cost"),D30*(1-D25),0) | E31: =E26+E27-E28-E29-IF(AND(Valuation!$B$47="adjusted",Valuation!$B$48="cost"),E30*(1-E25),0)
A32: EBITDA | C32: =C24+C27 | D32: =D24+D27 | E32: =E24+E27
A33: Adj. EBITDA | C33: =C24+C27+C22*(Model!E71) | D33: =D24+D27+D22*(Model!F71) | E33: =E24+E27+E22*(Model!G71)
A34: Shareholder returns + other uses | C34: =C22*Model!E69+Model!E68+Model!E70 | D34: =D22*Model!F69+Model!F68+Model!F70 | E34: =E22*Model!G69+Model!G68+Model!G70
A35: Share of year after target date | C35: =IF(C19<=$B$13,0,C19-MAX(C19-1,$B$13)) | D35: =IF(D19<=$B$13,0,D19-MAX(D19-1,$B$13)) | E35: =IF(E19<=$B$13,0,E19-MAX(E19-1,$B$13))
A36: PV at target date of FCFF | C36: =IF(C35=0,0,C31*C35/(1+$B$12)^(C19-$B$13)) | D36: =IF(D35=0,0,D31*D35/(1+$B$12)^(D19-$B$13)) | E36: =IF(E35=0,0,E31*E35/(1+$B$12)^(E19-$B$13))
A37: Overlap: balance date to target date | C37: =MAX(0,MIN(C19,$B$13)-MAX(C19-1,$B$14)) | D37: =MAX(0,MIN(D19,$B$13)-MAX(D19-1,$B$14)) | E37: =MAX(0,MIN(E19,$B$13)-MAX(E19-1,$B$14))
A38: NTM weight at target date | C38: =MAX(0,MIN(C19,$B$13+1)-MAX(C19-1,$B$13)) | D38: =MAX(0,MIN(D19,$B$13+1)-MAX(D19-1,$B$13)) | E38: =MAX(0,MIN(E19,$B$13+1)-MAX(E19-1,$B$13))
A39: LTM weight at target date | B39: =MAX(0,MIN(0,$B$13)-MAX(-1,$B$13-1)) | C39: =MAX(0,MIN(C19,$B$13)-MAX(C19-1,$B$13-1)) | D39: =MAX(0,MIN(D19,$B$13)-MAX(D19-1,$B$13-1)) | E39: =MAX(0,MIN(E19,$B$13)-MAX(E19-1,$B$13-1))
A41: Value at the target date
A42: PV of free cash flow after the target date | B42: =SUM($C$36:$E$36)
A43: Terminal value at final year | B43: =IF(Valuation!$B$52="exit_multiple",Valuation!$B$54*E32,E31*(1+Valuation!$B$53)/($B$12-Valuation!$B$53))
A44: PV of terminal value at target date | B44: =B43/(1+$B$12)^($B$16-$B$13)
A45: DCF enterprise value at target date | B45: =B42+B44
A46: Terminal value share of DCF | B46: =B44/B45
A47: Free cash flow earned, balance date to target date | B47: =SUMPRODUCT($C$37:$E$37,$C$31:$E$31)
A48: Shareholder returns + other uses paid | B48: =SUMPRODUCT($C$37:$E$37,$C$34:$E$34)
A49: Interest drag on net debt | B49: =Valuation!$B$58*(1-$C$25)*MAX(Valuation!$B$56,0)*MAX($B$13-$B$14,0)
A50: Net debt at target date | B50: =IF(Valuation!$B$59="",Valuation!$B$56-B47+B49+B48,Valuation!$B$59)
A51: Minority interests | B51: =Valuation!$B$57
A52: Adjustments (probability-weighted) | B52: =(Valuation!B79)*Valuation!C79+(Valuation!B80)*Valuation!C80+(Valuation!B81)*Valuation!C81+(Valuation!B82)*Valuation!C82+(Valuation!B83)*Valuation!C83+(Valuation!B84)*Valuation!C84+(Valuation!B85)*Valuation!C85+(Valuation!B86)*Valuation!C86+(Valuation!B87)*Valuation!C87+(Valuation!B88)*Valuation!C88+0
A53: Diluted shares at target date (M) | B53: =IF(Valuation!$B$63="",Valuation!$B$60*(1+Valuation!$B$62)^MAX($B$13-$B$15,0),Valuation!$B$63)
A54: After-tax interest on target-date net debt | B54: =Valuation!$B$58*(1-$C$25)*MAX(B50,0)
A55: Check: WACC vs terminal growth | B55: =IF(AND(Valuation!$B$52<>"exit_multiple",$B$12<=Valuation!$B$53+0.01),"WACC must exceed terminal growth by 1 point","ok")
A56: Check: projection length | B56: =IF(OR($B$13>=$B$16-1,$B$13+1>$B$16),"add projected years past the target date","ok")
A58: Metric at target date | B58: Next 12 months | C58: Last 12 months
A59: Revenue | B59: =SUMPRODUCT($C$38:$E$38,$C$22:$E$22) | C59: =SUMPRODUCT($C$39:$E$39,$C$22:$E$22)+$B$39*$B$22
A60: EBIT | B60: =SUMPRODUCT($C$38:$E$38,$C$24:$E$24) | C60: =SUMPRODUCT($C$39:$E$39,$C$24:$E$24)
A61: EBITDA | B61: =SUMPRODUCT($C$38:$E$38,$C$32:$E$32) | C61: =SUMPRODUCT($C$39:$E$39,$C$32:$E$32)
A62: Adj. EBITDA | B62: =SUMPRODUCT($C$38:$E$38,$C$33:$E$33) | C62: =SUMPRODUCT($C$39:$E$39,$C$33:$E$33)
A63: NOPAT | B63: =SUMPRODUCT($C$38:$E$38,$C$26:$E$26) | C63: =SUMPRODUCT($C$39:$E$39,$C$26:$E$26)
A64: Free cash flow to firm | B64: =SUMPRODUCT($C$38:$E$38,$C$31:$E$31) | C64: =SUMPRODUCT($C$39:$E$39,$C$31:$E$31)
A66: Valuation method | B66: Metric | C66: Multiple used | D66: Basis | E66: Metric at target date | F66: Value per share | G66: Weight | H66: Metric key | I66: Metric shown (stated per-share figure when used)
A67: DCF (cash flow to target date + terminal) | F67: =((B45)-$B$50-$B$51+$B$52)/$B$53 | G67: =Valuation!$B$64
A68: ="Multiple: "&Valuation!A70&" ("&Valuation!D70&")" | B68: =Valuation!A70 | C68: =IF(B68="FCF yield",(Valuation!B70)*(1-$B$8),(Valuation!B70)+IF(B68="EV/sales",0.1,1)*$B$6) | D68: =Valuation!D70 | E68: =IF(D68="ltm",CHOOSE(H68,$C$59,$C$60,$C$61,$C$62,$C$63,$C$64),CHOOSE(H68,$B$59,$B$60,$B$61,$B$62,$B$63,$B$64)) | F68: =IF(OR(B68="EV/EBITDA",B68="EV/sales",B68="EV/EBIT"),((C68*E68)-$B$50-$B$51+$B$52)/$B$53,IF(B68="P/E",IF(Valuation!F70<>"",C68*(Valuation!F70)*(1+$B$9),C68*(E68-$B$54)/$B$53),IF(Valuation!G70<>"",(Valuation!G70)*(1+$B$9)/C68,(E68-IF(Valuation!H70,$B$54,0))/C68/$B$53))+$B$52/$B$53) | G68: =Valuation!C70 | H68: =IF(B68="EV/sales",1,IF(B68="EV/EBIT",2,IF(B68="EV/EBITDA",IF(Valuation!E70="adjusted",4,3),IF(B68="P/E",5,6)))) | I68: =IF(AND(B68="P/E",Valuation!F70<>""),(Valuation!F70)*(1+$B$9),IF(AND(B68="FCF yield",Valuation!G70<>""),(Valuation!G70)*(1+$B$9),E68))
A69: Sum of the parts | F69: =((((Valuation!B73)*(Valuation!D73)+(Valuation!B74)*(Valuation!D74)+(Valuation!B75)*(Valuation!D75)+(Valuation!B76)*(Valuation!D76))*(1+$B$8))-$B$50-$B$51+$B$52)/$B$53 | G69: =Valuation!$B$65
A70: Value per share at target date (weighted methods) | F70: =SUMPRODUCT(F67:F69,G67:G69)/SUM(G67:G69)
A129: Segment build (model_engine.seg_build): revenue and EBIT are the segment sums plus corporate EBIT
A130: Segment | B130: Base | C130: =Model!E5 | D130: =Model!F5 | E130: =Model!G5
A131: AWS: revenue growth | C131: =Model!E12+$B$4 | D131: =Model!F12+$B$4 | E131: =Model!G12+$B$4
A132: AWS: revenue | B132: =Valuation!$B$99 | C132: =B132*(1+C131) | D132: =C132*(1+D131) | E132: =D132*(1+E131)
A133: AWS: EBIT margin | C133: =Model!E14+$B$5 | D133: =Model!F14+$B$5 | E133: =Model!G14+$B$5
A134: AWS: EBIT | C134: =C132*C133 | D134: =D132*D133 | E134: =E132*E133
A135: North America + International: revenue growth | C135: =Model!E16+$B$4 | D135: =Model!F16+$B$4 | E135: =Model!G16+$B$4
A136: North America + International: revenue | B136: =Valuation!$B$100 | C136: =B136*(1+C135) | D136: =C136*(1+D135) | E136: =D136*(1+E135)
A137: North America + International: EBIT margin | C137: =Model!E18+$B$5 | D137: =Model!F18+$B$5 | E137: =Model!G18+$B$5
A138: North America + International: EBIT | C138: =C136*C137 | D138: =D136*D137 | E138: =E136*E137
A139: Total segment revenue | C139: =C132+C136 | D139: =D132+D136 | E139: =E132+E136
A140: Total segment EBIT | C140: =C134+C138 | D140: =D134+D138 | E140: =E134+E138
A141: Corporate / unallocated EBIT | C141: =Model!E21 | D141: =Model!F21 | E141: =Model!G21
A142: EBIT (segments + corporate) | C142: =C140+C141 | D142: =D140+D141 | E142: =E140+E141

Sheet Calc - bull
A1: AMZN engine calculation: bull scenario
A2: Machinery behind the Valuation and Distribution tabs; drivers come from Model, assumptions from Valuation.
A4: Scenario Growth Δ | B4: =N(Valuation!C96)
A5: Scenario Margin Δ | B5: =N(Valuation!D96)
A6: Scenario Multiple Δ (turns) | B6: =N(Valuation!E96)
A7: Scenario WACC Δ | B7: =N(Valuation!F96)
A8: Scenario Multiple %Δ | B8: =N(Valuation!G96)
A9: Scenario Stated EPS/FCF %Δ | B9: =N(Valuation!H96)
A10: Scenario Custom %Δ | B10: =N(Valuation!I96)
A12: WACC | B12: =Valuation!$B$51+B7
A13: Years from last FY end to target date | B13: =(Valuation!$B$45-Valuation!$B$49)/365.25
A14: Years from last FY end to balance date | B14: =(Valuation!$B$55-Valuation!$B$49)/365.25
A15: Years from last FY end to share count date | B15: =(Valuation!$B$61-Valuation!$B$49)/365.25
A16: Projected years | B16: 3
A18: Projection | B18: Base | C18: =Model!E5 | D18: =Model!F5 | E18: =Model!G5
A19: Year index | B19: 0 | C19: 1 | D19: 2 | E19: 3
A20: Period end | C20: =Valuation!$B$49+ROUND(365.25*C19,0) | D20: =Valuation!$B$49+ROUND(365.25*D19,0) | E20: =Valuation!$B$49+ROUND(365.25*E19,0)
A21: Revenue growth | C21: =C22/B22-1 | D21: =D22/C22-1 | E21: =E22/D22-1
A22: Revenue | B22: =Valuation!$B$50 | C22: =C139 | D22: =D139 | E22: =E139
A23: EBIT margin | C23: =C24/C22 | D23: =D24/D22 | E23: =E24/E22
A24: EBIT | C24: =C142 | D24: =D142 | E24: =E142
A25: Tax rate | C25: =Model!E63 | D25: =Model!F63 | E25: =Model!G63
A26: NOPAT | C26: =C24*(1-C25) | D26: =D24*(1-D25) | E26: =E24*(1-E25)
A27: D&A | C27: =C22*(Model!E64+$B$250) | D27: =D22*(Model!F64+$B$251) | E27: =E22*(Model!G64+$B$252)
A28: Capex | C28: =C22*(Model!E65) | D28: =D22*(Model!F65) | E28: =E22*(Model!G65)
A29: Working capital increase | C29: =(Model!E66)*(C22-B22) | D29: =(Model!F66)*(D22-C22) | E29: =(Model!G66)*(E22-D22)
A30: Stock comp | C30: =C22*(Model!E67) | D30: =D22*(Model!F67) | E30: =E22*(Model!G67)
A31: Free cash flow to firm | C31: =C26+C27-C28-C29-IF(AND(Valuation!$B$47="adjusted",Valuation!$B$48="cost"),C30*(1-C25),0) | D31: =D26+D27-D28-D29-IF(AND(Valuation!$B$47="adjusted",Valuation!$B$48="cost"),D30*(1-D25),0) | E31: =E26+E27-E28-E29-IF(AND(Valuation!$B$47="adjusted",Valuation!$B$48="cost"),E30*(1-E25),0)
A32: EBITDA | C32: =C24+C27 | D32: =D24+D27 | E32: =E24+E27
A33: Adj. EBITDA | C33: =C24+C27+C22*(Model!E71) | D33: =D24+D27+D22*(Model!F71) | E33: =E24+E27+E22*(Model!G71)
A34: Shareholder returns + other uses | C34: =C22*Model!E69+Model!E68+Model!E70 | D34: =D22*Model!F69+Model!F68+Model!F70 | E34: =E22*Model!G69+Model!G68+Model!G70
A35: Share of year after target date | C35: =IF(C19<=$B$13,0,C19-MAX(C19-1,$B$13)) | D35: =IF(D19<=$B$13,0,D19-MAX(D19-1,$B$13)) | E35: =IF(E19<=$B$13,0,E19-MAX(E19-1,$B$13))
A36: PV at target date of FCFF | C36: =IF(C35=0,0,C31*C35/(1+$B$12)^(C19-$B$13)) | D36: =IF(D35=0,0,D31*D35/(1+$B$12)^(D19-$B$13)) | E36: =IF(E35=0,0,E31*E35/(1+$B$12)^(E19-$B$13))
A37: Overlap: balance date to target date | C37: =MAX(0,MIN(C19,$B$13)-MAX(C19-1,$B$14)) | D37: =MAX(0,MIN(D19,$B$13)-MAX(D19-1,$B$14)) | E37: =MAX(0,MIN(E19,$B$13)-MAX(E19-1,$B$14))
A38: NTM weight at target date | C38: =MAX(0,MIN(C19,$B$13+1)-MAX(C19-1,$B$13)) | D38: =MAX(0,MIN(D19,$B$13+1)-MAX(D19-1,$B$13)) | E38: =MAX(0,MIN(E19,$B$13+1)-MAX(E19-1,$B$13))
A39: LTM weight at target date | B39: =MAX(0,MIN(0,$B$13)-MAX(-1,$B$13-1)) | C39: =MAX(0,MIN(C19,$B$13)-MAX(C19-1,$B$13-1)) | D39: =MAX(0,MIN(D19,$B$13)-MAX(D19-1,$B$13-1)) | E39: =MAX(0,MIN(E19,$B$13)-MAX(E19-1,$B$13-1))
A41: Value at the target date
A42: PV of free cash flow after the target date | B42: =SUM($C$36:$E$36)
A43: Terminal value at final year | B43: =IF(Valuation!$B$52="exit_multiple",Valuation!$B$54*E32,E31*(1+Valuation!$B$53)/($B$12-Valuation!$B$53))
A44: PV of terminal value at target date | B44: =B43/(1+$B$12)^($B$16-$B$13)
A45: DCF enterprise value at target date | B45: =B42+B44
A46: Terminal value share of DCF | B46: =B44/B45
A47: Free cash flow earned, balance date to target date | B47: =SUMPRODUCT($C$37:$E$37,$C$31:$E$31)
A48: Shareholder returns + other uses paid | B48: =SUMPRODUCT($C$37:$E$37,$C$34:$E$34)
A49: Interest drag on net debt | B49: =Valuation!$B$58*(1-$C$25)*MAX(Valuation!$B$56,0)*MAX($B$13-$B$14,0)
A50: Net debt at target date | B50: =IF(Valuation!$B$59="",Valuation!$B$56-B47+B49+B48,Valuation!$B$59)
A51: Minority interests | B51: =Valuation!$B$57
A52: Adjustments (probability-weighted) | B52: =(Valuation!B79)*Valuation!C79+(Valuation!B80)*Valuation!C80+(Valuation!B81)*Valuation!C81+(Valuation!B82)*Valuation!C82+(Valuation!B83)*Valuation!C83+(Valuation!B84)*Valuation!C84+(Valuation!B85)*Valuation!C85+(Valuation!B86)*Valuation!C86+(Valuation!B87+$B$263)*Valuation!C87+(Valuation!B88)*Valuation!C88+0
A53: Diluted shares at target date (M) | B53: =IF(Valuation!$B$63="",Valuation!$B$60*(1+Valuation!$B$62)^MAX($B$13-$B$15,0),Valuation!$B$63)
A54: After-tax interest on target-date net debt | B54: =Valuation!$B$58*(1-$C$25)*MAX(B50,0)
A55: Check: WACC vs terminal growth | B55: =IF(AND(Valuation!$B$52<>"exit_multiple",$B$12<=Valuation!$B$53+0.01),"WACC must exceed terminal growth by 1 point","ok")
A56: Check: projection length | B56: =IF(OR($B$13>=$B$16-1,$B$13+1>$B$16),"add projected years past the target date","ok")
A58: Metric at target date | B58: Next 12 months | C58: Last 12 months
A59: Revenue | B59: =SUMPRODUCT($C$38:$E$38,$C$22:$E$22) | C59: =SUMPRODUCT($C$39:$E$39,$C$22:$E$22)+$B$39*$B$22
A60: EBIT | B60: =SUMPRODUCT($C$38:$E$38,$C$24:$E$24) | C60: =SUMPRODUCT($C$39:$E$39,$C$24:$E$24)
A61: EBITDA | B61: =SUMPRODUCT($C$38:$E$38,$C$32:$E$32) | C61: =SUMPRODUCT($C$39:$E$39,$C$32:$E$32)
A62: Adj. EBITDA | B62: =SUMPRODUCT($C$38:$E$38,$C$33:$E$33) | C62: =SUMPRODUCT($C$39:$E$39,$C$33:$E$33)
A63: NOPAT | B63: =SUMPRODUCT($C$38:$E$38,$C$26:$E$26) | C63: =SUMPRODUCT($C$39:$E$39,$C$26:$E$26)
A64: Free cash flow to firm | B64: =SUMPRODUCT($C$38:$E$38,$C$31:$E$31) | C64: =SUMPRODUCT($C$39:$E$39,$C$31:$E$31)
A66: Valuation method | B66: Metric | C66: Multiple used | D66: Basis | E66: Metric at target date | F66: Value per share | G66: Weight | H66: Metric key | I66: Metric shown (stated per-share figure when used)
A67: DCF (cash flow to target date + terminal) | F67: =((B45)-$B$50-$B$51+$B$52)/$B$53 | G67: =Valuation!$B$64
A68: ="Multiple: "&Valuation!A70&" ("&Valuation!D70&")" | B68: =Valuation!A70 | C68: =IF(B68="FCF yield",(Valuation!B70)*(1-$B$8),(Valuation!B70)+IF(B68="EV/sales",0.1,1)*$B$6) | D68: =Valuation!D70 | E68: =IF(D68="ltm",CHOOSE(H68,$C$59,$C$60,$C$61,$C$62,$C$63,$C$64),CHOOSE(H68,$B$59,$B$60,$B$61,$B$62,$B$63,$B$64)) | F68: =IF(OR(B68="EV/EBITDA",B68="EV/sales",B68="EV/EBIT"),((C68*E68)-$B$50-$B$51+$B$52)/$B$53,IF(B68="P/E",IF(Valuation!F70<>"",C68*(Valuation!F70+$B$264)*(1+$B$9),C68*(E68-$B$54)/$B$53),IF(Valuation!G70<>"",(Valuation!G70)*(1+$B$9)/C68,(E68-IF(Valuation!H70,$B$54,0))/C68/$B$53))+$B$52/$B$53) | G68: =Valuation!C70 | H68: =IF(B68="EV/sales",1,IF(B68="EV/EBIT",2,IF(B68="EV/EBITDA",IF(Valuation!E70="adjusted",4,3),IF(B68="P/E",5,6)))) | I68: =IF(AND(B68="P/E",Valuation!F70<>""),(Valuation!F70+$B$264)*(1+$B$9),IF(AND(B68="FCF yield",Valuation!G70<>""),(Valuation!G70)*(1+$B$9),E68))
A69: Sum of the parts | F69: =((((Valuation!B73+$B$265)*(Valuation!D73)+(Valuation!B74+$B$266)*(Valuation!D74)+(Valuation!B75)*(Valuation!D75)+(Valuation!B76)*(Valuation!D76))*(1+$B$8))-$B$50-$B$51+$B$52)/$B$53 | G69: =Valuation!$B$65
A70: Value per share at target date (weighted methods) | F70: =SUMPRODUCT(F67:F69,G67:G69)/SUM(G67:G69)
A129: Segment build (model_engine.seg_build): revenue and EBIT are the segment sums plus corporate EBIT
A130: Segment | B130: Base | C130: =Model!E5 | D130: =Model!F5 | E130: =Model!G5
A131: AWS: revenue growth | C131: =Model!E12+$B$4+$B$253 | D131: =Model!F12+$B$4 | E131: =Model!G12+$B$4
A132: AWS: revenue | B132: =Valuation!$B$99 | C132: =B132*(1+C131) | D132: =C132*(1+D131) | E132: =D132*(1+E131)
A133: AWS: EBIT margin | C133: =Model!E14+$B$5+$B$254 | D133: =Model!F14+$B$5+$B$255 | E133: =Model!G14+$B$5+$B$256
A134: AWS: EBIT | C134: =C132*C133 | D134: =D132*D133 | E134: =E132*E133
A135: North America + International: revenue growth | C135: =Model!E16+$B$4+$B$257 | D135: =Model!F16+$B$4+$B$259 | E135: =Model!G16+$B$4+$B$261
A136: North America + International: revenue | B136: =Valuation!$B$100 | C136: =B136*(1+C135) | D136: =C136*(1+D135) | E136: =D136*(1+E135)
A137: North America + International: EBIT margin | C137: =Model!E18+$B$5+$B$258 | D137: =Model!F18+$B$5+$B$260 | E137: =Model!G18+$B$5+$B$262
A138: North America + International: EBIT | C138: =C136*C137 | D138: =D136*D137 | E138: =E136*E137
A139: Total segment revenue | C139: =C132+C136 | D139: =D132+D136 | E139: =E132+E136
A140: Total segment EBIT | C140: =C134+C138 | D140: =D134+D138 | E140: =E134+E138
A141: Corporate / unallocated EBIT | C141: =Model!E21 | D141: =Model!F21 | E141: =Model!G21
A142: EBIT (segments + corporate) | C142: =C140+C141 | D142: =D140+D141 | E142: =E140+E141
A249: Driver scenario shifts: line-item changes model_drivers.py resolves from this scenario's driver deltas (added to the Model tab inputs)
A250: D&A % revenue, year 1 | B250: -0.0013608807
A251: D&A % revenue, year 2 | B251: -0.0018441375
A252: D&A % revenue, year 3 | B252: -0.0022544835
A253: AWS: revenue growth, year 1 | B253: 0.080995449
A254: AWS: EBIT margin, year 1 | B254: 0.02713929
A255: AWS: EBIT margin, year 2 | B255: 0.029400379
A256: AWS: EBIT margin, year 3 | B256: 0.030938311
A257: North America + International: revenue growth, year 1 | B257: 0.0043575559
A258: North America + International: EBIT margin, year 1 | B258: 0.0016671826
A259: North America + International: revenue growth, year 2 | B259: 0.00040143187
A260: North America + International: EBIT margin, year 2 | B260: 0.0018000106
A261: North America + International: revenue growth, year 3 | B261: 0.00036116398
... A266: Segment 2 NTM metric | B266: 1392.2684

Sheet Agents
A1: AMZN: each forecaster's own assumption set through the same engine (from model_engine.json, not live)
A3: Set | B3: Research target (12m) | C3: Median | D3: 25th pct | E3: 75th pct | F3: WACC | G3: Y1 growth | H3: Y1 margin | I3: Terminal growth | J3: DCF weight | K3: Years | L3: Multiples | M3: Supervisor's note
A4: supervisor | B4: 266.05145 | C4: 258.67848 | D4: 204.29537 | E4: 316.49997 | F4: 0.1044 | I4: 0.035 | J4: 0 | K4: 3 | L4: P/E 22.88 (ntm)
A5: agent_1 | M5: engine error: no model_inputs found
A6: agent_2 | M6: engine error: no model_inputs found
A7: agent_3 | M7: engine error: no model_inputs found

Sheet Sources
A1: AMZN: where each input comes from (source numbers point to the list below; F ids to the SEC fact table)
A3: Input | B3: Value | C3: Basis | D3: Sources | E3: SEC fact ids | F3: Derivation
A4: Base revenue FY2025 (fiscal year ended 2025-12-31) | B4: $716,924M | C4: reported | D4: 1, 2 | E4: F3 | F4: filled in (not stated in this set's original work): 10-K filed 2026-02-06, us-gaap:RevenueFromContractWithCustomerExcludingAssessedTax (fact pack F3).
A5: Tax rate | B5: 21% | C5: judgment | D5: 1, 4 | F5: The supervisor's after-tax factor x 0.79 (21%) in its SOTP.
A6: Stock comp % revenue | B6: 2.49% | C6: reported | D6: 1, 2 | E6: F46, F6 | F6: filled in (not stated in this set's original work): TTM SBC $19,314M / TTM revenue $775,680M (F46 / F6). GAAP EBIT is after stock comp (cost basis), so this is memo only.
A7: Working capital % of incremental revenue | B7: 0% | C7: judgment | F7: filled in (not stated in this set's original work): not stated in the run; Amazon runs negative working capital, set to 0 (memo; DCF weight 0).
A8: Net debt at the balance date (2026-06-30) | B8: $10,332M | C8: reported | D8: 1, 2 | E8: F85, F88, F83, F84, F92 | F8: filled in (not stated in this set's original work): long-term debt $132,995M + short-term borrowings $325M - cash $78,213M - marketable securities $44,775M = $10,332M (F92). Leases excluded (tags).
A9: Interest rate on debt | B9: 2.50% | C9: estimate | D9: 1, 2 | E9: F67, F91 | F9: filled in (not stated in this set's original work): TTM interest expense $3,331M / total debt $133,320M (F67 / F91); not used when net debt at the horizon is stated.
A10: Diluted shares now (Q2 2026 weighted average) | B10: 10,903M | C10: reported | D10: 1, 2 | E10: F33 | F10: filled in (not stated in this set's original work): Q2 2026 weighted-average diluted shares (F33).
A11: WACC (DCF diagnostic only) | B11: 10.44% | C11: estimate | D11: 4 | F11: filled in (not stated in this set's original work): agent_3's stated WACC, the only discount rate in the run: cost of equity 5.31% + 1.31 x 4.20% = 10.79%; debt $163.6B face at 5.6% pre-tax, 21% tax; equity $2,764B (10.783B sh x $256.29). The DCF leg has weight 0 in this set.
A12: Terminal growth (DCF diagnostic only) | B12: 3.5% | C12: judgment | D12: 4 | F12: filled in (not stated in this set's original work): agent_3's stated terminal growth (below the 5.31% 10-year).
A13: FY2027 EPS (consensus) | B13: $10.51 (52 analysts) | C13: consensus | D13: 5, 4 | F13: Yahoo EPS trend and MarketScreener, verified 2026-10-06 (supervisor key_drivers).
A14: FY2028 EPS used | B14: $13.20 (consensus $13.81) | C14: estimate | D14: 4, 23 | F14: Supervisor: mean of the three independent capex/D&A haircuts (13.40 + 13.00 + 13.24) / 3 = 13.21, rounded to $13.20; consensus 2028 capex $296.9B (+7%) vs the standing view's Big-4 1,080 -> 1,330.
A15: Stated EPS at the horizon (NTM at Oct-2027) | B15: $11.40 (driver-built) | C15: estimate | D15: 4 | F15: driver_build: 0.189 x (10.51 / 136.2) x EBIT_FY2027 + 0.811 x (13.81 / 182.7) x EBIT_FY2028 (consensus EPS per $B of EBIT, MarketScreener, source 4); weights rolled from 0.237 / 0.763 to the 2027-10-23 horizon (69 of 365 days of FY2027 left) = $11.40.
A16: P/E multiple | B16: 22.88x | C16: estimate | D16: 29, 30, 35, 36, 39, 40, 41, 42 | F16: Exit-multiple rule (Kilian card 2026-10-26 12:16Z; METHOD.md Peer comparables): exit = peer median x (own NTM multiple / peer median)^k, k = 0.8. Peer median 21.3x (unchanged, gated 2026-10-26: see the rest of this derivation). Own multiple 23.29x on the peers' basis: AMZN $248.00 / CY2027 Zacks consensus EPS $10.65 = 23.29x (same basis as the peer rows). Exit = 21.3 x (23.29 / 21.3)^0.8 = 21.3 x 1.0741 = 22.88x (was 21.3x). SOTP segment multiples (AWS 21.3x, ads 19.87x, stores 37.56x) stay at their peer medians: a segment has no own traded multiple (rule: no meaningful own multiple -> peer median). PREVIOUS DERIVATION: Median CY2027 P/E of MSFT, GOOGL, META at the Oct 23, 2026 close: MSFT 24.45x (524.51 / 21.45 = 0.500 x FY2027-06 19.65 + 0.500 x FY2028-06 23.25), GOOGL 21.3x (320.21 / 15.03), META 18.94x (642.62 / 33.93) (comps_cy27.json). Used at the median (was 23x, 2.3% below the base round's 11-name median). EPS basis checked per peer against its filings (comps_cy27.json basis_note; coordinator warning 2026-10-26): all on AMZN's GAAP-after-stock-comp basis; ORCL re-based; SE and SHOP not re-basable from XBRL but confirmed on the same basis from their earnings releases (SE: Zacks = GAAP diluted EPS; SHOP: Zacks = net income excluding equity investments, stock comp a cost), and neither can move the median. The subject EPS it multiplies is consensus GAAP ex mark-to-market gains (MarketScreener FY2027 $10.51 at 10-06 via the EPS-per-EBIT link; Zacks has $10.65 today, +1.3%, same basis).
A17: Segment base revenue FY2025: North America + International / AWS | B17: $588,200M / $128,700M | C17: reported | E17: F3 | F17: AMZN deep model 2026-10-19: FY2025 segment net sales NA $426.3B + International $161.9B = $588.2B; AWS $128.7B; sum $716.9B = F3 (Q4-25 8-K Ex.99.1, https://www.sec.gov/Archives/edgar/data/1018724/000101872426000002/amzn-20251231xex991.htm).
A18: AWS revenue growth / EBIT margin FY2026-FY2030 | B18: 35.2% / 32.2% / 25.2% / 18% / 14%; 37% / 36% / 35% / 34% / 33% | C18: estimate | D18: 1, 2 | F18: AMZN deep model 2026-10-19: FY2026-28 follow the supervisor's SOTP path (agent_1: 2026E ~$174B = 128.7 x 1.352; 2027 ~$230B at 36%; 2028 ~$288B at 35%). Evidence: Q2-26 AWS $42.2B +37%, OI $16.6B (39.3%, incl. ~$0.6B energy-derivative gain, 520bp ex gain; https://www.sec.gov/Archives/edgar/data/1018724/000101872426000024/amzn-20260630xex991.htm, https://www.investing.com/news/transcripts/earnings-call-transcript-amazon-tops-q2-2026-estimates-as-aws-growth-accelerates-93CH-4826442); backlog $496B, 6.4-yr weighted life (10-Q, https://www.sec.gov/Archives/edgar/data/1018724/000101872426000026/amzn-20260630.htm); 'double the power capacity by the end of 2027 that we had in 2025', 2028 capacity 'quite a bit ... already reserved', chips run-rate 'over $25 billion' (Q2 call, https://www.investing.com/news/transcripts/earnings-call-transcript-amazon-tops-q2-2026-estimates-as-aws-growth-accelerates-93CH-4826442). 2029-30 fade to 18% / 14% and 34% / 33% for the D&A wave: judgment for a steady-state DCF year.
A19: North America + International revenue growth / EBIT margin FY2026-FY2030 | B19: 11.24% / 9.72% / 12.75% / 9% / 8%; 6.73% / 7.38% / 7.54% / 8.0% / 8.5% | C19: estimate | D19: 4, 1, 2 | F19: AMZN deep model 2026-10-19: consensus sales (MarketScreener 828.3 / 947.9 / 1,097.4, source 4) less the AWS path = 654.3 / 717.9 / 809.4; OI ~$44B / $53B / $61B (agent_1, incl. Leo and Zoox costs) / revenue. 2029-30 judgment. Ads services $19.8B in Q2-26, +26% y/y (https://www.sec.gov/Archives/edgar/data/1018724/000101872426000024/amzn-20260630xex991.htm); FY2025 ads $68.6B = 13,921 + 15,694 + 17,703 + 21,317 (quarterly table, https://www.sec.gov/Archives/edgar/data/1018724/000101872426000002/amzn-20251231xex991.htm).
A20: D&A % revenue FY2026-FY2030 | B20: 9.69% / 14.48% / 15.73% / 16.0% / 16.0% | C20: estimate | D20: 4 | E20: F39, F6 | F20: FY2026 TTM D&A $75,200M / $775,680M (F39 / F6); FY2027-28 consensus EBITDA less EBIT (MarketScreener 2026-10-06: (355.3 - 182.7) / 1,097.4 = 15.73% for FY2028; the 2026-10-19 page 274.3 - 141.0 = 14.0% for FY2027, drift); FY2029-30 held near 16% (judgment).
A21: Capex % revenue FY2026-FY2030 | B21: 26.56% / 29.27% / 27.06% / 22% / 17% | C21: estimate | D21: 4 | F21: FY2026 ~$220B cash capex (Q2 call, https://www.investing.com/news/transcripts/earnings-call-transcript-amazon-tops-q2-2026-estimates-as-aws-growth-accelerates-93CH-4826442) / $828.3B; FY2027-28 MarketScreener consensus $277.4B / $296.9B; FY2029-30 normalise toward D&A + growth (agent_3's steady state assumed ~14% capex; 17% kept above it): judgment.
A22: Diluted shares at the horizon | B22: 11,027.5M (10,903M x 1.009^1.27) | C22: estimate | D22: 2 | E22: F33 | F22: AMZN deep model 2026-10-19: Amazon settles awards without a tax-withholding cash line (no PaymentsRelatedToTaxWithholdingForShareBasedCompensation fact in https://data.sec.gov/api/xbrl/companyfacts/CIK0001018724.json; no buybacks, $6.1B authorisation left), so pre-horizon SBC is charged as dilution: diluted shares 10,806M (Q2-25) -> 10,903M (Q2-26) = +0.90%/yr (8-K, https://www.sec.gov/Archives/edgar/data/1018724/000101872426000024/amzn-20260630xex991.htm), rolled 1.27 years. SBC is counted once: as cost in post-horizon earnings, as dilution before. Globalstar stock is not added (the deal is deducted at its full $10.9B instead). Replaces the supervisor's 10,950M (which had ~0.5% for SBC and Globalstar).
A23: Net debt at the horizon (SOTP leg only) | B23: $58,364M | C23: estimate | D23: 1, 4 | E23: F92 | F23: AMZN deep model 2026-10-19: bottom-up: 6/30 net debt $10,332M (F92) + OpenAI $21,300M paid after quarter-end (10-Q) + H2-26 FCF ($34.0B consensus 2026 FCF outflow less H1 CFO $71,419M - capex $98,411M = -$26,992M, fact pack) = $7,008M + 2027 FCF to 10-06 0.765 x $8.2B = $6,273M + finance lease liabilities $13,451M (6/30 XBRL FinanceLeaseLiability, https://data.sec.gov/api/xbrl/companyfacts/CIK0001018724.json) = $58,364M. Operating leases ($96,320M) stay out: rent is in OI and EPS. Replaces the MarketScreener interpolation $61,086M (which excluded leases).
A24: SOTP leg: AWS part | B24: NTM after-tax OI (driver-built, ~$71,508M) x 21.3 | C24: estimate | D24: 1, 2, 4, 35, 36, 41, 42, 43, 44 | F24: NTM after-tax AWS OI at the 2027-10-23 horizon (0.189 x FY2027 + 0.811 x FY2028 driver EBIT, x 0.79) x 21.3x = median CY2027 P/E of the cloud peers MSFT 24.45x (524.51 / 21.45 = 0.500 x FY2027-06 19.65 + 0.500 x FY2028-06 23.25), ORCL 17.55x (126.16 / 7.1902: Zacks 8.1475 = 0.417 x FY2027-05 6.73 + 0.583 x FY2028-05 9.16, re-based to GAAP after stock comp x 0.8825), GOOGL 21.3x (320.21 / 15.03). Was 25x (anchored on MSFT); no premium kept: ORCL's low multiple is part of the approved set and no persistence evidence for an AWS premium over the median is on file. Variant: MSFT's 24.45x alone, +$10.2 on the research target (12m). EPS basis checked per peer against its filings (comps_cy27.json basis_note; coordinator warning 2026-10-26): all on AMZN's GAAP-after-stock-comp basis; ORCL re-based; SE and SHOP not re-basable from XBRL but confirmed on the same basis from their earnings releases (SE: Zacks = GAAP diluted EPS; SHOP: Zacks = net income excluding equity investments, stock comp a cost), and neither can move the median.
A25: SOTP leg: North America + International part | B25: split into Advertising and Stores ex-advertising parts (2026-10-26) | C25: estimate | D25: 1, 2, 4 | F25: Replaced by the two rows below: the segment OI on the driver split is advertising ~$46.4B NTM after tax vs stores ~$0.9B (0.5 x ads_rev; stores_m x stores_rev).
A26: SOTP leg: Advertising part | B26: NTM after-tax OI (driver-built, ~$46,409M) x 19.87 | C26: estimate | D26: 31, 32, 35, 36, 39, 40, 45, 46 | F26: Advertising OI = 0.5 x ads_rev (50% ad margin, flagged estimate in driver stores_m), NTM after-tax, x 19.87x = median CY2027 P/E of the ad-platform peers META 18.94x (642.62 / 33.93), GOOGL 21.3x (320.21 / 15.03), RDDT 20.79x (144.25 / 6.94), APP 13.08x (260.25 / 19.9). New part (2026-10-26): the segment's earnings are ~98% advertising on the driver split, so the retail median applies to stores only (METHOD.md: a segment-only comp values that segment only). EPS basis checked per peer against its filings (comps_cy27.json basis_note; coordinator warning 2026-10-26): all on AMZN's GAAP-after-stock-comp basis; ORCL re-based; SE and SHOP not re-basable from XBRL but confirmed on the same basis from their earnings releases (SE: Zacks = GAAP diluted EPS; SHOP: Zacks = net income excluding equity investments, stock comp a cost), and neither can move the median.
A27: SOTP leg: Stores ex-advertising part | B27: NTM after-tax OI (driver-built, ~$853M) x 37.56 | C27: estimate | D27: 33, 34, 37, 38, 47, 48, 49, 50, 51, 52 | F27: Stores ex-advertising OI = stores_m x stores_rev (reported basis, incl. Leo and Zoox losses), NTM after-tax, x 37.56x = median CY2027 P/E of the approved retail/commerce peers WMT 37.56x (119.89 / 3.1917 = 0.083 x FY2027-01 2.88 + 0.917 x FY2028-01 3.22), COST 42.8x (1003.32 / 23.4433 = 0.667 x FY2027-08 22.7 + 0.333 x FY2028-08 24.93), MELI 32.8x (1810.15 / 55.19), SE 16.55x (74.63 / 4.51), SHOP 91.67x (168.68 / 1.84). Out: BABA, PDD (China), CPNG (Korea). SE has 2 EPS estimates (thin). EPS basis checked per peer against its filings (comps_cy27.json basis_note; coordinator warning 2026-10-26): all on AMZN's GAAP-after-stock-comp basis; ORCL re-based; SE and SHOP not re-basable from XBRL but confirmed on the same basis from their earnings releases (SE: Zacks = GAAP diluted EPS; SHOP: Zacks = net income excluding equity investments, stock comp a cost), and neither can move the median.
A28: SOTP leg: venture add-back basis correction | B28: +$46,389M EV | C28: estimate | F28: Exit k=0.8 re-set 2026-10-26: capitalised at the P/E leg multiple 22.88x (was 21.3x): -(2,500 + 1,500) x 0.79 x (22.88 - 37.56) = 46,388.8 ($M). PREVIOUS DERIVATION: The Leo and Zoox loss add-backs are capitalised at the P/E leg's 21.3x (adjustments); on this leg their losses sit inside the stores part at 37.56x, so the add-back is re-based: -(2,500 + 1,500) x 0.79 x (21.3 - 37.56) = +$51,382M. Entered as metric x 1.0.
A29: Anthropic: Amazon investments and form | B29: $8.0B convertible notes (2023-25) + $5.0B Series G + $5.0B Series H preferred (Q2-26) = $18.0B cash; carrying notes $97.9B + preferred $92.5B = $190.4B at 6/30 | C29: reported | D29: 1 | F29: 10-Q (https://www.sec.gov/Archives/edgar/data/1018724/000101872426000026/amzn-20260630.htm): notes $8.0B invested Q3-23 to Q4-25, AFS Level 3, fair value $97.9B, unrealized gain $92.0B in AOCI; portions converted to nonvoting preferred in Q1-25 and Q1-26 (reclassified gains $4.5B H1-26); preferred carrying $92.5B after $5.0B Series G + $5.0B Series H; upward adjustments $50.5B Q2 / $62.8B H1. Financing facility for Anthropic up to $20.0B (now $15.0B), milestone-based, expiring 30 months after a liquidity event.
A30: Anthropic: Amazon fully diluted ownership | B30: 19.5% pre-IPO (range 17-21%); 17.60% at the IPO | C30: estimate | D30: 1 | F30: Filing-implied: $190.4B carrying at the Series H $965B post-money (Anthropic 2026-05-28, https://www.anthropic.com/news/series-h) = 19.73%; press: 'about 21%' (Motley Fool 2026-08-06, https://www.fool.com/investing/2026/08/06/amazons-stake-in-anthropic-could-be-worth-over-200/); 19.5% used. At the IPO: x 0.95 for the Public Benefit Fund (5% of shares, subject to stockholder approval; Anthropic 2026-10-18, https://www.anthropic.com/news/public-benefit-fund) x (1 - $75B primary / $1,500B) (IFR: up to $100B at ~$2T, scaled to $1.5T; https://www.ifre.com/equities/2499407/anthropic-pushes-ahead-with-mid-november-ipo) = 17.5987%.
A31: Anthropic: IPO valuation used | B31: $1,500B (variant $1,924B) | C31: estimate | F31: Reuters via Investing.com 2026-10-15: investors at the 2026-10-14 investor day discussed ~$1.5T, below the ~$2T floated; Q3 revenue $16.8B (+45% q/q), adjusted profitable (https://www.investing.com/news/stock-market-news/some-investors-push-anthropic-to-cut-ipo-valuation-to-15-trillion--report-4952696). Variant: Polymarket expected first-day close mixed with the no-IPO case, $1.92T, as in runs/2026-10-06/GOOGL/anthropic_stake_2026-10-19.md (https://gamma-api.polymarket.com/public-search?q=anthropic%20ipo).
A32: Anthropic: tax and lock-up | B32: 24% on the gain over $18.0B cost; 10.37% lock-up/blockage discount | C32: estimate | D32: 1 | F32: Tax: the run's 24% (H1-26 discrete tax $15.9B / ($62.8B + $4.5B) = 23.6%, supervisor; Q2 OCI tax $13,695M on $41,988M after-tax AFS gain = 24.6% of the pre-tax gain, XBRL). Lock-up: Finnerty (2012) average-strike put, 65% vol, 0.5 year = 10.37% (recomputed; 1 year 14.36%); vol basis SpaceX realized 67% since its June IPO (GOOGL Anthropic file).
A33: Anthropic stake (AMZN deep model 2026-10-19) | B33: $183,692M after tax and lock-up (stakes block) | C33: estimate | D33: 1 | F33: 17.5987% x $1,500,000M = $263,980M; tax 0.24 x (263,980 - 18,000) = $59,035M; x (1 - 0.1037) = $183,692M. vs the run's $149.0B (190.4 - 0.24 x 172.4) in the SOTP leg: +$34,692M; the P/E leg carried no stakes before (see the P/E leg row).
A34: Consensus EPS excludes Anthropic mark-to-market gains (no double count) | B34: Q2-26 GAAP EPS $5.75 vs consensus $1.82; FY26 consensus jumped from $8.73 (90 days ago) to $12.81-12.90 after the Q2 gain; FY27 $10.51 on both vendors | C34: consensus | D34: 5, 4 | E34: F27 | F34: Q2-26 GAAP EPS $5.75 (F27) included $53.4B of non-operating income (Other income $53,415M, 10-Q) against a $1.82 consensus (TheWrap, https://www.thewrap.com/industry-news/business/amazon-earnings-q2-2026/); FY2026 consensus (Yahoo EPS trend, https://finance.yahoo.com/quote/AMZN/analysis/, read 2026-10-19): $8.73 90 days ago -> $12.81 60 days ago -> $12.90 now, a +$4.1 jump after the Q2 print, about the after-tax gain per share ($53.4B x 0.76 / 10.9B = $3.72); FY2027 moved only $10.00 -> $10.49 over the same window ($10.51 at 2026-10-06, $10.55 now) and FY2028 $13.81 forecast no gains. So the P/E leg on consensus EPS values the core only and the stakes are added on top.
A35: OpenAI stake (AMZN deep model 2026-10-19) | B35: $50,000M (5.87% at $852B post-money), at cost = last priced round; no tax | C35: estimate | D35: 1 | F35: 10-Q (https://www.sec.gov/Archives/edgar/data/1018724/000101872426000026/amzn-20260630.htm): $15.0B Series C in Q1-26, $35.0B letter-agreement commitment, $13.7B funded in Q2, carrying $28.7B, remaining $21.3B invested after 6/30; converts to common on an IPO. Round: $122B at $730B pre / $852B post, closed March 2026 (ValueAdd VC, https://valueaddvc.com/blog/openai-valuation-2026-852-billion-after-the-122b-raise); ~$7B employee share sale at $852B, 2026-08-10 (Dealroom, https://dealroom.co/news/144253-openai-closes-7b-share-sale-at-852b-valuation-ahead-of-ipo/). 50 / 852 = 5.87%. Held at cost: the last two priced transactions are at the round price; the preference protects the downside. Not in consensus EPS (no gain recognised, measurement alternative).
A36: Other equity investments and warrants (AMZN deep model 2026-10-19) | B36: +$4,636M | C36: estimate | D36: 1 | F36: 10-Q (https://www.sec.gov/Archives/edgar/data/1018724/000101872426000026/amzn-20260630.htm): private company equity investments $122.3B (includes Anthropic preferred $92.5B and OpenAI Series C $28.7B) leaves $1.1B; + equity warrants $4.3B + equity-method $0.395B = $5.795B x 0.80 for tax and liquidity = $4,636M. Marketable equity securities ($3.498B Level 1 + $1.189B Level 2) sit in cash, cash equivalents and marketable securities, so they are already in net debt. Cross-check: notes 97.9 + private 122.3 + warrants 4.3 + equity-method 0.4 + marketable equity 4.7 = $229.6B, agent_3's $229.7B. Not in the run.
A37: Globalstar acquisition (AMZN deep model 2026-10-19) | B37: -$10,900M on both legs | C37: reported | D37: 1 | F37: 10-Q (https://www.sec.gov/Archives/edgar/data/1018724/000101872426000026/amzn-20260630.htm): agreement 2026-04-13; $90.00 cash or 0.3210 AMZN shares per share, cash elections capped at 40%; implied EV ~$10.9B incl. debt; close 2027. Was deducted in the SOTP leg only; the P/E leg now deducts it too (an investing outflow not in EPS). No Globalstar shares in the count (value deducted in full).
A38: Amazon Leo: loss in consensus earnings (AMZN deep model 2026-10-19) | B38: $2.5B pre-tax in the NTM year at the horizon (range 1.5-4.0) | C38: estimate | F38: Not disclosed. Barclays: Kuiper losses 'peak at $3.3 billion in 2025', an 80bp OI-margin drag (Investing.com 2024-12-20, https://investing.com/news/stock-market-news/how-will-amazon-fund-kuiper-barclays-weighs-in-3785104); Amazon: Q1-26 OI guide 'includes approximately $1 billion of higher year-over-year Amazon Leo costs' (https://www.sec.gov/Archives/edgar/data/1018724/000101872426000002/amzn-20251231xex991.htm); CFO: ~$1B higher 2026 Leo costs, >20 launches in 2026 and >30 in 2027 (Via Satellite 2026-02-09, https://www.satellitetoday.com/finance/2026/02/09/amazon-expects-to-increase-spending-on-amazon-leo-by-1b-in-2026/); costs sit in North America. So 2026 ~$4.3B (3.3 + 1.0, est.); judgment (not disclosed): once satellites enter service their cost runs through depreciation and early subscription revenue offsets operating costs, so the expensed loss falls from the 2026 level: $2.5B used for Oct-27 to Sep-28.
A39: Amazon Leo: loss add-back (AMZN deep model 2026-10-19) | B39: +$45,188M | C39: estimate | F39: Exit k=0.8 re-set 2026-10-26: capitalised at the P/E leg multiple 22.88x (was 21.3x): 2,500 x 0.79 x 22.88 = 45,188.0 ($M). PREVIOUS DERIVATION: 2,500 x 0.79 x 21.3 = 42,067.5 (both legs; re-based to the stores multiple on the SOTP leg by the basis correction). Was 23x.
A40: Amazon Leo: own value (AMZN deep model 2026-10-19) | B40: +$13,000M | C40: estimate | F40: Scenarios for a 2030 run-rate (est.): bear p.35 2M subs x $60 x 12 + $0.5B enterprise = ~$2.0B revenue at ~2x sales = $4B; base p.45 6M x $65 x 12 + $2.0B enterprise/government/direct-to-device (Globalstar) = $6.7B, 25% EBIT x 20 = $33.5B; bull p.20 12M x $66 x 12 + $4.5B = $14.0B, 35% EBIT x 22 = $108B. Weighted $38.1B, / 1.15^3 = $25.0B at the horizon, less ~$12B PV of the remaining first-generation build (analysts $16-20B in total, >$10B invested per the FCC filing) (18 - 10 = ~$8B) and pre-scale burn (~$4B, INDmoney's assumed net pre-scale outflow) = ~$13B. Anchors: Starlink Q2-26 revenue $4.291B, OI $1.656B (38.6%), 12.0M subscribers, ARPU $66 (INDmoney, updated 2026-10-15, https://www.indmoney.com/blog/us-stocks/amazon-kuiper-vs-starlink-amzn-spcx-satellite-internet-stock-analysis); its illustrative Leo values -$1.3B / $3.8B / $19.8B; first-gen $16-20B, ~390 satellites by 2026-07-02, commercial service later in 2026 (Yahoo Finance, https://finance.yahoo.com/markets/stocks/articles/amazon-finally-taking-fight-starlink-163300161.html); Leo 'close to 400 satellites in orbit' (Q2 call).
A41: Zoox: loss in consensus earnings (AMZN deep model 2026-10-19) | B41: $1.5B pre-tax a year (range 1.0-2.0) | C41: estimate | F41: Not disclosed. 5,029 employees (TipRanks, read 2026-10-19, https://www.tipranks.com/private-companies/zoox) x ~$0.3M fully loaded (est.) = ~$1.5B, plus fleet and depots ~$0.1-0.3B, less staff cost capitalised into the vehicle and factory build (est.): $1.5B used. Paid rides in Las Vegas from 2026-08-10 under the first NHTSA Part 555 exemption for a purpose-built robotaxi, NHTSA exemption announced 2026-07-30 'limits Zoox's commercial fleet up to 2,500 vehicles annually for two years' (TechCrunch, https://techcrunch.com/2026/07/30/zoox-clears-final-federal-hurdle-to-launch-paid-robotaxi-service/; first purpose-built robotaxi with a Part 555 exemption, Q2 8-K); Las Vegas service flips from free to paid on 2026-08-10 (AI Weekly summarising TechCrunch 2026-08-05, https://aiweekly.co/alerts/zoox-starts-charging-for-robotaxi-rides-in-las-vegas-aug-10).
A42: Zoox: loss add-back (AMZN deep model 2026-10-19) | B42: +$27,113M | C42: estimate | F42: Exit k=0.8 re-set 2026-10-26: capitalised at the P/E leg multiple 22.88x (was 21.3x): 1,500 x 0.79 x 22.88 = 27,112.8 ($M). PREVIOUS DERIVATION: 1,500 x 0.79 x 21.3 = 25,240.5 (both legs; re-based on the SOTP leg). Was 23x.
A43: Zoox: own value (AMZN deep model 2026-10-19) | B43: +$9,000M | C43: estimate | F43: Bear p.40 $2B (technology value; Amazon paid about $1.2B in 2020 after a $3.2B valuation in Zoox's last round, SiliconANGLE 2020-06-26, https://siliconangle.com/2020/06/26/amazon-acquires-autonomous-vehicle-startup-zoox-reported-1-2b-deal/), base p.45 $10B, bull p.15 $40B = $11.3B, x (1 - 20% haircut, no outside round, illiquid) = ~$9.0B. Comparable: Waymo $126B post-money (2026-02-02, https://waymo.com/blog/2026/02/waymo-raises-usd16-billion-investment-round) with an estimated 2,500-3,000 active vehicles (Not a Tesla App 2026-03-18, https://www.notateslaapp.com/news/3775/the-great-robotaxi-race-a-look-at-teslas-competition) vs Zoox's fleet of 105 (TechCrunch 2026-07-17, https://techcrunch.com/2026/07/17/zoox-issues-software-recall-after-a-robotaxi-got-confused-by-heavy-smoke/): fleet-pro-rata 126 x 105 / 2,750 = $4.8B.
A44: Legal remedies, probability-weighted (AMZN deep model 2026-10-19) | B44: -$32,279M (driver-built) | C44: estimate | F44: Peer refresh 2026-10-26: the FTC remedy base (retail+ads value) is now the SOTP's Advertising + Stores parts (19.87x and 37.56x on the driver metrics, ~$954B, was 22x x metric) and the ad-auction forward-pricing piece uses the ads multiple 19.87x (0.4 x 50% x $2.9B x 0.79 x 19.87 = $9.1B, was 22x $10.1B); everything else unchanged; the sub-figures after this sentence are the base round's (22x, $1,025B) and are superseded by the totals here: FTC -$14.7B, ad-auction -$13.1B (damages -$4.0B + forward pricing -$9.1B), California/consumer -$4.0B, EU -$0.45B = -$32.3B (driver value -$32,278.7M). Driver formula constant $17,584M = the base round's $18,560M (set from the rounded total -$34.35B) - 10,080 + 9,104; the exact fixed pieces sum to $17,553M (4,000 + 9,104 + 4,000 + 449), a $31M rounding residue kept (removing it leaves the base horizon value at $256.82 and moves the bull case by +$0.01). FTC v. Amazon monopolization: trial 2027-03-29, delay to June denied 2026-10-09 (MLex, https://www.mlex.com/mlex/antitrust/articles/2536525/amazon-s-bid-to-delay-us-ftc-monopolization-trial-rejected-by-judge); FTC lost its Meta monopolization case on 2025-11-18 (Hogan Lovells, memorandum dated 2025-11-18, https://www.hlc.com/en/publications/federal-judge-says-meta-is-not-a-monopoly-ending-ftcs-longrunning-antitrust-case). p(liability) 0.35 (est.); given liability 0.8 behavioural (3% of the $1,025B retail+ads value) + 0.2 structural (10%) = $45.1B -> -$15.8B. FTC + 22 states ad-auction suit (2026-08-31): auction-rule change from 2019 alleged to have cost advertisers '$20 billion or more', 'tens of billions' in damages sought (Reuters via The Star, https://www.thestar.com.my/tech/tech-news/2026/09/01/amazon-sued-by-ftc-and-over-20-us-states): damages p 0.5 x $8B (40% of the $20B alleged, est.) = -$4.0B; forward pricing 0.4 x 50% x $2.9B/yr (20 / 7 years) x 0.79 x 22 = -$10.1B. California AG pricing case (trial set 2027-01-19, CA AG, https://oag.ca.gov/news/press-releases/attorney-general-bonta-delivers-prime-victory-against-amazon-ongoing-price) and the U.S. consumer class actions (one certified, three pre-certification, 10-Q legal proceedings): -$4.0B (est.). EU: Luxembourg EUR 746M GDPR fine annulled 2026-03-12 (Chronicle, https://chronicle.lu/category/legal-ip/60106-luxembourg-court-annuls-cnpd-ruling-in-amazon-data-protection-case) p 0.4 x EUR 0.5B re-imposed (est.) + DMA marketplace p 0.2 x EUR 1.0B (est.), x EUR/USD 1.1212 (Twelve Data 2026-10-19, as in runs/2026-10-06/GOOGL/remaining_items_2026-10-19.md) = -$0.45B. No accrual is disclosed for any matter (10-Q legal proceedings; $7.1B tax contingencies excluded).
A45: Conglomerate overlay 10% on non-core parts (AMZN deep model 2026-10-19) | B45: -26,033M | C45: estimate | F45: 10% x $260,328M of post-haircut non-core parts (Anthropic 183,692 after 24% tax and the 10.37% lock-up, OpenAI 50,000, other investments 4,636, Leo 13,000, Zoox 9,000). Evidence (as in runs/2026-10-06/GOOGL/remaining_items_2026-10-19.md): Berger & Ofek (1995) 13-15% diversification discount (JFE 37(1)); Campa & Kedia (2002) and Villalonga (2004) find it shrinks or reverses after self-selection; listed holdcos SoftBank ~34-49%, Naspers/Prosus ~43% (August 2026) bundle tax, illiquidity, holdco costs and governance. Tax and lock-up are already deducted here and Amazon has no holdco layer, so only the agency part remains: 10%. Not applied to the core multiples, net debt or the loss add-backs.
A46: P/E leg: stakes and equity-level adjustments added | B46: adjustments and stakes per share on 11,027.5M shares | C46: estimate | D46: 1, 6, 7, 8, 9 | F46: AMZN deep model 2026-10-19: the supervisor left the stakes out of the P/E leg ('AMZN's own 24.4x already prices them'), but 23x is the CY2027 peer median less 2.3%, not AMZN's own multiple, and consensus EPS excludes the mark-to-market gains (row above), so the peer multiple on core EPS carries no stake value. Net debt stays out of this leg (interest is in EPS). Peers MSFT (OpenAI) and GOOGL (Anthropic, SpaceX) embed their own stakes in their multiples, a small upward bias in the 23.5x median (not adjusted).
A47: Scenario bear | B47: $211.17 at p 0.25 | C47: estimate | D47: 4, 23 | F47: AMZN deep model 2026-10-19: AI-capex digestion or a lab customer stumble (forecasters' median bear $195): AWS growth toward the low-to-mid 20s while 2027 capex lifts D&A; ~17.5x on NTM EPS ~$11 as ORCL trades, segment multiples cut by the same 24%, and Anthropic prices at ~$1.0T instead of $1.5T (stakes x 0.67). Engine deltas {"eps_pct": -0.15361929, "multiple": -5.5, "multiple_pct": -0.26560388} (stake re-mark folded into eps_pct / multiple_pct for the Sheet layout; original {eps_pct, multiple, multiple_pct, stake_pct} {"eps_pct": -0.121932, "multiple": -5.5, "multiple_pct": -0.23913, "stake_pct": -0.333333}); engine value $211.17. Prices before the deepening (forecasters' median, transcription): $195 / $280 / $350.
A48: Scenario base | B48: $297.65 at p 0.5 | C48: estimate | D48: 4, 23 | F48: AMZN deep model 2026-10-19: Equals the reconciled fair value: consensus broadly delivered, AWS ~30% on reserved capacity and the $496B backlog, 23x NTM EPS; Anthropic IPO at ~$1.5T; ventures at their scenario values. Engine deltas {}; engine value $297.65. Prices before the deepening (forecasters' median, transcription): $195 / $280 / $350.
A49: Scenario bull | B49: $348.84 at p 0.25 | C49: estimate | D49: 4, 23 | F49: AMZN deep model 2026-10-19: AWS holds 35%+ with Trainium, FCF inflects (forecasters' median bull $350 before stakes): ~25.5x on NTM EPS ~$13.75, segment multiples +11%, Anthropic at ~$1.92T (Polymarket first-day-close variant; stakes x 1.28). Engine deltas {"eps_pct": 0.11489804, "multiple": 2.5, "multiple_pct": 0.12968463} (stake re-mark folded into eps_pct / multiple_pct for the Sheet layout; original {eps_pct, multiple, multiple_pct, stake_pct} {"eps_pct": 0.097585, "multiple": 2.5, "multiple_pct": 0.108696, "stake_pct": 0.28}); engine value $348.84. Prices before the deepening (forecasters' median, transcription): $195 / $280 / $350.
A50: driver:aws_ppe | B50: AWS average net property and equipment (installed capacity, $): 150.4 -> 266.2/426.3/590.8 (estimate) | C50: estimate | F50: Year-end PP&E = prior + AWS net additions - AWS D&A (0.14 x average). Net additions = cash capex x 1.080 (FY25 net additions $142,352M / cash capex $131,819M, 10-K segment note / F57) x 0.76 (AWS share of H1-26 net additions 90,120 / 118,648). Cash capex: 2026 ~$220B (Q2 call; H1 $98,411M actual, fact pack), 2027 $277.4B, 2028 $296.9B (MarketScreener consensus, source 4). 2026 rolls from the actual 2026-06-30 balance $263,750M: + H2 net additions ($220B - $98.4B) x 1.080 x 0.76 - H2 D&A (0.07 x H2 average) = 342.3; 2027-28 full-year roll. Year-ends 342.3, 510.3, 671.3.
A51: driver:aws_turn | B51: AWS revenue per $ of average net PP&E (capacity turnover): 0.8561 -> 0.6528/0.5503/0.4972 (estimate) | C51: estimate | F51: Turnover = AWS revenue path / aws_ppe. Revenue: 2026 = H1 actual $79.8B + H2-25 ($33.0B + $35.6B, 8-K Q4-25 quarterly table) x 1.37 (Q2-26 growth) = $173.8B; 2027 +35% (power doubling end-2025 to end-2027 is ~+41%/yr; 2026's revenue grew ~6 points slower (35.0% vs 41.4%) than that, held) = $234.6B; 2028 +25.2% (agent_1 path, no capacity statement for 2028 beyond 'quite a bit reserved') = $293.8B.
A52: driver:aws_ebitda_m | B52: AWS EBITDA margin (segment OI + segment D&A) / AWS sales: 0.5209 -> 0.571/0.585/0.6 (estimate) | C52: estimate | F52: 2026 = H1-26 ex gain 57.1%; then +1.4 / +1.5 points to 58.5% / 60.0% (about 40% of the FY24-H1-26 pace of ~+3.8 pts/yr: Trainium mix and scale on the cash cost base).
A53: driver:ads_rev | B53: Advertising services revenue: 68.64 -> 85.44/102.5/121 (estimate) | C53: estimate | F53: 2026 = H1 actual + H2-25 ($17,703M + $21,317M, 8-K Q4-25 quarterly table) x 1.24 = $85.4B; 2027 +20%, 2028 +18% (est.: deceleration from the ~25% run-rate; the deep model's ~$102B 2027 is the same path).
A54: driver:stores_rev | B54: North America + International revenue excluding advertising (stores, 3P services, subscriptions, other): 519.6 -> 579.8/626.2/676.3 (estimate) | C54: estimate | F54: 2026 = H1 actual + H2-25 stores (NA+Intl H2-25 $324,970M - ads $39,020M) x 1.10 = $579.8B; 2027-28 +8% a year (est.: paid units ~+11% less 3P mix and price; consensus sales less AWS gives +9.7% / +12.7% for the whole segment, source 4).
A55: driver:stores_m | B55: Operating margin of NA + International excluding advertising (ads at an assumed 50% margin): 0.0001 -> 0.00162/0.00162/0.00162 (estimate) | C55: estimate | F55: 2026 calibrated so that NA + Intl OI = H1-26 actual $20.5B + H2-25 $18.5B x 1.25 = $43.7B (old path $44B); held flat in 2027-28 (est.), so segment OI growth comes from ads. Includes Leo and Zoox losses (added back by the venture adjustments).
A57: # | B57: Source | C57: Date | D57: Link
A58: 1 | B58: Amazon.com Form 10-Q, quarter ended June 30, 2026 (Anthropic $92.5B + $97.9B; OpenAI $28.7B + $21.3B subsequent; debt face $133.0B; cash $78.2B; securities $44.8B; RPO ~$496B; Globalstar ~$10.9B; $15.9B discrete tax) | C58: 2026-07-31 | D58: https://www.sec.gov/Archives/edgar/data/1018724/000101872426000026/amzn-20260630.htm
A59: 2 | B59: Amazon Q2 2026 earnings release (8-K Ex.99.1): segments, Q3 guidance, TTM FCF -$7.6B | C59: 2026-07-30 | D59: https://www.sec.gov/Archives/edgar/data/1018724/000101872426000024/amzn-20260630xex991.htm
A60: 3 | B60: SEC EDGAR submissions feed, Amazon (CIK 1018724): Form 4 only since Sep 24 | C60: 2026-10-06 | D60: https://data.sec.gov/submissions/CIK0001018724.json
A61: 4 | B61: MarketScreener Amazon finances: EPS 2027 $10.51 / 2028 $13.81; net debt 2026 $22.3B / 2027 $74.0B; FCF; capex; EBIT; EBITDA | C61: 2026-10-06 | D61: https://www.marketscreener.com/quote/stock/AMAZON-COM-INC-12864605/finances/
A62: 5 | B62: Yahoo Finance AMZN analysis: FY27 $10.51 (52), EPS trend, revisions, Q3 EPS $1.95 / revenue $202.03B | C62: 2026-10-06 | D62: https://finance.yahoo.com/quote/AMZN/analysis/
A63: 6 | B63: MarketScreener Microsoft finances (FY Jun EPS FY27 $19.70, FY28 $23.58; price $529.30) | C63: 2026-10-06 | D63: https://www.marketscreener.com/quote/stock/MICROSOFT-CORPORATION-4835/finances/
A64: 7 | B64: MarketScreener Alphabet finances (2027 P/E 23.3x) | C64: 2026-10-06 | D64: https://www.marketscreener.com/quote/stock/ALPHABET-INC-24203373/finances/
A65: 8 | B65: MarketScreener Meta finances (2027 P/E 21.8x) | C65: 2026-10-06 | D65: https://www.marketscreener.com/quote/stock/META-PLATFORMS-INC-10547141/finances/
A66: 9 | B66: MarketScreener Oracle finances (FY May EPS FY27 $6.643, FY28 $9.144; price $142.48) | C66: 2026-10-06 | D66: https://www.marketscreener.com/quote/stock/ORACLE-CORPORATION-13620698/finances/
A67: 10 | B67: MarketScreener Walmart finances (FY Jan-28 P/E 33x) | C67: 2026-10-06 | D67: https://www.marketscreener.com/quote/stock/WALMART-INC-4841/finances/
A68: 11 | B68: MarketScreener Costco finances (FY Aug EPS FY27 $22.78, FY28 $24.96; price $935.68) | C68: 2026-10-06 | D68: https://www.marketscreener.com/quote/stock/COSTCO-WHOLESALE-CORPORAT-4866/finances/
A69: 12 | B69: MarketScreener MercadoLibre finances (2027 P/E 33x) | C69: 2026-10-06 | D69: https://www.marketscreener.com/quote/stock/MERCADOLIBRE-INC-58469/finances/
... A118: 61 | B118: Amazon 8-K Ex.99.1 results release 2026-07-30 (net sales and operating income; next-quarter guidance) | C118: 2026-07-30 | D118: https://www.sec.gov/Archives/edgar/data/1018724/000101872426000024/amzn-20260630xex991.htm
A120: Fact id | B120: Figure | C120: Value | D120: Filing
A121: F1 | B121: revenue FY ending 2023-12-31 (us-gaap:RevenueFromContractWithCustomerExcludingAssessedTax) | C121: 574785000000 | D121: https://www.sec.gov/Archives/edgar/data/1018724/000101872426000004/
A122: F2 | B122: revenue FY ending 2024-12-31 (us-gaap:RevenueFromContractWithCustomerExcludingAssessedTax) | C122: 637959000000 | D122: https://www.sec.gov/Archives/edgar/data/1018724/000101872426000004/
A123: F3 | B123: revenue FY ending 2025-12-31 (us-gaap:RevenueFromContractWithCustomerExcludingAssessedTax) | C123: 716924000000 | D123: https://www.sec.gov/Archives/edgar/data/1018724/000101872426000004/
A124: F4 | B124: revenue YTD 2026-01-01 to 2026-06-30 | C124: 382125000000 | D124: https://www.sec.gov/Archives/edgar/data/1018724/000101872426000026/
A125: F5 | B125: revenue prior-year YTD 2025-01-01 to 2025-06-30 | C125: 323369000000 | D125: https://www.sec.gov/Archives/edgar/data/1018724/000101872426000026/
A126: F6 | B126: revenue TTM to 2026-06-30 | C126: 775680000000
A127: F7 | B127: revenue quarter 2026-04-01 to 2026-06-30 | C127: 200606000000 | D127: https://www.sec.gov/Archives/edgar/data/1018724/000101872426000026/
A128: F8 | B128: operating_income FY ending 2023-12-31 (us-gaap:OperatingIncomeLoss) | C128: 36852000000 | D128: https://www.sec.gov/Archives/edgar/data/1018724/000101872426000004/
A129: F9 | B129: operating_income FY ending 2024-12-31 (us-gaap:OperatingIncomeLoss) | C129: 68593000000 | D129: https://www.sec.gov/Archives/edgar/data/1018724/000101872426000004/
A130: F10 | B130: operating_income FY ending 2025-12-31 (us-gaap:OperatingIncomeLoss) | C130: 79975000000 | D130: https://www.sec.gov/Archives/edgar/data/1018724/000101872426000004/
A131: F11 | B131: operating_income YTD 2026-01-01 to 2026-06-30 | C131: 51313000000 | D131: https://www.sec.gov/Archives/edgar/data/1018724/000101872426000026/
A132: F12 | B132: operating_income prior-year YTD 2025-01-01 to 2025-06-30 | C132: 37576000000 | D132: https://www.sec.gov/Archives/edgar/data/1018724/000101872426000026/
A133: F13 | B133: operating_income TTM to 2026-06-30 | C133: 93712000000
A134: F14 | B134: operating_income quarter 2026-04-01 to 2026-06-30 | C134: 27461000000 | D134: https://www.sec.gov/Archives/edgar/data/1018724/000101872426000026/
A135: F15 | B135: net_income FY ending 2023-12-31 (us-gaap:NetIncomeLoss) | C135: 30425000000 | D135: https://www.sec.gov/Archives/edgar/data/1018724/000101872426000004/
A136: F16 | B136: net_income FY ending 2024-12-31 (us-gaap:NetIncomeLoss) | C136: 59248000000 | D136: https://www.sec.gov/Archives/edgar/data/1018724/000101872426000004/
A137: F17 | B137: net_income FY ending 2025-12-31 (us-gaap:NetIncomeLoss) | C137: 77670000000 | D137: https://www.sec.gov/Archives/edgar/data/1018724/000101872426000004/
A138: F18 | B138: net_income YTD 2026-01-01 to 2026-06-30 | C138: 92902000000 | D138: https://www.sec.gov/Archives/edgar/data/1018724/000101872426000026/
A139: F19 | B139: net_income prior-year YTD 2025-01-01 to 2025-06-30 | C139: 35291000000 | D139: https://www.sec.gov/Archives/edgar/data/1018724/000101872426000026/
A140: F20 | B140: net_income TTM to 2026-06-30 | C140: 135281000000
A141: F21 | B141: net_income quarter 2026-04-01 to 2026-06-30 | C141: 62647000000 | D141: https://www.sec.gov/Archives/edgar/data/1018724/000101872426000026/
A142: F22 | B142: eps_diluted FY ending 2023-12-31 (us-gaap:EarningsPerShareDiluted) | C142: 2.9 | D142: https://www.sec.gov/Archives/edgar/data/1018724/000101872426000004/
A143: F23 | B143: eps_diluted FY ending 2024-12-31 (us-gaap:EarningsPerShareDiluted) | C143: 5.53 | D143: https://www.sec.gov/Archives/edgar/data/1018724/000101872426000004/
A144: F24 | B144: eps_diluted FY ending 2025-12-31 (us-gaap:EarningsPerShareDiluted) | C144: 7.17 | D144: https://www.sec.gov/Archives/edgar/data/1018724/000101872426000004/
A145: F25 | B145: eps_diluted YTD 2026-01-01 to 2026-06-30 | C145: 8.53 | D145: https://www.sec.gov/Archives/edgar/data/1018724/000101872426000026/
A146: F26 | B146: eps_diluted prior-year YTD 2025-01-01 to 2025-06-30 | C146: 3.27 | D146: https://www.sec.gov/Archives/edgar/data/1018724/000101872426000026/
A147: F27 | B147: eps_diluted quarter 2026-04-01 to 2026-06-30 | C147: 5.75 | D147: https://www.sec.gov/Archives/edgar/data/1018724/000101872426000026/
A148: F28 | B148: diluted_shares_wavg FY ending 2023-12-31 (us-gaap:WeightedAverageNumberOfDilutedSharesOutstanding) | C148: 10492000000 | D148: https://www.sec.gov/Archives/edgar/data/1018724/000101872426000004/
A149: F29 | B149: diluted_shares_wavg FY ending 2024-12-31 (us-gaap:WeightedAverageNumberOfDilutedSharesOutstanding) | C149: 10721000000 | D149: https://www.sec.gov/Archives/edgar/data/1018724/000101872426000004/
A150: F30 | B150: diluted_shares_wavg FY ending 2025-12-31 (us-gaap:WeightedAverageNumberOfDilutedSharesOutstanding) | C150: 10827000000 | D150: https://www.sec.gov/Archives/edgar/data/1018724/000101872426000004/
A151: F31 | B151: diluted_shares_wavg YTD 2026-01-01 to 2026-06-30 | C151: 10889000000 | D151: https://www.sec.gov/Archives/edgar/data/1018724/000101872426000026/
...
