Workbook

Sheet Summary
A1: VST standard model (trial) · research run 2026-10-23
A2: The supervisor's reconciled assumption set as a live model. Trial: shown beside the blended page target, not used for trade levels until its weight is decided. Edit blue cells on Model (drivers) and Valuation (assumptions).
A3: Price target box | B3: Value
A4: Live price | B4: =IFERROR(GOOGLEFINANCE("VST","price"),Valuation!$B$66)
A5: Price as of | B5: =NOW()
A6: Model target (12-month median) | B6: =Distribution!$B$13
A7: Upside to model target from live price | B7: =B6/B4-1
A8: Research target (12m) (no scenario deltas) | B8: =Valuation!$D$6
A9: Probability-weighted mean | B9: =Distribution!$B$10
A10: 10th percentile | B10: =Distribution!$B$14
A11: 25th percentile | B11: =Distribution!$B$15
A12: 75th percentile | B12: =Distribution!$B$16
A13: 90th percentile | B13: =Distribution!$B$17
A14: Target date | B14: =Valuation!$B$44
A15: Price at the run | B15: =Valuation!$B$66
A16: Blended page target (options 67% + agents 33%, not live) | B16: 144.6756
A17: Supervisor research target (12m) (its own methods) | B17: 147.67
A18: Thesis break price (supervisor) | B18: 115
A19: Supervisor confidence | B19: medium
A21: Key estimates | B21: FY2025A | C21: =Model!E5 | D21: =Model!F5
A22: Net sales | B22: =IF(Model!D24="","",Model!D24) | C22: =Model!E24 | D22: =Model!F24
A23: % YoY | B23: =IF(Model!D25="","",Model!D25) | C23: =Model!E25 | D23: =Model!F25
A24: Pretax margin | B24: =IF(Model!D35="","",Model!D35) | C24: =Model!E35 | D24: =Model!F35
A25: Diluted EPS (model) | B25: =IF(Model!D42="","",Model!D42) | C25: =Model!E42 | D25: =Model!F42
A26: % YoY | B26: =IF(Model!D43="","",Model!D43) | C26: =Model!E43 | D26: =Model!F43
A27: Free cash flow to firm | B27: =IF(Model!D52="","",Model!D52) | C27: =Model!E52 | D27: =Model!F52
A29: Valuation method | B29: Value per share | C29: Weight
A30: =Valuation!A4 | B30: =Valuation!D4 | C30: =Valuation!E4
A31: =Valuation!A5 | B31: =Valuation!D5 | C31: =Valuation!E5
A33: Scenario | B33: Probability | C33: Value at target date | D33: What has to happen
A34: =Distribution!A4 | B34: =Distribution!B4 | C34: =Distribution!C4 | D34: =Distribution!D4
A35: =Distribution!A5 | B35: =Distribution!B5 | C35: =Distribution!C5 | D35: =Distribution!D5
A36: =Distribution!A6 | B36: =Distribution!B6 | C36: =Distribution!C6 | D36: =Distribution!D6
A38: Price at target date | B38: Probability above
A39: =ROUND(Valuation!$B$66*0.7,0) | B39: =SUMPRODUCT(Distribution!$B$4:$B$6,1-NORMSDIST((LN(A39)-LN(Distribution!$C$4:$C$6))/Distribution!$B$9))
A40: =ROUND(Valuation!$B$66*0.8,0) | B40: =SUMPRODUCT(Distribution!$B$4:$B$6,1-NORMSDIST((LN(A40)-LN(Distribution!$C$4:$C$6))/Distribution!$B$9))
A41: =ROUND(Valuation!$B$66*0.9,0) | B41: =SUMPRODUCT(Distribution!$B$4:$B$6,1-NORMSDIST((LN(A41)-LN(Distribution!$C$4:$C$6))/Distribution!$B$9))
A42: =ROUND(Valuation!$B$66*1.0,0) | B42: =SUMPRODUCT(Distribution!$B$4:$B$6,1-NORMSDIST((LN(A42)-LN(Distribution!$C$4:$C$6))/Distribution!$B$9))
A43: =ROUND(Valuation!$B$66*1.1,0) | B43: =SUMPRODUCT(Distribution!$B$4:$B$6,1-NORMSDIST((LN(A43)-LN(Distribution!$C$4:$C$6))/Distribution!$B$9))
A44: =ROUND(Valuation!$B$66*1.2,0) | B44: =SUMPRODUCT(Distribution!$B$4:$B$6,1-NORMSDIST((LN(A44)-LN(Distribution!$C$4:$C$6))/Distribution!$B$9))
A45: =ROUND(Valuation!$B$66*1.3,0) | B45: =SUMPRODUCT(Distribution!$B$4:$B$6,1-NORMSDIST((LN(A45)-LN(Distribution!$C$4:$C$6))/Distribution!$B$9))
A46: =ROUND(Valuation!$B$66*1.5,0) | B46: =SUMPRODUCT(Distribution!$B$4:$B$6,1-NORMSDIST((LN(A46)-LN(Distribution!$C$4:$C$6))/Distribution!$B$9))
A48: Model checks | B48: Status
A49: Scenario probabilities sum to 100% | B49: =IF(ABS(Distribution!B8-1)<0.005,"ok","FLAG: "&TEXT(Distribution!B8,"0.0%"))
A50: WACC exceeds terminal growth by 1 point or more | B50: =IF('Calc - research target (12m)'!B55="ok","ok","FLAG")
A51: Projection runs a full year past the target date | B51: =IF('Calc - research target (12m)'!B56="ok","ok","FLAG")
A52: Method weights add up to more than zero | B52: =IF(SUM(Valuation!E4:E5)>0,"ok","FLAG")
A53: Terminal value under 85% of the DCF | B53: =IF('Calc - research target (12m)'!B46<0.85,"ok","note: "&TEXT('Calc - research target (12m)'!B46,"0%")&" of the DCF is terminal value")
A54: Segment base revenues tie to the last reported net sales (within 2%) | B54: =IF(ABS(Valuation!$B$88/Valuation!$B$49-1)<=0.02,"ok","FLAG")
A55: Matches the engine run at publication (target, research target (12m)) | B55: =IF(AND(ABS(Distribution!$B$13-144.4938)<0.01,ABS(Valuation!$D$6-147.6735)<0.01),"ok","inputs edited since publication")
A56: All checks | B56: =IF(COUNTIF(B49:B55,"ok")=7,"all ok",7-COUNTIF(B49:B55,"ok")&" to look at")

Sheet Model
A1: VST: annual model, base case
A2: (M of US dollars except per share; fiscal years named by the calendar year they end in)
A3: Blue = input · black = formula · green = link to another tab · actuals from SEC filings (fact ids in the last column, links on Sources)
A5: Fiscal year | B5: FY2023A | C5: FY2024A | D5: FY2025A | E5: FY2026E | F5: FY2027E | G5: FY2028E | H5: Source / note
A6: Period end | B6: 45291 | C6: 45657 | D6: 46022 | E6: =IF(DAY(Valuation!$B$48+1)=1,EOMONTH(Valuation!$B$48,12*E7),EDATE(Valuation!$B$48,12*E7)) | F6: =IF(DAY(Valuation!$B$48+1)=1,EOMONTH(Valuation!$B$48,12*F7),EDATE(Valuation!$B$48,12*F7)) | G6: =IF(DAY(Valuation!$B$48+1)=1,EOMONTH(Valuation!$B$48,12*G7),EDATE(Valuation!$B$48,12*G7))
A7: Projection year | B7: -2 | C7: -1 | D7: 0 | E7: 1 | F7: 2 | G7: 3
A10: Segment build (blue = input: revenue growth and EBIT margin by segment and year)
A11: Generation | D11: =Valuation!$B$86 | E11: =Valuation!$B$86*(1+E12) | F11: =E11*(1+F12) | G11: =F11*(1+G12)
A12: Revenue growth | E12: 0.19942963 | F12: 0.090378102 | G12: 0.0011564796
A13: Segment EBIT | E13: =E11*E14 | F13: =F11*F14 | G13: =G11*G14
A14: EBIT margin | E14: 1.4725031 | F14: 1.504293 | G14: 1.4996695
A15: Retail | D15: =Valuation!$B$87 | E15: =Valuation!$B$87*(1+E16) | F15: =E15*(1+F16) | G15: =F15*(1+G16)
A16: Revenue growth | E16: 0.0078475979 | F16: 0.032026108 | G16: 0.0042040712
A17: Segment EBIT | E17: =E15*E18 | F17: =F15*F18 | G17: =G15*G18
A18: EBIT margin | E18: 0.0060350261 | F18: 0.0038899324 | G18: 0.0042658658
A19: Total segment revenue (= net sales) | D19: =D11+D15 | E19: =E11+E15 | F19: =F11+F15 | G19: =G11+G15 | H19: base revenues on Valuation (segment build); net sales = this total
A20: Total segment EBIT | E20: =E13+E17 | F20: =F13+F17 | G20: =G13+G17
A21: Corporate / unallocated EBIT (blue = input) | E21: -2880 | F21: -3116 | G21: -3223 | H21: years[].corporate_ebit; EBIT = total segment EBIT + corporate
A23: Sales
A24: Net sales | B24: 13804 | C24: 14761 | D24: 17586 | E24: =E19 | F24: =F19 | G24: =G19 | H24: SEC XBRL F1, F2, F3
A25: % YoY | C25: =IF(OR(C24="",B24="",B24=0),"",C24/B24-1) | D25: =IF(OR(D24="",C24="",C24=0),"",D24/C24-1) | E25: =E24/Valuation!$B$49-1 | F25: =F24/E24-1 | G25: =G24/F24-1
A27: Operating profit
A28: EBIT (operating income) | E28: =E20+E21 | F28: =F20+F21 | G28: =G20+G21
A29: EBIT margin | E29: =E28/E24 | F29: =F28/F24 | G29: =G28/G24
A30: D&A | B30: 1502 | C30: 1843 | D30: 1986 | E30: =E24*E64 | F30: =F24*F64 | G30: =G24*G64 | H30: SEC XBRL F34, F35, F36
A31: EBITDA | E31: =E28+E30 | F31: =F28+F30 | G31: =G28+G30
A32: EBITDA margin | E32: =E31/E24 | F32: =F31/F24 | G32: =G31/G24
A33: Net interest income / (expense) | E33: =-Valuation!$B$57*Valuation!$B$55 | F33: =-Valuation!$B$57*E58 | G33: =-Valuation!$B$57*F58 | H33: rate x prior year-end net debt (memo roll)
A34: Pretax income | B34: 2000 | C34: 3467 | D34: 1123 | E34: =E28+E33 | F34: =F28+F33 | G34: =G28+G33 | H34: SEC XBRL F90, F91, F92
A35: Pretax margin | B35: =B34/B24 | C35: =C34/C24 | D35: =D34/D24 | E35: =E34/E24 | F35: =F34/F24 | G35: =G34/G24
A36: Income tax | B36: 508 | C36: 655 | D36: 179 | E36: =E34*E63 | F36: =F34*F63 | G36: =G34*G63 | H36: SEC XBRL F83, F84, F85
A37: Effective tax rate | B37: =B36/B34 | C37: =C36/C34 | D37: =D36/D34 | E37: =E36/E34 | F37: =F36/F34 | G37: =G36/G34
A38: Net income | B38: 1493 | C38: 2659 | D38: 944 | E38: =E34-E36 | F38: =F34-F36 | G38: =G34-G36 | H38: SEC XBRL F15, F16, F17
A39: % YoY | C39: =IF(OR(C38="",B38="",B38=0),"",C38/B38-1) | D39: =IF(OR(D38="",C38="",C38=0),"",D38/C38-1) | E39: =IF(OR(D38="",D38=0),"",E38/D38-1) | F39: =IF(OR(E38="",E38=0),"",F38/E38-1) | G39: =IF(OR(F38="",F38=0),"",G38/F38-1)
A40: Diluted shares (M, average) | B40: 375.19311 | C40: 352.56706 | D40: 345.65607 | E40: =Valuation!$B$59*(1+Valuation!$B$61)^(E7-0.5-((Valuation!$B$60-Valuation!$B$48)/365.25)) | F40: =Valuation!$B$59*(1+Valuation!$B$61)^(F7-0.5-((Valuation!$B$60-Valuation!$B$48)/365.25)) | G40: =Valuation!$B$59*(1+Valuation!$B$61)^(G7-0.5-((Valuation!$B$60-Valuation!$B$48)/365.25)) | H40: diluted count rolled at the annual change to mid-year
A41: % YoY | C41: =IF(OR(C40="",B40="",B40=0),"",C40/B40-1) | D41: =IF(OR(D40="",C40="",C40=0),"",D40/C40-1) | E41: =IF(OR(D40="",D40=0),"",E40/D40-1) | F41: =IF(OR(E40="",E40=0),"",F40/E40-1) | G41: =IF(OR(F40="",F40=0),"",G40/F40-1)
A42: Diluted EPS | B42: 3.58 | C42: 7 | D42: 2.18 | E42: =E38/E40 | F42: =F38/F40 | G42: =G38/G40 | H42: SEC XBRL F22, F23, F24
A43: % YoY | C43: =IF(OR(C42="",B42="",B42=0),"",C42/B42-1) | D43: =IF(OR(D42="",C42="",C42=0),"",D42/C42-1) | E43: =IF(OR(D42="",D42=0),"",E42/D42-1) | F43: =IF(OR(E42="",E42=0),"",F42/E42-1) | G43: =IF(OR(F42="",F42=0),"",G42/F42-1)
A45: Cash flow
A46: NOPAT (EBIT x (1 - tax)) | E46: =E28*(1-E63) | F46: =F28*(1-F63) | G46: =G28*(1-G63)
A47: + D&A | B47: =B30 | C47: =C30 | D47: =D30 | E47: =E30 | F47: =F30 | G47: =G30
A48: - Capex | B48: 1676 | C48: 2078 | D48: 2752 | E48: =E24*E65 | F48: =F24*F65 | G48: =G24*G65 | H48: SEC XBRL F55, F56, F57
A49: Capex % of sales | B49: =B48/B24 | C49: =C48/C24 | D49: =D48/D24 | E49: =E48/E24 | F49: =F48/F24 | G49: =G48/G24
A50: - Working capital increase | E50: =E66*(E24-Valuation!$B$49) | F50: =F66*(F24-E24) | G50: =G66*(G24-F24)
A51: - Stock comp (adjusted EBIT only) | E51: =IF(AND(Valuation!$B$46="adjusted",Valuation!$B$47="cost"),E55*(1-E63),0) | F51: =IF(AND(Valuation!$B$46="adjusted",Valuation!$B$47="cost"),F55*(1-F63),0) | G51: =IF(AND(Valuation!$B$46="adjusted",Valuation!$B$47="cost"),G55*(1-G63),0)
A52: Free cash flow to firm | E52: =E46+E47-E48-E50-E51 | F52: =F46+F47-F48-F50-F51 | G52: =G46+G47-G48-G50-G51 | H52: what the DCF discounts (Calc tabs)
A53: Operating cash flow (reported) | B53: 5453 | C53: 4563 | D53: 4070 | H53: SEC XBRL F48, F49, F50
A54: FCF (operating cash flow - capex) | B54: =B53-B48 | C54: =C53-C48 | D54: =D53-D48
A55: Stock comp (memo) | B55: 77 | C55: 100 | D55: 113 | E55: =E24*E67 | F55: =F24*F67 | G55: =G24*G67 | H55: SEC XBRL F41, F42, F43
A56: Buybacks + dividends + other uses | B56: 1558 | C56: 1571 | D56: 1334 | E56: =E24*E69+E68+E70 | F56: =F24*F69+F68+F70 | G56: =G24*G69+G68+G70 | H56: SEC XBRL F62, F69, F63, F70, F64, F71
A57: % of sales | B57: =B56/B24 | C57: =C56/C24 | D57: =D56/D24 | E57: =E56/E24 | F57: =F56/F24 | G57: =G56/G24
A58: Net debt / (net cash), year end (memo) | E58: =Valuation!$B$55-E52-E33*(1-E63)+E56 | F58: =E58-F52-F33*(1-F63)+F56 | G58: =F58-G52-G33*(1-G63)+G56 | H58: rolled from the balance-date figure; feeds interest only
A60: Drivers (blue = input; a year left black carries the prior year)
A61: Revenue growth | C61: =C25 | D61: =D25 | E61: =E25 | F61: =F25 | G61: =G25 | H61: implied by the segment build (edit the segment rows)
A62: EBIT margin | E62: =E29 | F62: =F29 | G62: =G29 | H62: implied by the segment build and corporate EBIT
A63: Tax rate | B63: =B37 | C63: =C37 | D63: =D37 | E63: 0.2 | F63: =E63 | G63: =F63
A64: D&A % revenue | B64: =B30/B24 | C64: =C30/C24 | D64: =D30/D24 | E64: 0.11 | F64: =E64 | G64: =F64
A65: Capex % revenue | B65: =B49 | C65: =C49 | D65: =D49 | E65: 0.145 | F65: 0.135 | G65: 0.105
A66: Working capital % of revenue increase | E66: 0.03 | F66: =E66 | G66: =F66
A67: Stock comp % revenue | B67: =B55/B24 | C67: =C55/C24 | D67: =D55/D24 | E67: 0.007 | F67: =E67 | G67: =F67
A68: Shareholder returns ($) | E68: 1500 | F68: 1500 | G68: 1500
A69: Shareholder returns % revenue | B69: =B57 | C69: =C57 | D69: =D57 | E69: 0 | F69: =E69 | G69: =F69
A70: Other uses of cash ($: M&A, investments) | E70: 0 | F70: 0 | G70: 0
A71: Adj. EBITDA addback % revenue | E71: 0 | F71: =E71 | G71: =F71
A73: Versus company guidance and street consensus
A74: Guidance: Adjusted EBITDA (Ongoing Operations) (Ongoing Operations Adjusted EBITDA (adds back non-cash comp $137M, D&A incl. nuclear fuel amortization, unrealized hedge marks)), midpoint | E74: =AVERAGE(6800,7600) | H74: 6800 to 7600; as of 2026-08-07; source 1, 2 (Vistra Q2 2026 results news release (8-K Ex. 99.1): 2026 gui)
A75: Guidance: Adjusted FCFbG (Ongoing Operations) (Ongoing Operations Adjusted Free Cash Flow before Growth), midpoint | E75: =AVERAGE(3925,4725) | H75: 3925 to 4725; as of 2026-08-07; source 1 (Vistra Q2 2026 results news release (8-K Ex. 99.1): 2026 gui)
A76: Guidance: Adjusted EBITDA midpoint opportunity (not guidance) (Ongoing Operations Adjusted EBITDA; excludes Cogentrix and the Meta PPA premium; curves as of 2025-10-31), midpoint | F76: =AVERAGE(7400,7800) | H76: 7400 to 7800; as of 2026-08-07; source 1, 2 (Vistra Q2 2026 results news release (8-K Ex. 99.1): 2026 gui)

Sheet Valuation
A1: VST: valuation and price target derivation
A2: Value per share at the target date = weighted methods below; the 12-month target is the median of the scenario mix (Distribution tab).
A3: Method | B3: Multiple | C3: Metric at target date | D3: Value per share | E3: Weight | F3: Contribution
A4: ='Calc - research target (12m)'!A67 | B4: =IF('Calc - research target (12m)'!C67="","",'Calc - research target (12m)'!C67) | C4: =IF('Calc - research target (12m)'!I67="","",'Calc - research target (12m)'!I67) | D4: ='Calc - research target (12m)'!F67 | E4: ='Calc - research target (12m)'!G67 | F4: =D4*E4/SUM($E$4:$E$5)
A5: ='Calc - research target (12m)'!A68 | B5: =IF('Calc - research target (12m)'!C68="","",'Calc - research target (12m)'!C68) | C5: =IF('Calc - research target (12m)'!I68="","",'Calc - research target (12m)'!I68) | D5: ='Calc - research target (12m)'!F68 | E5: ='Calc - research target (12m)'!G68 | F5: =D5*E5/SUM($E$4:$E$5)
A6: Research target (12m) per share | D6: ='Calc - research target (12m)'!$F$69 | F6: =SUM(F4:F5)
A8: 12-month EPS basis (what the P/E is applied to)
A9: Fiscal year | B9: =Model!E5 | C9: =Model!F5 | D9: =Model!G5
A10: Share of the 12 months after the target date | B10: ='Calc - research target (12m)'!C38 | C10: ='Calc - research target (12m)'!D38 | D10: ='Calc - research target (12m)'!E38
A11: Model EPS (Model tab) | B11: =Model!E42 | C11: =Model!F42 | D11: =Model!G42
A12: Model EPS, next 12 months after the target date | B12: =SUMPRODUCT(B10:D10,B11:D11)
A15: DCF build (free cash flow to firm, discounted to the target date)
A16: Fiscal year | B16: =Model!E5 | C16: =Model!F5 | D16: =Model!G5
A17: Free cash flow to firm | B17: ='Calc - research target (12m)'!C31 | C17: ='Calc - research target (12m)'!D31 | D17: ='Calc - research target (12m)'!E31
A18: Share of the year after the target date | B18: ='Calc - research target (12m)'!C35 | C18: ='Calc - research target (12m)'!D35 | D18: ='Calc - research target (12m)'!E35
A19: PV at target date | B19: ='Calc - research target (12m)'!C36 | C19: ='Calc - research target (12m)'!D36 | D19: ='Calc - research target (12m)'!E36
A21: PV of free cash flow after the target date | B21: ='Calc - research target (12m)'!B42
A22: Terminal value (final year) | B22: ='Calc - research target (12m)'!B43
A23: PV of terminal value | B23: ='Calc - research target (12m)'!B44
A24: Enterprise value at target date | B24: ='Calc - research target (12m)'!B45
A25: Terminal value share of DCF | B25: ='Calc - research target (12m)'!B46
A26: Net debt at target date | B26: ='Calc - research target (12m)'!B50
A27: Minority interests | B27: ='Calc - research target (12m)'!B51
A28: Adjustments | B28: ='Calc - research target (12m)'!B52
A29: Diluted shares at target date (M) | B29: ='Calc - research target (12m)'!B53
A30: DCF value per share | B30: ='Calc - research target (12m)'!F67
A31: WACC | B31: ='Calc - research target (12m)'!B12
A41: Assumptions (blue = input; sources on the Sources tab)
A42: Input | B42: Value | C42: Basis / note
A43: Run date (valuation as of) | B43: 46318
A44: Target date (run date + 365 days) | B44: =B43+365 | C44: 12-month horizon
A45: Money unit | B45: $M
A46: EBIT basis (gaap / adjusted) | B46: adjusted | C46: gaap = after stock comp
A47: Stock comp treatment (cost / dilution) | B47: dilution | C47: used only when EBIT is adjusted
A48: Last reported fiscal year end | B48: 46022
A49: Net sales, last reported year ($M) | B49: 17586
A50: WACC | B50: 0.09 | C50: Cost of equity 10.7% = 10-yr UST 5.21% (FRED DGS10, 2026-10-13, src 10) + beta 1.15 (judgment between agents' 1.1-1.3; merchant IPP with contracted nuclear) x ERP 4.75%; pre-tax cost of debt 6.5% (new junior subordinated notes priced at 7.000%/7.250%, src 14; senior debt lower; TTM interest 1,132 / debt 19,595 = 5.8%, F81/F98) x (1 - 20%) = 5.2%; weights ~70% equity ($51.1B = 152.2 x 335.6M) / 30% net debt + preferred ($21.6B). WACC = 0.7 x 10.7% + 0.3 x 5.2% = 9.0%.
A51: Terminal method (gordon / exit_multiple / steady_state) | B51: gordon
A52: Terminal growth | B52: 0.025
A53: Exit EV/EBITDA (exit_multiple only)
A54: Balance-sheet date | B54: 46203
A55: Net debt / (net cash) at balance date ($M) | B55: 19160 | C55: excludes operating leases
A56: Minority interests + preferred stock | B56: 2488
A57: Interest rate on net debt / cash | B57: 0.058
A58: Net debt at target date (override; blank = bridge) | B58: 20421.229
A59: Diluted shares (M) | B59: 335.6
A60: Share count date | B60: 46237
A61: Annual change in diluted shares | B61: 0 | C61: net of buybacks and stock-comp dilution
A62: Shares at target date (override; blank = from annual change) | B62: 334.6
A63: DCF weight | B63: 0 | C63: Kilian 2026-10-21: 0 unless the name has a DCF leg (dcf_policy)
A64: Sum-of-the-parts weight | B64: 0
A65: Spread within each scenario (lognormal vol) | B65: 0.27
A66: Share price at the run | B66: 140.16 | C66: close used by the run (2026-10-23)
A68: Target multiple | B68: Multiple | C68: Weight | D68: Basis (ntm / ltm) | E68: EBITDA basis | F68: Stated EPS | G68: Stated FCF/share | H68: Levered | I68: Peer basis
A69: EV/EBITDA | B69: 9 | C69: 0.7 | D69: ntm | E69: adjusted | H69: TRUE | I69: Peer refresh 2026-10-26 (Kilian 06:07Z): merchant/IPP peers only, CEG, TLN, NRG (3; regulated utilities NEE ETR D AEP SO DUK EXC PEG left the table, European generators context only). NTM EV/EBITDA at the 2026-10-23 close: CEG 10.9x, TLN 10.1x, NRG 8.5x; median 10.06x (TLN), mean 9.83x (CEG.ev_ebitda_ntm, TLN.ev_ebitda_ntm, NRG.ev_ebitda_ntm; consensus adjusted EBITDA, Bigdata.com/FMP snapshots of 2026-10-14, same NTM window, no peer print since; TLN basis checked against its own Adj. EBITDA definition, src 12, 17). Was 10.6x at the 10-14 close: peer prices fell 8-10% (CEG 279.34 -> 253.45, TLN 358.57 -> 327.91, NRG 100.84 -> 92.31), mostly the 10-22 sector move with no news. 9.0x = the base round's 1.1x (~10%) discount kept on the new median (10.06 - 1.1 = 8.96, rounded): the persistence case is unchanged and still on evidence, ERCOT merchant exposure (2028 only ~72% hedged, ERCOT forwards 'meaningfully lower', src 1-2) and the open PJM 2030/31+ design (src 6-7). VST itself ~9.3x NTM standalone adjusted EBITDA at 140.16 (estimate: EV $68.7B = 140.16 x 335.6M + 19,160 net debt + 2,488 pref/NCI, over ~$7.4B standalone).
A71: Segment (sum of the parts) | B71: NTM metric | C71: Metric | D71: Multiple | E71: Note
A72: none
A74: Adjustment (equity level) | B74: Value | C74: Probability | D74: Note
A75: Cogentrix tax benefits (NPV) | B75: 700 | C75: 0.9 | D75: Vistra's Cogentrix release (8-K Ex. 99.1, 2026-01-05) nets 'approximately $0.7 billion of net present value of expected tax benefits' out of the ~$4.7B gross price; the EV/EBITDA leg and the 20% DCF tax rate do not capture this deal-specific tax shield. x 0.9 closing probability (FERC approved per the Q2 release; NH/TX/CT approvals and an outside date of 2026-12-31, extendable twice by 90 days, per the 8-K).
A77: Custom method | B77: Value per share | C77: Weight | D77: Explanation
A78: none
A80: Scenario | B80: Probability | C80: Growth Δ | D80: Margin Δ | E80: Multiple Δ (turns) | F80: WACC Δ | G80: Multiple %Δ (FCF yield, segments) | H80: Stated EPS/FCF %Δ | I80: Custom methods %Δ | J80: Story
A81: bear | B81: 0.25 | E81: -1.5 | F81: 0.005 | J81: ERCOT forwards stay near $30/MWh as 2028 hedges roll off, PJM signals a cap or administrative design for 2030/31+, rates stay >5%: 8.0x NTM and ~2.5pt lower margins. Driver form: gen_price -3% (~-$1.9/MWh fleet, ~-$7/MWh on the open 2028 book) = ~-$460M FY2028 EBITDA. | K81: driver deltas: gen_price -0.03 %
A82: base | B82: 0.5 | J82: FY2026 7300 / FY2027 8055 / FY2028 7943 Ongoing Ops Adj. EBITDA from the drivers; 9.5x NTM adjusted EBITDA at the horizon.
A83: bull | B83: 0.25 | E83: 1.25 | J83: More nuclear contracted with hyperscalers (Comanche Peak, Beaver Valley), PJM capacity stays tight after the collar: 10.75x and ~2pt higher margins. Driver form: gen_price +2.5% = ~+$385M FY2028 EBITDA. | K83: driver deltas: gen_price +0.025 %
A85: Segment build (segment_build) | B85: Base revenue ($M) | C85: Driver note (growth and EBIT margin by year: Model tab)
A86: Generation | B86: 4561
A87: Retail | B87: 13025
A88: Sum of segment base revenues | B88: =SUM(B86:B87) | C88: =IF(ABS(B88/Valuation!$B$49-1)<=0.02,"ties to the last reported net sales (within 2%)","FLAG: does not tie to the last reported net sales")

Sheet Sensitivity
A1: VST: sensitivity tables (bold = current inputs; every cell recalculates from the live model)
A3: DCF value per share: WACC (down) x terminal growth (across)
A4: WACC \ growth | B4: =Valuation!$B$52+(-0.01) | C4: =Valuation!$B$52+(-0.005) | D4: =Valuation!$B$52+(0) | E4: =Valuation!$B$52+(0.005) | F4: =Valuation!$B$52+(0.01)
A5: =Valuation!$B$50+(-0.01) | B5: =IF($A5-B$4<=0.01,"n/a",((SUMPRODUCT('Calc - research target (12m)'!$C$31:$E$31,'Calc - research target (12m)'!$C$35:$E$35,(1+$A5)^(-('Calc - research target (12m)'!$C$19:$E$19-'Calc - research target (12m)'!$B$13)))+'Calc - research target (12m)'!$E$31*(1+B$4)/($A5-B$4)/(1+$A5)^('Calc - research target (12m)'!$B$16-'Calc - research target (12m)'!$B$13))-'Calc - research target (12m)'!$B$50-'Calc - research target (12m)'!$B$51+'Calc - research target (12m)'!$B$52)/'Calc - research target (12m)'!$B$53) | C5: =IF($A5-C$4<=0.01,"n/a",((SUMPRODUCT('Calc - research target (12m)'!$C$31:$E$31,'Calc - research target (12m)'!$C$35:$E$35,(1+$A5)^(-('Calc - research target (12m)'!$C$19:$E$19-'Calc - research target (12m)'!$B$13)))+'Calc - research target (12m)'!$E$31*(1+C$4)/($A5-C$4)/(1+$A5)^('Calc - research target (12m)'!$B$16-'Calc - research target (12m)'!$B$13))-'Calc - research target (12m)'!$B$50-'Calc - research target (12m)'!$B$51+'Calc - research target (12m)'!$B$52)/'Calc - research target (12m)'!$B$53) | D5: =IF($A5-D$4<=0.01,"n/a",((SUMPRODUCT('Calc - research target (12m)'!$C$31:$E$31,'Calc - research target (12m)'!$C$35:$E$35,(1+$A5)^(-('Calc - research target (12m)'!$C$19:$E$19-'Calc - research target (12m)'!$B$13)))+'Calc - research target (12m)'!$E$31*(1+D$4)/($A5-D$4)/(1+$A5)^('Calc - research target (12m)'!$B$16-'Calc - research target (12m)'!$B$13))-'Calc - research target (12m)'!$B$50-'Calc - research target (12m)'!$B$51+'Calc - research target (12m)'!$B$52)/'Calc - research target (12m)'!$B$53) | E5: =IF($A5-E$4<=0.01,"n/a",((SUMPRODUCT('Calc - research target (12m)'!$C$31:$E$31,'Calc - research target (12m)'!$C$35:$E$35,(1+$A5)^(-('Calc - research target (12m)'!$C$19:$E$19-'Calc - research target (12m)'!$B$13)))+'Calc - research target (12m)'!$E$31*(1+E$4)/($A5-E$4)/(1+$A5)^('Calc - research target (12m)'!$B$16-'Calc - research target (12m)'!$B$13))-'Calc - research target (12m)'!$B$50-'Calc - research target (12m)'!$B$51+'Calc - research target (12m)'!$B$52)/'Calc - research target (12m)'!$B$53) | F5: =IF($A5-F$4<=0.01,"n/a",((SUMPRODUCT('Calc - research target (12m)'!$C$31:$E$31,'Calc - research target (12m)'!$C$35:$E$35,(1+$A5)^(-('Calc - research target (12m)'!$C$19:$E$19-'Calc - research target (12m)'!$B$13)))+'Calc - research target (12m)'!$E$31*(1+F$4)/($A5-F$4)/(1+$A5)^('Calc - research target (12m)'!$B$16-'Calc - research target (12m)'!$B$13))-'Calc - research target (12m)'!$B$50-'Calc - research target (12m)'!$B$51+'Calc - research target (12m)'!$B$52)/'Calc - research target (12m)'!$B$53)
A6: =Valuation!$B$50+(-0.005) | B6: =IF($A6-B$4<=0.01,"n/a",((SUMPRODUCT('Calc - research target (12m)'!$C$31:$E$31,'Calc - research target (12m)'!$C$35:$E$35,(1+$A6)^(-('Calc - research target (12m)'!$C$19:$E$19-'Calc - research target (12m)'!$B$13)))+'Calc - research target (12m)'!$E$31*(1+B$4)/($A6-B$4)/(1+$A6)^('Calc - research target (12m)'!$B$16-'Calc - research target (12m)'!$B$13))-'Calc - research target (12m)'!$B$50-'Calc - research target (12m)'!$B$51+'Calc - research target (12m)'!$B$52)/'Calc - research target (12m)'!$B$53) | C6: =IF($A6-C$4<=0.01,"n/a",((SUMPRODUCT('Calc - research target (12m)'!$C$31:$E$31,'Calc - research target (12m)'!$C$35:$E$35,(1+$A6)^(-('Calc - research target (12m)'!$C$19:$E$19-'Calc - research target (12m)'!$B$13)))+'Calc - research target (12m)'!$E$31*(1+C$4)/($A6-C$4)/(1+$A6)^('Calc - research target (12m)'!$B$16-'Calc - research target (12m)'!$B$13))-'Calc - research target (12m)'!$B$50-'Calc - research target (12m)'!$B$51+'Calc - research target (12m)'!$B$52)/'Calc - research target (12m)'!$B$53) | D6: =IF($A6-D$4<=0.01,"n/a",((SUMPRODUCT('Calc - research target (12m)'!$C$31:$E$31,'Calc - research target (12m)'!$C$35:$E$35,(1+$A6)^(-('Calc - research target (12m)'!$C$19:$E$19-'Calc - research target (12m)'!$B$13)))+'Calc - research target (12m)'!$E$31*(1+D$4)/($A6-D$4)/(1+$A6)^('Calc - research target (12m)'!$B$16-'Calc - research target (12m)'!$B$13))-'Calc - research target (12m)'!$B$50-'Calc - research target (12m)'!$B$51+'Calc - research target (12m)'!$B$52)/'Calc - research target (12m)'!$B$53) | E6: =IF($A6-E$4<=0.01,"n/a",((SUMPRODUCT('Calc - research target (12m)'!$C$31:$E$31,'Calc - research target (12m)'!$C$35:$E$35,(1+$A6)^(-('Calc - research target (12m)'!$C$19:$E$19-'Calc - research target (12m)'!$B$13)))+'Calc - research target (12m)'!$E$31*(1+E$4)/($A6-E$4)/(1+$A6)^('Calc - research target (12m)'!$B$16-'Calc - research target (12m)'!$B$13))-'Calc - research target (12m)'!$B$50-'Calc - research target (12m)'!$B$51+'Calc - research target (12m)'!$B$52)/'Calc - research target (12m)'!$B$53) | F6: =IF($A6-F$4<=0.01,"n/a",((SUMPRODUCT('Calc - research target (12m)'!$C$31:$E$31,'Calc - research target (12m)'!$C$35:$E$35,(1+$A6)^(-('Calc - research target (12m)'!$C$19:$E$19-'Calc - research target (12m)'!$B$13)))+'Calc - research target (12m)'!$E$31*(1+F$4)/($A6-F$4)/(1+$A6)^('Calc - research target (12m)'!$B$16-'Calc - research target (12m)'!$B$13))-'Calc - research target (12m)'!$B$50-'Calc - research target (12m)'!$B$51+'Calc - research target (12m)'!$B$52)/'Calc - research target (12m)'!$B$53)
A7: =Valuation!$B$50+(0) | B7: =IF($A7-B$4<=0.01,"n/a",((SUMPRODUCT('Calc - research target (12m)'!$C$31:$E$31,'Calc - research target (12m)'!$C$35:$E$35,(1+$A7)^(-('Calc - research target (12m)'!$C$19:$E$19-'Calc - research target (12m)'!$B$13)))+'Calc - research target (12m)'!$E$31*(1+B$4)/($A7-B$4)/(1+$A7)^('Calc - research target (12m)'!$B$16-'Calc - research target (12m)'!$B$13))-'Calc - research target (12m)'!$B$50-'Calc - research target (12m)'!$B$51+'Calc - research target (12m)'!$B$52)/'Calc - research target (12m)'!$B$53) | C7: =IF($A7-C$4<=0.01,"n/a",((SUMPRODUCT('Calc - research target (12m)'!$C$31:$E$31,'Calc - research target (12m)'!$C$35:$E$35,(1+$A7)^(-('Calc - research target (12m)'!$C$19:$E$19-'Calc - research target (12m)'!$B$13)))+'Calc - research target (12m)'!$E$31*(1+C$4)/($A7-C$4)/(1+$A7)^('Calc - research target (12m)'!$B$16-'Calc - research target (12m)'!$B$13))-'Calc - research target (12m)'!$B$50-'Calc - research target (12m)'!$B$51+'Calc - research target (12m)'!$B$52)/'Calc - research target (12m)'!$B$53) | D7: =IF($A7-D$4<=0.01,"n/a",((SUMPRODUCT('Calc - research target (12m)'!$C$31:$E$31,'Calc - research target (12m)'!$C$35:$E$35,(1+$A7)^(-('Calc - research target (12m)'!$C$19:$E$19-'Calc - research target (12m)'!$B$13)))+'Calc - research target (12m)'!$E$31*(1+D$4)/($A7-D$4)/(1+$A7)^('Calc - research target (12m)'!$B$16-'Calc - research target (12m)'!$B$13))-'Calc - research target (12m)'!$B$50-'Calc - research target (12m)'!$B$51+'Calc - research target (12m)'!$B$52)/'Calc - research target (12m)'!$B$53) | E7: =IF($A7-E$4<=0.01,"n/a",((SUMPRODUCT('Calc - research target (12m)'!$C$31:$E$31,'Calc - research target (12m)'!$C$35:$E$35,(1+$A7)^(-('Calc - research target (12m)'!$C$19:$E$19-'Calc - research target (12m)'!$B$13)))+'Calc - research target (12m)'!$E$31*(1+E$4)/($A7-E$4)/(1+$A7)^('Calc - research target (12m)'!$B$16-'Calc - research target (12m)'!$B$13))-'Calc - research target (12m)'!$B$50-'Calc - research target (12m)'!$B$51+'Calc - research target (12m)'!$B$52)/'Calc - research target (12m)'!$B$53) | F7: =IF($A7-F$4<=0.01,"n/a",((SUMPRODUCT('Calc - research target (12m)'!$C$31:$E$31,'Calc - research target (12m)'!$C$35:$E$35,(1+$A7)^(-('Calc - research target (12m)'!$C$19:$E$19-'Calc - research target (12m)'!$B$13)))+'Calc - research target (12m)'!$E$31*(1+F$4)/($A7-F$4)/(1+$A7)^('Calc - research target (12m)'!$B$16-'Calc - research target (12m)'!$B$13))-'Calc - research target (12m)'!$B$50-'Calc - research target (12m)'!$B$51+'Calc - research target (12m)'!$B$52)/'Calc - research target (12m)'!$B$53)
A8: =Valuation!$B$50+(0.005) | B8: =IF($A8-B$4<=0.01,"n/a",((SUMPRODUCT('Calc - research target (12m)'!$C$31:$E$31,'Calc - research target (12m)'!$C$35:$E$35,(1+$A8)^(-('Calc - research target (12m)'!$C$19:$E$19-'Calc - research target (12m)'!$B$13)))+'Calc - research target (12m)'!$E$31*(1+B$4)/($A8-B$4)/(1+$A8)^('Calc - research target (12m)'!$B$16-'Calc - research target (12m)'!$B$13))-'Calc - research target (12m)'!$B$50-'Calc - research target (12m)'!$B$51+'Calc - research target (12m)'!$B$52)/'Calc - research target (12m)'!$B$53) | C8: =IF($A8-C$4<=0.01,"n/a",((SUMPRODUCT('Calc - research target (12m)'!$C$31:$E$31,'Calc - research target (12m)'!$C$35:$E$35,(1+$A8)^(-('Calc - research target (12m)'!$C$19:$E$19-'Calc - research target (12m)'!$B$13)))+'Calc - research target (12m)'!$E$31*(1+C$4)/($A8-C$4)/(1+$A8)^('Calc - research target (12m)'!$B$16-'Calc - research target (12m)'!$B$13))-'Calc - research target (12m)'!$B$50-'Calc - research target (12m)'!$B$51+'Calc - research target (12m)'!$B$52)/'Calc - research target (12m)'!$B$53) | D8: =IF($A8-D$4<=0.01,"n/a",((SUMPRODUCT('Calc - research target (12m)'!$C$31:$E$31,'Calc - research target (12m)'!$C$35:$E$35,(1+$A8)^(-('Calc - research target (12m)'!$C$19:$E$19-'Calc - research target (12m)'!$B$13)))+'Calc - research target (12m)'!$E$31*(1+D$4)/($A8-D$4)/(1+$A8)^('Calc - research target (12m)'!$B$16-'Calc - research target (12m)'!$B$13))-'Calc - research target (12m)'!$B$50-'Calc - research target (12m)'!$B$51+'Calc - research target (12m)'!$B$52)/'Calc - research target (12m)'!$B$53) | E8: =IF($A8-E$4<=0.01,"n/a",((SUMPRODUCT('Calc - research target (12m)'!$C$31:$E$31,'Calc - research target (12m)'!$C$35:$E$35,(1+$A8)^(-('Calc - research target (12m)'!$C$19:$E$19-'Calc - research target (12m)'!$B$13)))+'Calc - research target (12m)'!$E$31*(1+E$4)/($A8-E$4)/(1+$A8)^('Calc - research target (12m)'!$B$16-'Calc - research target (12m)'!$B$13))-'Calc - research target (12m)'!$B$50-'Calc - research target (12m)'!$B$51+'Calc - research target (12m)'!$B$52)/'Calc - research target (12m)'!$B$53) | F8: =IF($A8-F$4<=0.01,"n/a",((SUMPRODUCT('Calc - research target (12m)'!$C$31:$E$31,'Calc - research target (12m)'!$C$35:$E$35,(1+$A8)^(-('Calc - research target (12m)'!$C$19:$E$19-'Calc - research target (12m)'!$B$13)))+'Calc - research target (12m)'!$E$31*(1+F$4)/($A8-F$4)/(1+$A8)^('Calc - research target (12m)'!$B$16-'Calc - research target (12m)'!$B$13))-'Calc - research target (12m)'!$B$50-'Calc - research target (12m)'!$B$51+'Calc - research target (12m)'!$B$52)/'Calc - research target (12m)'!$B$53)
A9: =Valuation!$B$50+(0.01) | B9: =IF($A9-B$4<=0.01,"n/a",((SUMPRODUCT('Calc - research target (12m)'!$C$31:$E$31,'Calc - research target (12m)'!$C$35:$E$35,(1+$A9)^(-('Calc - research target (12m)'!$C$19:$E$19-'Calc - research target (12m)'!$B$13)))+'Calc - research target (12m)'!$E$31*(1+B$4)/($A9-B$4)/(1+$A9)^('Calc - research target (12m)'!$B$16-'Calc - research target (12m)'!$B$13))-'Calc - research target (12m)'!$B$50-'Calc - research target (12m)'!$B$51+'Calc - research target (12m)'!$B$52)/'Calc - research target (12m)'!$B$53) | C9: =IF($A9-C$4<=0.01,"n/a",((SUMPRODUCT('Calc - research target (12m)'!$C$31:$E$31,'Calc - research target (12m)'!$C$35:$E$35,(1+$A9)^(-('Calc - research target (12m)'!$C$19:$E$19-'Calc - research target (12m)'!$B$13)))+'Calc - research target (12m)'!$E$31*(1+C$4)/($A9-C$4)/(1+$A9)^('Calc - research target (12m)'!$B$16-'Calc - research target (12m)'!$B$13))-'Calc - research target (12m)'!$B$50-'Calc - research target (12m)'!$B$51+'Calc - research target (12m)'!$B$52)/'Calc - research target (12m)'!$B$53) | D9: =IF($A9-D$4<=0.01,"n/a",((SUMPRODUCT('Calc - research target (12m)'!$C$31:$E$31,'Calc - research target (12m)'!$C$35:$E$35,(1+$A9)^(-('Calc - research target (12m)'!$C$19:$E$19-'Calc - research target (12m)'!$B$13)))+'Calc - research target (12m)'!$E$31*(1+D$4)/($A9-D$4)/(1+$A9)^('Calc - research target (12m)'!$B$16-'Calc - research target (12m)'!$B$13))-'Calc - research target (12m)'!$B$50-'Calc - research target (12m)'!$B$51+'Calc - research target (12m)'!$B$52)/'Calc - research target (12m)'!$B$53) | E9: =IF($A9-E$4<=0.01,"n/a",((SUMPRODUCT('Calc - research target (12m)'!$C$31:$E$31,'Calc - research target (12m)'!$C$35:$E$35,(1+$A9)^(-('Calc - research target (12m)'!$C$19:$E$19-'Calc - research target (12m)'!$B$13)))+'Calc - research target (12m)'!$E$31*(1+E$4)/($A9-E$4)/(1+$A9)^('Calc - research target (12m)'!$B$16-'Calc - research target (12m)'!$B$13))-'Calc - research target (12m)'!$B$50-'Calc - research target (12m)'!$B$51+'Calc - research target (12m)'!$B$52)/'Calc - research target (12m)'!$B$53) | F9: =IF($A9-F$4<=0.01,"n/a",((SUMPRODUCT('Calc - research target (12m)'!$C$31:$E$31,'Calc - research target (12m)'!$C$35:$E$35,(1+$A9)^(-('Calc - research target (12m)'!$C$19:$E$19-'Calc - research target (12m)'!$B$13)))+'Calc - research target (12m)'!$E$31*(1+F$4)/($A9-F$4)/(1+$A9)^('Calc - research target (12m)'!$B$16-'Calc - research target (12m)'!$B$13))-'Calc - research target (12m)'!$B$50-'Calc - research target (12m)'!$B$51+'Calc - research target (12m)'!$B$52)/'Calc - research target (12m)'!$B$53)
A11: Research target (12m) per share: EV/EBITDA multiple (down) x metric at target date (across)
A12: Multiple \ metric | B12: ='Calc - research target (12m)'!$E$68*0.9 | C12: ='Calc - research target (12m)'!$E$68*0.95 | D12: ='Calc - research target (12m)'!$E$68*1.0 | E12: ='Calc - research target (12m)'!$E$68*1.05 | F12: ='Calc - research target (12m)'!$E$68*1.1
A13: =Valuation!$B$69+(-3) | B13: =((SUMPRODUCT('Calc - research target (12m)'!$F$67:$F$68,'Calc - research target (12m)'!$G$67:$G$68)-'Calc - research target (12m)'!$F$68*'Calc - research target (12m)'!$G$68)+'Calc - research target (12m)'!$G$68*((($A13*B$12)-'Calc - research target (12m)'!$B$50-'Calc - research target (12m)'!$B$51+'Calc - research target (12m)'!$B$52)/'Calc - research target (12m)'!$B$53))/SUM('Calc - research target (12m)'!$G$67:$G$68) | C13: =((SUMPRODUCT('Calc - research target (12m)'!$F$67:$F$68,'Calc - research target (12m)'!$G$67:$G$68)-'Calc - research target (12m)'!$F$68*'Calc - research target (12m)'!$G$68)+'Calc - research target (12m)'!$G$68*((($A13*C$12)-'Calc - research target (12m)'!$B$50-'Calc - research target (12m)'!$B$51+'Calc - research target (12m)'!$B$52)/'Calc - research target (12m)'!$B$53))/SUM('Calc - research target (12m)'!$G$67:$G$68) | D13: =((SUMPRODUCT('Calc - research target (12m)'!$F$67:$F$68,'Calc - research target (12m)'!$G$67:$G$68)-'Calc - research target (12m)'!$F$68*'Calc - research target (12m)'!$G$68)+'Calc - research target (12m)'!$G$68*((($A13*D$12)-'Calc - research target (12m)'!$B$50-'Calc - research target (12m)'!$B$51+'Calc - research target (12m)'!$B$52)/'Calc - research target (12m)'!$B$53))/SUM('Calc - research target (12m)'!$G$67:$G$68) | E13: =((SUMPRODUCT('Calc - research target (12m)'!$F$67:$F$68,'Calc - research target (12m)'!$G$67:$G$68)-'Calc - research target (12m)'!$F$68*'Calc - research target (12m)'!$G$68)+'Calc - research target (12m)'!$G$68*((($A13*E$12)-'Calc - research target (12m)'!$B$50-'Calc - research target (12m)'!$B$51+'Calc - research target (12m)'!$B$52)/'Calc - research target (12m)'!$B$53))/SUM('Calc - research target (12m)'!$G$67:$G$68) | F13: =((SUMPRODUCT('Calc - research target (12m)'!$F$67:$F$68,'Calc - research target (12m)'!$G$67:$G$68)-'Calc - research target (12m)'!$F$68*'Calc - research target (12m)'!$G$68)+'Calc - research target (12m)'!$G$68*((($A13*F$12)-'Calc - research target (12m)'!$B$50-'Calc - research target (12m)'!$B$51+'Calc - research target (12m)'!$B$52)/'Calc - research target (12m)'!$B$53))/SUM('Calc - research target (12m)'!$G$67:$G$68)
A14: =Valuation!$B$69+(-2) | B14: =((SUMPRODUCT('Calc - research target (12m)'!$F$67:$F$68,'Calc - research target (12m)'!$G$67:$G$68)-'Calc - research target (12m)'!$F$68*'Calc - research target (12m)'!$G$68)+'Calc - research target (12m)'!$G$68*((($A14*B$12)-'Calc - research target (12m)'!$B$50-'Calc - research target (12m)'!$B$51+'Calc - research target (12m)'!$B$52)/'Calc - research target (12m)'!$B$53))/SUM('Calc - research target (12m)'!$G$67:$G$68) | C14: =((SUMPRODUCT('Calc - research target (12m)'!$F$67:$F$68,'Calc - research target (12m)'!$G$67:$G$68)-'Calc - research target (12m)'!$F$68*'Calc - research target (12m)'!$G$68)+'Calc - research target (12m)'!$G$68*((($A14*C$12)-'Calc - research target (12m)'!$B$50-'Calc - research target (12m)'!$B$51+'Calc - research target (12m)'!$B$52)/'Calc - research target (12m)'!$B$53))/SUM('Calc - research target (12m)'!$G$67:$G$68) | D14: =((SUMPRODUCT('Calc - research target (12m)'!$F$67:$F$68,'Calc - research target (12m)'!$G$67:$G$68)-'Calc - research target (12m)'!$F$68*'Calc - research target (12m)'!$G$68)+'Calc - research target (12m)'!$G$68*((($A14*D$12)-'Calc - research target (12m)'!$B$50-'Calc - research target (12m)'!$B$51+'Calc - research target (12m)'!$B$52)/'Calc - research target (12m)'!$B$53))/SUM('Calc - research target (12m)'!$G$67:$G$68) | E14: =((SUMPRODUCT('Calc - research target (12m)'!$F$67:$F$68,'Calc - research target (12m)'!$G$67:$G$68)-'Calc - research target (12m)'!$F$68*'Calc - research target (12m)'!$G$68)+'Calc - research target (12m)'!$G$68*((($A14*E$12)-'Calc - research target (12m)'!$B$50-'Calc - research target (12m)'!$B$51+'Calc - research target (12m)'!$B$52)/'Calc - research target (12m)'!$B$53))/SUM('Calc - research target (12m)'!$G$67:$G$68) | F14: =((SUMPRODUCT('Calc - research target (12m)'!$F$67:$F$68,'Calc - research target (12m)'!$G$67:$G$68)-'Calc - research target (12m)'!$F$68*'Calc - research target (12m)'!$G$68)+'Calc - research target (12m)'!$G$68*((($A14*F$12)-'Calc - research target (12m)'!$B$50-'Calc - research target (12m)'!$B$51+'Calc - research target (12m)'!$B$52)/'Calc - research target (12m)'!$B$53))/SUM('Calc - research target (12m)'!$G$67:$G$68)
A15: =Valuation!$B$69+(-1) | B15: =((SUMPRODUCT('Calc - research target (12m)'!$F$67:$F$68,'Calc - research target (12m)'!$G$67:$G$68)-'Calc - research target (12m)'!$F$68*'Calc - research target (12m)'!$G$68)+'Calc - research target (12m)'!$G$68*((($A15*B$12)-'Calc - research target (12m)'!$B$50-'Calc - research target (12m)'!$B$51+'Calc - research target (12m)'!$B$52)/'Calc - research target (12m)'!$B$53))/SUM('Calc - research target (12m)'!$G$67:$G$68) | C15: =((SUMPRODUCT('Calc - research target (12m)'!$F$67:$F$68,'Calc - research target (12m)'!$G$67:$G$68)-'Calc - research target (12m)'!$F$68*'Calc - research target (12m)'!$G$68)+'Calc - research target (12m)'!$G$68*((($A15*C$12)-'Calc - research target (12m)'!$B$50-'Calc - research target (12m)'!$B$51+'Calc - research target (12m)'!$B$52)/'Calc - research target (12m)'!$B$53))/SUM('Calc - research target (12m)'!$G$67:$G$68) | D15: =((SUMPRODUCT('Calc - research target (12m)'!$F$67:$F$68,'Calc - research target (12m)'!$G$67:$G$68)-'Calc - research target (12m)'!$F$68*'Calc - research target (12m)'!$G$68)+'Calc - research target (12m)'!$G$68*((($A15*D$12)-'Calc - research target (12m)'!$B$50-'Calc - research target (12m)'!$B$51+'Calc - research target (12m)'!$B$52)/'Calc - research target (12m)'!$B$53))/SUM('Calc - research target (12m)'!$G$67:$G$68) | E15: =((SUMPRODUCT('Calc - research target (12m)'!$F$67:$F$68,'Calc - research target (12m)'!$G$67:$G$68)-'Calc - research target (12m)'!$F$68*'Calc - research target (12m)'!$G$68)+'Calc - research target (12m)'!$G$68*((($A15*E$12)-'Calc - research target (12m)'!$B$50-'Calc - research target (12m)'!$B$51+'Calc - research target (12m)'!$B$52)/'Calc - research target (12m)'!$B$53))/SUM('Calc - research target (12m)'!$G$67:$G$68) | F15: =((SUMPRODUCT('Calc - research target (12m)'!$F$67:$F$68,'Calc - research target (12m)'!$G$67:$G$68)-'Calc - research target (12m)'!$F$68*'Calc - research target (12m)'!$G$68)+'Calc - research target (12m)'!$G$68*((($A15*F$12)-'Calc - research target (12m)'!$B$50-'Calc - research target (12m)'!$B$51+'Calc - research target (12m)'!$B$52)/'Calc - research target (12m)'!$B$53))/SUM('Calc - research target (12m)'!$G$67:$G$68)
A16: =Valuation!$B$69+(0) | B16: =((SUMPRODUCT('Calc - research target (12m)'!$F$67:$F$68,'Calc - research target (12m)'!$G$67:$G$68)-'Calc - research target (12m)'!$F$68*'Calc - research target (12m)'!$G$68)+'Calc - research target (12m)'!$G$68*((($A16*B$12)-'Calc - research target (12m)'!$B$50-'Calc - research target (12m)'!$B$51+'Calc - research target (12m)'!$B$52)/'Calc - research target (12m)'!$B$53))/SUM('Calc - research target (12m)'!$G$67:$G$68) | C16: =((SUMPRODUCT('Calc - research target (12m)'!$F$67:$F$68,'Calc - research target (12m)'!$G$67:$G$68)-'Calc - research target (12m)'!$F$68*'Calc - research target (12m)'!$G$68)+'Calc - research target (12m)'!$G$68*((($A16*C$12)-'Calc - research target (12m)'!$B$50-'Calc - research target (12m)'!$B$51+'Calc - research target (12m)'!$B$52)/'Calc - research target (12m)'!$B$53))/SUM('Calc - research target (12m)'!$G$67:$G$68) | D16: =((SUMPRODUCT('Calc - research target (12m)'!$F$67:$F$68,'Calc - research target (12m)'!$G$67:$G$68)-'Calc - research target (12m)'!$F$68*'Calc - research target (12m)'!$G$68)+'Calc - research target (12m)'!$G$68*((($A16*D$12)-'Calc - research target (12m)'!$B$50-'Calc - research target (12m)'!$B$51+'Calc - research target (12m)'!$B$52)/'Calc - research target (12m)'!$B$53))/SUM('Calc - research target (12m)'!$G$67:$G$68) | E16: =((SUMPRODUCT('Calc - research target (12m)'!$F$67:$F$68,'Calc - research target (12m)'!$G$67:$G$68)-'Calc - research target (12m)'!$F$68*'Calc - research target (12m)'!$G$68)+'Calc - research target (12m)'!$G$68*((($A16*E$12)-'Calc - research target (12m)'!$B$50-'Calc - research target (12m)'!$B$51+'Calc - research target (12m)'!$B$52)/'Calc - research target (12m)'!$B$53))/SUM('Calc - research target (12m)'!$G$67:$G$68) | F16: =((SUMPRODUCT('Calc - research target (12m)'!$F$67:$F$68,'Calc - research target (12m)'!$G$67:$G$68)-'Calc - research target (12m)'!$F$68*'Calc - research target (12m)'!$G$68)+'Calc - research target (12m)'!$G$68*((($A16*F$12)-'Calc - research target (12m)'!$B$50-'Calc - research target (12m)'!$B$51+'Calc - research target (12m)'!$B$52)/'Calc - research target (12m)'!$B$53))/SUM('Calc - research target (12m)'!$G$67:$G$68)
A17: =Valuation!$B$69+(1) | B17: =((SUMPRODUCT('Calc - research target (12m)'!$F$67:$F$68,'Calc - research target (12m)'!$G$67:$G$68)-'Calc - research target (12m)'!$F$68*'Calc - research target (12m)'!$G$68)+'Calc - research target (12m)'!$G$68*((($A17*B$12)-'Calc - research target (12m)'!$B$50-'Calc - research target (12m)'!$B$51+'Calc - research target (12m)'!$B$52)/'Calc - research target (12m)'!$B$53))/SUM('Calc - research target (12m)'!$G$67:$G$68) | C17: =((SUMPRODUCT('Calc - research target (12m)'!$F$67:$F$68,'Calc - research target (12m)'!$G$67:$G$68)-'Calc - research target (12m)'!$F$68*'Calc - research target (12m)'!$G$68)+'Calc - research target (12m)'!$G$68*((($A17*C$12)-'Calc - research target (12m)'!$B$50-'Calc - research target (12m)'!$B$51+'Calc - research target (12m)'!$B$52)/'Calc - research target (12m)'!$B$53))/SUM('Calc - research target (12m)'!$G$67:$G$68) | D17: =((SUMPRODUCT('Calc - research target (12m)'!$F$67:$F$68,'Calc - research target (12m)'!$G$67:$G$68)-'Calc - research target (12m)'!$F$68*'Calc - research target (12m)'!$G$68)+'Calc - research target (12m)'!$G$68*((($A17*D$12)-'Calc - research target (12m)'!$B$50-'Calc - research target (12m)'!$B$51+'Calc - research target (12m)'!$B$52)/'Calc - research target (12m)'!$B$53))/SUM('Calc - research target (12m)'!$G$67:$G$68) | E17: =((SUMPRODUCT('Calc - research target (12m)'!$F$67:$F$68,'Calc - research target (12m)'!$G$67:$G$68)-'Calc - research target (12m)'!$F$68*'Calc - research target (12m)'!$G$68)+'Calc - research target (12m)'!$G$68*((($A17*E$12)-'Calc - research target (12m)'!$B$50-'Calc - research target (12m)'!$B$51+'Calc - research target (12m)'!$B$52)/'Calc - research target (12m)'!$B$53))/SUM('Calc - research target (12m)'!$G$67:$G$68) | F17: =((SUMPRODUCT('Calc - research target (12m)'!$F$67:$F$68,'Calc - research target (12m)'!$G$67:$G$68)-'Calc - research target (12m)'!$F$68*'Calc - research target (12m)'!$G$68)+'Calc - research target (12m)'!$G$68*((($A17*F$12)-'Calc - research target (12m)'!$B$50-'Calc - research target (12m)'!$B$51+'Calc - research target (12m)'!$B$52)/'Calc - research target (12m)'!$B$53))/SUM('Calc - research target (12m)'!$G$67:$G$68)
A18: =Valuation!$B$69+(2) | B18: =((SUMPRODUCT('Calc - research target (12m)'!$F$67:$F$68,'Calc - research target (12m)'!$G$67:$G$68)-'Calc - research target (12m)'!$F$68*'Calc - research target (12m)'!$G$68)+'Calc - research target (12m)'!$G$68*((($A18*B$12)-'Calc - research target (12m)'!$B$50-'Calc - research target (12m)'!$B$51+'Calc - research target (12m)'!$B$52)/'Calc - research target (12m)'!$B$53))/SUM('Calc - research target (12m)'!$G$67:$G$68) | C18: =((SUMPRODUCT('Calc - research target (12m)'!$F$67:$F$68,'Calc - research target (12m)'!$G$67:$G$68)-'Calc - research target (12m)'!$F$68*'Calc - research target (12m)'!$G$68)+'Calc - research target (12m)'!$G$68*((($A18*C$12)-'Calc - research target (12m)'!$B$50-'Calc - research target (12m)'!$B$51+'Calc - research target (12m)'!$B$52)/'Calc - research target (12m)'!$B$53))/SUM('Calc - research target (12m)'!$G$67:$G$68) | D18: =((SUMPRODUCT('Calc - research target (12m)'!$F$67:$F$68,'Calc - research target (12m)'!$G$67:$G$68)-'Calc - research target (12m)'!$F$68*'Calc - research target (12m)'!$G$68)+'Calc - research target (12m)'!$G$68*((($A18*D$12)-'Calc - research target (12m)'!$B$50-'Calc - research target (12m)'!$B$51+'Calc - research target (12m)'!$B$52)/'Calc - research target (12m)'!$B$53))/SUM('Calc - research target (12m)'!$G$67:$G$68) | E18: =((SUMPRODUCT('Calc - research target (12m)'!$F$67:$F$68,'Calc - research target (12m)'!$G$67:$G$68)-'Calc - research target (12m)'!$F$68*'Calc - research target (12m)'!$G$68)+'Calc - research target (12m)'!$G$68*((($A18*E$12)-'Calc - research target (12m)'!$B$50-'Calc - research target (12m)'!$B$51+'Calc - research target (12m)'!$B$52)/'Calc - research target (12m)'!$B$53))/SUM('Calc - research target (12m)'!$G$67:$G$68) | F18: =((SUMPRODUCT('Calc - research target (12m)'!$F$67:$F$68,'Calc - research target (12m)'!$G$67:$G$68)-'Calc - research target (12m)'!$F$68*'Calc - research target (12m)'!$G$68)+'Calc - research target (12m)'!$G$68*((($A18*F$12)-'Calc - research target (12m)'!$B$50-'Calc - research target (12m)'!$B$51+'Calc - research target (12m)'!$B$52)/'Calc - research target (12m)'!$B$53))/SUM('Calc - research target (12m)'!$G$67:$G$68)
A19: =Valuation!$B$69+(3) | B19: =((SUMPRODUCT('Calc - research target (12m)'!$F$67:$F$68,'Calc - research target (12m)'!$G$67:$G$68)-'Calc - research target (12m)'!$F$68*'Calc - research target (12m)'!$G$68)+'Calc - research target (12m)'!$G$68*((($A19*B$12)-'Calc - research target (12m)'!$B$50-'Calc - research target (12m)'!$B$51+'Calc - research target (12m)'!$B$52)/'Calc - research target (12m)'!$B$53))/SUM('Calc - research target (12m)'!$G$67:$G$68) | C19: =((SUMPRODUCT('Calc - research target (12m)'!$F$67:$F$68,'Calc - research target (12m)'!$G$67:$G$68)-'Calc - research target (12m)'!$F$68*'Calc - research target (12m)'!$G$68)+'Calc - research target (12m)'!$G$68*((($A19*C$12)-'Calc - research target (12m)'!$B$50-'Calc - research target (12m)'!$B$51+'Calc - research target (12m)'!$B$52)/'Calc - research target (12m)'!$B$53))/SUM('Calc - research target (12m)'!$G$67:$G$68) | D19: =((SUMPRODUCT('Calc - research target (12m)'!$F$67:$F$68,'Calc - research target (12m)'!$G$67:$G$68)-'Calc - research target (12m)'!$F$68*'Calc - research target (12m)'!$G$68)+'Calc - research target (12m)'!$G$68*((($A19*D$12)-'Calc - research target (12m)'!$B$50-'Calc - research target (12m)'!$B$51+'Calc - research target (12m)'!$B$52)/'Calc - research target (12m)'!$B$53))/SUM('Calc - research target (12m)'!$G$67:$G$68) | E19: =((SUMPRODUCT('Calc - research target (12m)'!$F$67:$F$68,'Calc - research target (12m)'!$G$67:$G$68)-'Calc - research target (12m)'!$F$68*'Calc - research target (12m)'!$G$68)+'Calc - research target (12m)'!$G$68*((($A19*E$12)-'Calc - research target (12m)'!$B$50-'Calc - research target (12m)'!$B$51+'Calc - research target (12m)'!$B$52)/'Calc - research target (12m)'!$B$53))/SUM('Calc - research target (12m)'!$G$67:$G$68) | F19: =((SUMPRODUCT('Calc - research target (12m)'!$F$67:$F$68,'Calc - research target (12m)'!$G$67:$G$68)-'Calc - research target (12m)'!$F$68*'Calc - research target (12m)'!$G$68)+'Calc - research target (12m)'!$G$68*((($A19*F$12)-'Calc - research target (12m)'!$B$50-'Calc - research target (12m)'!$B$51+'Calc - research target (12m)'!$B$52)/'Calc - research target (12m)'!$B$53))/SUM('Calc - research target (12m)'!$G$67:$G$68)
A22: FY2027E diluted EPS: revenue growth change in every year (down) x EBIT margin change (across)
A23: Growth Δ \ margin Δ | B23: -0.01 | C23: -0.005 | D23: 0 | E23: 0.005 | F23: 0.01
A24: -0.02 | B24: =(Valuation!$B$86*(1+Model!E12+$A24)*(1+Model!F12+$A24)*(Model!F14+B$23)+Valuation!$B$87*(1+Model!E16+$A24)*(1+Model!F16+$A24)*(Model!F18+B$23)+Model!F21+Model!F33)*(1-Model!F63)/Model!F40 | C24: =(Valuation!$B$86*(1+Model!E12+$A24)*(1+Model!F12+$A24)*(Model!F14+C$23)+Valuation!$B$87*(1+Model!E16+$A24)*(1+Model!F16+$A24)*(Model!F18+C$23)+Model!F21+Model!F33)*(1-Model!F63)/Model!F40 | D24: =(Valuation!$B$86*(1+Model!E12+$A24)*(1+Model!F12+$A24)*(Model!F14+D$23)+Valuation!$B$87*(1+Model!E16+$A24)*(1+Model!F16+$A24)*(Model!F18+D$23)+Model!F21+Model!F33)*(1-Model!F63)/Model!F40 | E24: =(Valuation!$B$86*(1+Model!E12+$A24)*(1+Model!F12+$A24)*(Model!F14+E$23)+Valuation!$B$87*(1+Model!E16+$A24)*(1+Model!F16+$A24)*(Model!F18+E$23)+Model!F21+Model!F33)*(1-Model!F63)/Model!F40 | F24: =(Valuation!$B$86*(1+Model!E12+$A24)*(1+Model!F12+$A24)*(Model!F14+F$23)+Valuation!$B$87*(1+Model!E16+$A24)*(1+Model!F16+$A24)*(Model!F18+F$23)+Model!F21+Model!F33)*(1-Model!F63)/Model!F40
A25: -0.01 | B25: =(Valuation!$B$86*(1+Model!E12+$A25)*(1+Model!F12+$A25)*(Model!F14+B$23)+Valuation!$B$87*(1+Model!E16+$A25)*(1+Model!F16+$A25)*(Model!F18+B$23)+Model!F21+Model!F33)*(1-Model!F63)/Model!F40 | C25: =(Valuation!$B$86*(1+Model!E12+$A25)*(1+Model!F12+$A25)*(Model!F14+C$23)+Valuation!$B$87*(1+Model!E16+$A25)*(1+Model!F16+$A25)*(Model!F18+C$23)+Model!F21+Model!F33)*(1-Model!F63)/Model!F40 | D25: =(Valuation!$B$86*(1+Model!E12+$A25)*(1+Model!F12+$A25)*(Model!F14+D$23)+Valuation!$B$87*(1+Model!E16+$A25)*(1+Model!F16+$A25)*(Model!F18+D$23)+Model!F21+Model!F33)*(1-Model!F63)/Model!F40 | E25: =(Valuation!$B$86*(1+Model!E12+$A25)*(1+Model!F12+$A25)*(Model!F14+E$23)+Valuation!$B$87*(1+Model!E16+$A25)*(1+Model!F16+$A25)*(Model!F18+E$23)+Model!F21+Model!F33)*(1-Model!F63)/Model!F40 | F25: =(Valuation!$B$86*(1+Model!E12+$A25)*(1+Model!F12+$A25)*(Model!F14+F$23)+Valuation!$B$87*(1+Model!E16+$A25)*(1+Model!F16+$A25)*(Model!F18+F$23)+Model!F21+Model!F33)*(1-Model!F63)/Model!F40
A26: 0 | B26: =(Valuation!$B$86*(1+Model!E12+$A26)*(1+Model!F12+$A26)*(Model!F14+B$23)+Valuation!$B$87*(1+Model!E16+$A26)*(1+Model!F16+$A26)*(Model!F18+B$23)+Model!F21+Model!F33)*(1-Model!F63)/Model!F40 | C26: =(Valuation!$B$86*(1+Model!E12+$A26)*(1+Model!F12+$A26)*(Model!F14+C$23)+Valuation!$B$87*(1+Model!E16+$A26)*(1+Model!F16+$A26)*(Model!F18+C$23)+Model!F21+Model!F33)*(1-Model!F63)/Model!F40 | D26: =(Valuation!$B$86*(1+Model!E12+$A26)*(1+Model!F12+$A26)*(Model!F14+D$23)+Valuation!$B$87*(1+Model!E16+$A26)*(1+Model!F16+$A26)*(Model!F18+D$23)+Model!F21+Model!F33)*(1-Model!F63)/Model!F40 | E26: =(Valuation!$B$86*(1+Model!E12+$A26)*(1+Model!F12+$A26)*(Model!F14+E$23)+Valuation!$B$87*(1+Model!E16+$A26)*(1+Model!F16+$A26)*(Model!F18+E$23)+Model!F21+Model!F33)*(1-Model!F63)/Model!F40 | F26: =(Valuation!$B$86*(1+Model!E12+$A26)*(1+Model!F12+$A26)*(Model!F14+F$23)+Valuation!$B$87*(1+Model!E16+$A26)*(1+Model!F16+$A26)*(Model!F18+F$23)+Model!F21+Model!F33)*(1-Model!F63)/Model!F40
A27: 0.01 | B27: =(Valuation!$B$86*(1+Model!E12+$A27)*(1+Model!F12+$A27)*(Model!F14+B$23)+Valuation!$B$87*(1+Model!E16+$A27)*(1+Model!F16+$A27)*(Model!F18+B$23)+Model!F21+Model!F33)*(1-Model!F63)/Model!F40 | C27: =(Valuation!$B$86*(1+Model!E12+$A27)*(1+Model!F12+$A27)*(Model!F14+C$23)+Valuation!$B$87*(1+Model!E16+$A27)*(1+Model!F16+$A27)*(Model!F18+C$23)+Model!F21+Model!F33)*(1-Model!F63)/Model!F40 | D27: =(Valuation!$B$86*(1+Model!E12+$A27)*(1+Model!F12+$A27)*(Model!F14+D$23)+Valuation!$B$87*(1+Model!E16+$A27)*(1+Model!F16+$A27)*(Model!F18+D$23)+Model!F21+Model!F33)*(1-Model!F63)/Model!F40 | E27: =(Valuation!$B$86*(1+Model!E12+$A27)*(1+Model!F12+$A27)*(Model!F14+E$23)+Valuation!$B$87*(1+Model!E16+$A27)*(1+Model!F16+$A27)*(Model!F18+E$23)+Model!F21+Model!F33)*(1-Model!F63)/Model!F40 | F27: =(Valuation!$B$86*(1+Model!E12+$A27)*(1+Model!F12+$A27)*(Model!F14+F$23)+Valuation!$B$87*(1+Model!E16+$A27)*(1+Model!F16+$A27)*(Model!F18+F$23)+Model!F21+Model!F33)*(1-Model!F63)/Model!F40
A28: 0.02 | B28: =(Valuation!$B$86*(1+Model!E12+$A28)*(1+Model!F12+$A28)*(Model!F14+B$23)+Valuation!$B$87*(1+Model!E16+$A28)*(1+Model!F16+$A28)*(Model!F18+B$23)+Model!F21+Model!F33)*(1-Model!F63)/Model!F40 | C28: =(Valuation!$B$86*(1+Model!E12+$A28)*(1+Model!F12+$A28)*(Model!F14+C$23)+Valuation!$B$87*(1+Model!E16+$A28)*(1+Model!F16+$A28)*(Model!F18+C$23)+Model!F21+Model!F33)*(1-Model!F63)/Model!F40 | D28: =(Valuation!$B$86*(1+Model!E12+$A28)*(1+Model!F12+$A28)*(Model!F14+D$23)+Valuation!$B$87*(1+Model!E16+$A28)*(1+Model!F16+$A28)*(Model!F18+D$23)+Model!F21+Model!F33)*(1-Model!F63)/Model!F40 | E28: =(Valuation!$B$86*(1+Model!E12+$A28)*(1+Model!F12+$A28)*(Model!F14+E$23)+Valuation!$B$87*(1+Model!E16+$A28)*(1+Model!F16+$A28)*(Model!F18+E$23)+Model!F21+Model!F33)*(1-Model!F63)/Model!F40 | F28: =(Valuation!$B$86*(1+Model!E12+$A28)*(1+Model!F12+$A28)*(Model!F14+F$23)+Valuation!$B$87*(1+Model!E16+$A28)*(1+Model!F16+$A28)*(Model!F18+F$23)+Model!F21+Model!F33)*(1-Model!F63)/Model!F40
A30: Net interest and the share count are held at the base case in table 3.

Sheet Distribution
A1: VST: 12-month distribution (mix of lognormals around each scenario value)
A3: Scenario | B3: Probability | C3: Value at target date | D3: Story
A4: bear | B4: =Valuation!B81 | C4: ='Calc - bear'!$F$69 | D4: =Valuation!J81
A5: base | B5: =Valuation!B82 | C5: ='Calc - base'!$F$69 | D5: =Valuation!J82
A6: bull | B6: =Valuation!B83 | C6: ='Calc - bull'!$F$69 | D6: =Valuation!J83
A8: Probabilities sum to | B8: =SUM(B4:B6)
A9: Spread within each scenario | B9: =Valuation!$B$65
A10: Probability-weighted mean | B10: =($B$4*$C$4+$B$5*$C$5+$B$6*$C$6)*EXP($B$9^2/2)
A12: Quantile | B12: Price
A13: Median (model target) | B13: =SQRT(A60*B60)
A14: 10th percentile | B14: =SQRT(D60*E60)
A15: 25th percentile | B15: =SQRT(G60*H60)
A16: 75th percentile | B16: =SQRT(J60*K60)
A17: 90th percentile | B17: =SQRT(M60*N60)
A19: Each quantile solved by bisection (block: low, high, probability above the midpoint)
A20: Median (model target): low | B20: high | C20: P(above mid) | D20: 10th percentile: low | E20: high | F20: P(above mid) | G20: 25th percentile: low | H20: high | I20: P(above mid) | J20: 75th percentile: low | K20: high | L20: P(above mid) | M20: 90th percentile: low | N20: high | O20: P(above mid)
A21: =MIN($C$4,$C$5,$C$6)*0.2 | B21: =MAX($C$4,$C$5,$C$6)*4 | C21: =SUMPRODUCT($B$4:$B$6,1-NORMSDIST((LN(SQRT(A21*B21))-LN($C$4:$C$6))/$B$9)) | D21: =MIN($C$4,$C$5,$C$6)*0.2 | E21: =MAX($C$4,$C$5,$C$6)*4 | F21: =SUMPRODUCT($B$4:$B$6,1-NORMSDIST((LN(SQRT(D21*E21))-LN($C$4:$C$6))/$B$9)) | G21: =MIN($C$4,$C$5,$C$6)*0.2 | H21: =MAX($C$4,$C$5,$C$6)*4 | I21: =SUMPRODUCT($B$4:$B$6,1-NORMSDIST((LN(SQRT(G21*H21))-LN($C$4:$C$6))/$B$9)) | J21: =MIN($C$4,$C$5,$C$6)*0.2 | K21: =MAX($C$4,$C$5,$C$6)*4 | L21: =SUMPRODUCT($B$4:$B$6,1-NORMSDIST((LN(SQRT(J21*K21))-LN($C$4:$C$6))/$B$9)) | M21: =MIN($C$4,$C$5,$C$6)*0.2 | N21: =MAX($C$4,$C$5,$C$6)*4 | O21: =SUMPRODUCT($B$4:$B$6,1-NORMSDIST((LN(SQRT(M21*N21))-LN($C$4:$C$6))/$B$9))
A22: =IF(C21>0.5,SQRT(A21*B21),A21) | B22: =IF(C21>0.5,B21,SQRT(A21*B21)) | C22: =SUMPRODUCT($B$4:$B$6,1-NORMSDIST((LN(SQRT(A22*B22))-LN($C$4:$C$6))/$B$9)) | D22: =IF(F21>0.9,SQRT(D21*E21),D21) | E22: =IF(F21>0.9,E21,SQRT(D21*E21)) | F22: =SUMPRODUCT($B$4:$B$6,1-NORMSDIST((LN(SQRT(D22*E22))-LN($C$4:$C$6))/$B$9)) | G22: =IF(I21>0.75,SQRT(G21*H21),G21) | H22: =IF(I21>0.75,H21,SQRT(G21*H21)) | I22: =SUMPRODUCT($B$4:$B$6,1-NORMSDIST((LN(SQRT(G22*H22))-LN($C$4:$C$6))/$B$9)) | J22: =IF(L21>0.25,SQRT(J21*K21),J21) | K22: =IF(L21>0.25,K21,SQRT(J21*K21)) | L22: =SUMPRODUCT($B$4:$B$6,1-NORMSDIST((LN(SQRT(J22*K22))-LN($C$4:$C$6))/$B$9)) | M22: =IF(O21>0.09999999999999998,SQRT(M21*N21),M21) | N22: =IF(O21>0.09999999999999998,N21,SQRT(M21*N21)) | O22: =SUMPRODUCT($B$4:$B$6,1-NORMSDIST((LN(SQRT(M22*N22))-LN($C$4:$C$6))/$B$9))
A23: =IF(C22>0.5,SQRT(A22*B22),A22) | B23: =IF(C22>0.5,B22,SQRT(A22*B22)) | C23: =SUMPRODUCT($B$4:$B$6,1-NORMSDIST((LN(SQRT(A23*B23))-LN($C$4:$C$6))/$B$9)) | D23: =IF(F22>0.9,SQRT(D22*E22),D22) | E23: =IF(F22>0.9,E22,SQRT(D22*E22)) | F23: =SUMPRODUCT($B$4:$B$6,1-NORMSDIST((LN(SQRT(D23*E23))-LN($C$4:$C$6))/$B$9)) | G23: =IF(I22>0.75,SQRT(G22*H22),G22) | H23: =IF(I22>0.75,H22,SQRT(G22*H22)) | I23: =SUMPRODUCT($B$4:$B$6,1-NORMSDIST((LN(SQRT(G23*H23))-LN($C$4:$C$6))/$B$9)) | J23: =IF(L22>0.25,SQRT(J22*K22),J22) | K23: =IF(L22>0.25,K22,SQRT(J22*K22)) | L23: =SUMPRODUCT($B$4:$B$6,1-NORMSDIST((LN(SQRT(J23*K23))-LN($C$4:$C$6))/$B$9)) | M23: =IF(O22>0.09999999999999998,SQRT(M22*N22),M22) | N23: =IF(O22>0.09999999999999998,N22,SQRT(M22*N22)) | O23: =SUMPRODUCT($B$4:$B$6,1-NORMSDIST((LN(SQRT(M23*N23))-LN($C$4:$C$6))/$B$9))
A24: =IF(C23>0.5,SQRT(A23*B23),A23) | B24: =IF(C23>0.5,B23,SQRT(A23*B23)) | C24: =SUMPRODUCT($B$4:$B$6,1-NORMSDIST((LN(SQRT(A24*B24))-LN($C$4:$C$6))/$B$9)) | D24: =IF(F23>0.9,SQRT(D23*E23),D23) | E24: =IF(F23>0.9,E23,SQRT(D23*E23)) | F24: =SUMPRODUCT($B$4:$B$6,1-NORMSDIST((LN(SQRT(D24*E24))-LN($C$4:$C$6))/$B$9)) | G24: =IF(I23>0.75,SQRT(G23*H23),G23) | H24: =IF(I23>0.75,H23,SQRT(G23*H23)) | I24: =SUMPRODUCT($B$4:$B$6,1-NORMSDIST((LN(SQRT(G24*H24))-LN($C$4:$C$6))/$B$9)) | J24: =IF(L23>0.25,SQRT(J23*K23),J23) | K24: =IF(L23>0.25,K23,SQRT(J23*K23)) | L24: =SUMPRODUCT($B$4:$B$6,1-NORMSDIST((LN(SQRT(J24*K24))-LN($C$4:$C$6))/$B$9)) | M24: =IF(O23>0.09999999999999998,SQRT(M23*N23),M23) | N24: =IF(O23>0.09999999999999998,N23,SQRT(M23*N23)) | O24: =SUMPRODUCT($B$4:$B$6,1-NORMSDIST((LN(SQRT(M24*N24))-LN($C$4:$C$6))/$B$9))
A25: =IF(C24>0.5,SQRT(A24*B24),A24) | B25: =IF(C24>0.5,B24,SQRT(A24*B24)) | C25: =SUMPRODUCT($B$4:$B$6,1-NORMSDIST((LN(SQRT(A25*B25))-LN($C$4:$C$6))/$B$9)) | D25: =IF(F24>0.9,SQRT(D24*E24),D24) | E25: =IF(F24>0.9,E24,SQRT(D24*E24)) | F25: =SUMPRODUCT($B$4:$B$6,1-NORMSDIST((LN(SQRT(D25*E25))-LN($C$4:$C$6))/$B$9)) | G25: =IF(I24>0.75,SQRT(G24*H24),G24) | H25: =IF(I24>0.75,H24,SQRT(G24*H24)) | I25: =SUMPRODUCT($B$4:$B$6,1-NORMSDIST((LN(SQRT(G25*H25))-LN($C$4:$C$6))/$B$9)) | J25: =IF(L24>0.25,SQRT(J24*K24),J24) | K25: =IF(L24>0.25,K24,SQRT(J24*K24)) | L25: =SUMPRODUCT($B$4:$B$6,1-NORMSDIST((LN(SQRT(J25*K25))-LN($C$4:$C$6))/$B$9)) | M25: =IF(O24>0.09999999999999998,SQRT(M24*N24),M24) | N25: =IF(O24>0.09999999999999998,N24,SQRT(M24*N24)) | O25: =SUMPRODUCT($B$4:$B$6,1-NORMSDIST((LN(SQRT(M25*N25))-LN($C$4:$C$6))/$B$9))
A26: =IF(C25>0.5,SQRT(A25*B25),A25) | B26: =IF(C25>0.5,B25,SQRT(A25*B25)) | C26: =SUMPRODUCT($B$4:$B$6,1-NORMSDIST((LN(SQRT(A26*B26))-LN($C$4:$C$6))/$B$9)) | D26: =IF(F25>0.9,SQRT(D25*E25),D25) | E26: =IF(F25>0.9,E25,SQRT(D25*E25)) | F26: =SUMPRODUCT($B$4:$B$6,1-NORMSDIST((LN(SQRT(D26*E26))-LN($C$4:$C$6))/$B$9)) | G26: =IF(I25>0.75,SQRT(G25*H25),G25) | H26: =IF(I25>0.75,H25,SQRT(G25*H25)) | I26: =SUMPRODUCT($B$4:$B$6,1-NORMSDIST((LN(SQRT(G26*H26))-LN($C$4:$C$6))/$B$9)) | J26: =IF(L25>0.25,SQRT(J25*K25),J25) | K26: =IF(L25>0.25,K25,SQRT(J25*K25)) | L26: =SUMPRODUCT($B$4:$B$6,1-NORMSDIST((LN(SQRT(J26*K26))-LN($C$4:$C$6))/$B$9)) | M26: =IF(O25>0.09999999999999998,SQRT(M25*N25),M25) | N26: =IF(O25>0.09999999999999998,N25,SQRT(M25*N25)) | O26: =SUMPRODUCT($B$4:$B$6,1-NORMSDIST((LN(SQRT(M26*N26))-LN($C$4:$C$6))/$B$9))
A27: =IF(C26>0.5,SQRT(A26*B26),A26) | B27: =IF(C26>0.5,B26,SQRT(A26*B26)) | C27: =SUMPRODUCT($B$4:$B$6,1-NORMSDIST((LN(SQRT(A27*B27))-LN($C$4:$C$6))/$B$9)) | D27: =IF(F26>0.9,SQRT(D26*E26),D26) | E27: =IF(F26>0.9,E26,SQRT(D26*E26)) | F27: =SUMPRODUCT($B$4:$B$6,1-NORMSDIST((LN(SQRT(D27*E27))-LN($C$4:$C$6))/$B$9)) | G27: =IF(I26>0.75,SQRT(G26*H26),G26) | H27: =IF(I26>0.75,H26,SQRT(G26*H26)) | I27: =SUMPRODUCT($B$4:$B$6,1-NORMSDIST((LN(SQRT(G27*H27))-LN($C$4:$C$6))/$B$9)) | J27: =IF(L26>0.25,SQRT(J26*K26),J26) | K27: =IF(L26>0.25,K26,SQRT(J26*K26)) | L27: =SUMPRODUCT($B$4:$B$6,1-NORMSDIST((LN(SQRT(J27*K27))-LN($C$4:$C$6))/$B$9)) | M27: =IF(O26>0.09999999999999998,SQRT(M26*N26),M26) | N27: =IF(O26>0.09999999999999998,N26,SQRT(M26*N26)) | O27: =SUMPRODUCT($B$4:$B$6,1-NORMSDIST((LN(SQRT(M27*N27))-LN($C$4:$C$6))/$B$9))
A28: =IF(C27>0.5,SQRT(A27*B27),A27) | B28: =IF(C27>0.5,B27,SQRT(A27*B27)) | C28: =SUMPRODUCT($B$4:$B$6,1-NORMSDIST((LN(SQRT(A28*B28))-LN($C$4:$C$6))/$B$9)) | D28: =IF(F27>0.9,SQRT(D27*E27),D27) | E28: =IF(F27>0.9,E27,SQRT(D27*E27)) | F28: =SUMPRODUCT($B$4:$B$6,1-NORMSDIST((LN(SQRT(D28*E28))-LN($C$4:$C$6))/$B$9)) | G28: =IF(I27>0.75,SQRT(G27*H27),G27) | H28: =IF(I27>0.75,H27,SQRT(G27*H27)) | I28: =SUMPRODUCT($B$4:$B$6,1-NORMSDIST((LN(SQRT(G28*H28))-LN($C$4:$C$6))/$B$9)) | J28: =IF(L27>0.25,SQRT(J27*K27),J27) | K28: =IF(L27>0.25,K27,SQRT(J27*K27)) | L28: =SUMPRODUCT($B$4:$B$6,1-NORMSDIST((LN(SQRT(J28*K28))-LN($C$4:$C$6))/$B$9)) | M28: =IF(O27>0.09999999999999998,SQRT(M27*N27),M27) | N28: =IF(O27>0.09999999999999998,N27,SQRT(M27*N27)) | O28: =SUMPRODUCT($B$4:$B$6,1-NORMSDIST((LN(SQRT(M28*N28))-LN($C$4:$C$6))/$B$9))
A29: =IF(C28>0.5,SQRT(A28*B28),A28) | B29: =IF(C28>0.5,B28,SQRT(A28*B28)) | C29: =SUMPRODUCT($B$4:$B$6,1-NORMSDIST((LN(SQRT(A29*B29))-LN($C$4:$C$6))/$B$9)) | D29: =IF(F28>0.9,SQRT(D28*E28),D28) | E29: =IF(F28>0.9,E28,SQRT(D28*E28)) | F29: =SUMPRODUCT($B$4:$B$6,1-NORMSDIST((LN(SQRT(D29*E29))-LN($C$4:$C$6))/$B$9)) | G29: =IF(I28>0.75,SQRT(G28*H28),G28) | H29: =IF(I28>0.75,H28,SQRT(G28*H28)) | I29: =SUMPRODUCT($B$4:$B$6,1-NORMSDIST((LN(SQRT(G29*H29))-LN($C$4:$C$6))/$B$9)) | J29: =IF(L28>0.25,SQRT(J28*K28),J28) | K29: =IF(L28>0.25,K28,SQRT(J28*K28)) | L29: =SUMPRODUCT($B$4:$B$6,1-NORMSDIST((LN(SQRT(J29*K29))-LN($C$4:$C$6))/$B$9)) | M29: =IF(O28>0.09999999999999998,SQRT(M28*N28),M28) | N29: =IF(O28>0.09999999999999998,N28,SQRT(M28*N28)) | O29: =SUMPRODUCT($B$4:$B$6,1-NORMSDIST((LN(SQRT(M29*N29))-LN($C$4:$C$6))/$B$9))
A30: =IF(C29>0.5,SQRT(A29*B29),A29) | B30: =IF(C29>0.5,B29,SQRT(A29*B29)) | C30: =SUMPRODUCT($B$4:$B$6,1-NORMSDIST((LN(SQRT(A30*B30))-LN($C$4:$C$6))/$B$9)) | D30: =IF(F29>0.9,SQRT(D29*E29),D29) | E30: =IF(F29>0.9,E29,SQRT(D29*E29)) | F30: =SUMPRODUCT($B$4:$B$6,1-NORMSDIST((LN(SQRT(D30*E30))-LN($C$4:$C$6))/$B$9)) | G30: =IF(I29>0.75,SQRT(G29*H29),G29) | H30: =IF(I29>0.75,H29,SQRT(G29*H29)) | I30: =SUMPRODUCT($B$4:$B$6,1-NORMSDIST((LN(SQRT(G30*H30))-LN($C$4:$C$6))/$B$9)) | J30: =IF(L29>0.25,SQRT(J29*K29),J29) | K30: =IF(L29>0.25,K29,SQRT(J29*K29)) | L30: =SUMPRODUCT($B$4:$B$6,1-NORMSDIST((LN(SQRT(J30*K30))-LN($C$4:$C$6))/$B$9)) | M30: =IF(O29>0.09999999999999998,SQRT(M29*N29),M29) | N30: =IF(O29>0.09999999999999998,N29,SQRT(M29*N29)) | O30: =SUMPRODUCT($B$4:$B$6,1-NORMSDIST((LN(SQRT(M30*N30))-LN($C$4:$C$6))/$B$9))
A31: =IF(C30>0.5,SQRT(A30*B30),A30) | B31: =IF(C30>0.5,B30,SQRT(A30*B30)) | C31: =SUMPRODUCT($B$4:$B$6,1-NORMSDIST((LN(SQRT(A31*B31))-LN($C$4:$C$6))/$B$9)) | D31: =IF(F30>0.9,SQRT(D30*E30),D30) | E31: =IF(F30>0.9,E30,SQRT(D30*E30)) | F31: =SUMPRODUCT($B$4:$B$6,1-NORMSDIST((LN(SQRT(D31*E31))-LN($C$4:$C$6))/$B$9)) | G31: =IF(I30>0.75,SQRT(G30*H30),G30) | H31: =IF(I30>0.75,H30,SQRT(G30*H30)) | I31: =SUMPRODUCT($B$4:$B$6,1-NORMSDIST((LN(SQRT(G31*H31))-LN($C$4:$C$6))/$B$9)) | J31: =IF(L30>0.25,SQRT(J30*K30),J30) | K31: =IF(L30>0.25,K30,SQRT(J30*K30)) | L31: =SUMPRODUCT($B$4:$B$6,1-NORMSDIST((LN(SQRT(J31*K31))-LN($C$4:$C$6))/$B$9)) | M31: =IF(O30>0.09999999999999998,SQRT(M30*N30),M30) | N31: =IF(O30>0.09999999999999998,N30,SQRT(M30*N30)) | O31: =SUMPRODUCT($B$4:$B$6,1-NORMSDIST((LN(SQRT(M31*N31))-LN($C$4:$C$6))/$B$9))
A32: =IF(C31>0.5,SQRT(A31*B31),A31) | B32: =IF(C31>0.5,B31,SQRT(A31*B31)) | C32: =SUMPRODUCT($B$4:$B$6,1-NORMSDIST((LN(SQRT(A32*B32))-LN($C$4:$C$6))/$B$9)) | D32: =IF(F31>0.9,SQRT(D31*E31),D31) | E32: =IF(F31>0.9,E31,SQRT(D31*E31)) | F32: =SUMPRODUCT($B$4:$B$6,1-NORMSDIST((LN(SQRT(D32*E32))-LN($C$4:$C$6))/$B$9)) | G32: =IF(I31>0.75,SQRT(G31*H31),G31) | H32: =IF(I31>0.75,H31,SQRT(G31*H31)) | I32: =SUMPRODUCT($B$4:$B$6,1-NORMSDIST((LN(SQRT(G32*H32))-LN($C$4:$C$6))/$B$9)) | J32: =IF(L31>0.25,SQRT(J31*K31),J31) | K32: =IF(L31>0.25,K31,SQRT(J31*K31)) | L32: =SUMPRODUCT($B$4:$B$6,1-NORMSDIST((LN(SQRT(J32*K32))-LN($C$4:$C$6))/$B$9)) | M32: =IF(O31>0.09999999999999998,SQRT(M31*N31),M31) | N32: =IF(O31>0.09999999999999998,N31,SQRT(M31*N31)) | O32: =SUMPRODUCT($B$4:$B$6,1-NORMSDIST((LN(SQRT(M32*N32))-LN($C$4:$C$6))/$B$9))
A33: =IF(C32>0.5,SQRT(A32*B32),A32) | B33: =IF(C32>0.5,B32,SQRT(A32*B32)) | C33: =SUMPRODUCT($B$4:$B$6,1-NORMSDIST((LN(SQRT(A33*B33))-LN($C$4:$C$6))/$B$9)) | D33: =IF(F32>0.9,SQRT(D32*E32),D32) | E33: =IF(F32>0.9,E32,SQRT(D32*E32)) | F33: =SUMPRODUCT($B$4:$B$6,1-NORMSDIST((LN(SQRT(D33*E33))-LN($C$4:$C$6))/$B$9)) | G33: =IF(I32>0.75,SQRT(G32*H32),G32) | H33: =IF(I32>0.75,H32,SQRT(G32*H32)) | I33: =SUMPRODUCT($B$4:$B$6,1-NORMSDIST((LN(SQRT(G33*H33))-LN($C$4:$C$6))/$B$9)) | J33: =IF(L32>0.25,SQRT(J32*K32),J32) | K33: =IF(L32>0.25,K32,SQRT(J32*K32)) | L33: =SUMPRODUCT($B$4:$B$6,1-NORMSDIST((LN(SQRT(J33*K33))-LN($C$4:$C$6))/$B$9)) | M33: =IF(O32>0.09999999999999998,SQRT(M32*N32),M32) | N33: =IF(O32>0.09999999999999998,N32,SQRT(M32*N32)) | O33: =SUMPRODUCT($B$4:$B$6,1-NORMSDIST((LN(SQRT(M33*N33))-LN($C$4:$C$6))/$B$9))
... A60: =IF(C59>0.5,SQRT(A59*B59),A59) | B60: =IF(C59>0.5,B59,SQRT(A59*B59)) | C60: =SUMPRODUCT($B$4:$B$6,1-NORMSDIST((LN(SQRT(A60*B60))-LN($C$4:$C$6))/$B$9)) | D60: =IF(F59>0.9,SQRT(D59*E59),D59) | E60: =IF(F59>0.9,E59,SQRT(D59*E59)) | F60: =SUMPRODUCT($B$4:$B$6,1-NORMSDIST((LN(SQRT(D60*E60))-LN($C$4:$C$6))/$B$9)) | G60: =IF(I59>0.75,SQRT(G59*H59),G59) | H60: =IF(I59>0.75,H59,SQRT(G59*H59)) | I60: =SUMPRODUCT($B$4:$B$6,1-NORMSDIST((LN(SQRT(G60*H60))-LN($C$4:$C$6))/$B$9)) | J60: =IF(L59>0.25,SQRT(J59*K59),J59) | K60: =IF(L59>0.25,K59,SQRT(J59*K59)) | L60: =SUMPRODUCT($B$4:$B$6,1-NORMSDIST((LN(SQRT(J60*K60))-LN($C$4:$C$6))/$B$9)) | M60: =IF(O59>0.09999999999999998,SQRT(M59*N59),M59) | N60: =IF(O59>0.09999999999999998,N59,SQRT(M59*N59)) | O60: =SUMPRODUCT($B$4:$B$6,1-NORMSDIST((LN(SQRT(M60*N60))-LN($C$4:$C$6))/$B$9))

Sheet Calc - research target (12m)
A1: VST engine calculation: research target (12m) (reconciled set, no scenario deltas)
A2: Machinery behind the Valuation and Distribution tabs; drivers come from Model, assumptions from Valuation.
A4: Scenario Growth Δ | B4: 0
A5: Scenario Margin Δ | B5: 0
A6: Scenario Multiple Δ (turns) | B6: 0
A7: Scenario WACC Δ | B7: 0
A8: Scenario Multiple %Δ | B8: 0
A9: Scenario Stated EPS/FCF %Δ | B9: 0
A10: Scenario Custom %Δ | B10: 0
A12: WACC | B12: =Valuation!$B$50+B7
A13: Years from last FY end to target date | B13: =(Valuation!$B$44-Valuation!$B$48)/365.25
A14: Years from last FY end to balance date | B14: =(Valuation!$B$54-Valuation!$B$48)/365.25
A15: Years from last FY end to share count date | B15: =(Valuation!$B$60-Valuation!$B$48)/365.25
A16: Projected years | B16: 3
A18: Projection | B18: Base | C18: =Model!E5 | D18: =Model!F5 | E18: =Model!G5
A19: Year index | B19: 0 | C19: 1 | D19: 2 | E19: 3
A20: Period end | C20: =Valuation!$B$48+ROUND(365.25*C19,0) | D20: =Valuation!$B$48+ROUND(365.25*D19,0) | E20: =Valuation!$B$48+ROUND(365.25*E19,0)
A21: Revenue growth | C21: =C22/B22-1 | D21: =D22/C22-1 | E21: =E22/D22-1
A22: Revenue | B22: =Valuation!$B$49 | C22: =C139 | D22: =D139 | E22: =E139
A23: EBIT margin | C23: =C24/C22 | D23: =D24/D22 | E23: =E24/E22
A24: EBIT | C24: =C142 | D24: =D142 | E24: =E142
A25: Tax rate | C25: =Model!E63 | D25: =Model!F63 | E25: =Model!G63
A26: NOPAT | C26: =C24*(1-C25) | D26: =D24*(1-D25) | E26: =E24*(1-E25)
A27: D&A | C27: =C22*(Model!E64) | D27: =D22*(Model!F64) | E27: =E22*(Model!G64)
A28: Capex | C28: =C22*(Model!E65) | D28: =D22*(Model!F65) | E28: =E22*(Model!G65)
A29: Working capital increase | C29: =(Model!E66)*(C22-B22) | D29: =(Model!F66)*(D22-C22) | E29: =(Model!G66)*(E22-D22)
A30: Stock comp | C30: =C22*(Model!E67) | D30: =D22*(Model!F67) | E30: =E22*(Model!G67)
A31: Free cash flow to firm | C31: =C26+C27-C28-C29-IF(AND(Valuation!$B$46="adjusted",Valuation!$B$47="cost"),C30*(1-C25),0) | D31: =D26+D27-D28-D29-IF(AND(Valuation!$B$46="adjusted",Valuation!$B$47="cost"),D30*(1-D25),0) | E31: =E26+E27-E28-E29-IF(AND(Valuation!$B$46="adjusted",Valuation!$B$47="cost"),E30*(1-E25),0)
A32: EBITDA | C32: =C24+C27 | D32: =D24+D27 | E32: =E24+E27
A33: Adj. EBITDA | C33: =C24+C27+C22*(Model!E71) | D33: =D24+D27+D22*(Model!F71) | E33: =E24+E27+E22*(Model!G71)
A34: Shareholder returns + other uses | C34: =C22*Model!E69+Model!E68+Model!E70 | D34: =D22*Model!F69+Model!F68+Model!F70 | E34: =E22*Model!G69+Model!G68+Model!G70
A35: Share of year after target date | C35: =IF(C19<=$B$13,0,C19-MAX(C19-1,$B$13)) | D35: =IF(D19<=$B$13,0,D19-MAX(D19-1,$B$13)) | E35: =IF(E19<=$B$13,0,E19-MAX(E19-1,$B$13))
A36: PV at target date of FCFF | C36: =IF(C35=0,0,C31*C35/(1+$B$12)^(C19-$B$13)) | D36: =IF(D35=0,0,D31*D35/(1+$B$12)^(D19-$B$13)) | E36: =IF(E35=0,0,E31*E35/(1+$B$12)^(E19-$B$13))
A37: Overlap: balance date to target date | C37: =MAX(0,MIN(C19,$B$13)-MAX(C19-1,$B$14)) | D37: =MAX(0,MIN(D19,$B$13)-MAX(D19-1,$B$14)) | E37: =MAX(0,MIN(E19,$B$13)-MAX(E19-1,$B$14))
A38: NTM weight at target date | C38: =MAX(0,MIN(C19,$B$13+1)-MAX(C19-1,$B$13)) | D38: =MAX(0,MIN(D19,$B$13+1)-MAX(D19-1,$B$13)) | E38: =MAX(0,MIN(E19,$B$13+1)-MAX(E19-1,$B$13))
A39: LTM weight at target date | B39: =MAX(0,MIN(0,$B$13)-MAX(-1,$B$13-1)) | C39: =MAX(0,MIN(C19,$B$13)-MAX(C19-1,$B$13-1)) | D39: =MAX(0,MIN(D19,$B$13)-MAX(D19-1,$B$13-1)) | E39: =MAX(0,MIN(E19,$B$13)-MAX(E19-1,$B$13-1))
A41: Value at the target date
A42: PV of free cash flow after the target date | B42: =SUM($C$36:$E$36)
A43: Terminal value at final year | B43: =IF(Valuation!$B$51="exit_multiple",Valuation!$B$53*E32,E31*(1+Valuation!$B$52)/($B$12-Valuation!$B$52))
A44: PV of terminal value at target date | B44: =B43/(1+$B$12)^($B$16-$B$13)
A45: DCF enterprise value at target date | B45: =B42+B44
A46: Terminal value share of DCF | B46: =B44/B45
A47: Free cash flow earned, balance date to target date | B47: =SUMPRODUCT($C$37:$E$37,$C$31:$E$31)
A48: Shareholder returns + other uses paid | B48: =SUMPRODUCT($C$37:$E$37,$C$34:$E$34)
A49: Interest drag on net debt | B49: =Valuation!$B$57*(1-$C$25)*MAX(Valuation!$B$55,0)*MAX($B$13-$B$14,0)
A50: Net debt at target date | B50: =IF(Valuation!$B$58="",Valuation!$B$55-B47+B49+B48,Valuation!$B$58)
A51: Minority interests | B51: =Valuation!$B$56
A52: Adjustments (probability-weighted) | B52: =(Valuation!B75)*Valuation!C75+0
A53: Diluted shares at target date (M) | B53: =IF(Valuation!$B$62="",Valuation!$B$59*(1+Valuation!$B$61)^MAX($B$13-$B$15,0),Valuation!$B$62)
A54: After-tax interest on target-date net debt | B54: =Valuation!$B$57*(1-$C$25)*MAX(B50,0)
A55: Check: WACC vs terminal growth | B55: =IF(AND(Valuation!$B$51<>"exit_multiple",$B$12<=Valuation!$B$52+0.01),"WACC must exceed terminal growth by 1 point","ok")
A56: Check: projection length | B56: =IF(OR($B$13>=$B$16-1,$B$13+1>$B$16),"add projected years past the target date","ok")
A58: Metric at target date | B58: Next 12 months | C58: Last 12 months
A59: Revenue | B59: =SUMPRODUCT($C$38:$E$38,$C$22:$E$22) | C59: =SUMPRODUCT($C$39:$E$39,$C$22:$E$22)+$B$39*$B$22
A60: EBIT | B60: =SUMPRODUCT($C$38:$E$38,$C$24:$E$24) | C60: =SUMPRODUCT($C$39:$E$39,$C$24:$E$24)
A61: EBITDA | B61: =SUMPRODUCT($C$38:$E$38,$C$32:$E$32) | C61: =SUMPRODUCT($C$39:$E$39,$C$32:$E$32)
A62: Adj. EBITDA | B62: =SUMPRODUCT($C$38:$E$38,$C$33:$E$33) | C62: =SUMPRODUCT($C$39:$E$39,$C$33:$E$33)
A63: NOPAT | B63: =SUMPRODUCT($C$38:$E$38,$C$26:$E$26) | C63: =SUMPRODUCT($C$39:$E$39,$C$26:$E$26)
A64: Free cash flow to firm | B64: =SUMPRODUCT($C$38:$E$38,$C$31:$E$31) | C64: =SUMPRODUCT($C$39:$E$39,$C$31:$E$31)
A66: Valuation method | B66: Metric | C66: Multiple used | D66: Basis | E66: Metric at target date | F66: Value per share | G66: Weight | H66: Metric key | I66: Metric shown (stated per-share figure when used)
A67: DCF (cash flow to target date + terminal) | F67: =((B45)-$B$50-$B$51+$B$52)/$B$53 | G67: =Valuation!$B$63
A68: ="Multiple: "&Valuation!A69&" ("&Valuation!D69&")" | B68: =Valuation!A69 | C68: =IF(B68="FCF yield",(Valuation!B69)*(1-$B$8),(Valuation!B69)+IF(B68="EV/sales",0.1,1)*$B$6) | D68: =Valuation!D69 | E68: =IF(D68="ltm",CHOOSE(H68,$C$59,$C$60,$C$61,$C$62,$C$63,$C$64),CHOOSE(H68,$B$59,$B$60,$B$61,$B$62,$B$63,$B$64)) | F68: =IF(OR(B68="EV/EBITDA",B68="EV/sales",B68="EV/EBIT"),((C68*E68)-$B$50-$B$51+$B$52)/$B$53,IF(B68="P/E",IF(Valuation!F69<>"",C68*(Valuation!F69)*(1+$B$9),C68*(E68-$B$54)/$B$53),IF(Valuation!G69<>"",(Valuation!G69)*(1+$B$9)/C68,(E68-IF(Valuation!H69,$B$54,0))/C68/$B$53))+$B$52/$B$53) | G68: =Valuation!C69 | H68: =IF(B68="EV/sales",1,IF(B68="EV/EBIT",2,IF(B68="EV/EBITDA",IF(Valuation!E69="adjusted",4,3),IF(B68="P/E",5,6)))) | I68: =IF(AND(B68="P/E",Valuation!F69<>""),(Valuation!F69)*(1+$B$9),IF(AND(B68="FCF yield",Valuation!G69<>""),(Valuation!G69)*(1+$B$9),E68))
A69: Value per share at target date (weighted methods) | F69: =SUMPRODUCT(F67:F68,G67:G68)/SUM(G67:G68)
A129: Segment build (model_engine.seg_build): revenue and EBIT are the segment sums plus corporate EBIT
A130: Segment | B130: Base | C130: =Model!E5 | D130: =Model!F5 | E130: =Model!G5
A131: Generation: revenue growth | C131: =Model!E12+$B$4 | D131: =Model!F12+$B$4 | E131: =Model!G12+$B$4
A132: Generation: revenue | B132: =Valuation!$B$86 | C132: =B132*(1+C131) | D132: =C132*(1+D131) | E132: =D132*(1+E131)
A133: Generation: EBIT margin | C133: =Model!E14+$B$5 | D133: =Model!F14+$B$5 | E133: =Model!G14+$B$5
A134: Generation: EBIT | C134: =C132*C133 | D134: =D132*D133 | E134: =E132*E133
A135: Retail: revenue growth | C135: =Model!E16+$B$4 | D135: =Model!F16+$B$4 | E135: =Model!G16+$B$4
A136: Retail: revenue | B136: =Valuation!$B$87 | C136: =B136*(1+C135) | D136: =C136*(1+D135) | E136: =D136*(1+E135)
A137: Retail: EBIT margin | C137: =Model!E18+$B$5 | D137: =Model!F18+$B$5 | E137: =Model!G18+$B$5
A138: Retail: EBIT | C138: =C136*C137 | D138: =D136*D137 | E138: =E136*E137
A139: Total segment revenue | C139: =C132+C136 | D139: =D132+D136 | E139: =E132+E136
A140: Total segment EBIT | C140: =C134+C138 | D140: =D134+D138 | E140: =E134+E138
A141: Corporate / unallocated EBIT | C141: =Model!E21 | D141: =Model!F21 | E141: =Model!G21
A142: EBIT (segments + corporate) | C142: =C140+C141 | D142: =D140+D141 | E142: =E140+E141

Sheet Calc - bear
A1: VST engine calculation: bear scenario
A2: Machinery behind the Valuation and Distribution tabs; drivers come from Model, assumptions from Valuation.
A4: Scenario Growth Δ | B4: =N(Valuation!C81)
A5: Scenario Margin Δ | B5: =N(Valuation!D81)
A6: Scenario Multiple Δ (turns) | B6: =N(Valuation!E81)
A7: Scenario WACC Δ | B7: =N(Valuation!F81)
A8: Scenario Multiple %Δ | B8: =N(Valuation!G81)
A9: Scenario Stated EPS/FCF %Δ | B9: =N(Valuation!H81)
A10: Scenario Custom %Δ | B10: =N(Valuation!I81)
A12: WACC | B12: =Valuation!$B$50+B7
A13: Years from last FY end to target date | B13: =(Valuation!$B$44-Valuation!$B$48)/365.25
A14: Years from last FY end to balance date | B14: =(Valuation!$B$54-Valuation!$B$48)/365.25
A15: Years from last FY end to share count date | B15: =(Valuation!$B$60-Valuation!$B$48)/365.25
A16: Projected years | B16: 3
A18: Projection | B18: Base | C18: =Model!E5 | D18: =Model!F5 | E18: =Model!G5
A19: Year index | B19: 0 | C19: 1 | D19: 2 | E19: 3
A20: Period end | C20: =Valuation!$B$48+ROUND(365.25*C19,0) | D20: =Valuation!$B$48+ROUND(365.25*D19,0) | E20: =Valuation!$B$48+ROUND(365.25*E19,0)
A21: Revenue growth | C21: =C22/B22-1 | D21: =D22/C22-1 | E21: =E22/D22-1
A22: Revenue | B22: =Valuation!$B$49 | C22: =C139 | D22: =D139 | E22: =E139
A23: EBIT margin | C23: =C24/C22 | D23: =D24/D22 | E23: =E24/E22
A24: EBIT | C24: =C142 | D24: =D142 | E24: =E142
A25: Tax rate | C25: =Model!E63 | D25: =Model!F63 | E25: =Model!G63
A26: NOPAT | C26: =C24*(1-C25) | D26: =D24*(1-D25) | E26: =E24*(1-E25)
A27: D&A | C27: =C22*(Model!E64) | D27: =D22*(Model!F64) | E27: =E22*(Model!G64)
A28: Capex | C28: =C22*(Model!E65) | D28: =D22*(Model!F65) | E28: =E22*(Model!G65)
A29: Working capital increase | C29: =(Model!E66)*(C22-B22) | D29: =(Model!F66)*(D22-C22) | E29: =(Model!G66)*(E22-D22)
A30: Stock comp | C30: =C22*(Model!E67) | D30: =D22*(Model!F67) | E30: =E22*(Model!G67)
A31: Free cash flow to firm | C31: =C26+C27-C28-C29-IF(AND(Valuation!$B$46="adjusted",Valuation!$B$47="cost"),C30*(1-C25),0) | D31: =D26+D27-D28-D29-IF(AND(Valuation!$B$46="adjusted",Valuation!$B$47="cost"),D30*(1-D25),0) | E31: =E26+E27-E28-E29-IF(AND(Valuation!$B$46="adjusted",Valuation!$B$47="cost"),E30*(1-E25),0)
A32: EBITDA | C32: =C24+C27 | D32: =D24+D27 | E32: =E24+E27
A33: Adj. EBITDA | C33: =C24+C27+C22*(Model!E71) | D33: =D24+D27+D22*(Model!F71) | E33: =E24+E27+E22*(Model!G71)
A34: Shareholder returns + other uses | C34: =C22*Model!E69+Model!E68+Model!E70 | D34: =D22*Model!F69+Model!F68+Model!F70 | E34: =E22*Model!G69+Model!G68+Model!G70
A35: Share of year after target date | C35: =IF(C19<=$B$13,0,C19-MAX(C19-1,$B$13)) | D35: =IF(D19<=$B$13,0,D19-MAX(D19-1,$B$13)) | E35: =IF(E19<=$B$13,0,E19-MAX(E19-1,$B$13))
A36: PV at target date of FCFF | C36: =IF(C35=0,0,C31*C35/(1+$B$12)^(C19-$B$13)) | D36: =IF(D35=0,0,D31*D35/(1+$B$12)^(D19-$B$13)) | E36: =IF(E35=0,0,E31*E35/(1+$B$12)^(E19-$B$13))
A37: Overlap: balance date to target date | C37: =MAX(0,MIN(C19,$B$13)-MAX(C19-1,$B$14)) | D37: =MAX(0,MIN(D19,$B$13)-MAX(D19-1,$B$14)) | E37: =MAX(0,MIN(E19,$B$13)-MAX(E19-1,$B$14))
A38: NTM weight at target date | C38: =MAX(0,MIN(C19,$B$13+1)-MAX(C19-1,$B$13)) | D38: =MAX(0,MIN(D19,$B$13+1)-MAX(D19-1,$B$13)) | E38: =MAX(0,MIN(E19,$B$13+1)-MAX(E19-1,$B$13))
A39: LTM weight at target date | B39: =MAX(0,MIN(0,$B$13)-MAX(-1,$B$13-1)) | C39: =MAX(0,MIN(C19,$B$13)-MAX(C19-1,$B$13-1)) | D39: =MAX(0,MIN(D19,$B$13)-MAX(D19-1,$B$13-1)) | E39: =MAX(0,MIN(E19,$B$13)-MAX(E19-1,$B$13-1))
A41: Value at the target date
A42: PV of free cash flow after the target date | B42: =SUM($C$36:$E$36)
A43: Terminal value at final year | B43: =IF(Valuation!$B$51="exit_multiple",Valuation!$B$53*E32,E31*(1+Valuation!$B$52)/($B$12-Valuation!$B$52))
A44: PV of terminal value at target date | B44: =B43/(1+$B$12)^($B$16-$B$13)
A45: DCF enterprise value at target date | B45: =B42+B44
A46: Terminal value share of DCF | B46: =B44/B45
A47: Free cash flow earned, balance date to target date | B47: =SUMPRODUCT($C$37:$E$37,$C$31:$E$31)
A48: Shareholder returns + other uses paid | B48: =SUMPRODUCT($C$37:$E$37,$C$34:$E$34)
A49: Interest drag on net debt | B49: =Valuation!$B$57*(1-$C$25)*MAX(Valuation!$B$55,0)*MAX($B$13-$B$14,0)
A50: Net debt at target date | B50: =IF(Valuation!$B$58="",Valuation!$B$55-B47+B49+B48,Valuation!$B$58+$B$260)
A51: Minority interests | B51: =Valuation!$B$56
A52: Adjustments (probability-weighted) | B52: =(Valuation!B75)*Valuation!C75+0
A53: Diluted shares at target date (M) | B53: =IF(Valuation!$B$62="",Valuation!$B$59*(1+Valuation!$B$61)^MAX($B$13-$B$15,0),Valuation!$B$62)
A54: After-tax interest on target-date net debt | B54: =Valuation!$B$57*(1-$C$25)*MAX(B50,0)
A55: Check: WACC vs terminal growth | B55: =IF(AND(Valuation!$B$51<>"exit_multiple",$B$12<=Valuation!$B$52+0.01),"WACC must exceed terminal growth by 1 point","ok")
A56: Check: projection length | B56: =IF(OR($B$13>=$B$16-1,$B$13+1>$B$16),"add projected years past the target date","ok")
A58: Metric at target date | B58: Next 12 months | C58: Last 12 months
A59: Revenue | B59: =SUMPRODUCT($C$38:$E$38,$C$22:$E$22) | C59: =SUMPRODUCT($C$39:$E$39,$C$22:$E$22)+$B$39*$B$22
A60: EBIT | B60: =SUMPRODUCT($C$38:$E$38,$C$24:$E$24) | C60: =SUMPRODUCT($C$39:$E$39,$C$24:$E$24)
A61: EBITDA | B61: =SUMPRODUCT($C$38:$E$38,$C$32:$E$32) | C61: =SUMPRODUCT($C$39:$E$39,$C$32:$E$32)
A62: Adj. EBITDA | B62: =SUMPRODUCT($C$38:$E$38,$C$33:$E$33) | C62: =SUMPRODUCT($C$39:$E$39,$C$33:$E$33)
A63: NOPAT | B63: =SUMPRODUCT($C$38:$E$38,$C$26:$E$26) | C63: =SUMPRODUCT($C$39:$E$39,$C$26:$E$26)
A64: Free cash flow to firm | B64: =SUMPRODUCT($C$38:$E$38,$C$31:$E$31) | C64: =SUMPRODUCT($C$39:$E$39,$C$31:$E$31)
A66: Valuation method | B66: Metric | C66: Multiple used | D66: Basis | E66: Metric at target date | F66: Value per share | G66: Weight | H66: Metric key | I66: Metric shown (stated per-share figure when used)
A67: DCF (cash flow to target date + terminal) | F67: =((B45)-$B$50-$B$51+$B$52)/$B$53 | G67: =Valuation!$B$63
A68: ="Multiple: "&Valuation!A69&" ("&Valuation!D69&")" | B68: =Valuation!A69 | C68: =IF(B68="FCF yield",(Valuation!B69)*(1-$B$8),(Valuation!B69)+IF(B68="EV/sales",0.1,1)*$B$6) | D68: =Valuation!D69 | E68: =IF(D68="ltm",CHOOSE(H68,$C$59,$C$60,$C$61,$C$62,$C$63,$C$64),CHOOSE(H68,$B$59,$B$60,$B$61,$B$62,$B$63,$B$64)) | F68: =IF(OR(B68="EV/EBITDA",B68="EV/sales",B68="EV/EBIT"),((C68*E68)-$B$50-$B$51+$B$52)/$B$53,IF(B68="P/E",IF(Valuation!F69<>"",C68*(Valuation!F69)*(1+$B$9),C68*(E68-$B$54)/$B$53),IF(Valuation!G69<>"",(Valuation!G69)*(1+$B$9)/C68,(E68-IF(Valuation!H69,$B$54,0))/C68/$B$53))+$B$52/$B$53) | G68: =Valuation!C69 | H68: =IF(B68="EV/sales",1,IF(B68="EV/EBIT",2,IF(B68="EV/EBITDA",IF(Valuation!E69="adjusted",4,3),IF(B68="P/E",5,6)))) | I68: =IF(AND(B68="P/E",Valuation!F69<>""),(Valuation!F69)*(1+$B$9),IF(AND(B68="FCF yield",Valuation!G69<>""),(Valuation!G69)*(1+$B$9),E68))
A69: Value per share at target date (weighted methods) | F69: =SUMPRODUCT(F67:F68,G67:G68)/SUM(G67:G68)
A129: Segment build (model_engine.seg_build): revenue and EBIT are the segment sums plus corporate EBIT
A130: Segment | B130: Base | C130: =Model!E5 | D130: =Model!F5 | E130: =Model!G5
A131: Generation: revenue growth | C131: =Model!E12+$B$4+$B$250 | D131: =Model!F12+$B$4+$B$252 | E131: =Model!G12+$B$4+$B$254
A132: Generation: revenue | B132: =Valuation!$B$86 | C132: =B132*(1+C131) | D132: =C132*(1+D131) | E132: =D132*(1+E131)
A133: Generation: EBIT margin | C133: =Model!E14+$B$5+$B$251 | D133: =Model!F14+$B$5+$B$253 | E133: =Model!G14+$B$5+$B$255
A134: Generation: EBIT | C134: =C132*C133 | D134: =D132*D133 | E134: =E132*E133
A135: Retail: revenue growth | C135: =Model!E16+$B$4+$B$256 | D135: =Model!F16+$B$4 | E135: =Model!G16+$B$4
A136: Retail: revenue | B136: =Valuation!$B$87 | C136: =B136*(1+C135) | D136: =C136*(1+D135) | E136: =D136*(1+E135)
A137: Retail: EBIT margin | C137: =Model!E18+$B$5+$B$257 | D137: =Model!F18+$B$5+$B$258 | E137: =Model!G18+$B$5+$B$259
A138: Retail: EBIT | C138: =C136*C137 | D138: =D136*D137 | E138: =E136*E137
A139: Total segment revenue | C139: =C132+C136 | D139: =D132+D136 | E139: =E132+E136
A140: Total segment EBIT | C140: =C134+C138 | D140: =D134+D138 | E140: =E134+E138
A141: Corporate / unallocated EBIT | C141: =Model!E21 | D141: =Model!F21 | E141: =Model!G21
A142: EBIT (segments + corporate) | C142: =C140+C141 | D142: =D140+D141 | E142: =E140+E141
A249: Driver scenario shifts: line-item changes model_drivers.py resolves from this scenario's driver deltas (added to the Model tab inputs)
A250: Generation: revenue growth, year 1 | B250: -0.0323202
A251: Generation: EBIT margin, year 1 | B251: -0.034213857
A252: Generation: revenue growth, year 2 | B252: -0.00041889932
A253: Generation: EBIT margin, year 2 | B253: -0.033808937
A254: Generation: revenue growth, year 3 | B254: -0.00013194547
A255: Generation: EBIT margin, year 3 | B255: -0.034102545
A256: Retail: revenue growth, year 1 | B256: -0.030235428
A257: Retail: EBIT margin, year 1 | B257: 0.0035887121
A258: Retail: EBIT margin, year 2 | B258: 0.003522369
A259: Retail: EBIT margin, year 3 | B259: 0.0035339959
A260: Net debt at target date (override) | B260: 217.65749

Sheet Calc - base
A1: VST engine calculation: base scenario
A2: Machinery behind the Valuation and Distribution tabs; drivers come from Model, assumptions from Valuation.
A4: Scenario Growth Δ | B4: =N(Valuation!C82)
A5: Scenario Margin Δ | B5: =N(Valuation!D82)
A6: Scenario Multiple Δ (turns) | B6: =N(Valuation!E82)
A7: Scenario WACC Δ | B7: =N(Valuation!F82)
A8: Scenario Multiple %Δ | B8: =N(Valuation!G82)
A9: Scenario Stated EPS/FCF %Δ | B9: =N(Valuation!H82)
A10: Scenario Custom %Δ | B10: =N(Valuation!I82)
A12: WACC | B12: =Valuation!$B$50+B7
A13: Years from last FY end to target date | B13: =(Valuation!$B$44-Valuation!$B$48)/365.25
A14: Years from last FY end to balance date | B14: =(Valuation!$B$54-Valuation!$B$48)/365.25
A15: Years from last FY end to share count date | B15: =(Valuation!$B$60-Valuation!$B$48)/365.25
A16: Projected years | B16: 3
A18: Projection | B18: Base | C18: =Model!E5 | D18: =Model!F5 | E18: =Model!G5
A19: Year index | B19: 0 | C19: 1 | D19: 2 | E19: 3
A20: Period end | C20: =Valuation!$B$48+ROUND(365.25*C19,0) | D20: =Valuation!$B$48+ROUND(365.25*D19,0) | E20: =Valuation!$B$48+ROUND(365.25*E19,0)
A21: Revenue growth | C21: =C22/B22-1 | D21: =D22/C22-1 | E21: =E22/D22-1
A22: Revenue | B22: =Valuation!$B$49 | C22: =C139 | D22: =D139 | E22: =E139
A23: EBIT margin | C23: =C24/C22 | D23: =D24/D22 | E23: =E24/E22
A24: EBIT | C24: =C142 | D24: =D142 | E24: =E142
A25: Tax rate | C25: =Model!E63 | D25: =Model!F63 | E25: =Model!G63
A26: NOPAT | C26: =C24*(1-C25) | D26: =D24*(1-D25) | E26: =E24*(1-E25)
A27: D&A | C27: =C22*(Model!E64) | D27: =D22*(Model!F64) | E27: =E22*(Model!G64)
A28: Capex | C28: =C22*(Model!E65) | D28: =D22*(Model!F65) | E28: =E22*(Model!G65)
A29: Working capital increase | C29: =(Model!E66)*(C22-B22) | D29: =(Model!F66)*(D22-C22) | E29: =(Model!G66)*(E22-D22)
A30: Stock comp | C30: =C22*(Model!E67) | D30: =D22*(Model!F67) | E30: =E22*(Model!G67)
A31: Free cash flow to firm | C31: =C26+C27-C28-C29-IF(AND(Valuation!$B$46="adjusted",Valuation!$B$47="cost"),C30*(1-C25),0) | D31: =D26+D27-D28-D29-IF(AND(Valuation!$B$46="adjusted",Valuation!$B$47="cost"),D30*(1-D25),0) | E31: =E26+E27-E28-E29-IF(AND(Valuation!$B$46="adjusted",Valuation!$B$47="cost"),E30*(1-E25),0)
A32: EBITDA | C32: =C24+C27 | D32: =D24+D27 | E32: =E24+E27
A33: Adj. EBITDA | C33: =C24+C27+C22*(Model!E71) | D33: =D24+D27+D22*(Model!F71) | E33: =E24+E27+E22*(Model!G71)
A34: Shareholder returns + other uses | C34: =C22*Model!E69+Model!E68+Model!E70 | D34: =D22*Model!F69+Model!F68+Model!F70 | E34: =E22*Model!G69+Model!G68+Model!G70
A35: Share of year after target date | C35: =IF(C19<=$B$13,0,C19-MAX(C19-1,$B$13)) | D35: =IF(D19<=$B$13,0,D19-MAX(D19-1,$B$13)) | E35: =IF(E19<=$B$13,0,E19-MAX(E19-1,$B$13))
A36: PV at target date of FCFF | C36: =IF(C35=0,0,C31*C35/(1+$B$12)^(C19-$B$13)) | D36: =IF(D35=0,0,D31*D35/(1+$B$12)^(D19-$B$13)) | E36: =IF(E35=0,0,E31*E35/(1+$B$12)^(E19-$B$13))
A37: Overlap: balance date to target date | C37: =MAX(0,MIN(C19,$B$13)-MAX(C19-1,$B$14)) | D37: =MAX(0,MIN(D19,$B$13)-MAX(D19-1,$B$14)) | E37: =MAX(0,MIN(E19,$B$13)-MAX(E19-1,$B$14))
A38: NTM weight at target date | C38: =MAX(0,MIN(C19,$B$13+1)-MAX(C19-1,$B$13)) | D38: =MAX(0,MIN(D19,$B$13+1)-MAX(D19-1,$B$13)) | E38: =MAX(0,MIN(E19,$B$13+1)-MAX(E19-1,$B$13))
A39: LTM weight at target date | B39: =MAX(0,MIN(0,$B$13)-MAX(-1,$B$13-1)) | C39: =MAX(0,MIN(C19,$B$13)-MAX(C19-1,$B$13-1)) | D39: =MAX(0,MIN(D19,$B$13)-MAX(D19-1,$B$13-1)) | E39: =MAX(0,MIN(E19,$B$13)-MAX(E19-1,$B$13-1))
A41: Value at the target date
A42: PV of free cash flow after the target date | B42: =SUM($C$36:$E$36)
A43: Terminal value at final year | B43: =IF(Valuation!$B$51="exit_multiple",Valuation!$B$53*E32,E31*(1+Valuation!$B$52)/($B$12-Valuation!$B$52))
A44: PV of terminal value at target date | B44: =B43/(1+$B$12)^($B$16-$B$13)
A45: DCF enterprise value at target date | B45: =B42+B44
A46: Terminal value share of DCF | B46: =B44/B45
A47: Free cash flow earned, balance date to target date | B47: =SUMPRODUCT($C$37:$E$37,$C$31:$E$31)
A48: Shareholder returns + other uses paid | B48: =SUMPRODUCT($C$37:$E$37,$C$34:$E$34)
A49: Interest drag on net debt | B49: =Valuation!$B$57*(1-$C$25)*MAX(Valuation!$B$55,0)*MAX($B$13-$B$14,0)
A50: Net debt at target date | B50: =IF(Valuation!$B$58="",Valuation!$B$55-B47+B49+B48,Valuation!$B$58)
A51: Minority interests | B51: =Valuation!$B$56
A52: Adjustments (probability-weighted) | B52: =(Valuation!B75)*Valuation!C75+0
A53: Diluted shares at target date (M) | B53: =IF(Valuation!$B$62="",Valuation!$B$59*(1+Valuation!$B$61)^MAX($B$13-$B$15,0),Valuation!$B$62)
A54: After-tax interest on target-date net debt | B54: =Valuation!$B$57*(1-$C$25)*MAX(B50,0)
A55: Check: WACC vs terminal growth | B55: =IF(AND(Valuation!$B$51<>"exit_multiple",$B$12<=Valuation!$B$52+0.01),"WACC must exceed terminal growth by 1 point","ok")
A56: Check: projection length | B56: =IF(OR($B$13>=$B$16-1,$B$13+1>$B$16),"add projected years past the target date","ok")
A58: Metric at target date | B58: Next 12 months | C58: Last 12 months
A59: Revenue | B59: =SUMPRODUCT($C$38:$E$38,$C$22:$E$22) | C59: =SUMPRODUCT($C$39:$E$39,$C$22:$E$22)+$B$39*$B$22
A60: EBIT | B60: =SUMPRODUCT($C$38:$E$38,$C$24:$E$24) | C60: =SUMPRODUCT($C$39:$E$39,$C$24:$E$24)
A61: EBITDA | B61: =SUMPRODUCT($C$38:$E$38,$C$32:$E$32) | C61: =SUMPRODUCT($C$39:$E$39,$C$32:$E$32)
A62: Adj. EBITDA | B62: =SUMPRODUCT($C$38:$E$38,$C$33:$E$33) | C62: =SUMPRODUCT($C$39:$E$39,$C$33:$E$33)
A63: NOPAT | B63: =SUMPRODUCT($C$38:$E$38,$C$26:$E$26) | C63: =SUMPRODUCT($C$39:$E$39,$C$26:$E$26)
A64: Free cash flow to firm | B64: =SUMPRODUCT($C$38:$E$38,$C$31:$E$31) | C64: =SUMPRODUCT($C$39:$E$39,$C$31:$E$31)
A66: Valuation method | B66: Metric | C66: Multiple used | D66: Basis | E66: Metric at target date | F66: Value per share | G66: Weight | H66: Metric key | I66: Metric shown (stated per-share figure when used)
A67: DCF (cash flow to target date + terminal) | F67: =((B45)-$B$50-$B$51+$B$52)/$B$53 | G67: =Valuation!$B$63
A68: ="Multiple: "&Valuation!A69&" ("&Valuation!D69&")" | B68: =Valuation!A69 | C68: =IF(B68="FCF yield",(Valuation!B69)*(1-$B$8),(Valuation!B69)+IF(B68="EV/sales",0.1,1)*$B$6) | D68: =Valuation!D69 | E68: =IF(D68="ltm",CHOOSE(H68,$C$59,$C$60,$C$61,$C$62,$C$63,$C$64),CHOOSE(H68,$B$59,$B$60,$B$61,$B$62,$B$63,$B$64)) | F68: =IF(OR(B68="EV/EBITDA",B68="EV/sales",B68="EV/EBIT"),((C68*E68)-$B$50-$B$51+$B$52)/$B$53,IF(B68="P/E",IF(Valuation!F69<>"",C68*(Valuation!F69)*(1+$B$9),C68*(E68-$B$54)/$B$53),IF(Valuation!G69<>"",(Valuation!G69)*(1+$B$9)/C68,(E68-IF(Valuation!H69,$B$54,0))/C68/$B$53))+$B$52/$B$53) | G68: =Valuation!C69 | H68: =IF(B68="EV/sales",1,IF(B68="EV/EBIT",2,IF(B68="EV/EBITDA",IF(Valuation!E69="adjusted",4,3),IF(B68="P/E",5,6)))) | I68: =IF(AND(B68="P/E",Valuation!F69<>""),(Valuation!F69)*(1+$B$9),IF(AND(B68="FCF yield",Valuation!G69<>""),(Valuation!G69)*(1+$B$9),E68))
A69: Value per share at target date (weighted methods) | F69: =SUMPRODUCT(F67:F68,G67:G68)/SUM(G67:G68)
A129: Segment build (model_engine.seg_build): revenue and EBIT are the segment sums plus corporate EBIT
A130: Segment | B130: Base | C130: =Model!E5 | D130: =Model!F5 | E130: =Model!G5
A131: Generation: revenue growth | C131: =Model!E12+$B$4 | D131: =Model!F12+$B$4 | E131: =Model!G12+$B$4
A132: Generation: revenue | B132: =Valuation!$B$86 | C132: =B132*(1+C131) | D132: =C132*(1+D131) | E132: =D132*(1+E131)
A133: Generation: EBIT margin | C133: =Model!E14+$B$5 | D133: =Model!F14+$B$5 | E133: =Model!G14+$B$5
A134: Generation: EBIT | C134: =C132*C133 | D134: =D132*D133 | E134: =E132*E133
A135: Retail: revenue growth | C135: =Model!E16+$B$4 | D135: =Model!F16+$B$4 | E135: =Model!G16+$B$4
A136: Retail: revenue | B136: =Valuation!$B$87 | C136: =B136*(1+C135) | D136: =C136*(1+D135) | E136: =D136*(1+E135)
A137: Retail: EBIT margin | C137: =Model!E18+$B$5 | D137: =Model!F18+$B$5 | E137: =Model!G18+$B$5
A138: Retail: EBIT | C138: =C136*C137 | D138: =D136*D137 | E138: =E136*E137
A139: Total segment revenue | C139: =C132+C136 | D139: =D132+D136 | E139: =E132+E136
A140: Total segment EBIT | C140: =C134+C138 | D140: =D134+D138 | E140: =E134+E138
A141: Corporate / unallocated EBIT | C141: =Model!E21 | D141: =Model!F21 | E141: =Model!G21
A142: EBIT (segments + corporate) | C142: =C140+C141 | D142: =D140+D141 | E142: =E140+E141

Sheet Calc - bull
A1: VST engine calculation: bull scenario
A2: Machinery behind the Valuation and Distribution tabs; drivers come from Model, assumptions from Valuation.
A4: Scenario Growth Δ | B4: =N(Valuation!C83)
A5: Scenario Margin Δ | B5: =N(Valuation!D83)
A6: Scenario Multiple Δ (turns) | B6: =N(Valuation!E83)
A7: Scenario WACC Δ | B7: =N(Valuation!F83)
A8: Scenario Multiple %Δ | B8: =N(Valuation!G83)
A9: Scenario Stated EPS/FCF %Δ | B9: =N(Valuation!H83)
A10: Scenario Custom %Δ | B10: =N(Valuation!I83)
A12: WACC | B12: =Valuation!$B$50+B7
A13: Years from last FY end to target date | B13: =(Valuation!$B$44-Valuation!$B$48)/365.25
A14: Years from last FY end to balance date | B14: =(Valuation!$B$54-Valuation!$B$48)/365.25
A15: Years from last FY end to share count date | B15: =(Valuation!$B$60-Valuation!$B$48)/365.25
A16: Projected years | B16: 3
A18: Projection | B18: Base | C18: =Model!E5 | D18: =Model!F5 | E18: =Model!G5
A19: Year index | B19: 0 | C19: 1 | D19: 2 | E19: 3
A20: Period end | C20: =Valuation!$B$48+ROUND(365.25*C19,0) | D20: =Valuation!$B$48+ROUND(365.25*D19,0) | E20: =Valuation!$B$48+ROUND(365.25*E19,0)
A21: Revenue growth | C21: =C22/B22-1 | D21: =D22/C22-1 | E21: =E22/D22-1
A22: Revenue | B22: =Valuation!$B$49 | C22: =C139 | D22: =D139 | E22: =E139
A23: EBIT margin | C23: =C24/C22 | D23: =D24/D22 | E23: =E24/E22
A24: EBIT | C24: =C142 | D24: =D142 | E24: =E142
A25: Tax rate | C25: =Model!E63 | D25: =Model!F63 | E25: =Model!G63
A26: NOPAT | C26: =C24*(1-C25) | D26: =D24*(1-D25) | E26: =E24*(1-E25)
A27: D&A | C27: =C22*(Model!E64) | D27: =D22*(Model!F64) | E27: =E22*(Model!G64)
A28: Capex | C28: =C22*(Model!E65) | D28: =D22*(Model!F65) | E28: =E22*(Model!G65)
A29: Working capital increase | C29: =(Model!E66)*(C22-B22) | D29: =(Model!F66)*(D22-C22) | E29: =(Model!G66)*(E22-D22)
A30: Stock comp | C30: =C22*(Model!E67) | D30: =D22*(Model!F67) | E30: =E22*(Model!G67)
A31: Free cash flow to firm | C31: =C26+C27-C28-C29-IF(AND(Valuation!$B$46="adjusted",Valuation!$B$47="cost"),C30*(1-C25),0) | D31: =D26+D27-D28-D29-IF(AND(Valuation!$B$46="adjusted",Valuation!$B$47="cost"),D30*(1-D25),0) | E31: =E26+E27-E28-E29-IF(AND(Valuation!$B$46="adjusted",Valuation!$B$47="cost"),E30*(1-E25),0)
A32: EBITDA | C32: =C24+C27 | D32: =D24+D27 | E32: =E24+E27
A33: Adj. EBITDA | C33: =C24+C27+C22*(Model!E71) | D33: =D24+D27+D22*(Model!F71) | E33: =E24+E27+E22*(Model!G71)
A34: Shareholder returns + other uses | C34: =C22*Model!E69+Model!E68+Model!E70 | D34: =D22*Model!F69+Model!F68+Model!F70 | E34: =E22*Model!G69+Model!G68+Model!G70
A35: Share of year after target date | C35: =IF(C19<=$B$13,0,C19-MAX(C19-1,$B$13)) | D35: =IF(D19<=$B$13,0,D19-MAX(D19-1,$B$13)) | E35: =IF(E19<=$B$13,0,E19-MAX(E19-1,$B$13))
A36: PV at target date of FCFF | C36: =IF(C35=0,0,C31*C35/(1+$B$12)^(C19-$B$13)) | D36: =IF(D35=0,0,D31*D35/(1+$B$12)^(D19-$B$13)) | E36: =IF(E35=0,0,E31*E35/(1+$B$12)^(E19-$B$13))
A37: Overlap: balance date to target date | C37: =MAX(0,MIN(C19,$B$13)-MAX(C19-1,$B$14)) | D37: =MAX(0,MIN(D19,$B$13)-MAX(D19-1,$B$14)) | E37: =MAX(0,MIN(E19,$B$13)-MAX(E19-1,$B$14))
A38: NTM weight at target date | C38: =MAX(0,MIN(C19,$B$13+1)-MAX(C19-1,$B$13)) | D38: =MAX(0,MIN(D19,$B$13+1)-MAX(D19-1,$B$13)) | E38: =MAX(0,MIN(E19,$B$13+1)-MAX(E19-1,$B$13))
A39: LTM weight at target date | B39: =MAX(0,MIN(0,$B$13)-MAX(-1,$B$13-1)) | C39: =MAX(0,MIN(C19,$B$13)-MAX(C19-1,$B$13-1)) | D39: =MAX(0,MIN(D19,$B$13)-MAX(D19-1,$B$13-1)) | E39: =MAX(0,MIN(E19,$B$13)-MAX(E19-1,$B$13-1))
A41: Value at the target date
A42: PV of free cash flow after the target date | B42: =SUM($C$36:$E$36)
A43: Terminal value at final year | B43: =IF(Valuation!$B$51="exit_multiple",Valuation!$B$53*E32,E31*(1+Valuation!$B$52)/($B$12-Valuation!$B$52))
A44: PV of terminal value at target date | B44: =B43/(1+$B$12)^($B$16-$B$13)
A45: DCF enterprise value at target date | B45: =B42+B44
A46: Terminal value share of DCF | B46: =B44/B45
A47: Free cash flow earned, balance date to target date | B47: =SUMPRODUCT($C$37:$E$37,$C$31:$E$31)
A48: Shareholder returns + other uses paid | B48: =SUMPRODUCT($C$37:$E$37,$C$34:$E$34)
A49: Interest drag on net debt | B49: =Valuation!$B$57*(1-$C$25)*MAX(Valuation!$B$55,0)*MAX($B$13-$B$14,0)
A50: Net debt at target date | B50: =IF(Valuation!$B$58="",Valuation!$B$55-B47+B49+B48,Valuation!$B$58+$B$260)
A51: Minority interests | B51: =Valuation!$B$56
A52: Adjustments (probability-weighted) | B52: =(Valuation!B75)*Valuation!C75+0
A53: Diluted shares at target date (M) | B53: =IF(Valuation!$B$62="",Valuation!$B$59*(1+Valuation!$B$61)^MAX($B$13-$B$15,0),Valuation!$B$62)
A54: After-tax interest on target-date net debt | B54: =Valuation!$B$57*(1-$C$25)*MAX(B50,0)
A55: Check: WACC vs terminal growth | B55: =IF(AND(Valuation!$B$51<>"exit_multiple",$B$12<=Valuation!$B$52+0.01),"WACC must exceed terminal growth by 1 point","ok")
A56: Check: projection length | B56: =IF(OR($B$13>=$B$16-1,$B$13+1>$B$16),"add projected years past the target date","ok")
A58: Metric at target date | B58: Next 12 months | C58: Last 12 months
A59: Revenue | B59: =SUMPRODUCT($C$38:$E$38,$C$22:$E$22) | C59: =SUMPRODUCT($C$39:$E$39,$C$22:$E$22)+$B$39*$B$22
A60: EBIT | B60: =SUMPRODUCT($C$38:$E$38,$C$24:$E$24) | C60: =SUMPRODUCT($C$39:$E$39,$C$24:$E$24)
A61: EBITDA | B61: =SUMPRODUCT($C$38:$E$38,$C$32:$E$32) | C61: =SUMPRODUCT($C$39:$E$39,$C$32:$E$32)
A62: Adj. EBITDA | B62: =SUMPRODUCT($C$38:$E$38,$C$33:$E$33) | C62: =SUMPRODUCT($C$39:$E$39,$C$33:$E$33)
A63: NOPAT | B63: =SUMPRODUCT($C$38:$E$38,$C$26:$E$26) | C63: =SUMPRODUCT($C$39:$E$39,$C$26:$E$26)
A64: Free cash flow to firm | B64: =SUMPRODUCT($C$38:$E$38,$C$31:$E$31) | C64: =SUMPRODUCT($C$39:$E$39,$C$31:$E$31)
A66: Valuation method | B66: Metric | C66: Multiple used | D66: Basis | E66: Metric at target date | F66: Value per share | G66: Weight | H66: Metric key | I66: Metric shown (stated per-share figure when used)
A67: DCF (cash flow to target date + terminal) | F67: =((B45)-$B$50-$B$51+$B$52)/$B$53 | G67: =Valuation!$B$63
A68: ="Multiple: "&Valuation!A69&" ("&Valuation!D69&")" | B68: =Valuation!A69 | C68: =IF(B68="FCF yield",(Valuation!B69)*(1-$B$8),(Valuation!B69)+IF(B68="EV/sales",0.1,1)*$B$6) | D68: =Valuation!D69 | E68: =IF(D68="ltm",CHOOSE(H68,$C$59,$C$60,$C$61,$C$62,$C$63,$C$64),CHOOSE(H68,$B$59,$B$60,$B$61,$B$62,$B$63,$B$64)) | F68: =IF(OR(B68="EV/EBITDA",B68="EV/sales",B68="EV/EBIT"),((C68*E68)-$B$50-$B$51+$B$52)/$B$53,IF(B68="P/E",IF(Valuation!F69<>"",C68*(Valuation!F69)*(1+$B$9),C68*(E68-$B$54)/$B$53),IF(Valuation!G69<>"",(Valuation!G69)*(1+$B$9)/C68,(E68-IF(Valuation!H69,$B$54,0))/C68/$B$53))+$B$52/$B$53) | G68: =Valuation!C69 | H68: =IF(B68="EV/sales",1,IF(B68="EV/EBIT",2,IF(B68="EV/EBITDA",IF(Valuation!E69="adjusted",4,3),IF(B68="P/E",5,6)))) | I68: =IF(AND(B68="P/E",Valuation!F69<>""),(Valuation!F69)*(1+$B$9),IF(AND(B68="FCF yield",Valuation!G69<>""),(Valuation!G69)*(1+$B$9),E68))
A69: Value per share at target date (weighted methods) | F69: =SUMPRODUCT(F67:F68,G67:G68)/SUM(G67:G68)
A129: Segment build (model_engine.seg_build): revenue and EBIT are the segment sums plus corporate EBIT
A130: Segment | B130: Base | C130: =Model!E5 | D130: =Model!F5 | E130: =Model!G5
A131: Generation: revenue growth | C131: =Model!E12+$B$4+$B$250 | D131: =Model!F12+$B$4+$B$252 | E131: =Model!G12+$B$4+$B$254
A132: Generation: revenue | B132: =Valuation!$B$86 | C132: =B132*(1+C131) | D132: =C132*(1+D131) | E132: =D132*(1+E131)
A133: Generation: EBIT margin | C133: =Model!E14+$B$5+$B$251 | D133: =Model!F14+$B$5+$B$253 | E133: =Model!G14+$B$5+$B$255
A134: Generation: EBIT | C134: =C132*C133 | D134: =D132*D133 | E134: =E132*E133
A135: Retail: revenue growth | C135: =Model!E16+$B$4+$B$256 | D135: =Model!F16+$B$4 | E135: =Model!G16+$B$4
A136: Retail: revenue | B136: =Valuation!$B$87 | C136: =B136*(1+C135) | D136: =C136*(1+D135) | E136: =D136*(1+E135)
A137: Retail: EBIT margin | C137: =Model!E18+$B$5+$B$257 | D137: =Model!F18+$B$5+$B$258 | E137: =Model!G18+$B$5+$B$259
A138: Retail: EBIT | C138: =C136*C137 | D138: =D136*D137 | E138: =E136*E137
A139: Total segment revenue | C139: =C132+C136 | D139: =D132+D136 | E139: =E132+E136
A140: Total segment EBIT | C140: =C134+C138 | D140: =D134+D138 | E140: =E134+E138
A141: Corporate / unallocated EBIT | C141: =Model!E21 | D141: =Model!F21 | E141: =Model!G21
A142: EBIT (segments + corporate) | C142: =C140+C141 | D142: =D140+D141 | E142: =E140+E141
A249: Driver scenario shifts: line-item changes model_drivers.py resolves from this scenario's driver deltas (added to the Model tab inputs)
A250: Generation: revenue growth, year 1 | B250: 0.0269335
A251: Generation: EBIT margin, year 1 | B251: 0.027133967
A252: Generation: revenue growth, year 2 | B252: 0.00033221627
A253: Generation: EBIT margin, year 2 | B253: 0.026794372
A254: Generation: revenue growth, year 3 | B254: 0.00010456986
A255: Generation: EBIT margin, year 3 | B255: 0.027020679
A256: Retail: revenue growth, year 1 | B256: 0.02519619
A257: Retail: EBIT margin, year 1 | B257: -0.0028301226
A258: Retail: EBIT margin, year 2 | B258: -0.0027778032
A259: Retail: EBIT margin, year 3 | B259: -0.0027869723
A260: Net debt at target date (override) | B260: -181.38124

Sheet Agents
A1: VST: each forecaster's own assumption set through the same engine (from model_engine.json, not live)
A3: Set | B3: Research target (12m) | C3: Median | D3: 25th pct | E3: 75th pct | F3: WACC | G3: Y1 growth | H3: Y1 margin | I3: Terminal growth | J3: DCF weight | K3: Years | L3: Multiples | M3: Supervisor's note
A4: agent 1 | B4: 170.97309 | C4: 167.67433 | D4: 127.62524 | E4: 217.60495 | F4: 0.0915 | G4: 0.115 | H4: 0.276 | I4: 0.02 | J4: 0 | K4: 4 | L4: EV/EBITDA 9.5 (ntm) | M4: Closest in structure; 2.0% terminal growth and ~$0.5B high net debt (FCFbG ~$5.4B to the horizon). [4 projected years (over the 3-year cap)]
A5: agent 2 | B5: 172.11375 | C5: 166.8553 | D5: 123.49637 | E5: 203.01154 | F5: 0.095 | G5: 0.12 | H5: 0.2591 | I5: 0.02 | J5: 0 | K5: 4 | L5: EV/EBITDA 9.5 (ntm) | M5: DCF check flag (-27%) at 9.5% WACC and 2.0% g, not argued; bridge otherwise sound. [4 projected years (over the 3-year cap)]
A6: agent 3 | B6: 163.47774 | C6: 159.25036 | D6: 125.73544 | E6: 196.73768 | F6: 0.0925 | G6: 0.1 | H6: 0.2764 | I6: 0.02 | J6: 0 | K6: 4 | L6: EV/EBITDA 9.25 (ntm); P/E 13.5 (ntm) | M6: 9.25x stacks a second discount; 2.0% terminal; DCF at -19.6%. [4 projected years (over the 3-year cap)]
A7: agent 4 | B7: 165.26404 | C7: 162.62634 | D7: 121.66676 | E7: 214.10702 | F7: 0.09 | G7: 0.11 | H7: 0.26 | I7: 0.025 | J7: 0 | K7: 5 | L7: EV/EBITDA 9.5 (ntm) | M7: Claims ~$0.8B high (cash build below FCFbG); FY2028 $8.29B; 0.4 DCF weight. [5 projected years (over the 3-year cap)]
A8: agent 5 | B8: 168.30149 | C8: 166.39106 | D8: 130.50535 | E8: 205.08276 | F8: 0.0937 | G8: 0.1 | H8: 0.2622 | I8: 0.025 | J8: 0 | K8: 5 | L8: EV/EBITDA 9.25 (ntm) | M8: Claims ~$0.6B low ($10B available cash prorated as generated); 9.25x. [5 projected years (over the 3-year cap)]
A9: supervisor | B9: 147.67352 | C9: 144.49383 | D9: 112.64487 | E9: 182.71624 | F9: 0.09 | I9: 0.025 | J9: 0 | K9: 3 | L9: EV/EBITDA 9.0 (ntm)

Sheet Sources
A1: VST: where each input comes from (source numbers point to the list below; F ids to the SEC fact table)
A3: Input | B3: Value | C3: Basis | D3: Sources | E3: SEC fact ids | F3: Derivation
A4: Base revenue FY2025 | B4: 17,586 | C4: reported | D4: 16 | E4: F3 | F4: 10-K FY2025 revenue.
A5: Revenue growth FY2026-30 | B5: +11% / +10% / +4% / +3% / +2.5% | C5: estimate | D5: 15, 4 | E5: F6, F3 | F5: TTM revenue 18,985 (F6) is +8% on FY2025 with H2 seasonally strong -> ~19,520 FY2026; FY2027 adds ~5,500 MW Cogentrix (src 4) and Meta PPA volumes; then load-driven growth. Revenue matters little: margins are set to hit the EBITDA path below.
A6: Adjusted EBITDA path FY2026 / FY2027 / FY2028 / FY2029 / FY2030 | B6: 7,300 / 8,095 / 8,508 / 8,603 / 8,700 (margin 37.4% / 37.7% / 38.1% / 37.4% / 36.9%) | C6: estimate | D6: 1, 2, 4 | F6: FY2026: guidance $6.8-7.6B, mgmt 'at or above the midpoint' ($7.2B) -> 7.3. FY2027: low end of the $7.4-7.8B midpoint opportunity (CFO 'trending towards the lower end') + ~$0.7B Cogentrix/Meta (CFO) = 8.1; Cogentrix alone ~$4.0B / 7.25x = ~$0.55B (src 4). FY2028: +5% for a full year of Meta PPA delivery and Comanche Peak data-center load targeted to energize end-2027 (call), offset by ERCOT softness with 2028 only ~72% hedged = 8.5 (judgment; no management 2028 figure exists). FY2029-30 roughly flat to +1% given the open PJM design after 2029/30.
A7: D&A % revenue | B7: 11.0% | C7: estimate | D7: 1 | E7: F36 | F7: Estimate (no revenue guidance exists): 2026 D&A guidance $2,150M incl. nuclear fuel amortization $423M (src 1) / ~19,520 estimated FY2026 revenue = 11.0%; FY2025 1,986 / 17,586 = 11.3% (F36). [citation gate 2026-10-14]
A8: EBIT margin (adjusted basis, before stock comp) | B8: 26.4% / 26.7% / 27.1% / 26.4% / 25.9% | C8: estimate | D8: 1 | F8: Adjusted EBITDA margin above minus D&A 11.0% of revenue.
A9: Capex % revenue (incl. nuclear fuel and growth ex-Cogentrix) | B9: 14.5% / 13.5% / 10.5% / 10.5% / 10.5% | C9: estimate | D9: 15, 16, 2 | E9: F57, F60 | F9: TTM capex 2,866 (F60, 15.1% of TTM revenue) incl. Permian peakers, Meta uprates, Oak Hill 2 solar (call: $4.5-5B growth 2026-27 incl. the $2.3B Cogentrix cash); growth spend tapers after 2027; long-run ~10.5% vs D&A 11%.
A10: Tax rate | B10: 20% | C10: estimate | D10: 15 | E10: F88, F95 | F10: TTM income tax 584 / pretax income 2,803 = 20.8% (F88/F95).
A11: Stock comp | B11: 0.7% of revenue, counted once as dilution (sbc_treatment 'dilution') | C11: estimate | D11: 1, 16 | E11: F43, F46 | F11: 2026 guidance reconciliation adds back $137M non-cash comp (src 1); FY2025 SBC 113 (F43), TTM 134 (F46). Peers' NTM consensus EBITDA is adjusted (pre-SBC; TLN confirmed, src 12), so the multiple is applied to pre-SBC EBITDA and SBC enters as ~1.1M shares issued by the horizon.
A12: Net debt 2026-06-30 | B12: 19,160 | C12: estimate | D12: 15 | E12: F105, F98, F97 | F12: Estimate derived from reported 10-Q lines at 2026-06-30 (no net-debt figure is reported): long-term debt due currently 1,876 + long-term debt less current 17,719 = 19,595, less cash and cash equivalents 435 = 19,160. Excludes AR financing 300, the forward repurchase obligation 613 and restricted cash 46. [citation gate 2026-10-14]
A13: Preferred stock + NCI (minorities) | B13: 2,488 | C13: estimate | D13: 13 | F13: Estimate: sum of two reported XBRL facts at 2026-06-30 (10-Q accn 0001692819-26-000019): PreferredStockValue 2,476 + MinorityInterest 12 = 2,488. The $1.5B junior notes of 2026-09-24 (src 14) leave total senior claims unchanged whether or not they redeem preferred. [citation gate 2026-10-14]
A14: Net debt at horizon (2027-10-14) | B14: 20,400 | C14: estimate | D14: 1, 2, 3, 4, 15 | E14: F105 | F14: 19,160 (F105) + Cogentrix cash 2,300 + assumed debt 1,500 (src 3/4) + growth spend ex-Cogentrix incl. Helix ~1,600 (($4.5-5B midpoint 4,750 - 2,300 Cogentrix) x 0.646 = 1,580; src 2) + distributions to equity holders ~1,840 (~$3,000M for 2026-27 incl. buybacks and common and preferred dividends, src 2, less ~$863M paid in H1-2026, x 15.5/18 months) - Adj. FCFbG to the horizon ~6,000 (H2-2026 half of the $4,325M guidance midpoint = 2,160, src 1; 2027 ~4,860 = 8,100 x 60% conversion (4,325 / 7,200) x 0.79 yr = 3,840) = 20,400. The call's 'more than $10 billion of available cash' is not prorated as cash generated: management allocates it to ~$3B equity, $4.5-5B growth and $2-2.5B still unallocated (src 2), and it exceeds FCFbG (2026 guidance midpoint 4,325 + 2027 estimate ~4,860 = ~9.2B; only 2026 is guided).
A15: Shares at horizon | B15: 334.6M | C15: estimate | D15: 15, 1, 3 | E15: F103 | F15: 335.6M cover count (2026-08-03, F103) + 5.0M Cogentrix shares (src 3) - ~7.1M bought back (~$1.1B of the ~$1.2B authorization at ~$155, src 1) + ~1.1M stock-comp issuance ($137M/yr / ~$150 x 1.2 yr) = 334.6M.
A16: WACC | B16: 9.0% | C16: estimate | D16: 10, 14 | E16: F81, F98 | F16: See discount_rate.basis.
A17: Terminal growth (Gordon) | B17: 2.5% | C17: judgment | D17: 5, 7, 19 | F17: Nominal growth at about long-run inflation (BLS: CPI +3.7% y/y, core +2.6% y/y, src 5), i.e. no real growth for the fleet after FY2030. Round 1 used 2.0% to price the post-2029/30 PJM design risk, but that risk is already in the 1.1x horizon-multiple discount, the flat FY2029-30 EBITDA (+1%/yr) and the bear scenario; the extra 0.5pt cost ~$13.5/share of DCF (~$4/share of fair value) against a probability-weighted PJM effect of ~-$3/share, and the risk is two-sided (src 19: a stakeholder proposal keeps the $325 cap for existing units, while Brattle recommended a $500-625 RTO-wide cap). See dcf_check.
A18: Horizon EV/EBITDA (NTM adjusted) | B18: 9.0x | C18: judgment | D18: 17, 12, 1, 2 | E18: CEG.ev_ebitda_ntm, TLN.ev_ebitda_ntm, NRG.ev_ebitda_ntm | F18: IPP median 10.06x at the 2026-10-23 close (CEG 10.9x, TLN 10.1x, NRG 8.5x; peers.md of runs/2026-10-23/VST) less the base round's 1.1x discount = 8.96x, rounded to 9.0x; was 10.6x less 1.1x = 9.5x at 10-14. See horizon_multiples.peer_basis. NTM EBITDA at the horizon (2027-10-23) = 0.19 x FY2027 8,056 + 0.81 x FY2028 7,944 = ~7,965 (engine, driver build).
A19: Cogentrix tax-benefit NPV adjustment | B19: 700 x 0.9 = 630 | C19: estimate | D19: 4, 3, 1 | F19: 700 reported (Ex. 99.1: '~$0.7 billion of net present value of expected tax benefits'); 0.9 is my judged closing probability, not on the page (approvals pending, outside date 2026-12-31 extendable); 700 x 0.9 = 630. [citation gate 2026-10-14]
A20: Leg weights | B20: EV/EBITDA 0.7, DCF 0.3 (no P/E leg) | C20: judgment | D20: 17 | F20: NTM EPS consensus rests on 1-2 analysts per quarter (peers.json notes, FMP), so the P/E leg adds noise rather than information; the DCF keeps the cash-flow check (reverse DCF: the 9.5x leg implies ~8.0% WACC).
A21: Fixed / other costs (years[].corporate_ebit, plain) | B21: 2880 / 3116 / 3223 | C21: estimate | D21: 16 | F21: FY2025 residual 2733 = Ongoing Ops Adj. EBITDA 5,912 (FY2025 release) less the driver contributions (gen-segment opex 2,490 + SG&A 429 + corporate 70 less other income/adjustments, 10-K pp.61-62). FY2026 x1.03 (CPI +3.7% y/y, src 5) + Lotus full-year fixed ~65 (2,600 MW x ~$30/kW-yr x 10/12, estimate); FY2027 x1.03 + Cogentrix ~150 (5,500 MW x ~$30/kW-yr x 11/12, estimate); FY2028 x1.03 + 14.
A22: driver:gen_twh | B22: Generation volume (Texas + East + West): 208.2 -> 221/239.8/242 (estimate) | C22: estimate | F22: FY2026 = H1-26 actual 100.7 + H2-25 114.5 x 1.05 (Lotus 2,600 MW owned all of H2-26 vs ~2 months of H2-25; H1-26 East gas +6.4 TWh y/y) = 221.0. FY2027 = + Cogentrix ~22.7 TWh/yr x 11/12 (5,500 MW, ~4,600 MW CCGT at ~55% CF, close assumed ~end-2026) - 2.0 (Casco Bay / Beaver Falls / Syracuse sale, 10-Q p.52). FY2028 = full Cogentrix + 0.3 Permian peakers (online 2028).
A23: driver:gen_price | B23: Realized generation revenue incl. hedges, PTC and retail transfer, ex capacity: 58.66 -> 62.65/63.83/63.62 (estimate) | C23: estimate | F23: Projected as spread + fuel_cost. Spread FY2026 36.65 = (7,300 - cap - retail + fixed) / TWh (100% hedged, see guidance_check). FY2027 37.93: standalone 7,400 low end -> 8290 contribution, + Cogentrix 654 (EBITDA 504 + fixed 150) + Meta premium 150, / 239.8 TWh. FY2028 37.62: + Cogentrix Dec 60 - hedge roll-off 160 (22% more volume open x $3/MWh below the hedged book; ERCOT North $30.20 Q2-26 vs $32.01 FY2025, 10-Q p.56) + Meta full delivery from YE2027 +50 (10-K p.53) + Comanche Peak AWS +60 (delivery from Q4-2027, ramp to full 1,200 MW by 2032, 10-K p.54).
A24: driver:fuel_cost | B24: Realized fuel, purchased power and delivery cost (ex nuclear fuel amortization): 26.02 -> 26/25.9/26 (estimate) | C24: estimate | F24: H1-2026 approx. $25.4/MWh (10-Q segment table: fuel/PP 2,797 less nuclear fuel 242 / 100.7 TWh; unrealized fuel marks not removed); FY2026 26.0 (gas hedged; Henry Hub H1-26 $3.91 vs FY2025 $3.53); FY2027 25.9 (Cogentrix gas at ~7.0 MMBtu/MWh x ~$3.5 = ~$24.5 dilutes); FY2028 26.0.
A25: driver:cap_rev | B25: Net capacity revenue (sold less bought for retail load): 227 -> 556.8/532.8/507.9 (estimate) | C25: estimate | F25: Calendar year = PJM MW x price x days per delivery year (Jan-May prior DY, Jun-Dec new DY) + non-PJM sold 189/yr (H1-26 x2) - capacity bought for retail load 8117 MW-eq (H1-26 411 / day-weighted PJM price) x price x days. FY2026 556.8, FY2027 532.8, FY2028 507.9.
A26: driver:retail_twh | B26: Retail electricity sales volume: 139.1 -> 131.3/133/134 (estimate) | C26: estimate | F26: FY2026 = H1-26 61.9 + H2-25 72.5 x Q2 y/y ratio 0.956 = 131.3; FY2027-28 +1%/yr (ERCOT load growth).
A27: driver:retail_margin | B27: Retail Adjusted EBITDA per MWh sold: 11.66 -> 11.6/11.6/11.6 (estimate) | C27: estimate | F27: FY2026 = (H1-26 841 + H2-25 682) / 131.3 TWh = 11.6; held flat (FY2025 had one-time supply-cost gains, 10-K p.63; H1-26 margin/MWh -4% y/y).
A29: # | B29: Source | C29: Date | D29: Link
A30: 1 | B30: Vistra Q2 2026 results news release (8-K Ex. 99.1): 2026 guidance reaffirmed ($6.8-7.6B Adj. EBITDA, $3.925-4.725B Adj. FCFbG), 2027 midpoint opportunity $7.4-7.8B excl. Cogentrix and Meta PPAs, hedges ~100%/94%/72% for 2026/27/28, ~$1.2B buyback authorization left, non-cash comp $137M, 2026 D&A $2,150M | C30: 2026-08-07 | D30: https://www.sec.gov/Archives/edgar/data/1692819/000169281926000017/vistra-20260630xearningsre.htm
A31: 2 | B31: Vistra Q2 2026 earnings call transcript (Quartr via Bigdata.com): CFO 'trending towards the lower end' of the 2027 $7.4-7.8B midpoint opportunity; Cogentrix + Meta 'roughly $700 million'; 'more than $10 billion of available cash in 2026 and 2027'; ~$3B to equity holders (buybacks, common and preferred dividends); ~$4.5-5B growth incl. Cogentrix and Helix; ~$2-2.5B additional cash available through YE2027; ~$1.2B buyback authorization to exhaust no later than end-2027, repurchases running ahead of pro rata | C31: 2026-08-07 | D31: https://app.bigdata.com/documents/195B479A48CB63C52BC7051FD044E9A5
A32: 3 | B32: Vistra 8-K: agreements to acquire Q-Generation (Cogentrix): ~$2.3B cash, ~$1.5B assumed debt, 5,000,000 shares at $185; FERC, HSR, NH/TX/CT approvals; outside date after 2026-12-31 with two 90-day extensions | C32: 2026-01-05 | D32: https://www.sec.gov/Archives/edgar/data/1692819/000119312526002589/d62722d8k.htm
A33: 4 | B33: Vistra press release (8-K Ex. 99.1): Acquisition of Cogentrix, net price ~$4.0B after ~$0.7B NPV of expected tax benefits, ~7.25x 2027 expected Adj. EBITDA contribution, ~5,500 MW, close expected mid-to-late 2026 | C33: 2026-01-05 | D33: https://www.sec.gov/Archives/edgar/data/1692819/000119312526002589/d62722dex991.htm
A34: 5 | B34: BLS CPI news release, September 2026 (USDL-26-1574), released 2026-10-14 08:30 ET: all items +0.6% m/m SA, +3.7% y/y; core +0.3% m/m, +2.6% y/y; energy +5.2% m/m, +20.4% y/y | C34: 2026-10-14 | D34: https://www.bls.gov/news.release/cpi.nr0.htm
A35: 6 | B35: FERC order accepting Reliability Backstop Procurement and establishing further procedures, 196 FERC 61,245, Docket Nos. ER26-3380-000 and EL26-108-000: accepted and suspended five months to effective 2027-02-28; new FPA 206 proceeding; $555/MW-day max willingness to pay; PJM states the price floor applies through the 2029/2030 delivery year | C35: 2026-09-29 | D35: https://www.pjm.com/pjmfiles/directory/etariff/FercOrders/9154/20260929-er26-3380-000.pdf
A36: 7 | B36: PJM answer in ER26-1556-000: extend the ~$325/MW-day cap and ~$175/MW-day floor for RPM auctions through the 2029/2030 delivery year; evaluate investment incentives with stakeholders by end of 2026 and determine the RPM path for 2030/2031 and beyond | C36: 2026-04-06 | D36: https://www.pjm.com/-/media/DotCom/documents/ferc/filings/2026/20260406-er26-1556-000.pdf
A37: 8 | B37: Troutman Pepper Energy Report: FERC accepts PJM capacity market price collar extension (order 2026-04-28, ER26-1556; ~$325 cap / ~$175 floor for 2028/2029 and 2029/2030) | C37: 2026-05 | D37: https://www.troutmanenergyreport.com/2026/05/ferc-accepts-pjm-capacity-market-price-collar-extension/
A38: 9 | B38: Vistra to Report Third Quarter Results on Nov. 6, 2026 (PR Newswire via Finviz): webcast 10:00 a.m. ET | C38: 2026-09-29 | D38: https://finviz.com/news/396792/vistra-to-report-third-quarter-results-on-nov-6-2026
A39: 10 | B39: FRED DGS10: 10-year Treasury constant maturity 5.21% on 2026-10-13 | C39: 2026-10-13 | D39: https://fred.stlouisfed.org/series/DGS10
A40: 11 | B40: Federal Reserve FOMC meeting calendar: 2026 meetings Oct 27-28 and Dec 8-9 | C40: 2026-10-14 | D40: https://www.federalreserve.gov/monetarypolicy/fomccalendars.htm
A41: 12 | B41: Talen Energy Q2 2026 results (8-K Ex. 99.1): 2026 Adj. EBITDA guidance raised to $2,025-2,225M; Adj. EBITDA excludes unrealized commodity derivative gains/losses and stock comp | C41: 2026-08-05 | D41: https://www.sec.gov/Archives/edgar/data/0001622536/000162253626000065/a20260805q22026earningsrel.htm
... A49: 20 | B49: Vistra Operations 424B5 prospectus supplement, junior subordinated notes due 2057: use of proceeds may include redemption of some or all of the 8.0% Series A / 7.0% Series B preferred (claims-neutral) | C49: 2026-09-10 | D49: https://www.sec.gov/Archives/edgar/data/1692819/000114036126036130/ny20081693x2_424b5.htm
A51: Fact id | B51: Figure | C51: Value | D51: Filing
A52: F1 | B52: revenue FY ending 2023-12-31 (us-gaap:RevenueFromContractWithCustomerExcludingAssessedTax) | C52: 13804000000 | D52: https://www.sec.gov/Archives/edgar/data/1692819/000169281926000006/
A53: F2 | B53: revenue FY ending 2024-12-31 (us-gaap:RevenueFromContractWithCustomerExcludingAssessedTax) | C53: 14761000000 | D53: https://www.sec.gov/Archives/edgar/data/1692819/000169281926000006/
A54: F3 | B54: revenue FY ending 2025-12-31 (us-gaap:RevenueFromContractWithCustomerExcludingAssessedTax) | C54: 17586000000 | D54: https://www.sec.gov/Archives/edgar/data/1692819/000169281926000006/
A55: F4 | B55: revenue YTD 2026-01-01 to 2026-06-30 | C55: 9402000000 | D55: https://www.sec.gov/Archives/edgar/data/1692819/000169281926000019/
A56: F5 | B56: revenue prior-year YTD 2025-01-01 to 2025-06-30 | C56: 8003000000 | D56: https://www.sec.gov/Archives/edgar/data/1692819/000169281926000019/
A57: F6 | B57: revenue TTM to 2026-06-30 | C57: 18985000000
A58: F7 | B58: revenue quarter 2026-04-01 to 2026-06-30 | C58: 4401000000 | D58: https://www.sec.gov/Archives/edgar/data/1692819/000169281926000019/
A59: F8 | B59: operating_income FY ending 2023-12-31 (us-gaap:OperatingIncomeLoss) | C59: 2661000000 | D59: https://www.sec.gov/Archives/edgar/data/1692819/000169281926000006/
A60: F9 | B60: operating_income FY ending 2024-12-31 (us-gaap:OperatingIncomeLoss) | C60: 4081000000 | D60: https://www.sec.gov/Archives/edgar/data/1692819/000169281926000006/
A61: F10 | B61: operating_income FY ending 2025-12-31 (us-gaap:OperatingIncomeLoss) | C61: 1906000000 | D61: https://www.sec.gov/Archives/edgar/data/1692819/000169281926000006/
A62: F11 | B62: operating_income YTD 2026-01-01 to 2026-06-30 | C62: 2052000000 | D62: https://www.sec.gov/Archives/edgar/data/1692819/000169281926000019/
A63: F12 | B63: operating_income prior-year YTD 2025-01-01 to 2025-06-30 | C63: 395000000 | D63: https://www.sec.gov/Archives/edgar/data/1692819/000169281926000019/
A64: F13 | B64: operating_income TTM to 2026-06-30 | C64: 3563000000
A65: F14 | B65: operating_income quarter 2026-04-01 to 2026-06-30 | C65: 553000000 | D65: https://www.sec.gov/Archives/edgar/data/1692819/000169281926000019/
A66: F15 | B66: net_income FY ending 2023-12-31 (us-gaap:NetIncomeLoss) | C66: 1493000000 | D66: https://www.sec.gov/Archives/edgar/data/1692819/000169281926000006/
A67: F16 | B67: net_income FY ending 2024-12-31 (us-gaap:NetIncomeLoss) | C67: 2659000000 | D67: https://www.sec.gov/Archives/edgar/data/1692819/000169281926000006/
A68: F17 | B68: net_income FY ending 2025-12-31 (us-gaap:NetIncomeLoss) | C68: 944000000 | D68: https://www.sec.gov/Archives/edgar/data/1692819/000169281926000006/
A69: F18 | B69: net_income YTD 2026-01-01 to 2026-06-30 | C69: 1334000000 | D69: https://www.sec.gov/Archives/edgar/data/1692819/000169281926000019/
A70: F19 | B70: net_income prior-year YTD 2025-01-01 to 2025-06-30 | C70: 59000000 | D70: https://www.sec.gov/Archives/edgar/data/1692819/000169281926000019/
A71: F20 | B71: net_income TTM to 2026-06-30 | C71: 2219000000
A72: F21 | B72: net_income quarter 2026-04-01 to 2026-06-30 | C72: 305000000 | D72: https://www.sec.gov/Archives/edgar/data/1692819/000169281926000019/
A73: F22 | B73: eps_diluted FY ending 2023-12-31 (us-gaap:EarningsPerShareDiluted) | C73: 3.58 | D73: https://www.sec.gov/Archives/edgar/data/1692819/000169281926000006/
A74: F23 | B74: eps_diluted FY ending 2024-12-31 (us-gaap:EarningsPerShareDiluted) | C74: 7 | D74: https://www.sec.gov/Archives/edgar/data/1692819/000169281926000006/
A75: F24 | B75: eps_diluted FY ending 2025-12-31 (us-gaap:EarningsPerShareDiluted) | C75: 2.18 | D75: https://www.sec.gov/Archives/edgar/data/1692819/000169281926000006/
A76: F25 | B76: eps_diluted YTD 2026-01-01 to 2026-06-30 | C76: 3.64 | D76: https://www.sec.gov/Archives/edgar/data/1692819/000169281926000019/
A77: F26 | B77: eps_diluted prior-year YTD 2025-01-01 to 2025-06-30 | C77: -0.11 | D77: https://www.sec.gov/Archives/edgar/data/1692819/000169281926000019/
A78: F27 | B78: eps_diluted quarter 2026-04-01 to 2026-06-30 | C78: 0.76 | D78: https://www.sec.gov/Archives/edgar/data/1692819/000169281926000019/
A79: F28 | B79: diluted_shares_wavg FY ending 2023-12-31 (us-gaap:WeightedAverageNumberOfDilutedSharesOutstanding) | C79: 375193110 | D79: https://www.sec.gov/Archives/edgar/data/1692819/000169281926000006/
A80: F29 | B80: diluted_shares_wavg FY ending 2024-12-31 (us-gaap:WeightedAverageNumberOfDilutedSharesOutstanding) | C80: 352567060 | D80: https://www.sec.gov/Archives/edgar/data/1692819/000169281926000006/
A81: F30 | B81: diluted_shares_wavg FY ending 2025-12-31 (us-gaap:WeightedAverageNumberOfDilutedSharesOutstanding) | C81: 345656067 | D81: https://www.sec.gov/Archives/edgar/data/1692819/000169281926000006/
A82: F31 | B82: diluted_shares_wavg YTD 2026-01-01 to 2026-06-30 | C82: 340541176 | D82: https://www.sec.gov/Archives/edgar/data/1692819/000169281926000019/
A83: F32 | B83: diluted_shares_wavg prior-year YTD 2025-01-01 to 2025-06-30 | C83: 339599887 | D83: https://www.sec.gov/Archives/edgar/data/1692819/000169281926000019/
... A89: F38 | B89: d_and_a prior-year YTD 2025-01-01 to 2025-06-30 | C89: 1063000000 | D89: https://www.sec.gov/Archives/edgar/data/1692819/000169281926000019/
A90: F39 | B90: d_and_a TTM to 2026-06-30 | C90: 1852000000
A91: F40 | B91: d_and_a quarter 2026-04-01 to 2026-06-30 | C91: 445000000 | D91: https://www.sec.gov/Archives/edgar/data/1692819/000169281926000019/
A92: F41 | B92: sbc FY ending 2023-12-31 (us-gaap:ShareBasedCompensation) | C92: 77000000 | D92: https://www.sec.gov/Archives/edgar/data/1692819/000169281926000006/
A93: F42 | B93: sbc FY ending 2024-12-31 (us-gaap:ShareBasedCompensation) | C93: 100000000 | D93: https://www.sec.gov/Archives/edgar/data/1692819/000169281926000006/
A94: F43 | B94: sbc FY ending 2025-12-31 (us-gaap:ShareBasedCompensation) | C94: 113000000 | D94: https://www.sec.gov/Archives/edgar/data/1692819/000169281926000006/
A95: F44 | B95: sbc YTD 2026-01-01 to 2026-06-30 | C95: 67000000 | D95: https://www.sec.gov/Archives/edgar/data/1692819/000169281926000019/
A96: F45 | B96: sbc prior-year YTD 2025-01-01 to 2025-06-30 | C96: 46000000 | D96: https://www.sec.gov/Archives/edgar/data/1692819/000169281926000019/
A97: F46 | B97: sbc TTM to 2026-06-30 | C97: 134000000
A98: F47 | B98: sbc quarter 2026-01-01 to 2026-03-31 | C98: 32000000 | D98: https://www.sec.gov/Archives/edgar/data/1692819/000169281926000014/
A99: F48 | B99: cfo FY ending 2023-12-31 (us-gaap:NetCashProvidedByUsedInOperatingActivities) | C99: 5453000000 | D99: https://www.sec.gov/Archives/edgar/data/1692819/000169281926000006/
A100: F49 | B100: cfo FY ending 2024-12-31 (us-gaap:NetCashProvidedByUsedInOperatingActivities) | C100: 4563000000 | D100: https://www.sec.gov/Archives/edgar/data/1692819/000169281926000006/
A101: F50 | B101: cfo FY ending 2025-12-31 (us-gaap:NetCashProvidedByUsedInOperatingActivities) | C101: 4070000000 | D101: https://www.sec.gov/Archives/edgar/data/1692819/000169281926000006/
A102: F51 | B102: cfo YTD 2026-01-01 to 2026-06-30 | C102: 2222000000 | D102: https://www.sec.gov/Archives/edgar/data/1692819/000169281926000019/
A103: F52 | B103: cfo prior-year YTD 2025-01-01 to 2025-06-30 | C103: 1171000000 | D103: https://www.sec.gov/Archives/edgar/data/1692819/000169281926000019/
A104: F53 | B104: cfo TTM to 2026-06-30 | C104: 5121000000
A105: F54 | B105: cfo quarter 2026-01-01 to 2026-03-31 | C105: 1199000000 | D105: https://www.sec.gov/Archives/edgar/data/1692819/000169281926000014/
A106: F55 | B106: capex FY ending 2023-12-31 (us-gaap:PaymentsToAcquirePropertyPlantAndEquipment) | C106: 1676000000 | D106: https://www.sec.gov/Archives/edgar/data/1692819/000169281926000006/
A107: F56 | B107: capex FY ending 2024-12-31 (us-gaap:PaymentsToAcquirePropertyPlantAndEquipment) | C107: 2078000000 | D107: https://www.sec.gov/Archives/edgar/data/1692819/000169281926000006/
A108: F57 | B108: capex FY ending 2025-12-31 (us-gaap:PaymentsToAcquirePropertyPlantAndEquipment) | C108: 2752000000 | D108: https://www.sec.gov/Archives/edgar/data/1692819/000169281926000006/
A109: F58 | B109: capex YTD 2026-01-01 to 2026-06-30 | C109: 1572000000 | D109: https://www.sec.gov/Archives/edgar/data/1692819/000169281926000019/
A110: F59 | B110: capex prior-year YTD 2025-01-01 to 2025-06-30 | C110: 1458000000 | D110: https://www.sec.gov/Archives/edgar/data/1692819/000169281926000019/
A111: F60 | B111: capex TTM to 2026-06-30 | C111: 2866000000
A112: F61 | B112: capex quarter 2026-01-01 to 2026-03-31 | C112: 883000000 | D112: https://www.sec.gov/Archives/edgar/data/1692819/000169281926000014/
A113: F62 | B113: buybacks FY ending 2023-12-31 (us-gaap:PaymentsForRepurchaseOfCommonStock) | C113: 1245000000 | D113: https://www.sec.gov/Archives/edgar/data/1692819/000169281926000006/
A114: F63 | B114: buybacks FY ending 2024-12-31 (us-gaap:PaymentsForRepurchaseOfCommonStock) | C114: 1266000000 | D114: https://www.sec.gov/Archives/edgar/data/1692819/000169281926000006/
A115: F64 | B115: buybacks FY ending 2025-12-31 (us-gaap:PaymentsForRepurchaseOfCommonStock) | C115: 1028000000 | D115: https://www.sec.gov/Archives/edgar/data/1692819/000169281926000006/
...
