Workbook

Sheet Summary
A1: AVGO standard model (trial) · research run 2026-10-29
A2: The supervisor's reconciled assumption set as a live model. Trial: shown beside the blended page target, not used for trade levels until its weight is decided. Edit blue cells on Model (drivers) and Valuation (assumptions).
A3: Price target box | B3: Value
A4: Live price | B4: =IFERROR(GOOGLEFINANCE("AVGO","price"),Valuation!$B$66)
A5: Price as of | B5: =NOW()
A6: Model target (12-month median) | B6: =Distribution!$B$13
A7: Upside to model target from live price | B7: =B6/B4-1
A8: Research target (12m) (no scenario deltas) | B8: =Valuation!$D$6
A9: Mean | B9: =Distribution!$B$10
A10: 10th percentile | B10: =Distribution!$B$14
A11: 25th percentile | B11: =Distribution!$B$15
A12: 75th percentile | B12: =Distribution!$B$16
A13: 90th percentile | B13: =Distribution!$B$17
A14: Target date | B14: =Valuation!$B$44
A15: Price at the run | B15: =Valuation!$B$66
A16: Blended page target (options 67% + agents 33%, not live) | B16: 399.2003
A17: Supervisor research target (12m) (its own methods) | B17: 488.51
A18: Thesis break price (supervisor) | B18: 260
A19: Supervisor confidence | B19: low
A21: Key estimates | B21: FY2025A | C21: =Model!E5 | D21: =Model!F5
A22: Net sales | B22: =IF(Model!D24="","",Model!D24) | C22: =Model!E24 | D22: =Model!F24
A23: % YoY | B23: =IF(Model!D25="","",Model!D25) | C23: =Model!E25 | D23: =Model!F25
A24: Pretax margin | B24: =IF(Model!D35="","",Model!D35) | C24: =Model!E35 | D24: =Model!F35
A25: Diluted EPS (model) | B25: =IF(Model!D42="","",Model!D42) | C25: =Model!E42 | D25: =Model!F42
A26: % YoY | B26: =IF(Model!D43="","",Model!D43) | C26: =Model!E43 | D26: =Model!F43
A27: Free cash flow to firm | B27: =IF(Model!D52="","",Model!D52) | C27: =Model!E52 | D27: =Model!F52
A28: Consensus: EPS () | D28: 17.45
A30: Valuation method | B30: Value per share | C30: Weight
A31: =Valuation!A4 | B31: =Valuation!D4 | C31: =Valuation!E4
A33: Case | B33: Percentile | C33: Value at target date | D33: What has to happen
A34: =Distribution!A4 | B34: =Distribution!B4 | C34: =Distribution!C4 | D34: =Distribution!D4
A35: =Distribution!A5 | B35: =Distribution!B5 | C35: =Distribution!C5 | D35: =Distribution!D5
A36: =Distribution!A6 | B36: =Distribution!B6 | C36: =Distribution!C6 | D36: =Distribution!D6
A38: Price at target date | B38: Probability above
A39: =ROUND(Valuation!$B$66*0.7,0) | B39: =1-NORMSDIST(LN(A39/Distribution!$C$5)/IF(A39<Distribution!$C$5,MAX(Distribution!$B$8,0.02),MAX(Distribution!$B$9,0.02)))
A40: =ROUND(Valuation!$B$66*0.8,0) | B40: =1-NORMSDIST(LN(A40/Distribution!$C$5)/IF(A40<Distribution!$C$5,MAX(Distribution!$B$8,0.02),MAX(Distribution!$B$9,0.02)))
A41: =ROUND(Valuation!$B$66*0.9,0) | B41: =1-NORMSDIST(LN(A41/Distribution!$C$5)/IF(A41<Distribution!$C$5,MAX(Distribution!$B$8,0.02),MAX(Distribution!$B$9,0.02)))
A42: =ROUND(Valuation!$B$66*1.0,0) | B42: =1-NORMSDIST(LN(A42/Distribution!$C$5)/IF(A42<Distribution!$C$5,MAX(Distribution!$B$8,0.02),MAX(Distribution!$B$9,0.02)))
A43: =ROUND(Valuation!$B$66*1.1,0) | B43: =1-NORMSDIST(LN(A43/Distribution!$C$5)/IF(A43<Distribution!$C$5,MAX(Distribution!$B$8,0.02),MAX(Distribution!$B$9,0.02)))
A44: =ROUND(Valuation!$B$66*1.2,0) | B44: =1-NORMSDIST(LN(A44/Distribution!$C$5)/IF(A44<Distribution!$C$5,MAX(Distribution!$B$8,0.02),MAX(Distribution!$B$9,0.02)))
A45: =ROUND(Valuation!$B$66*1.3,0) | B45: =1-NORMSDIST(LN(A45/Distribution!$C$5)/IF(A45<Distribution!$C$5,MAX(Distribution!$B$8,0.02),MAX(Distribution!$B$9,0.02)))
A46: =ROUND(Valuation!$B$66*1.5,0) | B46: =1-NORMSDIST(LN(A46/Distribution!$C$5)/IF(A46<Distribution!$C$5,MAX(Distribution!$B$8,0.02),MAX(Distribution!$B$9,0.02)))
A48: Model checks | B48: Status
A49: Downside below base and upside above base | B49: =IF(AND(Distribution!C8="",Distribution!C9=""),"ok","FLAG")
A50: Projection runs a full year past the target date | B50: =IF('Calc - research target (12m)'!B56="ok","ok","FLAG")
A51: Method weights add up to more than zero | B51: =IF(SUM(Valuation!E4:E5)>0,"ok","FLAG")
A52: Segment base revenues tie to the last reported net sales (within 2%) | B52: =IF(ABS(Valuation!$B$88/Valuation!$B$49-1)<=0.02,"ok","FLAG")
A53: Matches the engine run at publication (target, research target (12m)) | B53: =IF(AND(ABS(Distribution!$B$13-490.1005)<0.01,ABS(Valuation!$D$6-490.1005)<0.01),"ok","inputs edited since publication")
A54: All checks | B54: =IF(COUNTIF(B49:B53,"ok")=5,"all ok",5-COUNTIF(B49:B53,"ok")&" to look at")

Sheet Model
A1: AVGO: annual model, base case
A2: (M of US dollars except per share; fiscal years named by the calendar year they end in)
A3: Blue = input · black = formula · green = link to another tab · actuals from SEC filings (fact ids in the last column, links on Sources)
A5: Fiscal year | B5: FY2023A | C5: FY2024A | D5: FY2025A | E5: FY2026E | F5: FY2027E | G5: FY2028E | H5: Source / note
A6: Period end | B6: 45228 | C6: 45599 | D6: 45963 | E6: =IF(DAY(Valuation!$B$48+1)=1,EOMONTH(Valuation!$B$48,12*E7),EDATE(Valuation!$B$48,12*E7)) | F6: =IF(DAY(Valuation!$B$48+1)=1,EOMONTH(Valuation!$B$48,12*F7),EDATE(Valuation!$B$48,12*F7)) | G6: =IF(DAY(Valuation!$B$48+1)=1,EOMONTH(Valuation!$B$48,12*G7),EDATE(Valuation!$B$48,12*G7))
A7: Projection year | B7: -2 | C7: -1 | D7: 0 | E7: 1 | F7: 2 | G7: 3
A10: Segment build (blue = input: revenue growth and EBIT margin by segment and year)
A11: Semiconductor solutions | D11: =Valuation!$B$86 | E11: =Valuation!$B$86*(1+E12) | F11: =E11*(1+F12) | G11: =F11*(1+G12)
A12: Revenue growth | E12: 1.0284063 | F12: 0.77515616 | G12: 0.61055939
A13: Segment EBIT | E13: =E11*E14 | F13: =F11*F14 | G13: =G11*G14
A14: EBIT margin | E14: 0.61020589 | F14: 0.58905924 | G14: 0.57460851
A15: Infrastructure software | D15: =Valuation!$B$87 | E15: =Valuation!$B$87*(1+E16) | F15: =E15*(1+F16) | G15: =F15*(1+G16)
A16: Revenue growth | E16: 0.16452699 | F16: 0.14430042 | G16: 0.040007774
A17: Segment EBIT | E17: =E15*E18 | F17: =F15*F18 | G17: =G15*G18
A18: EBIT margin | E18: 0.8133578 | F18: 0.835 | G18: 0.835
A19: Total segment revenue (= net sales) | D19: =D11+D15 | E19: =E11+E15 | F19: =F11+F15 | G19: =G11+G15 | H19: base revenues on Valuation (segment build); net sales = this total
A20: Total segment EBIT | E20: =E13+E17 | F20: =F13+F17 | G20: =G13+G17
A21: Corporate / unallocated EBIT (blue = input) | E21: -8387 | F21: -9000 | G21: -9800 | H21: years[].corporate_ebit; EBIT = total segment EBIT + corporate
A23: Sales
A24: Net sales | B24: 35819 | C24: 51574 | D24: 63887 | E24: =E19 | F24: =F19 | G24: =G19 | H24: SEC XBRL F1, F2, F3
A25: % YoY | C25: =IF(OR(C24="",B24="",B24=0),"",C24/B24-1) | D25: =IF(OR(D24="",C24="",C24=0),"",D24/C24-1) | E25: =E24/Valuation!$B$49-1 | F25: =F24/E24-1 | G25: =G24/F24-1
A27: Operating profit
A28: EBIT (operating income) | E28: =E20+E21 | F28: =F20+F21 | G28: =G20+G21
A29: EBIT margin | E29: =E28/E24 | F29: =F28/F24 | G29: =G28/G24
A30: D&A | E30: =E24*E64 | F30: =F24*F64 | G30: =G24*G64
A31: EBITDA | E31: =E28+E30 | F31: =F28+F30 | G31: =G28+G30
A32: EBITDA margin | E32: =E31/E24 | F32: =F31/F24 | G32: =G31/G24
A33: Net interest income / (expense) | E33: =-Valuation!$B$57*Valuation!$B$55 | F33: =-Valuation!$B$57*E58 | G33: =-Valuation!$B$57*F58 | H33: rate x prior year-end net debt (memo roll)
A34: Pretax income | B34: 15097 | C34: 9916 | D34: 22729 | E34: =E28+E33 | F34: =F28+F33 | G34: =G28+G33 | H34: SEC XBRL F76, F77, F78
A35: Pretax margin | B35: =B34/B24 | C35: =C34/C24 | D35: =D34/D24 | E35: =E34/E24 | F35: =F34/F24 | G35: =G34/G24
A36: Income tax | B36: 1015 | C36: 3748 | D36: -397 | E36: =E34*E63 | F36: =F34*F63 | G36: =G34*G63 | H36: SEC XBRL F69, F70, F71
A37: Effective tax rate | B37: =B36/B34 | C37: =C36/C34 | D37: =D36/D34 | E37: =E36/E34 | F37: =F36/F34 | G37: =G36/G34
A38: Net income | B38: 14082 | C38: 5895 | D38: 23126 | E38: =E34-E36 | F38: =F34-F36 | G38: =G34-G36 | H38: SEC XBRL F15, F16, F17
A39: % YoY | C39: =IF(OR(C38="",B38="",B38=0),"",C38/B38-1) | D39: =IF(OR(D38="",C38="",C38=0),"",D38/C38-1) | E39: =IF(OR(D38="",D38=0),"",E38/D38-1) | F39: =IF(OR(E38="",E38=0),"",F38/E38-1) | G39: =IF(OR(F38="",F38=0),"",G38/F38-1)
A40: Diluted shares (M, average) | B40: 4272 | C40: 4778 | D40: 4853 | E40: =Valuation!$B$59*(1+Valuation!$B$61)^(E7-0.5-((Valuation!$B$60-Valuation!$B$48)/365.25)) | F40: =Valuation!$B$59*(1+Valuation!$B$61)^(F7-0.5-((Valuation!$B$60-Valuation!$B$48)/365.25)) | G40: =Valuation!$B$59*(1+Valuation!$B$61)^(G7-0.5-((Valuation!$B$60-Valuation!$B$48)/365.25)) | H40: diluted count rolled at the annual change to mid-year
A41: % YoY | C41: =IF(OR(C40="",B40="",B40=0),"",C40/B40-1) | D41: =IF(OR(D40="",C40="",C40=0),"",D40/C40-1) | E41: =IF(OR(D40="",D40=0),"",E40/D40-1) | F41: =IF(OR(E40="",E40=0),"",F40/E40-1) | G41: =IF(OR(F40="",F40=0),"",G40/F40-1)
A42: Diluted EPS | B42: 3.3 | C42: 1.23 | D42: 4.77 | E42: =E38/E40 | F42: =F38/F40 | G42: =G38/G40 | H42: SEC XBRL F22, F23, F24
A43: % YoY | C43: =IF(OR(C42="",B42="",B42=0),"",C42/B42-1) | D43: =IF(OR(D42="",C42="",C42=0),"",D42/C42-1) | E43: =IF(OR(D42="",D42=0),"",E42/D42-1) | F43: =IF(OR(E42="",E42=0),"",F42/E42-1) | G43: =IF(OR(F42="",F42=0),"",G42/F42-1)
A45: Cash flow
A46: NOPAT (EBIT x (1 - tax)) | E46: =E28*(1-E63) | F46: =F28*(1-F63) | G46: =G28*(1-G63)
A47: + D&A | B47: =B30 | C47: =C30 | D47: =D30 | E47: =E30 | F47: =F30 | G47: =G30
A48: - Capex | B48: 452 | C48: 548 | D48: 623 | E48: =E24*E65 | F48: =F24*F65 | G48: =G24*G65 | H48: SEC XBRL F48, F49, F50
A49: Capex % of sales | B49: =B48/B24 | C49: =C48/C24 | D49: =D48/D24 | E49: =E48/E24 | F49: =F48/F24 | G49: =G48/G24
A50: - Working capital increase | E50: =E66*(E24-Valuation!$B$49) | F50: =F66*(F24-E24) | G50: =G66*(G24-F24)
A51: - Stock comp (adjusted EBIT only) | E51: =IF(AND(Valuation!$B$46="adjusted",Valuation!$B$47="cost"),E55*(1-E63),0) | F51: =IF(AND(Valuation!$B$46="adjusted",Valuation!$B$47="cost"),F55*(1-F63),0) | G51: =IF(AND(Valuation!$B$46="adjusted",Valuation!$B$47="cost"),G55*(1-G63),0)
A52: Free cash flow to firm | E52: =E46+E47-E48-E50-E51 | F52: =F46+F47-F48-F50-F51 | G52: =G46+G47-G48-G50-G51 | H52: what the DCF discounts (Calc tabs)
A53: Operating cash flow (reported) | B53: 18085 | C53: 19962 | D53: 27537 | H53: SEC XBRL F41, F42, F43
A54: FCF (operating cash flow - capex) | B54: =B53-B48 | C54: =C53-C48 | D54: =D53-D48
A55: Stock comp (memo) | B55: 2171 | C55: 5741 | D55: 7568 | E55: =E24*E67 | F55: =F24*F67 | G55: =G24*G67 | H55: SEC XBRL F34, F35, F36
A56: Buybacks + dividends + other uses | B56: 13469 | C56: 16990 | D56: 13592 | E56: =E24*E69+E68+E70 | F56: =F24*F69+F68+F70 | G56: =G24*G69+G68+G70 | H56: SEC XBRL F55, F62, F56, F63, F57, F64
A57: % of sales | B57: =B56/B24 | C57: =C56/C24 | D57: =D56/D24 | E57: =E56/E24 | F57: =F56/F24 | G57: =G56/G24
A58: Net debt / (net cash), year end (memo) | E58: =Valuation!$B$55-E52-E33*(1-E63)+E56 | F58: =E58-F52-F33*(1-F63)+F56 | G58: =F58-G52-G33*(1-G63)+G56 | H58: rolled from the balance-date figure; feeds interest only
A60: Drivers (blue = input; a year left black carries the prior year)
A61: Revenue growth | C61: =C25 | D61: =D25 | E61: =E25 | F61: =F25 | G61: =G25 | H61: implied by the segment build (edit the segment rows)
A62: EBIT margin | E62: =E29 | F62: =F29 | G62: =G29 | H62: implied by the segment build and corporate EBIT
A63: Tax rate | B63: =B37 | C63: =C37 | D63: =D37 | E63: 0.16 | F63: =E63 | G63: =F63
A64: D&A % revenue | B64: =B30/B24 | C64: =C30/C24 | D64: =D30/D24 | E64: 0.006 | F64: =E64 | G64: =F64
A65: Capex % revenue | B65: =B49 | C65: =C49 | D65: =D49 | E65: 0.023 | F65: 0.015 | G65: 0.01
A66: Working capital % of revenue increase | E66: 0.12 | F66: =E66 | G66: =F66
A67: Stock comp % revenue | B67: =B55/B24 | C67: =C55/C24 | D67: =D55/D24 | E67: 0.08 | F67: =E67 | G67: =F67
A68: Shareholder returns ($) | E68: 12420 | F68: 14330 | G68: 15420
A69: Shareholder returns % revenue | B69: =B57 | C69: =C57 | D69: =D57 | E69: 0 | F69: =E69 | G69: =F69
A70: Other uses of cash ($: M&A, investments) | E70: 0 | F70: =E70 | G70: =F70
A71: Adj. EBITDA addback % revenue | E71: 0 | F71: =E71 | G71: =F71
A73: Versus company guidance and street consensus
A74: Guidance: AI semiconductor revenue (company figure ($M)), midpoint | F74: =AVERAGE(115000.0,115000.0) | H74: 1.15e+05 to 1.15e+05; as of 2026-09-02; source 37, 38 (Broadcom Q3 FY26 earnings call transcript (Benzinga via Webu)
A75: Guidance: AI semiconductor revenue (company figure ($M); 'line of sight', not formal guidance), midpoint | G75: =AVERAGE(230000.0,230000.0) | H75: 2.3e+05 to 2.3e+05; as of 2026-09-02; source 37, 38 (Broadcom Q3 FY26 earnings call transcript (Benzinga via Webu)
A76: Guidance: EPS diluted (non-GAAP (excludes stock comp, acquired-intangible amortization and other non-GAAP items)), midpoint | G76: 30 | H76: as of 2026-09-02; source 37, 38 (Broadcom Q3 FY26 earnings call transcript (Benzinga via Webu)
A77: Model vs guidance midpoint | G77: =G42/G76-1
A78: Guidance: tax rate (non-GAAP), midpoint | E78: =AVERAGE(0.16,0.16) | H78: 0.16 to 0.16; as of 2026-09-02; source 37 (Broadcom Q3 FY26 earnings call transcript (Benzinga via Webu)
A79: Model vs guidance midpoint | E79: =(E37-E78)*10000 | H79: =IF(E37<0.16,"below the guided range",IF(E37>0.16,"above the guided range","inside the guided range"))
A80: Consensus: EPS (Zacks) () | F80: 17.45 | H80: as of 2026-10-30; source 69 (Nasdaq.com analyst earnings forecast (Zacks consensus EPS, S)
A81: Consensus: EPS (Zacks) () | G81: 28.08 | H81: as of 2026-10-30; source 69 (Nasdaq.com analyst earnings forecast (Zacks consensus EPS, S)

Sheet Quarters
A1: AVGO quarter build (engine values: model_engine.quarter_rows; fiscal years on Model are the sums)
A2: Actual quarters are as reported (filings / XBRL); forecast quarters come from the drivers below through driver_build.quarters.
A4: Line item | B4: Q1 FY2026 | C4: Q2 FY2026 | D4: Q3 FY2026 | E4: Q4 FY2026 | F4: Q1 FY2027 | G4: Q2 FY2027 | H4: Q3 FY2027 | I4: Q4 FY2027 | J4: Q1 FY2028 | K4: Q2 FY2028 | L4: Q3 FY2028 | M4: Q4 FY2028
A5: Reported / forecast | B5: actual | C5: actual | D5: actual | E5: forecast | F5: forecast | G5: forecast | H5: forecast | I5: forecast | J5: forecast | K5: forecast | L5: forecast | M5: forecast
A6: Quarter end | B6: 46054 | C6: 46145 | D6: 46236 | E6: 46327 | F6: 46418 | G6: 46509 | H6: 46600 | I6: 46691 | J6: 46782 | K6: 46873 | L6: 46964 | M6: 47055
A7: Semiconductor solutions: revenue | B7: 12515 | C7: 15009 | D7: 20839 | E7: 26400 | F7: 28850 | G7: 31900 | H7: 33950 | I7: 38016 | J7: 44500 | K7: 50540 | L7: 56580 | M7: 62127
A8: Semiconductor solutions: EBIT | B8: 7503 | C8: 9281 | D8: 12770 | E8: 16066.82 | F8: 17259.49 | G8: 18895.58 | H8: 19940.41 | I8: 22082.1 | J8: 25775.32 | K8: 29093.05 | L8: 32451.5 | M8: 35500.97
A9: Infrastructure software: revenue | B9: 6796 | C9: 7178 | D9: 8752 | E9: 8750 | F9: 8850 | G9: 8950 | H9: 9050 | I9: 9168 | J9: 9250 | K9: 9320 | L9: 9400 | M9: 9489
A10: Infrastructure software: EBIT | B10: 5323 | C10: 5647 | D10: 7325 | E10: 7306.25 | F10: 7389.75 | G10: 7473.25 | H10: 7556.75 | I10: 7655.28 | J10: 7723.75 | K10: 7782.2 | L10: 7849 | M10: 7923.31
A11: Revenue | B11: 19311 | C11: 22187 | D11: 29591 | E11: 35150 | F11: 37700 | G11: 40850 | H11: 43000 | I11: 47184 | J11: 53750 | K11: 59860 | L11: 65980 | M11: 71616
A12: EBIT | B12: 10650 | C12: 12836 | D12: 18076 | E12: 21273.073 | F12: 22399.242 | G12: 24118.83 | H12: 25247.16 | I12: 27487.384 | J12: 31049.07 | K12: 34425.25 | L12: 37850.5 | M12: 40974.29
A13: EBIT margin | B13: 0.55149915 | C13: 0.57853698 | D13: 0.61086141 | E13: 0.60520834 | F13: 0.59414435 | G13: 0.59042424 | H13: 0.58714326 | I13: 0.58255731 | J13: 0.57765712 | K13: 0.57509606 | L13: 0.57366626 | M13: 0.57213877
A14: D&A | B14: 115.866 | C14: 133.122 | D14: 177.546 | E14: 210.9 | F14: 226.2 | G14: 245.1 | H14: 258 | I14: 283.104 | J14: 322.5 | K14: 359.16 | L14: 395.88 | M14: 429.696
A15: Capex | B15: 444.153 | C15: 510.301 | D15: 680.593 | E15: 808.45 | F15: 565.5 | G15: 612.75 | H15: 645 | I15: 707.76 | J15: 537.5 | K15: 598.6 | L15: 659.8 | M15: 716.16
A16: Stock comp | B16: 1544.88 | C16: 1774.96 | D16: 2367.28 | E16: 2812 | F16: 3016 | G16: 3268 | H16: 3440 | I16: 3774.72 | J16: 4300 | K16: 4788.8 | L16: 5278.4 | M16: 5729.28
A17: Free cash flow to firm | B17: 7693.9173 | C17: 9343.6837 | D17: 13265.225 | E17: 15590.333 | F17: 16800.483 | G17: 18076.585 | H17: 18909.475 | I17: 20567.649 | J17: 23748.656 | K17: 26319.495 | L17: 28931.118 | M17: 31310.519
A18: Model EPS (EBIT - interest, model tax and shares) | B18: 1.7496 | C18: 2.1213 | D18: 3.0123 | E18: 3.556 | F18: 3.7475 | G18: 4.0399 | H18: 4.2317 | I18: 4.6126 | J18: 5.2183 | K18: 5.7924 | L18: 6.3748 | M18: 6.906
A20: Drivers by quarter
A21: AI semiconductor revenue (custom XPUs + ($M per quarter, sum) | B21: 8400 | C21: 10800 | D21: 16700 | E21: 22100 | F21: 24500 | G21: 27500 | H21: 29500 | I21: 33500 | J21: 40000 | K21: 46000 | L21: 52000 | M21: 57500
A22: Custom XPU share of AI semiconductor rev (fraction, wmean:ai_rev) | B22: 0.6667 | C22: 0.61 | D22: 0.73 | E22: 0.72 | F22: 0.72 | G22: 0.73 | H22: 0.73 | I22: 0.74 | J22: 0.74 | K22: 0.75 | L22: 0.75 | M22: 0.75
A23: Custom XPU operating margin (non-GAAP, b (fraction, wmean:ai_rev*xpu_share) | B23: 0.5757 | C23: 0.597 | D23: 0.5945 | E23: 0.5811 | F23: 0.5628 | G23: 0.5544 | H23: 0.546 | I23: 0.5376 | J23: 0.5342 | K23: 0.5309 | L23: 0.5275 | M23: 0.5242
A24: Infrastructure software revenue (VMware ($M per quarter, sum) | B24: 6796 | C24: 7178 | D24: 8752 | E24: 8750 | F24: 8850 | G24: 8950 | H24: 9050 | I24: 9168 | J24: 9250 | K24: 9320 | L24: 9400 | M24: 9489
A25: Customer-financing exposure backed by Br ($M (stock, quarter-end), end) | B25: 0 | C25: 0 | D25: 49700 | E25: 79800 | F25: 79800 | G25: 94500 | H25: 94500 | I25: 94500 | J25: 94500 | K25: 105700 | L25: 105700 | M25: 105700
A26: Lifetime expected loss rate on Broadcom- (fraction of exposure, mean) | B26: 0.04321 | C26: 0.04321 | D26: 0.04321 | E26: 0.04321 | F26: 0.04321 | G26: 0.04321 | H26: 0.04321 | I26: 0.04321 | J26: 0.04321 | K26: 0.04321 | L26: 0.04321 | M26: 0.04321

Sheet Valuation
A1: AVGO: valuation and price target derivation
A2: Value per share at the target date = weighted methods below; the base case is the 12-month median, with the downside and upside cases as its 10th and 90th percentiles (Distribution tab).
A3: Method | B3: Multiple | C3: Metric at target date | D3: Value per share | E3: Weight | F3: Contribution
A4: ='Calc - research target (12m)'!A68 | B4: =IF('Calc - research target (12m)'!C68="","",'Calc - research target (12m)'!C68) | C4: =IF('Calc - research target (12m)'!I68="","",'Calc - research target (12m)'!I68) | D4: ='Calc - research target (12m)'!F68 | E4: ='Calc - research target (12m)'!G68 | F4: =D4*E4/SUM($E$4:$E$5)
A6: Research target (12m) per share | D6: ='Calc - research target (12m)'!$F$69 | F6: =SUM(F4:F5)
A8: 12-month EPS basis (what the P/E is applied to)
A9: Fiscal year | B9: =Model!E5 | C9: =Model!F5 | D9: =Model!G5
A10: Share of the 12 months after the target date | B10: ='Calc - research target (12m)'!C38 | C10: ='Calc - research target (12m)'!D38 | D10: ='Calc - research target (12m)'!E38
A11: Model EPS (Model tab) | B11: =Model!E42 | C11: =Model!F42 | D11: =Model!G42
A12: Model EPS, next 12 months after the target date | B12: =SUMPRODUCT(B10:D10,B11:D11)
A15: No DCF leg for this name (DCF weight 0), so no DCF build.
A41: Assumptions (blue = input; sources on the Sources tab)
A42: Input | B42: Value | C42: Basis / note
A43: Run date (valuation as of) | B43: 46324
A44: Target date (run date + 365 days) | B44: =B43+365 | C44: 12-month horizon
A45: Money unit | B45: $M
A46: EBIT basis (gaap / adjusted) | B46: gaap | C46: gaap = after stock comp
A47: Stock comp treatment (cost / dilution) | B47: cost | C47: used only when EBIT is adjusted
A48: Last reported fiscal year end | B48: 45963
A49: Net sales, last reported year ($M) | B49: 63887
A50: WACC | B50: 0.1 | C50: not used: no DCF leg (Kilian 2026-10-21); a placeholder so the DCF block still computes
A51: Terminal method (gordon / exit_multiple / steady_state) | B51: gordon
A52: Terminal growth | B52: 0.02
A53: Exit EV/EBITDA (exit_multiple only)
A54: Balance-sheet date | B54: 46236
A55: Net debt / (net cash) at balance date ($M) | B55: 35444 | C55: excludes operating leases
A56: Minority interests + preferred stock | B56: 0
A57: Interest rate on net debt / cash | B57: 0.0407
A58: Net debt at target date (override; blank = bridge)
A59: Diluted shares (M) | B59: 4940
A60: Share count date | B60: 46236
A61: Annual change in diluted shares | B61: 0 | C61: net of buybacks and stock-comp dilution
A62: Shares at target date (override; blank = from annual change)
A63: DCF weight | B63: 0 | C63: Kilian 2026-10-21: 0 unless the name has a DCF leg (dcf_policy)
A64: Sum-of-the-parts weight | B64: 0
A65: Spread on a side with no downside/upside case (lognormal vol) | B65: 0.313
A66: Share price at the run | B66: 345 | C66: close used by the run (2026-10-29)
A68: Target multiple | B68: Multiple | C68: Weight | D68: Basis (ntm / ltm) | E68: EBITDA basis | F68: Stated EPS | G68: Stated FCF/share | H68: Levered | I68: Peer basis
A69: P/E | B69: 19.81 | C69: 1 | D69: ntm | E69: gaap | H69: TRUE | I69: AVGO's own calendar-NTM P/E 19.81x (Zacks consensus, SBC kept as a cost, 2026-10-29 close), Kilian 2026-10-30 17:18Z: the exit rule's 21.9x is too high because the faster-growing peers skew the 8-peer median (32.73x: NVDA AMD MRVL TSM ANET CRDO ALAB COHR). Was 19x on non-GAAP ex-SBC EPS (Oct 6 set).
A71: Segment (sum of the parts) | B71: NTM metric | C71: Metric | D71: Multiple | E71: Note
A72: none
A74: Adjustment (equity level) | B74: Value | C74: Probability | D74: Note
A75: Customer-financing exposure: expected loss (cf_exposure x cf_loss_rate) | B75: -4567.297 | C75: 1 | D75: Driven: -cf_exposure (FY2028 year-end, probability-weighted utilised) x cf_loss_rate. Same five deals as before (10-Q Backstop, Anthropic $42B notes, Oct 27 2026 SPV Backstop, OpenAI package, future XPV backstops).
A76: Legal and regulatory: VMware EU abuse-of-dominance complaints and licensing suits, probability-weighted (AVGO deep model 2026-10-20) | B76: -1250 | C76: 1 | D76: Labelled estimate, low confidence. EU: p 0.25 of a fine of ~$3.0B (about 3% of FY26 revenue; the cap is 10% of turnover) = -$750M; customer and partner licensing suits and settlements -$500M (judgment). The 10-Q accrues nothing and says losses are not probable or estimable.
A78: Custom method | B78: Value per share | C78: Weight | D78: Explanation
A79: none
A81: Case | B81: Percentile | C81: Growth Δ | D81: Margin Δ | E81: Multiple Δ (turns) | F81: WACC Δ | G81: Multiple %Δ (FCF yield, segments) | H81: Stated EPS/FCF %Δ | I81: Custom methods %Δ | J81: Story
A82: downside | B82: 0.1 | E82: -4 | J82: AI air pocket: lab financing or power slips; AI revenue 35% below the base path in every forecast quarter (FY27 ~$75-80B run-rate exit, FY28 ~$127B vs $195.5B; base round bear FY28 flat at $115B), XPU margin -3pt (AI margin ~-2.5pt at a 75% XPU share) on opex deleverage, P/E -4 turns. The downside customer-financing loss is in the unconditional adjustment, not in this delta. | K82: driver deltas: ai_rev -0.35 %; xpu_margin -0.03
A83: upside | B83: 0.9 | E83: 2 | J83: Management's line of sight: FY28 AI ~$225-230B (all 20 GW), FY27 ~$120B+; XPU margin -0.7pt (AI ~-0.5pt) on rack mix; P/E +2 turns. | K83: driver deltas: ai_rev +0.15 %; xpu_margin -0.007
A85: Segment build (segment_build) | B85: Base revenue ($M) | C85: Driver note (growth and EBIT margin by year: Model tab)
A86: Semiconductor solutions | B86: 36858
A87: Infrastructure software | B87: 27029
A88: Sum of segment base revenues | B88: =SUM(B86:B87) | C88: =IF(ABS(B88/Valuation!$B$49-1)<=0.02,"ties to the last reported net sales (within 2%)","FLAG: does not tie to the last reported net sales")

Sheet Sensitivity
A1: AVGO: sensitivity tables (bold = current inputs; every cell recalculates from the live model)
A3: No DCF leg for this name (DCF weight 0), so no DCF sensitivity.
A11: Research target (12m) per share: P/E multiple (down) x metric at target date (across)
A12: Multiple \ metric | B12: ='Calc - research target (12m)'!$E$68*0.9 | C12: ='Calc - research target (12m)'!$E$68*0.95 | D12: ='Calc - research target (12m)'!$E$68*1.0 | E12: ='Calc - research target (12m)'!$E$68*1.05 | F12: ='Calc - research target (12m)'!$E$68*1.1
A13: =Valuation!$B$69+(-3) | B13: =((SUMPRODUCT('Calc - research target (12m)'!$F$67:$F$68,'Calc - research target (12m)'!$G$67:$G$68)-'Calc - research target (12m)'!$F$68*'Calc - research target (12m)'!$G$68)+'Calc - research target (12m)'!$G$68*($A13*(B$12-'Calc - research target (12m)'!$B$54)/'Calc - research target (12m)'!$B$53+'Calc - research target (12m)'!$B$52/'Calc - research target (12m)'!$B$53))/SUM('Calc - research target (12m)'!$G$67:$G$68) | C13: =((SUMPRODUCT('Calc - research target (12m)'!$F$67:$F$68,'Calc - research target (12m)'!$G$67:$G$68)-'Calc - research target (12m)'!$F$68*'Calc - research target (12m)'!$G$68)+'Calc - research target (12m)'!$G$68*($A13*(C$12-'Calc - research target (12m)'!$B$54)/'Calc - research target (12m)'!$B$53+'Calc - research target (12m)'!$B$52/'Calc - research target (12m)'!$B$53))/SUM('Calc - research target (12m)'!$G$67:$G$68) | D13: =((SUMPRODUCT('Calc - research target (12m)'!$F$67:$F$68,'Calc - research target (12m)'!$G$67:$G$68)-'Calc - research target (12m)'!$F$68*'Calc - research target (12m)'!$G$68)+'Calc - research target (12m)'!$G$68*($A13*(D$12-'Calc - research target (12m)'!$B$54)/'Calc - research target (12m)'!$B$53+'Calc - research target (12m)'!$B$52/'Calc - research target (12m)'!$B$53))/SUM('Calc - research target (12m)'!$G$67:$G$68) | E13: =((SUMPRODUCT('Calc - research target (12m)'!$F$67:$F$68,'Calc - research target (12m)'!$G$67:$G$68)-'Calc - research target (12m)'!$F$68*'Calc - research target (12m)'!$G$68)+'Calc - research target (12m)'!$G$68*($A13*(E$12-'Calc - research target (12m)'!$B$54)/'Calc - research target (12m)'!$B$53+'Calc - research target (12m)'!$B$52/'Calc - research target (12m)'!$B$53))/SUM('Calc - research target (12m)'!$G$67:$G$68) | F13: =((SUMPRODUCT('Calc - research target (12m)'!$F$67:$F$68,'Calc - research target (12m)'!$G$67:$G$68)-'Calc - research target (12m)'!$F$68*'Calc - research target (12m)'!$G$68)+'Calc - research target (12m)'!$G$68*($A13*(F$12-'Calc - research target (12m)'!$B$54)/'Calc - research target (12m)'!$B$53+'Calc - research target (12m)'!$B$52/'Calc - research target (12m)'!$B$53))/SUM('Calc - research target (12m)'!$G$67:$G$68)
A14: =Valuation!$B$69+(-2) | B14: =((SUMPRODUCT('Calc - research target (12m)'!$F$67:$F$68,'Calc - research target (12m)'!$G$67:$G$68)-'Calc - research target (12m)'!$F$68*'Calc - research target (12m)'!$G$68)+'Calc - research target (12m)'!$G$68*($A14*(B$12-'Calc - research target (12m)'!$B$54)/'Calc - research target (12m)'!$B$53+'Calc - research target (12m)'!$B$52/'Calc - research target (12m)'!$B$53))/SUM('Calc - research target (12m)'!$G$67:$G$68) | C14: =((SUMPRODUCT('Calc - research target (12m)'!$F$67:$F$68,'Calc - research target (12m)'!$G$67:$G$68)-'Calc - research target (12m)'!$F$68*'Calc - research target (12m)'!$G$68)+'Calc - research target (12m)'!$G$68*($A14*(C$12-'Calc - research target (12m)'!$B$54)/'Calc - research target (12m)'!$B$53+'Calc - research target (12m)'!$B$52/'Calc - research target (12m)'!$B$53))/SUM('Calc - research target (12m)'!$G$67:$G$68) | D14: =((SUMPRODUCT('Calc - research target (12m)'!$F$67:$F$68,'Calc - research target (12m)'!$G$67:$G$68)-'Calc - research target (12m)'!$F$68*'Calc - research target (12m)'!$G$68)+'Calc - research target (12m)'!$G$68*($A14*(D$12-'Calc - research target (12m)'!$B$54)/'Calc - research target (12m)'!$B$53+'Calc - research target (12m)'!$B$52/'Calc - research target (12m)'!$B$53))/SUM('Calc - research target (12m)'!$G$67:$G$68) | E14: =((SUMPRODUCT('Calc - research target (12m)'!$F$67:$F$68,'Calc - research target (12m)'!$G$67:$G$68)-'Calc - research target (12m)'!$F$68*'Calc - research target (12m)'!$G$68)+'Calc - research target (12m)'!$G$68*($A14*(E$12-'Calc - research target (12m)'!$B$54)/'Calc - research target (12m)'!$B$53+'Calc - research target (12m)'!$B$52/'Calc - research target (12m)'!$B$53))/SUM('Calc - research target (12m)'!$G$67:$G$68) | F14: =((SUMPRODUCT('Calc - research target (12m)'!$F$67:$F$68,'Calc - research target (12m)'!$G$67:$G$68)-'Calc - research target (12m)'!$F$68*'Calc - research target (12m)'!$G$68)+'Calc - research target (12m)'!$G$68*($A14*(F$12-'Calc - research target (12m)'!$B$54)/'Calc - research target (12m)'!$B$53+'Calc - research target (12m)'!$B$52/'Calc - research target (12m)'!$B$53))/SUM('Calc - research target (12m)'!$G$67:$G$68)
A15: =Valuation!$B$69+(-1) | B15: =((SUMPRODUCT('Calc - research target (12m)'!$F$67:$F$68,'Calc - research target (12m)'!$G$67:$G$68)-'Calc - research target (12m)'!$F$68*'Calc - research target (12m)'!$G$68)+'Calc - research target (12m)'!$G$68*($A15*(B$12-'Calc - research target (12m)'!$B$54)/'Calc - research target (12m)'!$B$53+'Calc - research target (12m)'!$B$52/'Calc - research target (12m)'!$B$53))/SUM('Calc - research target (12m)'!$G$67:$G$68) | C15: =((SUMPRODUCT('Calc - research target (12m)'!$F$67:$F$68,'Calc - research target (12m)'!$G$67:$G$68)-'Calc - research target (12m)'!$F$68*'Calc - research target (12m)'!$G$68)+'Calc - research target (12m)'!$G$68*($A15*(C$12-'Calc - research target (12m)'!$B$54)/'Calc - research target (12m)'!$B$53+'Calc - research target (12m)'!$B$52/'Calc - research target (12m)'!$B$53))/SUM('Calc - research target (12m)'!$G$67:$G$68) | D15: =((SUMPRODUCT('Calc - research target (12m)'!$F$67:$F$68,'Calc - research target (12m)'!$G$67:$G$68)-'Calc - research target (12m)'!$F$68*'Calc - research target (12m)'!$G$68)+'Calc - research target (12m)'!$G$68*($A15*(D$12-'Calc - research target (12m)'!$B$54)/'Calc - research target (12m)'!$B$53+'Calc - research target (12m)'!$B$52/'Calc - research target (12m)'!$B$53))/SUM('Calc - research target (12m)'!$G$67:$G$68) | E15: =((SUMPRODUCT('Calc - research target (12m)'!$F$67:$F$68,'Calc - research target (12m)'!$G$67:$G$68)-'Calc - research target (12m)'!$F$68*'Calc - research target (12m)'!$G$68)+'Calc - research target (12m)'!$G$68*($A15*(E$12-'Calc - research target (12m)'!$B$54)/'Calc - research target (12m)'!$B$53+'Calc - research target (12m)'!$B$52/'Calc - research target (12m)'!$B$53))/SUM('Calc - research target (12m)'!$G$67:$G$68) | F15: =((SUMPRODUCT('Calc - research target (12m)'!$F$67:$F$68,'Calc - research target (12m)'!$G$67:$G$68)-'Calc - research target (12m)'!$F$68*'Calc - research target (12m)'!$G$68)+'Calc - research target (12m)'!$G$68*($A15*(F$12-'Calc - research target (12m)'!$B$54)/'Calc - research target (12m)'!$B$53+'Calc - research target (12m)'!$B$52/'Calc - research target (12m)'!$B$53))/SUM('Calc - research target (12m)'!$G$67:$G$68)
A16: =Valuation!$B$69+(0) | B16: =((SUMPRODUCT('Calc - research target (12m)'!$F$67:$F$68,'Calc - research target (12m)'!$G$67:$G$68)-'Calc - research target (12m)'!$F$68*'Calc - research target (12m)'!$G$68)+'Calc - research target (12m)'!$G$68*($A16*(B$12-'Calc - research target (12m)'!$B$54)/'Calc - research target (12m)'!$B$53+'Calc - research target (12m)'!$B$52/'Calc - research target (12m)'!$B$53))/SUM('Calc - research target (12m)'!$G$67:$G$68) | C16: =((SUMPRODUCT('Calc - research target (12m)'!$F$67:$F$68,'Calc - research target (12m)'!$G$67:$G$68)-'Calc - research target (12m)'!$F$68*'Calc - research target (12m)'!$G$68)+'Calc - research target (12m)'!$G$68*($A16*(C$12-'Calc - research target (12m)'!$B$54)/'Calc - research target (12m)'!$B$53+'Calc - research target (12m)'!$B$52/'Calc - research target (12m)'!$B$53))/SUM('Calc - research target (12m)'!$G$67:$G$68) | D16: =((SUMPRODUCT('Calc - research target (12m)'!$F$67:$F$68,'Calc - research target (12m)'!$G$67:$G$68)-'Calc - research target (12m)'!$F$68*'Calc - research target (12m)'!$G$68)+'Calc - research target (12m)'!$G$68*($A16*(D$12-'Calc - research target (12m)'!$B$54)/'Calc - research target (12m)'!$B$53+'Calc - research target (12m)'!$B$52/'Calc - research target (12m)'!$B$53))/SUM('Calc - research target (12m)'!$G$67:$G$68) | E16: =((SUMPRODUCT('Calc - research target (12m)'!$F$67:$F$68,'Calc - research target (12m)'!$G$67:$G$68)-'Calc - research target (12m)'!$F$68*'Calc - research target (12m)'!$G$68)+'Calc - research target (12m)'!$G$68*($A16*(E$12-'Calc - research target (12m)'!$B$54)/'Calc - research target (12m)'!$B$53+'Calc - research target (12m)'!$B$52/'Calc - research target (12m)'!$B$53))/SUM('Calc - research target (12m)'!$G$67:$G$68) | F16: =((SUMPRODUCT('Calc - research target (12m)'!$F$67:$F$68,'Calc - research target (12m)'!$G$67:$G$68)-'Calc - research target (12m)'!$F$68*'Calc - research target (12m)'!$G$68)+'Calc - research target (12m)'!$G$68*($A16*(F$12-'Calc - research target (12m)'!$B$54)/'Calc - research target (12m)'!$B$53+'Calc - research target (12m)'!$B$52/'Calc - research target (12m)'!$B$53))/SUM('Calc - research target (12m)'!$G$67:$G$68)
A17: =Valuation!$B$69+(1) | B17: =((SUMPRODUCT('Calc - research target (12m)'!$F$67:$F$68,'Calc - research target (12m)'!$G$67:$G$68)-'Calc - research target (12m)'!$F$68*'Calc - research target (12m)'!$G$68)+'Calc - research target (12m)'!$G$68*($A17*(B$12-'Calc - research target (12m)'!$B$54)/'Calc - research target (12m)'!$B$53+'Calc - research target (12m)'!$B$52/'Calc - research target (12m)'!$B$53))/SUM('Calc - research target (12m)'!$G$67:$G$68) | C17: =((SUMPRODUCT('Calc - research target (12m)'!$F$67:$F$68,'Calc - research target (12m)'!$G$67:$G$68)-'Calc - research target (12m)'!$F$68*'Calc - research target (12m)'!$G$68)+'Calc - research target (12m)'!$G$68*($A17*(C$12-'Calc - research target (12m)'!$B$54)/'Calc - research target (12m)'!$B$53+'Calc - research target (12m)'!$B$52/'Calc - research target (12m)'!$B$53))/SUM('Calc - research target (12m)'!$G$67:$G$68) | D17: =((SUMPRODUCT('Calc - research target (12m)'!$F$67:$F$68,'Calc - research target (12m)'!$G$67:$G$68)-'Calc - research target (12m)'!$F$68*'Calc - research target (12m)'!$G$68)+'Calc - research target (12m)'!$G$68*($A17*(D$12-'Calc - research target (12m)'!$B$54)/'Calc - research target (12m)'!$B$53+'Calc - research target (12m)'!$B$52/'Calc - research target (12m)'!$B$53))/SUM('Calc - research target (12m)'!$G$67:$G$68) | E17: =((SUMPRODUCT('Calc - research target (12m)'!$F$67:$F$68,'Calc - research target (12m)'!$G$67:$G$68)-'Calc - research target (12m)'!$F$68*'Calc - research target (12m)'!$G$68)+'Calc - research target (12m)'!$G$68*($A17*(E$12-'Calc - research target (12m)'!$B$54)/'Calc - research target (12m)'!$B$53+'Calc - research target (12m)'!$B$52/'Calc - research target (12m)'!$B$53))/SUM('Calc - research target (12m)'!$G$67:$G$68) | F17: =((SUMPRODUCT('Calc - research target (12m)'!$F$67:$F$68,'Calc - research target (12m)'!$G$67:$G$68)-'Calc - research target (12m)'!$F$68*'Calc - research target (12m)'!$G$68)+'Calc - research target (12m)'!$G$68*($A17*(F$12-'Calc - research target (12m)'!$B$54)/'Calc - research target (12m)'!$B$53+'Calc - research target (12m)'!$B$52/'Calc - research target (12m)'!$B$53))/SUM('Calc - research target (12m)'!$G$67:$G$68)
A18: =Valuation!$B$69+(2) | B18: =((SUMPRODUCT('Calc - research target (12m)'!$F$67:$F$68,'Calc - research target (12m)'!$G$67:$G$68)-'Calc - research target (12m)'!$F$68*'Calc - research target (12m)'!$G$68)+'Calc - research target (12m)'!$G$68*($A18*(B$12-'Calc - research target (12m)'!$B$54)/'Calc - research target (12m)'!$B$53+'Calc - research target (12m)'!$B$52/'Calc - research target (12m)'!$B$53))/SUM('Calc - research target (12m)'!$G$67:$G$68) | C18: =((SUMPRODUCT('Calc - research target (12m)'!$F$67:$F$68,'Calc - research target (12m)'!$G$67:$G$68)-'Calc - research target (12m)'!$F$68*'Calc - research target (12m)'!$G$68)+'Calc - research target (12m)'!$G$68*($A18*(C$12-'Calc - research target (12m)'!$B$54)/'Calc - research target (12m)'!$B$53+'Calc - research target (12m)'!$B$52/'Calc - research target (12m)'!$B$53))/SUM('Calc - research target (12m)'!$G$67:$G$68) | D18: =((SUMPRODUCT('Calc - research target (12m)'!$F$67:$F$68,'Calc - research target (12m)'!$G$67:$G$68)-'Calc - research target (12m)'!$F$68*'Calc - research target (12m)'!$G$68)+'Calc - research target (12m)'!$G$68*($A18*(D$12-'Calc - research target (12m)'!$B$54)/'Calc - research target (12m)'!$B$53+'Calc - research target (12m)'!$B$52/'Calc - research target (12m)'!$B$53))/SUM('Calc - research target (12m)'!$G$67:$G$68) | E18: =((SUMPRODUCT('Calc - research target (12m)'!$F$67:$F$68,'Calc - research target (12m)'!$G$67:$G$68)-'Calc - research target (12m)'!$F$68*'Calc - research target (12m)'!$G$68)+'Calc - research target (12m)'!$G$68*($A18*(E$12-'Calc - research target (12m)'!$B$54)/'Calc - research target (12m)'!$B$53+'Calc - research target (12m)'!$B$52/'Calc - research target (12m)'!$B$53))/SUM('Calc - research target (12m)'!$G$67:$G$68) | F18: =((SUMPRODUCT('Calc - research target (12m)'!$F$67:$F$68,'Calc - research target (12m)'!$G$67:$G$68)-'Calc - research target (12m)'!$F$68*'Calc - research target (12m)'!$G$68)+'Calc - research target (12m)'!$G$68*($A18*(F$12-'Calc - research target (12m)'!$B$54)/'Calc - research target (12m)'!$B$53+'Calc - research target (12m)'!$B$52/'Calc - research target (12m)'!$B$53))/SUM('Calc - research target (12m)'!$G$67:$G$68)
A19: =Valuation!$B$69+(3) | B19: =((SUMPRODUCT('Calc - research target (12m)'!$F$67:$F$68,'Calc - research target (12m)'!$G$67:$G$68)-'Calc - research target (12m)'!$F$68*'Calc - research target (12m)'!$G$68)+'Calc - research target (12m)'!$G$68*($A19*(B$12-'Calc - research target (12m)'!$B$54)/'Calc - research target (12m)'!$B$53+'Calc - research target (12m)'!$B$52/'Calc - research target (12m)'!$B$53))/SUM('Calc - research target (12m)'!$G$67:$G$68) | C19: =((SUMPRODUCT('Calc - research target (12m)'!$F$67:$F$68,'Calc - research target (12m)'!$G$67:$G$68)-'Calc - research target (12m)'!$F$68*'Calc - research target (12m)'!$G$68)+'Calc - research target (12m)'!$G$68*($A19*(C$12-'Calc - research target (12m)'!$B$54)/'Calc - research target (12m)'!$B$53+'Calc - research target (12m)'!$B$52/'Calc - research target (12m)'!$B$53))/SUM('Calc - research target (12m)'!$G$67:$G$68) | D19: =((SUMPRODUCT('Calc - research target (12m)'!$F$67:$F$68,'Calc - research target (12m)'!$G$67:$G$68)-'Calc - research target (12m)'!$F$68*'Calc - research target (12m)'!$G$68)+'Calc - research target (12m)'!$G$68*($A19*(D$12-'Calc - research target (12m)'!$B$54)/'Calc - research target (12m)'!$B$53+'Calc - research target (12m)'!$B$52/'Calc - research target (12m)'!$B$53))/SUM('Calc - research target (12m)'!$G$67:$G$68) | E19: =((SUMPRODUCT('Calc - research target (12m)'!$F$67:$F$68,'Calc - research target (12m)'!$G$67:$G$68)-'Calc - research target (12m)'!$F$68*'Calc - research target (12m)'!$G$68)+'Calc - research target (12m)'!$G$68*($A19*(E$12-'Calc - research target (12m)'!$B$54)/'Calc - research target (12m)'!$B$53+'Calc - research target (12m)'!$B$52/'Calc - research target (12m)'!$B$53))/SUM('Calc - research target (12m)'!$G$67:$G$68) | F19: =((SUMPRODUCT('Calc - research target (12m)'!$F$67:$F$68,'Calc - research target (12m)'!$G$67:$G$68)-'Calc - research target (12m)'!$F$68*'Calc - research target (12m)'!$G$68)+'Calc - research target (12m)'!$G$68*($A19*(F$12-'Calc - research target (12m)'!$B$54)/'Calc - research target (12m)'!$B$53+'Calc - research target (12m)'!$B$52/'Calc - research target (12m)'!$B$53))/SUM('Calc - research target (12m)'!$G$67:$G$68)
A22: FY2027E diluted EPS: revenue growth change in every year (down) x EBIT margin change (across)
A23: Growth Δ \ margin Δ | B23: -0.01 | C23: -0.005 | D23: 0 | E23: 0.005 | F23: 0.01
A24: -0.02 | B24: =(Valuation!$B$86*(1+Model!E12+$A24)*(1+Model!F12+$A24)*(Model!F14+B$23)+Valuation!$B$87*(1+Model!E16+$A24)*(1+Model!F16+$A24)*(Model!F18+B$23)+Model!F21+Model!F33)*(1-Model!F63)/Model!F40 | C24: =(Valuation!$B$86*(1+Model!E12+$A24)*(1+Model!F12+$A24)*(Model!F14+C$23)+Valuation!$B$87*(1+Model!E16+$A24)*(1+Model!F16+$A24)*(Model!F18+C$23)+Model!F21+Model!F33)*(1-Model!F63)/Model!F40 | D24: =(Valuation!$B$86*(1+Model!E12+$A24)*(1+Model!F12+$A24)*(Model!F14+D$23)+Valuation!$B$87*(1+Model!E16+$A24)*(1+Model!F16+$A24)*(Model!F18+D$23)+Model!F21+Model!F33)*(1-Model!F63)/Model!F40 | E24: =(Valuation!$B$86*(1+Model!E12+$A24)*(1+Model!F12+$A24)*(Model!F14+E$23)+Valuation!$B$87*(1+Model!E16+$A24)*(1+Model!F16+$A24)*(Model!F18+E$23)+Model!F21+Model!F33)*(1-Model!F63)/Model!F40 | F24: =(Valuation!$B$86*(1+Model!E12+$A24)*(1+Model!F12+$A24)*(Model!F14+F$23)+Valuation!$B$87*(1+Model!E16+$A24)*(1+Model!F16+$A24)*(Model!F18+F$23)+Model!F21+Model!F33)*(1-Model!F63)/Model!F40
A25: -0.01 | B25: =(Valuation!$B$86*(1+Model!E12+$A25)*(1+Model!F12+$A25)*(Model!F14+B$23)+Valuation!$B$87*(1+Model!E16+$A25)*(1+Model!F16+$A25)*(Model!F18+B$23)+Model!F21+Model!F33)*(1-Model!F63)/Model!F40 | C25: =(Valuation!$B$86*(1+Model!E12+$A25)*(1+Model!F12+$A25)*(Model!F14+C$23)+Valuation!$B$87*(1+Model!E16+$A25)*(1+Model!F16+$A25)*(Model!F18+C$23)+Model!F21+Model!F33)*(1-Model!F63)/Model!F40 | D25: =(Valuation!$B$86*(1+Model!E12+$A25)*(1+Model!F12+$A25)*(Model!F14+D$23)+Valuation!$B$87*(1+Model!E16+$A25)*(1+Model!F16+$A25)*(Model!F18+D$23)+Model!F21+Model!F33)*(1-Model!F63)/Model!F40 | E25: =(Valuation!$B$86*(1+Model!E12+$A25)*(1+Model!F12+$A25)*(Model!F14+E$23)+Valuation!$B$87*(1+Model!E16+$A25)*(1+Model!F16+$A25)*(Model!F18+E$23)+Model!F21+Model!F33)*(1-Model!F63)/Model!F40 | F25: =(Valuation!$B$86*(1+Model!E12+$A25)*(1+Model!F12+$A25)*(Model!F14+F$23)+Valuation!$B$87*(1+Model!E16+$A25)*(1+Model!F16+$A25)*(Model!F18+F$23)+Model!F21+Model!F33)*(1-Model!F63)/Model!F40
A26: 0 | B26: =(Valuation!$B$86*(1+Model!E12+$A26)*(1+Model!F12+$A26)*(Model!F14+B$23)+Valuation!$B$87*(1+Model!E16+$A26)*(1+Model!F16+$A26)*(Model!F18+B$23)+Model!F21+Model!F33)*(1-Model!F63)/Model!F40 | C26: =(Valuation!$B$86*(1+Model!E12+$A26)*(1+Model!F12+$A26)*(Model!F14+C$23)+Valuation!$B$87*(1+Model!E16+$A26)*(1+Model!F16+$A26)*(Model!F18+C$23)+Model!F21+Model!F33)*(1-Model!F63)/Model!F40 | D26: =(Valuation!$B$86*(1+Model!E12+$A26)*(1+Model!F12+$A26)*(Model!F14+D$23)+Valuation!$B$87*(1+Model!E16+$A26)*(1+Model!F16+$A26)*(Model!F18+D$23)+Model!F21+Model!F33)*(1-Model!F63)/Model!F40 | E26: =(Valuation!$B$86*(1+Model!E12+$A26)*(1+Model!F12+$A26)*(Model!F14+E$23)+Valuation!$B$87*(1+Model!E16+$A26)*(1+Model!F16+$A26)*(Model!F18+E$23)+Model!F21+Model!F33)*(1-Model!F63)/Model!F40 | F26: =(Valuation!$B$86*(1+Model!E12+$A26)*(1+Model!F12+$A26)*(Model!F14+F$23)+Valuation!$B$87*(1+Model!E16+$A26)*(1+Model!F16+$A26)*(Model!F18+F$23)+Model!F21+Model!F33)*(1-Model!F63)/Model!F40
A27: 0.01 | B27: =(Valuation!$B$86*(1+Model!E12+$A27)*(1+Model!F12+$A27)*(Model!F14+B$23)+Valuation!$B$87*(1+Model!E16+$A27)*(1+Model!F16+$A27)*(Model!F18+B$23)+Model!F21+Model!F33)*(1-Model!F63)/Model!F40 | C27: =(Valuation!$B$86*(1+Model!E12+$A27)*(1+Model!F12+$A27)*(Model!F14+C$23)+Valuation!$B$87*(1+Model!E16+$A27)*(1+Model!F16+$A27)*(Model!F18+C$23)+Model!F21+Model!F33)*(1-Model!F63)/Model!F40 | D27: =(Valuation!$B$86*(1+Model!E12+$A27)*(1+Model!F12+$A27)*(Model!F14+D$23)+Valuation!$B$87*(1+Model!E16+$A27)*(1+Model!F16+$A27)*(Model!F18+D$23)+Model!F21+Model!F33)*(1-Model!F63)/Model!F40 | E27: =(Valuation!$B$86*(1+Model!E12+$A27)*(1+Model!F12+$A27)*(Model!F14+E$23)+Valuation!$B$87*(1+Model!E16+$A27)*(1+Model!F16+$A27)*(Model!F18+E$23)+Model!F21+Model!F33)*(1-Model!F63)/Model!F40 | F27: =(Valuation!$B$86*(1+Model!E12+$A27)*(1+Model!F12+$A27)*(Model!F14+F$23)+Valuation!$B$87*(1+Model!E16+$A27)*(1+Model!F16+$A27)*(Model!F18+F$23)+Model!F21+Model!F33)*(1-Model!F63)/Model!F40
A28: 0.02 | B28: =(Valuation!$B$86*(1+Model!E12+$A28)*(1+Model!F12+$A28)*(Model!F14+B$23)+Valuation!$B$87*(1+Model!E16+$A28)*(1+Model!F16+$A28)*(Model!F18+B$23)+Model!F21+Model!F33)*(1-Model!F63)/Model!F40 | C28: =(Valuation!$B$86*(1+Model!E12+$A28)*(1+Model!F12+$A28)*(Model!F14+C$23)+Valuation!$B$87*(1+Model!E16+$A28)*(1+Model!F16+$A28)*(Model!F18+C$23)+Model!F21+Model!F33)*(1-Model!F63)/Model!F40 | D28: =(Valuation!$B$86*(1+Model!E12+$A28)*(1+Model!F12+$A28)*(Model!F14+D$23)+Valuation!$B$87*(1+Model!E16+$A28)*(1+Model!F16+$A28)*(Model!F18+D$23)+Model!F21+Model!F33)*(1-Model!F63)/Model!F40 | E28: =(Valuation!$B$86*(1+Model!E12+$A28)*(1+Model!F12+$A28)*(Model!F14+E$23)+Valuation!$B$87*(1+Model!E16+$A28)*(1+Model!F16+$A28)*(Model!F18+E$23)+Model!F21+Model!F33)*(1-Model!F63)/Model!F40 | F28: =(Valuation!$B$86*(1+Model!E12+$A28)*(1+Model!F12+$A28)*(Model!F14+F$23)+Valuation!$B$87*(1+Model!E16+$A28)*(1+Model!F16+$A28)*(Model!F18+F$23)+Model!F21+Model!F33)*(1-Model!F63)/Model!F40
A30: Net interest and the share count are held at the base case in table 3.

Sheet Distribution
A1: AVGO: 12-month distribution (base case = median; downside = 10th, upside = 90th percentile; a lognormal with its own spread on each side)
A3: Case | B3: Percentile | C3: Value at target date | D3: Story
A4: downside | B4: 0.1 | C4: ='Calc - downside'!$F$69 | D4: =Valuation!J82
A5: base | B5: 0.5 | C5: ='Calc - research target (12m)'!$F$69 | D5: the reconciled set (research target (12m))
A6: upside | B6: 0.9 | C6: ='Calc - upside'!$F$69 | D6: =Valuation!J83
A8: Downside spread (log vol) | B8: =IF(ISNUMBER(C4),LN(C5/C4)/NORMSINV(0.9),Valuation!$B$65) | C8: =IF(B8<0.02,"FLAG: downside case at or above base","")
A9: Upside spread (log vol) | B9: =IF(ISNUMBER(C6),LN(C6/C5)/NORMSINV(0.9),Valuation!$B$65) | C9: =IF(B9<0.02,"FLAG: upside case at or below base","")
A10: Mean | B10: =C5*(EXP(B8^2/2)*NORMSDIST(-B8)+EXP(B9^2/2)*NORMSDIST(B9))
A12: Quantile | B12: Price
A13: Median (model target) | B13: =$C$5*EXP(NORMSINV(0.5)*MAX(Distribution!$B$9,0.02))
A14: 10th percentile | B14: =$C$5*EXP(NORMSINV(0.1)*MAX(Distribution!$B$8,0.02))
A15: 25th percentile | B15: =$C$5*EXP(NORMSINV(0.25)*MAX(Distribution!$B$8,0.02))
A16: 75th percentile | B16: =$C$5*EXP(NORMSINV(0.75)*MAX(Distribution!$B$9,0.02))
A17: 90th percentile | B17: =$C$5*EXP(NORMSINV(0.9)*MAX(Distribution!$B$9,0.02))

Sheet Calc - research target (12m)
A1: AVGO engine calculation: research target (12m) (reconciled set, no scenario deltas)
A2: Machinery behind the Valuation and Distribution tabs; drivers come from Model, assumptions from Valuation.
A4: Scenario Growth Δ | B4: 0
A5: Scenario Margin Δ | B5: 0
A6: Scenario Multiple Δ (turns) | B6: 0
A7: Scenario WACC Δ | B7: 0
A8: Scenario Multiple %Δ | B8: 0
A9: Scenario Stated EPS/FCF %Δ | B9: 0
A10: Scenario Custom %Δ | B10: 0
A12: WACC | B12: =Valuation!$B$50+B7
A13: Years from last FY end to target date | B13: =(Valuation!$B$44-Valuation!$B$48)/365.25
A14: Years from last FY end to balance date | B14: =(Valuation!$B$54-Valuation!$B$48)/365.25
A15: Years from last FY end to share count date | B15: =(Valuation!$B$60-Valuation!$B$48)/365.25
A16: Projected years | B16: 3
A18: Projection | B18: Base | C18: =Model!E5 | D18: =Model!F5 | E18: =Model!G5
A19: Year index | B19: 0 | C19: 1 | D19: 2 | E19: 3
A20: Period end | C20: =Valuation!$B$48+ROUND(365.25*C19,0) | D20: =Valuation!$B$48+ROUND(365.25*D19,0) | E20: =Valuation!$B$48+ROUND(365.25*E19,0)
A21: Revenue growth | C21: =C22/B22-1 | D21: =D22/C22-1 | E21: =E22/D22-1
A22: Revenue | B22: =Valuation!$B$49 | C22: =C139 | D22: =D139 | E22: =E139
A23: EBIT margin | C23: =C24/C22 | D23: =D24/D22 | E23: =E24/E22
A24: EBIT | C24: =C142 | D24: =D142 | E24: =E142
A25: Tax rate | C25: =Model!E63 | D25: =Model!F63 | E25: =Model!G63
A26: NOPAT | C26: =C24*(1-C25) | D26: =D24*(1-D25) | E26: =E24*(1-E25)
A27: D&A | C27: =C22*(Model!E64) | D27: =D22*(Model!F64) | E27: =E22*(Model!G64)
A28: Capex | C28: =C22*(Model!E65) | D28: =D22*(Model!F65) | E28: =E22*(Model!G65)
A29: Working capital increase | C29: =(Model!E66)*(C22-B22) | D29: =(Model!F66)*(D22-C22) | E29: =(Model!G66)*(E22-D22)
A30: Stock comp | C30: =C22*(Model!E67) | D30: =D22*(Model!F67) | E30: =E22*(Model!G67)
A31: Free cash flow to firm | C31: =C26+C27-C28-C29-IF(AND(Valuation!$B$46="adjusted",Valuation!$B$47="cost"),C30*(1-C25),0) | D31: =D26+D27-D28-D29-IF(AND(Valuation!$B$46="adjusted",Valuation!$B$47="cost"),D30*(1-D25),0) | E31: =E26+E27-E28-E29-IF(AND(Valuation!$B$46="adjusted",Valuation!$B$47="cost"),E30*(1-E25),0)
A32: EBITDA | C32: =C24+C27 | D32: =D24+D27 | E32: =E24+E27
A33: Adj. EBITDA | C33: =C24+C27+C22*(Model!E71) | D33: =D24+D27+D22*(Model!F71) | E33: =E24+E27+E22*(Model!G71)
A34: Shareholder returns + other uses | C34: =C22*Model!E69+Model!E68+Model!E70 | D34: =D22*Model!F69+Model!F68+Model!F70 | E34: =E22*Model!G69+Model!G68+Model!G70
A35: Share of year after target date | C35: =IF(C19<=$B$13,0,C19-MAX(C19-1,$B$13)) | D35: =IF(D19<=$B$13,0,D19-MAX(D19-1,$B$13)) | E35: =IF(E19<=$B$13,0,E19-MAX(E19-1,$B$13))
A36: PV at target date of FCFF | C36: =IF(C35=0,0,C31*C35/(1+$B$12)^(C19-$B$13)) | D36: =IF(D35=0,0,D31*D35/(1+$B$12)^(D19-$B$13)) | E36: =IF(E35=0,0,E31*E35/(1+$B$12)^(E19-$B$13))
A37: Overlap: balance date to target date | C37: =MAX(0,MIN(C19,$B$13)-MAX(C19-1,$B$14)) | D37: =MAX(0,MIN(D19,$B$13)-MAX(D19-1,$B$14)) | E37: =MAX(0,MIN(E19,$B$13)-MAX(E19-1,$B$14))
A38: NTM weight at target date | C38: =MAX(0,MIN(C19,$B$13+1)-MAX(C19-1,$B$13)) | D38: =MAX(0,MIN(D19,$B$13+1)-MAX(D19-1,$B$13)) | E38: =MAX(0,MIN(E19,$B$13+1)-MAX(E19-1,$B$13))
A39: LTM weight at target date | B39: =MAX(0,MIN(0,$B$13)-MAX(-1,$B$13-1)) | C39: =MAX(0,MIN(C19,$B$13)-MAX(C19-1,$B$13-1)) | D39: =MAX(0,MIN(D19,$B$13)-MAX(D19-1,$B$13-1)) | E39: =MAX(0,MIN(E19,$B$13)-MAX(E19-1,$B$13-1))
A41: Value at the target date
A42: PV of free cash flow after the target date | B42: =SUM($C$36:$E$36)
A43: Terminal value at final year | B43: =IF(Valuation!$B$51="exit_multiple",Valuation!$B$53*E32,E31*(1+Valuation!$B$52)/($B$12-Valuation!$B$52))
A44: PV of terminal value at target date | B44: =B43/(1+$B$12)^($B$16-$B$13)
A45: DCF enterprise value at target date | B45: =B42+B44
A46: Terminal value share of DCF | B46: =B44/B45
A47: Free cash flow earned, balance date to target date | B47: =SUMPRODUCT($C$193:$E$193,$C$31:$E$31)
A48: Shareholder returns + other uses paid | B48: =SUMPRODUCT($C$194:$E$194,$C$34:$E$34)
A49: Interest drag on net debt | B49: =Valuation!$B$57*(1-$C$25)*MAX(Valuation!$B$55,0)*MAX($B$13-$B$14,0)
A50: Net debt at target date | B50: =IF(Valuation!$B$58="",Valuation!$B$55-B47+B49+B48,Valuation!$B$58)
A51: Minority interests | B51: =Valuation!$B$56
A52: Adjustments (probability-weighted) | B52: =(Valuation!B75)*Valuation!C75+(Valuation!B76)*Valuation!C76+0
A53: Diluted shares at target date (M) | B53: =IF(Valuation!$B$62="",Valuation!$B$59*(1+Valuation!$B$61)^MAX($B$13-$B$15,0),Valuation!$B$62)
A54: After-tax interest on target-date net debt (net cash earns it: quarterly set) | B54: =Valuation!$B$57*(1-$C$25)*B50
A55: Check: WACC vs terminal growth | B55: =IF(AND(Valuation!$B$51<>"exit_multiple",$B$12<=Valuation!$B$52+0.01),"WACC must exceed terminal growth by 1 point","ok")
A56: Check: projection length | B56: =IF(OR($B$13>=$B$16-1,$B$13+1>$B$16),"add projected years past the target date","ok")
A58: Metric at target date | B58: Next 12 months | C58: Last 12 months
A59: Revenue | B59: =SUMPRODUCT($C$181:$E$181,$C$22:$E$22) | C59: =SUMPRODUCT($C$187:$E$187,$C$22:$E$22)
A60: EBIT | B60: =SUMPRODUCT($C$182:$E$182,$C$24:$E$24) | C60: =SUMPRODUCT($C$188:$E$188,$C$24:$E$24)
A61: EBITDA | B61: =SUMPRODUCT($C$183:$E$183,$C$32:$E$32) | C61: =SUMPRODUCT($C$189:$E$189,$C$32:$E$32)
A62: Adj. EBITDA | B62: =SUMPRODUCT($C$184:$E$184,$C$33:$E$33) | C62: =SUMPRODUCT($C$190:$E$190,$C$33:$E$33)
A63: NOPAT | B63: =SUMPRODUCT($C$185:$E$185,$C$26:$E$26) | C63: =SUMPRODUCT($C$191:$E$191,$C$26:$E$26)
A64: Free cash flow to firm | B64: =SUMPRODUCT($C$186:$E$186,$C$31:$E$31) | C64: =SUMPRODUCT($C$192:$E$192,$C$31:$E$31)
A66: Valuation method | B66: Metric | C66: Multiple used | D66: Basis | E66: Metric at target date | F66: Value per share | G66: Weight | H66: Metric key | I66: Metric shown (stated per-share figure when used)
A67: DCF (cash flow to target date + terminal) | F67: =((B45)-$B$50-$B$51+$B$52)/$B$53 | G67: =Valuation!$B$63
A68: ="Multiple: "&Valuation!A69&" ("&Valuation!D69&")" | B68: =Valuation!A69 | C68: =IF(B68="FCF yield",(Valuation!B69)*(1-$B$8),(Valuation!B69)+IF(B68="EV/sales",0.1,1)*$B$6) | D68: =Valuation!D69 | E68: =IF(D68="ltm",CHOOSE(H68,$C$59,$C$60,$C$61,$C$62,$C$63,$C$64),CHOOSE(H68,$B$59,$B$60,$B$61,$B$62,$B$63,$B$64)) | F68: =IF(OR(B68="EV/EBITDA",B68="EV/sales",B68="EV/EBIT"),((C68*E68)-$B$50-$B$51+$B$52)/$B$53,IF(B68="P/E",IF(Valuation!F69<>"",C68*(Valuation!F69)*(1+$B$9),C68*(E68-$B$54)/$B$53),IF(Valuation!G69<>"",(Valuation!G69)*(1+$B$9)/C68,(E68-IF(Valuation!H69,$B$54,0))/C68/$B$53))+$B$52/$B$53) | G68: =Valuation!C69 | H68: =IF(B68="EV/sales",1,IF(B68="EV/EBIT",2,IF(B68="EV/EBITDA",IF(Valuation!E69="adjusted",4,3),IF(B68="P/E",5,6)))) | I68: =IF(AND(B68="P/E",Valuation!F69<>""),(Valuation!F69)*(1+$B$9),IF(AND(B68="FCF yield",Valuation!G69<>""),(Valuation!G69)*(1+$B$9),E68))
A69: Value per share at target date (weighted methods) | F69: =SUMPRODUCT(F67:F68,G67:G68)/SUM(G67:G68)
A129: Segment build (model_engine.seg_build): revenue and EBIT are the segment sums plus corporate EBIT
A130: Segment | B130: Base | C130: =Model!E5 | D130: =Model!F5 | E130: =Model!G5
A131: Semiconductor solutions: revenue growth | C131: =Model!E12+$B$4 | D131: =Model!F12+$B$4 | E131: =Model!G12+$B$4
A132: Semiconductor solutions: revenue | B132: =Valuation!$B$86 | C132: =B132*(1+C131) | D132: =C132*(1+D131) | E132: =D132*(1+E131)
A133: Semiconductor solutions: EBIT margin | C133: =Model!E14+$B$5 | D133: =Model!F14+$B$5 | E133: =Model!G14+$B$5
A134: Semiconductor solutions: EBIT | C134: =C132*C133 | D134: =D132*D133 | E134: =E132*E133
A135: Infrastructure software: revenue growth | C135: =Model!E16+$B$4 | D135: =Model!F16+$B$4 | E135: =Model!G16+$B$4
A136: Infrastructure software: revenue | B136: =Valuation!$B$87 | C136: =B136*(1+C135) | D136: =C136*(1+D135) | E136: =D136*(1+E135)
A137: Infrastructure software: EBIT margin | C137: =Model!E18+$B$5 | D137: =Model!F18+$B$5 | E137: =Model!G18+$B$5
A138: Infrastructure software: EBIT | C138: =C136*C137 | D138: =D136*D137 | E138: =E136*E137
A139: Total segment revenue | C139: =C132+C136 | D139: =D132+D136 | E139: =E132+E136
A140: Total segment EBIT | C140: =C134+C138 | D140: =D134+D138 | E140: =E134+E138
A141: Corporate / unallocated EBIT | C141: =Model!E21 | D141: =Model!F21 | E141: =Model!G21
A142: EBIT (segments + corporate) | C142: =C140+C141 | D142: =D140+D141 | E142: =E140+E141
A180: Quarterly set: weight of each projected year in the metric at the target date, from the engine's quarter rows (model_engine.quarter_rows; replaces the straight-line weights in rows 37-39)
A181: NTM weight by year: revenue | C181: 0 | D181: 0.006145833 | E181: 0.99686716
A182: NTM weight by year: ebit | C182: 0 | D182: 0.0060866739 | E182: 0.99687963
A183: NTM weight by year: ebitda | C183: 0 | D183: 0.0060872715 | E183: 0.99687947
A184: NTM weight by year: adj_ebitda | C184: 0 | D184: 0.0060872715 | E184: 0.99687947
A185: NTM weight by year: nopat | C185: 0 | D185: 0.0060866739 | E185: 0.99687965
A186: NTM weight by year: fcff | C186: 0 | D186: 0.0060794992 | E186: 0.99688085
A187: LTM weight by year: revenue | C187: 0.010907399 | D187: 0.99385417 | E187: 0
A188: LTM weight by year: ebit | C188: 0.011161126 | D188: 0.99391329 | E188: 0
A189: LTM weight by year: ebitda | C189: 0.011158576 | D189: 0.99391273 | E189: 0
A190: LTM weight by year: adj_ebitda | C190: 0.011158576 | D190: 0.99391273 | E190: 0
A191: LTM weight by year: nopat | C191: 0.011161125 | D191: 0.9939133 | E191: 0
A192: LTM weight by year: fcff | C192: 0.011199207 | D192: 0.99392052 | E192: 0
... A194: ROLL weight by year: returns | C194: 0.33085779 | D194: 0.99385416 | E194: 0

Sheet Calc - downside
A1: AVGO engine calculation: downside scenario
A2: Machinery behind the Valuation and Distribution tabs; drivers come from Model, assumptions from Valuation.
A4: Scenario Growth Δ | B4: =N(Valuation!C82)
A5: Scenario Margin Δ | B5: =N(Valuation!D82)
A6: Scenario Multiple Δ (turns) | B6: =N(Valuation!E82)
A7: Scenario WACC Δ | B7: =N(Valuation!F82)
A8: Scenario Multiple %Δ | B8: =N(Valuation!G82)
A9: Scenario Stated EPS/FCF %Δ | B9: =N(Valuation!H82)
A10: Scenario Custom %Δ | B10: =N(Valuation!I82)
A12: WACC | B12: =Valuation!$B$50+B7
A13: Years from last FY end to target date | B13: =(Valuation!$B$44-Valuation!$B$48)/365.25
A14: Years from last FY end to balance date | B14: =(Valuation!$B$54-Valuation!$B$48)/365.25
A15: Years from last FY end to share count date | B15: =(Valuation!$B$60-Valuation!$B$48)/365.25
A16: Projected years | B16: 3
A18: Projection | B18: Base | C18: =Model!E5 | D18: =Model!F5 | E18: =Model!G5
A19: Year index | B19: 0 | C19: 1 | D19: 2 | E19: 3
A20: Period end | C20: =Valuation!$B$48+ROUND(365.25*C19,0) | D20: =Valuation!$B$48+ROUND(365.25*D19,0) | E20: =Valuation!$B$48+ROUND(365.25*E19,0)
A21: Revenue growth | C21: =C22/B22-1 | D21: =D22/C22-1 | E21: =E22/D22-1
A22: Revenue | B22: =Valuation!$B$49 | C22: =C139 | D22: =D139 | E22: =E139
A23: EBIT margin | C23: =C24/C22 | D23: =D24/D22 | E23: =E24/E22
A24: EBIT | C24: =C142 | D24: =D142 | E24: =E142
A25: Tax rate | C25: =Model!E63 | D25: =Model!F63 | E25: =Model!G63
A26: NOPAT | C26: =C24*(1-C25) | D26: =D24*(1-D25) | E26: =E24*(1-E25)
A27: D&A | C27: =C22*(Model!E64) | D27: =D22*(Model!F64) | E27: =E22*(Model!G64)
A28: Capex | C28: =C22*(Model!E65) | D28: =D22*(Model!F65) | E28: =E22*(Model!G65)
A29: Working capital increase | C29: =(Model!E66)*(C22-B22) | D29: =(Model!F66)*(D22-C22) | E29: =(Model!G66)*(E22-D22)
A30: Stock comp | C30: =C22*(Model!E67) | D30: =D22*(Model!F67) | E30: =E22*(Model!G67)
A31: Free cash flow to firm | C31: =C26+C27-C28-C29-IF(AND(Valuation!$B$46="adjusted",Valuation!$B$47="cost"),C30*(1-C25),0) | D31: =D26+D27-D28-D29-IF(AND(Valuation!$B$46="adjusted",Valuation!$B$47="cost"),D30*(1-D25),0) | E31: =E26+E27-E28-E29-IF(AND(Valuation!$B$46="adjusted",Valuation!$B$47="cost"),E30*(1-E25),0)
A32: EBITDA | C32: =C24+C27 | D32: =D24+D27 | E32: =E24+E27
A33: Adj. EBITDA | C33: =C24+C27+C22*(Model!E71) | D33: =D24+D27+D22*(Model!F71) | E33: =E24+E27+E22*(Model!G71)
A34: Shareholder returns + other uses | C34: =C22*Model!E69+Model!E68+Model!E70 | D34: =D22*Model!F69+Model!F68+Model!F70 | E34: =E22*Model!G69+Model!G68+Model!G70
A35: Share of year after target date | C35: =IF(C19<=$B$13,0,C19-MAX(C19-1,$B$13)) | D35: =IF(D19<=$B$13,0,D19-MAX(D19-1,$B$13)) | E35: =IF(E19<=$B$13,0,E19-MAX(E19-1,$B$13))
A36: PV at target date of FCFF | C36: =IF(C35=0,0,C31*C35/(1+$B$12)^(C19-$B$13)) | D36: =IF(D35=0,0,D31*D35/(1+$B$12)^(D19-$B$13)) | E36: =IF(E35=0,0,E31*E35/(1+$B$12)^(E19-$B$13))
A37: Overlap: balance date to target date | C37: =MAX(0,MIN(C19,$B$13)-MAX(C19-1,$B$14)) | D37: =MAX(0,MIN(D19,$B$13)-MAX(D19-1,$B$14)) | E37: =MAX(0,MIN(E19,$B$13)-MAX(E19-1,$B$14))
A38: NTM weight at target date | C38: =MAX(0,MIN(C19,$B$13+1)-MAX(C19-1,$B$13)) | D38: =MAX(0,MIN(D19,$B$13+1)-MAX(D19-1,$B$13)) | E38: =MAX(0,MIN(E19,$B$13+1)-MAX(E19-1,$B$13))
A39: LTM weight at target date | B39: =MAX(0,MIN(0,$B$13)-MAX(-1,$B$13-1)) | C39: =MAX(0,MIN(C19,$B$13)-MAX(C19-1,$B$13-1)) | D39: =MAX(0,MIN(D19,$B$13)-MAX(D19-1,$B$13-1)) | E39: =MAX(0,MIN(E19,$B$13)-MAX(E19-1,$B$13-1))
A41: Value at the target date
A42: PV of free cash flow after the target date | B42: =SUM($C$36:$E$36)
A43: Terminal value at final year | B43: =IF(Valuation!$B$51="exit_multiple",Valuation!$B$53*E32,E31*(1+Valuation!$B$52)/($B$12-Valuation!$B$52))
A44: PV of terminal value at target date | B44: =B43/(1+$B$12)^($B$16-$B$13)
A45: DCF enterprise value at target date | B45: =B42+B44
A46: Terminal value share of DCF | B46: =B44/B45
A47: Free cash flow earned, balance date to target date | B47: =SUMPRODUCT($C$193:$E$193,$C$31:$E$31)
A48: Shareholder returns + other uses paid | B48: =SUMPRODUCT($C$194:$E$194,$C$34:$E$34)
A49: Interest drag on net debt | B49: =Valuation!$B$57*(1-$C$25)*MAX(Valuation!$B$55,0)*MAX($B$13-$B$14,0)
A50: Net debt at target date | B50: =IF(Valuation!$B$58="",Valuation!$B$55-B47+B49+B48,Valuation!$B$58)
A51: Minority interests | B51: =Valuation!$B$56
A52: Adjustments (probability-weighted) | B52: =(Valuation!B75)*Valuation!C75+(Valuation!B76)*Valuation!C76+0
A53: Diluted shares at target date (M) | B53: =IF(Valuation!$B$62="",Valuation!$B$59*(1+Valuation!$B$61)^MAX($B$13-$B$15,0),Valuation!$B$62)
A54: After-tax interest on target-date net debt (net cash earns it: quarterly set) | B54: =Valuation!$B$57*(1-$C$25)*B50
A55: Check: WACC vs terminal growth | B55: =IF(AND(Valuation!$B$51<>"exit_multiple",$B$12<=Valuation!$B$52+0.01),"WACC must exceed terminal growth by 1 point","ok")
A56: Check: projection length | B56: =IF(OR($B$13>=$B$16-1,$B$13+1>$B$16),"add projected years past the target date","ok")
A58: Metric at target date | B58: Next 12 months | C58: Last 12 months
A59: Revenue | B59: =SUMPRODUCT($C$181:$E$181,$C$22:$E$22) | C59: =SUMPRODUCT($C$187:$E$187,$C$22:$E$22)
A60: EBIT | B60: =SUMPRODUCT($C$182:$E$182,$C$24:$E$24) | C60: =SUMPRODUCT($C$188:$E$188,$C$24:$E$24)
A61: EBITDA | B61: =SUMPRODUCT($C$183:$E$183,$C$32:$E$32) | C61: =SUMPRODUCT($C$189:$E$189,$C$32:$E$32)
A62: Adj. EBITDA | B62: =SUMPRODUCT($C$184:$E$184,$C$33:$E$33) | C62: =SUMPRODUCT($C$190:$E$190,$C$33:$E$33)
A63: NOPAT | B63: =SUMPRODUCT($C$185:$E$185,$C$26:$E$26) | C63: =SUMPRODUCT($C$191:$E$191,$C$26:$E$26)
A64: Free cash flow to firm | B64: =SUMPRODUCT($C$186:$E$186,$C$31:$E$31) | C64: =SUMPRODUCT($C$192:$E$192,$C$31:$E$31)
A66: Valuation method | B66: Metric | C66: Multiple used | D66: Basis | E66: Metric at target date | F66: Value per share | G66: Weight | H66: Metric key | I66: Metric shown (stated per-share figure when used)
A67: DCF (cash flow to target date + terminal) | F67: =((B45)-$B$50-$B$51+$B$52)/$B$53 | G67: =Valuation!$B$63
A68: ="Multiple: "&Valuation!A69&" ("&Valuation!D69&")" | B68: =Valuation!A69 | C68: =IF(B68="FCF yield",(Valuation!B69)*(1-$B$8),(Valuation!B69)+IF(B68="EV/sales",0.1,1)*$B$6) | D68: =Valuation!D69 | E68: =IF(D68="ltm",CHOOSE(H68,$C$59,$C$60,$C$61,$C$62,$C$63,$C$64),CHOOSE(H68,$B$59,$B$60,$B$61,$B$62,$B$63,$B$64)) | F68: =IF(OR(B68="EV/EBITDA",B68="EV/sales",B68="EV/EBIT"),((C68*E68)-$B$50-$B$51+$B$52)/$B$53,IF(B68="P/E",IF(Valuation!F69<>"",C68*(Valuation!F69)*(1+$B$9),C68*(E68-$B$54)/$B$53),IF(Valuation!G69<>"",(Valuation!G69)*(1+$B$9)/C68,(E68-IF(Valuation!H69,$B$54,0))/C68/$B$53))+$B$52/$B$53) | G68: =Valuation!C69 | H68: =IF(B68="EV/sales",1,IF(B68="EV/EBIT",2,IF(B68="EV/EBITDA",IF(Valuation!E69="adjusted",4,3),IF(B68="P/E",5,6)))) | I68: =IF(AND(B68="P/E",Valuation!F69<>""),(Valuation!F69)*(1+$B$9),IF(AND(B68="FCF yield",Valuation!G69<>""),(Valuation!G69)*(1+$B$9),E68))
A69: Value per share at target date (weighted methods) | F69: =SUMPRODUCT(F67:F68,G67:G68)/SUM(G67:G68)
A129: Segment build (model_engine.seg_build): revenue and EBIT are the segment sums plus corporate EBIT
A130: Segment | B130: Base | C130: =Model!E5 | D130: =Model!F5 | E130: =Model!G5
A131: Semiconductor solutions: revenue growth | C131: =Model!E12+$B$4+$B$250 | D131: =Model!F12+$B$4+$B$252 | E131: =Model!G12+$B$4+$B$254
A132: Semiconductor solutions: revenue | B132: =Valuation!$B$86 | C132: =B132*(1+C131) | D132: =C132*(1+D131) | E132: =D132*(1+E131)
A133: Semiconductor solutions: EBIT margin | C133: =Model!E14+$B$5+$B$251 | D133: =Model!F14+$B$5+$B$253 | E133: =Model!G14+$B$5+$B$255
A134: Semiconductor solutions: EBIT | C134: =C132*C133 | D134: =D132*D133 | E134: =E132*E133
A135: Infrastructure software: revenue growth | C135: =Model!E16+$B$4 | D135: =Model!F16+$B$4 | E135: =Model!G16+$B$4
A136: Infrastructure software: revenue | B136: =Valuation!$B$87 | C136: =B136*(1+C135) | D136: =C136*(1+D135) | E136: =D136*(1+E135)
A137: Infrastructure software: EBIT margin | C137: =Model!E18+$B$5 | D137: =Model!F18+$B$5 | E137: =Model!G18+$B$5
A138: Infrastructure software: EBIT | C138: =C136*C137 | D138: =D136*D137 | E138: =E136*E137
A139: Total segment revenue | C139: =C132+C136 | D139: =D132+D136 | E139: =E132+E136
A140: Total segment EBIT | C140: =C134+C138 | D140: =D134+D138 | E140: =E134+E138
A141: Corporate / unallocated EBIT | C141: =Model!E21 | D141: =Model!F21 | E141: =Model!G21+$B$256
A142: EBIT (segments + corporate) | C142: =C140+C141 | D142: =D140+D141 | E142: =E140+E141
A180: Quarterly set: weight of each projected year in the metric at the target date, from the engine's quarter rows (model_engine.quarter_rows; replaces the straight-line weights in rows 37-39)
A181: NTM weight by year: revenue | C181: 0 | D181: 0.0060654921 | E181: 0.9969043
A182: NTM weight by year: ebit | C182: 0 | D182: 0.0060103961 | E182: 0.99691813
A183: NTM weight by year: ebitda | C183: 0 | D183: 0.0060109671 | E183: 0.99691795
A184: NTM weight by year: adj_ebitda | C184: 0 | D184: 0.0060109671 | E184: 0.99691795
A185: NTM weight by year: nopat | C185: 0 | D185: 0.006010396 | E185: 0.99691807
A186: NTM weight by year: fcff | C186: 0 | D186: 0.006005811 | E186: 0.99691942
A187: LTM weight by year: revenue | C187: 0.0091751727 | D187: 0.99393451 | E187: 0
A188: LTM weight by year: ebit | C188: 0.0092324762 | D188: 0.99398962 | E188: 0
A189: LTM weight by year: ebitda | C189: 0.0092318945 | D189: 0.9939891 | E189: 0
A190: LTM weight by year: adj_ebitda | C190: 0.0092318945 | D190: 0.9939891 | E190: 0
A191: LTM weight by year: nopat | C191: 0.0092324754 | D191: 0.99398959 | E191: 0
A192: LTM weight by year: fcff | C192: 0.0092403044 | D192: 0.99399424 | E192: 0
... A194: ROLL weight by year: returns | C194: 0.27831357 | D194: 0.99393451 | E194: 0
A249: Driver scenario shifts: line-item changes model_drivers.py resolves from this scenario's driver deltas (added to the Model tab inputs)
A250: Semiconductor solutions: revenue growth, year 1 | B250: -0.20985946
A251: Semiconductor solutions: EBIT margin, year 1 | B251: -0.0057584821
A252: Semiconductor solutions: revenue growth, year 2 | B252: -0.39564312
A253: Semiconductor solutions: EBIT margin, year 2 | B253: -0.020342296
A254: Semiconductor solutions: revenue growth, year 3 | B254: -0.038933062
A255: Semiconductor solutions: EBIT margin, year 3 | B255: -0.020702636
A256: Corporate EBIT, year 3 | B256: -2.910383e-11

Sheet Calc - upside
A1: AVGO engine calculation: upside scenario
A2: Machinery behind the Valuation and Distribution tabs; drivers come from Model, assumptions from Valuation.
A4: Scenario Growth Δ | B4: =N(Valuation!C83)
A5: Scenario Margin Δ | B5: =N(Valuation!D83)
A6: Scenario Multiple Δ (turns) | B6: =N(Valuation!E83)
A7: Scenario WACC Δ | B7: =N(Valuation!F83)
A8: Scenario Multiple %Δ | B8: =N(Valuation!G83)
A9: Scenario Stated EPS/FCF %Δ | B9: =N(Valuation!H83)
A10: Scenario Custom %Δ | B10: =N(Valuation!I83)
A12: WACC | B12: =Valuation!$B$50+B7
A13: Years from last FY end to target date | B13: =(Valuation!$B$44-Valuation!$B$48)/365.25
A14: Years from last FY end to balance date | B14: =(Valuation!$B$54-Valuation!$B$48)/365.25
A15: Years from last FY end to share count date | B15: =(Valuation!$B$60-Valuation!$B$48)/365.25
A16: Projected years | B16: 3
A18: Projection | B18: Base | C18: =Model!E5 | D18: =Model!F5 | E18: =Model!G5
A19: Year index | B19: 0 | C19: 1 | D19: 2 | E19: 3
A20: Period end | C20: =Valuation!$B$48+ROUND(365.25*C19,0) | D20: =Valuation!$B$48+ROUND(365.25*D19,0) | E20: =Valuation!$B$48+ROUND(365.25*E19,0)
A21: Revenue growth | C21: =C22/B22-1 | D21: =D22/C22-1 | E21: =E22/D22-1
A22: Revenue | B22: =Valuation!$B$49 | C22: =C139 | D22: =D139 | E22: =E139
A23: EBIT margin | C23: =C24/C22 | D23: =D24/D22 | E23: =E24/E22
A24: EBIT | C24: =C142 | D24: =D142 | E24: =E142
A25: Tax rate | C25: =Model!E63 | D25: =Model!F63 | E25: =Model!G63
A26: NOPAT | C26: =C24*(1-C25) | D26: =D24*(1-D25) | E26: =E24*(1-E25)
A27: D&A | C27: =C22*(Model!E64) | D27: =D22*(Model!F64) | E27: =E22*(Model!G64)
A28: Capex | C28: =C22*(Model!E65) | D28: =D22*(Model!F65) | E28: =E22*(Model!G65)
A29: Working capital increase | C29: =(Model!E66)*(C22-B22) | D29: =(Model!F66)*(D22-C22) | E29: =(Model!G66)*(E22-D22)
A30: Stock comp | C30: =C22*(Model!E67) | D30: =D22*(Model!F67) | E30: =E22*(Model!G67)
A31: Free cash flow to firm | C31: =C26+C27-C28-C29-IF(AND(Valuation!$B$46="adjusted",Valuation!$B$47="cost"),C30*(1-C25),0) | D31: =D26+D27-D28-D29-IF(AND(Valuation!$B$46="adjusted",Valuation!$B$47="cost"),D30*(1-D25),0) | E31: =E26+E27-E28-E29-IF(AND(Valuation!$B$46="adjusted",Valuation!$B$47="cost"),E30*(1-E25),0)
A32: EBITDA | C32: =C24+C27 | D32: =D24+D27 | E32: =E24+E27
A33: Adj. EBITDA | C33: =C24+C27+C22*(Model!E71) | D33: =D24+D27+D22*(Model!F71) | E33: =E24+E27+E22*(Model!G71)
A34: Shareholder returns + other uses | C34: =C22*Model!E69+Model!E68+Model!E70 | D34: =D22*Model!F69+Model!F68+Model!F70 | E34: =E22*Model!G69+Model!G68+Model!G70
A35: Share of year after target date | C35: =IF(C19<=$B$13,0,C19-MAX(C19-1,$B$13)) | D35: =IF(D19<=$B$13,0,D19-MAX(D19-1,$B$13)) | E35: =IF(E19<=$B$13,0,E19-MAX(E19-1,$B$13))
A36: PV at target date of FCFF | C36: =IF(C35=0,0,C31*C35/(1+$B$12)^(C19-$B$13)) | D36: =IF(D35=0,0,D31*D35/(1+$B$12)^(D19-$B$13)) | E36: =IF(E35=0,0,E31*E35/(1+$B$12)^(E19-$B$13))
A37: Overlap: balance date to target date | C37: =MAX(0,MIN(C19,$B$13)-MAX(C19-1,$B$14)) | D37: =MAX(0,MIN(D19,$B$13)-MAX(D19-1,$B$14)) | E37: =MAX(0,MIN(E19,$B$13)-MAX(E19-1,$B$14))
A38: NTM weight at target date | C38: =MAX(0,MIN(C19,$B$13+1)-MAX(C19-1,$B$13)) | D38: =MAX(0,MIN(D19,$B$13+1)-MAX(D19-1,$B$13)) | E38: =MAX(0,MIN(E19,$B$13+1)-MAX(E19-1,$B$13))
A39: LTM weight at target date | B39: =MAX(0,MIN(0,$B$13)-MAX(-1,$B$13-1)) | C39: =MAX(0,MIN(C19,$B$13)-MAX(C19-1,$B$13-1)) | D39: =MAX(0,MIN(D19,$B$13)-MAX(D19-1,$B$13-1)) | E39: =MAX(0,MIN(E19,$B$13)-MAX(E19-1,$B$13-1))
A41: Value at the target date
A42: PV of free cash flow after the target date | B42: =SUM($C$36:$E$36)
A43: Terminal value at final year | B43: =IF(Valuation!$B$51="exit_multiple",Valuation!$B$53*E32,E31*(1+Valuation!$B$52)/($B$12-Valuation!$B$52))
A44: PV of terminal value at target date | B44: =B43/(1+$B$12)^($B$16-$B$13)
A45: DCF enterprise value at target date | B45: =B42+B44
A46: Terminal value share of DCF | B46: =B44/B45
A47: Free cash flow earned, balance date to target date | B47: =SUMPRODUCT($C$193:$E$193,$C$31:$E$31)
A48: Shareholder returns + other uses paid | B48: =SUMPRODUCT($C$194:$E$194,$C$34:$E$34)
A49: Interest drag on net debt | B49: =Valuation!$B$57*(1-$C$25)*MAX(Valuation!$B$55,0)*MAX($B$13-$B$14,0)
A50: Net debt at target date | B50: =IF(Valuation!$B$58="",Valuation!$B$55-B47+B49+B48,Valuation!$B$58)
A51: Minority interests | B51: =Valuation!$B$56
A52: Adjustments (probability-weighted) | B52: =(Valuation!B75)*Valuation!C75+(Valuation!B76)*Valuation!C76+0
A53: Diluted shares at target date (M) | B53: =IF(Valuation!$B$62="",Valuation!$B$59*(1+Valuation!$B$61)^MAX($B$13-$B$15,0),Valuation!$B$62)
A54: After-tax interest on target-date net debt (net cash earns it: quarterly set) | B54: =Valuation!$B$57*(1-$C$25)*B50
A55: Check: WACC vs terminal growth | B55: =IF(AND(Valuation!$B$51<>"exit_multiple",$B$12<=Valuation!$B$52+0.01),"WACC must exceed terminal growth by 1 point","ok")
A56: Check: projection length | B56: =IF(OR($B$13>=$B$16-1,$B$13+1>$B$16),"add projected years past the target date","ok")
A58: Metric at target date | B58: Next 12 months | C58: Last 12 months
A59: Revenue | B59: =SUMPRODUCT($C$181:$E$181,$C$22:$E$22) | C59: =SUMPRODUCT($C$187:$E$187,$C$22:$E$22)
A60: EBIT | B60: =SUMPRODUCT($C$182:$E$182,$C$24:$E$24) | C60: =SUMPRODUCT($C$188:$E$188,$C$24:$E$24)
A61: EBITDA | B61: =SUMPRODUCT($C$183:$E$183,$C$32:$E$32) | C61: =SUMPRODUCT($C$189:$E$189,$C$32:$E$32)
A62: Adj. EBITDA | B62: =SUMPRODUCT($C$184:$E$184,$C$33:$E$33) | C62: =SUMPRODUCT($C$190:$E$190,$C$33:$E$33)
A63: NOPAT | B63: =SUMPRODUCT($C$185:$E$185,$C$26:$E$26) | C63: =SUMPRODUCT($C$191:$E$191,$C$26:$E$26)
A64: Free cash flow to firm | B64: =SUMPRODUCT($C$186:$E$186,$C$31:$E$31) | C64: =SUMPRODUCT($C$192:$E$192,$C$31:$E$31)
A66: Valuation method | B66: Metric | C66: Multiple used | D66: Basis | E66: Metric at target date | F66: Value per share | G66: Weight | H66: Metric key | I66: Metric shown (stated per-share figure when used)
A67: DCF (cash flow to target date + terminal) | F67: =((B45)-$B$50-$B$51+$B$52)/$B$53 | G67: =Valuation!$B$63
A68: ="Multiple: "&Valuation!A69&" ("&Valuation!D69&")" | B68: =Valuation!A69 | C68: =IF(B68="FCF yield",(Valuation!B69)*(1-$B$8),(Valuation!B69)+IF(B68="EV/sales",0.1,1)*$B$6) | D68: =Valuation!D69 | E68: =IF(D68="ltm",CHOOSE(H68,$C$59,$C$60,$C$61,$C$62,$C$63,$C$64),CHOOSE(H68,$B$59,$B$60,$B$61,$B$62,$B$63,$B$64)) | F68: =IF(OR(B68="EV/EBITDA",B68="EV/sales",B68="EV/EBIT"),((C68*E68)-$B$50-$B$51+$B$52)/$B$53,IF(B68="P/E",IF(Valuation!F69<>"",C68*(Valuation!F69)*(1+$B$9),C68*(E68-$B$54)/$B$53),IF(Valuation!G69<>"",(Valuation!G69)*(1+$B$9)/C68,(E68-IF(Valuation!H69,$B$54,0))/C68/$B$53))+$B$52/$B$53) | G68: =Valuation!C69 | H68: =IF(B68="EV/sales",1,IF(B68="EV/EBIT",2,IF(B68="EV/EBITDA",IF(Valuation!E69="adjusted",4,3),IF(B68="P/E",5,6)))) | I68: =IF(AND(B68="P/E",Valuation!F69<>""),(Valuation!F69)*(1+$B$9),IF(AND(B68="FCF yield",Valuation!G69<>""),(Valuation!G69)*(1+$B$9),E68))
A69: Value per share at target date (weighted methods) | F69: =SUMPRODUCT(F67:F68,G67:G68)/SUM(G67:G68)
A129: Segment build (model_engine.seg_build): revenue and EBIT are the segment sums plus corporate EBIT
A130: Segment | B130: Base | C130: =Model!E5 | D130: =Model!F5 | E130: =Model!G5
A131: Semiconductor solutions: revenue growth | C131: =Model!E12+$B$4+$B$250 | D131: =Model!F12+$B$4+$B$252 | E131: =Model!G12+$B$4+$B$254
A132: Semiconductor solutions: revenue | B132: =Valuation!$B$86 | C132: =B132*(1+C131) | D132: =C132*(1+D131) | E132: =D132*(1+E131)
A133: Semiconductor solutions: EBIT margin | C133: =Model!E14+$B$5+$B$251 | D133: =Model!F14+$B$5+$B$253 | E133: =Model!G14+$B$5+$B$255
A134: Semiconductor solutions: EBIT | C134: =C132*C133 | D134: =D132*D133 | E134: =E132*E133
A135: Infrastructure software: revenue growth | C135: =Model!E16+$B$4 | D135: =Model!F16+$B$4 | E135: =Model!G16+$B$4
A136: Infrastructure software: revenue | B136: =Valuation!$B$87 | C136: =B136*(1+C135) | D136: =C136*(1+D135) | E136: =D136*(1+E135)
A137: Infrastructure software: EBIT margin | C137: =Model!E18+$B$5 | D137: =Model!F18+$B$5 | E137: =Model!G18+$B$5
A138: Infrastructure software: EBIT | C138: =C136*C137 | D138: =D136*D137 | E138: =E136*E137
A139: Total segment revenue | C139: =C132+C136 | D139: =D132+D136 | E139: =E132+E136
A140: Total segment EBIT | C140: =C134+C138 | D140: =D134+D138 | E140: =E134+E138
A141: Corporate / unallocated EBIT | C141: =Model!E21+$B$256 | D141: =Model!F21 | E141: =Model!G21+$B$257
A142: EBIT (segments + corporate) | C142: =C140+C141 | D142: =D140+D141 | E142: =E140+E141
A180: Quarterly set: weight of each projected year in the metric at the target date, from the engine's quarter rows (model_engine.quarter_rows; replaces the straight-line weights in rows 37-39)
A181: NTM weight by year: revenue | C181: 0 | D181: 0.0061696197 | E181: 0.99685679
A182: NTM weight by year: ebit | C182: 0 | D182: 0.0061037773 | E182: 0.99687092
A183: NTM weight by year: ebitda | C183: 0 | D183: 0.0061044452 | E183: 0.99687081
A184: NTM weight by year: adj_ebitda | C184: 0 | D184: 0.0061044452 | E184: 0.99687081
A185: NTM weight by year: nopat | C185: 0 | D185: 0.0061037769 | E185: 0.99687092
A186: NTM weight by year: fcff | C186: 0 | D186: 0.0060949154 | E186: 0.99687241
A187: LTM weight by year: revenue | C187: 0.011574903 | D187: 0.99383038 | E187: 0
A188: LTM weight by year: ebit | C188: 0.01181002 | D188: 0.99389624 | E188: 0
A189: LTM weight by year: ebitda | C189: 0.011807658 | D189: 0.99389552 | E189: 0
A190: LTM weight by year: adj_ebitda | C190: 0.011807658 | D190: 0.99389552 | E190: 0
A191: LTM weight by year: nopat | C191: 0.011810022 | D191: 0.99389618 | E191: 0
A192: LTM weight by year: fcff | C192: 0.011846705 | D192: 0.99390509 | E192: 0
... A194: ROLL weight by year: returns | C194: 0.35110539 | D194: 0.99383038 | E194: 0
A249: Driver scenario shifts: line-item changes model_drivers.py resolves from this scenario's driver deltas (added to the Model tab inputs)
A250: Semiconductor solutions: revenue growth, year 1 | B250: 0.089939769
A251: Semiconductor solutions: EBIT margin, year 1 | B251: -0.0012250654
A252: Semiconductor solutions: revenue growth, year 2 | B252: 0.14556415
A253: Semiconductor solutions: EBIT margin, year 2 | B253: -0.0038190388
A254: Semiconductor solutions: revenue growth, year 3 | B254: 0.010288002
A255: Semiconductor solutions: EBIT margin, year 3 | B255: -0.0045655465
A256: Corporate EBIT, year 1 | B256: -7.2759576e-12
A257: Corporate EBIT, year 3 | B257: -5.8207661e-11

Sheet Agents
A1: AVGO: each forecaster's own assumption set through the same engine (from model_engine.json, not live)
A3: Set | B3: Research target (12m) | C3: Median | D3: 25th pct | E3: 75th pct | F3: WACC | G3: Y1 growth | H3: Y1 margin | I3: Terminal growth | J3: DCF weight | K3: Years | L3: Multiples | M3: Supervisor's note
A4: supervisor | B4: 490.10049 | C4: 490.10049 | D4: 361.47671 | E4: 544.7875 | J4: 0 | K4: 3 | L4: P/E 19.81 (ntm)
A5: agent_1 | M5: engine error: no model_inputs found
A6: agent_2 | M6: engine error: no model_inputs found
A7: agent_3 | M7: engine error: no model_inputs found
A8: agent_4 | M8: engine error: no model_inputs found
A9: agent_5 | M9: engine error: no model_inputs found

Sheet Sources
A1: AVGO: where each input comes from (source numbers point to the list below; F ids to the SEC fact table)
A3: Input | B3: Value | C3: Basis | D3: Sources | E3: SEC fact ids | F3: Derivation
A4: Base revenue FY2025 (fiscal year ended 2025-11-02) | B4: $63,887M | C4: reported | D4: 55 | E4: F3 | F4: 10-K filed 2025-12-18, us-gaap revenue (fact pack F3).
A5: AI revenue per GW deployed (price driver) | B5: $11,500M per GW | C5: estimate | D5: 47, 48, 37 | F5: Two anchors: (1) Rasgon on the Q3 call: management's $115B / $230B outlook against the customers' stated deployments gives 'between $11 and $12 billion per gigawatt' (~10 GW in 2027, ~20 GW in 2028); (2) Mizuho (April 2026): $42B of 2027 Broadcom AI revenue from Anthropic on the ~3.5 GW deal = $12.0B per GW. Tan's 'content in the range of $20 to $30 billion per gigawatt' is full content per GW and, on management's own outlook, spreads over more than one fiscal year (StreetSignal notes the two may compare Broadcom revenue with customer spending). Used: $11.5B per GW of the year's deployments, which reproduces the $115B FY27 outlook on ~10 GW.
A6: FY2027 AI revenue (units x price) | B6: $115,000M = (Anthropic 5.0 + OpenAI 1.3 + others 3.7 GW) x $11.5B | C6: estimate | D6: 37, 38, 47 | F6: Anthropic: 'another 5 gigawatts of TPU version 8i in 2027'; OpenAI: 'planned deployment of 1.3 gigawatts in 2027'; others (Google TPU 'multi tens of billions of dollars ... annually', Meta MTIA, ByteDance, the sixth customer) 3.7 GW = Rasgon's ~10 GW total less 6.3. 10.0 x $11.5B = $115B = management's 'approximately $115 billion' with supply secured.
A7: FY2028 Anthropic GW realised | B7: 8.5 GW of 10 GW line of sight (85%) = $97,750M | C7: estimate | D7: 37, 51, 44, 46 | F7: Q3 call: 'in 2028 we have clear line of sight to deliver another, an incremental, 10 gigawatts'; Anthropic 'on track to become our largest XPU customer in 2027 and sustain that in 2028'. Support: Q3 revenue $16.8B (+45% q/q), profitable on an adjusted basis, IPO discussed at ~$1.5T (Reuters, 2026-10-15); $125.2B five-year TPU lease commitment; financing in place ($35B XPV tranche, $60B package syndicating). Haircut 15% for deployment timing (the Q3 call names land, power and shells alongside silicon, substrates, HBM and lasers as constraints) and IPO timing. 8.5 x $11.5B = $97.75B.
A8: FY2028 OpenAI GW realised | B8: 3.5 GW of >5 GW line of sight (70%) = $40,250M | C8: estimate | D8: 37, 52, 45 | F8: Q3 call: 'line of sight for OpenAI to deploy over 5 gigawatts of Jalapeno and its successor generation of XPU' in 2028. Haircut 30%: OpenAI's annualized revenue was 'approaching $50 billion at the end of September' (FT, below the ~$70B reported earlier); the chip project 'hit an $18 billion financing snag' in May (The Information); the >$50B financing Broadcom is arranging is in early talks (WSJ). 3.5 x $11.5B = $40.25B.
A9: FY2028 other customers GW (Google, Meta, ByteDance, sixth customer) | B9: 5.0 GW = $57,500M | C9: estimate | D9: 37, 47 | F9: Rasgon: ~20 GW in 2028, ~15 of which Anthropic and OpenAI, so ~5 GW for the others; Google: long-term agreement to deliver 'multi tens of billions of dollars of TPUs annually'; Meta: 'line of sight to deploy 3 gigawatts through 28'. Self-funded hyperscalers: no haircut. 5.0 x $11.5B = $57.5B.
A10: FY2028 AI revenue (sum) | B10: $195,500M (17.0 GW x $11.5B), -15% vs management $230B | C10: estimate | D10: 37, 47, 41 | F10: 97.75 + 40.25 + 57.5 = $195.5B. Management: 'line of sight for fiscal 2028 AI semiconductor revenue growth to again double to $230 billion' (20 GW x $11.5B). House capex file: 195.5 / 2,255 (2028 base) = 8.7% of customer AI capex vs 115 / 1,841 = 6.2% in 2027. Supervisor's original $180B and every forecaster's $175-184B are below; the set is above them because the customer GW lines (not a capex share) carry it.
A11: AI networking vs XPU split (memo) | B11: XPU 73% / networking 27% of AI revenue, held | C11: estimate | D11: 38, 37 | F11: Q3: XPUs 'representing 73% of AI revenue'; 'our AI networking revenue is expected to grow just as fast as XPUs over the next few years'. FY28: XPU $142.7B, networking $52.8B. Memo only: both carry the same per-GW price and AI margin.
A12: Tax rate | B12: 16% | C12: estimate | D12: 37, 35 | F12: Non-GAAP tax rate ~16% for Q4 and FY26 (global minimum tax), held. Our estimate: the guided ~16% non-GAAP rate held (FY26 9M GAAP rate is distorted by discrete items).
A13: D&A (depreciation) | B13: 0.6% of revenue | C13: estimate | D13: 55 | E13: F6 | F13: Depreciation 9M FY26 $484M / revenue $71,089M = 0.68% (XBRL Depreciation); non-GAAP operating income is after depreciation and before amortization of acquired intangibles (not a cash cost), so 0.6% is added back in FCFF.
A14: Capex | B14: FY26 2.3%, FY27 1.5%, FY28-FY30 1.0% of revenue | C14: estimate | D14: 35, 37, 54 | E14: F53 | F14: 9M capex $1,013M (8-K) + Q4 guide ~$1.4B = $2.41B / $105.9B = 2.3%; FY27 consensus capex $2,506M / $173,968M = 1.44% (MarketScreener) -> 1.5%; FY28 $2,055M / $271,925M = 0.76% -> 1.0% (Singapore substrate fab).
A15: Working capital | B15: 12% of the revenue increase | C15: estimate | D15: 55 | F15: Receivables $13,707M + inventory $4,523M at 2026-08-02 = $18,230M = 15.4% of annualised Q3 revenue ($29,591M x 4); less payables and accruals ~3.5% (judgment) = 12%. Replaces the transcribed one-line leakage (capex_pct_rev 8.38%), which mixed capex, working capital and cash-tax timing.
A16: Net debt at balance date 2026-08-02 | B16: $35,444M | C16: reported | D16: 35, 24 | E16: F84, F83, F89 | F16: Short-term debt $2,252M + long-term debt $57,167M = $59,419M carrying, less cash $23,975M (F89). Principal $61,079M (10-Q).
A17: Interest rate on debt | B17: 4.07% | C17: estimate | D17: 35 | E17: F84 | F17: Net interest $2,420M / debt $59,419M (transcribed); used only by the engine interest drag, which net_debt_horizon overrides.
A18: Customer financing: Backstop (disclosed) | B18: $29,000M max undiscounted; 70% average utilisation; LGD 45% | C18: estimate | D18: 29, 31, 38, 37 | F18: 10-Q: Backstop liability = '85% of the outstanding amounts owed' less 'the value of the AI racks', maximum ~$29B on full deployment, 5-year leases, fair value not material, nothing paid. The 10-Q names no customer; the size is consistent with the first $35B XPV tranche closed in June for Anthropic's 1 GW (0.85 x 35 = $29.75B; inference). Utilisation 70% (leases amortise over 5 years); LGD 45% of the maximum (rack resale after ~2 years in a downturn).
A19: Customer financing: Anthropic $42B senior tranche | B19: $42,000M, backed by Broadcom; 70% utilisation; LGD 35% | C19: estimate | D19: 44, 46, 45, 50, 29 | F19: Broadcom agreed to lend Anthropic up to $42B in convertible notes, restricted to TPU lease payments, ~a third of a $125.2B five-year lease commitment (Reuters, prospectus); the $60B package is a $42B Class A senior-secured tranche and an $18B Class B junior tranche led by Blackstone; FT: the $42B senior is 'backed by Broadcom', the junior 'without its guarantees'; Seoul Economic Daily: senior 'guaranteed by Broadcom'. LGD 35%: the $18B junior (30% of the stack) takes first loss and the racks are collateral.
A20: Customer financing: OpenAI package | B20: $35,000M Broadcom share x 0.6 probability; LGD 35% | C20: estimate | D20: 45 | F20: WSJ: Broadcom arranging 'more than $50 billion' with Apollo and Blackstone for OpenAI's custom chips, early talks, size may change; no report says whether Broadcom guarantees any of it. Assumed Anthropic-like: 70% senior = $35B, probability 0.6 that Broadcom backs it.
A21: Customer financing: future XPV backstops | B21: $32,000M x 0.5 probability; LGD 40% (was $75,000M) | C21: estimate | D21: 37, 38, 67 | F21: Was $75B of further Broadcom-backed exposure; the Oct 27 2026 8-K Backstop (~$43B max, Anthropic SPV) is the first of these to be signed, so it moves to its own row and the bucket keeps 75,000 - 43,000 = 32,000. XPV aims 'to enable more than 20 gigawatts of compute infrastructure for OpenAI and Anthropic by the end of 2028'; management 'may provide modest residual value guarantees' and will evaluate financings case by case. 20 GW at ~$20-30B content is $400-600B; $75B of further Broadcom-backed exposure is judgment.
A22: Customer financing: default probabilities | B22: Anthropic 10.5%, OpenAI 16.75%, mixed 12.5% (5-year, unconditional); bear 30/45/35%, base 5/9/6%, bull 2/4/3% | C22: estimate | D22: 49, 50, 51, 52 | F22: S&P 1981-2024 five-year cumulative defaults: BB 5.05%, B 14.69%. Anthropic's junior pays a 10% coupon vs ~7% for BB credits (ICE BofA BB index), so the market prices it between BB and B: 10.5% unconditional; OpenAI (revenue ~$50B annualized, unprofitable, financing snag) a B-or-worse 16.75%. Scenario-conditional PDs put most defaults in the bear (an AI-funding bust), weighted 0.25/0.5/0.25.
A23: Customer-financing expected loss (adjustment) | B23: -4,568 ($M) | C23: estimate | D23: 29, 44, 45, 49, 67 | F23: Labelled estimate. Base round unconditional expected loss 4,214 ($M) plus the Oct 27 8-K Backstop (max ~$43B, 72.5% of lease amounts owed less rack value; id 67) at 0.70 utilisation x Anthropic unconditional PD 10.5% x LGD 0.35 = +1,106, less the same $43B taken out of the 'future XPV backstops' bucket (75,000 -> 32,000 x 0.70 x p 0.5 x PD 12.5% x LGD 0.40 = -753): 4,214 + 354 = 4,568.
A24: Legal and regulatory (adjustment) | B24: -$1,250M | C24: estimate | D24: 53, 57, 29 | F24: CISPE complaint to DG Competition (2026-03-19; VMware VCSP termination, cost increases >1,000%, interim measures and fines sought); EU fines cap at 10% of turnover. p 0.25 x ~$3.0B = -$750M, plus licensing suits and settlements -$500M (judgment). The 10-Q accrues nothing ('not considered probable', 'not reasonably estimable').
A25: Conglomerate / holding-company discount | B25: none | C25: judgment | F25: No non-core parts sit on top of the core: no equity stakes, ventures or holdco assets are added; infrastructure software (VMware) is an operating segment inside the DCF and EPS, not a separately valued add-on. Diversification-discount evidence (Berger & Ofek 1995 13-15%; smaller after self-selection controls, Campa & Kedia 2002, Villalonga 2004; see runs/2026-10-06/GOOGL/remaining_items_2026-10-19.md) applies to the market value of a whole conglomerate, which AVGO's own 19x already reflects.
A26: Other non-traditional items (not modelled) | B26: equity investments, Anthropic note conversion option, tariffs, tax | C26: judgment | D26: 44, 55, 32 | F26: No material equity stakes (9M FY26 investment purchases $756M). Anthropic notes are convertible into Anthropic equity but no notes are issued and no conversion price is public: upside option not valued. Section 232 chip tariffs exempt US data-center use: not modelled. Unrecognized tax benefits $1,755M and a $2,186M global minimum tax payable are in the filings and the 16% rate.
A27: Customer financing: Oct 27 2026 Anthropic SPV Backstop | B27: $43,000M max undiscounted; 70% average utilisation; LGD 35%; carried with probability 1 | C27: estimate | D27: 67 | F27: 8-K Item 2.03 (2026-10-27): residual value support to a new SPV that took on rack purchase and lease agreements with 'the Company's customer'; liability = 72.5% of lease amounts owed less the racks' resale value; maximum ~$43B on deployment, rising with deliveries and falling with lease payments. The 8-K does not name the customer; we take it to be Anthropic (Broadcom's Oct 26 release on a $63B SPV financing for Anthropic's accelerators was reported by secondary outlets but not read at source here: flag). Anthropic's PD is applied. LGD 35% (same as the Anthropic senior row; 72.5% coverage < the 10-Q Backstop's 85%).
A28: constant: nonai_margin | B28: 55% every quarter | C28: estimate | D28: 38, 37, 68 | F28: Judgment carried from the base round (not disclosed; below the Q3 FY26 semiconductor segment average 61.3%). Only splits the semiconductor segment margin between AI and non-AI; the segment total is the filed figure in actual quarters.
A29: constant: sbc | B29: actual 1,280/1,771/2,322/2,195/2,176/2,092/2,019; forecast Q4 FY26 2,100, FY27 2,250/q, FY28 2,450/q ($M) | C29: estimate | D29: 68, 55 | E29: F39, F40 | F29: Actuals: XBRL ShareBasedCompensation by quarter. Forecast: unrecognized compensation cost $18,221M at 2026-08-02 (~2.1 years of the TTM $8.48B (F39)) with annual grants growing with headcount and the share price: FY27 $9.0B, FY28 $9.8B (base round 8.0% / 5.5% / 4.0% of revenue = ~$8.5B / $9.3B / $10.0B). Charged in EBIT (SBC as a cost), so EPS is on the Zacks basis.
A30: SBC basis (method) | B30: SBC charged in EBIT (was: non-GAAP EPS ex-SBC with flat shares and buyback cash in net debt) | C30: estimate | D30: 69, 70, 71, 66 | F30: The exit-multiple rule needs AVGO's own multiple and the peer median on one basis. Zacks consensus keeps SBC as a cost for AVGO and its peers (AVGO Q3 FY26 Zacks 3.03 vs non-GAAP 3.32 / GAAP 2.68), the basis the NVDA set adopted (Kilian card 2026-10-27). Buybacks then only offset dilution and are not in shareholder_returns (the SBC charge stands in for them); shares held flat.
A31: Shareholder returns (dividends) | B31: FY26 12,420; FY27 14,330; FY28 15,420 ($M) | C31: estimate | D31: 56, 54 | E31: F87 | F31: Dividends = DPS x 4,773.6M shares outstanding (F87): FY26 $0.65 x 4 = $2.60 (declared; 10-Q R55, id 56) -> 12,412; FY27 $2.997, FY28 $3.225 (MarketScreener DPS consensus) -> 14,306 / 15,395, rounded up for RSU growth. Buybacks offset SBC dilution (see SBC basis).
A32: Diluted shares | B32: 4,940M held flat to the horizon | C32: estimate | D32: 37, 35 | E32: F33 | F32: Q4 FY26 non-GAAP diluted share guide ~4,940M (Q3 4,937M); dilution from RSU vesting offset by buybacks funded by the SBC charge in EBIT.
A33: Net debt at the horizon | B33: engine cash roll from the quarter rows (no stated override) | C33: estimate | D33: 35 | E33: F84, F89 | F33: Was a stated -20,594 (bottom-up, ex-SBC basis with $10B buybacks). Now the engine rolls 2026-08-02 net debt 35,444 by quarter FCFF less dividends to the horizon; the SBC charge in EBIT replaces the buyback line.
A34: Leg weights | B34: P/E 1.0 (no DCF; policy) | C34: estimate | F34: No DCF leg for non-neoclouds (policy 2026-10-21); the forward P/E is the most accurate single method (semis playbook, Liu-Nissim-Thomas). The old set carried dcf_weight 0.2 that the engine already forced to 0.
A35: Horizon P/E multiple (exit rule) | B35: 21.9x, weight 1.0 | C35: estimate | D35: 69, 74, 73, 72 | F35: Peer calendar-NTM P/E (price / days-weighted Zacks FY EPS): AVGO 345.0 / 17.4112 = 19.81x; NVDA 213.66 / 14.0815 = 15.17x; AMD 566.42 / 12.8213 = 44.18x; MRVL 218.34 / 5.27 = 41.43x; TSM 431.81 / 21.5131 = 20.07x; ANET 184.22 / 4.5347 = 40.62x; CRDO 165.29 / 6.6555 = 24.84x; ALAB 290.43 / 4.2407 = 68.49x; COHR 237.22 / 10.1286 = 23.42x. Peer median (8, AI-exposed) 32.73x; exit = 32.73 x (19.81 / 32.73)^0.8 = 21.9x. QCOM/ADI/TXN removed 2026-10-30 (non-AI analog peers for ~7% of revenue). Implies EPS growth after FY28 at a discount to the AI peer group for AVGO's lab-customer concentration (own multiple 39% below the median).
A36: driver:ai_rev | B36: AI semiconductor revenue (custom XPUs + AI networking): 2.016e+04 -> 5.8e+04/1.15e+05/1.955e+05 (estimate; quarterly, sum) | C36: estimate | F36: Q4 FY26 22,100 = guide $21.7B x (1 + 1.8%): record-adjusted (median first-guide beat +2.2% over 6 quarters, guidance_check), shaded for supply. FY27 115,000 = (Anthropic 5.0 + OpenAI 1.3 + others 3.7 GW) x $11.5B/GW (management 'approximately $115 billion', supply secured); quarters 24,500 / 27,500 / 29,500 / 33,500 (+11% / +12% / +7% / +14% q/q, as XPU generations ramp; Q4 heavy as in FY25-26 where Q4 was the largest quarter). FY28 195,500 = 17.0 GW x $11.5B (Anthropic 8.5 of 10, OpenAI 3.5 of >5, others 5.0), -15% vs management's $230B line of sight; quarters 40,000 / 46,000 / 52,000 / 57,500 (+19% / +15% / +13% / +11% q/q, decelerating ramp). New since the base round: Broadcom's Oct 27 8-K (id 67) shows financing arranged for the Anthropic rack leases from 2027, which supports the Anthropic GW but does not change them.
A37: driver:xpu_share | B37: Custom XPU share of AI semiconductor revenue (rest = AI networking): 0.65 -> 0.6947/0.7308/0.748 (estimate; quarterly, wmean:ai_rev) | C37: estimate | F37: Actuals FY26: 0.667 / 0.61 / 0.73 (cited). FY25 quarters 0.65: not read from the FY25 calls (base year only; feeds no forecast and no filed-quarter EBIT). Q4 FY26 0.72 (both lines triple y/y). FY27 0.72-0.74, FY28 0.74-0.75: management's ~30% networking settle point, plus rack-level (memory-rich) systems for Anthropic from 2027 (8-K 2026-10-27, id 67) booked in the XPU line, which edges the XPU share up.
A38: driver:xpu_margin | B38: Custom XPU operating margin (non-GAAP, before SBC): 0.5317 -> 0.587/0.5491/0.5287 (estimate; quarterly, wmean:ai_rev*xpu_share) | C38: estimate | F38: FY26 derived 57.6% / 59.7% / 59.5%. A least-squares fit of the three FY26 quarters (derived AI margin vs networking share) gives XPU chips 58.8% and networking 72.2% (networking constant set at 72%). Q4 FY26 58.1%: from the Q4 guide (non-GAAP op margin ~66% on $34.8B, record-adjusted; AI 62.0%) at a 72% XPU share; chips only ('No racks. It is all a chip business only', Q2 FY26 call). FY27-FY28: chips 58.8% blended with rack systems at 42% operating margin (UBS's 45-50% rack gross margin less ~5pt opex; analyst figure, not Broadcom's) as Anthropic rack deliveries under the Oct 27 2026 SPV lease (id 67) start: rack share of XPU revenue 15/20/25/30% through FY27 and 32/34/36/38% in FY28 (estimate, not disclosed). Built independently of the old AI margin path.
A39: driver:sw_rev | B39: Infrastructure software revenue (VMware and mainframe/enterprise software), driven by y/y growth: 2.703e+04 -> 3.148e+04/3.602e+04/3.746e+04 (estimate; quarterly, sum) | C39: estimate | F39: Q4 FY26 8,750 (guide ~8.7B; Q3 8,752 after the +22% q/q step from large VCF renewals). FY27 36,018 = 8.7B x 4 x 1.035 (base round; VCF conversion largely done, revenue tracks renewals), quarters +1.1%/q; FY28 37,459 (+4%). As y/y growth: Q4 FY26 +26% (Q4 guide 'up 25% year on year'), FY27 +14.4% (the Q3 FY26 step annualises: Q4 FY27 +4.8% y/y), FY28 +4.0% (renewal pricing; VCF conversion done). Margin held at 83.5% (constant sw_margin).
A40: driver:cf_exposure | B40: Customer-financing exposure backed by Broadcom (probability-weighted, utilised): 0 -> 7.98e+04/9.45e+04/1.057e+05 (estimate; quarterly, end) | C40: estimate | F40: Each deal at its maximum x 70% average utilisation x probability Broadcom carries it: 10-Q Backstop 29,000 x 0.7 = 20,300 and Anthropic senior notes 42,000 x 0.7 = 29,400 (Q3 FY26, 49,700); Oct 27 SPV Backstop 43,000 x 0.7 = 30,100 (Q4 FY26, 79,800); OpenAI 35,000 x p 0.6 x 0.7 = 14,700 (from Q2 FY27, 94,500); future XPV backstops 32,000 x p 0.5 x 0.7 = 11,200 (from Q2 FY28, 105,700). The loss uses the FY28 year-end stock (every deal expected by 2028).
A41: driver:cf_loss_rate | B41: Lifetime expected loss rate on Broadcom-backed customer financing: 0.04321 -> 0.04321/0.04321/0.04321 (estimate; quarterly, mean) | C41: estimate | F41: Exposure-weighted PD x LGD of the five deals: 10-Q Backstop 10.5% x 45% (959), Anthropic notes 10.5% x 35% (1,080), Oct 27 SPV 10.5% x 35% (1,106), OpenAI 16.75% x 35% (862), future XPV 12.5% x 40% (560): 4,567.6 / 105,700 = 4.3210%. Unconditional (the downside revenue loss sits in the downside case, not here).
A43: # | B43: Source | C43: Date | D43: Link
A44: 1 | B44: US Treasury daily par yield curve CSV 2026 (10/05/2026: 10 Yr 5.31, 3 Mo 4.22) | C44: 2026-10-05 | D44: https://home.treasury.gov/resource-center/data-chart-center/interest-rates/daily-treasury-rates.csv/2026/all?type=daily_treasury_yield_curve&field_tdr_date_value=2026&page&_format=csv
A45: 2 | B45: Damodaran Online: implied ERP on October 1, 2026 = 4.20% (trailing 12m, adjusted payout); T-bond 5.29% | C45: 2026-10-01 | D45: https://pages.stern.nyu.edu/~adamodar/New_Home_Page/home.htm
A46: 3 | B46: StockAnalysis AVGO statistics (Beta 5Y 1.48; total debt $59.42B; cash $23.98B; EV/EBITDA 33.79) | C46: 2026-10-06 | D46: https://stockanalysis.com/stocks/avgo/statistics/
A47: 4 | B47: Finviz screener valuation table (Forward P/E, EPS next Y) for AVGO and peers | C47: 2026-10-06 | D47: https://finviz.com/screener.ashx?v=121&t=AVGO,NVDA,AMD,MRVL,TSM,ANET,ALAB,CRDO,QCOM,COHR,CSCO,ADI,ARM,MU
A48: 5 | B48: StockAnalysis CSCO forecast (FY27 to Jul-2027 EPS 5.15) | C48: 2026-10-06 | D48: https://stockanalysis.com/stocks/csco/forecast/
A49: 6 | B49: StockAnalysis COHR forecast (FY27 to Jun-2027 EPS 9.42) | C49: 2026-10-06 | D49: https://stockanalysis.com/stocks/cohr/forecast/
A50: 7 | B50: StockAnalysis CRDO forecast (FY27 to Apr-2027 EPS 6.31) | C50: 2026-10-06 | D50: https://stockanalysis.com/stocks/crdo/forecast/
A51: 8 | B51: Broadcom 10-Q (quarter to 2026-08-02) R17: Backstop ~$29B max undiscounted, 85%, 5-year leases; $42B convertible-note facility, none issued | C51: 2026-09-10 | D51: https://www.sec.gov/Archives/edgar/data/1730168/000173016826000080/R17.htm
A52: 9 | B52: Broadcom 10-Q R53: purchase commitments FY27 $52,674M, FY28 $72,952M, total $126,821M | C52: 2026-09-10 | D52: https://www.sec.gov/Archives/edgar/data/1730168/000173016826000080/R53.htm
A53: 10 | B53: Broadcom 10-Q R54: guarantor maximum exposure $29,000M; note facility $42,000M; drawn $0; 5-year term | C53: 2026-09-10 | D53: https://www.sec.gov/Archives/edgar/data/1730168/000173016826000080/R54.htm
A54: 11 | B54: Broadcom 10-Q main document: RPO ~$179.2B (~25% in 12 months); $10.1B buyback remaining; debt principal $61,079M | C54: 2026-09-10 | D54: https://www.sec.gov/Archives/edgar/data/1730168/000173016826000080/avgo-20260802.htm
A55: 12 | B55: Broadcom 10-Q (quarter to 2026-05-03) R52: purchase commitments FY27 $55,214M, FY28 $72,870M | C55: period ended 2026-05-03 | D55: https://www.sec.gov/Archives/edgar/data/1730168/000173016826000054/R52.htm
... A117: 74 | B117: Nasdaq.com Zacks consensus EPS by fiscal year for the 11 peers (data/estimates/SYM.json, saved 2026-10-30 by nasdaq_est.py) | C117: 2026-10-30 | D117: https://api.nasdaq.com/api/analyst/NVDA/earnings-forecast
A119: Fact id | B119: Figure | C119: Value | D119: Filing
A120: F1 | B120: revenue FY ending 2023-10-29 (us-gaap:RevenueFromContractWithCustomerExcludingAssessedTax) | C120: 35819000000 | D120: https://www.sec.gov/Archives/edgar/data/1730168/000173016825000121/
A121: F2 | B121: revenue FY ending 2024-11-03 (us-gaap:RevenueFromContractWithCustomerExcludingAssessedTax) | C121: 51574000000 | D121: https://www.sec.gov/Archives/edgar/data/1730168/000173016825000121/
A122: F3 | B122: revenue FY ending 2025-11-02 (us-gaap:RevenueFromContractWithCustomerExcludingAssessedTax) | C122: 63887000000 | D122: https://www.sec.gov/Archives/edgar/data/1730168/000173016825000121/
A123: F4 | B123: revenue YTD 2025-11-03 to 2026-08-02 | C123: 71089000000 | D123: https://www.sec.gov/Archives/edgar/data/1730168/000173016826000080/
A124: F5 | B124: revenue prior-year YTD 2024-11-04 to 2025-08-03 | C124: 45872000000 | D124: https://www.sec.gov/Archives/edgar/data/1730168/000173016826000080/
A125: F6 | B125: revenue TTM to 2026-08-02 | C125: 89104000000
A126: F7 | B126: revenue quarter 2026-05-04 to 2026-08-02 | C126: 29591000000 | D126: https://www.sec.gov/Archives/edgar/data/1730168/000173016826000080/
A127: F8 | B127: operating_income FY ending 2023-10-29 (us-gaap:OperatingIncomeLoss) | C127: 16207000000 | D127: https://www.sec.gov/Archives/edgar/data/1730168/000173016825000121/
A128: F9 | B128: operating_income FY ending 2024-11-03 (us-gaap:OperatingIncomeLoss) | C128: 13463000000 | D128: https://www.sec.gov/Archives/edgar/data/1730168/000173016825000121/
A129: F10 | B129: operating_income FY ending 2025-11-02 (us-gaap:OperatingIncomeLoss) | C129: 25484000000 | D129: https://www.sec.gov/Archives/edgar/data/1730168/000173016825000121/
A130: F11 | B130: operating_income YTD 2025-11-03 to 2026-08-02 | C130: 35306000000 | D130: https://www.sec.gov/Archives/edgar/data/1730168/000173016826000080/
A131: F12 | B131: operating_income prior-year YTD 2024-11-04 to 2025-08-03 | C131: 17976000000 | D131: https://www.sec.gov/Archives/edgar/data/1730168/000173016826000080/
A132: F13 | B132: operating_income TTM to 2026-08-02 | C132: 42814000000
A133: F14 | B133: operating_income quarter 2026-05-04 to 2026-08-02 | C133: 15955000000 | D133: https://www.sec.gov/Archives/edgar/data/1730168/000173016826000080/
A134: F15 | B134: net_income FY ending 2023-10-29 (us-gaap:ProfitLoss) | C134: 14082000000 | D134: https://www.sec.gov/Archives/edgar/data/1730168/000173016825000121/
A135: F16 | B135: net_income FY ending 2024-11-03 (us-gaap:ProfitLoss) | C135: 5895000000 | D135: https://www.sec.gov/Archives/edgar/data/1730168/000173016825000121/
A136: F17 | B136: net_income FY ending 2025-11-02 (us-gaap:ProfitLoss) | C136: 23126000000 | D136: https://www.sec.gov/Archives/edgar/data/1730168/000173016825000121/
A137: F18 | B137: net_income YTD 2025-11-03 to 2026-08-02 | C137: 29747000000 | D137: https://www.sec.gov/Archives/edgar/data/1730168/000173016826000080/
A138: F19 | B138: net_income prior-year YTD 2024-11-04 to 2025-08-03 | C138: 14608000000 | D138: https://www.sec.gov/Archives/edgar/data/1730168/000173016826000080/
A139: F20 | B139: net_income TTM to 2026-08-02 | C139: 38265000000
A140: F21 | B140: net_income quarter 2026-05-04 to 2026-08-02 | C140: 13088000000 | D140: https://www.sec.gov/Archives/edgar/data/1730168/000173016826000080/
A141: F22 | B141: eps_diluted FY ending 2023-10-29 (us-gaap:EarningsPerShareDiluted) | C141: 3.3 | D141: https://www.sec.gov/Archives/edgar/data/1730168/000173016825000121/
A142: F23 | B142: eps_diluted FY ending 2024-11-03 (us-gaap:EarningsPerShareDiluted) | C142: 1.23 | D142: https://www.sec.gov/Archives/edgar/data/1730168/000173016825000121/
A143: F24 | B143: eps_diluted FY ending 2025-11-02 (us-gaap:EarningsPerShareDiluted) | C143: 4.77 | D143: https://www.sec.gov/Archives/edgar/data/1730168/000173016825000121/
A144: F25 | B144: eps_diluted YTD 2025-11-03 to 2026-08-02 | C144: 6.09 | D144: https://www.sec.gov/Archives/edgar/data/1730168/000173016826000080/
A145: F26 | B145: eps_diluted prior-year YTD 2024-11-04 to 2025-08-03 | C145: 3.02 | D145: https://www.sec.gov/Archives/edgar/data/1730168/000173016826000080/
A146: F27 | B146: eps_diluted quarter 2026-05-04 to 2026-08-02 | C146: 2.68 | D146: https://www.sec.gov/Archives/edgar/data/1730168/000173016826000080/
A147: F28 | B147: diluted_shares_wavg FY ending 2023-10-29 (us-gaap:WeightedAverageNumberOfDilutedSharesOutstanding) | C147: 4272000000 | D147: https://www.sec.gov/Archives/edgar/data/1730168/000173016825000121/
A148: F29 | B148: diluted_shares_wavg FY ending 2024-11-03 (us-gaap:WeightedAverageNumberOfDilutedSharesOutstanding) | C148: 4778000000 | D148: https://www.sec.gov/Archives/edgar/data/1730168/000173016825000121/
A149: F30 | B149: diluted_shares_wavg FY ending 2025-11-02 (us-gaap:WeightedAverageNumberOfDilutedSharesOutstanding) | C149: 4853000000 | D149: https://www.sec.gov/Archives/edgar/data/1730168/000173016825000121/
A150: F31 | B150: diluted_shares_wavg YTD 2025-11-03 to 2026-08-02 | C150: 4884000000 | D150: https://www.sec.gov/Archives/edgar/data/1730168/000173016826000080/
A151: F32 | B151: diluted_shares_wavg prior-year YTD 2024-11-04 to 2025-08-03 | C151: 4841000000 | D151: https://www.sec.gov/Archives/edgar/data/1730168/000173016826000080/
... A157: F38 | B157: sbc prior-year YTD 2024-11-04 to 2025-08-03 | C157: 5373000000 | D157: https://www.sec.gov/Archives/edgar/data/1730168/000173016826000080/
A158: F39 | B158: sbc TTM to 2026-08-02 | C158: 8482000000
A159: F40 | B159: sbc quarter 2025-11-03 to 2026-02-01 | C159: 2176000000 | D159: https://www.sec.gov/Archives/edgar/data/1730168/000173016826000016/
A160: F41 | B160: cfo FY ending 2023-10-29 (us-gaap:NetCashProvidedByUsedInOperatingActivities) | C160: 18085000000 | D160: https://www.sec.gov/Archives/edgar/data/1730168/000173016825000121/
A161: F42 | B161: cfo FY ending 2024-11-03 (us-gaap:NetCashProvidedByUsedInOperatingActivities) | C161: 19962000000 | D161: https://www.sec.gov/Archives/edgar/data/1730168/000173016825000121/
A162: F43 | B162: cfo FY ending 2025-11-02 (us-gaap:NetCashProvidedByUsedInOperatingActivities) | C162: 27537000000 | D162: https://www.sec.gov/Archives/edgar/data/1730168/000173016825000121/
A163: F44 | B163: cfo YTD 2025-11-03 to 2026-08-02 | C163: 32950000000 | D163: https://www.sec.gov/Archives/edgar/data/1730168/000173016826000080/
A164: F45 | B164: cfo prior-year YTD 2024-11-04 to 2025-08-03 | C164: 19834000000 | D164: https://www.sec.gov/Archives/edgar/data/1730168/000173016826000080/
A165: F46 | B165: cfo TTM to 2026-08-02 | C165: 40653000000
A166: F47 | B166: cfo quarter 2025-11-03 to 2026-02-01 | C166: 8260000000 | D166: https://www.sec.gov/Archives/edgar/data/1730168/000173016826000016/
A167: F48 | B167: capex FY ending 2023-10-29 (us-gaap:PaymentsToAcquirePropertyPlantAndEquipment) | C167: 452000000 | D167: https://www.sec.gov/Archives/edgar/data/1730168/000173016825000121/
A168: F49 | B168: capex FY ending 2024-11-03 (us-gaap:PaymentsToAcquirePropertyPlantAndEquipment) | C168: 548000000 | D168: https://www.sec.gov/Archives/edgar/data/1730168/000173016825000121/
A169: F50 | B169: capex FY ending 2025-11-02 (us-gaap:PaymentsToAcquirePropertyPlantAndEquipment) | C169: 623000000 | D169: https://www.sec.gov/Archives/edgar/data/1730168/000173016825000121/
...
