Workbook

Sheet Summary
A1: MOD standard model (trial) · research run 2026-10-23
A2: The supervisor's reconciled assumption set as a live model. Trial: shown beside the blended page target, not used for trade levels until its weight is decided. Edit blue cells on Model (drivers) and Valuation (assumptions).
A3: Price target box | B3: Value
A4: Live price | B4: =IFERROR(GOOGLEFINANCE("MOD","price"),Valuation!$B$67)
A5: Price as of | B5: =NOW()
A6: Model target (12-month median) | B6: =Distribution!$B$13
A7: Upside to model target from live price | B7: =B6/B4-1
A8: Research target (12m) (no scenario deltas) | B8: =Valuation!$D$7
A9: Probability-weighted mean | B9: =Distribution!$B$10
A10: 10th percentile | B10: =Distribution!$B$14
A11: 25th percentile | B11: =Distribution!$B$15
A12: 75th percentile | B12: =Distribution!$B$16
A13: 90th percentile | B13: =Distribution!$B$17
A14: Target date | B14: =Valuation!$B$45
A15: Price at the run | B15: =Valuation!$B$67
A16: Blended page target (options 67% + agents 33%, not live) | B16: 139.5297
A17: Supervisor research target (12m) (its own methods) | B17: 169.01
A18: Thesis break price (supervisor) | B18: 125
A19: Supervisor confidence | B19: low
A21: Key estimates | B21: FY2026A | C21: =Model!E5 | D21: =Model!F5
A22: Net sales | B22: =IF(Model!D24="","",Model!D24) | C22: =Model!E24 | D22: =Model!F24
A23: % YoY | B23: =IF(Model!D25="","",Model!D25) | C23: =Model!E25 | D23: =Model!F25
A24: Pretax margin | B24: =IF(Model!D35="","",Model!D35) | C24: =Model!E35 | D24: =Model!F35
A25: Diluted EPS (model) | B25: =IF(Model!D42="","",Model!D42) | C25: =Model!E42 | D25: =Model!F42
A26: % YoY | B26: =IF(Model!D43="","",Model!D43) | C26: =Model!E43 | D26: =Model!F43
A27: Free cash flow to firm | B27: =IF(Model!D52="","",Model!D52) | C27: =Model!E52 | D27: =Model!F52
A29: Valuation method | B29: Value per share | C29: Weight
A30: =Valuation!A4 | B30: =Valuation!D4 | C30: =Valuation!E4
A31: =Valuation!A5 | B31: =Valuation!D5 | C31: =Valuation!E5
A32: =Valuation!A6 | B32: =Valuation!D6 | C32: =Valuation!E6
A34: Scenario | B34: Probability | C34: Value at target date | D34: What has to happen
A35: =Distribution!A4 | B35: =Distribution!B4 | C35: =Distribution!C4 | D35: =Distribution!D4
A36: =Distribution!A5 | B36: =Distribution!B5 | C36: =Distribution!C5 | D36: =Distribution!D5
A37: =Distribution!A6 | B37: =Distribution!B6 | C37: =Distribution!C6 | D37: =Distribution!D6
A39: Price at target date | B39: Probability above
A40: =ROUND(Valuation!$B$67*0.7,0) | B40: =SUMPRODUCT(Distribution!$B$4:$B$6,1-NORMSDIST((LN(A40)-LN(Distribution!$C$4:$C$6))/Distribution!$B$9))
A41: =ROUND(Valuation!$B$67*0.8,0) | B41: =SUMPRODUCT(Distribution!$B$4:$B$6,1-NORMSDIST((LN(A41)-LN(Distribution!$C$4:$C$6))/Distribution!$B$9))
A42: =ROUND(Valuation!$B$67*0.9,0) | B42: =SUMPRODUCT(Distribution!$B$4:$B$6,1-NORMSDIST((LN(A42)-LN(Distribution!$C$4:$C$6))/Distribution!$B$9))
A43: =ROUND(Valuation!$B$67*1.0,0) | B43: =SUMPRODUCT(Distribution!$B$4:$B$6,1-NORMSDIST((LN(A43)-LN(Distribution!$C$4:$C$6))/Distribution!$B$9))
A44: =ROUND(Valuation!$B$67*1.1,0) | B44: =SUMPRODUCT(Distribution!$B$4:$B$6,1-NORMSDIST((LN(A44)-LN(Distribution!$C$4:$C$6))/Distribution!$B$9))
A45: =ROUND(Valuation!$B$67*1.2,0) | B45: =SUMPRODUCT(Distribution!$B$4:$B$6,1-NORMSDIST((LN(A45)-LN(Distribution!$C$4:$C$6))/Distribution!$B$9))
A46: =ROUND(Valuation!$B$67*1.3,0) | B46: =SUMPRODUCT(Distribution!$B$4:$B$6,1-NORMSDIST((LN(A46)-LN(Distribution!$C$4:$C$6))/Distribution!$B$9))
A47: =ROUND(Valuation!$B$67*1.5,0) | B47: =SUMPRODUCT(Distribution!$B$4:$B$6,1-NORMSDIST((LN(A47)-LN(Distribution!$C$4:$C$6))/Distribution!$B$9))
A49: Model checks | B49: Status
A50: Scenario probabilities sum to 100% | B50: =IF(ABS(Distribution!B8-1)<0.005,"ok","FLAG: "&TEXT(Distribution!B8,"0.0%"))
A51: WACC exceeds terminal growth by 1 point or more | B51: =IF('Calc - research target (12m)'!B55="ok","ok","FLAG")
A52: Projection runs a full year past the target date | B52: =IF('Calc - research target (12m)'!B56="ok","ok","FLAG")
A53: Method weights add up to more than zero | B53: =IF(SUM(Valuation!E4:E6)>0,"ok","FLAG")
A54: Terminal value under 85% of the DCF | B54: =IF('Calc - research target (12m)'!B46<0.85,"ok","note: "&TEXT('Calc - research target (12m)'!B46,"0%")&" of the DCF is terminal value")
A55: Segment base revenues tie to the last reported net sales (within 2%) | B55: =IF(ABS(Valuation!$B$90/Valuation!$B$50-1)<=0.02,"ok","FLAG")
A56: Matches the engine run at publication (target, research target (12m)) | B56: =IF(AND(ABS(Distribution!$B$13-168.7888)<0.01,ABS(Valuation!$D$7-169.0132)<0.01),"ok","inputs edited since publication")
A57: All checks | B57: =IF(COUNTIF(B50:B56,"ok")=7,"all ok",7-COUNTIF(B50:B56,"ok")&" to look at")

Sheet Model
A1: MOD: annual model, base case
A2: (M of US dollars except per share; fiscal years named by the calendar year they end in)
A3: Blue = input · black = formula · green = link to another tab · actuals from SEC filings (fact ids in the last column, links on Sources)
A5: Fiscal year | B5: FY2024A | C5: FY2025A | D5: FY2026A | E5: FY2027E | F5: FY2028E | G5: FY2029E | H5: Source / note
A6: Period end | B6: 45382 | C6: 45747 | D6: 46112 | E6: =IF(DAY(Valuation!$B$49+1)=1,EOMONTH(Valuation!$B$49,12*E7),EDATE(Valuation!$B$49,12*E7)) | F6: =IF(DAY(Valuation!$B$49+1)=1,EOMONTH(Valuation!$B$49,12*F7),EDATE(Valuation!$B$49,12*F7)) | G6: =IF(DAY(Valuation!$B$49+1)=1,EOMONTH(Valuation!$B$49,12*G7),EDATE(Valuation!$B$49,12*G7))
A7: Projection year | B7: -2 | C7: -1 | D7: 0 | E7: 1 | F7: 2 | G7: 3
A10: Segment build (blue = input: revenue growth and EBIT margin by segment and year)
A11: Data Centers | D11: =Valuation!$B$88 | E11: =Valuation!$B$88*(1+E12) | F11: =E11*(1+F12) | G11: =F11*(1+G12)
A12: Revenue growth | E12: 0.64997293 | F12: 0.41646158 | G12: 0.2007722
A13: Segment EBIT | E13: =E11*E14 | F13: =F11*F14 | G13: =G11*G14
A14: EBIT margin | E14: 0.1742 | F14: 0.1772 | G14: 0.1772
A15: Commercial HVAC | D15: =Valuation!$B$89 | E15: =Valuation!$B$89*(1+E16) | F15: =E15*(1+F16) | G15: =F15*(1+G16)
A16: Revenue growth | E16: 0.067981105 | F16: 0.057692308 | G16: 0.063636364
A17: Segment EBIT | E17: =E15*E18 | F17: =F15*F18 | G17: =G15*G18
A18: EBIT margin | E18: 0.1422 | F18: 0.1447 | G18: 0.1447
A19: Total segment revenue (= net sales) | D19: =D11+D15 | E19: =E11+E15 | F19: =F11+F15 | G19: =G11+G15 | H19: base revenues on Valuation (segment build); net sales = this total
A20: Total segment EBIT | E20: =E13+E17 | F20: =F13+F17 | G20: =G13+G17
A21: Corporate / unallocated EBIT (blue = input) | E21: -80 | F21: -82 | G21: -85 | H21: years[].corporate_ebit; EBIT = total segment EBIT + corporate
A23: Sales
A24: Net sales | B24: 2407.8 | C24: 2583.5 | D24: 3181.1 | E24: =E19 | F24: =F19 | G24: =G19 | H24: SEC XBRL F1, F2, F3
A25: % YoY | C25: =IF(OR(C24="",B24="",B24=0),"",C24/B24-1) | D25: =IF(OR(D24="",C24="",C24=0),"",D24/C24-1) | E25: =E24/Valuation!$B$50-1 | F25: =F24/E24-1 | G25: =G24/F24-1
A27: Operating profit
A28: EBIT (operating income) | E28: =E20+E21 | F28: =F20+F21 | G28: =G20+G21
A29: EBIT margin | E29: =E28/E24 | F29: =F28/F24 | G29: =G28/G24
A30: D&A | B30: 56.1 | C30: 77.7 | D30: 79.7 | E30: =E24*E64 | F30: =F24*F64 | G30: =G24*G64 | H30: SEC XBRL F34, F35, F36
A31: EBITDA | E31: =E28+E30 | F31: =F28+F30 | G31: =G28+G30
A32: EBITDA margin | E32: =E31/E24 | F32: =F31/F24 | G32: =G31/G24
A33: Net interest income / (expense) | E33: =-Valuation!$B$58*Valuation!$B$56 | F33: =-Valuation!$B$58*E58 | G33: =-Valuation!$B$58*F58 | H33: rate x prior year-end net debt (memo roll)
A34: Pretax income | B34: 214.6 | C34: 254 | D34: 186.5 | E34: =E28+E33 | F34: =F28+F33 | G34: =G28+G33 | H34: SEC XBRL F83, F84, F85
A35: Pretax margin | B35: =B34/B24 | C35: =C34/C24 | D35: =D34/D24 | E35: =E34/E24 | F35: =F34/F24 | G35: =G34/G24
A36: Income tax | B36: 51.2 | C36: 68.5 | D36: 63.2 | E36: =E34*E63 | F36: =F34*F63 | G36: =G34*G63 | H36: SEC XBRL F76, F77, F78
A37: Effective tax rate | B37: =B36/B34 | C37: =C36/C34 | D37: =D36/D34 | E37: =E36/E34 | F37: =F36/F34 | G37: =G36/G34
A38: Net income | B38: 161.5 | C38: 184 | D38: 121.5 | E38: =E34-E36 | F38: =F34-F36 | G38: =G34-G36 | H38: SEC XBRL F15, F16, F17
A39: % YoY | C39: =IF(OR(C38="",B38="",B38=0),"",C38/B38-1) | D39: =IF(OR(D38="",C38="",C38=0),"",D38/C38-1) | E39: =IF(OR(D38="",D38=0),"",E38/D38-1) | F39: =IF(OR(E38="",E38=0),"",F38/E38-1) | G39: =IF(OR(F38="",F38=0),"",G38/F38-1)
A40: Diluted shares (M, average) | B40: 53.4 | C40: 53.9 | D40: 53.8 | E40: =Valuation!$B$60*(1+Valuation!$B$62)^(E7-0.5-((Valuation!$B$61-Valuation!$B$49)/365.25)) | F40: =Valuation!$B$60*(1+Valuation!$B$62)^(F7-0.5-((Valuation!$B$61-Valuation!$B$49)/365.25)) | G40: =Valuation!$B$60*(1+Valuation!$B$62)^(G7-0.5-((Valuation!$B$61-Valuation!$B$49)/365.25)) | H40: diluted count rolled at the annual change to mid-year
A41: % YoY | C41: =IF(OR(C40="",B40="",B40=0),"",C40/B40-1) | D41: =IF(OR(D40="",C40="",C40=0),"",D40/C40-1) | E41: =IF(OR(D40="",D40=0),"",E40/D40-1) | F41: =IF(OR(E40="",E40=0),"",F40/E40-1) | G41: =IF(OR(F40="",F40=0),"",G40/F40-1)
A42: Diluted EPS | B42: 3.03 | C42: 3.42 | D42: 2.26 | E42: =E38/E40 | F42: =F38/F40 | G42: =G38/G40 | H42: SEC XBRL F22, F23, F24
A43: % YoY | C43: =IF(OR(C42="",B42="",B42=0),"",C42/B42-1) | D43: =IF(OR(D42="",C42="",C42=0),"",D42/C42-1) | E43: =IF(OR(D42="",D42=0),"",E42/D42-1) | F43: =IF(OR(E42="",E42=0),"",F42/E42-1) | G43: =IF(OR(F42="",F42=0),"",G42/F42-1)
A45: Cash flow
A46: NOPAT (EBIT x (1 - tax)) | E46: =E28*(1-E63) | F46: =F28*(1-F63) | G46: =G28*(1-G63)
A47: + D&A | B47: =B30 | C47: =C30 | D47: =D30 | E47: =E30 | F47: =F30 | G47: =G30
A48: - Capex | B48: 87.7 | C48: 84 | D48: 143.3 | E48: =E24*E65 | F48: =F24*F65 | G48: =G24*G65 | H48: SEC XBRL F55, F56, F57
A49: Capex % of sales | B49: =B48/B24 | C49: =C48/C24 | D49: =D48/D24 | E49: =E48/E24 | F49: =F48/F24 | G49: =G48/G24
A50: - Working capital increase | E50: =E66*(E24-Valuation!$B$50) | F50: =F66*(F24-E24) | G50: =G66*(G24-F24)
A51: - Stock comp (adjusted EBIT only) | E51: =IF(AND(Valuation!$B$47="adjusted",Valuation!$B$48="cost"),E55*(1-E63),0) | F51: =IF(AND(Valuation!$B$47="adjusted",Valuation!$B$48="cost"),F55*(1-F63),0) | G51: =IF(AND(Valuation!$B$47="adjusted",Valuation!$B$48="cost"),G55*(1-G63),0)
A52: Free cash flow to firm | E52: =E46+E47-E48-E50-E51 | F52: =F46+F47-F48-F50-F51 | G52: =G46+G47-G48-G50-G51 | H52: what the DCF discounts (Calc tabs)
A53: Operating cash flow (reported) | B53: 214.6 | C53: 213.3 | D53: 248.7 | H53: SEC XBRL F48, F49, F50
A54: FCF (operating cash flow - capex) | B54: =B53-B48 | C54: =C53-C48 | D54: =D53-D48
A55: Stock comp (memo) | B55: 10.8 | C55: 26.4 | D55: 22.1 | E55: =E24*E67 | F55: =F24*F67 | G55: =G24*G67 | H55: SEC XBRL F41, F42, F43
A56: Buybacks + dividends + other uses | E56: =E24*E69+E68+E70 | F56: =F24*F69+F68+F70 | G56: =G24*G69+G68+G70
A57: % of sales | B57: =B56/B24 | C57: =C56/C24 | D57: =D56/D24 | E57: =E56/E24 | F57: =F56/F24 | G57: =G56/G24
A58: Net debt / (net cash), year end (memo) | E58: =Valuation!$B$56-E52-E33*(1-E63)+E56 | F58: =E58-F52-F33*(1-F63)+F56 | G58: =F58-G52-G33*(1-G63)+G56 | H58: rolled from the balance-date figure; feeds interest only
A60: Drivers (blue = input; a year left black carries the prior year)
A61: Revenue growth | C61: =C25 | D61: =D25 | E61: =E25 | F61: =F25 | G61: =G25 | H61: implied by the segment build (edit the segment rows)
A62: EBIT margin | E62: =E29 | F62: =F29 | G62: =G29 | H62: implied by the segment build and corporate EBIT
A63: Tax rate | B63: =B37 | C63: =C37 | D63: =D37 | E63: 0.24 | F63: =E63 | G63: =F63
A64: D&A % revenue | B64: =B30/B24 | C64: =C30/C24 | D64: =D30/D24 | E64: 0.0228 | F64: =E64 | G64: =F64
A65: Capex % revenue | B65: =B49 | C65: =C49 | D65: =D49 | E65: 0.05 | F65: =E65 | G65: =F65
A66: Working capital % of revenue increase | E66: 0.1 | F66: =E66 | G66: =F66
A67: Stock comp % revenue | B67: =B55/B24 | C67: =C55/C24 | D67: =D55/D24 | E67: 0 | F67: =E67 | G67: =F67
A68: Shareholder returns ($) | E68: 0 | F68: =E68 | G68: =F68
A69: Shareholder returns % revenue | B69: =B57 | C69: =C57 | D69: =D57 | E69: 0 | F69: =E69 | G69: =F69
A70: Other uses of cash ($: M&A, investments) | E70: 0 | F70: =E70 | G70: =F70
A71: Adj. EBITDA addback % revenue | E71: 0 | F71: =E71 | G71: =F71
A73: Versus company guidance and street consensus
A74: Guidance: Data Centers net sales growth (segment), midpoint | E74: =AVERAGE(0.6,0.8) | H74: 0.6 to 0.8; as of 2026-07-29; source 5 (Modine Q1 FY27 slides Ex.99.2 (slide 12 segment outlook))
A75: Guidance: Commercial HVAC net sales growth (segment), midpoint | E75: =AVERAGE(0.05,0.1) | H75: 0.05 to 0.1; as of 2026-07-29; source 5 (Modine Q1 FY27 slides Ex.99.2 (slide 12 segment outlook))
A76: Guidance: adj. EBITDA (consolidated incl. PT) (adjusted, pre-separation), midpoint | E76: =AVERAGE(650,680) | H76: 650 to 680; as of 2026-05-26; source 26 (Modine 8-K Ex.99.1, FY2026 results (record adj. EBITDA $471.)

Sheet Valuation
A1: MOD: valuation and price target derivation
A2: Value per share at the target date = weighted methods below; the 12-month target is the median of the scenario mix (Distribution tab).
A3: Method | B3: Multiple | C3: Metric at target date | D3: Value per share | E3: Weight | F3: Contribution
A4: ='Calc - research target (12m)'!A67 | B4: =IF('Calc - research target (12m)'!C67="","",'Calc - research target (12m)'!C67) | C4: =IF('Calc - research target (12m)'!I67="","",'Calc - research target (12m)'!I67) | D4: ='Calc - research target (12m)'!F67 | E4: ='Calc - research target (12m)'!G67 | F4: =D4*E4/SUM($E$4:$E$6)
A5: ='Calc - research target (12m)'!A68 | B5: =IF('Calc - research target (12m)'!C68="","",'Calc - research target (12m)'!C68) | C5: =IF('Calc - research target (12m)'!I68="","",'Calc - research target (12m)'!I68) | D5: ='Calc - research target (12m)'!F68 | E5: ='Calc - research target (12m)'!G68 | F5: =D5*E5/SUM($E$4:$E$6)
A6: ='Calc - research target (12m)'!A69 | B6: =IF('Calc - research target (12m)'!C69="","",'Calc - research target (12m)'!C69) | C6: =IF('Calc - research target (12m)'!I69="","",'Calc - research target (12m)'!I69) | D6: ='Calc - research target (12m)'!F69 | E6: ='Calc - research target (12m)'!G69 | F6: =D6*E6/SUM($E$4:$E$6)
A7: Research target (12m) per share | D7: ='Calc - research target (12m)'!$F$70 | F7: =SUM(F4:F6)
A9: 12-month EPS basis (what the P/E is applied to)
A10: Fiscal year | B10: =Model!E5 | C10: =Model!F5 | D10: =Model!G5
A11: Share of the 12 months after the target date | B11: ='Calc - research target (12m)'!C38 | C11: ='Calc - research target (12m)'!D38 | D11: ='Calc - research target (12m)'!E38
A12: Model EPS (Model tab) | B12: =Model!E42 | C12: =Model!F42 | D12: =Model!G42
A13: Model EPS, next 12 months after the target date | B13: =SUMPRODUCT(B11:D11,B12:D12)
A16: DCF build (free cash flow to firm, discounted to the target date)
A17: Fiscal year | B17: =Model!E5 | C17: =Model!F5 | D17: =Model!G5
A18: Free cash flow to firm | B18: ='Calc - research target (12m)'!C31 | C18: ='Calc - research target (12m)'!D31 | D18: ='Calc - research target (12m)'!E31
A19: Share of the year after the target date | B19: ='Calc - research target (12m)'!C35 | C19: ='Calc - research target (12m)'!D35 | D19: ='Calc - research target (12m)'!E35
A20: PV at target date | B20: ='Calc - research target (12m)'!C36 | C20: ='Calc - research target (12m)'!D36 | D20: ='Calc - research target (12m)'!E36
A22: PV of free cash flow after the target date | B22: ='Calc - research target (12m)'!B42
A23: Terminal value (final year) | B23: ='Calc - research target (12m)'!B43
A24: PV of terminal value | B24: ='Calc - research target (12m)'!B44
A25: Enterprise value at target date | B25: ='Calc - research target (12m)'!B45
A26: Terminal value share of DCF | B26: ='Calc - research target (12m)'!B46
A27: Net debt at target date | B27: ='Calc - research target (12m)'!B50
A28: Minority interests | B28: ='Calc - research target (12m)'!B51
A29: Adjustments | B29: ='Calc - research target (12m)'!B52
A30: Diluted shares at target date (M) | B30: ='Calc - research target (12m)'!B53
A31: DCF value per share | B31: ='Calc - research target (12m)'!F67
A32: WACC | B32: ='Calc - research target (12m)'!B12
A42: Assumptions (blue = input; sources on the Sources tab)
A43: Input | B43: Value | C43: Basis / note
A44: Run date (valuation as of) | B44: 46318
A45: Target date (run date + 365 days) | B45: =B44+365 | C45: 12-month horizon
A46: Money unit | B46: $M
A47: EBIT basis (gaap / adjusted) | B47: adjusted | C47: gaap = after stock comp
A48: Stock comp treatment (cost / dilution) | B48: dilution | C48: used only when EBIT is adjusted
A49: Last reported fiscal year end | B49: 46112
A50: Net sales, last reported year ($M) | B50: 2082
A51: WACC | B51: 0.1 | C51: not used: no DCF leg (Kilian 2026-10-21); a placeholder so the DCF block still computes
A52: Terminal method (gordon / exit_multiple / steady_state) | B52: gordon
A53: Terminal growth | B53: 0.02
A54: Exit EV/EBITDA (exit_multiple only)
A55: Balance-sheet date | B55: 46296
A56: Net debt / (net cash) at balance date ($M) | B56: 280 | C56: excludes operating leases
A57: Minority interests + preferred stock | B57: 0
A58: Interest rate on net debt / cash | B58: 0.0536
A59: Net debt at target date (override; blank = bridge) | B59: 280
A60: Diluted shares (M) | B60: 54
A61: Share count date | B61: 46203
A62: Annual change in diluted shares | B62: 0 | C62: net of buybacks and stock-comp dilution
A63: Shares at target date (override; blank = from annual change)
A64: DCF weight | B64: 0 | C64: Kilian 2026-10-21: 0 unless the name has a DCF leg (dcf_policy)
A65: Sum-of-the-parts weight | B65: 0
A66: Spread within each scenario (lognormal vol) | B66: 0.15
A67: Share price at the run | B67: 133.34 | C67: close used by the run (2026-10-23)
A69: Target multiple | B69: Multiple | C69: Weight | D69: Basis (ntm / ltm) | E69: EBITDA basis | F69: Stated EPS | G69: Stated FCF/share | H69: Levered | I69: Peer basis
A70: EV/EBITDA | B70: 13.57 | C70: 0.6 | D70: ntm | E70: adjusted | H70: TRUE | I70: at the 14.17x median of the 12-peer set (consensus NTM EBITDA, 2026-10-23; Kilian card 2026-10-26 06:25Z: plain medians, no discount); comps_review 2026-10-26 EXIT k=0.8 (2026-10-26T12:30Z): 14.17 x (13.43 / 14.17)^0.8 = 13.57x; own 13.43x (post-spin net debt 265.3M from the 8-K/A pro forma) on the post-spin model NTM (see inputs_detail exit row) (was 14.17x).
A71: P/E | B71: 21.25 | C71: 0.4 | D71: ntm | E71: gaap | H71: TRUE | I71: at the 23.23x NTM P/E median of the 12-peer set on MOD EPS basis (amortization in, stock comp expensed); EPS = model NTM (EBITDA - D&A - interest) x 0.76 / 54.0M, driver-linked EXIT k=0.8 (2026-10-26T12:30Z): 23.23 x (20.78 / 23.23)^0.8 = 21.25x; own 20.78x on the post-spin model NTM (was 23.23x).
A73: Segment (sum of the parts) | B73: NTM metric | C73: Metric | D73: Multiple | E73: Note
A74: none
A76: Adjustment (equity level) | B76: Value | C76: Probability | D76: Note
A77: none
A79: Custom method | B79: Value per share | C79: Weight | D79: Explanation
A80: none
A82: Scenario | B82: Probability | C82: Growth Δ | D82: Margin Δ | E82: Multiple Δ (turns) | F82: WACC Δ | G82: Multiple %Δ (FCF yield, segments) | H82: Stated EPS/FCF %Δ | I82: Custom methods %Δ | J82: Story
A83: bear | B83: 0.25 | E83: -4 | J83: Agents 1-5 bear (P 25%): AI capex digestion / share loss / LTA customer slip; DC FY28 growth ~15-20% (dc_rev -15% every year), DC margin stuck ~16% (-4pt), corporate ~-$90M (-$10M); NTM EBITDA ~$480M (agents median $480M); de-rate to ~13x EBITDA / ~20.5x EPS (multiple -4 turns, agents 12-13.5x). | K83: driver deltas: dc_rev -0.15 %; dc_margin -0.04; corp_cost -10
A84: base | B84: 0.5 | J84: [exit k=0.8 2026-10-26: EV/EBITDA 14.17x -> 13.57x; P/E 23.23x -> 21.25x] Agents median build: DC +65% / +42% / +20% at ~20%, CHVAC ~+6% at ~16.6%, corporate -$80-85M; 17x / 24.5x.
A85: bull | B85: 0.25 | E85: 3 | J85: Agents 1-5 bull (P 25%): DC on management's 50-70% path (dc_rev +15%), margins 21%+ (+1.5pt); NTM EBITDA ~$800M (agents $790-820M); ~20x EBITDA (multiple +3 turns, agents 19.5-21x). | K85: driver deltas: dc_rev +0.15 %; dc_margin +0.015
A87: Segment build (segment_build) | B87: Base revenue ($M) | C87: Driver note (growth and EBIT margin by year: Model tab)
A88: Data Centers | B88: 1108.2 | C88: dc_rev level; EBIT margin = dc_margin - D&A % of revenue
A89: Commercial HVAC | B89: 973.8 | C89: chvac_rev level; EBIT margin = chvac_margin - D&A %
A90: Sum of segment base revenues | B90: =SUM(B88:B89) | C90: =IF(ABS(B90/Valuation!$B$50-1)<=0.02,"ties to the last reported net sales (within 2%)","FLAG: does not tie to the last reported net sales")

Sheet Sensitivity
A1: MOD: sensitivity tables (bold = current inputs; every cell recalculates from the live model)
A3: DCF value per share: WACC (down) x terminal growth (across)
A4: WACC \ growth | B4: =Valuation!$B$53+(-0.01) | C4: =Valuation!$B$53+(-0.005) | D4: =Valuation!$B$53+(0) | E4: =Valuation!$B$53+(0.005) | F4: =Valuation!$B$53+(0.01)
A5: =Valuation!$B$51+(-0.01) | B5: =IF($A5-B$4<=0.01,"n/a",((SUMPRODUCT('Calc - research target (12m)'!$C$31:$E$31,'Calc - research target (12m)'!$C$35:$E$35,(1+$A5)^(-('Calc - research target (12m)'!$C$19:$E$19-'Calc - research target (12m)'!$B$13)))+'Calc - research target (12m)'!$E$31*(1+B$4)/($A5-B$4)/(1+$A5)^('Calc - research target (12m)'!$B$16-'Calc - research target (12m)'!$B$13))-'Calc - research target (12m)'!$B$50-'Calc - research target (12m)'!$B$51+'Calc - research target (12m)'!$B$52)/'Calc - research target (12m)'!$B$53) | C5: =IF($A5-C$4<=0.01,"n/a",((SUMPRODUCT('Calc - research target (12m)'!$C$31:$E$31,'Calc - research target (12m)'!$C$35:$E$35,(1+$A5)^(-('Calc - research target (12m)'!$C$19:$E$19-'Calc - research target (12m)'!$B$13)))+'Calc - research target (12m)'!$E$31*(1+C$4)/($A5-C$4)/(1+$A5)^('Calc - research target (12m)'!$B$16-'Calc - research target (12m)'!$B$13))-'Calc - research target (12m)'!$B$50-'Calc - research target (12m)'!$B$51+'Calc - research target (12m)'!$B$52)/'Calc - research target (12m)'!$B$53) | D5: =IF($A5-D$4<=0.01,"n/a",((SUMPRODUCT('Calc - research target (12m)'!$C$31:$E$31,'Calc - research target (12m)'!$C$35:$E$35,(1+$A5)^(-('Calc - research target (12m)'!$C$19:$E$19-'Calc - research target (12m)'!$B$13)))+'Calc - research target (12m)'!$E$31*(1+D$4)/($A5-D$4)/(1+$A5)^('Calc - research target (12m)'!$B$16-'Calc - research target (12m)'!$B$13))-'Calc - research target (12m)'!$B$50-'Calc - research target (12m)'!$B$51+'Calc - research target (12m)'!$B$52)/'Calc - research target (12m)'!$B$53) | E5: =IF($A5-E$4<=0.01,"n/a",((SUMPRODUCT('Calc - research target (12m)'!$C$31:$E$31,'Calc - research target (12m)'!$C$35:$E$35,(1+$A5)^(-('Calc - research target (12m)'!$C$19:$E$19-'Calc - research target (12m)'!$B$13)))+'Calc - research target (12m)'!$E$31*(1+E$4)/($A5-E$4)/(1+$A5)^('Calc - research target (12m)'!$B$16-'Calc - research target (12m)'!$B$13))-'Calc - research target (12m)'!$B$50-'Calc - research target (12m)'!$B$51+'Calc - research target (12m)'!$B$52)/'Calc - research target (12m)'!$B$53) | F5: =IF($A5-F$4<=0.01,"n/a",((SUMPRODUCT('Calc - research target (12m)'!$C$31:$E$31,'Calc - research target (12m)'!$C$35:$E$35,(1+$A5)^(-('Calc - research target (12m)'!$C$19:$E$19-'Calc - research target (12m)'!$B$13)))+'Calc - research target (12m)'!$E$31*(1+F$4)/($A5-F$4)/(1+$A5)^('Calc - research target (12m)'!$B$16-'Calc - research target (12m)'!$B$13))-'Calc - research target (12m)'!$B$50-'Calc - research target (12m)'!$B$51+'Calc - research target (12m)'!$B$52)/'Calc - research target (12m)'!$B$53)
A6: =Valuation!$B$51+(-0.005) | B6: =IF($A6-B$4<=0.01,"n/a",((SUMPRODUCT('Calc - research target (12m)'!$C$31:$E$31,'Calc - research target (12m)'!$C$35:$E$35,(1+$A6)^(-('Calc - research target (12m)'!$C$19:$E$19-'Calc - research target (12m)'!$B$13)))+'Calc - research target (12m)'!$E$31*(1+B$4)/($A6-B$4)/(1+$A6)^('Calc - research target (12m)'!$B$16-'Calc - research target (12m)'!$B$13))-'Calc - research target (12m)'!$B$50-'Calc - research target (12m)'!$B$51+'Calc - research target (12m)'!$B$52)/'Calc - research target (12m)'!$B$53) | C6: =IF($A6-C$4<=0.01,"n/a",((SUMPRODUCT('Calc - research target (12m)'!$C$31:$E$31,'Calc - research target (12m)'!$C$35:$E$35,(1+$A6)^(-('Calc - research target (12m)'!$C$19:$E$19-'Calc - research target (12m)'!$B$13)))+'Calc - research target (12m)'!$E$31*(1+C$4)/($A6-C$4)/(1+$A6)^('Calc - research target (12m)'!$B$16-'Calc - research target (12m)'!$B$13))-'Calc - research target (12m)'!$B$50-'Calc - research target (12m)'!$B$51+'Calc - research target (12m)'!$B$52)/'Calc - research target (12m)'!$B$53) | D6: =IF($A6-D$4<=0.01,"n/a",((SUMPRODUCT('Calc - research target (12m)'!$C$31:$E$31,'Calc - research target (12m)'!$C$35:$E$35,(1+$A6)^(-('Calc - research target (12m)'!$C$19:$E$19-'Calc - research target (12m)'!$B$13)))+'Calc - research target (12m)'!$E$31*(1+D$4)/($A6-D$4)/(1+$A6)^('Calc - research target (12m)'!$B$16-'Calc - research target (12m)'!$B$13))-'Calc - research target (12m)'!$B$50-'Calc - research target (12m)'!$B$51+'Calc - research target (12m)'!$B$52)/'Calc - research target (12m)'!$B$53) | E6: =IF($A6-E$4<=0.01,"n/a",((SUMPRODUCT('Calc - research target (12m)'!$C$31:$E$31,'Calc - research target (12m)'!$C$35:$E$35,(1+$A6)^(-('Calc - research target (12m)'!$C$19:$E$19-'Calc - research target (12m)'!$B$13)))+'Calc - research target (12m)'!$E$31*(1+E$4)/($A6-E$4)/(1+$A6)^('Calc - research target (12m)'!$B$16-'Calc - research target (12m)'!$B$13))-'Calc - research target (12m)'!$B$50-'Calc - research target (12m)'!$B$51+'Calc - research target (12m)'!$B$52)/'Calc - research target (12m)'!$B$53) | F6: =IF($A6-F$4<=0.01,"n/a",((SUMPRODUCT('Calc - research target (12m)'!$C$31:$E$31,'Calc - research target (12m)'!$C$35:$E$35,(1+$A6)^(-('Calc - research target (12m)'!$C$19:$E$19-'Calc - research target (12m)'!$B$13)))+'Calc - research target (12m)'!$E$31*(1+F$4)/($A6-F$4)/(1+$A6)^('Calc - research target (12m)'!$B$16-'Calc - research target (12m)'!$B$13))-'Calc - research target (12m)'!$B$50-'Calc - research target (12m)'!$B$51+'Calc - research target (12m)'!$B$52)/'Calc - research target (12m)'!$B$53)
A7: =Valuation!$B$51+(0) | B7: =IF($A7-B$4<=0.01,"n/a",((SUMPRODUCT('Calc - research target (12m)'!$C$31:$E$31,'Calc - research target (12m)'!$C$35:$E$35,(1+$A7)^(-('Calc - research target (12m)'!$C$19:$E$19-'Calc - research target (12m)'!$B$13)))+'Calc - research target (12m)'!$E$31*(1+B$4)/($A7-B$4)/(1+$A7)^('Calc - research target (12m)'!$B$16-'Calc - research target (12m)'!$B$13))-'Calc - research target (12m)'!$B$50-'Calc - research target (12m)'!$B$51+'Calc - research target (12m)'!$B$52)/'Calc - research target (12m)'!$B$53) | C7: =IF($A7-C$4<=0.01,"n/a",((SUMPRODUCT('Calc - research target (12m)'!$C$31:$E$31,'Calc - research target (12m)'!$C$35:$E$35,(1+$A7)^(-('Calc - research target (12m)'!$C$19:$E$19-'Calc - research target (12m)'!$B$13)))+'Calc - research target (12m)'!$E$31*(1+C$4)/($A7-C$4)/(1+$A7)^('Calc - research target (12m)'!$B$16-'Calc - research target (12m)'!$B$13))-'Calc - research target (12m)'!$B$50-'Calc - research target (12m)'!$B$51+'Calc - research target (12m)'!$B$52)/'Calc - research target (12m)'!$B$53) | D7: =IF($A7-D$4<=0.01,"n/a",((SUMPRODUCT('Calc - research target (12m)'!$C$31:$E$31,'Calc - research target (12m)'!$C$35:$E$35,(1+$A7)^(-('Calc - research target (12m)'!$C$19:$E$19-'Calc - research target (12m)'!$B$13)))+'Calc - research target (12m)'!$E$31*(1+D$4)/($A7-D$4)/(1+$A7)^('Calc - research target (12m)'!$B$16-'Calc - research target (12m)'!$B$13))-'Calc - research target (12m)'!$B$50-'Calc - research target (12m)'!$B$51+'Calc - research target (12m)'!$B$52)/'Calc - research target (12m)'!$B$53) | E7: =IF($A7-E$4<=0.01,"n/a",((SUMPRODUCT('Calc - research target (12m)'!$C$31:$E$31,'Calc - research target (12m)'!$C$35:$E$35,(1+$A7)^(-('Calc - research target (12m)'!$C$19:$E$19-'Calc - research target (12m)'!$B$13)))+'Calc - research target (12m)'!$E$31*(1+E$4)/($A7-E$4)/(1+$A7)^('Calc - research target (12m)'!$B$16-'Calc - research target (12m)'!$B$13))-'Calc - research target (12m)'!$B$50-'Calc - research target (12m)'!$B$51+'Calc - research target (12m)'!$B$52)/'Calc - research target (12m)'!$B$53) | F7: =IF($A7-F$4<=0.01,"n/a",((SUMPRODUCT('Calc - research target (12m)'!$C$31:$E$31,'Calc - research target (12m)'!$C$35:$E$35,(1+$A7)^(-('Calc - research target (12m)'!$C$19:$E$19-'Calc - research target (12m)'!$B$13)))+'Calc - research target (12m)'!$E$31*(1+F$4)/($A7-F$4)/(1+$A7)^('Calc - research target (12m)'!$B$16-'Calc - research target (12m)'!$B$13))-'Calc - research target (12m)'!$B$50-'Calc - research target (12m)'!$B$51+'Calc - research target (12m)'!$B$52)/'Calc - research target (12m)'!$B$53)
A8: =Valuation!$B$51+(0.005) | B8: =IF($A8-B$4<=0.01,"n/a",((SUMPRODUCT('Calc - research target (12m)'!$C$31:$E$31,'Calc - research target (12m)'!$C$35:$E$35,(1+$A8)^(-('Calc - research target (12m)'!$C$19:$E$19-'Calc - research target (12m)'!$B$13)))+'Calc - research target (12m)'!$E$31*(1+B$4)/($A8-B$4)/(1+$A8)^('Calc - research target (12m)'!$B$16-'Calc - research target (12m)'!$B$13))-'Calc - research target (12m)'!$B$50-'Calc - research target (12m)'!$B$51+'Calc - research target (12m)'!$B$52)/'Calc - research target (12m)'!$B$53) | C8: =IF($A8-C$4<=0.01,"n/a",((SUMPRODUCT('Calc - research target (12m)'!$C$31:$E$31,'Calc - research target (12m)'!$C$35:$E$35,(1+$A8)^(-('Calc - research target (12m)'!$C$19:$E$19-'Calc - research target (12m)'!$B$13)))+'Calc - research target (12m)'!$E$31*(1+C$4)/($A8-C$4)/(1+$A8)^('Calc - research target (12m)'!$B$16-'Calc - research target (12m)'!$B$13))-'Calc - research target (12m)'!$B$50-'Calc - research target (12m)'!$B$51+'Calc - research target (12m)'!$B$52)/'Calc - research target (12m)'!$B$53) | D8: =IF($A8-D$4<=0.01,"n/a",((SUMPRODUCT('Calc - research target (12m)'!$C$31:$E$31,'Calc - research target (12m)'!$C$35:$E$35,(1+$A8)^(-('Calc - research target (12m)'!$C$19:$E$19-'Calc - research target (12m)'!$B$13)))+'Calc - research target (12m)'!$E$31*(1+D$4)/($A8-D$4)/(1+$A8)^('Calc - research target (12m)'!$B$16-'Calc - research target (12m)'!$B$13))-'Calc - research target (12m)'!$B$50-'Calc - research target (12m)'!$B$51+'Calc - research target (12m)'!$B$52)/'Calc - research target (12m)'!$B$53) | E8: =IF($A8-E$4<=0.01,"n/a",((SUMPRODUCT('Calc - research target (12m)'!$C$31:$E$31,'Calc - research target (12m)'!$C$35:$E$35,(1+$A8)^(-('Calc - research target (12m)'!$C$19:$E$19-'Calc - research target (12m)'!$B$13)))+'Calc - research target (12m)'!$E$31*(1+E$4)/($A8-E$4)/(1+$A8)^('Calc - research target (12m)'!$B$16-'Calc - research target (12m)'!$B$13))-'Calc - research target (12m)'!$B$50-'Calc - research target (12m)'!$B$51+'Calc - research target (12m)'!$B$52)/'Calc - research target (12m)'!$B$53) | F8: =IF($A8-F$4<=0.01,"n/a",((SUMPRODUCT('Calc - research target (12m)'!$C$31:$E$31,'Calc - research target (12m)'!$C$35:$E$35,(1+$A8)^(-('Calc - research target (12m)'!$C$19:$E$19-'Calc - research target (12m)'!$B$13)))+'Calc - research target (12m)'!$E$31*(1+F$4)/($A8-F$4)/(1+$A8)^('Calc - research target (12m)'!$B$16-'Calc - research target (12m)'!$B$13))-'Calc - research target (12m)'!$B$50-'Calc - research target (12m)'!$B$51+'Calc - research target (12m)'!$B$52)/'Calc - research target (12m)'!$B$53)
A9: =Valuation!$B$51+(0.01) | B9: =IF($A9-B$4<=0.01,"n/a",((SUMPRODUCT('Calc - research target (12m)'!$C$31:$E$31,'Calc - research target (12m)'!$C$35:$E$35,(1+$A9)^(-('Calc - research target (12m)'!$C$19:$E$19-'Calc - research target (12m)'!$B$13)))+'Calc - research target (12m)'!$E$31*(1+B$4)/($A9-B$4)/(1+$A9)^('Calc - research target (12m)'!$B$16-'Calc - research target (12m)'!$B$13))-'Calc - research target (12m)'!$B$50-'Calc - research target (12m)'!$B$51+'Calc - research target (12m)'!$B$52)/'Calc - research target (12m)'!$B$53) | C9: =IF($A9-C$4<=0.01,"n/a",((SUMPRODUCT('Calc - research target (12m)'!$C$31:$E$31,'Calc - research target (12m)'!$C$35:$E$35,(1+$A9)^(-('Calc - research target (12m)'!$C$19:$E$19-'Calc - research target (12m)'!$B$13)))+'Calc - research target (12m)'!$E$31*(1+C$4)/($A9-C$4)/(1+$A9)^('Calc - research target (12m)'!$B$16-'Calc - research target (12m)'!$B$13))-'Calc - research target (12m)'!$B$50-'Calc - research target (12m)'!$B$51+'Calc - research target (12m)'!$B$52)/'Calc - research target (12m)'!$B$53) | D9: =IF($A9-D$4<=0.01,"n/a",((SUMPRODUCT('Calc - research target (12m)'!$C$31:$E$31,'Calc - research target (12m)'!$C$35:$E$35,(1+$A9)^(-('Calc - research target (12m)'!$C$19:$E$19-'Calc - research target (12m)'!$B$13)))+'Calc - research target (12m)'!$E$31*(1+D$4)/($A9-D$4)/(1+$A9)^('Calc - research target (12m)'!$B$16-'Calc - research target (12m)'!$B$13))-'Calc - research target (12m)'!$B$50-'Calc - research target (12m)'!$B$51+'Calc - research target (12m)'!$B$52)/'Calc - research target (12m)'!$B$53) | E9: =IF($A9-E$4<=0.01,"n/a",((SUMPRODUCT('Calc - research target (12m)'!$C$31:$E$31,'Calc - research target (12m)'!$C$35:$E$35,(1+$A9)^(-('Calc - research target (12m)'!$C$19:$E$19-'Calc - research target (12m)'!$B$13)))+'Calc - research target (12m)'!$E$31*(1+E$4)/($A9-E$4)/(1+$A9)^('Calc - research target (12m)'!$B$16-'Calc - research target (12m)'!$B$13))-'Calc - research target (12m)'!$B$50-'Calc - research target (12m)'!$B$51+'Calc - research target (12m)'!$B$52)/'Calc - research target (12m)'!$B$53) | F9: =IF($A9-F$4<=0.01,"n/a",((SUMPRODUCT('Calc - research target (12m)'!$C$31:$E$31,'Calc - research target (12m)'!$C$35:$E$35,(1+$A9)^(-('Calc - research target (12m)'!$C$19:$E$19-'Calc - research target (12m)'!$B$13)))+'Calc - research target (12m)'!$E$31*(1+F$4)/($A9-F$4)/(1+$A9)^('Calc - research target (12m)'!$B$16-'Calc - research target (12m)'!$B$13))-'Calc - research target (12m)'!$B$50-'Calc - research target (12m)'!$B$51+'Calc - research target (12m)'!$B$52)/'Calc - research target (12m)'!$B$53)
A11: Research target (12m) per share: EV/EBITDA multiple (down) x metric at target date (across)
A12: Multiple \ metric | B12: ='Calc - research target (12m)'!$E$68*0.9 | C12: ='Calc - research target (12m)'!$E$68*0.95 | D12: ='Calc - research target (12m)'!$E$68*1.0 | E12: ='Calc - research target (12m)'!$E$68*1.05 | F12: ='Calc - research target (12m)'!$E$68*1.1
A13: =Valuation!$B$70+(-3) | B13: =((SUMPRODUCT('Calc - research target (12m)'!$F$67:$F$69,'Calc - research target (12m)'!$G$67:$G$69)-'Calc - research target (12m)'!$F$68*'Calc - research target (12m)'!$G$68)+'Calc - research target (12m)'!$G$68*((($A13*B$12)-'Calc - research target (12m)'!$B$50-'Calc - research target (12m)'!$B$51+'Calc - research target (12m)'!$B$52)/'Calc - research target (12m)'!$B$53))/SUM('Calc - research target (12m)'!$G$67:$G$69) | C13: =((SUMPRODUCT('Calc - research target (12m)'!$F$67:$F$69,'Calc - research target (12m)'!$G$67:$G$69)-'Calc - research target (12m)'!$F$68*'Calc - research target (12m)'!$G$68)+'Calc - research target (12m)'!$G$68*((($A13*C$12)-'Calc - research target (12m)'!$B$50-'Calc - research target (12m)'!$B$51+'Calc - research target (12m)'!$B$52)/'Calc - research target (12m)'!$B$53))/SUM('Calc - research target (12m)'!$G$67:$G$69) | D13: =((SUMPRODUCT('Calc - research target (12m)'!$F$67:$F$69,'Calc - research target (12m)'!$G$67:$G$69)-'Calc - research target (12m)'!$F$68*'Calc - research target (12m)'!$G$68)+'Calc - research target (12m)'!$G$68*((($A13*D$12)-'Calc - research target (12m)'!$B$50-'Calc - research target (12m)'!$B$51+'Calc - research target (12m)'!$B$52)/'Calc - research target (12m)'!$B$53))/SUM('Calc - research target (12m)'!$G$67:$G$69) | E13: =((SUMPRODUCT('Calc - research target (12m)'!$F$67:$F$69,'Calc - research target (12m)'!$G$67:$G$69)-'Calc - research target (12m)'!$F$68*'Calc - research target (12m)'!$G$68)+'Calc - research target (12m)'!$G$68*((($A13*E$12)-'Calc - research target (12m)'!$B$50-'Calc - research target (12m)'!$B$51+'Calc - research target (12m)'!$B$52)/'Calc - research target (12m)'!$B$53))/SUM('Calc - research target (12m)'!$G$67:$G$69) | F13: =((SUMPRODUCT('Calc - research target (12m)'!$F$67:$F$69,'Calc - research target (12m)'!$G$67:$G$69)-'Calc - research target (12m)'!$F$68*'Calc - research target (12m)'!$G$68)+'Calc - research target (12m)'!$G$68*((($A13*F$12)-'Calc - research target (12m)'!$B$50-'Calc - research target (12m)'!$B$51+'Calc - research target (12m)'!$B$52)/'Calc - research target (12m)'!$B$53))/SUM('Calc - research target (12m)'!$G$67:$G$69)
A14: =Valuation!$B$70+(-2) | B14: =((SUMPRODUCT('Calc - research target (12m)'!$F$67:$F$69,'Calc - research target (12m)'!$G$67:$G$69)-'Calc - research target (12m)'!$F$68*'Calc - research target (12m)'!$G$68)+'Calc - research target (12m)'!$G$68*((($A14*B$12)-'Calc - research target (12m)'!$B$50-'Calc - research target (12m)'!$B$51+'Calc - research target (12m)'!$B$52)/'Calc - research target (12m)'!$B$53))/SUM('Calc - research target (12m)'!$G$67:$G$69) | C14: =((SUMPRODUCT('Calc - research target (12m)'!$F$67:$F$69,'Calc - research target (12m)'!$G$67:$G$69)-'Calc - research target (12m)'!$F$68*'Calc - research target (12m)'!$G$68)+'Calc - research target (12m)'!$G$68*((($A14*C$12)-'Calc - research target (12m)'!$B$50-'Calc - research target (12m)'!$B$51+'Calc - research target (12m)'!$B$52)/'Calc - research target (12m)'!$B$53))/SUM('Calc - research target (12m)'!$G$67:$G$69) | D14: =((SUMPRODUCT('Calc - research target (12m)'!$F$67:$F$69,'Calc - research target (12m)'!$G$67:$G$69)-'Calc - research target (12m)'!$F$68*'Calc - research target (12m)'!$G$68)+'Calc - research target (12m)'!$G$68*((($A14*D$12)-'Calc - research target (12m)'!$B$50-'Calc - research target (12m)'!$B$51+'Calc - research target (12m)'!$B$52)/'Calc - research target (12m)'!$B$53))/SUM('Calc - research target (12m)'!$G$67:$G$69) | E14: =((SUMPRODUCT('Calc - research target (12m)'!$F$67:$F$69,'Calc - research target (12m)'!$G$67:$G$69)-'Calc - research target (12m)'!$F$68*'Calc - research target (12m)'!$G$68)+'Calc - research target (12m)'!$G$68*((($A14*E$12)-'Calc - research target (12m)'!$B$50-'Calc - research target (12m)'!$B$51+'Calc - research target (12m)'!$B$52)/'Calc - research target (12m)'!$B$53))/SUM('Calc - research target (12m)'!$G$67:$G$69) | F14: =((SUMPRODUCT('Calc - research target (12m)'!$F$67:$F$69,'Calc - research target (12m)'!$G$67:$G$69)-'Calc - research target (12m)'!$F$68*'Calc - research target (12m)'!$G$68)+'Calc - research target (12m)'!$G$68*((($A14*F$12)-'Calc - research target (12m)'!$B$50-'Calc - research target (12m)'!$B$51+'Calc - research target (12m)'!$B$52)/'Calc - research target (12m)'!$B$53))/SUM('Calc - research target (12m)'!$G$67:$G$69)
A15: =Valuation!$B$70+(-1) | B15: =((SUMPRODUCT('Calc - research target (12m)'!$F$67:$F$69,'Calc - research target (12m)'!$G$67:$G$69)-'Calc - research target (12m)'!$F$68*'Calc - research target (12m)'!$G$68)+'Calc - research target (12m)'!$G$68*((($A15*B$12)-'Calc - research target (12m)'!$B$50-'Calc - research target (12m)'!$B$51+'Calc - research target (12m)'!$B$52)/'Calc - research target (12m)'!$B$53))/SUM('Calc - research target (12m)'!$G$67:$G$69) | C15: =((SUMPRODUCT('Calc - research target (12m)'!$F$67:$F$69,'Calc - research target (12m)'!$G$67:$G$69)-'Calc - research target (12m)'!$F$68*'Calc - research target (12m)'!$G$68)+'Calc - research target (12m)'!$G$68*((($A15*C$12)-'Calc - research target (12m)'!$B$50-'Calc - research target (12m)'!$B$51+'Calc - research target (12m)'!$B$52)/'Calc - research target (12m)'!$B$53))/SUM('Calc - research target (12m)'!$G$67:$G$69) | D15: =((SUMPRODUCT('Calc - research target (12m)'!$F$67:$F$69,'Calc - research target (12m)'!$G$67:$G$69)-'Calc - research target (12m)'!$F$68*'Calc - research target (12m)'!$G$68)+'Calc - research target (12m)'!$G$68*((($A15*D$12)-'Calc - research target (12m)'!$B$50-'Calc - research target (12m)'!$B$51+'Calc - research target (12m)'!$B$52)/'Calc - research target (12m)'!$B$53))/SUM('Calc - research target (12m)'!$G$67:$G$69) | E15: =((SUMPRODUCT('Calc - research target (12m)'!$F$67:$F$69,'Calc - research target (12m)'!$G$67:$G$69)-'Calc - research target (12m)'!$F$68*'Calc - research target (12m)'!$G$68)+'Calc - research target (12m)'!$G$68*((($A15*E$12)-'Calc - research target (12m)'!$B$50-'Calc - research target (12m)'!$B$51+'Calc - research target (12m)'!$B$52)/'Calc - research target (12m)'!$B$53))/SUM('Calc - research target (12m)'!$G$67:$G$69) | F15: =((SUMPRODUCT('Calc - research target (12m)'!$F$67:$F$69,'Calc - research target (12m)'!$G$67:$G$69)-'Calc - research target (12m)'!$F$68*'Calc - research target (12m)'!$G$68)+'Calc - research target (12m)'!$G$68*((($A15*F$12)-'Calc - research target (12m)'!$B$50-'Calc - research target (12m)'!$B$51+'Calc - research target (12m)'!$B$52)/'Calc - research target (12m)'!$B$53))/SUM('Calc - research target (12m)'!$G$67:$G$69)
A16: =Valuation!$B$70+(0) | B16: =((SUMPRODUCT('Calc - research target (12m)'!$F$67:$F$69,'Calc - research target (12m)'!$G$67:$G$69)-'Calc - research target (12m)'!$F$68*'Calc - research target (12m)'!$G$68)+'Calc - research target (12m)'!$G$68*((($A16*B$12)-'Calc - research target (12m)'!$B$50-'Calc - research target (12m)'!$B$51+'Calc - research target (12m)'!$B$52)/'Calc - research target (12m)'!$B$53))/SUM('Calc - research target (12m)'!$G$67:$G$69) | C16: =((SUMPRODUCT('Calc - research target (12m)'!$F$67:$F$69,'Calc - research target (12m)'!$G$67:$G$69)-'Calc - research target (12m)'!$F$68*'Calc - research target (12m)'!$G$68)+'Calc - research target (12m)'!$G$68*((($A16*C$12)-'Calc - research target (12m)'!$B$50-'Calc - research target (12m)'!$B$51+'Calc - research target (12m)'!$B$52)/'Calc - research target (12m)'!$B$53))/SUM('Calc - research target (12m)'!$G$67:$G$69) | D16: =((SUMPRODUCT('Calc - research target (12m)'!$F$67:$F$69,'Calc - research target (12m)'!$G$67:$G$69)-'Calc - research target (12m)'!$F$68*'Calc - research target (12m)'!$G$68)+'Calc - research target (12m)'!$G$68*((($A16*D$12)-'Calc - research target (12m)'!$B$50-'Calc - research target (12m)'!$B$51+'Calc - research target (12m)'!$B$52)/'Calc - research target (12m)'!$B$53))/SUM('Calc - research target (12m)'!$G$67:$G$69) | E16: =((SUMPRODUCT('Calc - research target (12m)'!$F$67:$F$69,'Calc - research target (12m)'!$G$67:$G$69)-'Calc - research target (12m)'!$F$68*'Calc - research target (12m)'!$G$68)+'Calc - research target (12m)'!$G$68*((($A16*E$12)-'Calc - research target (12m)'!$B$50-'Calc - research target (12m)'!$B$51+'Calc - research target (12m)'!$B$52)/'Calc - research target (12m)'!$B$53))/SUM('Calc - research target (12m)'!$G$67:$G$69) | F16: =((SUMPRODUCT('Calc - research target (12m)'!$F$67:$F$69,'Calc - research target (12m)'!$G$67:$G$69)-'Calc - research target (12m)'!$F$68*'Calc - research target (12m)'!$G$68)+'Calc - research target (12m)'!$G$68*((($A16*F$12)-'Calc - research target (12m)'!$B$50-'Calc - research target (12m)'!$B$51+'Calc - research target (12m)'!$B$52)/'Calc - research target (12m)'!$B$53))/SUM('Calc - research target (12m)'!$G$67:$G$69)
A17: =Valuation!$B$70+(1) | B17: =((SUMPRODUCT('Calc - research target (12m)'!$F$67:$F$69,'Calc - research target (12m)'!$G$67:$G$69)-'Calc - research target (12m)'!$F$68*'Calc - research target (12m)'!$G$68)+'Calc - research target (12m)'!$G$68*((($A17*B$12)-'Calc - research target (12m)'!$B$50-'Calc - research target (12m)'!$B$51+'Calc - research target (12m)'!$B$52)/'Calc - research target (12m)'!$B$53))/SUM('Calc - research target (12m)'!$G$67:$G$69) | C17: =((SUMPRODUCT('Calc - research target (12m)'!$F$67:$F$69,'Calc - research target (12m)'!$G$67:$G$69)-'Calc - research target (12m)'!$F$68*'Calc - research target (12m)'!$G$68)+'Calc - research target (12m)'!$G$68*((($A17*C$12)-'Calc - research target (12m)'!$B$50-'Calc - research target (12m)'!$B$51+'Calc - research target (12m)'!$B$52)/'Calc - research target (12m)'!$B$53))/SUM('Calc - research target (12m)'!$G$67:$G$69) | D17: =((SUMPRODUCT('Calc - research target (12m)'!$F$67:$F$69,'Calc - research target (12m)'!$G$67:$G$69)-'Calc - research target (12m)'!$F$68*'Calc - research target (12m)'!$G$68)+'Calc - research target (12m)'!$G$68*((($A17*D$12)-'Calc - research target (12m)'!$B$50-'Calc - research target (12m)'!$B$51+'Calc - research target (12m)'!$B$52)/'Calc - research target (12m)'!$B$53))/SUM('Calc - research target (12m)'!$G$67:$G$69) | E17: =((SUMPRODUCT('Calc - research target (12m)'!$F$67:$F$69,'Calc - research target (12m)'!$G$67:$G$69)-'Calc - research target (12m)'!$F$68*'Calc - research target (12m)'!$G$68)+'Calc - research target (12m)'!$G$68*((($A17*E$12)-'Calc - research target (12m)'!$B$50-'Calc - research target (12m)'!$B$51+'Calc - research target (12m)'!$B$52)/'Calc - research target (12m)'!$B$53))/SUM('Calc - research target (12m)'!$G$67:$G$69) | F17: =((SUMPRODUCT('Calc - research target (12m)'!$F$67:$F$69,'Calc - research target (12m)'!$G$67:$G$69)-'Calc - research target (12m)'!$F$68*'Calc - research target (12m)'!$G$68)+'Calc - research target (12m)'!$G$68*((($A17*F$12)-'Calc - research target (12m)'!$B$50-'Calc - research target (12m)'!$B$51+'Calc - research target (12m)'!$B$52)/'Calc - research target (12m)'!$B$53))/SUM('Calc - research target (12m)'!$G$67:$G$69)
A18: =Valuation!$B$70+(2) | B18: =((SUMPRODUCT('Calc - research target (12m)'!$F$67:$F$69,'Calc - research target (12m)'!$G$67:$G$69)-'Calc - research target (12m)'!$F$68*'Calc - research target (12m)'!$G$68)+'Calc - research target (12m)'!$G$68*((($A18*B$12)-'Calc - research target (12m)'!$B$50-'Calc - research target (12m)'!$B$51+'Calc - research target (12m)'!$B$52)/'Calc - research target (12m)'!$B$53))/SUM('Calc - research target (12m)'!$G$67:$G$69) | C18: =((SUMPRODUCT('Calc - research target (12m)'!$F$67:$F$69,'Calc - research target (12m)'!$G$67:$G$69)-'Calc - research target (12m)'!$F$68*'Calc - research target (12m)'!$G$68)+'Calc - research target (12m)'!$G$68*((($A18*C$12)-'Calc - research target (12m)'!$B$50-'Calc - research target (12m)'!$B$51+'Calc - research target (12m)'!$B$52)/'Calc - research target (12m)'!$B$53))/SUM('Calc - research target (12m)'!$G$67:$G$69) | D18: =((SUMPRODUCT('Calc - research target (12m)'!$F$67:$F$69,'Calc - research target (12m)'!$G$67:$G$69)-'Calc - research target (12m)'!$F$68*'Calc - research target (12m)'!$G$68)+'Calc - research target (12m)'!$G$68*((($A18*D$12)-'Calc - research target (12m)'!$B$50-'Calc - research target (12m)'!$B$51+'Calc - research target (12m)'!$B$52)/'Calc - research target (12m)'!$B$53))/SUM('Calc - research target (12m)'!$G$67:$G$69) | E18: =((SUMPRODUCT('Calc - research target (12m)'!$F$67:$F$69,'Calc - research target (12m)'!$G$67:$G$69)-'Calc - research target (12m)'!$F$68*'Calc - research target (12m)'!$G$68)+'Calc - research target (12m)'!$G$68*((($A18*E$12)-'Calc - research target (12m)'!$B$50-'Calc - research target (12m)'!$B$51+'Calc - research target (12m)'!$B$52)/'Calc - research target (12m)'!$B$53))/SUM('Calc - research target (12m)'!$G$67:$G$69) | F18: =((SUMPRODUCT('Calc - research target (12m)'!$F$67:$F$69,'Calc - research target (12m)'!$G$67:$G$69)-'Calc - research target (12m)'!$F$68*'Calc - research target (12m)'!$G$68)+'Calc - research target (12m)'!$G$68*((($A18*F$12)-'Calc - research target (12m)'!$B$50-'Calc - research target (12m)'!$B$51+'Calc - research target (12m)'!$B$52)/'Calc - research target (12m)'!$B$53))/SUM('Calc - research target (12m)'!$G$67:$G$69)
A19: =Valuation!$B$70+(3) | B19: =((SUMPRODUCT('Calc - research target (12m)'!$F$67:$F$69,'Calc - research target (12m)'!$G$67:$G$69)-'Calc - research target (12m)'!$F$68*'Calc - research target (12m)'!$G$68)+'Calc - research target (12m)'!$G$68*((($A19*B$12)-'Calc - research target (12m)'!$B$50-'Calc - research target (12m)'!$B$51+'Calc - research target (12m)'!$B$52)/'Calc - research target (12m)'!$B$53))/SUM('Calc - research target (12m)'!$G$67:$G$69) | C19: =((SUMPRODUCT('Calc - research target (12m)'!$F$67:$F$69,'Calc - research target (12m)'!$G$67:$G$69)-'Calc - research target (12m)'!$F$68*'Calc - research target (12m)'!$G$68)+'Calc - research target (12m)'!$G$68*((($A19*C$12)-'Calc - research target (12m)'!$B$50-'Calc - research target (12m)'!$B$51+'Calc - research target (12m)'!$B$52)/'Calc - research target (12m)'!$B$53))/SUM('Calc - research target (12m)'!$G$67:$G$69) | D19: =((SUMPRODUCT('Calc - research target (12m)'!$F$67:$F$69,'Calc - research target (12m)'!$G$67:$G$69)-'Calc - research target (12m)'!$F$68*'Calc - research target (12m)'!$G$68)+'Calc - research target (12m)'!$G$68*((($A19*D$12)-'Calc - research target (12m)'!$B$50-'Calc - research target (12m)'!$B$51+'Calc - research target (12m)'!$B$52)/'Calc - research target (12m)'!$B$53))/SUM('Calc - research target (12m)'!$G$67:$G$69) | E19: =((SUMPRODUCT('Calc - research target (12m)'!$F$67:$F$69,'Calc - research target (12m)'!$G$67:$G$69)-'Calc - research target (12m)'!$F$68*'Calc - research target (12m)'!$G$68)+'Calc - research target (12m)'!$G$68*((($A19*E$12)-'Calc - research target (12m)'!$B$50-'Calc - research target (12m)'!$B$51+'Calc - research target (12m)'!$B$52)/'Calc - research target (12m)'!$B$53))/SUM('Calc - research target (12m)'!$G$67:$G$69) | F19: =((SUMPRODUCT('Calc - research target (12m)'!$F$67:$F$69,'Calc - research target (12m)'!$G$67:$G$69)-'Calc - research target (12m)'!$F$68*'Calc - research target (12m)'!$G$68)+'Calc - research target (12m)'!$G$68*((($A19*F$12)-'Calc - research target (12m)'!$B$50-'Calc - research target (12m)'!$B$51+'Calc - research target (12m)'!$B$52)/'Calc - research target (12m)'!$B$53))/SUM('Calc - research target (12m)'!$G$67:$G$69)
A22: FY2028E diluted EPS: revenue growth change in every year (down) x EBIT margin change (across)
A23: Growth Δ \ margin Δ | B23: -0.01 | C23: -0.005 | D23: 0 | E23: 0.005 | F23: 0.01
A24: -0.02 | B24: =(Valuation!$B$88*(1+Model!E12+$A24)*(1+Model!F12+$A24)*(Model!F14+B$23)+Valuation!$B$89*(1+Model!E16+$A24)*(1+Model!F16+$A24)*(Model!F18+B$23)+Model!F21+Model!F33)*(1-Model!F63)/Model!F40 | C24: =(Valuation!$B$88*(1+Model!E12+$A24)*(1+Model!F12+$A24)*(Model!F14+C$23)+Valuation!$B$89*(1+Model!E16+$A24)*(1+Model!F16+$A24)*(Model!F18+C$23)+Model!F21+Model!F33)*(1-Model!F63)/Model!F40 | D24: =(Valuation!$B$88*(1+Model!E12+$A24)*(1+Model!F12+$A24)*(Model!F14+D$23)+Valuation!$B$89*(1+Model!E16+$A24)*(1+Model!F16+$A24)*(Model!F18+D$23)+Model!F21+Model!F33)*(1-Model!F63)/Model!F40 | E24: =(Valuation!$B$88*(1+Model!E12+$A24)*(1+Model!F12+$A24)*(Model!F14+E$23)+Valuation!$B$89*(1+Model!E16+$A24)*(1+Model!F16+$A24)*(Model!F18+E$23)+Model!F21+Model!F33)*(1-Model!F63)/Model!F40 | F24: =(Valuation!$B$88*(1+Model!E12+$A24)*(1+Model!F12+$A24)*(Model!F14+F$23)+Valuation!$B$89*(1+Model!E16+$A24)*(1+Model!F16+$A24)*(Model!F18+F$23)+Model!F21+Model!F33)*(1-Model!F63)/Model!F40
A25: -0.01 | B25: =(Valuation!$B$88*(1+Model!E12+$A25)*(1+Model!F12+$A25)*(Model!F14+B$23)+Valuation!$B$89*(1+Model!E16+$A25)*(1+Model!F16+$A25)*(Model!F18+B$23)+Model!F21+Model!F33)*(1-Model!F63)/Model!F40 | C25: =(Valuation!$B$88*(1+Model!E12+$A25)*(1+Model!F12+$A25)*(Model!F14+C$23)+Valuation!$B$89*(1+Model!E16+$A25)*(1+Model!F16+$A25)*(Model!F18+C$23)+Model!F21+Model!F33)*(1-Model!F63)/Model!F40 | D25: =(Valuation!$B$88*(1+Model!E12+$A25)*(1+Model!F12+$A25)*(Model!F14+D$23)+Valuation!$B$89*(1+Model!E16+$A25)*(1+Model!F16+$A25)*(Model!F18+D$23)+Model!F21+Model!F33)*(1-Model!F63)/Model!F40 | E25: =(Valuation!$B$88*(1+Model!E12+$A25)*(1+Model!F12+$A25)*(Model!F14+E$23)+Valuation!$B$89*(1+Model!E16+$A25)*(1+Model!F16+$A25)*(Model!F18+E$23)+Model!F21+Model!F33)*(1-Model!F63)/Model!F40 | F25: =(Valuation!$B$88*(1+Model!E12+$A25)*(1+Model!F12+$A25)*(Model!F14+F$23)+Valuation!$B$89*(1+Model!E16+$A25)*(1+Model!F16+$A25)*(Model!F18+F$23)+Model!F21+Model!F33)*(1-Model!F63)/Model!F40
A26: 0 | B26: =(Valuation!$B$88*(1+Model!E12+$A26)*(1+Model!F12+$A26)*(Model!F14+B$23)+Valuation!$B$89*(1+Model!E16+$A26)*(1+Model!F16+$A26)*(Model!F18+B$23)+Model!F21+Model!F33)*(1-Model!F63)/Model!F40 | C26: =(Valuation!$B$88*(1+Model!E12+$A26)*(1+Model!F12+$A26)*(Model!F14+C$23)+Valuation!$B$89*(1+Model!E16+$A26)*(1+Model!F16+$A26)*(Model!F18+C$23)+Model!F21+Model!F33)*(1-Model!F63)/Model!F40 | D26: =(Valuation!$B$88*(1+Model!E12+$A26)*(1+Model!F12+$A26)*(Model!F14+D$23)+Valuation!$B$89*(1+Model!E16+$A26)*(1+Model!F16+$A26)*(Model!F18+D$23)+Model!F21+Model!F33)*(1-Model!F63)/Model!F40 | E26: =(Valuation!$B$88*(1+Model!E12+$A26)*(1+Model!F12+$A26)*(Model!F14+E$23)+Valuation!$B$89*(1+Model!E16+$A26)*(1+Model!F16+$A26)*(Model!F18+E$23)+Model!F21+Model!F33)*(1-Model!F63)/Model!F40 | F26: =(Valuation!$B$88*(1+Model!E12+$A26)*(1+Model!F12+$A26)*(Model!F14+F$23)+Valuation!$B$89*(1+Model!E16+$A26)*(1+Model!F16+$A26)*(Model!F18+F$23)+Model!F21+Model!F33)*(1-Model!F63)/Model!F40
A27: 0.01 | B27: =(Valuation!$B$88*(1+Model!E12+$A27)*(1+Model!F12+$A27)*(Model!F14+B$23)+Valuation!$B$89*(1+Model!E16+$A27)*(1+Model!F16+$A27)*(Model!F18+B$23)+Model!F21+Model!F33)*(1-Model!F63)/Model!F40 | C27: =(Valuation!$B$88*(1+Model!E12+$A27)*(1+Model!F12+$A27)*(Model!F14+C$23)+Valuation!$B$89*(1+Model!E16+$A27)*(1+Model!F16+$A27)*(Model!F18+C$23)+Model!F21+Model!F33)*(1-Model!F63)/Model!F40 | D27: =(Valuation!$B$88*(1+Model!E12+$A27)*(1+Model!F12+$A27)*(Model!F14+D$23)+Valuation!$B$89*(1+Model!E16+$A27)*(1+Model!F16+$A27)*(Model!F18+D$23)+Model!F21+Model!F33)*(1-Model!F63)/Model!F40 | E27: =(Valuation!$B$88*(1+Model!E12+$A27)*(1+Model!F12+$A27)*(Model!F14+E$23)+Valuation!$B$89*(1+Model!E16+$A27)*(1+Model!F16+$A27)*(Model!F18+E$23)+Model!F21+Model!F33)*(1-Model!F63)/Model!F40 | F27: =(Valuation!$B$88*(1+Model!E12+$A27)*(1+Model!F12+$A27)*(Model!F14+F$23)+Valuation!$B$89*(1+Model!E16+$A27)*(1+Model!F16+$A27)*(Model!F18+F$23)+Model!F21+Model!F33)*(1-Model!F63)/Model!F40
A28: 0.02 | B28: =(Valuation!$B$88*(1+Model!E12+$A28)*(1+Model!F12+$A28)*(Model!F14+B$23)+Valuation!$B$89*(1+Model!E16+$A28)*(1+Model!F16+$A28)*(Model!F18+B$23)+Model!F21+Model!F33)*(1-Model!F63)/Model!F40 | C28: =(Valuation!$B$88*(1+Model!E12+$A28)*(1+Model!F12+$A28)*(Model!F14+C$23)+Valuation!$B$89*(1+Model!E16+$A28)*(1+Model!F16+$A28)*(Model!F18+C$23)+Model!F21+Model!F33)*(1-Model!F63)/Model!F40 | D28: =(Valuation!$B$88*(1+Model!E12+$A28)*(1+Model!F12+$A28)*(Model!F14+D$23)+Valuation!$B$89*(1+Model!E16+$A28)*(1+Model!F16+$A28)*(Model!F18+D$23)+Model!F21+Model!F33)*(1-Model!F63)/Model!F40 | E28: =(Valuation!$B$88*(1+Model!E12+$A28)*(1+Model!F12+$A28)*(Model!F14+E$23)+Valuation!$B$89*(1+Model!E16+$A28)*(1+Model!F16+$A28)*(Model!F18+E$23)+Model!F21+Model!F33)*(1-Model!F63)/Model!F40 | F28: =(Valuation!$B$88*(1+Model!E12+$A28)*(1+Model!F12+$A28)*(Model!F14+F$23)+Valuation!$B$89*(1+Model!E16+$A28)*(1+Model!F16+$A28)*(Model!F18+F$23)+Model!F21+Model!F33)*(1-Model!F63)/Model!F40
A30: Net interest and the share count are held at the base case in table 3.

Sheet Distribution
A1: MOD: 12-month distribution (mix of lognormals around each scenario value)
A3: Scenario | B3: Probability | C3: Value at target date | D3: Story
A4: bear | B4: =Valuation!B83 | C4: ='Calc - bear'!$F$70 | D4: =Valuation!J83
A5: base | B5: =Valuation!B84 | C5: ='Calc - base'!$F$70 | D5: =Valuation!J84
A6: bull | B6: =Valuation!B85 | C6: ='Calc - bull'!$F$70 | D6: =Valuation!J85
A8: Probabilities sum to | B8: =SUM(B4:B6)
A9: Spread within each scenario | B9: =Valuation!$B$66
A10: Probability-weighted mean | B10: =($B$4*$C$4+$B$5*$C$5+$B$6*$C$6)*EXP($B$9^2/2)
A12: Quantile | B12: Price
A13: Median (model target) | B13: =SQRT(A60*B60)
A14: 10th percentile | B14: =SQRT(D60*E60)
A15: 25th percentile | B15: =SQRT(G60*H60)
A16: 75th percentile | B16: =SQRT(J60*K60)
A17: 90th percentile | B17: =SQRT(M60*N60)
A19: Each quantile solved by bisection (block: low, high, probability above the midpoint)
A20: Median (model target): low | B20: high | C20: P(above mid) | D20: 10th percentile: low | E20: high | F20: P(above mid) | G20: 25th percentile: low | H20: high | I20: P(above mid) | J20: 75th percentile: low | K20: high | L20: P(above mid) | M20: 90th percentile: low | N20: high | O20: P(above mid)
A21: =MIN($C$4,$C$5,$C$6)*0.2 | B21: =MAX($C$4,$C$5,$C$6)*4 | C21: =SUMPRODUCT($B$4:$B$6,1-NORMSDIST((LN(SQRT(A21*B21))-LN($C$4:$C$6))/$B$9)) | D21: =MIN($C$4,$C$5,$C$6)*0.2 | E21: =MAX($C$4,$C$5,$C$6)*4 | F21: =SUMPRODUCT($B$4:$B$6,1-NORMSDIST((LN(SQRT(D21*E21))-LN($C$4:$C$6))/$B$9)) | G21: =MIN($C$4,$C$5,$C$6)*0.2 | H21: =MAX($C$4,$C$5,$C$6)*4 | I21: =SUMPRODUCT($B$4:$B$6,1-NORMSDIST((LN(SQRT(G21*H21))-LN($C$4:$C$6))/$B$9)) | J21: =MIN($C$4,$C$5,$C$6)*0.2 | K21: =MAX($C$4,$C$5,$C$6)*4 | L21: =SUMPRODUCT($B$4:$B$6,1-NORMSDIST((LN(SQRT(J21*K21))-LN($C$4:$C$6))/$B$9)) | M21: =MIN($C$4,$C$5,$C$6)*0.2 | N21: =MAX($C$4,$C$5,$C$6)*4 | O21: =SUMPRODUCT($B$4:$B$6,1-NORMSDIST((LN(SQRT(M21*N21))-LN($C$4:$C$6))/$B$9))
A22: =IF(C21>0.5,SQRT(A21*B21),A21) | B22: =IF(C21>0.5,B21,SQRT(A21*B21)) | C22: =SUMPRODUCT($B$4:$B$6,1-NORMSDIST((LN(SQRT(A22*B22))-LN($C$4:$C$6))/$B$9)) | D22: =IF(F21>0.9,SQRT(D21*E21),D21) | E22: =IF(F21>0.9,E21,SQRT(D21*E21)) | F22: =SUMPRODUCT($B$4:$B$6,1-NORMSDIST((LN(SQRT(D22*E22))-LN($C$4:$C$6))/$B$9)) | G22: =IF(I21>0.75,SQRT(G21*H21),G21) | H22: =IF(I21>0.75,H21,SQRT(G21*H21)) | I22: =SUMPRODUCT($B$4:$B$6,1-NORMSDIST((LN(SQRT(G22*H22))-LN($C$4:$C$6))/$B$9)) | J22: =IF(L21>0.25,SQRT(J21*K21),J21) | K22: =IF(L21>0.25,K21,SQRT(J21*K21)) | L22: =SUMPRODUCT($B$4:$B$6,1-NORMSDIST((LN(SQRT(J22*K22))-LN($C$4:$C$6))/$B$9)) | M22: =IF(O21>0.09999999999999998,SQRT(M21*N21),M21) | N22: =IF(O21>0.09999999999999998,N21,SQRT(M21*N21)) | O22: =SUMPRODUCT($B$4:$B$6,1-NORMSDIST((LN(SQRT(M22*N22))-LN($C$4:$C$6))/$B$9))
A23: =IF(C22>0.5,SQRT(A22*B22),A22) | B23: =IF(C22>0.5,B22,SQRT(A22*B22)) | C23: =SUMPRODUCT($B$4:$B$6,1-NORMSDIST((LN(SQRT(A23*B23))-LN($C$4:$C$6))/$B$9)) | D23: =IF(F22>0.9,SQRT(D22*E22),D22) | E23: =IF(F22>0.9,E22,SQRT(D22*E22)) | F23: =SUMPRODUCT($B$4:$B$6,1-NORMSDIST((LN(SQRT(D23*E23))-LN($C$4:$C$6))/$B$9)) | G23: =IF(I22>0.75,SQRT(G22*H22),G22) | H23: =IF(I22>0.75,H22,SQRT(G22*H22)) | I23: =SUMPRODUCT($B$4:$B$6,1-NORMSDIST((LN(SQRT(G23*H23))-LN($C$4:$C$6))/$B$9)) | J23: =IF(L22>0.25,SQRT(J22*K22),J22) | K23: =IF(L22>0.25,K22,SQRT(J22*K22)) | L23: =SUMPRODUCT($B$4:$B$6,1-NORMSDIST((LN(SQRT(J23*K23))-LN($C$4:$C$6))/$B$9)) | M23: =IF(O22>0.09999999999999998,SQRT(M22*N22),M22) | N23: =IF(O22>0.09999999999999998,N22,SQRT(M22*N22)) | O23: =SUMPRODUCT($B$4:$B$6,1-NORMSDIST((LN(SQRT(M23*N23))-LN($C$4:$C$6))/$B$9))
A24: =IF(C23>0.5,SQRT(A23*B23),A23) | B24: =IF(C23>0.5,B23,SQRT(A23*B23)) | C24: =SUMPRODUCT($B$4:$B$6,1-NORMSDIST((LN(SQRT(A24*B24))-LN($C$4:$C$6))/$B$9)) | D24: =IF(F23>0.9,SQRT(D23*E23),D23) | E24: =IF(F23>0.9,E23,SQRT(D23*E23)) | F24: =SUMPRODUCT($B$4:$B$6,1-NORMSDIST((LN(SQRT(D24*E24))-LN($C$4:$C$6))/$B$9)) | G24: =IF(I23>0.75,SQRT(G23*H23),G23) | H24: =IF(I23>0.75,H23,SQRT(G23*H23)) | I24: =SUMPRODUCT($B$4:$B$6,1-NORMSDIST((LN(SQRT(G24*H24))-LN($C$4:$C$6))/$B$9)) | J24: =IF(L23>0.25,SQRT(J23*K23),J23) | K24: =IF(L23>0.25,K23,SQRT(J23*K23)) | L24: =SUMPRODUCT($B$4:$B$6,1-NORMSDIST((LN(SQRT(J24*K24))-LN($C$4:$C$6))/$B$9)) | M24: =IF(O23>0.09999999999999998,SQRT(M23*N23),M23) | N24: =IF(O23>0.09999999999999998,N23,SQRT(M23*N23)) | O24: =SUMPRODUCT($B$4:$B$6,1-NORMSDIST((LN(SQRT(M24*N24))-LN($C$4:$C$6))/$B$9))
A25: =IF(C24>0.5,SQRT(A24*B24),A24) | B25: =IF(C24>0.5,B24,SQRT(A24*B24)) | C25: =SUMPRODUCT($B$4:$B$6,1-NORMSDIST((LN(SQRT(A25*B25))-LN($C$4:$C$6))/$B$9)) | D25: =IF(F24>0.9,SQRT(D24*E24),D24) | E25: =IF(F24>0.9,E24,SQRT(D24*E24)) | F25: =SUMPRODUCT($B$4:$B$6,1-NORMSDIST((LN(SQRT(D25*E25))-LN($C$4:$C$6))/$B$9)) | G25: =IF(I24>0.75,SQRT(G24*H24),G24) | H25: =IF(I24>0.75,H24,SQRT(G24*H24)) | I25: =SUMPRODUCT($B$4:$B$6,1-NORMSDIST((LN(SQRT(G25*H25))-LN($C$4:$C$6))/$B$9)) | J25: =IF(L24>0.25,SQRT(J24*K24),J24) | K25: =IF(L24>0.25,K24,SQRT(J24*K24)) | L25: =SUMPRODUCT($B$4:$B$6,1-NORMSDIST((LN(SQRT(J25*K25))-LN($C$4:$C$6))/$B$9)) | M25: =IF(O24>0.09999999999999998,SQRT(M24*N24),M24) | N25: =IF(O24>0.09999999999999998,N24,SQRT(M24*N24)) | O25: =SUMPRODUCT($B$4:$B$6,1-NORMSDIST((LN(SQRT(M25*N25))-LN($C$4:$C$6))/$B$9))
A26: =IF(C25>0.5,SQRT(A25*B25),A25) | B26: =IF(C25>0.5,B25,SQRT(A25*B25)) | C26: =SUMPRODUCT($B$4:$B$6,1-NORMSDIST((LN(SQRT(A26*B26))-LN($C$4:$C$6))/$B$9)) | D26: =IF(F25>0.9,SQRT(D25*E25),D25) | E26: =IF(F25>0.9,E25,SQRT(D25*E25)) | F26: =SUMPRODUCT($B$4:$B$6,1-NORMSDIST((LN(SQRT(D26*E26))-LN($C$4:$C$6))/$B$9)) | G26: =IF(I25>0.75,SQRT(G25*H25),G25) | H26: =IF(I25>0.75,H25,SQRT(G25*H25)) | I26: =SUMPRODUCT($B$4:$B$6,1-NORMSDIST((LN(SQRT(G26*H26))-LN($C$4:$C$6))/$B$9)) | J26: =IF(L25>0.25,SQRT(J25*K25),J25) | K26: =IF(L25>0.25,K25,SQRT(J25*K25)) | L26: =SUMPRODUCT($B$4:$B$6,1-NORMSDIST((LN(SQRT(J26*K26))-LN($C$4:$C$6))/$B$9)) | M26: =IF(O25>0.09999999999999998,SQRT(M25*N25),M25) | N26: =IF(O25>0.09999999999999998,N25,SQRT(M25*N25)) | O26: =SUMPRODUCT($B$4:$B$6,1-NORMSDIST((LN(SQRT(M26*N26))-LN($C$4:$C$6))/$B$9))
A27: =IF(C26>0.5,SQRT(A26*B26),A26) | B27: =IF(C26>0.5,B26,SQRT(A26*B26)) | C27: =SUMPRODUCT($B$4:$B$6,1-NORMSDIST((LN(SQRT(A27*B27))-LN($C$4:$C$6))/$B$9)) | D27: =IF(F26>0.9,SQRT(D26*E26),D26) | E27: =IF(F26>0.9,E26,SQRT(D26*E26)) | F27: =SUMPRODUCT($B$4:$B$6,1-NORMSDIST((LN(SQRT(D27*E27))-LN($C$4:$C$6))/$B$9)) | G27: =IF(I26>0.75,SQRT(G26*H26),G26) | H27: =IF(I26>0.75,H26,SQRT(G26*H26)) | I27: =SUMPRODUCT($B$4:$B$6,1-NORMSDIST((LN(SQRT(G27*H27))-LN($C$4:$C$6))/$B$9)) | J27: =IF(L26>0.25,SQRT(J26*K26),J26) | K27: =IF(L26>0.25,K26,SQRT(J26*K26)) | L27: =SUMPRODUCT($B$4:$B$6,1-NORMSDIST((LN(SQRT(J27*K27))-LN($C$4:$C$6))/$B$9)) | M27: =IF(O26>0.09999999999999998,SQRT(M26*N26),M26) | N27: =IF(O26>0.09999999999999998,N26,SQRT(M26*N26)) | O27: =SUMPRODUCT($B$4:$B$6,1-NORMSDIST((LN(SQRT(M27*N27))-LN($C$4:$C$6))/$B$9))
A28: =IF(C27>0.5,SQRT(A27*B27),A27) | B28: =IF(C27>0.5,B27,SQRT(A27*B27)) | C28: =SUMPRODUCT($B$4:$B$6,1-NORMSDIST((LN(SQRT(A28*B28))-LN($C$4:$C$6))/$B$9)) | D28: =IF(F27>0.9,SQRT(D27*E27),D27) | E28: =IF(F27>0.9,E27,SQRT(D27*E27)) | F28: =SUMPRODUCT($B$4:$B$6,1-NORMSDIST((LN(SQRT(D28*E28))-LN($C$4:$C$6))/$B$9)) | G28: =IF(I27>0.75,SQRT(G27*H27),G27) | H28: =IF(I27>0.75,H27,SQRT(G27*H27)) | I28: =SUMPRODUCT($B$4:$B$6,1-NORMSDIST((LN(SQRT(G28*H28))-LN($C$4:$C$6))/$B$9)) | J28: =IF(L27>0.25,SQRT(J27*K27),J27) | K28: =IF(L27>0.25,K27,SQRT(J27*K27)) | L28: =SUMPRODUCT($B$4:$B$6,1-NORMSDIST((LN(SQRT(J28*K28))-LN($C$4:$C$6))/$B$9)) | M28: =IF(O27>0.09999999999999998,SQRT(M27*N27),M27) | N28: =IF(O27>0.09999999999999998,N27,SQRT(M27*N27)) | O28: =SUMPRODUCT($B$4:$B$6,1-NORMSDIST((LN(SQRT(M28*N28))-LN($C$4:$C$6))/$B$9))
A29: =IF(C28>0.5,SQRT(A28*B28),A28) | B29: =IF(C28>0.5,B28,SQRT(A28*B28)) | C29: =SUMPRODUCT($B$4:$B$6,1-NORMSDIST((LN(SQRT(A29*B29))-LN($C$4:$C$6))/$B$9)) | D29: =IF(F28>0.9,SQRT(D28*E28),D28) | E29: =IF(F28>0.9,E28,SQRT(D28*E28)) | F29: =SUMPRODUCT($B$4:$B$6,1-NORMSDIST((LN(SQRT(D29*E29))-LN($C$4:$C$6))/$B$9)) | G29: =IF(I28>0.75,SQRT(G28*H28),G28) | H29: =IF(I28>0.75,H28,SQRT(G28*H28)) | I29: =SUMPRODUCT($B$4:$B$6,1-NORMSDIST((LN(SQRT(G29*H29))-LN($C$4:$C$6))/$B$9)) | J29: =IF(L28>0.25,SQRT(J28*K28),J28) | K29: =IF(L28>0.25,K28,SQRT(J28*K28)) | L29: =SUMPRODUCT($B$4:$B$6,1-NORMSDIST((LN(SQRT(J29*K29))-LN($C$4:$C$6))/$B$9)) | M29: =IF(O28>0.09999999999999998,SQRT(M28*N28),M28) | N29: =IF(O28>0.09999999999999998,N28,SQRT(M28*N28)) | O29: =SUMPRODUCT($B$4:$B$6,1-NORMSDIST((LN(SQRT(M29*N29))-LN($C$4:$C$6))/$B$9))
A30: =IF(C29>0.5,SQRT(A29*B29),A29) | B30: =IF(C29>0.5,B29,SQRT(A29*B29)) | C30: =SUMPRODUCT($B$4:$B$6,1-NORMSDIST((LN(SQRT(A30*B30))-LN($C$4:$C$6))/$B$9)) | D30: =IF(F29>0.9,SQRT(D29*E29),D29) | E30: =IF(F29>0.9,E29,SQRT(D29*E29)) | F30: =SUMPRODUCT($B$4:$B$6,1-NORMSDIST((LN(SQRT(D30*E30))-LN($C$4:$C$6))/$B$9)) | G30: =IF(I29>0.75,SQRT(G29*H29),G29) | H30: =IF(I29>0.75,H29,SQRT(G29*H29)) | I30: =SUMPRODUCT($B$4:$B$6,1-NORMSDIST((LN(SQRT(G30*H30))-LN($C$4:$C$6))/$B$9)) | J30: =IF(L29>0.25,SQRT(J29*K29),J29) | K30: =IF(L29>0.25,K29,SQRT(J29*K29)) | L30: =SUMPRODUCT($B$4:$B$6,1-NORMSDIST((LN(SQRT(J30*K30))-LN($C$4:$C$6))/$B$9)) | M30: =IF(O29>0.09999999999999998,SQRT(M29*N29),M29) | N30: =IF(O29>0.09999999999999998,N29,SQRT(M29*N29)) | O30: =SUMPRODUCT($B$4:$B$6,1-NORMSDIST((LN(SQRT(M30*N30))-LN($C$4:$C$6))/$B$9))
A31: =IF(C30>0.5,SQRT(A30*B30),A30) | B31: =IF(C30>0.5,B30,SQRT(A30*B30)) | C31: =SUMPRODUCT($B$4:$B$6,1-NORMSDIST((LN(SQRT(A31*B31))-LN($C$4:$C$6))/$B$9)) | D31: =IF(F30>0.9,SQRT(D30*E30),D30) | E31: =IF(F30>0.9,E30,SQRT(D30*E30)) | F31: =SUMPRODUCT($B$4:$B$6,1-NORMSDIST((LN(SQRT(D31*E31))-LN($C$4:$C$6))/$B$9)) | G31: =IF(I30>0.75,SQRT(G30*H30),G30) | H31: =IF(I30>0.75,H30,SQRT(G30*H30)) | I31: =SUMPRODUCT($B$4:$B$6,1-NORMSDIST((LN(SQRT(G31*H31))-LN($C$4:$C$6))/$B$9)) | J31: =IF(L30>0.25,SQRT(J30*K30),J30) | K31: =IF(L30>0.25,K30,SQRT(J30*K30)) | L31: =SUMPRODUCT($B$4:$B$6,1-NORMSDIST((LN(SQRT(J31*K31))-LN($C$4:$C$6))/$B$9)) | M31: =IF(O30>0.09999999999999998,SQRT(M30*N30),M30) | N31: =IF(O30>0.09999999999999998,N30,SQRT(M30*N30)) | O31: =SUMPRODUCT($B$4:$B$6,1-NORMSDIST((LN(SQRT(M31*N31))-LN($C$4:$C$6))/$B$9))
A32: =IF(C31>0.5,SQRT(A31*B31),A31) | B32: =IF(C31>0.5,B31,SQRT(A31*B31)) | C32: =SUMPRODUCT($B$4:$B$6,1-NORMSDIST((LN(SQRT(A32*B32))-LN($C$4:$C$6))/$B$9)) | D32: =IF(F31>0.9,SQRT(D31*E31),D31) | E32: =IF(F31>0.9,E31,SQRT(D31*E31)) | F32: =SUMPRODUCT($B$4:$B$6,1-NORMSDIST((LN(SQRT(D32*E32))-LN($C$4:$C$6))/$B$9)) | G32: =IF(I31>0.75,SQRT(G31*H31),G31) | H32: =IF(I31>0.75,H31,SQRT(G31*H31)) | I32: =SUMPRODUCT($B$4:$B$6,1-NORMSDIST((LN(SQRT(G32*H32))-LN($C$4:$C$6))/$B$9)) | J32: =IF(L31>0.25,SQRT(J31*K31),J31) | K32: =IF(L31>0.25,K31,SQRT(J31*K31)) | L32: =SUMPRODUCT($B$4:$B$6,1-NORMSDIST((LN(SQRT(J32*K32))-LN($C$4:$C$6))/$B$9)) | M32: =IF(O31>0.09999999999999998,SQRT(M31*N31),M31) | N32: =IF(O31>0.09999999999999998,N31,SQRT(M31*N31)) | O32: =SUMPRODUCT($B$4:$B$6,1-NORMSDIST((LN(SQRT(M32*N32))-LN($C$4:$C$6))/$B$9))
A33: =IF(C32>0.5,SQRT(A32*B32),A32) | B33: =IF(C32>0.5,B32,SQRT(A32*B32)) | C33: =SUMPRODUCT($B$4:$B$6,1-NORMSDIST((LN(SQRT(A33*B33))-LN($C$4:$C$6))/$B$9)) | D33: =IF(F32>0.9,SQRT(D32*E32),D32) | E33: =IF(F32>0.9,E32,SQRT(D32*E32)) | F33: =SUMPRODUCT($B$4:$B$6,1-NORMSDIST((LN(SQRT(D33*E33))-LN($C$4:$C$6))/$B$9)) | G33: =IF(I32>0.75,SQRT(G32*H32),G32) | H33: =IF(I32>0.75,H32,SQRT(G32*H32)) | I33: =SUMPRODUCT($B$4:$B$6,1-NORMSDIST((LN(SQRT(G33*H33))-LN($C$4:$C$6))/$B$9)) | J33: =IF(L32>0.25,SQRT(J32*K32),J32) | K33: =IF(L32>0.25,K32,SQRT(J32*K32)) | L33: =SUMPRODUCT($B$4:$B$6,1-NORMSDIST((LN(SQRT(J33*K33))-LN($C$4:$C$6))/$B$9)) | M33: =IF(O32>0.09999999999999998,SQRT(M32*N32),M32) | N33: =IF(O32>0.09999999999999998,N32,SQRT(M32*N32)) | O33: =SUMPRODUCT($B$4:$B$6,1-NORMSDIST((LN(SQRT(M33*N33))-LN($C$4:$C$6))/$B$9))
... A60: =IF(C59>0.5,SQRT(A59*B59),A59) | B60: =IF(C59>0.5,B59,SQRT(A59*B59)) | C60: =SUMPRODUCT($B$4:$B$6,1-NORMSDIST((LN(SQRT(A60*B60))-LN($C$4:$C$6))/$B$9)) | D60: =IF(F59>0.9,SQRT(D59*E59),D59) | E60: =IF(F59>0.9,E59,SQRT(D59*E59)) | F60: =SUMPRODUCT($B$4:$B$6,1-NORMSDIST((LN(SQRT(D60*E60))-LN($C$4:$C$6))/$B$9)) | G60: =IF(I59>0.75,SQRT(G59*H59),G59) | H60: =IF(I59>0.75,H59,SQRT(G59*H59)) | I60: =SUMPRODUCT($B$4:$B$6,1-NORMSDIST((LN(SQRT(G60*H60))-LN($C$4:$C$6))/$B$9)) | J60: =IF(L59>0.25,SQRT(J59*K59),J59) | K60: =IF(L59>0.25,K59,SQRT(J59*K59)) | L60: =SUMPRODUCT($B$4:$B$6,1-NORMSDIST((LN(SQRT(J60*K60))-LN($C$4:$C$6))/$B$9)) | M60: =IF(O59>0.09999999999999998,SQRT(M59*N59),M59) | N60: =IF(O59>0.09999999999999998,N59,SQRT(M59*N59)) | O60: =SUMPRODUCT($B$4:$B$6,1-NORMSDIST((LN(SQRT(M60*N60))-LN($C$4:$C$6))/$B$9))

Sheet Calc - research target (12m)
A1: MOD engine calculation: research target (12m) (reconciled set, no scenario deltas)
A2: Machinery behind the Valuation and Distribution tabs; drivers come from Model, assumptions from Valuation.
A4: Scenario Growth Δ | B4: 0
A5: Scenario Margin Δ | B5: 0
A6: Scenario Multiple Δ (turns) | B6: 0
A7: Scenario WACC Δ | B7: 0
A8: Scenario Multiple %Δ | B8: 0
A9: Scenario Stated EPS/FCF %Δ | B9: 0
A10: Scenario Custom %Δ | B10: 0
A12: WACC | B12: =Valuation!$B$51+B7
A13: Years from last FY end to target date | B13: =(Valuation!$B$45-Valuation!$B$49)/365.25
A14: Years from last FY end to balance date | B14: =(Valuation!$B$55-Valuation!$B$49)/365.25
A15: Years from last FY end to share count date | B15: =(Valuation!$B$61-Valuation!$B$49)/365.25
A16: Projected years | B16: 3
A18: Projection | B18: Base | C18: =Model!E5 | D18: =Model!F5 | E18: =Model!G5
A19: Year index | B19: 0 | C19: 1 | D19: 2 | E19: 3
A20: Period end | C20: =Valuation!$B$49+ROUND(365.25*C19,0) | D20: =Valuation!$B$49+ROUND(365.25*D19,0) | E20: =Valuation!$B$49+ROUND(365.25*E19,0)
A21: Revenue growth | C21: =C22/B22-1 | D21: =D22/C22-1 | E21: =E22/D22-1
A22: Revenue | B22: =Valuation!$B$50 | C22: =C139 | D22: =D139 | E22: =E139
A23: EBIT margin | C23: =C24/C22 | D23: =D24/D22 | E23: =E24/E22
A24: EBIT | C24: =C142 | D24: =D142 | E24: =E142
A25: Tax rate | C25: =Model!E63 | D25: =Model!F63 | E25: =Model!G63
A26: NOPAT | C26: =C24*(1-C25) | D26: =D24*(1-D25) | E26: =E24*(1-E25)
A27: D&A | C27: =C22*(Model!E64) | D27: =D22*(Model!F64) | E27: =E22*(Model!G64)
A28: Capex | C28: =C22*(Model!E65) | D28: =D22*(Model!F65) | E28: =E22*(Model!G65)
A29: Working capital increase | C29: =(Model!E66)*(C22-B22) | D29: =(Model!F66)*(D22-C22) | E29: =(Model!G66)*(E22-D22)
A30: Stock comp | C30: =C22*(Model!E67) | D30: =D22*(Model!F67) | E30: =E22*(Model!G67)
A31: Free cash flow to firm | C31: =C26+C27-C28-C29-IF(AND(Valuation!$B$47="adjusted",Valuation!$B$48="cost"),C30*(1-C25),0) | D31: =D26+D27-D28-D29-IF(AND(Valuation!$B$47="adjusted",Valuation!$B$48="cost"),D30*(1-D25),0) | E31: =E26+E27-E28-E29-IF(AND(Valuation!$B$47="adjusted",Valuation!$B$48="cost"),E30*(1-E25),0)
A32: EBITDA | C32: =C24+C27 | D32: =D24+D27 | E32: =E24+E27
A33: Adj. EBITDA | C33: =C24+C27+C22*(Model!E71) | D33: =D24+D27+D22*(Model!F71) | E33: =E24+E27+E22*(Model!G71)
A34: Shareholder returns + other uses | C34: =C22*Model!E69+Model!E68+Model!E70 | D34: =D22*Model!F69+Model!F68+Model!F70 | E34: =E22*Model!G69+Model!G68+Model!G70
A35: Share of year after target date | C35: =IF(C19<=$B$13,0,C19-MAX(C19-1,$B$13)) | D35: =IF(D19<=$B$13,0,D19-MAX(D19-1,$B$13)) | E35: =IF(E19<=$B$13,0,E19-MAX(E19-1,$B$13))
A36: PV at target date of FCFF | C36: =IF(C35=0,0,C31*C35/(1+$B$12)^(C19-$B$13)) | D36: =IF(D35=0,0,D31*D35/(1+$B$12)^(D19-$B$13)) | E36: =IF(E35=0,0,E31*E35/(1+$B$12)^(E19-$B$13))
A37: Overlap: balance date to target date | C37: =MAX(0,MIN(C19,$B$13)-MAX(C19-1,$B$14)) | D37: =MAX(0,MIN(D19,$B$13)-MAX(D19-1,$B$14)) | E37: =MAX(0,MIN(E19,$B$13)-MAX(E19-1,$B$14))
A38: NTM weight at target date | C38: =MAX(0,MIN(C19,$B$13+1)-MAX(C19-1,$B$13)) | D38: =MAX(0,MIN(D19,$B$13+1)-MAX(D19-1,$B$13)) | E38: =MAX(0,MIN(E19,$B$13+1)-MAX(E19-1,$B$13))
A39: LTM weight at target date | B39: =MAX(0,MIN(0,$B$13)-MAX(-1,$B$13-1)) | C39: =MAX(0,MIN(C19,$B$13)-MAX(C19-1,$B$13-1)) | D39: =MAX(0,MIN(D19,$B$13)-MAX(D19-1,$B$13-1)) | E39: =MAX(0,MIN(E19,$B$13)-MAX(E19-1,$B$13-1))
A41: Value at the target date
A42: PV of free cash flow after the target date | B42: =SUM($C$36:$E$36)
A43: Terminal value at final year | B43: =IF(Valuation!$B$52="exit_multiple",Valuation!$B$54*E32,E31*(1+Valuation!$B$53)/($B$12-Valuation!$B$53))
A44: PV of terminal value at target date | B44: =B43/(1+$B$12)^($B$16-$B$13)
A45: DCF enterprise value at target date | B45: =B42+B44
A46: Terminal value share of DCF | B46: =B44/B45
A47: Free cash flow earned, balance date to target date | B47: =SUMPRODUCT($C$37:$E$37,$C$31:$E$31)
A48: Shareholder returns + other uses paid | B48: =SUMPRODUCT($C$37:$E$37,$C$34:$E$34)
A49: Interest drag on net debt | B49: =Valuation!$B$58*(1-$C$25)*MAX(Valuation!$B$56,0)*MAX($B$13-$B$14,0)
A50: Net debt at target date | B50: =IF(Valuation!$B$59="",Valuation!$B$56-B47+B49+B48,Valuation!$B$59)
A51: Minority interests | B51: =Valuation!$B$57
A52: Adjustments (probability-weighted) | B52: =0
A53: Diluted shares at target date (M) | B53: =IF(Valuation!$B$63="",Valuation!$B$60*(1+Valuation!$B$62)^MAX($B$13-$B$15,0),Valuation!$B$63)
A54: After-tax interest on target-date net debt | B54: =Valuation!$B$58*(1-$C$25)*MAX(B50,0)
A55: Check: WACC vs terminal growth | B55: =IF(AND(Valuation!$B$52<>"exit_multiple",$B$12<=Valuation!$B$53+0.01),"WACC must exceed terminal growth by 1 point","ok")
A56: Check: projection length | B56: =IF(OR($B$13>=$B$16-1,$B$13+1>$B$16),"add projected years past the target date","ok")
A58: Metric at target date | B58: Next 12 months | C58: Last 12 months
A59: Revenue | B59: =SUMPRODUCT($C$38:$E$38,$C$22:$E$22) | C59: =SUMPRODUCT($C$39:$E$39,$C$22:$E$22)+$B$39*$B$22
A60: EBIT | B60: =SUMPRODUCT($C$38:$E$38,$C$24:$E$24) | C60: =SUMPRODUCT($C$39:$E$39,$C$24:$E$24)
A61: EBITDA | B61: =SUMPRODUCT($C$38:$E$38,$C$32:$E$32) | C61: =SUMPRODUCT($C$39:$E$39,$C$32:$E$32)
A62: Adj. EBITDA | B62: =SUMPRODUCT($C$38:$E$38,$C$33:$E$33) | C62: =SUMPRODUCT($C$39:$E$39,$C$33:$E$33)
A63: NOPAT | B63: =SUMPRODUCT($C$38:$E$38,$C$26:$E$26) | C63: =SUMPRODUCT($C$39:$E$39,$C$26:$E$26)
A64: Free cash flow to firm | B64: =SUMPRODUCT($C$38:$E$38,$C$31:$E$31) | C64: =SUMPRODUCT($C$39:$E$39,$C$31:$E$31)
A66: Valuation method | B66: Metric | C66: Multiple used | D66: Basis | E66: Metric at target date | F66: Value per share | G66: Weight | H66: Metric key | I66: Metric shown (stated per-share figure when used)
A67: DCF (cash flow to target date + terminal) | F67: =((B45)-$B$50-$B$51+$B$52)/$B$53 | G67: =Valuation!$B$64
A68: ="Multiple: "&Valuation!A70&" ("&Valuation!D70&")" | B68: =Valuation!A70 | C68: =IF(B68="FCF yield",(Valuation!B70)*(1-$B$8),(Valuation!B70)+IF(B68="EV/sales",0.1,1)*$B$6) | D68: =Valuation!D70 | E68: =IF(D68="ltm",CHOOSE(H68,$C$59,$C$60,$C$61,$C$62,$C$63,$C$64),CHOOSE(H68,$B$59,$B$60,$B$61,$B$62,$B$63,$B$64)) | F68: =IF(OR(B68="EV/EBITDA",B68="EV/sales",B68="EV/EBIT"),((C68*E68)-$B$50-$B$51+$B$52)/$B$53,IF(B68="P/E",IF(Valuation!F70<>"",C68*(Valuation!F70)*(1+$B$9),C68*(E68-$B$54)/$B$53),IF(Valuation!G70<>"",(Valuation!G70)*(1+$B$9)/C68,(E68-IF(Valuation!H70,$B$54,0))/C68/$B$53))+$B$52/$B$53) | G68: =Valuation!C70 | H68: =IF(B68="EV/sales",1,IF(B68="EV/EBIT",2,IF(B68="EV/EBITDA",IF(Valuation!E70="adjusted",4,3),IF(B68="P/E",5,6)))) | I68: =IF(AND(B68="P/E",Valuation!F70<>""),(Valuation!F70)*(1+$B$9),IF(AND(B68="FCF yield",Valuation!G70<>""),(Valuation!G70)*(1+$B$9),E68))
A69: ="Multiple: "&Valuation!A71&" ("&Valuation!D71&")" | B69: =Valuation!A71 | C69: =IF(B69="FCF yield",(Valuation!B71)*(1-$B$8),(Valuation!B71)+IF(B69="EV/sales",0.1,1)*$B$6) | D69: =Valuation!D71 | E69: =IF(D69="ltm",CHOOSE(H69,$C$59,$C$60,$C$61,$C$62,$C$63,$C$64),CHOOSE(H69,$B$59,$B$60,$B$61,$B$62,$B$63,$B$64)) | F69: =IF(OR(B69="EV/EBITDA",B69="EV/sales",B69="EV/EBIT"),((C69*E69)-$B$50-$B$51+$B$52)/$B$53,IF(B69="P/E",IF(Valuation!F71<>"",C69*(Valuation!F71)*(1+$B$9),C69*(E69-$B$54)/$B$53),IF(Valuation!G71<>"",(Valuation!G71)*(1+$B$9)/C69,(E69-IF(Valuation!H71,$B$54,0))/C69/$B$53))+$B$52/$B$53) | G69: =Valuation!C71 | H69: =IF(B69="EV/sales",1,IF(B69="EV/EBIT",2,IF(B69="EV/EBITDA",IF(Valuation!E71="adjusted",4,3),IF(B69="P/E",5,6)))) | I69: =IF(AND(B69="P/E",Valuation!F71<>""),(Valuation!F71)*(1+$B$9),IF(AND(B69="FCF yield",Valuation!G71<>""),(Valuation!G71)*(1+$B$9),E69))
A70: Value per share at target date (weighted methods) | F70: =SUMPRODUCT(F67:F69,G67:G69)/SUM(G67:G69)
A129: Segment build (model_engine.seg_build): revenue and EBIT are the segment sums plus corporate EBIT
A130: Segment | B130: Base | C130: =Model!E5 | D130: =Model!F5 | E130: =Model!G5
A131: Data Centers: revenue growth | C131: =Model!E12+$B$4 | D131: =Model!F12+$B$4 | E131: =Model!G12+$B$4
A132: Data Centers: revenue | B132: =Valuation!$B$88 | C132: =B132*(1+C131) | D132: =C132*(1+D131) | E132: =D132*(1+E131)
A133: Data Centers: EBIT margin | C133: =Model!E14+$B$5 | D133: =Model!F14+$B$5 | E133: =Model!G14+$B$5
A134: Data Centers: EBIT | C134: =C132*C133 | D134: =D132*D133 | E134: =E132*E133
A135: Commercial HVAC: revenue growth | C135: =Model!E16+$B$4 | D135: =Model!F16+$B$4 | E135: =Model!G16+$B$4
A136: Commercial HVAC: revenue | B136: =Valuation!$B$89 | C136: =B136*(1+C135) | D136: =C136*(1+D135) | E136: =D136*(1+E135)
A137: Commercial HVAC: EBIT margin | C137: =Model!E18+$B$5 | D137: =Model!F18+$B$5 | E137: =Model!G18+$B$5
A138: Commercial HVAC: EBIT | C138: =C136*C137 | D138: =D136*D137 | E138: =E136*E137
A139: Total segment revenue | C139: =C132+C136 | D139: =D132+D136 | E139: =E132+E136
A140: Total segment EBIT | C140: =C134+C138 | D140: =D134+D138 | E140: =E134+E138
A141: Corporate / unallocated EBIT | C141: =Model!E21 | D141: =Model!F21 | E141: =Model!G21
A142: EBIT (segments + corporate) | C142: =C140+C141 | D142: =D140+D141 | E142: =E140+E141

Sheet Calc - bear
A1: MOD engine calculation: bear scenario
A2: Machinery behind the Valuation and Distribution tabs; drivers come from Model, assumptions from Valuation.
A4: Scenario Growth Δ | B4: =N(Valuation!C83)
A5: Scenario Margin Δ | B5: =N(Valuation!D83)
A6: Scenario Multiple Δ (turns) | B6: =N(Valuation!E83)
A7: Scenario WACC Δ | B7: =N(Valuation!F83)
A8: Scenario Multiple %Δ | B8: =N(Valuation!G83)
A9: Scenario Stated EPS/FCF %Δ | B9: =N(Valuation!H83)
A10: Scenario Custom %Δ | B10: =N(Valuation!I83)
A12: WACC | B12: =Valuation!$B$51+B7
A13: Years from last FY end to target date | B13: =(Valuation!$B$45-Valuation!$B$49)/365.25
A14: Years from last FY end to balance date | B14: =(Valuation!$B$55-Valuation!$B$49)/365.25
A15: Years from last FY end to share count date | B15: =(Valuation!$B$61-Valuation!$B$49)/365.25
A16: Projected years | B16: 3
A18: Projection | B18: Base | C18: =Model!E5 | D18: =Model!F5 | E18: =Model!G5
A19: Year index | B19: 0 | C19: 1 | D19: 2 | E19: 3
A20: Period end | C20: =Valuation!$B$49+ROUND(365.25*C19,0) | D20: =Valuation!$B$49+ROUND(365.25*D19,0) | E20: =Valuation!$B$49+ROUND(365.25*E19,0)
A21: Revenue growth | C21: =C22/B22-1 | D21: =D22/C22-1 | E21: =E22/D22-1
A22: Revenue | B22: =Valuation!$B$50 | C22: =C139 | D22: =D139 | E22: =E139
A23: EBIT margin | C23: =C24/C22 | D23: =D24/D22 | E23: =E24/E22
A24: EBIT | C24: =C142 | D24: =D142 | E24: =E142
A25: Tax rate | C25: =Model!E63 | D25: =Model!F63 | E25: =Model!G63
A26: NOPAT | C26: =C24*(1-C25) | D26: =D24*(1-D25) | E26: =E24*(1-E25)
A27: D&A | C27: =C22*(Model!E64) | D27: =D22*(Model!F64) | E27: =E22*(Model!G64)
A28: Capex | C28: =C22*(Model!E65) | D28: =D22*(Model!F65) | E28: =E22*(Model!G65)
A29: Working capital increase | C29: =(Model!E66)*(C22-B22) | D29: =(Model!F66)*(D22-C22) | E29: =(Model!G66)*(E22-D22)
A30: Stock comp | C30: =C22*(Model!E67) | D30: =D22*(Model!F67) | E30: =E22*(Model!G67)
A31: Free cash flow to firm | C31: =C26+C27-C28-C29-IF(AND(Valuation!$B$47="adjusted",Valuation!$B$48="cost"),C30*(1-C25),0) | D31: =D26+D27-D28-D29-IF(AND(Valuation!$B$47="adjusted",Valuation!$B$48="cost"),D30*(1-D25),0) | E31: =E26+E27-E28-E29-IF(AND(Valuation!$B$47="adjusted",Valuation!$B$48="cost"),E30*(1-E25),0)
A32: EBITDA | C32: =C24+C27 | D32: =D24+D27 | E32: =E24+E27
A33: Adj. EBITDA | C33: =C24+C27+C22*(Model!E71) | D33: =D24+D27+D22*(Model!F71) | E33: =E24+E27+E22*(Model!G71)
A34: Shareholder returns + other uses | C34: =C22*Model!E69+Model!E68+Model!E70 | D34: =D22*Model!F69+Model!F68+Model!F70 | E34: =E22*Model!G69+Model!G68+Model!G70
A35: Share of year after target date | C35: =IF(C19<=$B$13,0,C19-MAX(C19-1,$B$13)) | D35: =IF(D19<=$B$13,0,D19-MAX(D19-1,$B$13)) | E35: =IF(E19<=$B$13,0,E19-MAX(E19-1,$B$13))
A36: PV at target date of FCFF | C36: =IF(C35=0,0,C31*C35/(1+$B$12)^(C19-$B$13)) | D36: =IF(D35=0,0,D31*D35/(1+$B$12)^(D19-$B$13)) | E36: =IF(E35=0,0,E31*E35/(1+$B$12)^(E19-$B$13))
A37: Overlap: balance date to target date | C37: =MAX(0,MIN(C19,$B$13)-MAX(C19-1,$B$14)) | D37: =MAX(0,MIN(D19,$B$13)-MAX(D19-1,$B$14)) | E37: =MAX(0,MIN(E19,$B$13)-MAX(E19-1,$B$14))
A38: NTM weight at target date | C38: =MAX(0,MIN(C19,$B$13+1)-MAX(C19-1,$B$13)) | D38: =MAX(0,MIN(D19,$B$13+1)-MAX(D19-1,$B$13)) | E38: =MAX(0,MIN(E19,$B$13+1)-MAX(E19-1,$B$13))
A39: LTM weight at target date | B39: =MAX(0,MIN(0,$B$13)-MAX(-1,$B$13-1)) | C39: =MAX(0,MIN(C19,$B$13)-MAX(C19-1,$B$13-1)) | D39: =MAX(0,MIN(D19,$B$13)-MAX(D19-1,$B$13-1)) | E39: =MAX(0,MIN(E19,$B$13)-MAX(E19-1,$B$13-1))
A41: Value at the target date
A42: PV of free cash flow after the target date | B42: =SUM($C$36:$E$36)
A43: Terminal value at final year | B43: =IF(Valuation!$B$52="exit_multiple",Valuation!$B$54*E32,E31*(1+Valuation!$B$53)/($B$12-Valuation!$B$53))
A44: PV of terminal value at target date | B44: =B43/(1+$B$12)^($B$16-$B$13)
A45: DCF enterprise value at target date | B45: =B42+B44
A46: Terminal value share of DCF | B46: =B44/B45
A47: Free cash flow earned, balance date to target date | B47: =SUMPRODUCT($C$37:$E$37,$C$31:$E$31)
A48: Shareholder returns + other uses paid | B48: =SUMPRODUCT($C$37:$E$37,$C$34:$E$34)
A49: Interest drag on net debt | B49: =Valuation!$B$58*(1-$C$25)*MAX(Valuation!$B$56,0)*MAX($B$13-$B$14,0)
A50: Net debt at target date | B50: =IF(Valuation!$B$59="",Valuation!$B$56-B47+B49+B48,Valuation!$B$59)
A51: Minority interests | B51: =Valuation!$B$57
A52: Adjustments (probability-weighted) | B52: =0
A53: Diluted shares at target date (M) | B53: =IF(Valuation!$B$63="",Valuation!$B$60*(1+Valuation!$B$62)^MAX($B$13-$B$15,0),Valuation!$B$63)
A54: After-tax interest on target-date net debt | B54: =Valuation!$B$58*(1-$C$25)*MAX(B50,0)
A55: Check: WACC vs terminal growth | B55: =IF(AND(Valuation!$B$52<>"exit_multiple",$B$12<=Valuation!$B$53+0.01),"WACC must exceed terminal growth by 1 point","ok")
A56: Check: projection length | B56: =IF(OR($B$13>=$B$16-1,$B$13+1>$B$16),"add projected years past the target date","ok")
A58: Metric at target date | B58: Next 12 months | C58: Last 12 months
A59: Revenue | B59: =SUMPRODUCT($C$38:$E$38,$C$22:$E$22) | C59: =SUMPRODUCT($C$39:$E$39,$C$22:$E$22)+$B$39*$B$22
A60: EBIT | B60: =SUMPRODUCT($C$38:$E$38,$C$24:$E$24) | C60: =SUMPRODUCT($C$39:$E$39,$C$24:$E$24)
A61: EBITDA | B61: =SUMPRODUCT($C$38:$E$38,$C$32:$E$32) | C61: =SUMPRODUCT($C$39:$E$39,$C$32:$E$32)
A62: Adj. EBITDA | B62: =SUMPRODUCT($C$38:$E$38,$C$33:$E$33) | C62: =SUMPRODUCT($C$39:$E$39,$C$33:$E$33)
A63: NOPAT | B63: =SUMPRODUCT($C$38:$E$38,$C$26:$E$26) | C63: =SUMPRODUCT($C$39:$E$39,$C$26:$E$26)
A64: Free cash flow to firm | B64: =SUMPRODUCT($C$38:$E$38,$C$31:$E$31) | C64: =SUMPRODUCT($C$39:$E$39,$C$31:$E$31)
A66: Valuation method | B66: Metric | C66: Multiple used | D66: Basis | E66: Metric at target date | F66: Value per share | G66: Weight | H66: Metric key | I66: Metric shown (stated per-share figure when used)
A67: DCF (cash flow to target date + terminal) | F67: =((B45)-$B$50-$B$51+$B$52)/$B$53 | G67: =Valuation!$B$64
A68: ="Multiple: "&Valuation!A70&" ("&Valuation!D70&")" | B68: =Valuation!A70 | C68: =IF(B68="FCF yield",(Valuation!B70)*(1-$B$8),(Valuation!B70)+IF(B68="EV/sales",0.1,1)*$B$6) | D68: =Valuation!D70 | E68: =IF(D68="ltm",CHOOSE(H68,$C$59,$C$60,$C$61,$C$62,$C$63,$C$64),CHOOSE(H68,$B$59,$B$60,$B$61,$B$62,$B$63,$B$64)) | F68: =IF(OR(B68="EV/EBITDA",B68="EV/sales",B68="EV/EBIT"),((C68*E68)-$B$50-$B$51+$B$52)/$B$53,IF(B68="P/E",IF(Valuation!F70<>"",C68*(Valuation!F70)*(1+$B$9),C68*(E68-$B$54)/$B$53),IF(Valuation!G70<>"",(Valuation!G70)*(1+$B$9)/C68,(E68-IF(Valuation!H70,$B$54,0))/C68/$B$53))+$B$52/$B$53) | G68: =Valuation!C70 | H68: =IF(B68="EV/sales",1,IF(B68="EV/EBIT",2,IF(B68="EV/EBITDA",IF(Valuation!E70="adjusted",4,3),IF(B68="P/E",5,6)))) | I68: =IF(AND(B68="P/E",Valuation!F70<>""),(Valuation!F70)*(1+$B$9),IF(AND(B68="FCF yield",Valuation!G70<>""),(Valuation!G70)*(1+$B$9),E68))
A69: ="Multiple: "&Valuation!A71&" ("&Valuation!D71&")" | B69: =Valuation!A71 | C69: =IF(B69="FCF yield",(Valuation!B71)*(1-$B$8),(Valuation!B71)+IF(B69="EV/sales",0.1,1)*$B$6) | D69: =Valuation!D71 | E69: =IF(D69="ltm",CHOOSE(H69,$C$59,$C$60,$C$61,$C$62,$C$63,$C$64),CHOOSE(H69,$B$59,$B$60,$B$61,$B$62,$B$63,$B$64)) | F69: =IF(OR(B69="EV/EBITDA",B69="EV/sales",B69="EV/EBIT"),((C69*E69)-$B$50-$B$51+$B$52)/$B$53,IF(B69="P/E",IF(Valuation!F71<>"",C69*(Valuation!F71)*(1+$B$9),C69*(E69-$B$54)/$B$53),IF(Valuation!G71<>"",(Valuation!G71)*(1+$B$9)/C69,(E69-IF(Valuation!H71,$B$54,0))/C69/$B$53))+$B$52/$B$53) | G69: =Valuation!C71 | H69: =IF(B69="EV/sales",1,IF(B69="EV/EBIT",2,IF(B69="EV/EBITDA",IF(Valuation!E71="adjusted",4,3),IF(B69="P/E",5,6)))) | I69: =IF(AND(B69="P/E",Valuation!F71<>""),(Valuation!F71)*(1+$B$9),IF(AND(B69="FCF yield",Valuation!G71<>""),(Valuation!G71)*(1+$B$9),E69))
A70: Value per share at target date (weighted methods) | F70: =SUMPRODUCT(F67:F69,G67:G69)/SUM(G67:G69)
A129: Segment build (model_engine.seg_build): revenue and EBIT are the segment sums plus corporate EBIT
A130: Segment | B130: Base | C130: =Model!E5 | D130: =Model!F5 | E130: =Model!G5
A131: Data Centers: revenue growth | C131: =Model!E12+$B$4+$B$250 | D131: =Model!F12+$B$4 | E131: =Model!G12+$B$4
A132: Data Centers: revenue | B132: =Valuation!$B$88 | C132: =B132*(1+C131) | D132: =C132*(1+D131) | E132: =D132*(1+E131)
A133: Data Centers: EBIT margin | C133: =Model!E14+$B$5+$B$251 | D133: =Model!F14+$B$5+$B$252 | E133: =Model!G14+$B$5+$B$253
A134: Data Centers: EBIT | C134: =C132*C133 | D134: =D132*D133 | E134: =E132*E133
A135: Commercial HVAC: revenue growth | C135: =Model!E16+$B$4 | D135: =Model!F16+$B$4 | E135: =Model!G16+$B$4
A136: Commercial HVAC: revenue | B136: =Valuation!$B$89 | C136: =B136*(1+C135) | D136: =C136*(1+D135) | E136: =D136*(1+E135)
A137: Commercial HVAC: EBIT margin | C137: =Model!E18+$B$5 | D137: =Model!F18+$B$5 | E137: =Model!G18+$B$5
A138: Commercial HVAC: EBIT | C138: =C136*C137 | D138: =D136*D137 | E138: =E136*E137
A139: Total segment revenue | C139: =C132+C136 | D139: =D132+D136 | E139: =E132+E136
A140: Total segment EBIT | C140: =C134+C138 | D140: =D134+D138 | E140: =E134+E138
A141: Corporate / unallocated EBIT | C141: =Model!E21+$B$254 | D141: =Model!F21+$B$255 | E141: =Model!G21+$B$256
A142: EBIT (segments + corporate) | C142: =C140+C141 | D142: =D140+D141 | E142: =E140+E141
A249: Driver scenario shifts: line-item changes model_drivers.py resolves from this scenario's driver deltas (added to the Model tab inputs)
A250: Data Centers: revenue growth, year 1 | B250: -0.24749594
A251: Data Centers: EBIT margin, year 1 | B251: -0.04
A252: Data Centers: EBIT margin, year 2 | B252: -0.04
A253: Data Centers: EBIT margin, year 3 | B253: -0.04
A254: Corporate EBIT, year 1 | B254: -10
A255: Corporate EBIT, year 2 | B255: -10
A256: Corporate EBIT, year 3 | B256: -10

Sheet Calc - base
A1: MOD engine calculation: base scenario
A2: Machinery behind the Valuation and Distribution tabs; drivers come from Model, assumptions from Valuation.
A4: Scenario Growth Δ | B4: =N(Valuation!C84)
A5: Scenario Margin Δ | B5: =N(Valuation!D84)
A6: Scenario Multiple Δ (turns) | B6: =N(Valuation!E84)
A7: Scenario WACC Δ | B7: =N(Valuation!F84)
A8: Scenario Multiple %Δ | B8: =N(Valuation!G84)
A9: Scenario Stated EPS/FCF %Δ | B9: =N(Valuation!H84)
A10: Scenario Custom %Δ | B10: =N(Valuation!I84)
A12: WACC | B12: =Valuation!$B$51+B7
A13: Years from last FY end to target date | B13: =(Valuation!$B$45-Valuation!$B$49)/365.25
A14: Years from last FY end to balance date | B14: =(Valuation!$B$55-Valuation!$B$49)/365.25
A15: Years from last FY end to share count date | B15: =(Valuation!$B$61-Valuation!$B$49)/365.25
A16: Projected years | B16: 3
A18: Projection | B18: Base | C18: =Model!E5 | D18: =Model!F5 | E18: =Model!G5
A19: Year index | B19: 0 | C19: 1 | D19: 2 | E19: 3
A20: Period end | C20: =Valuation!$B$49+ROUND(365.25*C19,0) | D20: =Valuation!$B$49+ROUND(365.25*D19,0) | E20: =Valuation!$B$49+ROUND(365.25*E19,0)
A21: Revenue growth | C21: =C22/B22-1 | D21: =D22/C22-1 | E21: =E22/D22-1
A22: Revenue | B22: =Valuation!$B$50 | C22: =C139 | D22: =D139 | E22: =E139
A23: EBIT margin | C23: =C24/C22 | D23: =D24/D22 | E23: =E24/E22
A24: EBIT | C24: =C142 | D24: =D142 | E24: =E142
A25: Tax rate | C25: =Model!E63 | D25: =Model!F63 | E25: =Model!G63
A26: NOPAT | C26: =C24*(1-C25) | D26: =D24*(1-D25) | E26: =E24*(1-E25)
A27: D&A | C27: =C22*(Model!E64) | D27: =D22*(Model!F64) | E27: =E22*(Model!G64)
A28: Capex | C28: =C22*(Model!E65) | D28: =D22*(Model!F65) | E28: =E22*(Model!G65)
A29: Working capital increase | C29: =(Model!E66)*(C22-B22) | D29: =(Model!F66)*(D22-C22) | E29: =(Model!G66)*(E22-D22)
A30: Stock comp | C30: =C22*(Model!E67) | D30: =D22*(Model!F67) | E30: =E22*(Model!G67)
A31: Free cash flow to firm | C31: =C26+C27-C28-C29-IF(AND(Valuation!$B$47="adjusted",Valuation!$B$48="cost"),C30*(1-C25),0) | D31: =D26+D27-D28-D29-IF(AND(Valuation!$B$47="adjusted",Valuation!$B$48="cost"),D30*(1-D25),0) | E31: =E26+E27-E28-E29-IF(AND(Valuation!$B$47="adjusted",Valuation!$B$48="cost"),E30*(1-E25),0)
A32: EBITDA | C32: =C24+C27 | D32: =D24+D27 | E32: =E24+E27
A33: Adj. EBITDA | C33: =C24+C27+C22*(Model!E71) | D33: =D24+D27+D22*(Model!F71) | E33: =E24+E27+E22*(Model!G71)
A34: Shareholder returns + other uses | C34: =C22*Model!E69+Model!E68+Model!E70 | D34: =D22*Model!F69+Model!F68+Model!F70 | E34: =E22*Model!G69+Model!G68+Model!G70
A35: Share of year after target date | C35: =IF(C19<=$B$13,0,C19-MAX(C19-1,$B$13)) | D35: =IF(D19<=$B$13,0,D19-MAX(D19-1,$B$13)) | E35: =IF(E19<=$B$13,0,E19-MAX(E19-1,$B$13))
A36: PV at target date of FCFF | C36: =IF(C35=0,0,C31*C35/(1+$B$12)^(C19-$B$13)) | D36: =IF(D35=0,0,D31*D35/(1+$B$12)^(D19-$B$13)) | E36: =IF(E35=0,0,E31*E35/(1+$B$12)^(E19-$B$13))
A37: Overlap: balance date to target date | C37: =MAX(0,MIN(C19,$B$13)-MAX(C19-1,$B$14)) | D37: =MAX(0,MIN(D19,$B$13)-MAX(D19-1,$B$14)) | E37: =MAX(0,MIN(E19,$B$13)-MAX(E19-1,$B$14))
A38: NTM weight at target date | C38: =MAX(0,MIN(C19,$B$13+1)-MAX(C19-1,$B$13)) | D38: =MAX(0,MIN(D19,$B$13+1)-MAX(D19-1,$B$13)) | E38: =MAX(0,MIN(E19,$B$13+1)-MAX(E19-1,$B$13))
A39: LTM weight at target date | B39: =MAX(0,MIN(0,$B$13)-MAX(-1,$B$13-1)) | C39: =MAX(0,MIN(C19,$B$13)-MAX(C19-1,$B$13-1)) | D39: =MAX(0,MIN(D19,$B$13)-MAX(D19-1,$B$13-1)) | E39: =MAX(0,MIN(E19,$B$13)-MAX(E19-1,$B$13-1))
A41: Value at the target date
A42: PV of free cash flow after the target date | B42: =SUM($C$36:$E$36)
A43: Terminal value at final year | B43: =IF(Valuation!$B$52="exit_multiple",Valuation!$B$54*E32,E31*(1+Valuation!$B$53)/($B$12-Valuation!$B$53))
A44: PV of terminal value at target date | B44: =B43/(1+$B$12)^($B$16-$B$13)
A45: DCF enterprise value at target date | B45: =B42+B44
A46: Terminal value share of DCF | B46: =B44/B45
A47: Free cash flow earned, balance date to target date | B47: =SUMPRODUCT($C$37:$E$37,$C$31:$E$31)
A48: Shareholder returns + other uses paid | B48: =SUMPRODUCT($C$37:$E$37,$C$34:$E$34)
A49: Interest drag on net debt | B49: =Valuation!$B$58*(1-$C$25)*MAX(Valuation!$B$56,0)*MAX($B$13-$B$14,0)
A50: Net debt at target date | B50: =IF(Valuation!$B$59="",Valuation!$B$56-B47+B49+B48,Valuation!$B$59)
A51: Minority interests | B51: =Valuation!$B$57
A52: Adjustments (probability-weighted) | B52: =0
A53: Diluted shares at target date (M) | B53: =IF(Valuation!$B$63="",Valuation!$B$60*(1+Valuation!$B$62)^MAX($B$13-$B$15,0),Valuation!$B$63)
A54: After-tax interest on target-date net debt | B54: =Valuation!$B$58*(1-$C$25)*MAX(B50,0)
A55: Check: WACC vs terminal growth | B55: =IF(AND(Valuation!$B$52<>"exit_multiple",$B$12<=Valuation!$B$53+0.01),"WACC must exceed terminal growth by 1 point","ok")
A56: Check: projection length | B56: =IF(OR($B$13>=$B$16-1,$B$13+1>$B$16),"add projected years past the target date","ok")
A58: Metric at target date | B58: Next 12 months | C58: Last 12 months
A59: Revenue | B59: =SUMPRODUCT($C$38:$E$38,$C$22:$E$22) | C59: =SUMPRODUCT($C$39:$E$39,$C$22:$E$22)+$B$39*$B$22
A60: EBIT | B60: =SUMPRODUCT($C$38:$E$38,$C$24:$E$24) | C60: =SUMPRODUCT($C$39:$E$39,$C$24:$E$24)
A61: EBITDA | B61: =SUMPRODUCT($C$38:$E$38,$C$32:$E$32) | C61: =SUMPRODUCT($C$39:$E$39,$C$32:$E$32)
A62: Adj. EBITDA | B62: =SUMPRODUCT($C$38:$E$38,$C$33:$E$33) | C62: =SUMPRODUCT($C$39:$E$39,$C$33:$E$33)
A63: NOPAT | B63: =SUMPRODUCT($C$38:$E$38,$C$26:$E$26) | C63: =SUMPRODUCT($C$39:$E$39,$C$26:$E$26)
A64: Free cash flow to firm | B64: =SUMPRODUCT($C$38:$E$38,$C$31:$E$31) | C64: =SUMPRODUCT($C$39:$E$39,$C$31:$E$31)
A66: Valuation method | B66: Metric | C66: Multiple used | D66: Basis | E66: Metric at target date | F66: Value per share | G66: Weight | H66: Metric key | I66: Metric shown (stated per-share figure when used)
A67: DCF (cash flow to target date + terminal) | F67: =((B45)-$B$50-$B$51+$B$52)/$B$53 | G67: =Valuation!$B$64
A68: ="Multiple: "&Valuation!A70&" ("&Valuation!D70&")" | B68: =Valuation!A70 | C68: =IF(B68="FCF yield",(Valuation!B70)*(1-$B$8),(Valuation!B70)+IF(B68="EV/sales",0.1,1)*$B$6) | D68: =Valuation!D70 | E68: =IF(D68="ltm",CHOOSE(H68,$C$59,$C$60,$C$61,$C$62,$C$63,$C$64),CHOOSE(H68,$B$59,$B$60,$B$61,$B$62,$B$63,$B$64)) | F68: =IF(OR(B68="EV/EBITDA",B68="EV/sales",B68="EV/EBIT"),((C68*E68)-$B$50-$B$51+$B$52)/$B$53,IF(B68="P/E",IF(Valuation!F70<>"",C68*(Valuation!F70)*(1+$B$9),C68*(E68-$B$54)/$B$53),IF(Valuation!G70<>"",(Valuation!G70)*(1+$B$9)/C68,(E68-IF(Valuation!H70,$B$54,0))/C68/$B$53))+$B$52/$B$53) | G68: =Valuation!C70 | H68: =IF(B68="EV/sales",1,IF(B68="EV/EBIT",2,IF(B68="EV/EBITDA",IF(Valuation!E70="adjusted",4,3),IF(B68="P/E",5,6)))) | I68: =IF(AND(B68="P/E",Valuation!F70<>""),(Valuation!F70)*(1+$B$9),IF(AND(B68="FCF yield",Valuation!G70<>""),(Valuation!G70)*(1+$B$9),E68))
A69: ="Multiple: "&Valuation!A71&" ("&Valuation!D71&")" | B69: =Valuation!A71 | C69: =IF(B69="FCF yield",(Valuation!B71)*(1-$B$8),(Valuation!B71)+IF(B69="EV/sales",0.1,1)*$B$6) | D69: =Valuation!D71 | E69: =IF(D69="ltm",CHOOSE(H69,$C$59,$C$60,$C$61,$C$62,$C$63,$C$64),CHOOSE(H69,$B$59,$B$60,$B$61,$B$62,$B$63,$B$64)) | F69: =IF(OR(B69="EV/EBITDA",B69="EV/sales",B69="EV/EBIT"),((C69*E69)-$B$50-$B$51+$B$52)/$B$53,IF(B69="P/E",IF(Valuation!F71<>"",C69*(Valuation!F71)*(1+$B$9),C69*(E69-$B$54)/$B$53),IF(Valuation!G71<>"",(Valuation!G71)*(1+$B$9)/C69,(E69-IF(Valuation!H71,$B$54,0))/C69/$B$53))+$B$52/$B$53) | G69: =Valuation!C71 | H69: =IF(B69="EV/sales",1,IF(B69="EV/EBIT",2,IF(B69="EV/EBITDA",IF(Valuation!E71="adjusted",4,3),IF(B69="P/E",5,6)))) | I69: =IF(AND(B69="P/E",Valuation!F71<>""),(Valuation!F71)*(1+$B$9),IF(AND(B69="FCF yield",Valuation!G71<>""),(Valuation!G71)*(1+$B$9),E69))
A70: Value per share at target date (weighted methods) | F70: =SUMPRODUCT(F67:F69,G67:G69)/SUM(G67:G69)
A129: Segment build (model_engine.seg_build): revenue and EBIT are the segment sums plus corporate EBIT
A130: Segment | B130: Base | C130: =Model!E5 | D130: =Model!F5 | E130: =Model!G5
A131: Data Centers: revenue growth | C131: =Model!E12+$B$4 | D131: =Model!F12+$B$4 | E131: =Model!G12+$B$4
A132: Data Centers: revenue | B132: =Valuation!$B$88 | C132: =B132*(1+C131) | D132: =C132*(1+D131) | E132: =D132*(1+E131)
A133: Data Centers: EBIT margin | C133: =Model!E14+$B$5 | D133: =Model!F14+$B$5 | E133: =Model!G14+$B$5
A134: Data Centers: EBIT | C134: =C132*C133 | D134: =D132*D133 | E134: =E132*E133
A135: Commercial HVAC: revenue growth | C135: =Model!E16+$B$4 | D135: =Model!F16+$B$4 | E135: =Model!G16+$B$4
A136: Commercial HVAC: revenue | B136: =Valuation!$B$89 | C136: =B136*(1+C135) | D136: =C136*(1+D135) | E136: =D136*(1+E135)
A137: Commercial HVAC: EBIT margin | C137: =Model!E18+$B$5 | D137: =Model!F18+$B$5 | E137: =Model!G18+$B$5
A138: Commercial HVAC: EBIT | C138: =C136*C137 | D138: =D136*D137 | E138: =E136*E137
A139: Total segment revenue | C139: =C132+C136 | D139: =D132+D136 | E139: =E132+E136
A140: Total segment EBIT | C140: =C134+C138 | D140: =D134+D138 | E140: =E134+E138
A141: Corporate / unallocated EBIT | C141: =Model!E21 | D141: =Model!F21 | E141: =Model!G21
A142: EBIT (segments + corporate) | C142: =C140+C141 | D142: =D140+D141 | E142: =E140+E141

Sheet Calc - bull
A1: MOD engine calculation: bull scenario
A2: Machinery behind the Valuation and Distribution tabs; drivers come from Model, assumptions from Valuation.
A4: Scenario Growth Δ | B4: =N(Valuation!C85)
A5: Scenario Margin Δ | B5: =N(Valuation!D85)
A6: Scenario Multiple Δ (turns) | B6: =N(Valuation!E85)
A7: Scenario WACC Δ | B7: =N(Valuation!F85)
A8: Scenario Multiple %Δ | B8: =N(Valuation!G85)
A9: Scenario Stated EPS/FCF %Δ | B9: =N(Valuation!H85)
A10: Scenario Custom %Δ | B10: =N(Valuation!I85)
A12: WACC | B12: =Valuation!$B$51+B7
A13: Years from last FY end to target date | B13: =(Valuation!$B$45-Valuation!$B$49)/365.25
A14: Years from last FY end to balance date | B14: =(Valuation!$B$55-Valuation!$B$49)/365.25
A15: Years from last FY end to share count date | B15: =(Valuation!$B$61-Valuation!$B$49)/365.25
A16: Projected years | B16: 3
A18: Projection | B18: Base | C18: =Model!E5 | D18: =Model!F5 | E18: =Model!G5
A19: Year index | B19: 0 | C19: 1 | D19: 2 | E19: 3
A20: Period end | C20: =Valuation!$B$49+ROUND(365.25*C19,0) | D20: =Valuation!$B$49+ROUND(365.25*D19,0) | E20: =Valuation!$B$49+ROUND(365.25*E19,0)
A21: Revenue growth | C21: =C22/B22-1 | D21: =D22/C22-1 | E21: =E22/D22-1
A22: Revenue | B22: =Valuation!$B$50 | C22: =C139 | D22: =D139 | E22: =E139
A23: EBIT margin | C23: =C24/C22 | D23: =D24/D22 | E23: =E24/E22
A24: EBIT | C24: =C142 | D24: =D142 | E24: =E142
A25: Tax rate | C25: =Model!E63 | D25: =Model!F63 | E25: =Model!G63
A26: NOPAT | C26: =C24*(1-C25) | D26: =D24*(1-D25) | E26: =E24*(1-E25)
A27: D&A | C27: =C22*(Model!E64) | D27: =D22*(Model!F64) | E27: =E22*(Model!G64)
A28: Capex | C28: =C22*(Model!E65) | D28: =D22*(Model!F65) | E28: =E22*(Model!G65)
A29: Working capital increase | C29: =(Model!E66)*(C22-B22) | D29: =(Model!F66)*(D22-C22) | E29: =(Model!G66)*(E22-D22)
A30: Stock comp | C30: =C22*(Model!E67) | D30: =D22*(Model!F67) | E30: =E22*(Model!G67)
A31: Free cash flow to firm | C31: =C26+C27-C28-C29-IF(AND(Valuation!$B$47="adjusted",Valuation!$B$48="cost"),C30*(1-C25),0) | D31: =D26+D27-D28-D29-IF(AND(Valuation!$B$47="adjusted",Valuation!$B$48="cost"),D30*(1-D25),0) | E31: =E26+E27-E28-E29-IF(AND(Valuation!$B$47="adjusted",Valuation!$B$48="cost"),E30*(1-E25),0)
A32: EBITDA | C32: =C24+C27 | D32: =D24+D27 | E32: =E24+E27
A33: Adj. EBITDA | C33: =C24+C27+C22*(Model!E71) | D33: =D24+D27+D22*(Model!F71) | E33: =E24+E27+E22*(Model!G71)
A34: Shareholder returns + other uses | C34: =C22*Model!E69+Model!E68+Model!E70 | D34: =D22*Model!F69+Model!F68+Model!F70 | E34: =E22*Model!G69+Model!G68+Model!G70
A35: Share of year after target date | C35: =IF(C19<=$B$13,0,C19-MAX(C19-1,$B$13)) | D35: =IF(D19<=$B$13,0,D19-MAX(D19-1,$B$13)) | E35: =IF(E19<=$B$13,0,E19-MAX(E19-1,$B$13))
A36: PV at target date of FCFF | C36: =IF(C35=0,0,C31*C35/(1+$B$12)^(C19-$B$13)) | D36: =IF(D35=0,0,D31*D35/(1+$B$12)^(D19-$B$13)) | E36: =IF(E35=0,0,E31*E35/(1+$B$12)^(E19-$B$13))
A37: Overlap: balance date to target date | C37: =MAX(0,MIN(C19,$B$13)-MAX(C19-1,$B$14)) | D37: =MAX(0,MIN(D19,$B$13)-MAX(D19-1,$B$14)) | E37: =MAX(0,MIN(E19,$B$13)-MAX(E19-1,$B$14))
A38: NTM weight at target date | C38: =MAX(0,MIN(C19,$B$13+1)-MAX(C19-1,$B$13)) | D38: =MAX(0,MIN(D19,$B$13+1)-MAX(D19-1,$B$13)) | E38: =MAX(0,MIN(E19,$B$13+1)-MAX(E19-1,$B$13))
A39: LTM weight at target date | B39: =MAX(0,MIN(0,$B$13)-MAX(-1,$B$13-1)) | C39: =MAX(0,MIN(C19,$B$13)-MAX(C19-1,$B$13-1)) | D39: =MAX(0,MIN(D19,$B$13)-MAX(D19-1,$B$13-1)) | E39: =MAX(0,MIN(E19,$B$13)-MAX(E19-1,$B$13-1))
A41: Value at the target date
A42: PV of free cash flow after the target date | B42: =SUM($C$36:$E$36)
A43: Terminal value at final year | B43: =IF(Valuation!$B$52="exit_multiple",Valuation!$B$54*E32,E31*(1+Valuation!$B$53)/($B$12-Valuation!$B$53))
A44: PV of terminal value at target date | B44: =B43/(1+$B$12)^($B$16-$B$13)
A45: DCF enterprise value at target date | B45: =B42+B44
A46: Terminal value share of DCF | B46: =B44/B45
A47: Free cash flow earned, balance date to target date | B47: =SUMPRODUCT($C$37:$E$37,$C$31:$E$31)
A48: Shareholder returns + other uses paid | B48: =SUMPRODUCT($C$37:$E$37,$C$34:$E$34)
A49: Interest drag on net debt | B49: =Valuation!$B$58*(1-$C$25)*MAX(Valuation!$B$56,0)*MAX($B$13-$B$14,0)
A50: Net debt at target date | B50: =IF(Valuation!$B$59="",Valuation!$B$56-B47+B49+B48,Valuation!$B$59)
A51: Minority interests | B51: =Valuation!$B$57
A52: Adjustments (probability-weighted) | B52: =0
A53: Diluted shares at target date (M) | B53: =IF(Valuation!$B$63="",Valuation!$B$60*(1+Valuation!$B$62)^MAX($B$13-$B$15,0),Valuation!$B$63)
A54: After-tax interest on target-date net debt | B54: =Valuation!$B$58*(1-$C$25)*MAX(B50,0)
A55: Check: WACC vs terminal growth | B55: =IF(AND(Valuation!$B$52<>"exit_multiple",$B$12<=Valuation!$B$53+0.01),"WACC must exceed terminal growth by 1 point","ok")
A56: Check: projection length | B56: =IF(OR($B$13>=$B$16-1,$B$13+1>$B$16),"add projected years past the target date","ok")
A58: Metric at target date | B58: Next 12 months | C58: Last 12 months
A59: Revenue | B59: =SUMPRODUCT($C$38:$E$38,$C$22:$E$22) | C59: =SUMPRODUCT($C$39:$E$39,$C$22:$E$22)+$B$39*$B$22
A60: EBIT | B60: =SUMPRODUCT($C$38:$E$38,$C$24:$E$24) | C60: =SUMPRODUCT($C$39:$E$39,$C$24:$E$24)
A61: EBITDA | B61: =SUMPRODUCT($C$38:$E$38,$C$32:$E$32) | C61: =SUMPRODUCT($C$39:$E$39,$C$32:$E$32)
A62: Adj. EBITDA | B62: =SUMPRODUCT($C$38:$E$38,$C$33:$E$33) | C62: =SUMPRODUCT($C$39:$E$39,$C$33:$E$33)
A63: NOPAT | B63: =SUMPRODUCT($C$38:$E$38,$C$26:$E$26) | C63: =SUMPRODUCT($C$39:$E$39,$C$26:$E$26)
A64: Free cash flow to firm | B64: =SUMPRODUCT($C$38:$E$38,$C$31:$E$31) | C64: =SUMPRODUCT($C$39:$E$39,$C$31:$E$31)
A66: Valuation method | B66: Metric | C66: Multiple used | D66: Basis | E66: Metric at target date | F66: Value per share | G66: Weight | H66: Metric key | I66: Metric shown (stated per-share figure when used)
A67: DCF (cash flow to target date + terminal) | F67: =((B45)-$B$50-$B$51+$B$52)/$B$53 | G67: =Valuation!$B$64
A68: ="Multiple: "&Valuation!A70&" ("&Valuation!D70&")" | B68: =Valuation!A70 | C68: =IF(B68="FCF yield",(Valuation!B70)*(1-$B$8),(Valuation!B70)+IF(B68="EV/sales",0.1,1)*$B$6) | D68: =Valuation!D70 | E68: =IF(D68="ltm",CHOOSE(H68,$C$59,$C$60,$C$61,$C$62,$C$63,$C$64),CHOOSE(H68,$B$59,$B$60,$B$61,$B$62,$B$63,$B$64)) | F68: =IF(OR(B68="EV/EBITDA",B68="EV/sales",B68="EV/EBIT"),((C68*E68)-$B$50-$B$51+$B$52)/$B$53,IF(B68="P/E",IF(Valuation!F70<>"",C68*(Valuation!F70)*(1+$B$9),C68*(E68-$B$54)/$B$53),IF(Valuation!G70<>"",(Valuation!G70)*(1+$B$9)/C68,(E68-IF(Valuation!H70,$B$54,0))/C68/$B$53))+$B$52/$B$53) | G68: =Valuation!C70 | H68: =IF(B68="EV/sales",1,IF(B68="EV/EBIT",2,IF(B68="EV/EBITDA",IF(Valuation!E70="adjusted",4,3),IF(B68="P/E",5,6)))) | I68: =IF(AND(B68="P/E",Valuation!F70<>""),(Valuation!F70)*(1+$B$9),IF(AND(B68="FCF yield",Valuation!G70<>""),(Valuation!G70)*(1+$B$9),E68))
A69: ="Multiple: "&Valuation!A71&" ("&Valuation!D71&")" | B69: =Valuation!A71 | C69: =IF(B69="FCF yield",(Valuation!B71)*(1-$B$8),(Valuation!B71)+IF(B69="EV/sales",0.1,1)*$B$6) | D69: =Valuation!D71 | E69: =IF(D69="ltm",CHOOSE(H69,$C$59,$C$60,$C$61,$C$62,$C$63,$C$64),CHOOSE(H69,$B$59,$B$60,$B$61,$B$62,$B$63,$B$64)) | F69: =IF(OR(B69="EV/EBITDA",B69="EV/sales",B69="EV/EBIT"),((C69*E69)-$B$50-$B$51+$B$52)/$B$53,IF(B69="P/E",IF(Valuation!F71<>"",C69*(Valuation!F71)*(1+$B$9),C69*(E69-$B$54)/$B$53),IF(Valuation!G71<>"",(Valuation!G71)*(1+$B$9)/C69,(E69-IF(Valuation!H71,$B$54,0))/C69/$B$53))+$B$52/$B$53) | G69: =Valuation!C71 | H69: =IF(B69="EV/sales",1,IF(B69="EV/EBIT",2,IF(B69="EV/EBITDA",IF(Valuation!E71="adjusted",4,3),IF(B69="P/E",5,6)))) | I69: =IF(AND(B69="P/E",Valuation!F71<>""),(Valuation!F71)*(1+$B$9),IF(AND(B69="FCF yield",Valuation!G71<>""),(Valuation!G71)*(1+$B$9),E69))
A70: Value per share at target date (weighted methods) | F70: =SUMPRODUCT(F67:F69,G67:G69)/SUM(G67:G69)
A129: Segment build (model_engine.seg_build): revenue and EBIT are the segment sums plus corporate EBIT
A130: Segment | B130: Base | C130: =Model!E5 | D130: =Model!F5 | E130: =Model!G5
A131: Data Centers: revenue growth | C131: =Model!E12+$B$4+$B$250 | D131: =Model!F12+$B$4 | E131: =Model!G12+$B$4
A132: Data Centers: revenue | B132: =Valuation!$B$88 | C132: =B132*(1+C131) | D132: =C132*(1+D131) | E132: =D132*(1+E131)
A133: Data Centers: EBIT margin | C133: =Model!E14+$B$5+$B$251 | D133: =Model!F14+$B$5+$B$252 | E133: =Model!G14+$B$5+$B$253
A134: Data Centers: EBIT | C134: =C132*C133 | D134: =D132*D133 | E134: =E132*E133
A135: Commercial HVAC: revenue growth | C135: =Model!E16+$B$4 | D135: =Model!F16+$B$4 | E135: =Model!G16+$B$4
A136: Commercial HVAC: revenue | B136: =Valuation!$B$89 | C136: =B136*(1+C135) | D136: =C136*(1+D135) | E136: =D136*(1+E135)
A137: Commercial HVAC: EBIT margin | C137: =Model!E18+$B$5 | D137: =Model!F18+$B$5 | E137: =Model!G18+$B$5
A138: Commercial HVAC: EBIT | C138: =C136*C137 | D138: =D136*D137 | E138: =E136*E137
A139: Total segment revenue | C139: =C132+C136 | D139: =D132+D136 | E139: =E132+E136
A140: Total segment EBIT | C140: =C134+C138 | D140: =D134+D138 | E140: =E134+E138
A141: Corporate / unallocated EBIT | C141: =Model!E21 | D141: =Model!F21 | E141: =Model!G21
A142: EBIT (segments + corporate) | C142: =C140+C141 | D142: =D140+D141 | E142: =E140+E141
A249: Driver scenario shifts: line-item changes model_drivers.py resolves from this scenario's driver deltas (added to the Model tab inputs)
A250: Data Centers: revenue growth, year 1 | B250: 0.24749594
A251: Data Centers: EBIT margin, year 1 | B251: 0.015
A252: Data Centers: EBIT margin, year 2 | B252: 0.015
A253: Data Centers: EBIT margin, year 3 | B253: 0.015

Sheet Agents
A1: MOD: each forecaster's own assumption set through the same engine (from model_engine.json, not live)
A3: Set | B3: Research target (12m) | C3: Median | D3: 25th pct | E3: 75th pct | F3: WACC | G3: Y1 growth | H3: Y1 margin | I3: Terminal growth | J3: DCF weight | K3: Years | L3: Multiples | M3: Supervisor's note
A4: supervisor | B4: 169.0132 | C4: 168.78876 | D4: 118.83726 | E4: 209.30389 | J4: 0 | K4: 3 | L4: EV/EBITDA 13.57 (ntm); P/E 21.25 (ntm)
A5: agent_1 | M5: engine error: no model_inputs found
A6: agent_2 | M6: engine error: no model_inputs found
A7: agent_3 | M7: engine error: no model_inputs found
A8: agent_4 | M8: engine error: no model_inputs found
A9: agent_5 | M9: engine error: no model_inputs found

Sheet Sources
A1: MOD: where each input comes from (source numbers point to the list below; F ids to the SEC fact table)
A3: Input | B3: Value | C3: Basis | D3: Sources | E3: SEC fact ids | F3: Derivation
A4: base revenue (RemainCo FY2026) | B4: 2082.0 | C4: reported | D4: 6 | E4: F3 | F4: DC $1,108.2M + CHVAC $973.8M before eliminations (recast Ex.99.1); consolidated FY26 $3,181.1M (F3) incl. PT.
A5: tax rate | B5: 0.24 | C5: estimate | E5: F78, F85 | F5: supervisor's 0.76 after-tax factor (normalized 24%, agents 1/2/4/5); FY26 GAAP ETR 63.2/186.5 = 33.9% (F78/F85) is not the basis
A6: D&A % of revenue | B6: 0.0228 | C6: estimate | D6: 6 | E6: F36 | F6: FY26 D&A DC $19.1M + CHVAC $28.4M = $47.5M (recast Ex.99.1 segment reconciliation, src 6; verified 2026-10-25) / $2,082.0M = 2.28%; consolidated FY26 D&A $79.7M (F36, same table total incl. PT $30.8M, corporate $1.4M). Supervisor used $85M NTM.
A7: capex % of revenue | B7: 0.05 | C7: estimate | D7: 5 | E7: F57 | F7: filled in (not stated in this set's original work): consolidated capex guide $150-200M (Q1 slides); FY26 $143.3M (F57). No FV effect with net debt at horizon fixed.
A8: NWC % of incremental revenue | B8: 0.1 | C8: estimate | F8: filled in (not stated in this set's original work); no FV effect with net debt at horizon fixed.
A9: net debt at close and at horizon | B9: 280.0 | C9: estimate | D9: 4, 1 | E9: F98 | F9: $432.9M at 2026-06-30 (Q1 FY27 Ex.99.1; F98 XBRL 434.5) - $155,991,275 Cash Distribution (Oct-1 8-K) = $276.9M, ~$280M; held at the horizon as in the supervisor FV.
A10: interest rate on net debt | B10: 0.0536 | C10: estimate | E10: F71 | F10: supervisor's $15M NTM interest / $280M; FY26 interest $31.6M (F71) on ~$530M debt (F97).
A11: diluted shares | B11: 54.0 | C11: reported | D11: 4, 14 | E11: F33 | F11: Q1 FY27 diluted weighted shares 54.0M (F33); held flat as the supervisor did.
A12: EV/EBITDA multiple | B12: 14.17 | C12: estimate | D12: 28, 29, 30, 31, 32, 33, 34, 35, 36, 37, 38, 39, 40, 41, 42, 43, 44, 45, 46, 47, 48, 49, 50, 51, 52, 53, 54, 55, 56, 57, 58, 59, 60, 61, 62, 63, 64, 65, 66, 67, 68, 69, 70, 71 | E12: VRT.price, NVT.price, AAON.price, TT.price, JCI.price, CARR.price, SPXC.price, CSW.price, ETN.price | F12: Peer refresh 2026-10-26 (Kilian 06:07Z set; 06:25Z card: plain medians). Median of 12 peers' EV / consensus EBITDA calendarised to 2026-10-23 (EV = 10-23 close x MarketScreener share count + current-FY net debt; no peer adds back stock comp, as MOD does not; Alfa Laval IFRS 16 put on the after-lease basis). Values: 6367.T 7.83, MTRS.ST 8.71, CARR 11.12, SPXC 12.17, AAON 12.45, ALFA.ST 14.16, NVT 14.17, CSW 15.76, VRT 16.13, JCI 16.93, ETN 17.99, TT 18.62 -> median 14.17x (mean of unrounded Alfa Laval 14.160 and NVT 14.174 = 14.167). DC-thermal peers 13.31x vs HVAC peers 14.16x: no mix premium or discount. Replaces 17.0x (16% below a 20.23x median on a TTM / (1 + 3Y CAGR) proxy, which on 10-23 reads 16.64x vs 14.07x on consensus for the same peers).
A13: P/E multiple | B13: 23.23 | C13: estimate | D13: 28, 29, 30, 31, 32, 33, 34, 35, 36, 37, 38, 39, 40, 41, 42, 43, 44, 45, 46, 47, 48, 49, 50, 51, 52, 53, 54, 55, 56, 57, 58, 59, 60, 61, 62, 63, 64, 65, 66, 67, 68, 69, 70, 71 | E13: VRT.price, NVT.price, AAON.price, TT.price, JCI.price, CARR.price, SPXC.price, CSW.price, ETN.price | F13: Median of 12 peers' 2026-10-23 close / NTM EPS calendarised to 2026-10-23, every peer put on MOD's EPS basis (MOD adjusted EPS excludes only restructuring, disposition and acquisition costs, keeps intangible amortization and stock comp; Q1 FY27 Ex.99.1). Zacks consensus matches each company's adjusted EPS (latest reported quarter equal); after-tax run-rate amortization taken out for VRT 0.76, NVT 0.77, CARR 0.79, SPXC 1.65, CSW 2.88, ETN 2.00 per share (each release). Foreign rows are reported EPS (bounded; see comps). Values: MTRS.ST 15.11, 6367.T 19.56, SPXC 20.51, AAON 20.67, ALFA.ST 22.07, JCI 23.19, CARR 23.27, NVT 23.45, VRT 24.97, TT 25.78, ETN 26.87, CSW 28.71 -> median 23.23x (mean of JCI 23.19 and CARR 23.27). Plain median (Kilian card 2026-10-26).
A14: driver:dc_rev | B14: Data Centers segment net sales: 1,108 -> 1,828/2,590/3,110 (estimate) | C14: estimate | F14: FY27 = 1,108.2 x 1.65 (agents 1830-1870, median 1830 = +65%); FY28 $2,590M = agents median (2380-2650; +41.6%); FY29 $3,110M = agents median of the 3 that state it (3100-3180; +20.1%). Cross-check: the >$4B CY27-29 agreement is ~$1.33B/yr (4/3, estimate), ~51% of FY28 DC sales. Variant view: management 50-70%/yr (FY28 $2.74-3.11B) above; the 2025 US capacity aim of "nearly $2B DC revenue in FY28" (agent_4 src 13, trade press) below.
A15: driver:dc_margin | B15: Data Centers segment adj. EBITDA margin: 0.1937 -> 0.197/0.2/0.2 (estimate) | C15: estimate | F15: Agents median: FY27 19.7% (18.5-20.0%), FY28 20.0% (19.5-20.0%), FY29 20.0% (19.5-20.5%, 2 agents). Variant: the >85% DC earnings guide implies ~21.7% for FY27 on our sales; bear stays ~16% (agent_1/3 bear).
A16: driver:chvac_rev | B16: Commercial HVAC segment net sales: 973.8 -> 1,040/1,100/1,170 (estimate) | C16: estimate | F16: Agents median: FY27 $1,040M (+6.8%; 1040-1060), FY28 $1,100M (+5.8%; 1097-1130), FY29 $1,170M (+6.4%; 1157-1209).
A17: driver:chvac_margin | B17: Commercial HVAC segment adj. EBITDA margin: 0.1668 -> 0.165/0.1675/0.1675 (estimate) | C17: estimate | F17: Agents median: FY27 16.5% (16.3-17.0%), FY28-29 16.75% (agent_1 17.0%, agent_5 16.5%).
A18: driver:corp_cost | B18: RemainCo corporate & eliminations (adj. EBITDA): -62.6 -> -80/-82/-85 (estimate) | C18: estimate | F18: All five agents -$80M FY27 (Q1 -$23.0M annualises to -$92M, less TSA income from the spun-off PT business); FY28 median -$82M (-82 to -83.5), FY29 -$85M. Variant: -$90M if the Q1 run-rate holds (agents 1/3 bear).
A19: Exit multiples k=0.8 (EV/EBITDA and P/E) | B19: 13.57x / 21.25x | C19: estimate | D19: 1, 4, 14, 72, 73, 74 | F19: Exit-multiple rule (Kilian card 2026-10-26 12:16Z; METHOD.md Peer comparables): exit = peer median x (own NTM multiple / peer median)^k, k = 0.8. Peer medians 14.17x EV/EBITDA and 23.23x P/E (unchanged, comps_review). MOD own multiples measured on the post-spin model's NTM (PT spin/Gentherm merger completed 2026-10-01, 8-K; consensus not yet post-spin: MarketScreener FY3/26 EBITDA 471 matches total pre-spin Modine, RemainCo is ~2.08B revenue, and Zacks FY3/27 EPS 7.02 vs the model's 5.23). Calendar NTM from 2026-10-23, w = 159/365 = 0.4356 on FY3/27: EBITDA 0.4356 x 451.81 + 0.5644 x 620.25 = 546.9M; EV = 133.34 x 53.113M (MarketScreener share count, as for the peers) + post-spin net debt 265.3M (8-K/A Ex.99.1 pro forma at 2026-06-30: debt 43.4 + 276.0 - cash 54.1) = 7,347M -> 13.43x. EPS (EBITDA - D&A - 5.36% x 280M interest) x 0.76 / 54.0M: FY3/27 5.227, FY3/28 7.334, NTM 6.416 -> 133.34 / 6.416 = 20.78x. Exits: EV/EBITDA 14.17 x (13.43 / 14.17)^0.8 = 13.57x; P/E 23.23 x (20.78 / 23.23)^0.8 = 21.25x. On stale consensus (EV 7,178M / NTM 723.5M = 9.92x; P/E 15.57x) the exits would be 10.65x / 16.87x (research target (12m) 132.60); card to Kilian. Re-measure on post-spin consensus after the Q2 report (date TBA) and Investor Day (Nov 18). Note: the model balance still carries the 280M net-debt estimate (unchanged here; the 8-K/A figure is 265.3M).
A21: # | B21: Source | C21: Date | D21: Link
A22: 1 | B22: Modine 8-K: completion of PT spin/Gentherm merger | C22: 2026-10-01 | D22: https://www.sec.gov/Archives/edgar/data/67347/000110465926112870/tm2626618d1_8k.htm
A23: 2 | B23: EDGAR submissions index, Modine (no 8-K/A as of Oct 6) | C23: 2026-10-06 | D23: https://data.sec.gov/submissions/CIK0000067347.json
A24: 3 | B24: EDGAR submissions index, Gentherm | C24: 2026-10-06 | D24: https://data.sec.gov/submissions/CIK0000903129.json
A25: 4 | B25: Modine Q1 FY27 results Ex.99.1 | C25: 2026-07-29 | D25: https://www.sec.gov/Archives/edgar/data/67347/000110465926088230/mod-20260729xex99d1.htm
A26: 5 | B26: Modine Q1 FY27 slides Ex.99.2 (slide 12 segment outlook) | C26: 2026-07-29 | D26: https://www.sec.gov/Archives/edgar/data/67347/000110465926088230/mod-20260729xex99d2.htm
A27: 6 | B27: Modine 8-K Ex.99.1 recast segment results | C27: 2026-07-24 | D27: https://www.sec.gov/Archives/edgar/data/67347/000110465926086644/mod-20260724xex99d1.htm
A28: 7 | B28: Modine FY2026 10-K | C28: 2026-05-27 | D28: https://www.sec.gov/Archives/edgar/data/67347/000110465926066795/mod-20260331x10k.htm
A29: 8 | B29: stockanalysis statistics: SPXC | C29: 2026-10-06 | D29: https://stockanalysis.com/stocks/spxc/statistics/
A30: 9 | B30: stockanalysis statistics: CSWI | C30: 2026-10-06 | D30: https://stockanalysis.com/stocks/cswi/statistics/
A31: 10 | B31: stockanalysis statistics: ETN | C31: 2026-10-06 | D31: https://stockanalysis.com/stocks/etn/statistics/
A32: 11 | B32: stockanalysis statistics: AAON | C32: 2026-10-06 | D32: https://stockanalysis.com/stocks/aaon/statistics/
A33: 12 | B33: Modine Form 4 re Platinum SpinCo (filed 2026-10-05): 53,197,549 SpinCo shares distributed pro rata to Modine holders of record on Sep 28, 2026 (one SpinCo share per Modine share per the Oct-1 8-K) | C33: 2026-10-05 | D33: https://www.sec.gov/Archives/edgar/data/67347/000110465926113588/xslF345X06/tm2626713-4_4seq1.xml
... A95: 74 | B95: Nasdaq.com analyst earnings forecast (Zacks consensus EPS) MOD: FY3/27 7.02, FY3/28 9.76 | C95: 2026-10-26 | D95: https://api.nasdaq.com/api/analyst/MOD/earnings-forecast
A97: Fact id | B97: Figure | C97: Value | D97: Filing
A98: F1 | B98: revenue FY ending 2024-03-31 (us-gaap:RevenueFromContractWithCustomerExcludingAssessedTax) | C98: 2407800000 | D98: https://www.sec.gov/Archives/edgar/data/67347/000110465926066795/
A99: F2 | B99: revenue FY ending 2025-03-31 (us-gaap:RevenueFromContractWithCustomerExcludingAssessedTax) | C99: 2583500000 | D99: https://www.sec.gov/Archives/edgar/data/67347/000110465926066795/
A100: F3 | B100: revenue FY ending 2026-03-31 (us-gaap:RevenueFromContractWithCustomerExcludingAssessedTax) | C100: 3181100000 | D100: https://www.sec.gov/Archives/edgar/data/67347/000110465926066795/
A101: F4 | B101: revenue YTD 2026-04-01 to 2026-06-30 | C101: 874100000 | D101: https://www.sec.gov/Archives/edgar/data/67347/000110465926088569/
A102: F5 | B102: revenue prior-year YTD 2025-04-01 to 2025-06-30 | C102: 682800000 | D102: https://www.sec.gov/Archives/edgar/data/67347/000110465926088569/
A103: F6 | B103: revenue TTM to 2026-06-30 | C103: 3372400000
A104: F7 | B104: revenue quarter 2026-04-01 to 2026-06-30 | C104: 874100000 | D104: https://www.sec.gov/Archives/edgar/data/67347/000110465926088569/
A105: F8 | B105: operating_income FY ending 2024-03-31 (us-gaap:OperatingIncomeLoss) | C105: 240700000 | D105: https://www.sec.gov/Archives/edgar/data/67347/000110465926066795/
A106: F9 | B106: operating_income FY ending 2025-03-31 (us-gaap:OperatingIncomeLoss) | C106: 283500000 | D106: https://www.sec.gov/Archives/edgar/data/67347/000110465926066795/
A107: F10 | B107: operating_income FY ending 2026-03-31 (us-gaap:OperatingIncomeLoss) | C107: 342400000 | D107: https://www.sec.gov/Archives/edgar/data/67347/000110465926066795/
A108: F11 | B108: operating_income YTD 2026-04-01 to 2026-06-30 | C108: 74800000 | D108: https://www.sec.gov/Archives/edgar/data/67347/000110465926088569/
A109: F12 | B109: operating_income prior-year YTD 2025-04-01 to 2025-06-30 | C109: 75700000 | D109: https://www.sec.gov/Archives/edgar/data/67347/000110465926088569/
A110: F13 | B110: operating_income TTM to 2026-06-30 | C110: 341500000
A111: F14 | B111: operating_income quarter 2026-04-01 to 2026-06-30 | C111: 74800000 | D111: https://www.sec.gov/Archives/edgar/data/67347/000110465926088569/
A112: F15 | B112: net_income FY ending 2024-03-31 (us-gaap:NetIncomeLoss) | C112: 161500000 | D112: https://www.sec.gov/Archives/edgar/data/67347/000110465926066795/
A113: F16 | B113: net_income FY ending 2025-03-31 (us-gaap:NetIncomeLoss) | C113: 184000000 | D113: https://www.sec.gov/Archives/edgar/data/67347/000110465926066795/
A114: F17 | B114: net_income FY ending 2026-03-31 (us-gaap:NetIncomeLoss) | C114: 121500000 | D114: https://www.sec.gov/Archives/edgar/data/67347/000110465926066795/
A115: F18 | B115: net_income YTD 2026-04-01 to 2026-06-30 | C115: 73900000 | D115: https://www.sec.gov/Archives/edgar/data/67347/000110465926088569/
A116: F19 | B116: net_income prior-year YTD 2025-04-01 to 2025-06-30 | C116: 51200000 | D116: https://www.sec.gov/Archives/edgar/data/67347/000110465926088569/
A117: F20 | B117: net_income TTM to 2026-06-30 | C117: 144200000
A118: F21 | B118: net_income quarter 2026-04-01 to 2026-06-30 | C118: 73900000 | D118: https://www.sec.gov/Archives/edgar/data/67347/000110465926088569/
A119: F22 | B119: eps_diluted FY ending 2024-03-31 (us-gaap:EarningsPerShareDiluted) | C119: 3.03 | D119: https://www.sec.gov/Archives/edgar/data/67347/000110465926066795/
A120: F23 | B120: eps_diluted FY ending 2025-03-31 (us-gaap:EarningsPerShareDiluted) | C120: 3.42 | D120: https://www.sec.gov/Archives/edgar/data/67347/000110465926066795/
A121: F24 | B121: eps_diluted FY ending 2026-03-31 (us-gaap:EarningsPerShareDiluted) | C121: 2.26 | D121: https://www.sec.gov/Archives/edgar/data/67347/000110465926066795/
A122: F25 | B122: eps_diluted YTD 2026-04-01 to 2026-06-30 | C122: 1.37 | D122: https://www.sec.gov/Archives/edgar/data/67347/000110465926088569/
A123: F26 | B123: eps_diluted prior-year YTD 2025-04-01 to 2025-06-30 | C123: 0.95 | D123: https://www.sec.gov/Archives/edgar/data/67347/000110465926088569/
A124: F27 | B124: eps_diluted quarter 2026-04-01 to 2026-06-30 | C124: 1.37 | D124: https://www.sec.gov/Archives/edgar/data/67347/000110465926088569/
A125: F28 | B125: diluted_shares_wavg FY ending 2024-03-31 (us-gaap:WeightedAverageNumberOfDilutedSharesOutstanding) | C125: 53400000 | D125: https://www.sec.gov/Archives/edgar/data/67347/000110465926066795/
A126: F29 | B126: diluted_shares_wavg FY ending 2025-03-31 (us-gaap:WeightedAverageNumberOfDilutedSharesOutstanding) | C126: 53900000 | D126: https://www.sec.gov/Archives/edgar/data/67347/000110465926066795/
A127: F30 | B127: diluted_shares_wavg FY ending 2026-03-31 (us-gaap:WeightedAverageNumberOfDilutedSharesOutstanding) | C127: 53800000 | D127: https://www.sec.gov/Archives/edgar/data/67347/000110465926066795/
A128: F31 | B128: diluted_shares_wavg YTD 2026-04-01 to 2026-06-30 | C128: 54000000 | D128: https://www.sec.gov/Archives/edgar/data/67347/000110465926088569/
A129: F32 | B129: diluted_shares_wavg prior-year YTD 2025-04-01 to 2025-06-30 | C129: 53700000 | D129: https://www.sec.gov/Archives/edgar/data/67347/000110465926088569/
... A135: F38 | B135: d_and_a prior-year YTD 2025-04-01 to 2025-06-30 | C135: 19000000 | D135: https://www.sec.gov/Archives/edgar/data/67347/000110465926088569/
A136: F39 | B136: d_and_a TTM to 2026-06-30 | C136: 81400000
A137: F40 | B137: d_and_a quarter 2026-04-01 to 2026-06-30 | C137: 20700000 | D137: https://www.sec.gov/Archives/edgar/data/67347/000110465926088569/
A138: F41 | B138: sbc FY ending 2024-03-31 (us-gaap:ShareBasedCompensation) | C138: 10800000 | D138: https://www.sec.gov/Archives/edgar/data/67347/000110465926066795/
A139: F42 | B139: sbc FY ending 2025-03-31 (us-gaap:ShareBasedCompensation) | C139: 26400000 | D139: https://www.sec.gov/Archives/edgar/data/67347/000110465926066795/
A140: F43 | B140: sbc FY ending 2026-03-31 (us-gaap:ShareBasedCompensation) | C140: 22100000 | D140: https://www.sec.gov/Archives/edgar/data/67347/000110465926066795/
A141: F44 | B141: sbc YTD 2026-04-01 to 2026-06-30 | C141: 8000000 | D141: https://www.sec.gov/Archives/edgar/data/67347/000110465926088569/
A142: F45 | B142: sbc prior-year YTD 2025-04-01 to 2025-06-30 | C142: 5300000 | D142: https://www.sec.gov/Archives/edgar/data/67347/000110465926088569/
A143: F46 | B143: sbc TTM to 2026-06-30 | C143: 24800000
A144: F47 | B144: sbc quarter 2026-04-01 to 2026-06-30 | C144: 8000000 | D144: https://www.sec.gov/Archives/edgar/data/67347/000110465926088569/
A145: F48 | B145: cfo FY ending 2024-03-31 (us-gaap:NetCashProvidedByUsedInOperatingActivities) | C145: 214600000 | D145: https://www.sec.gov/Archives/edgar/data/67347/000110465926066795/
A146: F49 | B146: cfo FY ending 2025-03-31 (us-gaap:NetCashProvidedByUsedInOperatingActivities) | C146: 213300000 | D146: https://www.sec.gov/Archives/edgar/data/67347/000110465926066795/
A147: F50 | B147: cfo FY ending 2026-03-31 (us-gaap:NetCashProvidedByUsedInOperatingActivities) | C147: 248700000 | D147: https://www.sec.gov/Archives/edgar/data/67347/000110465926066795/
A148: F51 | B148: cfo YTD 2026-04-01 to 2026-06-30 | C148: 41400000 | D148: https://www.sec.gov/Archives/edgar/data/67347/000110465926088569/
A149: F52 | B149: cfo prior-year YTD 2025-04-01 to 2025-06-30 | C149: 27700000 | D149: https://www.sec.gov/Archives/edgar/data/67347/000110465926088569/
A150: F53 | B150: cfo TTM to 2026-06-30 | C150: 262400000
A151: F54 | B151: cfo quarter 2026-04-01 to 2026-06-30 | C151: 41400000 | D151: https://www.sec.gov/Archives/edgar/data/67347/000110465926088569/
A152: F55 | B152: capex FY ending 2024-03-31 (us-gaap:PaymentsToAcquirePropertyPlantAndEquipment) | C152: 87700000 | D152: https://www.sec.gov/Archives/edgar/data/67347/000110465926066795/
A153: F56 | B153: capex FY ending 2025-03-31 (us-gaap:PaymentsToAcquirePropertyPlantAndEquipment) | C153: 84000000 | D153: https://www.sec.gov/Archives/edgar/data/67347/000110465926066795/
A154: F57 | B154: capex FY ending 2026-03-31 (us-gaap:PaymentsToAcquirePropertyPlantAndEquipment) | C154: 143300000 | D154: https://www.sec.gov/Archives/edgar/data/67347/000110465926066795/
A155: F58 | B155: capex YTD 2026-04-01 to 2026-06-30 | C155: 46400000 | D155: https://www.sec.gov/Archives/edgar/data/67347/000110465926088569/
A156: F59 | B156: capex prior-year YTD 2025-04-01 to 2025-06-30 | C156: 27500000 | D156: https://www.sec.gov/Archives/edgar/data/67347/000110465926088569/
A157: F60 | B157: capex TTM to 2026-06-30 | C157: 162200000
A158: F61 | B158: capex quarter 2026-04-01 to 2026-06-30 | C158: 46400000 | D158: https://www.sec.gov/Archives/edgar/data/67347/000110465926088569/
A159: F62 | B159: buybacks FY ending 2024-03-31 (us-gaap:PaymentsForRepurchaseOfCommonStock) | C159: 17700000 | D159: https://www.sec.gov/Archives/edgar/data/67347/000110465926066795/
A160: F63 | B160: buybacks FY ending 2025-03-31 (us-gaap:PaymentsForRepurchaseOfCommonStock) | C160: 30900000 | D160: https://www.sec.gov/Archives/edgar/data/67347/000110465926066795/
A161: F64 | B161: buybacks FY ending 2026-03-31 (us-gaap:PaymentsForRepurchaseOfCommonStock) | C161: 7000000 | D161: https://www.sec.gov/Archives/edgar/data/67347/000110465926066795/
A162: F65 | B162: buybacks YTD 2026-04-01 to 2026-06-30 | C162: 64600000 | D162: https://www.sec.gov/Archives/edgar/data/67347/000110465926088569/
A163: F66 | B163: buybacks prior-year YTD 2025-04-01 to 2025-06-30 | C163: 5100000 | D163: https://www.sec.gov/Archives/edgar/data/67347/000110465926088569/
A164: F67 | B164: buybacks TTM to 2026-06-30 | C164: 66500000
A165: F68 | B165: buybacks quarter 2026-04-01 to 2026-06-30 | C165: 64600000 | D165: https://www.sec.gov/Archives/edgar/data/67347/000110465926088569/
A166: F69 | B166: interest_expense FY ending 2024-03-31 (us-gaap:InterestExpenseNonoperating) | C166: 24100000 | D166: https://www.sec.gov/Archives/edgar/data/67347/000110465926066795/
A167: F70 | B167: interest_expense FY ending 2025-03-31 (us-gaap:InterestExpenseNonoperating) | C167: 26400000 | D167: https://www.sec.gov/Archives/edgar/data/67347/000110465926066795/
A168: F71 | B168: interest_expense FY ending 2026-03-31 (us-gaap:InterestExpenseNonoperating) | C168: 31600000 | D168: https://www.sec.gov/Archives/edgar/data/67347/000110465926066795/
A169: F72 | B169: interest_expense YTD 2026-04-01 to 2026-06-30 | C169: 6400000 | D169: https://www.sec.gov/Archives/edgar/data/67347/000110465926088569/
...
